{
  "type": "Feature",
  "properties": {
    "iso:country":"US",
    "sg:address":"275 S Main St Ste 208",
    "sg:city":"Longmont",
    "sg:classifiers":[
        {
            "category":"Personal",
            "subcategory":"Massage",
            "type":"Services"
        }
    ],
    "sg:phone":"+1 303 246 9597",
    "sg:postcode":"80501",
    "sg:province":"CO",
    "wof:name":"Massage Longmont",
    "wof:placetype":"venue"
},
  "geometry": {"coordinates":[-105.102547,40.154776],"type":"Point"}
}