{
  "type": "Feature",
  "properties": {
    "addr:full":"6825 Conquistador Ct Colorado Springs CO 80911",
    "addr:housenumber":"6825",
    "addr:postcode":"80911",
    "addr:street":"Conquistador Ct",
    "iso:country":"US",
    "sg:address":"6825 Conquistador Ct",
    "sg:city":"Colorado Springs",
    "sg:classifiers":[
        {
            "category":"Food & Beverages",
            "subcategory":"Groceries & Convenience Stores",
            "type":"Retail Goods"
        }
    ],
    "sg:phone":"+1 719 597 0244",
    "sg:postcode":"80911",
    "sg:province":"CO",
    "sg:tags":[
        "grocer"
    ],
    "wof:name":"Hyundai Oriental Market",
    "wof:placetype":"venue"
},
  "geometry": {"coordinates":[-104.69881599999999,38.733131],"type":"Point"}
}