{
  "type": "Feature",
  "properties": {
    "addr:full":"1424 Larimer Street Suite 200 Denver CO 80202",
    "addr:housenumber":"1424",
    "addr:postcode":"80202",
    "addr:street":"Larimer Street Suite 200",
    "iso:country":"US",
    "sg:address":"1424 Larimer Street Suite 200",
    "sg:city":"Denver",
    "sg:classifiers":[
        {
            "category":"Professional",
            "subcategory":"Accounting & Tax Preparation",
            "type":"Services"
        }
    ],
    "sg:phone":"+1 303 893 1555",
    "sg:postcode":"80202",
    "sg:province":"CO",
    "sg:tags":[
        "accountant"
    ],
    "wof:name":"Gage Michael J CPA PC",
    "wof:placetype":"venue"
},
  "geometry": {"coordinates":[-104.999531,39.747562],"type":"Point"}
}