{
  "type": "Feature",
  "properties": {
    "addr:full":"1743 S Carr St Denver CO 80232",
    "addr:housenumber":"1743",
    "addr:postcode":"80232",
    "addr:street":"S Carr St",
    "iso:country":"US",
    "sg:address":"1743 S Carr St",
    "sg:city":"Denver",
    "sg:classifiers":[
        {
            "category":"Building & Trades",
            "subcategory":"Construction",
            "type":"Services"
        }
    ],
    "sg:phone":"+1 303 378 3747",
    "sg:postcode":"80232",
    "sg:province":"CO",
    "sg:tags":[
        "general",
        "contractor"
    ],
    "wof:name":"Interntnal Commerce Cnstr Corp",
    "wof:placetype":"venue"
},
  "geometry": {"coordinates":[-105.090898,39.683184],"type":"Point"}
}