{
  "type": "Feature",
  "properties": {
    "addr:full":"807 E 31st St Durango CO 81301",
    "addr:housenumber":"807",
    "addr:postcode":"co 81301",
    "addr:street":"E 31St St",
    "iso:country":"US",
    "sg:address":"807 E 31st St",
    "sg:city":"Durango",
    "sg:classifiers":[
        {
            "category":"Professional",
            "subcategory":"Engineering",
            "type":"Services"
        }
    ],
    "sg:phone":"+1 970 375 7117",
    "sg:postcode":"81301",
    "sg:province":"CO",
    "sg:tags":[
        "engineer"
    ],
    "wof:name":"Lewis Engineering & Consulting",
    "wof:placetype":"venue"
},
  "geometry": {"coordinates":[-107.85927100000001,37.29678],"type":"Point"}
}