{
  "type": "Feature",
  "properties": {
    "iso:country":"US",
    "sg:address":"55114 E Bison Dr",
    "sg:city":"Strasburg",
    "sg:classifiers":[
        {
            "category":"Building & Trades",
            "subcategory":"Construction",
            "type":"Services"
        }
    ],
    "sg:phone":"+1 303 622 4352",
    "sg:postcode":"80136",
    "sg:province":"CO",
    "sg:tags":[
        "house"
    ],
    "wof:name":"Turner Brothers Custom Bldg",
    "wof:placetype":"venue"
},
  "geometry": {"coordinates":[-104.340541,39.732404],"type":"Point"}
}