{
  "type": "Feature",
  "properties": {
    "addr:full":"835 Garnet Ave Delta CO 81416",
    "addr:housenumber":"835",
    "addr:postcode":"81416",
    "addr:street":"Garnet Ave",
    "iso:country":"US",
    "sg:address":"835 Garnet Ave",
    "sg:city":"Delta",
    "sg:classifiers":[
        {
            "category":"Real Estate",
            "subcategory":"Real Estate Services",
            "type":"Services"
        }
    ],
    "sg:phone":"+1 970 874 4871",
    "sg:postcode":"81416",
    "sg:province":"CO",
    "sg:tags":[
        "abstract",
        "title"
    ],
    "wof:name":"T R I Escrow",
    "wof:placetype":"venue"
},
  "geometry": {"coordinates":[-108.060827,38.744774],"type":"Point"}
}