{
  "type": "Feature",
  "properties": {
    "addr:full":"1901 Kipling St Lakewood CO 80215",
    "addr:housenumber":"1901",
    "addr:postcode":"80215",
    "addr:street":"Kipling St",
    "iso:country":"US",
    "sg:address":"1901 Kipling St",
    "sg:city":"Lakewood",
    "sg:classifiers":[
        {
            "category":"Health Services",
            "subcategory":"Health Practitioner",
            "type":"Services"
        }
    ],
    "sg:phone":"+1 720 533 4880",
    "sg:postcode":"80215",
    "sg:province":"CO",
    "sg:tags":[
        "psychotherapist"
    ],
    "wof:name":"Path Of Life Counseling",
    "wof:placetype":"venue"
},
  "geometry": {"coordinates":[-105.109566,39.747423],"type":"Point"}
}