{
  "type": "Feature",
  "properties": {
    "iso:country":"US",
    "sg:address":"7348 S Alton Way",
    "sg:city":"Centennial",
    "sg:classifiers":[
        {
            "category":"Restaurant",
            "type":"Food & Drink"
        }
    ],
    "sg:phone":"+1 303 771 9391",
    "sg:postcode":"80112",
    "sg:province":"CO",
    "wof:name":"Dry Creek Deli Restaurant",
    "wof:placetype":"venue"
},
  "geometry": {"coordinates":[-104.88376100000001,39.58253],"type":"Point"}
}