{
  "type": "Feature",
  "properties": {
    "iso:country":"US",
    "sg:address":"9990 E Colfax Ave",
    "sg:city":"Aurora",
    "sg:classifiers":[
        {
            "category":"Building & Trades",
            "subcategory":"Equipment Rental",
            "type":"Services"
        }
    ],
    "sg:phone":"+1 303 365 1548",
    "sg:postcode":"80010",
    "sg:province":"CO",
    "sg:tags":[
        "leasing",
        "furniture"
    ],
    "wof:name":"Aarons Sales & Lease Ownership",
    "wof:placetype":"venue"
},
  "geometry": {"coordinates":[-104.872545,39.740134],"type":"Point"}
}