{
  "type": "Feature",
  "properties": {
    "iso:country":"US",
    "sg:address":"4000 Blake St",
    "sg:city":"Denver",
    "sg:classifiers":[
        {
            "category":"Freight",
            "type":"Transportation"
        }
    ],
    "sg:phone":"+1 303 292 5199",
    "sg:postcode":"80205",
    "sg:province":"CO",
    "sg:tags":[
        "handler",
        "cargo",
        "industrial",
        "marine",
        "equipment"
    ],
    "wof:name":"Magic Lift",
    "wof:placetype":"venue"
},
  "geometry": {"coordinates":[-104.968476,39.772909],"type":"Point"}
}