{
  "type": "Feature",
  "properties": {
    "addr:full":"122 W Hopkins Ave Aspen CO 81611",
    "addr:housenumber":"122",
    "addr:postcode":"81611",
    "addr:street":"W Hopkins Ave",
    "iso:country":"US",
    "sg:address":"122 W Hopkins Ave",
    "sg:city":"Aspen",
    "sg:classifiers":[
        {
            "category":"Retail",
            "subcategory":"Portrait Studio",
            "type":"Services"
        }
    ],
    "sg:phone":"+1 970 920 9270",
    "sg:postcode":"81611",
    "sg:province":"CO",
    "sg:tags":[
        "photographer"
    ],
    "wof:name":"Allana Ferguson Photography",
    "wof:placetype":"venue"
},
  "geometry": {"coordinates":[-106.82401,39.190863],"type":"Point"}
}