{
  "type": "Feature",
  "properties": {
    "iso:country":"US",
    "sg:address":"181 Vallejo St",
    "sg:city":"Denver",
    "sg:classifiers":[
        {
            "category":"Building & Trades",
            "subcategory":"Plumbing",
            "type":"Services"
        }
    ],
    "sg:phone":"+1 303 744 6311",
    "sg:postcode":"80223",
    "sg:province":"CO",
    "sg:tags":[
        "plumbing",
        "contractor"
    ],
    "wof:name":"Slattery Plumbing Htg & AC",
    "wof:placetype":"venue"
},
  "geometry": {"coordinates":[-105.013255,39.720092],"type":"Point"}
}