{
  "type": "Feature",
  "properties": {
    "iso:country":"US",
    "sg:address":"1100 N Taft Hill Rd",
    "sg:city":"Fort Collins",
    "sg:classifiers":[
        {
            "category":"Freight",
            "type":"Transportation"
        }
    ],
    "sg:phone":"+1 970 493 0986",
    "sg:postcode":"80521",
    "sg:province":"CO",
    "sg:tags":[
        "operator",
        "local",
        "trucking"
    ],
    "wof:name":"J L Trucking",
    "wof:placetype":"venue"
},
  "geometry": {"coordinates":[-105.114587,40.601873],"type":"Point"}
}