{
  "type": "Feature",
  "properties": {
    "addr:full":"2883 41st Ave Greeley CO 80634",
    "addr:housenumber":"2883",
    "addr:postcode":"80634",
    "addr:street":"41St Ave",
    "iso:country":"US",
    "sg:address":"2883 41st Ave",
    "sg:city":"Greeley",
    "sg:classifiers":[
        {
            "category":"Professional",
            "type":"Services"
        }
    ],
    "sg:phone":"+1 970 506 1709",
    "sg:postcode":"80634",
    "sg:province":"CO",
    "wof:name":"Privateer Racing Corp LLC",
    "wof:placetype":"venue"
},
  "geometry": {"coordinates":[-104.74744099999999,40.39021],"type":"Point"}
}