{
  "type": "Feature",
  "properties": {
    "iso:country":"US",
    "sg:address":"940 Central Park Dr",
    "sg:city":"Steamboat Springs",
    "sg:classifiers":[
        {
            "category":"Health Services",
            "subcategory":"Doctor",
            "type":"Services"
        }
    ],
    "sg:phone":"+1 970 879 6663",
    "sg:postcode":"80487",
    "sg:province":"CO",
    "sg:tags":[
        "medical"
    ],
    "wof:name":"Eric Verploeg MD",
    "wof:placetype":"venue"
},
  "geometry": {"coordinates":[-106.817532,40.462002],"type":"Point"}
}