{
  "type": "Feature",
  "properties": {
    "iso:country":"US",
    "sg:address":"1600 Washington Ave",
    "sg:city":"Rocky Ford",
    "sg:classifiers":[
        {
            "category":"Organizations",
            "subcategory":"Labor Organization",
            "type":"Services"
        }
    ],
    "sg:phone":"+1 719 254 3079",
    "sg:postcode":"81067",
    "sg:province":"CO",
    "wof:name":"Internationl Asoc Machnst Arop",
    "wof:placetype":"venue"
},
  "geometry": {"coordinates":[-103.713622,38.044153],"type":"Point"}
}