{
  "type": "Feature",
  "properties": {
    "addr:full":"3540 Austin Bluffs Pkwy Colorado Springs CO 80918",
    "addr:housenumber":"3540",
    "addr:postcode":"80918",
    "addr:street":"Austin Bluffs Pkwy",
    "iso:country":"US",
    "sg:address":"3540 Austin Bluffs Pkwy",
    "sg:city":"Colorado Springs",
    "sg:classifiers":[
        {
            "category":"Real Estate",
            "subcategory":"Real Estate Agent",
            "type":"Services"
        }
    ],
    "sg:phone":"+1 719 590 7272",
    "sg:postcode":"80918",
    "sg:province":"CO",
    "sg:tags":[
        "management"
    ],
    "wof:name":"Pilgrim Realty & Management",
    "wof:placetype":"venue"
},
  "geometry": {"coordinates":[-104.76205,38.890861],"type":"Point"}
}