{
  "type": "Feature",
  "properties": {
    "addr:full":"4975 Miller St Wheat Ridge CO 80033",
    "addr:housenumber":"4975",
    "addr:postcode":"80033",
    "addr:street":"Miller St",
    "iso:country":"US",
    "sg:address":"4975 Miller St",
    "sg:city":"Wheat Ridge",
    "sg:classifiers":[
        {
            "category":"Manufacturing",
            "subcategory":"Tools & Machinery",
            "type":"Manufacturing & Wholesale Goods"
        }
    ],
    "sg:phone":"+1 303 232 4700",
    "sg:postcode":"80033",
    "sg:province":"CO",
    "sg:tags":[
        "control",
        "mfg"
    ],
    "wof:name":"Byers Peak Inc",
    "wof:placetype":"venue"
},
  "geometry": {"coordinates":[-105.11425199999999,39.786029],"type":"Point"}
}