{
  "type": "Feature",
  "properties": {
    "iso:country":"US",
    "sg:address":"9678 E Arapahoe Rd",
    "sg:city":"Englewood",
    "sg:classifiers":[
        {
            "category":"Building & Trades",
            "subcategory":"Landscaping Services",
            "type":"Services"
        }
    ],
    "sg:phone":"+1 303 855 2211",
    "sg:postcode":"80112",
    "sg:province":"CO",
    "wof:name":"Lawn Gardner",
    "wof:placetype":"venue"
},
  "geometry": {"coordinates":[-104.87792899999999,39.594963],"type":"Point"}
}