{
  "type": "Feature",
  "properties": {
    "addr:full":"1217 Eastmeadow Dr Colorado Springs CO 80906",
    "addr:housenumber":"1217",
    "addr:postcode":"80906",
    "addr:street":"Eastmeadow Dr",
    "iso:country":"US",
    "sg:address":"1217 Eastmeadow Dr",
    "sg:city":"Colorado Springs",
    "sg:classifiers":[
        {
            "category":"Building & Trades",
            "subcategory":"Construction",
            "type":"Services"
        }
    ],
    "sg:phone":"+1 719 540 6353",
    "sg:postcode":"80906",
    "sg:province":"CO",
    "sg:tags":[
        "painter"
    ],
    "wof:name":"Mc Daniel Painting",
    "wof:placetype":"venue"
},
  "geometry": {"coordinates":[-104.80569199999999,38.779131],"type":"Point"}
}