{
  "type": "Feature",
  "properties": {
    "iso:country":"US",
    "sg:address":"11844 Flatiron Dr",
    "sg:city":"Lafayette",
    "sg:classifiers":[
        {
            "category":"Building & Trades",
            "subcategory":"Construction",
            "type":"Services"
        }
    ],
    "sg:phone":"+1 303 828 5102",
    "sg:postcode":"80026",
    "sg:province":"CO",
    "sg:tags":[
        "carpentry",
        "contractor"
    ],
    "wof:name":"Bedell Construction",
    "wof:placetype":"venue"
},
  "geometry": {"coordinates":[-105.080398,40.044811],"type":"Point"}
}