{
  "type": "Feature",
  "properties": {
    "addr:full":"5209 E Briarwood Ave Littleton CO 80122",
    "addr:housenumber":"5209",
    "addr:postcode":"80122",
    "addr:street":"E Briarwood Ave",
    "iso:country":"US",
    "sg:address":"5209 E Briarwood Ave",
    "sg:city":"Littleton",
    "sg:classifiers":[
        {
            "category":"Building & Trades",
            "subcategory":"Construction",
            "type":"Services"
        }
    ],
    "sg:phone":"+1 303 779 4515",
    "sg:postcode":"80122",
    "sg:province":"CO",
    "sg:tags":[
        "house"
    ],
    "wof:name":"L & L Builders Inc",
    "wof:placetype":"venue"
},
  "geometry": {"coordinates":[-104.927786,39.591618],"type":"Point"}
}