{
  "type": "Feature",
  "properties": {
    "iso:country":"US",
    "sg:address":"6113 Constitution Ave",
    "sg:city":"Colorado Springs",
    "sg:classifiers":[
        {
            "category":"Manufacturing",
            "subcategory":"Tools & Machinery",
            "type":"Manufacturing & Wholesale Goods"
        }
    ],
    "sg:phone":"+1 719 574 1135",
    "sg:postcode":"80915",
    "sg:province":"CO",
    "sg:tags":[
        "mfg",
        "co",
        "boards",
        "circuit",
        "printed"
    ],
    "wof:name":"Peak Contract Manufacturing",
    "wof:placetype":"venue"
},
  "geometry": {"coordinates":[-104.714921,38.87079],"type":"Point"}
}