{
  "type": "Feature",
  "properties": {
    "iso:country":"US",
    "sg:address":"1501 S Potomac St",
    "sg:city":"Aurora",
    "sg:classifiers":[
        {
            "category":"Professional",
            "subcategory":"Management & Consulting",
            "type":"Services"
        }
    ],
    "sg:phone":"+1 303 695 2766",
    "sg:postcode":"80012",
    "sg:province":"CO",
    "sg:tags":[
        "retail",
        "direct",
        "sales"
    ],
    "wof:name":"Sodexho Food Service",
    "wof:placetype":"venue"
},
  "geometry": {"coordinates":[-104.831568,39.686385],"type":"Point"}
}