{
  "type": "Feature",
  "properties": {
    "addr:full":"1820 E Colfax Ave Denver CO 80238",
    "addr:housenumber":"1820",
    "addr:postcode":"80238",
    "addr:street":"E Colfax Ave",
    "iso:country":"US",
    "sg:address":"1820 E Colfax Ave",
    "sg:city":"Denver",
    "sg:classifiers":[
        {
            "category":"Travel",
            "subcategory":"Hotels & Motels",
            "type":"Entertainment"
        }
    ],
    "sg:phone":"+1 303 437 8245",
    "sg:postcode":"80238",
    "sg:province":"CO",
    "wof:name":"The Holiday Chalet",
    "wof:placetype":"venue"
},
  "geometry": {"coordinates":[-104.96510600000001,39.73981],"type":"Point"}
}