{
  "type": "Feature",
  "properties": {
    "iso:country":"US",
    "sg:address":"2071 S Parker Rd",
    "sg:city":"Denver",
    "sg:classifiers":[
        {
            "category":"Organizations",
            "subcategory":"Religious Organization",
            "type":"Services"
        }
    ],
    "sg:phone":"+1 303 696 9800",
    "sg:postcode":"80231",
    "sg:province":"CO",
    "sg:tags":[
        "church"
    ],
    "wof:name":"Colorado Muslim Society",
    "wof:placetype":"venue"
},
  "geometry": {"coordinates":[-104.876593,39.679395],"type":"Point"}
}