{
  "type": "Feature",
  "properties": {
    "iso:country":"US",
    "sg:address":"1121 E Alameda Avenue",
    "sg:city":"Denver",
    "sg:classifiers":[
        {
            "category":"Autos & Motor Vehicles",
            "subcategory":"Fuel & Gas Station",
            "type":"Retail Goods"
        }
    ],
    "sg:phone":"+1 303 777 0274",
    "sg:postcode":"80209",
    "sg:province":"CO",
    "wof:name":"Bradley Petroleum",
    "wof:placetype":"venue"
},
  "geometry": {"coordinates":[-104.973631,39.711224],"type":"Point"}
}