{
  "type": "Feature",
  "properties": {
    "iso:country":"US",
    "sg:address":"9953 E Mexico Ave",
    "sg:city":"Denver",
    "sg:classifiers":[
        {
            "category":"Autos & Motor Vehicles",
            "subcategory":"Fuel & Gas Station",
            "type":"Retail Goods"
        }
    ],
    "sg:phone":"+1 303 752 2082",
    "sg:postcode":"80247",
    "sg:province":"CO",
    "sg:tags":[
        "station",
        "gasoline"
    ],
    "wof:name":"BP Enterprises Inc",
    "wof:placetype":"venue"
},
  "geometry": {"coordinates":[-104.87073599999999,39.685735],"type":"Point"}
}