{
  "type": "Feature",
  "properties": {
    "iso:country":"US",
    "sg:address":"6872 Wadsworth Blvd",
    "sg:city":"Arvada",
    "sg:classifiers":[
        {
            "category":"Utilities",
            "subcategory":"Mobile Phone",
            "type":"Services"
        }
    ],
    "sg:phone":"+1 303 420 0391",
    "sg:postcode":"80003",
    "sg:province":"CO",
    "sg:tags":[
        "telephone",
        "cellular"
    ],
    "wof:name":"Big Time Communications",
    "wof:placetype":"venue"
},
  "geometry": {"coordinates":[-105.081321,39.820614],"type":"Point"}
}