{
  "type": "Feature",
  "properties": {
    "addr:full":"1924 Wadsworth Blvd Denver CO 80214",
    "addr:housenumber":"1924",
    "addr:postcode":"80214",
    "addr:street":"Wadsworth Blvd",
    "iso:country":"US",
    "sg:address":"1924 Wadsworth Blvd",
    "sg:city":"Denver",
    "sg:classifiers":[
        {
            "category":"Restaurant",
            "type":"Food & Drink"
        }
    ],
    "sg:phone":"+1 303 232 1321",
    "sg:postcode":"80214",
    "sg:province":"CO",
    "sg:tags":[
        "eating"
    ],
    "wof:name":"Pizza Hut",
    "wof:placetype":"venue"
},
  "geometry": {"coordinates":[-105.081305,39.746427],"type":"Point"}
}