{
  "type": "Feature",
  "properties": {
    "iso:country":"US",
    "sg:address":"115 F St",
    "sg:city":"Salida",
    "sg:classifiers":[
        {
            "category":"Shopping",
            "subcategory":"Gifts & Souvenirs",
            "type":"Retail Goods"
        }
    ],
    "sg:phone":"+1 719 539 6587",
    "sg:postcode":"81201",
    "sg:province":"CO",
    "sg:tags":[
        "shop"
    ],
    "wof:name":"Balloonatics Enterprises Inc",
    "wof:placetype":"venue"
},
  "geometry": {"coordinates":[-105.99181400000001,38.536117],"type":"Point"}
}