{
  "type": "Feature",
  "properties": {
    "addr:full":"13101 James E Casey Ave Englewood CO 80112",
    "addr:housenumber":"13101",
    "addr:postcode":"80112",
    "addr:street":"James E Casey Ave",
    "iso:country":"US",
    "sg:address":"13101 James E Casey Ave",
    "sg:city":"Englewood",
    "sg:classifiers":[
        {
            "category":"Freight",
            "type":"Transportation"
        }
    ],
    "sg:phone":"+1 303 286 4777",
    "sg:postcode":"80112",
    "sg:province":"CO",
    "sg:tags":[
        "distance",
        "parcel",
        "l",
        "long",
        "delivery",
        "truck",
        "local"
    ],
    "wof:name":"UPS",
    "wof:placetype":"venue"
},
  "geometry": {"coordinates":[-104.83791600000001,39.561645],"type":"Point"}
}