{
  "type": "Feature",
  "properties": {
    "iso:country":"US",
    "sg:address":"1741 US Hwy 24",
    "sg:city":"Leadville",
    "sg:classifiers":[
        {
            "category":"Restaurant",
            "type":"Food & Drink"
        }
    ],
    "sg:phone":"+1 719 486 2898",
    "sg:postcode":"80461",
    "sg:province":"CO",
    "sg:tags":[
        "eating"
    ],
    "wof:name":"Leadville Steakhouse Trvn Inc",
    "wof:placetype":"venue"
},
  "geometry": {"coordinates":[-106.316479,39.234969],"type":"Point"}
}