{
  "type": "Feature",
  "properties": {
    "iso:country":"US",
    "sg:address":"429 Edwards Village Blvd",
    "sg:city":"Edwards",
    "sg:classifiers":[
        {
            "category":"Home & Garden",
            "subcategory":"Building Materials",
            "type":"Retail Goods"
        }
    ],
    "sg:phone":"+1 970 926 8733",
    "sg:postcode":"81632",
    "sg:province":"CO",
    "sg:tags":[
        "lumber"
    ],
    "wof:name":"Northstar Lumber Co",
    "wof:placetype":"venue"
},
  "geometry": {"coordinates":[-106.60194799999999,39.643687],"type":"Point"}
}