{
  "type": "Feature",
  "properties": {
    "iso:country":"US",
    "sg:address":"10420 E 106th Ave",
    "sg:city":"Brighton",
    "sg:classifiers":[
        {
            "category":"Building & Trades",
            "subcategory":"Construction",
            "type":"Services"
        }
    ],
    "sg:phone":"+1 303 286 1259",
    "sg:postcode":"80601",
    "sg:province":"CO",
    "sg:tags":[
        "general",
        "contractor"
    ],
    "wof:name":"J H Construction",
    "wof:placetype":"venue"
},
  "geometry": {"coordinates":[-104.868165,39.888897],"type":"Point"}
}