{
  "type": "Feature",
  "properties": {
    "iso:country":"US",
    "sg:address":"5230 E 72nd Ave",
    "sg:city":"Commerce City",
    "sg:classifiers":[
        {
            "category":"Restaurant",
            "type":"Food & Drink"
        }
    ],
    "sg:phone":"+1 303 853 4195",
    "sg:postcode":"80022",
    "sg:province":"CO",
    "sg:tags":[
        "eating"
    ],
    "wof:name":"Santiagos Express",
    "wof:placetype":"venue"
},
  "geometry": {"coordinates":[-104.926503,39.827159],"type":"Point"}
}