{
  "type": "Feature",
  "properties": {
    "iso:country":"US",
    "sg:address":"3075 Fremont St",
    "sg:city":"Boulder",
    "sg:classifiers":[
        {
            "category":"Professional",
            "type":"Services"
        }
    ],
    "sg:phone":"+1 303 444 8332",
    "sg:postcode":"80304",
    "sg:province":"CO",
    "sg:tags":[
        "scientist"
    ],
    "wof:name":"Madole & Assoc",
    "wof:placetype":"venue"
},
  "geometry": {"coordinates":[-105.26498599999999,40.031588],"type":"Point"}
}