{
  "type": "Feature",
  "properties": {
    "iso:country":"US",
    "sg:address":"1550 S Potomac St Ste 235",
    "sg:city":"Aurora",
    "sg:classifiers":[
        {
            "category":"Health Services",
            "subcategory":"Doctor",
            "type":"Services"
        }
    ],
    "sg:phone":"+1 303 369 8088",
    "sg:postcode":"80012",
    "sg:province":"CO",
    "sg:tags":[
        "physician",
        "surgeon"
    ],
    "wof:name":"Chin, George S L Md Mph Pc",
    "wof:placetype":"venue"
},
  "geometry": {"coordinates":[-104.831146,39.689512],"type":"Point"}
}