{
  "type": "Feature",
  "properties": {
    "addr:full":"5404 Stonemoor Dr Pueblo CO 81005",
    "addr:housenumber":"5404",
    "addr:postcode":"81005",
    "addr:street":"Stonemoor Dr",
    "iso:country":"US",
    "sg:address":"5404 Stonemoor Dr",
    "sg:city":"Pueblo",
    "sg:classifiers":[
        {
            "category":"Travel",
            "subcategory":"Hotels & Motels",
            "type":"Entertainment"
        },
        {
            "category":"Travel",
            "subcategory":"Bed & Breakfast",
            "type":"Entertainment"
        }
    ],
    "sg:phone":"+1 719 564 5534",
    "sg:postcode":"81005",
    "sg:province":"CO",
    "sg:tags":[
        "inn",
        "lodging"
    ],
    "sg:website":"http://www.abriendoinn.com",
    "wof:name":"B & B By Chase",
    "wof:placetype":"venue"
},
  "geometry": {"coordinates":[-104.684099,38.255788],"type":"Point"}
}