{
  "type": "Feature",
  "properties": {
    "iso:country":"US",
    "sg:address":"224 E 3rd St",
    "sg:city":"Loveland",
    "sg:classifiers":[
        {
            "category":"Shopping",
            "subcategory":"Discount & Variety Stores",
            "type":"Retail Goods"
        }
    ],
    "sg:phone":"+1 970 663 0321",
    "sg:postcode":"80537",
    "sg:province":"CO",
    "wof:name":"Alpine Lumber Company",
    "wof:placetype":"venue"
},
  "geometry": {"coordinates":[-105.07430100000001,40.39434],"type":"Point"}
}