{
  "type": "Feature",
  "properties": {
    "addr:full":"7300 E 4th Ave Denver CO 80230",
    "addr:housenumber":"7300",
    "addr:postcode":"80230",
    "addr:street":"E 4Th Ave",
    "iso:country":"US",
    "sg:address":"7300 E 4th Ave",
    "sg:city":"Denver",
    "sg:classifiers":[
        {
            "category":"Building & Trades",
            "subcategory":"Locksmith",
            "type":"Services"
        }
    ],
    "sg:phone":"+1 303 357 0259",
    "sg:postcode":"80230",
    "sg:province":"CO",
    "sg:tags":[
        "key"
    ],
    "wof:name":"A Locksmith 0 0 24 7",
    "wof:placetype":"venue"
},
  "geometry": {"coordinates":[-104.903814,39.722243],"type":"Point"}
}