{
  "type": "Feature",
  "properties": {
    "iso:country":"US",
    "sg:address":"1777 Rose Ave",
    "sg:city":"Burlington",
    "sg:classifiers":[
        {
            "category":"Retail",
            "subcategory":"Auto Repair",
            "type":"Services"
        }
    ],
    "sg:phone":"+1 719 346 9384",
    "sg:postcode":"80807",
    "sg:province":"CO",
    "sg:tags":[
        "wrecker"
    ],
    "wof:name":"Kleine Motor Co",
    "wof:placetype":"venue"
},
  "geometry": {"coordinates":[-102.27251099999999,39.300845],"type":"Point"}
}