{
  "type": "Feature",
  "properties": {
    "addr:full":"1080 6th St Berthoud CO 80513",
    "addr:housenumber":"1080",
    "addr:postcode":"80513",
    "addr:street":"6Th St",
    "iso:country":"US",
    "sg:address":"1080 6th St",
    "sg:city":"Berthoud",
    "sg:classifiers":[
        {
            "category":"Manufacturing",
            "subcategory":"Apparel",
            "type":"Manufacturing & Wholesale Goods"
        }
    ],
    "sg:phone":"+1 970 532 2144",
    "sg:postcode":"80513",
    "sg:province":"CO",
    "sg:tags":[
        "textile",
        "product",
        "fabricated",
        "mfg"
    ],
    "wof:name":"I Give Good Thread",
    "wof:placetype":"venue"
},
  "geometry": {"coordinates":[-105.082899,40.312123],"type":"Point"}
}