{
  "type": "Feature",
  "properties": {
    "addr:full":"2751 High Cliffe Pl Littleton CO 80129",
    "addr:housenumber":"2751",
    "addr:postcode":"80129",
    "addr:street":"High Cliffe Pl",
    "iso:country":"US",
    "sg:address":"2751 High Cliffe Pl",
    "sg:city":"Littleton",
    "sg:classifiers":[
        {
            "category":"Building & Trades",
            "subcategory":"Landscaping Services",
            "type":"Services"
        }
    ],
    "sg:phone":"+1 303 791 2900",
    "sg:postcode":"80129",
    "sg:province":"CO",
    "wof:name":"Lawncare Solutions LLC",
    "wof:placetype":"venue"
},
  "geometry": {"coordinates":[-105.021958,39.545672],"type":"Point"}
}