{
  "type": "Feature",
  "properties": {
    "addr:full":"3620 E Highlands Ranch Pkwy Littleton CO 80126",
    "addr:housenumber":"3620",
    "addr:postcode":"80126",
    "addr:street":"E Highlands Ranch Pkwy",
    "iso:country":"US",
    "sg:address":"3620 E Highlands Ranch Pkwy",
    "sg:city":"Littleton",
    "sg:classifiers":[
        {
            "category":"Restaurant",
            "type":"Food & Drink"
        }
    ],
    "sg:menulink":"http://www.allmenus.com/co/sedalia/99442-rubios/menu/",
    "sg:phone":"+1 303 471 6222",
    "sg:postcode":"80126",
    "sg:province":"CO",
    "sg:tags":[
        "seafood",
        "mexican",
        "american"
    ],
    "wof:name":"Rubio's",
    "wof:placetype":"venue"
},
  "geometry": {"coordinates":[-104.94699199999999,39.542749],"type":"Point"}
}