{
  "type": "Feature",
  "properties": {
    "iso:country":"US",
    "sg:address":"3142 S Truckee Ct",
    "sg:city":"Aurora",
    "sg:classifiers":[
        {
            "category":"Professional",
            "type":"Services"
        }
    ],
    "sg:phone":"+1 303 693 8412",
    "sg:postcode":"80013",
    "sg:province":"CO",
    "wof:name":"Vickie C Brennan",
    "wof:placetype":"venue"
},
  "geometry": {"coordinates":[-104.781429,39.657494],"type":"Point"}
}