{
  "type": "Feature",
  "properties": {
    "addr:full":"212 N 2nd St La Salle CO 80645",
    "addr:housenumber":"212",
    "addr:postcode":"80645",
    "addr:street":"N 2Nd St",
    "iso:country":"US",
    "sg:address":"212 N 2nd St",
    "sg:city":"La Salle",
    "sg:classifiers":[
        {
            "category":"Insurance",
            "subcategory":"Insurance Agent",
            "type":"Services"
        }
    ],
    "sg:phone":"+1 970 284 5237",
    "sg:postcode":"80645",
    "sg:province":"CO",
    "wof:name":"American Family Insurance",
    "wof:placetype":"venue"
},
  "geometry": {"coordinates":[-104.702016,40.352355],"type":"Point"}
}