{
  "type": "Feature",
  "properties": {
    "iso:country":"US",
    "sg:address":"2645 W Hampden Ave",
    "sg:city":"Englewood",
    "sg:classifiers":[
        {
            "category":"Building & Trades",
            "subcategory":"Plumbing",
            "type":"Services"
        }
    ],
    "sg:phone":"+1 303 761 1802",
    "sg:postcode":"80110",
    "sg:province":"CO",
    "sg:tags":[
        "air",
        "heating",
        "contractor"
    ],
    "wof:name":"Arapahoe Heating Service Inc",
    "wof:placetype":"venue"
},
  "geometry": {"coordinates":[-105.01851000000001,39.653347],"type":"Point"}
}