{
  "type": "Feature",
  "properties": {
    "iso:country":"US",
    "sg:address":"1116 Broadway",
    "sg:city":"Denver",
    "sg:classifiers":[
        {
            "category":"Food & Beverages",
            "subcategory":"Bakery",
            "type":"Retail Goods"
        }
    ],
    "sg:phone":"+1 303 861 5222",
    "sg:postcode":"80203",
    "sg:province":"CO",
    "sg:tags":[
        "sandwich"
    ],
    "sg:website":"www.tasteofphilly.biz",
    "wof:name":"Taste of Philly",
    "wof:placetype":"venue"
},
  "geometry": {"coordinates":[-104.987206,39.734233],"type":"Point"}
}