{
  "type": "Feature",
  "properties": {
    "addr:full":"845 Trumpeters Ct E Monument CO 80132",
    "addr:housenumber":"845",
    "addr:postcode":"80132",
    "addr:street":"Trumpeters Ct E Monument",
    "iso:country":"US",
    "sg:address":"845 Trumpeters Ct E",
    "sg:city":"Monument",
    "sg:classifiers":[
        {
            "category":"Professional",
            "subcategory":"Credit Reporting & Collection",
            "type":"Services"
        }
    ],
    "sg:phone":"+1 719 481 2637",
    "sg:postcode":"80132",
    "sg:province":"CO",
    "sg:tags":[
        "animal"
    ],
    "wof:name":"Ems Endeavors Inc",
    "wof:placetype":"venue"
},
  "geometry": {"coordinates":[-104.80134700000001,39.102502],"type":"Point"}
}