{
  "type": "Feature",
  "properties": {
    "addr:full":"1410 High St Denver CO 80218",
    "addr:housenumber":"1410",
    "addr:postcode":"80218",
    "addr:street":"High St",
    "iso:country":"US",
    "sg:address":"1410 High St",
    "sg:city":"Denver",
    "sg:classifiers":[
        {
            "category":"Professional",
            "type":"Services"
        }
    ],
    "sg:phone":"+1 303 832 2771",
    "sg:postcode":"80218",
    "sg:province":"CO",
    "wof:name":"Schaden Labpert & Lampert",
    "wof:placetype":"venue"
},
  "geometry": {"coordinates":[-104.964691,39.739836],"type":"Point"}
}