{
  "type": "Feature",
  "properties": {
    "iso:country":"US",
    "sg:address":"757 Peoria St",
    "sg:city":"Aurora",
    "sg:classifiers":[
        {
            "category":"Shopping",
            "subcategory":"Optical Goods",
            "type":"Retail Goods"
        }
    ],
    "sg:phone":"+1 303 363 7369",
    "sg:postcode":"80011",
    "sg:province":"CO",
    "wof:name":"Dr Scott's Optical Outlet",
    "wof:placetype":"venue"
},
  "geometry": {"coordinates":[-104.847275,39.726355],"type":"Point"}
}