{
  "type": "Feature",
  "properties": {
    "iso:country":"US",
    "sg:address":"1899 Cedar St",
    "sg:city":"Broomfield",
    "sg:classifiers":[
        {
            "category":"Retail",
            "subcategory":"Laundry & Dry Cleaning",
            "type":"Services"
        }
    ],
    "sg:phone":"+1 303 466 3442",
    "sg:postcode":"80020",
    "sg:province":"CO",
    "sg:tags":[
        "cleaners",
        "rug",
        "carpet"
    ],
    "wof:name":"Sunny Carpet & Upholstery",
    "wof:placetype":"venue"
},
  "geometry": {"coordinates":[-105.057918,39.941711],"type":"Point"}
}