{
  "type": "Feature",
  "properties": {
    "addr:full":"175 N 1st St Pagosa Springs CO 81147",
    "addr:housenumber":"175",
    "addr:postcode":"81147",
    "addr:street":"N 1St St",
    "iso:country":"US",
    "sg:address":"175 N 1st St",
    "sg:city":"Pagosa Springs",
    "sg:classifiers":[
        {
            "category":"Real Estate",
            "subcategory":"Real Estate Agent",
            "type":"Services"
        }
    ],
    "sg:phone":"+1 970 264 6096",
    "sg:postcode":"81147",
    "sg:province":"CO",
    "wof:name":"Romar Group",
    "wof:placetype":"venue"
},
  "geometry": {"coordinates":[-107.002655,37.269685],"type":"Point"}
}