{
  "type": "Feature",
  "properties": {
    "addr:full":"17365 Goshawk Rd Colorado Springs CO 80908",
    "addr:housenumber":"17365",
    "addr:postcode":"80908",
    "addr:street":"Goshawk Rd",
    "iso:country":"US",
    "sg:address":"17365 Goshawk Rd",
    "sg:city":"Colorado Springs",
    "sg:classifiers":[
        {
            "category":"Farming",
            "subcategory":"Livestock Farm",
            "type":"Manufacturing & Wholesale Goods"
        }
    ],
    "sg:phone":"+1 719 495 2242",
    "sg:postcode":"80908",
    "sg:province":"CO",
    "sg:tags":[
        "llama"
    ],
    "wof:name":"Touch The Earth Llamas",
    "wof:placetype":"venue"
},
  "geometry": {"coordinates":[-104.62947,39.07535],"type":"Point"}
}