{
  "type": "Feature",
  "properties": {
    "iso:country":"US",
    "sg:address":"2331 Firstview Dr",
    "sg:city":"Loveland",
    "sg:classifiers":[
        {
            "category":"Professional",
            "subcategory":"Computer Services",
            "type":"Services"
        }
    ],
    "sg:phone":"+1 970 667 7048",
    "sg:postcode":"80538",
    "sg:province":"CO",
    "sg:tags":[
        "home",
        "consulting",
        "page",
        "dev",
        "internet"
    ],
    "wof:name":"Webfoot Communications",
    "wof:placetype":"venue"
},
  "geometry": {"coordinates":[-105.10955300000001,40.416378],"type":"Point"}
}