{
  "type": "Feature",
  "properties": {
    "addr:full":"3090 Sterling Cir Boulder CO 80301",
    "addr:housenumber":"3090",
    "addr:postcode":"80301",
    "addr:street":"Sterling Cir",
    "iso:country":"US",
    "sg:address":"3090 Sterling Cir",
    "sg:city":"Boulder",
    "sg:classifiers":[
        {
            "category":"Wholesale",
            "subcategory":"Office Equipment",
            "type":"Manufacturing & Wholesale Goods"
        }
    ],
    "sg:phone":"+1 303 494 8443",
    "sg:postcode":"80301",
    "sg:province":"CO",
    "sg:tags":[
        "machine",
        "duplicating",
        "copying"
    ],
    "wof:name":"Copy Vend Inc",
    "wof:placetype":"venue"
},
  "geometry": {"coordinates":[-105.227116,40.032163],"type":"Point"}
}