{
  "type": "Feature",
  "properties": {
    "iso:country":"US",
    "sg:address":"555 Zang St",
    "sg:city":"Denver",
    "sg:classifiers":[
        {
            "category":"Government",
            "subcategory":"Office",
            "type":"Public Place"
        }
    ],
    "sg:phone":"+1 303 969 6730",
    "sg:postcode":"80228",
    "sg:province":"CO",
    "sg:tags":[
        "transportation"
    ],
    "wof:name":"Federal Highway Administration",
    "wof:placetype":"venue"
},
  "geometry": {"coordinates":[-105.142115,39.724347],"type":"Point"}
}