{
  "type": "Feature",
  "properties": {
    "iso:country":"US",
    "sg:address":"6515 Monaco St",
    "sg:city":"Commerce City",
    "sg:classifiers":[
        {
            "category":"Building & Trades",
            "subcategory":"Plumbing",
            "type":"Services"
        }
    ],
    "sg:phone":"+1 303 289 9248",
    "sg:postcode":"80022",
    "sg:province":"CO",
    "sg:tags":[
        "contractor"
    ],
    "wof:name":"Vigil Heating Air",
    "wof:placetype":"venue"
},
  "geometry": {"coordinates":[-104.912826,39.816109],"type":"Point"}
}