{
  "type": "Feature",
  "properties": {
    "iso:country":"US",
    "sg:address":"1660 17th Street, Suite 310",
    "sg:city":"Denver",
    "sg:classifiers":[
        {
            "category":"Professional",
            "subcategory":"Computer Services",
            "type":"Services"
        }
    ],
    "sg:phone":"+1 303 534 5106",
    "sg:postcode":"80202",
    "sg:province":"CO",
    "sg:website":"http://agentvi.com",
    "wof:name":"Agent Video Intelligence",
    "wof:placetype":"venue"
},
  "geometry": {"coordinates":[-104.999308,39.752384],"type":"Point"}
}