{
  "type": "Feature",
  "properties": {
    "addr:full":"1733 W Mississippi Ave Denver CO 80219",
    "addr:housenumber":"1733",
    "addr:postcode":"80219",
    "addr:street":"W Mississippi Ave",
    "iso:country":"US",
    "sg:address":"1733 W Mississippi Ave",
    "sg:city":"Denver",
    "sg:classifiers":[
        {
            "category":"Cinema",
            "subcategory":"Movie Rental",
            "type":"Entertainment"
        }
    ],
    "sg:phone":"+1 303 742 8894",
    "sg:postcode":"80219",
    "sg:province":"CO",
    "sg:tags":[
        "leasing",
        "video",
        "disc",
        "tape"
    ],
    "wof:name":"Panorama Video",
    "wof:placetype":"venue"
},
  "geometry": {"coordinates":[-105.007527,39.696799],"type":"Point"}
}