{
  "type": "Feature",
  "properties": {
    "addr:full":"330 18th St Greeley CO 80631",
    "addr:housenumber":"330",
    "addr:postcode":"80631",
    "addr:street":"18Th St",
    "iso:country":"US",
    "sg:address":"330 18th St",
    "sg:city":"Greeley",
    "sg:classifiers":[
        {
            "category":"Retail",
            "subcategory":"Repair Shop",
            "type":"Services"
        }
    ],
    "sg:phone":"+1 970 352 6885",
    "sg:postcode":"80631",
    "sg:province":"CO",
    "sg:tags":[
        "mfg"
    ],
    "wof:name":"Real Leather Co",
    "wof:placetype":"venue"
},
  "geometry": {"coordinates":[-104.683908,40.41003],"type":"Point"}
}