{
  "type": "Feature",
  "properties": {
    "addr:full":"645 2nd St Ouray CO 81427",
    "addr:housenumber":"645",
    "addr:postcode":"81427",
    "addr:street":"2Nd St",
    "iso:country":"US",
    "sg:address":"645 2nd St",
    "sg:city":"Ouray",
    "sg:classifiers":[
        {
            "category":"Professional",
            "subcategory":"Lawyer & Legal Services",
            "type":"Services"
        }
    ],
    "sg:phone":"+1 970 325 4414",
    "sg:postcode":"81427",
    "sg:province":"CO",
    "sg:tags":[
        "attorney"
    ],
    "wof:name":"Tisdell Hockersmith Muller/MCI",
    "wof:placetype":"venue"
},
  "geometry": {"coordinates":[-107.672815,38.023392],"type":"Point"}
}