{
  "type": "Feature",
  "properties": {
    "addr:full":"1461 E Eisenhower Blvd Loveland CO 80537",
    "addr:housenumber":"1461",
    "addr:postcode":"80537",
    "addr:street":"E Eisenhower Blvd",
    "iso:country":"US",
    "sg:address":"1461 E Eisenhower Blvd",
    "sg:city":"Loveland",
    "sg:classifiers":[
        {
            "category":"Shopping",
            "subcategory":"Gifts & Souvenirs",
            "type":"Retail Goods"
        }
    ],
    "sg:phone":"+1 970 461 9690",
    "sg:postcode":"80537",
    "sg:province":"CO",
    "wof:name":"Paper Warehouse",
    "wof:placetype":"venue"
},
  "geometry": {"coordinates":[-105.056416,40.407444],"type":"Point"}
}