{
  "type": "Feature",
  "properties": {
    "addr:full":"4450 Foreign Trade Zone Blvd Colorado Springs CO 80925",
    "addr:postcode":"4450;80925",
    "addr:street":"Zone Blvd",
    "iso:country":"US",
    "sg:address":"4450 Foreign Trade Zone Blvd",
    "sg:city":"Colorado Springs",
    "sg:classifiers":[
        {
            "category":"Manufacturing",
            "subcategory":"Food",
            "type":"Manufacturing & Wholesale Goods"
        }
    ],
    "sg:phone":"+1 719 391 8000",
    "sg:postcode":"80925",
    "sg:province":"CO",
    "sg:tags":[
        "chips"
    ],
    "wof:name":"Colorado Gold Chips Inc",
    "wof:placetype":"venue"
},
  "geometry": {"coordinates":[-104.669303,38.766782],"type":"Point"}
}