{
  "type": "Feature",
  "properties": {
    "iso:country":"US",
    "sg:address":"6010 S Holly St",
    "sg:city":"Englewood",
    "sg:classifiers":[
        {
            "category":"Shopping",
            "subcategory":"Optical Goods",
            "type":"Retail Goods"
        }
    ],
    "sg:phone":"+1 303 721 9666",
    "sg:postcode":"80111",
    "sg:province":"CO",
    "sg:tags":[
        "lense",
        "mfg"
    ],
    "wof:name":"Europtics Inc",
    "wof:placetype":"venue"
},
  "geometry": {"coordinates":[-104.922776,39.608858],"type":"Point"}
}