{
  "type": "Feature",
  "properties": {
    "iso:country":"US",
    "sg:address":"518 17th St",
    "sg:city":"Denver",
    "sg:classifiers":[
        {
            "category":"Real Estate",
            "subcategory":"Real Estate Agent",
            "type":"Services"
        }
    ],
    "sg:phone":"+1 303 825 7374",
    "sg:postcode":"80202",
    "sg:province":"CO",
    "sg:tags":[
        "investment"
    ],
    "wof:name":"David Malo Commercial Rl Est",
    "wof:placetype":"venue"
},
  "geometry": {"coordinates":[-104.990022,39.745271],"type":"Point"}
}