{
  "type": "Feature",
  "properties": {
    "iso:country":"US",
    "sg:address":"11948 Wyandot Cir",
    "sg:city":"Denver",
    "sg:classifiers":[
        {
            "category":"Wholesale",
            "subcategory":"Motor Vehicles",
            "type":"Manufacturing & Wholesale Goods"
        }
    ],
    "sg:phone":"+1 303 829 9730",
    "sg:postcode":"80234",
    "sg:province":"CO",
    "wof:name":"Df Interprizes",
    "wof:placetype":"venue"
},
  "geometry": {"coordinates":[-105.014793,39.913163],"type":"Point"}
}