{
  "type": "Feature",
  "properties": {
    "addr:full":"955 Alder Way Longmont CO 80503",
    "addr:housenumber":"955",
    "addr:postcode":"80503",
    "addr:street":"Alder Way",
    "iso:country":"US",
    "sg:address":"955 Alder Way",
    "sg:city":"Longmont",
    "sg:classifiers":[
        {
            "category":"Building & Trades",
            "subcategory":"Plumbing",
            "type":"Services"
        }
    ],
    "sg:phone":"+1 303 772 7285",
    "sg:postcode":"80503",
    "sg:province":"CO",
    "sg:tags":[
        "contractor"
    ],
    "wof:name":"At Home Heating & Air Inc",
    "wof:placetype":"venue"
},
  "geometry": {"coordinates":[-105.151753,40.147703],"type":"Point"}
}