{
  "type": "Feature",
  "properties": {
    "addr:full":"298 S Joe Martinez Blvd Pueblo CO 81007",
    "addr:housenumber":"298",
    "addr:postcode":"81007",
    "addr:street":"S Joe Martinez Blvd",
    "iso:country":"US",
    "sg:address":"298 S Joe Martinez Blvd",
    "sg:city":"Pueblo",
    "sg:classifiers":[
        {
            "category":"Education",
            "subcategory":"Library",
            "type":"Public Place"
        }
    ],
    "sg:phone":"+1 719 562 5660",
    "sg:postcode":"81007",
    "sg:province":"CO",
    "wof:name":"Pueblo City-County Library Dst",
    "wof:placetype":"venue"
},
  "geometry": {"coordinates":[-104.725955,38.308031],"type":"Point"}
}