{
  "type": "Feature",
  "properties": {
    "addr:full":"1075 Sherman St Ridgway CO 81432",
    "addr:housenumber":"1075",
    "addr:postcode":"81432",
    "addr:street":"Sherman St",
    "iso:country":"US",
    "sg:address":"1075 Sherman St",
    "sg:city":"Ridgway",
    "sg:classifiers":[
        {
            "category":"Professional",
            "type":"Services"
        }
    ],
    "sg:phone":"+1 970 626 5365",
    "sg:postcode":"81432",
    "sg:province":"CO",
    "sg:tags":[
        "establishment"
    ],
    "wof:name":"Juvenile Diversion Program",
    "wof:placetype":"venue"
},
  "geometry": {"coordinates":[-107.763626,38.151315],"type":"Point"}
}