{
  "type": "Feature",
  "properties": {
    "addr:full":"11665 Crow Hill Dr Parker CO 80134",
    "addr:housenumber":"11665",
    "addr:postcode":"80134",
    "addr:street":"Crow Hill Dr",
    "iso:country":"US",
    "sg:address":"11665 Crow Hill Dr",
    "sg:city":"Parker",
    "sg:classifiers":[
        {
            "category":"Building & Trades",
            "subcategory":"Plumbing",
            "type":"Services"
        }
    ],
    "sg:phone":"+1 303 840 6316",
    "sg:postcode":"80134",
    "sg:province":"CO",
    "sg:tags":[
        "plumbing",
        "contractor"
    ],
    "wof:name":"Loenhorst Plumbing",
    "wof:placetype":"venue"
},
  "geometry": {"coordinates":[-104.757266,39.504886],"type":"Point"}
}