{
  "type": "Feature",
  "properties": {
    "addr:full":"4940 Paris St Denver CO 80239",
    "addr:housenumber":"4940",
    "addr:postcode":"80239",
    "addr:street":"Paris St",
    "iso:country":"US",
    "sg:address":"4940 Paris St",
    "sg:city":"Denver",
    "sg:classifiers":[
        {
            "category":"Building & Trades",
            "subcategory":"Construction",
            "type":"Services"
        }
    ],
    "sg:phone":"+1 303 460 8483",
    "sg:postcode":"80239",
    "sg:province":"CO",
    "sg:tags":[
        "cabinetry"
    ],
    "wof:name":"Concepts In Wood Inc",
    "wof:placetype":"venue"
},
  "geometry": {"coordinates":[-104.84882399999999,39.789479],"type":"Point"}
}