{
  "type": "Feature",
  "properties": {
    "addr:full":"2490 W Hampden Ave Sheridan CO 80110",
    "addr:housenumber":"2490",
    "addr:postcode":"80110",
    "addr:street":"W Hampden Ave",
    "iso:country":"US",
    "sg:address":"2490 W Hampden Ave",
    "sg:city":"Sheridan",
    "sg:classifiers":[
        {
            "category":"Restaurant",
            "type":"Food & Drink"
        }
    ],
    "sg:phone":"+1 303 781 9408",
    "sg:postcode":"80110",
    "sg:province":"CO",
    "sg:tags":[
        "caterer"
    ],
    "wof:name":"Fat Fenders Catering",
    "wof:placetype":"venue"
},
  "geometry": {"coordinates":[-105.015975,39.653597],"type":"Point"}
}