{
  "type": "Feature",
  "properties": {
    "iso:country":"US",
    "sg:address":"408 W Ouray Ave",
    "sg:city":"Grand Junction",
    "sg:classifiers":[
        {
            "category":"Building & Trades",
            "subcategory":"Construction",
            "type":"Services"
        }
    ],
    "sg:phone":"+1 970 242 5322",
    "sg:postcode":"81501",
    "sg:province":"CO",
    "sg:tags":[
        "contractor"
    ],
    "wof:name":"G G Drywall",
    "wof:placetype":"venue"
},
  "geometry": {"coordinates":[-108.57717100000001,39.071237],"type":"Point"}
}