{
  "type": "Feature",
  "properties": {
    "iso:country":"US",
    "sg:address":"1350 Independence St",
    "sg:city":"Denver",
    "sg:classifiers":[
        {
            "category":"Shopping",
            "subcategory":"Gifts & Souvenirs",
            "type":"Retail Goods"
        },
        {
            "category":"Manufacturing",
            "subcategory":"Printing",
            "type":"Manufacturing & Wholesale Goods"
        }
    ],
    "sg:phone":"+1 303 233 8798",
    "sg:postcode":"80215",
    "sg:province":"CO",
    "sg:tags":[
        "cards",
        "plastic"
    ],
    "wof:name":"Card Store",
    "wof:placetype":"venue"
},
  "geometry": {"coordinates":[-105.10485199999999,39.738337],"type":"Point"}
}