{
  "type": "Feature",
  "properties": {
    "iso:country":"US",
    "sg:address":"1802 Columbine Village Dr",
    "sg:city":"Woodland Park",
    "sg:classifiers":[
        {
            "category":"Shopping",
            "type":"Retail Goods"
        }
    ],
    "sg:phone":"+1 719 686 8952",
    "sg:postcode":"80863",
    "sg:province":"CO",
    "sg:tags":[
        "candle"
    ],
    "wof:name":"Deluna Naturals Inc",
    "wof:placetype":"venue"
},
  "geometry": {"coordinates":[-105.06246400000001,39.01025],"type":"Point"}
}