{
  "type": "Feature",
  "properties": {
    "addr:full":"3704 Osage St Denver CO 80211",
    "addr:housenumber":"3704",
    "addr:postcode":"80211",
    "addr:street":"Osage St",
    "iso:country":"US",
    "sg:address":"3704 Osage St",
    "sg:city":"Denver",
    "sg:classifiers":[
        {
            "category":"Wholesale",
            "subcategory":"Electrical",
            "type":"Manufacturing & Wholesale Goods"
        }
    ],
    "sg:phone":"+1 303 477 1430",
    "sg:postcode":"80211",
    "sg:province":"CO",
    "sg:tags":[
        "fire",
        "alarm",
        "system"
    ],
    "wof:name":"Bronco Fire Alarm Systems",
    "wof:placetype":"venue"
},
  "geometry": {"coordinates":[-105.005212,39.769232],"type":"Point"}
}