{
  "type": "Feature",
  "properties": {
    "iso:country":"US",
    "sg:address":"506 Main St",
    "sg:city":"Walsenburg",
    "sg:classifiers":[
        {
            "category":"Home & Garden",
            "subcategory":"Hardware",
            "type":"Retail Goods"
        }
    ],
    "sg:phone":"+1 719 738 1370",
    "sg:postcode":"81089",
    "sg:province":"CO",
    "wof:name":"Unfug Hardware Co",
    "wof:placetype":"venue"
},
  "geometry": {"coordinates":[-104.78130400000001,37.624621],"type":"Point"}
}