{
  "type": "Feature",
  "properties": {
    "iso:country":"US",
    "sg:address":"4120 Mark Dabling Blvd",
    "sg:city":"Colorado Springs",
    "sg:classifiers":[
        {
            "category":"Airline",
            "type":"Transportation"
        }
    ],
    "sg:phone":"+1 719 594 0033",
    "sg:postcode":"80907",
    "sg:province":"CO",
    "sg:tags":[
        "cargo",
        "air"
    ],
    "wof:name":"Colorado Air Cargo Inc",
    "wof:placetype":"venue"
},
  "geometry": {"coordinates":[-104.826379,38.889383],"type":"Point"}
}