{
  "type": "Feature",
  "properties": {
    "iso:country":"US",
    "sg:address":"3718 Norwood Dr",
    "sg:city":"Littleton",
    "sg:classifiers":[
        {
            "category":"Retail",
            "subcategory":"Auto Repair",
            "type":"Services"
        }
    ],
    "sg:phone":"+1 303 761 8888",
    "sg:postcode":"80125",
    "sg:province":"CO",
    "sg:tags":[
        "transmission"
    ],
    "wof:name":"Ccgg Inc",
    "wof:placetype":"venue"
},
  "geometry": {"coordinates":[-105.037396,39.555322],"type":"Point"}
}