{
  "type": "Feature",
  "properties": {
    "iso:country":"US",
    "sg:address":"102 S Tejon St",
    "sg:city":"Colorado Springs",
    "sg:classifiers":[
        {
            "category":"Manufacturing",
            "subcategory":"Chemicals & Compounds",
            "type":"Manufacturing & Wholesale Goods"
        }
    ],
    "sg:phone":"+1 719 578 3344",
    "sg:postcode":"80903",
    "sg:province":"CO",
    "sg:tags":[
        "preparation",
        "toilet",
        "mfg"
    ],
    "wof:name":"Monty D Cosmetics LLC",
    "wof:placetype":"venue"
},
  "geometry": {"coordinates":[-104.823711,38.831557],"type":"Point"}
}