{
  "type": "Feature",
  "properties": {
    "addr:full":"1705 1st Ave Greeley CO 80631",
    "addr:housenumber":"1705",
    "addr:postcode":"80631",
    "addr:street":"1St Ave",
    "iso:country":"US",
    "sg:address":"1705 1st Ave",
    "sg:city":"Greeley",
    "sg:classifiers":[
        {
            "category":"Wholesale",
            "subcategory":"Machinery & Supplies",
            "type":"Manufacturing & Wholesale Goods"
        }
    ],
    "sg:phone":"+1 970 352 0101",
    "sg:postcode":"80631",
    "sg:province":"CO",
    "sg:tags":[
        "field",
        "oil"
    ],
    "wof:name":"W B Supply Co",
    "wof:placetype":"venue"
},
  "geometry": {"coordinates":[-104.67805300000001,40.411986],"type":"Point"}
}