{
  "type": "Feature",
  "properties": {
    "iso:country":"US",
    "sg:address":"1400 E County Line Rd",
    "sg:city":"Littleton",
    "sg:classifiers":[
        {
            "category":"Freight",
            "type":"Transportation"
        }
    ],
    "sg:phone":"+1 303 799 6466",
    "sg:postcode":"80126",
    "sg:province":"CO",
    "sg:tags":[
        "general"
    ],
    "wof:name":"AAA County Line Self Storage",
    "wof:placetype":"venue"
},
  "geometry": {"coordinates":[-104.97711200000001,39.566083],"type":"Point"}
}