{
  "type": "Feature",
  "properties": {
    "addr:full":"961 Main St Grand Junction CO 81501",
    "addr:housenumber":"961",
    "addr:postcode":"81501",
    "addr:street":"Main St",
    "iso:country":"US",
    "sg:address":"961 Main St",
    "sg:city":"Grand Junction",
    "sg:classifiers":[
        {
            "category":"Education",
            "subcategory":"Special Training",
            "type":"Public Place"
        }
    ],
    "sg:phone":"+1 970 245 0669",
    "sg:postcode":"81501",
    "sg:province":"CO",
    "sg:tags":[
        "center"
    ],
    "wof:name":"Pal Learning Ctr",
    "wof:placetype":"venue"
},
  "geometry": {"coordinates":[-108.55685800000001,39.067231],"type":"Point"}
}