{
  "type": "Feature",
  "properties": {
    "iso:country":"US",
    "sg:address":"5070 Federal Boulevard",
    "sg:city":"Denver",
    "sg:classifiers":[
        {
            "category":"Education",
            "subcategory":"Vocational School",
            "type":"Public Place"
        }
    ],
    "sg:phone":"+1 303 458 7899",
    "sg:postcode":"80221",
    "sg:province":"CO",
    "sg:tags":[
        "cosmetology"
    ],
    "wof:name":"Yesenia's Beauty Salon & School",
    "wof:placetype":"venue"
},
  "geometry": {"coordinates":[-105.024987,39.788695],"type":"Point"}
}