{
  "type": "Feature",
  "properties": {
    "addr:full":"2591 Begonia Ct Loveland CO 80537",
    "addr:housenumber":"2591",
    "addr:postcode":"80537",
    "addr:street":"Begonia Ct",
    "iso:country":"US",
    "sg:address":"2591 Begonia Ct",
    "sg:city":"Loveland",
    "sg:classifiers":[
        {
            "category":"Shopping",
            "subcategory":"Beauty & Cosmetics",
            "type":"Retail Goods"
        }
    ],
    "sg:phone":"+1 970 667 5732",
    "sg:postcode":"80537",
    "sg:province":"CO",
    "sg:tags":[
        "merchandise"
    ],
    "wof:name":"Mary Kay Cosmetics",
    "wof:placetype":"venue"
},
  "geometry": {"coordinates":[-105.11184900000001,40.391604],"type":"Point"}
}