{
  "type": "Feature",
  "properties": {
    "iso:country":"US",
    "sg:address":"1411 Enterprise Ct",
    "sg:city":"Rifle",
    "sg:classifiers":[
        {
            "category":"Manufacturing",
            "subcategory":"Food",
            "type":"Manufacturing & Wholesale Goods"
        }
    ],
    "sg:phone":"+1 970 625 2817",
    "sg:postcode":"81650",
    "sg:province":"CO",
    "sg:tags":[
        "tea",
        "coffee",
        "product"
    ],
    "wof:name":"True Brew Coffee",
    "wof:placetype":"venue"
},
  "geometry": {"coordinates":[-107.760597,39.52328],"type":"Point"}
}