{
  "type": "Feature",
  "properties": {
    "addr:full":"915 Co Rd 23 Leadville CO 80461",
    "addr:housenumber":"915;23",
    "addr:postcode":"80461",
    "addr:street":"Co Rd",
    "iso:country":"US",
    "sg:address":"915 Co Rd 23",
    "sg:city":"Leadville",
    "sg:classifiers":[
        {
            "category":"Building & Trades",
            "subcategory":"Equipment Rental",
            "type":"Services"
        }
    ],
    "sg:phone":"+1 719 486 2627",
    "sg:postcode":"80461",
    "sg:province":"CO",
    "sg:tags":[
        "aircraft",
        "leasing",
        "charter"
    ],
    "wof:name":"Leadville Airport",
    "wof:placetype":"venue"
},
  "geometry": {"coordinates":[-106.32024199999999,39.23254],"type":"Point"}
}