{
  "type": "Feature",
  "properties": {
    "addr:full":"4196 Ute Hwy Longmont CO 80503",
    "addr:housenumber":"4196",
    "addr:postcode":"80503",
    "addr:street":"Ute Hwy",
    "iso:country":"US",
    "sg:address":"4196 Ute Hwy",
    "sg:city":"Longmont",
    "sg:classifiers":[
        {
            "category":"Retail",
            "subcategory":"Repair Shop",
            "type":"Services"
        }
    ],
    "sg:phone":"+1 303 823 6363",
    "sg:postcode":"80503",
    "sg:province":"CO",
    "sg:tags":[
        "scooter",
        "motorcycle",
        "motor"
    ],
    "wof:name":"Redhill Motorcycle WERX",
    "wof:placetype":"venue"
},
  "geometry": {"coordinates":[-105.257498,40.21685],"type":"Point"}
}