{
  "type": "Feature",
  "properties": {
    "iso:country":"US",
    "sg:address":"4466 Barnes Rd",
    "sg:city":"Colorado Springs",
    "sg:classifiers":[
        {
            "category":"Professional",
            "subcategory":"Computer Services",
            "type":"Services"
        }
    ],
    "sg:phone":"+1 719 596 9884",
    "sg:postcode":"80917",
    "sg:province":"CO",
    "sg:tags":[
        "internet"
    ],
    "wof:name":"Castleguard Cyber Cafe",
    "wof:placetype":"venue"
},
  "geometry": {"coordinates":[-104.74417099999999,38.897058],"type":"Point"}
}