{
  "type": "Feature",
  "properties": {
    "addr:full":"697 Mesa Ave Rifle CO 81650",
    "addr:housenumber":"697",
    "addr:postcode":"81650",
    "addr:street":"Mesa Ave",
    "iso:country":"US",
    "sg:address":"697 Mesa Ave",
    "sg:city":"Rifle",
    "sg:classifiers":[
        {
            "category":"Building & Trades",
            "subcategory":"Construction",
            "type":"Services"
        }
    ],
    "sg:phone":"+1 970 625 5233",
    "sg:postcode":"81650",
    "sg:province":"CO",
    "sg:tags":[
        "project"
    ],
    "wof:name":"Roan Cliff Construction Inc",
    "wof:placetype":"venue"
},
  "geometry": {"coordinates":[-107.798564,39.533947],"type":"Point"}
}