{
  "type": "Feature",
  "properties": {
    "addr:full":"4465 Kipling St Wheat Ridge CO 80033",
    "addr:housenumber":"4465",
    "addr:postcode":"80033",
    "addr:street":"Kipling St",
    "iso:country":"US",
    "sg:address":"4465 Kipling St",
    "sg:city":"Wheat Ridge",
    "sg:classifiers":[
        {
            "category":"Professional",
            "subcategory":"Lawyer & Legal Services",
            "type":"Services"
        }
    ],
    "sg:phone":"+1 303 456 8472",
    "sg:postcode":"80033",
    "sg:province":"CO",
    "sg:tags":[
        "attorney"
    ],
    "wof:name":"Floyd M Youngblood PC",
    "wof:placetype":"venue"
},
  "geometry": {"coordinates":[-105.10968,39.779242],"type":"Point"}
}