{
  "type": "Feature",
  "properties": {
    "addr:full":"110 S Main St Mancos CO 81328",
    "addr:housenumber":"110",
    "addr:postcode":"81328",
    "addr:street":"S Main St",
    "iso:country":"US",
    "sg:address":"110 S Main St",
    "sg:city":"Mancos",
    "sg:classifiers":[
        {
            "category":"Food & Beverages",
            "subcategory":"Bakery",
            "type":"Retail Goods"
        }
    ],
    "sg:phone":"+1 970 533 1200",
    "sg:postcode":"81328",
    "sg:province":"CO",
    "sg:tags":[
        "baker"
    ],
    "wof:name":"Absolute Bakery & Cafe",
    "wof:placetype":"venue"
},
  "geometry": {"coordinates":[-108.289008,37.345099],"type":"Point"}
}