{
  "type": "Feature",
  "properties": {
    "iso:country":"US",
    "sg:address":"1302 S Shields St",
    "sg:city":"Fort Collins",
    "sg:classifiers":[
        {
            "category":"Health Services",
            "subcategory":"Health Practitioner",
            "type":"Services"
        }
    ],
    "sg:phone":"+1 970 282 7151",
    "sg:postcode":"80521",
    "sg:province":"CO",
    "sg:tags":[
        "psychologist"
    ],
    "wof:name":"Scott Poland PHD",
    "wof:placetype":"venue"
},
  "geometry": {"coordinates":[-105.09591,40.57059],"type":"Point"}
}