{
  "type": "Feature",
  "properties": {
    "iso:country":"US",
    "sg:address":"6365 W Crestline Ave",
    "sg:city":"Littleton",
    "sg:classifiers":[
        {
            "category":"Professional",
            "type":"Services"
        }
    ],
    "sg:phone":"+1 303 703 3985",
    "sg:postcode":"80123",
    "sg:province":"CO",
    "wof:name":"S & S Drilling Inc",
    "wof:placetype":"venue"
},
  "geometry": {"coordinates":[-105.067937,39.617703],"type":"Point"}
}