{
  "type": "Feature",
  "properties": {
    "addr:full":"1209 E 9th Ave Denver CO 80218",
    "addr:housenumber":"1209",
    "addr:postcode":"80218",
    "addr:street":"E 9Th Ave",
    "iso:country":"US",
    "sg:address":"1209 E 9th Ave",
    "sg:city":"Denver",
    "sg:classifiers":[
        {
            "category":"Shopping",
            "subcategory":"Gifts & Souvenirs",
            "type":"Retail Goods"
        }
    ],
    "sg:phone":"+1 303 832 4244",
    "sg:postcode":"80218",
    "sg:province":"CO",
    "wof:name":"Absolutely Fabulous",
    "wof:placetype":"venue"
},
  "geometry": {"coordinates":[-104.972418,39.730534],"type":"Point"}
}