{
  "type": "Feature",
  "properties": {
    "iso:country":"US",
    "sg:address":"733 Main St",
    "sg:city":"Ouray",
    "sg:classifiers":[
        {
            "category":"Shopping",
            "subcategory":"Gifts & Souvenirs",
            "type":"Retail Goods"
        }
    ],
    "sg:phone":"+1 970 325 4530",
    "sg:postcode":"81427",
    "sg:province":"CO",
    "sg:tags":[
        "shop"
    ],
    "wof:name":"Kendall Mountain Trading Co",
    "wof:placetype":"venue"
},
  "geometry": {"coordinates":[-107.67142800000001,38.02462],"type":"Point"}
}