{
  "type": "Feature",
  "properties": {
    "addr:full":"541 S Lincoln Ave Loveland CO 80537",
    "addr:housenumber":"541",
    "addr:postcode":"80537",
    "addr:street":"S Lincoln Ave",
    "iso:country":"US",
    "sg:address":"541 S Lincoln Ave",
    "sg:city":"Loveland",
    "sg:classifiers":[
        {
            "category":"Professional",
            "subcategory":"Computer Services",
            "type":"Services"
        }
    ],
    "sg:phone":"+1 970 962 9506",
    "sg:postcode":"80537",
    "sg:province":"CO",
    "sg:tags":[
        "processing",
        "datum"
    ],
    "wof:name":"Banking Services Group LLC",
    "wof:placetype":"venue"
},
  "geometry": {"coordinates":[-105.07335,40.388574],"type":"Point"}
}