{
  "type": "Feature",
  "properties": {
    "iso:country":"US",
    "sg:address":"60 S Jay St",
    "sg:city":"Lakewood",
    "sg:classifiers":[
        {
            "category":"Building & Trades",
            "subcategory":"Construction",
            "type":"Services"
        }
    ],
    "sg:phone":"+1 303 237 9299",
    "sg:postcode":"80226",
    "sg:province":"CO",
    "sg:tags":[
        "masonry",
        "contractor"
    ],
    "wof:name":"James Robertson Artist Crftsmn",
    "wof:placetype":"venue"
},
  "geometry": {"coordinates":[-105.064988,39.71601],"type":"Point"}
}