{
  "type": "Feature",
  "properties": {
    "iso:country":"US",
    "sg:address":"100 W Colorado Ave",
    "sg:city":"Telluride",
    "sg:classifiers":[
        {
            "category":"Building & Trades",
            "subcategory":"Construction",
            "type":"Services"
        }
    ],
    "sg:phone":"+1 970 728 4753",
    "sg:postcode":"81435",
    "sg:province":"CO",
    "sg:tags":[
        "general",
        "contractor"
    ],
    "wof:name":"Groman Construction Co",
    "wof:placetype":"venue"
},
  "geometry": {"coordinates":[-107.811789,37.937806],"type":"Point"}
}