{
  "type": "Feature",
  "properties": {
    "addr:full":"1960 Sherman St Denver CO 80203",
    "addr:housenumber":"1960",
    "addr:postcode":"80203",
    "addr:street":"Sherman St",
    "iso:country":"US",
    "sg:address":"1960 Sherman St",
    "sg:city":"Denver",
    "sg:classifiers":[
        {
            "category":"Professional",
            "type":"Services"
        }
    ],
    "sg:phone":"+1 303 861 1093",
    "sg:postcode":"80203",
    "sg:province":"CO",
    "wof:name":"Zecchino Piernas",
    "wof:placetype":"venue"
},
  "geometry": {"coordinates":[-104.98477699999999,39.746714],"type":"Point"}
}