{
  "type": "Feature",
  "properties": {
    "iso:country":"US",
    "sg:address":"5450 Trail Pt",
    "sg:city":"Fort Collins",
    "sg:classifiers":[
        {
            "category":"Food & Beverages",
            "subcategory":"Liquor & Beverages",
            "type":"Retail Goods"
        }
    ],
    "sg:phone":"+1 970 472 5445",
    "sg:postcode":"80524",
    "sg:province":"CO",
    "sg:tags":[
        "wine"
    ],
    "wof:name":"Wine Design",
    "wof:placetype":"venue"
},
  "geometry": {"coordinates":[-104.974169,40.597031],"type":"Point"}
}