{
  "type": "Feature",
  "properties": {
    "addr:full":"109 E 37th St Loveland CO 80538",
    "addr:housenumber":"109",
    "addr:postcode":"80538",
    "addr:street":"E 37Th St",
    "iso:country":"US",
    "sg:address":"109 E 37th St",
    "sg:city":"Loveland",
    "sg:classifiers":[
        {
            "category":"Retail",
            "subcategory":"Laundry & Dry Cleaning",
            "type":"Services"
        }
    ],
    "sg:phone":"+1 970 667 7724",
    "sg:postcode":"80538",
    "sg:province":"CO",
    "sg:tags":[
        "cleaners"
    ],
    "wof:name":"Blue Ribbon Cleaners",
    "wof:placetype":"venue"
},
  "geometry": {"coordinates":[-105.07646800000001,40.430496],"type":"Point"}
}