{
  "type": "Feature",
  "properties": {
    "iso:country":"US",
    "sg:address":"4643 S Ulster St",
    "sg:city":"Denver",
    "sg:classifiers":[
        {
            "category":"Professional",
            "type":"Services"
        }
    ],
    "sg:phone":"+1 720 200 7600",
    "sg:postcode":"80237",
    "sg:province":"CO",
    "wof:name":"Old Mutual Asset",
    "wof:placetype":"venue"
},
  "geometry": {"coordinates":[-104.89620600000001,39.630875],"type":"Point"}
}