{
  "type": "Feature",
  "properties": {
    "iso:country":"US",
    "sg:address":"28292 Gale Rd",
    "sg:city":"Pueblo",
    "sg:classifiers":[
        {
            "category":"Building & Trades",
            "subcategory":"Landscaping Services",
            "type":"Services"
        }
    ],
    "sg:phone":"+1 719 948 4558",
    "sg:postcode":"81006",
    "sg:province":"CO",
    "sg:tags":[
        "lawn",
        "maintenance",
        "grounds"
    ],
    "wof:name":"J B's Lawn Svc",
    "wof:placetype":"venue"
},
  "geometry": {"coordinates":[-104.519178,38.24863],"type":"Point"}
}