{
  "type": "Feature",
  "properties": {
    "addr:full":"6686 York St Denver CO 80229",
    "addr:housenumber":"6686",
    "addr:postcode":"80229",
    "addr:street":"York St",
    "iso:country":"US",
    "sg:address":"6686 York St",
    "sg:city":"Denver",
    "sg:classifiers":[
        {
            "category":"Home & Garden",
            "subcategory":"Building Materials",
            "type":"Retail Goods"
        },
        {
            "category":"Manufacturing",
            "subcategory":"Glass & Minerals",
            "type":"Manufacturing & Wholesale Goods"
        }
    ],
    "sg:phone":"+1 303 286 7653",
    "sg:postcode":"80229",
    "sg:province":"CO",
    "sg:tags":[
        "concrete",
        "stone",
        "mfg",
        "product",
        "contractor"
    ],
    "wof:name":"Blake's Stone Specialties",
    "wof:placetype":"venue"
},
  "geometry": {"coordinates":[-104.95914,39.816593],"type":"Point"}
}