{
  "type": "Feature",
  "properties": {
    "iso:country":"US",
    "sg:address":"10003 W 81st Ln",
    "sg:city":"Arvada",
    "sg:classifiers":[
        {
            "category":"Building & Trades",
            "subcategory":"Plumbing",
            "type":"Services"
        }
    ],
    "sg:phone":"+1 303 424 6188",
    "sg:postcode":"80005",
    "sg:province":"CO",
    "sg:tags":[
        "sheet",
        "metal",
        "heating",
        "air",
        "conditioning",
        "contractor"
    ],
    "wof:name":"L & H Sheet Metal",
    "wof:placetype":"venue"
},
  "geometry": {"coordinates":[-105.111694,39.846538],"type":"Point"}
}