{
  "type": "Feature",
  "properties": {
    "iso:country":"US",
    "sg:address":"1025 W Fillmore St",
    "sg:city":"Colorado Springs",
    "sg:classifiers":[
        {
            "category":"Personal",
            "subcategory":"Beauty Salon",
            "type":"Services"
        }
    ],
    "sg:phone":"+1 719 632 4748",
    "sg:postcode":"80907",
    "sg:province":"CO",
    "sg:tags":[
        "to",
        "ca",
        "hair",
        "ready",
        "wear",
        "apparel",
        "lady"
    ],
    "wof:name":"Aristocuts",
    "wof:placetype":"venue"
},
  "geometry": {"coordinates":[-104.843779,38.876243],"type":"Point"}
}