{
  "type": "Feature",
  "properties": {
    "addr:full":"7903 S Carr Ct Littleton CO 80128",
    "addr:housenumber":"7903",
    "addr:postcode":"80128",
    "addr:street":"S Carr Ct",
    "iso:country":"US",
    "sg:address":"7903 S Carr Ct",
    "sg:city":"Littleton",
    "sg:classifiers":[
        {
            "category":"Real Estate",
            "subcategory":"Real Estate Agent",
            "type":"Services"
        }
    ],
    "sg:phone":"+1 303 904 2450",
    "sg:postcode":"80128",
    "sg:province":"CO",
    "wof:name":"Dunning Group Real Estate",
    "wof:placetype":"venue"
},
  "geometry": {"coordinates":[-105.092563,39.569879],"type":"Point"}
}