{
  "type": "Feature",
  "properties": {
    "iso:country":"US",
    "sg:address":"715 Washington Ave",
    "sg:city":"Golden",
    "sg:classifiers":[
        {
            "category":"Restaurant",
            "type":"Food & Drink"
        }
    ],
    "sg:phone":"+1 303 277 0966",
    "sg:postcode":"80401",
    "sg:province":"CO",
    "sg:tags":[
        "eating"
    ],
    "wof:name":"Santiago's Mexican Restaurant",
    "wof:placetype":"venue"
},
  "geometry": {"coordinates":[-105.225222,39.7597],"type":"Point"}
}