{
  "type": "Feature",
  "properties": {
    "iso:country":"US",
    "sg:address":"1658 York St",
    "sg:city":"Denver",
    "sg:classifiers":[
        {
            "category":"Professional",
            "subcategory":"Management & Consulting",
            "type":"Services"
        },
        {
            "category":"Arts & Performance",
            "subcategory":"Theater",
            "type":"Entertainment"
        }
    ],
    "sg:phone":"+1 303 329 9292",
    "sg:postcode":"80206",
    "sg:province":"CO",
    "sg:tags":[
        "bureau",
        "entertainers-family",
        "musical",
        "business",
        "artist"
    ],
    "wof:name":"Chuck Morris Entertainment",
    "wof:placetype":"venue"
},
  "geometry": {"coordinates":[-104.959822,39.742582],"type":"Point"}
}