{
  "type": "Feature",
  "properties": {
    "iso:country":"US",
    "sg:address":"6192 N Wilder Ct",
    "sg:city":"Parker",
    "sg:classifiers":[
        {
            "category":"Professional",
            "subcategory":"Employment Agencies",
            "type":"Services"
        }
    ],
    "sg:phone":"+1 303 841 5564",
    "sg:postcode":"80134",
    "sg:province":"CO",
    "wof:name":"Project Search Inc",
    "wof:placetype":"venue"
},
  "geometry": {"coordinates":[-104.71212300000001,39.452411],"type":"Point"}
}