{
  "type": "Feature",
  "properties": {
    "addr:full":"301 E Douglas Rd Fort Collins CO 80524",
    "addr:housenumber":"301",
    "addr:postcode":"80524",
    "addr:street":"E Douglas Rd",
    "iso:country":"US",
    "sg:address":"301 E Douglas Rd",
    "sg:city":"Fort Collins",
    "sg:classifiers":[
        {
            "category":"Freight",
            "type":"Transportation"
        }
    ],
    "sg:phone":"+1 970 691 1437",
    "sg:postcode":"80524",
    "sg:province":"CO",
    "sg:tags":[
        "operator",
        "local",
        "trucking"
    ],
    "wof:name":"Mistler Trucking Inc",
    "wof:placetype":"venue"
},
  "geometry": {"coordinates":[-105.072525,40.639517],"type":"Point"}
}