{
  "type": "Feature",
  "properties": {
    "addr:full":"3501 W 104th Ave Westminster CO 80031",
    "addr:housenumber":"3501",
    "addr:postcode":"80031",
    "addr:street":"W 104Th Ave",
    "iso:country":"US",
    "sg:address":"3501 W 104th Ave",
    "sg:city":"Westminster",
    "sg:classifiers":[
        {
            "category":"Social Services",
            "subcategory":"Child Care",
            "type":"Services"
        }
    ],
    "sg:phone":"+1 303 466 6887",
    "sg:postcode":"80031",
    "sg:province":"CO",
    "sg:website":"www.wcon.org",
    "wof:name":"Noah's Ark Learning Ctr",
    "wof:placetype":"venue"
},
  "geometry": {"coordinates":[-105.034437,39.885166],"type":"Point"}
}