{
  "type": "Feature",
  "properties": {
    "iso:country":"US",
    "sg:address":"338 W Victory Way",
    "sg:city":"Craig",
    "sg:classifiers":[
        {
            "category":"Shopping",
            "type":"Retail Goods"
        }
    ],
    "sg:phone":"+1 970 824 4664",
    "sg:postcode":"81625",
    "sg:province":"CO",
    "sg:tags":[
        "product",
        "wood"
    ],
    "wof:name":"Modern Wood Inc",
    "wof:placetype":"venue"
},
  "geometry": {"coordinates":[-107.55100299999999,40.514155],"type":"Point"}
}