{
  "type": "Feature",
  "properties": {
    "addr:full":"32755 Co Rd 85 Crook CO 80726",
    "addr:housenumber":"32755;85",
    "addr:postcode":"80726",
    "addr:street":"Co Rd",
    "iso:country":"US",
    "sg:address":"32755 Co Rd 85",
    "sg:city":"Crook",
    "sg:phone":"+1 970 886 2855",
    "sg:postcode":"80726",
    "sg:province":"CO",
    "sg:tags":[
        "farm",
        "field",
        "management",
        "crop"
    ],
    "wof:name":"Chad Lange",
    "wof:placetype":"venue"
},
  "geometry": {"coordinates":[-102.767539,40.913597],"type":"Point"}
}