{
  "type": "Feature",
  "properties": {
    "iso:country":"US",
    "sg:address":"7812 S Newbern Cir",
    "sg:city":"Aurora",
    "sg:classifiers":[
        {
            "category":"Retail",
            "subcategory":"Repair Shop",
            "type":"Services"
        }
    ],
    "sg:phone":"+1 303 693 6419",
    "sg:postcode":"80016",
    "sg:province":"CO",
    "sg:tags":[
        "scale"
    ],
    "wof:name":"Q A Balance Svc",
    "wof:placetype":"venue"
},
  "geometry": {"coordinates":[-104.686241,39.570957],"type":"Point"}
}