{
  "type": "Feature",
  "properties": {
    "iso:country":"US",
    "sg:address":"321 7th St",
    "sg:city":"Meeker",
    "sg:classifiers":[
        {
            "category":"Government",
            "subcategory":"Office",
            "type":"Public Place"
        }
    ],
    "sg:phone":"+1 970 878 5086",
    "sg:postcode":"81641",
    "sg:province":"CO",
    "wof:name":"US Geological Water Resources",
    "wof:placetype":"venue"
},
  "geometry": {"coordinates":[-107.915232,40.037392],"type":"Point"}
}