{
  "type": "Feature",
  "properties": {
    "iso:country":"US",
    "sg:address":"455 S 3rd St",
    "sg:city":"Carbondale",
    "sg:classifiers":[
        {
            "category":"Education",
            "subcategory":"School",
            "type":"Public Place"
        }
    ],
    "sg:phone":"+1 970 384 5700",
    "sg:postcode":"81623",
    "sg:province":"CO",
    "sg:tags":[
        "middle"
    ],
    "wof:name":"Carbondale Middle School",
    "wof:placetype":"venue"
},
  "geometry": {"coordinates":[-107.21005,39.39644],"type":"Point"}
}