{
  "type": "Feature",
  "properties": {
    "addr:full":"3501 E Prospect Rd Fort Collins CO 80525",
    "addr:housenumber":"3501",
    "addr:postcode":"80525",
    "addr:street":"E Prospect Rd",
    "iso:country":"US",
    "sg:address":"3501 E Prospect Rd",
    "sg:city":"Fort Collins",
    "sg:classifiers":[
        {
            "category":"Wholesale",
            "subcategory":"Farm Supplies",
            "type":"Manufacturing & Wholesale Goods"
        }
    ],
    "sg:phone":"+1 970 221 7173",
    "sg:postcode":"80525",
    "sg:province":"CO",
    "sg:tags":[
        "mulch"
    ],
    "wof:name":"Hageman Earth Cycle",
    "wof:placetype":"venue"
},
  "geometry": {"coordinates":[-105.010184,40.566748],"type":"Point"}
}