{
  "type": "Feature",
  "properties": {
    "iso:country":"US",
    "sg:address":"54043 Co Rd 37",
    "sg:city":"Nunn",
    "sg:classifiers":[
        {
            "category":"Professional",
            "subcategory":"Testing Lab",
            "type":"Services"
        }
    ],
    "sg:phone":"+1 970 897 2340",
    "sg:postcode":"80648",
    "sg:province":"CO",
    "sg:tags":[
        "calibration"
    ],
    "sg:website":"www.ceesi.com",
    "wof:name":"Colorado Engineering",
    "wof:placetype":"venue"
},
  "geometry": {"coordinates":[-104.715155,40.79331],"type":"Point"}
}