{
  "type": "Feature",
  "properties": {
    "addr:full":"606 S Santa Fe Ave Fountain CO 80817",
    "addr:housenumber":"606",
    "addr:postcode":"80817",
    "addr:street":"S Santa Fe Ave",
    "iso:country":"US",
    "sg:address":"606 S Santa Fe Ave",
    "sg:city":"Fountain",
    "sg:classifiers":[
        {
            "category":"Bars & Pubs",
            "type":"Food & Drink"
        }
    ],
    "sg:phone":"+1 719 382 7467",
    "sg:postcode":"80817",
    "sg:province":"CO",
    "sg:tags":[
        "drinking"
    ],
    "wof:name":"Coody Brown's Saloon",
    "wof:placetype":"venue"
},
  "geometry": {"coordinates":[-104.70549099999999,38.676431],"type":"Point"}
}