{
  "type": "Feature",
  "properties": {
    "addr:full":"514 S College Ave Fort Collins CO 80524",
    "addr:housenumber":"514",
    "addr:postcode":"80524",
    "addr:street":"S College Ave",
    "iso:country":"US",
    "sg:address":"514 S College Ave",
    "sg:city":"Fort Collins",
    "sg:classifiers":[
        {
            "category":"Shopping",
            "subcategory":"Discount & Variety Stores",
            "type":"Retail Goods"
        }
    ],
    "sg:phone":"+1 970 207 9851",
    "sg:postcode":"80524",
    "sg:province":"CO",
    "wof:name":"JD Dollar Inc",
    "wof:placetype":"venue"
},
  "geometry": {"coordinates":[-105.07699700000001,40.580298],"type":"Point"}
}