{
  "type": "Feature",
  "properties": {
    "iso:country":"US",
    "sg:address":"19013 W 61st Pl",
    "sg:city":"Golden",
    "sg:classifiers":[
        {
            "category":"Building & Trades",
            "subcategory":"Construction",
            "type":"Services"
        }
    ],
    "sg:phone":"+1 303 278 0662",
    "sg:postcode":"80403",
    "sg:province":"CO",
    "sg:tags":[
        "house"
    ],
    "wof:name":"Old Time Construction",
    "wof:placetype":"venue"
},
  "geometry": {"coordinates":[-105.21316400000001,39.807949],"type":"Point"}
}