{
  "type": "Feature",
  "properties": {
    "iso:country":"US",
    "sg:address":"830 Macon Ave",
    "sg:city":"Canon City",
    "sg:classifiers":[
        {
            "category":"Banks & Credit Unions",
            "subcategory":"Bank",
            "type":"Services"
        }
    ],
    "sg:phone":"+1 719 275 8300",
    "sg:postcode":"81212",
    "sg:province":"CO",
    "sg:tags":[
        "loan",
        "real estate"
    ],
    "wof:name":"Homequest Mortgage",
    "wof:placetype":"venue"
},
  "geometry": {"coordinates":[-105.236492,38.443565],"type":"Point"}
}