{
  "type": "Feature",
  "properties": {
    "iso:country":"US",
    "sg:address":"430 S Tejon St",
    "sg:city":"Denver",
    "sg:classifiers":[
        {
            "category":"Organizations",
            "subcategory":"Religious Organization",
            "type":"Services"
        }
    ],
    "sg:phone":"+1 303 698 1789",
    "sg:postcode":"80223",
    "sg:province":"CO",
    "sg:tags":[
        "church"
    ],
    "wof:name":"Valverde Community Church",
    "wof:placetype":"venue"
},
  "geometry": {"coordinates":[-105.01091700000001,39.709027],"type":"Point"}
}