{
  "type": "Feature",
  "properties": {
    "iso:country":"US",
    "sg:address":"1586 S Robb Way",
    "sg:city":"Denver",
    "sg:classifiers":[
        {
            "category":"Manufacturing",
            "subcategory":"Metals",
            "type":"Manufacturing & Wholesale Goods"
        }
    ],
    "sg:phone":"+1 303 789 1200",
    "sg:postcode":"80232",
    "sg:province":"CO",
    "sg:tags":[
        "mfg",
        "fabricated",
        "rubber",
        "prod",
        "fabrication",
        "structural"
    ],
    "wof:name":"Baski Inc",
    "wof:placetype":"venue"
},
  "geometry": {"coordinates":[-105.126706,39.686425],"type":"Point"}
}