{
  "type": "Feature",
  "properties": {
    "addr:full":"5325 Co Rd 154 Glenwood Springs CO 81601",
    "addr:housenumber":"5325;154",
    "addr:postcode":"81601",
    "addr:street":"Co Rd",
    "iso:country":"US",
    "sg:address":"5325 Co Rd 154",
    "sg:city":"Glenwood Springs",
    "sg:classifiers":[
        {
            "category":"Professional",
            "subcategory":"Business Services",
            "type":"Services"
        }
    ],
    "sg:phone":"+1 970 945 0447",
    "sg:postcode":"81601",
    "sg:province":"CO",
    "sg:tags":[
        "record",
        "document"
    ],
    "wof:name":"File Finders LTD",
    "wof:placetype":"venue"
},
  "geometry": {"coordinates":[-107.27281000000001,39.474386],"type":"Point"}
}