{
  "type": "Feature",
  "properties": {
    "addr:full":"630 S 42nd St Boulder CO 80305",
    "addr:housenumber":"630",
    "addr:postcode":"80305",
    "addr:street":"S 42Nd St",
    "iso:country":"US",
    "sg:address":"630 S 42nd St",
    "sg:city":"Boulder",
    "sg:classifiers":[
        {
            "category":"Professional",
            "subcategory":"Art Services",
            "type":"Services"
        }
    ],
    "sg:phone":"+1 303 245 0433",
    "sg:postcode":"80305",
    "sg:province":"CO",
    "sg:tags":[
        "photographer"
    ],
    "wof:name":"Houser Lincoln Photography",
    "wof:placetype":"venue"
},
  "geometry": {"coordinates":[-105.24538699999999,39.983656],"type":"Point"}
}