{
  "type": "Feature",
  "properties": {
    "addr:full":"8430 N 107th St Longmont CO 80504",
    "addr:housenumber":"8430",
    "addr:postcode":"80504",
    "addr:street":"N 107Th St",
    "iso:country":"US",
    "sg:address":"8430 N 107th St",
    "sg:city":"Longmont",
    "sg:classifiers":[
        {
            "category":"Building & Trades",
            "subcategory":"Construction",
            "type":"Services"
        }
    ],
    "sg:phone":"+1 303 651 6391",
    "sg:postcode":"80504",
    "sg:province":"CO",
    "sg:tags":[
        "home",
        "builder"
    ],
    "wof:name":"G L Construction",
    "wof:placetype":"venue"
},
  "geometry": {"coordinates":[-105.102541,40.127276],"type":"Point"}
}