{
  "type": "Feature",
  "properties": {
    "addr:full":"1821 Frontier Rd Greeley CO 80634",
    "addr:housenumber":"1821",
    "addr:postcode":"80634",
    "addr:street":"Frontier Rd",
    "iso:country":"US",
    "sg:address":"1821 Frontier Rd",
    "sg:city":"Greeley",
    "sg:classifiers":[
        {
            "category":"Real Estate",
            "subcategory":"Real Estate Agent",
            "type":"Services"
        }
    ],
    "sg:phone":"+1 970 330 1828",
    "sg:postcode":"80634",
    "sg:province":"CO",
    "sg:tags":[
        "development",
        "management",
        "construction"
    ],
    "wof:name":"Evams Group LLC",
    "wof:placetype":"venue"
},
  "geometry": {"coordinates":[-104.736099,40.409275],"type":"Point"}
}