{
  "type": "Feature",
  "properties": {
    "iso:country":"US",
    "sg:address":"6795 E Tennessee Ave",
    "sg:city":"Denver",
    "sg:classifiers":[
        {
            "category":"Building & Trades",
            "subcategory":"Construction",
            "type":"Services"
        }
    ],
    "sg:phone":"+1 303 759 0690",
    "sg:postcode":"80224",
    "sg:province":"CO",
    "sg:tags":[
        "remodeling",
        "si",
        "general",
        "commercial",
        "contractor"
    ],
    "wof:name":"Midas Builders Inc",
    "wof:placetype":"venue"
},
  "geometry": {"coordinates":[-104.90918000000001,39.698508],"type":"Point"}
}