{
  "type": "Feature",
  "properties": {
    "iso:country":"US",
    "sg:address":"3536 Hartsel Dr",
    "sg:city":"Colorado Springs",
    "sg:classifiers":[
        {
            "category":"Recreation",
            "type":"Entertainment"
        }
    ],
    "sg:phone":"+1 719 260 1893",
    "sg:postcode":"80920",
    "sg:province":"CO",
    "sg:tags":[
        "personal"
    ],
    "wof:name":"Colorado Aerials",
    "wof:placetype":"venue"
},
  "geometry": {"coordinates":[-104.761697,38.939039],"type":"Point"}
}