{
  "type": "Feature",
  "properties": {
    "iso:country":"US",
    "sg:address":"5700 Indiana St",
    "sg:city":"Golden",
    "sg:classifiers":[
        {
            "category":"Professional",
            "type":"Services"
        }
    ],
    "sg:phone":"+1 303 215 9200",
    "sg:postcode":"80403",
    "sg:province":"CO",
    "wof:name":"Heimbecher Family",
    "wof:placetype":"venue"
},
  "geometry": {"coordinates":[-105.165188,39.798002],"type":"Point"}
}