{
  "type": "Feature",
  "properties": {
    "addr:full":"200 West Mountain Avenue Suite A-105 Fort Collins  CO 80521",
    "addr:housenumber":"200",
    "addr:postcode":"80521",
    "addr:street":"West Mountain Avenue Suite A-105",
    "iso:country":"US",
    "sg:address":"200 West Mountain Avenue Suite A-105",
    "sg:city":"Fort Collins ",
    "sg:classifiers":[
        {
            "category":"Professional",
            "subcategory":"Research",
            "type":"Services"
        }
    ],
    "sg:phone":"+1 970 407 0005",
    "sg:postcode":"80521",
    "sg:province":"CO",
    "sg:tags":[
        "auto",
        "automotive",
        "cleantech",
        "engine",
        "supercharger",
        "turbo",
        "turbocharger"
    ],
    "sg:website":"http://www.vandynesuperturbo.com/",
    "wof:name":"VanDyne SuperTurbo",
    "wof:placetype":"venue"
},
  "geometry": {"coordinates":[-105.080693,40.587043],"type":"Point"}
}