{
  "type": "Feature",
  "properties": {
    "iso:country":"US",
    "sg:address":"807 Waxberry Ct",
    "sg:city":"Loveland",
    "sg:classifiers":[
        {
            "category":"Building & Trades",
            "subcategory":"Construction",
            "type":"Services"
        }
    ],
    "sg:phone":"+1 970 622 9875",
    "sg:postcode":"80538",
    "sg:province":"CO",
    "sg:tags":[
        "hanging",
        "contractor"
    ],
    "wof:name":"Advanced Painting Concept",
    "wof:placetype":"venue"
},
  "geometry": {"coordinates":[-105.06736100000001,40.45709],"type":"Point"}
}