{
  "type": "Feature",
  "properties": {
    "addr:full":"8269 S Balsam St Littleton CO 80128",
    "addr:housenumber":"8269",
    "addr:postcode":"80128",
    "addr:street":"S Balsam St",
    "iso:country":"US",
    "sg:address":"8269 S Balsam St",
    "sg:city":"Littleton",
    "sg:classifiers":[
        {
            "category":"Wholesale",
            "subcategory":"Non-durable Goods",
            "type":"Manufacturing & Wholesale Goods"
        }
    ],
    "sg:phone":"+1 303 948 1382",
    "sg:postcode":"80128",
    "sg:province":"CO",
    "wof:name":"MCK Gifts Inc",
    "wof:placetype":"venue"
},
  "geometry": {"coordinates":[-105.089128,39.567737],"type":"Point"}
}