{
  "type": "Feature",
  "properties": {
    "iso:country":"US",
    "sg:address":"7425 W 52nd Ave",
    "sg:city":"Arvada",
    "sg:classifiers":[
        {
            "category":"Retail",
            "subcategory":"Auto Repair",
            "type":"Services"
        }
    ],
    "sg:phone":"+1 303 424 7587",
    "sg:postcode":"80002",
    "sg:province":"CO",
    "wof:name":"Alignments Plus Total Car Care",
    "wof:placetype":"venue"
},
  "geometry": {"coordinates":[-105.07903,39.7913],"type":"Point"}
}