{
  "type": "Feature",
  "properties": {
    "iso:country":"US",
    "sg:address":"3013 S Ogden St",
    "sg:city":"Englewood",
    "sg:classifiers":[
        {
            "category":"Manufacturing",
            "subcategory":"Glass & Minerals",
            "type":"Manufacturing & Wholesale Goods"
        }
    ],
    "sg:phone":"+1 303 781 4139",
    "sg:postcode":"80113",
    "sg:province":"CO",
    "sg:tags":[
        "tile",
        "ceramic",
        "mfg"
    ],
    "wof:name":"Front Range Tile",
    "wof:placetype":"venue"
},
  "geometry": {"coordinates":[-104.975865,39.661379],"type":"Point"}
}