{
  "type": "Feature",
  "properties": {
    "addr:full":"2104 Oakcrest Cir Castle Rock CO 80104",
    "addr:housenumber":"2104",
    "addr:postcode":"80104",
    "addr:street":"Oakcrest Cir",
    "iso:country":"US",
    "sg:address":"2104 Oakcrest Cir",
    "sg:city":"Castle Rock",
    "sg:classifiers":[
        {
            "category":"Building & Trades",
            "subcategory":"Construction",
            "type":"Services"
        }
    ],
    "sg:phone":"+1 303 688 7926",
    "sg:postcode":"80104",
    "sg:province":"CO",
    "sg:tags":[
        "carpentry",
        "contractor"
    ],
    "wof:name":"Riverside Custom Carpentry",
    "wof:placetype":"venue"
},
  "geometry": {"coordinates":[-104.838857,39.357242],"type":"Point"}
}