{
  "type": "Feature",
  "properties": {
    "addr:full":"1230 W 3rd St Florence CO 81226",
    "addr:housenumber":"1230",
    "addr:postcode":"florence;81226",
    "addr:street":"W 3Rd St",
    "iso:country":"US",
    "sg:address":"1230 W 3rd St",
    "sg:city":"Florence",
    "sg:classifiers":[
        {
            "category":"Social Services",
            "subcategory":"Adult Care",
            "type":"Services"
        }
    ],
    "sg:phone":"+1 719 784 4830",
    "sg:postcode":"81226",
    "sg:province":"CO",
    "sg:tags":[
        "home",
        "residential"
    ],
    "wof:name":"Florence Care Home Inc",
    "wof:placetype":"venue"
},
  "geometry": {"coordinates":[-105.130673,38.398159],"type":"Point"}
}