{
  "type": "Feature",
  "properties": {
    "addr:full":"3016 N Hancock Ave Colorado Springs CO 80907",
    "addr:housenumber":"3016",
    "addr:postcode":"80907",
    "addr:street":"N Hancock Ave",
    "iso:country":"US",
    "sg:address":"3016 N Hancock Ave",
    "sg:city":"Colorado Springs",
    "sg:classifiers":[
        {
            "category":"Shopping",
            "subcategory":"Bicycles & Sporting Goods",
            "type":"Retail Goods"
        }
    ],
    "sg:phone":"+1 719 473 6915",
    "sg:postcode":"80907",
    "sg:province":"CO",
    "wof:name":"Ted's Bicycles Inc",
    "wof:placetype":"venue"
},
  "geometry": {"coordinates":[-104.803488,38.874029],"type":"Point"}
}