{
  "type": "Feature",
  "properties": {
    "iso:country":"US",
    "sg:address":"2548 15th St",
    "sg:city":"Denver",
    "sg:classifiers":[
        {
            "category":"Home & Garden",
            "subcategory":"Building Materials",
            "type":"Retail Goods"
        }
    ],
    "sg:phone":"+1 303 721 6373",
    "sg:postcode":"80202",
    "sg:province":"CO",
    "sg:tags":[
        "glass",
        "window",
        "plate"
    ],
    "wof:name":"Prism Glass Works 5300 Dtc",
    "wof:placetype":"venue"
},
  "geometry": {"coordinates":[-105.011315,39.757861],"type":"Point"}
}