{
  "type": "Feature",
  "properties": {
    "iso:country":"US",
    "sg:address":"801 E 22nd Ave",
    "sg:city":"Denver",
    "sg:classifiers":[
        {
            "category":"Manufacturing",
            "subcategory":"Glass & Minerals",
            "type":"Manufacturing & Wholesale Goods"
        }
    ],
    "sg:phone":"+1 303 831 9297",
    "sg:postcode":"80205",
    "sg:province":"CO",
    "sg:tags":[
        "product",
        "nonmetallic",
        "mfg"
    ],
    "wof:name":"Warren Sculpture Studios Inc",
    "wof:placetype":"venue"
},
  "geometry": {"coordinates":[-104.975759,39.74948],"type":"Point"}
}