{
  "type": "Feature",
  "properties": {
    "addr:full":"Colorado Convention Center 700 14th St Denver CO 80202",
    "addr:housenumber":"700",
    "addr:postcode":"80202",
    "addr:street":"14Th St",
    "iso:country":"US",
    "sg:address":"Colorado Convention Center 700 14th St",
    "sg:city":"Denver",
    "sg:classifiers":[
        {
            "category":"Landmark",
            "subcategory":"Historic",
            "type":"Public Place"
        }
    ],
    "sg:postcode":"80202",
    "sg:province":"CO",
    "sg:tags":[
        "building",
        "historical"
    ],
    "sg:website":"www.denvergov.org/tabid/392940/D...",
    "wof:name":"I See What You Mean by Lawrence Argent",
    "wof:placetype":"venue"
},
  "geometry": {"coordinates":[-104.99628,39.742192],"type":"Point"}
}