{
  "type": "Feature",
  "properties": {
    "addr:full":"1041 Federal Blvd Denver CO 80204",
    "addr:housenumber":"1041",
    "addr:postcode":"80204",
    "addr:street":"Federal Blvd",
    "iso:country":"US",
    "sg:address":"1041 Federal Blvd",
    "sg:city":"Denver",
    "sg:classifiers":[
        {
            "category":"Retail",
            "subcategory":"Auto Repair",
            "type":"Services"
        }
    ],
    "sg:phone":"+1 303 892 7931",
    "sg:postcode":"80204",
    "sg:province":"CO",
    "wof:name":"America Auto Service",
    "wof:placetype":"venue"
},
  "geometry": {"coordinates":[-105.025002,39.733398],"type":"Point"}
}