{
  "type": "Feature",
  "properties": {
    "iso:country":"US",
    "sg:address":"9751 Wild Crocus Cir",
    "sg:city":"Parker",
    "sg:classifiers":[
        {
            "category":"Home & Garden",
            "subcategory":"Building Materials",
            "type":"Retail Goods"
        }
    ],
    "sg:phone":"+1 303 805 8115",
    "sg:postcode":"80134",
    "sg:province":"CO",
    "wof:name":"Weatherdrain",
    "wof:placetype":"venue"
},
  "geometry": {"coordinates":[-104.703259,39.426933],"type":"Point"}
}