{
  "type": "Feature",
  "properties": {
    "addr:full":"2591 Dexter St Denver CO 80207",
    "addr:housenumber":"2591",
    "addr:postcode":"80207",
    "addr:street":"Dexter St",
    "iso:country":"US",
    "sg:address":"2591 Dexter St",
    "sg:city":"Denver",
    "sg:classifiers":[
        {
            "category":"Professional",
            "type":"Services"
        }
    ],
    "sg:phone":"+1 303 355 0646",
    "sg:postcode":"80207",
    "sg:province":"CO",
    "sg:tags":[
        "establishment"
    ],
    "wof:name":"Susan Rahe & Assoc",
    "wof:placetype":"venue"
},
  "geometry": {"coordinates":[-104.9329,39.752999],"type":"Point"}
}