{
  "type": "Feature",
  "properties": {
    "iso:country":"US",
    "sg:address":"1899 Wynkoop St",
    "sg:city":"Denver",
    "sg:classifiers":[
        {
            "category":"Building & Trades",
            "subcategory":"Construction",
            "type":"Services"
        },
        {
            "category":"Mining & Drilling",
            "type":"Manufacturing & Wholesale Goods"
        }
    ],
    "sg:phone":"+1 303 866 0011",
    "sg:postcode":"80202",
    "sg:province":"CO",
    "sg:tags":[
        "development",
        "home",
        "builder",
        "oil",
        "gas"
    ],
    "wof:name":"Sagebrush Group",
    "wof:placetype":"venue"
},
  "geometry": {"coordinates":[-104.998481,39.753782],"type":"Point"}
}