{
  "type": "Feature",
  "properties": {
    "iso:country":"US",
    "sg:address":"425 S Cherry Street",
    "sg:city":"Denver",
    "sg:classifiers":[
        {
            "category":"Professional",
            "subcategory":"Accounting & Tax Preparation",
            "type":"Services"
        }
    ],
    "sg:phone":"+1 303 322 8771",
    "sg:postcode":"80246",
    "sg:province":"CO",
    "sg:tags":[
        "accountant"
    ],
    "wof:name":"Jackson Kenneth & Associates PC CPA",
    "wof:placetype":"venue"
},
  "geometry": {"coordinates":[-104.933396,39.708653],"type":"Point"}
}