{
  "type": "Feature",
  "properties": {
    "iso:country":"US",
    "sg:address":"4800 28th St",
    "sg:city":"Boulder",
    "sg:classifiers":[
        {
            "category":"Recreation",
            "subcategory":"Amusement Park",
            "type":"Entertainment"
        }
    ],
    "sg:phone":"+1 303 442 4386",
    "sg:postcode":"80301",
    "sg:province":"CO",
    "sg:tags":[
        "park"
    ],
    "sg:website":"www.gatewayfunpark.com",
    "wof:name":"Gateway Park Fun Center",
    "wof:placetype":"venue"
},
  "geometry": {"coordinates":[-105.28004199999999,40.063983],"type":"Point"}
}