{
  "type": "Feature",
  "properties": {
    "iso:country":"US",
    "sg:address":"558 Castle Pines Pkwy",
    "sg:city":"Castle Rock",
    "sg:classifiers":[
        {
            "category":"Restaurant",
            "type":"Food & Drink"
        }
    ],
    "sg:phone":"+1 303 663 2111",
    "sg:postcode":"80108",
    "sg:province":"CO",
    "sg:tags":[
        "eating",
        "pizza"
    ],
    "wof:name":"Little Italy Pizzeria",
    "wof:placetype":"venue"
},
  "geometry": {"coordinates":[-104.884293,39.469052],"type":"Point"}
}