{
  "type": "Feature",
  "properties": {
    "iso:country":"US",
    "sg:address":"1334 E 21st St",
    "sg:city":"Pueblo",
    "sg:classifiers":[
        {
            "category":"Restaurant",
            "type":"Food & Drink"
        }
    ],
    "sg:menulink":"http://www.allmenus.com/co/pueblo/189455-kfc---kentucky-fried-chicken/menu/",
    "sg:phone":"+1 719 545 6355",
    "sg:postcode":"81001",
    "sg:province":"CO",
    "sg:tags":[
        "american",
        "chicken"
    ],
    "wof:name":"KFC - Kentucky Fried Chicken",
    "wof:placetype":"venue"
},
  "geometry": {"coordinates":[-104.587439,38.286857],"type":"Point"}
}