{
  "type": "Feature",
  "properties": {
    "iso:country":"US",
    "sg:address":"12675 Home Farm Dr",
    "sg:city":"Denver",
    "sg:classifiers":[
        {
            "category":"Building & Trades",
            "subcategory":"Landscaping Services",
            "type":"Services"
        }
    ],
    "sg:phone":"+1 303 453 4992",
    "sg:postcode":"80234",
    "sg:province":"CO",
    "wof:name":"Father & Son Building Srvcs",
    "wof:placetype":"venue"
},
  "geometry": {"coordinates":[-104.999832,39.928334],"type":"Point"}
}