{
  "type": "Feature",
  "properties": {
    "addr:full":"4425 Casa Grande Dr Greeley CO 80634",
    "addr:housenumber":"4425",
    "addr:postcode":"80634",
    "addr:street":"Casa Grande Dr",
    "iso:country":"US",
    "sg:address":"4425 Casa Grande Dr",
    "sg:city":"Greeley",
    "sg:classifiers":[
        {
            "category":"Food & Beverages",
            "subcategory":"Specialty",
            "type":"Retail Goods"
        }
    ],
    "sg:phone":"+1 970 330 0502",
    "sg:postcode":"80634",
    "sg:province":"CO",
    "wof:name":"R&J Rainbow Enterprises",
    "wof:placetype":"venue"
},
  "geometry": {"coordinates":[-104.75157,40.367003],"type":"Point"}
}