{
  "type": "Feature",
  "properties": {
    "addr:full":"7076 S Alton Way Englewood CO 80112",
    "addr:housenumber":"7076",
    "addr:postcode":"80112",
    "addr:street":"S Alton Way",
    "iso:country":"US",
    "sg:address":"7076 S Alton Way",
    "sg:city":"Englewood",
    "sg:classifiers":[
        {
            "category":"Wholesale",
            "subcategory":"Furniture",
            "type":"Manufacturing & Wholesale Goods"
        }
    ],
    "sg:phone":"+1 303 779 3636",
    "sg:postcode":"80112",
    "sg:province":"CO",
    "wof:name":"Rmmr Milne Assoc",
    "wof:placetype":"venue"
},
  "geometry": {"coordinates":[-104.882966,39.58346],"type":"Point"}
}