{
  "type": "Feature",
  "properties": {
    "iso:country":"US",
    "sg:address":"19672 E 34th Dr",
    "sg:city":"Aurora",
    "sg:classifiers":[
        {
            "category":"Manufacturing",
            "subcategory":"Metals",
            "type":"Manufacturing & Wholesale Goods"
        }
    ],
    "sg:phone":"+1 303 375 8240",
    "sg:postcode":"80011",
    "sg:province":"CO",
    "sg:tags":[
        "fabricated",
        "mfg"
    ],
    "wof:name":"Potts Welding & Boiler Repr Co",
    "wof:placetype":"venue"
},
  "geometry": {"coordinates":[-104.759095,39.761173],"type":"Point"}
}