{
  "type": "Feature",
  "properties": {
    "addr:full":"922 19th St Golden CO 80401",
    "addr:housenumber":"922",
    "addr:postcode":"80401",
    "addr:street":"19Th St",
    "iso:country":"US",
    "sg:address":"922 19th St",
    "sg:city":"Golden",
    "sg:classifiers":[
        {
            "category":"Mining & Drilling",
            "type":"Manufacturing & Wholesale Goods"
        }
    ],
    "sg:phone":"+1 303 215 0151",
    "sg:postcode":"80401",
    "sg:province":"CO",
    "sg:tags":[
        "exploration",
        "mineral"
    ],
    "wof:name":"American Copper & Nickel Co",
    "wof:placetype":"venue"
},
  "geometry": {"coordinates":[-105.21800399999999,39.748686],"type":"Point"}
}