{
  "type": "Feature",
  "properties": {
    "addr:full":"2121 S Oneida St Ste 525 Denver CO 80224",
    "addr:housenumber":"2121",
    "addr:postcode":"80224",
    "addr:street":"S Oneida St Ste 525",
    "iso:country":"US",
    "sg:address":"2121 S Oneida St Ste 525",
    "sg:city":"Denver",
    "sg:classifiers":[
        {
            "category":"Professional",
            "subcategory":"Accounting & Tax Preparation",
            "type":"Services"
        }
    ],
    "sg:phone":"+1 303 758 1796",
    "sg:postcode":"80224",
    "sg:province":"CO",
    "sg:tags":[
        "accountant"
    ],
    "wof:name":"Youmans Bruce CPA",
    "wof:placetype":"venue"
},
  "geometry": {"coordinates":[-104.90799699999999,39.677898],"type":"Point"}
}