{
  "type": "Feature",
  "properties": {
    "iso:country":"US",
    "sg:address":"407 Glenwood Ave",
    "sg:city":"Grand Junction",
    "sg:classifiers":[
        {
            "category":"Wholesale",
            "subcategory":"Non-durable Goods",
            "type":"Manufacturing & Wholesale Goods"
        }
    ],
    "sg:phone":"+1 970 241 7611",
    "sg:postcode":"81501",
    "sg:province":"CO",
    "sg:tags":[
        "advertising",
        "specialty"
    ],
    "wof:name":"Impact Promotional Products",
    "wof:placetype":"venue"
},
  "geometry": {"coordinates":[-108.564547,39.078925],"type":"Point"}
}