{
  "type": "Feature",
  "properties": {
    "addr:full":"6460 S Zephyr Ct Littleton CO 80123",
    "addr:housenumber":"6460",
    "addr:postcode":"80123",
    "addr:street":"S Zephyr Ct",
    "iso:country":"US",
    "sg:address":"6460 S Zephyr Ct",
    "sg:city":"Littleton",
    "sg:classifiers":[
        {
            "category":"Military Area",
            "subcategory":"Naval Base",
            "type":"Public Place"
        }
    ],
    "sg:phone":"+1 303 972 7964",
    "sg:postcode":"80123",
    "sg:province":"CO",
    "sg:tags":[
        "range",
        "part",
        "ovens-supplies"
    ],
    "wof:name":"Front Range Sports Officials A",
    "wof:placetype":"venue"
},
  "geometry": {"coordinates":[-105.083558,39.599111],"type":"Point"}
}