{
  "type": "Feature",
  "properties": {
    "iso:country":"US",
    "sg:address":"1755 State Hwy 66",
    "sg:city":"Estes Park",
    "sg:classifiers":[
        {
            "category":"Building & Trades",
            "subcategory":"Landscaping Services",
            "type":"Services"
        }
    ],
    "sg:phone":"+1 970 586 4461",
    "sg:postcode":"80517",
    "sg:province":"CO",
    "sg:tags":[
        "retail",
        "lawn",
        "flower",
        "garden",
        "supply"
    ],
    "wof:name":"Judys Flowers Ltd",
    "wof:placetype":"venue"
},
  "geometry": {"coordinates":[-105.554636,40.361023],"type":"Point"}
}