{
  "type": "Feature",
  "properties": {
    "addr:full":"6 Chism Trl Pueblo CO 81008",
    "addr:housenumber":"6",
    "addr:postcode":"81008",
    "addr:street":"Chism Trl",
    "iso:country":"US",
    "sg:address":"6 Chism Trl",
    "sg:city":"Pueblo",
    "sg:classifiers":[
        {
            "category":"Shopping",
            "subcategory":"Discount & Variety Stores",
            "type":"Retail Goods"
        }
    ],
    "sg:phone":"+1 719 584 4557",
    "sg:postcode":"81008",
    "sg:province":"CO",
    "wof:name":"Variety Vacuum",
    "wof:placetype":"venue"
},
  "geometry": {"coordinates":[-104.632456,38.319239],"type":"Point"}
}