{
  "type": "Feature",
  "properties": {
    "iso:country":"US",
    "sg:address":"6630 Gunpark Dr",
    "sg:city":"Boulder",
    "sg:classifiers":[
        {
            "category":"Professional",
            "subcategory":"Lawyer & Legal Services",
            "type":"Services"
        }
    ],
    "sg:phone":"+1 303 527 3462",
    "sg:postcode":"80301",
    "sg:province":"CO",
    "sg:tags":[
        "attorney"
    ],
    "wof:name":"Rachel Maizes Law Office",
    "wof:placetype":"venue"
},
  "geometry": {"coordinates":[-105.199786,40.069886],"type":"Point"}
}