{
  "type": "Feature",
  "properties": {
    "iso:country":"US",
    "sg:address":"32251 Co Rd K",
    "sg:city":"Campo",
    "sg:classifiers":[
        {
            "category":"Wholesale",
            "subcategory":"Farm Supplies",
            "type":"Manufacturing & Wholesale Goods"
        }
    ],
    "sg:phone":"+1 719 523 4320",
    "sg:postcode":"81029",
    "sg:province":"CO",
    "sg:tags":[
        "alfalfa",
        "hay"
    ],
    "wof:name":"Bullock Industries",
    "wof:placetype":"venue"
},
  "geometry": {"coordinates":[-102.505217,37.11988],"type":"Point"}
}