{
  "type": "Feature",
  "properties": {
    "addr:full":"159 Ward Ct Lakewood CO 80228",
    "addr:housenumber":"159",
    "addr:postcode":"80228",
    "addr:street":"Ward Ct",
    "iso:country":"US",
    "sg:address":"159 Ward Ct",
    "sg:city":"Lakewood",
    "sg:classifiers":[
        {
            "category":"Professional",
            "type":"Services"
        }
    ],
    "sg:phone":"+1 303 987 4695",
    "sg:postcode":"80228",
    "sg:province":"CO",
    "sg:tags":[
        "writer"
    ],
    "wof:name":"Carwile Carla/Creative Copy",
    "wof:placetype":"venue"
},
  "geometry": {"coordinates":[-105.14053199999999,39.716459],"type":"Point"}
}