{
  "type": "Feature",
  "properties": {
    "iso:country":"US",
    "sg:address":"216 16th St Ste 1300",
    "sg:city":"Denver",
    "sg:classifiers":[
        {
            "category":"Professional",
            "subcategory":"Lawyer & Legal Services",
            "type":"Services"
        }
    ],
    "sg:phone":"+1 303 825 1125",
    "sg:postcode":"80202",
    "sg:province":"CO",
    "wof:name":"Akers & Carleton Llc",
    "wof:placetype":"venue"
},
  "geometry": {"coordinates":[-104.987999,39.741901],"type":"Point"}
}