{
  "type": "Feature",
  "properties": {
    "iso:country":"US",
    "sg:address":"7968 W 90th Ave",
    "sg:city":"Broomfield",
    "sg:classifiers":[
        {
            "category":"Building & Trades",
            "subcategory":"Electrical",
            "type":"Services"
        }
    ],
    "sg:phone":"+1 303 404 0934",
    "sg:postcode":"80021",
    "sg:province":"CO",
    "sg:tags":[
        "electrical",
        "contractor"
    ],
    "wof:name":"Access Electric Co",
    "wof:placetype":"venue"
},
  "geometry": {"coordinates":[-105.08762400000001,39.859698],"type":"Point"}
}