{
  "type": "Feature",
  "properties": {
    "iso:country":"US",
    "sg:address":"1291 Eagle St",
    "sg:city":"Aurora",
    "sg:classifiers":[
        {
            "category":"Insurance",
            "subcategory":"Insurance Agent",
            "type":"Services"
        }
    ],
    "sg:phone":"+1 303 360 5878",
    "sg:postcode":"80011",
    "sg:province":"CO",
    "wof:name":"Ronald Mangean Installation",
    "wof:placetype":"venue"
},
  "geometry": {"coordinates":[-104.81618400000001,39.733468],"type":"Point"}
}