{
  "type": "Feature",
  "properties": {
    "iso:country":"US",
    "sg:address":"1313 Alexandria St",
    "sg:city":"Lafayette",
    "sg:classifiers":[
        {
            "category":"Professional",
            "subcategory":"Management & Consulting",
            "type":"Services"
        }
    ],
    "sg:phone":"+1 303 665 9688",
    "sg:postcode":"80026",
    "sg:province":"CO",
    "wof:name":"Grosvenor House Conslt",
    "wof:placetype":"venue"
},
  "geometry": {"coordinates":[-105.087459,40.013726],"type":"Point"}
}