{
  "type": "Feature",
  "properties": {
    "iso:country":"US",
    "sg:address":"4075 Chippewa Dr",
    "sg:city":"Boulder",
    "sg:classifiers":[
        {
            "category":"Professional",
            "subcategory":"Computer Services",
            "type":"Services"
        }
    ],
    "sg:phone":"+1 303 494 7115",
    "sg:postcode":"80303",
    "sg:province":"CO",
    "sg:tags":[
        "design",
        "software"
    ],
    "wof:name":"Mathcom Inc",
    "wof:placetype":"venue"
},
  "geometry": {"coordinates":[-105.243661,39.99709],"type":"Point"}
}