{
  "type": "Feature",
  "properties": {
    "iso:country":"US",
    "sg:address":"3816 US Hwy 50",
    "sg:city":"Fowler",
    "sg:classifiers":[
        {
            "category":"Professional",
            "type":"Services"
        }
    ],
    "sg:phone":"+1 719 263 5381",
    "sg:postcode":"81039",
    "sg:province":"CO",
    "wof:name":"James C Mason",
    "wof:placetype":"venue"
},
  "geometry": {"coordinates":[-104.00766,38.129535],"type":"Point"}
}