{
  "type": "Feature",
  "properties": {
    "addr:full":"404 S Oak St La Veta CO 81055",
    "addr:housenumber":"404",
    "addr:postcode":"veta;81055",
    "addr:street":"S Oak St",
    "iso:country":"US",
    "sg:address":"404 S Oak St",
    "sg:city":"La Veta",
    "sg:classifiers":[
        {
            "category":"Wholesale",
            "subcategory":"Durable Goods & Equipment",
            "type":"Manufacturing & Wholesale Goods"
        }
    ],
    "sg:phone":"+1 719 742 5303",
    "sg:postcode":"81055",
    "sg:province":"CO",
    "sg:tags":[
        "instrument",
        "musical"
    ],
    "wof:name":"Cuchara River Cabins",
    "wof:placetype":"venue"
},
  "geometry": {"coordinates":[-105.011304,37.503607],"type":"Point"}
}