{
  "type": "Feature",
  "properties": {
    "iso:country":"US",
    "sg:address":"11496 S Regency Pl",
    "sg:city":"Parker",
    "sg:classifiers":[
        {
            "category":"Shopping",
            "subcategory":"Bicycles & Sporting Goods",
            "type":"Retail Goods"
        }
    ],
    "sg:phone":"+1 303 421 8050",
    "sg:postcode":"80138",
    "sg:province":"CO",
    "wof:name":"Denver Trampoline Inc",
    "wof:placetype":"venue"
},
  "geometry": {"coordinates":[-104.750388,39.509163],"type":"Point"}
}