{
  "type": "Feature",
  "properties": {
    "iso:country":"US",
    "sg:address":"4501 W Kentucky Ave",
    "sg:city":"Denver",
    "sg:classifiers":[
        {
            "category":"Building & Trades",
            "subcategory":"Construction",
            "type":"Services"
        }
    ],
    "sg:phone":"+1 303 202 2165",
    "sg:postcode":"80219",
    "sg:province":"CO",
    "sg:tags":[
        "hanging",
        "contractor"
    ],
    "wof:name":"Juan Rico Painting",
    "wof:placetype":"venue"
},
  "geometry": {"coordinates":[-105.046959,39.70041],"type":"Point"}
}