{
  "type": "Feature",
  "properties": {
    "addr:full":"6320 Lange Dr Colorado Springs CO 80918",
    "addr:housenumber":"6320",
    "addr:postcode":"80918",
    "addr:street":"Lange Dr",
    "iso:country":"US",
    "sg:address":"6320 Lange Dr",
    "sg:city":"Colorado Springs",
    "sg:classifiers":[
        {
            "category":"Education",
            "subcategory":"Special Training",
            "type":"Public Place"
        }
    ],
    "sg:phone":"+1 719 590 9564",
    "sg:postcode":"80918",
    "sg:province":"CO",
    "sg:tags":[
        "educational"
    ],
    "wof:name":"Colorado Safety Institute",
    "wof:placetype":"venue"
},
  "geometry": {"coordinates":[-104.769234,38.923328],"type":"Point"}
}