{
  "type": "Feature",
  "properties": {
    "addr:full":"1000 S Lowell Blvd Denver CO 80219",
    "addr:housenumber":"1000",
    "addr:postcode":"80219",
    "addr:street":"S Lowell Blvd",
    "iso:country":"US",
    "sg:address":"1000 S Lowell Blvd",
    "sg:city":"Denver",
    "sg:classifiers":[
        {
            "category":"Government",
            "subcategory":"Office",
            "type":"Public Place"
        }
    ],
    "sg:phone":"+1 303 936 8808",
    "sg:postcode":"80219",
    "sg:province":"CO",
    "sg:tags":[
        "clinic",
        "health"
    ],
    "wof:name":"Health Dept",
    "wof:placetype":"venue"
},
  "geometry": {"coordinates":[-105.034363,39.69782],"type":"Point"}
}