{
  "type": "Feature",
  "properties": {
    "addr:full":"1111 W Exposition Avenue Denver CO 80223",
    "addr:housenumber":"1111",
    "addr:postcode":"80223",
    "addr:street":"W Exposition Avenue",
    "iso:country":"US",
    "sg:address":"1111 W Exposition Avenue",
    "sg:city":"Denver",
    "sg:classifiers":[
        {
            "category":"Professional",
            "type":"Services"
        }
    ],
    "sg:phone":"+1 303 592 9100",
    "sg:postcode":"80223",
    "sg:province":"CO",
    "sg:tags":[
        "caterer"
    ],
    "wof:name":"Culinaire",
    "wof:placetype":"venue"
},
  "geometry": {"coordinates":[-105.001768,39.703861],"type":"Point"}
}