{
  "type": "Feature",
  "properties": {
    "iso:country":"US",
    "sg:address":"27436 Co Rd 313",
    "sg:city":"Buena Vista",
    "sg:classifiers":[
        {
            "category":"Freight",
            "type":"Transportation"
        }
    ],
    "sg:phone":"+1 719 395 2244",
    "sg:postcode":"81211",
    "sg:province":"CO",
    "sg:tags":[
        "hauling",
        "trucking"
    ],
    "wof:name":"Eveready Freight Svc",
    "wof:placetype":"venue"
},
  "geometry": {"coordinates":[-106.108993,38.816838],"type":"Point"}
}