{
  "type": "Feature",
  "properties": {
    "iso:country":"US",
    "sg:address":"1015 W Colorado Ave",
    "sg:city":"Colorado Springs",
    "sg:classifiers":[
        {
            "category":"Restaurant",
            "type":"Food & Drink"
        }
    ],
    "sg:menulink":"http://www.allmenus.com/co/colorado-springs/4210-la-petite-maison/menu/",
    "sg:phone":"+1 719 632 4887",
    "sg:postcode":"80904",
    "sg:province":"CO",
    "sg:tags":[
        "french"
    ],
    "wof:name":"La Petite Maison",
    "wof:placetype":"venue"
},
  "geometry": {"coordinates":[-104.841838,38.8351],"type":"Point"}
}