{
  "type": "Feature",
  "properties": {
    "iso:country":"US",
    "sg:address":"1360 S Wadsworth Boulevard",
    "sg:city":"Lakewood",
    "sg:classifiers":[
        {
            "category":"Health Services",
            "subcategory":"Chiropractor",
            "type":"Services"
        }
    ],
    "sg:phone":"+1 303 988 5220",
    "sg:postcode":"80232",
    "sg:province":"CO",
    "wof:name":"Barbara Gauthier DC",
    "wof:placetype":"venue"
},
  "geometry": {"coordinates":[-105.081574,39.692201],"type":"Point"}
}