{
  "type": "Feature",
  "properties": {
    "addr:full":"7420 Newport St Commerce City CO 80022",
    "addr:housenumber":"7420",
    "addr:postcode":"80022",
    "addr:street":"Newport St",
    "iso:country":"US",
    "sg:address":"7420 Newport St",
    "sg:city":"Commerce City",
    "sg:classifiers":[
        {
            "category":"Social Services",
            "subcategory":"Child Care",
            "type":"Services"
        }
    ],
    "sg:phone":"+1 303 288 9507",
    "sg:postcode":"80022",
    "sg:province":"CO",
    "wof:name":"Little Giants Day Care",
    "wof:placetype":"venue"
},
  "geometry": {"coordinates":[-104.909187,39.832106],"type":"Point"}
}