{
  "type": "Feature",
  "properties": {
    "iso:country":"US",
    "sg:address":"1320 27th St",
    "sg:city":"Denver",
    "sg:classifiers":[
        {
            "category":"Professional",
            "subcategory":"Art Services",
            "type":"Services"
        }
    ],
    "sg:phone":"+1 303 525 1717",
    "sg:postcode":"80205",
    "sg:province":"CO",
    "sg:tags":[
        "photographer"
    ],
    "sg:website":"www.contemporaryexpressions.net/",
    "wof:name":"Contemporary Expressions",
    "wof:placetype":"venue"
},
  "geometry": {"coordinates":[-104.9845,39.759603],"type":"Point"}
}