{
  "type": "Feature",
  "properties": {
    "iso:country":"US",
    "sg:address":"400 Lashley St",
    "sg:city":"Longmont",
    "sg:classifiers":[
        {
            "category":"Social Services",
            "subcategory":"Job Training",
            "type":"Services"
        }
    ],
    "sg:phone":"+1 303 684 9173",
    "sg:postcode":"80501",
    "sg:province":"CO",
    "sg:tags":[
        "rehabilitation"
    ],
    "wof:name":"New Beginnings",
    "wof:placetype":"venue"
},
  "geometry": {"coordinates":[-105.088177,40.166239],"type":"Point"}
}