{
  "type": "Feature",
  "properties": {
    "addr:full":"201 E Platte Ave Fort Morgan CO 80701",
    "addr:housenumber":"201",
    "addr:postcode":"80701",
    "addr:street":"E Platte Ave",
    "iso:country":"US",
    "sg:address":"201 E Platte Ave",
    "sg:city":"Fort Morgan",
    "sg:classifiers":[
        {
            "category":"Autos & Motor Vehicles",
            "subcategory":"Auto Supplies",
            "type":"Retail Goods"
        }
    ],
    "sg:phone":"+1 970 542 0570",
    "sg:postcode":"80701",
    "sg:province":"CO",
    "wof:name":"Autozone 822",
    "wof:placetype":"venue"
},
  "geometry": {"coordinates":[-103.80021000000001,40.253979],"type":"Point"}
}