{
  "type": "Feature",
  "properties": {
    "addr:full":"249 S 4th St Grand Junction CO 81501",
    "addr:housenumber":"249",
    "addr:postcode":"81501",
    "addr:street":"S 4Th St",
    "iso:country":"US",
    "sg:address":"249 S 4th St",
    "sg:city":"Grand Junction",
    "sg:classifiers":[
        {
            "category":"Organizations",
            "subcategory":"Community Association",
            "type":"Services"
        }
    ],
    "sg:phone":"+1 970 243 0675",
    "sg:postcode":"81501",
    "sg:province":"CO",
    "sg:tags":[
        "fraternal"
    ],
    "wof:name":"Elks Lodge",
    "wof:placetype":"venue"
},
  "geometry": {"coordinates":[-108.566222,39.065834],"type":"Point"}
}