{
  "type": "Feature",
  "properties": {
    "iso:country":"US",
    "sg:address":"1678 Topaz Dr",
    "sg:city":"Loveland",
    "sg:classifiers":[
        {
            "category":"Real Estate",
            "subcategory":"Real Estate Agent",
            "type":"Services"
        }
    ],
    "sg:phone":"+1 970 613 4400",
    "sg:postcode":"80537",
    "sg:province":"CO",
    "sg:tags":[
        "manager"
    ],
    "wof:name":"Premier Lifestyle Realty",
    "wof:placetype":"venue"
},
  "geometry": {"coordinates":[-105.05122799999999,40.406593],"type":"Point"}
}