{
  "type": "Feature",
  "properties": {
    "addr:full":"7475 Co Rd 146 Salida CO 81201",
    "addr:housenumber":"7475",
    "addr:postcode":"81201",
    "addr:street":"Co Rd 146",
    "iso:country":"US",
    "sg:address":"7475 Co Rd 146",
    "sg:city":"Salida",
    "sg:classifiers":[
        {
            "category":"Farming",
            "subcategory":"Dairy Farm",
            "type":"Manufacturing & Wholesale Goods"
        }
    ],
    "sg:phone":"+1 719 539 2007",
    "sg:postcode":"81201",
    "sg:province":"CO",
    "wof:name":"Thomas Dairy",
    "wof:placetype":"venue"
},
  "geometry": {"coordinates":[-106.04285,38.533501],"type":"Point"}
}