{
  "type": "Feature",
  "properties": {
    "addr:full":"21883 Scenic Dr Morrison CO 80465",
    "addr:housenumber":"21883",
    "addr:postcode":"80465",
    "addr:street":"Scenic Dr",
    "iso:country":"US",
    "sg:address":"21883 Scenic Dr",
    "sg:city":"Morrison",
    "sg:classifiers":[
        {
            "category":"Professional",
            "subcategory":"Research",
            "type":"Services"
        }
    ],
    "sg:phone":"+1 303 697 4996",
    "sg:postcode":"80465",
    "sg:province":"CO",
    "sg:tags":[
        "development",
        "electronic"
    ],
    "wof:name":"Analog Systems",
    "wof:placetype":"venue"
},
  "geometry": {"coordinates":[-105.248999,39.564851],"type":"Point"}
}