{
  "type": "Feature",
  "properties": {
    "iso:country":"US",
    "sg:address":"3660 W Saratoga Ave",
    "sg:city":"Denver",
    "sg:classifiers":[
        {
            "category":"Building & Trades",
            "subcategory":"Landscaping Services",
            "type":"Services"
        }
    ],
    "sg:phone":"+1 303 777 7768",
    "sg:postcode":"80123",
    "sg:province":"CO",
    "sg:tags":[
        "landscape",
        "contractor"
    ],
    "wof:name":"A Better Landscape & Sprinkler",
    "wof:placetype":"venue"
},
  "geometry": {"coordinates":[-105.035464,39.628511],"type":"Point"}
}