{
  "type": "Feature",
  "properties": {
    "iso:country":"US",
    "sg:address":"903 Cottonwood Dr",
    "sg:city":"Loveland",
    "sg:classifiers":[
        {
            "category":"Home & Garden",
            "subcategory":"Garden Supply",
            "type":"Retail Goods"
        }
    ],
    "sg:phone":"+1 970 663 3237",
    "sg:postcode":"80538",
    "sg:province":"CO",
    "sg:tags":[
        "center"
    ],
    "wof:name":"Garden Treasures",
    "wof:placetype":"venue"
},
  "geometry": {"coordinates":[-105.087385,40.434129],"type":"Point"}
}