{
  "type": "Feature",
  "properties": {
    "iso:country":"US",
    "sg:address":"3478 16th Cir",
    "sg:city":"Boulder",
    "sg:classifiers":[
        {
            "category":"Professional",
            "type":"Services"
        }
    ],
    "sg:phone":"+1 303 546 6639",
    "sg:postcode":"80304",
    "sg:province":"CO",
    "wof:name":"Norman L Koren",
    "wof:placetype":"venue"
},
  "geometry": {"coordinates":[-105.277157,40.03768],"type":"Point"}
}