{
  "type": "Feature",
  "properties": {
    "addr:full":"1500 W 4th St Pueblo CO 81003",
    "addr:housenumber":"1500",
    "addr:postcode":"81003",
    "addr:street":"W 4Th St",
    "iso:country":"US",
    "sg:address":"1500 W 4th St",
    "sg:city":"Pueblo",
    "sg:classifiers":[
        {
            "category":"Professional",
            "type":"Services"
        }
    ],
    "sg:phone":"+1 719 545 4487",
    "sg:postcode":"81003",
    "sg:province":"CO",
    "sg:tags":[
        "establishment"
    ],
    "wof:name":"Grakek & Pisciotta",
    "wof:placetype":"venue"
},
  "geometry": {"coordinates":[-104.62802499999999,38.266037],"type":"Point"}
}