{
  "type": "Feature",
  "properties": {
    "addr:full":"930 Main St Longmont CO 80501",
    "addr:housenumber":"930",
    "addr:postcode":"80501",
    "addr:street":"Main St",
    "iso:country":"US",
    "sg:address":"930 Main St",
    "sg:city":"Longmont",
    "sg:classifiers":[
        {
            "category":"Retail",
            "subcategory":"Auto Repair",
            "type":"Services"
        }
    ],
    "sg:phone":"+1 303 651 0443",
    "sg:postcode":"80501",
    "sg:province":"CO",
    "sg:tags":[
        "automotive"
    ],
    "wof:name":"AAMCO Transmissions",
    "wof:placetype":"venue"
},
  "geometry": {"coordinates":[-105.102383,40.175254],"type":"Point"}
}