{
  "type": "Feature",
  "properties": {
    "iso:country":"US",
    "sg:address":"2030 Terry St",
    "sg:city":"Longmont",
    "sg:classifiers":[
        {
            "category":"Professional",
            "subcategory":"Accounting & Tax Preparation",
            "type":"Services"
        }
    ],
    "sg:phone":"+1 303 776 5908",
    "sg:postcode":"80501",
    "sg:province":"CO",
    "sg:tags":[
        "accountant"
    ],
    "wof:name":"O'Donnell & Plaster",
    "wof:placetype":"venue"
},
  "geometry": {"coordinates":[-105.10466700000001,40.195121],"type":"Point"}
}