{
  "type": "Feature",
  "properties": {
    "iso:country":"US",
    "sg:address":"6601 S Vine St",
    "sg:city":"Littleton",
    "sg:classifiers":[
        {
            "category":"Professional",
            "type":"Services"
        }
    ],
    "sg:phone":"+1 303 347 8755",
    "sg:postcode":"80121",
    "sg:province":"CO",
    "wof:name":"Richard R Riss",
    "wof:placetype":"venue"
},
  "geometry": {"coordinates":[-104.963204,39.597064],"type":"Point"}
}