{
  "type": "Feature",
  "properties": {
    "iso:country":"US",
    "sg:address":"5840 Chokecherry Dr",
    "sg:city":"Colorado Springs",
    "sg:classifiers":[
        {
            "category":"Shopping",
            "subcategory":"Clothing, Apparel, & Fashions",
            "type":"Retail Goods"
        }
    ],
    "sg:phone":"+1 719 268 0235",
    "sg:postcode":"80919",
    "sg:province":"CO",
    "wof:name":"I Do Bridal",
    "wof:placetype":"venue"
},
  "geometry": {"coordinates":[-104.861862,38.916505],"type":"Point"}
}