{
  "type": "Feature",
  "properties": {
    "addr:full":"4436 S Himalaya Ct Aurora CO 80015",
    "addr:housenumber":"4436",
    "addr:postcode":"80015",
    "addr:street":"S Himalaya Ct",
    "iso:country":"US",
    "sg:address":"4436 S Himalaya Ct",
    "sg:city":"Aurora",
    "sg:classifiers":[
        {
            "category":"Restaurant",
            "type":"Food & Drink"
        }
    ],
    "sg:phone":"+1 303 680 0133",
    "sg:postcode":"80015",
    "sg:province":"CO",
    "sg:tags":[
        "house",
        "steak"
    ],
    "wof:name":"Signatures",
    "wof:placetype":"venue"
},
  "geometry": {"coordinates":[-104.75279399999999,39.636207],"type":"Point"}
}