{
  "type": "Feature",
  "properties": {
    "iso:country":"US",
    "sg:address":"5606 S Court Pl",
    "sg:city":"Littleton",
    "sg:classifiers":[
        {
            "category":"Building & Trades",
            "subcategory":"Construction",
            "type":"Services"
        }
    ],
    "sg:phone":"+1 303 730 1448",
    "sg:postcode":"80120",
    "sg:province":"CO",
    "sg:tags":[
        "house"
    ],
    "wof:name":"Adolfson Pterson Constructiion",
    "wof:placetype":"venue"
},
  "geometry": {"coordinates":[-105.013144,39.61335],"type":"Point"}
}