{
  "type": "Feature",
  "properties": {
    "addr:full":"10841 Fox Sedge Way Littleton CO 80126",
    "addr:housenumber":"10841",
    "addr:postcode":"80126",
    "addr:street":"Fox Sedge Way",
    "iso:country":"US",
    "sg:address":"10841 Fox Sedge Way",
    "sg:city":"Littleton",
    "sg:classifiers":[
        {
            "category":"Professional",
            "type":"Services"
        }
    ],
    "sg:phone":"+1 303 688 9031",
    "sg:postcode":"80126",
    "sg:province":"CO",
    "wof:name":"Project Professional LP",
    "wof:placetype":"venue"
},
  "geometry": {"coordinates":[-104.95146099999999,39.519047],"type":"Point"}
}