{
  "type": "Feature",
  "properties": {
    "iso:country":"US",
    "sg:address":"204 S 7th St",
    "sg:city":"Canon City",
    "sg:classifiers":[
        {
            "category":"Social Services",
            "type":"Services"
        }
    ],
    "sg:phone":"+1 719 275 2429",
    "sg:postcode":"81212",
    "sg:province":"CO",
    "sg:tags":[
        "information",
        "abuse",
        "domestic",
        "treatment"
    ],
    "wof:name":"Domestic Violence Svc",
    "wof:placetype":"venue"
},
  "geometry": {"coordinates":[-105.23715300000001,38.440622],"type":"Point"}
}