{
  "type": "Feature",
  "properties": {
    "addr:full":"2900 S Havana St Aurora CO 80014",
    "addr:housenumber":"2900",
    "addr:postcode":"80014",
    "addr:street":"S Havana St",
    "iso:country":"US",
    "sg:address":"2900 S Havana St",
    "sg:city":"Aurora",
    "sg:classifiers":[
        {
            "category":"Manufacturing",
            "subcategory":"Glass & Minerals",
            "type":"Manufacturing & Wholesale Goods"
        }
    ],
    "sg:phone":"+1 303 755 1584",
    "sg:postcode":"80014",
    "sg:province":"CO",
    "sg:tags":[
        "ready",
        "concrete",
        "mfg"
    ],
    "wof:name":"Flanagan Ready Mix",
    "wof:placetype":"venue"
},
  "geometry": {"coordinates":[-104.866113,39.665622],"type":"Point"}
}