{
  "type": "Feature",
  "properties": {
    "iso:country":"US",
    "sg:address":"2287 Co Rd 143",
    "sg:city":"Canon City",
    "sg:classifiers":[
        {
            "category":"Communications",
            "subcategory":"Film & Video Production",
            "type":"Services"
        }
    ],
    "sg:phone":"+1 719 269 3929",
    "sg:postcode":"81212",
    "sg:province":"CO",
    "sg:tags":[
        "taping"
    ],
    "sg:website":"www.donbendell.com",
    "wof:name":"Bendell Intermedia Group Inc",
    "wof:placetype":"venue"
},
  "geometry": {"coordinates":[-105.239768,38.399027],"type":"Point"}
}