{
  "type": "Feature",
  "properties": {
    "addr:full":"1832 Woodmoor Dr Monument CO 80132",
    "addr:housenumber":"1832",
    "addr:postcode":"80132",
    "addr:street":"Woodmoor Dr",
    "iso:country":"US",
    "sg:address":"1832 Woodmoor Dr",
    "sg:city":"Monument",
    "sg:classifiers":[
        {
            "category":"Social Services",
            "subcategory":"Child Care",
            "type":"Services"
        }
    ],
    "sg:phone":"+1 719 481 8728",
    "sg:postcode":"80132",
    "sg:province":"CO",
    "sg:tags":[
        "day"
    ],
    "wof:name":"Youth Sports Program",
    "wof:placetype":"venue"
},
  "geometry": {"coordinates":[-104.859632,39.102399],"type":"Point"}
}