{
  "type": "Feature",
  "properties": {
    "iso:country":"US",
    "sg:address":"455 Prospect Village Dr",
    "sg:city":"Estes Park",
    "sg:classifiers":[
        {
            "category":"Recreation",
            "subcategory":"Amusement Park",
            "type":"Entertainment"
        }
    ],
    "sg:phone":"+1 970 586 2828",
    "sg:postcode":"80517",
    "sg:province":"CO",
    "wof:name":"Fun City",
    "wof:placetype":"venue"
},
  "geometry": {"coordinates":[-105.524492,40.3712],"type":"Point"}
}