{
  "type": "Feature",
  "properties": {
    "iso:country":"US",
    "sg:address":"4550 S Kipling St",
    "sg:city":"Denver",
    "sg:classifiers":[
        {
            "category":"Retail",
            "subcategory":"Animal Services",
            "type":"Services"
        }
    ],
    "sg:phone":"+1 303 979 4642",
    "sg:postcode":"80127",
    "sg:province":"CO",
    "sg:tags":[
        "pet",
        "grooming",
        "washing"
    ],
    "wof:name":"Doggy Dog World",
    "wof:placetype":"venue"
},
  "geometry": {"coordinates":[-105.109819,39.63288],"type":"Point"}
}