{
  "type": "Feature",
  "properties": {
    "iso:country":"US",
    "sg:address":"735 Wedgewood St",
    "sg:city":"Cortez",
    "sg:classifiers":[
        {
            "category":"Building & Trades",
            "subcategory":"Construction",
            "type":"Services"
        },
        {
            "category":"Home & Garden",
            "subcategory":"Home Furnishings",
            "type":"Retail Goods"
        }
    ],
    "sg:phone":"+1 970 564 1519",
    "sg:postcode":"81321",
    "sg:province":"CO",
    "sg:tags":[
        "dry wall",
        "contractor"
    ],
    "wof:name":"Custom Cuts Drywall & Insul",
    "wof:placetype":"venue"
},
  "geometry": {"coordinates":[-108.583178,37.356715],"type":"Point"}
}