{
  "type": "Feature",
  "properties": {
    "addr:full":"309 N Santa Fe Ave Fountain CO 80817",
    "addr:housenumber":"309",
    "addr:postcode":"80817",
    "addr:street":"N Santa Fe Ave",
    "iso:country":"US",
    "sg:address":"309 N Santa Fe Ave",
    "sg:city":"Fountain",
    "sg:classifiers":[
        {
            "category":"Retail",
            "subcategory":"Auto Rental",
            "type":"Services"
        }
    ],
    "sg:phone":"+1 719 322 9476",
    "sg:postcode":"80817",
    "sg:province":"CO",
    "sg:tags":[
        "renting",
        "truck",
        "leasing"
    ],
    "wof:name":"U-Haul Co",
    "wof:placetype":"venue"
},
  "geometry": {"coordinates":[-104.70437699999999,38.685489],"type":"Point"}
}