{
  "type": "Feature",
  "properties": {
    "iso:country":"US",
    "sg:address":"870 S Lipan St",
    "sg:city":"Denver",
    "sg:classifiers":[
        {
            "category":"Building & Trades",
            "subcategory":"Construction",
            "type":"Services"
        }
    ],
    "sg:phone":"+1 303 937 8314",
    "sg:postcode":"80223",
    "sg:province":"CO",
    "sg:tags":[
        "tile",
        "dealer",
        "flooring",
        "contractor"
    ],
    "wof:name":"Artistic Marble and Tile Inc",
    "wof:placetype":"venue"
},
  "geometry": {"coordinates":[-105.00144899999999,39.70028],"type":"Point"}
}