{
  "type": "Feature",
  "properties": {
    "addr:full":"26072 Highway 160 Durango CO 81303",
    "addr:housenumber":"26072",
    "addr:postcode":"co 81303",
    "addr:street":"Highway 160",
    "iso:country":"US",
    "sg:address":"26072 Highway 160",
    "sg:city":"Durango",
    "sg:classifiers":[
        {
            "category":"Restaurant",
            "type":"Food & Drink"
        }
    ],
    "sg:phone":"+1 970 382 0267",
    "sg:postcode":"81303",
    "sg:province":"CO",
    "sg:tags":[
        "mexican"
    ],
    "sg:website":"http://www.aztecamex.com",
    "wof:name":"Azteca",
    "wof:placetype":"venue"
},
  "geometry": {"coordinates":[-107.85766700000001,37.22431],"type":"Point"}
}