{
  "type": "Feature",
  "properties": {
    "iso:country":"US",
    "sg:address":"2385 Heartwood Ct",
    "sg:city":"Lafayette",
    "sg:classifiers":[
        {
            "category":"Wholesale",
            "subcategory":"Durable Goods & Equipment",
            "type":"Manufacturing & Wholesale Goods"
        }
    ],
    "sg:phone":"+1 303 604 9885",
    "sg:postcode":"80026",
    "sg:province":"CO",
    "wof:name":"Glitter Queen",
    "wof:placetype":"venue"
},
  "geometry": {"coordinates":[-105.09314500000001,39.973765],"type":"Point"}
}