{
  "type": "Feature",
  "properties": {
    "addr:full":"34705 Co Rd 24 Mc Clave CO 81057",
    "addr:housenumber":"34705;24",
    "addr:postcode":"81057",
    "addr:street":"Co Rd;Mc Clave",
    "iso:country":"US",
    "sg:address":"34705 Co Rd 24",
    "sg:city":"Mc Clave",
    "sg:classifiers":[
        {
            "category":"Farming",
            "subcategory":"Farm & Veterinary Services",
            "type":"Manufacturing & Wholesale Goods"
        }
    ],
    "sg:phone":"+1 719 829 4569",
    "sg:postcode":"81057",
    "sg:province":"CO",
    "sg:tags":[
        "aerial",
        "applicator"
    ],
    "wof:name":"Gill Lynden E Denton Aerial",
    "wof:placetype":"venue"
},
  "geometry": {"coordinates":[-102.95867800000001,38.131576],"type":"Point"}
}