{
  "type": "Feature",
  "properties": {
    "iso:country":"US",
    "sg:address":"1660 Lincoln St",
    "sg:city":"Denver",
    "sg:classifiers":[
        {
            "category":"Restaurant",
            "type":"Food & Drink"
        }
    ],
    "sg:menulink":"http://www.allmenus.com/co/denver/124174-quiznos-sub/menu/",
    "sg:phone":"+1 303 831 8282",
    "sg:postcode":"80264",
    "sg:province":"CO",
    "sg:tags":[
        "wrap",
        "american",
        "sandwich"
    ],
    "wof:name":"Quiznos Sub",
    "wof:placetype":"venue"
},
  "geometry": {"coordinates":[-104.98610600000001,39.74295],"type":"Point"}
}