{
  "type": "Feature",
  "properties": {
    "addr:full":"3472 W 125th Dr Broomfield CO 80020",
    "addr:housenumber":"3472",
    "addr:postcode":"80020",
    "addr:street":"W 125Th Dr",
    "iso:country":"US",
    "sg:address":"3472 W 125th Dr",
    "sg:city":"Broomfield",
    "sg:classifiers":[
        {
            "category":"Shopping",
            "subcategory":"Clothing, Apparel, & Fashions",
            "type":"Retail Goods"
        }
    ],
    "sg:phone":"+1 303 673 0474",
    "sg:postcode":"80020",
    "sg:province":"CO",
    "sg:tags":[
        "alteration"
    ],
    "wof:name":"Alterations By Sue Mc Kinney",
    "wof:placetype":"venue"
},
  "geometry": {"coordinates":[-105.03165199999999,39.922832],"type":"Point"}
}