{
  "type": "Feature",
  "properties": {
    "addr:full":"3371 Peoria St Aurora CO 80010",
    "addr:housenumber":"3371",
    "addr:postcode":"80010",
    "addr:street":"Peoria St",
    "iso:country":"US",
    "sg:address":"3371 Peoria St",
    "sg:city":"Aurora",
    "sg:classifiers":[
        {
            "category":"Restaurant",
            "type":"Food & Drink"
        }
    ],
    "sg:phone":"+1 303 367 9884",
    "sg:postcode":"80010",
    "sg:province":"CO",
    "sg:tags":[
        "style",
        "family"
    ],
    "wof:name":"Duy Restaurant Ii",
    "wof:placetype":"venue"
},
  "geometry": {"coordinates":[-104.846971,39.764353],"type":"Point"}
}