{
  "type": "Feature",
  "properties": {
    "addr:full":"1296 Co Rd 46 Gunnison CO 81239",
    "addr:housenumber":"1296;46",
    "addr:postcode":"81239",
    "addr:street":"Co Rd",
    "iso:country":"US",
    "sg:address":"1296 Co Rd 46",
    "sg:city":"Gunnison",
    "sg:classifiers":[
        {
            "category":"Wholesale",
            "subcategory":"Construction Materials",
            "type":"Manufacturing & Wholesale Goods"
        }
    ],
    "sg:phone":"+1 970 642 6400",
    "sg:postcode":"81239",
    "sg:province":"CO",
    "wof:name":"Nisbet Co LLC",
    "wof:placetype":"venue"
},
  "geometry": {"coordinates":[-106.60369799999999,38.435552],"type":"Point"}
}