{
  "type": "Feature",
  "properties": {
    "iso:country":"US",
    "sg:address":"1128 W Cucharras St",
    "sg:city":"Colorado Springs",
    "sg:classifiers":[
        {
            "category":"Retail",
            "subcategory":"Animal Services",
            "type":"Services"
        }
    ],
    "sg:phone":"+1 719 632 5446",
    "sg:postcode":"80904",
    "sg:province":"CO",
    "sg:tags":[
        "pet",
        "grooming",
        "supply"
    ],
    "wof:name":"Canine Corner",
    "wof:placetype":"venue"
},
  "geometry": {"coordinates":[-104.844707,38.835404],"type":"Point"}
}