{
  "type": "Feature",
  "properties": {
    "addr:full":"8355 E Lightening View Dr Parker CO 80134",
    "addr:housenumber":"8355",
    "addr:postcode":"80134",
    "addr:street":"E Lightening View Dr",
    "iso:country":"US",
    "sg:address":"8355 E Lightening View Dr",
    "sg:city":"Parker",
    "sg:classifiers":[
        {
            "category":"Professional",
            "type":"Services"
        }
    ],
    "sg:phone":"+1 303 778 8145",
    "sg:postcode":"80134",
    "sg:province":"CO",
    "wof:name":"Starfeather Designs",
    "wof:placetype":"venue"
},
  "geometry": {"coordinates":[-104.731219,39.450227],"type":"Point"}
}