{
  "type": "Feature",
  "properties": {
    "addr:full":"11636 US Hwy 40 Empire CO 80438",
    "addr:housenumber":"11636",
    "addr:postcode":"80438",
    "addr:street":"Us Hwy 40",
    "iso:country":"US",
    "sg:address":"11636 US Hwy 40",
    "sg:city":"Empire",
    "sg:classifiers":[
        {
            "category":"Restaurant",
            "type":"Food & Drink"
        }
    ],
    "sg:phone":"+1 303 569 2997",
    "sg:postcode":"80438",
    "sg:province":"CO",
    "wof:name":"Marietta",
    "wof:placetype":"venue"
},
  "geometry": {"coordinates":[-105.755182,39.769178],"type":"Point"}
}