{
  "type": "Feature",
  "properties": {
    "iso:country":"US",
    "sg:address":"5883 W 38th Ave",
    "sg:city":"Wheat Ridge",
    "sg:classifiers":[
        {
            "category":"Retail",
            "subcategory":"Repair Shop",
            "type":"Services"
        }
    ],
    "sg:phone":"+1 303 424 5141",
    "sg:postcode":"80212",
    "sg:province":"CO",
    "sg:tags":[
        "reupholstery",
        "furniture"
    ],
    "sg:website":"www.randkupholstery.com",
    "wof:name":"R & K Upholstery",
    "wof:placetype":"venue"
},
  "geometry": {"coordinates":[-105.061622,39.769673],"type":"Point"}
}