{
  "type": "Feature",
  "properties": {
    "addr:full":"3119 Crockett St Fort Collins CO 80526",
    "addr:housenumber":"3119",
    "addr:postcode":"80526",
    "addr:street":"Crockett St",
    "iso:country":"US",
    "sg:address":"3119 Crockett St",
    "sg:city":"Fort Collins",
    "sg:classifiers":[
        {
            "category":"Professional",
            "type":"Services"
        }
    ],
    "sg:phone":"+1 970 226 4377",
    "sg:postcode":"80526",
    "sg:province":"CO",
    "wof:name":"Multiproducts Dist Inc",
    "wof:placetype":"venue"
},
  "geometry": {"coordinates":[-105.100739,40.544892],"type":"Point"}
}