{
  "type": "Feature",
  "properties": {
    "iso:country":"US",
    "sg:address":"925 15th Street",
    "sg:city":"Denver",
    "sg:classifiers":[
        {
            "category":"Food & Beverages",
            "subcategory":"Groceries & Convenience Stores",
            "type":"Retail Goods"
        }
    ],
    "sg:phone":"+1 303 436 1900",
    "sg:postcode":"80202",
    "sg:province":"CO",
    "wof:name":"Canyon Deli",
    "wof:placetype":"venue"
},
  "geometry": {"coordinates":[-104.99579,39.745942],"type":"Point"}
}