{
  "type": "Feature",
  "properties": {
    "iso:country":"US",
    "sg:address":"872 S Ogden St",
    "sg:city":"Denver",
    "sg:classifiers":[
        {
            "category":"Restaurant",
            "type":"Food & Drink"
        }
    ],
    "sg:phone":"+1 720 941 9767",
    "sg:postcode":"80209",
    "sg:province":"CO",
    "sg:tags":[
        "eating"
    ],
    "wof:name":"Fig & Frog Inc",
    "wof:placetype":"venue"
},
  "geometry": {"coordinates":[-104.97568,39.701564],"type":"Point"}
}