{
  "type": "Feature",
  "properties": {
    "iso:country":"US",
    "sg:address":"204 Sioux Dr",
    "sg:city":"Berthoud",
    "sg:classifiers":[
        {
            "category":"Building & Trades",
            "subcategory":"Construction",
            "type":"Services"
        }
    ],
    "sg:phone":"+1 970 532 2753",
    "sg:postcode":"80513",
    "sg:province":"CO",
    "sg:tags":[
        "excavation",
        "contractor"
    ],
    "wof:name":"Redabaugh Excavating",
    "wof:placetype":"venue"
},
  "geometry": {"coordinates":[-105.091155,40.300772],"type":"Point"}
}