{
  "type": "Feature",
  "properties": {
    "iso:country":"US",
    "sg:address":"25797 Conifer Rd",
    "sg:city":"Conifer",
    "sg:classifiers":[
        {
            "category":"Insurance",
            "subcategory":"Insurance Agent",
            "type":"Services"
        }
    ],
    "sg:phone":"+1 303 838 3300",
    "sg:postcode":"80433",
    "sg:province":"CO",
    "wof:name":"Renata J Bochenek & Assoc",
    "wof:placetype":"venue"
},
  "geometry": {"coordinates":[-105.29364200000001,39.543013],"type":"Point"}
}