{
  "type": "Feature",
  "properties": {
    "iso:country":"US",
    "sg:address":"470 S Federal Blvd",
    "sg:city":"Denver",
    "sg:classifiers":[
        {
            "category":"Restaurant",
            "type":"Food & Drink"
        }
    ],
    "sg:phone":"+1 303 922 2387",
    "sg:postcode":"80219",
    "sg:province":"CO",
    "sg:tags":[
        "mexican"
    ],
    "wof:name":"Tarasco's New Latino Cuisine",
    "wof:placetype":"venue"
},
  "geometry": {"coordinates":[-105.024693,39.707988],"type":"Point"}
}