{
  "type": "Feature",
  "properties": {
    "iso:country":"US",
    "sg:address":"3923 E Costilla Ave",
    "sg:city":"Littleton",
    "sg:classifiers":[
        {
            "category":"Shopping",
            "subcategory":"Gifts & Souvenirs",
            "type":"Retail Goods"
        }
    ],
    "sg:phone":"+1 303 779 9602",
    "sg:postcode":"80122",
    "sg:province":"CO",
    "wof:name":"With You In Mind",
    "wof:placetype":"venue"
},
  "geometry": {"coordinates":[-104.94564699999999,39.593011],"type":"Point"}
}