{
  "type": "Feature",
  "properties": {
    "addr:full":"3923 E Costilla Ave Littleton CO 80122",
    "addr:housenumber":"3923",
    "addr:postcode":"80122",
    "addr:street":"E Costilla Ave",
    "iso:country":"US",
    "sg:address":"3923 E Costilla Ave",
    "sg:city":"Littleton",
    "sg:classifiers":[
        {
            "category":"Shopping",
            "subcategory":"Gifts & Souvenirs",
            "type":"Retail Goods"
        }
    ],
    "sg:phone":"+1 303 779 9602",
    "sg:postcode":"80122",
    "sg:province":"CO",
    "wof:name":"With You In Mind",
    "wof:placetype":"venue"
},
  "geometry": {"coordinates":[-104.94564699999999,39.593011],"type":"Point"}
}