{
  "type": "Feature",
  "properties": {
    "addr:full":"1609 Underhill Dr Fort Collins CO 80526",
    "addr:housenumber":"1609",
    "addr:postcode":"80526",
    "addr:street":"Underhill Dr",
    "iso:country":"US",
    "sg:address":"1609 Underhill Dr",
    "sg:city":"Fort Collins",
    "sg:classifiers":[
        {
            "category":"Building & Trades",
            "subcategory":"Construction",
            "type":"Services"
        }
    ],
    "sg:phone":"+1 970 482 0228",
    "sg:postcode":"80526",
    "sg:province":"CO",
    "sg:tags":[
        "house"
    ],
    "wof:name":"Delash Custom Construction",
    "wof:placetype":"venue"
},
  "geometry": {"coordinates":[-105.109782,40.566781],"type":"Point"}
}