{
  "type": "Feature",
  "properties": {
    "iso:country":"US",
    "sg:address":"6200 Greenwood Plaza Blvd",
    "sg:city":"Greenwood Vlg",
    "sg:classifiers":[
        {
            "category":"Professional",
            "subcategory":"Management & Consulting",
            "type":"Services"
        }
    ],
    "sg:phone":"+1 303 796 7224",
    "sg:postcode":"80111",
    "sg:province":"CO",
    "sg:tags":[
        "consultant",
        "business"
    ],
    "sg:website":"www.coloradoconsultinggroupinc.com",
    "wof:name":"Colorado Consulting Group Inc",
    "wof:placetype":"venue"
},
  "geometry": {"coordinates":[-104.894848,39.603383],"type":"Point"}
}