{
  "type": "Feature",
  "properties": {
    "iso:country":"US",
    "sg:address":"4820 W 99th Ave",
    "sg:city":"Westminster",
    "sg:classifiers":[
        {
            "category":"Building & Trades",
            "subcategory":"Construction",
            "type":"Services"
        }
    ],
    "sg:phone":"+1 303 919 6325",
    "sg:postcode":"80031",
    "sg:province":"CO",
    "sg:tags":[
        "painter"
    ],
    "wof:name":"Nielsen Painting",
    "wof:placetype":"venue"
},
  "geometry": {"coordinates":[-105.048061,39.876282],"type":"Point"}
}