{
  "type": "Feature",
  "properties": {
    "iso:country":"US",
    "sg:address":"9050 W 58th Ave",
    "sg:city":"Arvada",
    "sg:classifiers":[
        {
            "category":"Restaurant",
            "type":"Food & Drink"
        }
    ],
    "sg:phone":"+1 303 422 3388",
    "sg:postcode":"80002",
    "sg:province":"CO",
    "wof:name":"Happy Gourmet Asian Bistro",
    "wof:placetype":"venue"
},
  "geometry": {"coordinates":[-105.097381,39.801983],"type":"Point"}
}