{
  "type": "Feature",
  "properties": {
    "iso:country":"US",
    "sg:address":"28755 State Hwy 9",
    "sg:city":"Silverthorne",
    "sg:classifiers":[
        {
            "category":"Wholesale",
            "subcategory":"Construction Materials",
            "type":"Manufacturing & Wholesale Goods"
        }
    ],
    "sg:phone":"+1 970 468 2521",
    "sg:postcode":"80498",
    "sg:province":"CO",
    "sg:tags":[
        "sand",
        "gravel"
    ],
    "wof:name":"Everist Marterials LLC",
    "wof:placetype":"venue"
},
  "geometry": {"coordinates":[-106.103905,39.690492],"type":"Point"}
}