{
  "type": "Feature",
  "properties": {
    "addr:full":"32705 Saint Moritz Dr Evergreen CO 80439",
    "addr:housenumber":"32705",
    "addr:postcode":"80439",
    "addr:street":"Saint Moritz Dr",
    "iso:country":"US",
    "sg:address":"32705 Saint Moritz Dr",
    "sg:city":"Evergreen",
    "sg:classifiers":[
        {
            "category":"Building & Trades",
            "subcategory":"Construction",
            "type":"Services"
        }
    ],
    "sg:phone":"+1 303 670 0343",
    "sg:postcode":"80439",
    "sg:province":"CO",
    "sg:tags":[
        "house"
    ],
    "wof:name":"Mountain High Construction Co",
    "wof:placetype":"venue"
},
  "geometry": {"coordinates":[-105.383774,39.574475],"type":"Point"}
}