{
  "type": "Feature",
  "properties": {
    "iso:country":"US",
    "sg:address":"4500 E 9th Ave Ste 620",
    "sg:city":"Denver",
    "sg:classifiers":[
        {
            "category":"Health Services",
            "subcategory":"Hospital",
            "type":"Services"
        },
        {
            "category":"Community Center",
            "type":"Public Place"
        }
    ],
    "sg:phone":"+1 720 941 8384",
    "sg:postcode":"80220",
    "sg:province":"CO",
    "sg:tags":[
        "medical"
    ],
    "sg:website":"www.questdiagnostics.com",
    "wof:name":"Quest Diagnostics",
    "wof:placetype":"venue"
},
  "geometry": {"coordinates":[-104.935157,39.730923],"type":"Point"}
}