{
  "type": "Feature",
  "properties": {
    "addr:full":"602 S Tejon St Colorado Springs CO 80903",
    "addr:housenumber":"602",
    "addr:postcode":"80903",
    "addr:street":"S Tejon St",
    "iso:country":"US",
    "sg:address":"602 S Tejon St",
    "sg:city":"Colorado Springs",
    "sg:classifiers":[
        {
            "category":"Professional",
            "subcategory":"Lawyer & Legal Services",
            "type":"Services"
        }
    ],
    "sg:phone":"+1 719 520 5011",
    "sg:postcode":"80903",
    "sg:province":"CO",
    "sg:tags":[
        "attorney"
    ],
    "wof:name":"Anderson & Travis",
    "wof:placetype":"venue"
},
  "geometry": {"coordinates":[-104.824078,38.824505],"type":"Point"}
}