{
  "type": "Feature",
  "properties": {
    "iso:country":"US",
    "sg:address":"1916 13th St",
    "sg:city":"Boulder",
    "sg:classifiers":[
        {
            "category":"Shopping",
            "type":"Retail Goods"
        }
    ],
    "sg:phone":"+1 303 402 0140",
    "sg:postcode":"80302",
    "sg:province":"CO",
    "sg:tags":[
        "merchandise"
    ],
    "wof:name":"Tibet Gallery",
    "wof:placetype":"venue"
},
  "geometry": {"coordinates":[-105.27835399999999,40.01741],"type":"Point"}
}