{
  "type": "Feature",
  "properties": {
    "addr:full":"1115 Turley Cir Colorado Springs CO 80915",
    "addr:housenumber":"1115",
    "addr:postcode":"80915",
    "addr:street":"Turley Cir",
    "iso:country":"US",
    "sg:address":"1115 Turley Cir",
    "sg:city":"Colorado Springs",
    "sg:classifiers":[
        {
            "category":"Education",
            "subcategory":"Special Training",
            "type":"Public Place"
        }
    ],
    "sg:phone":"+1 719 574 6460",
    "sg:postcode":"80915",
    "sg:province":"CO",
    "sg:tags":[
        "management"
    ],
    "wof:name":"Peak Performance Consulting",
    "wof:placetype":"venue"
},
  "geometry": {"coordinates":[-104.73985,38.849709],"type":"Point"}
}