{
  "type": "Feature",
  "properties": {
    "addr:full":"16648 E Hialeah Ave Aurora CO 80015",
    "addr:housenumber":"16648",
    "addr:postcode":"80015",
    "addr:street":"E Hialeah Ave",
    "iso:country":"US",
    "sg:address":"16648 E Hialeah Ave",
    "sg:city":"Aurora",
    "sg:classifiers":[
        {
            "category":"Food & Beverages",
            "subcategory":"Groceries & Convenience Stores",
            "type":"Retail Goods"
        },
        {
            "category":"Professional",
            "subcategory":"Employment Agencies",
            "type":"Services"
        }
    ],
    "sg:phone":"+1 303 693 6678",
    "sg:postcode":"80015",
    "sg:province":"CO",
    "sg:tags":[
        "consultant",
        "search",
        "executive"
    ],
    "wof:name":"Market Crafters International",
    "wof:placetype":"venue"
},
  "geometry": {"coordinates":[-104.794749,39.622874],"type":"Point"}
}