{
  "type": "Feature",
  "properties": {
    "iso:country":"US",
    "sg:address":"460 Garland Dr",
    "sg:city":"Northglenn",
    "sg:classifiers":[
        {
            "category":"Social Services",
            "subcategory":"Child Care",
            "type":"Services"
        }
    ],
    "sg:phone":"+1 303 280 5880",
    "sg:postcode":"80233",
    "sg:province":"CO",
    "wof:name":"Brother Bear Child Care",
    "wof:placetype":"venue"
},
  "geometry": {"coordinates":[-104.980358,39.889838],"type":"Point"}
}