{
  "type": "Feature",
  "properties": {
    "iso:country":"US",
    "sg:address":"1124 E Lake Pl",
    "sg:city":"Fort Collins",
    "sg:classifiers":[
        {
            "category":"Building & Trades",
            "subcategory":"Construction",
            "type":"Services"
        }
    ],
    "sg:phone":"+1 970 224 4389",
    "sg:postcode":"80524",
    "sg:province":"CO",
    "sg:tags":[
        "industrial",
        "contractor"
    ],
    "wof:name":"S B McGuire Construction Co",
    "wof:placetype":"venue"
},
  "geometry": {"coordinates":[-105.05838,40.568757],"type":"Point"}
}