{
  "type": "Feature",
  "properties": {
    "addr:full":"317 Nebraska Ave Stratton CO 80836",
    "addr:housenumber":"317",
    "addr:postcode":"80836",
    "addr:street":"Nebraska Ave",
    "iso:country":"US",
    "sg:address":"317 Nebraska Ave",
    "sg:city":"Stratton",
    "sg:classifiers":[
        {
            "category":"Professional",
            "type":"Services"
        }
    ],
    "sg:phone":"+1 719 348 5491",
    "sg:postcode":"80836",
    "sg:province":"CO",
    "wof:name":"E Peters Donald",
    "wof:placetype":"venue"
},
  "geometry": {"coordinates":[-102.60757599999999,39.303462],"type":"Point"}
}