{
  "type": "Feature",
  "properties": {
    "iso:country":"US",
    "sg:address":"633 S Federal Boulevard",
    "sg:city":"Denver",
    "sg:classifiers":[
        {
            "category":"Health Services",
            "subcategory":"Doctor",
            "type":"Services"
        }
    ],
    "sg:phone":"+1 303 935 3566",
    "sg:postcode":"80219",
    "sg:province":"CO",
    "sg:tags":[
        "medicine",
        "internal"
    ],
    "wof:name":"Nguyen Dinh Dr Internist",
    "wof:placetype":"venue"
},
  "geometry": {"coordinates":[-105.02507900000001,39.705131],"type":"Point"}
}