{
  "type": "Feature",
  "properties": {
    "iso:country":"US",
    "sg:address":"2266 S Chambers Rd",
    "sg:city":"Aurora",
    "sg:classifiers":[
        {
            "category":"Shopping",
            "subcategory":"Florist",
            "type":"Retail Goods"
        }
    ],
    "sg:phone":"+1 303 745 2500",
    "sg:postcode":"80014",
    "sg:province":"CO",
    "wof:name":"Best Buds Flowers & Gifts",
    "wof:placetype":"venue"
},
  "geometry": {"coordinates":[-104.809845,39.676102],"type":"Point"}
}