{
  "type": "Feature",
  "properties": {
    "addr:full":"6710 Federal Blvd Denver CO 80221",
    "addr:housenumber":"6710",
    "addr:postcode":"80221",
    "addr:street":"Federal Blvd",
    "iso:country":"US",
    "sg:address":"6710 Federal Blvd",
    "sg:city":"Denver",
    "sg:classifiers":[
        {
            "category":"Bars & Pubs",
            "type":"Food & Drink"
        }
    ],
    "sg:phone":"+1 303 426 6996",
    "sg:postcode":"80221",
    "sg:province":"CO",
    "sg:tags":[
        "bar"
    ],
    "wof:name":"Cheerleaders",
    "wof:placetype":"venue"
},
  "geometry": {"coordinates":[-105.025004,39.818478],"type":"Point"}
}