{
  "type": "Feature",
  "properties": {
    "addr:full":"840 Drake St Denver CO 80221",
    "addr:housenumber":"840",
    "addr:postcode":"80221",
    "addr:street":"Drake St",
    "iso:country":"US",
    "sg:address":"840 Drake St",
    "sg:city":"Denver",
    "sg:classifiers":[
        {
            "category":"Retail",
            "subcategory":"Repair Shop",
            "type":"Services"
        }
    ],
    "sg:phone":"+1 303 427 8121",
    "sg:postcode":"80221",
    "sg:province":"CO",
    "sg:tags":[
        "upholsterer"
    ],
    "wof:name":"S & J Upholstery",
    "wof:placetype":"venue"
},
  "geometry": {"coordinates":[-104.99826400000001,39.833581],"type":"Point"}
}