{
  "type": "Feature",
  "properties": {
    "iso:country":"US",
    "sg:address":"11189 W 63rd Ave",
    "sg:city":"Arvada",
    "sg:classifiers":[
        {
            "category":"Building & Trades",
            "subcategory":"Construction",
            "type":"Services"
        }
    ],
    "sg:phone":"+1 303 422 9495",
    "sg:postcode":"80004",
    "sg:province":"CO",
    "sg:tags":[
        "house"
    ],
    "wof:name":"Lowe Custom Building",
    "wof:placetype":"venue"
},
  "geometry": {"coordinates":[-105.12296600000001,39.811051],"type":"Point"}
}