{
  "type": "Feature",
  "properties": {
    "addr:full":"315 S Galena St Aspen CO 81611",
    "addr:housenumber":"315",
    "addr:postcode":"81611",
    "addr:street":"S Galena St",
    "iso:country":"US",
    "sg:address":"315 S Galena St",
    "sg:city":"Aspen",
    "sg:classifiers":[
        {
            "category":"Real Estate",
            "subcategory":"Real Estate Agent",
            "type":"Services"
        }
    ],
    "sg:phone":"+1 970 925 6176",
    "sg:postcode":"81611",
    "sg:province":"CO",
    "wof:name":"Len & Candy Allen",
    "wof:placetype":"venue"
},
  "geometry": {"coordinates":[-106.818679,39.188729],"type":"Point"}
}