{
  "type": "Feature",
  "properties": {
    "addr:full":"3140 S Parker Rd Aurora CO 80014",
    "addr:housenumber":"3140",
    "addr:postcode":"80014",
    "addr:street":"S Parker Rd",
    "iso:country":"US",
    "sg:address":"3140 S Parker Rd",
    "sg:city":"Aurora",
    "sg:classifiers":[
        {
            "category":"Shopping",
            "subcategory":"Clothing, Apparel, & Fashions",
            "type":"Retail Goods"
        }
    ],
    "sg:phone":"+1 303 369 6545",
    "sg:postcode":"80014",
    "sg:province":"CO",
    "sg:tags":[
        "tailor",
        "custom"
    ],
    "wof:name":"Artistic Custom Tailor",
    "wof:placetype":"venue"
},
  "geometry": {"coordinates":[-104.851349,39.659815],"type":"Point"}
}