{
  "type": "Feature",
  "properties": {
    "iso:country":"US",
    "sg:address":"17150 W Colfax Ave",
    "sg:city":"Golden",
    "sg:classifiers":[
        {
            "category":"Travel",
            "subcategory":"Hotels & Motels",
            "type":"Entertainment"
        }
    ],
    "sg:phone":"+1 303 278 6600",
    "sg:postcode":"80401",
    "sg:province":"CO",
    "sg:tags":[
        "operation"
    ],
    "sg:website":"www.hamptoninn.com",
    "wof:name":"Hampton Inn",
    "wof:placetype":"venue"
},
  "geometry": {"coordinates":[-105.193218,39.723354],"type":"Point"}
}