{
  "type": "Feature",
  "properties": {
    "iso:country":"US",
    "sg:address":"1275 E Magnolia St",
    "sg:city":"Fort Collins",
    "sg:classifiers":[
        {
            "category":"Restaurant",
            "type":"Food & Drink"
        }
    ],
    "sg:menulink":"http://www.allmenus.com/co/fort-collins/98179-qdoba/menu/",
    "sg:phone":"+1 970 472 0461",
    "sg:postcode":"80524",
    "sg:province":"CO",
    "sg:tags":[
        "mexican"
    ],
    "wof:name":"Qdoba",
    "wof:placetype":"venue"
},
  "geometry": {"coordinates":[-105.05511799999999,40.584371],"type":"Point"}
}