{
  "type": "Feature",
  "properties": {
    "iso:country":"US",
    "sg:address":"451 E 58th Ave Unit 269",
    "sg:city":"Denver",
    "sg:classifiers":[
        {
            "category":"Shopping",
            "subcategory":"Jewelry",
            "type":"Retail Goods"
        }
    ],
    "sg:phone":"+1 303 295 1286",
    "sg:postcode":"80216",
    "sg:province":"CO",
    "wof:name":"Finelines Jewelers",
    "wof:placetype":"venue"
},
  "geometry": {"coordinates":[-104.982002,39.801998],"type":"Point"}
}