{
  "type": "Feature",
  "properties": {
    "iso:country":"US",
    "sg:address":"12252 S Parker Rd",
    "sg:city":"Denver",
    "sg:classifiers":[
        {
            "category":"Home & Garden",
            "subcategory":"Household Appliances",
            "type":"Retail Goods"
        },
        {
            "category":"Retail",
            "subcategory":"Repair Shop",
            "type":"Services"
        }
    ],
    "sg:phone":"+1 720 851 8855",
    "sg:postcode":"80231",
    "sg:province":"CO",
    "sg:tags":[
        "major",
        "refinishing"
    ],
    "wof:name":"Appliance Factory Outlet Inc",
    "wof:placetype":"venue"
},
  "geometry": {"coordinates":[-104.866428,39.671135],"type":"Point"}
}