{
  "type": "Feature",
  "properties": {
    "addr:full":"3031 Bookcliff Ave Grand Junction CO 81504",
    "addr:housenumber":"3031",
    "addr:postcode":"81504",
    "addr:street":"Bookcliff Ave",
    "iso:country":"US",
    "sg:address":"3031 Bookcliff Ave",
    "sg:city":"Grand Junction",
    "sg:classifiers":[
        {
            "category":"Building & Trades",
            "subcategory":"Construction",
            "type":"Services"
        }
    ],
    "sg:phone":"+1 970 434 0748",
    "sg:postcode":"81504",
    "sg:province":"CO",
    "sg:tags":[
        "general",
        "contractor"
    ],
    "wof:name":"Jfh Construction",
    "wof:placetype":"venue"
},
  "geometry": {"coordinates":[-108.489543,39.088095],"type":"Point"}
}