{
  "type": "Feature",
  "properties": {
    "addr:full":"4538 S Meadow Dr Boulder CO 80301",
    "addr:housenumber":"4538",
    "addr:postcode":"80301",
    "addr:street":"S Meadow Dr",
    "iso:country":"US",
    "sg:address":"4538 S Meadow Dr",
    "sg:city":"Boulder",
    "sg:classifiers":[
        {
            "category":"Professional",
            "type":"Services"
        }
    ],
    "sg:phone":"+1 303 530 3781",
    "sg:postcode":"80301",
    "sg:province":"CO",
    "wof:name":"Frank Shelledy LLC",
    "wof:placetype":"venue"
},
  "geometry": {"coordinates":[-105.182599,40.056142],"type":"Point"}
}