{
  "type": "Feature",
  "properties": {
    "iso:country":"US",
    "sg:address":"78 E Allen St",
    "sg:city":"Castle Rock",
    "sg:classifiers":[
        {
            "category":"Shopping",
            "subcategory":"Mobile Phones",
            "type":"Retail Goods"
        }
    ],
    "sg:phone":"+1 720 733 1651",
    "sg:postcode":"80108",
    "sg:province":"CO",
    "wof:name":"Cct Wireless",
    "wof:placetype":"venue"
},
  "geometry": {"coordinates":[-104.86283899999999,39.413429],"type":"Point"}
}