{
  "type": "Feature",
  "properties": {
    "iso:country":"US",
    "sg:address":"235 Sedona Dr",
    "sg:city":"Colorado Springs",
    "sg:classifiers":[
        {
            "category":"Building & Trades",
            "subcategory":"Construction",
            "type":"Services"
        }
    ],
    "sg:phone":"+1 719 538 5762",
    "sg:postcode":"80921",
    "sg:province":"CO",
    "sg:tags":[
        "house"
    ],
    "wof:name":"Rogers Construction",
    "wof:placetype":"venue"
},
  "geometry": {"coordinates":[-104.831407,39.039458],"type":"Point"}
}