{
  "type": "Feature",
  "properties": {
    "addr:full":"4343 S Buckley Rd Aurora CO 80015",
    "addr:housenumber":"4343",
    "addr:postcode":"80015",
    "addr:street":"S Buckley Rd",
    "iso:country":"US",
    "sg:address":"4343 S Buckley Rd",
    "sg:city":"Aurora",
    "sg:classifiers":[
        {
            "category":"Insurance",
            "subcategory":"Insurance Agent",
            "type":"Services"
        }
    ],
    "sg:phone":"+1 303 400 0291",
    "sg:postcode":"80015",
    "sg:province":"CO",
    "sg:tags":[
        "consultant"
    ],
    "wof:name":"Chapman & Assoc",
    "wof:placetype":"venue"
},
  "geometry": {"coordinates":[-104.79156399999999,39.634974],"type":"Point"}
}