{
  "type": "Feature",
  "properties": {
    "addr:full":"934 S Tejon St Colorado Springs CO 80903",
    "addr:housenumber":"934",
    "addr:postcode":"80903",
    "addr:street":"S Tejon St",
    "iso:country":"US",
    "sg:address":"934 S Tejon St",
    "sg:city":"Colorado Springs",
    "sg:classifiers":[
        {
            "category":"Autos & Motor Vehicles",
            "subcategory":"Automobile Sales",
            "type":"Retail Goods"
        }
    ],
    "sg:phone":"+1 719 633 1718",
    "sg:postcode":"80903",
    "sg:province":"CO",
    "sg:tags":[
        "used"
    ],
    "wof:name":"Bernmar Motors Inc",
    "wof:placetype":"venue"
},
  "geometry": {"coordinates":[-104.824319,38.820047],"type":"Point"}
}