{
  "type": "Feature",
  "properties": {
    "addr:full":"11101 S Parker Rd Parker CO 80134",
    "addr:housenumber":"11101",
    "addr:postcode":"80134",
    "addr:street":"S Parker Rd",
    "iso:country":"US",
    "sg:address":"11101 S Parker Rd",
    "sg:city":"Parker",
    "sg:classifiers":[
        {
            "category":"Personal",
            "subcategory":"Beauty Salon",
            "type":"Services"
        }
    ],
    "sg:phone":"+1 720 842 1283",
    "sg:postcode":"80134",
    "sg:province":"CO",
    "wof:name":"Smart Style Family Hair Salon",
    "wof:placetype":"venue"
},
  "geometry": {"coordinates":[-104.766068,39.523842],"type":"Point"}
}