{
  "type": "Feature",
  "properties": {
    "iso:country":"US",
    "sg:address":"324 Wright St",
    "sg:city":"Lakewood",
    "sg:classifiers":[
        {
            "category":"Professional",
            "type":"Services"
        }
    ],
    "sg:phone":"+1 303 980 6233",
    "sg:postcode":"80228",
    "sg:province":"CO",
    "sg:tags":[
        "establishment"
    ],
    "wof:name":"Telluride West HOA",
    "wof:placetype":"venue"
},
  "geometry": {"coordinates":[-105.141581,39.72093],"type":"Point"}
}