{
  "type": "Feature",
  "properties": {
    "addr:full":"1123 Spruce St Boulder CO 80302",
    "addr:housenumber":"1123",
    "addr:postcode":"80302",
    "addr:street":"Spruce St",
    "iso:country":"US",
    "sg:address":"1123 Spruce St",
    "sg:city":"Boulder",
    "sg:classifiers":[
        {
            "category":"Professional",
            "subcategory":"Research",
            "type":"Services"
        }
    ],
    "sg:phone":"+1 303 442 1200",
    "sg:postcode":"80302",
    "sg:province":"CO",
    "sg:tags":[
        "foundation",
        "philanthropic"
    ],
    "wof:name":"Brett Family Foundation",
    "wof:placetype":"venue"
},
  "geometry": {"coordinates":[-105.280576,40.018908],"type":"Point"}
}