{
  "type": "Feature",
  "properties": {
    "addr:full":"6066 Blackfoot Cir Sedalia CO 80135",
    "addr:housenumber":"6066",
    "addr:postcode":"80135",
    "addr:street":"Blackfoot Cir",
    "iso:country":"US",
    "sg:address":"6066 Blackfoot Cir",
    "sg:city":"Sedalia",
    "sg:classifiers":[
        {
            "category":"Retail",
            "subcategory":"Auto Repair",
            "type":"Services"
        }
    ],
    "sg:phone":"+1 303 688 8945",
    "sg:postcode":"80135",
    "sg:province":"CO",
    "sg:tags":[
        "repairing",
        "automobile"
    ],
    "wof:name":"Santa Fe Svc Ctr",
    "wof:placetype":"venue"
},
  "geometry": {"coordinates":[-104.999768,39.414844],"type":"Point"}
}