{
  "type": "Feature",
  "properties": {
    "addr:full":"516 Violet St Golden CO 80401",
    "addr:housenumber":"516",
    "addr:postcode":"80401",
    "addr:street":"Violet St",
    "iso:country":"US",
    "sg:address":"516 Violet St",
    "sg:city":"Golden",
    "sg:classifiers":[
        {
            "category":"Shopping",
            "type":"Retail Goods"
        }
    ],
    "sg:phone":"+1 303 216 9323",
    "sg:postcode":"80401",
    "sg:province":"CO",
    "sg:tags":[
        "merchandise"
    ],
    "wof:name":"Maxair",
    "wof:placetype":"venue"
},
  "geometry": {"coordinates":[-105.19726,39.723495],"type":"Point"}
}