{
  "type": "Feature",
  "properties": {
    "iso:country":"US",
    "sg:address":"710 Lodgepole Dr",
    "sg:city":"Bellvue",
    "sg:classifiers":[
        {
            "category":"Recreation",
            "type":"Entertainment"
        }
    ],
    "sg:phone":"+1 970 224 4200",
    "sg:postcode":"80512",
    "sg:province":"CO",
    "sg:tags":[
        "stable"
    ],
    "wof:name":"Double Diamond Stable",
    "wof:placetype":"venue"
},
  "geometry": {"coordinates":[-105.178585,40.577799],"type":"Point"}
}