{
  "type": "Feature",
  "properties": {
    "addr:full":"3151 S Vaughn Way Ste 412 Aurora CO 80014",
    "addr:housenumber":"3151",
    "addr:postcode":"80014",
    "addr:street":"S Vaughn Way Ste 412",
    "iso:country":"US",
    "sg:address":"3151 S Vaughn Way Ste 412",
    "sg:city":"Aurora",
    "sg:classifiers":[
        {
            "category":"Professional",
            "subcategory":"Employment Agencies",
            "type":"Services"
        }
    ],
    "sg:phone":"+1 303 909 3868",
    "sg:postcode":"80014",
    "sg:province":"CO",
    "sg:tags":[
        "opportunity"
    ],
    "sg:website":"http://www.10til2.com",
    "wof:name":"10 Til 2",
    "wof:placetype":"venue"
},
  "geometry": {"coordinates":[-104.83778,39.659195],"type":"Point"}
}