{
  "type": "Feature",
  "properties": {
    "iso:country":"US",
    "sg:address":"222 E 8th Ave",
    "sg:city":"Yuma",
    "sg:classifiers":[
        {
            "category":"Restaurant",
            "type":"Food & Drink"
        }
    ],
    "sg:phone":"+1 970 848 8242",
    "sg:postcode":"80759",
    "sg:province":"CO",
    "wof:name":"Broken Wheel Bar & Grille",
    "wof:placetype":"venue"
},
  "geometry": {"coordinates":[-102.722255,40.118562],"type":"Point"}
}