{
  "type": "Feature",
  "properties": {
    "iso:country":"US",
    "sg:address":"6170 Lehman Dr",
    "sg:city":"Colorado Springs",
    "sg:classifiers":[
        {
            "category":"Insurance",
            "subcategory":"Insurance Agent",
            "type":"Services"
        }
    ],
    "sg:phone":"+1 719 599 5757",
    "sg:postcode":"80918",
    "sg:province":"CO",
    "wof:name":"Hansen Agency",
    "wof:placetype":"venue"
},
  "geometry": {"coordinates":[-104.790576,38.91981],"type":"Point"}
}