{
  "type": "Feature",
  "properties": {
    "addr:full":"1703 Whitehall Dr Longmont CO 80501",
    "addr:housenumber":"1703",
    "addr:postcode":"80501",
    "addr:street":"Whitehall Dr",
    "iso:country":"US",
    "sg:address":"1703 Whitehall Dr",
    "sg:city":"Longmont",
    "sg:classifiers":[
        {
            "category":"Building & Trades",
            "subcategory":"Construction",
            "type":"Services"
        }
    ],
    "sg:phone":"+1 303 682 5454",
    "sg:postcode":"80501",
    "sg:province":"CO",
    "sg:tags":[
        "fireproofing"
    ],
    "wof:name":"United Fire Containment",
    "wof:placetype":"venue"
},
  "geometry": {"coordinates":[-105.076891,40.189482],"type":"Point"}
}