{
  "type": "Feature",
  "properties": {
    "addr:full":"434 Short St Rangely CO 81648",
    "addr:housenumber":"434",
    "addr:postcode":"81648",
    "addr:street":"Short St",
    "iso:country":"US",
    "sg:address":"434 Short St",
    "sg:city":"Rangely",
    "sg:classifiers":[
        {
            "category":"Building & Trades",
            "subcategory":"Construction",
            "type":"Services"
        }
    ],
    "sg:phone":"+1 970 675 2196",
    "sg:postcode":"81648",
    "sg:province":"CO",
    "wof:name":"JW Production & Contracting",
    "wof:placetype":"venue"
},
  "geometry": {"coordinates":[-108.80442499999999,40.082128],"type":"Point"}
}