{
  "type": "Feature",
  "properties": {
    "addr:full":"505 Babcock Rd Colorado Springs CO 80915",
    "addr:housenumber":"505",
    "addr:postcode":"80915",
    "addr:street":"Babcock Rd",
    "iso:country":"US",
    "sg:address":"505 Babcock Rd",
    "sg:city":"Colorado Springs",
    "sg:classifiers":[
        {
            "category":"Manufacturing",
            "subcategory":"Buildings",
            "type":"Manufacturing & Wholesale Goods"
        }
    ],
    "sg:phone":"+1 719 622 9077",
    "sg:postcode":"80915",
    "sg:province":"CO",
    "sg:tags":[
        "mobile",
        "home",
        "mfg"
    ],
    "wof:name":"Clayton Homes Inc",
    "wof:placetype":"venue"
},
  "geometry": {"coordinates":[-104.72965600000001,38.839851],"type":"Point"}
}