{
  "type": "Feature",
  "properties": {
    "iso:country":"US",
    "sg:address":"6120 S Broadway",
    "sg:city":"Littleton",
    "sg:classifiers":[
        {
            "category":"Autos & Motor Vehicles",
            "subcategory":"Automobile Sales",
            "type":"Retail Goods"
        },
        {
            "category":"Retail",
            "subcategory":"Auto Repair",
            "type":"Services"
        }
    ],
    "sg:phone":"+1 888 400 0320",
    "sg:postcode":"80121",
    "sg:province":"CO",
    "sg:tags":[
        "car",
        "used",
        "new"
    ],
    "sg:website":"http://www.qualitymitsubishi.com",
    "wof:name":"Quality Mitsubishi",
    "wof:placetype":"venue"
},
  "geometry": {"coordinates":[-104.988055,39.605471],"type":"Point"}
}