{
  "type": "Feature",
  "properties": {
    "iso:country":"US",
    "sg:address":"452 Dickson St",
    "sg:city":"Longmont",
    "sg:classifiers":[
        {
            "category":"Recreation",
            "type":"Entertainment"
        }
    ],
    "sg:phone":"+1 303 774 6383",
    "sg:postcode":"80501",
    "sg:province":"CO",
    "wof:name":"Cynthia Tiger",
    "wof:placetype":"venue"
},
  "geometry": {"coordinates":[-105.082419,40.165676],"type":"Point"}
}