{
  "type": "Feature",
  "properties": {
    "iso:country":"US",
    "sg:address":"305 S Kipling St",
    "sg:city":"Lakewood",
    "sg:classifiers":[
        {
            "category":"Personal",
            "subcategory":"Beauty Salon",
            "type":"Services"
        }
    ],
    "sg:phone":"+1 303 987 2288",
    "sg:postcode":"80226",
    "sg:province":"CO",
    "wof:name":"Salon 305",
    "wof:placetype":"venue"
},
  "geometry": {"coordinates":[-105.109713,39.710199],"type":"Point"}
}