{
  "type": "Feature",
  "properties": {
    "iso:country":"US",
    "sg:address":"12835 E Arapahoe Rd",
    "sg:city":"Centennial",
    "sg:classifiers":[
        {
            "category":"Real Estate",
            "subcategory":"Developer",
            "type":"Services"
        }
    ],
    "sg:phone":"+1 303 649 1542",
    "sg:postcode":"80112",
    "sg:province":"CO",
    "wof:name":"Ute Lake Ranch Inc",
    "wof:placetype":"venue"
},
  "geometry": {"coordinates":[-104.83904200000001,39.59512],"type":"Point"}
}