{
  "type": "Feature",
  "properties": {
    "addr:full":"732 Grand Ave Glenwood Springs CO 81601",
    "addr:housenumber":"732",
    "addr:postcode":"81601",
    "addr:street":"Grand Ave",
    "iso:country":"US",
    "sg:address":"732 Grand Ave",
    "sg:city":"Glenwood Springs",
    "sg:classifiers":[
        {
            "category":"Shopping",
            "subcategory":"Bicycles & Sporting Goods",
            "type":"Retail Goods"
        },
        {
            "category":"Shopping",
            "subcategory":"Clothing, Apparel, & Fashions",
            "type":"Retail Goods"
        }
    ],
    "sg:phone":"+1 970 945 6994",
    "sg:postcode":"81601",
    "sg:province":"CO",
    "sg:tags":[
        "equipment",
        "sport",
        "specialty",
        "camping"
    ],
    "sg:website":"www.summitcanyon.com",
    "wof:name":"Summit Canyon Mountaineering",
    "wof:placetype":"venue"
},
  "geometry": {"coordinates":[-107.32463300000001,39.547307],"type":"Point"}
}