{
  "type": "Feature",
  "properties": {
    "iso:country":"US",
    "sg:address":"421 Main St",
    "sg:city":"Ouray",
    "sg:classifiers":[
        {
            "category":"Organizations",
            "subcategory":"Community Association",
            "type":"Services"
        }
    ],
    "sg:phone":"+1 970 325 4510",
    "sg:postcode":"81427",
    "sg:province":"CO",
    "sg:tags":[
        "fraternal"
    ],
    "wof:name":"Elks Lodge",
    "wof:placetype":"venue"
},
  "geometry": {"coordinates":[-107.671437,38.020875],"type":"Point"}
}