{
  "type": "Feature",
  "properties": {
    "addr:full":"1745 Shea Center Dr Littleton CO 80129",
    "addr:housenumber":"1745",
    "addr:postcode":"80129",
    "addr:street":"Shea Center Dr",
    "iso:country":"US",
    "sg:address":"1745 Shea Center Dr",
    "sg:city":"Littleton",
    "sg:classifiers":[
        {
            "category":"Real Estate",
            "subcategory":"Real Estate Agent",
            "type":"Services"
        }
    ],
    "sg:phone":"+1 303 347 1291",
    "sg:postcode":"80129",
    "sg:province":"CO",
    "wof:name":"Linx Land",
    "wof:placetype":"venue"
},
  "geometry": {"coordinates":[-105.00846,39.553208],"type":"Point"}
}