{
  "type": "Feature",
  "properties": {
    "addr:full":"2596 F Rd Grand Junction CO 81505",
    "addr:housenumber":"2596",
    "addr:postcode":"81505",
    "addr:street":"F Rd",
    "iso:country":"US",
    "sg:address":"2596 F Rd",
    "sg:city":"Grand Junction",
    "sg:classifiers":[
        {
            "category":"Health Services",
            "subcategory":"Doctor",
            "type":"Services"
        }
    ],
    "sg:phone":"+1 970 244 9148",
    "sg:postcode":"81505",
    "sg:province":"CO",
    "sg:tags":[
        "physician",
        "surgeon"
    ],
    "wof:name":"Surgery Center",
    "wof:placetype":"venue"
},
  "geometry": {"coordinates":[-108.57332100000001,39.091837],"type":"Point"}
}