{
  "type": "Feature",
  "properties": {
    "addr:full":"101 E 88th Ave Denver CO 80229",
    "addr:housenumber":"101",
    "addr:postcode":"80229",
    "addr:street":"E 88Th Ave",
    "iso:country":"US",
    "sg:address":"101 E 88th Ave",
    "sg:city":"Denver",
    "sg:classifiers":[
        {
            "category":"Professional",
            "type":"Services"
        }
    ],
    "sg:phone":"+1 720 540 5621",
    "sg:postcode":"80229",
    "sg:province":"CO",
    "wof:name":"Tabitha Ellis",
    "wof:placetype":"venue"
},
  "geometry": {"coordinates":[-104.98688,39.856311],"type":"Point"}
}