{
  "type": "Feature",
  "properties": {
    "addr:full":"1915 Zephyr St Lakewood CO 80214",
    "addr:housenumber":"1915",
    "addr:postcode":"80214",
    "addr:street":"Zephyr St",
    "iso:country":"US",
    "sg:address":"1915 Zephyr St",
    "sg:city":"Lakewood",
    "sg:classifiers":[
        {
            "category":"Retail",
            "subcategory":"Repair Shop",
            "type":"Services"
        }
    ],
    "sg:phone":"+1 303 238 6330",
    "sg:postcode":"80214",
    "sg:province":"CO",
    "sg:tags":[
        "machine"
    ],
    "wof:name":"Precision Appliance",
    "wof:placetype":"venue"
},
  "geometry": {"coordinates":[-105.08496599999999,39.746085],"type":"Point"}
}