{
  "type": "Feature",
  "properties": {
    "addr:full":"10301 E Arapahoe Rd Centennial CO 80112",
    "addr:housenumber":"10301",
    "addr:postcode":"80112",
    "addr:street":"E Arapahoe Rd",
    "iso:country":"US",
    "sg:address":"10301 E Arapahoe Rd",
    "sg:city":"Centennial",
    "sg:classifiers":[
        {
            "category":"Autos & Motor Vehicles",
            "subcategory":"Automobile Sales",
            "type":"Retail Goods"
        }
    ],
    "sg:phone":"+1 303 360 8000",
    "sg:postcode":"80112",
    "sg:province":"CO",
    "sg:tags":[
        "car",
        "dealer"
    ],
    "sg:website":"www.burt-ford.com",
    "wof:name":"Burt Ford Mazda",
    "wof:placetype":"venue"
},
  "geometry": {"coordinates":[-104.86773599999999,39.595107],"type":"Point"}
}