{
  "type": "Feature",
  "properties": {
    "addr:full":"4281 E Mexico Ave Denver CO 80222",
    "addr:housenumber":"4281",
    "addr:postcode":"80222",
    "addr:street":"E Mexico Ave",
    "iso:country":"US",
    "sg:address":"4281 E Mexico Ave",
    "sg:city":"Denver",
    "sg:classifiers":[
        {
            "category":"Building & Trades",
            "subcategory":"Locksmith",
            "type":"Services"
        }
    ],
    "sg:phone":"+1 303 328 9954",
    "sg:postcode":"80222",
    "sg:province":"CO",
    "sg:tags":[
        "key"
    ],
    "wof:name":"A-1 15 Minutes On Time Locksmith",
    "wof:placetype":"venue"
},
  "geometry": {"coordinates":[-104.937448,39.685837],"type":"Point"}
}