{
  "type": "Feature",
  "properties": {
    "iso:country":"US",
    "sg:address":"4155 Danceglen Dr",
    "sg:city":"Colorado Springs",
    "sg:classifiers":[
        {
            "category":"Manufacturing",
            "subcategory":"Printing",
            "type":"Manufacturing & Wholesale Goods"
        }
    ],
    "sg:phone":"+1 719 630 7575",
    "sg:postcode":"80906",
    "sg:province":"CO",
    "sg:tags":[
        "commercial"
    ],
    "wof:name":"Act 3 Printing",
    "wof:placetype":"venue"
},
  "geometry": {"coordinates":[-104.812568,38.756368],"type":"Point"}
}