{
  "type": "Feature",
  "properties": {
    "iso:country":"US",
    "sg:address":"8457 S Yosemite St",
    "sg:city":"Lone Tree",
    "sg:classifiers":[
        {
            "category":"Shopping",
            "subcategory":"Clothing, Apparel, & Fashions",
            "type":"Retail Goods"
        }
    ],
    "sg:phone":"+1 303 708 9361",
    "sg:postcode":"80124",
    "sg:province":"CO",
    "sg:tags":[
        "family",
        "store"
    ],
    "wof:name":"Old Navy",
    "wof:placetype":"venue"
},
  "geometry": {"coordinates":[-104.88278800000001,39.563619],"type":"Point"}
}