{
  "type": "Feature",
  "properties": {
    "iso:country":"US",
    "sg:address":"8460 Quigley St",
    "sg:city":"Westminster",
    "sg:classifiers":[
        {
            "category":"Freight",
            "type":"Transportation"
        }
    ],
    "sg:phone":"+1 303 427 9068",
    "sg:postcode":"80031",
    "sg:province":"CO",
    "sg:tags":[
        "trucking"
    ],
    "wof:name":"Richard Leonard Trucking",
    "wof:placetype":"venue"
},
  "geometry": {"coordinates":[-105.045742,39.850117],"type":"Point"}
}