{
  "type": "Feature",
  "properties": {
    "iso:country":"US",
    "sg:address":"2975 S Xanthia Ct",
    "sg:city":"Denver",
    "sg:classifiers":[
        {
            "category":"Professional",
            "subcategory":"Accounting & Tax Preparation",
            "type":"Services"
        }
    ],
    "sg:phone":"+1 303 750 5052",
    "sg:postcode":"80231",
    "sg:province":"CO",
    "sg:tags":[
        "accountant"
    ],
    "wof:name":"Catharine S Kolb CPA",
    "wof:placetype":"venue"
},
  "geometry": {"coordinates":[-104.88645699999999,39.664392],"type":"Point"}
}