{
  "type": "Feature",
  "properties": {
    "addr:full":"5947 S Zenobia Ct Littleton CO 80123",
    "addr:housenumber":"5947",
    "addr:postcode":"80123",
    "addr:street":"S Zenobia Ct",
    "iso:country":"US",
    "sg:address":"5947 S Zenobia Ct",
    "sg:city":"Littleton",
    "sg:classifiers":[
        {
            "category":"Building & Trades",
            "subcategory":"Construction",
            "type":"Services"
        }
    ],
    "sg:phone":"+1 303 795 9556",
    "sg:postcode":"80123",
    "sg:province":"CO",
    "sg:tags":[
        "interior",
        "finishing"
    ],
    "wof:name":"Hammel Interiors Inc",
    "wof:placetype":"venue"
},
  "geometry": {"coordinates":[-105.05258000000001,39.608318],"type":"Point"}
}