{
  "type": "Feature",
  "properties": {
    "addr:full":"1444 Stuart St Denver CO 80204",
    "addr:housenumber":"1444",
    "addr:postcode":"80204",
    "addr:street":"Stuart St",
    "iso:country":"US",
    "sg:address":"1444 Stuart St",
    "sg:city":"Denver",
    "sg:classifiers":[
        {
            "category":"Professional",
            "subcategory":"Lawyer & Legal Services",
            "type":"Services"
        }
    ],
    "sg:phone":"+1 303 623 3200",
    "sg:postcode":"80204",
    "sg:province":"CO",
    "wof:name":"Podboy Ronald A Atty",
    "wof:placetype":"venue"
},
  "geometry": {"coordinates":[-105.04299899999999,39.740101],"type":"Point"}
}