{
  "type": "Feature",
  "properties": {
    "addr:full":"90 Health Park Dr Louisville CO 80027",
    "addr:housenumber":"90",
    "addr:postcode":"80027",
    "addr:street":"Health Park Dr",
    "iso:country":"US",
    "sg:address":"90 Health Park Dr",
    "sg:city":"Louisville",
    "sg:classifiers":[
        {
            "category":"Health Services",
            "subcategory":"Doctor",
            "type":"Services"
        }
    ],
    "sg:phone":"+1 303 673 0777",
    "sg:postcode":"80027",
    "sg:province":"CO",
    "sg:tags":[
        "physician",
        "surgeon"
    ],
    "wof:name":"Centennial Valley Women's Clnc",
    "wof:placetype":"venue"
},
  "geometry": {"coordinates":[-105.149502,39.95193],"type":"Point"}
}