{
  "type": "Feature",
  "properties": {
    "addr:full":"13 W Ranch Rd Morrison CO 80465",
    "addr:housenumber":"13",
    "addr:postcode":"80465",
    "addr:street":"W Ranch Rd",
    "iso:country":"US",
    "sg:address":"13 W Ranch Rd",
    "sg:city":"Morrison",
    "sg:classifiers":[
        {
            "category":"Real Estate",
            "subcategory":"Real Estate Operator",
            "type":"Services"
        }
    ],
    "sg:phone":"+1 303 697 5541",
    "sg:postcode":"80465",
    "sg:province":"CO",
    "sg:tags":[
        "mobile",
        "home",
        "park"
    ],
    "wof:name":"Friendly Vlg Indian Oaks LLC",
    "wof:placetype":"venue"
},
  "geometry": {"coordinates":[-105.195015,39.573223],"type":"Point"}
}