{
  "type": "Feature",
  "properties": {
    "addr:full":"78415 Us Highway 40 Winter Park CO 80482",
    "addr:postcode":"78415;80482",
    "addr:street":"Us Highway 40;Park",
    "iso:country":"US",
    "sg:address":"78415 Us Highway 40",
    "sg:city":"Winter Park",
    "sg:classifiers":[
        {
            "category":"Restaurant",
            "type":"Food & Drink"
        }
    ],
    "sg:menulink":"http://www.allmenus.com/co/granby/276157-mirasol-cantina/menu/",
    "sg:phone":"+1 970 726 0280",
    "sg:postcode":"80482",
    "sg:province":"CO",
    "sg:tags":[
        "mexican"
    ],
    "wof:name":"Mirasol Cantina",
    "wof:placetype":"venue"
},
  "geometry": {"coordinates":[-105.78742200000001,39.925579],"type":"Point"}
}