{
  "type": "Feature",
  "properties": {
    "addr:full":"517 W 5th St Pueblo CO 81003",
    "addr:housenumber":"517",
    "addr:postcode":"81003",
    "addr:street":"W 5Th St",
    "iso:country":"US",
    "sg:address":"517 W 5th St",
    "sg:city":"Pueblo",
    "sg:classifiers":[
        {
            "category":"Health Services",
            "subcategory":"Doctor",
            "type":"Services"
        }
    ],
    "sg:phone":"+1 719 545 1607",
    "sg:postcode":"81003",
    "sg:province":"CO",
    "sg:tags":[
        "clinic"
    ],
    "wof:name":"Pueblo Vascular Diagnostics",
    "wof:placetype":"venue"
},
  "geometry": {"coordinates":[-104.614425,38.271587],"type":"Point"}
}