{
  "type": "Feature",
  "properties": {
    "addr:full":"7801 SW Frontage Rd Fort Collins CO 80528",
    "addr:housenumber":"7801",
    "addr:postcode":"80528",
    "addr:street":"Sw Frontage Rd",
    "iso:country":"US",
    "sg:address":"7801 SW Frontage Rd",
    "sg:city":"Fort Collins",
    "sg:classifiers":[
        {
            "category":"Retail",
            "subcategory":"Veterinary Services",
            "type":"Services"
        },
        {
            "category":"Health Services",
            "subcategory":"Health Practitioner",
            "type":"Services"
        }
    ],
    "sg:phone":"+1 970 204 1663",
    "sg:postcode":"80528",
    "sg:province":"CO",
    "sg:tags":[
        "veterinarian"
    ],
    "wof:name":"Fossil Creek Veterinary Clinic",
    "wof:placetype":"venue"
},
  "geometry": {"coordinates":[-104.992335,40.473334],"type":"Point"}
}