{
  "type": "Feature",
  "properties": {
    "iso:country":"US",
    "sg:address":"46501 Co Rd Q",
    "sg:city":"Yuma",
    "sg:classifiers":[
        {
            "category":"Real Estate",
            "subcategory":"Real Estate Agent",
            "type":"Services"
        }
    ],
    "sg:phone":"+1 970 848 4155",
    "sg:postcode":"80759",
    "sg:province":"CO",
    "sg:tags":[
        "cooperative"
    ],
    "wof:name":"Alliance Farms Co-Op Assoc",
    "wof:placetype":"venue"
},
  "geometry": {"coordinates":[-102.54737900000001,40.249915],"type":"Point"}
}