{
  "type": "Feature",
  "properties": {
    "iso:country":"US",
    "sg:address":"407 S Tejon St",
    "sg:city":"Colorado Springs",
    "sg:classifiers":[
        {
            "category":"Social Services",
            "type":"Services"
        }
    ],
    "sg:phone":"+1 719 471 4265",
    "sg:postcode":"80903",
    "sg:province":"CO",
    "sg:tags":[
        "counselor",
        "marriage",
        "family"
    ],
    "wof:name":"Lifeline Education & Cnslng",
    "wof:placetype":"venue"
},
  "geometry": {"coordinates":[-104.823804,38.826941],"type":"Point"}
}