{
  "type": "Feature",
  "properties": {
    "iso:country":"US",
    "sg:address":"6834 S University Blvd",
    "sg:city":"Littleton",
    "sg:classifiers":[
        {
            "category":"Banks & Credit Unions",
            "subcategory":"Financial Services",
            "type":"Services"
        }
    ],
    "sg:phone":"+1 303 312 1421",
    "sg:postcode":"80122",
    "sg:province":"CO",
    "sg:tags":[
        "company",
        "holding"
    ],
    "wof:name":"Merritt Raechel Inc",
    "wof:placetype":"venue"
},
  "geometry": {"coordinates":[-104.960075,39.593925],"type":"Point"}
}