{
  "type": "Feature",
  "properties": {
    "iso:country":"US",
    "sg:address":"1733 Boulder St",
    "sg:city":"Denver",
    "sg:classifiers":[
        {
            "category":"Professional",
            "type":"Services"
        }
    ],
    "sg:phone":"+1 303 458 6156",
    "sg:postcode":"80211",
    "sg:province":"CO",
    "sg:tags":[
        "establishment"
    ],
    "wof:name":"Gandalf & Assoc",
    "wof:placetype":"venue"
},
  "geometry": {"coordinates":[-105.0085,39.760865],"type":"Point"}
}