{
  "type": "Feature",
  "properties": {
    "addr:full":"5860 S Zante Way Aurora CO 80015",
    "addr:housenumber":"5860",
    "addr:postcode":"80015",
    "addr:street":"S Zante Way",
    "iso:country":"US",
    "sg:address":"5860 S Zante Way",
    "sg:city":"Aurora",
    "sg:classifiers":[
        {
            "category":"Manufacturing",
            "subcategory":"Chemicals & Compounds",
            "type":"Manufacturing & Wholesale Goods"
        }
    ],
    "sg:phone":"+1 303 400 9287",
    "sg:postcode":"80015",
    "sg:province":"CO",
    "sg:tags":[
        "mfg"
    ],
    "wof:name":"Expert Glass Cleaning",
    "wof:placetype":"venue"
},
  "geometry": {"coordinates":[-104.717432,39.609377],"type":"Point"}
}