{
  "type": "Feature",
  "properties": {
    "addr:full":"2950 E Harmony Rd Fort Collins CO 80528",
    "addr:housenumber":"2950",
    "addr:postcode":"80528",
    "addr:street":"E Harmony Rd",
    "iso:country":"US",
    "sg:address":"2950 E Harmony Rd",
    "sg:city":"Fort Collins",
    "sg:classifiers":[
        {
            "category":"Professional",
            "type":"Services"
        }
    ],
    "sg:phone":"+1 970 223 5100",
    "sg:postcode":"80528",
    "sg:province":"CO",
    "sg:tags":[
        "establishment"
    ],
    "wof:name":"L S I Logic",
    "wof:placetype":"venue"
},
  "geometry": {"coordinates":[-105.020877,40.523477],"type":"Point"}
}