{
  "type": "Feature",
  "properties": {
    "iso:country":"US",
    "sg:address":"6315 Peerless Farms Rd",
    "sg:city":"Peyton",
    "sg:classifiers":[
        {
            "category":"Building & Trades",
            "subcategory":"Construction",
            "type":"Services"
        }
    ],
    "sg:phone":"+1 719 683 4560",
    "sg:postcode":"80831",
    "sg:province":"CO",
    "wof:name":"B & C Grading",
    "wof:placetype":"venue"
},
  "geometry": {"coordinates":[-104.507053,38.922617],"type":"Point"}
}