{
  "type": "Feature",
  "properties": {
    "addr:full":"600 Hunt Ave Alamosa CO 81101",
    "addr:housenumber":"600",
    "addr:postcode":"81101",
    "addr:street":"Hunt Ave",
    "iso:country":"US",
    "sg:address":"600 Hunt Ave",
    "sg:city":"Alamosa",
    "sg:classifiers":[
        {
            "category":"Professional",
            "type":"Services"
        }
    ],
    "sg:phone":"+1 719 589 2470",
    "sg:postcode":"81101",
    "sg:province":"CO",
    "wof:name":"Gala",
    "wof:placetype":"venue"
},
  "geometry": {"coordinates":[-105.86381900000001,37.467099],"type":"Point"}
}