{
  "type": "Feature",
  "properties": {
    "addr:full":"1015 4th St Alamosa CO 81101",
    "addr:housenumber":"1015",
    "addr:postcode":"81101",
    "addr:street":"4Th St",
    "iso:country":"US",
    "sg:address":"1015 4th St",
    "sg:city":"Alamosa",
    "sg:classifiers":[
        {
            "category":"Social Services",
            "type":"Services"
        }
    ],
    "sg:phone":"+1 719 587 5670",
    "sg:postcode":"81101",
    "sg:province":"CO",
    "sg:tags":[
        "organization",
        "welfare"
    ],
    "wof:name":"Southern Colorado Aids Project",
    "wof:placetype":"venue"
},
  "geometry": {"coordinates":[-105.872755,37.469356],"type":"Point"}
}