{
  "type": "Feature",
  "properties": {
    "iso:country":"US",
    "sg:address":"12460 1st St",
    "sg:city":"Northglenn",
    "sg:classifiers":[
        {
            "category":"Real Estate",
            "subcategory":"Developer",
            "type":"Services"
        }
    ],
    "sg:phone":"+1 303 457 2966",
    "sg:postcode":"80241",
    "sg:province":"CO",
    "wof:name":"Carlson Associates Inc",
    "wof:placetype":"venue"
},
  "geometry": {"coordinates":[-104.961609,39.922973],"type":"Point"}
}