{
  "type": "Feature",
  "properties": {
    "addr:full":"1000 E Lincoln Ave Fort Collins CO 80524",
    "addr:housenumber":"1000",
    "addr:postcode":"80524",
    "addr:street":"E Lincoln Ave",
    "iso:country":"US",
    "sg:address":"1000 E Lincoln Ave",
    "sg:city":"Fort Collins",
    "sg:classifiers":[
        {
            "category":"Freight",
            "type":"Transportation"
        }
    ],
    "sg:phone":"+1 970 493 8313",
    "sg:postcode":"80524",
    "sg:province":"CO",
    "sg:tags":[
        "commercial",
        "storage"
    ],
    "wof:name":"A-1 U Store-It Warehouses",
    "wof:placetype":"venue"
},
  "geometry": {"coordinates":[-105.062428,40.588859],"type":"Point"}
}