{
  "type": "Feature",
  "properties": {
    "iso:country":"US",
    "sg:address":"8 Inverness Dr E",
    "sg:city":"Englewood",
    "sg:classifiers":[
        {
            "category":"Banks & Credit Unions",
            "subcategory":"Bank",
            "type":"Services"
        }
    ],
    "sg:phone":"+1 303 840 3419",
    "sg:postcode":"80112",
    "sg:province":"CO",
    "sg:tags":[
        "mortgage",
        "loan",
        "broker",
        "real estate"
    ],
    "wof:name":"First Source Funding Inc",
    "wof:placetype":"venue"
},
  "geometry": {"coordinates":[-104.86543,39.566668],"type":"Point"}
}