{
  "type": "Feature",
  "properties": {
    "iso:country":"US",
    "sg:address":"2401 15th St Ste 150",
    "sg:city":"Denver",
    "sg:classifiers":[
        {
            "category":"Education",
            "subcategory":"Special Training",
            "type":"Public Place"
        }
    ],
    "sg:phone":"+1 888 948 4949",
    "sg:postcode":"80202",
    "sg:province":"CO",
    "sg:tags":[
        "educational"
    ],
    "sg:website":"www.firstnetlearning.com",
    "wof:name":"FirstNet Learning",
    "wof:placetype":"venue"
},
  "geometry": {"coordinates":[-105.009006,39.756814],"type":"Point"}
}