{
  "type": "Feature",
  "properties": {
    "iso:country":"US",
    "sg:address":"1116 Columbia Dr",
    "sg:city":"Longmont",
    "sg:classifiers":[
        {
            "category":"Professional",
            "subcategory":"Management & Consulting",
            "type":"Services"
        }
    ],
    "sg:phone":"+1 303 651 1811",
    "sg:postcode":"80503",
    "sg:province":"CO",
    "sg:tags":[
        "fuel"
    ],
    "wof:name":"Butcher Management Co",
    "wof:placetype":"venue"
},
  "geometry": {"coordinates":[-105.15288099999999,40.177757],"type":"Point"}
}