{
  "type": "Feature",
  "properties": {
    "iso:country":"US",
    "sg:address":"206 Platte St",
    "sg:city":"Sterling",
    "sg:classifiers":[
        {
            "category":"Shopping",
            "subcategory":"Catalog Store",
            "type":"Retail Goods"
        }
    ],
    "sg:phone":"+1 970 522 2916",
    "sg:postcode":"80751",
    "sg:province":"CO",
    "sg:tags":[
        "mail",
        "house"
    ],
    "wof:name":"Crazed",
    "wof:placetype":"venue"
},
  "geometry": {"coordinates":[-103.21342799999999,40.628167],"type":"Point"}
}