{
  "type": "Feature",
  "properties": {
    "iso:country":"US",
    "sg:address":"8101 Ralston Rd",
    "sg:city":"Arvada",
    "sg:classifiers":[
        {
            "category":"Government",
            "subcategory":"Office",
            "type":"Public Place"
        }
    ],
    "sg:phone":"+1 720 898 7465",
    "sg:postcode":"80002",
    "sg:province":"CO",
    "sg:tags":[
        "village"
    ],
    "wof:name":"Arvada Code Enforcement",
    "wof:placetype":"venue"
},
  "geometry": {"coordinates":[-105.088774,39.802028],"type":"Point"}
}