{
  "type": "Feature",
  "properties": {
    "iso:country":"US",
    "sg:address":"395 Dawson Ct",
    "sg:city":"Castle Rock",
    "sg:classifiers":[
        {
            "category":"Building & Trades",
            "subcategory":"Construction",
            "type":"Services"
        }
    ],
    "sg:phone":"+1 303 660 1515",
    "sg:postcode":"80104",
    "sg:province":"CO",
    "sg:tags":[
        "repairing",
        "remodeling",
        "contractor"
    ],
    "wof:name":"Meier Construction & Engineer",
    "wof:placetype":"venue"
},
  "geometry": {"coordinates":[-104.84020700000001,39.373285],"type":"Point"}
}