{
  "type": "Feature",
  "properties": {
    "iso:country":"US",
    "sg:address":"3531 Terry Point Dr",
    "sg:city":"Fort Collins",
    "sg:classifiers":[
        {
            "category":"Shopping",
            "type":"Retail Goods"
        },
        {
            "category":"Shopping",
            "subcategory":"Gifts & Souvenirs",
            "type":"Retail Goods"
        }
    ],
    "sg:phone":"+1 970 224 4945",
    "sg:postcode":"80524",
    "sg:province":"CO",
    "sg:tags":[
        "collectible",
        "merchandise"
    ],
    "wof:name":"Coop's Collectibles",
    "wof:placetype":"venue"
},
  "geometry": {"coordinates":[-105.0829,40.639029],"type":"Point"}
}