{
  "type": "Feature",
  "properties": {
    "addr:full":"13850 Co Rd 13 Weston CO 81091",
    "addr:housenumber":"13850;13",
    "addr:postcode":"81091",
    "addr:street":"Co Rd",
    "iso:country":"US",
    "sg:address":"13850 Co Rd 13",
    "sg:city":"Weston",
    "sg:classifiers":[
        {
            "category":"Farming",
            "subcategory":"Livestock Farm",
            "type":"Manufacturing & Wholesale Goods"
        }
    ],
    "sg:phone":"+1 719 868 2235",
    "sg:postcode":"81091",
    "sg:province":"CO",
    "sg:tags":[
        "feedlot",
        "field",
        "crop",
        "beef",
        "cattle"
    ],
    "wof:name":"Whiskey Creek Ranch Ltd",
    "wof:placetype":"venue"
},
  "geometry": {"coordinates":[-105.02689599999999,37.185428],"type":"Point"}
}