{
  "type": "Feature",
  "properties": {
    "iso:country":"US",
    "sg:address":"9380 Desert Willow Rd",
    "sg:city":"Littleton",
    "sg:classifiers":[
        {
            "category":"Shopping",
            "type":"Retail Goods"
        }
    ],
    "sg:phone":"+1 303 471 5400",
    "sg:postcode":"80129",
    "sg:province":"CO",
    "sg:tags":[
        "technical",
        "product",
        "outdoor"
    ],
    "wof:name":"Fresh Tracks Map Store LLC",
    "wof:placetype":"venue"
},
  "geometry": {"coordinates":[-105.011467,39.547471],"type":"Point"}
}