{
  "type": "Feature",
  "properties": {
    "addr:full":"4485 Wadsworth Boulevard Wheat Ridge CO 80033",
    "addr:housenumber":"4485",
    "addr:postcode":"80033",
    "addr:street":"Wadsworth Boulevard",
    "iso:country":"US",
    "sg:address":"4485 Wadsworth Boulevard",
    "sg:city":"Wheat Ridge",
    "sg:classifiers":[
        {
            "category":"Health Services",
            "subcategory":"Doctor",
            "type":"Services"
        }
    ],
    "sg:phone":"+1 303 421 0194",
    "sg:postcode":"80033",
    "sg:province":"CO",
    "wof:name":"Fleischaker G H Pediatrics",
    "wof:placetype":"venue"
},
  "geometry": {"coordinates":[-105.081445,39.778043],"type":"Point"}
}