{
  "type": "Feature",
  "properties": {
    "addr:full":"12400 Hwy 145 Dolores CO 81323",
    "addr:housenumber":"12400",
    "addr:postcode":"81323",
    "addr:street":"Hwy 145",
    "iso:country":"US",
    "sg:address":"12400 Hwy 145",
    "sg:city":"Dolores",
    "sg:classifiers":[
        {
            "category":"Shopping",
            "subcategory":"Used Merchandise",
            "type":"Retail Goods"
        }
    ],
    "sg:phone":"+1 970 565 3311",
    "sg:postcode":"81323",
    "sg:province":"CO",
    "sg:tags":[
        "book",
        "rare",
        "dealer"
    ],
    "wof:name":"Prairie Dog Hardback",
    "wof:placetype":"venue"
},
  "geometry": {"coordinates":[-108.554519,37.390834],"type":"Point"}
}