{
  "type": "Feature",
  "properties": {
    "iso:country":"US",
    "sg:address":"15200 E 6th Ave",
    "sg:city":"Aurora",
    "sg:classifiers":[
        {
            "category":"Health Services",
            "subcategory":"Health Practitioner",
            "type":"Services"
        }
    ],
    "sg:phone":"+1 720 857 7662",
    "sg:postcode":"80011",
    "sg:province":"CO",
    "sg:tags":[
        "therapist",
        "physical"
    ],
    "wof:name":"Rocky Mountain Medical Ctr",
    "wof:placetype":"venue"
},
  "geometry": {"coordinates":[-104.81108999999999,39.725537],"type":"Point"}
}