{
  "type": "Feature",
  "properties": {
    "iso:country":"US",
    "sg:address":"550 Lipan St",
    "sg:city":"Denver",
    "sg:classifiers":[
        {
            "category":"Building & Trades",
            "subcategory":"Locksmith",
            "type":"Services"
        }
    ],
    "sg:phone":"+1 866 717 3805",
    "sg:postcode":"80204",
    "sg:province":"CO",
    "sg:tags":[
        "key"
    ],
    "wof:name":"1 24 7 Available Emergency Locksmith",
    "wof:placetype":"venue"
},
  "geometry": {"coordinates":[-105.001392,39.724914],"type":"Point"}
}