{
  "type": "Feature",
  "properties": {
    "iso:country":"US",
    "sg:address":"2091 E 74th Ave",
    "sg:city":"Denver",
    "sg:classifiers":[
        {
            "category":"Building & Trades",
            "subcategory":"Construction",
            "type":"Services"
        }
    ],
    "sg:phone":"+1 303 280 5892",
    "sg:postcode":"80229",
    "sg:province":"CO",
    "sg:tags":[
        "resurfacing",
        "laying",
        "refinishing",
        "floor"
    ],
    "wof:name":"Morris Floor Coverings",
    "wof:placetype":"venue"
},
  "geometry": {"coordinates":[-104.960229,39.830951],"type":"Point"}
}