{
  "type": "Feature",
  "properties": {
    "addr:full":"3256 Tessman Rd Delta CO 81416",
    "addr:housenumber":"3256",
    "addr:postcode":"81416",
    "addr:street":"Tessman Rd",
    "iso:country":"US",
    "sg:address":"3256 Tessman Rd",
    "sg:city":"Delta",
    "sg:classifiers":[
        {
            "category":"Manufacturing",
            "subcategory":"Signs",
            "type":"Manufacturing & Wholesale Goods"
        }
    ],
    "sg:phone":"+1 970 874 9708",
    "sg:postcode":"81416",
    "sg:province":"CO",
    "sg:tags":[
        "specialty",
        "mfg"
    ],
    "wof:name":"Kp & Co",
    "wof:placetype":"venue"
},
  "geometry": {"coordinates":[-108.06448399999999,38.700927],"type":"Point"}
}