{
  "type": "Feature",
  "properties": {
    "addr:full":"3980 Cambridge Ave Broomfield CO 80020",
    "addr:housenumber":"3980",
    "addr:postcode":"80020",
    "addr:street":"Cambridge Ave",
    "iso:country":"US",
    "sg:address":"3980 Cambridge Ave",
    "sg:city":"Broomfield",
    "sg:classifiers":[
        {
            "category":"Manufacturing",
            "subcategory":"Printing",
            "type":"Manufacturing & Wholesale Goods"
        }
    ],
    "sg:phone":"+1 720 887 6230",
    "sg:postcode":"80020",
    "sg:province":"CO",
    "sg:tags":[
        "multimedia"
    ],
    "wof:name":"A C Nielsen Media Research",
    "wof:placetype":"venue"
},
  "geometry": {"coordinates":[-105.03929100000001,39.927583],"type":"Point"}
}