{
  "type": "Feature",
  "properties": {
    "addr:full":"414 E 3rd Ave Durango CO 81301",
    "addr:housenumber":"414",
    "addr:postcode":"co 81301",
    "addr:street":"E 3Rd Ave",
    "iso:country":"US",
    "sg:address":"414 E 3rd Ave",
    "sg:city":"Durango",
    "sg:classifiers":[
        {
            "category":"Social Services",
            "type":"Services"
        }
    ],
    "sg:phone":"+1 970 560 2027",
    "sg:postcode":"81301",
    "sg:province":"CO",
    "sg:tags":[
        "information",
        "planning",
        "center",
        "family"
    ],
    "wof:name":"Four Corners Fertilitycare Ctr",
    "wof:placetype":"venue"
},
  "geometry": {"coordinates":[-107.87934,37.268334],"type":"Point"}
}