{
  "type": "Feature",
  "properties": {
    "addr:full":"112 W 5th St Walsenburg CO 81089",
    "addr:housenumber":"112",
    "addr:postcode":"81089",
    "addr:street":"W 5Th St",
    "iso:country":"US",
    "sg:address":"112 W 5th St",
    "sg:city":"Walsenburg",
    "sg:classifiers":[
        {
            "category":"Museum",
            "type":"Entertainment"
        }
    ],
    "sg:phone":"+1 719 738 1992",
    "sg:postcode":"81089",
    "sg:province":"CO",
    "wof:name":"Walsenburg Mining Museum",
    "wof:placetype":"venue"
},
  "geometry": {"coordinates":[-104.78157899999999,37.624657],"type":"Point"}
}