{
  "type": "Feature",
  "properties": {
    "addr:full":"14 Southgate Center Colorado Springs CO 80906",
    "addr:housenumber":"14",
    "addr:postcode":"80906",
    "addr:street":"Southgate Center",
    "iso:country":"US",
    "sg:address":"14 Southgate Center",
    "sg:city":"Colorado Springs",
    "sg:classifiers":[
        {
            "category":"Shopping",
            "type":"Retail Goods"
        }
    ],
    "sg:phone":"+1 719 471 1888",
    "sg:postcode":"80906",
    "sg:province":"CO",
    "sg:tags":[
        "pet",
        "store"
    ],
    "wof:name":"Pet City",
    "wof:placetype":"venue"
},
  "geometry": {"coordinates":[-104.820013,38.805402],"type":"Point"}
}