{
  "type": "Feature",
  "properties": {
    "iso:country":"US",
    "sg:address":"501 Chipeta Dr",
    "sg:city":"Ridgway",
    "sg:classifiers":[
        {
            "category":"Building & Trades",
            "subcategory":"Construction",
            "type":"Services"
        }
    ],
    "sg:phone":"+1 970 626 4047",
    "sg:postcode":"81432",
    "sg:province":"CO",
    "sg:tags":[
        "contractor"
    ],
    "wof:name":"Premier Tile Marble",
    "wof:placetype":"venue"
},
  "geometry": {"coordinates":[-107.75762,38.14852],"type":"Point"}
}