{
  "type": "Feature",
  "properties": {
    "addr:full":"25135 Co Rd P Dolores CO 81323",
    "addr:housenumber":"25135",
    "addr:postcode":"81323",
    "addr:street":"Co Rd",
    "iso:country":"US",
    "sg:address":"25135 Co Rd P",
    "sg:city":"Dolores",
    "sg:classifiers":[
        {
            "category":"Building & Trades",
            "subcategory":"Plumbing",
            "type":"Services"
        }
    ],
    "sg:phone":"+1 970 565 7794",
    "sg:postcode":"81323",
    "sg:province":"CO",
    "sg:tags":[
        "contractor"
    ],
    "wof:name":"Cortez Plumbing & Heating",
    "wof:placetype":"venue"
},
  "geometry": {"coordinates":[-108.588452,37.417415],"type":"Point"}
}