{
  "type": "Feature",
  "properties": {
    "iso:country":"US",
    "sg:address":"7076 S Alton Way",
    "sg:city":"Centennial",
    "sg:classifiers":[
        {
            "category":"Building & Trades",
            "subcategory":"Construction",
            "type":"Services"
        }
    ],
    "sg:phone":"+1 303 226 4098",
    "sg:postcode":"80112",
    "sg:province":"CO",
    "sg:tags":[
        "steel",
        "e",
        "nonresidential",
        "general",
        "erectors",
        "build"
    ],
    "wof:name":"Colorado Steel Systems Inc",
    "wof:placetype":"venue"
},
  "geometry": {"coordinates":[-104.882966,39.58346],"type":"Point"}
}