{
  "type": "Feature",
  "properties": {
    "addr:full":"2090 E 104th Ave Thornton CO 80233",
    "addr:housenumber":"2090",
    "addr:postcode":"80233",
    "addr:street":"E 104Th Ave",
    "iso:country":"US",
    "sg:address":"2090 E 104th Ave",
    "sg:city":"Thornton",
    "sg:classifiers":[
        {
            "category":"Manufacturing",
            "subcategory":"Printing",
            "type":"Manufacturing & Wholesale Goods"
        }
    ],
    "sg:phone":"+1 303 450 0878",
    "sg:postcode":"80233",
    "sg:province":"CO",
    "sg:tags":[
        "multimedia"
    ],
    "wof:name":"Myenetworks Media Solutions",
    "wof:placetype":"venue"
},
  "geometry": {"coordinates":[-104.960131,39.884885],"type":"Point"}
}