{
  "type": "Feature",
  "properties": {
    "iso:country":"US",
    "sg:address":"3440 Hill Cir",
    "sg:city":"Colorado Springs",
    "sg:classifiers":[
        {
            "category":"Professional",
            "type":"Services"
        }
    ],
    "sg:phone":"+1 719 630 7777",
    "sg:postcode":"80904",
    "sg:province":"CO",
    "sg:tags":[
        "establishment"
    ],
    "wof:name":"Villa Vedado",
    "wof:placetype":"venue"
},
  "geometry": {"coordinates":[-104.871831,38.888321],"type":"Point"}
}