{
  "type": "Feature",
  "properties": {
    "iso:country":"US",
    "sg:address":"1815 Yorktown Ave",
    "sg:city":"Fort Collins",
    "sg:classifiers":[
        {
            "category":"Social Services",
            "subcategory":"Child Care",
            "type":"Services"
        }
    ],
    "sg:phone":"+1 970 498 9409",
    "sg:postcode":"80526",
    "sg:province":"CO",
    "sg:website":"www.hopechildrenscenter.org",
    "wof:name":"Hope Infant & Childrens Ctr",
    "wof:placetype":"venue"
},
  "geometry": {"coordinates":[-105.110889,40.553466],"type":"Point"}
}