{
  "type": "Feature",
  "properties": {
    "iso:country":"US",
    "sg:address":"3243 Simms St",
    "sg:city":"Wheat Ridge",
    "sg:classifiers":[
        {
            "category":"Freight",
            "type":"Transportation"
        }
    ],
    "sg:phone":"+1 303 232 3333",
    "sg:postcode":"80033",
    "sg:province":"CO",
    "sg:tags":[
        "export",
        "broker"
    ],
    "wof:name":"Hanninpex",
    "wof:placetype":"venue"
},
  "geometry": {"coordinates":[-105.128552,39.764389],"type":"Point"}
}