{
  "type": "Feature",
  "properties": {
    "iso:country":"US",
    "sg:address":"3660 Wadsworth Boulevard",
    "sg:city":"Wheat Ridge",
    "sg:classifiers":[
        {
            "category":"Shopping",
            "subcategory":"Pharmacy",
            "type":"Retail Goods"
        }
    ],
    "sg:phone":"+1 303 463 4875",
    "sg:postcode":"80033",
    "sg:province":"CO",
    "sg:tags":[
        "drugstore"
    ],
    "sg:website":"www.rxplus.com",
    "wof:name":"Rx Plus Pharmacies",
    "wof:placetype":"venue"
},
  "geometry": {"coordinates":[-105.08130300000001,39.767572],"type":"Point"}
}