{
  "type": "Feature",
  "properties": {
    "addr:full":"8544 E Geddes Pl Centennial CO 80112",
    "addr:housenumber":"8544",
    "addr:postcode":"80112",
    "addr:street":"E Geddes Pl",
    "iso:country":"US",
    "sg:address":"8544 E Geddes Pl",
    "sg:city":"Centennial",
    "sg:classifiers":[
        {
            "category":"Professional",
            "subcategory":"Lawyer & Legal Services",
            "type":"Services"
        }
    ],
    "sg:phone":"+1 303 221 3719",
    "sg:postcode":"80112",
    "sg:province":"CO",
    "sg:tags":[
        "attorney"
    ],
    "wof:name":"Richard D Crabtree",
    "wof:placetype":"venue"
},
  "geometry": {"coordinates":[-104.890004,39.583666],"type":"Point"}
}