{
  "type": "Feature",
  "properties": {
    "addr:full":"2525 Miller St Denver CO 80215",
    "addr:housenumber":"2525",
    "addr:postcode":"80215",
    "addr:street":"Miller St",
    "iso:country":"US",
    "sg:address":"2525 Miller St",
    "sg:city":"Denver",
    "sg:classifiers":[
        {
            "category":"Building & Trades",
            "subcategory":"Construction",
            "type":"Services"
        }
    ],
    "sg:phone":"+1 303 279 1117",
    "sg:postcode":"80215",
    "sg:province":"CO",
    "sg:tags":[
        "residential",
        "industrial"
    ],
    "wof:name":"Applewood Contracting",
    "wof:placetype":"venue"
},
  "geometry": {"coordinates":[-105.114383,39.754213],"type":"Point"}
}