{
  "type": "Feature",
  "properties": {
    "addr:full":"2522 S Olathe Way Aurora CO 80013",
    "addr:housenumber":"2522",
    "addr:postcode":"80013",
    "addr:street":"S Olathe Way",
    "iso:country":"US",
    "sg:address":"2522 S Olathe Way",
    "sg:city":"Aurora",
    "sg:classifiers":[
        {
            "category":"Train Station",
            "subcategory":"Light Rail",
            "type":"Transportation"
        }
    ],
    "sg:phone":"+1 303 994 0116",
    "sg:postcode":"80013",
    "sg:province":"CO",
    "sg:tags":[
        "signal"
    ],
    "wof:name":"Ultra Tech Systems",
    "wof:placetype":"venue"
},
  "geometry": {"coordinates":[-104.794105,39.671383],"type":"Point"}
}