{
  "type": "Feature",
  "properties": {
    "addr:full":"3900 E Arapahoe Rd Littleton CO 80122",
    "addr:housenumber":"3900",
    "addr:postcode":"80122",
    "addr:street":"E Arapahoe Rd",
    "iso:country":"US",
    "sg:address":"3900 E Arapahoe Rd",
    "sg:city":"Littleton",
    "sg:classifiers":[
        {
            "category":"Professional",
            "type":"Services"
        }
    ],
    "sg:phone":"+1 303 694 6132",
    "sg:postcode":"80122",
    "sg:province":"CO",
    "sg:tags":[
        "establishment"
    ],
    "wof:name":"Solid Rock Enrichment Inc",
    "wof:placetype":"venue"
},
  "geometry": {"coordinates":[-104.941407,39.595172],"type":"Point"}
}