{
  "type": "Feature",
  "properties": {
    "iso:country":"US",
    "sg:address":"241 Broadway St",
    "sg:city":"Eagle",
    "sg:classifiers":[
        {
            "category":"Bars & Pubs",
            "type":"Food & Drink"
        }
    ],
    "sg:phone":"+1 970 328 5279",
    "sg:postcode":"81631",
    "sg:province":"CO",
    "wof:name":"Brush Creek Saloon",
    "wof:placetype":"venue"
},
  "geometry": {"coordinates":[-106.82792499999999,39.654823],"type":"Point"}
}