{
  "type": "Feature",
  "properties": {
    "iso:country":"US",
    "sg:address":"3530 Milwaukee St",
    "sg:city":"Denver",
    "sg:classifiers":[
        {
            "category":"Building & Trades",
            "subcategory":"Construction",
            "type":"Services"
        }
    ],
    "sg:phone":"+1 303 296 8931",
    "sg:postcode":"80205",
    "sg:province":"CO",
    "sg:tags":[
        "house"
    ],
    "wof:name":"T&J Construction LLC",
    "wof:placetype":"venue"
},
  "geometry": {"coordinates":[-104.95233399999999,39.766545],"type":"Point"}
}