{
  "type": "Feature",
  "properties": {
    "iso:country":"US",
    "sg:address":"14853 E Radcliff Pl",
    "sg:city":"Aurora",
    "sg:classifiers":[
        {
            "category":"Professional",
            "type":"Services"
        }
    ],
    "sg:phone":"+1 303 690 4228",
    "sg:postcode":"80015",
    "sg:province":"CO",
    "wof:name":"C B I LLC",
    "wof:placetype":"venue"
},
  "geometry": {"coordinates":[-104.814894,39.636029],"type":"Point"}
}