{
  "type": "Feature",
  "properties": {
    "addr:full":"3440 S Brady Ct Englewood CO 80110",
    "addr:housenumber":"3440",
    "addr:postcode":"80110",
    "addr:street":"S Brady Ct",
    "iso:country":"US",
    "sg:address":"3440 S Brady Ct",
    "sg:city":"Englewood",
    "sg:classifiers":[
        {
            "category":"Personal",
            "subcategory":"Tattoo Parlor",
            "type":"Services"
        },
        {
            "category":"Personal",
            "subcategory":"Piercing",
            "type":"Services"
        }
    ],
    "sg:phone":"+1 303 607 9252",
    "sg:postcode":"80110",
    "sg:province":"CO",
    "sg:tags":[
        "body"
    ],
    "wof:name":"Remis Tattoo",
    "wof:placetype":"venue"
},
  "geometry": {"coordinates":[-105.013784,39.654301],"type":"Point"}
}