{
  "type": "Feature",
  "properties": {
    "addr:full":"231 S Market St Cortez CO 81321",
    "addr:housenumber":"231",
    "addr:postcode":"81321",
    "addr:street":"S Market St",
    "iso:country":"US",
    "sg:address":"231 S Market St",
    "sg:city":"Cortez",
    "sg:classifiers":[
        {
            "category":"Wholesale",
            "subcategory":"Hardware",
            "type":"Manufacturing & Wholesale Goods"
        }
    ],
    "sg:phone":"+1 970 565 7233",
    "sg:postcode":"81321",
    "sg:province":"CO",
    "sg:tags":[
        "refrigerating"
    ],
    "wof:name":"Steve's Commercial Refrig",
    "wof:placetype":"venue"
},
  "geometry": {"coordinates":[-108.585201,37.346196],"type":"Point"}
}