{
  "type": "Feature",
  "properties": {
    "iso:country":"US",
    "sg:address":"17201 W 64th Ave",
    "sg:city":"Arvada",
    "sg:classifiers":[
        {
            "category":"Farming",
            "subcategory":"Nursery",
            "type":"Manufacturing & Wholesale Goods"
        }
    ],
    "sg:phone":"+1 303 420 3343",
    "sg:postcode":"80007",
    "sg:province":"CO",
    "sg:tags":[
        "ornamental",
        "supply"
    ],
    "wof:name":"Veldkamps Wholesale Greenhouse",
    "wof:placetype":"venue"
},
  "geometry": {"coordinates":[-105.1964,39.8127],"type":"Point"}
}