{
  "type": "Feature",
  "properties": {
    "iso:country":"US",
    "sg:address":"3595 Wynkoop Street",
    "sg:city":"Denver",
    "sg:classifiers":[
        {
            "category":"Sports & Exercise",
            "subcategory":"Gym",
            "type":"Entertainment"
        }
    ],
    "sg:phone":"+1 605 639 0302",
    "sg:postcode":"80216",
    "sg:province":"CO",
    "sg:tags":[
        "trainer"
    ],
    "sg:website":"barefootfts.com/",
    "wof:name":"Barefoot Fitness",
    "wof:placetype":"venue"
},
  "geometry": {"coordinates":[-104.97725199999999,39.770584],"type":"Point"}
}