{
  "type": "Feature",
  "properties": {
    "addr:full":"162 E Main St Trinidad CO 81082",
    "addr:housenumber":"162",
    "addr:postcode":"81082",
    "addr:street":"E Main St",
    "iso:country":"US",
    "sg:address":"162 E Main St",
    "sg:city":"Trinidad",
    "sg:classifiers":[
        {
            "category":"Shopping",
            "subcategory":"Used Merchandise",
            "type":"Retail Goods"
        }
    ],
    "sg:phone":"+1 719 846 7224",
    "sg:postcode":"81082",
    "sg:province":"CO",
    "sg:tags":[
        "antique"
    ],
    "wof:name":"Theresa's Antiques & Cllctbls",
    "wof:placetype":"venue"
},
  "geometry": {"coordinates":[-104.505,37.168637],"type":"Point"}
}