{
  "type": "Feature",
  "properties": {
    "addr:full":"9591 E 22nd Ave Aurora CO 80010",
    "addr:housenumber":"9591",
    "addr:postcode":"80010",
    "addr:street":"E 22Nd Ave",
    "iso:country":"US",
    "sg:address":"9591 E 22nd Ave",
    "sg:city":"Aurora",
    "sg:classifiers":[
        {
            "category":"Freight",
            "type":"Transportation"
        }
    ],
    "sg:phone":"+1 303 364 6032",
    "sg:postcode":"80010",
    "sg:province":"CO",
    "sg:tags":[
        "commercial",
        "storage"
    ],
    "wof:name":"Lock-Ur-Own Storage Inc",
    "wof:placetype":"venue"
},
  "geometry": {"coordinates":[-104.87722100000001,39.749354],"type":"Point"}
}