{
  "type": "Feature",
  "properties": {
    "iso:country":"US",
    "sg:address":"4900 S I- 25",
    "sg:city":"Castle Rock",
    "sg:classifiers":[
        {
            "category":"Wholesale",
            "subcategory":"Construction Materials",
            "type":"Manufacturing & Wholesale Goods"
        }
    ],
    "sg:phone":"+1 303 681 2696",
    "sg:postcode":"80104",
    "sg:province":"CO",
    "sg:tags":[
        "sand",
        "gravel"
    ],
    "wof:name":"Castle Rock Rock Inc",
    "wof:placetype":"venue"
},
  "geometry": {"coordinates":[-104.89228199999999,39.295002],"type":"Point"}
}