{
  "type": "Feature",
  "properties": {
    "iso:country":"US",
    "sg:address":"600 17th St",
    "sg:city":"Denver",
    "sg:classifiers":[
        {
            "category":"Professional",
            "subcategory":"Business Services",
            "type":"Services"
        },
        {
            "category":"Wholesale",
            "subcategory":"Electrical",
            "type":"Manufacturing & Wholesale Goods"
        }
    ],
    "sg:phone":"+1 303 909 5314",
    "sg:postcode":"80202",
    "sg:province":"CO",
    "sg:tags":[
        "telecommunication"
    ],
    "wof:name":"Idea! Communications Group Inc",
    "wof:placetype":"venue"
},
  "geometry": {"coordinates":[-104.990966,39.746117],"type":"Point"}
}