{
  "type": "Feature",
  "properties": {
    "iso:country":"US",
    "sg:address":"5757 Arapahoe Ave",
    "sg:city":"Boulder",
    "sg:classifiers":[
        {
            "category":"Autos & Motor Vehicles",
            "subcategory":"Auto Supplies",
            "type":"Retail Goods"
        }
    ],
    "sg:phone":"+1 303 449 5011",
    "sg:postcode":"80303",
    "sg:province":"CO",
    "sg:tags":[
        "equipment",
        "racing",
        "car",
        "automobile"
    ],
    "wof:name":"Logic Imports LLC",
    "wof:placetype":"venue"
},
  "geometry": {"coordinates":[-105.21901699999999,40.014783],"type":"Point"}
}