{
  "type": "Feature",
  "properties": {
    "iso:country":"US",
    "sg:address":"2707 Featherstar Way",
    "sg:city":"Fort Collins",
    "sg:classifiers":[
        {
            "category":"Personal",
            "type":"Services"
        }
    ],
    "sg:phone":"+1 970 204 0283",
    "sg:postcode":"80526",
    "sg:province":"CO",
    "sg:tags":[
        "miscellaneous"
    ],
    "wof:name":"King Enterprises",
    "wof:placetype":"venue"
},
  "geometry": {"coordinates":[-105.119998,40.552058],"type":"Point"}
}