{
  "type": "Feature",
  "properties": {
    "addr:full":"4200 E 128th Ave Thornton CO 80241",
    "addr:housenumber":"4200",
    "addr:postcode":"80241",
    "addr:street":"E 128Th Ave",
    "iso:country":"US",
    "sg:address":"4200 E 128th Ave",
    "sg:city":"Thornton",
    "sg:classifiers":[
        {
            "category":"Social Services",
            "subcategory":"Child Care",
            "type":"Services"
        }
    ],
    "sg:phone":"+1 303 451 5210",
    "sg:postcode":"80241",
    "sg:province":"CO",
    "sg:website":"www.kindercare.com",
    "wof:name":"Kinder Care Learning Ctr",
    "wof:placetype":"venue"
},
  "geometry": {"coordinates":[-104.937496,39.928296],"type":"Point"}
}