{
  "type": "Feature",
  "properties": {
    "addr:full":"400 Palmers Dr Silverthorne CO 80498",
    "addr:housenumber":"400",
    "addr:postcode":"80498",
    "addr:street":"Palmers Dr",
    "iso:country":"US",
    "sg:address":"400 Palmers Dr",
    "sg:city":"Silverthorne",
    "sg:classifiers":[
        {
            "category":"Organizations",
            "subcategory":"Religious Organization",
            "type":"Services"
        }
    ],
    "sg:phone":"+1 970 468 0870",
    "sg:postcode":"80498",
    "sg:province":"CO",
    "sg:tags":[
        "church"
    ],
    "sg:website":"www.abundantlifesilverthorne.com",
    "wof:name":"Abundant Life Church",
    "wof:placetype":"venue"
},
  "geometry": {"coordinates":[-106.071826,39.638875],"type":"Point"}
}