{
  "type": "Feature",
  "properties": {
    "addr:full":"1607 Ridgeway Ave Colorado Springs CO 80906",
    "addr:housenumber":"1607",
    "addr:postcode":"80906",
    "addr:street":"Ridgeway Ave",
    "iso:country":"US",
    "sg:address":"1607 Ridgeway Ave",
    "sg:city":"Colorado Springs",
    "sg:classifiers":[
        {
            "category":"Real Estate",
            "subcategory":"Real Estate Agent",
            "type":"Services"
        }
    ],
    "sg:phone":"+1 719 633 2223",
    "sg:postcode":"80906",
    "sg:province":"CO",
    "sg:website":"www.nakedontv.com",
    "wof:name":"Action Matrix",
    "wof:placetype":"venue"
},
  "geometry": {"coordinates":[-104.85829,38.795035],"type":"Point"}
}