{
  "type": "Feature",
  "properties": {
    "addr:full":"202 W North St Cortez CO 81321",
    "addr:housenumber":"202",
    "addr:postcode":"81321",
    "addr:street":"W North St",
    "iso:country":"US",
    "sg:address":"202 W North St",
    "sg:city":"Cortez",
    "sg:classifiers":[
        {
            "category":"Professional",
            "subcategory":"Lawyer & Legal Services",
            "type":"Services"
        }
    ],
    "sg:phone":"+1 970 565 2455",
    "sg:postcode":"81321",
    "sg:province":"CO",
    "sg:tags":[
        "attorney"
    ],
    "wof:name":"Kim S Shropshire",
    "wof:placetype":"venue"
},
  "geometry": {"coordinates":[-108.589136,37.349728],"type":"Point"}
}