{
  "type": "Feature",
  "properties": {
    "iso:country":"US",
    "sg:address":"4698 S Xavier St",
    "sg:city":"Denver",
    "sg:classifiers":[
        {
            "category":"Building & Trades",
            "subcategory":"Construction",
            "type":"Services"
        }
    ],
    "sg:phone":"+1 303 935 4028",
    "sg:postcode":"80236",
    "sg:province":"CO",
    "sg:tags":[
        "hanging",
        "contractor"
    ],
    "wof:name":"Reeds Painting",
    "wof:placetype":"venue"
},
  "geometry": {"coordinates":[-105.05086799999999,39.63489],"type":"Point"}
}