{
  "type": "Feature",
  "properties": {
    "iso:country":"US",
    "sg:address":"4724 E 127th Dr",
    "sg:city":"Denver",
    "sg:classifiers":[
        {
            "category":"Professional",
            "subcategory":"Engineering",
            "type":"Services"
        }
    ],
    "sg:phone":"+1 303 450 6600",
    "sg:postcode":"80241",
    "sg:province":"CO",
    "sg:tags":[
        "engineer"
    ],
    "wof:name":"CBT Co",
    "wof:placetype":"venue"
},
  "geometry": {"coordinates":[-104.931741,39.926411],"type":"Point"}
}