{
  "type": "Feature",
  "properties": {
    "addr:full":"8109 E 39th Ave Denver CO 80207",
    "addr:housenumber":"8109",
    "addr:postcode":"80207",
    "addr:street":"E 39Th Ave",
    "iso:country":"US",
    "sg:address":"8109 E 39th Ave",
    "sg:city":"Denver",
    "sg:classifiers":[
        {
            "category":"Retail",
            "subcategory":"Auto Repair",
            "type":"Services"
        }
    ],
    "sg:phone":"+1 303 399 5741",
    "sg:postcode":"80207",
    "sg:province":"CO",
    "sg:tags":[
        "engine"
    ],
    "wof:name":"Mitchcon Corp",
    "wof:placetype":"venue"
},
  "geometry": {"coordinates":[-104.890894,39.77141],"type":"Point"}
}