{
  "type": "Feature",
  "properties": {
    "iso:country":"US",
    "sg:address":"1637 Dallas St",
    "sg:city":"Aurora",
    "sg:classifiers":[
        {
            "category":"Building & Trades",
            "subcategory":"Construction",
            "type":"Services"
        }
    ],
    "sg:phone":"+1 303 537 4776",
    "sg:postcode":"80010",
    "sg:province":"CO",
    "sg:tags":[
        "contractor"
    ],
    "wof:name":"Drywall Framing",
    "wof:placetype":"venue"
},
  "geometry": {"coordinates":[-104.876468,39.743115],"type":"Point"}
}