{
  "type": "Feature",
  "properties": {
    "iso:country":"US",
    "sg:address":"6440 Odell Pl",
    "sg:city":"Boulder",
    "sg:classifiers":[
        {
            "category":"Manufacturing",
            "subcategory":"Food",
            "type":"Manufacturing & Wholesale Goods"
        }
    ],
    "sg:phone":"+1 303 516 9031",
    "sg:postcode":"80301",
    "sg:province":"CO",
    "sg:tags":[
        "winery"
    ],
    "wof:name":"Boulder Creek Winery",
    "wof:placetype":"venue"
},
  "geometry": {"coordinates":[-105.202709,40.073546],"type":"Point"}
}