{
  "type": "Feature",
  "properties": {
    "iso:country":"US",
    "sg:address":"205 S Garrison St",
    "sg:city":"Lakewood",
    "sg:classifiers":[
        {
            "category":"Health Services",
            "subcategory":"Doctor",
            "type":"Services"
        }
    ],
    "sg:phone":"+1 303 232 2873",
    "sg:postcode":"80226",
    "sg:province":"CO",
    "sg:tags":[
        "dentist"
    ],
    "wof:name":"Lakewood Dental Assoc",
    "wof:placetype":"venue"
},
  "geometry": {"coordinates":[-105.100279,39.711522],"type":"Point"}
}