{
  "type": "Feature",
  "properties": {
    "addr:full":"315 E 8th Ave Yuma CO 80759",
    "addr:housenumber":"315",
    "addr:postcode":"80759",
    "addr:street":"E 8Th Ave",
    "iso:country":"US",
    "sg:address":"315 E 8th Ave",
    "sg:city":"Yuma",
    "sg:classifiers":[
        {
            "category":"Food & Beverages",
            "subcategory":"Groceries & Convenience Stores",
            "type":"Retail Goods"
        },
        {
            "category":"Shopping",
            "subcategory":"Pharmacy",
            "type":"Retail Goods"
        }
    ],
    "sg:phone":"+1 970 848 5427",
    "sg:postcode":"80759",
    "sg:province":"CO",
    "sg:tags":[
        "drug"
    ],
    "wof:name":"Shop All Family Pharmacy",
    "wof:placetype":"venue"
},
  "geometry": {"coordinates":[-102.720946,40.11842],"type":"Point"}
}