{
  "type": "Feature",
  "properties": {
    "addr:full":"20203 State Hwy 60 Platteville CO 80651",
    "addr:housenumber":"20203",
    "addr:postcode":"80651",
    "addr:street":"State Hwy 60",
    "iso:country":"US",
    "sg:address":"20203 State Hwy 60",
    "sg:city":"Platteville",
    "sg:phone":"+1 970 737 2476",
    "sg:postcode":"80651",
    "sg:province":"CO",
    "sg:tags":[
        "farm",
        "field",
        "crop"
    ],
    "wof:name":"Eppinger Farms",
    "wof:placetype":"venue"
},
  "geometry": {"coordinates":[-104.811081,40.292843],"type":"Point"}
}