{
  "type": "Feature",
  "properties": {
    "addr:full":"2645 E 74th Ave Denver CO 80229",
    "addr:housenumber":"2645",
    "addr:postcode":"80229",
    "addr:street":"E 74Th Ave",
    "iso:country":"US",
    "sg:address":"2645 E 74th Ave",
    "sg:city":"Denver",
    "sg:classifiers":[
        {
            "category":"Home & Garden",
            "subcategory":"Building Materials",
            "type":"Retail Goods"
        },
        {
            "category":"Organizations",
            "subcategory":"Professional Association",
            "type":"Services"
        }
    ],
    "sg:phone":"+1 303 289 4151",
    "sg:postcode":"80229",
    "sg:province":"CO",
    "sg:tags":[
        "insulation",
        "heat",
        "business"
    ],
    "wof:name":"Eagle Rock Supply Company",
    "wof:placetype":"venue"
},
  "geometry": {"coordinates":[-104.958129,39.829171],"type":"Point"}
}