{
  "type": "Feature",
  "properties": {
    "iso:country":"US",
    "sg:address":"297 W North St",
    "sg:city":"Bayfield",
    "sg:classifiers":[
        {
            "category":"Building & Trades",
            "subcategory":"Plumbing",
            "type":"Services"
        }
    ],
    "sg:phone":"+1 970 884 9189",
    "sg:postcode":"81122",
    "sg:province":"CO",
    "sg:tags":[
        "plumbing",
        "contractor"
    ],
    "wof:name":"Larkin's Plumbing",
    "wof:placetype":"venue"
},
  "geometry": {"coordinates":[-107.604178,37.226149],"type":"Point"}
}