{
  "type": "Feature",
  "properties": {
    "addr:full":"4733 Denver View Dr Evergreen CO 80439",
    "addr:housenumber":"4733",
    "addr:postcode":"80439",
    "addr:street":"Denver View Dr",
    "iso:country":"US",
    "sg:address":"4733 Denver View Dr",
    "sg:city":"Evergreen",
    "sg:classifiers":[
        {
            "category":"Building & Trades",
            "subcategory":"Landscaping Services",
            "type":"Services"
        }
    ],
    "sg:phone":"+1 303 674 7996",
    "sg:postcode":"80439",
    "sg:province":"CO",
    "sg:tags":[
        "computer",
        "landscape",
        "related"
    ],
    "wof:name":"Rokit-Roksolid Informatio",
    "wof:placetype":"venue"
},
  "geometry": {"coordinates":[-105.28326199999999,39.629199],"type":"Point"}
}