{
  "type": "Feature",
  "properties": {
    "iso:country":"US",
    "sg:address":"31013 Co Rd 17",
    "sg:city":"Windsor",
    "sg:classifiers":[
        {
            "category":"Mining & Drilling",
            "type":"Manufacturing & Wholesale Goods"
        }
    ],
    "sg:phone":"+1 970 686 2238",
    "sg:postcode":"80550",
    "sg:province":"CO",
    "sg:tags":[
        "ore",
        "gold"
    ],
    "wof:name":"Scientific Engineering",
    "wof:placetype":"venue"
},
  "geometry": {"coordinates":[-104.912721,40.45118],"type":"Point"}
}