{
  "type": "Feature",
  "properties": {
    "iso:country":"US",
    "sg:address":"9000 Washington St",
    "sg:city":"Thornton",
    "sg:classifiers":[
        {
            "category":"Autos & Motor Vehicles",
            "subcategory":"Automobile Sales",
            "type":"Retail Goods"
        }
    ],
    "sg:phone":"+1 303 289 7777",
    "sg:postcode":"80229",
    "sg:province":"CO",
    "sg:tags":[
        "car",
        "dealer"
    ],
    "wof:name":"Thornton Car Co",
    "wof:placetype":"venue"
},
  "geometry": {"coordinates":[-104.977743,39.856621],"type":"Point"}
}