{
  "type": "Feature",
  "properties": {
    "iso:country":"US",
    "sg:address":"737 S 10th St",
    "sg:city":"Montrose",
    "sg:classifiers":[
        {
            "category":"Travel",
            "subcategory":"Travel Agent",
            "type":"Entertainment"
        }
    ],
    "sg:phone":"+1 970 249 3463",
    "sg:postcode":"81401",
    "sg:province":"CO",
    "sg:tags":[
        "agency",
        "bureau"
    ],
    "wof:name":"Park Avenue Travel",
    "wof:placetype":"venue"
},
  "geometry": {"coordinates":[-107.863209,38.475225],"type":"Point"}
}