{
  "type": "Feature",
  "properties": {
    "iso:country":"US",
    "sg:address":"279 Beacon Lite Rd",
    "sg:city":"Monument",
    "sg:classifiers":[
        {
            "category":"Shopping",
            "subcategory":"Bicycles & Sporting Goods",
            "type":"Retail Goods"
        }
    ],
    "sg:phone":"+1 719 488 9007",
    "sg:postcode":"80132",
    "sg:province":"CO",
    "wof:name":"Balanced Rock Bike & Ski",
    "wof:placetype":"venue"
},
  "geometry": {"coordinates":[-104.86827700000001,39.092872],"type":"Point"}
}