{
  "type": "Feature",
  "properties": {
    "addr:full":"11597 US Hwy 24 Leadville CO 80461",
    "addr:housenumber":"11597",
    "addr:postcode":"80461",
    "addr:street":"Us Hwy 24",
    "iso:country":"US",
    "sg:address":"11597 US Hwy 24",
    "sg:city":"Leadville",
    "sg:classifiers":[
        {
            "category":"Manufacturing",
            "subcategory":"Jewelry",
            "type":"Manufacturing & Wholesale Goods"
        }
    ],
    "sg:phone":"+1 719 486 3223",
    "sg:postcode":"80461",
    "sg:province":"CO",
    "sg:tags":[
        "product",
        "mfg"
    ],
    "wof:name":"Ernies Steel Shop",
    "wof:placetype":"venue"
},
  "geometry": {"coordinates":[-106.34487900000001,39.206264],"type":"Point"}
}