{
  "type": "Feature",
  "properties": {
    "iso:country":"US",
    "sg:address":"5160 Silver Dr",
    "sg:city":"Colorado Springs",
    "sg:classifiers":[
        {
            "category":"Real Estate",
            "subcategory":"Real Estate Agent",
            "type":"Services"
        }
    ],
    "sg:phone":"+1 719 533 1101",
    "sg:postcode":"80918",
    "sg:province":"CO",
    "wof:name":"Remax Advantage",
    "wof:placetype":"venue"
},
  "geometry": {"coordinates":[-104.74153200000001,38.90994],"type":"Point"}
}