{
  "type": "Feature",
  "properties": {
    "iso:country":"US",
    "sg:address":"2066 S Abilene St",
    "sg:city":"Aurora",
    "sg:classifiers":[
        {
            "category":"Restaurant",
            "type":"Food & Drink"
        }
    ],
    "sg:menulink":"http://www.allmenus.com/co/south-aurora/97941-outback-steakhouse/menu/",
    "sg:phone":"+1 303 695 9600",
    "sg:postcode":"80014",
    "sg:province":"CO",
    "sg:tags":[
        "american",
        "steakhouse"
    ],
    "wof:name":"Outback Steakhouse",
    "wof:placetype":"venue"
},
  "geometry": {"coordinates":[-104.828311,39.679274],"type":"Point"}
}