{
  "type": "Feature",
  "properties": {
    "iso:country":"US",
    "sg:address":"644 N 4th St",
    "sg:city":"Montrose",
    "sg:classifiers":[
        {
            "category":"Arts & Performance",
            "subcategory":"Theater",
            "type":"Entertainment"
        }
    ],
    "sg:phone":"+1 970 240 9277",
    "sg:postcode":"81401",
    "sg:province":"CO",
    "sg:tags":[
        "band",
        "orchestra"
    ],
    "wof:name":"Fleeting Moment",
    "wof:placetype":"venue"
},
  "geometry": {"coordinates":[-107.87729400000001,38.484328],"type":"Point"}
}