{
  "type": "Feature",
  "properties": {
    "addr:full":"51 School St Basalt CO 81621",
    "addr:housenumber":"51",
    "addr:postcode":"81621",
    "addr:street":"School St",
    "iso:country":"US",
    "sg:address":"51 School St",
    "sg:city":"Basalt",
    "sg:classifiers":[
        {
            "category":"Education",
            "subcategory":"School",
            "type":"Public Place"
        }
    ],
    "sg:phone":"+1 970 384 5900",
    "sg:postcode":"81621",
    "sg:province":"CO",
    "sg:website":"www.rfsd.k12.co.us",
    "wof:name":"Basalt Middle School",
    "wof:placetype":"venue"
},
  "geometry": {"coordinates":[-107.030424,39.364815],"type":"Point"}
}