{
  "type": "Feature",
  "properties": {
    "iso:country":"US",
    "sg:address":"3300 28th St",
    "sg:city":"Boulder",
    "sg:classifiers":[
        {
            "category":"Building & Trades",
            "subcategory":"Construction",
            "type":"Services"
        }
    ],
    "sg:phone":"+1 303 444 6224",
    "sg:postcode":"80301",
    "sg:province":"CO",
    "sg:tags":[
        "house"
    ],
    "wof:name":"Moore & Co",
    "wof:placetype":"venue"
},
  "geometry": {"coordinates":[-105.258366,40.035082],"type":"Point"}
}