{
  "type": "Feature",
  "properties": {
    "addr:full":"7050 S Fillmore Ct Littleton CO 80122",
    "addr:housenumber":"7050",
    "addr:postcode":"80122",
    "addr:street":"S Fillmore Ct",
    "iso:country":"US",
    "sg:address":"7050 S Fillmore Ct",
    "sg:city":"Littleton",
    "sg:classifiers":[
        {
            "category":"Banks & Credit Unions",
            "subcategory":"Financial Services",
            "type":"Services"
        }
    ],
    "sg:phone":"+1 303 770 8968",
    "sg:postcode":"80122",
    "sg:province":"CO",
    "sg:tags":[
        "company",
        "holding"
    ],
    "wof:name":"Ip Holdings Inc",
    "wof:placetype":"venue"
},
  "geometry": {"coordinates":[-104.95372399999999,39.588321],"type":"Point"}
}