{
  "type": "Feature",
  "properties": {
    "iso:country":"US",
    "sg:address":"10990 W Kentucky Dr",
    "sg:city":"Lakewood",
    "sg:classifiers":[
        {
            "category":"Building & Trades",
            "subcategory":"Construction",
            "type":"Services"
        }
    ],
    "sg:phone":"+1 303 986 2564",
    "sg:postcode":"80226",
    "sg:province":"CO",
    "sg:tags":[
        "marking",
        "maintenance",
        "parking"
    ],
    "wof:name":"Universal Parking",
    "wof:placetype":"venue"
},
  "geometry": {"coordinates":[-105.11999400000001,39.698652],"type":"Point"}
}