{
  "type": "Feature",
  "properties": {
    "addr:full":"288 S Madison Ave Louisville CO 80027",
    "addr:housenumber":"288",
    "addr:postcode":"80027",
    "addr:street":"S Madison Ave",
    "iso:country":"US",
    "sg:address":"288 S Madison Ave",
    "sg:city":"Louisville",
    "sg:classifiers":[
        {
            "category":"Shopping",
            "subcategory":"Crafts & Fabrics",
            "type":"Retail Goods"
        }
    ],
    "sg:phone":"+1 303 665 1317",
    "sg:postcode":"80027",
    "sg:province":"CO",
    "sg:tags":[
        "sewing"
    ],
    "wof:name":"Needle & Thread",
    "wof:placetype":"venue"
},
  "geometry": {"coordinates":[-105.15084299999999,39.968424],"type":"Point"}
}