{
  "type": "Feature",
  "properties": {
    "addr:full":"1432 Cedar St Pueblo CO 81004",
    "addr:housenumber":"1432",
    "addr:postcode":"81004",
    "addr:street":"Cedar St",
    "iso:country":"US",
    "sg:address":"1432 Cedar St",
    "sg:city":"Pueblo",
    "sg:classifiers":[
        {
            "category":"Building & Trades",
            "subcategory":"Construction",
            "type":"Services"
        }
    ],
    "sg:phone":"+1 719 564 1195",
    "sg:postcode":"81004",
    "sg:province":"CO",
    "sg:tags":[
        "house"
    ],
    "wof:name":"Deck Professionals LLC",
    "wof:placetype":"venue"
},
  "geometry": {"coordinates":[-104.619489,38.241176],"type":"Point"}
}