{
  "type": "Feature",
  "properties": {
    "iso:country":"US",
    "sg:address":"31 Crystal Cove",
    "sg:city":"Dillon",
    "sg:classifiers":[
        {
            "category":"Building & Trades",
            "subcategory":"Plumbing",
            "type":"Services"
        }
    ],
    "sg:phone":"+1 970 468 0553",
    "sg:postcode":"80435",
    "sg:province":"CO",
    "sg:tags":[
        "contractor"
    ],
    "wof:name":"AC Cleaning",
    "wof:placetype":"venue"
},
  "geometry": {"coordinates":[-106.009417,39.60251],"type":"Point"}
}