{
  "type": "Feature",
  "properties": {
    "iso:country":"US",
    "sg:address":"8001 Shaffer Pkwy",
    "sg:city":"Littleton",
    "sg:classifiers":[
        {
            "category":"Restaurant",
            "type":"Food & Drink"
        }
    ],
    "sg:phone":"+1 303 948 7404",
    "sg:postcode":"80127",
    "sg:province":"CO",
    "sg:tags":[
        "caterer"
    ],
    "wof:name":"Panache Catering",
    "wof:placetype":"venue"
},
  "geometry": {"coordinates":[-105.13037799999999,39.572493],"type":"Point"}
}