{
  "type": "Feature",
  "properties": {
    "iso:country":"US",
    "sg:address":"8365 Orchard Path Rd",
    "sg:city":"Colorado Springs",
    "sg:classifiers":[
        {
            "category":"Education",
            "subcategory":"School",
            "type":"Public Place"
        }
    ],
    "sg:phone":"+1 719 598 1715",
    "sg:postcode":"80919",
    "sg:province":"CO",
    "sg:tags":[
        "high",
        "middle",
        "elementary"
    ],
    "wof:name":"Woodmen Roberts Elementary School",
    "wof:placetype":"venue"
},
  "geometry": {"coordinates":[-104.871002,38.945702],"type":"Point"}
}