{
  "type": "Feature",
  "properties": {
    "iso:country":"US",
    "sg:address":"482 Laredo St",
    "sg:city":"Aurora",
    "sg:classifiers":[
        {
            "category":"Retail",
            "subcategory":"Auto Repair",
            "type":"Services"
        }
    ],
    "sg:phone":"+1 303 340 4229",
    "sg:postcode":"80011",
    "sg:province":"CO",
    "sg:tags":[
        "body",
        "automobile",
        "painting"
    ],
    "wof:name":"Autobodyautoteck",
    "wof:placetype":"venue"
},
  "geometry": {"coordinates":[-104.800496,39.723808],"type":"Point"}
}