{
  "type": "Feature",
  "properties": {
    "addr:full":"2416 Sheffield Cir W Fort Collins CO 80526",
    "addr:housenumber":"2416",
    "addr:postcode":"80526",
    "addr:street":"Sheffield Cir W",
    "iso:country":"US",
    "sg:address":"2416 Sheffield Cir W",
    "sg:city":"Fort Collins",
    "sg:classifiers":[
        {
            "category":"Manufacturing",
            "subcategory":"Printing",
            "type":"Manufacturing & Wholesale Goods"
        }
    ],
    "sg:phone":"+1 970 221 5898",
    "sg:postcode":"80526",
    "sg:province":"CO",
    "sg:tags":[
        "publishing"
    ],
    "wof:name":"Sensa Business Communications",
    "wof:placetype":"venue"
},
  "geometry": {"coordinates":[-105.112025,40.554304],"type":"Point"}
}