{
  "type": "Feature",
  "properties": {
    "iso:country":"US",
    "sg:address":"801 Manitou Ave",
    "sg:city":"Manitou Springs",
    "sg:classifiers":[
        {
            "category":"Shopping",
            "subcategory":"Clothing, Apparel, & Fashions",
            "type":"Retail Goods"
        }
    ],
    "sg:phone":"+1 719 685 0571",
    "sg:postcode":"80829",
    "sg:province":"CO",
    "sg:tags":[
        "accessory",
        "clothing",
        "women's"
    ],
    "wof:name":"The Rising Sun",
    "wof:placetype":"venue"
},
  "geometry": {"coordinates":[-104.917,38.857498],"type":"Point"}
}