{
  "type": "Feature",
  "properties": {
    "addr:full":"7405 Turkey Rock Rd Littleton CO 80125",
    "addr:housenumber":"7405",
    "addr:postcode":"80125",
    "addr:street":"Turkey Rock Rd",
    "iso:country":"US",
    "sg:address":"7405 Turkey Rock Rd",
    "sg:city":"Littleton",
    "sg:classifiers":[
        {
            "category":"Manufacturing",
            "subcategory":"Tools & Machinery",
            "type":"Manufacturing & Wholesale Goods"
        }
    ],
    "sg:phone":"+1 303 948 8051",
    "sg:postcode":"80125",
    "sg:province":"CO",
    "sg:tags":[
        "industrial",
        "mfg"
    ],
    "wof:name":"Trick Custom Machining LLC",
    "wof:placetype":"venue"
},
  "geometry": {"coordinates":[-105.07796999999999,39.470198],"type":"Point"}
}