{
  "type": "Feature",
  "properties": {
    "addr:full":"1409 N Chelton Rd Colorado Springs CO 80909",
    "addr:housenumber":"1409",
    "addr:postcode":"80909",
    "addr:street":"N Chelton Rd",
    "iso:country":"US",
    "sg:address":"1409 N Chelton Rd",
    "sg:city":"Colorado Springs",
    "sg:classifiers":[
        {
            "category":"Building & Trades",
            "subcategory":"Cleaning & Sanitation",
            "type":"Services"
        }
    ],
    "sg:phone":"+1 719 574 3273",
    "sg:postcode":"80909",
    "sg:province":"CO",
    "sg:tags":[
        "house"
    ],
    "wof:name":"Maid Day",
    "wof:placetype":"venue"
},
  "geometry": {"coordinates":[-104.76535800000001,38.854266],"type":"Point"}
}