{
  "type": "Feature",
  "properties": {
    "iso:country":"US",
    "sg:address":"737 Gregory Rd",
    "sg:city":"Fort Collins",
    "sg:classifiers":[
        {
            "category":"Wholesale",
            "subcategory":"Hardware",
            "type":"Manufacturing & Wholesale Goods"
        },
        {
            "category":"Home & Garden",
            "subcategory":"Building Materials",
            "type":"Retail Goods"
        }
    ],
    "sg:phone":"+1 970 482 6924",
    "sg:postcode":"80524",
    "sg:province":"CO",
    "sg:tags":[
        "equipment",
        "energy",
        "solar"
    ],
    "sg:website":"www.burnhambeck.com",
    "wof:name":"Burnham Beck & Sun",
    "wof:placetype":"venue"
},
  "geometry": {"coordinates":[-105.06212499999999,40.625001],"type":"Point"}
}