{
  "type": "Feature",
  "properties": {
    "addr:full":"58 Inverness Dr E Englewood CO 80112",
    "addr:housenumber":"58",
    "addr:postcode":"80112",
    "addr:street":"Inverness Dr E",
    "iso:country":"US",
    "sg:address":"58 Inverness Dr E",
    "sg:city":"Englewood",
    "sg:classifiers":[
        {
            "category":"Real Estate",
            "subcategory":"Architect",
            "type":"Services"
        }
    ],
    "sg:phone":"+1 303 662 8670",
    "sg:postcode":"80112",
    "sg:province":"CO",
    "wof:name":"A D Arizado",
    "wof:placetype":"venue"
},
  "geometry": {"coordinates":[-104.85671499999999,39.578023],"type":"Point"}
}