{
  "type": "Feature",
  "properties": {
    "addr:full":"995 US Hwy 85 Brighton CO 80603",
    "addr:housenumber":"995",
    "addr:postcode":"80603",
    "addr:street":"Us Hwy 85",
    "iso:country":"US",
    "sg:address":"995 US Hwy 85",
    "sg:city":"Brighton",
    "sg:classifiers":[
        {
            "category":"Farming",
            "subcategory":"Livestock Farm",
            "type":"Manufacturing & Wholesale Goods"
        }
    ],
    "sg:phone":"+1 303 659 2386",
    "sg:postcode":"80603",
    "sg:province":"CO",
    "sg:tags":[
        "general"
    ],
    "wof:name":"Baja Ranch Company",
    "wof:placetype":"venue"
},
  "geometry": {"coordinates":[-104.819305,40.007574],"type":"Point"}
}