{
  "type": "Feature",
  "properties": {
    "addr:full":"2537 Research Blvd Fort Collins CO 80526",
    "addr:housenumber":"2537",
    "addr:postcode":"80526",
    "addr:street":"Research Blvd",
    "iso:country":"US",
    "sg:address":"2537 Research Blvd",
    "sg:city":"Fort Collins",
    "sg:classifiers":[
        {
            "category":"Insurance",
            "subcategory":"Insurance Agent",
            "type":"Services"
        }
    ],
    "sg:phone":"+1 970 484 0097",
    "sg:postcode":"80526",
    "sg:province":"CO",
    "wof:name":"Herbert-Leavitt Insurance Inc",
    "wof:placetype":"venue"
},
  "geometry": {"coordinates":[-105.087615,40.556162],"type":"Point"}
}