{
  "type": "Feature",
  "properties": {
    "addr:full":"660 W Aspen Ct Aurora CO 80027",
    "addr:housenumber":"660",
    "addr:postcode":"80027",
    "addr:street":"W Aspen Ct",
    "iso:country":"US",
    "sg:address":"660 W Aspen Ct",
    "sg:city":"Aurora",
    "sg:classifiers":[
        {
            "category":"Government",
            "subcategory":"Office",
            "type":"Public Place"
        }
    ],
    "sg:phone":"+1 303 677 6743",
    "sg:postcode":"80027",
    "sg:province":"CO",
    "sg:tags":[
        "national"
    ],
    "wof:name":"Colorado National Guard",
    "wof:placetype":"venue"
},
  "geometry": {"coordinates":[-105.152604,39.967819],"type":"Point"}
}