{
  "type": "Feature",
  "properties": {
    "iso:country":"US",
    "sg:address":"7800 E Iliff Ave",
    "sg:city":"Denver",
    "sg:classifiers":[
        {
            "category":"Professional",
            "subcategory":"Printing & Photocopies",
            "type":"Services"
        }
    ],
    "sg:phone":"+1 303 750 5566",
    "sg:postcode":"80231",
    "sg:province":"CO",
    "sg:tags":[
        "duplicating",
        "copying"
    ],
    "sg:website":"www.printpointe.com",
    "wof:name":"Print Pointe",
    "wof:placetype":"venue"
},
  "geometry": {"coordinates":[-104.895017,39.674708],"type":"Point"}
}