{
  "type": "Feature",
  "properties": {
    "addr:full":"2211 W Mulberry St Fort Collins CO 80521",
    "addr:housenumber":"2211",
    "addr:postcode":"80521",
    "addr:street":"W Mulberry St",
    "iso:country":"US",
    "sg:address":"2211 W Mulberry St",
    "sg:city":"Fort Collins",
    "sg:classifiers":[
        {
            "category":"Professional",
            "type":"Services"
        }
    ],
    "sg:phone":"+1 970 224 2532",
    "sg:postcode":"80521",
    "sg:province":"CO",
    "wof:name":"Let ME Show You Somthin",
    "wof:placetype":"venue"
},
  "geometry": {"coordinates":[-105.11502299999999,40.581987],"type":"Point"}
}