{
  "type": "Feature",
  "properties": {
    "addr:full":"3801 E Florida Ave Denver CO 80210",
    "addr:housenumber":"3801",
    "addr:postcode":"80210",
    "addr:street":"E Florida Ave",
    "iso:country":"US",
    "sg:address":"3801 E Florida Ave",
    "sg:city":"Denver",
    "sg:classifiers":[
        {
            "category":"Banks & Credit Unions",
            "subcategory":"Financial Services",
            "type":"Services"
        }
    ],
    "sg:phone":"+1 303 300 9920",
    "sg:postcode":"80210",
    "sg:province":"CO",
    "sg:tags":[
        "broker",
        "mortgage"
    ],
    "wof:name":"Paramount Financial Services",
    "wof:placetype":"venue"
},
  "geometry": {"coordinates":[-104.943001,39.689301],"type":"Point"}
}