{
  "type": "Feature",
  "properties": {
    "iso:country":"US",
    "sg:address":"444 17th St",
    "sg:city":"Denver",
    "sg:classifiers":[
        {
            "category":"Communications",
            "type":"Services"
        }
    ],
    "sg:phone":"+1 888 855 2534",
    "sg:postcode":"80202",
    "sg:province":"CO",
    "sg:tags":[
        "web",
        "design"
    ],
    "sg:website":"sophic.net",
    "wof:name":"Sophic, Market Your Business Online",
    "wof:placetype":"venue"
},
  "geometry": {"coordinates":[-104.988799,39.744398],"type":"Point"}
}