{
  "type": "Feature",
  "properties": {
    "addr:full":"5440 Marshall St Arvada CO 80002",
    "addr:housenumber":"5440",
    "addr:postcode":"80002",
    "addr:street":"Marshall St",
    "iso:country":"US",
    "sg:address":"5440 Marshall St",
    "sg:city":"Arvada",
    "sg:classifiers":[
        {
            "category":"Wholesale",
            "subcategory":"Auto Parts",
            "type":"Manufacturing & Wholesale Goods"
        }
    ],
    "sg:phone":"+1 303 432 8989",
    "sg:postcode":"80002",
    "sg:province":"CO",
    "sg:tags":[
        "automobile",
        "rebuilt"
    ],
    "wof:name":"Rs Motor Sports",
    "wof:placetype":"venue"
},
  "geometry": {"coordinates":[-105.068426,39.795302],"type":"Point"}
}