{
  "type": "Feature",
  "properties": {
    "iso:country":"US",
    "sg:address":"3401 S Lincoln St",
    "sg:city":"Englewood",
    "sg:classifiers":[
        {
            "category":"Personal",
            "subcategory":"Beauty Salon",
            "type":"Services"
        }
    ],
    "sg:phone":"+1 303 781 8186",
    "sg:postcode":"80113",
    "sg:province":"CO",
    "wof:name":"Hair Karie Weidaman",
    "wof:placetype":"venue"
},
  "geometry": {"coordinates":[-104.986384,39.653164],"type":"Point"}
}