{
  "type": "Feature",
  "properties": {
    "addr:full":"265 S Holly St Denver CO 80246",
    "addr:housenumber":"265",
    "addr:postcode":"80246",
    "addr:street":"S Holly St",
    "iso:country":"US",
    "sg:address":"265 S Holly St",
    "sg:city":"Denver",
    "sg:classifiers":[
        {
            "category":"Banks & Credit Unions",
            "subcategory":"Investment Brokerage",
            "type":"Services"
        },
        {
            "category":"Professional",
            "subcategory":"Business Services",
            "type":"Services"
        }
    ],
    "sg:phone":"+1 303 322 2777",
    "sg:postcode":"80246",
    "sg:province":"CO",
    "sg:tags":[
        "consultant",
        "planning",
        "financial"
    ],
    "wof:name":"American College Funding Svcs",
    "wof:placetype":"venue"
},
  "geometry": {"coordinates":[-104.92235700000001,39.712489],"type":"Point"}
}