{
  "type": "Feature",
  "properties": {
    "iso:country":"US",
    "sg:address":"16500 S Golden Rd",
    "sg:city":"Golden",
    "sg:classifiers":[
        {
            "category":"Retail",
            "subcategory":"Auto Repair",
            "type":"Services"
        },
        {
            "category":"Professional",
            "subcategory":"Credit Reporting & Collection",
            "type":"Services"
        }
    ],
    "sg:phone":"+1 720 497 1119",
    "sg:postcode":"80401",
    "sg:province":"CO",
    "sg:tags":[
        "automotive",
        "agency"
    ],
    "wof:name":"Skyline Recovery Systems LLC",
    "wof:placetype":"venue"
},
  "geometry": {"coordinates":[-105.185748,39.735577],"type":"Point"}
}