{
  "type": "Feature",
  "properties": {
    "iso:country":"US",
    "sg:address":"1010 W Colorado Ave",
    "sg:city":"Colorado Springs",
    "sg:classifiers":[
        {
            "category":"Personal",
            "type":"Services"
        }
    ],
    "sg:phone":"+1 719 510 0691",
    "sg:postcode":"80904",
    "sg:province":"CO",
    "sg:tags":[
        "therapist",
        "massage"
    ],
    "wof:name":"Nancy Weigand",
    "wof:placetype":"venue"
},
  "geometry": {"coordinates":[-104.84167100000001,38.83504],"type":"Point"}
}