{
  "type": "Feature",
  "properties": {
    "addr:full":"1872 S Meade St Denver CO 80219",
    "addr:housenumber":"1872",
    "addr:postcode":"80219",
    "addr:street":"S Meade St",
    "iso:country":"US",
    "sg:address":"1872 S Meade St",
    "sg:city":"Denver",
    "sg:classifiers":[
        {
            "category":"Government",
            "subcategory":"Office",
            "type":"Public Place"
        }
    ],
    "sg:phone":"+1 303 698 5504",
    "sg:postcode":"80219",
    "sg:province":"CO",
    "sg:tags":[
        "conservation"
    ],
    "wof:name":"Denver Parks & Recreation",
    "wof:placetype":"venue"
},
  "geometry": {"coordinates":[-105.037021,39.684127],"type":"Point"}
}