{
  "type": "Feature",
  "properties": {
    "iso:country":"US",
    "sg:address":"4401 Mark Dabling Blvd",
    "sg:city":"Colorado Springs",
    "sg:classifiers":[
        {
            "category":"Retail",
            "subcategory":"Auto Repair",
            "type":"Services"
        }
    ],
    "sg:phone":"+1 719 262 0900",
    "sg:postcode":"80907",
    "sg:province":"CO",
    "sg:tags":[
        "body",
        "automobile",
        "painting"
    ],
    "sg:website":"www.carscollision.com",
    "wof:name":"Cars Collision Ctr",
    "wof:placetype":"venue"
},
  "geometry": {"coordinates":[-104.825519,38.893495],"type":"Point"}
}