{
  "type": "Feature",
  "properties": {
    "iso:country":"US",
    "sg:address":"9197 E Oxford Dr",
    "sg:city":"Denver",
    "sg:classifiers":[
        {
            "category":"Freight",
            "type":"Transportation"
        }
    ],
    "sg:phone":"+1 303 741 2514",
    "sg:postcode":"80237",
    "sg:province":"CO",
    "sg:tags":[
        "delivery"
    ],
    "wof:name":"Mal Interprises Inc",
    "wof:placetype":"venue"
},
  "geometry": {"coordinates":[-104.88197700000001,39.641558],"type":"Point"}
}