{
  "type": "Feature",
  "properties": {
    "iso:country":"US",
    "sg:address":"752 E Agate Ave",
    "sg:city":"Granby",
    "sg:classifiers":[
        {
            "category":"Professional",
            "subcategory":"Engineering",
            "type":"Services"
        }
    ],
    "sg:phone":"+1 970 887 0531",
    "sg:postcode":"80446",
    "sg:province":"CO",
    "sg:tags":[
        "engineer"
    ],
    "wof:name":"Ground Engineering Consultants",
    "wof:placetype":"venue"
},
  "geometry": {"coordinates":[-105.93155,40.08487],"type":"Point"}
}