{
  "type": "Feature",
  "properties": {
    "iso:country":"US",
    "sg:address":"25500 E 78th Ave",
    "sg:city":"Denver",
    "sg:classifiers":[
        {
            "category":"Retail",
            "subcategory":"Auto Rental",
            "type":"Services"
        }
    ],
    "sg:phone":"+1 303 342 5500",
    "sg:postcode":"80249",
    "sg:province":"CO",
    "sg:tags":[
        "renting",
        "automobile"
    ],
    "sg:website":"www.avis.com",
    "wof:name":"Avis Rent A Car",
    "wof:placetype":"venue"
},
  "geometry": {"coordinates":[-104.687991,39.838006],"type":"Point"}
}