{
  "type": "Feature",
  "properties": {
    "addr:full":"579 Asbury Ct Grand Junction CO 81504",
    "addr:housenumber":"579",
    "addr:postcode":"81504",
    "addr:street":"Asbury Ct",
    "iso:country":"US",
    "sg:address":"579 Asbury Ct",
    "sg:city":"Grand Junction",
    "sg:classifiers":[
        {
            "category":"Retail",
            "subcategory":"Laundry & Dry Cleaning",
            "type":"Services"
        }
    ],
    "sg:phone":"+1 970 523 1201",
    "sg:postcode":"81504",
    "sg:province":"CO",
    "sg:tags":[
        "cleaners",
        "rug",
        "carpet"
    ],
    "wof:name":"Delicate Carpet & Upholstery",
    "wof:placetype":"venue"
},
  "geometry": {"coordinates":[-108.482252,39.088793],"type":"Point"}
}