{
  "type": "Feature",
  "properties": {
    "iso:country":"US",
    "sg:address":"8782 S Martin Ln",
    "sg:city":"Conifer",
    "sg:classifiers":[
        {
            "category":"Shopping",
            "subcategory":"Bicycles & Sporting Goods",
            "type":"Retail Goods"
        }
    ],
    "sg:phone":"+1 303 674 7215",
    "sg:postcode":"80433",
    "sg:province":"CO",
    "wof:name":"X Caliber Guns & Accessories",
    "wof:placetype":"venue"
},
  "geometry": {"coordinates":[-105.372248,39.562461],"type":"Point"}
}