{
  "type": "Feature",
  "properties": {
    "addr:full":"337 Co Rd 217 Durango CO 81303",
    "addr:housenumber":"337;217",
    "addr:postcode":"co 81303",
    "addr:street":"Co Rd",
    "iso:country":"US",
    "sg:address":"337 Co Rd 217",
    "sg:city":"Durango",
    "sg:classifiers":[
        {
            "category":"Building & Trades",
            "subcategory":"Plumbing",
            "type":"Services"
        }
    ],
    "sg:phone":"+1 970 247 9717",
    "sg:postcode":"81303",
    "sg:province":"CO",
    "sg:tags":[
        "contractor"
    ],
    "wof:name":"Ancell Plumbing Co",
    "wof:placetype":"venue"
},
  "geometry": {"coordinates":[-107.865357,37.096506],"type":"Point"}
}