{
  "type": "Feature",
  "properties": {
    "addr:full":"561 Lincoln St Craig CO 81625",
    "addr:housenumber":"561",
    "addr:postcode":"81625",
    "addr:street":"Lincoln St",
    "iso:country":"US",
    "sg:address":"561 Lincoln St",
    "sg:city":"Craig",
    "sg:classifiers":[
        {
            "category":"Building & Trades",
            "subcategory":"Construction",
            "type":"Services"
        }
    ],
    "sg:phone":"+1 970 824 3570",
    "sg:postcode":"81625",
    "sg:province":"CO",
    "sg:tags":[
        "contractor"
    ],
    "wof:name":"Five Star Construction",
    "wof:placetype":"venue"
},
  "geometry": {"coordinates":[-107.541139,40.515454],"type":"Point"}
}