{
  "type": "Feature",
  "properties": {
    "iso:country":"US",
    "sg:address":"19218 Hwy 82",
    "sg:city":"Carbondale",
    "sg:classifiers":[
        {
            "category":"Travel",
            "subcategory":"Travel Agent",
            "type":"Entertainment"
        }
    ],
    "sg:phone":"+1 970 925 9500",
    "sg:postcode":"81623",
    "sg:province":"CO",
    "sg:tags":[
        "tour",
        "agency",
        "arrangement"
    ],
    "wof:name":"Mid Valley Travel",
    "wof:placetype":"venue"
},
  "geometry": {"coordinates":[-107.113715,39.40155],"type":"Point"}
}