{
  "type": "Feature",
  "properties": {
    "addr:full":"3790 S Delaware St Englewood CO 80110",
    "addr:housenumber":"3790",
    "addr:postcode":"80110",
    "addr:street":"S Delaware St",
    "iso:country":"US",
    "sg:address":"3790 S Delaware St",
    "sg:city":"Englewood",
    "sg:classifiers":[
        {
            "category":"Professional",
            "type":"Services"
        }
    ],
    "sg:phone":"+1 303 789 3218",
    "sg:postcode":"80110",
    "sg:province":"CO",
    "wof:name":"High Twelve International",
    "wof:placetype":"venue"
},
  "geometry": {"coordinates":[-104.992341,39.648671],"type":"Point"}
}