{
  "type": "Feature",
  "properties": {
    "iso:country":"US",
    "sg:address":"2880 Folsom St",
    "sg:city":"Boulder",
    "sg:classifiers":[
        {
            "category":"Health Services",
            "subcategory":"Doctor",
            "type":"Services"
        }
    ],
    "sg:phone":"+1 303 440 5600",
    "sg:postcode":"80304",
    "sg:province":"CO",
    "sg:tags":[
        "clinic"
    ],
    "wof:name":"Da Vita Inc",
    "wof:placetype":"venue"
},
  "geometry": {"coordinates":[-105.263049,40.028779],"type":"Point"}
}