{
  "type": "Feature",
  "properties": {
    "addr:full":"461 S Kingston Cir Aurora CO 80012",
    "addr:housenumber":"461",
    "addr:postcode":"80012",
    "addr:street":"S Kingston Cir",
    "iso:country":"US",
    "sg:address":"461 S Kingston Cir",
    "sg:city":"Aurora",
    "sg:classifiers":[
        {
            "category":"Wholesale",
            "subcategory":"Machinery & Supplies",
            "type":"Manufacturing & Wholesale Goods"
        }
    ],
    "sg:phone":"+1 303 366 1919",
    "sg:postcode":"80012",
    "sg:province":"CO",
    "sg:tags":[
        "specializing",
        "equipment",
        "industrial",
        "dust",
        "air"
    ],
    "wof:name":"Tech Air Systems Inc",
    "wof:placetype":"venue"
},
  "geometry": {"coordinates":[-104.858735,39.707547],"type":"Point"}
}