{
  "type": "Feature",
  "properties": {
    "addr:full":"7370 E Florida Ave Denver CO 80231",
    "addr:housenumber":"7370",
    "addr:postcode":"80231",
    "addr:street":"E Florida Ave",
    "iso:country":"US",
    "sg:address":"7370 E Florida Ave",
    "sg:city":"Denver",
    "sg:classifiers":[
        {
            "category":"Professional",
            "subcategory":"Computer Services",
            "type":"Services"
        }
    ],
    "sg:phone":"+1 303 745 2099",
    "sg:postcode":"80231",
    "sg:province":"CO",
    "sg:tags":[
        "consultant"
    ],
    "wof:name":"Stardyne Systems Consulting",
    "wof:placetype":"venue"
},
  "geometry": {"coordinates":[-104.902029,39.689268],"type":"Point"}
}