{
  "type": "Feature",
  "properties": {
    "iso:country":"US",
    "sg:address":"30275 State Hwy 24",
    "sg:city":"Buena Vista",
    "sg:classifiers":[
        {
            "category":"Organizations",
            "subcategory":"Religious Organization",
            "type":"Services"
        }
    ],
    "sg:phone":"+1 719 395 6730",
    "sg:postcode":"81211",
    "sg:province":"CO",
    "sg:tags":[
        "church"
    ],
    "wof:name":"High Country Church",
    "wof:placetype":"venue"
},
  "geometry": {"coordinates":[-106.14639099999999,38.860822],"type":"Point"}
}