{
  "type": "Feature",
  "properties": {
    "addr:full":"28310 Co Rd 31 Oak Creek CO 80467",
    "addr:housenumber":"28310;31",
    "addr:postcode":"80467",
    "addr:street":"Co Rd",
    "iso:country":"US",
    "sg:address":"28310 Co Rd 31",
    "sg:city":"Oak Creek",
    "sg:classifiers":[
        {
            "category":"Recreation",
            "type":"Entertainment"
        }
    ],
    "sg:phone":"+1 970 879 7353",
    "sg:postcode":"80467",
    "sg:province":"CO",
    "sg:tags":[
        "guide"
    ],
    "wof:name":"Middle Creek Ranch Outfitters",
    "wof:placetype":"venue"
},
  "geometry": {"coordinates":[-107.045427,40.329902],"type":"Point"}
}