{
  "type": "Feature",
  "properties": {
    "iso:country":"US",
    "sg:address":"1009 S 9th St",
    "sg:city":"Grand Junction",
    "sg:classifiers":[
        {
            "category":"Government",
            "subcategory":"Office",
            "type":"Public Place"
        }
    ],
    "sg:phone":"+1 970 244 1811",
    "sg:postcode":"81501",
    "sg:province":"CO",
    "sg:tags":[
        "executive"
    ],
    "wof:name":"County of Mesa",
    "wof:placetype":"venue"
},
  "geometry": {"coordinates":[-108.557738,39.057555],"type":"Point"}
}