{
  "type": "Feature",
  "properties": {
    "iso:country":"US",
    "sg:address":"88 Cottonwood Trl",
    "sg:city":"Gunnison",
    "sg:classifiers":[
        {
            "category":"Shopping",
            "subcategory":"Gifts & Souvenirs",
            "type":"Retail Goods"
        }
    ],
    "sg:phone":"+1 970 641 2458",
    "sg:postcode":"81230",
    "sg:province":"CO",
    "sg:tags":[
        "work",
        "art"
    ],
    "wof:name":"Class Act Gifts",
    "wof:placetype":"venue"
},
  "geometry": {"coordinates":[-106.94436399999999,38.510538],"type":"Point"}
}