{
  "type": "Feature",
  "properties": {
    "addr:full":"8000 E Prentice Ave Englewood CO 80111",
    "addr:housenumber":"8000",
    "addr:postcode":"80111",
    "addr:street":"E Prentice Ave",
    "iso:country":"US",
    "sg:address":"8000 E Prentice Ave",
    "sg:city":"Englewood",
    "sg:classifiers":[
        {
            "category":"Social Services",
            "subcategory":"Child Care",
            "type":"Services"
        }
    ],
    "sg:phone":"+1 303 721 1213",
    "sg:postcode":"80111",
    "sg:province":"CO",
    "sg:tags":[
        "day"
    ],
    "wof:name":"People Care Assoc LLC",
    "wof:placetype":"venue"
},
  "geometry": {"coordinates":[-104.895183,39.620609],"type":"Point"}
}