{
  "type": "Feature",
  "properties": {
    "iso:country":"US",
    "sg:address":"7250 State Hwy 73",
    "sg:city":"Evergreen",
    "sg:classifiers":[
        {
            "category":"Building & Trades",
            "subcategory":"Landscaping Services",
            "type":"Services"
        }
    ],
    "sg:phone":"+1 303 674 7573",
    "sg:postcode":"80439",
    "sg:province":"CO",
    "sg:tags":[
        "excavating"
    ],
    "wof:name":"Pearl Scott Inc",
    "wof:placetype":"venue"
},
  "geometry": {"coordinates":[-105.310097,39.584519],"type":"Point"}
}