{
  "type": "Feature",
  "properties": {
    "addr:full":"3661 Star Ranch Rd Colorado Springs CO 80906",
    "addr:housenumber":"3661",
    "addr:postcode":"80906",
    "addr:street":"Star Ranch Rd",
    "iso:country":"US",
    "sg:address":"3661 Star Ranch Rd",
    "sg:city":"Colorado Springs",
    "sg:classifiers":[
        {
            "category":"Education",
            "subcategory":"Dance Studio",
            "type":"Public Place"
        }
    ],
    "sg:phone":"+1 719 579 6657",
    "sg:postcode":"80906",
    "sg:province":"CO",
    "sg:tags":[
        "instruction",
        "dancing"
    ],
    "wof:name":"Synergy Dance Academy",
    "wof:placetype":"venue"
},
  "geometry": {"coordinates":[-104.81723599999999,38.775476],"type":"Point"}
}