{
  "type": "Feature",
  "properties": {
    "addr:full":"3618 Jeannine Dr Colorado Springs CO 80917",
    "addr:postcode":"3618;80917",
    "addr:street":"Jeannine Dr",
    "iso:country":"US",
    "sg:address":"3618 Jeannine Dr",
    "sg:city":"Colorado Springs",
    "sg:classifiers":[
        {
            "category":"Personal",
            "type":"Services"
        }
    ],
    "sg:phone":"+1 719 444 0708",
    "sg:postcode":"80917",
    "sg:province":"CO",
    "sg:tags":[
        "therapist",
        "massage"
    ],
    "wof:name":"Joe's Body Shop",
    "wof:placetype":"venue"
},
  "geometry": {"coordinates":[-104.757317,38.885749],"type":"Point"}
}