{
  "type": "Feature",
  "properties": {
    "addr:full":"1211 E Main St Cortez CO 81321",
    "addr:housenumber":"1211",
    "addr:postcode":"81321",
    "addr:street":"E Main St",
    "iso:country":"US",
    "sg:address":"1211 E Main St",
    "sg:city":"Cortez",
    "sg:classifiers":[
        {
            "category":"Utilities",
            "subcategory":"Mobile Phone",
            "type":"Services"
        }
    ],
    "sg:phone":"+1 970 564 1700",
    "sg:postcode":"81321",
    "sg:province":"CO",
    "sg:tags":[
        "telephone",
        "cellular"
    ],
    "wof:name":"Airtime Cellular",
    "wof:placetype":"venue"
},
  "geometry": {"coordinates":[-108.569475,37.348782],"type":"Point"}
}