{
  "type": "Feature",
  "properties": {
    "addr:full":"2233 Academy Pl Colorado Springs CO 80909",
    "addr:housenumber":"2233",
    "addr:postcode":"80909",
    "addr:street":"Academy Pl",
    "iso:country":"US",
    "sg:address":"2233 Academy Pl",
    "sg:city":"Colorado Springs",
    "sg:classifiers":[
        {
            "category":"Health Services",
            "subcategory":"Health Practitioner",
            "type":"Services"
        }
    ],
    "sg:phone":"+1 719 475 0808",
    "sg:postcode":"80909",
    "sg:province":"CO",
    "sg:tags":[
        "therapist",
        "physical"
    ],
    "wof:name":"Action Potential",
    "wof:placetype":"venue"
},
  "geometry": {"coordinates":[-104.755475,38.866067],"type":"Point"}
}