{
  "type": "Feature",
  "properties": {
    "iso:country":"US",
    "sg:address":"8150 W 48th Avenue",
    "sg:city":"Wheat Ridge",
    "sg:classifiers":[
        {
            "category":"Education",
            "subcategory":"Kindergarten",
            "type":"Public Place"
        }
    ],
    "sg:phone":"+1 303 431 0069",
    "sg:postcode":"80033",
    "sg:province":"CO",
    "sg:tags":[
        "school",
        "driving"
    ],
    "sg:website":"www.ustruck.com",
    "wof:name":"US Truck Driving School",
    "wof:placetype":"venue"
},
  "geometry": {"coordinates":[-105.085792,39.783825],"type":"Point"}
}