{
  "type": "Feature",
  "properties": {
    "addr:full":"1905 Foothills Dr S Golden CO 80401",
    "addr:housenumber":"1905",
    "addr:postcode":"80401",
    "addr:street":"Foothills Dr S",
    "iso:country":"US",
    "sg:address":"1905 Foothills Dr S",
    "sg:city":"Golden",
    "sg:classifiers":[
        {
            "category":"Banks & Credit Unions",
            "subcategory":"Bank",
            "type":"Services"
        }
    ],
    "sg:phone":"+1 303 526 5851",
    "sg:postcode":"80401",
    "sg:province":"CO",
    "sg:tags":[
        "loan",
        "broker",
        "financing",
        "lease"
    ],
    "wof:name":"First Municipal Leasing",
    "wof:placetype":"venue"
},
  "geometry": {"coordinates":[-105.283648,39.682116],"type":"Point"}
}