{
  "type": "Feature",
  "properties": {
    "addr:full":"1740 Wazee St Denver CO 80202",
    "addr:housenumber":"1740",
    "addr:postcode":"80202",
    "addr:street":"Wazee St",
    "iso:country":"US",
    "sg:address":"1740 Wazee St",
    "sg:city":"Denver",
    "sg:classifiers":[
        {
            "category":"Shopping",
            "type":"Retail Goods"
        }
    ],
    "sg:phone":"+1 303 298 1171",
    "sg:postcode":"80202",
    "sg:province":"CO",
    "sg:tags":[
        "merchandise"
    ],
    "wof:name":"Building For Art Lllp",
    "wof:placetype":"venue"
},
  "geometry": {"coordinates":[-104.997997,39.752659],"type":"Point"}
}