{
  "type": "Feature",
  "properties": {
    "iso:country":"US",
    "sg:address":"6789 Niwot Rd",
    "sg:city":"Longmont",
    "sg:phone":"+1 303 530 2545",
    "sg:postcode":"80503",
    "sg:province":"CO",
    "sg:tags":[
        "farm",
        "corn"
    ],
    "wof:name":"Johnny Heil Farm",
    "wof:placetype":"venue"
},
  "geometry": {"coordinates":[-105.186059,40.102944],"type":"Point"}
}