{
  "type": "Feature",
  "properties": {
    "addr:full":"498 Vail Valley Dr Vail CO 81657",
    "addr:housenumber":"498",
    "addr:postcode":"81657",
    "addr:street":"Vail Valley Dr",
    "iso:country":"US",
    "sg:address":"498 Vail Valley Dr",
    "sg:city":"Vail",
    "sg:classifiers":[
        {
            "category":"Social Services",
            "subcategory":"Child Care",
            "type":"Services"
        }
    ],
    "sg:phone":"+1 970 479 3285",
    "sg:postcode":"81657",
    "sg:province":"CO",
    "wof:name":"Small World Nursery",
    "wof:placetype":"venue"
},
  "geometry": {"coordinates":[-106.367672,39.638526],"type":"Point"}
}