{
  "type": "Feature",
  "properties": {
    "iso:country":"US",
    "sg:address":"1776 S Jackson St",
    "sg:city":"Denver",
    "sg:classifiers":[
        {
            "category":"Professional",
            "subcategory":"Accounting & Tax Preparation",
            "type":"Services"
        }
    ],
    "sg:phone":"+1 303 991 0090",
    "sg:postcode":"80210",
    "sg:province":"CO",
    "sg:tags":[
        "accountant"
    ],
    "wof:name":"Mark F Janicki CPA",
    "wof:placetype":"venue"
},
  "geometry": {"coordinates":[-104.942943,39.685306],"type":"Point"}
}