{
  "type": "Feature",
  "properties": {
    "addr:full":"4134 N Townsend Ave Montrose CO 81401",
    "addr:housenumber":"4134",
    "addr:postcode":"81401",
    "addr:street":"N Townsend Ave",
    "iso:country":"US",
    "sg:address":"4134 N Townsend Ave",
    "sg:city":"Montrose",
    "sg:classifiers":[
        {
            "category":"Home & Garden",
            "subcategory":"Building Materials",
            "type":"Retail Goods"
        }
    ],
    "sg:phone":"+1 970 249 7731",
    "sg:postcode":"81401",
    "sg:province":"CO",
    "sg:tags":[
        "brick",
        "stone"
    ],
    "wof:name":"Rocky Mtn Brick & Stone LLC",
    "wof:placetype":"venue"
},
  "geometry": {"coordinates":[-107.919337,38.516745],"type":"Point"}
}