{
  "type": "Feature",
  "properties": {
    "addr:full":"228 Ray Ave Rifle CO 81650",
    "addr:housenumber":"228",
    "addr:postcode":"81650",
    "addr:street":"Ray Ave",
    "iso:country":"US",
    "sg:address":"228 Ray Ave",
    "sg:city":"Rifle",
    "sg:classifiers":[
        {
            "category":"Utilities",
            "subcategory":"Cable",
            "type":"Services"
        }
    ],
    "sg:phone":"+1 970 625 2504",
    "sg:postcode":"81650",
    "sg:province":"CO",
    "sg:tags":[
        "company",
        "system"
    ],
    "wof:name":"AT&T",
    "wof:placetype":"venue"
},
  "geometry": {"coordinates":[-107.801118,39.529177],"type":"Point"}
}