{
  "type": "Feature",
  "properties": {
    "iso:country":"US",
    "sg:address":"10300 E Colfax Ave",
    "sg:city":"Aurora",
    "sg:phone":"+1 303 341 0888",
    "sg:postcode":"80010",
    "sg:province":"CO",
    "wof:name":"New China City",
    "wof:placetype":"venue"
},
  "geometry": {"coordinates":[-104.868202,39.740101],"type":"Point"}
}