{
  "type": "Feature",
  "properties": {
    "addr:full":"9435 S University Blvd Littleton CO 80126",
    "addr:housenumber":"9435",
    "addr:postcode":"80126",
    "addr:street":"S University Blvd",
    "iso:country":"US",
    "sg:address":"9435 S University Blvd",
    "sg:city":"Littleton",
    "sg:classifiers":[
        {
            "category":"Ice Cream",
            "type":"Food & Drink"
        }
    ],
    "sg:menulink":"http://www.allmenus.com/co/sedalia/165051-dairy-queen/menu/",
    "sg:phone":"+1 303 683 1553",
    "sg:postcode":"80126",
    "sg:province":"CO",
    "sg:tags":[
        "burger",
        "american"
    ],
    "wof:name":"Dairy Queen",
    "wof:placetype":"venue"
},
  "geometry": {"coordinates":[-104.945804,39.545695],"type":"Point"}
}