{
  "type": "Feature",
  "properties": {
    "addr:full":"8445 Drayton Hall Dr Colorado Springs CO 80920",
    "addr:housenumber":"8445",
    "addr:postcode":"80920",
    "addr:street":"Drayton Hall Dr",
    "iso:country":"US",
    "sg:address":"8445 Drayton Hall Dr",
    "sg:city":"Colorado Springs",
    "sg:classifiers":[
        {
            "category":"Professional",
            "subcategory":"Computer Services",
            "type":"Services"
        }
    ],
    "sg:phone":"+1 719 471 8731",
    "sg:postcode":"80920",
    "sg:province":"CO",
    "sg:tags":[
        "website",
        "design"
    ],
    "sg:website":"www.i-piece.com",
    "wof:name":"I-Piece Web Site Design",
    "wof:placetype":"venue"
},
  "geometry": {"coordinates":[-104.7616,38.955215],"type":"Point"}
}