{
  "type": "Feature",
  "properties": {
    "iso:country":"US",
    "sg:address":"2449 S Colorado Boulevard",
    "sg:city":"Denver",
    "sg:classifiers":[
        {
            "category":"Real Estate",
            "subcategory":"Real Estate Operator",
            "type":"Services"
        }
    ],
    "sg:phone":"+1 303 758 0915",
    "sg:postcode":"80222",
    "sg:province":"CO",
    "sg:tags":[
        "apartment"
    ],
    "wof:name":"Southern Garden Apartments",
    "wof:placetype":"venue"
},
  "geometry": {"coordinates":[-104.940808,39.672629],"type":"Point"}
}