{
  "type": "Feature",
  "properties": {
    "addr:full":"12745 State Hwy 318 Maybell CO 81626",
    "addr:housenumber":"12745",
    "addr:postcode":"81626",
    "addr:street":"State Hwy 318 Maybell",
    "iso:country":"US",
    "sg:address":"12745 State Hwy 318",
    "sg:city":"Maybell",
    "sg:classifiers":[
        {
            "category":"Food & Beverages",
            "subcategory":"Groceries & Convenience Stores",
            "type":"Retail Goods"
        }
    ],
    "sg:phone":"+1 970 365 3658",
    "sg:postcode":"81626",
    "sg:province":"CO",
    "sg:tags":[
        "auto",
        "rep",
        "station",
        "gasoline",
        "general"
    ],
    "wof:name":"Browns Park Garage",
    "wof:placetype":"venue"
},
  "geometry": {"coordinates":[-108.86271000000001,40.77783],"type":"Point"}
}