{
  "type": "Feature",
  "properties": {
    "iso:country":"US",
    "sg:address":"1330 S Parker Rd",
    "sg:city":"Denver",
    "sg:classifiers":[
        {
            "category":"Home & Garden",
            "subcategory":"Garden Supply",
            "type":"Retail Goods"
        }
    ],
    "sg:phone":"+1 303 755 6585",
    "sg:postcode":"80231",
    "sg:province":"CO",
    "sg:tags":[
        "equipment",
        "lawn",
        "industrial",
        "mower"
    ],
    "wof:name":"Four Seasons Outdoor Equipment",
    "wof:placetype":"venue"
},
  "geometry": {"coordinates":[-104.892211,39.691687],"type":"Point"}
}