{
  "type": "Feature",
  "properties": {
    "iso:country":"US",
    "sg:address":"614 E Kentucky Ave",
    "sg:city":"Denver",
    "sg:classifiers":[
        {
            "category":"Food & Beverages",
            "subcategory":"Bakery",
            "type":"Retail Goods"
        }
    ],
    "sg:phone":"+1 303 722 6779",
    "sg:postcode":"80209",
    "sg:province":"CO",
    "sg:tags":[
        "donut",
        "doughnut"
    ],
    "wof:name":"Chuck's Do-nut Shop",
    "wof:placetype":"venue"
},
  "geometry": {"coordinates":[-104.980003,39.700199],"type":"Point"}
}