{
  "type": "Feature",
  "properties": {
    "iso:country":"US",
    "sg:address":"4272 S Chambers Rd",
    "sg:city":"Aurora",
    "sg:classifiers":[
        {
            "category":"Insurance",
            "subcategory":"Insurance Agent",
            "type":"Services"
        }
    ],
    "sg:phone":"+1 720 870 1076",
    "sg:postcode":"80014",
    "sg:province":"CO",
    "wof:name":"Matthew Deep Ins",
    "wof:placetype":"venue"
},
  "geometry": {"coordinates":[-104.810175,39.639764],"type":"Point"}
}