{
  "type": "Feature",
  "properties": {
    "iso:country":"US",
    "sg:address":"813 8th St",
    "sg:city":"Greeley",
    "sg:classifiers":[
        {
            "category":"Education",
            "subcategory":"Dance Studio",
            "type":"Public Place"
        }
    ],
    "sg:phone":"+1 970 356 7104",
    "sg:postcode":"80631",
    "sg:province":"CO",
    "sg:tags":[
        "instruction",
        "dancing"
    ],
    "wof:name":"Colorado Dance Theatre Inc",
    "wof:placetype":"venue"
},
  "geometry": {"coordinates":[-104.69246099999999,40.42495],"type":"Point"}
}