{
  "type": "Feature",
  "properties": {
    "iso:country":"US",
    "sg:address":"3911 Pearl Dr",
    "sg:city":"Colorado Springs",
    "sg:classifiers":[
        {
            "category":"Shopping",
            "type":"Retail Goods"
        }
    ],
    "sg:phone":"+1 719 209 1048",
    "sg:postcode":"80918",
    "sg:province":"CO",
    "sg:tags":[
        "merchandise"
    ],
    "wof:name":"After Birth Care",
    "wof:placetype":"venue"
},
  "geometry": {"coordinates":[-104.75661100000001,38.898867],"type":"Point"}
}