{
  "type": "Feature",
  "properties": {
    "addr:full":"710 Grand Ave Canon City CO 81212",
    "addr:housenumber":"710",
    "addr:postcode":"81212",
    "addr:street":"Grand Ave",
    "iso:country":"US",
    "sg:address":"710 Grand Ave",
    "sg:city":"Canon City",
    "sg:classifiers":[
        {
            "category":"Professional",
            "subcategory":"Accounting & Tax Preparation",
            "type":"Services"
        }
    ],
    "sg:phone":"+1 719 269 3272",
    "sg:postcode":"81212",
    "sg:province":"CO",
    "sg:tags":[
        "return",
        "filing"
    ],
    "wof:name":"Taylor Tax Svc",
    "wof:placetype":"venue"
},
  "geometry": {"coordinates":[-105.236574,38.428475],"type":"Point"}
}