{
  "type": "Feature",
  "properties": {
    "addr:full":"1059 S Gaylord Street Denver CO 80209",
    "addr:housenumber":"1059",
    "addr:postcode":"80209",
    "addr:street":"S Gaylord Street",
    "iso:country":"US",
    "sg:address":"1059 S Gaylord Street",
    "sg:city":"Denver",
    "sg:classifiers":[
        {
            "category":"Arts & Performance",
            "subcategory":"Art Gallery",
            "type":"Entertainment"
        }
    ],
    "sg:phone":"+1 303 871 0800",
    "sg:postcode":"80209",
    "sg:province":"CO",
    "sg:website":"www.brushstrokesstudio.com",
    "wof:name":"Brushstrokes Studio- Art Gallery",
    "wof:placetype":"venue"
},
  "geometry": {"coordinates":[-104.96157100000001,39.697498],"type":"Point"}
}