{
  "type": "Feature",
  "properties": {
    "iso:country":"US",
    "sg:address":"1650 Briargate Blvd",
    "sg:city":"Colorado Springs",
    "sg:classifiers":[
        {
            "category":"Professional",
            "subcategory":"Accounting & Tax Preparation",
            "type":"Services"
        }
    ],
    "sg:phone":"+1 719 593 4971",
    "sg:postcode":"80920",
    "sg:province":"CO",
    "sg:tags":[
        "return",
        "filing"
    ],
    "wof:name":"H & R Block Tax Svc",
    "wof:placetype":"venue"
},
  "geometry": {"coordinates":[-104.79782400000001,38.945358],"type":"Point"}
}