{
  "type": "Feature",
  "properties": {
    "iso:country":"US",
    "sg:address":"2139 Jerry Murphy Rd",
    "sg:city":"Pueblo",
    "sg:classifiers":[
        {
            "category":"Restaurant",
            "type":"Food & Drink"
        }
    ],
    "sg:phone":"+1 719 542 7344",
    "sg:postcode":"81001",
    "sg:province":"CO",
    "sg:tags":[
        "eating"
    ],
    "wof:name":"Noodles Pasta-Deli Catering Co",
    "wof:placetype":"venue"
},
  "geometry": {"coordinates":[-104.598434,38.30637],"type":"Point"}
}