{
  "type": "Feature",
  "properties": {
    "iso:country":"US",
    "sg:address":"825 S Shields St",
    "sg:city":"Fort Collins",
    "sg:classifiers":[
        {
            "category":"Food & Beverages",
            "subcategory":"Bakery",
            "type":"Retail Goods"
        },
        {
            "category":"Wholesale",
            "subcategory":"Groceries",
            "type":"Manufacturing & Wholesale Goods"
        }
    ],
    "sg:phone":"+1 970 484 8861",
    "sg:postcode":"80521",
    "sg:province":"CO",
    "sg:tags":[
        "cookie",
        "cracker"
    ],
    "wof:name":"Marys Mountain Cookies Inc",
    "wof:placetype":"venue"
},
  "geometry": {"coordinates":[-105.09601600000001,40.574773],"type":"Point"}
}