{
  "type": "Feature",
  "properties": {
    "addr:full":"3220 W Mississippi Ave Denver CO 80219",
    "addr:housenumber":"3220",
    "addr:postcode":"80219",
    "addr:street":"W Mississippi Ave",
    "iso:country":"US",
    "sg:address":"3220 W Mississippi Ave",
    "sg:city":"Denver",
    "sg:classifiers":[
        {
            "category":"Building & Trades",
            "subcategory":"Construction",
            "type":"Services"
        }
    ],
    "sg:phone":"+1 303 935 8437",
    "sg:postcode":"80219",
    "sg:province":"CO",
    "sg:tags":[
        "house"
    ],
    "wof:name":"Esparza Construction",
    "wof:placetype":"venue"
},
  "geometry": {"coordinates":[-105.028696,39.696666],"type":"Point"}
}