{
  "type": "Feature",
  "properties": {
    "iso:country":"US",
    "sg:address":"1550 Larimer St",
    "sg:city":"Denver",
    "sg:classifiers":[
        {
            "category":"Taxi",
            "type":"Transportation"
        }
    ],
    "sg:phone":"+1 720 377 3649",
    "sg:postcode":"80202",
    "sg:province":"CO",
    "sg:tags":[
        "taxicab"
    ],
    "wof:name":"Amerishuttle",
    "wof:placetype":"venue"
},
  "geometry": {"coordinates":[-104.997816,39.748892],"type":"Point"}
}