{
  "type": "Feature",
  "properties": {
    "addr:full":"13788 Ivanhoe St Thornton CO 80602",
    "addr:housenumber":"13788",
    "addr:postcode":"80602",
    "addr:street":"Ivanhoe St",
    "iso:country":"US",
    "sg:address":"13788 Ivanhoe St",
    "sg:city":"Thornton",
    "sg:classifiers":[
        {
            "category":"Building & Trades",
            "subcategory":"Construction",
            "type":"Services"
        }
    ],
    "sg:phone":"+1 303 451 9588",
    "sg:postcode":"80602",
    "sg:province":"CO",
    "sg:tags":[
        "home",
        "builder"
    ],
    "wof:name":"Kaufman & Broad",
    "wof:placetype":"venue"
},
  "geometry": {"coordinates":[-104.921229,39.946518],"type":"Point"}
}