{
  "type": "Feature",
  "properties": {
    "addr:full":"159 Co Rd 205 Durango CO 81301",
    "addr:housenumber":"159;205",
    "addr:postcode":"co 81301",
    "addr:street":"Co Rd",
    "iso:country":"US",
    "sg:address":"159 Co Rd 205",
    "sg:city":"Durango",
    "sg:classifiers":[
        {
            "category":"Building & Trades",
            "subcategory":"Construction",
            "type":"Services"
        }
    ],
    "sg:phone":"+1 970 385 6773",
    "sg:postcode":"81301",
    "sg:province":"CO",
    "sg:tags":[
        "contractor"
    ],
    "wof:name":"Seibel Construction Inc",
    "wof:placetype":"venue"
},
  "geometry": {"coordinates":[-107.896075,37.324598],"type":"Point"}
}