{
  "type": "Feature",
  "properties": {
    "iso:country":"US",
    "sg:address":"22372 E Mercer Pl",
    "sg:city":"Aurora",
    "sg:classifiers":[
        {
            "category":"Professional",
            "type":"Services"
        }
    ],
    "sg:phone":"+1 720 870 1679",
    "sg:postcode":"80018",
    "sg:province":"CO",
    "wof:name":"Starrcon LLC",
    "wof:placetype":"venue"
},
  "geometry": {"coordinates":[-104.72783,39.644057],"type":"Point"}
}