{
  "type": "Feature",
  "properties": {
    "iso:country":"US",
    "sg:address":"7253 Monaco St",
    "sg:city":"Commerce City",
    "sg:classifiers":[
        {
            "category":"Shopping",
            "subcategory":"Department Store",
            "type":"Retail Goods"
        }
    ],
    "sg:phone":"+1 303 289 3192",
    "sg:postcode":"80022",
    "sg:province":"CO",
    "wof:name":"Dollar Mart",
    "wof:placetype":"venue"
},
  "geometry": {"coordinates":[-104.912109,39.829251],"type":"Point"}
}