{
  "type": "Feature",
  "properties": {
    "iso:country":"US",
    "sg:address":"3975 E 56th Ave",
    "sg:city":"Commerce City",
    "sg:classifiers":[
        {
            "category":"Utilities",
            "subcategory":"Refuse",
            "type":"Services"
        }
    ],
    "sg:phone":"+1 303 681 3321",
    "sg:postcode":"80022",
    "sg:province":"CO",
    "sg:tags":[
        "system"
    ],
    "wof:name":"Rubbish Solutions",
    "wof:placetype":"venue"
},
  "geometry": {"coordinates":[-104.93902300000001,39.798378],"type":"Point"}
}