{
  "type": "Feature",
  "properties": {
    "addr:full":"13250 US Hwy 40 Hayden CO 81639",
    "addr:housenumber":"13250",
    "addr:postcode":"81639",
    "addr:street":"Us Hwy 40",
    "iso:country":"US",
    "sg:address":"13250 US Hwy 40",
    "sg:city":"Hayden",
    "sg:classifiers":[
        {
            "category":"Farming",
            "subcategory":"Livestock Farm",
            "type":"Manufacturing & Wholesale Goods"
        }
    ],
    "sg:phone":"+1 970 276 4626",
    "sg:postcode":"81639",
    "sg:province":"CO",
    "sg:tags":[
        "ranch"
    ],
    "wof:name":"Carpenter Ranch",
    "wof:placetype":"venue"
},
  "geometry": {"coordinates":[-107.183699,40.495098],"type":"Point"}
}