{
  "type": "Feature",
  "properties": {
    "iso:country":"US",
    "sg:address":"182 16th St",
    "sg:city":"Burlington",
    "sg:classifiers":[
        {
            "category":"Health Services",
            "subcategory":"Doctor",
            "type":"Services"
        }
    ],
    "sg:phone":"+1 719 346 9481",
    "sg:postcode":"80807",
    "sg:province":"CO",
    "sg:tags":[
        "clinic",
        "medical"
    ],
    "wof:name":"Parke Health Center",
    "wof:placetype":"venue"
},
  "geometry": {"coordinates":[-102.27061999999999,39.301214],"type":"Point"}
}