{
  "type": "Feature",
  "properties": {
    "addr:full":"1450 Main St Longmont CO 80501",
    "addr:housenumber":"1450",
    "addr:postcode":"80501",
    "addr:street":"Main St",
    "iso:country":"US",
    "sg:address":"1450 Main St",
    "sg:city":"Longmont",
    "sg:classifiers":[
        {
            "category":"Shopping",
            "subcategory":"Crafts & Fabrics",
            "type":"Retail Goods"
        }
    ],
    "sg:phone":"+1 303 651 9205",
    "sg:postcode":"80501",
    "sg:province":"CO",
    "sg:tags":[
        "shop",
        "sewing"
    ],
    "wof:name":"Fabric Yard",
    "wof:placetype":"venue"
},
  "geometry": {"coordinates":[-105.102289,40.182138],"type":"Point"}
}