{
  "type": "Feature",
  "properties": {
    "addr:full":"2124 E 18th St Greeley CO 80631",
    "addr:housenumber":"2124",
    "addr:postcode":"80631",
    "addr:street":"E 18Th St",
    "iso:country":"US",
    "sg:address":"2124 E 18th St",
    "sg:city":"Greeley",
    "sg:classifiers":[
        {
            "category":"Building & Trades",
            "subcategory":"Construction",
            "type":"Services"
        }
    ],
    "sg:phone":"+1 970 353 7037",
    "sg:postcode":"80631",
    "sg:province":"CO",
    "sg:tags":[
        "concrete",
        "contractor"
    ],
    "wof:name":"Gcs",
    "wof:placetype":"venue"
},
  "geometry": {"coordinates":[-104.647964,40.410103],"type":"Point"}
}