{
  "type": "Feature",
  "properties": {
    "iso:country":"US",
    "sg:address":"4902 W 103rd Pl",
    "sg:city":"Westminster",
    "sg:classifiers":[
        {
            "category":"Professional",
            "subcategory":"Secretarial Services",
            "type":"Services"
        }
    ],
    "sg:phone":"+1 303 466 6425",
    "sg:postcode":"80031",
    "sg:province":"CO",
    "sg:tags":[
        "typing"
    ],
    "sg:website":"www.neighborlynews.com",
    "wof:name":"Mind Your Business",
    "wof:placetype":"venue"
},
  "geometry": {"coordinates":[-105.04926,39.884041],"type":"Point"}
}