{
  "type": "Feature",
  "properties": {
    "addr:city":"Pueblo",
    "addr:full":"419 W 14Th St Pueblo, Co 81003-2707",
    "addr:house_number":"419",
    "addr:housenumber":"419",
    "addr:phone":"+1 719-545-5290",
    "addr:postcode":"81003-2707",
    "addr:road":"W 14Th St",
    "addr:state":"CO",
    "addr:street":"W 14Th St",
    "iso:country":"US",
    "sg:address":"419 W 14th St",
    "sg:city":"Pueblo",
    "sg:classifiers":[
        {
            "category":"Museum",
            "type":"Entertainment"
        }
    ],
    "sg:phone":"+1 719 545 5290",
    "sg:postcode":"81003",
    "sg:province":"CO",
    "sg:website":"www.rosemount.org",
    "wof:airports":[
        102532457
    ],
    "wof:name":"Rosemount Museum",
    "wof:placetype":"venue"
},
  "geometry": {"coordinates":[-104.61203999999999,38.27992],"type":"Point"}
}