{
  "type": "Feature",
  "properties": {
    "iso:country":"US",
    "sg:address":"419 W 14th St",
    "sg:city":"Pueblo",
    "sg:classifiers":[
        {
            "category":"Museum",
            "type":"Entertainment"
        }
    ],
    "sg:phone":"+1 719 545 5290",
    "sg:postcode":"81003",
    "sg:province":"CO",
    "sg:website":"www.rosemount.org",
    "wof:name":"Rosemount Museum",
    "wof:placetype":"venue"
},
  "geometry": {"coordinates":[-104.613051,38.279908],"type":"Point"}
}