{
  "type": "Feature",
  "properties": {
    "addr:full":"226 Greenwood Ave Crawford CO 81415",
    "addr:housenumber":"226",
    "addr:postcode":"81415",
    "addr:street":"Greenwood Ave",
    "iso:country":"US",
    "sg:address":"226 Greenwood Ave",
    "sg:city":"Crawford",
    "sg:classifiers":[
        {
            "category":"Retail",
            "subcategory":"Repair Shop",
            "type":"Services"
        }
    ],
    "sg:phone":"+1 970 921 3229",
    "sg:postcode":"81415",
    "sg:province":"CO",
    "sg:tags":[
        "welding"
    ],
    "wof:name":"Roland's Welding",
    "wof:placetype":"venue"
},
  "geometry": {"coordinates":[-107.61242799999999,38.706475],"type":"Point"}
}