{
  "type": "Feature",
  "properties": {
    "iso:country":"US",
    "sg:address":"11770 Jackson St",
    "sg:city":"Denver",
    "sg:classifiers":[
        {
            "category":"Freight",
            "type":"Transportation"
        }
    ],
    "sg:phone":"+1 303 252 7896",
    "sg:postcode":"80233",
    "sg:province":"CO",
    "sg:tags":[
        "operator",
        "trucking"
    ],
    "wof:name":"DLM Auto Transporters Inc",
    "wof:placetype":"venue"
},
  "geometry": {"coordinates":[-104.941895,39.908805],"type":"Point"}
}