{
  "type": "Feature",
  "properties": {
    "addr:full":"2770 E Uintah St Colorado Springs CO 80909",
    "addr:housenumber":"2770",
    "addr:postcode":"80909",
    "addr:street":"E Uintah St",
    "iso:country":"US",
    "sg:address":"2770 E Uintah St",
    "sg:city":"Colorado Springs",
    "sg:classifiers":[
        {
            "category":"Government",
            "subcategory":"Office",
            "type":"Public Place"
        }
    ],
    "sg:phone":"+1 719 526 3572",
    "sg:postcode":"80909",
    "sg:province":"CO",
    "sg:tags":[
        "national",
        "security"
    ],
    "wof:name":"Fox Troop Second Squadron",
    "wof:placetype":"venue"
},
  "geometry": {"coordinates":[-104.77593299999999,38.849046],"type":"Point"}
}