{
  "type": "Feature",
  "properties": {
    "iso:country":"US",
    "sg:address":"111 Dupps Ave",
    "sg:city":"Pueblo",
    "sg:classifiers":[
        {
            "category":"Professional",
            "type":"Services"
        }
    ],
    "sg:phone":"+1 719 561 2882",
    "sg:postcode":"81005",
    "sg:province":"CO",
    "wof:name":"Marvin D Cortner",
    "wof:placetype":"venue"
},
  "geometry": {"coordinates":[-104.650983,38.263099],"type":"Point"}
}