{
  "type": "Feature",
  "properties": {
    "iso:country":"US",
    "sg:address":"2905 S Zurich Ct",
    "sg:city":"Denver",
    "sg:classifiers":[
        {
            "category":"Professional",
            "type":"Services"
        },
        {
            "category":"Professional",
            "subcategory":"Business Services",
            "type":"Services"
        }
    ],
    "sg:phone":"+1 303 975 4585",
    "sg:postcode":"80236",
    "sg:province":"CO",
    "sg:tags":[
        "embroidery"
    ],
    "wof:name":"Flutter By Designs",
    "wof:placetype":"venue"
},
  "geometry": {"coordinates":[-105.05214599999999,39.659802],"type":"Point"}
}