{
  "type": "Feature",
  "properties": {
    "iso:country":"US",
    "sg:address":"1300 S Inca St",
    "sg:city":"Denver",
    "sg:classifiers":[
        {
            "category":"Building & Trades",
            "subcategory":"Electrical",
            "type":"Services"
        }
    ],
    "sg:phone":"+1 303 733 6244",
    "sg:postcode":"80223",
    "sg:province":"CO",
    "sg:tags":[
        "electrical",
        "contractor"
    ],
    "wof:name":"International Electric Inc",
    "wof:placetype":"venue"
},
  "geometry": {"coordinates":[-104.99803300000001,39.691126],"type":"Point"}
}