{
  "type": "Feature",
  "properties": {
    "iso:country":"US",
    "sg:address":"28065 Harebell Ln",
    "sg:city":"Evergreen",
    "sg:classifiers":[
        {
            "category":"Arts & Performance",
            "subcategory":"Theater",
            "type":"Entertainment"
        }
    ],
    "sg:phone":"+1 303 882 0652",
    "sg:postcode":"80439",
    "sg:province":"CO",
    "sg:tags":[
        "live",
        "music"
    ],
    "wof:name":"O'Brien Family Band",
    "wof:placetype":"venue"
},
  "geometry": {"coordinates":[-105.319131,39.638877],"type":"Point"}
}