{
  "type": "Feature",
  "properties": {
    "addr:full":"275 S 3rd Ave Brighton CO 80601",
    "addr:housenumber":"275",
    "addr:postcode":"80601",
    "addr:street":"S 3Rd Ave",
    "iso:country":"US",
    "sg:address":"275 S 3rd Ave",
    "sg:city":"Brighton",
    "sg:classifiers":[
        {
            "category":"Home & Garden",
            "subcategory":"Garden Supply",
            "type":"Retail Goods"
        }
    ],
    "sg:phone":"+1 303 659 4169",
    "sg:postcode":"80601",
    "sg:province":"CO",
    "sg:tags":[
        "sprinkler"
    ],
    "wof:name":"Bee-Line Sprinkler Inc",
    "wof:placetype":"venue"
},
  "geometry": {"coordinates":[-104.81958400000001,39.983288],"type":"Point"}
}