{
  "type": "Feature",
  "properties": {
    "addr:full":"6700 E Colfax Ave Denver CO 80220",
    "addr:housenumber":"6700",
    "addr:postcode":"80220",
    "addr:street":"E Colfax Ave",
    "iso:country":"US",
    "sg:address":"6700 E Colfax Ave",
    "sg:city":"Denver",
    "sg:classifiers":[
        {
            "category":"Banks & Credit Unions",
            "subcategory":"Bank",
            "type":"Services"
        }
    ],
    "sg:phone":"+1 303 333 2910",
    "sg:postcode":"80220",
    "sg:province":"CO",
    "wof:name":"Zion United Credit UNION",
    "wof:placetype":"venue"
},
  "geometry": {"coordinates":[-104.909356,39.740147],"type":"Point"}
}