{
  "type": "Feature",
  "properties": {
    "iso:country":"US",
    "sg:address":"5650 E Evans Ave",
    "sg:city":"Denver",
    "sg:classifiers":[
        {
            "category":"Food & Beverages",
            "subcategory":"Meat & Fish",
            "type":"Retail Goods"
        }
    ],
    "sg:phone":"+1 303 300 6568",
    "sg:postcode":"80222",
    "sg:province":"CO",
    "sg:tags":[
        "seafood"
    ],
    "wof:name":"United Ocean Seafood",
    "wof:placetype":"venue"
},
  "geometry": {"coordinates":[-104.921273,39.678386],"type":"Point"}
}