{
  "type": "Feature",
  "properties": {
    "iso:country":"US",
    "sg:address":"3500 Woodgate Rd",
    "sg:city":"Montrose",
    "sg:classifiers":[
        {
            "category":"Education",
            "subcategory":"School",
            "type":"Public Place"
        }
    ],
    "sg:phone":"+1 970 249 2539",
    "sg:postcode":"81401",
    "sg:province":"CO",
    "wof:name":"Cottonwood Elementary School",
    "wof:placetype":"venue"
},
  "geometry": {"coordinates":[-107.864323,38.45434],"type":"Point"}
}