{
  "type": "Feature",
  "properties": {
    "addr:full":"833 W Crestline Ave Littleton CO 80120",
    "addr:housenumber":"833",
    "addr:postcode":"80120",
    "addr:street":"W Crestline Ave",
    "iso:country":"US",
    "sg:address":"833 W Crestline Ave",
    "sg:city":"Littleton",
    "sg:classifiers":[
        {
            "category":"Banks & Credit Unions",
            "subcategory":"Bank",
            "type":"Services"
        }
    ],
    "sg:phone":"+1 303 730 2287",
    "sg:postcode":"80120",
    "sg:province":"CO",
    "sg:tags":[
        "assistance",
        "foreclosure"
    ],
    "wof:name":"Outhouse Foreclosures",
    "wof:placetype":"venue"
},
  "geometry": {"coordinates":[-104.998504,39.619139],"type":"Point"}
}