{
  "type": "Feature",
  "properties": {
    "addr:full":"11000 W Colfax Ave Denver CO 80215",
    "addr:housenumber":"11000",
    "addr:postcode":"80215",
    "addr:street":"W Colfax Ave",
    "iso:country":"US",
    "sg:address":"11000 W Colfax Ave",
    "sg:city":"Denver",
    "sg:classifiers":[
        {
            "category":"Autos & Motor Vehicles",
            "subcategory":"Automobile Sales",
            "type":"Retail Goods"
        }
    ],
    "sg:phone":"+1 303 232 2200",
    "sg:postcode":"80215",
    "sg:province":"CO",
    "sg:tags":[
        "a",
        "car",
        "used",
        "dealer",
        "general"
    ],
    "wof:name":"Lakewood Fordland",
    "wof:placetype":"venue"
},
  "geometry": {"coordinates":[-105.121526,39.740114],"type":"Point"}
}