{
  "type": "Feature",
  "properties": {
    "addr:full":"3509 Erving Ct Berthoud CO 80513",
    "addr:housenumber":"3509",
    "addr:postcode":"80513",
    "addr:street":"Erving Ct",
    "iso:country":"US",
    "sg:address":"3509 Erving Ct",
    "sg:city":"Berthoud",
    "sg:classifiers":[
        {
            "category":"Manufacturing",
            "subcategory":"Retail Goods",
            "type":"Manufacturing & Wholesale Goods"
        }
    ],
    "sg:phone":"+1 970 532 7026",
    "sg:postcode":"80513",
    "sg:province":"CO",
    "sg:tags":[
        "lead",
        "mfg"
    ],
    "wof:name":"Creative Products of Colorado",
    "wof:placetype":"venue"
},
  "geometry": {"coordinates":[-105.13763299999999,40.298559],"type":"Point"}
}