{
  "type": "Feature",
  "properties": {
    "addr:full":"19 Stassinos Ranch Rd Rock Springs CO 82901",
    "addr:housenumber":"19",
    "addr:postcode":"82901",
    "addr:street":"Stassinos Ranch Rd",
    "iso:country":"US",
    "sg:address":"19 Stassinos Ranch Rd",
    "sg:city":"Rock Springs",
    "sg:classifiers":[
        {
            "category":"Freight",
            "type":"Transportation"
        }
    ],
    "sg:phone":"+1 307 362 9066",
    "sg:postcode":"82901",
    "sg:province":"CO",
    "sg:tags":[
        "trucking"
    ],
    "wof:name":"O'Toole's Hot Shot Svc",
    "wof:placetype":"venue"
},
  "geometry": {"coordinates":[-109.285884,41.69344],"type":"Point"}
}