{
  "type": "Feature",
  "properties": {
    "addr:full":"1209 E Caramillo St Colorado Springs CO 80909",
    "addr:housenumber":"1209",
    "addr:postcode":"80909",
    "addr:street":"E Caramillo St",
    "iso:country":"US",
    "sg:address":"1209 E Caramillo St",
    "sg:city":"Colorado Springs",
    "sg:classifiers":[
        {
            "category":"Social Services",
            "subcategory":"Adult Care",
            "type":"Services"
        }
    ],
    "sg:phone":"+1 719 473 4239",
    "sg:postcode":"80909",
    "sg:province":"CO",
    "sg:tags":[
        "residential"
    ],
    "wof:name":"Crestview Manor",
    "wof:placetype":"venue"
},
  "geometry": {"coordinates":[-104.798829,38.855155],"type":"Point"}
}