{
  "type": "Feature",
  "properties": {
    "iso:country":"US",
    "sg:address":"613 Oak St",
    "sg:city":"Steamboat Springs",
    "sg:classifiers":[
        {
            "category":"Food & Beverages",
            "subcategory":"Liquor & Beverages",
            "type":"Retail Goods"
        }
    ],
    "sg:phone":"+1 970 879 8249",
    "sg:postcode":"80487",
    "sg:province":"CO",
    "sg:tags":[
        "alcoholic"
    ],
    "wof:name":"High Ctry Home Brew & Wine Sup",
    "wof:placetype":"venue"
},
  "geometry": {"coordinates":[-106.832268,40.485975],"type":"Point"}
}