{
  "type": "Feature",
  "properties": {
    "iso:country":"US",
    "sg:address":"5453 W 88th Ave",
    "sg:city":"Westminster",
    "sg:classifiers":[
        {
            "category":"Health Services",
            "subcategory":"Optometrist",
            "type":"Services"
        }
    ],
    "sg:phone":"+1 303 429 6366",
    "sg:postcode":"80031",
    "sg:province":"CO",
    "wof:name":"Susan Eissenberg OD",
    "wof:placetype":"venue"
},
  "geometry": {"coordinates":[-105.06151300000001,39.856559],"type":"Point"}
}