{
  "type": "Feature",
  "properties": {
    "addr:full":"1805 Cottonwood Point Dr Fort Collins CO 80524",
    "addr:housenumber":"1805",
    "addr:postcode":"80524",
    "addr:street":"Cottonwood Point Dr",
    "iso:country":"US",
    "sg:address":"1805 Cottonwood Point Dr",
    "sg:city":"Fort Collins",
    "sg:classifiers":[
        {
            "category":"Professional",
            "type":"Services"
        }
    ],
    "sg:phone":"+1 970 482 7325",
    "sg:postcode":"80524",
    "sg:province":"CO",
    "wof:name":"Nomad Air LLC",
    "wof:placetype":"venue"
},
  "geometry": {"coordinates":[-105.044252,40.619336],"type":"Point"}
}