{
  "type": "Feature",
  "properties": {
    "iso:country":"US",
    "sg:address":"511 Red Lady Ave",
    "sg:city":"Crested Butte",
    "sg:classifiers":[
        {
            "category":"Professional",
            "subcategory":"Management & Consulting",
            "type":"Services"
        }
    ],
    "sg:phone":"+1 970 349 1939",
    "sg:postcode":"81224",
    "sg:province":"CO",
    "sg:tags":[
        "marketing",
        "program"
    ],
    "sg:website":"www.xsportsnetwork.com",
    "wof:name":"Mountain Sports Intl",
    "wof:placetype":"venue"
},
  "geometry": {"coordinates":[-106.98244699999999,38.866232],"type":"Point"}
}