{
  "type": "Feature",
  "properties": {
    "addr:full":"3301 S Grant St Englewood CO 80113",
    "addr:housenumber":"3301",
    "addr:postcode":"80113",
    "addr:street":"S Grant St",
    "iso:country":"US",
    "sg:address":"3301 S Grant St",
    "sg:city":"Englewood",
    "sg:classifiers":[
        {
            "category":"Social Services",
            "type":"Services"
        }
    ],
    "sg:phone":"+1 303 762 9525",
    "sg:postcode":"80113",
    "sg:province":"CO",
    "sg:tags":[
        "shelter",
        "homeless"
    ],
    "sg:website":"www.thefamilytree.org",
    "wof:name":"House Of Hope",
    "wof:placetype":"venue"
},
  "geometry": {"coordinates":[-104.9841,39.654982],"type":"Point"}
}