{
  "type": "Feature",
  "properties": {
    "addr:full":"1625 Court Place Denver CO 80202",
    "addr:housenumber":"1625",
    "addr:postcode":"80202",
    "addr:street":"Court Place",
    "iso:country":"US",
    "sg:address":"1625 Court Place",
    "sg:city":"Denver",
    "sg:classifiers":[
        {
            "category":"Retail",
            "subcategory":"Laundry & Dry Cleaning",
            "type":"Services"
        }
    ],
    "sg:phone":"+1 303 595 9988",
    "sg:postcode":"80202",
    "sg:province":"CO",
    "wof:name":"Dependable Cleaners",
    "wof:placetype":"venue"
},
  "geometry": {"coordinates":[-104.9884,39.742751],"type":"Point"}
}