{
  "type": "Feature",
  "properties": {
    "iso:country":"US",
    "sg:address":"435 14th Ave",
    "sg:city":"Greeley",
    "sg:classifiers":[
        {
            "category":"Shopping",
            "subcategory":"Clothing, Apparel, & Fashions",
            "type":"Retail Goods"
        }
    ],
    "sg:phone":"+1 970 378 1133",
    "sg:postcode":"80631",
    "sg:province":"CO",
    "wof:name":"El Piteado",
    "wof:placetype":"venue"
},
  "geometry": {"coordinates":[-104.70164,40.429862],"type":"Point"}
}