{
  "type": "Feature",
  "properties": {
    "addr:full":"1870 Ski Time Square Dr Steamboat Spgs CO 80487",
    "addr:postcode":"1870;80487",
    "addr:street":"Square Dr;Spgs",
    "iso:country":"US",
    "sg:address":"1870 Ski Time Square Dr",
    "sg:city":"Steamboat Spgs",
    "sg:classifiers":[
        {
            "category":"Cinema",
            "subcategory":"Movie Theater",
            "type":"Entertainment"
        }
    ],
    "sg:phone":"+1 970 879 7299",
    "sg:postcode":"80487",
    "sg:province":"CO",
    "wof:name":"Mountain Movie",
    "wof:placetype":"venue"
},
  "geometry": {"coordinates":[-106.803528,40.460106],"type":"Point"}
}