{
  "type": "Feature",
  "properties": {
    "iso:country":"US",
    "sg:address":"1001 SW Frontage Rd",
    "sg:city":"Fort Collins",
    "sg:classifiers":[
        {
            "category":"Shopping",
            "type":"Retail Goods"
        }
    ],
    "sg:phone":"+1 970 482 7887",
    "sg:postcode":"80524",
    "sg:province":"CO",
    "sg:tags":[
        "merchandise"
    ],
    "wof:name":"J & J Sales",
    "wof:placetype":"venue"
},
  "geometry": {"coordinates":[-105.00169,40.577906],"type":"Point"}
}