{
  "type": "Feature",
  "properties": {
    "iso:country":"US",
    "sg:address":"59 Mount Harvard Rd",
    "sg:city":"Livermore",
    "sg:classifiers":[
        {
            "category":"Home & Garden",
            "subcategory":"Furniture",
            "type":"Retail Goods"
        }
    ],
    "sg:phone":"+1 970 482 8746",
    "sg:postcode":"80536",
    "sg:province":"CO",
    "sg:tags":[
        "builder",
        "custom"
    ],
    "wof:name":"Elkhorncreek Designs Log",
    "wof:placetype":"venue"
},
  "geometry": {"coordinates":[-105.411934,40.741657],"type":"Point"}
}