{
  "type": "Feature",
  "properties": {
    "addr:full":"878 E 2nd Ave Durango CO 81301",
    "addr:housenumber":"878",
    "addr:postcode":"co 81301",
    "addr:street":"E 2Nd Ave",
    "iso:country":"US",
    "sg:address":"878 E 2nd Ave",
    "sg:city":"Durango",
    "sg:classifiers":[
        {
            "category":"Organizations",
            "subcategory":"Community Association",
            "type":"Services"
        }
    ],
    "sg:phone":"+1 970 247 1590",
    "sg:postcode":"81301",
    "sg:province":"CO",
    "sg:tags":[
        "military"
    ],
    "wof:name":"American Legion",
    "wof:placetype":"venue"
},
  "geometry": {"coordinates":[-107.879538,37.272235],"type":"Point"}
}