{
  "type": "Feature",
  "properties": {
    "addr:full":"1151 S Huron St Denver CO 80223",
    "addr:housenumber":"1151",
    "addr:postcode":"80223",
    "addr:street":"S Huron St",
    "iso:country":"US",
    "sg:address":"1151 S Huron St",
    "sg:city":"Denver",
    "sg:classifiers":[
        {
            "category":"Freight",
            "type":"Transportation"
        }
    ],
    "sg:phone":"+1 303 477 8989",
    "sg:postcode":"80223",
    "sg:province":"CO",
    "sg:tags":[
        "operator",
        "delivery",
        "local",
        "trucking"
    ],
    "wof:name":"Flash Delivery Srvc",
    "wof:placetype":"venue"
},
  "geometry": {"coordinates":[-104.996877,39.695797],"type":"Point"}
}