{
  "type": "Feature",
  "properties": {
    "addr:full":"3975 E 56th Avenue Commerce City CO 80022",
    "addr:housenumber":"3975",
    "addr:postcode":"80022",
    "addr:street":"E 56Th Avenue",
    "iso:country":"US",
    "sg:address":"3975 E 56th Avenue",
    "sg:city":"Commerce City",
    "sg:classifiers":[
        {
            "category":"Food & Beverages",
            "subcategory":"Groceries & Convenience Stores",
            "type":"Retail Goods"
        }
    ],
    "sg:phone":"+1 303 297 9112",
    "sg:postcode":"80022",
    "sg:province":"CO",
    "sg:website":"www.rockymountainpropane.com",
    "wof:name":"Rocky Mountain Propane",
    "wof:placetype":"venue"
},
  "geometry": {"coordinates":[-104.93857300000001,39.79835],"type":"Point"}
}