{
  "type": "Feature",
  "properties": {
    "addr:full":"10648 Huron St Northglenn CO 80234",
    "addr:housenumber":"10648",
    "addr:postcode":"80234",
    "addr:street":"Huron St",
    "iso:country":"US",
    "sg:address":"10648 Huron St",
    "sg:city":"Northglenn",
    "sg:classifiers":[
        {
            "category":"Retail",
            "subcategory":"Repair Shop",
            "type":"Services"
        }
    ],
    "sg:phone":"+1 303 451 9040",
    "sg:postcode":"80234",
    "sg:province":"CO",
    "sg:tags":[
        "related"
    ],
    "wof:name":"Bargain Dealer",
    "wof:placetype":"venue"
},
  "geometry": {"coordinates":[-104.99651,39.889973],"type":"Point"}
}