{
  "type": "Feature",
  "properties": {
    "iso:country":"US",
    "sg:address":"2999 N New Center Pt",
    "sg:city":"Colorado Springs",
    "sg:classifiers":[
        {
            "category":"Health Services",
            "subcategory":"Health Practitioner",
            "type":"Services"
        }
    ],
    "sg:phone":"+1 719 365 5842",
    "sg:postcode":"80922",
    "sg:province":"CO",
    "sg:tags":[
        "therapist",
        "physical"
    ],
    "sg:website":"www.memorialhospital.com",
    "wof:name":"Memorial Hospital Rehab Ctr",
    "wof:placetype":"venue"
},
  "geometry": {"coordinates":[-104.718017,38.873545],"type":"Point"}
}