{
  "type": "Feature",
  "properties": {
    "addr:full":"383 Pika Pt Lafayette CO 80026",
    "addr:housenumber":"383",
    "addr:postcode":"80026",
    "addr:street":"Pika Pt",
    "iso:country":"US",
    "sg:address":"383 Pika Pt",
    "sg:city":"Lafayette",
    "sg:classifiers":[
        {
            "category":"Organizations",
            "subcategory":"Professional Association",
            "type":"Services"
        }
    ],
    "sg:phone":"+1 303 666 4100",
    "sg:postcode":"80026",
    "sg:province":"CO",
    "wof:name":"Lafayette Girls Softball Assn",
    "wof:placetype":"venue"
},
  "geometry": {"coordinates":[-105.098924,39.971542],"type":"Point"}
}