{
  "type": "Feature",
  "properties": {
    "iso:country":"US",
    "sg:address":"106 W Main St",
    "sg:city":"Florence",
    "sg:classifiers":[
        {
            "category":"Shopping",
            "subcategory":"Crafts & Fabrics",
            "type":"Retail Goods"
        }
    ],
    "sg:phone":"+1 719 784 0775",
    "sg:postcode":"81226",
    "sg:province":"CO",
    "sg:tags":[
        "sewing",
        "yarn"
    ],
    "wof:name":"D J's Fibercrafts",
    "wof:placetype":"venue"
},
  "geometry": {"coordinates":[-105.119305,38.390294],"type":"Point"}
}