{
  "type": "Feature",
  "properties": {
    "addr:full":"6995 W 120th Ave Broomfield CO 80020",
    "addr:housenumber":"6995",
    "addr:postcode":"80020",
    "addr:street":"W 120Th Ave",
    "iso:country":"US",
    "sg:address":"6995 W 120th Ave",
    "sg:city":"Broomfield",
    "sg:classifiers":[
        {
            "category":"Education",
            "subcategory":"School",
            "type":"Public Place"
        }
    ],
    "sg:phone":"+1 303 469 2049",
    "sg:postcode":"80020",
    "sg:province":"CO",
    "wof:name":"Beautiful Savior Lutheran Schl",
    "wof:placetype":"venue"
},
  "geometry": {"coordinates":[-105.07530300000001,39.914423],"type":"Point"}
}