{
  "type": "Feature",
  "properties": {
    "iso:country":"US",
    "sg:address":"693 Peoria St",
    "sg:city":"Aurora",
    "sg:classifiers":[
        {
            "category":"Restaurant",
            "type":"Food & Drink"
        }
    ],
    "sg:phone":"+1 303 366 2223",
    "sg:postcode":"80011",
    "sg:province":"CO",
    "sg:tags":[
        "eating"
    ],
    "wof:name":"Imperial Cafe",
    "wof:placetype":"venue"
},
  "geometry": {"coordinates":[-104.847269,39.727379],"type":"Point"}
}