{
  "type": "Feature",
  "properties": {
    "iso:country":"US",
    "sg:address":"7675 W 14th Ave",
    "sg:city":"Lakewood",
    "sg:classifiers":[
        {
            "category":"Insurance",
            "subcategory":"Hazard Insurance",
            "type":"Services"
        }
    ],
    "sg:phone":"+1 303 548 1155",
    "sg:postcode":"80214",
    "sg:province":"CO",
    "sg:tags":[
        "bond"
    ],
    "wof:name":"No Bull Bail Bonds",
    "wof:placetype":"venue"
},
  "geometry": {"coordinates":[-105.081737,39.738534],"type":"Point"}
}