{
  "type": "Feature",
  "properties": {
    "addr:full":"2450 E Arapahoe Rd Littleton CO 80122",
    "addr:housenumber":"2450",
    "addr:postcode":"80122",
    "addr:street":"E Arapahoe Rd",
    "iso:country":"US",
    "sg:address":"2450 E Arapahoe Rd",
    "sg:city":"Littleton",
    "sg:classifiers":[
        {
            "category":"Personal",
            "type":"Services"
        }
    ],
    "sg:phone":"+1 303 488 9797",
    "sg:postcode":"80122",
    "sg:province":"CO",
    "sg:tags":[
        "loss",
        "center",
        "weight"
    ],
    "wof:name":"Jenny Craig",
    "wof:placetype":"venue"
},
  "geometry": {"coordinates":[-104.95854799999999,39.595072],"type":"Point"}
}