{
  "type": "Feature",
  "properties": {
    "iso:country":"US",
    "sg:address":"256 Nashua Ct",
    "sg:city":"Grand Junction",
    "sg:classifiers":[
        {
            "category":"Manufacturing",
            "subcategory":"Printing",
            "type":"Manufacturing & Wholesale Goods"
        }
    ],
    "sg:phone":"+1 970 243 8780",
    "sg:postcode":"81503",
    "sg:province":"CO",
    "sg:tags":[
        "house",
        "book"
    ],
    "wof:name":"Centennial Classic Sale",
    "wof:placetype":"venue"
},
  "geometry": {"coordinates":[-108.53787800000001,39.042234],"type":"Point"}
}