{
  "type": "Feature",
  "properties": {
    "addr:full":"5314 Co Rd 154 Glenwood Springs CO 81601",
    "addr:housenumber":"5314;154",
    "addr:postcode":"81601",
    "addr:street":"Co Rd",
    "iso:country":"US",
    "sg:address":"5314 Co Rd 154",
    "sg:city":"Glenwood Springs",
    "sg:classifiers":[
        {
            "category":"Building & Trades",
            "subcategory":"Construction",
            "type":"Services"
        }
    ],
    "sg:phone":"+1 970 384 0517",
    "sg:postcode":"81601",
    "sg:province":"CO",
    "sg:tags":[
        "home",
        "builder"
    ],
    "wof:name":"Teamcorp Inc",
    "wof:placetype":"venue"
},
  "geometry": {"coordinates":[-107.27289500000001,39.474546],"type":"Point"}
}