{
  "type": "Feature",
  "properties": {
    "addr:full":"344 Judson St Longmont CO 80501",
    "addr:housenumber":"344",
    "addr:postcode":"80501",
    "addr:street":"Judson St",
    "iso:country":"US",
    "sg:address":"344 Judson St",
    "sg:city":"Longmont",
    "sg:classifiers":[
        {
            "category":"Building & Trades",
            "subcategory":"Construction",
            "type":"Services"
        }
    ],
    "sg:phone":"+1 303 776 7676",
    "sg:postcode":"80501",
    "sg:province":"CO",
    "sg:tags":[
        "contractor"
    ],
    "wof:name":"Xylem Woodworks",
    "wof:placetype":"venue"
},
  "geometry": {"coordinates":[-105.11770199999999,40.168261],"type":"Point"}
}