{
  "type": "Feature",
  "properties": {
    "iso:country":"US",
    "sg:address":"16621 Co Rd 71.1",
    "sg:city":"Trinidad",
    "sg:classifiers":[
        {
            "category":"Wholesale",
            "subcategory":"Electrical",
            "type":"Manufacturing & Wholesale Goods"
        }
    ],
    "sg:phone":"+1 719 846 9800",
    "sg:postcode":"81082",
    "sg:province":"CO",
    "sg:tags":[
        "mobile",
        "telephone"
    ],
    "wof:name":"Mobile Telecommunications Tech",
    "wof:placetype":"venue"
},
  "geometry": {"coordinates":[-104.494641,37.237417],"type":"Point"}
}