{
  "type": "Feature",
  "properties": {
    "iso:country":"US",
    "sg:address":"13004 Co Rd 2",
    "sg:city":"Sterling",
    "sg:classifiers":[
        {
            "category":"Autos & Motor Vehicles",
            "subcategory":"Motorcycle Sales",
            "type":"Retail Goods"
        }
    ],
    "sg:phone":"+1 970 522 7810",
    "sg:postcode":"80751",
    "sg:province":"CO",
    "sg:tags":[
        "car",
        "golf",
        "cart"
    ],
    "wof:name":"Ermar",
    "wof:placetype":"venue"
},
  "geometry": {"coordinates":[-103.062763,40.437015],"type":"Point"}
}