{
  "type": "Feature",
  "properties": {
    "addr:full":"200 W Grand Ave Grand Junction CO 81501",
    "addr:housenumber":"200",
    "addr:postcode":"81501",
    "addr:street":"W Grand Ave",
    "iso:country":"US",
    "sg:address":"200 W Grand Ave",
    "sg:city":"Grand Junction",
    "sg:classifiers":[
        {
            "category":"Professional",
            "type":"Services"
        },
        {
            "category":"Restaurant",
            "type":"Food & Drink"
        }
    ],
    "sg:phone":"+1 970 243 6727",
    "sg:postcode":"81501",
    "sg:province":"CO",
    "wof:name":"Fly'n Roosters",
    "wof:placetype":"venue"
},
  "geometry": {"coordinates":[-108.573182,39.070257],"type":"Point"}
}