{
  "type": "Feature",
  "properties": {
    "iso:country":"US",
    "sg:address":"13287 W Montana Pl",
    "sg:city":"Denver",
    "sg:classifiers":[
        {
            "category":"Shopping",
            "subcategory":"Books",
            "type":"Retail Goods"
        }
    ],
    "sg:phone":"+1 303 985 9171",
    "sg:postcode":"80228",
    "sg:province":"CO",
    "wof:name":"Plumbline Publication",
    "wof:placetype":"venue"
},
  "geometry": {"coordinates":[-105.14896400000001,39.685914],"type":"Point"}
}