{
  "type": "Feature",
  "properties": {
    "addr:full":"343 S Saint Vrain Ave Estes Park CO 80517",
    "addr:housenumber":"343",
    "addr:postcode":"80517",
    "addr:street":"S Saint Vrain Ave",
    "iso:country":"US",
    "sg:address":"343 S Saint Vrain Ave",
    "sg:city":"Estes Park",
    "sg:classifiers":[
        {
            "category":"Manufacturing",
            "subcategory":"Printing",
            "type":"Manufacturing & Wholesale Goods"
        }
    ],
    "sg:phone":"+1 970 577 0778",
    "sg:postcode":"80517",
    "sg:province":"CO",
    "sg:tags":[
        "periodical"
    ],
    "wof:name":"She Sends Magazine",
    "wof:placetype":"venue"
},
  "geometry": {"coordinates":[-105.508222,40.3738],"type":"Point"}
}