{
  "type": "Feature",
  "properties": {
    "iso:country":"US",
    "sg:address":"2727 W 5th Avenue",
    "sg:city":"Denver",
    "sg:classifiers":[
        {
            "category":"Building & Trades",
            "subcategory":"Construction",
            "type":"Services"
        }
    ],
    "sg:phone":"+1 303 892 1234",
    "sg:postcode":"80204",
    "sg:province":"CO",
    "sg:tags":[
        "interior",
        "design"
    ],
    "wof:name":"Design Force Corporation",
    "wof:placetype":"venue"
},
  "geometry": {"coordinates":[-105.021378,39.723754],"type":"Point"}
}