{
  "type": "Feature",
  "properties": {
    "addr:full":"13009 E Bethany Pl Aurora CO 80014",
    "addr:housenumber":"13009",
    "addr:postcode":"80014",
    "addr:street":"E Bethany Pl",
    "iso:country":"US",
    "sg:address":"13009 E Bethany Pl",
    "sg:city":"Aurora",
    "sg:classifiers":[
        {
            "category":"Professional",
            "subcategory":"Business Services",
            "type":"Services"
        }
    ],
    "sg:phone":"+1 303 355 3146",
    "sg:postcode":"80014",
    "sg:province":"CO",
    "sg:tags":[
        "translator",
        "interpreter"
    ],
    "wof:name":"Us Consulting Group",
    "wof:placetype":"venue"
},
  "geometry": {"coordinates":[-104.838652,39.662914],"type":"Point"}
}