{
  "type": "Feature",
  "properties": {
    "addr:full":"440 Co Rd 232 Durango CO 81303",
    "addr:housenumber":"440;232",
    "addr:postcode":"co 81303",
    "addr:street":"Co Rd",
    "iso:country":"US",
    "sg:address":"440 Co Rd 232",
    "sg:city":"Durango",
    "sg:classifiers":[
        {
            "category":"Building & Trades",
            "subcategory":"Construction",
            "type":"Services"
        }
    ],
    "sg:phone":"+1 970 259 2139",
    "sg:postcode":"81303",
    "sg:province":"CO",
    "sg:tags":[
        "product",
        "asphalt"
    ],
    "wof:name":"C M Asphalt Maintenance & Roof",
    "wof:placetype":"venue"
},
  "geometry": {"coordinates":[-107.825202,37.226855],"type":"Point"}
}