{
  "type": "Feature",
  "properties": {
    "addr:full":"135 Moraine Ave Estes Park CO 80517",
    "addr:housenumber":"135",
    "addr:postcode":"80517",
    "addr:street":"Moraine Ave",
    "iso:country":"US",
    "sg:address":"135 Moraine Ave",
    "sg:city":"Estes Park",
    "sg:classifiers":[
        {
            "category":"Shopping",
            "subcategory":"Shoes",
            "type":"Retail Goods"
        }
    ],
    "sg:phone":"+1 970 586 4061",
    "sg:postcode":"80517",
    "sg:province":"CO",
    "wof:name":"Plum Creek Shoe Station",
    "wof:placetype":"venue"
},
  "geometry": {"coordinates":[-105.523641,40.375446],"type":"Point"}
}