{
  "type": "Feature",
  "properties": {
    "iso:country":"US",
    "sg:address":"216 E Grand Ave",
    "sg:city":"Mancos",
    "sg:classifiers":[
        {
            "category":"Building & Trades",
            "subcategory":"Construction",
            "type":"Services"
        }
    ],
    "sg:phone":"+1 970 533 9829",
    "sg:postcode":"81328",
    "sg:province":"CO",
    "sg:tags":[
        "concrete",
        "pumping"
    ],
    "wof:name":"Menefee Concrete Pumping",
    "wof:placetype":"venue"
},
  "geometry": {"coordinates":[-108.290435,37.345188],"type":"Point"}
}