{
  "type": "Feature",
  "properties": {
    "addr:full":"999 18th St Denver CO 80206",
    "addr:housenumber":"999",
    "addr:postcode":"80206",
    "addr:street":"18Th St",
    "iso:country":"US",
    "sg:address":"999 18th St",
    "sg:city":"Denver",
    "sg:classifiers":[
        {
            "category":"Professional",
            "subcategory":"Lawyer & Legal Services",
            "type":"Services"
        }
    ],
    "sg:phone":"+1 303 294 0707",
    "sg:postcode":"80206",
    "sg:province":"CO",
    "sg:tags":[
        "attorney"
    ],
    "sg:website":"www.altermanlaw.com",
    "wof:name":"Carter & Alterman",
    "wof:placetype":"venue"
},
  "geometry": {"coordinates":[-104.99151999999999,39.748394],"type":"Point"}
}