{
  "type": "Feature",
  "properties": {
    "iso:country":"US",
    "sg:address":"4605 E 74th Ave",
    "sg:city":"Commerce City",
    "sg:classifiers":[
        {
            "category":"Restaurant",
            "type":"Food & Drink"
        }
    ],
    "sg:phone":"+1 303 289 2055",
    "sg:postcode":"80022",
    "sg:province":"CO",
    "sg:tags":[
        "eating"
    ],
    "wof:name":"Butcher Block Restaurant",
    "wof:placetype":"venue"
},
  "geometry": {"coordinates":[-104.933938,39.83095],"type":"Point"}
}