{
  "type": "Feature",
  "properties": {
    "iso:country":"US",
    "sg:address":"3101 N Hancock Ave",
    "sg:city":"Colorado Springs",
    "sg:classifiers":[
        {
            "category":"Manufacturing",
            "subcategory":"Pottery",
            "type":"Manufacturing & Wholesale Goods"
        }
    ],
    "sg:phone":"+1 719 636 1999",
    "sg:postcode":"80907",
    "sg:province":"CO",
    "sg:tags":[
        "class",
        "mfg"
    ],
    "wof:name":"Alexander Pottery",
    "wof:placetype":"venue"
},
  "geometry": {"coordinates":[-104.803423,38.87666],"type":"Point"}
}