{
  "type": "Feature",
  "properties": {
    "iso:country":"US",
    "sg:address":"6650 W Prentice Ave",
    "sg:city":"Lakewood",
    "sg:classifiers":[
        {
            "category":"Building & Trades",
            "subcategory":"Construction",
            "type":"Services"
        }
    ],
    "sg:phone":"+1 303 794 7321",
    "sg:postcode":"80123",
    "sg:province":"CO",
    "sg:tags":[
        "house",
        "builder",
        "home"
    ],
    "wof:name":"Alexander Homes Inc",
    "wof:placetype":"venue"
},
  "geometry": {"coordinates":[-105.07067499999999,39.619181],"type":"Point"}
}