{
  "type": "Feature",
  "properties": {
    "addr:full":"7375 E Woodmen Rd Colorado Springs CO 80908",
    "addr:housenumber":"7375",
    "addr:postcode":"80908",
    "addr:street":"E Woodmen Rd",
    "iso:country":"US",
    "sg:address":"7375 E Woodmen Rd",
    "sg:city":"Colorado Springs",
    "sg:classifiers":[
        {
            "category":"Retail",
            "subcategory":"Veterinary Services",
            "type":"Services"
        }
    ],
    "sg:phone":"+1 719 494 1156",
    "sg:postcode":"80908",
    "sg:province":"CO",
    "sg:tags":[
        "veterinarian"
    ],
    "wof:name":"CVC Natural Healthcare",
    "wof:placetype":"venue"
},
  "geometry": {"coordinates":[-104.69082299999999,38.940877],"type":"Point"}
}