{
  "type": "Feature",
  "properties": {
    "iso:country":"US",
    "sg:address":"52 Harlston Green Rd",
    "sg:city":"Snowmass Village",
    "sg:classifiers":[
        {
            "category":"Professional",
            "type":"Services"
        }
    ],
    "sg:phone":"+1 970 923 6133",
    "sg:postcode":"81615",
    "sg:province":"CO",
    "sg:tags":[
        "establishment"
    ],
    "wof:name":"Gross & Gross",
    "wof:placetype":"venue"
},
  "geometry": {"coordinates":[-106.929924,39.217798],"type":"Point"}
}