{
  "type": "Feature",
  "properties": {
    "iso:country":"US",
    "sg:address":"5637 Wyandot St",
    "sg:city":"Denver",
    "sg:classifiers":[
        {
            "category":"Real Estate",
            "subcategory":"Real Estate Services",
            "type":"Services"
        },
        {
            "category":"Building & Trades",
            "subcategory":"Cleaning & Sanitation",
            "type":"Services"
        }
    ],
    "sg:phone":"+1 303 284 1278",
    "sg:postcode":"80221",
    "sg:province":"CO",
    "sg:tags":[
        "maintenance",
        "cleaners-interior"
    ],
    "wof:name":"K&S Property Maintenance",
    "wof:placetype":"venue"
},
  "geometry": {"coordinates":[-105.01467100000001,39.799071],"type":"Point"}
}