{
  "type": "Feature",
  "properties": {
    "iso:country":"US",
    "sg:address":"4315 N Nevada Ave",
    "sg:city":"Colorado Springs",
    "sg:classifiers":[
        {
            "category":"Wholesale",
            "subcategory":"Machinery & Supplies",
            "type":"Manufacturing & Wholesale Goods"
        }
    ],
    "sg:phone":"+1 719 634 4141",
    "sg:postcode":"80907",
    "sg:province":"CO",
    "sg:tags":[
        "equipment",
        "layer",
        "carpet"
    ],
    "wof:name":"Professional Trade Supply-Co",
    "wof:placetype":"venue"
},
  "geometry": {"coordinates":[-104.818448,38.896091],"type":"Point"}
}