{
  "type": "Feature",
  "properties": {
    "iso:country":"US",
    "sg:address":"3375 S Bannock St",
    "sg:city":"Englewood",
    "sg:classifiers":[
        {
            "category":"Professional",
            "subcategory":"Advertising",
            "type":"Services"
        }
    ],
    "sg:phone":"+1 303 761 4200",
    "sg:postcode":"80110",
    "sg:province":"CO",
    "sg:tags":[
        "mailing",
        "direct"
    ],
    "wof:name":"Yankee Pedler Postal Service",
    "wof:placetype":"venue"
},
  "geometry": {"coordinates":[-104.990061,39.656101],"type":"Point"}
}