{
  "type": "Feature",
  "properties": {
    "addr:full":"15578 Co Rd 133 Simla CO 80835",
    "addr:housenumber":"15578;133",
    "addr:postcode":"simla;80835",
    "addr:street":"Co Rd",
    "iso:country":"US",
    "sg:address":"15578 Co Rd 133",
    "sg:city":"Simla",
    "sg:classifiers":[
        {
            "category":"Freight",
            "type":"Transportation"
        }
    ],
    "sg:phone":"+1 719 541 3590",
    "sg:postcode":"80835",
    "sg:province":"CO",
    "sg:tags":[
        "operator",
        "local",
        "trucking"
    ],
    "wof:name":"Prairieland Trucking LLC",
    "wof:placetype":"venue"
},
  "geometry": {"coordinates":[-104.052753,39.071844],"type":"Point"}
}