{
  "type": "Feature",
  "properties": {
    "iso:country":"US",
    "sg:address":"635 Pitkin Ave",
    "sg:city":"Grand Junction",
    "sg:classifiers":[
        {
            "category":"Autos & Motor Vehicles",
            "subcategory":"Auto Supplies",
            "type":"Retail Goods"
        }
    ],
    "sg:phone":"+1 970 241 0718",
    "sg:postcode":"81501",
    "sg:province":"CO",
    "sg:tags":[
        "filter",
        "gas"
    ],
    "wof:name":"Filter House",
    "wof:placetype":"venue"
},
  "geometry": {"coordinates":[-108.56159100000001,39.064307],"type":"Point"}
}