{
  "type": "Feature",
  "properties": {
    "addr:full":"3133 San Luis Dr Colorado Springs CO 80909",
    "addr:housenumber":"3133",
    "addr:postcode":"80909",
    "addr:street":"San Luis Dr",
    "iso:country":"US",
    "sg:address":"3133 San Luis Dr",
    "sg:city":"Colorado Springs",
    "sg:classifiers":[
        {
            "category":"Insurance",
            "subcategory":"Insurance Agent",
            "type":"Services"
        }
    ],
    "sg:phone":"+1 719 634 5019",
    "sg:postcode":"80909",
    "sg:province":"CO",
    "wof:name":"Sage Financial Corp",
    "wof:placetype":"venue"
},
  "geometry": {"coordinates":[-104.770684,38.866958],"type":"Point"}
}