{
  "type": "Feature",
  "properties": {
    "iso:country":"US",
    "sg:address":"5390 Manhattan Cir",
    "sg:city":"Boulder",
    "sg:classifiers":[
        {
            "category":"Professional",
            "subcategory":"Lawyer & Legal Services",
            "type":"Services"
        }
    ],
    "sg:phone":"+1 303 499 0303",
    "sg:postcode":"80303",
    "sg:province":"CO",
    "sg:tags":[
        "attorney"
    ],
    "wof:name":"Enstad Law Firm",
    "wof:placetype":"venue"
},
  "geometry": {"coordinates":[-105.229091,39.985788],"type":"Point"}
}