{
  "type": "Feature",
  "properties": {
    "addr:full":"3165 S Ogden St Englewood CO 80113",
    "addr:housenumber":"3165",
    "addr:postcode":"80113",
    "addr:street":"S Ogden St",
    "iso:country":"US",
    "sg:address":"3165 S Ogden St",
    "sg:city":"Englewood",
    "sg:classifiers":[
        {
            "category":"Wholesale",
            "subcategory":"Non-durable Goods",
            "type":"Manufacturing & Wholesale Goods"
        }
    ],
    "sg:phone":"+1 303 788 0455",
    "sg:postcode":"80113",
    "sg:province":"CO",
    "wof:name":"High Tide Imports",
    "wof:placetype":"venue"
},
  "geometry": {"coordinates":[-104.975874,39.659802],"type":"Point"}
}