{
  "type": "Feature",
  "properties": {
    "iso:country":"US",
    "sg:address":"4850 E 74th Ave",
    "sg:city":"Commerce City",
    "sg:classifiers":[
        {
            "category":"Retail",
            "subcategory":"Repair Shop",
            "type":"Services"
        }
    ],
    "sg:phone":"+1 303 289 3149",
    "sg:postcode":"80022",
    "sg:province":"CO",
    "sg:tags":[
        "heavy",
        "duty",
        "tank",
        "trailer"
    ],
    "sg:website":"www.beallcorp.com",
    "wof:name":"Beall Trailers Of Colorado",
    "wof:placetype":"venue"
},
  "geometry": {"coordinates":[-104.927064,39.830681],"type":"Point"}
}