{
  "type": "Feature",
  "properties": {
    "addr:full":"5457 Manhart St Sedalia CO 80135",
    "addr:housenumber":"5457",
    "addr:postcode":"80135",
    "addr:street":"Manhart St",
    "iso:country":"US",
    "sg:address":"5457 Manhart St",
    "sg:city":"Sedalia",
    "sg:classifiers":[
        {
            "category":"Restaurant",
            "type":"Food & Drink"
        }
    ],
    "sg:phone":"+1 303 660 5650",
    "sg:postcode":"80135",
    "sg:province":"CO",
    "sg:tags":[
        "parlor",
        "ice",
        "cream"
    ],
    "wof:name":"Rock Top Ice Cream Shop",
    "wof:placetype":"venue"
},
  "geometry": {"coordinates":[-104.96230799999999,39.437228],"type":"Point"}
}