{
  "type": "Feature",
  "properties": {
    "addr:full":"18249 E Mexico Pl Aurora CO 80017",
    "addr:housenumber":"18249",
    "addr:postcode":"80017",
    "addr:street":"E Mexico Pl",
    "iso:country":"US",
    "sg:address":"18249 E Mexico Pl",
    "sg:city":"Aurora",
    "sg:classifiers":[
        {
            "category":"Manufacturing",
            "subcategory":"Lumber",
            "type":"Manufacturing & Wholesale Goods"
        }
    ],
    "sg:phone":"+1 720 213 0196",
    "sg:postcode":"80017",
    "sg:province":"CO",
    "sg:tags":[
        "hardwood",
        "mill",
        "restoration",
        "furniture"
    ],
    "wof:name":"Steven Morin",
    "wof:placetype":"venue"
},
  "geometry": {"coordinates":[-104.77476,39.685314],"type":"Point"}
}