{
  "type": "Feature",
  "properties": {
    "iso:country":"US",
    "sg:address":"4740 Table Mesa Dr",
    "sg:city":"Boulder",
    "sg:classifiers":[
        {
            "category":"Food & Beverages",
            "subcategory":"Specialty",
            "type":"Retail Goods"
        }
    ],
    "sg:phone":"+1 720 304 6540",
    "sg:postcode":"80305",
    "sg:province":"CO",
    "sg:tags":[
        "health",
        "diet"
    ],
    "sg:website":"www.nutracompute.com",
    "wof:name":"Nutracompute Testing Ctr",
    "wof:placetype":"venue"
},
  "geometry": {"coordinates":[-105.239622,39.985684],"type":"Point"}
}