{
  "type": "Feature",
  "properties": {
    "iso:country":"US",
    "sg:address":"2976 W Union Ave",
    "sg:city":"Englewood",
    "sg:classifiers":[
        {
            "category":"Recreation",
            "type":"Entertainment"
        }
    ],
    "sg:phone":"+1 303 794 3571",
    "sg:postcode":"80110",
    "sg:province":"CO",
    "sg:tags":[
        "club"
    ],
    "wof:name":"International Soccer Camps",
    "wof:placetype":"venue"
},
  "geometry": {"coordinates":[-105.02405,39.631371],"type":"Point"}
}