{
  "type": "Feature",
  "properties": {
    "addr:full":"7101 W Yale Ave Denver CO 80227",
    "addr:housenumber":"7101",
    "addr:postcode":"80227",
    "addr:street":"W Yale Ave",
    "iso:country":"US",
    "sg:address":"7101 W Yale Ave",
    "sg:city":"Denver",
    "sg:classifiers":[
        {
            "category":"Building & Trades",
            "subcategory":"Construction",
            "type":"Services"
        }
    ],
    "sg:phone":"+1 303 989 4198",
    "sg:postcode":"80227",
    "sg:province":"CO",
    "sg:tags":[
        "house"
    ],
    "wof:name":"Jones Dupont Construction",
    "wof:placetype":"venue"
},
  "geometry": {"coordinates":[-105.07406,39.667686],"type":"Point"}
}