{
  "type": "Feature",
  "properties": {
    "addr:full":"7505-A Grandview Ave Arvada CO 80001",
    "addr:housenumber":"7505-a",
    "addr:postcode":"80001",
    "addr:street":"Grandview Ave",
    "iso:country":"US",
    "sg:address":"7505-A Grandview Ave",
    "sg:city":"Arvada",
    "sg:classifiers":[
        {
            "category":"Shopping",
            "subcategory":"Hobbies, Toys, & Games",
            "type":"Retail Goods"
        }
    ],
    "sg:phone":"+1 303 456 2021",
    "sg:postcode":"80001",
    "sg:province":"CO",
    "sg:tags":[
        "shop",
        "hobby"
    ],
    "sg:website":"www.knitknack.org",
    "wof:name":"Knit Knack",
    "wof:placetype":"venue"
},
  "geometry": {"coordinates":[-105.08012600000001,39.799348],"type":"Point"}
}