{
  "type": "Feature",
  "properties": {
    "iso:country":"US",
    "sg:address":"13816 W 66th Pl",
    "sg:city":"Arvada",
    "sg:classifiers":[
        {
            "category":"Building & Trades",
            "subcategory":"Construction",
            "type":"Services"
        }
    ],
    "sg:phone":"+1 303 421 9849",
    "sg:postcode":"80004",
    "sg:province":"CO",
    "sg:tags":[
        "sheet",
        "metal",
        "contractor"
    ],
    "wof:name":"Dalton Construction Company",
    "wof:placetype":"venue"
},
  "geometry": {"coordinates":[-105.154071,39.817379],"type":"Point"}
}