{
  "type": "Feature",
  "properties": {
    "iso:country":"US",
    "sg:address":"8926 Vrain St",
    "sg:city":"Westminster",
    "sg:classifiers":[
        {
            "category":"Building & Trades",
            "subcategory":"Electrical",
            "type":"Services"
        }
    ],
    "sg:phone":"+1 303 429 6380",
    "sg:postcode":"80031",
    "sg:province":"CO",
    "sg:tags":[
        "alarm",
        "installation",
        "system"
    ],
    "wof:name":"Protection Concepts Company",
    "wof:placetype":"venue"
},
  "geometry": {"coordinates":[-105.045024,39.858744],"type":"Point"}
}