{
  "type": "Feature",
  "properties": {
    "addr:full":"5339 Co Rd 214 New Castle CO 81652",
    "addr:housenumber":"5339;214",
    "addr:postcode":"81652",
    "addr:street":"Co Rd",
    "iso:country":"US",
    "sg:address":"5339 Co Rd 214",
    "sg:city":"New Castle",
    "sg:classifiers":[
        {
            "category":"Manufacturing",
            "subcategory":"Building Materials",
            "type":"Manufacturing & Wholesale Goods"
        }
    ],
    "sg:phone":"+1 970 876 5982",
    "sg:postcode":"81652",
    "sg:province":"CO",
    "sg:tags":[
        "mfg",
        "wood",
        "kitchen",
        "cabinet"
    ],
    "wof:name":"Peach Valley Woodworks",
    "wof:placetype":"venue"
},
  "geometry": {"coordinates":[-107.585105,39.557939],"type":"Point"}
}