{
  "type": "Feature",
  "properties": {
    "iso:country":"US",
    "sg:address":"736C W. Castleton rd.",
    "sg:city":"Castle Rock",
    "sg:classifiers":[
        {
            "category":"Retail",
            "subcategory":"Auto Repair",
            "type":"Services"
        }
    ],
    "sg:phone":"+1 303 688 1001",
    "sg:postcode":"80109",
    "sg:province":"CO",
    "sg:website":"www.advanced4x4.com",
    "wof:name":"Advanced Four Wheel Drive & Auto Repair",
    "wof:placetype":"venue"
},
  "geometry": {"coordinates":[-104.870225,39.409592],"type":"Point"}
}