{
  "type": "Feature",
  "properties": {
    "addr:full":"2310 Edison St Brush CO 80723",
    "addr:housenumber":"2310",
    "addr:postcode":"80723",
    "addr:street":"Edison St",
    "iso:country":"US",
    "sg:address":"2310 Edison St",
    "sg:city":"Brush",
    "sg:classifiers":[
        {
            "category":"Organizations",
            "subcategory":"Community Association",
            "type":"Services"
        }
    ],
    "sg:phone":"+1 970 842 2396",
    "sg:postcode":"80723",
    "sg:province":"CO",
    "sg:tags":[
        "fraternal"
    ],
    "wof:name":"Loyal Order Of Moose",
    "wof:placetype":"venue"
},
  "geometry": {"coordinates":[-103.641763,40.254688],"type":"Point"}
}