{
  "type": "Feature",
  "properties": {
    "addr:full":"111 S Madison St Denver CO 80209",
    "addr:housenumber":"111",
    "addr:postcode":"80209",
    "addr:street":"S Madison St",
    "iso:country":"US",
    "sg:address":"111 S Madison St",
    "sg:city":"Denver",
    "sg:classifiers":[
        {
            "category":"Professional",
            "subcategory":"Computer Services",
            "type":"Services"
        }
    ],
    "sg:phone":"+1 303 393 0689",
    "sg:postcode":"80209",
    "sg:province":"CO",
    "wof:name":"On Site Computer Svc Inc",
    "wof:placetype":"venue"
},
  "geometry": {"coordinates":[-104.946247,39.714268],"type":"Point"}
}