{
  "type": "Feature",
  "properties": {
    "addr:full":"2223 S Monaco Pkwy Denver CO 80222",
    "addr:housenumber":"2223",
    "addr:postcode":"80222",
    "addr:street":"S Monaco Pkwy",
    "iso:country":"US",
    "sg:address":"2223 S Monaco Pkwy",
    "sg:city":"Denver",
    "sg:classifiers":[
        {
            "category":"Building & Trades",
            "subcategory":"Locksmith",
            "type":"Services"
        }
    ],
    "sg:phone":"+1 866 531 5196",
    "sg:postcode":"80222",
    "sg:province":"CO",
    "sg:tags":[
        "key"
    ],
    "wof:name":"Anytime Emergency Locksmith",
    "wof:placetype":"venue"
},
  "geometry": {"coordinates":[-104.913111,39.676504],"type":"Point"}
}