{
  "type": "Feature",
  "properties": {
    "iso:country":"US",
    "sg:address":"1401 Walnut St",
    "sg:city":"Boulder",
    "sg:classifiers":[
        {
            "category":"Professional",
            "type":"Services"
        }
    ],
    "sg:phone":"+1 303 443 5103",
    "sg:postcode":"80302",
    "sg:province":"CO",
    "wof:name":"Front Range Alliance",
    "wof:placetype":"venue"
},
  "geometry": {"coordinates":[-105.27569099999999,40.017686],"type":"Point"}
}