{
  "type": "Feature",
  "properties": {
    "iso:country":"US",
    "sg:address":"7001 S University Blvd",
    "sg:city":"Centennial",
    "sg:classifiers":[
        {
            "category":"Professional",
            "subcategory":"Accounting & Tax Preparation",
            "type":"Services"
        }
    ],
    "sg:phone":"+1 303 730 5539",
    "sg:postcode":"80122",
    "sg:province":"CO",
    "sg:tags":[
        "return",
        "filing"
    ],
    "wof:name":"H & R Block Tax Svc",
    "wof:placetype":"venue"
},
  "geometry": {"coordinates":[-104.9603,39.589215],"type":"Point"}
}