{
  "type": "Feature",
  "properties": {
    "addr:full":"944 Pearl St Boulder CO 80302",
    "addr:housenumber":"944",
    "addr:postcode":"80302",
    "addr:street":"Pearl St",
    "iso:country":"US",
    "sg:address":"944 Pearl St",
    "sg:city":"Boulder",
    "sg:classifiers":[
        {
            "category":"Manufacturing",
            "subcategory":"Textiles",
            "type":"Manufacturing & Wholesale Goods"
        },
        {
            "category":"Wholesale",
            "subcategory":"Home Furnishings",
            "type":"Manufacturing & Wholesale Goods"
        }
    ],
    "sg:phone":"+1 303 938 9851",
    "sg:postcode":"80302",
    "sg:province":"CO",
    "sg:tags":[
        "rug",
        "carpet"
    ],
    "wof:name":"Flying Carpet Studio",
    "wof:placetype":"venue"
},
  "geometry": {"coordinates":[-105.284172,40.016932],"type":"Point"}
}