{
  "type": "Feature",
  "properties": {
    "addr:full":"3512 E Colfax Ave Denver CO 80206",
    "addr:housenumber":"3512",
    "addr:postcode":"80206",
    "addr:street":"E Colfax Ave",
    "iso:country":"US",
    "sg:address":"3512 E Colfax Ave",
    "sg:city":"Denver",
    "sg:classifiers":[
        {
            "category":"Food & Beverages",
            "subcategory":"Groceries & Convenience Stores",
            "type":"Retail Goods"
        }
    ],
    "sg:phone":"+1 303 394 9545",
    "sg:postcode":"80206",
    "sg:province":"CO",
    "wof:name":"Food Club",
    "wof:placetype":"venue"
},
  "geometry": {"coordinates":[-104.945618,39.740073],"type":"Point"}
}