{
  "type": "Feature",
  "properties": {
    "iso:country":"US",
    "sg:address":"1260 Upper Broadview Rd",
    "sg:city":"Estes Park",
    "sg:classifiers":[
        {
            "category":"Professional",
            "type":"Services"
        }
    ],
    "sg:phone":"+1 970 586 2624",
    "sg:postcode":"80517",
    "sg:province":"CO",
    "sg:tags":[
        "establishment"
    ],
    "wof:name":"Heron",
    "wof:placetype":"venue"
},
  "geometry": {"coordinates":[-105.54773900000001,40.358438],"type":"Point"}
}