{
  "type": "Feature",
  "properties": {
    "iso:country":"US",
    "sg:address":"1414 Grand Ave",
    "sg:city":"Glenwood Springs",
    "sg:classifiers":[
        {
            "category":"Home & Garden",
            "subcategory":"Carpets & Floor Coverings",
            "type":"Retail Goods"
        }
    ],
    "sg:phone":"+1 970 928 7283",
    "sg:postcode":"81601",
    "sg:province":"CO",
    "sg:tags":[
        "dealer",
        "rug"
    ],
    "wof:name":"Carpet Max",
    "wof:placetype":"venue"
},
  "geometry": {"coordinates":[-107.324933,39.539054],"type":"Point"}
}