{
  "type": "Feature",
  "properties": {
    "iso:country":"US",
    "sg:address":"295 E 29th St",
    "sg:city":"Loveland",
    "sg:classifiers":[
        {
            "category":"Social Services",
            "type":"Services"
        }
    ],
    "sg:phone":"+1 970 593 9523",
    "sg:postcode":"80538",
    "sg:province":"CO",
    "sg:tags":[
        "counselor",
        "marriage",
        "family"
    ],
    "wof:name":"Healing Prayer Ministry",
    "wof:placetype":"venue"
},
  "geometry": {"coordinates":[-105.073303,40.421799],"type":"Point"}
}