{
  "type": "Feature",
  "properties": {
    "iso:country":"US",
    "sg:address":"1412 S Parker Rd",
    "sg:city":"Denver",
    "sg:classifiers":[
        {
            "category":"Personal",
            "subcategory":"Beauty Salon",
            "type":"Services"
        }
    ],
    "sg:phone":"+1 303 805 9158",
    "sg:postcode":"80231",
    "sg:province":"CO",
    "sg:tags":[
        "manicuring"
    ],
    "wof:name":"Classic Nail",
    "wof:placetype":"venue"
},
  "geometry": {"coordinates":[-104.889681,39.689593],"type":"Point"}
}