{
  "type": "Feature",
  "properties": {
    "iso:country":"US",
    "sg:address":"142 E 29th St",
    "sg:city":"Loveland",
    "sg:classifiers":[
        {
            "category":"Personal",
            "subcategory":"Tanning Parlor",
            "type":"Services"
        }
    ],
    "sg:phone":"+1 970 622 8174",
    "sg:postcode":"80538",
    "sg:province":"CO",
    "sg:tags":[
        "salon"
    ],
    "wof:name":"Ultratanz",
    "wof:placetype":"venue"
},
  "geometry": {"coordinates":[-105.076932,40.421591],"type":"Point"}
}