{
  "type": "Feature",
  "properties": {
    "addr:full":"7650 S Broadway Littleton CO 80122",
    "addr:housenumber":"7650",
    "addr:postcode":"80122",
    "addr:street":"S Broadway",
    "iso:country":"US",
    "sg:address":"7650 S Broadway",
    "sg:city":"Littleton",
    "sg:classifiers":[
        {
            "category":"Freight",
            "type":"Transportation"
        }
    ],
    "sg:phone":"+1 303 798 8078",
    "sg:postcode":"80122",
    "sg:province":"CO",
    "sg:tags":[
        "commercial",
        "storage"
    ],
    "wof:name":"Colorado Self Storage Svc Ctr",
    "wof:placetype":"venue"
},
  "geometry": {"coordinates":[-104.988407,39.57889],"type":"Point"}
}