{
  "type": "Feature",
  "properties": {
    "addr:full":"6395 E Evans Ave Wholesale / Distributor Denver CO 80224",
    "addr:housenumber":"6395",
    "addr:postcode":"80224",
    "addr:street":"E Evans Ave",
    "iso:country":"US",
    "sg:address":"6395 E Evans Ave Wholesale / Distributor",
    "sg:city":"Denver",
    "sg:classifiers":[
        {
            "category":"Autos & Motor Vehicles",
            "subcategory":"Auto Supplies",
            "type":"Retail Goods"
        }
    ],
    "sg:phone":"+1 303 758 2323",
    "sg:postcode":"80224",
    "sg:province":"CO",
    "sg:tags":[
        "tire"
    ],
    "sg:website":"www.thetirestore.com",
    "wof:name":"Coloradoland Tire and Service",
    "wof:placetype":"venue"
},
  "geometry": {"coordinates":[-104.914238,39.67888],"type":"Point"}
}