{
  "type": "Feature",
  "properties": {
    "iso:country":"US",
    "sg:address":"8100 Ralston Rd",
    "sg:city":"Arvada",
    "sg:classifiers":[
        {
            "category":"Health Services",
            "subcategory":"Clinic",
            "type":"Services"
        }
    ],
    "sg:phone":"+1 303 320 1240",
    "sg:postcode":"80002",
    "sg:province":"CO",
    "sg:tags":[
        "hypnotherapy"
    ],
    "wof:name":"Cherry Creek Acupuncture",
    "wof:placetype":"venue"
},
  "geometry": {"coordinates":[-105.087266,39.802022],"type":"Point"}
}