{
  "type": "Feature",
  "properties": {
    "iso:country":"US",
    "sg:address":"20197 Riverside Dr",
    "sg:city":"Sterling",
    "sg:classifiers":[
        {
            "category":"Wholesale",
            "subcategory":"Farm Supplies",
            "type":"Manufacturing & Wholesale Goods"
        },
        {
            "category":"Professional",
            "subcategory":"Business Services",
            "type":"Services"
        }
    ],
    "sg:phone":"+1 970 522 1950",
    "sg:postcode":"80751",
    "sg:province":"CO",
    "sg:tags":[
        "livestock",
        "auctioneer"
    ],
    "wof:name":"Sterling Livestock Commission",
    "wof:placetype":"venue"
},
  "geometry": {"coordinates":[-103.199191,40.627642],"type":"Point"}
}