{
  "type": "Feature",
  "properties": {
    "iso:country":"US",
    "sg:address":"4620 Co Rd 100",
    "sg:city":"Florissant",
    "sg:classifiers":[
        {
            "category":"Recreation",
            "type":"Entertainment"
        }
    ],
    "sg:phone":"+1 719 748 3466",
    "sg:postcode":"80816",
    "sg:province":"CO",
    "sg:tags":[
        "stable"
    ],
    "wof:name":"Mc Namara's Working Guest Rnch",
    "wof:placetype":"venue"
},
  "geometry": {"coordinates":[-105.44606,38.875718],"type":"Point"}
}