{
  "type": "Feature",
  "properties": {
    "addr:full":"53549 Co Rd 42 Arriba CO 80804",
    "addr:housenumber":"53549;42",
    "addr:postcode":"arriba;80804",
    "addr:street":"Co Rd",
    "iso:country":"US",
    "sg:address":"53549 Co Rd 42",
    "sg:city":"Arriba",
    "sg:phone":"+1 719 768 3417",
    "sg:postcode":"80804",
    "sg:province":"CO",
    "sg:tags":[
        "farm",
        "wheat"
    ],
    "wof:name":"Andersen Farms",
    "wof:placetype":"venue"
},
  "geometry": {"coordinates":[-103.2859,39.279623],"type":"Point"}
}