{
  "type": "Feature",
  "properties": {
    "iso:country":"US",
    "sg:address":"53549 Co Rd 42",
    "sg:city":"Arriba",
    "sg:phone":"+1 719 768 3417",
    "sg:postcode":"80804",
    "sg:province":"CO",
    "sg:tags":[
        "farm",
        "wheat"
    ],
    "wof:name":"Andersen Farms",
    "wof:placetype":"venue"
},
  "geometry": {"coordinates":[-103.2859,39.279623],"type":"Point"}
}