{
  "type": "Feature",
  "properties": {
    "iso:country":"US",
    "sg:address":"4600 S Syracuse St",
    "sg:city":"Denver",
    "sg:classifiers":[
        {
            "category":"Banks & Credit Unions",
            "subcategory":"Bank",
            "type":"Services"
        }
    ],
    "sg:phone":"+1 303 256 6524",
    "sg:postcode":"80237",
    "sg:province":"CO",
    "sg:tags":[
        "loan",
        "real estate"
    ],
    "wof:name":"Firestack Mortgage Inc",
    "wof:placetype":"venue"
},
  "geometry": {"coordinates":[-104.89976299999999,39.62815],"type":"Point"}
}