{
  "type": "Feature",
  "properties": {
    "iso:country":"US",
    "sg:address":"4860 Ironton St",
    "sg:city":"Denver",
    "sg:classifiers":[
        {
            "category":"Manufacturing",
            "subcategory":"Printing",
            "type":"Manufacturing & Wholesale Goods"
        }
    ],
    "sg:phone":"+1 303 377 1020",
    "sg:postcode":"80239",
    "sg:province":"CO",
    "sg:tags":[
        "screen",
        "commercial"
    ],
    "wof:name":"Creative Exposure Land",
    "wof:placetype":"venue"
},
  "geometry": {"coordinates":[-104.86321,39.783229],"type":"Point"}
}