{
  "type": "Feature",
  "properties": {
    "addr:full":"77 W 9th Avenue Denver CO 80204",
    "addr:housenumber":"77",
    "addr:postcode":"80204",
    "addr:street":"W 9Th Avenue",
    "iso:country":"US",
    "sg:address":"77 W 9th Avenue",
    "sg:city":"Denver",
    "sg:classifiers":[
        {
            "category":"Home & Garden",
            "subcategory":"Furniture",
            "type":"Retail Goods"
        }
    ],
    "sg:phone":"+1 303 825 3770",
    "sg:postcode":"80204",
    "sg:province":"CO",
    "sg:tags":[
        "store"
    ],
    "wof:name":"Element",
    "wof:placetype":"venue"
},
  "geometry": {"coordinates":[-104.988158,39.730345],"type":"Point"}
}