{
  "type": "Feature",
  "properties": {
    "addr:full":"4267 S Broadway Englewood CO 80113",
    "addr:housenumber":"4267",
    "addr:postcode":"80113",
    "addr:street":"S Broadway",
    "iso:country":"US",
    "sg:address":"4267 S Broadway",
    "sg:city":"Englewood",
    "sg:classifiers":[
        {
            "category":"Professional",
            "type":"Services"
        }
    ],
    "sg:phone":"+1 303 789 9186",
    "sg:postcode":"80113",
    "sg:province":"CO",
    "wof:name":"Angelo Dent of Colorado",
    "wof:placetype":"venue"
},
  "geometry": {"coordinates":[-104.98788399999999,39.639772],"type":"Point"}
}