{
  "type": "Feature",
  "properties": {
    "iso:country":"US",
    "sg:address":"150 Ash Ave",
    "sg:city":"Akron",
    "sg:classifiers":[
        {
            "category":"Professional",
            "subcategory":"Business Services",
            "type":"Services"
        }
    ],
    "sg:phone":"+1 970 345 2311",
    "sg:postcode":"80720",
    "sg:province":"CO",
    "sg:tags":[
        "information",
        "referral"
    ],
    "wof:name":"Rural Communities Resource Ctr",
    "wof:placetype":"venue"
},
  "geometry": {"coordinates":[-103.211386,40.159646],"type":"Point"}
}