{
  "type": "Feature",
  "properties": {
    "iso:country":"US",
    "sg:address":"360 E Ave",
    "sg:city":"Limon",
    "sg:classifiers":[
        {
            "category":"Personal",
            "subcategory":"Beauty Salon",
            "type":"Services"
        }
    ],
    "sg:phone":"+1 719 775 0556",
    "sg:postcode":"80828",
    "sg:province":"CO",
    "wof:name":"C B Bodyworks",
    "wof:placetype":"venue"
},
  "geometry": {"coordinates":[-103.68785200000001,39.263814],"type":"Point"}
}