{
  "type": "Feature",
  "properties": {
    "iso:country":"US",
    "sg:address":"1203 S Main St",
    "sg:city":"Lamar",
    "sg:classifiers":[
        {
            "category":"Restaurant",
            "type":"Food & Drink"
        }
    ],
    "sg:menulink":"http://www.allmenus.com/co/lamar/87180-little-caesars-pizza/menu/",
    "sg:phone":"+1 719 336 8777",
    "sg:postcode":"81052",
    "sg:province":"CO",
    "sg:tags":[
        "american",
        "pizza"
    ],
    "wof:name":"Little Caesar's Pizza",
    "wof:placetype":"venue"
},
  "geometry": {"coordinates":[-102.61830500000001,38.077719],"type":"Point"}
}