{
  "type": "Feature",
  "properties": {
    "iso:country":"US",
    "sg:address":"232 N Circle Dr",
    "sg:city":"Colorado Springs",
    "sg:classifiers":[
        {
            "category":"Autos & Motor Vehicles",
            "subcategory":"Automobile Sales",
            "type":"Retail Goods"
        }
    ],
    "sg:phone":"+1 719 635 0275",
    "sg:postcode":"80909",
    "sg:province":"CO",
    "sg:tags":[
        "used"
    ],
    "wof:name":"Bennett Brothers Motors",
    "wof:placetype":"venue"
},
  "geometry": {"coordinates":[-104.77597400000001,38.836386],"type":"Point"}
}