{
  "type": "Feature",
  "properties": {
    "iso:country":"US",
    "sg:address":"9218 Arapahoe Rd",
    "sg:city":"Boulder",
    "sg:classifiers":[
        {
            "category":"Building & Trades",
            "subcategory":"Landscaping Services",
            "type":"Services"
        }
    ],
    "sg:phone":"+1 303 817 8761",
    "sg:postcode":"80303",
    "sg:province":"CO",
    "wof:name":"Buckinghams Fence & Repair",
    "wof:placetype":"venue"
},
  "geometry": {"coordinates":[-105.138464,40.014587],"type":"Point"}
}