{
  "type": "Feature",
  "properties": {
    "iso:country":"US",
    "sg:address":"606 Pratt St",
    "sg:city":"Longmont",
    "sg:classifiers":[
        {
            "category":"Real Estate",
            "subcategory":"Real Estate Operator",
            "type":"Services"
        }
    ],
    "sg:phone":"+1 303 776 3785",
    "sg:postcode":"80501",
    "sg:province":"CO",
    "sg:tags":[
        "apartment"
    ],
    "wof:name":"St Vrain Manor",
    "wof:placetype":"venue"
},
  "geometry": {"coordinates":[-105.106767,40.170571],"type":"Point"}
}