{
  "type": "Feature",
  "properties": {
    "addr:full":"233 W Airport Rd Aspen CO 81611",
    "addr:housenumber":"233",
    "addr:postcode":"81611",
    "addr:street":"W Airport Rd",
    "iso:country":"US",
    "sg:address":"233 W Airport Rd",
    "sg:city":"Aspen",
    "sg:classifiers":[
        {
            "category":"Retail",
            "subcategory":"Auto Rental",
            "type":"Services"
        }
    ],
    "sg:phone":"+1 970 925 2355",
    "sg:postcode":"81611",
    "sg:province":"CO",
    "sg:tags":[
        "renting",
        "automobile"
    ],
    "wof:name":"Avis Rent A Car",
    "wof:placetype":"venue"
},
  "geometry": {"coordinates":[-106.86478700000001,39.22081],"type":"Point"}
}