{
  "type": "Feature",
  "properties": {
    "iso:country":"US",
    "sg:address":"801 W 4th St",
    "sg:city":"Pueblo",
    "sg:classifiers":[
        {
            "category":"Shopping",
            "subcategory":"Computers & Home Electronics",
            "type":"Retail Goods"
        }
    ],
    "sg:phone":"+1 719 544 7956",
    "sg:postcode":"81004",
    "sg:province":"CO",
    "sg:tags":[
        "equipment",
        "dealer"
    ],
    "sg:website":"www.maxtechs.com",
    "wof:name":"Maxtech",
    "wof:placetype":"venue"
},
  "geometry": {"coordinates":[-104.619738,38.270517],"type":"Point"}
}