{
  "type": "Feature",
  "properties": {
    "addr:full":"2623 W Colorado Ave Colorado Springs CO 80904",
    "addr:housenumber":"2623",
    "addr:postcode":"80904",
    "addr:street":"W Colorado Ave",
    "iso:country":"US",
    "sg:address":"2623 W Colorado Ave",
    "sg:city":"Colorado Springs",
    "sg:classifiers":[
        {
            "category":"Wholesale",
            "subcategory":"Durable Goods & Equipment",
            "type":"Manufacturing & Wholesale Goods"
        }
    ],
    "sg:phone":"+1 719 227 1963",
    "sg:postcode":"80904",
    "sg:province":"CO",
    "sg:tags":[
        "importer"
    ],
    "wof:name":"Everest Tibet Imports",
    "wof:placetype":"venue"
},
  "geometry": {"coordinates":[-104.86536099999999,38.848735],"type":"Point"}
}