{
  "type": "Feature",
  "properties": {
    "addr:full":"10151 S Woodrose Ln Littleton CO 80129",
    "addr:housenumber":"10151",
    "addr:postcode":"80129",
    "addr:street":"S Woodrose Ln",
    "iso:country":"US",
    "sg:address":"10151 S Woodrose Ln",
    "sg:city":"Littleton",
    "sg:classifiers":[
        {
            "category":"Banks & Credit Unions",
            "subcategory":"Bank",
            "type":"Services"
        }
    ],
    "sg:phone":"+1 303 759 4666",
    "sg:postcode":"80129",
    "sg:province":"CO",
    "sg:tags":[
        "loan",
        "real estate"
    ],
    "wof:name":"Alternative Mortgage Svc",
    "wof:placetype":"venue"
},
  "geometry": {"coordinates":[-105.02228100000001,39.531716],"type":"Point"}
}