{
  "type": "Feature",
  "properties": {
    "iso:country":"US",
    "sg:address":"12708 N 5th St",
    "sg:city":"Parker",
    "sg:classifiers":[
        {
            "category":"Building & Trades",
            "subcategory":"Construction",
            "type":"Services"
        }
    ],
    "sg:phone":"+1 303 840 3085",
    "sg:postcode":"80134",
    "sg:province":"CO",
    "sg:tags":[
        "woodworker"
    ],
    "wof:name":"Hawk Custom Woodworks",
    "wof:placetype":"venue"
},
  "geometry": {"coordinates":[-104.816823,39.546695],"type":"Point"}
}