{
  "type": "Feature",
  "properties": {
    "iso:country":"US",
    "sg:address":"6556 S Academy Blvd",
    "sg:city":"Colorado Springs",
    "sg:classifiers":[
        {
            "category":"Restaurant",
            "type":"Food & Drink"
        }
    ],
    "sg:menulink":"http://www.allmenus.com/co/cheyenne-mountain/81052-papa-johns-pizza/menu/",
    "sg:phone":"+1 719 538 8811",
    "sg:postcode":"80906",
    "sg:province":"CO",
    "sg:tags":[
        "american",
        "pizza"
    ],
    "wof:name":"Papa John's Pizza",
    "wof:placetype":"venue"
},
  "geometry": {"coordinates":[-104.815592,38.765875],"type":"Point"}
}