{
  "type": "Feature",
  "properties": {
    "addr:full":"229 Midland Ave Basalt CO 81621",
    "addr:housenumber":"229",
    "addr:postcode":"81621",
    "addr:street":"Midland Ave",
    "iso:country":"US",
    "sg:address":"229 Midland Ave",
    "sg:city":"Basalt",
    "sg:classifiers":[
        {
            "category":"Real Estate",
            "subcategory":"Architect",
            "type":"Services"
        }
    ],
    "sg:phone":"+1 970 927 0635",
    "sg:postcode":"81621",
    "sg:province":"CO",
    "wof:name":"Studiograppa LLC",
    "wof:placetype":"venue"
},
  "geometry": {"coordinates":[-107.031052,39.369322],"type":"Point"}
}