{
  "type": "Feature",
  "properties": {
    "iso:country":"US",
    "sg:address":"2426 Rock Creek Dr",
    "sg:city":"Fort Collins",
    "sg:classifiers":[
        {
            "category":"Shopping",
            "type":"Retail Goods"
        }
    ],
    "sg:phone":"+1 970 225 3798",
    "sg:postcode":"80528",
    "sg:province":"CO",
    "sg:tags":[
        "art",
        "gallery",
        "dealer"
    ],
    "wof:name":"Shelly Hearne Original Art",
    "wof:placetype":"venue"
},
  "geometry": {"coordinates":[-105.03200099999999,40.515741],"type":"Point"}
}