{
  "type": "Feature",
  "properties": {
    "iso:country":"US",
    "sg:address":"400 Marion Ave",
    "sg:city":"Platteville",
    "sg:classifiers":[
        {
            "category":"Government",
            "subcategory":"Post Office",
            "type":"Public Place"
        }
    ],
    "sg:phone":"+1 970 785 2295",
    "sg:postcode":"80651",
    "sg:province":"CO",
    "wof:name":"Platteville PO",
    "wof:placetype":"venue"
},
  "geometry": {"coordinates":[-104.82379899999999,40.214908],"type":"Point"}
}