{
  "type": "Feature",
  "properties": {
    "iso:country":"US",
    "sg:address":"260 W Main St",
    "sg:city":"Cedaredge",
    "sg:classifiers":[
        {
            "category":"Shopping",
            "type":"Retail Goods"
        }
    ],
    "sg:phone":"+1 970 856 6070",
    "sg:postcode":"81413",
    "sg:province":"CO",
    "sg:tags":[
        "art",
        "gallery",
        "dealer"
    ],
    "wof:name":"Main Street Gallery",
    "wof:placetype":"venue"
},
  "geometry": {"coordinates":[-107.925873,38.900771],"type":"Point"}
}