{
  "type": "Feature",
  "properties": {
    "iso:country":"US",
    "sg:address":"11005 State Hwy 83",
    "sg:city":"Colorado Springs",
    "sg:classifiers":[
        {
            "category":"Organizations",
            "subcategory":"Religious Organization",
            "type":"Services"
        }
    ],
    "sg:phone":"+1 719 262 9922",
    "sg:postcode":"80921",
    "sg:province":"CO",
    "sg:website":"www.globalharvest.org",
    "wof:name":"Global Harvest Ministries",
    "wof:placetype":"venue"
},
  "geometry": {"coordinates":[-104.798053,38.988423],"type":"Point"}
}