{
  "type": "Feature",
  "properties": {
    "iso:country":"US",
    "sg:address":"8071 S Lamar St",
    "sg:city":"Littleton",
    "sg:classifiers":[
        {
            "category":"Arts & Performance",
            "subcategory":"Theater",
            "type":"Entertainment"
        }
    ],
    "sg:phone":"+1 303 933 6824",
    "sg:postcode":"80128",
    "sg:province":"CO",
    "sg:tags":[
        "band",
        "orchestra"
    ],
    "wof:name":"Littleton Symphony",
    "wof:placetype":"venue"
},
  "geometry": {"coordinates":[-105.06708999999999,39.569094],"type":"Point"}
}