{
  "type": "Feature",
  "properties": {
    "iso:country":"US",
    "sg:address":"410 S Santa Fe Ave",
    "sg:city":"Fountain",
    "sg:classifiers":[
        {
            "category":"Banks & Credit Unions",
            "subcategory":"Bank",
            "type":"Services"
        }
    ],
    "sg:phone":"+1 719 382 5643",
    "sg:postcode":"80817",
    "sg:province":"CO",
    "sg:tags":[
        "state",
        "commercial"
    ],
    "wof:name":"Colorado Mountain Bank",
    "wof:placetype":"venue"
},
  "geometry": {"coordinates":[-104.704474,38.679122],"type":"Point"}
}