{
  "type": "Feature",
  "properties": {
    "addr:full":"237 Church St Trinidad CO 81082",
    "addr:housenumber":"237",
    "addr:postcode":"81082",
    "addr:street":"Church St",
    "iso:country":"US",
    "sg:address":"237 Church St",
    "sg:city":"Trinidad",
    "sg:classifiers":[
        {
            "category":"Education",
            "subcategory":"School",
            "type":"Public Place"
        }
    ],
    "sg:phone":"+1 719 846 7218",
    "sg:postcode":"81082",
    "sg:province":"CO",
    "wof:name":"Trinidad Catholic Elementary",
    "wof:placetype":"venue"
},
  "geometry": {"coordinates":[-104.50721299999999,37.168565],"type":"Point"}
}