{
  "type": "Feature",
  "properties": {
    "addr:full":"3762 US Hwy 160 Monte Vista CO 81144",
    "addr:housenumber":"3762",
    "addr:postcode":"81144",
    "addr:street":"Us Hwy 160;Vista",
    "iso:country":"US",
    "sg:address":"3762 US Hwy 160",
    "sg:city":"Monte Vista",
    "sg:classifiers":[
        {
            "category":"Real Estate",
            "subcategory":"Developer",
            "type":"Services"
        }
    ],
    "sg:phone":"+1 719 852 3925",
    "sg:postcode":"81144",
    "sg:province":"CO",
    "sg:tags":[
        "cemetery"
    ],
    "wof:name":"San Luis Valley Cemetery Assn",
    "wof:placetype":"venue"
},
  "geometry": {"coordinates":[-106.20335799999999,37.591581],"type":"Point"}
}