{
  "type": "Feature",
  "properties": {
    "iso:country":"US",
    "sg:address":"7180 E 54th Pl",
    "sg:city":"Commerce City",
    "sg:classifiers":[
        {
            "category":"Banks & Credit Unions",
            "subcategory":"Bank",
            "type":"Services"
        }
    ],
    "sg:phone":"+1 303 288 9550",
    "sg:postcode":"80022",
    "sg:province":"CO",
    "wof:name":"United Florists Federal Credit Union",
    "wof:placetype":"venue"
},
  "geometry": {"coordinates":[-104.905013,39.795525],"type":"Point"}
}