{
  "type": "Feature",
  "properties": {
    "iso:country":"US",
    "sg:address":"6140 S Gun Club Rd I-2",
    "sg:city":"Aurora",
    "sg:classifiers":[
        {
            "category":"Food & Beverages",
            "subcategory":"Liquor & Beverages",
            "type":"Retail Goods"
        },
        {
            "category":"Food & Beverages",
            "subcategory":"Groceries & Convenience Stores",
            "type":"Retail Goods"
        }
    ],
    "sg:phone":"+1 303 400 5533",
    "sg:postcode":"80016",
    "sg:province":"CO",
    "sg:tags":[
        "juice",
        "bottler",
        "beverages-distributors"
    ],
    "wof:name":"Inta Juice",
    "wof:placetype":"venue"
},
  "geometry": {"coordinates":[-104.716718,39.604853],"type":"Point"}
}