{
  "type": "Feature",
  "properties": {
    "addr:full":"3840 E 104th Ave Denver CO 80233",
    "addr:housenumber":"3840",
    "addr:postcode":"80233",
    "addr:street":"E 104Th Ave",
    "iso:country":"US",
    "sg:address":"3840 E 104th Ave",
    "sg:city":"Denver",
    "sg:classifiers":[
        {
            "category":"Bakery",
            "type":"Food & Drink"
        },
        {
            "category":"Shopping",
            "subcategory":"Pharmacy",
            "type":"Retail Goods"
        },
        {
            "category":"Food & Beverages",
            "subcategory":"Groceries & Convenience Stores",
            "type":"Retail Goods"
        }
    ],
    "sg:phone":"+1 303 255 0596",
    "sg:postcode":"80233",
    "sg:province":"CO",
    "sg:website":"http://www.albertsons.com/",
    "wof:name":"Albertson's",
    "wof:placetype":"venue"
},
  "geometry": {"coordinates":[-104.94234,39.884795],"type":"Point"}
}