{
  "type": "Feature",
  "properties": {
    "iso:country":"US",
    "sg:address":"2584 Baseline Rd",
    "sg:city":"Boulder",
    "sg:classifiers":[
        {
            "category":"Food & Beverages",
            "subcategory":"Specialty",
            "type":"Retail Goods"
        }
    ],
    "sg:phone":"+1 303 499 7636",
    "sg:postcode":"80305",
    "sg:province":"CO",
    "sg:tags":[
        "grocery"
    ],
    "wof:name":"Wild Oats Community Market",
    "wof:placetype":"venue"
},
  "geometry": {"coordinates":[-105.263518,40.00007],"type":"Point"}
}