{
  "type": "Feature",
  "properties": {
    "iso:country":"US",
    "sg:address":"2322 20th St",
    "sg:city":"Boulder",
    "sg:classifiers":[
        {
            "category":"Real Estate",
            "subcategory":"Real Estate Agent",
            "type":"Services"
        }
    ],
    "sg:phone":"+1 303 499 4442",
    "sg:postcode":"80304",
    "sg:province":"CO",
    "wof:name":"Corporate Rental Connection",
    "wof:placetype":"venue"
},
  "geometry": {"coordinates":[-105.270904,40.023824],"type":"Point"}
}