{
  "type": "Feature",
  "properties": {
    "iso:country":"US",
    "sg:address":"5122 Co Rd 37",
    "sg:city":"Yuma",
    "sg:phone":"+1 970 848 2191",
    "sg:postcode":"80759",
    "sg:province":"CO",
    "sg:tags":[
        "farm",
        "wheat",
        "beef",
        "feedlot",
        "cattle"
    ],
    "wof:name":"Clara J Salzman",
    "wof:placetype":"venue"
},
  "geometry": {"coordinates":[-102.71055,40.104049],"type":"Point"}
}