{
  "type": "Feature",
  "properties": {
    "iso:country":"US",
    "sg:address":"825 Anglers Ct",
    "sg:city":"Steamboat Spgs",
    "sg:classifiers":[
        {
            "category":"Government",
            "subcategory":"Office",
            "type":"Public Place"
        }
    ],
    "sg:phone":"+1 970 879 0715",
    "sg:postcode":"80487",
    "sg:province":"CO",
    "sg:tags":[
        "state",
        "program"
    ],
    "wof:name":"Drivers License",
    "wof:placetype":"venue"
},
  "geometry": {"coordinates":[-106.816766,40.469463],"type":"Point"}
}