{
  "type": "Feature",
  "properties": {
    "addr:full":"9975 W Bowles Ave Littleton CO 80123",
    "addr:housenumber":"9975",
    "addr:postcode":"80123",
    "addr:street":"W Bowles Ave",
    "iso:country":"US",
    "sg:address":"9975 W Bowles Ave",
    "sg:city":"Littleton",
    "sg:classifiers":[
        {
            "category":"Retail",
            "subcategory":"Auto Repair",
            "type":"Services"
        }
    ],
    "sg:phone":"+1 303 972 7108",
    "sg:postcode":"80123",
    "sg:province":"CO",
    "sg:tags":[
        "repairing",
        "automotive",
        "automobile"
    ],
    "wof:name":"Econo Lube N Tune",
    "wof:placetype":"venue"
},
  "geometry": {"coordinates":[-105.10840399999999,39.609803],"type":"Point"}
}