{
  "type": "Feature",
  "properties": {
    "iso:country":"US",
    "sg:address":"5757 Central Ave",
    "sg:city":"Boulder",
    "sg:classifiers":[
        {
            "category":"Professional",
            "subcategory":"Computer Services",
            "type":"Services"
        }
    ],
    "sg:phone":"+1 303 440 0909",
    "sg:postcode":"80301",
    "sg:province":"CO",
    "sg:tags":[
        "related",
        "maintenance"
    ],
    "wof:name":"Sdl PLC",
    "wof:placetype":"venue"
},
  "geometry": {"coordinates":[-105.219832,40.019682],"type":"Point"}
}