{
  "type": "Feature",
  "properties": {
    "addr:full":"714 S Sheridan Ave Holyoke CO 80734",
    "addr:housenumber":"714",
    "addr:postcode":"80734",
    "addr:street":"S Sheridan Ave",
    "iso:country":"US",
    "sg:address":"714 S Sheridan Ave",
    "sg:city":"Holyoke",
    "sg:phone":"+1 970 854 4300",
    "sg:postcode":"80734",
    "sg:province":"CO",
    "sg:tags":[
        "farm",
        "corn"
    ],
    "wof:name":"Hoffner Co",
    "wof:placetype":"venue"
},
  "geometry": {"coordinates":[-102.30906299999999,40.578945],"type":"Point"}
}