{
  "type": "Feature",
  "properties": {
    "addr:full":"1310 Hwy 133 Carbondale CO 81623",
    "addr:housenumber":"1310",
    "addr:postcode":"81623",
    "addr:street":"Hwy 133",
    "iso:country":"US",
    "sg:address":"1310 Hwy 133",
    "sg:city":"Carbondale",
    "sg:classifiers":[
        {
            "category":"Food & Beverages",
            "subcategory":"Liquor & Beverages",
            "type":"Retail Goods"
        }
    ],
    "sg:phone":"+1 970 963 2355",
    "sg:postcode":"81623",
    "sg:province":"CO",
    "sg:tags":[
        "coin",
        "laundry",
        "alcoholic"
    ],
    "wof:name":"Crystal River Liquor Mart",
    "wof:placetype":"venue"
},
  "geometry": {"coordinates":[-107.215907,39.397064],"type":"Point"}
}