{
  "type": "Feature",
  "properties": {
    "iso:country":"US",
    "sg:address":"11040 Pearl Way",
    "sg:city":"Denver",
    "sg:classifiers":[
        {
            "category":"Building & Trades",
            "subcategory":"Landscaping Services",
            "type":"Services"
        }
    ],
    "sg:phone":"+1 303 452 5951",
    "sg:postcode":"80233",
    "sg:province":"CO",
    "wof:name":"Pro Quality Landscape & Sprink",
    "wof:placetype":"venue"
},
  "geometry": {"coordinates":[-104.97912700000001,39.895236],"type":"Point"}
}