{
  "type": "Feature",
  "properties": {
    "iso:country":"US",
    "sg:address":"2106 Co Rd 106",
    "sg:city":"Elizabeth",
    "sg:classifiers":[
        {
            "category":"Real Estate",
            "subcategory":"Real Estate Agent",
            "type":"Services"
        }
    ],
    "sg:phone":"+1 303 648 3758",
    "sg:postcode":"80107",
    "sg:province":"CO",
    "wof:name":"Stilson Cope Properties LLC",
    "wof:placetype":"venue"
},
  "geometry": {"coordinates":[-104.610029,39.250847],"type":"Point"}
}