{
  "type": "Feature",
  "properties": {
    "addr:full":"14076 E Briarwood Ave Centennial CO 80112",
    "addr:housenumber":"14076",
    "addr:postcode":"80112",
    "addr:street":"E Briarwood Ave",
    "iso:country":"US",
    "sg:address":"14076 E Briarwood Ave",
    "sg:city":"Centennial",
    "sg:classifiers":[
        {
            "category":"Education",
            "subcategory":"School",
            "type":"Public Place"
        }
    ],
    "sg:phone":"+1 720 886 7200",
    "sg:postcode":"80112",
    "sg:province":"CO",
    "sg:website":"www.cherrycreekschools.org",
    "wof:name":"PREP School",
    "wof:placetype":"venue"
},
  "geometry": {"coordinates":[-104.824958,39.592381],"type":"Point"}
}