{
  "type": "Feature",
  "properties": {
    "iso:country":"US",
    "sg:address":"725 Wilcox St",
    "sg:city":"Castle Rock",
    "sg:classifiers":[
        {
            "category":"Professional",
            "type":"Services"
        }
    ],
    "sg:phone":"+1 303 688 7852",
    "sg:postcode":"80104",
    "sg:province":"CO",
    "wof:name":"Home Instead Sr",
    "wof:placetype":"venue"
},
  "geometry": {"coordinates":[-104.860018,39.377834],"type":"Point"}
}