{
  "type": "Feature",
  "properties": {
    "addr:full":"1919 14th St Boulder CO 80302",
    "addr:housenumber":"1919",
    "addr:postcode":"80302",
    "addr:street":"14Th St",
    "iso:country":"US",
    "sg:address":"1919 14th St",
    "sg:city":"Boulder",
    "sg:classifiers":[
        {
            "category":"Professional",
            "subcategory":"Lawyer & Legal Services",
            "type":"Services"
        }
    ],
    "sg:phone":"+1 303 447 1400",
    "sg:postcode":"80302",
    "sg:province":"CO",
    "sg:tags":[
        "attorney"
    ],
    "wof:name":"Mattson & Moorhead",
    "wof:placetype":"venue"
},
  "geometry": {"coordinates":[-105.277191,40.017639],"type":"Point"}
}