{
  "type": "Feature",
  "properties": {
    "iso:country":"US",
    "sg:address":"1520 N Academy Blvd",
    "sg:city":"Colorado Springs",
    "sg:classifiers":[
        {
            "category":"Banks & Credit Unions",
            "subcategory":"Bank",
            "type":"Services"
        }
    ],
    "sg:phone":"+1 719 597 9570",
    "sg:postcode":"80909",
    "sg:province":"CO",
    "sg:tags":[
        "cashing",
        "check"
    ],
    "wof:name":"First American Cash Advance",
    "wof:placetype":"venue"
},
  "geometry": {"coordinates":[-104.757445,38.85707],"type":"Point"}
}