{
  "type": "Feature",
  "properties": {
    "addr:full":"121 W Main St Trinidad CO 81082",
    "addr:housenumber":"121",
    "addr:postcode":"81082",
    "addr:street":"W Main St",
    "iso:country":"US",
    "sg:address":"121 W Main St",
    "sg:city":"Trinidad",
    "sg:classifiers":[
        {
            "category":"Restaurant",
            "type":"Food & Drink"
        }
    ],
    "sg:phone":"+1 719 846 8779",
    "sg:postcode":"81082",
    "sg:province":"CO",
    "sg:tags":[
        "eating"
    ],
    "wof:name":"Main St Bakery Cafe A",
    "wof:placetype":"venue"
},
  "geometry": {"coordinates":[-104.50585700000001,37.168475],"type":"Point"}
}