{
  "type": "Feature",
  "properties": {
    "addr:full":"4555 W Mineral Dr Littleton CO 80128",
    "addr:housenumber":"4555",
    "addr:postcode":"80128",
    "addr:street":"W Mineral Dr",
    "iso:country":"US",
    "sg:address":"4555 W Mineral Dr",
    "sg:city":"Littleton",
    "sg:classifiers":[
        {
            "category":"Manufacturing",
            "subcategory":"Signs",
            "type":"Manufacturing & Wholesale Goods"
        }
    ],
    "sg:phone":"+1 303 904 1270",
    "sg:postcode":"80128",
    "sg:province":"CO",
    "sg:tags":[
        "specialty",
        "mfg"
    ],
    "wof:name":"Century Signs Inc",
    "wof:placetype":"venue"
},
  "geometry": {"coordinates":[-105.052198,39.579295],"type":"Point"}
}