{
  "type": "Feature",
  "properties": {
    "addr:full":"833 E Platte Ave Colorado Springs CO 80903",
    "addr:housenumber":"833",
    "addr:postcode":"80903",
    "addr:street":"E Platte Ave",
    "iso:country":"US",
    "sg:address":"833 E Platte Ave",
    "sg:city":"Colorado Springs",
    "sg:classifiers":[
        {
            "category":"Real Estate",
            "subcategory":"Real Estate Agent",
            "type":"Services"
        }
    ],
    "sg:phone":"+1 719 475 1862",
    "sg:postcode":"80903",
    "sg:province":"CO",
    "wof:name":"Appraisal Network",
    "wof:placetype":"venue"
},
  "geometry": {"coordinates":[-104.808184,38.837638],"type":"Point"}
}