{
  "type": "Feature",
  "properties": {
    "iso:country":"US",
    "sg:address":"9898 E Mexico Ave",
    "sg:city":"Denver",
    "sg:classifiers":[
        {
            "category":"Arts & Performance",
            "subcategory":"Theater",
            "type":"Entertainment"
        }
    ],
    "sg:phone":"+1 720 366 5353",
    "sg:postcode":"80247",
    "sg:province":"CO",
    "sg:tags":[
        "entertainer"
    ],
    "wof:name":"Ebony Sabbath",
    "wof:placetype":"venue"
},
  "geometry": {"coordinates":[-104.872613,39.685589],"type":"Point"}
}