{
  "type": "Feature",
  "properties": {
    "addr:full":"4745 Bunchberry Ln Colorado Springs CO 80917",
    "addr:housenumber":"4745",
    "addr:postcode":"80917",
    "addr:street":"Bunchberry Ln",
    "iso:country":"US",
    "sg:address":"4745 Bunchberry Ln",
    "sg:city":"Colorado Springs",
    "sg:classifiers":[
        {
            "category":"Wholesale",
            "subcategory":"Hardware",
            "type":"Manufacturing & Wholesale Goods"
        }
    ],
    "sg:phone":"+1 719 573 1981",
    "sg:postcode":"80917",
    "sg:province":"CO",
    "sg:tags":[
        "refrigerating"
    ],
    "wof:name":"Joseph Refrigeration-Heating",
    "wof:placetype":"venue"
},
  "geometry": {"coordinates":[-104.73750099999999,38.900912],"type":"Point"}
}