{
  "type": "Feature",
  "properties": {
    "iso:country":"US",
    "sg:address":"619 Agana Dr",
    "sg:city":"Grand Junction",
    "sg:classifiers":[
        {
            "category":"Building & Trades",
            "subcategory":"Construction",
            "type":"Services"
        }
    ],
    "sg:phone":"+1 970 523 9063",
    "sg:postcode":"81504",
    "sg:province":"CO",
    "sg:tags":[
        "contractor"
    ],
    "wof:name":"Bunch Construction",
    "wof:placetype":"venue"
},
  "geometry": {"coordinates":[-108.494456,39.09438],"type":"Point"}
}