{
  "type": "Feature",
  "properties": {
    "iso:country":"US",
    "sg:address":"1336 Leyden St",
    "sg:city":"Denver",
    "sg:classifiers":[
        {
            "category":"Health Services",
            "subcategory":"Optometrist",
            "type":"Services"
        }
    ],
    "sg:phone":"+1 303 333 1010",
    "sg:postcode":"80220",
    "sg:province":"CO",
    "sg:website":"www.mayfairvisionclinic.com",
    "wof:name":"Mayfair Vision Clinic",
    "wof:placetype":"venue"
},
  "geometry": {"coordinates":[-104.915001,39.737],"type":"Point"}
}