{
  "type": "Feature",
  "properties": {
    "iso:country":"US",
    "sg:address":"16519 W 55th Dr",
    "sg:city":"Golden",
    "sg:classifiers":[
        {
            "category":"Professional",
            "type":"Services"
        }
    ],
    "sg:phone":"+1 303 358 3936",
    "sg:postcode":"80403",
    "sg:province":"CO",
    "wof:name":"Warbirds West Inc",
    "wof:placetype":"venue"
},
  "geometry": {"coordinates":[-105.185654,39.796901],"type":"Point"}
}