{
  "type": "Feature",
  "properties": {
    "iso:country":"US",
    "sg:address":"4901 W 38th Ave",
    "sg:city":"Denver",
    "sg:classifiers":[
        {
            "category":"Health Services",
            "subcategory":"Doctor",
            "type":"Services"
        }
    ],
    "sg:phone":"+1 303 781 7862",
    "sg:postcode":"80212",
    "sg:province":"CO",
    "sg:website":"www.drgentile.com",
    "wof:name":"Gentile Maria T DO",
    "wof:placetype":"venue"
},
  "geometry": {"coordinates":[-105.049976,39.769618],"type":"Point"}
}