{
  "type": "Feature",
  "properties": {
    "addr:full":"2003 W Arbor Ave Littleton CO 80120",
    "addr:housenumber":"2003",
    "addr:postcode":"80120",
    "addr:street":"W Arbor Ave",
    "iso:country":"US",
    "sg:address":"2003 W Arbor Ave",
    "sg:city":"Littleton",
    "sg:classifiers":[
        {
            "category":"Communications",
            "subcategory":"Film & Video Production",
            "type":"Services"
        }
    ],
    "sg:phone":"+1 303 738 0278",
    "sg:postcode":"80120",
    "sg:province":"CO",
    "sg:tags":[
        "audio"
    ],
    "wof:name":"Surefire Productions",
    "wof:placetype":"venue"
},
  "geometry": {"coordinates":[-105.013919,39.603665],"type":"Point"}
}