{
  "type": "Feature",
  "properties": {
    "iso:country":"US",
    "sg:address":"2395 Cherry St",
    "sg:city":"Canon City",
    "sg:classifiers":[
        {
            "category":"Organizations",
            "subcategory":"Religious Organization",
            "type":"Services"
        }
    ],
    "sg:phone":"+1 719 275 7337",
    "sg:postcode":"81212",
    "sg:province":"CO",
    "sg:tags":[
        "church"
    ],
    "wof:name":"Freedom Center Chr On The Rock",
    "wof:placetype":"venue"
},
  "geometry": {"coordinates":[-105.21267400000001,38.454064],"type":"Point"}
}