{
  "type": "Feature",
  "properties": {
    "addr:full":"386 Beaver Trl Bailey CO 80421",
    "addr:housenumber":"386",
    "addr:postcode":"80421",
    "addr:street":"Beaver Trl",
    "iso:country":"US",
    "sg:address":"386 Beaver Trl",
    "sg:city":"Bailey",
    "sg:classifiers":[
        {
            "category":"Building & Trades",
            "subcategory":"Construction",
            "type":"Services"
        }
    ],
    "sg:phone":"+1 303 816 1565",
    "sg:postcode":"80421",
    "sg:province":"CO",
    "sg:tags":[
        "contractor"
    ],
    "wof:name":"CBM Consulting",
    "wof:placetype":"venue"
},
  "geometry": {"coordinates":[-105.45746800000001,39.424163],"type":"Point"}
}