{
  "type": "Feature",
  "properties": {
    "addr:full":"320 Broadway Denver CO 80203",
    "addr:housenumber":"320",
    "addr:postcode":"80203",
    "addr:street":"Broadway",
    "iso:country":"US",
    "sg:address":"320 Broadway",
    "sg:city":"Denver",
    "sg:classifiers":[
        {
            "category":"Insurance",
            "subcategory":"Insurance Agent",
            "type":"Services"
        }
    ],
    "sg:phone":"+1 303 534 4285",
    "sg:postcode":"80203",
    "sg:province":"CO",
    "wof:name":"Troyer Insurance",
    "wof:placetype":"venue"
},
  "geometry": {"coordinates":[-104.987402,39.722211],"type":"Point"}
}