{
  "type": "Feature",
  "properties": {
    "iso:country":"US",
    "sg:address":"951 W Elkhorn Ave",
    "sg:city":"Estes Park",
    "sg:classifiers":[
        {
            "category":"Organizations",
            "subcategory":"Religious Organization",
            "type":"Services"
        }
    ],
    "sg:phone":"+1 970 586 2729",
    "sg:postcode":"80517",
    "sg:province":"CO",
    "sg:tags":[
        "church"
    ],
    "wof:name":"Christian Science Svc",
    "wof:placetype":"venue"
},
  "geometry": {"coordinates":[-105.540909,40.382834],"type":"Point"}
}