{
  "type": "Feature",
  "properties": {
    "iso:country":"US",
    "sg:address":"24300 Co Rd 11",
    "sg:city":"Yampa",
    "sg:classifiers":[
        {
            "category":"Farming",
            "subcategory":"Livestock Farm",
            "type":"Manufacturing & Wholesale Goods"
        }
    ],
    "sg:phone":"+1 970 638 4604",
    "sg:postcode":"80403",
    "sg:province":"CO",
    "sg:tags":[
        "ranch"
    ],
    "wof:name":"Lazy EH Ranch",
    "wof:placetype":"venue"
},
  "geometry": {"coordinates":[-105.46325899999999,39.892831],"type":"Point"}
}