{
  "type": "Feature",
  "properties": {
    "addr:full":"422 Idlewild Dr Dillon CO 80435",
    "addr:housenumber":"422",
    "addr:postcode":"80435",
    "addr:street":"Idlewild Dr",
    "iso:country":"US",
    "sg:address":"422 Idlewild Dr",
    "sg:city":"Dillon",
    "sg:classifiers":[
        {
            "category":"Building & Trades",
            "subcategory":"Construction",
            "type":"Services"
        }
    ],
    "sg:phone":"+1 970 390 4177",
    "sg:postcode":"80435",
    "sg:province":"CO",
    "sg:tags":[
        "painter"
    ],
    "wof:name":"Venturoni Painting",
    "wof:placetype":"venue"
},
  "geometry": {"coordinates":[-106.000765,39.592874],"type":"Point"}
}