{
  "type": "Feature",
  "properties": {
    "iso:country":"US",
    "sg:address":"3111 N el Paso St",
    "sg:city":"Colorado Springs",
    "sg:classifiers":[
        {
            "category":"Building & Trades",
            "subcategory":"Landscaping Services",
            "type":"Services"
        }
    ],
    "sg:phone":"+1 719 447 0174",
    "sg:postcode":"80907",
    "sg:province":"CO",
    "wof:name":"Grants Landscape Maintenance",
    "wof:placetype":"venue"
},
  "geometry": {"coordinates":[-104.812736,38.878415],"type":"Point"}
}