{
  "type": "Feature",
  "properties": {
    "addr:full":"815 Lincoln Ave Steamboat Spgs CO 80487",
    "addr:housenumber":"815",
    "addr:postcode":"80487",
    "addr:street":"Lincoln Ave;Spgs",
    "iso:country":"US",
    "sg:address":"815 Lincoln Ave",
    "sg:city":"Steamboat Spgs",
    "sg:classifiers":[
        {
            "category":"Shopping",
            "subcategory":"Optical Goods",
            "type":"Retail Goods"
        }
    ],
    "sg:phone":"+1 970 870 0142",
    "sg:postcode":"80487",
    "sg:province":"CO",
    "sg:tags":[
        "sun",
        "goggles",
        "sunglasses"
    ],
    "wof:name":"Visia Eyewear",
    "wof:placetype":"venue"
},
  "geometry": {"coordinates":[-106.83564800000001,40.486622],"type":"Point"}
}