{
  "type": "Feature",
  "properties": {
    "addr:full":"16455 Co Rd 21 Fort Morgan CO 80701",
    "addr:housenumber":"16455;21",
    "addr:postcode":"80701",
    "addr:street":"Co Rd",
    "iso:country":"US",
    "sg:address":"16455 Co Rd 21",
    "sg:city":"Fort Morgan",
    "sg:classifiers":[
        {
            "category":"Social Services",
            "type":"Services"
        }
    ],
    "sg:phone":"+1 970 867 2218",
    "sg:postcode":"80701",
    "sg:province":"CO",
    "sg:tags":[
        "organization",
        "welfare"
    ],
    "wof:name":"United Way",
    "wof:placetype":"venue"
},
  "geometry": {"coordinates":[-103.75448,40.23301],"type":"Point"}
}