{
  "type": "Feature",
  "properties": {
    "addr:full":"1320 Simms St Golden CO 80401",
    "addr:housenumber":"1320",
    "addr:postcode":"80401",
    "addr:street":"Simms St",
    "iso:country":"US",
    "sg:address":"1320 Simms St",
    "sg:city":"Golden",
    "sg:classifiers":[
        {
            "category":"Professional",
            "subcategory":"Testing Lab",
            "type":"Services"
        },
        {
            "category":"Professional",
            "subcategory":"Management & Consulting",
            "type":"Services"
        }
    ],
    "sg:phone":"+1 303 232 2660",
    "sg:postcode":"80401",
    "sg:province":"CO",
    "sg:tags":[
        "asbestos"
    ],
    "wof:name":"Foothills Environmental Inc",
    "wof:placetype":"venue"
},
  "geometry": {"coordinates":[-105.128276,39.736942],"type":"Point"}
}