{
  "type": "Feature",
  "properties": {
    "addr:full":"530 Main St Meeker CO 81641",
    "addr:housenumber":"530",
    "addr:postcode":"81641",
    "addr:street":"Main St",
    "iso:country":"US",
    "sg:address":"530 Main St",
    "sg:city":"Meeker",
    "sg:classifiers":[
        {
            "category":"Shopping",
            "subcategory":"Pharmacy",
            "type":"Retail Goods"
        }
    ],
    "sg:phone":"+1 970 878 5071",
    "sg:postcode":"81641",
    "sg:province":"CO",
    "wof:name":"Meeker Drug",
    "wof:placetype":"venue"
},
  "geometry": {"coordinates":[-107.91268599999999,40.037433],"type":"Point"}
}