{
  "type": "Feature",
  "properties": {
    "addr:full":"510 E 11th St Leadville CO 80461",
    "addr:housenumber":"510",
    "addr:postcode":"80461",
    "addr:street":"E 11Th St",
    "iso:country":"US",
    "sg:address":"510 E 11th St",
    "sg:city":"Leadville",
    "sg:classifiers":[
        {
            "category":"Shopping",
            "subcategory":"Clothing, Apparel, & Fashions",
            "type":"Retail Goods"
        }
    ],
    "sg:phone":"+1 719 486 0701",
    "sg:postcode":"80461",
    "sg:province":"CO",
    "wof:name":"Dupont Graphics",
    "wof:placetype":"venue"
},
  "geometry": {"coordinates":[-106.28522100000001,39.254583],"type":"Point"}
}