{
  "type": "Feature",
  "properties": {
    "iso:country":"US",
    "sg:address":"650 S Cherry St",
    "sg:city":"Denver",
    "sg:classifiers":[
        {
            "category":"Professional",
            "subcategory":"Accounting & Tax Preparation",
            "type":"Services"
        }
    ],
    "sg:phone":"+1 303 399 8722",
    "sg:postcode":"80246",
    "sg:province":"CO",
    "sg:tags":[
        "accountant"
    ],
    "wof:name":"Smith Brock & Gwinn",
    "wof:placetype":"venue"
},
  "geometry": {"coordinates":[-104.933635,39.704826],"type":"Point"}
}