{
  "type": "Feature",
  "properties": {
    "iso:country":"US",
    "sg:address":"7961 Shaffer Pkwy",
    "sg:city":"Littleton",
    "sg:classifiers":[
        {
            "category":"Professional",
            "subcategory":"Engineering",
            "type":"Services"
        }
    ],
    "sg:phone":"+1 303 979 4690",
    "sg:postcode":"80127",
    "sg:province":"CO",
    "sg:tags":[
        "general",
        "contractor"
    ],
    "wof:name":"Wunderlich Malec Engineering",
    "wof:placetype":"venue"
},
  "geometry": {"coordinates":[-105.130014,39.572167],"type":"Point"}
}