{
  "type": "Feature",
  "properties": {
    "addr:full":"1143 13th St Boulder CO 80302",
    "addr:housenumber":"1143",
    "addr:postcode":"80302",
    "addr:street":"13Th St",
    "iso:country":"US",
    "sg:address":"1143 13th St",
    "sg:city":"Boulder",
    "sg:classifiers":[
        {
            "category":"Bars & Pubs",
            "type":"Food & Drink"
        },
        {
            "category":"Restaurant",
            "type":"Food & Drink"
        }
    ],
    "sg:menulink":"http://www.allmenus.com/co/boulder/4030-the-players-club/menu/",
    "sg:phone":"+1 303 942 8009",
    "sg:postcode":"80302",
    "sg:province":"CO",
    "sg:tags":[
        "american"
    ],
    "wof:name":"The Players Club",
    "wof:placetype":"venue"
},
  "geometry": {"coordinates":[-105.276225,40.007891],"type":"Point"}
}