{
  "type": "Feature",
  "properties": {
    "iso:country":"US",
    "sg:address":"8795 Ralston Rd",
    "sg:city":"Arvada",
    "sg:classifiers":[
        {
            "category":"Banks & Credit Unions",
            "subcategory":"Bank",
            "type":"Services"
        }
    ],
    "sg:phone":"+1 303 431 1588",
    "sg:postcode":"80002",
    "sg:province":"CO",
    "sg:tags":[
        "broker",
        "mortgage"
    ],
    "wof:name":"Capital Financial Network LLC",
    "wof:placetype":"venue"
},
  "geometry": {"coordinates":[-105.09472599999999,39.802127],"type":"Point"}
}