{
  "type": "Feature",
  "properties": {
    "addr:full":"17483 Co Rd 501 Bayfield CO 81122",
    "addr:housenumber":"17483",
    "addr:postcode":"81122",
    "addr:street":"Co Rd 501",
    "iso:country":"US",
    "sg:address":"17483 Co Rd 501",
    "sg:city":"Bayfield",
    "sg:classifiers":[
        {
            "category":"Real Estate",
            "subcategory":"Real Estate Agent",
            "type":"Services"
        }
    ],
    "sg:phone":"+1 970 884 4627",
    "sg:postcode":"81122",
    "sg:province":"CO",
    "wof:name":"Realty Executives",
    "wof:placetype":"venue"
},
  "geometry": {"coordinates":[-107.557968,37.438063],"type":"Point"}
}