{
  "type": "Feature",
  "properties": {
    "addr:full":"908 8th St Greeley CO 80631",
    "addr:housenumber":"908",
    "addr:postcode":"80631",
    "addr:street":"8Th St",
    "iso:country":"US",
    "sg:address":"908 8th St",
    "sg:city":"Greeley",
    "sg:classifiers":[
        {
            "category":"Communications",
            "subcategory":"Radio Station",
            "type":"Services"
        }
    ],
    "sg:phone":"+1 970 356 1450",
    "sg:postcode":"80631",
    "sg:province":"CO",
    "sg:tags":[
        "company",
        "broadcasting"
    ],
    "wof:name":"KGRE",
    "wof:placetype":"venue"
},
  "geometry": {"coordinates":[-104.694311,40.424821],"type":"Point"}
}