{
  "type": "Feature",
  "properties": {
    "addr:full":"310 Belview Ct Longmont CO 80501",
    "addr:housenumber":"310",
    "addr:postcode":"80501",
    "addr:street":"Belview Ct",
    "iso:country":"US",
    "sg:address":"310 Belview Ct",
    "sg:city":"Longmont",
    "sg:classifiers":[
        {
            "category":"Building & Trades",
            "subcategory":"Plumbing",
            "type":"Services"
        }
    ],
    "sg:phone":"+1 303 776 6062",
    "sg:postcode":"80501",
    "sg:province":"CO",
    "sg:tags":[
        "contractor"
    ],
    "wof:name":"Longmont Plumbing & Heating",
    "wof:placetype":"venue"
},
  "geometry": {"coordinates":[-105.127753,40.167985],"type":"Point"}
}