{
  "type": "Feature",
  "properties": {
    "addr:full":"995 S Chase St Lakewood CO 80226",
    "addr:housenumber":"995",
    "addr:postcode":"80226",
    "addr:street":"S Chase St",
    "iso:country":"US",
    "sg:address":"995 S Chase St",
    "sg:city":"Lakewood",
    "sg:classifiers":[
        {
            "category":"Professional",
            "subcategory":"Computer Services",
            "type":"Services"
        }
    ],
    "sg:phone":"+1 303 934 1975",
    "sg:postcode":"80226",
    "sg:province":"CO",
    "sg:tags":[
        "home",
        "consulting",
        "page",
        "dev",
        "internet"
    ],
    "sg:website":"www.shopdirect.com",
    "wof:name":"Shop Direct",
    "wof:placetype":"venue"
},
  "geometry": {"coordinates":[-105.058522,39.698661],"type":"Point"}
}