{
  "type": "Feature",
  "properties": {
    "iso:country":"US",
    "sg:address":"3001 Rawhide Dr",
    "sg:city":"Laporte",
    "sg:classifiers":[
        {
            "category":"Building & Trades",
            "subcategory":"Construction",
            "type":"Services"
        }
    ],
    "sg:phone":"+1 970 482 6950",
    "sg:postcode":"80535",
    "sg:province":"CO",
    "sg:tags":[
        "excavating",
        "contractor"
    ],
    "wof:name":"Willford Excavating",
    "wof:placetype":"venue"
},
  "geometry": {"coordinates":[-105.149394,40.631459],"type":"Point"}
}