{
  "type": "Feature",
  "properties": {
    "addr:full":"8156 W Bowles Ave Littleton CO 80123",
    "addr:housenumber":"8156",
    "addr:postcode":"80123",
    "addr:street":"W Bowles Ave",
    "iso:country":"US",
    "sg:address":"8156 W Bowles Ave",
    "sg:city":"Littleton",
    "sg:classifiers":[
        {
            "category":"Restaurant",
            "type":"Food & Drink"
        }
    ],
    "sg:phone":"+1 303 904 9495",
    "sg:postcode":"80123",
    "sg:province":"CO",
    "sg:tags":[
        "eating",
        "italian"
    ],
    "sg:website":"http://www.macaronigrill.com",
    "wof:name":"Romano's Macaroni Grill",
    "wof:placetype":"venue"
},
  "geometry": {"coordinates":[-105.08794899999999,39.609643],"type":"Point"}
}