{
  "type": "Feature",
  "properties": {
    "addr:full":"220 Main St Delta CO 81416",
    "addr:housenumber":"220",
    "addr:postcode":"81416",
    "addr:street":"Main St",
    "iso:country":"US",
    "sg:address":"220 Main St",
    "sg:city":"Delta",
    "sg:classifiers":[
        {
            "category":"Restaurant",
            "type":"Food & Drink"
        }
    ],
    "sg:phone":"+1 970 874 7060",
    "sg:postcode":"81416",
    "sg:province":"CO",
    "sg:tags":[
        "eating"
    ],
    "wof:name":"Critters Sports Bar & Grill",
    "wof:placetype":"venue"
},
  "geometry": {"coordinates":[-108.070713,38.744018],"type":"Point"}
}