{
  "type": "Feature",
  "properties": {
    "addr:full":"141 W Meadow Dr Vail CO 81657",
    "addr:housenumber":"141",
    "addr:postcode":"81657",
    "addr:street":"W Meadow Dr",
    "iso:country":"US",
    "sg:address":"141 W Meadow Dr",
    "sg:city":"Vail",
    "sg:classifiers":[
        {
            "category":"Professional",
            "type":"Services"
        }
    ],
    "sg:phone":"+1 970 476 7436",
    "sg:postcode":"81657",
    "sg:province":"CO",
    "sg:tags":[
        "establishment"
    ],
    "wof:name":"Skaalhus",
    "wof:placetype":"venue"
},
  "geometry": {"coordinates":[-106.38284899999999,39.64302],"type":"Point"}
}