{
  "type": "Feature",
  "properties": {
    "addr:full":"1902 W Colorado Ave Colorado Springs CO 80904",
    "addr:housenumber":"1902",
    "addr:postcode":"80904",
    "addr:street":"W Colorado Ave",
    "iso:country":"US",
    "sg:address":"1902 W Colorado Ave",
    "sg:city":"Colorado Springs",
    "sg:classifiers":[
        {
            "category":"Personal",
            "subcategory":"Beauty Salon",
            "type":"Services"
        }
    ],
    "sg:phone":"+1 719 473 5506",
    "sg:postcode":"80904",
    "sg:province":"CO",
    "wof:name":"Tangles Salon",
    "wof:placetype":"venue"
},
  "geometry": {"coordinates":[-104.85512900000001,38.842669],"type":"Point"}
}