{
  "type": "Feature",
  "properties": {
    "iso:country":"US",
    "sg:address":"1100 W Evans Ave",
    "sg:city":"Denver",
    "sg:classifiers":[
        {
            "category":"Retail",
            "subcategory":"Auto Repair",
            "type":"Services"
        }
    ],
    "sg:phone":"+1 303 922 7665",
    "sg:postcode":"80223",
    "sg:province":"CO",
    "wof:name":"Mitsubishi Hyundai Specialist",
    "wof:placetype":"venue"
},
  "geometry": {"coordinates":[-105.000942,39.678127],"type":"Point"}
}