{
  "type": "Feature",
  "properties": {
    "addr:full":"10382 Coal Ridge St Firestone CO 80504",
    "addr:housenumber":"10382",
    "addr:postcode":"80504",
    "addr:street":"Coal Ridge St",
    "iso:country":"US",
    "sg:address":"10382 Coal Ridge St",
    "sg:city":"Firestone",
    "sg:classifiers":[
        {
            "category":"Arts & Performance",
            "subcategory":"Theater",
            "type":"Entertainment"
        },
        {
            "category":"Shopping",
            "subcategory":"Musical Instruments",
            "type":"Retail Goods"
        }
    ],
    "sg:phone":"+1 303 682 5242",
    "sg:postcode":"80504",
    "sg:province":"CO",
    "sg:tags":[
        "live",
        "music"
    ],
    "wof:name":"Quality Mobile Sound",
    "wof:placetype":"venue"
},
  "geometry": {"coordinates":[-104.943456,40.151355],"type":"Point"}
}