{
  "type": "Feature",
  "properties": {
    "iso:country":"US",
    "sg:address":"2124 Douglas Mountain Dr",
    "sg:city":"Golden",
    "sg:classifiers":[
        {
            "category":"Retail",
            "subcategory":"Car Wash",
            "type":"Services"
        }
    ],
    "sg:phone":"+1 303 937 0311",
    "sg:postcode":"80403",
    "sg:province":"CO",
    "sg:tags":[
        "carwash"
    ],
    "wof:name":"A S A P Mobile Wash Inc",
    "wof:placetype":"venue"
},
  "geometry": {"coordinates":[-105.39585,39.749137],"type":"Point"}
}