{
  "type": "Feature",
  "properties": {
    "iso:country":"US",
    "sg:address":"1202 Folsom St",
    "sg:city":"Boulder",
    "sg:classifiers":[
        {
            "category":"Organizations",
            "subcategory":"Religious Organization",
            "type":"Services"
        }
    ],
    "sg:phone":"+1 303 443 8720",
    "sg:postcode":"80302",
    "sg:province":"CO",
    "sg:tags":[
        "church"
    ],
    "wof:name":"University Lutheran Chapel",
    "wof:placetype":"venue"
},
  "geometry": {"coordinates":[-105.264055,40.009524],"type":"Point"}
}