{
  "type": "Feature",
  "properties": {
    "iso:country":"US",
    "sg:address":"11756 E Evans Ave",
    "sg:city":"Aurora",
    "sg:classifiers":[
        {
            "category":"Professional",
            "subcategory":"Management & Consulting",
            "type":"Services"
        }
    ],
    "sg:phone":"+1 303 745 4493",
    "sg:postcode":"80014",
    "sg:province":"CO",
    "sg:tags":[
        "consultant",
        "business"
    ],
    "wof:name":"Nextgen Software Inc",
    "wof:placetype":"venue"
},
  "geometry": {"coordinates":[-104.850477,39.677994],"type":"Point"}
}