{
  "type": "Feature",
  "properties": {
    "addr:full":"2610 Black Canyon Rd Colorado Springs CO 80904",
    "addr:housenumber":"2610",
    "addr:postcode":"80904",
    "addr:street":"Black Canyon Rd",
    "iso:country":"US",
    "sg:address":"2610 Black Canyon Rd",
    "sg:city":"Colorado Springs",
    "sg:classifiers":[
        {
            "category":"Building & Trades",
            "subcategory":"Locksmith",
            "type":"Services"
        }
    ],
    "sg:phone":"+1 719 313 5020",
    "sg:postcode":"80904",
    "sg:province":"CO",
    "sg:tags":[
        "key"
    ],
    "wof:name":"A Locksmith A 24 Hour",
    "wof:placetype":"venue"
},
  "geometry": {"coordinates":[-104.905894,38.869206],"type":"Point"}
}