{
  "type": "Feature",
  "properties": {
    "iso:country":"US",
    "sg:address":"2953 S Peoria St",
    "sg:city":"Aurora",
    "sg:classifiers":[
        {
            "category":"Professional",
            "subcategory":"Engineering",
            "type":"Services"
        }
    ],
    "sg:phone":"+1 303 337 4700",
    "sg:postcode":"80014",
    "sg:province":"CO",
    "sg:tags":[
        "engineer"
    ],
    "wof:name":"Venture Engineering Corp",
    "wof:placetype":"venue"
},
  "geometry": {"coordinates":[-104.847328,39.662461],"type":"Point"}
}