{
  "type": "Feature",
  "properties": {
    "addr:full":"1098 S Wadsworth Blvd Lakewood CO 80226",
    "addr:housenumber":"1098",
    "addr:postcode":"80226",
    "addr:street":"S Wadsworth Blvd",
    "iso:country":"US",
    "sg:address":"1098 S Wadsworth Blvd",
    "sg:city":"Lakewood",
    "sg:classifiers":[
        {
            "category":"Retail",
            "subcategory":"Auto Repair",
            "type":"Services"
        }
    ],
    "sg:phone":"+1 303 934 1098",
    "sg:postcode":"80226",
    "sg:province":"CO",
    "sg:tags":[
        "automobile",
        "lubrication"
    ],
    "wof:name":"Grease Monkey",
    "wof:placetype":"venue"
},
  "geometry": {"coordinates":[-105.081509,39.69858],"type":"Point"}
}