{
  "type": "Feature",
  "properties": {
    "iso:country":"US",
    "sg:address":"4856 Chambers Rd",
    "sg:city":"Denver",
    "sg:classifiers":[
        {
            "category":"Food & Beverages",
            "subcategory":"Liquor & Beverages",
            "type":"Retail Goods"
        }
    ],
    "sg:phone":"+1 303 373 1100",
    "sg:postcode":"80239",
    "sg:province":"CO",
    "wof:name":"Chambers Place Liquors",
    "wof:placetype":"venue"
},
  "geometry": {"coordinates":[-104.809792,39.77898],"type":"Point"}
}