{
  "type": "Feature",
  "properties": {
    "iso:country":"US",
    "sg:address":"4045 Wadsworth Boulevard",
    "sg:city":"Wheat Ridge",
    "sg:classifiers":[
        {
            "category":"Health Services",
            "subcategory":"Optometrist",
            "type":"Services"
        }
    ],
    "sg:phone":"+1 303 456 9456",
    "sg:postcode":"80033",
    "sg:province":"CO",
    "wof:name":"King Robert MD",
    "wof:placetype":"venue"
},
  "geometry": {"coordinates":[-105.081444,39.772509],"type":"Point"}
}