{
  "type": "Feature",
  "properties": {
    "addr:full":"766 Valley Ct Grand Junction CO 81505",
    "addr:housenumber":"766",
    "addr:postcode":"81505",
    "addr:street":"Valley Ct",
    "iso:country":"US",
    "sg:address":"766 Valley Ct",
    "sg:city":"Grand Junction",
    "sg:classifiers":[
        {
            "category":"Freight",
            "type":"Transportation"
        }
    ],
    "sg:phone":"+1 970 677 2640",
    "sg:postcode":"81505",
    "sg:province":"CO",
    "sg:tags":[
        "dry",
        "bulk",
        "trucking"
    ],
    "wof:name":"Thompson Trucking",
    "wof:placetype":"venue"
},
  "geometry": {"coordinates":[-108.649933,39.114935],"type":"Point"}
}