{
  "type": "Feature",
  "properties": {
    "addr:full":"1225 Boston Ave Longmont CO 80501",
    "addr:housenumber":"1225",
    "addr:postcode":"80501",
    "addr:street":"Boston Ave",
    "iso:country":"US",
    "sg:address":"1225 Boston Ave",
    "sg:city":"Longmont",
    "sg:classifiers":[
        {
            "category":"Manufacturing",
            "subcategory":"Textiles",
            "type":"Manufacturing & Wholesale Goods"
        }
    ],
    "sg:phone":"+1 303 651 3236",
    "sg:postcode":"80501",
    "sg:province":"CO",
    "sg:tags":[
        "finishing",
        "plant",
        "cotton"
    ],
    "wof:name":"Neographics",
    "wof:placetype":"venue"
},
  "geometry": {"coordinates":[-105.114205,40.158689],"type":"Point"}
}