{
  "type": "Feature",
  "properties": {
    "iso:country":"US",
    "sg:address":"8315 S Wadsworth Blvd",
    "sg:city":"Littleton",
    "sg:classifiers":[
        {
            "category":"Banks & Credit Unions",
            "subcategory":"Bank",
            "type":"Services"
        }
    ],
    "sg:phone":"+1 303 979 7800",
    "sg:postcode":"80128",
    "sg:province":"CO",
    "sg:tags":[
        "mortgage"
    ],
    "wof:name":"Milton Valley Mortgage",
    "wof:placetype":"venue"
},
  "geometry": {"coordinates":[-105.082762,39.562085],"type":"Point"}
}