{
  "type": "Feature",
  "properties": {
    "addr:full":"1440 Stockyard Rd Pueblo CO 81001",
    "addr:housenumber":"1440",
    "addr:postcode":"81001",
    "addr:street":"Stockyard Rd",
    "iso:country":"US",
    "sg:address":"1440 Stockyard Rd",
    "sg:city":"Pueblo",
    "sg:classifiers":[
        {
            "category":"Utilities",
            "subcategory":"Refuse",
            "type":"Services"
        }
    ],
    "sg:phone":"+1 719 545 6558",
    "sg:postcode":"81001",
    "sg:province":"CO",
    "sg:tags":[
        "system"
    ],
    "wof:name":"Pueblo Sanitation Inc",
    "wof:placetype":"venue"
},
  "geometry": {"coordinates":[-104.583366,38.255886],"type":"Point"}
}