{
  "type": "Feature",
  "properties": {
    "addr:full":"3065 Windjammer Dr Colorado Springs CO 80920",
    "addr:housenumber":"3065",
    "addr:postcode":"80920",
    "addr:street":"Windjammer Dr",
    "iso:country":"US",
    "sg:address":"3065 Windjammer Dr",
    "sg:city":"Colorado Springs",
    "sg:classifiers":[
        {
            "category":"Wholesale",
            "subcategory":"Machinery & Supplies",
            "type":"Manufacturing & Wholesale Goods"
        }
    ],
    "sg:phone":"+1 719 598 5567",
    "sg:postcode":"80920",
    "sg:province":"CO",
    "sg:tags":[
        "equipment",
        "industrial"
    ],
    "wof:name":"Sales Automation Technologies",
    "wof:placetype":"venue"
},
  "geometry": {"coordinates":[-104.769685,38.953682],"type":"Point"}
}