{
  "type": "Feature",
  "properties": {
    "iso:country":"US",
    "sg:address":"305 Pine Ridge Ave",
    "sg:city":"Manitou Springs",
    "sg:classifiers":[
        {
            "category":"Manufacturing",
            "subcategory":"Toys & Sporting Goods",
            "type":"Manufacturing & Wholesale Goods"
        }
    ],
    "sg:phone":"+1 719 685 4642",
    "sg:postcode":"80829",
    "sg:province":"CO",
    "sg:tags":[
        "mfg"
    ],
    "wof:name":"Leatherbee Bears",
    "wof:placetype":"venue"
},
  "geometry": {"coordinates":[-104.92319500000001,38.86063],"type":"Point"}
}