{
  "type": "Feature",
  "properties": {
    "iso:country":"US",
    "sg:address":"120 S 1st St E",
    "sg:city":"Cheyenne Wells",
    "sg:classifiers":[
        {
            "category":"Organizations",
            "subcategory":"Community Association",
            "type":"Services"
        }
    ],
    "sg:phone":"+1 719 767 5353",
    "sg:postcode":"80810",
    "sg:province":"CO",
    "sg:tags":[
        "fraternal"
    ],
    "wof:name":"Knights Of Columbus",
    "wof:placetype":"venue"
},
  "geometry": {"coordinates":[-102.347263,38.820708],"type":"Point"}
}