{
  "type": "Feature",
  "properties": {
    "iso:country":"US",
    "sg:address":"2039 S University Blvd",
    "sg:city":"Denver",
    "sg:classifiers":[
        {
            "category":"Restaurant",
            "type":"Food & Drink"
        }
    ],
    "sg:phone":"+1 720 475 1603",
    "sg:postcode":"80210",
    "sg:province":"CO",
    "sg:tags":[
        "greek"
    ],
    "sg:website":"thegreeksgonewild.com/blog/menu/",
    "wof:name":"Greeks Gone Wild",
    "wof:placetype":"venue"
},
  "geometry": {"coordinates":[-104.959513,39.679479],"type":"Point"}
}