{
  "type": "Feature",
  "properties": {
    "iso:country":"US",
    "sg:address":"208 S Main St",
    "sg:city":"Holly",
    "sg:classifiers":[
        {
            "category":"Government",
            "subcategory":"Office",
            "type":"Public Place"
        }
    ],
    "sg:phone":"+1 719 537 6945",
    "sg:postcode":"81047",
    "sg:province":"CO",
    "wof:name":"Prowers County Senior Svc",
    "wof:placetype":"venue"
},
  "geometry": {"coordinates":[-102.12272900000001,38.051932],"type":"Point"}
}