{
  "type": "Feature",
  "properties": {
    "addr:full":"1119 Phillips Ct Montrose CO 81401",
    "addr:housenumber":"1119",
    "addr:postcode":"81401",
    "addr:street":"Phillips Ct",
    "iso:country":"US",
    "sg:address":"1119 Phillips Ct",
    "sg:city":"Montrose",
    "sg:classifiers":[
        {
            "category":"Banks & Credit Unions",
            "subcategory":"Bank",
            "type":"Services"
        }
    ],
    "sg:phone":"+1 970 240 3000",
    "sg:postcode":"81401",
    "sg:province":"CO",
    "sg:tags":[
        "loan"
    ],
    "wof:name":"Colorado West Payday Loans",
    "wof:placetype":"venue"
},
  "geometry": {"coordinates":[-107.851494,38.475129],"type":"Point"}
}