{
  "type": "Feature",
  "properties": {
    "iso:country":"US",
    "sg:address":"600 17th St",
    "sg:city":"Denver",
    "sg:classifiers":[
        {
            "category":"Building & Trades",
            "subcategory":"Locksmith",
            "type":"Services"
        }
    ],
    "sg:phone":"+1 770 278 7141",
    "sg:postcode":"80202",
    "sg:province":"CO",
    "sg:tags":[
        "key"
    ],
    "wof:name":"Jason Locksmith Denver CO",
    "wof:placetype":"venue"
},
  "geometry": {"coordinates":[-104.990796,39.745293],"type":"Point"}
}