{
  "type": "Feature",
  "properties": {
    "iso:country":"US",
    "sg:address":"610 Main St",
    "sg:city":"Pitkin",
    "sg:classifiers":[
        {
            "category":"Real Estate",
            "subcategory":"Developer",
            "type":"Services"
        }
    ],
    "sg:phone":"+1 970 641 3475",
    "sg:postcode":"81241",
    "sg:province":"CO",
    "wof:name":"Lull Development Co",
    "wof:placetype":"venue"
},
  "geometry": {"coordinates":[-106.515913,38.610262],"type":"Point"}
}