{
  "type": "Feature",
  "properties": {
    "addr:full":"327 S McKinley Ct Louisville CO 80027",
    "addr:housenumber":"327",
    "addr:postcode":"80027",
    "addr:street":"S Mckinley Ct",
    "iso:country":"US",
    "sg:address":"327 S McKinley Ct",
    "sg:city":"Louisville",
    "sg:classifiers":[
        {
            "category":"Building & Trades",
            "subcategory":"Construction",
            "type":"Services"
        }
    ],
    "sg:phone":"+1 303 661 9935",
    "sg:postcode":"80027",
    "sg:province":"CO",
    "sg:tags":[
        "nonresidential"
    ],
    "wof:name":"Pflugcon Inc",
    "wof:placetype":"venue"
},
  "geometry": {"coordinates":[-105.139398,39.966613],"type":"Point"}
}