{
  "type": "Feature",
  "properties": {
    "iso:country":"US",
    "sg:address":"84 Spruce St Unit 101",
    "sg:city":"Denver",
    "sg:classifiers":[
        {
            "category":"Professional",
            "subcategory":"Employment Agencies",
            "type":"Services"
        }
    ],
    "sg:phone":"+1 720 278 2100",
    "sg:postcode":"80230",
    "sg:province":"CO",
    "wof:name":"Organic People Inc",
    "wof:placetype":"venue"
},
  "geometry": {"coordinates":[-104.894442,39.721895],"type":"Point"}
}