{
  "type": "Feature",
  "properties": {
    "addr:full":"101 Main St Windsor CO 80550",
    "addr:housenumber":"101",
    "addr:postcode":"80550",
    "addr:street":"Main St",
    "iso:country":"US",
    "sg:address":"101 Main St",
    "sg:city":"Windsor",
    "sg:classifiers":[
        {
            "category":"Building & Trades",
            "subcategory":"Construction",
            "type":"Services"
        }
    ],
    "sg:phone":"+1 970 686 5660",
    "sg:postcode":"80550",
    "sg:province":"CO",
    "sg:tags":[
        "plastering",
        "contractor"
    ],
    "wof:name":"A Custom Hand Plaster Inc",
    "wof:placetype":"venue"
},
  "geometry": {"coordinates":[-104.896897,40.479761],"type":"Point"}
}