{
  "type": "Feature",
  "properties": {
    "addr:full":"2755 W Alameda Ave Denver CO 80219",
    "addr:housenumber":"2755",
    "addr:postcode":"80219",
    "addr:street":"W Alameda Ave",
    "iso:country":"US",
    "sg:address":"2755 W Alameda Ave",
    "sg:city":"Denver",
    "sg:classifiers":[
        {
            "category":"Autos & Motor Vehicles",
            "subcategory":"Automobile Sales",
            "type":"Retail Goods"
        }
    ],
    "sg:phone":"+1 303 936 9905",
    "sg:postcode":"80219",
    "sg:province":"CO",
    "sg:tags":[
        "car",
        "dealer"
    ],
    "wof:name":"Kar Kompany",
    "wof:placetype":"venue"
},
  "geometry": {"coordinates":[-105.022565,39.711232],"type":"Point"}
}