{
  "type": "Feature",
  "properties": {
    "addr:full":"11550 Washington St Northglenn CO 80233",
    "addr:housenumber":"11550",
    "addr:postcode":"80233",
    "addr:street":"Washington St",
    "iso:country":"US",
    "sg:address":"11550 Washington St",
    "sg:city":"Northglenn",
    "sg:classifiers":[
        {
            "category":"Organizations",
            "subcategory":"Religious Organization",
            "type":"Services"
        }
    ],
    "sg:phone":"+1 303 452 6721",
    "sg:postcode":"80233",
    "sg:province":"CO",
    "sg:tags":[
        "church"
    ],
    "wof:name":"Northside Baptist Church",
    "wof:placetype":"venue"
},
  "geometry": {"coordinates":[-104.977597,39.905676],"type":"Point"}
}