{
  "type": "Feature",
  "properties": {
    "iso:country":"US",
    "sg:address":"2950 Professional Pl",
    "sg:city":"Colorado Springs",
    "sg:classifiers":[
        {
            "category":"Real Estate",
            "subcategory":"Real Estate Agent",
            "type":"Services"
        }
    ],
    "sg:phone":"+1 719 442 2000",
    "sg:postcode":"80904",
    "sg:province":"CO",
    "wof:name":"Bach Commercial Brokerage Co",
    "wof:placetype":"venue"
},
  "geometry": {"coordinates":[-104.854894,38.873795],"type":"Point"}
}