{
  "type": "Feature",
  "properties": {
    "addr:full":"4857 Raleigh St Denver CO 80212",
    "addr:housenumber":"4857",
    "addr:postcode":"80212",
    "addr:street":"Raleigh St",
    "iso:country":"US",
    "sg:address":"4857 Raleigh St",
    "sg:city":"Denver",
    "sg:classifiers":[
        {
            "category":"Building & Trades",
            "subcategory":"Landscaping Services",
            "type":"Services"
        }
    ],
    "sg:phone":"+1 303 455 9556",
    "sg:postcode":"80212",
    "sg:province":"CO",
    "wof:name":"Livingston Landscape & Design",
    "wof:placetype":"venue"
},
  "geometry": {"coordinates":[-105.04165500000001,39.784629],"type":"Point"}
}