{
  "type": "Feature",
  "properties": {
    "iso:country":"US",
    "sg:address":"5801 Piedmont Dr",
    "sg:city":"Englewood",
    "sg:classifiers":[
        {
            "category":"Wholesale",
            "subcategory":"Machinery & Supplies",
            "type":"Manufacturing & Wholesale Goods"
        }
    ],
    "sg:phone":"+1 303 770 2592",
    "sg:postcode":"80111",
    "sg:province":"CO",
    "sg:tags":[
        "equipment",
        "industrial"
    ],
    "wof:name":"Impex International Company",
    "wof:placetype":"venue"
},
  "geometry": {"coordinates":[-104.920447,39.62638],"type":"Point"}
}