{
  "type": "Feature",
  "properties": {
    "addr:full":"6140 E 49th Ave Commerce City CO 80022",
    "addr:housenumber":"6140",
    "addr:postcode":"80022",
    "addr:street":"E 49Th Ave",
    "iso:country":"US",
    "sg:address":"6140 E 49th Ave",
    "sg:city":"Commerce City",
    "sg:classifiers":[
        {
            "category":"Shopping",
            "subcategory":"Discount & Variety Stores",
            "type":"Retail Goods"
        }
    ],
    "sg:phone":"+1 303 227 1774",
    "sg:postcode":"80022",
    "sg:province":"CO",
    "sg:tags":[
        "miscellaneous",
        "merchandise",
        "general"
    ],
    "wof:name":"Mexican Grocery Supply I",
    "wof:placetype":"venue"
},
  "geometry": {"coordinates":[-104.91840999999999,39.786695],"type":"Point"}
}