{
  "type": "Feature",
  "properties": {
    "addr:full":"2510 Oak Hills Dr Colorado Springs CO 80919",
    "addr:housenumber":"2510",
    "addr:postcode":"80919",
    "addr:street":"Oak Hills Dr",
    "iso:country":"US",
    "sg:address":"2510 Oak Hills Dr",
    "sg:city":"Colorado Springs",
    "sg:classifiers":[
        {
            "category":"Real Estate",
            "subcategory":"Real Estate Agent",
            "type":"Services"
        }
    ],
    "sg:phone":"+1 719 594 6684",
    "sg:postcode":"80919",
    "sg:province":"CO",
    "wof:name":"Asmantop LLC",
    "wof:placetype":"venue"
},
  "geometry": {"coordinates":[-104.864346,38.935149],"type":"Point"}
}