{
  "type": "Feature",
  "properties": {
    "addr:full":"1840 N 12th St Grand Junction CO 81501",
    "addr:housenumber":"1840",
    "addr:postcode":"81501",
    "addr:street":"N 12Th St",
    "iso:country":"US",
    "sg:address":"1840 N 12th St",
    "sg:city":"Grand Junction",
    "sg:classifiers":[
        {
            "category":"Restaurant",
            "type":"Food & Drink"
        }
    ],
    "sg:menulink":"http://www.allmenus.com/co/grand-junction/128568-subway/menu/",
    "sg:phone":"+1 970 241 2442",
    "sg:postcode":"81501",
    "sg:province":"CO",
    "sg:tags":[
        "american",
        "sandwich"
    ],
    "wof:name":"Subway",
    "wof:placetype":"venue"
},
  "geometry": {"coordinates":[-108.552347,39.084085],"type":"Point"}
}