{
  "type": "Feature",
  "properties": {
    "iso:country":"US",
    "sg:address":"7320 Canosa Ct",
    "sg:city":"Westminster",
    "sg:classifiers":[
        {
            "category":"Retail",
            "subcategory":"Repair Shop",
            "type":"Services"
        }
    ],
    "sg:phone":"+1 303 429 9510",
    "sg:postcode":"80030",
    "sg:province":"CO",
    "sg:tags":[
        "appliance"
    ],
    "wof:name":"Automatic Appliance Svc",
    "wof:placetype":"venue"
},
  "geometry": {"coordinates":[-105.019572,39.830444],"type":"Point"}
}