{
  "type": "Feature",
  "properties": {
    "iso:country":"US",
    "sg:address":"785 Russell St",
    "sg:city":"Craig",
    "sg:classifiers":[
        {
            "category":"Health Services",
            "subcategory":"Health Practitioner",
            "type":"Services"
        }
    ],
    "sg:phone":"+1 970 824 7286",
    "sg:postcode":"81625",
    "sg:province":"CO",
    "sg:tags":[
        "audiologists"
    ],
    "wof:name":"Northwest Speech & Hearing Svc",
    "wof:placetype":"venue"
},
  "geometry": {"coordinates":[-107.546028,40.519098],"type":"Point"}
}