{
  "type": "Feature",
  "properties": {
    "addr:full":"601 Center Ave Grand Junction CO 81501",
    "addr:housenumber":"601",
    "addr:postcode":"81501",
    "addr:street":"Center Ave",
    "iso:country":"US",
    "sg:address":"601 Center Ave",
    "sg:city":"Grand Junction",
    "sg:classifiers":[
        {
            "category":"Health Services",
            "subcategory":"Doctor",
            "type":"Services"
        }
    ],
    "sg:phone":"+1 970 242 1566",
    "sg:postcode":"81501",
    "sg:province":"CO",
    "sg:tags":[
        "physician",
        "surgeon"
    ],
    "wof:name":"Craig Gustafson MD",
    "wof:placetype":"venue"
},
  "geometry": {"coordinates":[-108.561019,39.089247],"type":"Point"}
}