{
  "type": "Feature",
  "properties": {
    "iso:country":"US",
    "sg:address":"712 E Godding Ave",
    "sg:city":"Trinidad",
    "sg:classifiers":[
        {
            "category":"Real Estate",
            "subcategory":"Real Estate Operator",
            "type":"Services"
        }
    ],
    "sg:phone":"+1 719 846 4816",
    "sg:postcode":"81082",
    "sg:province":"CO",
    "sg:tags":[
        "building",
        "apartment"
    ],
    "wof:name":"Casa Village Apartments",
    "wof:placetype":"venue"
},
  "geometry": {"coordinates":[-104.500523,37.182097],"type":"Point"}
}