{
  "type": "Feature",
  "properties": {
    "iso:country":"US",
    "sg:address":"19216 E Clear Creek Pl",
    "sg:city":"Parker",
    "sg:classifiers":[
        {
            "category":"Insurance",
            "subcategory":"Insurance Agent",
            "type":"Services"
        }
    ],
    "sg:phone":"+1 303 840 1244",
    "sg:postcode":"80134",
    "sg:province":"CO",
    "wof:name":"Nelson Jervonda",
    "wof:placetype":"venue"
},
  "geometry": {"coordinates":[-104.76470500000001,39.488391],"type":"Point"}
}