{
  "type": "Feature",
  "properties": {
    "iso:country":"US",
    "sg:address":"1675 Broadway",
    "sg:city":"Denver",
    "sg:classifiers":[
        {
            "category":"Wholesale",
            "subcategory":"Medical Equipment & Supplies",
            "type":"Manufacturing & Wholesale Goods"
        }
    ],
    "sg:phone":"+1 303 366 6800",
    "sg:postcode":"80203",
    "sg:province":"CO",
    "sg:tags":[
        "x"
    ],
    "wof:name":"Picker Medical Products",
    "wof:placetype":"venue"
},
  "geometry": {"coordinates":[-104.987488,39.742237],"type":"Point"}
}