{
  "type": "Feature",
  "properties": {
    "addr:full":"214 E Park Ave Fowler CO 81039",
    "addr:housenumber":"214",
    "addr:postcode":"81039",
    "addr:street":"E Park Ave",
    "iso:country":"US",
    "sg:address":"214 E Park Ave",
    "sg:city":"Fowler",
    "sg:classifiers":[
        {
            "category":"Building & Trades",
            "subcategory":"Cleaning & Sanitation",
            "type":"Services"
        }
    ],
    "sg:phone":"+1 970 724 9699",
    "sg:postcode":"81039",
    "sg:province":"CO",
    "sg:tags":[
        "janitor"
    ],
    "wof:name":"Grand County Catastrope Clean",
    "wof:placetype":"venue"
},
  "geometry": {"coordinates":[-104.022571,38.1262],"type":"Point"}
}