{
  "type": "Feature",
  "properties": {
    "iso:country":"US",
    "sg:address":"633 Buss Ave",
    "sg:city":"Greeley",
    "sg:classifiers":[
        {
            "category":"Building & Trades",
            "subcategory":"Equipment Rental",
            "type":"Services"
        }
    ],
    "sg:phone":"+1 970 351 7736",
    "sg:postcode":"80631",
    "sg:province":"CO",
    "sg:tags":[
        "aircraft",
        "leasing",
        "charter"
    ],
    "wof:name":"Platte Valley Flight Ctr LLC",
    "wof:placetype":"venue"
},
  "geometry": {"coordinates":[-104.638785,40.42565],"type":"Point"}
}