{
  "type": "Feature",
  "properties": {
    "iso:country":"US",
    "sg:address":"12365 Huron St Ste 800",
    "sg:city":"Denver",
    "sg:classifiers":[
        {
            "category":"Home & Garden",
            "subcategory":"Carpets & Floor Coverings",
            "type":"Retail Goods"
        }
    ],
    "sg:phone":"+1 303 451 1701",
    "sg:postcode":"80234",
    "sg:province":"CO",
    "sg:tags":[
        "flooring"
    ],
    "sg:website":"www.benjaminmoore.com",
    "wof:name":"Northside Paint & Decorating Inc",
    "wof:placetype":"venue"
},
  "geometry": {"coordinates":[-104.997101,39.703892],"type":"Point"}
}