{
  "type": "Feature",
  "properties": {
    "iso:country":"US",
    "sg:address":"1101 Clark St",
    "sg:city":"Fort Collins",
    "sg:phone":"+1 970 482 6596",
    "sg:postcode":"80524",
    "sg:province":"CO",
    "sg:tags":[
        "farm",
        "field",
        "crop"
    ],
    "wof:name":"Loren Maxey",
    "wof:placetype":"venue"
},
  "geometry": {"coordinates":[-105.05671599999999,40.605413],"type":"Point"}
}