{
  "type": "Feature",
  "properties": {
    "iso:country":"US",
    "sg:address":"2880 Osceola St",
    "sg:city":"Denver",
    "sg:classifiers":[
        {
            "category":"Social Services",
            "type":"Services"
        }
    ],
    "sg:phone":"+1 303 458 4868",
    "sg:postcode":"80212",
    "sg:province":"CO",
    "sg:tags":[
        "counseling",
        "senior",
        "citizen"
    ],
    "sg:website":"http://denvergov.org/",
    "wof:name":"Highland Senior Citizens Ctr",
    "wof:placetype":"venue"
},
  "geometry": {"coordinates":[-105.03814800000001,39.758271],"type":"Point"}
}