{
  "type": "Feature",
  "properties": {
    "iso:country":"US",
    "sg:address":"730 S Cam del Rio",
    "sg:city":"Durango",
    "sg:classifiers":[
        {
            "category":"Real Estate",
            "subcategory":"Real Estate Agent",
            "type":"Services"
        }
    ],
    "sg:phone":"+1 970 247 4266",
    "sg:postcode":"81301",
    "sg:province":"CO",
    "sg:tags":[
        "consulting",
        "management"
    ],
    "wof:name":"Campbell Realty Inc",
    "wof:placetype":"venue"
},
  "geometry": {"coordinates":[-107.870772,37.23862],"type":"Point"}
}