{
  "type": "Feature",
  "properties": {
    "addr:full":"16431 E Colfax Ave Aurora CO 80011",
    "addr:housenumber":"16431",
    "addr:postcode":"80011",
    "addr:street":"E Colfax Ave",
    "iso:country":"US",
    "sg:address":"16431 E Colfax Ave",
    "sg:city":"Aurora",
    "sg:classifiers":[
        {
            "category":"Real Estate",
            "subcategory":"Developer",
            "type":"Services"
        },
        {
            "category":"Real Estate",
            "subcategory":"Real Estate Operator",
            "type":"Services"
        }
    ],
    "sg:phone":"+1 303 367 4050",
    "sg:postcode":"80011",
    "sg:province":"CO",
    "sg:tags":[
        "mobile",
        "home",
        "site"
    ],
    "wof:name":"Aurora Mobile Home Park",
    "wof:placetype":"venue"
},
  "geometry": {"coordinates":[-104.796566,39.7402],"type":"Point"}
}