{
  "type": "Feature",
  "properties": {
    "iso:country":"US",
    "sg:address":"326 Hwy 133",
    "sg:city":"Carbondale",
    "sg:classifiers":[
        {
            "category":"Banks & Credit Unions",
            "subcategory":"Bank",
            "type":"Services"
        }
    ],
    "sg:phone":"+1 970 963 5563",
    "sg:postcode":"81623",
    "sg:province":"CO",
    "sg:tags":[
        "broker",
        "mortgage"
    ],
    "wof:name":"Homebuyers Mortgage Western Co",
    "wof:placetype":"venue"
},
  "geometry": {"coordinates":[-107.221408,39.410094],"type":"Point"}
}