{
  "type": "Feature",
  "properties": {
    "iso:country":"US",
    "sg:address":"60 Debra Ann Rd",
    "sg:city":"Golden",
    "sg:classifiers":[
        {
            "category":"Professional",
            "type":"Services"
        }
    ],
    "sg:phone":"+1 303 642 7548",
    "sg:postcode":"80403",
    "sg:province":"CO",
    "wof:name":"Windom Systems Inc",
    "wof:placetype":"venue"
},
  "geometry": {"coordinates":[-105.397719,39.916612],"type":"Point"}
}