{
  "type": "Feature",
  "properties": {
    "addr:full":"415 W Pikes Peak Ave Colorado Springs CO 80905",
    "addr:housenumber":"415",
    "addr:postcode":"80905",
    "addr:street":"W Pikes Peak Ave",
    "iso:country":"US",
    "sg:address":"415 W Pikes Peak Ave",
    "sg:city":"Colorado Springs",
    "sg:classifiers":[
        {
            "category":"Manufacturing",
            "subcategory":"Food",
            "type":"Manufacturing & Wholesale Goods"
        }
    ],
    "sg:phone":"+1 719 633 2653",
    "sg:postcode":"80905",
    "sg:province":"CO",
    "sg:tags":[
        "bottler"
    ],
    "sg:website":"www.cokecce.com",
    "wof:name":"Coca-Cola Bottling Co",
    "wof:placetype":"venue"
},
  "geometry": {"coordinates":[-104.834115,38.834102],"type":"Point"}
}