{
  "type": "Feature",
  "properties": {
    "iso:country":"US",
    "sg:address":"14304 E Kentucky Pl",
    "sg:city":"Aurora",
    "sg:classifiers":[
        {
            "category":"Professional",
            "type":"Services"
        }
    ],
    "sg:phone":"+1 303 504 9203",
    "sg:postcode":"80012",
    "sg:province":"CO",
    "wof:name":"Cajun King",
    "wof:placetype":"venue"
},
  "geometry": {"coordinates":[-104.822412,39.701605],"type":"Point"}
}