{
  "type": "Feature",
  "properties": {
    "addr:full":"269 Ross Rd Telluride CO 81435",
    "addr:housenumber":"269",
    "addr:postcode":"81435",
    "addr:street":"Ross Rd",
    "iso:country":"US",
    "sg:address":"269 Ross Rd",
    "sg:city":"Telluride",
    "sg:classifiers":[
        {
            "category":"Building & Trades",
            "subcategory":"Construction",
            "type":"Services"
        }
    ],
    "sg:phone":"+1 970 728 0512",
    "sg:postcode":"81435",
    "sg:province":"CO",
    "sg:tags":[
        "house"
    ],
    "wof:name":"Db Home Repair",
    "wof:placetype":"venue"
},
  "geometry": {"coordinates":[-108.01898799999999,37.937032],"type":"Point"}
}