{
  "type": "Feature",
  "properties": {
    "addr:full":"6923 Granite Crag Cir Evergreen CO 80439",
    "addr:housenumber":"6923",
    "addr:postcode":"80439",
    "addr:street":"Granite Crag Cir",
    "iso:country":"US",
    "sg:address":"6923 Granite Crag Cir",
    "sg:city":"Evergreen",
    "sg:classifiers":[
        {
            "category":"Building & Trades",
            "subcategory":"Construction",
            "type":"Services"
        }
    ],
    "sg:phone":"+1 303 588 2617",
    "sg:postcode":"80439",
    "sg:province":"CO",
    "sg:tags":[
        "general",
        "contractor"
    ],
    "sg:website":"www.homesofdesign.com",
    "wof:name":"Homes Of Design Inc",
    "wof:placetype":"venue"
},
  "geometry": {"coordinates":[-105.339145,39.589615],"type":"Point"}
}