{
  "type": "Feature",
  "properties": {
    "iso:country":"US",
    "sg:address":"2600 Leyden St",
    "sg:city":"Denver",
    "sg:classifiers":[
        {
            "category":"Organizations",
            "subcategory":"Religious Organization",
            "type":"Services"
        }
    ],
    "sg:phone":"+1 303 322 9122",
    "sg:postcode":"80207",
    "sg:province":"CO",
    "sg:tags":[
        "church"
    ],
    "sg:website":"www.phccucc.org",
    "wof:name":"Park Hill Congregational Chr",
    "wof:placetype":"venue"
},
  "geometry": {"coordinates":[-104.915189,39.756577],"type":"Point"}
}