{
  "type": "Feature",
  "properties": {
    "addr:full":"3455 Salida St Aurora CO 80011",
    "addr:housenumber":"3455",
    "addr:postcode":"80011",
    "addr:street":"Salida St",
    "iso:country":"US",
    "sg:address":"3455 Salida St",
    "sg:city":"Aurora",
    "sg:classifiers":[
        {
            "category":"Utilities",
            "subcategory":"Mobile Phone",
            "type":"Services"
        },
        {
            "category":"Coffee & Tea",
            "type":"Food & Drink"
        }
    ],
    "sg:phone":"+1 303 371 3594",
    "sg:postcode":"80011",
    "sg:province":"CO",
    "sg:tags":[
        "shop",
        "wi-fi",
        "espresso",
        "hotspot",
        "restaurant"
    ],
    "sg:website":"http://www.starbuckscoffee.com",
    "wof:name":"Starbucks Coffee",
    "wof:placetype":"venue"
},
  "geometry": {"coordinates":[-104.77430699999999,39.7645],"type":"Point"}
}