{
  "type": "Feature",
  "properties": {
    "addr:full":"7336 S Alton Way Centennial CO 80112",
    "addr:housenumber":"7336",
    "addr:postcode":"80112",
    "addr:street":"S Alton Way",
    "iso:country":"US",
    "sg:address":"7336 S Alton Way",
    "sg:city":"Centennial",
    "sg:classifiers":[
        {
            "category":"Manufacturing",
            "subcategory":"Printing",
            "type":"Manufacturing & Wholesale Goods"
        }
    ],
    "sg:phone":"+1 720 529 1400",
    "sg:postcode":"80112",
    "sg:province":"CO",
    "sg:tags":[
        "printer"
    ],
    "sg:website":"www.nextprint.net",
    "wof:name":"Next Print LLC",
    "wof:placetype":"venue"
},
  "geometry": {"coordinates":[-104.883965,39.582413],"type":"Point"}
}