{
  "type": "Feature",
  "properties": {
    "addr:full":"7035 Newland St Arvada CO 80003",
    "addr:housenumber":"7035",
    "addr:postcode":"80003",
    "addr:street":"Newland St",
    "iso:country":"US",
    "sg:address":"7035 Newland St",
    "sg:city":"Arvada",
    "sg:classifiers":[
        {
            "category":"Building & Trades",
            "subcategory":"Plumbing",
            "type":"Services"
        }
    ],
    "sg:phone":"+1 303 432 9531",
    "sg:postcode":"80003",
    "sg:province":"CO",
    "sg:tags":[
        "contractor"
    ],
    "wof:name":"A OK Heating Air Conditioning",
    "wof:placetype":"venue"
},
  "geometry": {"coordinates":[-105.06930199999999,39.82689],"type":"Point"}
}