{
  "type": "Feature",
  "properties": {
    "iso:country":"US",
    "sg:address":"1525 43rd Ave",
    "sg:city":"Greeley",
    "sg:classifiers":[
        {
            "category":"Organizations",
            "subcategory":"Religious Organization",
            "type":"Services"
        }
    ],
    "sg:phone":"+1 970 353 5500",
    "sg:postcode":"80634",
    "sg:province":"CO",
    "sg:tags":[
        "church"
    ],
    "sg:website":"www.stpaulsgreeley.org",
    "wof:name":"St Pauls Congregational Church",
    "wof:placetype":"venue"
},
  "geometry": {"coordinates":[-104.74879300000001,40.41276],"type":"Point"}
}