{
  "type": "Feature",
  "properties": {
    "addr:full":"9025 Co Rd 11 Longmont CO 80504",
    "addr:housenumber":"9025;11",
    "addr:postcode":"80504",
    "addr:street":"Co Rd",
    "iso:country":"US",
    "sg:address":"9025 Co Rd 11",
    "sg:city":"Longmont",
    "sg:classifiers":[
        {
            "category":"Farming",
            "subcategory":"Farm",
            "type":"Manufacturing & Wholesale Goods"
        }
    ],
    "sg:phone":"+1 303 678 0210",
    "sg:postcode":"80504",
    "sg:province":"CO",
    "sg:tags":[
        "crop",
        "general"
    ],
    "wof:name":"Jj Properties",
    "wof:placetype":"venue"
},
  "geometry": {"coordinates":[-104.96107000000001,40.13284],"type":"Point"}
}