{
  "type": "Feature",
  "properties": {
    "iso:country":"US",
    "sg:address":"1109 Aruba Dr",
    "sg:city":"Fort Collins",
    "sg:classifiers":[
        {
            "category":"Restaurant",
            "type":"Food & Drink"
        }
    ],
    "sg:phone":"+1 970 223 6555",
    "sg:postcode":"80525",
    "sg:province":"CO",
    "sg:tags":[
        "eating"
    ],
    "wof:name":"Wok & Roll Teriyaki",
    "wof:placetype":"venue"
},
  "geometry": {"coordinates":[-105.057118,40.489399],"type":"Point"}
}