{
  "type": "Feature",
  "properties": {
    "iso:country":"US",
    "sg:address":"1193 Cooley Mesa Rd",
    "sg:city":"Gypsum",
    "sg:classifiers":[
        {
            "category":"Airport",
            "type":"Transportation"
        }
    ],
    "sg:phone":"+1 970 524 9490",
    "sg:postcode":"81637",
    "sg:province":"CO",
    "wof:name":"Eagle County Regional Airport",
    "wof:placetype":"venue"
},
  "geometry": {"coordinates":[-106.925567,39.639127],"type":"Point"}
}