{
  "type": "Feature",
  "properties": {
    "iso:country":"US",
    "sg:address":"2726 Jon St",
    "sg:city":"Colorado Springs",
    "sg:classifiers":[
        {
            "category":"Food & Beverages",
            "subcategory":"Specialty",
            "type":"Retail Goods"
        },
        {
            "category":"Professional",
            "type":"Services"
        }
    ],
    "sg:phone":"+1 719 471 0060",
    "sg:postcode":"80907",
    "sg:province":"CO",
    "sg:tags":[
        "establishment"
    ],
    "wof:name":"Changes International Ind Dist",
    "wof:placetype":"venue"
},
  "geometry": {"coordinates":[-104.80604099999999,38.869382],"type":"Point"}
}