{
  "type": "Feature",
  "properties": {
    "addr:full":"9658 S Timber Hawk Cir Littleton CO 80126",
    "addr:housenumber":"9658",
    "addr:postcode":"80126",
    "addr:street":"S Timber Hawk Cir",
    "iso:country":"US",
    "sg:address":"9658 S Timber Hawk Cir",
    "sg:city":"Littleton",
    "sg:classifiers":[
        {
            "category":"Professional",
            "type":"Services"
        }
    ],
    "sg:phone":"+1 303 470 0509",
    "sg:postcode":"80126",
    "sg:province":"CO",
    "wof:name":"Btc Inc",
    "wof:placetype":"venue"
},
  "geometry": {"coordinates":[-104.937214,39.538617],"type":"Point"}
}