{
  "type": "Feature",
  "properties": {
    "iso:country":"US",
    "sg:address":"1033 Kalmia Ave",
    "sg:city":"Boulder",
    "sg:classifiers":[
        {
            "category":"Health Services",
            "subcategory":"Health Practitioner",
            "type":"Services"
        }
    ],
    "sg:phone":"+1 303 440 4762",
    "sg:postcode":"80304",
    "sg:province":"CO",
    "sg:tags":[
        "psychotherapist"
    ],
    "wof:name":"Paulette K Feuer Phd",
    "wof:placetype":"venue"
},
  "geometry": {"coordinates":[-105.28354,40.039148],"type":"Point"}
}