{
  "type": "Feature",
  "properties": {
    "addr:full":"4700 E Colfax Ave Denver CO 80220",
    "addr:housenumber":"4700",
    "addr:postcode":"80220",
    "addr:street":"E Colfax Ave",
    "iso:country":"US",
    "sg:address":"4700 E Colfax Ave",
    "sg:city":"Denver",
    "sg:classifiers":[
        {
            "category":"Retail",
            "subcategory":"Car Wash",
            "type":"Services"
        },
        {
            "category":"Retail",
            "subcategory":"Auto Repair",
            "type":"Services"
        }
    ],
    "sg:postcode":"80220",
    "sg:province":"CO",
    "sg:tags":[
        "detailing"
    ],
    "sg:website":"www.theglasshousecarwash.com",
    "wof:name":"Glass House Car Wash",
    "wof:placetype":"venue"
},
  "geometry": {"coordinates":[-104.932377,39.739795],"type":"Point"}
}