{
  "type": "Feature",
  "properties": {
    "addr:full":"1512 Larimer St Denver CO 80202",
    "addr:housenumber":"1512",
    "addr:postcode":"80202",
    "addr:street":"Larimer St",
    "iso:country":"US",
    "sg:address":"1512 Larimer St",
    "sg:city":"Denver",
    "sg:classifiers":[
        {
            "category":"Food & Beverages",
            "subcategory":"Bakery",
            "type":"Retail Goods"
        }
    ],
    "sg:phone":"+1 303 436 0486",
    "sg:postcode":"80202",
    "sg:province":"CO",
    "sg:tags":[
        "sandwich"
    ],
    "sg:website":"www.subway.com",
    "wof:name":"Subway",
    "wof:placetype":"venue"
},
  "geometry": {"coordinates":[-104.9982,39.748469],"type":"Point"}
}