{
  "type": "Feature",
  "properties": {
    "addr:full":"56 S Hwy 105 Palmer Lake CO 80133",
    "addr:housenumber":"56",
    "addr:postcode":"80133",
    "addr:street":"S Hwy 105",
    "iso:country":"US",
    "sg:address":"56 S Hwy 105",
    "sg:city":"Palmer Lake",
    "sg:classifiers":[
        {
            "category":"Food & Beverages",
            "subcategory":"Groceries & Convenience Stores",
            "type":"Retail Goods"
        }
    ],
    "sg:phone":"+1 719 481 8859",
    "sg:postcode":"80133",
    "sg:province":"CO",
    "wof:name":"Palmer Lake Country Store",
    "wof:placetype":"venue"
},
  "geometry": {"coordinates":[-104.91425599999999,39.120049],"type":"Point"}
}