{
  "type": "Feature",
  "properties": {
    "addr:full":"245 Bannock St Denver CO 80223",
    "addr:housenumber":"245",
    "addr:postcode":"80223",
    "addr:street":"Bannock St",
    "iso:country":"US",
    "sg:address":"245 Bannock St",
    "sg:city":"Denver",
    "sg:classifiers":[
        {
            "category":"Freight",
            "type":"Transportation"
        }
    ],
    "sg:phone":"+1 303 722 2324",
    "sg:postcode":"80223",
    "sg:province":"CO",
    "sg:tags":[
        "operator",
        "local",
        "trucking"
    ],
    "wof:name":"Chavez Delivery",
    "wof:placetype":"venue"
},
  "geometry": {"coordinates":[-104.99091,39.72023],"type":"Point"}
}