{
  "type": "Feature",
  "properties": {
    "iso:country":"US",
    "sg:address":"2500 E 6th Avenue",
    "sg:city":"Denver",
    "sg:classifiers":[
        {
            "category":"Shopping",
            "subcategory":"Bicycles & Sporting Goods",
            "type":"Retail Goods"
        }
    ],
    "sg:phone":"+1 303 320 9499",
    "sg:postcode":"80206",
    "sg:province":"CO",
    "wof:name":"Breakaway Sports Superstore",
    "wof:placetype":"venue"
},
  "geometry": {"coordinates":[-104.95784399999999,39.725592],"type":"Point"}
}