{
  "type": "Feature",
  "properties": {
    "iso:country":"US",
    "sg:address":"8400 E Prentice Ave",
    "sg:city":"Englewood",
    "sg:classifiers":[
        {
            "category":"Professional",
            "subcategory":"Advertising",
            "type":"Services"
        }
    ],
    "sg:phone":"+1 303 220 5562",
    "sg:postcode":"80111",
    "sg:province":"CO",
    "sg:tags":[
        "agency"
    ],
    "wof:name":"Saatchi & Saatchi North Amer",
    "wof:placetype":"venue"
},
  "geometry": {"coordinates":[-104.88999800000001,39.619804],"type":"Point"}
}