{
  "type": "Feature",
  "properties": {
    "iso:country":"US",
    "sg:address":"600 S Dayton St",
    "sg:city":"Denver",
    "sg:classifiers":[
        {
            "category":"Building & Trades",
            "subcategory":"Construction",
            "type":"Services"
        }
    ],
    "sg:phone":"+1 303 365 0328",
    "sg:postcode":"80247",
    "sg:province":"CO",
    "sg:tags":[
        "house"
    ],
    "wof:name":"Nissis Construction",
    "wof:placetype":"venue"
},
  "geometry": {"coordinates":[-104.875338,39.703862],"type":"Point"}
}