{
  "type": "Feature",
  "properties": {
    "addr:full":"1776 E Tufts Ave Englewood CO 80113",
    "addr:housenumber":"1776",
    "addr:postcode":"80113",
    "addr:street":"E Tufts Ave",
    "iso:country":"US",
    "sg:address":"1776 E Tufts Ave",
    "sg:city":"Englewood",
    "sg:classifiers":[
        {
            "category":"Communications",
            "subcategory":"Radio Station",
            "type":"Services"
        }
    ],
    "sg:phone":"+1 303 789 1118",
    "sg:postcode":"80113",
    "sg:province":"CO",
    "sg:tags":[
        "owner"
    ],
    "wof:name":"On-Air Family LLC",
    "wof:placetype":"venue"
},
  "geometry": {"coordinates":[-104.969053,39.633241],"type":"Point"}
}