{
  "type": "Feature",
  "properties": {
    "addr:full":"3600 Christy Ridge Rd Sedalia CO 80135",
    "addr:housenumber":"3600",
    "addr:postcode":"80135",
    "addr:street":"Christy Ridge Rd",
    "iso:country":"US",
    "sg:address":"3600 Christy Ridge Rd",
    "sg:city":"Sedalia",
    "sg:classifiers":[
        {
            "category":"Banks & Credit Unions",
            "subcategory":"Investment Brokerage",
            "type":"Services"
        }
    ],
    "sg:phone":"+1 303 688 8275",
    "sg:postcode":"80135",
    "sg:province":"CO",
    "sg:tags":[
        "security"
    ],
    "wof:name":"Bloomquist Retirement LLC",
    "wof:placetype":"venue"
},
  "geometry": {"coordinates":[-104.94508399999999,39.342929],"type":"Point"}
}