{
  "type": "Feature",
  "properties": {
    "addr:full":"2955 Village Dr Steamboat Spgs CO 80487",
    "addr:housenumber":"2955",
    "addr:postcode":"80487",
    "addr:street":"Village Dr;Spgs",
    "iso:country":"US",
    "sg:address":"2955 Village Dr",
    "sg:city":"Steamboat Spgs",
    "sg:classifiers":[
        {
            "category":"Real Estate",
            "subcategory":"Real Estate Agent",
            "type":"Services"
        }
    ],
    "sg:phone":"+1 970 879 4771",
    "sg:postcode":"80487",
    "sg:province":"CO",
    "wof:name":"Core Real Estate LTD",
    "wof:placetype":"venue"
},
  "geometry": {"coordinates":[-106.805526,40.451134],"type":"Point"}
}