{
  "type": "Feature",
  "properties": {
    "addr:full":"1010 Yosemite Street Denver CO 80230",
    "addr:housenumber":"1010",
    "addr:postcode":"80230",
    "addr:street":"Yosemite Street",
    "iso:country":"US",
    "sg:address":"1010 Yosemite Street",
    "sg:city":"Denver",
    "sg:classifiers":[
        {
            "category":"Health Services",
            "subcategory":"Hospital",
            "type":"Services"
        }
    ],
    "sg:phone":"+1 303 436 4545",
    "sg:postcode":"80230",
    "sg:province":"CO",
    "wof:name":"Denver Health",
    "wof:placetype":"venue"
},
  "geometry": {"coordinates":[-104.885032,39.730424],"type":"Point"}
}