{
  "type": "Feature",
  "properties": {
    "addr:full":"3230 E Colfax Avenue Denver CO 80206",
    "addr:housenumber":"3230",
    "addr:postcode":"80206",
    "addr:street":"E Colfax Avenue",
    "iso:country":"US",
    "sg:address":"3230 E Colfax Avenue",
    "sg:city":"Denver",
    "sg:classifiers":[
        {
            "category":"Restaurant",
            "type":"Food & Drink"
        }
    ],
    "sg:phone":"+1 303 322 5219",
    "sg:postcode":"80206",
    "sg:province":"CO",
    "sg:website":"www.mezcal-restaurant.com",
    "wof:name":"Mezcall",
    "wof:placetype":"venue"
},
  "geometry": {"coordinates":[-104.949062,39.740062],"type":"Point"}
}