{
  "type": "Feature",
  "properties": {
    "addr:full":"3965 Fox St Denver CO 80216",
    "addr:housenumber":"3965",
    "addr:postcode":"80216",
    "addr:street":"Fox St",
    "iso:country":"US",
    "sg:address":"3965 Fox St",
    "sg:city":"Denver",
    "sg:classifiers":[
        {
            "category":"Retail",
            "subcategory":"Auto Rental",
            "type":"Services"
        }
    ],
    "sg:phone":"+1 303 455 8192",
    "sg:postcode":"80216",
    "sg:province":"CO",
    "sg:tags":[
        "renting",
        "automobile"
    ],
    "wof:name":"Easy Rent A Car",
    "wof:placetype":"venue"
},
  "geometry": {"coordinates":[-104.99493200000001,39.770926],"type":"Point"}
}