{
  "type": "Feature",
  "properties": {
    "iso:country":"US",
    "sg:address":"121 W 2nd St",
    "sg:city":"La Junta",
    "sg:classifiers":[
        {
            "category":"Retail",
            "subcategory":"Auto Repair",
            "type":"Services"
        }
    ],
    "sg:phone":"+1 719 384 2901",
    "sg:postcode":"81050",
    "sg:province":"CO",
    "sg:tags":[
        "repairing",
        "automobile"
    ],
    "wof:name":"Downtown Auto Svc",
    "wof:placetype":"venue"
},
  "geometry": {"coordinates":[-103.545571,37.987015],"type":"Point"}
}