{
  "type": "Feature",
  "properties": {
    "iso:country":"US",
    "sg:address":"2660 S. Federal Blvd",
    "sg:city":"Denver",
    "sg:classifiers":[
        {
            "category":"Autos & Motor Vehicles",
            "subcategory":"Auto Supplies",
            "type":"Retail Goods"
        }
    ],
    "sg:phone":"+1 303 935 1831",
    "sg:postcode":"80219",
    "sg:province":"CO",
    "sg:tags":[
        "tire"
    ],
    "sg:website":"www.gogreentires.net/",
    "wof:name":"Go Green Tires",
    "wof:placetype":"venue"
},
  "geometry": {"coordinates":[-105.024682,39.668794],"type":"Point"}
}