{
  "type": "Feature",
  "properties": {
    "iso:country":"US",
    "sg:address":"1917 Santa Fe Dr",
    "sg:city":"Pueblo",
    "sg:classifiers":[
        {
            "category":"Food & Beverages",
            "subcategory":"Liquor & Beverages",
            "type":"Retail Goods"
        }
    ],
    "sg:phone":"+1 719 544 8641",
    "sg:postcode":"81006",
    "sg:province":"CO",
    "wof:name":"Blende Liquor Store",
    "wof:placetype":"venue"
},
  "geometry": {"coordinates":[-104.575254,38.245677],"type":"Point"}
}