{
  "type": "Feature",
  "properties": {
    "addr:full":"10430 Livingston Dr Northglenn CO 80234",
    "addr:housenumber":"10430",
    "addr:postcode":"80234",
    "addr:street":"Livingston Dr",
    "iso:country":"US",
    "sg:address":"10430 Livingston Dr",
    "sg:city":"Northglenn",
    "sg:classifiers":[
        {
            "category":"Professional",
            "subcategory":"Business Services",
            "type":"Services"
        }
    ],
    "sg:phone":"+1 303 457 3807",
    "sg:postcode":"80234",
    "sg:province":"CO",
    "wof:name":"Nordac LLC",
    "wof:placetype":"venue"
},
  "geometry": {"coordinates":[-105.00285599999999,39.88838],"type":"Point"}
}