{
  "type": "Feature",
  "properties": {
    "iso:country":"US",
    "sg:address":"205 Main St",
    "sg:city":"Ovid",
    "sg:classifiers":[
        {
            "category":"Restaurant",
            "type":"Food & Drink"
        }
    ],
    "sg:phone":"+1 970 463 8866",
    "sg:postcode":"80744",
    "sg:province":"CO",
    "sg:tags":[
        "drinking",
        "eating"
    ],
    "wof:name":"El Alegre",
    "wof:placetype":"venue"
},
  "geometry": {"coordinates":[-102.3879,40.960761],"type":"Point"}
}