{
  "type": "Feature",
  "properties": {
    "addr:full":"425 S 1st St E Cheyenne Wells CO 80810",
    "addr:housenumber":"425",
    "addr:postcode":"80810",
    "addr:street":"S 1St St E",
    "iso:country":"US",
    "sg:address":"425 S 1st St E",
    "sg:city":"Cheyenne Wells",
    "sg:classifiers":[
        {
            "category":"Food & Beverages",
            "subcategory":"Groceries & Convenience Stores",
            "type":"Retail Goods"
        }
    ],
    "sg:phone":"+1 719 767 5265",
    "sg:postcode":"80810",
    "sg:province":"CO",
    "sg:tags":[
        "grocer"
    ],
    "wof:name":"Cheyenne Wells Iga",
    "wof:placetype":"venue"
},
  "geometry": {"coordinates":[-102.34343,38.821691],"type":"Point"}
}