{
  "type": "Feature",
  "properties": {
    "addr:full":"1165 N Ellicott Hwy Calhan CO 80808",
    "addr:housenumber":"1165",
    "addr:postcode":"80808",
    "addr:street":"N Ellicott Hwy",
    "iso:country":"US",
    "sg:address":"1165 N Ellicott Hwy",
    "sg:city":"Calhan",
    "sg:classifiers":[
        {
            "category":"Freight",
            "type":"Transportation"
        }
    ],
    "sg:phone":"+1 719 683 5300",
    "sg:postcode":"80808",
    "sg:province":"CO",
    "sg:tags":[
        "special",
        "general"
    ],
    "wof:name":"Treasure Chest",
    "wof:placetype":"venue"
},
  "geometry": {"coordinates":[-104.38720499999999,38.8493],"type":"Point"}
}