{
  "type": "Feature",
  "properties": {
    "iso:country":"US",
    "sg:address":"9800 US Hwy 50",
    "sg:city":"Lamar",
    "sg:classifiers":[
        {
            "category":"Manufacturing",
            "subcategory":"Electronics",
            "type":"Manufacturing & Wholesale Goods"
        }
    ],
    "sg:phone":"+1 719 336 4194",
    "sg:postcode":"81052",
    "sg:province":"CO",
    "sg:tags":[
        "equipment",
        "mfg",
        "communication"
    ],
    "wof:name":"Nunnery Satelite",
    "wof:placetype":"venue"
},
  "geometry": {"coordinates":[-102.57761499999999,38.091501],"type":"Point"}
}