{
  "type": "Feature",
  "properties": {
    "addr:full":"111 Market St Morrison CO 80465",
    "addr:housenumber":"111",
    "addr:postcode":"80465",
    "addr:street":"Market St",
    "iso:country":"US",
    "sg:address":"111 Market St",
    "sg:city":"Morrison",
    "sg:classifiers":[
        {
            "category":"Organizations",
            "subcategory":"Religious Organization",
            "type":"Services"
        }
    ],
    "sg:phone":"+1 303 697 1968",
    "sg:postcode":"80465",
    "sg:province":"CO",
    "sg:tags":[
        "church"
    ],
    "wof:name":"Morrison Community Church",
    "wof:placetype":"venue"
},
  "geometry": {"coordinates":[-105.18912899999999,39.653642],"type":"Point"}
}