{
  "type": "Feature",
  "properties": {
    "addr:full":"1661 N Estrella Ave Loveland CO 80538",
    "addr:housenumber":"1661",
    "addr:postcode":"80538",
    "addr:street":"N Estrella Ave",
    "iso:country":"US",
    "sg:address":"1661 N Estrella Ave",
    "sg:city":"Loveland",
    "sg:classifiers":[
        {
            "category":"Banks & Credit Unions",
            "subcategory":"Bank",
            "type":"Services"
        }
    ],
    "sg:phone":"+1 970 667 8585",
    "sg:postcode":"80538",
    "sg:province":"CO",
    "sg:tags":[
        "state"
    ],
    "sg:website":"www.lpcu.org",
    "wof:name":"Long's Peak Credit Union",
    "wof:placetype":"venue"
},
  "geometry": {"coordinates":[-105.10808900000001,40.409606],"type":"Point"}
}