{
  "type": "Feature",
  "properties": {
    "iso:country":"US",
    "sg:address":"3250 Quentin St",
    "sg:city":"Aurora",
    "sg:classifiers":[
        {
            "category":"Wholesale",
            "subcategory":"Electrical",
            "type":"Manufacturing & Wholesale Goods"
        }
    ],
    "sg:phone":"+1 303 360 8612",
    "sg:postcode":"80011",
    "sg:province":"CO",
    "sg:tags":[
        "equipment",
        "material",
        "electronic",
        "supply"
    ],
    "wof:name":"Insulectro",
    "wof:placetype":"venue"
},
  "geometry": {"coordinates":[-104.844368,39.763886],"type":"Point"}
}