{
  "type": "Feature",
  "properties": {
    "iso:country":"US",
    "sg:address":"116 N Alder St",
    "sg:city":"Crestone",
    "sg:classifiers":[
        {
            "category":"Manufacturing",
            "subcategory":"Printing",
            "type":"Manufacturing & Wholesale Goods"
        }
    ],
    "sg:phone":"+1 719 256 4008",
    "sg:postcode":"81131",
    "sg:province":"CO",
    "sg:tags":[
        "lithographic",
        "commercial"
    ],
    "wof:name":"Peak Printing",
    "wof:placetype":"venue"
},
  "geometry": {"coordinates":[-105.69899599999999,37.99609],"type":"Point"}
}