{
  "type": "Feature",
  "properties": {
    "iso:country":"US",
    "sg:address":"2445 Youngfield St",
    "sg:city":"Golden",
    "sg:classifiers":[
        {
            "category":"Health Services",
            "subcategory":"Nursing And Care Facility",
            "type":"Services"
        }
    ],
    "sg:phone":"+1 303 234 0172",
    "sg:postcode":"80401",
    "sg:province":"CO",
    "sg:tags":[
        "home",
        "retirement",
        "community"
    ],
    "wof:name":"Applewood Retirement Community",
    "wof:placetype":"venue"
},
  "geometry": {"coordinates":[-105.142448,39.751101],"type":"Point"}
}