{
  "type": "Feature",
  "properties": {
    "addr:full":"2915 W 38th Ave Denver CO 80211",
    "addr:housenumber":"2915",
    "addr:postcode":"80211",
    "addr:street":"W 38Th Ave",
    "iso:country":"US",
    "sg:address":"2915 W 38th Ave",
    "sg:city":"Denver",
    "sg:classifiers":[
        {
            "category":"Restaurant",
            "type":"Food & Drink"
        }
    ],
    "sg:menulink":"http://www.allmenus.com/co/denver/22790-sing-on/menu/",
    "sg:phone":"+1 303 458 1303",
    "sg:postcode":"80211",
    "sg:province":"CO",
    "sg:tags":[
        "asian",
        "chinese"
    ],
    "wof:name":"Sing On",
    "wof:placetype":"venue"
},
  "geometry": {"coordinates":[-105.02333,39.76929],"type":"Point"}
}