{
  "type": "Feature",
  "properties": {
    "addr:full":"230 E Cheyenne Mountain Blvd Colorado Springs CO 80906",
    "addr:housenumber":"230",
    "addr:postcode":"80906",
    "addr:street":"E Cheyenne Mountain Blvd",
    "iso:country":"US",
    "sg:address":"230 E Cheyenne Mountain Blvd",
    "sg:city":"Colorado Springs",
    "sg:classifiers":[
        {
            "category":"Real Estate",
            "subcategory":"Real Estate Agent",
            "type":"Services"
        }
    ],
    "sg:phone":"+1 719 576 0178",
    "sg:postcode":"80906",
    "sg:province":"CO",
    "wof:name":"Dunn & Assoc",
    "wof:placetype":"venue"
},
  "geometry": {"coordinates":[-104.823809,38.789424],"type":"Point"}
}