{
  "type": "Feature",
  "properties": {
    "iso:country":"US",
    "sg:address":"1301 Pennsylvania St",
    "sg:city":"Denver",
    "sg:classifiers":[
        {
            "category":"Banks & Credit Unions",
            "subcategory":"Investment Brokerage",
            "type":"Services"
        }
    ],
    "sg:phone":"+1 303 830 2518",
    "sg:postcode":"80203",
    "sg:province":"CO",
    "sg:tags":[
        "advisory",
        "financial"
    ],
    "wof:name":"Citigroup",
    "wof:placetype":"venue"
},
  "geometry": {"coordinates":[-104.981081,39.73843],"type":"Point"}
}