{
  "type": "Feature",
  "properties": {
    "addr:full":"6102 W 55th Ave Arvada CO 80002",
    "addr:housenumber":"6102",
    "addr:postcode":"80002",
    "addr:street":"W 55Th Ave",
    "iso:country":"US",
    "sg:address":"6102 W 55th Ave",
    "sg:city":"Arvada",
    "sg:classifiers":[
        {
            "category":"Building & Trades",
            "subcategory":"Construction",
            "type":"Services"
        }
    ],
    "sg:phone":"+1 303 487 1870",
    "sg:postcode":"80002",
    "sg:province":"CO",
    "sg:tags":[
        "carpentry",
        "contractor"
    ],
    "wof:name":"Woodcrafters By Design",
    "wof:placetype":"venue"
},
  "geometry": {"coordinates":[-105.06802999999999,39.796255],"type":"Point"}
}