{
  "type": "Feature",
  "properties": {
    "iso:country":"US",
    "sg:address":"1032 E South Boulder Rd",
    "sg:city":"Louisville",
    "sg:classifiers":[
        {
            "category":"Professional",
            "subcategory":"Accounting & Tax Preparation",
            "type":"Services"
        }
    ],
    "sg:phone":"+1 303 665 8422",
    "sg:postcode":"80027",
    "sg:province":"CO",
    "sg:tags":[
        "return",
        "filing"
    ],
    "wof:name":"L & L Tax Svc",
    "wof:placetype":"venue"
},
  "geometry": {"coordinates":[-105.13123,39.986846],"type":"Point"}
}