{
  "type": "Feature",
  "properties": {
    "iso:country":"US",
    "sg:address":"700 W Main St",
    "sg:city":"Sterling",
    "sg:classifiers":[
        {
            "category":"Restaurant",
            "type":"Food & Drink"
        }
    ],
    "sg:menulink":"http://www.allmenus.com/co/sterling/189457-kfc---kentucky-fried-chicken/menu/",
    "sg:phone":"+1 303 522 5220",
    "sg:postcode":"80751",
    "sg:province":"CO",
    "sg:tags":[
        "american",
        "chicken"
    ],
    "wof:name":"KFC - Kentucky Fried Chicken",
    "wof:placetype":"venue"
},
  "geometry": {"coordinates":[-103.22110600000001,40.625339],"type":"Point"}
}