{
  "type": "Feature",
  "properties": {
    "addr:full":"6785 W 120th Ave Broomfield CO 80020",
    "addr:housenumber":"6785",
    "addr:postcode":"80020",
    "addr:street":"W 120Th Ave",
    "iso:country":"US",
    "sg:address":"6785 W 120th Ave",
    "sg:city":"Broomfield",
    "sg:classifiers":[
        {
            "category":"Autos & Motor Vehicles",
            "subcategory":"Auto Supplies",
            "type":"Retail Goods"
        }
    ],
    "sg:phone":"+1 303 466 8805",
    "sg:postcode":"80020",
    "sg:province":"CO",
    "sg:tags":[
        "automobile",
        "parts"
    ],
    "sg:website":"www.partsamerica.com",
    "wof:name":"Checker Auto Parts 1131",
    "wof:placetype":"venue"
},
  "geometry": {"coordinates":[-105.069458,39.914368],"type":"Point"}
}