{
  "type": "Feature",
  "properties": {
    "addr:full":"101 Airpark Rd Gypsum CO 81637",
    "addr:postcode":"81637",
    "addr:street":"Airpark Rd",
    "iso:country":"US",
    "sg:address":"101 Airpark Rd",
    "sg:city":"Gypsum",
    "sg:classifiers":[
        {
            "category":"Building & Trades",
            "subcategory":"Construction",
            "type":"Services"
        }
    ],
    "sg:phone":"+1 970 524 1543",
    "sg:postcode":"81637",
    "sg:province":"CO",
    "sg:tags":[
        "tile",
        "dealer"
    ],
    "wof:name":"Professional Marble & Tile Inc",
    "wof:placetype":"venue"
},
  "geometry": {"coordinates":[-106.908148,39.636028],"type":"Point"}
}