{
  "type": "Feature",
  "properties": {
    "addr:full":"575 Union Blvd Ste 208 Lakewood CO 80228",
    "addr:housenumber":"575",
    "addr:postcode":"80228",
    "addr:street":"Union Blvd Ste 208",
    "iso:country":"US",
    "sg:address":"575 Union Blvd Ste 208",
    "sg:city":"Lakewood",
    "sg:classifiers":[
        {
            "category":"Utilities",
            "subcategory":"Fuel Oil & Lpg",
            "type":"Services"
        }
    ],
    "sg:phone":"+1 303 945 2850",
    "sg:postcode":"80228",
    "sg:province":"CO",
    "sg:tags":[
        "development",
        "exploration",
        "gas"
    ],
    "wof:name":"Coyote Oil And Gas",
    "wof:placetype":"venue"
},
  "geometry": {"coordinates":[-105.131817,39.724402],"type":"Point"}
}