{
  "type": "Feature",
  "properties": {
    "addr:full":"1112 Main St Delta CO 81416",
    "addr:housenumber":"1112",
    "addr:postcode":"81416",
    "addr:street":"Main St",
    "iso:country":"US",
    "sg:address":"1112 Main St",
    "sg:city":"Delta",
    "sg:classifiers":[
        {
            "category":"Manufacturing",
            "subcategory":"Signs",
            "type":"Manufacturing & Wholesale Goods"
        }
    ],
    "sg:phone":"+1 970 874 3396",
    "sg:postcode":"81416",
    "sg:province":"CO",
    "sg:tags":[
        "specialty",
        "mfg"
    ],
    "wof:name":"Colorado Sign Studio",
    "wof:placetype":"venue"
},
  "geometry": {"coordinates":[-108.070536,38.732383],"type":"Point"}
}