{
  "type": "Feature",
  "properties": {
    "addr:full":"37418 State Hwy 145 Redvale CO 81423",
    "addr:housenumber":"37418",
    "addr:postcode":"81423",
    "addr:street":"State Hwy 145 Redvale",
    "iso:country":"US",
    "sg:address":"37418 State Hwy 145",
    "sg:city":"Redvale",
    "sg:classifiers":[
        {
            "category":"Building & Trades",
            "subcategory":"Construction",
            "type":"Services"
        }
    ],
    "sg:phone":"+1 970 327 0130",
    "sg:postcode":"81423",
    "sg:province":"CO",
    "sg:tags":[
        "contractor"
    ],
    "wof:name":"Sutherland Je Construction",
    "wof:placetype":"venue"
},
  "geometry": {"coordinates":[-108.383717,38.160074],"type":"Point"}
}