{
  "type": "Feature",
  "properties": {
    "iso:country":"US",
    "sg:address":"929 W 1st Ave",
    "sg:city":"Denver",
    "sg:classifiers":[
        {
            "category":"Home & Garden",
            "subcategory":"Building Materials",
            "type":"Retail Goods"
        },
        {
            "category":"Home & Garden",
            "subcategory":"Carpets & Floor Coverings",
            "type":"Retail Goods"
        }
    ],
    "sg:phone":"+1 303 825 3006",
    "sg:postcode":"80223",
    "sg:province":"CO",
    "sg:tags":[
        "hardwood",
        "flooring",
        "contractor"
    ],
    "sg:website":"http://www.macwoods.com",
    "wof:name":"MacDonald Hardwoods Inc.",
    "wof:placetype":"venue"
},
  "geometry": {"coordinates":[-104.999322,39.718709],"type":"Point"}
}