{
  "type": "Feature",
  "properties": {
    "addr:full":"1661 W Evans Ave Denver CO 80223",
    "addr:housenumber":"1661",
    "addr:postcode":"80223",
    "addr:street":"W Evans Ave",
    "iso:country":"US",
    "sg:address":"1661 W Evans Ave",
    "sg:city":"Denver",
    "sg:classifiers":[
        {
            "category":"Autos & Motor Vehicles",
            "subcategory":"Automobile Sales",
            "type":"Retail Goods"
        }
    ],
    "sg:phone":"+1 303 922 0821",
    "sg:postcode":"80223",
    "sg:province":"CO",
    "sg:tags":[
        "used"
    ],
    "wof:name":"Gordies Auto Sales",
    "wof:placetype":"venue"
},
  "geometry": {"coordinates":[-105.008032,39.67869],"type":"Point"}
}