{
  "type": "Feature",
  "properties": {
    "iso:country":"US",
    "sg:address":"7580 W 64th Ave",
    "sg:city":"Arvada",
    "sg:classifiers":[
        {
            "category":"Restaurant",
            "type":"Food & Drink"
        }
    ],
    "sg:phone":"+1 303 424 1202",
    "sg:postcode":"80003",
    "sg:province":"CO",
    "sg:tags":[
        "frozen",
        "yogurt",
        "eating",
        "ice",
        "cream"
    ],
    "wof:name":"Dairy Queen",
    "wof:placetype":"venue"
},
  "geometry": {"coordinates":[-105.08110499999999,39.812579],"type":"Point"}
}