{
  "type": "Feature",
  "properties": {
    "addr:full":"520 S 9th St Grand Junction CO 81501",
    "addr:housenumber":"520",
    "addr:postcode":"81501",
    "addr:street":"S 9Th St",
    "iso:country":"US",
    "sg:address":"520 S 9th St",
    "sg:city":"Grand Junction",
    "sg:classifiers":[
        {
            "category":"Wholesale",
            "subcategory":"Farm Supplies",
            "type":"Manufacturing & Wholesale Goods"
        }
    ],
    "sg:phone":"+1 970 241 0979",
    "sg:postcode":"81501",
    "sg:province":"CO",
    "sg:tags":[
        "distributor",
        "seed"
    ],
    "wof:name":"Green Fields Seed & Feed",
    "wof:placetype":"venue"
},
  "geometry": {"coordinates":[-108.55761099999999,39.062686],"type":"Point"}
}