{
  "type": "Feature",
  "properties": {
    "iso:country":"US",
    "sg:address":"13990 Gleneagle Dr",
    "sg:city":"Colorado Springs",
    "sg:classifiers":[
        {
            "category":"Restaurant",
            "type":"Food & Drink"
        }
    ],
    "sg:menulink":"http://www.allmenus.com/co/black-forest-peyton/4256-the-place/menu/",
    "sg:phone":"+1 719 481 4383",
    "sg:postcode":"80921",
    "sg:province":"CO",
    "sg:tags":[
        "american"
    ],
    "wof:name":"The Place",
    "wof:placetype":"venue"
},
  "geometry": {"coordinates":[-104.828895,39.033359],"type":"Point"}
}