{
  "type": "Feature",
  "properties": {
    "addr:full":"3773 Monarch St Erie CO 80516",
    "addr:housenumber":"3773",
    "addr:postcode":"80516",
    "addr:street":"Monarch St",
    "iso:country":"US",
    "sg:address":"3773 Monarch St",
    "sg:city":"Erie",
    "sg:classifiers":[
        {
            "category":"Home & Garden",
            "subcategory":"Building Materials",
            "type":"Retail Goods"
        }
    ],
    "sg:phone":"+1 303 287 9970",
    "sg:postcode":"80516",
    "sg:province":"CO",
    "sg:tags":[
        "door"
    ],
    "wof:name":"Western Dock & Door Systems",
    "wof:placetype":"venue"
},
  "geometry": {"coordinates":[-104.98241299999999,40.081463],"type":"Point"}
}