{
  "type": "Feature",
  "properties": {
    "iso:country":"US",
    "sg:address":"697 Peoria St",
    "sg:city":"Aurora",
    "sg:classifiers":[
        {
            "category":"Professional",
            "subcategory":"Management & Consulting",
            "type":"Services"
        }
    ],
    "sg:phone":"+1 303 344 3173",
    "sg:postcode":"80011",
    "sg:province":"CO",
    "sg:tags":[
        "consultant",
        "business"
    ],
    "wof:name":"Aurora Plaza",
    "wof:placetype":"venue"
},
  "geometry": {"coordinates":[-104.847269,39.727315],"type":"Point"}
}