{
  "type": "Feature",
  "properties": {
    "addr:full":"11 Rawhide Rd Edwards CO 81632",
    "addr:housenumber":"11",
    "addr:postcode":"81632",
    "addr:street":"Rawhide Rd",
    "iso:country":"US",
    "sg:address":"11 Rawhide Rd",
    "sg:city":"Edwards",
    "sg:classifiers":[
        {
            "category":"Building & Trades",
            "subcategory":"Plumbing",
            "type":"Services"
        }
    ],
    "sg:phone":"+1 970 926 2412",
    "sg:postcode":"81632",
    "sg:province":"CO",
    "sg:tags":[
        "plumbing",
        "contractor"
    ],
    "wof:name":"Alpine Mechanical Contractors",
    "wof:placetype":"venue"
},
  "geometry": {"coordinates":[-106.577748,39.64627],"type":"Point"}
}