{
  "type": "Feature",
  "properties": {
    "addr:full":"21732 US Hwy 285 La Jara CO 81140",
    "addr:postcode":"21732;81140",
    "addr:street":"Us Hwy 285",
    "iso:country":"US",
    "sg:address":"21732 US Hwy 285",
    "sg:city":"La Jara",
    "sg:phone":"+1 719 274 4073",
    "sg:postcode":"81140",
    "sg:province":"CO",
    "sg:tags":[
        "farm",
        "field",
        "crop",
        "mfg"
    ],
    "wof:name":"JB Shawcroft Farm",
    "wof:placetype":"venue"
},
  "geometry": {"coordinates":[-105.94113299999999,37.334431],"type":"Point"}
}