{
  "type": "Feature",
  "properties": {
    "iso:country":"US",
    "sg:address":"1509 Wadsworth Boulevard",
    "sg:city":"Lakewood",
    "sg:classifiers":[
        {
            "category":"Restaurant",
            "type":"Food & Drink"
        }
    ],
    "sg:phone":"+1 303 237 0728",
    "sg:postcode":"80214",
    "sg:province":"CO",
    "wof:name":"Panda Express No 1107",
    "wof:placetype":"venue"
},
  "geometry": {"coordinates":[-105.081337,39.740493],"type":"Point"}
}