{
  "type": "Feature",
  "properties": {
    "addr:full":"3572 Vera Cruz Ct Colorado Springs CO 80910",
    "addr:housenumber":"3572",
    "addr:postcode":"80910",
    "addr:street":"Vera Cruz Ct",
    "iso:country":"US",
    "sg:address":"3572 Vera Cruz Ct",
    "sg:city":"Colorado Springs",
    "sg:classifiers":[
        {
            "category":"Building & Trades",
            "subcategory":"Construction",
            "type":"Services"
        }
    ],
    "sg:phone":"+1 719 638 2849",
    "sg:postcode":"80910",
    "sg:province":"CO",
    "sg:tags":[
        "general",
        "contractor"
    ],
    "wof:name":"ABC Construction",
    "wof:placetype":"venue"
},
  "geometry": {"coordinates":[-104.763127,38.816627],"type":"Point"}
}