{
  "type": "Feature",
  "properties": {
    "addr:full":"7663 S Independence Way Littleton CO 80128",
    "addr:housenumber":"7663",
    "addr:postcode":"80128",
    "addr:street":"S Independence Way",
    "iso:country":"US",
    "sg:address":"7663 S Independence Way",
    "sg:city":"Littleton",
    "sg:classifiers":[
        {
            "category":"Building & Trades",
            "subcategory":"Electrical",
            "type":"Services"
        }
    ],
    "sg:phone":"+1 303 979 9596",
    "sg:postcode":"80128",
    "sg:province":"CO",
    "sg:tags":[
        "contractor",
        "electrical",
        "electric",
        "general"
    ],
    "wof:name":"Economy Services Corporation",
    "wof:placetype":"venue"
},
  "geometry": {"coordinates":[-105.105001,39.576584],"type":"Point"}
}