{
  "type": "Feature",
  "properties": {
    "iso:country":"US",
    "sg:address":"5021 N Blazingstar Trl",
    "sg:city":"Castle Rock",
    "sg:classifiers":[
        {
            "category":"Building & Trades",
            "subcategory":"Construction",
            "type":"Services"
        }
    ],
    "sg:phone":"+1 303 688 5948",
    "sg:postcode":"80109",
    "sg:province":"CO",
    "sg:tags":[
        "contractor"
    ],
    "wof:name":"David R Hinkley Builders",
    "wof:placetype":"venue"
},
  "geometry": {"coordinates":[-104.90082200000001,39.411514],"type":"Point"}
}