{
  "type": "Feature",
  "properties": {
    "addr:full":"4775 W 127th Pl Broomfield CO 80020",
    "addr:housenumber":"4775",
    "addr:postcode":"80020",
    "addr:street":"W 127Th Pl",
    "iso:country":"US",
    "sg:address":"4775 W 127th Pl",
    "sg:city":"Broomfield",
    "sg:classifiers":[
        {
            "category":"Organizations",
            "subcategory":"Community Association",
            "type":"Services"
        }
    ],
    "sg:phone":"+1 303 469 6901",
    "sg:postcode":"80020",
    "sg:province":"CO",
    "sg:tags":[
        "sporting"
    ],
    "wof:name":"Colorado Outdoor Sports",
    "wof:placetype":"venue"
},
  "geometry": {"coordinates":[-105.047842,39.926577],"type":"Point"}
}