{
  "type": "Feature",
  "properties": {
    "addr:full":"2254 Eastwood Dr Fort Collins CO 80525",
    "addr:housenumber":"2254",
    "addr:postcode":"80525",
    "addr:street":"Eastwood Dr",
    "iso:country":"US",
    "sg:address":"2254 Eastwood Dr",
    "sg:city":"Fort Collins",
    "sg:classifiers":[
        {
            "category":"Professional",
            "subcategory":"Business Services",
            "type":"Services"
        }
    ],
    "sg:phone":"+1 970 221 0367",
    "sg:postcode":"80525",
    "sg:province":"CO",
    "sg:tags":[
        "interior",
        "consultant",
        "design",
        "decorator"
    ],
    "wof:name":"Interiors Extraordinaire",
    "wof:placetype":"venue"
},
  "geometry": {"coordinates":[-105.04429500000001,40.557025],"type":"Point"}
}