{
  "type": "Feature",
  "properties": {
    "addr:full":"601 S Prospect St Colorado Springs CO 80903",
    "addr:housenumber":"601",
    "addr:postcode":"80903",
    "addr:street":"S Prospect St",
    "iso:country":"US",
    "sg:address":"601 S Prospect St",
    "sg:city":"Colorado Springs",
    "sg:classifiers":[
        {
            "category":"Organizations",
            "subcategory":"Religious Organization",
            "type":"Services"
        }
    ],
    "sg:phone":"+1 719 630 8709",
    "sg:postcode":"80903",
    "sg:province":"CO",
    "sg:tags":[
        "church"
    ],
    "wof:name":"New Resurrection Baptist Chr",
    "wof:placetype":"venue"
},
  "geometry": {"coordinates":[-104.81075199999999,38.824073],"type":"Point"}
}