{
  "type": "Feature",
  "properties": {
    "addr:full":"7955 S Field St Littleton CO 80128",
    "addr:housenumber":"7955",
    "addr:postcode":"80128",
    "addr:street":"S Field St",
    "iso:country":"US",
    "sg:address":"7955 S Field St",
    "sg:city":"Littleton",
    "sg:classifiers":[
        {
            "category":"Freight",
            "type":"Transportation"
        }
    ],
    "sg:phone":"+1 720 981 9757",
    "sg:postcode":"80128",
    "sg:province":"CO",
    "sg:tags":[
        "operator",
        "local",
        "trucking"
    ],
    "wof:name":"Ebele Bros Trucking",
    "wof:placetype":"venue"
},
  "geometry": {"coordinates":[-105.099056,39.572121],"type":"Point"}
}