{
  "type": "Feature",
  "properties": {
    "iso:country":"US",
    "sg:address":"973 E Nichols Ave",
    "sg:city":"Centennial",
    "sg:classifiers":[
        {
            "category":"Retail",
            "subcategory":"Portrait Studio",
            "type":"Services"
        }
    ],
    "sg:phone":"+1 303 347 8001",
    "sg:postcode":"80122",
    "sg:province":"CO",
    "sg:tags":[
        "photographer"
    ],
    "sg:website":"www.erlenesphotos.com",
    "wof:name":"Erlene Finch Photography",
    "wof:placetype":"venue"
},
  "geometry": {"coordinates":[-104.976578,39.571446],"type":"Point"}
}