{
  "type": "Feature",
  "properties": {
    "addr:full":"64 Zip Ln Bailey CO 80421",
    "addr:housenumber":"64",
    "addr:postcode":"80421",
    "addr:street":"Zip Ln",
    "iso:country":"US",
    "sg:address":"64 Zip Ln",
    "sg:city":"Bailey",
    "sg:classifiers":[
        {
            "category":"Manufacturing",
            "subcategory":"Glass & Minerals",
            "type":"Manufacturing & Wholesale Goods"
        }
    ],
    "sg:phone":"+1 303 838 7674",
    "sg:postcode":"80421",
    "sg:province":"CO",
    "sg:tags":[
        "concrete",
        "product",
        "mfg"
    ],
    "wof:name":"Henles Fireplace",
    "wof:placetype":"venue"
},
  "geometry": {"coordinates":[-105.406761,39.419595],"type":"Point"}
}