{
  "type": "Feature",
  "properties": {
    "addr:full":"11353 W Colfax Ave Lakewood CO 80215",
    "addr:housenumber":"11353",
    "addr:postcode":"80215",
    "addr:street":"W Colfax Ave",
    "iso:country":"US",
    "sg:address":"11353 W Colfax Ave",
    "sg:city":"Lakewood",
    "sg:classifiers":[
        {
            "category":"Restaurant",
            "type":"Food & Drink"
        }
    ],
    "sg:phone":"+1 303 233 7800",
    "sg:postcode":"80215",
    "sg:province":"CO",
    "sg:website":"www.sydneystation.com",
    "wof:name":"Sydney Station",
    "wof:placetype":"venue"
},
  "geometry": {"coordinates":[-105.12554799999999,39.740247],"type":"Point"}
}