{
  "type": "Feature",
  "properties": {
    "addr:full":"1528 W 18th St Pueblo CO 81003",
    "addr:housenumber":"1528",
    "addr:postcode":"81003",
    "addr:street":"W 18Th St",
    "iso:country":"US",
    "sg:address":"1528 W 18th St",
    "sg:city":"Pueblo",
    "sg:classifiers":[
        {
            "category":"Building & Trades",
            "subcategory":"Construction",
            "type":"Services"
        }
    ],
    "sg:phone":"+1 719 546 3247",
    "sg:postcode":"81003",
    "sg:province":"CO",
    "sg:tags":[
        "painter"
    ],
    "wof:name":"JLS Painting",
    "wof:placetype":"venue"
},
  "geometry": {"coordinates":[-104.632189,38.283443],"type":"Point"}
}