{
  "type": "Feature",
  "properties": {
    "addr:full":"2721 W Kiowa St Colorado Springs CO 80904",
    "addr:housenumber":"2721",
    "addr:postcode":"80904",
    "addr:street":"W Kiowa St",
    "iso:country":"US",
    "sg:address":"2721 W Kiowa St",
    "sg:city":"Colorado Springs",
    "sg:classifiers":[
        {
            "category":"Building & Trades",
            "subcategory":"Construction",
            "type":"Services"
        }
    ],
    "sg:phone":"+1 719 632 9470",
    "sg:postcode":"80904",
    "sg:province":"CO",
    "sg:tags":[
        "residential",
        "commercial"
    ],
    "wof:name":"Kiva Construction Inc",
    "wof:placetype":"venue"
},
  "geometry": {"coordinates":[-104.865655,38.851095],"type":"Point"}
}