{
  "type": "Feature",
  "properties": {
    "addr:full":"6433 S Datura St Littleton CO 80120",
    "addr:housenumber":"6433",
    "addr:postcode":"80120",
    "addr:street":"S Datura St",
    "iso:country":"US",
    "sg:address":"6433 S Datura St",
    "sg:city":"Littleton",
    "sg:classifiers":[
        {
            "category":"Shopping",
            "subcategory":"Jewelry",
            "type":"Retail Goods"
        }
    ],
    "sg:phone":"+1 303 795 7698",
    "sg:postcode":"80120",
    "sg:province":"CO",
    "sg:tags":[
        "clocks"
    ],
    "wof:name":"Front Range Clocks LLC",
    "wof:placetype":"venue"
},
  "geometry": {"coordinates":[-105.004752,39.599328],"type":"Point"}
}