{
  "type": "Feature",
  "properties": {
    "addr:full":"444 E Pikes Peak Ave Colorado Springs CO 80903",
    "addr:housenumber":"444",
    "addr:postcode":"80903",
    "addr:street":"E Pikes Peak Ave",
    "iso:country":"US",
    "sg:address":"444 E Pikes Peak Ave",
    "sg:city":"Colorado Springs",
    "sg:classifiers":[
        {
            "category":"Real Estate",
            "subcategory":"Real Estate Operator",
            "type":"Services"
        }
    ],
    "sg:phone":"+1 719 492 3213",
    "sg:postcode":"80903",
    "sg:province":"CO",
    "sg:tags":[
        "apartment"
    ],
    "wof:name":"Sun Meadow Villas",
    "wof:placetype":"venue"
},
  "geometry": {"coordinates":[-104.81636899999999,38.833781],"type":"Point"}
}