{
  "type": "Feature",
  "properties": {
    "addr:full":"7995 E Prentice Ave Englewood CO 80111",
    "addr:housenumber":"7995",
    "addr:postcode":"80111",
    "addr:street":"E Prentice Ave",
    "iso:country":"US",
    "sg:address":"7995 E Prentice Ave",
    "sg:city":"Englewood",
    "sg:classifiers":[
        {
            "category":"Building & Trades",
            "subcategory":"Construction",
            "type":"Services"
        }
    ],
    "sg:phone":"+1 303 721 5800",
    "sg:postcode":"80111",
    "sg:province":"CO",
    "sg:tags":[
        "general",
        "contractor"
    ],
    "wof:name":"Boots Construction Company",
    "wof:placetype":"venue"
},
  "geometry": {"coordinates":[-104.894846,39.620875],"type":"Point"}
}