{
  "type": "Feature",
  "properties": {
    "addr:full":"1276 Harwig Cir Steamboat Spgs CO 80487",
    "addr:housenumber":"1276",
    "addr:postcode":"80487",
    "addr:street":"Harwig Cir;Spgs",
    "iso:country":"US",
    "sg:address":"1276 Harwig Cir",
    "sg:city":"Steamboat Spgs",
    "sg:classifiers":[
        {
            "category":"Freight",
            "type":"Transportation"
        }
    ],
    "sg:phone":"+1 970 870 1959",
    "sg:postcode":"80487",
    "sg:province":"CO",
    "sg:tags":[
        "commercial",
        "storage"
    ],
    "wof:name":"Affordable Storage",
    "wof:placetype":"venue"
},
  "geometry": {"coordinates":[-106.810633,40.482687],"type":"Point"}
}