{
  "type": "Feature",
  "properties": {
    "iso:country":"US",
    "sg:address":"1963 Jasper St",
    "sg:city":"Aurora",
    "sg:classifiers":[
        {
            "category":"Freight",
            "type":"Transportation"
        }
    ],
    "sg:phone":"+1 303 364 6555",
    "sg:postcode":"80011",
    "sg:province":"CO",
    "sg:tags":[
        "operator",
        "delivery",
        "local",
        "trucking"
    ],
    "wof:name":"Major Carriers Inc",
    "wof:placetype":"venue"
},
  "geometry": {"coordinates":[-104.805903,39.747158],"type":"Point"}
}