{
  "type": "Feature",
  "properties": {
    "iso:country":"US",
    "sg:address":"318 Juniper Pl",
    "sg:city":"Loveland",
    "sg:classifiers":[
        {
            "category":"Building & Trades",
            "subcategory":"Construction",
            "type":"Services"
        }
    ],
    "sg:phone":"+1 970 461 8658",
    "sg:postcode":"80538",
    "sg:province":"CO",
    "sg:tags":[
        "contractor"
    ],
    "wof:name":"Little Feat LLC",
    "wof:placetype":"venue"
},
  "geometry": {"coordinates":[-105.079369,40.438994],"type":"Point"}
}