{
  "type": "Feature",
  "properties": {
    "iso:country":"US",
    "sg:address":"44961 Co Rd 29",
    "sg:city":"Elizabeth",
    "sg:classifiers":[
        {
            "category":"Shopping",
            "type":"Retail Goods"
        }
    ],
    "sg:phone":"+1 303 646 3712",
    "sg:postcode":"80107",
    "sg:province":"CO",
    "sg:tags":[
        "merchandise"
    ],
    "wof:name":"Colo Country Frame & Art",
    "wof:placetype":"venue"
},
  "geometry": {"coordinates":[-104.53238,39.519354],"type":"Point"}
}