{
  "type": "Feature",
  "properties": {
    "iso:country":"US",
    "sg:address":"12000 Washington St",
    "sg:city":"Denver",
    "sg:classifiers":[
        {
            "category":"Health Services",
            "subcategory":"Clinic",
            "type":"Services"
        }
    ],
    "sg:phone":"+1 303 920 2022",
    "sg:postcode":"80241",
    "sg:province":"CO",
    "wof:name":"Advanced Holastic Health Svc",
    "wof:placetype":"venue"
},
  "geometry": {"coordinates":[-104.97782100000001,39.919353],"type":"Point"}
}