{
  "type": "Feature",
  "properties": {
    "iso:country":"US",
    "sg:address":"2035 S Julian Cir",
    "sg:city":"Denver",
    "sg:classifiers":[
        {
            "category":"Building & Trades",
            "subcategory":"Electrical",
            "type":"Services"
        },
        {
            "category":"Wholesale",
            "subcategory":"Electrical",
            "type":"Manufacturing & Wholesale Goods"
        }
    ],
    "sg:phone":"+1 303 937 7525",
    "sg:postcode":"80219",
    "sg:province":"CO",
    "sg:tags":[
        "fire",
        "alarm",
        "system",
        "contractor"
    ],
    "wof:name":"B & J Life Safety Co Inc",
    "wof:placetype":"venue"
},
  "geometry": {"coordinates":[-105.030597,39.678983],"type":"Point"}
}