{
  "type": "Feature",
  "properties": {
    "addr:full":"2201 Pearl St Boulder CO 80302",
    "addr:housenumber":"2201",
    "addr:postcode":"80302",
    "addr:street":"Pearl St",
    "iso:country":"US",
    "sg:address":"2201 Pearl St",
    "sg:city":"Boulder",
    "sg:classifiers":[
        {
            "category":"Banks & Credit Unions",
            "subcategory":"Financial Services",
            "type":"Services"
        }
    ],
    "sg:phone":"+1 303 413 1837",
    "sg:postcode":"80302",
    "sg:province":"CO",
    "sg:tags":[
        "investor"
    ],
    "wof:name":"Newberry Investments LLC",
    "wof:placetype":"venue"
},
  "geometry": {"coordinates":[-105.268163,40.02039],"type":"Point"}
}