{
  "type": "Feature",
  "properties": {
    "addr:full":"5168 Parfet St Wheat Ridge CO 80033",
    "addr:housenumber":"5168",
    "addr:postcode":"80033",
    "addr:street":"Parfet St",
    "iso:country":"US",
    "sg:address":"5168 Parfet St",
    "sg:city":"Wheat Ridge",
    "sg:classifiers":[
        {
            "category":"Retail",
            "subcategory":"Repair Shop",
            "type":"Services"
        }
    ],
    "sg:phone":"+1 303 423 3496",
    "sg:postcode":"80033",
    "sg:province":"CO",
    "sg:tags":[
        "welding"
    ],
    "sg:website":"www.calweldllc.com",
    "wof:name":"Calweld",
    "wof:placetype":"venue"
},
  "geometry": {"coordinates":[-105.121008,39.788553],"type":"Point"}
}