{
  "type": "Feature",
  "properties": {
    "addr:full":"1300 Clayton St Denver CO 80206",
    "addr:housenumber":"1300",
    "addr:postcode":"80206",
    "addr:street":"Clayton St",
    "iso:country":"US",
    "sg:address":"1300 Clayton St",
    "sg:city":"Denver",
    "sg:classifiers":[
        {
            "category":"Wholesale",
            "subcategory":"Motor Vehicles",
            "type":"Manufacturing & Wholesale Goods"
        }
    ],
    "sg:phone":"+1 303 394 3988",
    "sg:postcode":"80206",
    "sg:province":"CO",
    "sg:tags":[
        "business"
    ],
    "wof:name":"Tindall Motors",
    "wof:placetype":"venue"
},
  "geometry": {"coordinates":[-104.95511500000001,39.738378],"type":"Point"}
}