{
  "type": "Feature",
  "properties": {
    "iso:country":"US",
    "sg:address":"1410 Marion St Apt 8",
    "sg:city":"Denver",
    "sg:classifiers":[
        {
            "category":"Bakery",
            "type":"Food & Drink"
        }
    ],
    "sg:phone":"+1 303 860 0568",
    "sg:postcode":"80218",
    "sg:province":"CO",
    "sg:tags":[
        "photographs-stock"
    ],
    "sg:website":"http://www.memolinkcorp.com",
    "wof:name":"David Allen Designs",
    "wof:placetype":"venue"
},
  "geometry": {"coordinates":[-104.971864,39.738565],"type":"Point"}
}