{
  "type": "Feature",
  "properties": {
    "iso:country":"US",
    "sg:address":"6955 E 50th Ave",
    "sg:city":"Commerce City",
    "sg:classifiers":[
        {
            "category":"Wholesale",
            "subcategory":"Motor Vehicles",
            "type":"Manufacturing & Wholesale Goods"
        }
    ],
    "sg:phone":"+1 303 287 8077",
    "sg:postcode":"80022",
    "sg:province":"CO",
    "sg:tags":[
        "auction",
        "automobile",
        "through"
    ],
    "wof:name":"Colorado Auto Auction",
    "wof:placetype":"venue"
},
  "geometry": {"coordinates":[-104.907473,39.787535],"type":"Point"}
}