{
  "type": "Feature",
  "properties": {
    "iso:country":"US",
    "sg:address":"2720 S Colorado Boulevard Unit 700",
    "sg:city":"Denver",
    "sg:classifiers":[
        {
            "category":"Banks & Credit Unions",
            "subcategory":"Bank",
            "type":"Services"
        }
    ],
    "sg:phone":"+1 303 757 3368",
    "sg:postcode":"80222",
    "sg:province":"CO",
    "wof:name":"Bank of the West",
    "wof:placetype":"venue"
},
  "geometry": {"coordinates":[-104.940684,39.667265],"type":"Point"}
}