{
  "type": "Feature",
  "properties": {
    "iso:country":"US",
    "sg:address":"100 Bellview Dr",
    "sg:city":"Rock Springs",
    "sg:classifiers":[
        {
            "category":"Home & Garden",
            "subcategory":"Building Materials",
            "type":"Retail Goods"
        }
    ],
    "sg:phone":"+1 307 362 2226",
    "sg:postcode":"82901",
    "sg:province":"CO",
    "sg:tags":[
        "glass",
        "window",
        "plate"
    ],
    "wof:name":"Ted's Body & Paint Shop",
    "wof:placetype":"venue"
},
  "geometry": {"coordinates":[-109.22748,41.59701],"type":"Point"}
}