{
  "type": "Feature",
  "properties": {
    "addr:full":"365 Main St Walden CO 80480",
    "addr:housenumber":"365",
    "addr:postcode":"80480",
    "addr:street":"Main St",
    "iso:country":"US",
    "sg:address":"365 Main St",
    "sg:city":"Walden",
    "sg:classifiers":[
        {
            "category":"Travel",
            "subcategory":"Hotels & Motels",
            "type":"Entertainment"
        }
    ],
    "sg:phone":"+1 970 723 4680",
    "sg:postcode":"80480",
    "sg:province":"CO",
    "wof:name":"Round Up Motel",
    "wof:placetype":"venue"
},
  "geometry": {"coordinates":[-106.281998,40.732096],"type":"Point"}
}