{
  "type": "Feature",
  "properties": {
    "addr:full":"7652 S Johnson St Littleton CO 80127",
    "addr:housenumber":"7652",
    "addr:postcode":"80127",
    "addr:street":"S Johnson St",
    "iso:country":"US",
    "sg:address":"7652 S Johnson St",
    "sg:city":"Littleton",
    "sg:classifiers":[
        {
            "category":"Banks & Credit Unions",
            "subcategory":"Investment Brokerage",
            "type":"Services"
        }
    ],
    "sg:phone":"+1 303 948 2194",
    "sg:postcode":"80127",
    "sg:province":"CO",
    "sg:tags":[
        "advisory",
        "financial"
    ],
    "wof:name":"Toucan Financial Group Inc",
    "wof:placetype":"venue"
},
  "geometry": {"coordinates":[-105.109043,39.578142],"type":"Point"}
}