{
  "type": "Feature",
  "properties": {
    "addr:full":"2001 Kent Ct Fort Collins CO 80526",
    "addr:housenumber":"2001",
    "addr:postcode":"80526",
    "addr:street":"Kent Ct",
    "iso:country":"US",
    "sg:address":"2001 Kent Ct",
    "sg:city":"Fort Collins",
    "sg:classifiers":[
        {
            "category":"Building & Trades",
            "subcategory":"Construction",
            "type":"Services"
        }
    ],
    "sg:phone":"+1 970 223 4203",
    "sg:postcode":"80526",
    "sg:province":"CO",
    "sg:tags":[
        "contractor"
    ],
    "wof:name":"Kitchen Solvers",
    "wof:placetype":"venue"
},
  "geometry": {"coordinates":[-105.114654,40.539528],"type":"Point"}
}