{
  "type": "Feature",
  "properties": {
    "addr:full":"410 N Coffman Ln Olathe CO 81425",
    "addr:housenumber":"410",
    "addr:postcode":"81425",
    "addr:street":"N Coffman Ln",
    "iso:country":"US",
    "sg:address":"410 N Coffman Ln",
    "sg:city":"Olathe",
    "sg:classifiers":[
        {
            "category":"Building & Trades",
            "subcategory":"Electrical",
            "type":"Services"
        }
    ],
    "sg:phone":"+1 970 240 4202",
    "sg:postcode":"81425",
    "sg:province":"CO",
    "sg:tags":[
        "electric",
        "contractor"
    ],
    "wof:name":"A A Electric",
    "wof:placetype":"venue"
},
  "geometry": {"coordinates":[-107.993498,38.611432],"type":"Point"}
}