{
  "type": "Feature",
  "properties": {
    "addr:full":"1425 Lawton Ln Fort Collins CO 80524",
    "addr:housenumber":"1425",
    "addr:postcode":"80524",
    "addr:street":"Lawton Ln",
    "iso:country":"US",
    "sg:address":"1425 Lawton Ln",
    "sg:city":"Fort Collins",
    "sg:classifiers":[
        {
            "category":"Building & Trades",
            "subcategory":"Plumbing",
            "type":"Services"
        }
    ],
    "sg:phone":"+1 970 493 4355",
    "sg:postcode":"80524",
    "sg:province":"CO",
    "sg:tags":[
        "plumbing",
        "heating",
        "contractor"
    ],
    "wof:name":"Bershinsky Plumbing & Heating",
    "wof:placetype":"venue"
},
  "geometry": {"coordinates":[-105.09947099999999,40.610869],"type":"Point"}
}