{
  "type": "Feature",
  "properties": {
    "iso:country":"US",
    "sg:address":"317 N Main St",
    "sg:city":"Pueblo",
    "sg:classifiers":[
        {
            "category":"Professional",
            "type":"Services"
        }
    ],
    "sg:phone":"+1 719 595 0483",
    "sg:postcode":"81003",
    "sg:province":"CO",
    "sg:tags":[
        "establishment"
    ],
    "wof:name":"TPA",
    "wof:placetype":"venue"
},
  "geometry": {"coordinates":[-104.608671,38.270045],"type":"Point"}
}