{
  "type": "Feature",
  "properties": {
    "addr:full":"327 Main St Antonito NM 81120",
    "addr:housenumber":"327",
    "addr:postcode":"81120",
    "addr:street":"Main St",
    "iso:country":"US",
    "sg:address":"327 Main St",
    "sg:city":"Antonito",
    "sg:classifiers":[
        {
            "category":"Shopping",
            "subcategory":"Pharmacy",
            "type":"Retail Goods"
        }
    ],
    "sg:phone":"+1 719 376 5450",
    "sg:postcode":"81120",
    "sg:province":"NM",
    "wof:name":"Peoples Drug Stores",
    "wof:placetype":"venue"
},
  "geometry": {"coordinates":[-106.00870500000001,37.074724],"type":"Point"}
}