{
  "type": "Feature",
  "properties": {
    "iso:country":"US",
    "sg:address":"736 Pearl St",
    "sg:city":"Boulder",
    "sg:classifiers":[
        {
            "category":"Organizations",
            "subcategory":"Non-profit Organization",
            "type":"Services"
        }
    ],
    "sg:phone":"+1 303 546 6514",
    "sg:postcode":"80302",
    "sg:province":"CO",
    "sg:website":"www.beertown.org",
    "wof:name":"Great American Beer Festival",
    "wof:placetype":"venue"
},
  "geometry": {"coordinates":[-105.286531,40.016532],"type":"Point"}
}