{
  "type": "Feature",
  "properties": {
    "addr:full":"9602 E Arapahoe Rd Greenwood Vlg CO 80112",
    "addr:housenumber":"9602",
    "addr:postcode":"co 80112",
    "addr:street":"E Arapahoe Rd",
    "iso:country":"US",
    "sg:address":"9602 E Arapahoe Rd",
    "sg:city":"Greenwood Vlg",
    "sg:classifiers":[
        {
            "category":"Food & Beverages",
            "subcategory":"Specialty",
            "type":"Retail Goods"
        }
    ],
    "sg:phone":"+1 303 397 6986",
    "sg:postcode":"80112",
    "sg:province":"CO",
    "sg:tags":[
        "tea",
        "coffee"
    ],
    "wof:name":"Peaberry Coffee",
    "wof:placetype":"venue"
},
  "geometry": {"coordinates":[-104.877202,39.594958],"type":"Point"}
}