{
  "type": "Feature",
  "properties": {
    "iso:country":"US",
    "sg:address":"4407 Co Rd 44",
    "sg:city":"Johnstown",
    "sg:classifiers":[
        {
            "category":"Building & Trades",
            "subcategory":"Construction",
            "type":"Services"
        }
    ],
    "sg:phone":"+1 970 532 0390",
    "sg:postcode":"80534",
    "sg:province":"CO",
    "sg:tags":[
        "marking",
        "maintenance",
        "parking"
    ],
    "wof:name":"A-1 Pavement MARKING LLC",
    "wof:placetype":"venue"
},
  "geometry": {"coordinates":[-104.97090799999999,40.306609],"type":"Point"}
}