{
  "type": "Feature",
  "properties": {
    "iso:country":"US",
    "sg:address":"107 W Grand St",
    "sg:city":"La Veta",
    "sg:classifiers":[
        {
            "category":"Building & Trades",
            "subcategory":"Construction",
            "type":"Services"
        }
    ],
    "sg:phone":"+1 719 742 0275",
    "sg:postcode":"81055",
    "sg:province":"CO",
    "sg:tags":[
        "contractor"
    ],
    "wof:name":"Hockett Fencing Service",
    "wof:placetype":"venue"
},
  "geometry": {"coordinates":[-105.008954,37.503663],"type":"Point"}
}