{
  "type": "Feature",
  "properties": {
    "iso:country":"US",
    "sg:address":"2147 Fremont Dr",
    "sg:city":"Canon City",
    "sg:classifiers":[
        {
            "category":"Restaurant",
            "type":"Food & Drink"
        }
    ],
    "sg:menulink":"http://www.allmenus.com/co/canon-city/124259-quiznos-sub/menu/",
    "sg:phone":"+1 719 275 4558",
    "sg:postcode":"81212",
    "sg:province":"CO",
    "sg:tags":[
        "wrap",
        "american",
        "sandwich"
    ],
    "wof:name":"Quiznos Sub",
    "wof:placetype":"venue"
},
  "geometry": {"coordinates":[-105.216707,38.448184],"type":"Point"}
}