{
  "type": "Feature",
  "properties": {
    "addr:full":"2725 Lowell Boulevard Denver CO 80211",
    "addr:housenumber":"2725",
    "addr:postcode":"80211",
    "addr:street":"Lowell Boulevard",
    "iso:country":"US",
    "sg:address":"2725 Lowell Boulevard",
    "sg:city":"Denver",
    "sg:classifiers":[
        {
            "category":"Professional",
            "subcategory":"Lawyer & Legal Services",
            "type":"Services"
        }
    ],
    "sg:phone":"+1 303 934 1750",
    "sg:postcode":"80211",
    "sg:province":"CO",
    "wof:name":"Salzberg Marc",
    "wof:placetype":"venue"
},
  "geometry": {"coordinates":[-105.03471,39.75645],"type":"Point"}
}