{
  "type": "Feature",
  "properties": {
    "iso:country":"US",
    "sg:address":"8110 Ouray Dr",
    "sg:city":"Longmont",
    "sg:classifiers":[
        {
            "category":"Farming",
            "subcategory":"Livestock Farm",
            "type":"Manufacturing & Wholesale Goods"
        }
    ],
    "sg:phone":"+1 303 776 2318",
    "sg:postcode":"80503",
    "sg:province":"CO",
    "sg:tags":[
        "beef",
        "feedlot",
        "cattle"
    ],
    "wof:name":"Behrmann Farms",
    "wof:placetype":"venue"
},
  "geometry": {"coordinates":[-105.234949,40.123328],"type":"Point"}
}