{
  "type": "Feature",
  "properties": {
    "addr:full":"300 Puppy Smith St Aspen CO 81611",
    "addr:housenumber":"300",
    "addr:postcode":"81611",
    "addr:street":"Puppy Smith St",
    "iso:country":"US",
    "sg:address":"300 Puppy Smith St",
    "sg:city":"Aspen",
    "sg:classifiers":[
        {
            "category":"Cinema",
            "subcategory":"Movie Rental",
            "type":"Entertainment"
        }
    ],
    "sg:phone":"+1 970 920 4457",
    "sg:postcode":"81611",
    "sg:province":"CO",
    "sg:tags":[
        "leasing",
        "video",
        "disc",
        "tape"
    ],
    "wof:name":"Take Two Video",
    "wof:placetype":"venue"
},
  "geometry": {"coordinates":[-106.81858800000001,39.192325],"type":"Point"}
}