{
  "type": "Feature",
  "properties": {
    "iso:country":"US",
    "sg:address":"5748 S College Ave",
    "sg:city":"Fort Collins",
    "sg:classifiers":[
        {
            "category":"Home & Garden",
            "subcategory":"Home Furnishings",
            "type":"Retail Goods"
        }
    ],
    "sg:phone":"+1 970 229 5933",
    "sg:postcode":"80525",
    "sg:province":"CO",
    "wof:name":"Scherrer Molly",
    "wof:placetype":"venue"
},
  "geometry": {"coordinates":[-105.07731800000001,40.508028],"type":"Point"}
}