{
  "type": "Feature",
  "properties": {
    "iso:country":"US",
    "sg:address":"32214 Ellingwood Trl",
    "sg:city":"Evergreen",
    "sg:classifiers":[
        {
            "category":"Shopping",
            "subcategory":"Florist",
            "type":"Retail Goods"
        }
    ],
    "sg:phone":"+1 303 679 0064",
    "sg:postcode":"80439",
    "sg:province":"CO",
    "wof:name":"Petals On The Parkway Inc",
    "wof:placetype":"venue"
},
  "geometry": {"coordinates":[-105.365708,39.68511],"type":"Point"}
}