{
  "type": "Feature",
  "properties": {
    "addr:full":"925 Weiss Dr Steamboat Springs CO 80487",
    "addr:housenumber":"925",
    "addr:postcode":"80487",
    "addr:street":"Weiss Dr",
    "iso:country":"US",
    "sg:address":"925 Weiss Dr",
    "sg:city":"Steamboat Springs",
    "sg:classifiers":[
        {
            "category":"Government",
            "subcategory":"Office",
            "type":"Public Place"
        }
    ],
    "sg:phone":"+1 970 879 1870",
    "sg:postcode":"80487",
    "sg:province":"CO",
    "sg:tags":[
        "ranger",
        "district"
    ],
    "wof:name":"Hahns Pk/Bears Ears Ranger Dst",
    "wof:placetype":"venue"
},
  "geometry": {"coordinates":[-106.816073,40.448493],"type":"Point"}
}