{
  "type": "Feature",
  "properties": {
    "iso:country":"US",
    "sg:address":"2695 W 92nd Ave",
    "sg:city":"Denver",
    "sg:classifiers":[
        {
            "category":"Bars & Pubs",
            "type":"Food & Drink"
        }
    ],
    "sg:phone":"+1 303 412 0257",
    "sg:postcode":"80260",
    "sg:province":"CO",
    "sg:tags":[
        "drinking"
    ],
    "wof:name":"One Leg Johnnys Bar & Grill",
    "wof:placetype":"venue"
},
  "geometry": {"coordinates":[-105.020495,39.86358],"type":"Point"}
}