{
  "type": "Feature",
  "properties": {
    "addr:full":"320 Jersey St Denver CO 80220",
    "addr:housenumber":"320",
    "addr:postcode":"80220",
    "addr:street":"Jersey St",
    "iso:country":"US",
    "sg:address":"320 Jersey St",
    "sg:city":"Denver",
    "sg:classifiers":[
        {
            "category":"Banks & Credit Unions",
            "subcategory":"Financial Services",
            "type":"Services"
        }
    ],
    "sg:phone":"+1 303 322 3186",
    "sg:postcode":"80220",
    "sg:province":"CO",
    "sg:tags":[
        "company",
        "holding"
    ],
    "wof:name":"Eav Holdings LLC",
    "wof:placetype":"venue"
},
  "geometry": {"coordinates":[-104.919231,39.72322],"type":"Point"}
}