{
  "type": "Feature",
  "properties": {
    "addr:full":"9480 Federal Blvd Denver CO 80260",
    "addr:housenumber":"9480",
    "addr:postcode":"80260",
    "addr:street":"Federal Blvd",
    "iso:country":"US",
    "sg:address":"9480 Federal Blvd",
    "sg:city":"Denver",
    "sg:classifiers":[
        {
            "category":"Retail",
            "subcategory":"Auto Repair",
            "type":"Services"
        }
    ],
    "sg:phone":"+1 303 426 4446",
    "sg:postcode":"80260",
    "sg:province":"CO",
    "sg:tags":[
        "automobile",
        "lubrication"
    ],
    "wof:name":"Finish Line Express Lube",
    "wof:placetype":"venue"
},
  "geometry": {"coordinates":[-105.024923,39.867473],"type":"Point"}
}