{
  "type": "Feature",
  "properties": {
    "iso:country":"US",
    "sg:address":"7645 N Academy Blvd",
    "sg:city":"Colorado Springs",
    "sg:classifiers":[
        {
            "category":"Home & Garden",
            "subcategory":"Furniture",
            "type":"Retail Goods"
        }
    ],
    "sg:phone":"+1 719 548 1922",
    "sg:postcode":"80920",
    "sg:province":"CO",
    "wof:name":"Furniture Max Inc",
    "wof:placetype":"venue"
},
  "geometry": {"coordinates":[-104.79989999999999,38.942573],"type":"Point"}
}