{
  "type": "Feature",
  "properties": {
    "addr:full":"1660 Albion St Denver CO 80220",
    "addr:housenumber":"1660",
    "addr:postcode":"80220",
    "addr:street":"Albion St",
    "iso:country":"US",
    "sg:address":"1660 Albion St",
    "sg:city":"Denver",
    "sg:classifiers":[
        {
            "category":"Health Services",
            "subcategory":"Clinic",
            "type":"Services"
        }
    ],
    "sg:phone":"+1 303 759 5847",
    "sg:postcode":"80220",
    "sg:province":"CO",
    "sg:tags":[
        "home"
    ],
    "wof:name":"Arcadia Temporary Health Care",
    "wof:placetype":"venue"
},
  "geometry": {"coordinates":[-104.93893799999999,39.74339],"type":"Point"}
}