{
  "type": "Feature",
  "properties": {
    "addr:full":"193 E Jefferson Ave Hayden CO 81639",
    "addr:housenumber":"193",
    "addr:postcode":"81639",
    "addr:street":"E Jefferson Ave",
    "iso:country":"US",
    "sg:address":"193 E Jefferson Ave",
    "sg:city":"Hayden",
    "sg:classifiers":[
        {
            "category":"Autos & Motor Vehicles",
            "subcategory":"Fuel & Gas Station",
            "type":"Retail Goods"
        }
    ],
    "sg:phone":"+1 970 276 3313",
    "sg:postcode":"81639",
    "sg:province":"CO",
    "sg:tags":[
        "oil"
    ],
    "wof:name":"Bear River Valley Co-Op",
    "wof:placetype":"venue"
},
  "geometry": {"coordinates":[-107.257925,40.495149],"type":"Point"}
}