{
  "type": "Feature",
  "properties": {
    "addr:full":"2874 S Shoshone St Englewood CO 80110",
    "addr:housenumber":"2874",
    "addr:postcode":"80110",
    "addr:street":"S Shoshone St",
    "iso:country":"US",
    "sg:address":"2874 S Shoshone St",
    "sg:city":"Englewood",
    "sg:classifiers":[
        {
            "category":"Building & Trades",
            "subcategory":"Construction",
            "type":"Services"
        }
    ],
    "sg:phone":"+1 303 783 5474",
    "sg:postcode":"80110",
    "sg:province":"CO",
    "sg:tags":[
        "removal",
        "floor",
        "contractor"
    ],
    "wof:name":"Advanced Floor Removal Inc",
    "wof:placetype":"venue"
},
  "geometry": {"coordinates":[-105.00978499999999,39.667306],"type":"Point"}
}