{
  "type": "Feature",
  "properties": {
    "iso:country":"US",
    "sg:address":"280 E 64th Ave",
    "sg:city":"Denver",
    "sg:classifiers":[
        {
            "category":"Retail",
            "subcategory":"Repair Shop",
            "type":"Services"
        },
        {
            "category":"Building & Trades",
            "subcategory":"Construction",
            "type":"Services"
        }
    ],
    "sg:phone":"+1 303 657 1233",
    "sg:postcode":"80221",
    "sg:province":"CO",
    "sg:tags":[
        "fabricator",
        "metal",
        "welding"
    ],
    "sg:website":"www.roadrunnerfabrication.com",
    "wof:name":"Road Runner Fabrication",
    "wof:placetype":"venue"
},
  "geometry": {"coordinates":[-104.984835,39.812685],"type":"Point"}
}