{
  "type": "Feature",
  "properties": {
    "iso:country":"US",
    "sg:address":"4195 Oneida St",
    "sg:city":"Denver",
    "sg:classifiers":[
        {
            "category":"Professional",
            "subcategory":"Business Services",
            "type":"Services"
        }
    ],
    "sg:phone":"+1 303 393 9585",
    "sg:postcode":"80216",
    "sg:province":"CO",
    "sg:tags":[
        "embroidery"
    ],
    "wof:name":"Designer Threads Custom Embrdr",
    "wof:placetype":"venue"
},
  "geometry": {"coordinates":[-104.908287,39.775055],"type":"Point"}
}