{
  "type": "Feature",
  "properties": {
    "addr:full":"3234 W Girard Ave Englewood CO 80110",
    "addr:housenumber":"3234",
    "addr:postcode":"80110",
    "addr:street":"W Girard Ave",
    "iso:country":"US",
    "sg:address":"3234 W Girard Ave",
    "sg:city":"Englewood",
    "sg:classifiers":[
        {
            "category":"Building & Trades",
            "subcategory":"Electrical",
            "type":"Services"
        }
    ],
    "sg:phone":"+1 303 781 7507",
    "sg:postcode":"80110",
    "sg:province":"CO",
    "sg:tags":[
        "electric",
        "contractor"
    ],
    "wof:name":"Communication Wire Controls",
    "wof:placetype":"venue"
},
  "geometry": {"coordinates":[-105.02922700000001,39.655229],"type":"Point"}
}