{
  "type": "Feature",
  "properties": {
    "iso:country":"US",
    "sg:address":"200 W Oak St",
    "sg:city":"Fort Collins",
    "sg:classifiers":[
        {
            "category":"Building & Trades",
            "subcategory":"Construction",
            "type":"Services"
        }
    ],
    "sg:phone":"+1 970 498 5740",
    "sg:postcode":"80521",
    "sg:province":"CO",
    "sg:tags":[
        "grading",
        "contractor"
    ],
    "wof:name":"Larimer Cnty Public Works Adm",
    "wof:placetype":"venue"
},
  "geometry": {"coordinates":[-105.07987300000001,40.585602],"type":"Point"}
}