{
  "type": "Feature",
  "properties": {
    "addr:full":"205 N Boundary St Woodland Park CO 80863",
    "addr:housenumber":"205",
    "addr:postcode":"80863",
    "addr:street":"N Boundary St",
    "iso:country":"US",
    "sg:address":"205 N Boundary St",
    "sg:city":"Woodland Park",
    "sg:classifiers":[
        {
            "category":"Organizations",
            "subcategory":"Religious Organization",
            "type":"Services"
        }
    ],
    "sg:phone":"+1 719 687 6528",
    "sg:postcode":"80863",
    "sg:province":"CO",
    "sg:tags":[
        "church"
    ],
    "wof:name":"Dayspring Christian Fellowship",
    "wof:placetype":"venue"
},
  "geometry": {"coordinates":[-105.04849,38.995359],"type":"Point"}
}