{
  "type": "Feature",
  "properties": {
    "iso:country":"US",
    "sg:address":"613 Co Rd 264",
    "sg:city":"Rifle",
    "sg:classifiers":[
        {
            "category":"Utilities",
            "subcategory":"Natural Gas",
            "type":"Services"
        }
    ],
    "sg:phone":"+1 970 625 1017",
    "sg:postcode":"81650",
    "sg:province":"CO",
    "wof:name":"Questar Corporation",
    "wof:placetype":"venue"
},
  "geometry": {"coordinates":[-107.825616,39.529563],"type":"Point"}
}