{
  "type": "Feature",
  "properties": {
    "iso:country":"US",
    "sg:address":"6890 Tower Rd",
    "sg:city":"Denver",
    "sg:classifiers":[
        {
            "category":"Travel",
            "subcategory":"Hotels & Motels",
            "type":"Entertainment"
        }
    ],
    "sg:phone":"+1 800 424 6423",
    "sg:postcode":"80249",
    "sg:province":"CO",
    "sg:website":"http://www.qualityinn.com/hotel-denver-colorado-CO235?promo=yplocal",
    "wof:name":"Quality Inn & Suites Denver International Airport",
    "wof:placetype":"venue"
},
  "geometry": {"coordinates":[-104.771884,39.821723],"type":"Point"}
}