{
  "type": "Feature",
  "properties": {
    "iso:country":"US",
    "sg:address":"102 E Charlotte St",
    "sg:city":"Johnstown",
    "sg:classifiers":[
        {
            "category":"Personal",
            "subcategory":"Tanning Parlor",
            "type":"Services"
        }
    ],
    "sg:phone":"+1 970 587 4811",
    "sg:postcode":"80534",
    "sg:province":"CO",
    "sg:tags":[
        "salon"
    ],
    "wof:name":"Rejuvenations",
    "wof:placetype":"venue"
},
  "geometry": {"coordinates":[-104.906173,40.335998],"type":"Point"}
}