{
  "type": "Feature",
  "properties": {
    "iso:country":"US",
    "sg:address":"6472 S Quebec St",
    "sg:city":"Centennial",
    "sg:classifiers":[
        {
            "category":"Insurance",
            "subcategory":"Insurance Agent",
            "type":"Services"
        }
    ],
    "sg:phone":"+1 303 220 1194",
    "sg:postcode":"80111",
    "sg:province":"CO",
    "sg:tags":[
        "consultant"
    ],
    "wof:name":"Publishers Research Corp",
    "wof:placetype":"venue"
},
  "geometry": {"coordinates":[-104.904077,39.599461],"type":"Point"}
}