{
  "type": "Feature",
  "properties": {
    "addr:full":"5680 Greenwood Plaza Blvd Englewood CO 80111",
    "addr:housenumber":"5680",
    "addr:postcode":"80111",
    "addr:street":"Greenwood Plaza Blvd",
    "iso:country":"US",
    "sg:address":"5680 Greenwood Plaza Blvd",
    "sg:city":"Englewood",
    "sg:classifiers":[
        {
            "category":"Manufacturing",
            "subcategory":"Printing",
            "type":"Manufacturing & Wholesale Goods"
        }
    ],
    "sg:phone":"+1 303 741 2901",
    "sg:postcode":"80111",
    "sg:province":"CO",
    "sg:tags":[
        "magazine",
        "publishing"
    ],
    "wof:name":"Primedia",
    "wof:placetype":"venue"
},
  "geometry": {"coordinates":[-104.899466,39.610994],"type":"Point"}
}