{
  "type": "Feature",
  "properties": {
    "addr:full":"368 N Chico Rd Pueblo CO 81006",
    "addr:housenumber":"368",
    "addr:postcode":"81006",
    "addr:street":"N Chico Rd",
    "iso:country":"US",
    "sg:address":"368 N Chico Rd",
    "sg:city":"Pueblo",
    "sg:classifiers":[
        {
            "category":"Farming",
            "subcategory":"Farm & Veterinary Services",
            "type":"Manufacturing & Wholesale Goods"
        }
    ],
    "sg:phone":"+1 719 948 9068",
    "sg:postcode":"81006",
    "sg:province":"CO",
    "sg:tags":[
        "livestock"
    ],
    "wof:name":"Owl Canyon LLC",
    "wof:placetype":"venue"
},
  "geometry": {"coordinates":[-104.398842,38.278466],"type":"Point"}
}