{
  "type": "Feature",
  "properties": {
    "addr:full":"208 S Wilcox St Castle Rock CO 80104",
    "addr:housenumber":"208",
    "addr:postcode":"80104",
    "addr:street":"S Wilcox St",
    "iso:country":"US",
    "sg:address":"208 S Wilcox St",
    "sg:city":"Castle Rock",
    "sg:classifiers":[
        {
            "category":"Home & Garden",
            "subcategory":"Furniture",
            "type":"Retail Goods"
        }
    ],
    "sg:phone":"+1 303 688 0328",
    "sg:postcode":"80104",
    "sg:province":"CO",
    "sg:tags":[
        "builder",
        "custom"
    ],
    "wof:name":"Brittany Hill LTD Custom Hand",
    "wof:placetype":"venue"
},
  "geometry": {"coordinates":[-104.861335,39.367221],"type":"Point"}
}