{
  "type": "Feature",
  "properties": {
    "iso:country":"US",
    "sg:address":"220 Virginia Dr",
    "sg:city":"Estes Park",
    "sg:classifiers":[
        {
            "category":"Travel",
            "subcategory":"Hotels & Motels",
            "type":"Entertainment"
        }
    ],
    "sg:phone":"+1 970 577 1229",
    "sg:postcode":"80517",
    "sg:province":"CO",
    "sg:tags":[
        "resort"
    ],
    "wof:name":"Epco",
    "wof:placetype":"venue"
},
  "geometry": {"coordinates":[-105.521981,40.377846],"type":"Point"}
}