{
  "type": "Feature",
  "properties": {
    "addr:full":"3021 S Tejon St Englewood CO 80110",
    "addr:housenumber":"3021",
    "addr:postcode":"80110",
    "addr:street":"S Tejon St",
    "iso:country":"US",
    "sg:address":"3021 S Tejon St",
    "sg:city":"Englewood",
    "sg:classifiers":[
        {
            "category":"Building & Trades",
            "subcategory":"Electrical",
            "type":"Services"
        },
        {
            "category":"Building & Trades",
            "subcategory":"Plumbing",
            "type":"Services"
        }
    ],
    "sg:phone":"+1 303 789 1700",
    "sg:postcode":"80110",
    "sg:province":"CO",
    "sg:tags":[
        "heating",
        "contractor",
        "air",
        "system",
        "conditioning"
    ],
    "sg:website":"www.msicolorado.com",
    "wof:name":"Mechanical Solutions Inc",
    "wof:placetype":"venue"
},
  "geometry": {"coordinates":[-105.01115299999999,39.660871],"type":"Point"}
}