{
  "type": "Feature",
  "properties": {
    "iso:country":"US",
    "sg:address":"1515 Wazee St Ste D",
    "sg:city":"Denver",
    "sg:classifiers":[
        {
            "category":"Health Services",
            "subcategory":"Doctor",
            "type":"Services"
        }
    ],
    "sg:phone":"+1 303 534 9550",
    "sg:postcode":"80202",
    "sg:province":"CO",
    "sg:tags":[
        "medicine",
        "internal"
    ],
    "wof:name":"Thomas Pulk, MD",
    "wof:placetype":"venue"
},
  "geometry": {"coordinates":[-105.000868,39.750714],"type":"Point"}
}