{
  "type": "Feature",
  "properties": {
    "addr:full":"8500 W Bowles Ave Littleton CO 80123",
    "addr:housenumber":"8500",
    "addr:postcode":"80123",
    "addr:street":"W Bowles Ave",
    "iso:country":"US",
    "sg:address":"8500 W Bowles Ave",
    "sg:city":"Littleton",
    "sg:classifiers":[
        {
            "category":"Banks & Credit Unions",
            "subcategory":"Bank",
            "type":"Services"
        }
    ],
    "sg:phone":"+1 303 904 3091",
    "sg:postcode":"80123",
    "sg:province":"CO",
    "sg:tags":[
        "loan",
        "real estate"
    ],
    "wof:name":"Colorado Professional Mortgage",
    "wof:placetype":"venue"
},
  "geometry": {"coordinates":[-105.095546,39.609689],"type":"Point"}
}