{
  "type": "Feature",
  "properties": {
    "iso:country":"US",
    "sg:address":"6550 S Yosemite St",
    "sg:city":"Englewood",
    "sg:classifiers":[
        {
            "category":"Building & Trades",
            "subcategory":"Equipment Rental",
            "type":"Services"
        }
    ],
    "sg:phone":"+1 303 770 2980",
    "sg:postcode":"80111",
    "sg:province":"CO",
    "sg:tags":[
        "yard"
    ],
    "wof:name":"All Seasons Rent-All",
    "wof:placetype":"venue"
},
  "geometry": {"coordinates":[-104.888828,39.597052],"type":"Point"}
}