{
  "type": "Feature",
  "properties": {
    "iso:country":"US",
    "sg:address":"4641 W 109th Pl",
    "sg:city":"Westminster",
    "sg:classifiers":[
        {
            "category":"Banks & Credit Unions",
            "subcategory":"Bank",
            "type":"Services"
        }
    ],
    "sg:phone":"+1 303 466 7886",
    "sg:postcode":"80031",
    "sg:province":"CO",
    "sg:tags":[
        "loan",
        "real estate"
    ],
    "wof:name":"Clarion Mortgage",
    "wof:placetype":"venue"
},
  "geometry": {"coordinates":[-105.04765399999999,39.895192],"type":"Point"}
}