{
  "type": "Feature",
  "properties": {
    "iso:country":"US",
    "sg:address":"60 S 8th St",
    "sg:city":"Carbondale",
    "sg:classifiers":[
        {
            "category":"Health Services",
            "subcategory":"Doctor",
            "type":"Services"
        }
    ],
    "sg:phone":"+1 970 963 3013",
    "sg:postcode":"81623",
    "sg:province":"CO",
    "sg:tags":[
        "dentist"
    ],
    "wof:name":"Today's Family Dental",
    "wof:placetype":"venue"
},
  "geometry": {"coordinates":[-107.215476,39.400154],"type":"Point"}
}