{
  "type": "Feature",
  "properties": {
    "iso:country":"US",
    "sg:address":"5587 S Hill St",
    "sg:city":"Littleton",
    "sg:classifiers":[
        {
            "category":"Shopping",
            "subcategory":"Computers & Home Electronics",
            "type":"Retail Goods"
        }
    ],
    "sg:phone":"+1 303 738 8222",
    "sg:postcode":"80120",
    "sg:province":"CO",
    "sg:tags":[
        "system"
    ],
    "wof:name":"Digital Vision & Sound",
    "wof:placetype":"venue"
},
  "geometry": {"coordinates":[-105.014003,39.616684],"type":"Point"}
}