{
  "type": "Feature",
  "properties": {
    "iso:country":"US",
    "sg:address":"7150 S Platte Canyon Rd",
    "sg:city":"Littleton",
    "sg:classifiers":[
        {
            "category":"Wholesale",
            "subcategory":"Sporting Goods",
            "type":"Manufacturing & Wholesale Goods"
        }
    ],
    "sg:phone":"+1 303 933 3142",
    "sg:postcode":"80128",
    "sg:province":"CO",
    "sg:tags":[
        "c",
        "parts",
        "representative",
        "for",
        "manufacturer"
    ],
    "wof:name":"Wee House of Wood",
    "wof:placetype":"venue"
},
  "geometry": {"coordinates":[-105.048942,39.586166],"type":"Point"}
}