{
  "type": "Feature",
  "properties": {
    "iso:country":"US",
    "sg:address":"530 Compton St",
    "sg:city":"Broomfield",
    "sg:classifiers":[
        {
            "category":"Building & Trades",
            "subcategory":"Construction",
            "type":"Services"
        }
    ],
    "sg:phone":"+1 303 533 1458",
    "sg:postcode":"80020",
    "sg:province":"CO",
    "wof:name":"Kiewit Western Co",
    "wof:placetype":"venue"
},
  "geometry": {"coordinates":[-105.098754,39.925363],"type":"Point"}
}