{
  "type": "Feature",
  "properties": {
    "iso:country":"US",
    "sg:address":"1765 Gillaspie Dr",
    "sg:city":"Boulder",
    "sg:classifiers":[
        {
            "category":"Professional",
            "type":"Services"
        }
    ],
    "sg:phone":"+1 303 494 1850",
    "sg:postcode":"80305",
    "sg:province":"CO",
    "sg:tags":[
        "establishment"
    ],
    "sg:website":"www.salsacruise.com",
    "wof:name":"Segal Hillel",
    "wof:placetype":"venue"
},
  "geometry": {"coordinates":[-105.24858,39.970204],"type":"Point"}
}