{
  "type": "Feature",
  "properties": {
    "iso:country":"US",
    "sg:address":"6472 W 20th Avenue",
    "sg:city":"Lakewood",
    "sg:classifiers":[
        {
            "category":"Personal",
            "subcategory":"Beauty Salon",
            "type":"Services"
        }
    ],
    "sg:phone":"+1 303 237 0208",
    "sg:postcode":"80214",
    "sg:province":"CO",
    "sg:tags":[
        "hair"
    ],
    "wof:name":"Shear Pleasure On West 20 Ave",
    "wof:placetype":"venue"
},
  "geometry": {"coordinates":[-105.068078,39.747726],"type":"Point"}
}