{
  "type": "Feature",
  "properties": {
    "iso:country":"US",
    "sg:address":"42218 Hwy 133",
    "sg:city":"Paonia",
    "sg:classifiers":[
        {
            "category":"Wholesale",
            "subcategory":"Jewelry",
            "type":"Manufacturing & Wholesale Goods"
        }
    ],
    "sg:phone":"+1 970 527 6368",
    "sg:postcode":"81428",
    "sg:province":"CO",
    "sg:tags":[
        "stone"
    ],
    "wof:name":"Dragons Designs",
    "wof:placetype":"venue"
},
  "geometry": {"coordinates":[-107.565247,38.900248],"type":"Point"}
}