{
  "type": "Feature",
  "properties": {
    "addr:full":"3425 Belcaro Ln Denver CO 80209",
    "addr:housenumber":"3425",
    "addr:postcode":"80209",
    "addr:street":"Belcaro Ln",
    "iso:country":"US",
    "sg:address":"3425 Belcaro Ln",
    "sg:city":"Denver",
    "sg:classifiers":[
        {
            "category":"Retail",
            "subcategory":"Repair Shop",
            "type":"Services"
        }
    ],
    "sg:phone":"+1 303 722 4006",
    "sg:postcode":"80209",
    "sg:province":"CO",
    "sg:tags":[
        "instrument",
        "musical"
    ],
    "wof:name":"Pipe Organ Sales & Service",
    "wof:placetype":"venue"
},
  "geometry": {"coordinates":[-104.947821,39.703196],"type":"Point"}
}