{
  "type": "Feature",
  "properties": {
    "iso:country":"US",
    "sg:address":"5624 N 115th St",
    "sg:city":"Longmont",
    "sg:classifiers":[
        {
            "category":"Building & Trades",
            "subcategory":"Construction",
            "type":"Services"
        }
    ],
    "sg:phone":"+1 303 652 2429",
    "sg:postcode":"80504",
    "sg:province":"CO",
    "sg:tags":[
        "nonresidential"
    ],
    "wof:name":"Ted Morton Construction",
    "wof:placetype":"venue"
},
  "geometry": {"coordinates":[-105.083764,40.079414],"type":"Point"}
}