{
  "type": "Feature",
  "properties": {
    "iso:country":"US",
    "sg:address":"2702 Imperial Ridge Dr",
    "sg:city":"Loveland",
    "sg:classifiers":[
        {
            "category":"Building & Trades",
            "subcategory":"Construction",
            "type":"Services"
        }
    ],
    "sg:phone":"+1 970 622 8164",
    "sg:postcode":"80537",
    "sg:province":"CO",
    "sg:tags":[
        "house"
    ],
    "wof:name":"Trunette Property & Const",
    "wof:placetype":"venue"
},
  "geometry": {"coordinates":[-105.115275,40.404156],"type":"Point"}
}