{
  "type": "Feature",
  "properties": {
    "iso:country":"US",
    "sg:address":"1647 Maxwell St",
    "sg:city":"Colorado Springs",
    "sg:classifiers":[
        {
            "category":"Professional",
            "type":"Services"
        }
    ],
    "sg:phone":"+1 719 392 0359",
    "sg:postcode":"80906",
    "sg:province":"CO",
    "sg:tags":[
        "establishment"
    ],
    "wof:name":"Michaelpierce",
    "wof:placetype":"venue"
},
  "geometry": {"coordinates":[-104.765789,38.762138],"type":"Point"}
}