{
  "type": "Feature",
  "properties": {
    "iso:country":"US",
    "sg:address":"5411 Quebec Street",
    "sg:city":"Commerce City",
    "sg:classifiers":[
        {
            "category":"Restaurant",
            "type":"Food & Drink"
        }
    ],
    "sg:phone":"+1 303 287 2210",
    "sg:postcode":"80022",
    "sg:province":"CO",
    "sg:tags":[
        "mexican"
    ],
    "wof:name":"El Viva Villa",
    "wof:placetype":"venue"
},
  "geometry": {"coordinates":[-104.90362,39.794422],"type":"Point"}
}