{
  "type": "Feature",
  "properties": {
    "addr:full":"810 N 11th St Gunnison CO 81230",
    "addr:housenumber":"810",
    "addr:postcode":"81230",
    "addr:street":"N 11Th St",
    "iso:country":"US",
    "sg:address":"810 N 11th St",
    "sg:city":"Gunnison",
    "sg:classifiers":[
        {
            "category":"Organizations",
            "subcategory":"Religious Organization",
            "type":"Services"
        }
    ],
    "sg:phone":"+1 970 641 4640",
    "sg:postcode":"81230",
    "sg:province":"CO",
    "sg:tags":[
        "church"
    ],
    "wof:name":"Church Of Jesus Christ Of Lds",
    "wof:placetype":"venue"
},
  "geometry": {"coordinates":[-106.93602,38.554265],"type":"Point"}
}