{
  "type": "Feature",
  "properties": {
    "addr:full":"783 Glenarbor Cir Longmont CO 80501",
    "addr:housenumber":"783",
    "addr:postcode":"80501",
    "addr:street":"Glenarbor Cir",
    "iso:country":"US",
    "sg:address":"783 Glenarbor Cir",
    "sg:city":"Longmont",
    "sg:classifiers":[
        {
            "category":"Manufacturing",
            "subcategory":"Electronics",
            "type":"Manufacturing & Wholesale Goods"
        }
    ],
    "sg:phone":"+1 303 651 2009",
    "sg:postcode":"80501",
    "sg:province":"CO",
    "sg:tags":[
        "mfg",
        "boards",
        "circuit",
        "printed"
    ],
    "wof:name":"Tamara Schlagel Front Ran",
    "wof:placetype":"venue"
},
  "geometry": {"coordinates":[-105.074474,40.193947],"type":"Point"}
}