{
  "type": "Feature",
  "properties": {
    "addr:full":"120 Main St Breckenridge CO 80424",
    "addr:housenumber":"120",
    "addr:postcode":"80424",
    "addr:street":"Main St",
    "iso:country":"US",
    "sg:address":"120 Main St",
    "sg:city":"Breckenridge",
    "sg:classifiers":[
        {
            "category":"Building & Trades",
            "subcategory":"Cleaning & Sanitation",
            "type":"Services"
        }
    ],
    "sg:phone":"+1 970 453 6344",
    "sg:postcode":"80424",
    "sg:province":"CO",
    "sg:tags":[
        "butler",
        "maid"
    ],
    "wof:name":"SCI Management Co",
    "wof:placetype":"venue"
},
  "geometry": {"coordinates":[-106.046188,39.480669],"type":"Point"}
}