{
  "type": "Feature",
  "properties": {
    "iso:country":"US",
    "sg:address":"1875 W Victory Way",
    "sg:city":"Craig",
    "sg:classifiers":[
        {
            "category":"Autos & Motor Vehicles",
            "subcategory":"Auto Supplies",
            "type":"Retail Goods"
        }
    ],
    "sg:phone":"+1 970 824 6544",
    "sg:postcode":"81625",
    "sg:province":"CO",
    "sg:tags":[
        "automobile",
        "parts"
    ],
    "wof:name":"Auto Parts Of Craig",
    "wof:placetype":"venue"
},
  "geometry": {"coordinates":[-107.56881,40.514215],"type":"Point"}
}