{
  "type": "Feature",
  "properties": {
    "addr:full":"1613 Allison St Lakewood CO 80214",
    "addr:housenumber":"1613",
    "addr:postcode":"80214",
    "addr:street":"Allison St",
    "iso:country":"US",
    "sg:address":"1613 Allison St",
    "sg:city":"Lakewood",
    "sg:classifiers":[
        {
            "category":"Organizations",
            "subcategory":"Professional Association",
            "type":"Services"
        }
    ],
    "sg:phone":"+1 303 233 2516",
    "sg:postcode":"80214",
    "sg:province":"CO",
    "wof:name":"Greater Denver Area Gem Cncl",
    "wof:placetype":"venue"
},
  "geometry": {"coordinates":[-105.08614,39.740476],"type":"Point"}
}