{
  "type": "Feature",
  "properties": {
    "addr:full":"1215 9th St Rock Springs CO 82901",
    "addr:housenumber":"1215",
    "addr:postcode":"82901",
    "addr:street":"9Th St",
    "iso:country":"US",
    "sg:address":"1215 9th St",
    "sg:city":"Rock Springs",
    "sg:classifiers":[
        {
            "category":"Retail",
            "subcategory":"Laundry & Dry Cleaning",
            "type":"Services"
        }
    ],
    "sg:phone":"+1 307 382 6092",
    "sg:postcode":"82901",
    "sg:province":"CO",
    "sg:tags":[
        "garment",
        "coin",
        "agent"
    ],
    "wof:name":"9th Street Laundromat",
    "wof:placetype":"venue"
},
  "geometry": {"coordinates":[-109.212034,41.596187],"type":"Point"}
}