{
  "type": "Feature",
  "properties": {
    "iso:country":"US",
    "sg:address":"419 W Main St",
    "sg:city":"Trinidad",
    "sg:classifiers":[
        {
            "category":"Professional",
            "subcategory":"Business Services",
            "type":"Services"
        }
    ],
    "sg:phone":"+1 719 846 7633",
    "sg:postcode":"81082",
    "sg:province":"CO",
    "sg:tags":[
        "interior",
        "consultant",
        "design",
        "decorator"
    ],
    "wof:name":"Phoenix West Designs",
    "wof:placetype":"venue"
},
  "geometry": {"coordinates":[-104.50831700000001,37.167326],"type":"Point"}
}