{
  "type": "Feature",
  "properties": {
    "iso:country":"US",
    "sg:address":"1929 Lake Dr",
    "sg:city":"Larkspur",
    "sg:classifiers":[
        {
            "category":"Wholesale",
            "subcategory":"Groceries",
            "type":"Manufacturing & Wholesale Goods"
        }
    ],
    "sg:phone":"+1 303 681 2309",
    "sg:postcode":"80118",
    "sg:province":"CO",
    "sg:tags":[
        "canned",
        "soup"
    ],
    "wof:name":"Campbell Soup",
    "wof:placetype":"venue"
},
  "geometry": {"coordinates":[-104.921582,39.255286],"type":"Point"}
}