{
  "type": "Feature",
  "properties": {
    "iso:country":"US",
    "sg:address":"1746 S Lincoln St",
    "sg:city":"Denver",
    "sg:classifiers":[
        {
            "category":"Shopping",
            "subcategory":"Gifts & Souvenirs",
            "type":"Retail Goods"
        }
    ],
    "sg:phone":"+1 303 282 7455",
    "sg:postcode":"80210",
    "sg:province":"CO",
    "wof:name":"Poudre River Cards",
    "wof:placetype":"venue"
},
  "geometry": {"coordinates":[-104.986239,39.684813],"type":"Point"}
}