{
  "type": "Feature",
  "properties": {
    "addr:full":"3812 E Pikes Peak Ave Colorado Springs CO 80909",
    "addr:housenumber":"3812",
    "addr:postcode":"80909",
    "addr:street":"E Pikes Peak Ave",
    "iso:country":"US",
    "sg:address":"3812 E Pikes Peak Ave",
    "sg:city":"Colorado Springs",
    "sg:classifiers":[
        {
            "category":"Professional",
            "subcategory":"Credit Reporting & Collection",
            "type":"Services"
        }
    ],
    "sg:phone":"+1 719 574 1887",
    "sg:postcode":"80909",
    "sg:province":"CO",
    "sg:tags":[
        "agency"
    ],
    "wof:name":"Advanced Screening Research",
    "wof:placetype":"venue"
},
  "geometry": {"coordinates":[-104.75581,38.832011],"type":"Point"}
}