{
  "type": "Feature",
  "properties": {
    "addr:full":"4445 Eldridge St Golden CO 80403",
    "addr:housenumber":"4445",
    "addr:postcode":"80403",
    "addr:street":"Eldridge St",
    "iso:country":"US",
    "sg:address":"4445 Eldridge St",
    "sg:city":"Golden",
    "sg:classifiers":[
        {
            "category":"Building & Trades",
            "subcategory":"Construction",
            "type":"Services"
        }
    ],
    "sg:phone":"+1 303 238 2823",
    "sg:postcode":"80403",
    "sg:province":"CO",
    "sg:tags":[
        "house"
    ],
    "wof:name":"Liberty Building & Remodel",
    "wof:placetype":"venue"
},
  "geometry": {"coordinates":[-105.156814,39.781157],"type":"Point"}
}