{
  "type": "Feature",
  "properties": {
    "iso:country":"US",
    "sg:address":"1 Manitou Ave",
    "sg:city":"Manitou Springs",
    "sg:classifiers":[
        {
            "category":"Professional",
            "type":"Services"
        }
    ],
    "sg:phone":"+1 719 685 5094",
    "sg:postcode":"80829",
    "sg:province":"CO",
    "wof:name":"Glen Limmer",
    "wof:placetype":"venue"
},
  "geometry": {"coordinates":[-104.887449,38.856823],"type":"Point"}
}