{
  "type": "Feature",
  "properties": {
    "addr:full":"30 Manitou Ave Manitou Springs CO 80829",
    "addr:housenumber":"30",
    "addr:postcode":"80829",
    "addr:street":"Manitou Ave",
    "iso:country":"US",
    "sg:address":"30 Manitou Ave",
    "sg:city":"Manitou Springs",
    "sg:classifiers":[
        {
            "category":"Building & Trades",
            "subcategory":"Landscaping Services",
            "type":"Services"
        }
    ],
    "sg:phone":"+1 719 685 3373",
    "sg:postcode":"80829",
    "sg:province":"CO",
    "sg:tags":[
        "landscape",
        "contractor"
    ],
    "wof:name":"Lucky's Lawncare & Landscaping",
    "wof:placetype":"venue"
},
  "geometry": {"coordinates":[-104.890298,38.857359],"type":"Point"}
}