{
  "type": "Feature",
  "properties": {
    "addr:full":"500 W Bijou St Colorado Springs CO 80905",
    "addr:housenumber":"500",
    "addr:postcode":"80905",
    "addr:street":"W Bijou St",
    "iso:country":"US",
    "sg:address":"500 W Bijou St",
    "sg:city":"Colorado Springs",
    "sg:classifiers":[
        {
            "category":"Organizations",
            "subcategory":"Religious Organization",
            "type":"Services"
        }
    ],
    "sg:phone":"+1 719 633 4879",
    "sg:postcode":"80905",
    "sg:province":"CO",
    "sg:tags":[
        "church"
    ],
    "wof:name":"New Life Baptist Church",
    "wof:placetype":"venue"
},
  "geometry": {"coordinates":[-104.83593500000001,38.837012],"type":"Point"}
}