{
  "type": "Feature",
  "properties": {
    "addr:full":"1855 S Pitkin Ave Superior CO 80027",
    "addr:housenumber":"1855",
    "addr:postcode":"80027",
    "addr:street":"S Pitkin Ave",
    "iso:country":"US",
    "sg:address":"1855 S Pitkin Ave",
    "sg:city":"Superior",
    "sg:classifiers":[
        {
            "category":"Retail",
            "subcategory":"Portrait Studio",
            "type":"Services"
        }
    ],
    "sg:phone":"+1 303 494 2200",
    "sg:postcode":"80027",
    "sg:province":"CO",
    "sg:tags":[
        "photographer"
    ],
    "wof:name":"David Schlatter Photography",
    "wof:placetype":"venue"
},
  "geometry": {"coordinates":[-105.160636,39.937282],"type":"Point"}
}