{
  "type": "Feature",
  "properties": {
    "addr:full":"2505 Walnut St Boulder CO 80302",
    "addr:housenumber":"2505",
    "addr:postcode":"80302",
    "addr:street":"Walnut St",
    "iso:country":"US",
    "sg:address":"2505 Walnut St",
    "sg:city":"Boulder",
    "sg:classifiers":[
        {
            "category":"Personal",
            "subcategory":"Beauty Salon",
            "type":"Services"
        }
    ],
    "sg:phone":"+1 303 444 4234",
    "sg:postcode":"80302",
    "sg:province":"CO",
    "sg:tags":[
        "spa",
        "day"
    ],
    "wof:name":"Wildflowers Salon & Spa",
    "wof:placetype":"venue"
},
  "geometry": {"coordinates":[-105.260633,40.020102],"type":"Point"}
}