{
  "type": "Feature",
  "properties": {
    "iso:country":"US",
    "sg:address":"3625 Old Ranch Rd",
    "sg:city":"Colorado Springs",
    "sg:classifiers":[
        {
            "category":"Retail",
            "subcategory":"Veterinary Services",
            "type":"Services"
        }
    ],
    "sg:phone":"+1 719 575 0007",
    "sg:postcode":"80908",
    "sg:province":"CO",
    "wof:name":"Cattails Feline Center",
    "wof:placetype":"venue"
},
  "geometry": {"coordinates":[-104.760688,38.984901],"type":"Point"}
}