{
  "type": "Feature",
  "properties": {
    "iso:country":"US",
    "sg:address":"3649 Star Ranch Rd",
    "sg:city":"Colorado Springs",
    "sg:classifiers":[
        {
            "category":"Insurance",
            "subcategory":"Insurance Agent",
            "type":"Services"
        }
    ],
    "sg:phone":"+1 719 540 9520",
    "sg:postcode":"80906",
    "sg:province":"CO",
    "sg:website":"www.statefarm.com",
    "wof:name":"State Farm Insurance",
    "wof:placetype":"venue"
},
  "geometry": {"coordinates":[-104.815634,38.776148],"type":"Point"}
}