{
  "type": "Feature",
  "properties": {
    "addr:full":"4958 S Hoyt St Littleton CO 80123",
    "addr:housenumber":"4958",
    "addr:postcode":"80123",
    "addr:street":"S Hoyt St",
    "iso:country":"US",
    "sg:address":"4958 S Hoyt St",
    "sg:city":"Littleton",
    "sg:classifiers":[
        {
            "category":"Insurance",
            "subcategory":"Insurance Agent",
            "type":"Services"
        }
    ],
    "sg:phone":"+1 303 973 5715",
    "sg:postcode":"80123",
    "sg:province":"CO",
    "wof:name":"SPD Solutions Inc",
    "wof:placetype":"venue"
},
  "geometry": {"coordinates":[-105.104276,39.625497],"type":"Point"}
}