{
  "type": "Feature",
  "properties": {
    "iso:country":"US",
    "sg:address":"1220 Potter Dr",
    "sg:city":"Colorado Springs",
    "sg:classifiers":[
        {
            "category":"Real Estate",
            "subcategory":"Real Estate Operator",
            "type":"Services"
        }
    ],
    "sg:phone":"+1 719 596 4115",
    "sg:postcode":"80909",
    "sg:province":"CO",
    "sg:tags":[
        "apartment",
        "complex"
    ],
    "wof:name":"Rustic Hills Park Apartments",
    "wof:placetype":"venue"
},
  "geometry": {"coordinates":[-104.752797,38.850021],"type":"Point"}
}