{
  "type": "Feature",
  "properties": {
    "addr:full":"5523 W 88th Ave Westminster CO 80031",
    "addr:housenumber":"5523",
    "addr:postcode":"80031",
    "addr:street":"W 88Th Ave",
    "iso:country":"US",
    "sg:address":"5523 W 88th Ave",
    "sg:city":"Westminster",
    "sg:classifiers":[
        {
            "category":"Shopping",
            "subcategory":"Clothing, Apparel, & Fashions",
            "type":"Retail Goods"
        }
    ],
    "sg:phone":"+1 303 427 6727",
    "sg:postcode":"80031",
    "sg:province":"CO",
    "wof:name":"Anchor Blue",
    "wof:placetype":"venue"
},
  "geometry": {"coordinates":[-105.060804,39.856546],"type":"Point"}
}