{
  "type": "Feature",
  "properties": {
    "iso:country":"US",
    "sg:address":"2536 Champa St",
    "sg:city":"Denver",
    "sg:classifiers":[
        {
            "category":"Banks & Credit Unions",
            "subcategory":"Bank",
            "type":"Services"
        }
    ],
    "sg:phone":"+1 303 292 0872",
    "sg:postcode":"80205",
    "sg:province":"CO",
    "sg:tags":[
        "broker",
        "mortgage"
    ],
    "wof:name":"Liberty Lending Usa Inc",
    "wof:placetype":"venue"
},
  "geometry": {"coordinates":[-104.982196,39.755471],"type":"Point"}
}