{
  "type": "Feature",
  "properties": {
    "addr:full":"6125 E Parkway Drive Commerce City CO 80022",
    "addr:housenumber":"6125",
    "addr:postcode":"80022",
    "addr:street":"E Parkway Drive",
    "iso:country":"US",
    "sg:address":"6125 E Parkway Drive",
    "sg:city":"Commerce City",
    "sg:classifiers":[
        {
            "category":"Restaurant",
            "type":"Food & Drink"
        }
    ],
    "sg:phone":"+1 303 287 2275",
    "sg:postcode":"80022",
    "sg:province":"CO",
    "sg:website":"www.wingstreet.com",
    "wof:name":"Pizza Hut",
    "wof:placetype":"venue"
},
  "geometry": {"coordinates":[-104.928628,39.807831],"type":"Point"}
}