{
  "type": "Feature",
  "properties": {
    "addr:full":"8672 N Union Blvd Colorado Springs CO 80920",
    "addr:housenumber":"8672",
    "addr:postcode":"80920",
    "addr:street":"N Union Blvd",
    "iso:country":"US",
    "sg:address":"8672 N Union Blvd",
    "sg:city":"Colorado Springs",
    "sg:classifiers":[
        {
            "category":"Personal",
            "subcategory":"Beauty Salon",
            "type":"Services"
        }
    ],
    "sg:phone":"+1 719 597 2833",
    "sg:postcode":"80920",
    "sg:province":"CO",
    "sg:tags":[
        "spa",
        "day"
    ],
    "wof:name":"Desirabelles",
    "wof:placetype":"venue"
},
  "geometry": {"coordinates":[-104.764263,38.954813],"type":"Point"}
}