{
  "type": "Feature",
  "properties": {
    "addr:full":"455 Animosa Dr Durango CO 81301",
    "addr:housenumber":"455",
    "addr:postcode":"co 81301",
    "addr:street":"Animosa Dr",
    "iso:country":"US",
    "sg:address":"455 Animosa Dr",
    "sg:city":"Durango",
    "sg:classifiers":[
        {
            "category":"Building & Trades",
            "subcategory":"Construction",
            "type":"Services"
        }
    ],
    "sg:phone":"+1 970 382 8815",
    "sg:postcode":"81301",
    "sg:province":"CO",
    "sg:tags":[
        "home",
        "family",
        "contractor"
    ],
    "wof:name":"M Tech Contracting",
    "wof:placetype":"venue"
},
  "geometry": {"coordinates":[-107.83362200000001,37.40821],"type":"Point"}
}