{
  "type": "Feature",
  "properties": {
    "addr:full":"1310 W Fortino Blvd Pueblo CO 81008",
    "addr:housenumber":"1310",
    "addr:postcode":"81008",
    "addr:street":"W Fortino Blvd",
    "iso:country":"US",
    "sg:address":"1310 W Fortino Blvd",
    "sg:city":"Pueblo",
    "sg:classifiers":[
        {
            "category":"Professional",
            "subcategory":"Employment Agencies",
            "type":"Services"
        }
    ],
    "sg:phone":"+1 719 542 1777",
    "sg:postcode":"81008",
    "sg:province":"CO",
    "sg:tags":[
        "temporary",
        "placement",
        "contract"
    ],
    "wof:name":"Allegis Group Inc",
    "wof:placetype":"venue"
},
  "geometry": {"coordinates":[-104.626058,38.312412],"type":"Point"}
}