{
  "type": "Feature",
  "properties": {
    "addr:full":"4350 Reed St Wheat Ridge CO 80033",
    "addr:housenumber":"4350",
    "addr:postcode":"80033",
    "addr:street":"Reed St",
    "iso:country":"US",
    "sg:address":"4350 Reed St",
    "sg:city":"Wheat Ridge",
    "sg:classifiers":[
        {
            "category":"Building & Trades",
            "subcategory":"Construction",
            "type":"Services"
        }
    ],
    "sg:phone":"+1 720 331 3325",
    "sg:postcode":"80033",
    "sg:province":"CO",
    "sg:tags":[
        "builder",
        "deck"
    ],
    "wof:name":"Deck 1 One",
    "wof:placetype":"venue"
},
  "geometry": {"coordinates":[-105.074337,39.775711],"type":"Point"}
}