{
  "type": "Feature",
  "properties": {
    "iso:country":"US",
    "sg:address":"25938 Genesee Trail Rd",
    "sg:city":"Golden",
    "sg:classifiers":[
        {
            "category":"Health Services",
            "subcategory":"Clinic",
            "type":"Services"
        }
    ],
    "sg:phone":"+1 303 526 2565",
    "sg:postcode":"80401",
    "sg:province":"CO",
    "sg:tags":[
        "information",
        "disability",
        "learning"
    ],
    "wof:name":"Foothills Pediatric Therapies",
    "wof:placetype":"venue"
},
  "geometry": {"coordinates":[-105.293959,39.708904],"type":"Point"}
}