{
  "type": "Feature",
  "properties": {
    "addr:full":"250 3rd Ave Longmont CO 80501",
    "addr:housenumber":"250",
    "addr:postcode":"80501",
    "addr:street":"3Rd Ave",
    "iso:country":"US",
    "sg:address":"250 3rd Ave",
    "sg:city":"Longmont",
    "sg:classifiers":[
        {
            "category":"Organizations",
            "subcategory":"Non-profit Organization",
            "type":"Services"
        }
    ],
    "sg:phone":"+1 303 772 5529",
    "sg:postcode":"80501",
    "sg:province":"CO",
    "wof:name":"OUR Ctr",
    "wof:placetype":"venue"
},
  "geometry": {"coordinates":[-105.09754700000001,40.164007],"type":"Point"}
}