{
  "type": "Feature",
  "properties": {
    "iso:country":"US",
    "sg:address":"430 S 4th St",
    "sg:city":"Grand Junction",
    "sg:classifiers":[
        {
            "category":"Wholesale",
            "subcategory":"Electrical",
            "type":"Manufacturing & Wholesale Goods"
        }
    ],
    "sg:phone":"+1 970 243 3944",
    "sg:postcode":"81501",
    "sg:province":"CO",
    "sg:tags":[
        "electric",
        "motor"
    ],
    "wof:name":"Stout's Electric Motor Svc",
    "wof:placetype":"venue"
},
  "geometry": {"coordinates":[-108.566097,39.06372],"type":"Point"}
}