{
  "type": "Feature",
  "properties": {
    "addr:full":"11465 W 48th Ave Wheat Ridge CO 80033",
    "addr:housenumber":"11465",
    "addr:postcode":"80033",
    "addr:street":"W 48Th Ave",
    "iso:country":"US",
    "sg:address":"11465 W 48th Ave",
    "sg:city":"Wheat Ridge",
    "sg:classifiers":[
        {
            "category":"Wholesale",
            "subcategory":"Machinery & Supplies",
            "type":"Manufacturing & Wholesale Goods"
        }
    ],
    "sg:phone":"+1 303 422 8088",
    "sg:postcode":"80033",
    "sg:province":"CO",
    "sg:tags":[
        "commercial",
        "industrial",
        "e",
        "computer"
    ],
    "wof:name":"Uav Flight Systems Inc",
    "wof:placetype":"venue"
},
  "geometry": {"coordinates":[-105.12758599999999,39.783756],"type":"Point"}
}