{
  "type": "Feature",
  "properties": {
    "iso:country":"US",
    "sg:address":"7200 S Sundown Cir",
    "sg:city":"Littleton",
    "sg:classifiers":[
        {
            "category":"Professional",
            "subcategory":"Lawyer & Legal Services",
            "type":"Services"
        }
    ],
    "sg:phone":"+1 303 795 2716",
    "sg:postcode":"80120",
    "sg:province":"CO",
    "wof:name":"Firm Ltd",
    "wof:placetype":"venue"
},
  "geometry": {"coordinates":[-104.99574200000001,39.590123],"type":"Point"}
}