{
  "type": "Feature",
  "properties": {
    "addr:full":"2034 Larimer St Denver CO 80205",
    "addr:housenumber":"2034",
    "addr:postcode":"80205",
    "addr:street":"Larimer St",
    "iso:country":"US",
    "sg:address":"2034 Larimer St",
    "sg:city":"Denver",
    "sg:classifiers":[
        {
            "category":"Personal",
            "subcategory":"Beauty Salon",
            "type":"Services"
        },
        {
            "category":"Bars & Pubs",
            "subcategory":"Lounge",
            "type":"Food & Drink"
        }
    ],
    "sg:phone":"+1 303 296 3242",
    "sg:postcode":"80205",
    "sg:province":"CO",
    "sg:tags":[
        "hair"
    ],
    "sg:website":"theretroroomlounge.com",
    "wof:name":"Retro Room Lounge and Salon",
    "wof:placetype":"venue"
},
  "geometry": {"coordinates":[-104.991674,39.753264],"type":"Point"}
}