{
  "type": "Feature",
  "properties": {
    "iso:country":"US",
    "sg:address":"1290 Bannock St",
    "sg:city":"Denver",
    "sg:classifiers":[
        {
            "category":"Building & Trades",
            "subcategory":"Locksmith",
            "type":"Services"
        }
    ],
    "sg:phone":"+1 303 876 0364",
    "sg:postcode":"80204",
    "sg:province":"CO",
    "sg:tags":[
        "key"
    ],
    "wof:name":"A0001 First Call Locksmith",
    "wof:placetype":"venue"
},
  "geometry": {"coordinates":[-104.99004499999999,39.736725],"type":"Point"}
}