{
  "type": "Feature",
  "properties": {
    "addr:full":"901 E Baseline Rd Lafayette CO 80026",
    "addr:housenumber":"901",
    "addr:postcode":"80026",
    "addr:street":"E Baseline Rd",
    "iso:country":"US",
    "sg:address":"901 E Baseline Rd",
    "sg:city":"Lafayette",
    "sg:classifiers":[
        {
            "category":"Retail",
            "subcategory":"Auto Repair",
            "type":"Services"
        }
    ],
    "sg:phone":"+1 303 666 9752",
    "sg:postcode":"80026",
    "sg:province":"CO",
    "sg:tags":[
        "body",
        "automobile",
        "painting"
    ],
    "wof:name":"Collision Center Inc",
    "wof:placetype":"venue"
},
  "geometry": {"coordinates":[-105.078593,40.000225],"type":"Point"}
}