{
  "type": "Feature",
  "properties": {
    "addr:full":"10440 Co Rd 50.5 Eads CO 81036",
    "addr:housenumber":"10440",
    "addr:postcode":"81036",
    "addr:street":"Co Rd",
    "iso:country":"US",
    "sg:address":"10440 Co Rd 50.5",
    "sg:city":"Eads",
    "sg:classifiers":[
        {
            "category":"Manufacturing",
            "subcategory":"Tools & Machinery",
            "type":"Manufacturing & Wholesale Goods"
        }
    ],
    "sg:phone":"+1 719 729 3509",
    "sg:postcode":"81036",
    "sg:province":"CO",
    "sg:tags":[
        "windmill"
    ],
    "wof:name":"Peterson High Reach",
    "wof:placetype":"venue"
},
  "geometry": {"coordinates":[-102.59293700000001,38.430362],"type":"Point"}
}