{
  "type": "Feature",
  "properties": {
    "iso:country":"US",
    "sg:address":"100 N 6th St",
    "sg:city":"Granby",
    "sg:classifiers":[
        {
            "category":"Building & Trades",
            "subcategory":"Equipment Rental",
            "type":"Services"
        }
    ],
    "sg:phone":"+1 970 887 3845",
    "sg:postcode":"80446",
    "sg:province":"CO",
    "sg:tags":[
        "crane"
    ],
    "wof:name":"Sky Crane LTD",
    "wof:placetype":"venue"
},
  "geometry": {"coordinates":[-105.932227,40.085792],"type":"Point"}
}