{
  "type": "Feature",
  "properties": {
    "iso:country":"US",
    "sg:address":"7950 E Mississippi Ave Ste J",
    "sg:city":"Denver",
    "sg:classifiers":[
        {
            "category":"Bars & Pubs",
            "subcategory":"Nightclub",
            "type":"Food & Drink"
        }
    ],
    "sg:phone":"+1 303 368 4959",
    "sg:postcode":"80247",
    "sg:province":"CO",
    "sg:tags":[
        "nightlife"
    ],
    "wof:name":"Naughty Prince the",
    "wof:placetype":"venue"
},
  "geometry": {"coordinates":[-104.895951,39.696395],"type":"Point"}
}