{
  "type": "Feature",
  "properties": {
    "iso:country":"US",
    "sg:address":"11782 E Basswood Ln",
    "sg:city":"Franktown",
    "sg:classifiers":[
        {
            "category":"Manufacturing",
            "subcategory":"Wood Products",
            "type":"Manufacturing & Wholesale Goods"
        }
    ],
    "sg:phone":"+1 303 840 4616",
    "sg:postcode":"80116",
    "sg:province":"CO",
    "sg:tags":[
        "mfg"
    ],
    "wof:name":"A Box & A Theme",
    "wof:placetype":"venue"
},
  "geometry": {"coordinates":[-104.66828099999999,39.404492],"type":"Point"}
}