{
  "type": "Feature",
  "properties": {
    "iso:country":"US",
    "sg:address":"2853 Country Club Cir",
    "sg:city":"Colorado Springs",
    "sg:classifiers":[
        {
            "category":"Professional",
            "subcategory":"Management & Consulting",
            "type":"Services"
        }
    ],
    "sg:phone":"+1 719 473 7160",
    "sg:postcode":"80909",
    "sg:province":"CO",
    "sg:tags":[
        "consultant"
    ],
    "wof:name":"Affordable Housing Concepts",
    "wof:placetype":"venue"
},
  "geometry": {"coordinates":[-104.78647599999999,38.871039],"type":"Point"}
}