{
  "type": "Feature",
  "properties": {
    "iso:country":"US",
    "sg:address":"29369 Thunderbolt Cir",
    "sg:city":"Conifer",
    "sg:classifiers":[
        {
            "category":"Professional",
            "type":"Services"
        }
    ],
    "sg:phone":"+1 303 838 2508",
    "sg:postcode":"80433",
    "sg:province":"CO",
    "wof:name":"Rebecca S Bramlage",
    "wof:placetype":"venue"
},
  "geometry": {"coordinates":[-105.33664400000001,39.54448],"type":"Point"}
}