{
  "type": "Feature",
  "properties": {
    "addr:full":"5433 W 88th Ave Westminster CO 80031",
    "addr:housenumber":"5433",
    "addr:postcode":"80031",
    "addr:street":"W 88Th Ave",
    "iso:country":"US",
    "sg:address":"5433 W 88th Ave",
    "sg:city":"Westminster",
    "sg:classifiers":[
        {
            "category":"Shopping",
            "subcategory":"Jewelry",
            "type":"Retail Goods"
        }
    ],
    "sg:phone":"+1 303 429 8911",
    "sg:postcode":"80031",
    "sg:province":"CO",
    "sg:tags":[
        "jeweler"
    ],
    "wof:name":"Piercing Pagoda",
    "wof:placetype":"venue"
},
  "geometry": {"coordinates":[-105.061716,39.856563],"type":"Point"}
}