{
  "type": "Feature",
  "properties": {
    "addr:full":"409 Juanita St Colorado Springs CO 80909",
    "addr:housenumber":"409",
    "addr:postcode":"80909",
    "addr:street":"Juanita St",
    "iso:country":"US",
    "sg:address":"409 Juanita St",
    "sg:city":"Colorado Springs",
    "sg:classifiers":[
        {
            "category":"Retail",
            "subcategory":"Laundry & Dry Cleaning",
            "type":"Services"
        }
    ],
    "sg:phone":"+1 719 260 6344",
    "sg:postcode":"80909",
    "sg:province":"CO",
    "wof:name":"Chem-Clean Cleaning Supplies",
    "wof:placetype":"venue"
},
  "geometry": {"coordinates":[-104.774477,38.838445],"type":"Point"}
}