{
  "type": "Feature",
  "properties": {
    "iso:country":"US",
    "sg:address":"6803 Co Rd 334",
    "sg:city":"Ignacio",
    "sg:classifiers":[
        {
            "category":"Retail",
            "subcategory":"Auto Repair",
            "type":"Services"
        }
    ],
    "sg:phone":"+1 970 749 8698",
    "sg:postcode":"81137",
    "sg:province":"CO",
    "sg:tags":[
        "wrecker"
    ],
    "wof:name":"A-1 Towing",
    "wof:placetype":"venue"
},
  "geometry": {"coordinates":[-107.550686,37.12353],"type":"Point"}
}