{
  "type": "Feature",
  "properties": {
    "iso:country":"US",
    "sg:address":"560 Grand Ave",
    "sg:city":"Del Norte",
    "sg:classifiers":[
        {
            "category":"Shopping",
            "subcategory":"Used Merchandise",
            "type":"Retail Goods"
        }
    ],
    "sg:phone":"+1 719 657 2850",
    "sg:postcode":"81132",
    "sg:province":"CO",
    "wof:name":"Golden Fleece Antiques",
    "wof:placetype":"venue"
},
  "geometry": {"coordinates":[-106.355177,37.678998],"type":"Point"}
}