{
  "type": "Feature",
  "properties": {
    "iso:country":"US",
    "sg:address":"1168 Co Rd 22",
    "sg:city":"Montrose",
    "sg:classifiers":[
        {
            "category":"Shopping",
            "subcategory":"Used Merchandise",
            "type":"Retail Goods"
        }
    ],
    "sg:phone":"+1 970 240 0122",
    "sg:postcode":"81401",
    "sg:province":"CO",
    "wof:name":"GPJ Inc",
    "wof:placetype":"venue"
},
  "geometry": {"coordinates":[-107.825591,38.297047],"type":"Point"}
}