{
  "type": "Feature",
  "properties": {
    "iso:country":"US",
    "sg:address":"421 S Tejon St",
    "sg:city":"Colorado Springs",
    "sg:classifiers":[
        {
            "category":"Professional",
            "subcategory":"Accounting & Tax Preparation",
            "type":"Services"
        }
    ],
    "sg:phone":"+1 719 667 5201",
    "sg:postcode":"80903",
    "sg:province":"CO",
    "wof:name":"Healthcare Resource Management",
    "wof:placetype":"venue"
},
  "geometry": {"coordinates":[-104.823791,38.827135],"type":"Point"}
}