{
  "type": "Feature",
  "properties": {
    "iso:country":"US",
    "sg:address":"7862 Anchor Dr",
    "sg:city":"Longmont",
    "sg:classifiers":[
        {
            "category":"Building & Trades",
            "subcategory":"Construction",
            "type":"Services"
        }
    ],
    "sg:phone":"+1 720 352 6056",
    "sg:postcode":"80504",
    "sg:province":"CO",
    "sg:tags":[
        "excavation",
        "contractor"
    ],
    "wof:name":"Hart Brothers Excavating LLC",
    "wof:placetype":"venue"
},
  "geometry": {"coordinates":[-105.105386,40.117251],"type":"Point"}
}