{
  "type": "Feature",
  "properties": {
    "iso:country":"US",
    "sg:address":"8207 W Brook Dr",
    "sg:city":"Littleton",
    "sg:classifiers":[
        {
            "category":"Retail",
            "subcategory":"Repair Shop",
            "type":"Services"
        }
    ],
    "sg:phone":"+1 303 986 9906",
    "sg:postcode":"80128",
    "sg:province":"CO",
    "sg:tags":[
        "appliance"
    ],
    "wof:name":"United Appliance",
    "wof:placetype":"venue"
},
  "geometry": {"coordinates":[-105.09112,39.563393],"type":"Point"}
}