{
  "type": "Feature",
  "properties": {
    "addr:full":"641 Delta St Denver CO 80221",
    "addr:housenumber":"641",
    "addr:postcode":"80221",
    "addr:street":"Delta St",
    "iso:country":"US",
    "sg:address":"641 Delta St",
    "sg:city":"Denver",
    "sg:classifiers":[
        {
            "category":"Building & Trades",
            "subcategory":"Plumbing",
            "type":"Services"
        }
    ],
    "sg:phone":"+1 303 487 1915",
    "sg:postcode":"80221",
    "sg:province":"CO",
    "sg:tags":[
        "contractor"
    ],
    "wof:name":"Swenson Sprinklers",
    "wof:placetype":"venue"
},
  "geometry": {"coordinates":[-104.994213,39.834747],"type":"Point"}
}