{
  "type": "Feature",
  "properties": {
    "addr:full":"9831 Adams St Thornton CO 80229",
    "addr:housenumber":"9831",
    "addr:postcode":"80229",
    "addr:street":"Adams St",
    "iso:country":"US",
    "sg:address":"9831 Adams St",
    "sg:city":"Thornton",
    "sg:classifiers":[
        {
            "category":"Manufacturing",
            "subcategory":"Tools & Machinery",
            "type":"Manufacturing & Wholesale Goods"
        }
    ],
    "sg:phone":"+1 303 450 7431",
    "sg:postcode":"80229",
    "sg:province":"CO",
    "sg:tags":[
        "industry"
    ],
    "wof:name":"Hawthorne Treatment Systems",
    "wof:placetype":"venue"
},
  "geometry": {"coordinates":[-104.94825299999999,39.876081],"type":"Point"}
}