{
  "type": "Feature",
  "properties": {
    "addr:full":"2501 15th St Denver CO 80211",
    "addr:housenumber":"2501",
    "addr:postcode":"80211",
    "addr:street":"15Th St",
    "iso:country":"US",
    "sg:address":"2501 15th St",
    "sg:city":"Denver",
    "sg:classifiers":[
        {
            "category":"Health Services",
            "subcategory":"Chiropractor",
            "type":"Services"
        }
    ],
    "sg:phone":"+1 303 433 0933",
    "sg:postcode":"80211",
    "sg:province":"CO",
    "wof:name":"Vespa Marco Chiropractic",
    "wof:placetype":"venue"
},
  "geometry": {"coordinates":[-105.010352,39.757539],"type":"Point"}
}