{
  "type": "Feature",
  "properties": {
    "iso:country":"US",
    "sg:address":"6255 Co Rd 74",
    "sg:city":"Windsor",
    "sg:classifiers":[
        {
            "category":"Recreation",
            "type":"Entertainment"
        }
    ],
    "sg:phone":"+1 970 686 5210",
    "sg:postcode":"80550",
    "sg:province":"CO",
    "sg:tags":[
        "skeet",
        "hunting",
        "facility",
        "trapshooting",
        "range",
        "trap",
        "shooting"
    ],
    "sg:website":"www.pawneesports.com",
    "wof:name":"Buckeye Trap & Skeet Range",
    "wof:placetype":"venue"
},
  "geometry": {"coordinates":[-104.941462,40.522868],"type":"Point"}
}