{
  "type": "Feature",
  "properties": {
    "iso:country":"US",
    "sg:address":"10121 W 37th Pl",
    "sg:city":"Wheat Ridge",
    "sg:classifiers":[
        {
            "category":"Social Services",
            "subcategory":"Child Care",
            "type":"Services"
        }
    ],
    "sg:phone":"+1 303 431 2626",
    "sg:postcode":"80033",
    "sg:province":"CO",
    "sg:tags":[
        "day"
    ],
    "wof:name":"Kids In Action Inc One",
    "wof:placetype":"venue"
},
  "geometry": {"coordinates":[-105.11179300000001,39.768343],"type":"Point"}
}