{
  "type": "Feature",
  "properties": {
    "iso:country":"US",
    "sg:address":"2000 Clay St",
    "sg:city":"Denver",
    "sg:classifiers":[
        {
            "category":"Building & Trades",
            "subcategory":"Cleaning & Sanitation",
            "type":"Services"
        }
    ],
    "sg:phone":"+1 303 279 9500",
    "sg:postcode":"80211",
    "sg:province":"CO",
    "sg:tags":[
        "janitorial"
    ],
    "wof:name":"ABM",
    "wof:placetype":"venue"
},
  "geometry": {"coordinates":[-105.020453,39.748526],"type":"Point"}
}