{
  "type": "Feature",
  "properties": {
    "addr:full":"40 Pine Tree Cir Bailey CO 80421",
    "addr:housenumber":"40",
    "addr:postcode":"80421",
    "addr:street":"Pine Tree Cir",
    "iso:country":"US",
    "sg:address":"40 Pine Tree Cir",
    "sg:city":"Bailey",
    "sg:classifiers":[
        {
            "category":"Personal",
            "subcategory":"Beauty Salon",
            "type":"Services"
        }
    ],
    "sg:phone":"+1 303 838 1176",
    "sg:postcode":"80421",
    "sg:province":"CO",
    "wof:name":"Bailey Hair & Nails",
    "wof:placetype":"venue"
},
  "geometry": {"coordinates":[-105.471295,39.4218],"type":"Point"}
}