{
  "type": "Feature",
  "properties": {
    "addr:full":"1000 Carbon Ct Erie CO 80516",
    "addr:housenumber":"1000",
    "addr:postcode":"80516",
    "addr:street":"Carbon Ct",
    "iso:country":"US",
    "sg:address":"1000 Carbon Ct",
    "sg:city":"Erie",
    "sg:classifiers":[
        {
            "category":"Freight",
            "type":"Transportation"
        }
    ],
    "sg:phone":"+1 303 449 1166",
    "sg:postcode":"80516",
    "sg:province":"CO",
    "sg:tags":[
        "special"
    ],
    "wof:name":"Home Pak",
    "wof:placetype":"venue"
},
  "geometry": {"coordinates":[-105.054967,40.03065],"type":"Point"}
}