{
  "type": "Feature",
  "properties": {
    "iso:country":"US",
    "sg:address":"2706 Templeton Gap Rd",
    "sg:city":"Colorado Springs",
    "sg:classifiers":[
        {
            "category":"Real Estate",
            "subcategory":"Real Estate Agent",
            "type":"Services"
        }
    ],
    "sg:phone":"+1 719 630 0994",
    "sg:postcode":"80907",
    "sg:province":"CO",
    "wof:name":"C & S Realty",
    "wof:placetype":"venue"
},
  "geometry": {"coordinates":[-104.802978,38.870573],"type":"Point"}
}