{
  "type": "Feature",
  "properties": {
    "iso:country":"US",
    "sg:address":"9135 Ridgeline Blvd",
    "sg:city":"Littleton",
    "sg:classifiers":[
        {
            "category":"Wholesale",
            "subcategory":"Medical Equipment & Supplies",
            "type":"Manufacturing & Wholesale Goods"
        },
        {
            "category":"Professional",
            "type":"Services"
        }
    ],
    "sg:phone":"+1 303 989 8900",
    "sg:postcode":"80129",
    "sg:province":"CO",
    "sg:tags":[
        "establishment",
        "monitoring",
        "alcohol"
    ],
    "wof:name":"Alcohol Monitoring Systems",
    "wof:placetype":"venue"
},
  "geometry": {"coordinates":[-104.996503,39.550424],"type":"Point"}
}