{
  "type": "Feature",
  "properties": {
    "addr:full":"7225 Magnolia St Commerce City CO 80022",
    "addr:housenumber":"7225",
    "addr:postcode":"80022",
    "addr:street":"Magnolia St",
    "iso:country":"US",
    "sg:address":"7225 Magnolia St",
    "sg:city":"Commerce City",
    "sg:classifiers":[
        {
            "category":"Retail",
            "subcategory":"Auto Repair",
            "type":"Services"
        }
    ],
    "sg:phone":"+1 303 287 2988",
    "sg:postcode":"80022",
    "sg:province":"CO",
    "sg:tags":[
        "repairing",
        "automobile"
    ],
    "wof:name":"Ernie's Auto",
    "wof:placetype":"venue"
},
  "geometry": {"coordinates":[-104.910792,39.827728],"type":"Point"}
}