{
  "type": "Feature",
  "properties": {
    "iso:country":"US",
    "sg:address":"1602 E Eisenhower Blvd",
    "sg:city":"Loveland",
    "sg:classifiers":[
        {
            "category":"Restaurant",
            "type":"Food & Drink"
        }
    ],
    "sg:phone":"+1 970 669 8847",
    "sg:postcode":"80537",
    "sg:province":"CO",
    "sg:tags":[
        "family"
    ],
    "wof:name":"Mc Graffs Restaurant",
    "wof:placetype":"venue"
},
  "geometry": {"coordinates":[-105.053668,40.407296],"type":"Point"}
}