{
  "type": "Feature",
  "properties": {
    "iso:country":"US",
    "sg:address":"6292 S Billings Way",
    "sg:city":"Englewood",
    "sg:classifiers":[
        {
            "category":"Real Estate",
            "subcategory":"Real Estate Agent",
            "type":"Services"
        }
    ],
    "sg:phone":"+1 303 690 8699",
    "sg:postcode":"80111",
    "sg:province":"CO",
    "wof:name":"Strata Real Estate LLC",
    "wof:placetype":"venue"
},
  "geometry": {"coordinates":[-104.82807,39.602748],"type":"Point"}
}