{
  "type": "Feature",
  "properties": {
    "addr:full":"6840 Richthofen Pkwy Denver CO 80220",
    "addr:postcode":"6840;80220",
    "addr:street":"Richthofen Pkwy",
    "iso:country":"US",
    "sg:address":"6840 Richthofen Pkwy",
    "sg:city":"Denver",
    "sg:classifiers":[
        {
            "category":"Museum",
            "type":"Entertainment"
        }
    ],
    "sg:phone":"+1 303 377 4048",
    "sg:postcode":"80220",
    "sg:province":"CO",
    "wof:name":"Colorado Military History",
    "wof:placetype":"venue"
},
  "geometry": {"coordinates":[-104.90850399999999,39.734276],"type":"Point"}
}