{
  "type": "Feature",
  "properties": {
    "addr:full":"160 E 12th St Durango CO 81301",
    "addr:housenumber":"160",
    "addr:postcode":"co 81301",
    "addr:street":"E 12Th St",
    "iso:country":"US",
    "sg:address":"160 E 12th St",
    "sg:city":"Durango",
    "sg:classifiers":[
        {
            "category":"Professional",
            "subcategory":"Lawyer & Legal Services",
            "type":"Services"
        }
    ],
    "sg:phone":"+1 970 259 4830",
    "sg:postcode":"81301",
    "sg:province":"CO",
    "sg:tags":[
        "attorney"
    ],
    "sg:website":"www.tcwright.com",
    "wof:name":"Ted C Wright PC",
    "wof:placetype":"venue"
},
  "geometry": {"coordinates":[-107.879175,37.276429],"type":"Point"}
}