{
  "type": "Feature",
  "properties": {
    "iso:country":"US",
    "sg:address":"6530 S Academy Blvd",
    "sg:city":"Colorado Springs",
    "sg:classifiers":[
        {
            "category":"Retail",
            "subcategory":"Laundry & Dry Cleaning",
            "type":"Services"
        }
    ],
    "sg:phone":"+1 719 527 8282",
    "sg:postcode":"80906",
    "sg:province":"CO",
    "sg:tags":[
        "cleaners"
    ],
    "wof:name":"Cheyenne Canyon Cleaners",
    "wof:placetype":"venue"
},
  "geometry": {"coordinates":[-104.809241,38.765814],"type":"Point"}
}