{
  "type": "Feature",
  "properties": {
    "addr:full":"4505 Filter Plant Rd Bellvue CO 80512",
    "addr:housenumber":"4505",
    "addr:postcode":"80512",
    "addr:street":"Filter Plant Rd",
    "iso:country":"US",
    "sg:address":"4505 Filter Plant Rd",
    "sg:city":"Bellvue",
    "sg:classifiers":[
        {
            "category":"Building & Trades",
            "subcategory":"Construction",
            "type":"Services"
        }
    ],
    "sg:phone":"+1 970 221 9238",
    "sg:postcode":"80512",
    "sg:province":"CO",
    "sg:tags":[
        "residential"
    ],
    "wof:name":"Stanek Constructors Inc",
    "wof:placetype":"venue"
},
  "geometry": {"coordinates":[-105.192374,40.652979],"type":"Point"}
}