{
  "type": "Feature",
  "properties": {
    "iso:country":"US",
    "sg:address":"3770 Joliet St",
    "sg:city":"Denver",
    "sg:classifiers":[
        {
            "category":"Manufacturing",
            "subcategory":"Signs",
            "type":"Manufacturing & Wholesale Goods"
        }
    ],
    "sg:phone":"+1 303 375 9933",
    "sg:postcode":"80239",
    "sg:province":"CO",
    "wof:name":"Young Electric Sign Co",
    "wof:placetype":"venue"
},
  "geometry": {"coordinates":[-104.86102700000001,39.772227],"type":"Point"}
}