{
  "type": "Feature",
  "properties": {
    "iso:country":"US",
    "sg:address":"1326 Allison St",
    "sg:city":"Lakewood",
    "sg:classifiers":[
        {
            "category":"Building & Trades",
            "subcategory":"Plumbing",
            "type":"Services"
        }
    ],
    "sg:phone":"+1 303 238 4750",
    "sg:postcode":"80214",
    "sg:province":"CO",
    "wof:name":"Crown Services",
    "wof:placetype":"venue"
},
  "geometry": {"coordinates":[-105.085868,39.737174],"type":"Point"}
}