{
  "type": "Feature",
  "properties": {
    "iso:country":"US",
    "sg:address":"1213 Camrose St",
    "sg:city":"Fort Collins",
    "sg:classifiers":[
        {
            "category":"Wholesale",
            "subcategory":"Vending Machines",
            "type":"Manufacturing & Wholesale Goods"
        }
    ],
    "sg:phone":"+1 970 206 0431",
    "sg:postcode":"80525",
    "sg:province":"CO",
    "sg:tags":[
        "operator"
    ],
    "wof:name":"Kaplan Vending",
    "wof:placetype":"venue"
},
  "geometry": {"coordinates":[-105.054222,40.543628],"type":"Point"}
}