{
  "type": "Feature",
  "properties": {
    "iso:country":"US",
    "sg:address":"9906 E Arizona Dr # 1025",
    "sg:city":"Denver",
    "sg:classifiers":[
        {
            "category":"Personal",
            "subcategory":"Massage",
            "type":"Services"
        }
    ],
    "sg:phone":"+1 720 300 2534",
    "sg:postcode":"80247",
    "sg:province":"CO",
    "wof:name":"Solutions Modern Massage",
    "wof:placetype":"venue"
},
  "geometry": {"coordinates":[-104.873154,39.695207],"type":"Point"}
}