{
  "type": "Feature",
  "properties": {
    "addr:full":"253 Adams Ranch Rd Telluride CO 81435",
    "addr:housenumber":"253",
    "addr:postcode":"81435",
    "addr:street":"Adams Ranch Rd",
    "iso:country":"US",
    "sg:address":"253 Adams Ranch Rd",
    "sg:city":"Telluride",
    "sg:classifiers":[
        {
            "category":"Banks & Credit Unions",
            "subcategory":"Investment Brokerage",
            "type":"Services"
        }
    ],
    "sg:phone":"+1 970 728 1447",
    "sg:postcode":"81435",
    "sg:province":"CO",
    "sg:tags":[
        "advisory"
    ],
    "wof:name":"Garner & Assoc L L C",
    "wof:placetype":"venue"
},
  "geometry": {"coordinates":[-107.867316,37.943593],"type":"Point"}
}