{
  "type": "Feature",
  "properties": {
    "addr:full":"9630 Dallas St Henderson CO 80640",
    "addr:housenumber":"9630",
    "addr:postcode":"80640",
    "addr:street":"Dallas St",
    "iso:country":"US",
    "sg:address":"9630 Dallas St",
    "sg:city":"Henderson",
    "sg:classifiers":[
        {
            "category":"Wholesale",
            "subcategory":"Electrical",
            "type":"Manufacturing & Wholesale Goods"
        }
    ],
    "sg:phone":"+1 303 288 6057",
    "sg:postcode":"80640",
    "sg:province":"CO",
    "sg:tags":[
        "testing",
        "apparatus"
    ],
    "wof:name":"KUKA Industries",
    "wof:placetype":"venue"
},
  "geometry": {"coordinates":[-104.87607300000001,39.872794],"type":"Point"}
}