{
  "type": "Feature",
  "properties": {
    "addr:full":"725 25th St Greeley CO 80631",
    "addr:housenumber":"725",
    "addr:postcode":"80631",
    "addr:street":"25Th St",
    "iso:country":"US",
    "sg:address":"725 25th St",
    "sg:city":"Greeley",
    "sg:classifiers":[
        {
            "category":"Restaurant",
            "type":"Food & Drink"
        }
    ],
    "sg:menulink":"http://www.allmenus.com/co/greeley/128847-subway/menu/",
    "sg:phone":"+1 970 353 8477",
    "sg:postcode":"80631",
    "sg:province":"CO",
    "sg:tags":[
        "american",
        "sandwich"
    ],
    "wof:name":"Subway",
    "wof:placetype":"venue"
},
  "geometry": {"coordinates":[-104.69006899999999,40.397235],"type":"Point"}
}