{
  "type": "Feature",
  "properties": {
    "addr:full":"5601 W 18th St Greeley CO 80634",
    "addr:housenumber":"5601",
    "addr:postcode":"80634",
    "addr:street":"W 18Th St",
    "iso:country":"US",
    "sg:address":"5601 W 18th St",
    "sg:city":"Greeley",
    "sg:classifiers":[
        {
            "category":"Professional",
            "type":"Services"
        }
    ],
    "sg:phone":"+1 970 330 1119",
    "sg:postcode":"80634",
    "sg:province":"CO",
    "sg:tags":[
        "establishment"
    ],
    "wof:name":"Miller & Miller",
    "wof:placetype":"venue"
},
  "geometry": {"coordinates":[-104.770006,40.409524],"type":"Point"}
}