{
  "type": "Feature",
  "properties": {
    "iso:country":"US",
    "sg:address":"1626 Sinton Rd",
    "sg:city":"Evergreen",
    "sg:classifiers":[
        {
            "category":"Building & Trades",
            "subcategory":"Construction",
            "type":"Services"
        }
    ],
    "sg:phone":"+1 303 679 0460",
    "sg:postcode":"80439",
    "sg:province":"CO",
    "sg:tags":[
        "general",
        "contractor"
    ],
    "wof:name":"Jackson's Home Improvement",
    "wof:placetype":"venue"
},
  "geometry": {"coordinates":[-105.421694,39.672511],"type":"Point"}
}