{
  "type": "Feature",
  "properties": {
    "iso:country":"US",
    "sg:address":"550 Santa Fe Drive",
    "sg:city":"Denver",
    "sg:classifiers":[
        {
            "category":"Building & Trades",
            "subcategory":"Locksmith",
            "type":"Services"
        }
    ],
    "sg:phone":"+1 303 534 0886",
    "sg:postcode":"80204",
    "sg:province":"CO",
    "sg:tags":[
        "key"
    ],
    "wof:name":"A B C Custom Iron & Locksmith",
    "wof:placetype":"venue"
},
  "geometry": {"coordinates":[-104.998582,39.724926],"type":"Point"}
}