{
  "type": "Feature",
  "properties": {
    "addr:full":"6014 S Kipling St Littleton CO 80127",
    "addr:housenumber":"6014",
    "addr:postcode":"80127",
    "addr:street":"S Kipling St",
    "iso:country":"US",
    "sg:address":"6014 S Kipling St",
    "sg:city":"Littleton",
    "sg:classifiers":[
        {
            "category":"Professional",
            "type":"Services"
        }
    ],
    "sg:phone":"+1 303 948 3249",
    "sg:postcode":"80127",
    "sg:province":"CO",
    "sg:tags":[
        "establishment"
    ],
    "wof:name":"Kipling Place",
    "wof:placetype":"venue"
},
  "geometry": {"coordinates":[-105.109909,39.608214],"type":"Point"}
}