{
  "type": "Feature",
  "properties": {
    "iso:country":"US",
    "sg:address":"6390 Wadsworth Blvd",
    "sg:city":"Arvada",
    "sg:classifiers":[
        {
            "category":"Shopping",
            "subcategory":"Bicycles & Sporting Goods",
            "type":"Retail Goods"
        }
    ],
    "sg:phone":"+1 720 898 5345",
    "sg:postcode":"80003",
    "sg:province":"CO",
    "wof:name":"Colorado Racquet Co",
    "wof:placetype":"venue"
},
  "geometry": {"coordinates":[-105.079464,39.810105],"type":"Point"}
}