{
  "type": "Feature",
  "properties": {
    "addr:full":"621 Schulze Ranch Rd Westcliffe CO 81252",
    "addr:housenumber":"621",
    "addr:postcode":"81252",
    "addr:street":"Schulze Ranch Rd",
    "iso:country":"US",
    "sg:address":"621 Schulze Ranch Rd",
    "sg:city":"Westcliffe",
    "sg:classifiers":[
        {
            "category":"Wholesale",
            "subcategory":"Machinery & Supplies",
            "type":"Manufacturing & Wholesale Goods"
        }
    ],
    "sg:phone":"+1 719 783 4042",
    "sg:postcode":"81252",
    "sg:province":"CO",
    "sg:tags":[
        "valve"
    ],
    "wof:name":"General Valve Co",
    "wof:placetype":"venue"
},
  "geometry": {"coordinates":[-105.284024,38.056132],"type":"Point"}
}