{
  "type": "Feature",
  "properties": {
    "iso:country":"US",
    "sg:address":"7000 E Quincy Ave",
    "sg:city":"Denver",
    "sg:classifiers":[
        {
            "category":"Real Estate",
            "subcategory":"Developer",
            "type":"Services"
        }
    ],
    "sg:phone":"+1 303 290 0909",
    "sg:postcode":"80237",
    "sg:province":"CO",
    "wof:name":"Newport Realty",
    "wof:placetype":"venue"
},
  "geometry": {"coordinates":[-104.908736,39.638616],"type":"Point"}
}