{
  "type": "Feature",
  "properties": {
    "addr:full":"1221 40th St Evans CO 80620",
    "addr:housenumber":"1221",
    "addr:postcode":"80620",
    "addr:street":"40Th St",
    "iso:country":"US",
    "sg:address":"1221 40th St",
    "sg:city":"Evans",
    "sg:classifiers":[
        {
            "category":"Real Estate",
            "subcategory":"Real Estate Agent",
            "type":"Services"
        }
    ],
    "sg:phone":"+1 970 350 0500",
    "sg:postcode":"80620",
    "sg:province":"CO",
    "wof:name":"First Team Real Estate LLC",
    "wof:placetype":"venue"
},
  "geometry": {"coordinates":[-104.697531,40.373081],"type":"Point"}
}