{
  "type": "Feature",
  "properties": {
    "addr:full":"55 S 32nd St Boulder CO 80305",
    "addr:housenumber":"55",
    "addr:postcode":"80305",
    "addr:street":"S 32Nd St",
    "iso:country":"US",
    "sg:address":"55 S 32nd St",
    "sg:city":"Boulder",
    "sg:classifiers":[
        {
            "category":"Building & Trades",
            "subcategory":"Construction",
            "type":"Services"
        }
    ],
    "sg:phone":"+1 720 304 3827",
    "sg:postcode":"80305",
    "sg:province":"CO",
    "wof:name":"Down To Earth",
    "wof:placetype":"venue"
},
  "geometry": {"coordinates":[-105.25499000000001,39.992563],"type":"Point"}
}