{
  "type": "Feature",
  "properties": {
    "iso:country":"US",
    "sg:address":"2109 S Wadsworth Blvd",
    "sg:city":"Lakewood",
    "sg:classifiers":[
        {
            "category":"Professional",
            "subcategory":"Engineering",
            "type":"Services"
        }
    ],
    "sg:phone":"+1 303 980 9104",
    "sg:postcode":"80227",
    "sg:province":"CO",
    "sg:tags":[
        "engineer"
    ],
    "wof:name":"Burdick Engineering Consultant",
    "wof:placetype":"venue"
},
  "geometry": {"coordinates":[-105.081532,39.677954],"type":"Point"}
}