{
  "type": "Feature",
  "properties": {
    "iso:country":"US",
    "sg:address":"625 Manhattan Pl",
    "sg:city":"Boulder",
    "sg:classifiers":[
        {
            "category":"Real Estate",
            "subcategory":"Real Estate Operator",
            "type":"Services"
        }
    ],
    "sg:phone":"+1 303 494 2011",
    "sg:postcode":"80303",
    "sg:province":"CO",
    "sg:tags":[
        "building",
        "apartment"
    ],
    "wof:name":"Chateau Montagne",
    "wof:placetype":"venue"
},
  "geometry": {"coordinates":[-105.23017,39.998208],"type":"Point"}
}