{
  "type": "Feature",
  "properties": {
    "iso:country":"US",
    "sg:address":"214 6th St",
    "sg:city":"Glenwood Springs",
    "sg:classifiers":[
        {
            "category":"Food & Beverages",
            "subcategory":"Liquor & Beverages",
            "type":"Retail Goods"
        }
    ],
    "sg:phone":"+1 970 945 6283",
    "sg:postcode":"81601",
    "sg:province":"CO",
    "sg:tags":[
        "alcoholic"
    ],
    "wof:name":"Springs Liquors",
    "wof:placetype":"venue"
},
  "geometry": {"coordinates":[-107.32584900000001,39.550161],"type":"Point"}
}