{
  "type": "Feature",
  "properties": {
    "iso:country":"US",
    "sg:address":"2418 S Colorado Blvd",
    "sg:city":"Denver",
    "sg:classifiers":[
        {
            "category":"Coffee & Tea",
            "type":"Food & Drink"
        }
    ],
    "sg:phone":"+1 303 759 0337",
    "sg:postcode":"80222",
    "sg:province":"CO",
    "wof:name":"From The Ground Up",
    "wof:placetype":"venue"
},
  "geometry": {"coordinates":[-104.94059,39.672537],"type":"Point"}
}