{
  "type": "Feature",
  "properties": {
    "iso:country":"US",
    "sg:address":"405 Ridges Blvd",
    "sg:city":"Grand Junction",
    "sg:classifiers":[
        {
            "category":"Professional",
            "subcategory":"Engineering",
            "type":"Services"
        },
        {
            "category":"Real Estate",
            "subcategory":"Surveying",
            "type":"Services"
        }
    ],
    "sg:phone":"+1 970 243 8300",
    "sg:postcode":"81503",
    "sg:province":"CO",
    "sg:tags":[
        "engineer"
    ],
    "wof:name":"Rolland Engineering",
    "wof:placetype":"venue"
},
  "geometry": {"coordinates":[-108.604175,39.06599],"type":"Point"}
}