{
  "type": "Feature",
  "properties": {
    "iso:country":"US",
    "sg:address":"8595 Washington St",
    "sg:city":"Denver",
    "sg:classifiers":[
        {
            "category":"Autos & Motor Vehicles",
            "subcategory":"Automobile Sales",
            "type":"Retail Goods"
        }
    ],
    "sg:phone":"+1 303 287 5511",
    "sg:postcode":"80229",
    "sg:province":"CO",
    "sg:tags":[
        "car",
        "used",
        "dealer"
    ],
    "wof:name":"King Credit Auto Sales",
    "wof:placetype":"venue"
},
  "geometry": {"coordinates":[-104.97805,39.851118],"type":"Point"}
}