{
  "type": "Feature",
  "properties": {
    "addr:full":"16730 Pine Valley Rd Pine CO 80470",
    "addr:housenumber":"16730",
    "addr:postcode":"80470",
    "addr:street":"Pine Valley Rd Pine Co",
    "iso:country":"US",
    "sg:address":"16730 Pine Valley Rd",
    "sg:city":"Pine",
    "sg:classifiers":[
        {
            "category":"Restaurant",
            "type":"Food & Drink"
        }
    ],
    "sg:phone":"+1 303 838 8785",
    "sg:postcode":"80470",
    "sg:province":"CO",
    "wof:name":"Elephant Rock Cafe",
    "wof:placetype":"venue"
},
  "geometry": {"coordinates":[-105.32122099999999,39.408107],"type":"Point"}
}