{
  "type": "Feature",
  "properties": {
    "iso:country":"US",
    "sg:address":"12080 W Auburn Ave",
    "sg:city":"Denver",
    "sg:classifiers":[
        {
            "category":"Building & Trades",
            "subcategory":"Construction",
            "type":"Services"
        }
    ],
    "sg:phone":"+1 303 716 2942",
    "sg:postcode":"80228",
    "sg:province":"CO",
    "sg:tags":[
        "hanging",
        "contractor"
    ],
    "wof:name":"Work Of Art Painting",
    "wof:placetype":"venue"
},
  "geometry": {"coordinates":[-105.128871,39.674517],"type":"Point"}
}