{
  "type": "Feature",
  "properties": {
    "iso:country":"US",
    "sg:address":"402 W Missouri Ave",
    "sg:city":"Fountain",
    "sg:classifiers":[
        {
            "category":"Freight",
            "type":"Transportation"
        }
    ],
    "sg:phone":"+1 719 382 7922",
    "sg:postcode":"80817",
    "sg:province":"CO",
    "sg:tags":[
        "operator",
        "local",
        "trucking"
    ],
    "wof:name":"Adams Trucking",
    "wof:placetype":"venue"
},
  "geometry": {"coordinates":[-104.705887,38.682234],"type":"Point"}
}