{
  "type": "Feature",
  "properties": {
    "addr:full":"523 Meeker St Delta CO 81416",
    "addr:housenumber":"523",
    "addr:postcode":"81416",
    "addr:street":"Meeker St",
    "iso:country":"US",
    "sg:address":"523 Meeker St",
    "sg:city":"Delta",
    "sg:classifiers":[
        {
            "category":"Building & Trades",
            "subcategory":"Construction",
            "type":"Services"
        }
    ],
    "sg:phone":"+1 970 874 3439",
    "sg:postcode":"81416",
    "sg:province":"CO",
    "sg:tags":[
        "excavation",
        "contractor"
    ],
    "wof:name":"Shuss Excavating",
    "wof:placetype":"venue"
},
  "geometry": {"coordinates":[-108.06952099999999,38.740079],"type":"Point"}
}