{
  "type": "Feature",
  "properties": {
    "iso:country":"US",
    "sg:address":"3800 Lewiston St",
    "sg:city":"Aurora",
    "sg:classifiers":[
        {
            "category":"Professional",
            "subcategory":"Computer Services",
            "type":"Services"
        }
    ],
    "sg:phone":"+1 303 307 3471",
    "sg:postcode":"80011",
    "sg:province":"CO",
    "sg:tags":[
        "system",
        "integration"
    ],
    "wof:name":"Northrop Grumman I T T A S C",
    "wof:placetype":"venue"
},
  "geometry": {"coordinates":[-104.799097,39.772779],"type":"Point"}
}