{
  "type": "Feature",
  "properties": {
    "iso:country":"US",
    "sg:address":"2739 E Las Vegas St",
    "sg:city":"Colorado Springs",
    "sg:classifiers":[
        {
            "category":"Government",
            "subcategory":"Jail",
            "type":"Public Place"
        }
    ],
    "sg:phone":"+1 719 390 2000",
    "sg:postcode":"80906",
    "sg:province":"CO",
    "sg:tags":[
        "county",
        "govt",
        "institution"
    ],
    "wof:name":"El Paso County Jail",
    "wof:placetype":"venue"
},
  "geometry": {"coordinates":[-104.77655799999999,38.787578],"type":"Point"}
}