{
  "type": "Feature",
  "properties": {
    "addr:full":"578 Sundisk Dr Loveland CO 80538",
    "addr:housenumber":"578",
    "addr:postcode":"80538",
    "addr:street":"Sundisk Dr",
    "iso:country":"US",
    "sg:address":"578 Sundisk Dr",
    "sg:city":"Loveland",
    "sg:classifiers":[
        {
            "category":"Professional",
            "subcategory":"Business Services",
            "type":"Services"
        }
    ],
    "sg:phone":"+1 970 669 8322",
    "sg:postcode":"80538",
    "sg:province":"CO",
    "sg:tags":[
        "notary"
    ],
    "wof:name":"Margo's Mobile Notary",
    "wof:placetype":"venue"
},
  "geometry": {"coordinates":[-105.071769,40.439673],"type":"Point"}
}