{
  "type": "Feature",
  "properties": {
    "addr:full":"11777 E Wesley Ave Aurora CO 80014",
    "addr:housenumber":"11777",
    "addr:postcode":"80014",
    "addr:street":"E Wesley Ave",
    "iso:country":"US",
    "sg:address":"11777 E Wesley Ave",
    "sg:city":"Aurora",
    "sg:classifiers":[
        {
            "category":"Education",
            "subcategory":"School",
            "type":"Public Place"
        }
    ],
    "sg:phone":"+1 720 747 2200",
    "sg:postcode":"80014",
    "sg:province":"CO",
    "sg:website":"www.ccsd.k12.co.us",
    "wof:name":"Eastridge Elementary School",
    "wof:placetype":"venue"
},
  "geometry": {"coordinates":[-104.852265,39.672437],"type":"Point"}
}