{
  "type": "Feature",
  "properties": {
    "addr:full":"9559 S University Blvd Littleton CO 80126",
    "addr:housenumber":"9559",
    "addr:postcode":"80126",
    "addr:street":"S University Blvd",
    "iso:country":"US",
    "sg:address":"9559 S University Blvd",
    "sg:city":"Littleton",
    "sg:classifiers":[
        {
            "category":"Cinema",
            "subcategory":"Movie Rental",
            "type":"Entertainment"
        }
    ],
    "sg:phone":"+1 303 471 6900",
    "sg:postcode":"80126",
    "sg:province":"CO",
    "sg:tags":[
        "leasing",
        "video",
        "disc",
        "tape"
    ],
    "wof:name":"Blockbuster Video",
    "wof:placetype":"venue"
},
  "geometry": {"coordinates":[-104.94233,39.543432],"type":"Point"}
}