{
  "type": "Feature",
  "properties": {
    "iso:country":"US",
    "sg:address":"6260 S Dayton St",
    "sg:city":"Englewood",
    "sg:classifiers":[
        {
            "category":"Education",
            "subcategory":"School",
            "type":"Public Place"
        }
    ],
    "sg:phone":"+1 303 779 8988",
    "sg:postcode":"80111",
    "sg:province":"CO",
    "sg:website":"www.cherrycreekacademy.org",
    "wof:name":"Cherry Creek Academy Charter",
    "wof:placetype":"venue"
},
  "geometry": {"coordinates":[-104.876058,39.602637],"type":"Point"}
}