{
  "type": "Feature",
  "properties": {
    "addr:full":"5854 Rawhide Ct Boulder CO 80302",
    "addr:housenumber":"5854",
    "addr:postcode":"80302",
    "addr:street":"Rawhide Ct",
    "iso:country":"US",
    "sg:address":"5854 Rawhide Ct",
    "sg:city":"Boulder",
    "sg:classifiers":[
        {
            "category":"Manufacturing",
            "subcategory":"Lumber",
            "type":"Manufacturing & Wholesale Goods"
        }
    ],
    "sg:phone":"+1 303 449 7170",
    "sg:postcode":"80302",
    "sg:province":"CO",
    "sg:tags":[
        "wood"
    ],
    "wof:name":"Drozda & Nittman Woodturning",
    "wof:placetype":"venue"
},
  "geometry": {"coordinates":[-105.28099,40.080089],"type":"Point"}
}