{
  "type": "Feature",
  "properties": {
    "iso:country":"US",
    "sg:address":"1300 S Steele St",
    "sg:city":"Denver",
    "sg:classifiers":[
        {
            "category":"Organizations",
            "subcategory":"Religious Organization",
            "type":"Services"
        }
    ],
    "sg:phone":"+1 303 765 4592",
    "sg:postcode":"80210",
    "sg:province":"CO",
    "wof:name":"Religious Sisters Of Mercy",
    "wof:placetype":"venue"
},
  "geometry": {"coordinates":[-104.94996,39.691172],"type":"Point"}
}