{
  "type": "Feature",
  "properties": {
    "addr:full":"1655 Airport Rd Breckenridge CO 80424",
    "addr:housenumber":"1655",
    "addr:postcode":"80424",
    "addr:street":"Airport Rd",
    "iso:country":"US",
    "sg:address":"1655 Airport Rd",
    "sg:city":"Breckenridge",
    "sg:classifiers":[
        {
            "category":"Home & Garden",
            "subcategory":"Carpets & Floor Coverings",
            "type":"Retail Goods"
        }
    ],
    "sg:phone":"+1 970 453 5444",
    "sg:postcode":"80424",
    "sg:province":"CO",
    "sg:tags":[
        "dealer",
        "rug"
    ],
    "wof:name":"Balentine Collection Intl",
    "wof:placetype":"venue"
},
  "geometry": {"coordinates":[-106.049572,39.497711],"type":"Point"}
}