{
  "type": "Feature",
  "properties": {
    "iso:country":"US",
    "sg:address":"923 Balsam St",
    "sg:city":"Cortez",
    "sg:classifiers":[
        {
            "category":"Retail",
            "subcategory":"Portrait Studio",
            "type":"Services"
        }
    ],
    "sg:phone":"+1 970 565 1732",
    "sg:postcode":"81321",
    "sg:province":"CO",
    "sg:tags":[
        "photography"
    ],
    "wof:name":"Sandstone Images By Barbara",
    "wof:placetype":"venue"
},
  "geometry": {"coordinates":[-108.55764499999999,37.360671],"type":"Point"}
}