{
  "type": "Feature",
  "properties": {
    "iso:country":"US",
    "sg:address":"2442 S Downing Street",
    "sg:city":"Denver",
    "sg:classifiers":[
        {
            "category":"Shopping",
            "subcategory":"Stationery & Office Supplies",
            "type":"Retail Goods"
        }
    ],
    "sg:phone":"+1 303 722 1617",
    "sg:postcode":"80210",
    "sg:province":"CO",
    "sg:tags":[
        "equipment"
    ],
    "wof:name":"Aei",
    "wof:placetype":"venue"
},
  "geometry": {"coordinates":[-104.973416,39.6723],"type":"Point"}
}