{
  "type": "Feature",
  "properties": {
    "iso:country":"US",
    "sg:address":"4711 Constitution Ave",
    "sg:city":"Colorado Springs",
    "sg:classifiers":[
        {
            "category":"Utilities",
            "subcategory":"Natural Gas",
            "type":"Services"
        }
    ],
    "sg:phone":"+1 719 574 7723",
    "sg:postcode":"80915",
    "sg:province":"CO",
    "sg:tags":[
        "transmission"
    ],
    "wof:name":"J R N Enterprises LLC",
    "wof:placetype":"venue"
},
  "geometry": {"coordinates":[-104.741708,38.865069],"type":"Point"}
}