{
  "type": "Feature",
  "properties": {
    "iso:country":"US",
    "sg:address":"6548 Lange Dr",
    "sg:city":"Colorado Springs",
    "sg:classifiers":[
        {
            "category":"Shopping",
            "subcategory":"Clothing, Apparel, & Fashions",
            "type":"Retail Goods"
        }
    ],
    "sg:phone":"+1 719 590 7546",
    "sg:postcode":"80918",
    "sg:province":"CO",
    "wof:name":"Vicki L Auckland",
    "wof:placetype":"venue"
},
  "geometry": {"coordinates":[-104.767443,38.923317],"type":"Point"}
}