{
  "type": "Feature",
  "properties": {
    "addr:full":"2418 S Academy Blvd Colorado Springs CO 80916",
    "addr:housenumber":"2418",
    "addr:postcode":"80916",
    "addr:street":"S Academy Blvd",
    "iso:country":"US",
    "sg:address":"2418 S Academy Blvd",
    "sg:city":"Colorado Springs",
    "sg:classifiers":[
        {
            "category":"Manufacturing",
            "subcategory":"Printing",
            "type":"Manufacturing & Wholesale Goods"
        }
    ],
    "sg:phone":"+1 719 390 4282",
    "sg:postcode":"80916",
    "sg:province":"CO",
    "sg:tags":[
        "offset"
    ],
    "wof:name":"KWIK KOPY Printing",
    "wof:placetype":"venue"
},
  "geometry": {"coordinates":[-104.757644,38.797864],"type":"Point"}
}