{
  "type": "Feature",
  "properties": {
    "addr:full":"776 Lincoln Street Denver CO 80203",
    "addr:housenumber":"776",
    "addr:postcode":"80203",
    "addr:street":"Lincoln Street",
    "iso:country":"US",
    "sg:address":"776 Lincoln Street",
    "sg:city":"Denver",
    "sg:classifiers":[
        {
            "category":"Restaurant",
            "type":"Food & Drink"
        },
        {
            "category":"Bars & Pubs",
            "subcategory":"Nightclub",
            "type":"Food & Drink"
        }
    ],
    "sg:phone":"+1 303 832 5075",
    "sg:postcode":"80203",
    "sg:province":"CO",
    "sg:tags":[
        "nightlife"
    ],
    "wof:name":"The Buddha Lounge",
    "wof:placetype":"venue"
},
  "geometry": {"coordinates":[-104.986002,39.728465],"type":"Point"}
}