{
  "type": "Feature",
  "properties": {
    "iso:country":"US",
    "sg:address":"6075 E Parkway Dr",
    "sg:city":"Commerce City",
    "sg:classifiers":[
        {
            "category":"Food & Beverages",
            "subcategory":"Liquor & Beverages",
            "type":"Retail Goods"
        }
    ],
    "sg:phone":"+1 303 288 9137",
    "sg:postcode":"80022",
    "sg:province":"CO",
    "sg:tags":[
        "alcoholic"
    ],
    "wof:name":"Parkway Liquor",
    "wof:placetype":"venue"
},
  "geometry": {"coordinates":[-104.929002,39.807327],"type":"Point"}
}