{
  "type": "Feature",
  "properties": {
    "addr:full":"810 Quail St Lakewood CO 80215",
    "addr:housenumber":"810",
    "addr:postcode":"80215",
    "addr:street":"Quail St",
    "iso:country":"US",
    "sg:address":"810 Quail St",
    "sg:city":"Lakewood",
    "sg:classifiers":[
        {
            "category":"Professional",
            "subcategory":"Research",
            "type":"Services"
        }
    ],
    "sg:phone":"+1 303 231 0075",
    "sg:postcode":"80215",
    "sg:province":"CO",
    "sg:tags":[
        "laboratory"
    ],
    "wof:name":"Omni Laboratories",
    "wof:placetype":"venue"
},
  "geometry": {"coordinates":[-105.12363999999999,39.730706],"type":"Point"}
}