{
  "type": "Feature",
  "properties": {
    "iso:country":"US",
    "sg:address":"4949 Co Rd 237",
    "sg:city":"Durango",
    "sg:classifiers":[
        {
            "category":"Autos & Motor Vehicles",
            "subcategory":"Fuel & Gas Station",
            "type":"Retail Goods"
        }
    ],
    "sg:phone":"+1 970 385 5551",
    "sg:postcode":"81301",
    "sg:province":"CO",
    "sg:tags":[
        "oil"
    ],
    "wof:name":"Horse Gulch Businesses",
    "wof:placetype":"venue"
},
  "geometry": {"coordinates":[-107.802741,37.294708],"type":"Point"}
}