{
  "type": "Feature",
  "properties": {
    "iso:country":"US",
    "sg:address":"128 Mountain Shadows Dr",
    "sg:city":"Glenwood Springs",
    "sg:classifiers":[
        {
            "category":"Social Services",
            "subcategory":"Adult Care",
            "type":"Services"
        }
    ],
    "sg:phone":"+1 970 945 9465",
    "sg:postcode":"81601",
    "sg:province":"CO",
    "sg:tags":[
        "home",
        "group"
    ],
    "wof:name":"Pitkin House",
    "wof:placetype":"venue"
},
  "geometry": {"coordinates":[-107.363302,39.567055],"type":"Point"}
}