{
  "type": "Feature",
  "properties": {
    "addr:full":"6759 E 50th Ave Commerce City CO 80022",
    "addr:housenumber":"6759",
    "addr:postcode":"80022",
    "addr:street":"E 50Th Ave",
    "iso:country":"US",
    "sg:address":"6759 E 50th Ave",
    "sg:city":"Commerce City",
    "sg:classifiers":[
        {
            "category":"Manufacturing",
            "subcategory":"Rubber & Plastics",
            "type":"Manufacturing & Wholesale Goods"
        }
    ],
    "sg:phone":"+1 303 227 0300",
    "sg:postcode":"80022",
    "sg:province":"CO",
    "sg:tags":[
        "conveyor"
    ],
    "wof:name":"MIR Inc",
    "wof:placetype":"venue"
},
  "geometry": {"coordinates":[-104.910605,39.787531],"type":"Point"}
}