{
  "type": "Feature",
  "properties": {
    "iso:country":"US",
    "sg:address":"2560 W Main St",
    "sg:city":"Littleton",
    "sg:classifiers":[
        {
            "category":"Food & Beverages",
            "subcategory":"Candy",
            "type":"Retail Goods"
        },
        {
            "category":"Wholesale",
            "subcategory":"Groceries",
            "type":"Manufacturing & Wholesale Goods"
        }
    ],
    "sg:phone":"+1 303 795 7913",
    "sg:postcode":"80120",
    "sg:province":"CO",
    "sg:tags":[
        "confectionery"
    ],
    "wof:name":"Chocolates By Mary Carol",
    "wof:placetype":"venue"
},
  "geometry": {"coordinates":[-105.017883,39.613652],"type":"Point"}
}