{
  "type": "Feature",
  "properties": {
    "iso:country":"US",
    "sg:address":"1441 W 46th Ave Unit 11",
    "sg:city":"Denver",
    "sg:classifiers":[
        {
            "category":"Food & Beverages",
            "subcategory":"Meat & Fish",
            "type":"Retail Goods"
        }
    ],
    "sg:phone":"+1 303 292 5401",
    "sg:postcode":"80211",
    "sg:province":"CO",
    "sg:tags":[
        "seafood",
        "market"
    ],
    "wof:name":"Santa Lucia Dairies",
    "wof:placetype":"venue"
},
  "geometry": {"coordinates":[-105.004486,39.780324],"type":"Point"}
}