{
  "type": "Feature",
  "properties": {
    "iso:country":"US",
    "sg:address":"4311 S Tabor Ct",
    "sg:city":"Morrison",
    "sg:classifiers":[
        {
            "category":"Building & Trades",
            "subcategory":"Construction",
            "type":"Services"
        }
    ],
    "sg:phone":"+1 303 973 7385",
    "sg:postcode":"80465",
    "sg:province":"CO",
    "sg:tags":[
        "hanging",
        "contractor"
    ],
    "wof:name":"Dave Pennel Painting & Dctg",
    "wof:placetype":"venue"
},
  "geometry": {"coordinates":[-105.131631,39.637323],"type":"Point"}
}