{
  "type": "Feature",
  "properties": {
    "iso:country":"US",
    "sg:address":"1828 Clarkson Street",
    "sg:city":"Denver",
    "sg:classifiers":[
        {
            "category":"Banks & Credit Unions",
            "subcategory":"Atm",
            "type":"Services"
        }
    ],
    "sg:phone":"+1 303 830 2300",
    "sg:postcode":"80218",
    "sg:province":"CO",
    "sg:tags":[
        "bankruptcy"
    ],
    "wof:name":"Bernstein Bruce C PC",
    "wof:placetype":"venue"
},
  "geometry": {"coordinates":[-104.977413,39.745277],"type":"Point"}
}