{
  "type": "Feature",
  "properties": {
    "addr:full":"5226 W 38th Ave Wheat Ridge CO 80212",
    "addr:housenumber":"5226",
    "addr:postcode":"80212",
    "addr:street":"W 38Th Ave",
    "iso:country":"US",
    "sg:address":"5226 W 38th Ave",
    "sg:city":"Wheat Ridge",
    "sg:classifiers":[
        {
            "category":"Building & Trades",
            "subcategory":"Locksmith",
            "type":"Services"
        }
    ],
    "sg:phone":"+1 303 801 0077",
    "sg:postcode":"80212",
    "sg:province":"CO",
    "sg:tags":[
        "key"
    ],
    "wof:name":"AAA 15 Minutes On Call Locksmith",
    "wof:placetype":"venue"
},
  "geometry": {"coordinates":[-105.05338999999999,39.769176],"type":"Point"}
}