{
  "type": "Feature",
  "properties": {
    "iso:country":"US",
    "sg:address":"5226 W 38th Ave",
    "sg:city":"Wheat Ridge",
    "sg:classifiers":[
        {
            "category":"Building & Trades",
            "subcategory":"Locksmith",
            "type":"Services"
        }
    ],
    "sg:phone":"+1 303 801 0077",
    "sg:postcode":"80212",
    "sg:province":"CO",
    "sg:tags":[
        "key"
    ],
    "wof:name":"AAA 15 Minutes On Call Locksmith",
    "wof:placetype":"venue"
},
  "geometry": {"coordinates":[-105.05339,39.769176],"type":"Point"}
}