{
  "type": "Feature",
  "properties": {
    "addr:full":"9165 W 102nd Pl Broomfield CO 80021",
    "addr:housenumber":"9165",
    "addr:postcode":"80021",
    "addr:street":"W 102Nd Pl",
    "iso:country":"US",
    "sg:address":"9165 W 102nd Pl",
    "sg:city":"Broomfield",
    "sg:classifiers":[
        {
            "category":"Freight",
            "type":"Transportation"
        }
    ],
    "sg:phone":"+1 303 438 5827",
    "sg:postcode":"80021",
    "sg:province":"CO",
    "sg:tags":[
        "hauling",
        "trucking"
    ],
    "wof:name":"Aaz Enterprises Inc",
    "wof:placetype":"venue"
},
  "geometry": {"coordinates":[-105.100931,39.881463],"type":"Point"}
}