{
  "type": "Feature",
  "properties": {
    "addr:full":"40039 Co Rd 26 Fleming CO 80728",
    "addr:housenumber":"40039;26",
    "addr:postcode":"80728",
    "addr:street":"Co Rd",
    "iso:country":"US",
    "sg:address":"40039 Co Rd 26",
    "sg:city":"Fleming",
    "sg:phone":"+1 970 265 2963",
    "sg:postcode":"80728",
    "sg:province":"CO",
    "sg:tags":[
        "farm",
        "grain",
        "cash"
    ],
    "wof:name":"Harms Farms",
    "wof:placetype":"venue"
},
  "geometry": {"coordinates":[-102.814967,40.613821],"type":"Point"}
}