{
  "type": "Feature",
  "properties": {
    "iso:country":"US",
    "sg:address":"609 W Littleton Blvd",
    "sg:city":"Littleton",
    "sg:classifiers":[
        {
            "category":"Banks & Credit Unions",
            "subcategory":"Bank",
            "type":"Services"
        }
    ],
    "sg:phone":"+1 303 734 0557",
    "sg:postcode":"80120",
    "sg:province":"CO",
    "sg:tags":[
        "broker",
        "mortgage"
    ],
    "wof:name":"Liberty Financial Group",
    "wof:placetype":"venue"
},
  "geometry": {"coordinates":[-104.99531399999999,39.613252],"type":"Point"}
}