{
  "type": "Feature",
  "properties": {
    "addr:full":"511 Ruffner Ave Flagler CO 80815",
    "addr:housenumber":"511",
    "addr:postcode":"80815",
    "addr:street":"Ruffner Ave",
    "iso:country":"US",
    "sg:address":"511 Ruffner Ave",
    "sg:city":"Flagler",
    "sg:classifiers":[
        {
            "category":"Organizations",
            "subcategory":"Religious Organization",
            "type":"Services"
        }
    ],
    "sg:phone":"+1 719 765 4615",
    "sg:postcode":"80815",
    "sg:province":"CO",
    "wof:name":"Church Of Christ",
    "wof:placetype":"venue"
},
  "geometry": {"coordinates":[-103.06171000000001,39.29478],"type":"Point"}
}