{
  "type": "Feature",
  "properties": {
    "iso:country":"US",
    "sg:address":"5764 S Olathe St",
    "sg:city":"Centennial",
    "sg:classifiers":[
        {
            "category":"Professional",
            "subcategory":"Management & Consulting",
            "type":"Services"
        }
    ],
    "sg:phone":"+1 303 690 1091",
    "sg:postcode":"80015",
    "sg:province":"CO",
    "sg:tags":[
        "consultant",
        "energy",
        "conservation"
    ],
    "wof:name":"Chiron Resources Inc",
    "wof:placetype":"venue"
},
  "geometry": {"coordinates":[-104.79415400000001,39.612252],"type":"Point"}
}