{
  "type": "Feature",
  "properties": {
    "iso:country":"US",
    "sg:address":"188 E 9th Ave",
    "sg:city":"Springfield",
    "sg:classifiers":[
        {
            "category":"Government",
            "subcategory":"Post Office",
            "type":"Public Place"
        }
    ],
    "sg:phone":"+1 719 523 6609",
    "sg:postcode":"81073",
    "sg:province":"CO",
    "wof:name":"US Post Office",
    "wof:placetype":"venue"
},
  "geometry": {"coordinates":[-102.615594,37.40504],"type":"Point"}
}