{
  "type": "Feature",
  "properties": {
    "iso:country":"US",
    "sg:address":"161 Cherrywood Ln",
    "sg:city":"Louisville",
    "sg:classifiers":[
        {
            "category":"Organizations",
            "subcategory":"Religious Organization",
            "type":"Services"
        }
    ],
    "sg:phone":"+1 303 665 8208",
    "sg:postcode":"80027",
    "sg:province":"CO",
    "sg:tags":[
        "church"
    ],
    "wof:name":"Cool Creek Lutheran Church",
    "wof:placetype":"venue"
},
  "geometry": {"coordinates":[-105.16135,39.969057],"type":"Point"}
}