{
  "type": "Feature",
  "properties": {
    "iso:country":"US",
    "sg:address":"1536 Cedarwood Dr",
    "sg:city":"Fort Collins",
    "sg:classifiers":[
        {
            "category":"Building & Trades",
            "subcategory":"Construction",
            "type":"Services"
        }
    ],
    "sg:phone":"+1 970 484 6064",
    "sg:postcode":"80521",
    "sg:province":"CO",
    "sg:tags":[
        "contractor"
    ],
    "wof:name":"Moseley General Contracting",
    "wof:placetype":"venue"
},
  "geometry": {"coordinates":[-105.126147,40.568249],"type":"Point"}
}