{
  "type": "Feature",
  "properties": {
    "iso:country":"US",
    "sg:address":"3011 N el Paso St",
    "sg:city":"Colorado Springs",
    "sg:classifiers":[
        {
            "category":"Retail",
            "subcategory":"Repair Shop",
            "type":"Services"
        }
    ],
    "sg:phone":"+1 719 632 5928",
    "sg:postcode":"80907",
    "sg:province":"CO",
    "sg:tags":[
        "upholsterer"
    ],
    "wof:name":"European Upholstery Co",
    "wof:placetype":"venue"
},
  "geometry": {"coordinates":[-104.812752,38.876268],"type":"Point"}
}