{
  "type": "Feature",
  "properties": {
    "iso:country":"US",
    "sg:address":"4100 E Mississippi Ave",
    "sg:city":"Denver",
    "sg:classifiers":[
        {
            "category":"Banks & Credit Unions",
            "subcategory":"Investment Brokerage",
            "type":"Services"
        }
    ],
    "sg:phone":"+1 303 584 1135",
    "sg:postcode":"80246",
    "sg:province":"CO",
    "sg:tags":[
        "consultant",
        "planning",
        "financial"
    ],
    "wof:name":"Castlewood Financial Svc",
    "wof:placetype":"venue"
},
  "geometry": {"coordinates":[-104.938635,39.696605],"type":"Point"}
}