{
  "type": "Feature",
  "properties": {
    "addr:full":"895 Tabor Street Denver CO 80214",
    "addr:housenumber":"895",
    "addr:postcode":"80214",
    "addr:street":"Tabor Street",
    "iso:country":"US",
    "sg:address":"895 Tabor Street",
    "sg:city":"Denver",
    "sg:classifiers":[
        {
            "category":"Travel",
            "subcategory":"Hotels & Motels",
            "type":"Entertainment"
        },
        {
            "category":"Real Estate",
            "subcategory":"Real Estate Operator",
            "type":"Services"
        }
    ],
    "sg:phone":"+1 303 232 7171",
    "sg:postcode":"80214",
    "sg:province":"CO",
    "sg:tags":[
        "apartment"
    ],
    "wof:name":"Candlewood Suites",
    "wof:placetype":"venue"
},
  "geometry": {"coordinates":[-105.070088,39.745641],"type":"Point"}
}