{
  "type": "Feature",
  "properties": {
    "addr:full":"7345 E Woodmen Rd Colorado Springs CO 80908",
    "addr:housenumber":"7345",
    "addr:postcode":"80908",
    "addr:street":"E Woodmen Rd",
    "iso:country":"US",
    "sg:address":"7345 E Woodmen Rd",
    "sg:city":"Colorado Springs",
    "sg:classifiers":[
        {
            "category":"Organizations",
            "subcategory":"Religious Organization",
            "type":"Services"
        }
    ],
    "sg:phone":"+1 719 495 6688",
    "sg:postcode":"80908",
    "sg:province":"CO",
    "sg:tags":[
        "church"
    ],
    "sg:website":"www.mountainsprings.org",
    "wof:name":"Mountain Springs Church",
    "wof:placetype":"venue"
},
  "geometry": {"coordinates":[-104.691812,38.94088],"type":"Point"}
}