{
  "type": "Feature",
  "properties": {
    "iso:country":"US",
    "sg:address":"3000 Youngfield St",
    "sg:city":"Denver",
    "sg:classifiers":[
        {
            "category":"Banks & Credit Unions",
            "subcategory":"Financial Services",
            "type":"Services"
        }
    ],
    "sg:phone":"+1 303 233 1426",
    "sg:postcode":"80215",
    "sg:province":"CO",
    "sg:tags":[
        "agency",
        "licensing"
    ],
    "wof:name":"Iron Carbide Holdings Ltd",
    "wof:placetype":"venue"
},
  "geometry": {"coordinates":[-105.14238,39.760045],"type":"Point"}
}