{
  "type": "Feature",
  "properties": {
    "iso:country":"US",
    "sg:address":"119 F St",
    "sg:city":"Salida",
    "sg:classifiers":[
        {
            "category":"Shopping",
            "type":"Retail Goods"
        },
        {
            "category":"Shopping",
            "subcategory":"Gifts & Souvenirs",
            "type":"Retail Goods"
        }
    ],
    "sg:phone":"+1 719 539 3904",
    "sg:postcode":"81201",
    "sg:province":"CO",
    "sg:tags":[
        "shop",
        "merchandise"
    ],
    "wof:name":"Earth's Treasures",
    "wof:placetype":"venue"
},
  "geometry": {"coordinates":[-105.99184,38.536082],"type":"Point"}
}