{
  "type": "Feature",
  "properties": {
    "addr:full":"480 Japonica Way Boulder CO 80304",
    "addr:housenumber":"480",
    "addr:postcode":"80304",
    "addr:street":"Japonica Way",
    "iso:country":"US",
    "sg:address":"480 Japonica Way",
    "sg:city":"Boulder",
    "sg:classifiers":[
        {
            "category":"Wholesale",
            "subcategory":"Electrical",
            "type":"Manufacturing & Wholesale Goods"
        }
    ],
    "sg:phone":"+1 303 570 6934",
    "sg:postcode":"80304",
    "sg:province":"CO",
    "sg:tags":[
        "electronics"
    ],
    "wof:name":"Baseline Technology LLC",
    "wof:placetype":"venue"
},
  "geometry": {"coordinates":[-105.29023100000001,40.036849],"type":"Point"}
}