{
  "type": "Feature",
  "properties": {
    "iso:country":"US",
    "sg:address":"304 W Tomichi Ave",
    "sg:city":"Gunnison",
    "sg:classifiers":[
        {
            "category":"Professional",
            "subcategory":"Lawyer & Legal Services",
            "type":"Services"
        }
    ],
    "sg:phone":"+1 970 641 2181",
    "sg:postcode":"81230",
    "sg:province":"CO",
    "sg:tags":[
        "attorney"
    ],
    "wof:name":"David M Barton Law Offices",
    "wof:placetype":"venue"
},
  "geometry": {"coordinates":[-106.930756,38.544472],"type":"Point"}
}