{
  "type": "Feature",
  "properties": {
    "addr:full":"12655 US Hwy 24 Leadville CO 80461",
    "addr:housenumber":"12655",
    "addr:postcode":"80461",
    "addr:street":"Us Hwy 24",
    "iso:country":"US",
    "sg:address":"12655 US Hwy 24",
    "sg:city":"Leadville",
    "sg:classifiers":[
        {
            "category":"Professional",
            "subcategory":"Management & Consulting",
            "type":"Services"
        }
    ],
    "sg:phone":"+1 719 486 5100",
    "sg:postcode":"80461",
    "sg:province":"CO",
    "sg:tags":[
        "marketing",
        "program"
    ],
    "wof:name":"Advanced Marketing",
    "wof:placetype":"venue"
},
  "geometry": {"coordinates":[-106.34859,39.222263],"type":"Point"}
}