{
  "type": "Feature",
  "properties": {
    "addr:full":"2747 E Las Vegas St Colorado Springs CO 80906",
    "addr:housenumber":"2747",
    "addr:postcode":"80906",
    "addr:street":"E Las Vegas St",
    "iso:country":"US",
    "sg:address":"2747 E Las Vegas St",
    "sg:city":"Colorado Springs",
    "sg:classifiers":[
        {
            "category":"Government",
            "subcategory":"Police Station",
            "type":"Public Place"
        }
    ],
    "sg:phone":"+1 719 390 2490",
    "sg:postcode":"80906",
    "sg:province":"CO",
    "sg:tags":[
        "sheriff"
    ],
    "wof:name":"El Paso Cnty Sheriff Fleet Svc",
    "wof:placetype":"venue"
},
  "geometry": {"coordinates":[-104.776763,38.787967],"type":"Point"}
}