{
  "type": "Feature",
  "properties": {
    "iso:country":"US",
    "sg:address":"300 Union Blvd",
    "sg:city":"Lakewood",
    "sg:classifiers":[
        {
            "category":"Banks & Credit Unions",
            "subcategory":"Bank",
            "type":"Services"
        }
    ],
    "sg:phone":"+1 303 984 7201",
    "sg:postcode":"80228",
    "sg:province":"CO",
    "sg:tags":[
        "loan",
        "real estate"
    ],
    "sg:website":"www.gmac.com",
    "wof:name":"GMAC Mortgage",
    "wof:placetype":"venue"
},
  "geometry": {"coordinates":[-105.132205,39.721126],"type":"Point"}
}