{
  "type": "Feature",
  "properties": {
    "iso:country":"US",
    "sg:address":"46 Yarborough Ln",
    "sg:city":"Coaldale",
    "sg:classifiers":[
        {
            "category":"Building & Trades",
            "subcategory":"Construction",
            "type":"Services"
        }
    ],
    "sg:phone":"+1 719 942 4303",
    "sg:postcode":"81222",
    "sg:province":"CO",
    "sg:tags":[
        "water",
        "well",
        "drilling"
    ],
    "wof:name":"Moody Drilling",
    "wof:placetype":"venue"
},
  "geometry": {"coordinates":[-105.761685,38.357225],"type":"Point"}
}