{
  "type": "Feature",
  "properties": {
    "iso:country":"US",
    "sg:address":"5478 Balsam Ct",
    "sg:city":"Arvada",
    "sg:classifiers":[
        {
            "category":"Professional",
            "type":"Services"
        }
    ],
    "sg:phone":"+1 303 421 2712",
    "sg:postcode":"80002",
    "sg:province":"CO",
    "wof:name":"Halvorson Slade Inc",
    "wof:placetype":"venue"
},
  "geometry": {"coordinates":[-105.089508,39.796415],"type":"Point"}
}