{
  "type": "Feature",
  "properties": {
    "iso:country":"US",
    "sg:address":"19700 Co Rd 96",
    "sg:city":"Pierce",
    "sg:classifiers":[
        {
            "category":"Farming",
            "subcategory":"Farm & Veterinary Services",
            "type":"Manufacturing & Wholesale Goods"
        }
    ],
    "sg:phone":"+1 970 834 2094",
    "sg:postcode":"80650",
    "sg:province":"CO",
    "sg:tags":[
        "breeder",
        "livestock"
    ],
    "wof:name":"Miller Cattle Feeders",
    "wof:placetype":"venue"
},
  "geometry": {"coordinates":[-104.68613999999999,40.682277],"type":"Point"}
}