{
  "type": "Feature",
  "properties": {
    "addr:full":"4200 E 50th Ave Denver CO 80216",
    "addr:housenumber":"4200",
    "addr:postcode":"80216",
    "addr:street":"E 50Th Ave",
    "iso:country":"US",
    "sg:address":"4200 E 50th Ave",
    "sg:city":"Denver",
    "sg:classifiers":[
        {
            "category":"Professional",
            "type":"Services"
        }
    ],
    "sg:phone":"+1 720 941 8355",
    "sg:postcode":"80216",
    "sg:province":"CO",
    "wof:name":"Buehler Alliance",
    "wof:placetype":"venue"
},
  "geometry": {"coordinates":[-104.93161499999999,39.787051],"type":"Point"}
}