{
  "type": "Feature",
  "properties": {
    "addr:full":"3137 Worchester St Aurora CO 80011",
    "addr:housenumber":"3137",
    "addr:postcode":"80011",
    "addr:street":"Worchester St",
    "iso:country":"US",
    "sg:address":"3137 Worchester St",
    "sg:city":"Aurora",
    "sg:classifiers":[
        {
            "category":"Shopping",
            "subcategory":"Music",
            "type":"Retail Goods"
        }
    ],
    "sg:phone":"+1 303 367 9247",
    "sg:postcode":"80011",
    "sg:province":"CO",
    "wof:name":"Cut Like That Records Pro",
    "wof:placetype":"venue"
},
  "geometry": {"coordinates":[-104.830056,39.761363],"type":"Point"}
}