{
  "type": "Feature",
  "properties": {
    "addr:full":"106 W 4th Ave Antonito CO 81120",
    "addr:housenumber":"106",
    "addr:postcode":"81120",
    "addr:street":"W 4Th Ave",
    "iso:country":"US",
    "sg:address":"106 W 4th Ave",
    "sg:city":"Antonito",
    "sg:classifiers":[
        {
            "category":"Personal",
            "subcategory":"Beauty Salon",
            "type":"Services"
        }
    ],
    "sg:phone":"+1 719 376 2074",
    "sg:postcode":"81120",
    "sg:province":"CO",
    "wof:name":"Hair Studio",
    "wof:placetype":"venue"
},
  "geometry": {"coordinates":[-106.00941,37.074937],"type":"Point"}
}