{
  "type": "Feature",
  "properties": {
    "iso:country":"US",
    "sg:address":"9903 Titan Ct",
    "sg:city":"Littleton",
    "sg:classifiers":[
        {
            "category":"Home & Garden",
            "subcategory":"Building Materials",
            "type":"Retail Goods"
        },
        {
            "category":"Building & Trades",
            "subcategory":"Construction",
            "type":"Services"
        }
    ],
    "sg:phone":"+1 303 797 3667",
    "sg:postcode":"80125",
    "sg:province":"CO",
    "sg:tags":[
        "repair",
        "installation",
        "do",
        "sales",
        "garage",
        "overhead",
        "door",
        "type"
    ],
    "sg:website":"www.rmds.com",
    "wof:name":"Rocky Mountain Door Systems",
    "wof:placetype":"venue"
},
  "geometry": {"coordinates":[-105.01991700000001,39.505721],"type":"Point"}
}