{
  "type": "Feature",
  "properties": {
    "iso:country":"US",
    "sg:address":"6363 W 120th Ave",
    "sg:city":"Broomfield",
    "sg:classifiers":[
        {
            "category":"Health Services",
            "subcategory":"Doctor",
            "type":"Services"
        }
    ],
    "sg:phone":"+1 303 635 0045",
    "sg:postcode":"80020",
    "sg:province":"CO",
    "sg:tags":[
        "medical"
    ],
    "wof:name":"Rocky Mounatin Primary Care",
    "wof:placetype":"venue"
},
  "geometry": {"coordinates":[-105.066974,39.914296],"type":"Point"}
}