{
  "type": "Feature",
  "properties": {
    "iso:country":"US",
    "sg:address":"219 Edison St",
    "sg:city":"Brush",
    "sg:classifiers":[
        {
            "category":"Banks & Credit Unions",
            "subcategory":"Bank",
            "type":"Services"
        }
    ],
    "sg:phone":"+1 970 842 4711",
    "sg:postcode":"80723",
    "sg:province":"CO",
    "sg:tags":[
        "loan",
        "real estate"
    ],
    "wof:name":"Colorado Financial Corp",
    "wof:placetype":"venue"
},
  "geometry": {"coordinates":[-103.620813,40.255413],"type":"Point"}
}