{
  "type": "Feature",
  "properties": {
    "addr:full":"10155 Westmoor Dr Broomfield CO 80021",
    "addr:housenumber":"10155",
    "addr:postcode":"80021",
    "addr:street":"Westmoor Dr",
    "iso:country":"US",
    "sg:address":"10155 Westmoor Dr",
    "sg:city":"Broomfield",
    "sg:classifiers":[
        {
            "category":"Banks & Credit Unions",
            "subcategory":"Financial Services",
            "type":"Services"
        }
    ],
    "sg:phone":"+1 303 450 5252",
    "sg:postcode":"80021",
    "sg:province":"CO",
    "sg:tags":[
        "investor"
    ],
    "wof:name":"Hutton Acquisition Corporation",
    "wof:placetype":"venue"
},
  "geometry": {"coordinates":[-105.115056,39.898172],"type":"Point"}
}