{
  "type": "Feature",
  "properties": {
    "iso:country":"US",
    "sg:address":"213 E 29th St",
    "sg:city":"Loveland",
    "sg:phone":"+1 970 593 0655",
    "sg:postcode":"80538",
    "sg:province":"CO",
    "sg:website":"http://www.applebees.com",
    "wof:name":"Applebee's",
    "wof:placetype":"venue"
},
  "geometry": {"coordinates":[-105.075648,40.421676],"type":"Point"}
}