{
  "type": "Feature",
  "properties": {
    "addr:full":"13840 Gleneagle Dr Colorado Springs CO 80921",
    "addr:housenumber":"13840",
    "addr:postcode":"80921",
    "addr:street":"Gleneagle Dr",
    "iso:country":"US",
    "sg:address":"13840 Gleneagle Dr",
    "sg:city":"Colorado Springs",
    "sg:classifiers":[
        {
            "category":"Organizations",
            "subcategory":"Religious Organization",
            "type":"Services"
        }
    ],
    "sg:phone":"+1 719 481 3528",
    "sg:postcode":"80921",
    "sg:province":"CO",
    "sg:website":"www.outreachofhope.org",
    "wof:name":"Dave Dravecky Outreach-Hope",
    "wof:placetype":"venue"
},
  "geometry": {"coordinates":[-104.830946,39.030752],"type":"Point"}
}