{
  "type": "Feature",
  "properties": {
    "iso:country":"US",
    "sg:address":"3013 N Hancock Ave",
    "sg:city":"Colorado Springs",
    "sg:classifiers":[
        {
            "category":"Retail",
            "subcategory":"Repair Shop",
            "type":"Services"
        }
    ],
    "sg:phone":"+1 719 471 0095",
    "sg:postcode":"80907",
    "sg:province":"CO",
    "sg:tags":[
        "locksmith"
    ],
    "wof:name":"Colorado State Safe & Lock Co",
    "wof:placetype":"venue"
},
  "geometry": {"coordinates":[-104.803344,38.873345],"type":"Point"}
}