{
  "type": "Feature",
  "properties": {
    "addr:full":"313 N Fork Ave Paonia CO 81428",
    "addr:housenumber":"313",
    "addr:postcode":"81428",
    "addr:street":"N Fork Ave",
    "iso:country":"US",
    "sg:address":"313 N Fork Ave",
    "sg:city":"Paonia",
    "sg:classifiers":[
        {
            "category":"Wholesale",
            "subcategory":"Non-durable Goods",
            "type":"Manufacturing & Wholesale Goods"
        }
    ],
    "sg:phone":"+1 970 527 6395",
    "sg:postcode":"81428",
    "sg:province":"CO",
    "sg:tags":[
        "leather"
    ],
    "wof:name":"Kendall Braiding Co",
    "wof:placetype":"venue"
},
  "geometry": {"coordinates":[-107.592997,38.869115],"type":"Point"}
}