{
  "type": "Feature",
  "properties": {
    "addr:full":"4181 Everett Dr Wheat Ridge CO 80033",
    "addr:housenumber":"4181",
    "addr:postcode":"80033",
    "addr:street":"Everett Dr",
    "iso:country":"US",
    "sg:address":"4181 Everett Dr",
    "sg:city":"Wheat Ridge",
    "sg:classifiers":[
        {
            "category":"Professional",
            "type":"Services"
        }
    ],
    "sg:phone":"+1 303 420 5145",
    "sg:postcode":"80033",
    "sg:province":"CO",
    "wof:name":"Foster Jeffco Family Asso",
    "wof:placetype":"venue"
},
  "geometry": {"coordinates":[-105.096636,39.773396],"type":"Point"}
}