{
  "type": "Feature",
  "properties": {
    "addr:full":"2010 16th St Boulder CO 80302",
    "addr:housenumber":"2010",
    "addr:postcode":"80302",
    "addr:street":"16Th St",
    "iso:country":"US",
    "sg:address":"2010 16th St",
    "sg:city":"Boulder",
    "sg:classifiers":[
        {
            "category":"Restaurant",
            "type":"Food & Drink"
        }
    ],
    "sg:menulink":"http://www.allmenus.com/co/boulder/4093-leaf-vegetarian-restaurant/menu/",
    "sg:phone":"+1 303 442 1485",
    "sg:postcode":"80302",
    "sg:province":"CO",
    "sg:tags":[
        "vegetarian",
        "american",
        "salad"
    ],
    "wof:name":"Leaf Vegetarian Restaurant",
    "wof:placetype":"venue"
},
  "geometry": {"coordinates":[-105.274773,40.019094],"type":"Point"}
}