{
  "type": "Feature",
  "properties": {
    "addr:full":"4500 US Hwy 36 Joes CO 80822",
    "addr:housenumber":"4500",
    "addr:postcode":"80822",
    "addr:street":"Us Hwy 36",
    "iso:country":"US",
    "sg:address":"4500 US Hwy 36",
    "sg:city":"Joes",
    "sg:classifiers":[
        {
            "category":"Building & Trades",
            "subcategory":"Construction",
            "type":"Services"
        }
    ],
    "sg:phone":"+1 970 358 4204",
    "sg:postcode":"80822",
    "sg:province":"CO",
    "sg:tags":[
        "excavating",
        "contractor"
    ],
    "wof:name":"Hastings Trenching & Backhoe",
    "wof:placetype":"venue"
},
  "geometry": {"coordinates":[-102.716517,39.655853],"type":"Point"}
}