{
  "type": "Feature",
  "properties": {
    "addr:full":"2414 Keystone Ct Boulder CO 80304",
    "addr:housenumber":"2414",
    "addr:postcode":"80304",
    "addr:street":"Keystone Ct",
    "iso:country":"US",
    "sg:address":"2414 Keystone Ct",
    "sg:city":"Boulder",
    "sg:classifiers":[
        {
            "category":"Professional",
            "type":"Services"
        }
    ],
    "sg:phone":"+1 303 544 5910",
    "sg:postcode":"80304",
    "sg:province":"CO",
    "wof:name":"Ann E Roddy",
    "wof:placetype":"venue"
},
  "geometry": {"coordinates":[-105.26613500000001,40.038563],"type":"Point"}
}