{
  "type": "Feature",
  "properties": {
    "addr:full":"3360 Mitchell Ln Boulder CO 80301",
    "addr:housenumber":"3360",
    "addr:postcode":"80301",
    "addr:street":"Mitchell Ln",
    "iso:country":"US",
    "sg:address":"3360 Mitchell Ln",
    "sg:city":"Boulder",
    "sg:classifiers":[
        {
            "category":"Manufacturing",
            "subcategory":"Printing",
            "type":"Manufacturing & Wholesale Goods"
        }
    ],
    "sg:phone":"+1 303 245 9054",
    "sg:postcode":"80301",
    "sg:province":"CO",
    "sg:tags":[
        "publisher"
    ],
    "wof:name":"Paradigm Publishers",
    "wof:placetype":"venue"
},
  "geometry": {"coordinates":[-105.243673,40.035295],"type":"Point"}
}