{
  "type": "Feature",
  "properties": {
    "addr:full":"45 Village Pl Snowmass Village CO 81632",
    "addr:housenumber":"45",
    "addr:postcode":"81632",
    "addr:street":"Village Pl",
    "iso:country":"US",
    "sg:address":"45 Village Pl",
    "sg:city":"Snowmass Village",
    "sg:classifiers":[
        {
            "category":"Recreation",
            "type":"Entertainment"
        }
    ],
    "sg:phone":"+1 970 923 3443",
    "sg:postcode":"81632",
    "sg:province":"CO",
    "sg:tags":[
        "equipment",
        "skiing"
    ],
    "wof:name":"Breeze Ski Rentals",
    "wof:placetype":"venue"
},
  "geometry": {"coordinates":[-106.566802,39.633455],"type":"Point"}
}