{
  "type": "Feature",
  "properties": {
    "addr:full":"304 Eagle St Minturn CO 81645",
    "addr:housenumber":"304",
    "addr:postcode":"81645",
    "addr:street":"Eagle St",
    "iso:country":"US",
    "sg:address":"304 Eagle St",
    "sg:city":"Minturn",
    "sg:classifiers":[
        {
            "category":"Building & Trades",
            "subcategory":"Construction",
            "type":"Services"
        }
    ],
    "sg:phone":"+1 970 827 4118",
    "sg:postcode":"81645",
    "sg:province":"CO",
    "sg:tags":[
        "tile",
        "dealer"
    ],
    "wof:name":"Trygve Tile",
    "wof:placetype":"venue"
},
  "geometry": {"coordinates":[-106.42884100000001,39.586482],"type":"Point"}
}