{
  "type": "Feature",
  "properties": {
    "iso:country":"US",
    "sg:address":"9999 W 60th Ave",
    "sg:city":"Arvada",
    "sg:classifiers":[
        {
            "category":"Health Services",
            "subcategory":"Doctor",
            "type":"Services"
        }
    ],
    "sg:phone":"+1 303 423 0930",
    "sg:postcode":"80004",
    "sg:province":"CO",
    "sg:tags":[
        "dentist"
    ],
    "wof:name":"Robert M Eyer DDS",
    "wof:placetype":"venue"
},
  "geometry": {"coordinates":[-105.107714,39.806011],"type":"Point"}
}