{
  "type": "Feature",
  "properties": {
    "addr:full":"4600 Peoria St Denver CO 80239",
    "addr:housenumber":"4600",
    "addr:postcode":"80239",
    "addr:street":"Peoria St",
    "iso:country":"US",
    "sg:address":"4600 Peoria St",
    "sg:city":"Denver",
    "sg:classifiers":[
        {
            "category":"Restaurant",
            "type":"Food & Drink"
        }
    ],
    "sg:phone":"+1 303 371 0151",
    "sg:postcode":"80239",
    "sg:province":"CO",
    "sg:tags":[
        "fast"
    ],
    "wof:name":"Rob-Kraft Inc",
    "wof:placetype":"venue"
},
  "geometry": {"coordinates":[-104.84701,39.782385],"type":"Point"}
}