{
  "type": "Feature",
  "properties": {
    "addr:full":"42 N Amherst St Colorado Springs CO 80911",
    "addr:housenumber":"42",
    "addr:postcode":"80911",
    "addr:street":"N Amherst St",
    "iso:country":"US",
    "sg:address":"42 N Amherst St",
    "sg:city":"Colorado Springs",
    "sg:classifiers":[
        {
            "category":"Building & Trades",
            "subcategory":"Construction",
            "type":"Services"
        }
    ],
    "sg:phone":"+1 719 635 1712",
    "sg:postcode":"80911",
    "sg:province":"CO",
    "sg:tags":[
        "windows"
    ],
    "wof:name":"Frank Hicks Glass",
    "wof:placetype":"venue"
},
  "geometry": {"coordinates":[-104.722354,38.741564],"type":"Point"}
}