{
  "type": "Feature",
  "properties": {
    "iso:country":"US",
    "sg:address":"22487 US Hwy 385",
    "sg:city":"Burlington",
    "sg:phone":"+1 719 346 5016",
    "sg:postcode":"80807",
    "sg:province":"CO",
    "sg:tags":[
        "farm",
        "wheat",
        "livestock"
    ],
    "wof:name":"R & R Farms",
    "wof:placetype":"venue"
},
  "geometry": {"coordinates":[-102.259676,39.370302],"type":"Point"}
}