{
  "type": "Feature",
  "properties": {
    "iso:country":"US",
    "sg:address":"269 McCaslin Blvd",
    "sg:city":"Louisville",
    "sg:classifiers":[
        {
            "category":"Restaurant",
            "type":"Food & Drink"
        }
    ],
    "sg:phone":"+1 720 890 0999",
    "sg:postcode":"80027",
    "sg:province":"CO",
    "sg:tags":[
        "eating"
    ],
    "sg:website":"www.spicechina.com",
    "wof:name":"Spice China",
    "wof:placetype":"venue"
},
  "geometry": {"coordinates":[-105.165537,39.953133],"type":"Point"}
}