{
  "type": "Feature",
  "properties": {
    "iso:country":"US",
    "sg:address":"15 Highlands Ln",
    "sg:city":"Avon",
    "sg:classifiers":[
        {
            "category":"Real Estate",
            "subcategory":"Real Estate Agent",
            "type":"Services"
        },
        {
            "category":"Professional",
            "subcategory":"Management & Consulting",
            "type":"Services"
        }
    ],
    "sg:phone":"+1 970 949 5071",
    "sg:postcode":"81620",
    "sg:province":"CO",
    "sg:tags":[
        "prop"
    ],
    "wof:name":"East West Resorts Llc",
    "wof:placetype":"venue"
},
  "geometry": {"coordinates":[-106.513086,39.60455],"type":"Point"}
}