{
  "type": "Feature",
  "properties": {
    "addr:full":"611 S Broadway St Boulder CO 80305",
    "addr:housenumber":"611",
    "addr:postcode":"80305",
    "addr:street":"S Broadway St",
    "iso:country":"US",
    "sg:address":"611 S Broadway St",
    "sg:city":"Boulder",
    "sg:classifiers":[
        {
            "category":"Cinema",
            "subcategory":"Movie Rental",
            "type":"Entertainment"
        }
    ],
    "sg:phone":"+1 303 554 0150",
    "sg:postcode":"80305",
    "sg:province":"CO",
    "sg:tags":[
        "leasing",
        "video",
        "disc",
        "tape"
    ],
    "wof:name":"Movie Gallery",
    "wof:placetype":"venue"
},
  "geometry": {"coordinates":[-105.243123,39.977813],"type":"Point"}
}