{
  "type": "Feature",
  "properties": {
    "addr:full":"9201 W Columbine Dr Littleton CO 80128",
    "addr:housenumber":"9201",
    "addr:postcode":"80128",
    "addr:street":"W Columbine Dr",
    "iso:country":"US",
    "sg:address":"9201 W Columbine Dr",
    "sg:city":"Littleton",
    "sg:classifiers":[
        {
            "category":"Education",
            "subcategory":"School",
            "type":"Public Place"
        }
    ],
    "sg:phone":"+1 303 982 3820",
    "sg:postcode":"80128",
    "sg:province":"CO",
    "sg:tags":[
        "middle"
    ],
    "wof:name":"Deer Creek Middle School",
    "wof:placetype":"venue"
},
  "geometry": {"coordinates":[-105.105661,39.584648],"type":"Point"}
}