{
  "type": "Feature",
  "properties": {
    "addr:full":"23044 Co Rd 742 Almont CO 81210",
    "addr:housenumber":"23044;742",
    "addr:postcode":"81210",
    "addr:street":"Co Rd",
    "iso:country":"US",
    "sg:address":"23044 Co Rd 742",
    "sg:city":"Almont",
    "sg:classifiers":[
        {
            "category":"Restaurant",
            "type":"Food & Drink"
        }
    ],
    "sg:phone":"+1 970 642 0454",
    "sg:postcode":"81210",
    "sg:province":"CO",
    "wof:name":"Nugget Cafe",
    "wof:placetype":"venue"
},
  "geometry": {"coordinates":[-106.55882699999999,38.819492],"type":"Point"}
}