{
  "type": "Feature",
  "properties": {
    "addr:full":"17265 Shahara Rd Monument CO 80132",
    "addr:housenumber":"17265",
    "addr:postcode":"80132",
    "addr:street":"Shahara Rd",
    "iso:country":"US",
    "sg:address":"17265 Shahara Rd",
    "sg:city":"Monument",
    "sg:classifiers":[
        {
            "category":"Manufacturing",
            "subcategory":"Tools & Machinery",
            "type":"Manufacturing & Wholesale Goods"
        }
    ],
    "sg:phone":"+1 719 488 3505",
    "sg:postcode":"80132",
    "sg:province":"CO",
    "sg:tags":[
        "shop",
        "machine",
        "job",
        "metal",
        "fabrication"
    ],
    "wof:name":"Tri Lakes Machine Co",
    "wof:placetype":"venue"
},
  "geometry": {"coordinates":[-104.782461,39.082703],"type":"Point"}
}