{
  "type": "Feature",
  "properties": {
    "iso:country":"US",
    "sg:address":"7777 W Jewell Ave",
    "sg:city":"Lakewood",
    "sg:classifiers":[
        {
            "category":"Shopping",
            "type":"Retail Goods"
        }
    ],
    "sg:phone":"+1 303 985 0077",
    "sg:postcode":"80232",
    "sg:province":"CO",
    "sg:tags":[
        "equipment",
        "pool",
        "swimming"
    ],
    "wof:name":"Marina Pool Spa & Patio",
    "wof:placetype":"venue"
},
  "geometry": {"coordinates":[-105.086242,39.682302],"type":"Point"}
}