{
  "type": "Feature",
  "properties": {
    "iso:country":"US",
    "sg:address":"102 S Washington St",
    "sg:city":"Otis",
    "sg:classifiers":[
        {
            "category":"Government",
            "subcategory":"Office",
            "type":"Public Place"
        }
    ],
    "sg:phone":"+1 970 246 3235",
    "sg:postcode":"80743",
    "sg:province":"CO",
    "sg:tags":[
        "city"
    ],
    "wof:name":"Town Hall",
    "wof:placetype":"venue"
},
  "geometry": {"coordinates":[-102.961455,40.149073],"type":"Point"}
}