{
  "type": "Feature",
  "properties": {
    "iso:country":"US",
    "sg:address":"10292 S Progress Way",
    "sg:city":"Parker",
    "sg:classifiers":[
        {
            "category":"Social Services",
            "type":"Services"
        }
    ],
    "sg:phone":"+1 303 840 2636",
    "sg:postcode":"80134",
    "sg:province":"CO",
    "sg:tags":[
        "counselor",
        "marriage",
        "family"
    ],
    "wof:name":"First Step Counseling",
    "wof:placetype":"venue"
},
  "geometry": {"coordinates":[-104.769221,39.530093],"type":"Point"}
}