{
  "type": "Feature",
  "properties": {
    "iso:country":"US",
    "sg:address":"7600 Park Meadows Dr",
    "sg:city":"Lone Tree",
    "sg:classifiers":[
        {
            "category":"Social Services",
            "subcategory":"Child Care",
            "type":"Services"
        }
    ],
    "sg:phone":"+1 303 858 0055",
    "sg:postcode":"80124",
    "sg:province":"CO",
    "sg:website":"www.planetplaykids.com",
    "wof:name":"Planet Play",
    "wof:placetype":"venue"
},
  "geometry": {"coordinates":[-104.89846799999999,39.562572],"type":"Point"}
}