{
  "type": "Feature",
  "properties": {
    "addr:full":"1705 W Baltic Pl Englewood CO 80110",
    "addr:housenumber":"1705",
    "addr:postcode":"80110",
    "addr:street":"W Baltic Pl",
    "iso:country":"US",
    "sg:address":"1705 W Baltic Pl",
    "sg:city":"Englewood",
    "sg:classifiers":[
        {
            "category":"Retail",
            "subcategory":"Auto Repair",
            "type":"Services"
        }
    ],
    "sg:phone":"+1 303 471 6992",
    "sg:postcode":"80110",
    "sg:province":"CO",
    "sg:tags":[
        "body",
        "automobile",
        "painting"
    ],
    "wof:name":"Bumper To Bumper Auto Body",
    "wof:placetype":"venue"
},
  "geometry": {"coordinates":[-105.007773,39.675973],"type":"Point"}
}