{
  "type": "Feature",
  "properties": {
    "iso:country":"US",
    "sg:address":"417 S Broadway",
    "sg:city":"Denver",
    "sg:classifiers":[
        {
            "category":"Home & Garden",
            "subcategory":"Hardware",
            "type":"Retail Goods"
        }
    ],
    "sg:phone":"+1 303 733 3399",
    "sg:postcode":"80209",
    "sg:province":"CO",
    "sg:tags":[
        "store"
    ],
    "wof:name":"Clear Reach Networks",
    "wof:placetype":"venue"
},
  "geometry": {"coordinates":[-104.987771,39.709068],"type":"Point"}
}