{
  "type": "Feature",
  "properties": {
    "iso:country":"US",
    "sg:address":"2701 S York St",
    "sg:city":"Denver",
    "sg:classifiers":[
        {
            "category":"Place Of Worship",
            "type":"Public Place"
        },
        {
            "category":"Education",
            "subcategory":"School",
            "type":"Public Place"
        }
    ],
    "sg:phone":"+1 303 756 9481",
    "sg:postcode":"80210",
    "sg:province":"CO",
    "sg:tags":[
        "k-",
        "high",
        "middle",
        "private",
        "church",
        "elementary"
    ],
    "sg:website":"http://www.st-annes.org",
    "wof:name":"St Anne's Episcopal School",
    "wof:placetype":"venue"
},
  "geometry": {"coordinates":[-104.959999,39.668201],"type":"Point"}
}