{
  "type": "Feature",
  "properties": {
    "iso:country":"US",
    "sg:address":"2375 Telstar Dr",
    "sg:city":"Colorado Springs",
    "sg:classifiers":[
        {
            "category":"Health Services",
            "subcategory":"Health Practitioner",
            "type":"Services"
        }
    ],
    "sg:phone":"+1 719 590 7777",
    "sg:postcode":"80920",
    "sg:province":"CO",
    "sg:tags":[
        "occupational",
        "therapist"
    ],
    "wof:name":"P T Works",
    "wof:placetype":"venue"
},
  "geometry": {"coordinates":[-104.788279,38.958658],"type":"Point"}
}