{
  "type": "Feature",
  "properties": {
    "iso:country":"US",
    "sg:address":"7402 E Alameda Ave",
    "sg:city":"Denver",
    "sg:classifiers":[
        {
            "category":"Organizations",
            "subcategory":"Non-profit Organization",
            "type":"Services"
        }
    ],
    "sg:phone":"+1 303 322 3895",
    "sg:postcode":"80247",
    "sg:province":"CO",
    "sg:tags":[
        "service/non-profit",
        "community"
    ],
    "wof:name":"Fairmont Heritage Foundation",
    "wof:placetype":"venue"
},
  "geometry": {"coordinates":[-104.90260499999999,39.711204],"type":"Point"}
}