{
  "type": "Feature",
  "properties": {
    "addr:full":"152 Wolf Rd Golden CO 80403",
    "addr:housenumber":"152",
    "addr:postcode":"80403",
    "addr:street":"Wolf Rd",
    "iso:country":"US",
    "sg:address":"152 Wolf Rd",
    "sg:city":"Golden",
    "sg:classifiers":[
        {
            "category":"Building & Trades",
            "subcategory":"Construction",
            "type":"Services"
        }
    ],
    "sg:phone":"+1 303 582 3969",
    "sg:postcode":"80403",
    "sg:province":"CO",
    "sg:tags":[
        "excavating",
        "sub"
    ],
    "wof:name":"Blackhawk Builders",
    "wof:placetype":"venue"
},
  "geometry": {"coordinates":[-105.48915100000001,39.827523],"type":"Point"}
}