{
  "type": "Feature",
  "properties": {
    "iso:country":"US",
    "sg:address":"301 N Main St",
    "sg:city":"Pueblo",
    "sg:classifiers":[
        {
            "category":"Social Services",
            "type":"Services"
        }
    ],
    "sg:phone":"+1 719 544 1965",
    "sg:postcode":"81003",
    "sg:province":"CO",
    "sg:tags":[
        "counselor",
        "marriage",
        "family"
    ],
    "wof:name":"Gambling Recovery Counseling",
    "wof:placetype":"venue"
},
  "geometry": {"coordinates":[-104.608576,38.270201],"type":"Point"}
}