{
  "type": "Feature",
  "properties": {
    "iso:country":"US",
    "sg:address":"350 Kimbark St",
    "sg:city":"Longmont",
    "sg:classifiers":[
        {
            "category":"Professional",
            "subcategory":"Employment Agencies",
            "type":"Services"
        }
    ],
    "sg:phone":"+1 303 651 8609",
    "sg:postcode":"80501",
    "sg:province":"CO",
    "wof:name":"City Personnel",
    "wof:placetype":"venue"
},
  "geometry": {"coordinates":[-105.101113,40.164814],"type":"Point"}
}