{
  "type": "Feature",
  "properties": {
    "iso:country":"US",
    "sg:address":"6330 Tennyson Street",
    "sg:city":"Arvada",
    "sg:classifiers":[
        {
            "category":"Education",
            "subcategory":"School",
            "type":"Public Place"
        }
    ],
    "sg:phone":"+1 303 429 4090",
    "sg:postcode":"80003",
    "sg:province":"CO",
    "sg:tags":[
        "high",
        "middle",
        "elementary"
    ],
    "wof:name":"Schools-Public",
    "wof:placetype":"venue"
},
  "geometry": {"coordinates":[-105.04393,39.811228],"type":"Point"}
}