{
  "type": "Feature",
  "properties": {
    "iso:country":"US",
    "sg:address":"2020 N Academy Blvd",
    "sg:city":"Colorado Springs",
    "sg:classifiers":[
        {
            "category":"Professional",
            "subcategory":"Engineering",
            "type":"Services"
        }
    ],
    "sg:phone":"+1 719 591 7200",
    "sg:postcode":"80909",
    "sg:province":"CO",
    "wof:name":"Lockheed Martin",
    "wof:placetype":"venue"
},
  "geometry": {"coordinates":[-104.757375,38.861718],"type":"Point"}
}