{
  "type": "Feature",
  "properties": {
    "addr:full":"8101 E Belleview Ave Denver CO 80237",
    "addr:housenumber":"8101",
    "addr:postcode":"80237",
    "addr:street":"E Belleview Ave",
    "iso:country":"US",
    "sg:address":"8101 E Belleview Ave",
    "sg:city":"Denver",
    "sg:classifiers":[
        {
            "category":"Real Estate",
            "subcategory":"Real Estate Agent",
            "type":"Services"
        }
    ],
    "sg:phone":"+1 303 478 8441",
    "sg:postcode":"80237",
    "sg:province":"CO",
    "wof:name":"Duggan Realty",
    "wof:placetype":"venue"
},
  "geometry": {"coordinates":[-104.891733,39.624114],"type":"Point"}
}