{
  "type": "Feature",
  "properties": {
    "iso:country":"US",
    "sg:address":"1508 Ambrosia Pl",
    "sg:city":"Fort Collins",
    "sg:classifiers":[
        {
            "category":"Professional",
            "type":"Services"
        }
    ],
    "sg:phone":"+1 970 282 8474",
    "sg:postcode":"80526",
    "sg:province":"CO",
    "wof:name":"James C Abbott",
    "wof:placetype":"venue"
},
  "geometry": {"coordinates":[-105.104181,40.536974],"type":"Point"}
}