{
  "type": "Feature",
  "properties": {
    "iso:country":"US",
    "sg:address":"1250 S Buckley Rd",
    "sg:city":"Aurora",
    "sg:classifiers":[
        {
            "category":"Food & Beverages",
            "subcategory":"Liquor & Beverages",
            "type":"Retail Goods"
        }
    ],
    "sg:phone":"+1 720 747 9332",
    "sg:postcode":"80017",
    "sg:province":"CO",
    "wof:name":"Somerset Liquor",
    "wof:placetype":"venue"
},
  "geometry": {"coordinates":[-104.79098999999999,39.694206],"type":"Point"}
}