{
  "type": "Feature",
  "properties": {
    "addr:full":"6257 Lakepoint Pl Parker CO 80134",
    "addr:housenumber":"6257",
    "addr:postcode":"80134",
    "addr:street":"Lakepoint Pl",
    "iso:country":"US",
    "sg:address":"6257 Lakepoint Pl",
    "sg:city":"Parker",
    "sg:classifiers":[
        {
            "category":"Professional",
            "subcategory":"Management & Consulting",
            "type":"Services"
        }
    ],
    "sg:phone":"+1 303 840 1059",
    "sg:postcode":"80134",
    "sg:province":"CO",
    "sg:tags":[
        "association"
    ],
    "wof:name":"Association Resources Inc",
    "wof:placetype":"venue"
},
  "geometry": {"coordinates":[-104.740951,39.4545],"type":"Point"}
}