{
  "type": "Feature",
  "properties": {
    "addr:full":"1138 Manford Ave Estes Park CO 80517",
    "addr:housenumber":"1138",
    "addr:postcode":"80517",
    "addr:street":"Manford Ave",
    "iso:country":"US",
    "sg:address":"1138 Manford Ave",
    "sg:city":"Estes Park",
    "sg:classifiers":[
        {
            "category":"Home & Garden",
            "subcategory":"Carpets & Floor Coverings",
            "type":"Retail Goods"
        }
    ],
    "sg:phone":"+1 970 586 4042",
    "sg:postcode":"80517",
    "sg:province":"CO",
    "sg:tags":[
        "wallpaper",
        "drapery"
    ],
    "wof:name":"Abbey Carpet & Tile Of Estes",
    "wof:placetype":"venue"
},
  "geometry": {"coordinates":[-105.503816,40.371964],"type":"Point"}
}