{
  "type": "Feature",
  "properties": {
    "addr:full":"3565 22nd St Boulder CO 80304",
    "addr:housenumber":"3565",
    "addr:postcode":"80304",
    "addr:street":"22Nd St",
    "iso:country":"US",
    "sg:address":"3565 22nd St",
    "sg:city":"Boulder",
    "sg:classifiers":[
        {
            "category":"Manufacturing",
            "subcategory":"Retail Goods",
            "type":"Manufacturing & Wholesale Goods"
        }
    ],
    "sg:phone":"+1 303 440 8112",
    "sg:postcode":"80304",
    "sg:province":"CO",
    "sg:tags":[
        "manufacturer"
    ],
    "wof:name":"River Run Mfg",
    "wof:placetype":"venue"
},
  "geometry": {"coordinates":[-105.26855,40.037392],"type":"Point"}
}