{
  "type": "Feature",
  "properties": {
    "iso:country":"US",
    "sg:address":"17169 Cornerstone Dr",
    "sg:city":"Parker",
    "sg:classifiers":[
        {
            "category":"Shopping",
            "type":"Retail Goods"
        },
        {
            "category":"Wholesale",
            "subcategory":"Electrical",
            "type":"Manufacturing & Wholesale Goods"
        }
    ],
    "sg:phone":"+1 303 805 5588",
    "sg:postcode":"80134",
    "sg:province":"CO",
    "sg:tags":[
        "specializing",
        "communication",
        "sales",
        "system",
        "radio",
        "way",
        "rental",
        "com"
    ],
    "wof:name":"Sunny Communications Inc",
    "wof:placetype":"venue"
},
  "geometry": {"coordinates":[-104.788117,39.531136],"type":"Point"}
}