{
  "type": "Feature",
  "properties": {
    "addr:full":"1688 Ensenada Way Aurora CO 80011",
    "addr:housenumber":"1688",
    "addr:postcode":"80011",
    "addr:street":"Ensenada Way",
    "iso:country":"US",
    "sg:address":"1688 Ensenada Way",
    "sg:city":"Aurora",
    "sg:classifiers":[
        {
            "category":"Building & Trades",
            "subcategory":"Construction",
            "type":"Services"
        }
    ],
    "sg:phone":"+1 303 364 8823",
    "sg:postcode":"80011",
    "sg:province":"CO",
    "sg:tags":[
        "house"
    ],
    "wof:name":"RJS Construction",
    "wof:placetype":"venue"
},
  "geometry": {"coordinates":[-104.761105,39.742504],"type":"Point"}
}