{
  "type": "Feature",
  "properties": {
    "addr:full":"2121 W Northern Ave Pueblo CO 81004",
    "addr:housenumber":"2121",
    "addr:postcode":"81004",
    "addr:street":"W Northern Ave",
    "iso:country":"US",
    "sg:address":"2121 W Northern Ave",
    "sg:city":"Pueblo",
    "sg:classifiers":[
        {
            "category":"Shopping",
            "type":"Retail Goods"
        }
    ],
    "sg:phone":"+1 719 564 9618",
    "sg:postcode":"81004",
    "sg:province":"CO",
    "sg:tags":[
        "cards",
        "sport",
        "baseball",
        "memorabilia"
    ],
    "wof:name":"Rocky Mountain Sports Cards",
    "wof:placetype":"venue"
},
  "geometry": {"coordinates":[-104.636154,38.244159],"type":"Point"}
}