{
  "type": "Feature",
  "properties": {
    "addr:full":"1551 Wolff St Denver CO 80204",
    "addr:housenumber":"1551",
    "addr:postcode":"80204",
    "addr:street":"Wolff St",
    "iso:country":"US",
    "sg:address":"1551 Wolff St",
    "sg:city":"Denver",
    "sg:classifiers":[
        {
            "category":"Travel",
            "subcategory":"Hotels & Motels",
            "type":"Entertainment"
        }
    ],
    "sg:phone":"+1 303 534 7414",
    "sg:postcode":"80204",
    "sg:province":"CO",
    "wof:name":"Pig-N-Whistle",
    "wof:placetype":"venue"
},
  "geometry": {"coordinates":[-105.04874700000001,39.741246],"type":"Point"}
}