{
  "type": "Feature",
  "properties": {
    "iso:country":"US",
    "sg:address":"510 18th St",
    "sg:city":"Greeley",
    "sg:classifiers":[
        {
            "category":"Utilities",
            "subcategory":"Electric",
            "type":"Services"
        }
    ],
    "sg:phone":"+1 970 352 6700",
    "sg:postcode":"80631",
    "sg:province":"CO",
    "sg:tags":[
        "facility",
        "electricity",
        "gas",
        "t",
        "using",
        "producing"
    ],
    "wof:name":"Thermo Power & Electric Inc",
    "wof:placetype":"venue"
},
  "geometry": {"coordinates":[-104.684361,40.410031],"type":"Point"}
}