{
  "type": "Feature",
  "properties": {
    "addr:full":"5480 W 60th Ave Arvada CO 80003",
    "addr:housenumber":"5480",
    "addr:postcode":"80003",
    "addr:street":"W 60Th Ave",
    "iso:country":"US",
    "sg:address":"5480 W 60th Ave",
    "sg:city":"Arvada",
    "sg:classifiers":[
        {
            "category":"Wholesale",
            "subcategory":"Apparel",
            "type":"Manufacturing & Wholesale Goods"
        }
    ],
    "sg:phone":"+1 303 420 6626",
    "sg:postcode":"80003",
    "sg:province":"CO",
    "sg:tags":[
        "pantyhose"
    ],
    "wof:name":"LEggs Products",
    "wof:placetype":"venue"
},
  "geometry": {"coordinates":[-105.056059,39.805478],"type":"Point"}
}