{
  "type": "Feature",
  "properties": {
    "iso:country":"US",
    "sg:address":"201 W 67th Ct",
    "sg:city":"Loveland",
    "sg:classifiers":[
        {
            "category":"Retail",
            "subcategory":"Veterinary Services",
            "type":"Services"
        }
    ],
    "sg:phone":"+1 970 663 5760",
    "sg:postcode":"80538",
    "sg:province":"CO",
    "sg:tags":[
        "veterinarian"
    ],
    "wof:name":"Animal Emergency Svc-Northern",
    "wof:placetype":"venue"
},
  "geometry": {"coordinates":[-105.080168,40.461168],"type":"Point"}
}