{
  "type": "Feature",
  "properties": {
    "iso:country":"US",
    "sg:address":"2961 S Utica St",
    "sg:city":"Denver",
    "sg:classifiers":[
        {
            "category":"Building & Trades",
            "subcategory":"Locksmith",
            "type":"Services"
        }
    ],
    "sg:phone":"+1 303 566 0364",
    "sg:postcode":"80236",
    "sg:province":"CO",
    "sg:tags":[
        "key"
    ],
    "wof:name":"001 15 Minutes Express Locksmith",
    "wof:placetype":"venue"
},
  "geometry": {"coordinates":[-105.04631000000001,39.661138],"type":"Point"}
}