{
  "type": "Feature",
  "properties": {
    "addr:full":"2502 W Colorado Ave Colorado Springs CO 80904",
    "addr:housenumber":"2502",
    "addr:postcode":"80904",
    "addr:street":"W Colorado Ave",
    "iso:country":"US",
    "sg:address":"2502 W Colorado Ave",
    "sg:city":"Colorado Springs",
    "sg:classifiers":[
        {
            "category":"Health Services",
            "subcategory":"Clinic",
            "type":"Services"
        }
    ],
    "sg:phone":"+1 719 471 1404",
    "sg:postcode":"80904",
    "sg:province":"CO",
    "sg:tags":[
        "hypnotherapy"
    ],
    "wof:name":"Archways To Tomorrow",
    "wof:placetype":"venue"
},
  "geometry": {"coordinates":[-104.86411,38.848156],"type":"Point"}
}