{
  "type": "Feature",
  "properties": {
    "iso:country":"US",
    "sg:address":"2850 29th St",
    "sg:city":"Boulder",
    "sg:classifiers":[
        {
            "category":"Bars & Pubs",
            "type":"Food & Drink"
        },
        {
            "category":"Restaurant",
            "type":"Food & Drink"
        }
    ],
    "sg:phone":"+1 303 443 3787",
    "sg:postcode":"80301",
    "sg:province":"CO",
    "sg:tags":[
        "tavern",
        "brew"
    ],
    "wof:name":"Oscar's Pub",
    "wof:placetype":"venue"
},
  "geometry": {"coordinates":[-105.256023,40.027761],"type":"Point"}
}