{
  "type": "Feature",
  "properties": {
    "addr:full":"4181 S Yukon Way Denver CO 80235",
    "addr:housenumber":"4181",
    "addr:postcode":"80235",
    "addr:street":"S Yukon Way",
    "iso:country":"US",
    "sg:address":"4181 S Yukon Way",
    "sg:city":"Denver",
    "sg:classifiers":[
        {
            "category":"Real Estate",
            "subcategory":"Real Estate Agent",
            "type":"Services"
        }
    ],
    "sg:phone":"+1 303 985 0907",
    "sg:postcode":"80235",
    "sg:province":"CO",
    "wof:name":"HMS Real Estate",
    "wof:placetype":"venue"
},
  "geometry": {"coordinates":[-105.08282800000001,39.640732],"type":"Point"}
}