{
  "type": "Feature",
  "properties": {
    "addr:full":"23712 Co Rd 48 Arapahoe CO 80802",
    "addr:housenumber":"23712;48",
    "addr:postcode":"80802",
    "addr:street":"Co Rd",
    "iso:country":"US",
    "sg:address":"23712 Co Rd 48",
    "sg:city":"Arapahoe",
    "sg:phone":"+1 719 767 5257",
    "sg:postcode":"80802",
    "sg:province":"CO",
    "sg:tags":[
        "farm",
        "wheat"
    ],
    "wof:name":"Shirley Pharo",
    "wof:placetype":"venue"
},
  "geometry": {"coordinates":[-102.27807,38.945699],"type":"Point"}
}