{
  "type": "Feature",
  "properties": {
    "iso:country":"US",
    "sg:address":"5353 N Union Blvd",
    "sg:city":"Colorado Springs",
    "sg:classifiers":[
        {
            "category":"Real Estate",
            "subcategory":"Real Estate Agent",
            "type":"Services"
        }
    ],
    "sg:phone":"+1 719 576 0000",
    "sg:postcode":"80918",
    "sg:province":"CO",
    "sg:website":"www.mcginnis.com",
    "wof:name":"McGinnis GMAC Real Estate",
    "wof:placetype":"venue"
},
  "geometry": {"coordinates":[-104.77509000000001,38.909943],"type":"Point"}
}