{
  "type": "Feature",
  "properties": {
    "iso:country":"US",
    "sg:address":"2424 6th St",
    "sg:city":"Boulder",
    "sg:classifiers":[
        {
            "category":"Professional",
            "type":"Services"
        }
    ],
    "sg:phone":"+1 303 524 9911",
    "sg:postcode":"80304",
    "sg:province":"CO",
    "wof:name":"Robert H Leland M D P C",
    "wof:placetype":"venue"
},
  "geometry": {"coordinates":[-105.288482,40.020691],"type":"Point"}
}