{
  "type": "Feature",
  "properties": {
    "iso:country":"US",
    "sg:address":"1417 Nolan Dr",
    "sg:city":"Trinidad",
    "sg:classifiers":[
        {
            "category":"Sports & Exercise",
            "subcategory":"Golf",
            "type":"Entertainment"
        }
    ],
    "sg:phone":"+1 719 846 4015",
    "sg:postcode":"81082",
    "sg:province":"CO",
    "sg:tags":[
        "course"
    ],
    "wof:name":"Trinidad Golf Course Grounds",
    "wof:placetype":"venue"
},
  "geometry": {"coordinates":[-104.51442,37.160077],"type":"Point"}
}