{
  "type": "Feature",
  "properties": {
    "iso:country":"US",
    "sg:address":"4612 E 23rd Ave",
    "sg:city":"Denver",
    "sg:classifiers":[
        {
            "category":"Building & Trades",
            "subcategory":"Locksmith",
            "type":"Services"
        }
    ],
    "sg:phone":"+1 866 690 2761",
    "sg:postcode":"80207",
    "sg:province":"CO",
    "sg:tags":[
        "key"
    ],
    "wof:name":"24 7 Available Locksmith",
    "wof:placetype":"venue"
},
  "geometry": {"coordinates":[-104.933797,39.750913],"type":"Point"}
}