{
  "type": "Feature",
  "properties": {
    "iso:country":"US",
    "sg:address":"1795 Launa Dr",
    "sg:city":"Montrose",
    "sg:classifiers":[
        {
            "category":"Real Estate",
            "subcategory":"Real Estate Agent",
            "type":"Services"
        }
    ],
    "sg:phone":"+1 970 240 8442",
    "sg:postcode":"81401",
    "sg:province":"CO",
    "wof:name":"Bourelle Property MGT LLP",
    "wof:placetype":"venue"
},
  "geometry": {"coordinates":[-107.89750100000001,38.496361],"type":"Point"}
}