{
  "type": "Feature",
  "properties": {
    "iso:country":"US",
    "sg:address":"3198 N Speer Blvd",
    "sg:city":"Denver",
    "sg:classifiers":[
        {
            "category":"Shopping",
            "subcategory":"Clothing, Apparel, & Fashions",
            "type":"Retail Goods"
        }
    ],
    "sg:phone":"+1 303 458 8027",
    "sg:postcode":"80211",
    "sg:province":"CO",
    "sg:tags":[
        "mfg",
        "banner",
        "jacket",
        "flag",
        "pennant",
        "badge"
    ],
    "wof:name":"American Pennant Mfg Co",
    "wof:placetype":"venue"
},
  "geometry": {"coordinates":[-105.02685200000001,39.761082],"type":"Point"}
}