{
  "type": "Feature",
  "properties": {
    "addr:full":"1673 Woodmoor Dr Monument CO 80132",
    "addr:housenumber":"1673",
    "addr:postcode":"80132",
    "addr:street":"Woodmoor Dr",
    "iso:country":"US",
    "sg:address":"1673 Woodmoor Dr",
    "sg:city":"Monument",
    "sg:classifiers":[
        {
            "category":"Manufacturing",
            "subcategory":"Tools & Machinery",
            "type":"Manufacturing & Wholesale Goods"
        }
    ],
    "sg:phone":"+1 719 481 3048",
    "sg:postcode":"80132",
    "sg:province":"CO",
    "sg:tags":[
        "computer",
        "electronic",
        "mfg"
    ],
    "wof:name":"HP",
    "wof:placetype":"venue"
},
  "geometry": {"coordinates":[-104.858597,39.106643],"type":"Point"}
}