{
  "type": "Feature",
  "properties": {
    "addr:full":"2454 F Rd Grand Junction CO 81505",
    "addr:housenumber":"2454",
    "addr:postcode":"81505",
    "addr:street":"F Rd",
    "iso:country":"US",
    "sg:address":"2454 F Rd",
    "sg:city":"Grand Junction",
    "sg:classifiers":[
        {
            "category":"Real Estate",
            "subcategory":"Real Estate Agent",
            "type":"Services"
        }
    ],
    "sg:phone":"+1 970 255 7000",
    "sg:postcode":"81505",
    "sg:province":"CO",
    "wof:name":"Cunningham Brokerage Co",
    "wof:placetype":"venue"
},
  "geometry": {"coordinates":[-108.596563,39.09195],"type":"Point"}
}