{
  "type": "Feature",
  "properties": {
    "addr:full":"615 W 8th Ave Yuma CO 80759",
    "addr:housenumber":"615",
    "addr:postcode":"80759",
    "addr:street":"W 8Th Ave",
    "iso:country":"US",
    "sg:address":"615 W 8th Ave",
    "sg:city":"Yuma",
    "sg:classifiers":[
        {
            "category":"Banks & Credit Unions",
            "subcategory":"Financial Services",
            "type":"Services"
        }
    ],
    "sg:phone":"+1 970 246 3456",
    "sg:postcode":"80759",
    "sg:province":"CO",
    "sg:tags":[
        "company",
        "investor",
        "holding"
    ],
    "wof:name":"Washington Investment Company",
    "wof:placetype":"venue"
},
  "geometry": {"coordinates":[-102.731219,40.11836],"type":"Point"}
}