{
  "type": "Feature",
  "properties": {
    "iso:country":"US",
    "sg:address":"450 W 14th St Suite 40003",
    "sg:city":"Denver",
    "sg:classifiers":[
        {
            "category":"Building & Trades",
            "subcategory":"Construction",
            "type":"Services"
        }
    ],
    "sg:phone":"+1 303 507 0535",
    "sg:postcode":"80204",
    "sg:province":"CO",
    "sg:tags":[
        "roofing",
        "contractor"
    ],
    "sg:website":"www.devinbrookeroofing.com",
    "wof:name":"Devinbrooke Roofing",
    "wof:placetype":"venue"
},
  "geometry": {"coordinates":[-104.993532,39.738443],"type":"Point"}
}