{
  "type": "Feature",
  "properties": {
    "iso:country":"US",
    "sg:address":"2139 Gale Rd",
    "sg:city":"Pueblo",
    "sg:classifiers":[
        {
            "category":"Building & Trades",
            "subcategory":"Construction",
            "type":"Services"
        }
    ],
    "sg:phone":"+1 719 545 4322",
    "sg:postcode":"81006",
    "sg:province":"CO",
    "sg:tags":[
        "paving",
        "contractor"
    ],
    "wof:name":"C & C Asphalt & Gravel Inc",
    "wof:placetype":"venue"
},
  "geometry": {"coordinates":[-104.55201099999999,38.249085],"type":"Point"}
}