{
  "type": "Feature",
  "properties": {
    "addr:full":"8490 Pecos St Denver CO 80260",
    "addr:housenumber":"8490",
    "addr:postcode":"80260",
    "addr:street":"Pecos St",
    "iso:country":"US",
    "sg:address":"8490 Pecos St",
    "sg:city":"Denver",
    "sg:classifiers":[
        {
            "category":"Banks & Credit Unions",
            "subcategory":"Bank",
            "type":"Services"
        }
    ],
    "sg:phone":"+1 303 427 0841",
    "sg:postcode":"80260",
    "sg:province":"CO",
    "sg:tags":[
        "loan"
    ],
    "wof:name":"Payday Loans",
    "wof:placetype":"venue"
},
  "geometry": {"coordinates":[-105.00588399999999,39.853006],"type":"Point"}
}