{
  "type": "Feature",
  "properties": {
    "iso:country":"US",
    "sg:address":"5350 Tomah Dr",
    "sg:city":"Colorado Springs",
    "sg:classifiers":[
        {
            "category":"Professional",
            "subcategory":"Detective & Security Services",
            "type":"Services"
        }
    ],
    "sg:phone":"+1 719 488 4500",
    "sg:postcode":"80918",
    "sg:province":"CO",
    "sg:tags":[
        "other"
    ],
    "wof:name":"Security Horizon Inc",
    "wof:placetype":"venue"
},
  "geometry": {"coordinates":[-104.77951899999999,38.90797],"type":"Point"}
}