{
  "type": "Feature",
  "properties": {
    "iso:country":"US",
    "sg:address":"10961 W 68th Pl",
    "sg:city":"Arvada",
    "sg:classifiers":[
        {
            "category":"Building & Trades",
            "subcategory":"Construction",
            "type":"Services"
        }
    ],
    "sg:phone":"+1 303 421 6997",
    "sg:postcode":"80004",
    "sg:province":"CO",
    "sg:tags":[
        "control",
        "adhesive",
        "corrosion",
        "contractor"
    ],
    "wof:name":"Colorado Technical Staffing",
    "wof:placetype":"venue"
},
  "geometry": {"coordinates":[-105.12158599999999,39.820461],"type":"Point"}
}