{
  "type": "Feature",
  "properties": {
    "iso:country":"US",
    "sg:address":"5200 Hahns Peak Dr",
    "sg:city":"Loveland",
    "sg:classifiers":[
        {
            "category":"Building & Trades",
            "subcategory":"Construction",
            "type":"Services"
        }
    ],
    "sg:phone":"+1 970 663 3923",
    "sg:postcode":"80538",
    "sg:province":"CO",
    "sg:tags":[
        "home",
        "builder"
    ],
    "wof:name":"Mc Stain",
    "wof:placetype":"venue"
},
  "geometry": {"coordinates":[-105.007897,40.412649],"type":"Point"}
}