{
  "type": "Feature",
  "properties": {
    "iso:country":"US",
    "sg:address":"525 S 44th St",
    "sg:city":"Boulder",
    "sg:classifiers":[
        {
            "category":"Building & Trades",
            "subcategory":"Equipment Rental",
            "type":"Services"
        }
    ],
    "sg:phone":"+1 303 499 9133",
    "sg:postcode":"80305",
    "sg:province":"CO",
    "sg:tags":[
        "yard",
        "leasing",
        "store"
    ],
    "wof:name":"Fernsler Services",
    "wof:placetype":"venue"
},
  "geometry": {"coordinates":[-105.243605,39.985535],"type":"Point"}
}