{
  "type": "Feature",
  "properties": {
    "addr:full":"6956 S Pierce Ct Littleton CO 80128",
    "addr:housenumber":"6956",
    "addr:postcode":"80128",
    "addr:street":"S Pierce Ct",
    "iso:country":"US",
    "sg:address":"6956 S Pierce Ct",
    "sg:city":"Littleton",
    "sg:classifiers":[
        {
            "category":"Retail",
            "subcategory":"Auto Repair",
            "type":"Services"
        }
    ],
    "sg:phone":"+1 303 973 4210",
    "sg:postcode":"80128",
    "sg:province":"CO",
    "sg:tags":[
        "automobile",
        "restoration",
        "classic"
    ],
    "wof:name":"Best Buy Custom Design",
    "wof:placetype":"venue"
},
  "geometry": {"coordinates":[-105.07369300000001,39.589342],"type":"Point"}
}