{
  "type": "Feature",
  "properties": {
    "iso:country":"US",
    "sg:address":"1827 Somerville Dr",
    "sg:city":"Fort Collins",
    "sg:classifiers":[
        {
            "category":"Real Estate",
            "subcategory":"Real Estate Operator",
            "type":"Services"
        }
    ],
    "sg:phone":"+1 970 282 7522",
    "sg:postcode":"80526",
    "sg:province":"CO",
    "sg:tags":[
        "apartment"
    ],
    "wof:name":"CARE Housing Inc",
    "wof:placetype":"venue"
},
  "geometry": {"coordinates":[-105.127307,40.565365],"type":"Point"}
}