{
  "type": "Feature",
  "properties": {
    "iso:country":"US",
    "sg:address":"1337 Riverside Ave",
    "sg:city":"Fort Collins",
    "sg:classifiers":[
        {
            "category":"Health Services",
            "subcategory":"Doctor",
            "type":"Services"
        }
    ],
    "sg:phone":"+1 970 221 1658",
    "sg:postcode":"80524",
    "sg:province":"CO",
    "sg:tags":[
        "dentist"
    ],
    "wof:name":"Kenneth B Allen DDS",
    "wof:placetype":"venue"
},
  "geometry": {"coordinates":[-105.049357,40.573262],"type":"Point"}
}