{
  "type": "Feature",
  "properties": {
    "iso:country":"US",
    "sg:address":"313 Park Place Ct",
    "sg:city":"Fort Collins",
    "sg:classifiers":[
        {
            "category":"Restaurant",
            "type":"Food & Drink"
        }
    ],
    "sg:phone":"+1 970 461 4966",
    "sg:postcode":"80525",
    "sg:province":"CO",
    "sg:tags":[
        "eating"
    ],
    "wof:name":"Michelles Gourmet Mustards LL",
    "wof:placetype":"venue"
},
  "geometry": {"coordinates":[-105.07305599999999,40.476873],"type":"Point"}
}