{
  "type": "Feature",
  "properties": {
    "addr:full":"2930 W Colorado Ave Colorado Springs CO 80904",
    "addr:housenumber":"2930",
    "addr:postcode":"80904",
    "addr:street":"W Colorado Ave",
    "iso:country":"US",
    "sg:address":"2930 W Colorado Ave",
    "sg:city":"Colorado Springs",
    "sg:classifiers":[
        {
            "category":"Restaurant",
            "type":"Food & Drink"
        }
    ],
    "sg:phone":"+1 719 475 7402",
    "sg:postcode":"80904",
    "sg:province":"CO",
    "sg:website":"www.subway.com",
    "wof:name":"Subway Sandwiches & Salads",
    "wof:placetype":"venue"
},
  "geometry": {"coordinates":[-104.870003,38.851601],"type":"Point"}
}