{
  "type": "Feature",
  "properties": {
    "addr:full":"Atomic Cowboy 3237 E Colfax Ave Denver CO 80206",
    "addr:housenumber":"3237",
    "addr:postcode":"80206",
    "addr:street":"E Colfax Ave",
    "iso:country":"US",
    "sg:address":"Atomic Cowboy 3237 E Colfax Ave",
    "sg:city":"Denver",
    "sg:classifiers":[
        {
            "category":"Restaurant",
            "type":"Food & Drink"
        },
        {
            "category":"Food & Beverages",
            "subcategory":"Bakery",
            "type":"Retail Goods"
        }
    ],
    "sg:phone":"+1 303 377 7900",
    "sg:postcode":"80206",
    "sg:province":"CO",
    "sg:tags":[
        "sandwich",
        "southern"
    ],
    "sg:website":"www.denbisco.com",
    "wof:name":"Denver Biscuit Company",
    "wof:placetype":"venue"
},
  "geometry": {"coordinates":[-104.949045,39.740373],"type":"Point"}
}