{
  "type": "Feature",
  "properties": {
    "iso:country":"US",
    "sg:address":"19691 E Bethany Dr",
    "sg:city":"Aurora",
    "sg:classifiers":[
        {
            "category":"Manufacturing",
            "subcategory":"Apparel",
            "type":"Manufacturing & Wholesale Goods"
        }
    ],
    "sg:phone":"+1 303 373 1750",
    "sg:postcode":"80013",
    "sg:province":"CO",
    "wof:name":"Embroidery Systems LLC",
    "wof:placetype":"venue"
},
  "geometry": {"coordinates":[-104.75774699999999,39.663151],"type":"Point"}
}