{
  "type": "Feature",
  "properties": {
    "addr:full":"750 Co Rd 112 Craig CO 81626",
    "addr:housenumber":"750;112",
    "addr:postcode":"81626",
    "addr:street":"Co Rd",
    "iso:country":"US",
    "sg:address":"750 Co Rd 112",
    "sg:city":"Craig",
    "sg:classifiers":[
        {
            "category":"Professional",
            "type":"Services"
        }
    ],
    "sg:phone":"+1 970 824 9208",
    "sg:postcode":"81626",
    "sg:province":"CO",
    "wof:name":"Norman D Yoast",
    "wof:placetype":"venue"
},
  "geometry": {"coordinates":[-107.52934999999999,40.536359],"type":"Point"}
}