{
  "type": "Feature",
  "properties": {
    "iso:country":"US",
    "sg:address":"41801 E Quincy Ave",
    "sg:city":"Bennett",
    "sg:classifiers":[
        {
            "category":"Organizations",
            "subcategory":"Labor Organization",
            "type":"Services"
        }
    ],
    "sg:phone":"+1 303 644 3909",
    "sg:postcode":"80102",
    "sg:province":"CO",
    "wof:name":"Colorado Journeymen & Apprntce",
    "wof:placetype":"venue"
},
  "geometry": {"coordinates":[-104.50958300000001,39.636898],"type":"Point"}
}