{
  "type": "Feature",
  "properties": {
    "iso:country":"US",
    "sg:address":"6375 Leadville Cir",
    "sg:city":"Colorado Springs",
    "sg:classifiers":[
        {
            "category":"Mining & Drilling",
            "type":"Manufacturing & Wholesale Goods"
        }
    ],
    "sg:phone":"+1 719 592 9555",
    "sg:postcode":"80919",
    "sg:province":"CO",
    "sg:tags":[
        "petroleum",
        "commercial",
        "construction",
        "real estate",
        "crude"
    ],
    "wof:name":"Dwayne Black & Associates",
    "wof:placetype":"venue"
},
  "geometry": {"coordinates":[-104.83951500000001,38.924368],"type":"Point"}
}