{
  "type": "Feature",
  "properties": {
    "addr:full":"303 S Broadway Denver CO 80210",
    "addr:housenumber":"303",
    "addr:postcode":"80210",
    "addr:street":"S Broadway",
    "iso:country":"US",
    "sg:address":"303 S Broadway",
    "sg:city":"Denver",
    "sg:classifiers":[
        {
            "category":"Real Estate",
            "subcategory":"Real Estate Agent",
            "type":"Services"
        }
    ],
    "sg:phone":"+1 303 282 7085",
    "sg:postcode":"80210",
    "sg:province":"CO",
    "wof:name":"Building Winners Inc",
    "wof:placetype":"venue"
},
  "geometry": {"coordinates":[-104.987657,39.710277],"type":"Point"}
}