{
  "type": "Feature",
  "properties": {
    "addr:full":"12510 E Iliff Ave Aurora CO 80014",
    "addr:housenumber":"12510",
    "addr:postcode":"80014",
    "addr:street":"E Iliff Ave",
    "iso:country":"US",
    "sg:address":"12510 E Iliff Ave",
    "sg:city":"Aurora",
    "sg:classifiers":[
        {
            "category":"Insurance",
            "subcategory":"Insurance Agent",
            "type":"Services"
        }
    ],
    "sg:phone":"+1 303 337 0455",
    "sg:postcode":"80014",
    "sg:province":"CO",
    "wof:name":"Allstate Insurance",
    "wof:placetype":"venue"
},
  "geometry": {"coordinates":[-104.84481599999999,39.674772],"type":"Point"}
}