{
  "type": "Feature",
  "properties": {
    "addr:full":"4634 E Phillips Pl Littleton CO 80122",
    "addr:housenumber":"4634",
    "addr:postcode":"80122",
    "addr:street":"E Phillips Pl",
    "iso:country":"US",
    "sg:address":"4634 E Phillips Pl",
    "sg:city":"Littleton",
    "sg:classifiers":[
        {
            "category":"Banks & Credit Unions",
            "subcategory":"Financial Services",
            "type":"Services"
        }
    ],
    "sg:phone":"+1 303 886 3411",
    "sg:postcode":"80122",
    "sg:province":"CO",
    "sg:tags":[
        "investment",
        "real estate"
    ],
    "wof:name":"R M B Properties LLC",
    "wof:placetype":"venue"
},
  "geometry": {"coordinates":[-104.934281,39.566728],"type":"Point"}
}