{
  "type": "Feature",
  "properties": {
    "iso:country":"US",
    "sg:address":"4952 Alcott St",
    "sg:city":"Denver",
    "sg:classifiers":[
        {
            "category":"Personal",
            "type":"Services"
        }
    ],
    "sg:phone":"+1 303 458 3711",
    "sg:postcode":"80221",
    "sg:province":"CO",
    "sg:tags":[
        "therapist",
        "massage"
    ],
    "wof:name":"Peaceful Nature Massage",
    "wof:placetype":"venue"
},
  "geometry": {"coordinates":[-105.016919,39.786466],"type":"Point"}
}