{
  "type": "Feature",
  "properties": {
    "addr:full":"3700 Quebec St Suite 100-255 Denver CO 80207",
    "addr:housenumber":"3700",
    "addr:postcode":"80207",
    "addr:street":"Quebec St Suite 100-255",
    "iso:country":"US",
    "sg:address":"3700 Quebec St Suite 100-255",
    "sg:city":"Denver",
    "sg:classifiers":[
        {
            "category":"Professional",
            "subcategory":"Computer Services",
            "type":"Services"
        }
    ],
    "sg:postcode":"80207",
    "sg:province":"CO",
    "sg:tags":[
        "gourmet",
        "cheese",
        "food",
        "italian-cuisine",
        "french-cuisine",
        "coffee",
        "lavazza",
        "tea",
        "mighty-leaf",
        "beans",
        "rice",
        "dry-cured-meat"
    ],
    "sg:website":"http://www.mondofood.com",
    "wof:name":"Mondo Food",
    "wof:placetype":"venue"
},
  "geometry": {"coordinates":[-104.903418,39.771064],"type":"Point"}
}