{
  "type": "Feature",
  "properties": {
    "addr:full":"461 Co Rd 219 Durango CO 81303",
    "addr:housenumber":"461;219",
    "addr:postcode":"co 81303",
    "addr:street":"Co Rd",
    "iso:country":"US",
    "sg:address":"461 Co Rd 219",
    "sg:city":"Durango",
    "sg:classifiers":[
        {
            "category":"Building & Trades",
            "subcategory":"Plumbing",
            "type":"Services"
        }
    ],
    "sg:phone":"+1 970 946 4328",
    "sg:postcode":"81303",
    "sg:province":"CO",
    "sg:tags":[
        "contractor"
    ],
    "wof:name":"McMahons Heating & Air Inc",
    "wof:placetype":"venue"
},
  "geometry": {"coordinates":[-107.853297,37.190487],"type":"Point"}
}