{
  "type": "Feature",
  "properties": {
    "addr:full":"26416 Co Rd 11 Haxtun CO 80731",
    "addr:housenumber":"26416;11",
    "addr:postcode":"80731",
    "addr:street":"Co Rd",
    "iso:country":"US",
    "sg:address":"26416 Co Rd 11",
    "sg:city":"Haxtun",
    "sg:classifiers":[
        {
            "category":"Professional",
            "type":"Services"
        }
    ],
    "sg:phone":"+1 970 774 3888",
    "sg:postcode":"80731",
    "sg:province":"CO",
    "sg:tags":[
        "establishment"
    ],
    "wof:name":"Plain Folk Carving Inc",
    "wof:placetype":"venue"
},
  "geometry": {"coordinates":[-102.569974,40.622864],"type":"Point"}
}