{
  "type": "Feature",
  "properties": {
    "iso:country":"US",
    "sg:address":"2580 S Havana St",
    "sg:city":"Aurora",
    "sg:classifiers":[
        {
            "category":"Restaurant",
            "type":"Food & Drink"
        }
    ],
    "sg:phone":"+1 303 751 4707",
    "sg:postcode":"80014",
    "sg:province":"CO",
    "sg:tags":[
        "eating"
    ],
    "wof:name":"Cocos",
    "wof:placetype":"venue"
},
  "geometry": {"coordinates":[-104.866242,39.66771],"type":"Point"}
}