{
  "type": "Feature",
  "properties": {
    "iso:country":"US",
    "sg:address":"5954 S Sheridan Way",
    "sg:city":"Littleton",
    "sg:classifiers":[
        {
            "category":"Home & Garden",
            "subcategory":"Building Materials",
            "type":"Retail Goods"
        }
    ],
    "sg:phone":"+1 303 232 5208",
    "sg:postcode":"80123",
    "sg:province":"CO",
    "wof:name":"Sigala Glass",
    "wof:placetype":"venue"
},
  "geometry": {"coordinates":[-105.054034,39.607369],"type":"Point"}
}