{
  "type": "Feature",
  "properties": {
    "addr:full":"741 Lone Pine Dr Estes Park CO 80517",
    "addr:housenumber":"741",
    "addr:postcode":"80517",
    "addr:street":"Lone Pine Dr",
    "iso:country":"US",
    "sg:address":"741 Lone Pine Dr",
    "sg:city":"Estes Park",
    "sg:classifiers":[
        {
            "category":"Professional",
            "type":"Services"
        }
    ],
    "sg:phone":"+1 970 586 0585",
    "sg:postcode":"80517",
    "sg:province":"CO",
    "wof:name":"Tucker & Linda",
    "wof:placetype":"venue"
},
  "geometry": {"coordinates":[-105.49445799999999,40.385553],"type":"Point"}
}