{
  "type": "Feature",
  "properties": {
    "addr:full":"3302 S Corona St Englewood CO 80113",
    "addr:housenumber":"3302",
    "addr:postcode":"80113",
    "addr:street":"S Corona St",
    "iso:country":"US",
    "sg:address":"3302 S Corona St",
    "sg:city":"Englewood",
    "sg:classifiers":[
        {
            "category":"Building & Trades",
            "subcategory":"Plumbing",
            "type":"Services"
        }
    ],
    "sg:phone":"+1 303 781 6460",
    "sg:postcode":"80113",
    "sg:province":"CO",
    "sg:tags":[
        "specializing",
        "plumbing",
        "work",
        "heating",
        "contractor"
    ],
    "wof:name":"Hollanders Plumbing & Heating",
    "wof:placetype":"venue"
},
  "geometry": {"coordinates":[-104.974575,39.655002],"type":"Point"}
}