{
  "type": "Feature",
  "properties": {
    "iso:country":"US",
    "sg:address":"1710 S Buckley Rd",
    "sg:city":"Aurora",
    "sg:classifiers":[
        {
            "category":"Travel",
            "subcategory":"Hotels & Motels",
            "type":"Entertainment"
        },
        {
            "category":"Personal",
            "subcategory":"Barber",
            "type":"Services"
        }
    ],
    "sg:phone":"+1 303 752 4436",
    "sg:postcode":"80017",
    "sg:province":"CO",
    "sg:tags":[
        "membership",
        "lodging"
    ],
    "wof:name":"Aurora Highland Barbers",
    "wof:placetype":"venue"
},
  "geometry": {"coordinates":[-104.790919,39.682093],"type":"Point"}
}