{
  "type": "Feature",
  "properties": {
    "addr:full":"5005 W 72nd Ave Westminster CO 80030",
    "addr:housenumber":"5005",
    "addr:postcode":"80030",
    "addr:street":"W 72Nd Ave",
    "iso:country":"US",
    "sg:address":"5005 W 72nd Ave",
    "sg:city":"Westminster",
    "sg:classifiers":[
        {
            "category":"Restaurant",
            "type":"Food & Drink"
        }
    ],
    "sg:phone":"+1 303 426 5252",
    "sg:postcode":"80030",
    "sg:province":"CO",
    "sg:tags":[
        "eating"
    ],
    "wof:name":"Sheridan Cafe",
    "wof:placetype":"venue"
},
  "geometry": {"coordinates":[-105.05067099999999,39.827362],"type":"Point"}
}