{
  "type": "Feature",
  "properties": {
    "addr:full":"2075 S University Boulevard Unit B Denver CO 80210",
    "addr:housenumber":"2075",
    "addr:postcode":"80210",
    "addr:street":"S University Boulevard Unit B",
    "iso:country":"US",
    "sg:address":"2075 S University Boulevard Unit B",
    "sg:city":"Denver",
    "sg:classifiers":[
        {
            "category":"Restaurant",
            "type":"Food & Drink"
        }
    ],
    "sg:phone":"+1 303 722 5222",
    "sg:postcode":"80210",
    "sg:province":"CO",
    "sg:tags":[
        "pizza"
    ],
    "wof:name":"Blackjack Pizza",
    "wof:placetype":"venue"
},
  "geometry": {"coordinates":[-104.959411,39.678825],"type":"Point"}
}