{
  "type": "Feature",
  "properties": {
    "addr:full":"301 Main St Gilcrest CO 80623",
    "addr:housenumber":"301",
    "addr:postcode":"80623",
    "addr:street":"Main St",
    "iso:country":"US",
    "sg:address":"301 Main St",
    "sg:city":"Gilcrest",
    "sg:classifiers":[
        {
            "category":"Government",
            "subcategory":"Post Office",
            "type":"Public Place"
        }
    ],
    "sg:phone":"+1 970 737 2934",
    "sg:postcode":"80623",
    "sg:province":"CO",
    "wof:name":"US Post Office",
    "wof:placetype":"venue"
},
  "geometry": {"coordinates":[-104.77697499999999,40.282634],"type":"Point"}
}