{
  "type": "Feature",
  "properties": {
    "iso:country":"US",
    "sg:address":"1201 Graves Ave",
    "sg:city":"Estes Park",
    "sg:classifiers":[
        {
            "category":"Utilities",
            "subcategory":"Sewage",
            "type":"Services"
        }
    ],
    "sg:phone":"+1 970 586 2866",
    "sg:postcode":"80517",
    "sg:province":"CO",
    "sg:tags":[
        "disposal",
        "system"
    ],
    "wof:name":"Estes Park Sanitation District",
    "wof:placetype":"venue"
},
  "geometry": {"coordinates":[-105.502081,40.369228],"type":"Point"}
}