{
  "type": "Feature",
  "properties": {
    "addr:full":"4900 63rd St Boulder CO 80301",
    "addr:housenumber":"4900",
    "addr:postcode":"80301",
    "addr:street":"63Rd St",
    "iso:country":"US",
    "sg:address":"4900 63rd St",
    "sg:city":"Boulder",
    "sg:classifiers":[
        {
            "category":"Organizations",
            "subcategory":"Community Association",
            "type":"Services"
        }
    ],
    "sg:phone":"+1 303 530 0776",
    "sg:postcode":"80301",
    "sg:province":"CO",
    "sg:tags":[
        "club"
    ],
    "wof:name":"AAA Automobile Club",
    "wof:placetype":"venue"
},
  "geometry": {"coordinates":[-105.20667899999999,40.062199],"type":"Point"}
}