{
  "type": "Feature",
  "properties": {
    "iso:country":"US",
    "sg:address":"2730 Timberchase Trl",
    "sg:city":"Littleton",
    "sg:classifiers":[
        {
            "category":"Banks & Credit Unions",
            "subcategory":"Financial Services",
            "type":"Services"
        }
    ],
    "sg:phone":"+1 303 471 9737",
    "sg:postcode":"80126",
    "sg:province":"CO",
    "sg:tags":[
        "management",
        "open",
        "investment"
    ],
    "wof:name":"Laudus Mutual Funds",
    "wof:placetype":"venue"
},
  "geometry": {"coordinates":[-104.958943,39.527163],"type":"Point"}
}