{
  "type": "Feature",
  "properties": {
    "addr:full":"2555 N Chelton Rd Colorado Springs CO 80909",
    "addr:housenumber":"2555",
    "addr:postcode":"80909",
    "addr:street":"N Chelton Rd",
    "iso:country":"US",
    "sg:address":"2555 N Chelton Rd",
    "sg:city":"Colorado Springs",
    "sg:classifiers":[
        {
            "category":"Organizations",
            "subcategory":"Religious Organization",
            "type":"Services"
        }
    ],
    "sg:phone":"+1 719 633 0655",
    "sg:postcode":"80909",
    "sg:province":"CO",
    "sg:tags":[
        "monastery",
        "convent"
    ],
    "sg:website":"www.benethillmonastery.org",
    "wof:name":"Benet Hill Monastery",
    "wof:placetype":"venue"
},
  "geometry": {"coordinates":[-104.772412,38.869286],"type":"Point"}
}