{
  "type": "Feature",
  "properties": {
    "addr:full":"510 Bryant St Denver CO 80204",
    "addr:housenumber":"510",
    "addr:postcode":"80204",
    "addr:street":"Bryant St",
    "iso:country":"US",
    "sg:address":"510 Bryant St",
    "sg:city":"Denver",
    "sg:classifiers":[
        {
            "category":"Wholesale",
            "subcategory":"Chemicals & Plastics",
            "type":"Manufacturing & Wholesale Goods"
        }
    ],
    "sg:phone":"+1 303 693 5076",
    "sg:postcode":"80204",
    "sg:province":"CO",
    "sg:tags":[
        "equipment",
        "melting",
        "ice",
        "supply"
    ],
    "wof:name":"Agricultural-Industrial Chem",
    "wof:placetype":"venue"
},
  "geometry": {"coordinates":[-105.018596,39.724669],"type":"Point"}
}