{
  "type": "Feature",
  "properties": {
    "iso:country":"US",
    "sg:address":"8672 Carr Loop",
    "sg:city":"Arvada",
    "sg:classifiers":[
        {
            "category":"Professional",
            "type":"Services"
        }
    ],
    "sg:phone":"+1 303 421 8992",
    "sg:postcode":"80005",
    "sg:province":"CO",
    "wof:name":"Finishing Touch Kitchen & Bath",
    "wof:placetype":"venue"
},
  "geometry": {"coordinates":[-105.092195,39.855885],"type":"Point"}
}