{
  "type": "Feature",
  "properties": {
    "iso:country":"US",
    "sg:address":"2473 S Chase Ln",
    "sg:city":"Lakewood",
    "sg:classifiers":[
        {
            "category":"Home & Garden",
            "subcategory":"Hardware",
            "type":"Retail Goods"
        },
        {
            "category":"Building & Trades",
            "subcategory":"Locksmith",
            "type":"Services"
        }
    ],
    "sg:phone":"+1 303 531 1417",
    "sg:postcode":"80227",
    "sg:province":"CO",
    "sg:tags":[
        "store",
        "key"
    ],
    "wof:name":"Locks A A A Locksmith",
    "wof:placetype":"venue"
},
  "geometry": {"coordinates":[-105.055745,39.673028],"type":"Point"}
}