{
  "type": "Feature",
  "properties": {
    "iso:country":"US",
    "sg:address":"3645 Jeannine Dr",
    "sg:city":"Colorado Springs",
    "sg:classifiers":[
        {
            "category":"Professional",
            "type":"Services"
        }
    ],
    "sg:phone":"+1 719 573 4488",
    "sg:postcode":"80917",
    "sg:province":"CO",
    "sg:tags":[
        "establishment"
    ],
    "wof:name":"Mountain View Home Exteriors",
    "wof:placetype":"venue"
},
  "geometry": {"coordinates":[-104.75787699999999,38.8856],"type":"Point"}
}