{
  "type": "Feature",
  "properties": {
    "iso:country":"US",
    "sg:address":"628 S Delaney Dr",
    "sg:city":"Pueblo",
    "sg:classifiers":[
        {
            "category":"Home & Garden",
            "subcategory":"Furniture",
            "type":"Retail Goods"
        }
    ],
    "sg:phone":"+1 719 547 9896",
    "sg:postcode":"81007",
    "sg:province":"CO",
    "wof:name":"Oak Express",
    "wof:placetype":"venue"
},
  "geometry": {"coordinates":[-104.808046,38.318981],"type":"Point"}
}