{
  "type": "Feature",
  "properties": {
    "iso:country":"US",
    "sg:address":"2583 Hwy 6 and 50",
    "sg:city":"Grand Junction",
    "sg:classifiers":[
        {
            "category":"Retail",
            "subcategory":"Auto Repair",
            "type":"Services"
        }
    ],
    "sg:phone":"+1 970 257 9427",
    "sg:postcode":"81501",
    "sg:province":"CO",
    "sg:tags":[
        "body",
        "automobile",
        "painting"
    ],
    "wof:name":"Billing Kar Kolor",
    "wof:placetype":"venue"
},
  "geometry": {"coordinates":[-108.571195,39.07071],"type":"Point"}
}