{
  "type": "Feature",
  "properties": {
    "addr:full":"10662 E 51st Ave Denver CO 80239",
    "addr:housenumber":"10662",
    "addr:postcode":"80239",
    "addr:street":"E 51St Ave",
    "iso:country":"US",
    "sg:address":"10662 E 51st Ave",
    "sg:city":"Denver",
    "sg:classifiers":[
        {
            "category":"Real Estate",
            "subcategory":"Real Estate Operator",
            "type":"Services"
        }
    ],
    "sg:phone":"+1 303 371 1607",
    "sg:postcode":"80239",
    "sg:province":"CO",
    "sg:tags":[
        "building",
        "nonresidential"
    ],
    "wof:name":"Winthrop Management",
    "wof:placetype":"venue"
},
  "geometry": {"coordinates":[-104.865368,39.790239],"type":"Point"}
}