{
  "type": "Feature",
  "properties": {
    "addr:full":"1345 S Broadway Denver CO 80210",
    "addr:housenumber":"1345",
    "addr:postcode":"80210",
    "addr:street":"S Broadway",
    "iso:country":"US",
    "sg:address":"1345 S Broadway",
    "sg:city":"Denver",
    "sg:classifiers":[
        {
            "category":"Professional",
            "subcategory":"Advertising",
            "type":"Services"
        }
    ],
    "sg:phone":"+1 303 777 5008",
    "sg:postcode":"80210",
    "sg:province":"CO",
    "sg:tags":[
        "counselor"
    ],
    "wof:name":"Media Visions",
    "wof:placetype":"venue"
},
  "geometry": {"coordinates":[-104.98755,39.691998],"type":"Point"}
}