{
  "type": "Feature",
  "properties": {
    "iso:country":"US",
    "sg:address":"1970 Dominion Way",
    "sg:city":"Colorado Springs",
    "sg:classifiers":[
        {
            "category":"Health Services",
            "subcategory":"Chiropractor",
            "type":"Services"
        }
    ],
    "sg:phone":"+1 719 599 4343",
    "sg:postcode":"80918",
    "sg:province":"CO",
    "wof:name":"Hefty Chiropractic Ctr",
    "wof:placetype":"venue"
},
  "geometry": {"coordinates":[-104.789428,38.921711],"type":"Point"}
}