{
  "type": "Feature",
  "properties": {
    "addr:full":"417 Front St Fairplay CO 80440",
    "addr:housenumber":"417",
    "addr:postcode":"80440",
    "addr:street":"Front St",
    "iso:country":"US",
    "sg:address":"417 Front St",
    "sg:city":"Fairplay",
    "sg:classifiers":[
        {
            "category":"Wholesale",
            "subcategory":"Jewelry",
            "type":"Manufacturing & Wholesale Goods"
        }
    ],
    "sg:phone":"+1 719 836 2698",
    "sg:postcode":"80440",
    "sg:province":"CO",
    "sg:tags":[
        "beads"
    ],
    "wof:name":"South Park Pottery & Beads",
    "wof:placetype":"venue"
},
  "geometry": {"coordinates":[-106.003801,39.224604],"type":"Point"}
}