{
  "type": "Feature",
  "properties": {
    "addr:full":"2600 S Wadsworth Boulevard Denver CO 80227",
    "addr:housenumber":"2600",
    "addr:postcode":"80227",
    "addr:street":"S Wadsworth Boulevard",
    "iso:country":"US",
    "sg:address":"2600 S Wadsworth Boulevard",
    "sg:city":"Denver",
    "sg:classifiers":[
        {
            "category":"Education",
            "subcategory":"Preschool",
            "type":"Public Place"
        },
        {
            "category":"Education",
            "subcategory":"School",
            "type":"Public Place"
        },
        {
            "category":"Organizations",
            "subcategory":"Religious Organization",
            "type":"Services"
        }
    ],
    "sg:phone":"+1 303 985 2334",
    "sg:postcode":"80227",
    "sg:province":"CO",
    "sg:tags":[
        "elementary"
    ],
    "wof:name":"Zion Lutheran Church & School",
    "wof:placetype":"venue"
},
  "geometry": {"coordinates":[-105.081425,39.671003],"type":"Point"}
}