{
  "type": "Feature",
  "properties": {
    "addr:full":"899 Logan Street Denver CO 80203",
    "addr:housenumber":"899",
    "addr:postcode":"80203",
    "addr:street":"Logan Street",
    "iso:country":"US",
    "sg:address":"899 Logan Street",
    "sg:city":"Denver",
    "sg:classifiers":[
        {
            "category":"Professional",
            "subcategory":"Accounting & Tax Preparation",
            "type":"Services"
        }
    ],
    "sg:phone":"+1 303 861 1907",
    "sg:postcode":"80203",
    "sg:province":"CO",
    "sg:tags":[
        "accountant"
    ],
    "wof:name":"First National Mortgage Sources",
    "wof:placetype":"venue"
},
  "geometry": {"coordinates":[-104.982355,39.730329],"type":"Point"}
}