{
  "type": "Feature",
  "properties": {
    "iso:country":"US",
    "sg:address":"348 Main St",
    "sg:city":"Colorado Springs",
    "sg:classifiers":[
        {
            "category":"Banks & Credit Unions",
            "subcategory":"Bank",
            "type":"Services"
        }
    ],
    "sg:phone":"+1 719 390 8706",
    "sg:postcode":"80911",
    "sg:province":"CO",
    "sg:tags":[
        "loan"
    ],
    "wof:name":"Mister Money USA",
    "wof:placetype":"venue"
},
  "geometry": {"coordinates":[-104.740923,38.753115],"type":"Point"}
}