{
  "type": "Feature",
  "properties": {
    "addr:full":"4039 W Chenango Ave Denver CO 80123",
    "addr:housenumber":"4039",
    "addr:postcode":"80123",
    "addr:street":"W Chenango Ave",
    "iso:country":"US",
    "sg:address":"4039 W Chenango Ave",
    "sg:city":"Denver",
    "sg:classifiers":[
        {
            "category":"Shopping",
            "type":"Retail Goods"
        }
    ],
    "sg:phone":"+1 303 730 0862",
    "sg:postcode":"80123",
    "sg:province":"CO",
    "sg:tags":[
        "trophy",
        "medal",
        "merchandise",
        "award"
    ],
    "wof:name":"T C Engraving",
    "wof:placetype":"venue"
},
  "geometry": {"coordinates":[-105.040544,39.630751],"type":"Point"}
}