{
  "type": "Feature",
  "properties": {
    "addr:full":"10680 del Mar Pkwy Aurora CO 80010",
    "addr:housenumber":"10680",
    "addr:postcode":"80010",
    "addr:street":"Del Mar Pkwy",
    "iso:country":"US",
    "sg:address":"10680 del Mar Pkwy",
    "sg:city":"Aurora",
    "sg:classifiers":[
        {
            "category":"Place Of Worship",
            "subcategory":"Church",
            "type":"Public Place"
        },
        {
            "category":"Place Of Worship",
            "type":"Public Place"
        },
        {
            "category":"Organizations",
            "subcategory":"Religious Organization",
            "type":"Services"
        }
    ],
    "sg:phone":"+1 720 859 1737",
    "sg:postcode":"80010",
    "sg:province":"CO",
    "sg:tags":[
        "churches-interdenominational",
        "churches-various",
        "denomination"
    ],
    "sg:website":"http://www.handsonworldmissions.org",
    "wof:name":"Hand-On Christian Church",
    "wof:placetype":"venue"
},
  "geometry": {"coordinates":[-104.86406700000001,39.731613],"type":"Point"}
}