{
  "type": "Feature",
  "properties": {
    "iso:country":"US",
    "sg:address":"7732 S Shenandoah Dr",
    "sg:city":"Elizabeth",
    "sg:classifiers":[
        {
            "category":"Building & Trades",
            "subcategory":"Construction",
            "type":"Services"
        }
    ],
    "sg:phone":"+1 303 646 1204",
    "sg:postcode":"80107",
    "sg:province":"CO",
    "sg:tags":[
        "painting",
        "contractor"
    ],
    "wof:name":"Custom Colors Painting Inc",
    "wof:placetype":"venue"
},
  "geometry": {"coordinates":[-104.51893800000001,39.501158],"type":"Point"}
}