{
  "type": "Feature",
  "properties": {
    "addr:full":"4315 Thatcher Ave Pueblo CO 81005",
    "addr:housenumber":"4315",
    "addr:postcode":"81005",
    "addr:street":"Thatcher Ave",
    "iso:country":"US",
    "sg:address":"4315 Thatcher Ave",
    "sg:city":"Pueblo",
    "sg:classifiers":[
        {
            "category":"Food & Beverages",
            "subcategory":"Liquor & Beverages",
            "type":"Retail Goods"
        }
    ],
    "sg:phone":"+1 719 561 3878",
    "sg:postcode":"81005",
    "sg:province":"CO",
    "wof:name":"Reservior Liquor",
    "wof:placetype":"venue"
},
  "geometry": {"coordinates":[-104.66489799999999,38.258443],"type":"Point"}
}