{
  "type": "Feature",
  "properties": {
    "addr:full":"44 E Spaulding Ave Pueblo West CO 81007",
    "addr:housenumber":"44",
    "addr:postcode":"81007",
    "addr:street":"E Spaulding Ave",
    "iso:country":"US",
    "sg:address":"44 E Spaulding Ave",
    "sg:city":"Pueblo West",
    "sg:classifiers":[
        {
            "category":"Building & Trades",
            "subcategory":"Construction",
            "type":"Services"
        }
    ],
    "sg:phone":"+1 719 647 1026",
    "sg:postcode":"81007",
    "sg:province":"CO",
    "sg:tags":[
        "home",
        "builder"
    ],
    "wof:name":"Family Home & Building Corp",
    "wof:placetype":"venue"
},
  "geometry": {"coordinates":[-104.742654,38.332429],"type":"Point"}
}