{
  "type": "Feature",
  "properties": {
    "iso:country":"US",
    "sg:address":"303 S Broadway Ste 200",
    "sg:city":"Denver",
    "sg:classifiers":[
        {
            "category":"Retail",
            "subcategory":"Auto Repair",
            "type":"Services"
        }
    ],
    "sg:phone":"+1 303 927 0581",
    "sg:postcode":"80209",
    "sg:province":"CO",
    "sg:tags":[
        "windshield"
    ],
    "wof:name":"Johnston Auto Glass",
    "wof:placetype":"venue"
},
  "geometry": {"coordinates":[-104.987587,39.711114],"type":"Point"}
}