{
  "type": "Feature",
  "properties": {
    "iso:country":"US",
    "sg:address":"2107 Templeton Gap Rd",
    "sg:city":"Colorado Springs",
    "sg:classifiers":[
        {
            "category":"Building & Trades",
            "subcategory":"Electrical",
            "type":"Services"
        }
    ],
    "sg:phone":"+1 719 473 8235",
    "sg:postcode":"80907",
    "sg:province":"CO",
    "sg:tags":[
        "repair",
        "installation",
        "telephone",
        "system"
    ],
    "wof:name":"Fast Line Svcs",
    "wof:placetype":"venue"
},
  "geometry": {"coordinates":[-104.80986,38.863833],"type":"Point"}
}