{
  "type": "Feature",
  "properties": {
    "iso:country":"US",
    "sg:address":"12784 N 3rd St",
    "sg:city":"Parker",
    "sg:classifiers":[
        {
            "category":"Manufacturing",
            "subcategory":"Toys & Sporting Goods",
            "type":"Manufacturing & Wholesale Goods"
        }
    ],
    "sg:phone":"+1 303 805 8991",
    "sg:postcode":"80134",
    "sg:province":"CO",
    "sg:tags":[
        "mfg"
    ],
    "wof:name":"Progressive Playgrounds Inc",
    "wof:placetype":"venue"
},
  "geometry": {"coordinates":[-104.82338300000001,39.545318],"type":"Point"}
}