{
  "type": "Feature",
  "properties": {
    "iso:country":"US",
    "sg:address":"902 S 4th St",
    "sg:city":"Montrose",
    "sg:classifiers":[
        {
            "category":"Health Services",
            "subcategory":"Doctor",
            "type":"Services"
        }
    ],
    "sg:phone":"+1 970 249 4321",
    "sg:postcode":"81401",
    "sg:province":"CO",
    "sg:tags":[
        "medical"
    ],
    "wof:name":"Surgical Montrose Assoc PC",
    "wof:placetype":"venue"
},
  "geometry": {"coordinates":[-107.86798899999999,38.479956],"type":"Point"}
}