{
  "type": "Feature",
  "properties": {
    "addr:full":"5480 Valmont Rd Boulder CO 80301",
    "addr:housenumber":"5480",
    "addr:postcode":"80301",
    "addr:street":"Valmont Rd",
    "iso:country":"US",
    "sg:address":"5480 Valmont Rd",
    "sg:city":"Boulder",
    "sg:classifiers":[
        {
            "category":"Building & Trades",
            "subcategory":"Construction",
            "type":"Services"
        }
    ],
    "sg:phone":"+1 720 565 2602",
    "sg:postcode":"80301",
    "sg:province":"CO",
    "sg:tags":[
        "contractor"
    ],
    "wof:name":"Valmont Building",
    "wof:placetype":"venue"
},
  "geometry": {"coordinates":[-105.226924,40.029153],"type":"Point"}
}