{
  "type": "Feature",
  "properties": {
    "iso:country":"US",
    "sg:address":"11392 Jay St",
    "sg:city":"Broomfield",
    "sg:classifiers":[
        {
            "category":"Building & Trades",
            "subcategory":"Electrical",
            "type":"Services"
        }
    ],
    "sg:phone":"+1 303 465 9272",
    "sg:postcode":"80020",
    "sg:province":"CO",
    "sg:tags":[
        "fire",
        "detection",
        "alarm",
        "system"
    ],
    "wof:name":"Holder Security Systems",
    "wof:placetype":"venue"
},
  "geometry": {"coordinates":[-105.063845,39.903665],"type":"Point"}
}