{
  "type": "Feature",
  "properties": {
    "addr:full":"13 Miners Creek Rd Frisco CO 80443",
    "addr:housenumber":"13",
    "addr:postcode":"80443",
    "addr:street":"Miners Creek Rd",
    "iso:country":"US",
    "sg:address":"13 Miners Creek Rd",
    "sg:city":"Frisco",
    "sg:classifiers":[
        {
            "category":"Travel",
            "subcategory":"Travel Agent",
            "type":"Entertainment"
        }
    ],
    "sg:phone":"+1 970 668 8900",
    "sg:postcode":"80443",
    "sg:province":"CO",
    "sg:tags":[
        "bicycle",
        "tours"
    ],
    "wof:name":"Colorado Bike Tours Etc",
    "wof:placetype":"venue"
},
  "geometry": {"coordinates":[-106.10401899999999,39.580347],"type":"Point"}
}