{
  "type": "Feature",
  "properties": {
    "addr:full":"2050 S Townsend Ave Montrose CO 81401",
    "addr:housenumber":"2050",
    "addr:postcode":"81401",
    "addr:street":"S Townsend Ave",
    "iso:country":"US",
    "sg:address":"2050 S Townsend Ave",
    "sg:city":"Montrose",
    "sg:classifiers":[
        {
            "category":"Restaurant",
            "type":"Food & Drink"
        }
    ],
    "sg:menulink":"http://www.allmenus.com/co/montrose/207930-taco-bell/menu/",
    "sg:phone":"+1 970 249 8570",
    "sg:postcode":"81401",
    "sg:province":"CO",
    "sg:tags":[
        "mexican"
    ],
    "wof:name":"Taco Bell",
    "wof:placetype":"venue"
},
  "geometry": {"coordinates":[-107.866274,38.461915],"type":"Point"}
}