{
  "type": "Feature",
  "properties": {
    "iso:country":"US",
    "sg:address":"9445 E Dry Creek Rd",
    "sg:city":"Englewood",
    "sg:classifiers":[
        {
            "category":"Travel",
            "subcategory":"Hotels & Motels",
            "type":"Entertainment"
        }
    ],
    "sg:phone":"+1 303 694 3400",
    "sg:postcode":"80112",
    "sg:province":"CO",
    "sg:website":"www.druryhotels.com",
    "wof:name":"Drury Inn & Suites-Near Tech",
    "wof:placetype":"venue"
},
  "geometry": {"coordinates":[-104.88117699999999,39.580529],"type":"Point"}
}