{
  "type": "Feature",
  "properties": {
    "iso:country":"US",
    "sg:address":"633 17th Street",
    "sg:city":"Denver",
    "sg:classifiers":[
        {
            "category":"Professional",
            "subcategory":"Lawyer & Legal Services",
            "type":"Services"
        }
    ],
    "sg:phone":"+1 303 297 2900",
    "sg:postcode":"80202",
    "sg:province":"CO",
    "wof:name":"Koenigs Christopher J Atty",
    "wof:placetype":"venue"
},
  "geometry": {"coordinates":[-104.990413,39.745648],"type":"Point"}
}