{
  "type": "Feature",
  "properties": {
    "iso:country":"US",
    "sg:address":"2629 Redwing Rd",
    "sg:city":"Fort Collins",
    "sg:classifiers":[
        {
            "category":"Professional",
            "subcategory":"Accounting & Tax Preparation",
            "type":"Services"
        }
    ],
    "sg:phone":"+1 970 226 1515",
    "sg:postcode":"80526",
    "sg:province":"CO",
    "sg:tags":[
        "accountant"
    ],
    "wof:name":"Hogan & Co",
    "wof:placetype":"venue"
},
  "geometry": {"coordinates":[-105.080499,40.55116],"type":"Point"}
}