{
  "type": "Feature",
  "properties": {
    "addr:full":"6560 S Academy Blvd Colorado Springs CO 80906",
    "addr:housenumber":"6560",
    "addr:postcode":"80906",
    "addr:street":"S Academy Blvd",
    "iso:country":"US",
    "sg:address":"6560 S Academy Blvd",
    "sg:city":"Colorado Springs",
    "sg:classifiers":[
        {
            "category":"Autos & Motor Vehicles",
            "subcategory":"Fuel & Gas Station",
            "type":"Retail Goods"
        }
    ],
    "sg:phone":"+1 719 538 0680",
    "sg:postcode":"80906",
    "sg:province":"CO",
    "sg:tags":[
        "station",
        "gasoline"
    ],
    "wof:name":"Shell Station Self Service",
    "wof:placetype":"venue"
},
  "geometry": {"coordinates":[-104.80939499999999,38.765816],"type":"Point"}
}