{
  "type": "Feature",
  "properties": {
    "iso:country":"US",
    "sg:address":"1495 W Garden of the Gods Rd",
    "sg:city":"Colorado Springs",
    "sg:classifiers":[
        {
            "category":"Health Services",
            "subcategory":"Medical Lab",
            "type":"Services"
        }
    ],
    "sg:phone":"+1 719 260 1128",
    "sg:postcode":"80907",
    "sg:province":"CO",
    "sg:tags":[
        "detection",
        "equipment",
        "drug"
    ],
    "wof:name":"H & L Drug Compliance",
    "wof:placetype":"venue"
},
  "geometry": {"coordinates":[-104.85356899999999,38.896544],"type":"Point"}
}