{
  "type": "Feature",
  "properties": {
    "iso:country":"US",
    "sg:address":"8858 Fiesta Ter",
    "sg:city":"Lone Tree",
    "sg:classifiers":[
        {
            "category":"Professional",
            "subcategory":"Accounting & Tax Preparation",
            "type":"Services"
        }
    ],
    "sg:phone":"+1 303 799 3910",
    "sg:postcode":"80124",
    "sg:province":"CO",
    "sg:tags":[
        "accountant"
    ],
    "wof:name":"Roger De Vries CPA",
    "wof:placetype":"venue"
},
  "geometry": {"coordinates":[-104.88609,39.549233],"type":"Point"}
}