{
  "type": "Feature",
  "properties": {
    "addr:full":"400 S Zuni St Denver CO 80223",
    "addr:housenumber":"400",
    "addr:postcode":"80223",
    "addr:street":"S Zuni St",
    "iso:country":"US",
    "sg:address":"400 S Zuni St",
    "sg:city":"Denver",
    "sg:classifiers":[
        {
            "category":"Home & Garden",
            "subcategory":"Hardware",
            "type":"Retail Goods"
        },
        {
            "category":"Home & Garden",
            "subcategory":"Building Materials",
            "type":"Retail Goods"
        }
    ],
    "sg:phone":"+1 303 262 5150",
    "sg:postcode":"80223",
    "sg:province":"CO",
    "sg:tags":[
        "store",
        "supply"
    ],
    "sg:website":"www.lowes.com",
    "wof:name":"Lowe's Home Improvement",
    "wof:placetype":"venue"
},
  "geometry": {"coordinates":[-105.01436200000001,39.709349],"type":"Point"}
}