{
  "type": "Feature",
  "properties": {
    "iso:country":"US",
    "sg:address":"2645 9th Ave",
    "sg:city":"Longmont",
    "sg:classifiers":[
        {
            "category":"Building & Trades",
            "subcategory":"Landscaping Services",
            "type":"Services"
        }
    ],
    "sg:phone":"+1 303 682 1126",
    "sg:postcode":"80503",
    "sg:province":"CO",
    "sg:tags":[
        "landscape"
    ],
    "wof:name":"Porter Bros",
    "wof:placetype":"venue"
},
  "geometry": {"coordinates":[-105.137182,40.174074],"type":"Point"}
}