{
  "type": "Feature",
  "properties": {
    "iso:country":"US",
    "sg:address":"319 Main St",
    "sg:city":"Grand Junction",
    "sg:classifiers":[
        {
            "category":"Restaurant",
            "type":"Food & Drink"
        }
    ],
    "sg:menulink":"http://www.allmenus.com/co/grand-junction/278130-pablos-pizza/menu/",
    "sg:phone":"+1 970 255 8879",
    "sg:postcode":"81501",
    "sg:province":"CO",
    "sg:tags":[
        "american",
        "pizza"
    ],
    "wof:name":"Pablo's Pizza",
    "wof:placetype":"venue"
},
  "geometry": {"coordinates":[-108.567392,39.067161],"type":"Point"}
}