{
  "type": "Feature",
  "properties": {
    "addr:full":"1005 Caprice Dr Castle Rock CO 80109",
    "addr:housenumber":"1005",
    "addr:postcode":"80109",
    "addr:street":"Caprice Dr",
    "iso:country":"US",
    "sg:address":"1005 Caprice Dr",
    "sg:city":"Castle Rock",
    "sg:classifiers":[
        {
            "category":"Personal",
            "subcategory":"Beauty Salon",
            "type":"Services"
        }
    ],
    "sg:phone":"+1 303 660 0947",
    "sg:postcode":"80109",
    "sg:province":"CO",
    "wof:name":"Affordable Cuts",
    "wof:placetype":"venue"
},
  "geometry": {"coordinates":[-104.86401499999999,39.382429],"type":"Point"}
}