{
  "type": "Feature",
  "properties": {
    "addr:full":"4155 W 76th Ave Westminster CO 80030",
    "addr:housenumber":"4155",
    "addr:postcode":"80030",
    "addr:street":"W 76Th Ave",
    "iso:country":"US",
    "sg:address":"4155 W 76th Ave",
    "sg:city":"Westminster",
    "sg:classifiers":[
        {
            "category":"Manufacturing",
            "subcategory":"Tools & Machinery",
            "type":"Manufacturing & Wholesale Goods"
        }
    ],
    "sg:phone":"+1 303 424 7465",
    "sg:postcode":"80030",
    "sg:province":"CO",
    "sg:tags":[
        "industrial",
        "mfg"
    ],
    "wof:name":"Sigys Machine Service",
    "wof:placetype":"venue"
},
  "geometry": {"coordinates":[-105.043058,39.834608],"type":"Point"}
}