{
  "type": "Feature",
  "properties": {
    "addr:full":"5525 Astrozon Blvd Colorado Springs CO 80916",
    "addr:housenumber":"5525",
    "addr:postcode":"80916",
    "addr:street":"Astrozon Blvd",
    "iso:country":"US",
    "sg:address":"5525 Astrozon Blvd",
    "sg:city":"Colorado Springs",
    "sg:classifiers":[
        {
            "category":"Education",
            "subcategory":"School",
            "type":"Public Place"
        }
    ],
    "sg:phone":"+1 719 591 2122",
    "sg:postcode":"80916",
    "sg:province":"CO",
    "sg:website":"www.jamesirwin.org",
    "wof:name":"James Irwin Charter Middle",
    "wof:placetype":"venue"
},
  "geometry": {"coordinates":[-104.7239,38.798769],"type":"Point"}
}