{
  "type": "Feature",
  "properties": {
    "iso:country":"US",
    "sg:address":"6235 N Taft Hill Rd",
    "sg:city":"Fort Collins",
    "sg:classifiers":[
        {
            "category":"Banks & Credit Unions",
            "subcategory":"Financial Services",
            "type":"Services"
        }
    ],
    "sg:phone":"+1 970 484 3103",
    "sg:postcode":"80524",
    "sg:province":"CO",
    "sg:tags":[
        "investor"
    ],
    "wof:name":"HEI",
    "wof:placetype":"venue"
},
  "geometry": {"coordinates":[-105.11316100000001,40.67857],"type":"Point"}
}