{
  "type": "Feature",
  "properties": {
    "iso:country":"US",
    "sg:address":"10260 W 44th Ave",
    "sg:city":"Wheat Ridge",
    "sg:classifiers":[
        {
            "category":"Shopping",
            "subcategory":"Computers & Home Electronics",
            "type":"Retail Goods"
        }
    ],
    "sg:phone":"+1 303 403 0561",
    "sg:postcode":"80033",
    "sg:province":"CO",
    "wof:name":"Disconnect Cable Inc",
    "wof:placetype":"venue"
},
  "geometry": {"coordinates":[-105.113983,39.778081],"type":"Point"}
}