{
  "type": "Feature",
  "properties": {
    "iso:country":"US",
    "sg:address":"7249 Mineral Wells Dr",
    "sg:city":"Colorado Springs",
    "sg:classifiers":[
        {
            "category":"Building & Trades",
            "subcategory":"Construction",
            "type":"Services"
        }
    ],
    "sg:phone":"+1 719 592 0144",
    "sg:postcode":"80923",
    "sg:province":"CO",
    "sg:tags":[
        "general",
        "contractor"
    ],
    "wof:name":"Star Construction & Mntnc",
    "wof:placetype":"venue"
},
  "geometry": {"coordinates":[-104.728641,38.935137],"type":"Point"}
}