{
  "type": "Feature",
  "properties": {
    "addr:full":"700 E 9th Ave Denver CO 80203",
    "addr:housenumber":"700",
    "addr:postcode":"80203",
    "addr:street":"E 9Th Ave",
    "iso:country":"US",
    "sg:address":"700 E 9th Ave",
    "sg:city":"Denver",
    "sg:classifiers":[
        {
            "category":"Health Services",
            "subcategory":"Doctor",
            "type":"Services"
        }
    ],
    "sg:phone":"+1 303 832 7300",
    "sg:postcode":"80203",
    "sg:province":"CO",
    "wof:name":"Venuto Nick DDS",
    "wof:placetype":"venue"
},
  "geometry": {"coordinates":[-104.977585,39.730433],"type":"Point"}
}