{
  "type": "Feature",
  "properties": {
    "addr:full":"1327 Coffman St Longmont CO 80501",
    "addr:housenumber":"1327",
    "addr:postcode":"80501",
    "addr:street":"Coffman St",
    "iso:country":"US",
    "sg:address":"1327 Coffman St",
    "sg:city":"Longmont",
    "sg:classifiers":[
        {
            "category":"Retail",
            "subcategory":"Auto Repair",
            "type":"Services"
        }
    ],
    "sg:phone":"+1 303 485 7666",
    "sg:postcode":"80501",
    "sg:province":"CO",
    "sg:tags":[
        "repairing",
        "automobile"
    ],
    "wof:name":"Bigger Better Faster",
    "wof:placetype":"venue"
},
  "geometry": {"coordinates":[-105.103729,40.181885],"type":"Point"}
}