{
  "type": "Feature",
  "properties": {
    "addr:full":"200 E 7th Ave Denver CO 80203",
    "addr:housenumber":"200",
    "addr:postcode":"80203",
    "addr:street":"E 7Th Ave",
    "iso:country":"US",
    "sg:address":"200 E 7th Ave",
    "sg:city":"Denver",
    "sg:classifiers":[
        {
            "category":"Retail",
            "subcategory":"Laundry & Dry Cleaning",
            "type":"Services"
        }
    ],
    "sg:phone":"+1 303 837 1338",
    "sg:postcode":"80203",
    "sg:province":"CO",
    "wof:name":"Colorado Lace & Dry Clg Co",
    "wof:placetype":"venue"
},
  "geometry": {"coordinates":[-104.98362299999999,39.727282],"type":"Point"}
}