{
  "type": "Feature",
  "properties": {
    "addr:full":"9210 W 2nd Ave Lakewood CO 80226",
    "addr:housenumber":"9210",
    "addr:postcode":"80226",
    "addr:street":"W 2Nd Ave",
    "iso:country":"US",
    "sg:address":"9210 W 2nd Ave",
    "sg:city":"Lakewood",
    "sg:classifiers":[
        {
            "category":"Organizations",
            "subcategory":"Religious Organization",
            "type":"Services"
        }
    ],
    "sg:phone":"+1 303 233 7017",
    "sg:postcode":"80226",
    "sg:province":"CO",
    "sg:tags":[
        "church"
    ],
    "sg:website":"www.gfol.org",
    "wof:name":"Grace Fellowship Of Lakewood",
    "wof:placetype":"venue"
},
  "geometry": {"coordinates":[-105.101529,39.719764],"type":"Point"}
}