{
  "type": "Feature",
  "properties": {
    "addr:full":"2187 Lassen Ct Grand Junction CO 81503",
    "addr:housenumber":"2187",
    "addr:postcode":"81503",
    "addr:street":"Lassen Ct",
    "iso:country":"US",
    "sg:address":"2187 Lassen Ct",
    "sg:city":"Grand Junction",
    "sg:classifiers":[
        {
            "category":"Building & Trades",
            "subcategory":"Construction",
            "type":"Services"
        }
    ],
    "sg:phone":"+1 970 245 3448",
    "sg:postcode":"81503",
    "sg:province":"CO",
    "sg:tags":[
        "residential",
        "remodeling",
        "commercial",
        "renovation"
    ],
    "wof:name":"Scott Hodges Construction",
    "wof:placetype":"venue"
},
  "geometry": {"coordinates":[-108.65072000000001,39.09301],"type":"Point"}
}