{
  "type": "Feature",
  "properties": {
    "iso:country":"US",
    "sg:address":"6587 W Colfax Ave",
    "sg:city":"Denver",
    "sg:classifiers":[
        {
            "category":"Shopping",
            "subcategory":"Clothing, Apparel, & Fashions",
            "type":"Retail Goods"
        }
    ],
    "sg:phone":"+1 303 274 6963",
    "sg:postcode":"80214",
    "sg:province":"CO",
    "wof:name":"New Sensation Fashion",
    "wof:placetype":"venue"
},
  "geometry": {"coordinates":[-105.067885,39.740411],"type":"Point"}
}