{
  "type": "Feature",
  "properties": {
    "addr:full":"3021 N Hancock Ave Colorado Springs CO 80907",
    "addr:housenumber":"3021",
    "addr:postcode":"80907",
    "addr:street":"N Hancock Ave",
    "iso:country":"US",
    "sg:address":"3021 N Hancock Ave",
    "sg:city":"Colorado Springs",
    "sg:classifiers":[
        {
            "category":"Social Services",
            "subcategory":"Child Care",
            "type":"Services"
        }
    ],
    "sg:phone":"+1 719 329 0137",
    "sg:postcode":"80907",
    "sg:province":"CO",
    "wof:name":"Medallion School Partnerships",
    "wof:placetype":"venue"
},
  "geometry": {"coordinates":[-104.803425,38.872987],"type":"Point"}
}