{
  "type": "Feature",
  "properties": {
    "addr:full":"7562 S University Blvd Centennial CO 80122",
    "addr:housenumber":"7562",
    "addr:postcode":"80122",
    "addr:street":"S University Blvd",
    "iso:country":"US",
    "sg:address":"7562 S University Blvd",
    "sg:city":"Centennial",
    "sg:classifiers":[
        {
            "category":"Shopping",
            "subcategory":"Books",
            "type":"Retail Goods"
        }
    ],
    "sg:phone":"+1 303 973 5440",
    "sg:postcode":"80122",
    "sg:province":"CO",
    "sg:tags":[
        "dealer"
    ],
    "wof:name":"Logos Christian Book Store",
    "wof:placetype":"venue"
},
  "geometry": {"coordinates":[-104.960289,39.578747],"type":"Point"}
}