{
  "type": "Feature",
  "properties": {
    "addr:full":"258 S Downing St Denver CO 80209",
    "addr:housenumber":"258",
    "addr:postcode":"80209",
    "addr:street":"S Downing St",
    "iso:country":"US",
    "sg:address":"258 S Downing St",
    "sg:city":"Denver",
    "sg:classifiers":[
        {
            "category":"Retail",
            "subcategory":"Laundry & Dry Cleaning",
            "type":"Services"
        }
    ],
    "sg:phone":"+1 303 733 6557",
    "sg:postcode":"80209",
    "sg:province":"CO",
    "sg:tags":[
        "cleaner"
    ],
    "sg:website":"revolutioncleaners.com",
    "wof:name":"Revolution Cleaners",
    "wof:placetype":"venue"
},
  "geometry": {"coordinates":[-104.973052,39.711683],"type":"Point"}
}