{
  "type": "Feature",
  "properties": {
    "iso:country":"US",
    "sg:address":"344 E Foothills Pkwy",
    "sg:city":"Fort Collins",
    "sg:classifiers":[
        {
            "category":"Government",
            "subcategory":"Office",
            "type":"Public Place"
        }
    ],
    "sg:phone":"+1 970 223 9838",
    "sg:postcode":"80525",
    "sg:province":"CO",
    "wof:name":"Co State Electrical Board",
    "wof:placetype":"venue"
},
  "geometry": {"coordinates":[-105.076252,40.543415],"type":"Point"}
}