{
  "type": "Feature",
  "properties": {
    "addr:full":"3840 Camels Ridge Ln Colorado Springs CO 80904",
    "addr:postcode":"3840;80904",
    "addr:street":"Camels Ridge Ln",
    "iso:country":"US",
    "sg:address":"3840 Camels Ridge Ln",
    "sg:city":"Colorado Springs",
    "sg:classifiers":[
        {
            "category":"Professional",
            "subcategory":"Advertising",
            "type":"Services"
        }
    ],
    "sg:phone":"+1 719 634 3006",
    "sg:postcode":"80904",
    "sg:province":"CO",
    "sg:tags":[
        "counselor"
    ],
    "wof:name":"Steve Haggart Creative Svc",
    "wof:placetype":"venue"
},
  "geometry": {"coordinates":[-104.856949,38.885963],"type":"Point"}
}