{
  "type": "Feature",
  "properties": {
    "addr:full":"2629 S Prairie Ave Pueblo CO 81005",
    "addr:housenumber":"2629",
    "addr:postcode":"81005",
    "addr:street":"S Prairie Ave",
    "iso:country":"US",
    "sg:address":"2629 S Prairie Ave",
    "sg:city":"Pueblo",
    "sg:classifiers":[
        {
            "category":"Building & Trades",
            "subcategory":"Construction",
            "type":"Services"
        }
    ],
    "sg:phone":"+1 719 566 3240",
    "sg:postcode":"81005",
    "sg:province":"CO",
    "sg:tags":[
        "sheet",
        "metal",
        "heating",
        "air",
        "conditioning",
        "contractor"
    ],
    "wof:name":"Elmers Sheetmetal Inc",
    "wof:placetype":"venue"
},
  "geometry": {"coordinates":[-104.64378600000001,38.222685],"type":"Point"}
}