{
  "type": "Feature",
  "properties": {
    "iso:country":"US",
    "sg:address":"13945 Turnberry Ct",
    "sg:city":"Broomfield",
    "sg:classifiers":[
        {
            "category":"Banks & Credit Unions",
            "subcategory":"Financial Services",
            "type":"Services"
        }
    ],
    "sg:phone":"+1 303 349 7469",
    "sg:postcode":"80020",
    "sg:province":"CO",
    "sg:tags":[
        "investor"
    ],
    "wof:name":"High States Investments LLC",
    "wof:placetype":"venue"
},
  "geometry": {"coordinates":[-105.03903800000001,39.950631],"type":"Point"}
}