{
  "type": "Feature",
  "properties": {
    "iso:country":"US",
    "sg:address":"13187 Co Rd 25",
    "sg:city":"Karval",
    "sg:classifiers":[
        {
            "category":"Wholesale",
            "subcategory":"Farm Supplies",
            "type":"Manufacturing & Wholesale Goods"
        }
    ],
    "sg:phone":"+1 719 446 5373",
    "sg:postcode":"80823",
    "sg:province":"CO",
    "sg:tags":[
        "livestock"
    ],
    "wof:name":"Carson D Kravig",
    "wof:placetype":"venue"
},
  "geometry": {"coordinates":[-103.607699,38.70327],"type":"Point"}
}