{
  "type": "Feature",
  "properties": {
    "addr:full":"1670 Broadway Denver CO 80202",
    "addr:housenumber":"1670",
    "addr:postcode":"80202",
    "addr:street":"Broadway",
    "iso:country":"US",
    "sg:address":"1670 Broadway",
    "sg:city":"Denver",
    "sg:classifiers":[
        {
            "category":"Banks & Credit Unions",
            "subcategory":"Financial Services",
            "type":"Services"
        }
    ],
    "sg:phone":"+1 720 407 1540",
    "sg:postcode":"80202",
    "sg:province":"CO",
    "sg:tags":[
        "broker",
        "mortgage"
    ],
    "wof:name":"In-House Lenders",
    "wof:placetype":"venue"
},
  "geometry": {"coordinates":[-104.987386,39.742941],"type":"Point"}
}