{
  "type": "Feature",
  "properties": {
    "addr:full":"109 W Main St Trinidad CO 81082",
    "addr:housenumber":"109",
    "addr:postcode":"81082",
    "addr:street":"W Main St",
    "iso:country":"US",
    "sg:address":"109 W Main St",
    "sg:city":"Trinidad",
    "sg:classifiers":[
        {
            "category":"Mining & Drilling",
            "type":"Manufacturing & Wholesale Goods"
        }
    ],
    "sg:phone":"+1 719 868 2115",
    "sg:postcode":"81082",
    "sg:province":"CO",
    "sg:tags":[
        "coal"
    ],
    "wof:name":"Lorencito Coal Co LLC",
    "wof:placetype":"venue"
},
  "geometry": {"coordinates":[-104.50574899999999,37.16852],"type":"Point"}
}