{
  "type": "Feature",
  "properties": {
    "addr:full":"27680 US Hwy 50 La Junta CO 81050",
    "addr:postcode":"27680;81050",
    "addr:street":"Us Hwy 50",
    "iso:country":"US",
    "sg:address":"27680 US Hwy 50",
    "sg:city":"La Junta",
    "sg:classifiers":[
        {
            "category":"Restaurant",
            "type":"Food & Drink"
        }
    ],
    "sg:phone":"+1 719 384 8979",
    "sg:postcode":"81050",
    "sg:province":"CO",
    "wof:name":"Mc Donald's",
    "wof:placetype":"venue"
},
  "geometry": {"coordinates":[-103.568206,37.990853],"type":"Point"}
}