{
  "type": "Feature",
  "properties": {
    "iso:country":"US",
    "sg:address":"1019 Ohio Ave",
    "sg:city":"Canon City",
    "sg:classifiers":[
        {
            "category":"Building & Trades",
            "subcategory":"Construction",
            "type":"Services"
        }
    ],
    "sg:phone":"+1 719 269 3613",
    "sg:postcode":"81212",
    "sg:province":"CO",
    "sg:tags":[
        "contractor"
    ],
    "wof:name":"Tim Reed & Sons",
    "wof:placetype":"venue"
},
  "geometry": {"coordinates":[-105.236221,38.45481],"type":"Point"}
}