{
  "type": "Feature",
  "properties": {
    "addr:full":"515 Valley View Rd Loveland CO 80537",
    "addr:housenumber":"515",
    "addr:postcode":"80537",
    "addr:street":"Valley View Rd",
    "iso:country":"US",
    "sg:address":"515 Valley View Rd",
    "sg:city":"Loveland",
    "sg:classifiers":[
        {
            "category":"Shopping",
            "type":"Retail Goods"
        }
    ],
    "sg:phone":"+1 970 667 0533",
    "sg:postcode":"80537",
    "sg:province":"CO",
    "sg:tags":[
        "wedding",
        "supply"
    ],
    "wof:name":"Sunshine Photography",
    "wof:placetype":"venue"
},
  "geometry": {"coordinates":[-105.07409199999999,40.3536],"type":"Point"}
}