{
  "type": "Feature",
  "properties": {
    "addr:full":"8800 E Colfax Ave Denver CO 80220",
    "addr:housenumber":"8800",
    "addr:postcode":"80220",
    "addr:street":"E Colfax Ave",
    "iso:country":"US",
    "sg:address":"8800 E Colfax Ave",
    "sg:city":"Denver",
    "sg:classifiers":[
        {
            "category":"Food & Beverages",
            "subcategory":"Ethnic Foods",
            "type":"Retail Goods"
        },
        {
            "category":"Food & Beverages",
            "subcategory":"Groceries & Convenience Stores",
            "type":"Retail Goods"
        }
    ],
    "sg:phone":"+1 303 399 3777",
    "sg:postcode":"80220",
    "sg:province":"CO",
    "wof:name":"Family Asia Market",
    "wof:placetype":"venue"
},
  "geometry": {"coordinates":[-104.88581000000001,39.739953],"type":"Point"}
}