{
  "type": "Feature",
  "properties": {
    "iso:country":"US",
    "sg:address":"6312 S Fiddlers Green Cir",
    "sg:city":"Englewood",
    "sg:classifiers":[
        {
            "category":"Restaurant",
            "type":"Food & Drink"
        }
    ],
    "sg:phone":"+1 303 290 8911",
    "sg:postcode":"80111",
    "sg:province":"CO",
    "sg:tags":[
        "eating"
    ],
    "wof:name":"Munch A Lunch I",
    "wof:placetype":"venue"
},
  "geometry": {"coordinates":[-104.890475,39.60152],"type":"Point"}
}