{
  "type": "Feature",
  "properties": {
    "iso:country":"US",
    "sg:address":"1523 18th St",
    "sg:city":"Denver",
    "sg:classifiers":[
        {
            "category":"Shopping",
            "type":"Retail Goods"
        }
    ],
    "sg:phone":"+1 303 298 1119",
    "sg:postcode":"80206",
    "sg:province":"CO",
    "sg:tags":[
        "merchandise"
    ],
    "wof:name":"Art Framers",
    "wof:placetype":"venue"
},
  "geometry": {"coordinates":[-104.997379,39.752987],"type":"Point"}
}