{
  "type": "Feature",
  "properties": {
    "iso:country":"US",
    "sg:address":"2 N Cascade Ave",
    "sg:city":"Colorado Springs",
    "sg:classifiers":[
        {
            "category":"Real Estate",
            "subcategory":"Real Estate Agent",
            "type":"Services"
        }
    ],
    "sg:phone":"+1 719 634 1330",
    "sg:postcode":"80903",
    "sg:province":"CO",
    "sg:tags":[
        "appraiser"
    ],
    "wof:name":"Turner Commercial Research",
    "wof:placetype":"venue"
},
  "geometry": {"coordinates":[-104.82514999999999,38.835369],"type":"Point"}
}