{
  "type": "Feature",
  "properties": {
    "addr:full":"11590 Black Forest Rd Colorado Springs CO 80908",
    "addr:housenumber":"11590",
    "addr:postcode":"80908",
    "addr:street":"Black Forest Rd",
    "iso:country":"US",
    "sg:address":"11590 Black Forest Rd",
    "sg:city":"Colorado Springs",
    "sg:classifiers":[
        {
            "category":"Shopping",
            "subcategory":"Bicycles & Sporting Goods",
            "type":"Retail Goods"
        }
    ],
    "sg:phone":"+1 719 495 8906",
    "sg:postcode":"80908",
    "sg:province":"CO",
    "sg:tags":[
        "saddlery",
        "harness"
    ],
    "wof:name":"Equi-Line",
    "wof:placetype":"venue"
},
  "geometry": {"coordinates":[-104.70043099999999,38.999535],"type":"Point"}
}