{
  "type": "Feature",
  "properties": {
    "addr:full":"700 Colorado Blvd Unit A Denver CO 80206",
    "addr:housenumber":"700",
    "addr:postcode":"80206",
    "addr:street":"Colorado Blvd Unit A",
    "iso:country":"US",
    "sg:address":"700 Colorado Blvd Unit A",
    "sg:city":"Denver",
    "sg:classifiers":[
        {
            "category":"Building & Trades",
            "subcategory":"Construction",
            "type":"Services"
        }
    ],
    "sg:phone":"+1 303 586 8022",
    "sg:postcode":"80206",
    "sg:province":"CO",
    "sg:tags":[
        "contractor"
    ],
    "sg:website":"www.garagedoors-denver.com",
    "wof:name":"Northgate Garage Doors",
    "wof:placetype":"venue"
},
  "geometry": {"coordinates":[-104.94028900000001,39.727672],"type":"Point"}
}