{
  "type": "Feature",
  "properties": {
    "iso:country":"US",
    "sg:address":"1102 W 95th Pl",
    "sg:city":"Denver",
    "sg:classifiers":[
        {
            "category":"Retail",
            "subcategory":"Repair Shop",
            "type":"Services"
        }
    ],
    "sg:phone":"+1 303 650 8672",
    "sg:postcode":"80260",
    "sg:province":"CO",
    "sg:tags":[
        "range",
        "oven"
    ],
    "wof:name":"Precision Appliance",
    "wof:placetype":"venue"
},
  "geometry": {"coordinates":[-105.002343,39.869629],"type":"Point"}
}