{
  "type": "Feature",
  "properties": {
    "addr:full":"203 W Mulberry St Fort Collins CO 80521",
    "addr:housenumber":"203",
    "addr:postcode":"80521",
    "addr:street":"W Mulberry St",
    "iso:country":"US",
    "sg:address":"203 W Mulberry St",
    "sg:city":"Fort Collins",
    "sg:classifiers":[
        {
            "category":"Retail",
            "subcategory":"Auto Repair",
            "type":"Services"
        }
    ],
    "sg:phone":"+1 970 490 2000",
    "sg:postcode":"80521",
    "sg:province":"CO",
    "sg:tags":[
        "repairing",
        "automobile"
    ],
    "wof:name":"King's Auto Svc & Emissions",
    "wof:placetype":"venue"
},
  "geometry": {"coordinates":[-105.079801,40.581411],"type":"Point"}
}