{
  "type": "Feature",
  "properties": {
    "addr:full":"415 Mason Ct Fort Collins CO 80524",
    "addr:housenumber":"415",
    "addr:postcode":"80524",
    "addr:street":"Mason Ct",
    "iso:country":"US",
    "sg:address":"415 Mason Ct",
    "sg:city":"Fort Collins",
    "sg:classifiers":[
        {
            "category":"Professional",
            "subcategory":"Lawyer & Legal Services",
            "type":"Services"
        }
    ],
    "sg:phone":"+1 970 482 5262",
    "sg:postcode":"80524",
    "sg:province":"CO",
    "sg:tags":[
        "attorney"
    ],
    "wof:name":"Randall C Lococo",
    "wof:placetype":"venue"
},
  "geometry": {"coordinates":[-105.079005,40.592254],"type":"Point"}
}