{
  "type": "Feature",
  "properties": {
    "iso:country":"US",
    "sg:address":"7365 Alkire Ct",
    "sg:city":"Arvada",
    "sg:classifiers":[
        {
            "category":"Wholesale",
            "subcategory":"Furniture",
            "type":"Manufacturing & Wholesale Goods"
        }
    ],
    "sg:phone":"+1 303 420 7345",
    "sg:postcode":"80005",
    "sg:province":"CO",
    "wof:name":"D & D Record Systems",
    "wof:placetype":"venue"
},
  "geometry": {"coordinates":[-105.14810199999999,39.829981],"type":"Point"}
}