{
  "type": "Feature",
  "properties": {
    "iso:country":"US",
    "sg:address":"571 Lafayette St",
    "sg:city":"Denver",
    "sg:classifiers":[
        {
            "category":"Professional",
            "type":"Services"
        }
    ],
    "sg:phone":"+1 303 715 0168",
    "sg:postcode":"80218",
    "sg:province":"CO",
    "wof:name":"Barking Dog Inc",
    "wof:placetype":"venue"
},
  "geometry": {"coordinates":[-104.970671,39.724274],"type":"Point"}
}