{
  "type": "Feature",
  "properties": {
    "iso:country":"US",
    "sg:address":"453 W Elkhorn Ave",
    "sg:city":"Estes Park",
    "sg:classifiers":[
        {
            "category":"Insurance",
            "subcategory":"Insurance Agent",
            "type":"Services"
        }
    ],
    "sg:phone":"+1 970 586 9581",
    "sg:postcode":"80517",
    "sg:province":"CO",
    "wof:name":"Farmers Insurance Group",
    "wof:placetype":"venue"
},
  "geometry": {"coordinates":[-105.529808,40.376398],"type":"Point"}
}