{
  "type": "Feature",
  "properties": {
    "addr:full":"501 S Cherry St Ste 500 Denver CO 80246",
    "addr:housenumber":"501",
    "addr:postcode":"80246",
    "addr:street":"S Cherry St Ste 500",
    "iso:country":"US",
    "sg:address":"501 S Cherry St Ste 500",
    "sg:city":"Denver",
    "sg:classifiers":[
        {
            "category":"Professional",
            "subcategory":"Lawyer & Legal Services",
            "type":"Services"
        }
    ],
    "sg:phone":"+1 405 333 3333",
    "sg:postcode":"80246",
    "sg:province":"CO",
    "sg:website":"www.coloradolawyers.com",
    "wof:name":"Irwin & Boesen",
    "wof:placetype":"venue"
},
  "geometry": {"coordinates":[-104.933548,39.707417],"type":"Point"}
}