{
  "type": "Feature",
  "properties": {
    "iso:country":"US",
    "sg:address":"3333 S Bannock St",
    "sg:city":"Englewood",
    "sg:classifiers":[
        {
            "category":"Banks & Credit Unions",
            "subcategory":"Bank",
            "type":"Services"
        }
    ],
    "sg:phone":"+1 303 788 1693",
    "sg:postcode":"80110",
    "sg:province":"CO",
    "sg:tags":[
        "loan",
        "real estate"
    ],
    "wof:name":"Wallick & Volk",
    "wof:placetype":"venue"
},
  "geometry": {"coordinates":[-104.99006300000001,39.655598],"type":"Point"}
}