{
  "type": "Feature",
  "properties": {
    "iso:country":"US",
    "sg:address":"5450 Meridian Rd",
    "sg:city":"Peyton",
    "sg:classifiers":[
        {
            "category":"Education",
            "subcategory":"School",
            "type":"Public Place"
        }
    ],
    "sg:phone":"+1 719 683 9544",
    "sg:postcode":"80831",
    "sg:province":"CO",
    "sg:website":"www.ppsel.org",
    "wof:name":"Pikes Peak School Of Learning",
    "wof:placetype":"venue"
},
  "geometry": {"coordinates":[-104.607837,38.911609],"type":"Point"}
}