{
  "type": "Feature",
  "properties": {
    "iso:country":"US",
    "sg:address":"7950 S Lincoln St",
    "sg:city":"Centennial",
    "sg:classifiers":[
        {
            "category":"Professional",
            "subcategory":"Art Services",
            "type":"Services"
        }
    ],
    "sg:phone":"+1 303 798 6448",
    "sg:postcode":"80122",
    "sg:province":"CO",
    "sg:tags":[
        "graphic",
        "designer"
    ],
    "wof:name":"Source Unlimited",
    "wof:placetype":"venue"
},
  "geometry": {"coordinates":[-104.98732200000001,39.571498],"type":"Point"}
}