{
  "type": "Feature",
  "properties": {
    "iso:country":"US",
    "sg:address":"107 N 10th St",
    "sg:city":"Canon City",
    "sg:classifiers":[
        {
            "category":"Personal",
            "subcategory":"Beauty Salon",
            "type":"Services"
        }
    ],
    "sg:phone":"+1 719 275 7575",
    "sg:postcode":"81212",
    "sg:province":"CO",
    "wof:name":"Hot Loc's Salon",
    "wof:placetype":"venue"
},
  "geometry": {"coordinates":[-105.234586,38.443961],"type":"Point"}
}