{
  "type": "Feature",
  "properties": {
    "addr:full":"110 N 7th St Silt CO 81652",
    "addr:housenumber":"110",
    "addr:postcode":"81652",
    "addr:street":"N 7Th St",
    "iso:country":"US",
    "sg:address":"110 N 7th St",
    "sg:city":"Silt",
    "sg:classifiers":[
        {
            "category":"Home & Garden",
            "subcategory":"Furniture",
            "type":"Retail Goods"
        }
    ],
    "sg:phone":"+1 970 876 2786",
    "sg:postcode":"81652",
    "sg:province":"CO",
    "wof:name":"Woodworks",
    "wof:placetype":"venue"
},
  "geometry": {"coordinates":[-107.655682,39.547367],"type":"Point"}
}