{
  "type": "Feature",
  "properties": {
    "addr:full":"10556 Snowy Trl Conifer CO 80433",
    "addr:housenumber":"10556",
    "addr:postcode":"80433",
    "addr:street":"Snowy Trl",
    "iso:country":"US",
    "sg:address":"10556 Snowy Trl",
    "sg:city":"Conifer",
    "sg:classifiers":[
        {
            "category":"Manufacturing",
            "subcategory":"Food",
            "type":"Manufacturing & Wholesale Goods"
        }
    ],
    "sg:phone":"+1 303 697 0140",
    "sg:postcode":"80433",
    "sg:province":"CO",
    "sg:tags":[
        "product",
        "dairy",
        "mfg"
    ],
    "wof:name":"Success For Life",
    "wof:placetype":"venue"
},
  "geometry": {"coordinates":[-105.24991900000001,39.525417],"type":"Point"}
}