{
  "type": "Feature",
  "properties": {
    "iso:country":"US",
    "sg:address":"7697 E Iliff Ave",
    "sg:city":"Denver",
    "sg:classifiers":[
        {
            "category":"Retail",
            "subcategory":"Auto Repair",
            "type":"Services"
        }
    ],
    "sg:phone":"+1 303 369 6124",
    "sg:postcode":"80231",
    "sg:province":"CO",
    "sg:tags":[
        "automotive"
    ],
    "wof:name":"Jiffy Lube",
    "wof:placetype":"venue"
},
  "geometry": {"coordinates":[-104.899018,39.674973],"type":"Point"}
}