{
  "type": "Feature",
  "properties": {
    "addr:full":"6000 E Evans Ave 1-100 Denver CO 80222",
    "addr:housenumber":"6000;1-100",
    "addr:postcode":"80222",
    "addr:street":"E Evans Ave",
    "iso:country":"US",
    "sg:address":"6000 E Evans Ave 1-100",
    "sg:city":"Denver",
    "sg:classifiers":[
        {
            "category":"Professional",
            "subcategory":"Lawyer & Legal Services",
            "type":"Services"
        }
    ],
    "sg:phone":"+1 303 629 8333",
    "sg:postcode":"80222",
    "sg:province":"CO",
    "sg:tags":[
        "trust",
        "living",
        "planning",
        "probate",
        "estate"
    ],
    "wof:name":"Foundation Advancing Community Economics",
    "wof:placetype":"venue"
},
  "geometry": {"coordinates":[-104.917838,39.678446],"type":"Point"}
}