{
  "type": "Feature",
  "properties": {
    "iso:country":"US",
    "sg:address":"3600 S Clarkson St",
    "sg:city":"Englewood",
    "sg:classifiers":[
        {
            "category":"Social Services",
            "subcategory":"Child Care",
            "type":"Services"
        }
    ],
    "sg:phone":"+1 303 806 5127",
    "sg:postcode":"80113",
    "sg:province":"CO",
    "sg:tags":[
        "kindergarten",
        "academic",
        "school"
    ],
    "wof:name":"My School Pre School",
    "wof:placetype":"venue"
},
  "geometry": {"coordinates":[-104.9783,39.649491],"type":"Point"}
}