{
  "type": "Feature",
  "properties": {
    "addr:full":"33300 Placer Cir Elizabeth CO 80107",
    "addr:housenumber":"33300",
    "addr:postcode":"80107",
    "addr:street":"Placer Cir",
    "iso:country":"US",
    "sg:address":"33300 Placer Cir",
    "sg:city":"Elizabeth",
    "sg:classifiers":[
        {
            "category":"Professional",
            "subcategory":"Accounting & Tax Preparation",
            "type":"Services"
        }
    ],
    "sg:phone":"+1 303 646 9600",
    "sg:postcode":"80107",
    "sg:province":"CO",
    "sg:tags":[
        "billing"
    ],
    "wof:name":"Alternative Billing Solutions",
    "wof:placetype":"venue"
},
  "geometry": {"coordinates":[-104.61241699999999,39.349168],"type":"Point"}
}