{
  "type": "Feature",
  "properties": {
    "iso:country":"US",
    "sg:address":"7255 Grand Valley Dr",
    "sg:city":"Colorado Springs",
    "sg:classifiers":[
        {
            "category":"Freight",
            "type":"Transportation"
        }
    ],
    "sg:phone":"+1 719 391 2347",
    "sg:postcode":"80911",
    "sg:province":"CO",
    "wof:name":"A1 Moving & Storage Inc",
    "wof:placetype":"venue"
},
  "geometry": {"coordinates":[-104.68758200000001,38.7266],"type":"Point"}
}