{
  "type": "Feature",
  "properties": {
    "addr:full":"400 Upper Glenway St Palmer Lake CO 80132",
    "addr:housenumber":"400",
    "addr:postcode":"80132",
    "addr:street":"Upper Glenway St",
    "iso:country":"US",
    "sg:address":"400 Upper Glenway St",
    "sg:city":"Palmer Lake",
    "sg:classifiers":[
        {
            "category":"Building & Trades",
            "subcategory":"Construction",
            "type":"Services"
        }
    ],
    "sg:phone":"+1 719 488 1360",
    "sg:postcode":"80132",
    "sg:province":"CO",
    "sg:tags":[
        "general",
        "contractor"
    ],
    "wof:name":"CFI Construction",
    "wof:placetype":"venue"
},
  "geometry": {"coordinates":[-104.914631,39.127103],"type":"Point"}
}