{
  "type": "Feature",
  "properties": {
    "addr:full":"2348 Sijan Dr Usaf Academy CO 80840",
    "addr:housenumber":"2348",
    "addr:postcode":"80840",
    "addr:street":"Sijan Dr",
    "iso:country":"US",
    "sg:address":"2348 Sijan Dr",
    "sg:city":"Usaf Academy",
    "sg:classifiers":[
        {
            "category":"Professional",
            "type":"Services"
        }
    ],
    "sg:phone":"+1 719 472 0285",
    "sg:postcode":"80840",
    "sg:province":"CO",
    "sg:tags":[
        "establishment"
    ],
    "wof:name":"Mc Carty Corp",
    "wof:placetype":"venue"
},
  "geometry": {"coordinates":[-104.89298599999999,39.004795],"type":"Point"}
}