{
  "type": "Feature",
  "properties": {
    "addr:full":"5161 Ward Rd Wheat Ridge CO 80033",
    "addr:housenumber":"5161",
    "addr:postcode":"80033",
    "addr:street":"Ward Rd",
    "iso:country":"US",
    "sg:address":"5161 Ward Rd",
    "sg:city":"Wheat Ridge",
    "sg:classifiers":[
        {
            "category":"Home & Garden",
            "subcategory":"Building Materials",
            "type":"Retail Goods"
        }
    ],
    "sg:phone":"+1 303 425 6543",
    "sg:postcode":"80033",
    "sg:province":"CO",
    "wof:name":"American Siding Windows Sunroo",
    "wof:placetype":"venue"
},
  "geometry": {"coordinates":[-105.13805000000001,39.79006],"type":"Point"}
}