{
  "type": "Feature",
  "properties": {
    "addr:full":"522 Colorado Ave La Junta CO 81050",
    "addr:housenumber":"522",
    "addr:postcode":"81050",
    "addr:street":"Colorado Ave",
    "iso:country":"US",
    "sg:address":"522 Colorado Ave",
    "sg:city":"La Junta",
    "sg:classifiers":[
        {
            "category":"Education",
            "subcategory":"Library",
            "type":"Public Place"
        }
    ],
    "sg:phone":"+1 719 384 4612",
    "sg:postcode":"81050",
    "sg:province":"CO",
    "wof:name":"Woodruff Memorial Library",
    "wof:placetype":"venue"
},
  "geometry": {"coordinates":[-103.543143,37.983715],"type":"Point"}
}