{
  "type": "Feature",
  "properties": {
    "iso:country":"US",
    "sg:address":"13661 N Travois Trl",
    "sg:city":"Parker",
    "sg:classifiers":[
        {
            "category":"Building & Trades",
            "subcategory":"Construction",
            "type":"Services"
        }
    ],
    "sg:phone":"+1 720 851 7060",
    "sg:postcode":"80138",
    "sg:province":"CO",
    "sg:tags":[
        "house"
    ],
    "wof:name":"Majestic Development Co LLC",
    "wof:placetype":"venue"
},
  "geometry": {"coordinates":[-104.742811,39.561911],"type":"Point"}
}