{
  "type": "Feature",
  "properties": {
    "iso:country":"US",
    "sg:address":"6795 W 88th Ave",
    "sg:city":"Westminster",
    "sg:classifiers":[
        {
            "category":"Shopping",
            "subcategory":"Crafts & Fabrics",
            "type":"Retail Goods"
        }
    ],
    "sg:phone":"+1 303 431 9300",
    "sg:postcode":"80031",
    "sg:province":"CO",
    "sg:tags":[
        "shop"
    ],
    "wof:name":"Jo-Ann Fabrics & Crafts",
    "wof:placetype":"venue"
},
  "geometry": {"coordinates":[-105.07128400000001,39.856631],"type":"Point"}
}