{
  "type": "Feature",
  "properties": {
    "addr:full":"885 Arapahoe Ave Boulder CO 80302",
    "addr:housenumber":"885",
    "addr:postcode":"80302",
    "addr:street":"Arapahoe Ave",
    "iso:country":"US",
    "sg:address":"885 Arapahoe Ave",
    "sg:city":"Boulder",
    "sg:classifiers":[
        {
            "category":"Professional",
            "subcategory":"Management & Consulting",
            "type":"Services"
        }
    ],
    "sg:phone":"+1 720 564 1220",
    "sg:postcode":"80302",
    "sg:province":"CO",
    "sg:tags":[
        "health",
        "care"
    ],
    "wof:name":"Sandy River Health System",
    "wof:placetype":"venue"
},
  "geometry": {"coordinates":[-105.28352599999999,40.013207],"type":"Point"}
}