{
  "type": "Feature",
  "properties": {
    "addr:full":"4698 Skywriter Cir Colorado Springs CO 80922",
    "addr:housenumber":"4698",
    "addr:postcode":"80922",
    "addr:street":"Skywriter Cir",
    "iso:country":"US",
    "sg:address":"4698 Skywriter Cir",
    "sg:city":"Colorado Springs",
    "sg:classifiers":[
        {
            "category":"Food & Beverages",
            "subcategory":"Specialty",
            "type":"Retail Goods"
        }
    ],
    "sg:phone":"+1 719 531 5444",
    "sg:postcode":"80922",
    "sg:province":"CO",
    "sg:tags":[
        "tea",
        "coffee"
    ],
    "wof:name":"Mountain Mudd",
    "wof:placetype":"venue"
},
  "geometry": {"coordinates":[-104.71545999999999,38.90088],"type":"Point"}
}