{
  "type": "Feature",
  "properties": {
    "iso:country":"US",
    "sg:address":"181 W Meadow Dr",
    "sg:city":"Vail",
    "sg:classifiers":[
        {
            "category":"Health Services",
            "subcategory":"Doctor",
            "type":"Services"
        }
    ],
    "sg:phone":"+1 970 476 7226",
    "sg:postcode":"81657",
    "sg:province":"CO",
    "sg:tags":[
        "physician",
        "surgeon"
    ],
    "wof:name":"Vail Summit Surgery",
    "wof:placetype":"venue"
},
  "geometry": {"coordinates":[-106.382102,39.642934],"type":"Point"}
}