{
  "type": "Feature",
  "properties": {
    "iso:country":"US",
    "sg:address":"3302 Corte Almaden",
    "sg:city":"Fort Collins",
    "sg:classifiers":[
        {
            "category":"Travel",
            "subcategory":"Hotels & Motels",
            "type":"Entertainment"
        }
    ],
    "sg:phone":"+1 970 484 1362",
    "sg:postcode":"80524",
    "sg:province":"CO",
    "sg:tags":[
        "ranch",
        "guest"
    ],
    "wof:name":"Sky Corral Ranch",
    "wof:placetype":"venue"
},
  "geometry": {"coordinates":[-105.04171700000001,40.635074],"type":"Point"}
}