{
  "type": "Feature",
  "properties": {
    "addr:full":"140 Basalt Center Rd Basalt CO 81621",
    "addr:housenumber":"140",
    "addr:postcode":"81621",
    "addr:street":"Basalt Center Rd",
    "iso:country":"US",
    "sg:address":"140 Basalt Center Rd",
    "sg:city":"Basalt",
    "sg:classifiers":[
        {
            "category":"Food & Beverages",
            "subcategory":"Groceries & Convenience Stores",
            "type":"Retail Goods"
        }
    ],
    "sg:phone":"+1 970 927 3111",
    "sg:postcode":"81621",
    "sg:province":"CO",
    "sg:tags":[
        "grocer"
    ],
    "sg:website":"www.clarksmarket.com",
    "wof:name":"Clark's Super Market",
    "wof:placetype":"venue"
},
  "geometry": {"coordinates":[-107.03445499999999,39.368722],"type":"Point"}
}