{
  "type": "Feature",
  "properties": {
    "addr:full":"3775 Co Rd 307 Durango CO 81303",
    "addr:housenumber":"3775;307",
    "addr:postcode":"co 81303",
    "addr:street":"Co Rd",
    "iso:country":"US",
    "sg:address":"3775 Co Rd 307",
    "sg:city":"Durango",
    "sg:classifiers":[
        {
            "category":"Mining & Drilling",
            "type":"Manufacturing & Wholesale Goods"
        }
    ],
    "sg:phone":"+1 970 259 8238",
    "sg:postcode":"81303",
    "sg:province":"CO",
    "sg:tags":[
        "field"
    ],
    "wof:name":"Cross Country Energy Svcs LLC",
    "wof:placetype":"venue"
},
  "geometry": {"coordinates":[-107.78681400000001,37.143084],"type":"Point"}
}