{
  "type": "Feature",
  "properties": {
    "addr:full":"3060 E Bridge St Brighton CO 80601",
    "addr:housenumber":"3060",
    "addr:postcode":"80601",
    "addr:street":"E Bridge St",
    "iso:country":"US",
    "sg:address":"3060 E Bridge St",
    "sg:city":"Brighton",
    "sg:classifiers":[
        {
            "category":"Banks & Credit Unions",
            "subcategory":"Bank",
            "type":"Services"
        }
    ],
    "sg:phone":"+1 720 685 9974",
    "sg:postcode":"80601",
    "sg:province":"CO",
    "sg:tags":[
        "loan",
        "real estate"
    ],
    "wof:name":"Aroyle Prestige Mortgage",
    "wof:placetype":"venue"
},
  "geometry": {"coordinates":[-104.78508100000001,39.986818],"type":"Point"}
}