{
  "type": "Feature",
  "properties": {
    "addr:full":"7150 Leetsdale Dr Denver CO 80224",
    "addr:housenumber":"7150",
    "addr:postcode":"80224",
    "addr:street":"Leetsdale Dr",
    "iso:country":"US",
    "sg:address":"7150 Leetsdale Dr",
    "sg:city":"Denver",
    "sg:classifiers":[
        {
            "category":"Restaurant",
            "type":"Food & Drink"
        }
    ],
    "sg:menulink":"http://www.allmenus.com/co/denver/166842-burger-king/menu/",
    "sg:phone":"+1 303 394 3654",
    "sg:postcode":"80224",
    "sg:province":"CO",
    "sg:tags":[
        "burger",
        "american"
    ],
    "wof:name":"Burger King",
    "wof:placetype":"venue"
},
  "geometry": {"coordinates":[-104.905377,39.698213],"type":"Point"}
}