{
  "type": "Feature",
  "properties": {
    "iso:country":"US",
    "sg:address":"7887 E Belleview Ave",
    "sg:city":"Englewood",
    "sg:classifiers":[
        {
            "category":"Travel",
            "subcategory":"Travel Agent",
            "type":"Entertainment"
        }
    ],
    "sg:phone":"+1 303 694 8749",
    "sg:postcode":"80111",
    "sg:province":"CO",
    "sg:tags":[
        "tours",
        "promoter"
    ],
    "wof:name":"Trax World Tours",
    "wof:placetype":"venue"
},
  "geometry": {"coordinates":[-104.89589100000001,39.624068],"type":"Point"}
}