{
  "type": "Feature",
  "properties": {
    "iso:country":"US",
    "sg:address":"1012 S 9th St",
    "sg:city":"Canon City",
    "sg:classifiers":[
        {
            "category":"Banks & Credit Unions",
            "subcategory":"Bank",
            "type":"Services"
        }
    ],
    "sg:phone":"+1 719 275 0003",
    "sg:postcode":"81212",
    "sg:province":"CO",
    "sg:tags":[
        "loan",
        "real estate"
    ],
    "wof:name":"Clarion Mortgage Of Canon City",
    "wof:placetype":"venue"
},
  "geometry": {"coordinates":[-105.231855,38.433928],"type":"Point"}
}