{
  "type": "Feature",
  "properties": {
    "addr:full":"410 Riverside Dr Estes Park CO 80517",
    "addr:housenumber":"410",
    "addr:postcode":"80517",
    "addr:street":"Riverside Dr",
    "iso:country":"US",
    "sg:address":"410 Riverside Dr",
    "sg:city":"Estes Park",
    "sg:classifiers":[
        {
            "category":"Home & Garden",
            "subcategory":"Building Materials",
            "type":"Retail Goods"
        }
    ],
    "sg:phone":"+1 970 586 8592",
    "sg:postcode":"80517",
    "sg:province":"CO",
    "sg:tags":[
        "door"
    ],
    "wof:name":"Estes Park Garage Door",
    "wof:placetype":"venue"
},
  "geometry": {"coordinates":[-105.52735,40.369465],"type":"Point"}
}