{
  "type": "Feature",
  "properties": {
    "iso:country":"US",
    "sg:address":"3800 W 20th St",
    "sg:city":"Greeley",
    "sg:classifiers":[
        {
            "category":"Social Services",
            "subcategory":"Child Care",
            "type":"Services"
        }
    ],
    "sg:phone":"+1 970 339 3305",
    "sg:postcode":"80634",
    "sg:province":"CO",
    "sg:tags":[
        "day"
    ],
    "wof:name":"Wee Love Preschool",
    "wof:placetype":"venue"
},
  "geometry": {"coordinates":[-104.74139099999999,40.406611],"type":"Point"}
}