{
  "type": "Feature",
  "properties": {
    "addr:full":"2001 S Shields St Fort Collins CO 80526",
    "addr:housenumber":"2001",
    "addr:postcode":"80526",
    "addr:street":"S Shields St",
    "iso:country":"US",
    "sg:address":"2001 S Shields St",
    "sg:city":"Fort Collins",
    "sg:classifiers":[
        {
            "category":"Health Services",
            "subcategory":"Doctor",
            "type":"Services"
        }
    ],
    "sg:phone":"+1 970 224 4358",
    "sg:postcode":"80526",
    "sg:province":"CO",
    "sg:tags":[
        "dentist"
    ],
    "wof:name":"Scott K Perkins DDS",
    "wof:placetype":"venue"
},
  "geometry": {"coordinates":[-105.096062,40.561116],"type":"Point"}
}