{
  "type": "Feature",
  "properties": {
    "iso:country":"US",
    "sg:address":"42180 London Dr",
    "sg:city":"Parker",
    "sg:classifiers":[
        {
            "category":"Freight",
            "type":"Transportation"
        }
    ],
    "sg:phone":"+1 720 363 0528",
    "sg:postcode":"80138",
    "sg:province":"CO",
    "sg:tags":[
        "operator",
        "local",
        "trucking"
    ],
    "wof:name":"Mark Nolan Trucking",
    "wof:placetype":"venue"
},
  "geometry": {"coordinates":[-104.642032,39.479699],"type":"Point"}
}