{
  "type": "Feature",
  "properties": {
    "iso:country":"US",
    "sg:address":"5299 Dtc Blvd",
    "sg:city":"Greenwood Vlg",
    "sg:classifiers":[
        {
            "category":"Professional",
            "subcategory":"Accounting & Tax Preparation",
            "type":"Services"
        }
    ],
    "sg:phone":"+1 303 770 8383",
    "sg:postcode":"80111",
    "sg:province":"CO",
    "sg:tags":[
        "accountant"
    ],
    "sg:website":"www.ghbcpa.com",
    "wof:name":"Gordon Hughes & Banks",
    "wof:placetype":"venue"
},
  "geometry": {"coordinates":[-104.88981699999999,39.620999],"type":"Point"}
}