{
  "type": "Feature",
  "properties": {
    "iso:country":"US",
    "sg:address":"3430 Ash Ave",
    "sg:city":"Boulder",
    "sg:classifiers":[
        {
            "category":"Professional",
            "subcategory":"Engineering",
            "type":"Services"
        }
    ],
    "sg:phone":"+1 303 499 2644",
    "sg:postcode":"80305",
    "sg:province":"CO",
    "sg:tags":[
        "engineer"
    ],
    "wof:name":"Sable Instruments Inc",
    "wof:placetype":"venue"
},
  "geometry": {"coordinates":[-105.2516,39.994606],"type":"Point"}
}