{
  "type": "Feature",
  "properties": {
    "addr:full":"6877 E Chestnut Hill St Littleton CO 80130",
    "addr:housenumber":"6877",
    "addr:postcode":"80130",
    "addr:street":"E Chestnut Hill St",
    "iso:country":"US",
    "sg:address":"6877 E Chestnut Hill St",
    "sg:city":"Littleton",
    "sg:classifiers":[
        {
            "category":"Real Estate",
            "subcategory":"Real Estate Agent",
            "type":"Services"
        }
    ],
    "sg:phone":"+1 303 683 9010",
    "sg:postcode":"80130",
    "sg:province":"CO",
    "wof:name":"Abbey Realty",
    "wof:placetype":"venue"
},
  "geometry": {"coordinates":[-104.90942200000001,39.554693],"type":"Point"}
}