{
  "type": "Feature",
  "properties": {
    "addr:full":"7567 Union Ct Arvada CO 80005",
    "addr:housenumber":"7567",
    "addr:postcode":"80005",
    "addr:street":"Union Ct",
    "iso:country":"US",
    "sg:address":"7567 Union Ct",
    "sg:city":"Arvada",
    "sg:classifiers":[
        {
            "category":"Real Estate",
            "subcategory":"Real Estate Operator",
            "type":"Services"
        }
    ],
    "sg:phone":"+1 303 422 7631",
    "sg:postcode":"80005",
    "sg:province":"CO",
    "sg:tags":[
        "building",
        "nonresidential"
    ],
    "wof:name":"Jels Properties LLC",
    "wof:placetype":"venue"
},
  "geometry": {"coordinates":[-105.135317,39.835487],"type":"Point"}
}