{
  "type": "Feature",
  "properties": {
    "iso:country":"US",
    "sg:address":"5452 S Bahama Ct",
    "sg:city":"Aurora",
    "sg:classifiers":[
        {
            "category":"Banks & Credit Unions",
            "subcategory":"Bank",
            "type":"Services"
        }
    ],
    "sg:phone":"+1 303 808 7458",
    "sg:postcode":"80015",
    "sg:province":"CO",
    "sg:tags":[
        "loan",
        "broker"
    ],
    "wof:name":"VIP Lending Incorporated",
    "wof:placetype":"venue"
},
  "geometry": {"coordinates":[-104.76890899999999,39.618352],"type":"Point"}
}