{
  "type": "Feature",
  "properties": {
    "addr:full":"1520 N Hancock Ave Colorado Springs CO 80903",
    "addr:housenumber":"1520",
    "addr:postcode":"80903",
    "addr:street":"N Hancock Ave",
    "iso:country":"US",
    "sg:address":"1520 N Hancock Ave",
    "sg:city":"Colorado Springs",
    "sg:classifiers":[
        {
            "category":"Retail",
            "subcategory":"Portrait Studio",
            "type":"Services"
        }
    ],
    "sg:phone":"+1 719 228 4175",
    "sg:postcode":"80903",
    "sg:province":"CO",
    "sg:tags":[
        "photographer"
    ],
    "wof:name":"Reed's Photography",
    "wof:placetype":"venue"
},
  "geometry": {"coordinates":[-104.80271,38.854721],"type":"Point"}
}