{
  "type": "Feature",
  "properties": {
    "iso:country":"US",
    "sg:address":"5948 Colby St",
    "sg:city":"Fort Collins",
    "sg:classifiers":[
        {
            "category":"Travel",
            "subcategory":"Hotels & Motels",
            "type":"Entertainment"
        }
    ],
    "sg:phone":"+1 970 204 6988",
    "sg:postcode":"80525",
    "sg:province":"CO",
    "wof:name":"Relocation Property Consultant",
    "wof:placetype":"venue"
},
  "geometry": {"coordinates":[-105.073716,40.50293],"type":"Point"}
}