{
  "type": "Feature",
  "properties": {
    "addr:full":"202 E Aspen Ave Fruita CO 81521",
    "addr:housenumber":"202",
    "addr:postcode":"81521",
    "addr:street":"E Aspen Ave",
    "iso:country":"US",
    "sg:address":"202 E Aspen Ave",
    "sg:city":"Fruita",
    "sg:classifiers":[
        {
            "category":"Shopping",
            "subcategory":"Bicycles & Sporting Goods",
            "type":"Retail Goods"
        }
    ],
    "sg:phone":"+1 970 858 7220",
    "sg:postcode":"81521",
    "sg:province":"CO",
    "wof:name":"Over The Edge Sports",
    "wof:placetype":"venue"
},
  "geometry": {"coordinates":[-108.732466,39.158806],"type":"Point"}
}