{
  "type": "Feature",
  "properties": {
    "addr:full":"3762 Eureka Way Erie CO 80516",
    "addr:housenumber":"3762",
    "addr:postcode":"80516",
    "addr:street":"Eureka Way",
    "iso:country":"US",
    "sg:address":"3762 Eureka Way",
    "sg:city":"Erie",
    "sg:classifiers":[
        {
            "category":"Real Estate",
            "subcategory":"Developer",
            "type":"Services"
        }
    ],
    "sg:phone":"+1 303 833 4454",
    "sg:postcode":"80516",
    "sg:province":"CO",
    "wof:name":"Glacier Business Park",
    "wof:placetype":"venue"
},
  "geometry": {"coordinates":[-104.987341,40.081399],"type":"Point"}
}