{
  "type": "Feature",
  "properties": {
    "iso:country":"US",
    "sg:address":"1722 N Empire Ave",
    "sg:city":"Loveland",
    "sg:classifiers":[
        {
            "category":"Professional",
            "subcategory":"Computer Services",
            "type":"Services"
        }
    ],
    "sg:phone":"+1 970 622 0378",
    "sg:postcode":"80538",
    "sg:province":"CO",
    "sg:tags":[
        "internet"
    ],
    "wof:name":"EWM Enterprises",
    "wof:placetype":"venue"
},
  "geometry": {"coordinates":[-105.106938,40.410515],"type":"Point"}
}