{
  "type": "Feature",
  "properties": {
    "iso:country":"US",
    "sg:address":"1630 W Dartmouth Ave",
    "sg:city":"Englewood",
    "sg:classifiers":[
        {
            "category":"Restaurant",
            "type":"Food & Drink"
        }
    ],
    "sg:phone":"+1 303 751 1111",
    "sg:postcode":"80110",
    "sg:province":"CO",
    "wof:name":"Pizza Hut",
    "wof:placetype":"venue"
},
  "geometry": {"coordinates":[-105.008518,39.660414],"type":"Point"}
}