{
  "type": "Feature",
  "properties": {
    "iso:country":"US",
    "sg:address":"1050 13th St",
    "sg:city":"Denver",
    "sg:classifiers":[
        {
            "category":"Banks & Credit Unions",
            "subcategory":"Financial Services",
            "type":"Services"
        }
    ],
    "sg:phone":"+1 303 893 4000",
    "sg:postcode":"80204",
    "sg:province":"CO",
    "wof:name":"Helen G Bonfils Foundation",
    "wof:placetype":"venue"
},
  "geometry": {"coordinates":[-104.999005,39.744714],"type":"Point"}
}