{
  "type": "Feature",
  "properties": {
    "addr:full":"1025 Acoma Street Denver CO 80204",
    "addr:housenumber":"1025",
    "addr:postcode":"80204",
    "addr:street":"Acoma Street",
    "iso:country":"US",
    "sg:address":"1025 Acoma Street",
    "sg:city":"Denver",
    "sg:classifiers":[
        {
            "category":"Animal Shelter",
            "type":"Public Place"
        }
    ],
    "sg:phone":"+1 303 629 5900",
    "sg:postcode":"80204",
    "sg:province":"CO",
    "sg:website":"www.thegabrielfoundation.org/Home/",
    "wof:name":"Gabriel Foundation",
    "wof:placetype":"venue"
},
  "geometry": {"coordinates":[-104.988997,39.732779],"type":"Point"}
}