{
  "type": "Feature",
  "properties": {
    "iso:country":"US",
    "sg:address":"615 S Pratt Pkwy",
    "sg:city":"Longmont",
    "sg:classifiers":[
        {
            "category":"Personal",
            "subcategory":"Beauty Salon",
            "type":"Services"
        }
    ],
    "sg:phone":"+1 303 776 8588",
    "sg:postcode":"80501",
    "sg:province":"CO",
    "wof:name":"Hair-Works Barbers",
    "wof:placetype":"venue"
},
  "geometry": {"coordinates":[-105.107383,40.152277],"type":"Point"}
}