{
  "type": "Feature",
  "properties": {
    "addr:full":"1621 S Pennsylvania St Denver CO 80210",
    "addr:housenumber":"1621",
    "addr:postcode":"80210",
    "addr:street":"S Pennsylvania St",
    "iso:country":"US",
    "sg:address":"1621 S Pennsylvania St",
    "sg:city":"Denver",
    "sg:classifiers":[
        {
            "category":"Home & Garden",
            "subcategory":"Furniture",
            "type":"Retail Goods"
        }
    ],
    "sg:phone":"+1 720 374 8775",
    "sg:postcode":"80210",
    "sg:province":"CO",
    "wof:name":"Miller Fine Cabinetry",
    "wof:placetype":"venue"
},
  "geometry": {"coordinates":[-104.981685,39.686131],"type":"Point"}
}