{
  "type": "Feature",
  "properties": {
    "iso:country":"US",
    "sg:address":"5381 Parmalee Gulch Rd",
    "sg:city":"Indian Hills",
    "sg:classifiers":[
        {
            "category":"Recreation",
            "type":"Entertainment"
        }
    ],
    "sg:phone":"+1 303 697 7659",
    "sg:postcode":"80454",
    "sg:province":"CO",
    "sg:tags":[
        "amusement"
    ],
    "wof:name":"Indian Hills Community Ctr",
    "wof:placetype":"venue"
},
  "geometry": {"coordinates":[-105.240773,39.620274],"type":"Point"}
}