{
  "type": "Feature",
  "properties": {
    "iso:country":"US",
    "sg:address":"41st & Sheridan",
    "sg:city":"Denver",
    "sg:classifiers":[
        {
            "category":"Shopping",
            "subcategory":"Tobacco",
            "type":"Retail Goods"
        }
    ],
    "sg:phone":"+1 303 458 7326",
    "sg:postcode":"80202",
    "sg:province":"CO",
    "sg:tags":[
        "shop"
    ],
    "wof:name":"Freakys Gift Shoppe",
    "wof:placetype":"venue"
},
  "geometry": {"coordinates":[-104.995747,39.749758],"type":"Point"}
}