{
  "type": "Feature",
  "properties": {
    "iso:country":"US",
    "sg:address":"1995 Dover St",
    "sg:city":"Broomfield",
    "sg:classifiers":[
        {
            "category":"Wholesale",
            "subcategory":"Machinery & Supplies",
            "type":"Manufacturing & Wholesale Goods"
        }
    ],
    "sg:phone":"+1 303 469 6226",
    "sg:postcode":"80020",
    "sg:province":"CO",
    "sg:tags":[
        "janitor"
    ],
    "wof:name":"Wheeler Janitorial & Mntnc",
    "wof:placetype":"venue"
},
  "geometry": {"coordinates":[-105.055032,39.941172],"type":"Point"}
}