{
  "type": "Feature",
  "properties": {
    "addr:full":"890 South Josephine Street Denver CO 80209",
    "addr:housenumber":"890",
    "addr:postcode":"80209",
    "addr:street":"South Josephine Street",
    "iso:country":"US",
    "sg:address":"890 South Josephine Street",
    "sg:city":"Denver",
    "sg:classifiers":[
        {
            "category":"Professional",
            "type":"Services"
        }
    ],
    "sg:phone":"+1 303 744 9024",
    "sg:postcode":"80209",
    "sg:province":"CO",
    "wof:name":"MarketingTactics",
    "wof:placetype":"venue"
},
  "geometry": {"coordinates":[-104.95782,39.700512],"type":"Point"}
}