{
  "type": "Feature",
  "properties": {
    "addr:full":"162 E Rolling Hills Dr Pueblo West CO 81007",
    "addr:housenumber":"162",
    "addr:postcode":"81007",
    "addr:street":"E Rolling Hills Dr",
    "iso:country":"US",
    "sg:address":"162 E Rolling Hills Dr",
    "sg:city":"Pueblo West",
    "sg:classifiers":[
        {
            "category":"Building & Trades",
            "subcategory":"Construction",
            "type":"Services"
        }
    ],
    "sg:phone":"+1 719 547 9442",
    "sg:postcode":"81007",
    "sg:province":"CO",
    "sg:tags":[
        "residential",
        "general",
        "contractor"
    ],
    "wof:name":"Y Construction Inc",
    "wof:placetype":"venue"
},
  "geometry": {"coordinates":[-104.73063500000001,38.29719],"type":"Point"}
}