{
  "type": "Feature",
  "properties": {
    "iso:country":"US",
    "sg:address":"9025 Co Rd 11",
    "sg:city":"Longmont",
    "sg:classifiers":[
        {
            "category":"Professional",
            "subcategory":"Business Services",
            "type":"Services"
        }
    ],
    "sg:phone":"+1 303 776 1980",
    "sg:postcode":"80504",
    "sg:province":"CO",
    "sg:tags":[
        "arbitration"
    ],
    "wof:name":"E J Doering Mediation & Confli",
    "wof:placetype":"venue"
},
  "geometry": {"coordinates":[-104.96107000000001,40.13284],"type":"Point"}
}