{
  "type": "Feature",
  "properties": {
    "iso:country":"US",
    "sg:address":"969 Denver St",
    "sg:city":"Calhan",
    "sg:classifiers":[
        {
            "category":"Building & Trades",
            "subcategory":"Construction",
            "type":"Services"
        }
    ],
    "sg:phone":"+1 719 347 0787",
    "sg:postcode":"80808",
    "sg:province":"CO",
    "sg:tags":[
        "house"
    ],
    "wof:name":"R & S Homes",
    "wof:placetype":"venue"
},
  "geometry": {"coordinates":[-104.299378,39.031479],"type":"Point"}
}