{
  "type": "Feature",
  "properties": {
    "iso:country":"US",
    "sg:address":"505 3rd St",
    "sg:city":"Alamosa",
    "sg:classifiers":[
        {
            "category":"Government",
            "subcategory":"Post Office",
            "type":"Public Place"
        }
    ],
    "sg:phone":"+1 719 589 4908",
    "sg:postcode":"81101",
    "sg:province":"CO",
    "wof:name":"US Post Office",
    "wof:placetype":"venue"
},
  "geometry": {"coordinates":[-105.865431,37.470451],"type":"Point"}
}