{
  "type": "Feature",
  "properties": {
    "addr:full":"13006 US Hwy 34 Yuma CO 80759",
    "addr:housenumber":"13006",
    "addr:postcode":"80759",
    "addr:street":"Us Hwy 34",
    "iso:country":"US",
    "sg:address":"13006 US Hwy 34",
    "sg:city":"Yuma",
    "sg:phone":"+1 970 848 2435",
    "sg:postcode":"80759",
    "sg:province":"CO",
    "sg:tags":[
        "wheat",
        "beef",
        "farm",
        "corn",
        "cattle",
        "feedlot"
    ],
    "wof:name":"Dexter Robertson",
    "wof:placetype":"venue"
},
  "geometry": {"coordinates":[-102.56746800000001,40.110248],"type":"Point"}
}