{
  "type": "Feature",
  "properties": {
    "iso:country":"US",
    "sg:address":"222 S 6th St",
    "sg:city":"Grand Junction",
    "sg:classifiers":[
        {
            "category":"Government",
            "subcategory":"Office",
            "type":"Public Place"
        }
    ],
    "sg:phone":"+1 970 248 7140",
    "sg:postcode":"81501",
    "sg:province":"CO",
    "sg:tags":[
        "revenue"
    ],
    "wof:name":"Taxpayer Service Center",
    "wof:placetype":"venue"
},
  "geometry": {"coordinates":[-108.56267200000001,39.065587],"type":"Point"}
}