{
  "type": "Feature",
  "properties": {
    "addr:full":"3233 Dillon Dr Pueblo CO 81008",
    "addr:housenumber":"3233",
    "addr:postcode":"81008",
    "addr:street":"Dillon Dr",
    "iso:country":"US",
    "sg:address":"3233 Dillon Dr",
    "sg:city":"Pueblo",
    "sg:classifiers":[
        {
            "category":"Personal",
            "subcategory":"Beauty Salon",
            "type":"Services"
        }
    ],
    "sg:phone":"+1 719 545 0502",
    "sg:postcode":"81008",
    "sg:province":"CO",
    "wof:name":"Trade Secret",
    "wof:placetype":"venue"
},
  "geometry": {"coordinates":[-104.606567,38.30311],"type":"Point"}
}