{
  "type": "Feature",
  "properties": {
    "iso:country":"US",
    "sg:address":"3119 E Eisenhower Blvd",
    "sg:city":"Loveland",
    "sg:classifiers":[
        {
            "category":"Utilities",
            "subcategory":"Water",
            "type":"Services"
        }
    ],
    "sg:phone":"+1 970 667 7031",
    "sg:postcode":"80537",
    "sg:province":"CO",
    "sg:tags":[
        "company",
        "sewage",
        "supply"
    ],
    "wof:name":"Boyd Lake Filter Plant",
    "wof:placetype":"venue"
},
  "geometry": {"coordinates":[-105.020957,40.407449],"type":"Point"}
}