{
  "type": "Feature",
  "properties": {
    "iso:country":"US",
    "sg:address":"1877 Broadway St",
    "sg:city":"Boulder",
    "sg:classifiers":[
        {
            "category":"Real Estate",
            "subcategory":"Architect",
            "type":"Services"
        }
    ],
    "sg:phone":"+1 303 449 4831",
    "sg:postcode":"80302",
    "sg:province":"CO",
    "sg:tags":[
        "architectural"
    ],
    "sg:website":"www.zdesigngroup.net",
    "wof:name":"Zmistowski Design Group LLC",
    "wof:placetype":"venue"
},
  "geometry": {"coordinates":[-105.279471,40.016117],"type":"Point"}
}