{
  "type": "Feature",
  "properties": {
    "iso:country":"US",
    "sg:address":"11154 Thomas Dr",
    "sg:city":"Conifer",
    "sg:classifiers":[
        {
            "category":"Professional",
            "subcategory":"Employment Agencies",
            "type":"Services"
        }
    ],
    "sg:phone":"+1 303 838 3334",
    "sg:postcode":"80433",
    "sg:province":"CO",
    "sg:tags":[
        "consultant",
        "search",
        "executive"
    ],
    "wof:name":"Denver Executive Search",
    "wof:placetype":"venue"
},
  "geometry": {"coordinates":[-105.34871800000001,39.51704],"type":"Point"}
}