{
  "type": "Feature",
  "properties": {
    "addr:full":"1286 Co Rd 24 Kremmling CO 80459",
    "addr:housenumber":"1286;24",
    "addr:postcode":"80459",
    "addr:street":"Co Rd",
    "iso:country":"US",
    "sg:address":"1286 Co Rd 24",
    "sg:city":"Kremmling",
    "sg:phone":"+1 970 724 9530",
    "sg:postcode":"80459",
    "sg:province":"CO",
    "sg:tags":[
        "farm",
        "wheat",
        "beef",
        "feedlot",
        "cattle"
    ],
    "wof:name":"Spring Creek Ranch",
    "wof:placetype":"venue"
},
  "geometry": {"coordinates":[-106.382546,39.901553],"type":"Point"}
}