{
  "type": "Feature",
  "properties": {
    "iso:country":"US",
    "sg:address":"1535 Platte St",
    "sg:city":"Denver",
    "sg:classifiers":[
        {
            "category":"Shopping",
            "subcategory":"Shoes",
            "type":"Retail Goods"
        }
    ],
    "sg:phone":"+1 303 446 0400",
    "sg:postcode":"80202",
    "sg:province":"CO",
    "sg:tags":[
        "store"
    ],
    "sg:website":"www.the400.net",
    "wof:name":"The 400",
    "wof:placetype":"venue"
},
  "geometry": {"coordinates":[-105.00856,39.757028],"type":"Point"}
}