{
  "type": "Feature",
  "properties": {
    "addr:full":"183 Gore Creek Dr Vail CO 81657",
    "addr:housenumber":"183",
    "addr:postcode":"81657",
    "addr:street":"Gore Creek Dr",
    "iso:country":"US",
    "sg:address":"183 Gore Creek Dr",
    "sg:city":"Vail",
    "sg:classifiers":[
        {
            "category":"Restaurant",
            "type":"Food & Drink"
        }
    ],
    "sg:menulink":"http://www.allmenus.com/co/minturn-red-cliff/269101-left-bank-restaurant/menu/",
    "sg:phone":"+1 970 476 3696",
    "sg:postcode":"81657",
    "sg:province":"CO",
    "sg:tags":[
        "french"
    ],
    "wof:name":"Left Bank Restaurant",
    "wof:placetype":"venue"
},
  "geometry": {"coordinates":[-106.375382,39.640665],"type":"Point"}
}