{
  "type": "Feature",
  "properties": {
    "addr:full":"159 State Hwy 72 Nederland CO 80466",
    "addr:housenumber":"159",
    "addr:postcode":"80466",
    "addr:street":"State Hwy 72",
    "iso:country":"US",
    "sg:address":"159 State Hwy 72",
    "sg:city":"Nederland",
    "sg:classifiers":[
        {
            "category":"Real Estate",
            "subcategory":"Real Estate Agent",
            "type":"Services"
        }
    ],
    "sg:phone":"+1 303 258 3028",
    "sg:postcode":"80466",
    "sg:province":"CO",
    "wof:name":"Century 21 Peak Performance",
    "wof:placetype":"venue"
},
  "geometry": {"coordinates":[-105.51197999999999,39.962799],"type":"Point"}
}