{
  "type": "Feature",
  "properties": {
    "iso:country":"US",
    "sg:address":"1626 E Pikes Peak Ave",
    "sg:city":"Colorado Springs",
    "sg:classifiers":[
        {
            "category":"Real Estate",
            "subcategory":"Architect",
            "type":"Services"
        }
    ],
    "sg:phone":"+1 719 632 3384",
    "sg:postcode":"80909",
    "sg:province":"CO",
    "wof:name":"John P Nelson Assoc",
    "wof:placetype":"venue"
},
  "geometry": {"coordinates":[-104.79729,38.83311],"type":"Point"}
}