{
  "type": "Feature",
  "properties": {
    "addr:full":"826 N 1st St Grand Junction CO 81501",
    "addr:housenumber":"826",
    "addr:postcode":"81501",
    "addr:street":"N 1St St",
    "iso:country":"US",
    "sg:address":"826 N 1st St",
    "sg:city":"Grand Junction",
    "sg:classifiers":[
        {
            "category":"Manufacturing",
            "subcategory":"Printing",
            "type":"Manufacturing & Wholesale Goods"
        }
    ],
    "sg:phone":"+1 970 241 5581",
    "sg:postcode":"81501",
    "sg:province":"CO",
    "sg:tags":[
        "commercial"
    ],
    "wof:name":"Hole In The Wall Shirt Shoppe",
    "wof:placetype":"venue"
},
  "geometry": {"coordinates":[-108.570795,39.075184],"type":"Point"}
}