{
  "type": "Feature",
  "properties": {
    "iso:country":"US",
    "sg:address":"11930 E Bates Cir",
    "sg:city":"Aurora",
    "sg:classifiers":[
        {
            "category":"Recreation",
            "subcategory":"Boat Charter",
            "type":"Entertainment"
        }
    ],
    "sg:phone":"+1 303 337 7609",
    "sg:postcode":"80014",
    "sg:province":"CO",
    "sg:tags":[
        "boat-rental"
    ],
    "wof:name":"Ski Run View",
    "wof:placetype":"venue"
},
  "geometry": {"coordinates":[-104.847961,39.663523],"type":"Point"}
}