{
  "type": "Feature",
  "properties": {
    "iso:country":"US",
    "sg:address":"1104 S Lincoln Ave",
    "sg:city":"Steamboat Spgs",
    "sg:classifiers":[
        {
            "category":"Restaurant",
            "type":"Food & Drink"
        }
    ],
    "sg:phone":"+1 970 879 1441",
    "sg:postcode":"80487",
    "sg:province":"CO",
    "wof:name":"Old West Steak House",
    "wof:placetype":"venue"
},
  "geometry": {"coordinates":[-106.82626999999999,40.469496],"type":"Point"}
}