{
  "type": "Feature",
  "properties": {
    "addr:full":"9231 Harrison St Thornton CO 80229",
    "addr:housenumber":"9231",
    "addr:postcode":"80229",
    "addr:street":"Harrison St",
    "iso:country":"US",
    "sg:address":"9231 Harrison St",
    "sg:city":"Thornton",
    "sg:classifiers":[
        {
            "category":"Freight",
            "type":"Transportation"
        }
    ],
    "sg:phone":"+1 303 227 3141",
    "sg:postcode":"80229",
    "sg:province":"CO",
    "sg:tags":[
        "mover"
    ],
    "wof:name":"C R Movers",
    "wof:placetype":"venue"
},
  "geometry": {"coordinates":[-104.941141,39.86402],"type":"Point"}
}