{
  "type": "Feature",
  "properties": {
    "iso:country":"US",
    "sg:address":"911 Rudd Ave",
    "sg:city":"Canon City",
    "sg:classifiers":[
        {
            "category":"Professional",
            "subcategory":"Management & Consulting",
            "type":"Services"
        }
    ],
    "sg:phone":"+1 719 275 8561",
    "sg:postcode":"81212",
    "sg:province":"CO",
    "sg:tags":[
        "consultant",
        "publishing"
    ],
    "wof:name":"Mean Mommy Publishing",
    "wof:placetype":"venue"
},
  "geometry": {"coordinates":[-105.236833,38.44682],"type":"Point"}
}