{
  "type": "Feature",
  "properties": {
    "iso:country":"US",
    "sg:address":"8257 Ames Way",
    "sg:city":"Arvada",
    "sg:classifiers":[
        {
            "category":"Building & Trades",
            "subcategory":"Landscaping Services",
            "type":"Services"
        }
    ],
    "sg:phone":"+1 303 423 6559",
    "sg:postcode":"80003",
    "sg:province":"CO",
    "sg:tags":[
        "lawn",
        "maintenance",
        "grounds"
    ],
    "wof:name":"Turf Management",
    "wof:placetype":"venue"
},
  "geometry": {"coordinates":[-105.055623,39.846274],"type":"Point"}
}