{
  "type": "Feature",
  "properties": {
    "addr:full":"6542 E Millstone Pl Littleton CO 80130",
    "addr:housenumber":"6542",
    "addr:postcode":"80130",
    "addr:street":"E Millstone Pl",
    "iso:country":"US",
    "sg:address":"6542 E Millstone Pl",
    "sg:city":"Littleton",
    "sg:classifiers":[
        {
            "category":"Professional",
            "subcategory":"Accounting & Tax Preparation",
            "type":"Services"
        }
    ],
    "sg:phone":"+1 303 346 9344",
    "sg:postcode":"80130",
    "sg:province":"CO",
    "sg:tags":[
        "solution",
        "business"
    ],
    "wof:name":"Automated Time Solutions",
    "wof:placetype":"venue"
},
  "geometry": {"coordinates":[-104.911694,39.538641],"type":"Point"}
}