{
  "type": "Feature",
  "properties": {
    "addr:full":"225 E Polk St Colorado Springs CO 80907",
    "addr:housenumber":"225",
    "addr:postcode":"80907",
    "addr:street":"E Polk St",
    "iso:country":"US",
    "sg:address":"225 E Polk St",
    "sg:city":"Colorado Springs",
    "sg:classifiers":[
        {
            "category":"Autos & Motor Vehicles",
            "subcategory":"Auto Supplies",
            "type":"Retail Goods"
        }
    ],
    "sg:phone":"+1 719 634 0666",
    "sg:postcode":"80907",
    "sg:province":"CO",
    "wof:name":"FN Jeep Parts",
    "wof:placetype":"venue"
},
  "geometry": {"coordinates":[-104.81942600000001,38.871813],"type":"Point"}
}