{
  "type": "Feature",
  "properties": {
    "addr:full":"5455 US Hwy 36 Estes Park CO 80517",
    "addr:housenumber":"5455",
    "addr:postcode":"80517",
    "addr:street":"Us Hwy 36",
    "iso:country":"US",
    "sg:address":"5455 US Hwy 36",
    "sg:city":"Estes Park",
    "sg:classifiers":[
        {
            "category":"Professional",
            "subcategory":"Accounting & Tax Preparation",
            "type":"Services"
        }
    ],
    "sg:phone":"+1 970 586 5008",
    "sg:postcode":"80517",
    "sg:province":"CO",
    "sg:tags":[
        "accountant"
    ],
    "wof:name":"Carl Henderson CPA",
    "wof:placetype":"venue"
},
  "geometry": {"coordinates":[-105.431096,40.34194],"type":"Point"}
}