{
  "type": "Feature",
  "properties": {
    "addr:full":"207 Judson St Longmont CO 80501",
    "addr:housenumber":"207",
    "addr:postcode":"80501",
    "addr:street":"Judson St",
    "iso:country":"US",
    "sg:address":"207 Judson St",
    "sg:city":"Longmont",
    "sg:classifiers":[
        {
            "category":"Real Estate",
            "subcategory":"Architect",
            "type":"Services"
        }
    ],
    "sg:phone":"+1 303 678 7275",
    "sg:postcode":"80501",
    "sg:province":"CO",
    "wof:name":"L Russell Donato Architecture",
    "wof:placetype":"venue"
},
  "geometry": {"coordinates":[-105.11845599999999,40.166689],"type":"Point"}
}