{
  "type": "Feature",
  "properties": {
    "addr:full":"1000 S Frontage Rd W Vail CO 81657",
    "addr:housenumber":"1000",
    "addr:postcode":"81657",
    "addr:street":"S Frontage Rd W",
    "iso:country":"US",
    "sg:address":"1000 S Frontage Rd W",
    "sg:city":"Vail",
    "sg:classifiers":[
        {
            "category":"Professional",
            "subcategory":"Accounting & Tax Preparation",
            "type":"Services"
        }
    ],
    "sg:phone":"+1 970 476 4171",
    "sg:postcode":"81657",
    "sg:province":"CO",
    "sg:tags":[
        "accountant"
    ],
    "wof:name":"Gordon Hughes & Banks",
    "wof:placetype":"venue"
},
  "geometry": {"coordinates":[-106.397458,39.641057],"type":"Point"}
}