{
  "type": "Feature",
  "properties": {
    "addr:full":"3848 Vallejo St Denver CO 80211",
    "addr:housenumber":"3848",
    "addr:postcode":"80211",
    "addr:street":"Vallejo St",
    "iso:country":"US",
    "sg:address":"3848 Vallejo St",
    "sg:city":"Denver",
    "sg:classifiers":[
        {
            "category":"Freight",
            "type":"Transportation"
        }
    ],
    "sg:phone":"+1 303 455 7964",
    "sg:postcode":"80211",
    "sg:province":"CO",
    "sg:tags":[
        "courier"
    ],
    "wof:name":"E Express Courier",
    "wof:placetype":"venue"
},
  "geometry": {"coordinates":[-105.013454,39.76991],"type":"Point"}
}