{
  "type": "Feature",
  "properties": {
    "addr:full":"10927 Clermont Ct Denver CO 80233",
    "addr:housenumber":"10927",
    "addr:postcode":"80233",
    "addr:street":"Clermont Ct",
    "iso:country":"US",
    "sg:address":"10927 Clermont Ct",
    "sg:city":"Denver",
    "sg:classifiers":[
        {
            "category":"Shopping",
            "subcategory":"Gifts & Souvenirs",
            "type":"Retail Goods"
        }
    ],
    "sg:phone":"+1 303 457 0071",
    "sg:postcode":"80233",
    "sg:province":"CO",
    "wof:name":"Carolinas Basket and Gifts Co",
    "wof:placetype":"venue"
},
  "geometry": {"coordinates":[-104.933802,39.893192],"type":"Point"}
}