{
  "type": "Feature",
  "properties": {
    "iso:country":"US",
    "sg:address":"611 Greenwood Ave",
    "sg:city":"Canon City",
    "sg:classifiers":[
        {
            "category":"Insurance",
            "subcategory":"Insurance Agent",
            "type":"Services"
        }
    ],
    "sg:phone":"+1 719 275 7421",
    "sg:postcode":"81212",
    "sg:province":"CO",
    "sg:tags":[
        "agency"
    ],
    "wof:name":"Fredrcksn-Brown Lf Hlth Dprtme",
    "wof:placetype":"venue"
},
  "geometry": {"coordinates":[-105.239484,38.443378],"type":"Point"}
}