{
  "type": "Feature",
  "properties": {
    "addr:full":"400 Mack Ln Craig CO 81625",
    "addr:housenumber":"400",
    "addr:postcode":"81625",
    "addr:street":"Mack Ln",
    "iso:country":"US",
    "sg:address":"400 Mack Ln",
    "sg:city":"Craig",
    "sg:classifiers":[
        {
            "category":"Recreation",
            "type":"Entertainment"
        }
    ],
    "sg:phone":"+1 970 824 2282",
    "sg:postcode":"81625",
    "sg:province":"CO",
    "sg:tags":[
        "information",
        "activity"
    ],
    "wof:name":"Gymstar Fun N Fit Gymnastics",
    "wof:placetype":"venue"
},
  "geometry": {"coordinates":[-107.56269,40.512299],"type":"Point"}
}