{
  "type": "Feature",
  "properties": {
    "addr:full":"755 S Broadway Denver CO 80209",
    "addr:housenumber":"755",
    "addr:postcode":"80209",
    "addr:street":"S Broadway",
    "iso:country":"US",
    "sg:address":"755 S Broadway",
    "sg:city":"Denver",
    "sg:classifiers":[
        {
            "category":"Wholesale",
            "subcategory":"Auto Parts",
            "type":"Manufacturing & Wholesale Goods"
        }
    ],
    "sg:phone":"+1 303 900 3858",
    "sg:postcode":"80209",
    "sg:province":"CO",
    "sg:tags":[
        "automotive",
        "sale",
        "radiator"
    ],
    "sg:website":"http://www.usaradiator.com",
    "wof:name":"Performance Radiator",
    "wof:placetype":"venue"
},
  "geometry": {"coordinates":[-104.98755300000001,39.702845],"type":"Point"}
}