{
  "type": "Feature",
  "properties": {
    "iso:country":"US",
    "sg:address":"7043 Pecos St",
    "sg:city":"Denver",
    "sg:classifiers":[
        {
            "category":"Shopping",
            "subcategory":"Clothing, Apparel, & Fashions",
            "type":"Retail Goods"
        }
    ],
    "sg:phone":"+1 303 428 4787",
    "sg:postcode":"80221",
    "sg:province":"CO",
    "sg:tags":[
        "garment"
    ],
    "wof:name":"Ortega's Kidz Apparel",
    "wof:placetype":"venue"
},
  "geometry": {"coordinates":[-105.006303,39.825335],"type":"Point"}
}