{
  "type": "Feature",
  "properties": {
    "addr:full":"23251 E Dorado Ave Aurora CO 80015",
    "addr:housenumber":"23251",
    "addr:postcode":"80015",
    "addr:street":"E Dorado Ave",
    "iso:country":"US",
    "sg:address":"23251 E Dorado Ave",
    "sg:city":"Aurora",
    "sg:classifiers":[
        {
            "category":"Building & Trades",
            "subcategory":"Construction",
            "type":"Services"
        }
    ],
    "sg:phone":"+1 303 400 8989",
    "sg:postcode":"80015",
    "sg:province":"CO",
    "sg:tags":[
        "house"
    ],
    "wof:name":"Leeper Construction LLC",
    "wof:placetype":"venue"
},
  "geometry": {"coordinates":[-104.718345,39.61163],"type":"Point"}
}