{
  "type": "Feature",
  "properties": {
    "iso:country":"US",
    "sg:address":"104 Tiffany Dr",
    "sg:city":"Pueblo",
    "sg:classifiers":[
        {
            "category":"Manufacturing",
            "subcategory":"Printing",
            "type":"Manufacturing & Wholesale Goods"
        }
    ],
    "sg:phone":"+1 719 547 7934",
    "sg:postcode":"81007",
    "sg:province":"CO",
    "sg:tags":[
        "mfg"
    ],
    "wof:name":"Amore Memories LLC",
    "wof:placetype":"venue"
},
  "geometry": {"coordinates":[-104.703377,38.323053],"type":"Point"}
}