{
  "type": "Feature",
  "properties": {
    "iso:country":"US",
    "sg:address":"3655 Star Ranch Rd",
    "sg:city":"Colorado Springs",
    "sg:classifiers":[
        {
            "category":"Personal",
            "subcategory":"Tanning Parlor",
            "type":"Services"
        }
    ],
    "sg:phone":"+1 719 579 0000",
    "sg:postcode":"80906",
    "sg:province":"CO",
    "sg:tags":[
        "salon"
    ],
    "wof:name":"Euro-Tan",
    "wof:placetype":"venue"
},
  "geometry": {"coordinates":[-104.817386,38.775396],"type":"Point"}
}