{
  "type": "Feature",
  "properties": {
    "iso:country":"US",
    "sg:address":"24290 Rockland Rd",
    "sg:city":"Golden",
    "sg:classifiers":[
        {
            "category":"Restaurant",
            "type":"Food & Drink"
        }
    ],
    "sg:phone":"+1 303 526 9189",
    "sg:postcode":"80401",
    "sg:province":"CO",
    "sg:tags":[
        "grocery",
        "eating"
    ],
    "wof:name":"Denver Deli & Market",
    "wof:placetype":"venue"
},
  "geometry": {"coordinates":[-105.266806,39.708874],"type":"Point"}
}