{
  "type": "Feature",
  "properties": {
    "iso:country":"US",
    "sg:address":"1320 W 133rd Way",
    "sg:city":"Denver",
    "sg:classifiers":[
        {
            "category":"Professional",
            "subcategory":"Computer Services",
            "type":"Services"
        }
    ],
    "sg:phone":"+1 303 252 7950",
    "sg:postcode":"80234",
    "sg:province":"CO",
    "sg:tags":[
        "graphic"
    ],
    "sg:website":"http://www.cubuffaloes.com",
    "wof:name":"Prominence Web Services",
    "wof:placetype":"venue"
},
  "geometry": {"coordinates":[-105.00325,39.937119],"type":"Point"}
}