{
  "type": "Feature",
  "properties": {
    "iso:country":"US",
    "sg:address":"4614 Northpark Dr",
    "sg:city":"Colorado Springs",
    "sg:classifiers":[
        {
            "category":"Wholesale",
            "subcategory":"Machinery & Supplies",
            "type":"Manufacturing & Wholesale Goods"
        },
        {
            "category":"Wholesale",
            "subcategory":"Stationery",
            "type":"Manufacturing & Wholesale Goods"
        }
    ],
    "sg:phone":"+1 719 594 5991",
    "sg:postcode":"80918",
    "sg:province":"CO",
    "sg:tags":[
        "janitor"
    ],
    "wof:name":"Corporate Express Inc",
    "wof:placetype":"venue"
},
  "geometry": {"coordinates":[-104.826336,38.901458],"type":"Point"}
}