{
  "type": "Feature",
  "properties": {
    "iso:country":"US",
    "sg:address":"1980 Dahlia St",
    "sg:city":"Denver",
    "sg:classifiers":[
        {
            "category":"Organizations",
            "subcategory":"Non-profit Organization",
            "type":"Services"
        }
    ],
    "sg:phone":"+1 303 399 2425",
    "sg:postcode":"80220",
    "sg:province":"CO",
    "sg:tags":[
        "human"
    ],
    "wof:name":"Metropolitan Organization",
    "wof:placetype":"venue"
},
  "geometry": {"coordinates":[-104.931988,39.746354],"type":"Point"}
}