{
  "type": "Feature",
  "properties": {
    "addr:full":"6140 Harlan St Arvada CO 80003",
    "addr:housenumber":"6140",
    "addr:postcode":"80003",
    "addr:street":"Harlan St",
    "iso:country":"US",
    "sg:address":"6140 Harlan St",
    "sg:city":"Arvada",
    "sg:classifiers":[
        {
            "category":"Manufacturing",
            "subcategory":"Tools & Machinery",
            "type":"Manufacturing & Wholesale Goods"
        }
    ],
    "sg:phone":"+1 303 422 3156",
    "sg:postcode":"80003",
    "sg:province":"CO",
    "sg:tags":[
        "equipment",
        "industry",
        "station",
        "mfg"
    ],
    "wof:name":"B D & L Maintenance",
    "wof:placetype":"venue"
},
  "geometry": {"coordinates":[-105.06251899999999,39.807886],"type":"Point"}
}