{
  "type": "Feature",
  "properties": {
    "iso:country":"US",
    "sg:address":"5277 Manhattan Cir",
    "sg:city":"Boulder",
    "sg:classifiers":[
        {
            "category":"Wholesale",
            "subcategory":"Electrical",
            "type":"Manufacturing & Wholesale Goods"
        }
    ],
    "sg:phone":"+1 720 304 9050",
    "sg:postcode":"80303",
    "sg:province":"CO",
    "sg:tags":[
        "electronic"
    ],
    "wof:name":"Channel Technology",
    "wof:placetype":"venue"
},
  "geometry": {"coordinates":[-105.227895,39.984622],"type":"Point"}
}