{
  "type": "Feature",
  "properties": {
    "iso:country":"US",
    "sg:address":"6160 Sailing Ct",
    "sg:city":"Colorado Springs",
    "sg:classifiers":[
        {
            "category":"Shopping",
            "type":"Retail Goods"
        }
    ],
    "sg:phone":"+1 719 594 6731",
    "sg:postcode":"80918",
    "sg:province":"CO",
    "sg:tags":[
        "merchandise"
    ],
    "wof:name":"B & L Map Co",
    "wof:placetype":"venue"
},
  "geometry": {"coordinates":[-104.760194,38.919471],"type":"Point"}
}