{
  "type": "Feature",
  "properties": {
    "addr:full":"600 17th Street Suite 2800 South Denver CO 80202",
    "addr:housenumber":"600",
    "addr:postcode":"80202",
    "addr:street":"17Th Street Suite 2800 South",
    "iso:country":"US",
    "sg:address":"600 17th Street Suite 2800 South",
    "sg:city":"Denver",
    "sg:classifiers":[
        {
            "category":"Professional",
            "subcategory":"Lawyer & Legal Services",
            "type":"Services"
        }
    ],
    "sg:phone":"+1 303 831 8924",
    "sg:postcode":"80202",
    "sg:province":"CO",
    "sg:website":"www.koplinlaw.com",
    "wof:name":"Law Office of Ross Koplin",
    "wof:placetype":"venue"
},
  "geometry": {"coordinates":[-104.990801,39.74529],"type":"Point"}
}