{
  "type": "Feature",
  "properties": {
    "addr:full":"2825 15th Ave Longmont CO 80503",
    "addr:housenumber":"2825",
    "addr:postcode":"80503",
    "addr:street":"15Th Ave",
    "iso:country":"US",
    "sg:address":"2825 15th Ave",
    "sg:city":"Longmont",
    "sg:classifiers":[
        {
            "category":"Personal",
            "type":"Services"
        }
    ],
    "sg:phone":"+1 303 776 5577",
    "sg:postcode":"80503",
    "sg:province":"CO",
    "sg:tags":[
        "sewing"
    ],
    "wof:name":"Threads",
    "wof:placetype":"venue"
},
  "geometry": {"coordinates":[-105.140349,40.185519],"type":"Point"}
}