{
  "type": "Feature",
  "properties": {
    "addr:full":"10413 N Roxborough Park Rd Littleton CO 80125",
    "addr:housenumber":"10413",
    "addr:postcode":"80125",
    "addr:street":"N Roxborough Park Rd",
    "iso:country":"US",
    "sg:address":"10413 N Roxborough Park Rd",
    "sg:city":"Littleton",
    "sg:classifiers":[
        {
            "category":"Banks & Credit Unions",
            "subcategory":"Investment Brokerage",
            "type":"Services"
        }
    ],
    "sg:phone":"+1 303 791 3891",
    "sg:postcode":"80125",
    "sg:province":"CO",
    "sg:tags":[
        "security",
        "agency",
        "travel"
    ],
    "wof:name":"Burleigh Travel Enterprises",
    "wof:placetype":"venue"
},
  "geometry": {"coordinates":[-105.054579,39.514058],"type":"Point"}
}