{
  "type": "Feature",
  "properties": {
    "iso:country":"US",
    "sg:address":"7720 S Broadway",
    "sg:city":"Littleton",
    "sg:classifiers":[
        {
            "category":"Health Services",
            "subcategory":"Doctor",
            "type":"Services"
        }
    ],
    "sg:phone":"+1 303 798 8262",
    "sg:postcode":"80122",
    "sg:province":"CO",
    "sg:tags":[
        "medical"
    ],
    "wof:name":"Wood Lawrence & Wallack David",
    "wof:placetype":"venue"
},
  "geometry": {"coordinates":[-104.988317,39.578095],"type":"Point"}
}