{
  "type": "Feature",
  "properties": {
    "addr:full":"10503 Isabelle Rd Lafayette CO 80026",
    "addr:housenumber":"10503",
    "addr:postcode":"80026",
    "addr:street":"Isabelle Rd",
    "iso:country":"US",
    "sg:address":"10503 Isabelle Rd",
    "sg:city":"Lafayette",
    "sg:classifiers":[
        {
            "category":"Farming",
            "subcategory":"Farm",
            "type":"Manufacturing & Wholesale Goods"
        }
    ],
    "sg:phone":"+1 303 665 5704",
    "sg:postcode":"80026",
    "sg:province":"CO",
    "sg:tags":[
        "crop",
        "general"
    ],
    "wof:name":"Schwartz Farms LLC",
    "wof:placetype":"venue"
},
  "geometry": {"coordinates":[-105.10341,40.036675],"type":"Point"}
}