{
  "type": "Feature",
  "properties": {
    "addr:full":"33 S Pratt Pkwy Longmont CO 80501",
    "addr:housenumber":"33",
    "addr:postcode":"80501",
    "addr:street":"S Pratt Pkwy",
    "iso:country":"US",
    "sg:address":"33 S Pratt Pkwy",
    "sg:city":"Longmont",
    "sg:classifiers":[
        {
            "category":"Manufacturing",
            "subcategory":"Tools & Machinery",
            "type":"Manufacturing & Wholesale Goods"
        }
    ],
    "sg:phone":"+1 303 684 9585",
    "sg:postcode":"80501",
    "sg:province":"CO",
    "sg:tags":[
        "machine",
        "shop",
        "job"
    ],
    "wof:name":"HI Tech Specialists Inc",
    "wof:placetype":"venue"
},
  "geometry": {"coordinates":[-105.106844,40.160153],"type":"Point"}
}