{
  "type": "Feature",
  "properties": {
    "iso:country":"US",
    "sg:address":"270 E Yucca Hills Rd",
    "sg:city":"Castle Rock",
    "sg:classifiers":[
        {
            "category":"Building & Trades",
            "subcategory":"Construction",
            "type":"Services"
        }
    ],
    "sg:phone":"+1 303 663 8622",
    "sg:postcode":"80109",
    "sg:province":"CO",
    "sg:tags":[
        "house"
    ],
    "wof:name":"Dakota Construction",
    "wof:placetype":"venue"
},
  "geometry": {"coordinates":[-104.87094,39.356737],"type":"Point"}
}