{
  "type": "Feature",
  "properties": {
    "addr:full":"1510 Cook Street Denver CO 80206",
    "addr:housenumber":"1510",
    "addr:postcode":"80206",
    "addr:street":"Cook Street",
    "iso:country":"US",
    "sg:address":"1510 Cook Street",
    "sg:city":"Denver",
    "sg:classifiers":[
        {
            "category":"Professional",
            "subcategory":"Accounting & Tax Preparation",
            "type":"Services"
        }
    ],
    "sg:phone":"+1 303 316 8332",
    "sg:postcode":"80206",
    "sg:province":"CO",
    "sg:tags":[
        "accountant"
    ],
    "wof:name":"The Tax Place",
    "wof:placetype":"venue"
},
  "geometry": {"coordinates":[-104.94752099999999,39.74039],"type":"Point"}
}