{
  "type": "Feature",
  "properties": {
    "iso:country":"US",
    "sg:address":"1643 31st Ave",
    "sg:city":"Greeley",
    "sg:classifiers":[
        {
            "category":"Manufacturing",
            "subcategory":"Tools & Machinery",
            "type":"Manufacturing & Wholesale Goods"
        }
    ],
    "sg:phone":"+1 970 339 5764",
    "sg:postcode":"80634",
    "sg:province":"CO",
    "sg:tags":[
        "machine",
        "weighing",
        "mfg"
    ],
    "wof:name":"Medical Measurements LLC",
    "wof:placetype":"venue"
},
  "geometry": {"coordinates":[-104.73112399999999,40.413287],"type":"Point"}
}