{
  "type": "Feature",
  "properties": {
    "iso:country":"US",
    "sg:address":"1935 Enchantment Dr",
    "sg:city":"Fort Collins",
    "sg:classifiers":[
        {
            "category":"Professional",
            "type":"Services"
        }
    ],
    "sg:phone":"+1 970 407 0088",
    "sg:postcode":"80525",
    "sg:province":"CO",
    "wof:name":"Enchanted Threads EMB & Design",
    "wof:placetype":"venue"
},
  "geometry": {"coordinates":[-104.98115300000001,40.561751],"type":"Point"}
}