{
  "type": "Feature",
  "properties": {
    "iso:country":"US",
    "sg:address":"4436 Grant St",
    "sg:city":"Denver",
    "sg:classifiers":[
        {
            "category":"Autos & Motor Vehicles",
            "subcategory":"Auto Supplies",
            "type":"Retail Goods"
        }
    ],
    "sg:phone":"+1 720 299 3775",
    "sg:postcode":"80216",
    "sg:province":"CO",
    "sg:tags":[
        "glass"
    ],
    "sg:website":"www.absoluteautoglassdenver.com",
    "wof:name":"Absolute Auto Glass",
    "wof:placetype":"venue"
},
  "geometry": {"coordinates":[-104.983258,39.777231],"type":"Point"}
}