{
  "type": "Feature",
  "properties": {
    "iso:country":"US",
    "sg:address":"604 Locust Ave",
    "sg:city":"Las Animas",
    "sg:classifiers":[
        {
            "category":"Restaurant",
            "type":"Food & Drink"
        }
    ],
    "sg:phone":"+1 719 456 0062",
    "sg:postcode":"81054",
    "sg:province":"CO",
    "sg:tags":[
        "eating"
    ],
    "wof:name":"Troll House The",
    "wof:placetype":"venue"
},
  "geometry": {"coordinates":[-103.223823,38.066314],"type":"Point"}
}