{
  "type": "Feature",
  "properties": {
    "iso:country":"US",
    "sg:address":"224 Comanche St",
    "sg:city":"Kiowa",
    "sg:classifiers":[
        {
            "category":"Restaurant",
            "type":"Food & Drink"
        }
    ],
    "sg:phone":"+1 303 621 2688",
    "sg:postcode":"80117",
    "sg:province":"CO",
    "wof:name":"Homestead Cafe",
    "wof:placetype":"venue"
},
  "geometry": {"coordinates":[-104.467833,39.3465],"type":"Point"}
}