{
  "type": "Feature",
  "properties": {
    "iso:country":"US",
    "sg:address":"2186 S Holly St",
    "sg:city":"Denver",
    "sg:classifiers":[
        {
            "category":"Organizations",
            "subcategory":"Non-profit Organization",
            "type":"Services"
        }
    ],
    "sg:phone":"+1 303 504 9524",
    "sg:postcode":"80222",
    "sg:province":"CO",
    "sg:tags":[
        "fund",
        "counselor",
        "raising"
    ],
    "wof:name":"Take Charge",
    "wof:placetype":"venue"
},
  "geometry": {"coordinates":[-104.922203,39.676334],"type":"Point"}
}