{
  "type": "Feature",
  "properties": {
    "iso:country":"US",
    "sg:address":"10370 Ralston Rd",
    "sg:city":"Arvada",
    "sg:classifiers":[
        {
            "category":"Restaurant",
            "type":"Food & Drink"
        }
    ],
    "sg:phone":"+1 303 421 1045",
    "sg:postcode":"80004",
    "sg:province":"CO",
    "sg:tags":[
        "caterer"
    ],
    "wof:name":"Ala Carte Cakes Catering-Deli",
    "wof:placetype":"venue"
},
  "geometry": {"coordinates":[-105.11391,39.811698],"type":"Point"}
}