{
  "type": "Feature",
  "properties": {
    "addr:full":"2175 S Jasmine St Ste 111 Denver CO 80222",
    "addr:housenumber":"2175",
    "addr:postcode":"80222",
    "addr:street":"S Jasmine St Ste 111",
    "iso:country":"US",
    "sg:address":"2175 S Jasmine St Ste 111",
    "sg:city":"Denver",
    "sg:classifiers":[
        {
            "category":"Professional",
            "subcategory":"Accounting & Tax Preparation",
            "type":"Services"
        },
        {
            "category":"Banks & Credit Unions",
            "subcategory":"Investment Brokerage",
            "type":"Services"
        },
        {
            "category":"Banks & Credit Unions",
            "subcategory":"Financial Services",
            "type":"Services"
        }
    ],
    "sg:phone":"+1 303 758 7764",
    "sg:postcode":"80222",
    "sg:province":"CO",
    "sg:tags":[
        "consultant",
        "planning",
        "return"
    ],
    "wof:name":"Beecher Business Svc Inc",
    "wof:placetype":"venue"
},
  "geometry": {"coordinates":[-104.91878699999999,39.677103],"type":"Point"}
}