{
  "type": "Feature",
  "properties": {
    "addr:full":"3245 W Bellewood Dr Englewood CO 80110",
    "addr:housenumber":"3245",
    "addr:postcode":"80110",
    "addr:street":"W Bellewood Dr",
    "iso:country":"US",
    "sg:address":"3245 W Bellewood Dr",
    "sg:city":"Englewood",
    "sg:classifiers":[
        {
            "category":"Building & Trades",
            "subcategory":"Construction",
            "type":"Services"
        }
    ],
    "sg:phone":"+1 303 347 1117",
    "sg:postcode":"80110",
    "sg:province":"CO",
    "sg:tags":[
        "nonresidential"
    ],
    "wof:name":"Shawn Moss Construction",
    "wof:placetype":"venue"
},
  "geometry": {"coordinates":[-105.029388,39.625079],"type":"Point"}
}