{
  "type": "Feature",
  "properties": {
    "addr:full":"9605 Kingston Ct Englewood CO 80112",
    "addr:housenumber":"9605",
    "addr:postcode":"80112",
    "addr:street":"Kingston Ct",
    "iso:country":"US",
    "sg:address":"9605 Kingston Ct",
    "sg:city":"Englewood",
    "sg:classifiers":[
        {
            "category":"Real Estate",
            "subcategory":"Real Estate Agent",
            "type":"Services"
        }
    ],
    "sg:phone":"+1 303 858 0920",
    "sg:postcode":"80112",
    "sg:province":"CO",
    "wof:name":"Triumph Real Estate Corp",
    "wof:placetype":"venue"
},
  "geometry": {"coordinates":[-104.861189,39.543344],"type":"Point"}
}