{
  "type": "Feature",
  "properties": {
    "addr:full":"17580 Co Rd 500 Pagosa Springs CO 81147",
    "addr:housenumber":"17580;500",
    "addr:postcode":"81147",
    "addr:street":"Co Rd",
    "iso:country":"US",
    "sg:address":"17580 Co Rd 500",
    "sg:city":"Pagosa Springs",
    "sg:classifiers":[
        {
            "category":"Building & Trades",
            "subcategory":"Cleaning & Sanitation",
            "type":"Services"
        }
    ],
    "sg:phone":"+1 970 264 4324",
    "sg:postcode":"81147",
    "sg:province":"CO",
    "sg:tags":[
        "fireplace",
        "chimney"
    ],
    "wof:name":"Top Notch Chimney Sweep",
    "wof:placetype":"venue"
},
  "geometry": {"coordinates":[-107.08997599999999,37.061884],"type":"Point"}
}