{
  "type": "Feature",
  "properties": {
    "addr:full":"1449 S Vaughn Cir Aurora CO 80012",
    "addr:housenumber":"1449",
    "addr:postcode":"80012",
    "addr:street":"S Vaughn Cir",
    "iso:country":"US",
    "sg:address":"1449 S Vaughn Cir",
    "sg:city":"Aurora",
    "sg:classifiers":[
        {
            "category":"Home & Garden",
            "subcategory":"Building Materials",
            "type":"Retail Goods"
        }
    ],
    "sg:phone":"+1 303 671 6174",
    "sg:postcode":"80012",
    "sg:province":"CO",
    "wof:name":"International Coating Chem Co",
    "wof:placetype":"venue"
},
  "geometry": {"coordinates":[-104.83783200000001,39.690991],"type":"Point"}
}