{
  "type": "Feature",
  "properties": {
    "iso:country":"US",
    "sg:address":"2117 Kieler Ln",
    "sg:city":"Loveland",
    "sg:classifiers":[
        {
            "category":"Utilities",
            "subcategory":"Telephone",
            "type":"Services"
        }
    ],
    "sg:phone":"+1 970 690 0608",
    "sg:postcode":"80538",
    "sg:province":"CO",
    "sg:tags":[
        "communications"
    ],
    "wof:name":"LP Broadband Inc",
    "wof:placetype":"venue"
},
  "geometry": {"coordinates":[-105.04589300000001,40.456538],"type":"Point"}
}