{
  "type": "Feature",
  "properties": {
    "addr:full":"1015 25th Ave Greeley CO 80634",
    "addr:housenumber":"1015",
    "addr:postcode":"80634",
    "addr:street":"25Th Ave",
    "iso:country":"US",
    "sg:address":"1015 25th Ave",
    "sg:city":"Greeley",
    "sg:classifiers":[
        {
            "category":"Manufacturing",
            "subcategory":"Printing",
            "type":"Manufacturing & Wholesale Goods"
        }
    ],
    "sg:phone":"+1 970 352 6595",
    "sg:postcode":"80634",
    "sg:province":"CO",
    "sg:tags":[
        "commercial"
    ],
    "wof:name":"Westview Printing Inc",
    "wof:placetype":"venue"
},
  "geometry": {"coordinates":[-104.72085800000001,40.421937],"type":"Point"}
}