{
  "type": "Feature",
  "properties": {
    "addr:full":"17660 Cleese Ct Peyton CO 80831",
    "addr:housenumber":"17660",
    "addr:postcode":"80831",
    "addr:street":"Cleese Ct",
    "iso:country":"US",
    "sg:address":"17660 Cleese Ct",
    "sg:city":"Peyton",
    "sg:classifiers":[
        {
            "category":"Building & Trades",
            "subcategory":"Construction",
            "type":"Services"
        }
    ],
    "sg:phone":"+1 719 749 2609",
    "sg:postcode":"80831",
    "sg:province":"CO",
    "sg:tags":[
        "hanging",
        "contractor"
    ],
    "wof:name":"RPM Painting",
    "wof:placetype":"venue"
},
  "geometry": {"coordinates":[-104.50326,39.081514],"type":"Point"}
}