{
  "type": "Feature",
  "properties": {
    "addr:full":"8073 Chaparral Rd Lone Tree CO 80124",
    "addr:housenumber":"8073",
    "addr:postcode":"80124",
    "addr:street":"Chaparral Rd",
    "iso:country":"US",
    "sg:address":"8073 Chaparral Rd",
    "sg:city":"Lone Tree",
    "sg:classifiers":[
        {
            "category":"Shopping",
            "subcategory":"News",
            "type":"Retail Goods"
        }
    ],
    "sg:phone":"+1 303 708 0224",
    "sg:postcode":"80124",
    "sg:province":"CO",
    "sg:tags":[
        "dealer"
    ],
    "wof:name":"Pollard Clint Good News Jail",
    "wof:placetype":"venue"
},
  "geometry": {"coordinates":[-104.896508,39.550474],"type":"Point"}
}