{
  "type": "Feature",
  "properties": {
    "addr:full":"309 Cam Real Fort Collins CO 80524",
    "addr:housenumber":"309",
    "addr:postcode":"80524",
    "addr:street":"Cam Real",
    "iso:country":"US",
    "sg:address":"309 Cam Real",
    "sg:city":"Fort Collins",
    "sg:classifiers":[
        {
            "category":"Professional",
            "type":"Services"
        }
    ],
    "sg:phone":"+1 970 282 9726",
    "sg:postcode":"80524",
    "sg:province":"CO",
    "wof:name":"Colorado & West Wheels LLC",
    "wof:placetype":"venue"
},
  "geometry": {"coordinates":[-104.98448999999999,40.58294],"type":"Point"}
}