{
  "type": "Feature",
  "properties": {
    "iso:country":"US",
    "sg:address":"3396 E Fair Pl",
    "sg:city":"Littleton",
    "sg:classifiers":[
        {
            "category":"Professional",
            "type":"Services"
        }
    ],
    "sg:phone":"+1 303 740 6254",
    "sg:postcode":"80121",
    "sg:province":"CO",
    "wof:name":"Creative Playcenters By Pat We",
    "wof:placetype":"venue"
},
  "geometry": {"coordinates":[-104.94939100000001,39.602763],"type":"Point"}
}