{
  "type": "Feature",
  "properties": {
    "iso:country":"US",
    "sg:address":"2922 Evergreen Pkwy",
    "sg:city":"Evergreen",
    "sg:classifiers":[
        {
            "category":"Professional",
            "subcategory":"Accounting & Tax Preparation",
            "type":"Services"
        }
    ],
    "sg:phone":"+1 303 674 0964",
    "sg:postcode":"80439",
    "sg:province":"CO",
    "sg:tags":[
        "bookkeeping",
        "general"
    ],
    "wof:name":"Evergreen Bookkeepers",
    "wof:placetype":"venue"
},
  "geometry": {"coordinates":[-105.35411999999999,39.662031],"type":"Point"}
}