{
  "type": "Feature",
  "properties": {
    "iso:country":"US",
    "sg:address":"3934 Federal Blvd",
    "sg:city":"Denver",
    "sg:classifiers":[
        {
            "category":"Insurance",
            "subcategory":"Hazard Insurance",
            "type":"Services"
        }
    ],
    "sg:phone":"+1 303 271 3881",
    "sg:postcode":"80211",
    "sg:province":"CO",
    "sg:tags":[
        "bond"
    ],
    "wof:name":"Reliable Bail Bonds",
    "wof:placetype":"venue"
},
  "geometry": {"coordinates":[-105.02521900000001,39.771728],"type":"Point"}
}