{
  "type": "Feature",
  "properties": {
    "addr:full":"7313 Centennial St Fountain CO 80817",
    "addr:housenumber":"7313",
    "addr:postcode":"80817",
    "addr:street":"Centennial St",
    "iso:country":"US",
    "sg:address":"7313 Centennial St",
    "sg:city":"Fountain",
    "sg:classifiers":[
        {
            "category":"Real Estate",
            "subcategory":"Real Estate Agent",
            "type":"Services"
        }
    ],
    "sg:phone":"+1 719 390 8081",
    "sg:postcode":"80817",
    "sg:province":"CO",
    "wof:name":"Kent Walters Real Estate",
    "wof:placetype":"venue"
},
  "geometry": {"coordinates":[-104.68985499999999,38.730928],"type":"Point"}
}