{
  "type": "Feature",
  "properties": {
    "addr:full":"14799 W 6th Ave Golden CO 80401",
    "addr:housenumber":"14799",
    "addr:postcode":"80401",
    "addr:street":"W 6Th Ave",
    "iso:country":"US",
    "sg:address":"14799 W 6th Ave",
    "sg:city":"Golden",
    "sg:classifiers":[
        {
            "category":"Utilities",
            "subcategory":"Mobile Phone",
            "type":"Services"
        }
    ],
    "sg:phone":"+1 303 215 0090",
    "sg:postcode":"80401",
    "sg:province":"CO",
    "sg:tags":[
        "telephone",
        "cellular"
    ],
    "wof:name":"Conexus",
    "wof:placetype":"venue"
},
  "geometry": {"coordinates":[-105.16668300000001,39.72551],"type":"Point"}
}