{
  "type": "Feature",
  "properties": {
    "iso:country":"US",
    "sg:address":"13800 E 39th Ave",
    "sg:city":"Aurora",
    "sg:classifiers":[
        {
            "category":"Wholesale",
            "subcategory":"Stationery",
            "type":"Manufacturing & Wholesale Goods"
        }
    ],
    "sg:phone":"+1 303 373 8228",
    "sg:postcode":"80011",
    "sg:province":"CO",
    "sg:tags":[
        "real estate"
    ],
    "wof:name":"Corporate Express Office Pdts",
    "wof:placetype":"venue"
},
  "geometry": {"coordinates":[-104.8192,39.771265],"type":"Point"}
}