{
  "type": "Feature",
  "properties": {
    "iso:country":"US",
    "sg:address":"1332 Pearl St",
    "sg:city":"Boulder",
    "sg:classifiers":[
        {
            "category":"Shopping",
            "subcategory":"Computers & Home Electronics",
            "type":"Retail Goods"
        }
    ],
    "sg:phone":"+1 303 444 1476",
    "sg:postcode":"80302",
    "sg:province":"CO",
    "sg:tags":[
        "software"
    ],
    "sg:website":"www.nmci.com",
    "wof:name":"New Millennium Communications",
    "wof:placetype":"venue"
},
  "geometry": {"coordinates":[-105.277677,40.018286],"type":"Point"}
}