{
  "type": "Feature",
  "properties": {
    "addr:full":"1120 Washington Ave Golden CO 80401",
    "addr:housenumber":"1120",
    "addr:postcode":"80401",
    "addr:street":"Washington Ave",
    "iso:country":"US",
    "sg:address":"1120 Washington Ave",
    "sg:city":"Golden",
    "sg:classifiers":[
        {
            "category":"Professional",
            "subcategory":"Computer Services",
            "type":"Services"
        }
    ],
    "sg:phone":"+1 303 215 3436",
    "sg:postcode":"80401",
    "sg:province":"CO",
    "sg:tags":[
        "communications",
        "telephone",
        "programing",
        "custom"
    ],
    "wof:name":"Nreach",
    "wof:placetype":"venue"
},
  "geometry": {"coordinates":[-105.221504,39.755522],"type":"Point"}
}