{
  "type": "Feature",
  "properties": {
    "iso:country":"US",
    "sg:address":"1731 15th St",
    "sg:city":"Boulder",
    "sg:classifiers":[
        {
            "category":"Food & Beverages",
            "subcategory":"Dairy",
            "type":"Retail Goods"
        }
    ],
    "sg:phone":"+1 303 938 1499",
    "sg:postcode":"80302",
    "sg:province":"CO",
    "sg:tags":[
        "cheese",
        "product"
    ],
    "wof:name":"Boulder Cheese Company",
    "wof:placetype":"venue"
},
  "geometry": {"coordinates":[-105.275024,40.015455],"type":"Point"}
}