{
  "type": "Feature",
  "properties": {
    "addr:full":"1333 Darby St Colorado Springs CO 80907",
    "addr:housenumber":"1333",
    "addr:postcode":"80907",
    "addr:street":"Darby St",
    "iso:country":"US",
    "sg:address":"1333 Darby St",
    "sg:city":"Colorado Springs",
    "sg:classifiers":[
        {
            "category":"Health Services",
            "subcategory":"Nursing And Care Facility",
            "type":"Services"
        }
    ],
    "sg:phone":"+1 719 522 1671",
    "sg:postcode":"80907",
    "sg:province":"CO",
    "sg:tags":[
        "skilled",
        "home",
        "retirement",
        "community"
    ],
    "wof:name":"Gentle Care House Inc",
    "wof:placetype":"venue"
},
  "geometry": {"coordinates":[-104.844425,38.89141],"type":"Point"}
}