{
  "type": "Feature",
  "properties": {
    "iso:country":"US",
    "sg:address":"4840 Pearl East Cir",
    "sg:city":"Boulder",
    "sg:classifiers":[
        {
            "category":"Professional",
            "subcategory":"Computer Services",
            "type":"Services"
        }
    ],
    "sg:phone":"+1 303 858 2000",
    "sg:postcode":"80301",
    "sg:province":"CO",
    "sg:tags":[
        "develops",
        "networking",
        "system"
    ],
    "wof:name":"3 Com Corporation",
    "wof:placetype":"venue"
},
  "geometry": {"coordinates":[-105.239993,40.02119],"type":"Point"}
}