{
  "type": "Feature",
  "properties": {
    "iso:country":"US",
    "sg:address":"9665 Townsville Cir",
    "sg:city":"Littleton",
    "sg:classifiers":[
        {
            "category":"Shopping",
            "subcategory":"Musical Instruments",
            "type":"Retail Goods"
        }
    ],
    "sg:phone":"+1 303 683 5429",
    "sg:postcode":"80130",
    "sg:province":"CO",
    "wof:name":"Heather Brecl Music Studi",
    "wof:placetype":"venue"
},
  "geometry": {"coordinates":[-104.934618,39.541846],"type":"Point"}
}