{
  "type": "Feature",
  "properties": {
    "iso:country":"US",
    "sg:address":"10674 US Hwy 285",
    "sg:city":"Conifer",
    "sg:classifiers":[
        {
            "category":"Building & Trades",
            "subcategory":"Construction",
            "type":"Services"
        }
    ],
    "sg:phone":"+1 303 838 6188",
    "sg:postcode":"80433",
    "sg:province":"CO",
    "sg:tags":[
        "contractor"
    ],
    "wof:name":"Birdsong Masonry Inc",
    "wof:placetype":"venue"
},
  "geometry": {"coordinates":[-105.30652600000001,39.524083],"type":"Point"}
}