{
  "type": "Feature",
  "properties": {
    "addr:full":"249 Co Rd 233 Durango CO 81301",
    "addr:housenumber":"249;233",
    "addr:postcode":"co 81301",
    "addr:street":"Co Rd",
    "iso:country":"US",
    "sg:address":"249 Co Rd 233",
    "sg:city":"Durango",
    "sg:classifiers":[
        {
            "category":"Freight",
            "type":"Transportation"
        }
    ],
    "sg:phone":"+1 970 247 2680",
    "sg:postcode":"81301",
    "sg:province":"CO",
    "sg:tags":[
        "commercial",
        "storage"
    ],
    "wof:name":"LA Plata Boat & Rv Storage",
    "wof:placetype":"venue"
},
  "geometry": {"coordinates":[-107.81908900000001,37.228691],"type":"Point"}
}