{
  "type": "Feature",
  "properties": {
    "iso:country":"US",
    "sg:address":"414 E 6th St",
    "sg:city":"Loveland",
    "sg:classifiers":[
        {
            "category":"Restaurant",
            "type":"Food & Drink"
        }
    ],
    "sg:phone":"+1 970 669 9577",
    "sg:postcode":"80537",
    "sg:province":"CO",
    "sg:tags":[
        "eating"
    ],
    "wof:name":"Adelita's Fine Mexican Food",
    "wof:placetype":"venue"
},
  "geometry": {"coordinates":[-105.07069,40.397424],"type":"Point"}
}