{
  "type": "Feature",
  "properties": {
    "addr:full":"10865 W Half Moon Pass Littleton CO 80127",
    "addr:housenumber":"10865",
    "addr:postcode":"80127",
    "addr:street":"W Half Moon Pass",
    "iso:country":"US",
    "sg:address":"10865 W Half Moon Pass",
    "sg:city":"Littleton",
    "sg:classifiers":[
        {
            "category":"Building & Trades",
            "subcategory":"Construction",
            "type":"Services"
        }
    ],
    "sg:phone":"+1 303 979 7908",
    "sg:postcode":"80127",
    "sg:province":"CO",
    "sg:tags":[
        "house",
        "con"
    ],
    "wof:name":"Absolute Construction",
    "wof:placetype":"venue"
},
  "geometry": {"coordinates":[-105.120305,39.571684],"type":"Point"}
}