{
  "type": "Feature",
  "properties": {
    "iso:country":"US",
    "sg:address":"1701 Wynkoop St",
    "sg:city":"Denver",
    "sg:classifiers":[
        {
            "category":"Shopping",
            "subcategory":"Optical Goods",
            "type":"Retail Goods"
        }
    ],
    "sg:phone":"+1 303 333 9191",
    "sg:postcode":"80202",
    "sg:province":"CO",
    "sg:tags":[
        "sun",
        "goggles",
        "sunglasses"
    ],
    "wof:name":"Rudy Project",
    "wof:placetype":"venue"
},
  "geometry": {"coordinates":[-104.998481,39.753782],"type":"Point"}
}