{
  "type": "Feature",
  "properties": {
    "iso:country":"US",
    "sg:address":"807 W Co Rd 4e",
    "sg:city":"Berthoud",
    "sg:classifiers":[
        {
            "category":"Retail",
            "subcategory":"Animal Services",
            "type":"Services"
        }
    ],
    "sg:phone":"+1 970 532 2667",
    "sg:postcode":"80513",
    "sg:province":"CO",
    "wof:name":"Pawsitive Approach",
    "wof:placetype":"venue"
},
  "geometry": {"coordinates":[-105.08751599999999,40.28334],"type":"Point"}
}