{
  "type": "Feature",
  "properties": {
    "iso:country":"US",
    "sg:address":"441 Birket Dr",
    "sg:city":"Durango",
    "sg:classifiers":[
        {
            "category":"Real Estate",
            "subcategory":"Architect",
            "type":"Services"
        }
    ],
    "sg:phone":"+1 970 382 2529",
    "sg:postcode":"81301",
    "sg:province":"CO",
    "sg:tags":[
        "building",
        "designer"
    ],
    "wof:name":"Bolster Design & Construction",
    "wof:placetype":"venue"
},
  "geometry": {"coordinates":[-107.87767700000001,37.300067],"type":"Point"}
}