{
  "type": "Feature",
  "properties": {
    "addr:full":"1630 Summit St Norwood CO 81423",
    "addr:housenumber":"1630",
    "addr:postcode":"81423",
    "addr:street":"Summit St",
    "iso:country":"US",
    "sg:address":"1630 Summit St",
    "sg:city":"Norwood",
    "sg:classifiers":[
        {
            "category":"Wholesale",
            "subcategory":"Non-durable Goods",
            "type":"Manufacturing & Wholesale Goods"
        }
    ],
    "sg:phone":"+1 970 327 0304",
    "sg:postcode":"81423",
    "sg:province":"CO",
    "wof:name":"Tomboy Soap Co",
    "wof:placetype":"venue"
},
  "geometry": {"coordinates":[-108.28924000000001,38.131682],"type":"Point"}
}