{
  "type": "Feature",
  "properties": {
    "addr:full":"956 Mountain View Dr Castle Rock CO 80104",
    "addr:housenumber":"956",
    "addr:postcode":"80104",
    "addr:street":"Mountain View Dr",
    "iso:country":"US",
    "sg:address":"956 Mountain View Dr",
    "sg:city":"Castle Rock",
    "sg:classifiers":[
        {
            "category":"Building & Trades",
            "subcategory":"Construction",
            "type":"Services"
        }
    ],
    "sg:phone":"+1 303 688 2138",
    "sg:postcode":"80104",
    "sg:province":"CO",
    "sg:tags":[
        "contractor"
    ],
    "wof:name":"Caz Masonry Inc",
    "wof:placetype":"venue"
},
  "geometry": {"coordinates":[-104.85409199999999,39.385185],"type":"Point"}
}