{
  "type": "Feature",
  "properties": {
    "iso:country":"US",
    "sg:address":"1360 Indian Trl",
    "sg:city":"Steamboat Spgs",
    "sg:classifiers":[
        {
            "category":"Retail",
            "subcategory":"Repair Shop",
            "type":"Services"
        }
    ],
    "sg:phone":"+1 970 879 7866",
    "sg:postcode":"80487",
    "sg:province":"CO",
    "sg:tags":[
        "appliance"
    ],
    "wof:name":"High Country Appliance Svc",
    "wof:placetype":"venue"
},
  "geometry": {"coordinates":[-106.84667399999999,40.496143],"type":"Point"}
}