{
  "type": "Feature",
  "properties": {
    "addr:full":"333 S Tejon St Colorado Springs CO 80903",
    "addr:housenumber":"333",
    "addr:postcode":"80903",
    "addr:street":"S Tejon St",
    "iso:country":"US",
    "sg:address":"333 S Tejon St",
    "sg:city":"Colorado Springs",
    "sg:classifiers":[
        {
            "category":"Restaurant",
            "type":"Food & Drink"
        }
    ],
    "sg:phone":"+1 719 471 8070",
    "sg:postcode":"80903",
    "sg:province":"CO",
    "wof:name":"Oscar's Tejon Street",
    "wof:placetype":"venue"
},
  "geometry": {"coordinates":[-104.82370299999999,38.828666],"type":"Point"}
}