{
  "type": "Feature",
  "properties": {
    "iso:country":"US",
    "sg:address":"460 Broadway",
    "sg:city":"Denver",
    "sg:classifiers":[
        {
            "category":"Shopping",
            "subcategory":"Department Store",
            "type":"Retail Goods"
        },
        {
            "category":"Shopping Center",
            "type":"Public Place"
        }
    ],
    "sg:phone":"+1 303 744 3900",
    "sg:postcode":"80203",
    "sg:province":"CO",
    "sg:website":"www.familydollar.com",
    "wof:name":"Family Dollar Store",
    "wof:placetype":"venue"
},
  "geometry": {"coordinates":[-104.98713100000001,39.723422],"type":"Point"}
}