{
  "type": "Feature",
  "properties": {
    "addr:full":"3400 S Fairplay Way Aurora CO 80014",
    "addr:housenumber":"3400",
    "addr:postcode":"80014",
    "addr:street":"S Fairplay Way",
    "iso:country":"US",
    "sg:address":"3400 S Fairplay Way",
    "sg:city":"Aurora",
    "sg:classifiers":[
        {
            "category":"Social Services",
            "subcategory":"Child Care",
            "type":"Services"
        }
    ],
    "sg:phone":"+1 303 690 0300",
    "sg:postcode":"80014",
    "sg:province":"CO",
    "sg:tags":[
        "day"
    ],
    "wof:name":"Childrens World Lrng Ctr 454",
    "wof:placetype":"venue"
},
  "geometry": {"coordinates":[-104.81309,39.653083],"type":"Point"}
}