{
  "type": "Feature",
  "properties": {
    "iso:country":"US",
    "sg:address":"15001 E Mississippi Ave",
    "sg:city":"Aurora",
    "sg:classifiers":[
        {
            "category":"Bars & Pubs",
            "subcategory":"Lounge",
            "type":"Food & Drink"
        },
        {
            "category":"Restaurant",
            "type":"Food & Drink"
        }
    ],
    "sg:phone":"+1 303 337 2761",
    "sg:postcode":"80012",
    "sg:province":"CO",
    "sg:tags":[
        "grill",
        "style",
        "mexican",
        "family",
        "cocktail",
        "lunch",
        "brunch",
        "breakfast"
    ],
    "sg:website":"http://www.armadillorestaurants.com",
    "wof:name":"Armadillo Mexican Restaurant",
    "wof:placetype":"venue"
},
  "geometry": {"coordinates":[-104.813957,39.696678],"type":"Point"}
}