{
  "type": "Feature",
  "properties": {
    "iso:country":"US",
    "sg:address":"62429 US Hwy 40",
    "sg:city":"Granby",
    "sg:classifiers":[
        {
            "category":"Food & Beverages",
            "subcategory":"Bakery",
            "type":"Retail Goods"
        }
    ],
    "sg:phone":"+1 970 887 2051",
    "sg:postcode":"80446",
    "sg:province":"CO",
    "sg:tags":[
        "baker"
    ],
    "wof:name":"Holsum Bread",
    "wof:placetype":"venue"
},
  "geometry": {"coordinates":[-105.927187,40.074377],"type":"Point"}
}