{
  "type": "Feature",
  "properties": {
    "iso:country":"US",
    "sg:address":"510 Colorado Ave",
    "sg:city":"Pueblo",
    "sg:classifiers":[
        {
            "category":"Health Services",
            "subcategory":"Doctor",
            "type":"Services"
        }
    ],
    "sg:phone":"+1 719 543 1132",
    "sg:postcode":"81004",
    "sg:province":"CO",
    "sg:tags":[
        "dentist"
    ],
    "wof:name":"William J Jagger DDS",
    "wof:placetype":"venue"
},
  "geometry": {"coordinates":[-104.62728199999999,38.254809],"type":"Point"}
}