{
  "type": "Feature",
  "properties": {
    "iso:country":"US",
    "sg:address":"5810 Lamar St",
    "sg:city":"Denver",
    "sg:classifiers":[
        {
            "category":"Professional",
            "type":"Services"
        }
    ],
    "sg:phone":"+1 303 422 2222",
    "sg:postcode":"80238",
    "sg:province":"CO",
    "sg:website":"www.sedelivery.com",
    "wof:name":"SE delivery",
    "wof:placetype":"venue"
},
  "geometry": {"coordinates":[-105.067187,39.739381],"type":"Point"}
}