{
  "type": "Feature",
  "properties": {
    "iso:country":"US",
    "sg:address":"1755 S Zuni St",
    "sg:city":"Denver",
    "sg:classifiers":[
        {
            "category":"Social Services",
            "type":"Services"
        }
    ],
    "sg:phone":"+1 303 936 0469",
    "sg:postcode":"80223",
    "sg:province":"CO",
    "sg:tags":[
        "organization",
        "welfare"
    ],
    "wof:name":"Community Ministry",
    "wof:placetype":"venue"
},
  "geometry": {"coordinates":[-105.015755,39.68512],"type":"Point"}
}