{
  "type": "Feature",
  "properties": {
    "iso:country":"US",
    "sg:address":"770 W 100th Pl",
    "sg:city":"Denver",
    "sg:classifiers":[
        {
            "category":"Shopping",
            "subcategory":"Catalog Store",
            "type":"Retail Goods"
        }
    ],
    "sg:phone":"+1 303 758 1846",
    "sg:postcode":"80260",
    "sg:province":"CO",
    "sg:tags":[
        "mail",
        "house"
    ],
    "wof:name":"Pt Specialities",
    "wof:placetype":"venue"
},
  "geometry": {"coordinates":[-104.994393,39.878485],"type":"Point"}
}