{
  "type": "Feature",
  "properties": {
    "iso:country":"US",
    "sg:address":"10001 W Hampden Ave",
    "sg:city":"Denver",
    "sg:classifiers":[
        {
            "category":"Utilities",
            "type":"Services"
        }
    ],
    "sg:phone":"+1 303 980 3802",
    "sg:postcode":"80227",
    "sg:province":"CO",
    "sg:tags":[
        "other",
        "electric",
        "combined"
    ],
    "wof:name":"Kipling Office/Service Center",
    "wof:placetype":"venue"
},
  "geometry": {"coordinates":[-105.113356,39.654185],"type":"Point"}
}