{
  "type": "Feature",
  "properties": {
    "iso:country":"US",
    "sg:address":"500 E 3rd St",
    "sg:city":"Loveland",
    "sg:classifiers":[
        {
            "category":"Recreation",
            "type":"Entertainment"
        }
    ],
    "sg:phone":"+1 970 962 2727",
    "sg:postcode":"80537",
    "sg:province":"CO",
    "sg:tags":[
        "parks"
    ],
    "sg:website":"www.cityofloveland.org",
    "wof:name":"Loveland Parks & Recreation",
    "wof:placetype":"venue"
},
  "geometry": {"coordinates":[-105.07061899999999,40.394369],"type":"Point"}
}