{
  "type": "Feature",
  "properties": {
    "addr:full":"7600 E Arapahoe Rd Englewood CO 80112",
    "addr:housenumber":"7600",
    "addr:postcode":"80112",
    "addr:street":"E Arapahoe Rd",
    "iso:country":"US",
    "sg:address":"7600 E Arapahoe Rd",
    "sg:city":"Englewood",
    "sg:classifiers":[
        {
            "category":"Wholesale",
            "subcategory":"Machinery & Supplies",
            "type":"Manufacturing & Wholesale Goods"
        }
    ],
    "sg:phone":"+1 303 741 0200",
    "sg:postcode":"80112",
    "sg:province":"CO",
    "sg:tags":[
        "importing",
        "distribution",
        "industrial",
        "exporting"
    ],
    "wof:name":"Hbm Associates Inc",
    "wof:placetype":"venue"
},
  "geometry": {"coordinates":[-104.901197,39.594956],"type":"Point"}
}