{
  "type": "Feature",
  "properties": {
    "iso:country":"US",
    "sg:address":"19th & Blake Street",
    "sg:city":"Denver",
    "sg:classifiers":[
        {
            "category":"Arts & Performance",
            "subcategory":"Music",
            "type":"Entertainment"
        },
        {
            "category":"Recreation",
            "subcategory":"Dance Hall",
            "type":"Entertainment"
        }
    ],
    "sg:phone":"+1 303 800 1357",
    "sg:postcode":"80202",
    "sg:province":"CO",
    "sg:tags":[
        "club",
        "dj"
    ],
    "sg:website":"www.DenverDiscJockeys.com",
    "wof:name":"DENVER DISC JOCKEY SERVICES",
    "wof:placetype":"venue"
},
  "geometry": {"coordinates":[-104.99555100000001,39.753363],"type":"Point"}
}