{
  "type": "Feature",
  "properties": {
    "addr:full":"6860 W Airview Ave Denver CO 80232",
    "addr:housenumber":"6860",
    "addr:postcode":"80232",
    "addr:street":"W Airview Ave",
    "iso:country":"US",
    "sg:address":"6860 W Airview Ave",
    "sg:city":"Denver",
    "sg:classifiers":[
        {
            "category":"Professional",
            "subcategory":"Business Services",
            "type":"Services"
        }
    ],
    "sg:phone":"+1 720 425 9156",
    "sg:postcode":"80232",
    "sg:province":"CO",
    "sg:tags":[
        "delivery",
        "courier"
    ],
    "sg:website":"tdcouriers.com",
    "wof:name":"TD Couriers",
    "wof:placetype":"venue"
},
  "geometry": {"coordinates":[-105.073075,39.688463],"type":"Point"}
}