{
  "type": "Feature",
  "properties": {
    "addr:full":"4920 Carr St Ste B Arvada CO 80002",
    "addr:housenumber":"4920",
    "addr:postcode":"80002",
    "addr:street":"Carr St Ste B",
    "iso:country":"US",
    "sg:address":"4920 Carr St Ste B",
    "sg:city":"Arvada",
    "sg:classifiers":[
        {
            "category":"Home & Garden",
            "subcategory":"Building Materials",
            "type":"Retail Goods"
        },
        {
            "category":"Building & Trades",
            "subcategory":"Construction",
            "type":"Services"
        }
    ],
    "sg:phone":"+1 303 463 7819",
    "sg:postcode":"80002",
    "sg:province":"CO",
    "sg:tags":[
        "concrete",
        "staining",
        "contractor"
    ],
    "wof:name":"Asphalt & Concrete Pros",
    "wof:placetype":"venue"
},
  "geometry": {"coordinates":[-105.090784,39.785661],"type":"Point"}
}