{
  "type": "Feature",
  "properties": {
    "iso:country":"US",
    "sg:address":"2477 Commerce Blvd",
    "sg:city":"Grand Junction",
    "sg:classifiers":[
        {
            "category":"Building & Trades",
            "subcategory":"Construction",
            "type":"Services"
        }
    ],
    "sg:phone":"+1 970 243 9105",
    "sg:postcode":"81505",
    "sg:province":"CO",
    "sg:tags":[
        "boring",
        "drilling",
        "contractor"
    ],
    "wof:name":"B & B Drilling",
    "wof:placetype":"venue"
},
  "geometry": {"coordinates":[-108.59198600000001,39.090796],"type":"Point"}
}