{
  "type": "Feature",
  "properties": {
    "iso:country":"US",
    "sg:address":"3720 S Huron St",
    "sg:city":"Englewood",
    "sg:classifiers":[
        {
            "category":"Building & Trades",
            "subcategory":"Construction",
            "type":"Services"
        }
    ],
    "sg:phone":"+1 303 781 8649",
    "sg:postcode":"80110",
    "sg:province":"CO",
    "sg:tags":[
        "house"
    ],
    "wof:name":"Byrd Construction",
    "wof:placetype":"venue"
},
  "geometry": {"coordinates":[-104.997024,39.647954],"type":"Point"}
}