{
  "type": "Feature",
  "properties": {
    "addr:full":"300 Main St Black Hawk CO 80403",
    "addr:housenumber":"300",
    "addr:postcode":"80403",
    "addr:street":"Main St",
    "iso:country":"US",
    "sg:address":"300 Main St",
    "sg:city":"Black Hawk",
    "sg:classifiers":[
        {
            "category":"Casinos & Gambling",
            "type":"Entertainment"
        }
    ],
    "sg:phone":"+1 303 582 5600",
    "sg:postcode":"80403",
    "sg:province":"CO",
    "sg:website":"www.goldencasinogroup.com/www/co...",
    "wof:name":"Golden Mardi Gras Casino",
    "wof:placetype":"venue"
},
  "geometry": {"coordinates":[-105.48793000000001,39.798731],"type":"Point"}
}