{
  "type": "Feature",
  "properties": {
    "iso:country":"US",
    "sg:address":"1753 S Broadway",
    "sg:city":"Denver",
    "sg:classifiers":[
        {
            "category":"Real Estate",
            "subcategory":"Architect",
            "type":"Services"
        }
    ],
    "sg:phone":"+1 303 337 1067",
    "sg:postcode":"80210",
    "sg:province":"CO",
    "sg:website":"www.architecturalaccentsinc.com",
    "wof:name":"Architectural Accents",
    "wof:placetype":"venue"
},
  "geometry": {"coordinates":[-104.987723,39.684816],"type":"Point"}
}