{
  "type": "Feature",
  "properties": {
    "iso:country":"US",
    "sg:address":"1719 E 19th Ave",
    "sg:city":"Denver",
    "sg:classifiers":[
        {
            "category":"Health Services",
            "subcategory":"Clinic",
            "type":"Services"
        }
    ],
    "sg:phone":"+1 303 839 6910",
    "sg:postcode":"80218",
    "sg:province":"CO",
    "sg:tags":[
        "banks",
        "blood",
        "center"
    ],
    "wof:name":"Healthone Blood Donor Svc",
    "wof:placetype":"venue"
},
  "geometry": {"coordinates":[-104.967911,39.746145],"type":"Point"}
}