{
  "type": "Feature",
  "properties": {
    "iso:country":"US",
    "sg:address":"4655 W Kentucky Ave",
    "sg:city":"Denver",
    "sg:classifiers":[
        {
            "category":"Organizations",
            "subcategory":"Non-profit Organization",
            "type":"Services"
        }
    ],
    "sg:phone":"+1 303 936 1500",
    "sg:postcode":"80219",
    "sg:province":"CO",
    "sg:tags":[
        "charitable",
        "institution"
    ],
    "wof:name":"Cars Helping Charities Inc",
    "wof:placetype":"venue"
},
  "geometry": {"coordinates":[-105.04756500000001,39.700489],"type":"Point"}
}