{
  "type": "Feature",
  "properties": {
    "addr:full":"1400 Grape Street Denver CO 80220",
    "addr:housenumber":"1400",
    "addr:postcode":"80220",
    "addr:street":"Grape Street",
    "iso:country":"US",
    "sg:address":"1400 Grape Street",
    "sg:city":"Denver",
    "sg:classifiers":[
        {
            "category":"Social Services",
            "subcategory":"Child Care",
            "type":"Services"
        }
    ],
    "sg:phone":"+1 303 321 5437",
    "sg:postcode":"80220",
    "sg:province":"CO",
    "sg:tags":[
        "day"
    ],
    "wof:name":"Cowliks Childcare",
    "wof:placetype":"venue"
},
  "geometry": {"coordinates":[-104.924474,39.738608],"type":"Point"}
}