{
  "type": "Feature",
  "properties": {
    "addr:full":"1221 S Edinburgh Dr Loveland CO 80537",
    "addr:housenumber":"1221",
    "addr:postcode":"80537",
    "addr:street":"S Edinburgh Dr",
    "iso:country":"US",
    "sg:address":"1221 S Edinburgh Dr",
    "sg:city":"Loveland",
    "sg:classifiers":[
        {
            "category":"Freight",
            "type":"Transportation"
        }
    ],
    "sg:phone":"+1 970 669 6613",
    "sg:postcode":"80537",
    "sg:province":"CO",
    "sg:tags":[
        "operator",
        "local",
        "trucking"
    ],
    "wof:name":"Swg Trucking",
    "wof:placetype":"venue"
},
  "geometry": {"coordinates":[-105.112482,40.378377],"type":"Point"}
}