{
  "type": "Feature",
  "properties": {
    "addr:full":"9621 Brook Hill Ln Lone Tree CO 80124",
    "addr:housenumber":"9621",
    "addr:postcode":"80124",
    "addr:street":"Brook Hill Ln",
    "iso:country":"US",
    "sg:address":"9621 Brook Hill Ln",
    "sg:city":"Lone Tree",
    "sg:classifiers":[
        {
            "category":"Real Estate",
            "subcategory":"Real Estate Agent",
            "type":"Services"
        }
    ],
    "sg:phone":"+1 303 773 6575",
    "sg:postcode":"80124",
    "sg:province":"CO",
    "sg:tags":[
        "appraiser"
    ],
    "wof:name":"Premier Appraisals",
    "wof:placetype":"venue"
},
  "geometry": {"coordinates":[-104.887232,39.544418],"type":"Point"}
}