{
  "type": "Feature",
  "properties": {
    "addr:full":"2531 W 65th Place Denver CO 80221",
    "addr:housenumber":"2531",
    "addr:postcode":"80221",
    "addr:street":"W 65Th Place",
    "iso:country":"US",
    "sg:address":"2531 W 65th Place",
    "sg:city":"Denver",
    "sg:classifiers":[
        {
            "category":"Organizations",
            "subcategory":"Religious Organization",
            "type":"Services"
        }
    ],
    "sg:phone":"+1 303 429 7947",
    "sg:postcode":"80221",
    "sg:province":"CO",
    "wof:name":"Our Lady of Visitation Church",
    "wof:placetype":"venue"
},
  "geometry": {"coordinates":[-105.018531,39.815603],"type":"Point"}
}