{
  "type": "Feature",
  "properties": {
    "iso:country":"US",
    "sg:address":"6632 W 113th Ave",
    "sg:city":"Broomfield",
    "sg:classifiers":[
        {
            "category":"Building & Trades",
            "subcategory":"Construction",
            "type":"Services"
        }
    ],
    "sg:phone":"+1 303 469 2157",
    "sg:postcode":"80020",
    "sg:province":"CO",
    "sg:tags":[
        "resurfacing",
        "floor",
        "laying",
        "refinishing",
        "contractor"
    ],
    "wof:name":"Masterpiece Floors",
    "wof:placetype":"venue"
},
  "geometry": {"coordinates":[-105.070792,39.901036],"type":"Point"}
}