{
  "type": "Feature",
  "properties": {
    "iso:country":"US",
    "sg:address":"6565 S Dayton St",
    "sg:city":"Englewood",
    "sg:classifiers":[
        {
            "category":"Banks & Credit Unions",
            "subcategory":"Bank",
            "type":"Services"
        }
    ],
    "sg:phone":"+1 303 858 0400",
    "sg:postcode":"80111",
    "sg:province":"CO",
    "sg:tags":[
        "mortgage"
    ],
    "wof:name":"El Dorado Mortgage",
    "wof:placetype":"venue"
},
  "geometry": {"coordinates":[-104.87626,39.59623],"type":"Point"}
}