{
  "type": "Feature",
  "properties": {
    "iso:country":"US",
    "sg:address":"1629 Cheyenne Blvd",
    "sg:city":"Colorado Springs",
    "sg:classifiers":[
        {
            "category":"Manufacturing",
            "subcategory":"Metals",
            "type":"Manufacturing & Wholesale Goods"
        }
    ],
    "sg:phone":"+1 719 533 0075",
    "sg:postcode":"80906",
    "sg:province":"CO",
    "sg:tags":[
        "mfg",
        "tool",
        "industrial",
        "supply"
    ],
    "wof:name":"Collins Industries Intl",
    "wof:placetype":"venue"
},
  "geometry": {"coordinates":[-104.85892699999999,38.792829],"type":"Point"}
}