{
  "type": "Feature",
  "properties": {
    "addr:full":"2960 S Tejon St Englewood CO 80110",
    "addr:housenumber":"2960",
    "addr:postcode":"80110",
    "addr:street":"S Tejon St",
    "iso:country":"US",
    "sg:address":"2960 S Tejon St",
    "sg:city":"Englewood",
    "sg:classifiers":[
        {
            "category":"Retail",
            "subcategory":"Auto Repair",
            "type":"Services"
        }
    ],
    "sg:phone":"+1 303 288 7377",
    "sg:postcode":"80110",
    "sg:province":"CO",
    "sg:tags":[
        "transmission"
    ],
    "wof:name":"Performance Transmission",
    "wof:placetype":"venue"
},
  "geometry": {"coordinates":[-105.011014,39.663449],"type":"Point"}
}