{
  "type": "Feature",
  "properties": {
    "iso:country":"US",
    "sg:address":"704 Darren Ct",
    "sg:city":"Fort Collins",
    "sg:classifiers":[
        {
            "category":"Organizations",
            "subcategory":"Professional Association",
            "type":"Services"
        }
    ],
    "sg:phone":"+1 970 482 7948",
    "sg:postcode":"80524",
    "sg:province":"CO",
    "wof:name":"Countryside Homeowners Assn",
    "wof:placetype":"venue"
},
  "geometry": {"coordinates":[-105.029101,40.577642],"type":"Point"}
}