{
  "type": "Feature",
  "properties": {
    "addr:full":"151 Co Rd 27 Brighton CO 80603",
    "addr:housenumber":"151;27",
    "addr:postcode":"80603",
    "addr:street":"Co Rd",
    "iso:country":"US",
    "sg:address":"151 Co Rd 27",
    "sg:city":"Brighton",
    "sg:classifiers":[
        {
            "category":"Shopping",
            "subcategory":"Gifts & Souvenirs",
            "type":"Retail Goods"
        }
    ],
    "sg:phone":"+1 303 654 9935",
    "sg:postcode":"80603",
    "sg:province":"CO",
    "sg:tags":[
        "collectible"
    ],
    "wof:name":"Kay's Treasurers",
    "wof:placetype":"venue"
},
  "geometry": {"coordinates":[-104.815968,40.003061],"type":"Point"}
}