{
  "type": "Feature",
  "properties": {
    "iso:country":"US",
    "sg:address":"7000 S Yosemite St",
    "sg:city":"Centennial",
    "sg:classifiers":[
        {
            "category":"Real Estate",
            "subcategory":"Real Estate Agent",
            "type":"Services"
        }
    ],
    "sg:phone":"+1 303 224 0004",
    "sg:postcode":"80112",
    "sg:province":"CO",
    "sg:tags":[
        "management"
    ],
    "sg:website":"www.pcms.net",
    "wof:name":"PCMS",
    "wof:placetype":"venue"
},
  "geometry": {"coordinates":[-104.88538800000001,39.589807],"type":"Point"}
}