{
  "type": "Feature",
  "properties": {
    "addr:full":"1550 S Monroe St Denver CO 80210",
    "addr:housenumber":"1550",
    "addr:postcode":"80210",
    "addr:street":"S Monroe St",
    "iso:country":"US",
    "sg:address":"1550 S Monroe St",
    "sg:city":"Denver",
    "sg:classifiers":[
        {
            "category":"Shopping",
            "subcategory":"Beauty & Cosmetics",
            "type":"Retail Goods"
        }
    ],
    "sg:phone":"+1 303 759 9325",
    "sg:postcode":"80210",
    "sg:province":"CO",
    "sg:tags":[
        "woman",
        "health",
        "cream"
    ],
    "wof:name":"Women Helping Women",
    "wof:placetype":"venue"
},
  "geometry": {"coordinates":[-104.945283,39.688426],"type":"Point"}
}