{
  "type": "Feature",
  "properties": {
    "addr:full":"2561 S Shields St Fort Collins CO 80526",
    "addr:housenumber":"2561",
    "addr:postcode":"80526",
    "addr:street":"S Shields St",
    "iso:country":"US",
    "sg:address":"2561 S Shields St",
    "sg:city":"Fort Collins",
    "sg:classifiers":[
        {
            "category":"Personal",
            "subcategory":"Beauty Salon",
            "type":"Services"
        }
    ],
    "sg:phone":"+1 970 226 1673",
    "sg:postcode":"80526",
    "sg:province":"CO",
    "wof:name":"D F Goodhair",
    "wof:placetype":"venue"
},
  "geometry": {"coordinates":[-105.096172,40.555063],"type":"Point"}
}