{
  "type": "Feature",
  "properties": {
    "addr:full":"725 Grand Ave Glenwood Springs CO 81601",
    "addr:housenumber":"725",
    "addr:postcode":"81601",
    "addr:street":"Grand Ave",
    "iso:country":"US",
    "sg:address":"725 Grand Ave",
    "sg:city":"Glenwood Springs",
    "sg:classifiers":[
        {
            "category":"Food & Beverages",
            "subcategory":"Bakery",
            "type":"Retail Goods"
        }
    ],
    "sg:phone":"+1 970 928 8804",
    "sg:postcode":"81601",
    "sg:province":"CO",
    "sg:tags":[
        "bagel"
    ],
    "sg:website":"www.sacredgrounds.biz",
    "wof:name":"Sacred Grounds",
    "wof:placetype":"venue"
},
  "geometry": {"coordinates":[-107.32478,39.547385],"type":"Point"}
}