{
  "type": "Feature",
  "properties": {
    "addr:full":"8795 Ralston Rd Arvada CO 80002",
    "addr:housenumber":"8795",
    "addr:postcode":"80002",
    "addr:street":"Ralston Rd",
    "iso:country":"US",
    "sg:address":"8795 Ralston Rd",
    "sg:city":"Arvada",
    "sg:classifiers":[
        {
            "category":"Organizations",
            "subcategory":"Non-profit Organization",
            "type":"Services"
        }
    ],
    "sg:phone":"+1 303 420 1007",
    "sg:postcode":"80002",
    "sg:province":"CO",
    "sg:tags":[
        "information",
        "alcoholism",
        "treatment"
    ],
    "wof:name":"Family Violence Program",
    "wof:placetype":"venue"
},
  "geometry": {"coordinates":[-105.09472599999999,39.802127],"type":"Point"}
}