{
  "type": "Feature",
  "properties": {
    "addr:full":"3444 S Emerson St Englewood CO 80113",
    "addr:housenumber":"3444",
    "addr:postcode":"80113",
    "addr:street":"S Emerson St",
    "iso:country":"US",
    "sg:address":"3444 S Emerson St",
    "sg:city":"Englewood",
    "sg:classifiers":[
        {
            "category":"Social Services",
            "type":"Services"
        }
    ],
    "sg:phone":"+1 303 789 1519",
    "sg:postcode":"80113",
    "sg:province":"CO",
    "wof:name":"Health One",
    "wof:placetype":"venue"
},
  "geometry": {"coordinates":[-104.976969,39.653958],"type":"Point"}
}