{
  "type": "Feature",
  "properties": {
    "iso:country":"US",
    "sg:address":"160 W Fillmore St",
    "sg:city":"Colorado Springs",
    "sg:classifiers":[
        {
            "category":"Health Services",
            "subcategory":"Doctor",
            "type":"Services"
        }
    ],
    "sg:phone":"+1 719 635 1190",
    "sg:postcode":"80907",
    "sg:province":"CO",
    "sg:tags":[
        "physician",
        "surgeon"
    ],
    "wof:name":"H J Arnold MD",
    "wof:placetype":"venue"
},
  "geometry": {"coordinates":[-104.825457,38.874817],"type":"Point"}
}