{
  "type": "Feature",
  "properties": {
    "addr:full":"600 Steamboat Blvd Steamboat Spgs CO 80487",
    "addr:housenumber":"600",
    "addr:postcode":"80487",
    "addr:street":"Steamboat Blvd;Spgs",
    "iso:country":"US",
    "sg:address":"600 Steamboat Blvd",
    "sg:city":"Steamboat Spgs",
    "sg:classifiers":[
        {
            "category":"Real Estate",
            "subcategory":"Architect",
            "type":"Services"
        }
    ],
    "sg:phone":"+1 970 879 4831",
    "sg:postcode":"80487",
    "sg:province":"CO",
    "wof:name":"Frey Construction",
    "wof:placetype":"venue"
},
  "geometry": {"coordinates":[-106.79333699999999,40.474731],"type":"Point"}
}