{
  "type": "Feature",
  "properties": {
    "addr:full":"1628 Pearl St Boulder CO 80302",
    "addr:housenumber":"1628",
    "addr:postcode":"80302",
    "addr:street":"Pearl St",
    "iso:country":"US",
    "sg:address":"1628 Pearl St",
    "sg:city":"Boulder",
    "sg:classifiers":[
        {
            "category":"Restaurant",
            "type":"Food & Drink"
        }
    ],
    "sg:menulink":"http://www.allmenus.com/co/boulder/44859-moongate-asian-bistro/menu/",
    "sg:phone":"+1 720 406 8888",
    "sg:postcode":"80302",
    "sg:province":"CO",
    "sg:tags":[
        "japanese",
        "asian"
    ],
    "wof:name":"Moongate Asian Bistro",
    "wof:placetype":"venue"
},
  "geometry": {"coordinates":[-105.274331,40.019044],"type":"Point"}
}