{
  "type": "Feature",
  "properties": {
    "iso:country":"US",
    "sg:address":"7450 W 52nd Ave",
    "sg:city":"Arvada",
    "sg:phone":"+1 303 232 3241",
    "sg:postcode":"80002",
    "sg:province":"CO",
    "sg:website":"http://www.easy-tapper.com",
    "wof:name":"Easy Tapper",
    "wof:placetype":"venue"
},
  "geometry": {"coordinates":[-105.078549,39.791051],"type":"Point"}
}