{
  "type": "Feature",
  "properties": {
    "addr:full":"1444 Elizabeth St Denver CO 80206",
    "addr:housenumber":"1444",
    "addr:postcode":"80206",
    "addr:street":"Elizabeth St",
    "iso:country":"US",
    "sg:address":"1444 Elizabeth St",
    "sg:city":"Denver",
    "sg:classifiers":[
        {
            "category":"Education",
            "subcategory":"Music School",
            "type":"Public Place"
        },
        {
            "category":"Arts & Performance",
            "subcategory":"Arts Center",
            "type":"Entertainment"
        }
    ],
    "sg:phone":"+1 303 333 0464",
    "sg:postcode":"80206",
    "sg:province":"CO",
    "sg:tags":[
        "instrument",
        "musical",
        "teacher"
    ],
    "sg:website":"www.chpschool.com",
    "wof:name":"Capitol Hill Piano School",
    "wof:placetype":"venue"
},
  "geometry": {"coordinates":[-104.956261,39.739266],"type":"Point"}
}