{
  "type": "Feature",
  "properties": {
    "addr:full":"2021 W Colorado Ave Colorado Springs CO 80904",
    "addr:housenumber":"2021",
    "addr:postcode":"80904",
    "addr:street":"W Colorado Ave",
    "iso:country":"US",
    "sg:address":"2021 W Colorado Ave",
    "sg:city":"Colorado Springs",
    "sg:classifiers":[
        {
            "category":"Banks & Credit Unions",
            "subcategory":"Investment Brokerage",
            "type":"Services"
        }
    ],
    "sg:phone":"+1 719 471 4774",
    "sg:postcode":"80904",
    "sg:province":"CO",
    "sg:tags":[
        "consultant",
        "planning",
        "financial"
    ],
    "wof:name":"Paulette J Hubbard Cfp",
    "wof:placetype":"venue"
},
  "geometry": {"coordinates":[-104.856427,38.843298],"type":"Point"}
}