{
  "type": "Feature",
  "properties": {
    "iso:country":"US",
    "sg:address":"3141 S Santa Fe Dr",
    "sg:city":"Englewood",
    "sg:classifiers":[
        {
            "category":"Real Estate",
            "subcategory":"Developer",
            "type":"Services"
        }
    ],
    "sg:phone":"+1 303 762 6090",
    "sg:postcode":"80110",
    "sg:province":"CO",
    "sg:tags":[
        "mobile",
        "home"
    ],
    "wof:name":"Elm Trailer Park",
    "wof:placetype":"venue"
},
  "geometry": {"coordinates":[-104.999636,39.65856],"type":"Point"}
}