{
  "type": "Feature",
  "properties": {
    "addr:full":"2301 S Broadway Denver CO 80210",
    "addr:housenumber":"2301",
    "addr:postcode":"80210",
    "addr:street":"S Broadway",
    "iso:country":"US",
    "sg:address":"2301 S Broadway",
    "sg:city":"Denver",
    "sg:classifiers":[
        {
            "category":"Bars & Pubs",
            "type":"Food & Drink"
        }
    ],
    "sg:phone":"+1 303 722 6484",
    "sg:postcode":"80210",
    "sg:province":"CO",
    "sg:tags":[
        "drinking"
    ],
    "wof:name":"Len & Bill's Lounge",
    "wof:placetype":"venue"
},
  "geometry": {"coordinates":[-104.98758100000001,39.673087],"type":"Point"}
}