{
  "type": "Feature",
  "properties": {
    "iso:country":"US",
    "sg:address":"15320 E Iliff Ave",
    "sg:city":"Aurora",
    "sg:classifiers":[
        {
            "category":"Autos & Motor Vehicles",
            "subcategory":"Auto Supplies",
            "type":"Retail Goods"
        },
        {
            "category":"Retail",
            "subcategory":"Auto Repair",
            "type":"Services"
        }
    ],
    "sg:phone":"+1 303 337 9631",
    "sg:postcode":"80013",
    "sg:province":"CO",
    "sg:tags":[
        "wheel",
        "oil",
        "tire",
        "retread",
        "lube",
        "balancing",
        "wheels-aligning",
        "recap",
        "brake"
    ],
    "sg:website":"http://www.bigotires.com",
    "wof:name":"Big O Tires",
    "wof:placetype":"venue"
},
  "geometry": {"coordinates":[-104.809415,39.674881],"type":"Point"}
}