{
  "type": "Feature",
  "properties": {
    "addr:full":"8321 S Sangre De Cristo Rd  Suite 302 Littleton CO 80127",
    "addr:housenumber":"8321",
    "addr:postcode":"80127",
    "addr:street":"S Sangre De Cristo Rd Suite 302",
    "iso:country":"US",
    "sg:address":"8321 S Sangre De Cristo Rd  Suite 302",
    "sg:city":"Littleton",
    "sg:classifiers":[
        {
            "category":"Professional",
            "subcategory":"Computer Services",
            "type":"Services"
        }
    ],
    "sg:phone":"+1 303 679 6161",
    "sg:postcode":"80127",
    "sg:province":"CO",
    "sg:website":"http://iphase3.com/",
    "wof:name":"iPhase3",
    "wof:placetype":"venue"
},
  "geometry": {"coordinates":[-105.113676,39.568753],"type":"Point"}
}