{
  "type": "Feature",
  "properties": {
    "addr:full":"14172 Summit Dr Sterling CO 80751",
    "addr:housenumber":"14172",
    "addr:postcode":"80751",
    "addr:street":"Summit Dr",
    "iso:country":"US",
    "sg:address":"14172 Summit Dr",
    "sg:city":"Sterling",
    "sg:classifiers":[
        {
            "category":"Insurance",
            "subcategory":"Insurance Agent",
            "type":"Services"
        }
    ],
    "sg:phone":"+1 970 522 0510",
    "sg:postcode":"80751",
    "sg:province":"CO",
    "sg:tags":[
        "adjuster"
    ],
    "wof:name":"Frontier Adjusters America Inc",
    "wof:placetype":"venue"
},
  "geometry": {"coordinates":[-103.236602,40.643805],"type":"Point"}
}