{
  "type": "Feature",
  "properties": {
    "addr:full":"2417 N Elizabeth St Pueblo CO 81003",
    "addr:housenumber":"2417",
    "addr:postcode":"81003",
    "addr:street":"N Elizabeth St",
    "iso:country":"US",
    "sg:address":"2417 N Elizabeth St",
    "sg:city":"Pueblo",
    "sg:classifiers":[
        {
            "category":"Wholesale",
            "subcategory":"Stationery",
            "type":"Manufacturing & Wholesale Goods"
        }
    ],
    "sg:phone":"+1 719 543 0408",
    "sg:postcode":"81003",
    "sg:province":"CO",
    "sg:tags":[
        "product",
        "industrial",
        "art",
        "supply",
        "graphic",
        "paper"
    ],
    "wof:name":"Bd Associates Ltd",
    "wof:placetype":"venue"
},
  "geometry": {"coordinates":[-104.615106,38.292273],"type":"Point"}
}