{
  "type": "Feature",
  "properties": {
    "addr:full":"326 E 8th Ave Longmont CO 80501",
    "addr:housenumber":"326",
    "addr:postcode":"80501",
    "addr:street":"E 8Th Ave",
    "iso:country":"US",
    "sg:address":"326 E 8th Ave",
    "sg:city":"Longmont",
    "sg:classifiers":[
        {
            "category":"Building & Trades",
            "subcategory":"Construction",
            "type":"Services"
        }
    ],
    "sg:phone":"+1 303 678 1386",
    "sg:postcode":"80501",
    "sg:province":"CO",
    "sg:tags":[
        "core",
        "cutting",
        "drilling"
    ],
    "wof:name":"B T Farris Drilling LLC",
    "wof:placetype":"venue"
},
  "geometry": {"coordinates":[-105.08404400000001,40.172059],"type":"Point"}
}