{
  "type": "Feature",
  "properties": {
    "iso:country":"US",
    "sg:address":"326 E 8th Ave",
    "sg:city":"Longmont",
    "sg:classifiers":[
        {
            "category":"Building & Trades",
            "subcategory":"Construction",
            "type":"Services"
        }
    ],
    "sg:phone":"+1 303 678 1386",
    "sg:postcode":"80501",
    "sg:province":"CO",
    "sg:tags":[
        "core",
        "cutting",
        "drilling"
    ],
    "wof:name":"B T Farris Drilling LLC",
    "wof:placetype":"venue"
},
  "geometry": {"coordinates":[-105.084044,40.172059],"type":"Point"}
}