{
  "type": "Feature",
  "properties": {
    "addr:full":"1721 San Pedro Ave Trinidad CO 81082",
    "addr:housenumber":"1721",
    "addr:postcode":"81082",
    "addr:street":"San Pedro Ave",
    "iso:country":"US",
    "sg:address":"1721 San Pedro Ave",
    "sg:city":"Trinidad",
    "sg:classifiers":[
        {
            "category":"Building & Trades",
            "subcategory":"Construction",
            "type":"Services"
        }
    ],
    "sg:phone":"+1 719 846 0699",
    "sg:postcode":"81082",
    "sg:province":"CO",
    "sg:tags":[
        "hanging",
        "contractor"
    ],
    "wof:name":"Sabol Home Painting Service",
    "wof:placetype":"venue"
},
  "geometry": {"coordinates":[-104.50779900000001,37.185006],"type":"Point"}
}