{
  "type": "Feature",
  "properties": {
    "iso:country":"US",
    "sg:address":"1560 S Broadway",
    "sg:city":"Denver",
    "sg:classifiers":[
        {
            "category":"Home & Garden",
            "subcategory":"Furniture",
            "type":"Retail Goods"
        }
    ],
    "sg:phone":"+1 303 744 3000",
    "sg:postcode":"80210",
    "sg:province":"CO",
    "sg:tags":[
        "equipment",
        "kitchen",
        "cabinet"
    ],
    "wof:name":"Integria Inc",
    "wof:placetype":"venue"
},
  "geometry": {"coordinates":[-104.987431,39.688691],"type":"Point"}
}