{
  "type": "Feature",
  "properties": {
    "iso:country":"US",
    "sg:address":"1501 Wynkoop St",
    "sg:city":"Denver",
    "sg:classifiers":[
        {
            "category":"Professional",
            "subcategory":"Business Services",
            "type":"Services"
        }
    ],
    "sg:phone":"+1 303 454 4046",
    "sg:postcode":"80202",
    "sg:province":"CO",
    "wof:name":"US Post Office",
    "wof:placetype":"venue"
},
  "geometry": {"coordinates":[-105.000919,39.751906],"type":"Point"}
}