{
  "type": "Feature",
  "properties": {
    "iso:country":"US",
    "sg:address":"5300 5300 Rd",
    "sg:city":"Olathe",
    "sg:classifiers":[
        {
            "category":"Farming",
            "subcategory":"Livestock Farm",
            "type":"Manufacturing & Wholesale Goods"
        }
    ],
    "sg:phone":"+1 970 323 6479",
    "sg:postcode":"81425",
    "sg:province":"CO",
    "sg:tags":[
        "beef",
        "feedlot",
        "cattle"
    ],
    "wof:name":"Richard Dickerson",
    "wof:placetype":"venue"
},
  "geometry": {"coordinates":[-108.096282,38.615623],"type":"Point"}
}