{
  "type": "Feature",
  "properties": {
    "iso:country":"US",
    "sg:address":"1129 10th St",
    "sg:city":"Greeley",
    "sg:classifiers":[
        {
            "category":"Professional",
            "subcategory":"Lawyer & Legal Services",
            "type":"Services"
        }
    ],
    "sg:phone":"+1 970 352 4776",
    "sg:postcode":"80631",
    "sg:province":"CO",
    "sg:tags":[
        "attorney"
    ],
    "wof:name":"Sherry Rawlings Law Office",
    "wof:placetype":"venue"
},
  "geometry": {"coordinates":[-104.69765099999999,40.422658],"type":"Point"}
}