{
  "type": "Feature",
  "properties": {
    "iso:country":"US",
    "sg:address":"11723 Xavier Ct",
    "sg:city":"Westminster",
    "sg:classifiers":[
        {
            "category":"Building & Trades",
            "subcategory":"Plumbing",
            "type":"Services"
        }
    ],
    "sg:phone":"+1 303 422 3580",
    "sg:postcode":"80031",
    "sg:province":"CO",
    "sg:tags":[
        "contractor"
    ],
    "wof:name":"Faehnrich Fire Protection Inc",
    "wof:placetype":"venue"
},
  "geometry": {"coordinates":[-105.050133,39.910042],"type":"Point"}
}