{
  "type": "Feature",
  "properties": {
    "iso:country":"US",
    "sg:address":"5280 Garfield Ave",
    "sg:city":"Loveland",
    "sg:classifiers":[
        {
            "category":"Manufacturing",
            "subcategory":"Signs",
            "type":"Manufacturing & Wholesale Goods"
        }
    ],
    "sg:phone":"+1 970 663 5464",
    "sg:postcode":"80538",
    "sg:province":"CO",
    "wof:name":"Autographics",
    "wof:placetype":"venue"
},
  "geometry": {"coordinates":[-105.07732900000001,40.445491],"type":"Point"}
}