{
  "type": "Feature",
  "properties": {
    "iso:country":"US",
    "sg:address":"1488 Wazee St",
    "sg:city":"Denver",
    "sg:classifiers":[
        {
            "category":"Real Estate",
            "subcategory":"Developer",
            "type":"Services"
        }
    ],
    "sg:phone":"+1 303 534 6620",
    "sg:postcode":"80202",
    "sg:province":"CO",
    "wof:name":"Citiventure Assoc",
    "wof:placetype":"venue"
},
  "geometry": {"coordinates":[-105.002208,39.749372],"type":"Point"}
}