{
  "type": "Feature",
  "properties": {
    "addr:full":"8931 Hunter Way Westminster CO 80031",
    "addr:housenumber":"8931",
    "addr:postcode":"80031",
    "addr:street":"Hunter Way",
    "iso:country":"US",
    "sg:address":"8931 Hunter Way",
    "sg:city":"Westminster",
    "sg:classifiers":[
        {
            "category":"Professional",
            "type":"Services"
        }
    ],
    "sg:phone":"+1 303 427 5549",
    "sg:postcode":"80031",
    "sg:province":"CO",
    "wof:name":"Westminster Area Cmnty Awrness",
    "wof:placetype":"venue"
},
  "geometry": {"coordinates":[-105.029743,39.857059],"type":"Point"}
}