{
  "type": "Feature",
  "properties": {
    "iso:country":"US",
    "sg:address":"1100 Goeglein Gulch",
    "sg:city":"Durango",
    "sg:classifiers":[
        {
            "category":"Building & Trades",
            "subcategory":"Construction",
            "type":"Services"
        }
    ],
    "sg:phone":"+1 970 903 8340",
    "sg:postcode":"81301",
    "sg:province":"CO",
    "sg:tags":[
        "residential"
    ],
    "wof:name":"Stewart Construction",
    "wof:placetype":"venue"
},
  "geometry": {"coordinates":[-107.85908499999999,37.279833],"type":"Point"}
}