{
  "type": "Feature",
  "properties": {
    "addr:full":"28 Dreher Dr Evergreen CO 80439",
    "addr:housenumber":"28",
    "addr:postcode":"80439",
    "addr:street":"Dreher Dr",
    "iso:country":"US",
    "sg:address":"28 Dreher Dr",
    "sg:city":"Evergreen",
    "sg:classifiers":[
        {
            "category":"Professional",
            "subcategory":"Secretarial Services",
            "type":"Services"
        }
    ],
    "sg:phone":"+1 303 670 4773",
    "sg:postcode":"80439",
    "sg:province":"CO",
    "sg:tags":[
        "processing",
        "word"
    ],
    "wof:name":"Aspen Leaf Publishing",
    "wof:placetype":"venue"
},
  "geometry": {"coordinates":[-105.413214,39.63916],"type":"Point"}
}