{
  "type": "Feature",
  "properties": {
    "iso:country":"US",
    "sg:address":"823 S Perry St",
    "sg:city":"Castle Rock",
    "sg:classifiers":[
        {
            "category":"Health Services",
            "subcategory":"Clinic",
            "type":"Services"
        }
    ],
    "sg:phone":"+1 303 539 0407",
    "sg:postcode":"80104",
    "sg:province":"CO",
    "wof:name":"Quantum Health Accounting",
    "wof:placetype":"venue"
},
  "geometry": {"coordinates":[-104.86148300000001,39.364545],"type":"Point"}
}