{
  "type": "Feature",
  "properties": {
    "iso:country":"US",
    "sg:address":"210 E Hyman Ave",
    "sg:city":"Aspen",
    "sg:classifiers":[
        {
            "category":"Real Estate",
            "subcategory":"Real Estate Agent",
            "type":"Services"
        }
    ],
    "sg:phone":"+1 970 544 3771",
    "sg:postcode":"81611",
    "sg:province":"CO",
    "sg:website":"www.whitmanfineproperties.com",
    "wof:name":"Whitman Fine Properties",
    "wof:placetype":"venue"
},
  "geometry": {"coordinates":[-106.822018,39.18961],"type":"Point"}
}