{
  "type": "Feature",
  "properties": {
    "iso:country":"US",
    "sg:address":"1155 Kelly Johnson Blvd",
    "sg:city":"Colorado Springs",
    "sg:classifiers":[
        {
            "category":"Professional",
            "subcategory":"Computer Services",
            "type":"Services"
        }
    ],
    "sg:phone":"+1 719 488 0707",
    "sg:postcode":"80920",
    "sg:province":"CO",
    "sg:tags":[
        "design",
        "system"
    ],
    "wof:name":"Chronotech International Inc",
    "wof:placetype":"venue"
},
  "geometry": {"coordinates":[-104.8053,38.945258],"type":"Point"}
}