{
  "type": "Feature",
  "properties": {
    "iso:country":"US",
    "sg:address":"300 Sunlight Dr",
    "sg:city":"Carbondale",
    "sg:classifiers":[
        {
            "category":"Restaurant",
            "type":"Food & Drink"
        }
    ],
    "sg:phone":"+1 970 963 0192",
    "sg:postcode":"81623",
    "sg:province":"CO",
    "sg:tags":[
        "eating"
    ],
    "wof:name":"Roaring Fork Cuisine",
    "wof:placetype":"venue"
},
  "geometry": {"coordinates":[-107.12549,39.441802],"type":"Point"}
}