{
  "type": "Feature",
  "properties": {
    "addr:full":"738 42nd St SW Loveland CO 80537",
    "addr:housenumber":"738",
    "addr:postcode":"80537",
    "addr:street":"42Nd St Sw",
    "iso:country":"US",
    "sg:address":"738 42nd St SW",
    "sg:city":"Loveland",
    "sg:classifiers":[
        {
            "category":"Building & Trades",
            "subcategory":"Construction",
            "type":"Services"
        }
    ],
    "sg:phone":"+1 970 278 0864",
    "sg:postcode":"80537",
    "sg:province":"CO",
    "sg:tags":[
        "excavation",
        "contractor"
    ],
    "wof:name":"Mighty Mini Excavating",
    "wof:placetype":"venue"
},
  "geometry": {"coordinates":[-105.089181,40.349359],"type":"Point"}
}