{
  "type": "Feature",
  "properties": {
    "addr:full":"15712 W 70th Dr Arvada CO 80007",
    "addr:housenumber":"15712",
    "addr:postcode":"80007",
    "addr:street":"W 70Th Dr",
    "iso:country":"US",
    "sg:address":"15712 W 70th Dr",
    "sg:city":"Arvada",
    "sg:classifiers":[
        {
            "category":"Wholesale",
            "subcategory":"Beer",
            "type":"Manufacturing & Wholesale Goods"
        }
    ],
    "sg:phone":"+1 303 463 1806",
    "sg:postcode":"80007",
    "sg:province":"CO",
    "sg:tags":[
        "importer",
        "wine"
    ],
    "wof:name":"Vintage Sellers LLC",
    "wof:placetype":"venue"
},
  "geometry": {"coordinates":[-105.175335,39.825023],"type":"Point"}
}