{
  "type": "Feature",
  "properties": {
    "iso:country":"US",
    "sg:address":"4364 S Ceylon Way",
    "sg:city":"Aurora",
    "sg:classifiers":[
        {
            "category":"Building & Trades",
            "subcategory":"Construction",
            "type":"Services"
        }
    ],
    "sg:phone":"+1 303 766 0186",
    "sg:postcode":"80015",
    "sg:province":"CO",
    "sg:tags":[
        "contractor"
    ],
    "wof:name":"Akw Family Roofing Inc",
    "wof:placetype":"venue"
},
  "geometry": {"coordinates":[-104.76387,39.637309],"type":"Point"}
}