{
  "type": "Feature",
  "properties": {
    "addr:full":"5849 Pierce St Arvada CO 80003",
    "addr:housenumber":"5849",
    "addr:postcode":"80003",
    "addr:street":"Pierce St",
    "iso:country":"US",
    "sg:address":"5849 Pierce St",
    "sg:city":"Arvada",
    "sg:classifiers":[
        {
            "category":"Professional",
            "type":"Services"
        }
    ],
    "sg:phone":"+1 720 837 3633",
    "sg:postcode":"80003",
    "sg:province":"CO",
    "wof:name":"Denise Miller Training",
    "wof:placetype":"venue"
},
  "geometry": {"coordinates":[-105.072457,39.80396],"type":"Point"}
}