{
  "type": "Feature",
  "properties": {
    "addr:full":"6821 Ammons St Arvada CO 80004",
    "addr:housenumber":"6821",
    "addr:postcode":"80004",
    "addr:street":"Ammons St",
    "iso:country":"US",
    "sg:address":"6821 Ammons St",
    "sg:city":"Arvada",
    "sg:classifiers":[
        {
            "category":"Professional",
            "type":"Services"
        }
    ],
    "sg:phone":"+1 303 421 8788",
    "sg:postcode":"80004",
    "sg:province":"CO",
    "wof:name":"James W Pooley",
    "wof:placetype":"venue"
},
  "geometry": {"coordinates":[-105.08672,39.821591],"type":"Point"}
}