{
  "type": "Feature",
  "properties": {
    "addr:full":"302 W San Juan Ave Telluride CO 81435",
    "addr:housenumber":"302",
    "addr:postcode":"81435",
    "addr:street":"W San Juan Ave",
    "iso:country":"US",
    "sg:address":"302 W San Juan Ave",
    "sg:city":"Telluride",
    "sg:classifiers":[
        {
            "category":"Recreation",
            "type":"Entertainment"
        }
    ],
    "sg:phone":"+1 970 728 3134",
    "sg:postcode":"81435",
    "sg:province":"CO",
    "sg:tags":[
        "equipment",
        "skiing"
    ],
    "wof:name":"Telluride Sports Oak Street",
    "wof:placetype":"venue"
},
  "geometry": {"coordinates":[-107.8143,37.936334],"type":"Point"}
}