{
  "type": "Feature",
  "properties": {
    "addr:full":"200 Linden St Fort Collins CO 80524",
    "addr:housenumber":"200",
    "addr:postcode":"80524",
    "addr:street":"Linden St",
    "iso:country":"US",
    "sg:address":"200 Linden St",
    "sg:city":"Fort Collins",
    "sg:classifiers":[
        {
            "category":"Shopping",
            "subcategory":"Clothing, Apparel, & Fashions",
            "type":"Retail Goods"
        }
    ],
    "sg:phone":"+1 970 484 6932",
    "sg:postcode":"80524",
    "sg:province":"CO",
    "sg:tags":[
        "sporting"
    ],
    "wof:name":"Wright Life Inc",
    "wof:placetype":"venue"
},
  "geometry": {"coordinates":[-105.074747,40.588536],"type":"Point"}
}