{
  "type": "Feature",
  "properties": {
    "iso:country":"US",
    "sg:address":"2106 Access Rd",
    "sg:city":"Rifle",
    "sg:classifiers":[
        {
            "category":"Professional",
            "subcategory":"Employment Agencies",
            "type":"Services"
        }
    ],
    "sg:phone":"+1 970 625 2600",
    "sg:postcode":"81650",
    "sg:province":"CO",
    "sg:tags":[
        "opportunity"
    ],
    "sg:website":"www.sosstaffing.com",
    "wof:name":"SOS Staffing Svc",
    "wof:placetype":"venue"
},
  "geometry": {"coordinates":[-107.809121,39.528137],"type":"Point"}
}