{
  "type": "Feature",
  "properties": {
    "addr:full":"113 S Main St La Veta CO 81055",
    "addr:housenumber":"113",
    "addr:postcode":"veta;81055",
    "addr:street":"S Main St",
    "iso:country":"US",
    "sg:address":"113 S Main St",
    "sg:city":"La Veta",
    "sg:classifiers":[
        {
            "category":"Government",
            "subcategory":"Office",
            "type":"Public Place"
        }
    ],
    "sg:phone":"+1 719 742 3655",
    "sg:postcode":"81055",
    "sg:province":"CO",
    "sg:tags":[
        "village"
    ],
    "wof:name":"Maintenance Shop",
    "wof:placetype":"venue"
},
  "geometry": {"coordinates":[-105.00908200000001,37.510287],"type":"Point"}
}