{
  "type": "Feature",
  "properties": {
    "addr:full":"4905 Olive St Commerce City CO 80022",
    "addr:housenumber":"4905",
    "addr:postcode":"80022",
    "addr:street":"Olive St",
    "iso:country":"US",
    "sg:address":"4905 Olive St",
    "sg:city":"Commerce City",
    "sg:classifiers":[
        {
            "category":"Professional",
            "type":"Services"
        }
    ],
    "sg:phone":"+1 303 853 8091",
    "sg:postcode":"80022",
    "sg:province":"CO",
    "wof:name":"Truck Corral",
    "wof:placetype":"venue"
},
  "geometry": {"coordinates":[-104.906997,39.787369],"type":"Point"}
}