{
  "type": "Feature",
  "properties": {
    "iso:country":"US",
    "sg:address":"1555 Stuart Street",
    "sg:city":"Denver",
    "sg:classifiers":[
        {
            "category":"Education",
            "subcategory":"School",
            "type":"Public Place"
        }
    ],
    "sg:phone":"+1 303 629 8200",
    "sg:postcode":"80204",
    "sg:province":"CO",
    "wof:name":"Yeshiva Toras Chaim",
    "wof:placetype":"venue"
},
  "geometry": {"coordinates":[-105.04294,39.742332],"type":"Point"}
}