{
  "type": "Feature",
  "properties": {
    "iso:country":"US",
    "sg:address":"1951 Yellowstone Rd",
    "sg:city":"Rock Springs",
    "sg:classifiers":[
        {
            "category":"Utilities",
            "subcategory":"Natural Gas",
            "type":"Services"
        }
    ],
    "sg:phone":"+1 307 382 6787",
    "sg:postcode":"82901",
    "sg:province":"CO",
    "sg:tags":[
        "transmission",
        "distributor"
    ],
    "wof:name":"Colorado Interstate Gas Co",
    "wof:placetype":"venue"
},
  "geometry": {"coordinates":[-109.256112,41.646645],"type":"Point"}
}