{
  "type": "Feature",
  "properties": {
    "addr:full":"1321 Hawk Ridge Ln Snowmass Village CO 81615",
    "addr:housenumber":"1321",
    "addr:postcode":"81615",
    "addr:street":"Hawk Ridge Ln",
    "iso:country":"US",
    "sg:address":"1321 Hawk Ridge Ln",
    "sg:city":"Snowmass Village",
    "sg:classifiers":[
        {
            "category":"Personal",
            "subcategory":"Beauty Salon",
            "type":"Services"
        }
    ],
    "sg:phone":"+1 970 923 3704",
    "sg:postcode":"81615",
    "sg:province":"CO",
    "sg:tags":[
        "aromatherapy"
    ],
    "wof:name":"Alma Del Sol Aromatherapy",
    "wof:placetype":"venue"
},
  "geometry": {"coordinates":[-106.954847,39.210889],"type":"Point"}
}