{
  "type": "Feature",
  "properties": {
    "addr:full":"1100 Main St Fort Morgan CO 80701",
    "addr:housenumber":"1100",
    "addr:postcode":"80701",
    "addr:street":"Main St",
    "iso:country":"US",
    "sg:address":"1100 Main St",
    "sg:city":"Fort Morgan",
    "sg:classifiers":[
        {
            "category":"Health Services",
            "subcategory":"Optometrist",
            "type":"Services"
        }
    ],
    "sg:phone":"+1 970 867 3046",
    "sg:postcode":"80701",
    "sg:province":"CO",
    "wof:name":"Optometry Clinic-Fort Morgan",
    "wof:placetype":"venue"
},
  "geometry": {"coordinates":[-103.80149299999999,40.261184],"type":"Point"}
}