{
  "type": "Feature",
  "properties": {
    "iso:country":"US",
    "sg:address":"2453 S Flanders Ct",
    "sg:city":"Aurora",
    "sg:classifiers":[
        {
            "category":"Building & Trades",
            "subcategory":"Electrical",
            "type":"Services"
        }
    ],
    "sg:phone":"+1 303 369 5029",
    "sg:postcode":"80013",
    "sg:province":"CO",
    "sg:tags":[
        "electrical",
        "contractor"
    ],
    "wof:name":"B TEC Inc",
    "wof:placetype":"venue"
},
  "geometry": {"coordinates":[-104.75973,39.672232],"type":"Point"}
}