{
  "type": "Feature",
  "properties": {
    "iso:country":"US",
    "sg:address":"1450 Dairy Ln",
    "sg:city":"Limon",
    "sg:classifiers":[
        {
            "category":"Building & Trades",
            "subcategory":"Plumbing",
            "type":"Services"
        }
    ],
    "sg:phone":"+1 719 775 2198",
    "sg:postcode":"80828",
    "sg:province":"CO",
    "sg:tags":[
        "septic"
    ],
    "wof:name":"Rob's Septic Svc & Porta-Pot",
    "wof:placetype":"venue"
},
  "geometry": {"coordinates":[-103.694892,39.257411],"type":"Point"}
}