{
  "type": "Feature",
  "properties": {
    "iso:country":"US",
    "sg:address":"1732 East 17th Ave",
    "sg:city":"Denver",
    "sg:classifiers":[
        {
            "category":"Personal",
            "subcategory":"Beauty Salon",
            "type":"Services"
        }
    ],
    "sg:phone":"+1 303 905 6800",
    "sg:postcode":"80218",
    "sg:province":"CO",
    "sg:tags":[
        "spa"
    ],
    "sg:website":"www.hairstraighteningexpert.com",
    "wof:name":"Hair Straightening Expert @ Salon 17",
    "wof:placetype":"venue"
},
  "geometry": {"coordinates":[-104.966339,39.743053],"type":"Point"}
}