{
  "type": "Feature",
  "properties": {
    "iso:country":"US",
    "sg:address":"1303 Loch Lomand Ave",
    "sg:city":"Broomfield",
    "sg:classifiers":[
        {
            "category":"Manufacturing",
            "subcategory":"Printing",
            "type":"Manufacturing & Wholesale Goods"
        }
    ],
    "sg:phone":"+1 303 469 9355",
    "sg:postcode":"80020",
    "sg:province":"CO",
    "sg:tags":[
        "printer"
    ],
    "wof:name":"Tattored Page Ink",
    "wof:placetype":"venue"
},
  "geometry": {"coordinates":[-105.055993,39.919037],"type":"Point"}
}