{
  "type": "Feature",
  "properties": {
    "addr:full":"210 S Ridge St Breckenridge CO 80424",
    "addr:housenumber":"210",
    "addr:postcode":"80424",
    "addr:street":"S Ridge St",
    "iso:country":"US",
    "sg:address":"210 S Ridge St",
    "sg:city":"Breckenridge",
    "sg:classifiers":[
        {
            "category":"Banks & Credit Unions",
            "subcategory":"Bank",
            "type":"Services"
        }
    ],
    "sg:phone":"+1 970 453 6300",
    "sg:postcode":"80424",
    "sg:province":"CO",
    "sg:tags":[
        "loan"
    ],
    "wof:name":"Mountain Resort Mortgage Inc",
    "wof:placetype":"venue"
},
  "geometry": {"coordinates":[-106.04453599999999,39.480782],"type":"Point"}
}