{
  "type": "Feature",
  "properties": {
    "addr:full":"16086 E 97th Pl Commerce City CO 80022",
    "addr:housenumber":"16086",
    "addr:postcode":"80022",
    "addr:street":"E 97Th Pl",
    "iso:country":"US",
    "sg:address":"16086 E 97th Pl",
    "sg:city":"Commerce City",
    "sg:classifiers":[
        {
            "category":"Building & Trades",
            "subcategory":"Construction",
            "type":"Services"
        }
    ],
    "sg:phone":"+1 303 287 4102",
    "sg:postcode":"80022",
    "sg:province":"CO",
    "sg:tags":[
        "utility",
        "contractor"
    ],
    "wof:name":"Utility Notification Ctr",
    "wof:placetype":"venue"
},
  "geometry": {"coordinates":[-104.800746,39.873201],"type":"Point"}
}