{
  "type": "Feature",
  "properties": {
    "iso:country":"US",
    "sg:address":"211 Main St",
    "sg:city":"Ovid",
    "sg:classifiers":[
        {
            "category":"Government",
            "subcategory":"Office",
            "type":"Public Place"
        }
    ],
    "sg:phone":"+1 970 463 5446",
    "sg:postcode":"80744",
    "sg:province":"CO",
    "sg:tags":[
        "city"
    ],
    "wof:name":"Town Clerk",
    "wof:placetype":"venue"
},
  "geometry": {"coordinates":[-102.38789800000001,40.96068],"type":"Point"}
}