{
  "type": "Feature",
  "properties": {
    "iso:country":"US",
    "sg:address":"6395 Monaco St",
    "sg:city":"Commerce City",
    "sg:classifiers":[
        {
            "category":"Organizations",
            "subcategory":"Religious Organization",
            "type":"Services"
        }
    ],
    "sg:phone":"+1 303 287 7827",
    "sg:postcode":"80022",
    "sg:province":"CO",
    "sg:tags":[
        "church"
    ],
    "wof:name":"Rose Hill Tabernacle",
    "wof:placetype":"venue"
},
  "geometry": {"coordinates":[-104.912949,39.81203],"type":"Point"}
}