{
  "type": "Feature",
  "properties": {
    "addr:full":"5837 Wright Dr Loveland CO 80538",
    "addr:housenumber":"5837",
    "addr:postcode":"80538",
    "addr:street":"Wright Dr",
    "iso:country":"US",
    "sg:address":"5837 Wright Dr",
    "sg:city":"Loveland",
    "sg:classifiers":[
        {
            "category":"Wholesale",
            "subcategory":"Construction Materials",
            "type":"Manufacturing & Wholesale Goods"
        }
    ],
    "sg:phone":"+1 970 203 0664",
    "sg:postcode":"80538",
    "sg:province":"CO",
    "sg:tags":[
        "stucco"
    ],
    "wof:name":"Jones Heartz Lime Co Inc",
    "wof:placetype":"venue"
},
  "geometry": {"coordinates":[-104.99912,40.45222],"type":"Point"}
}