{
  "type": "Feature",
  "properties": {
    "iso:country":"US",
    "sg:address":"1330 Leyden Street Suite 107",
    "sg:city":"Denver",
    "sg:classifiers":[
        {
            "category":"Personal",
            "subcategory":"Beauty Salon",
            "type":"Services"
        }
    ],
    "sg:phone":"+1 303 629 6482",
    "sg:postcode":"80220",
    "sg:province":"CO",
    "sg:tags":[
        "hair"
    ],
    "wof:name":"Hair Loom Designs",
    "wof:placetype":"venue"
},
  "geometry": {"coordinates":[-104.915183,39.737236],"type":"Point"}
}