{
  "type": "Feature",
  "properties": {
    "addr:full":"513 S Circle Dr Colorado Springs CO 80910",
    "addr:housenumber":"513",
    "addr:postcode":"80910",
    "addr:street":"S Circle Dr",
    "iso:country":"US",
    "sg:address":"513 S Circle Dr",
    "sg:city":"Colorado Springs",
    "sg:classifiers":[
        {
            "category":"Personal",
            "subcategory":"Beauty Salon",
            "type":"Services"
        }
    ],
    "sg:phone":"+1 719 634 5941",
    "sg:postcode":"80910",
    "sg:province":"CO",
    "wof:name":"Clean Cuts Family Haircare",
    "wof:placetype":"venue"
},
  "geometry": {"coordinates":[-104.78042600000001,38.824527],"type":"Point"}
}