{
  "type": "Feature",
  "properties": {
    "addr:full":"27373 Mesa Dr Evergreen CO 80439",
    "addr:housenumber":"27373",
    "addr:postcode":"80439",
    "addr:street":"Mesa Dr",
    "iso:country":"US",
    "sg:address":"27373 Mesa Dr",
    "sg:city":"Evergreen",
    "sg:classifiers":[
        {
            "category":"Building & Trades",
            "subcategory":"Construction",
            "type":"Services"
        }
    ],
    "sg:phone":"+1 303 674 8899",
    "sg:postcode":"80439",
    "sg:province":"CO",
    "sg:tags":[
        "industrial",
        "contractor",
        "contractors-commercial",
        "masonry",
        "mason"
    ],
    "wof:name":"Neil Butler",
    "wof:placetype":"venue"
},
  "geometry": {"coordinates":[-105.30934600000001,39.615398],"type":"Point"}
}