{
  "type": "Feature",
  "properties": {
    "iso:country":"US",
    "sg:address":"1550 Co Rd 320",
    "sg:city":"Rifle",
    "sg:classifiers":[
        {
            "category":"Professional",
            "subcategory":"Detective & Security Services",
            "type":"Services"
        }
    ],
    "sg:phone":"+1 970 625 2728",
    "sg:postcode":"81650",
    "sg:province":"CO",
    "sg:tags":[
        "guard",
        "patrol"
    ],
    "wof:name":"Executive Security Intl",
    "wof:placetype":"venue"
},
  "geometry": {"coordinates":[-107.937928,39.49033],"type":"Point"}
}