{
  "type": "Feature",
  "properties": {
    "iso:country":"US",
    "sg:address":"2617 E Hwy 86",
    "sg:city":"Castle Rock",
    "sg:classifiers":[
        {
            "category":"Shopping",
            "subcategory":"Used Merchandise",
            "type":"Retail Goods"
        }
    ],
    "sg:phone":"+1 303 660 9476",
    "sg:postcode":"80104",
    "sg:province":"CO",
    "wof:name":"Howertons Antiques",
    "wof:placetype":"venue"
},
  "geometry": {"coordinates":[-104.83534899999999,39.376805],"type":"Point"}
}