{
  "type": "Feature",
  "properties": {
    "addr:full":"950 S Cherry Street Suite 710 Denver CO 80246",
    "addr:housenumber":"950",
    "addr:postcode":"80246",
    "addr:street":"S Cherry Street Suite 710",
    "iso:country":"US",
    "sg:address":"950 S Cherry Street Suite 710",
    "sg:city":"Denver",
    "sg:classifiers":[
        {
            "category":"Banks & Credit Unions",
            "subcategory":"Atm",
            "type":"Services"
        }
    ],
    "sg:phone":"+1 303 691 9774",
    "sg:postcode":"80246",
    "sg:province":"CO",
    "sg:tags":[
        "bankruptcy"
    ],
    "sg:website":"www.alklaw.com|troubleshooter.com",
    "wof:name":"Lindquist-Kleissler Arthur",
    "wof:placetype":"venue"
},
  "geometry": {"coordinates":[-104.931669,39.699447],"type":"Point"}
}