{
  "type": "Feature",
  "properties": {
    "iso:country":"US",
    "sg:address":"7369 E Easter Ave",
    "sg:city":"Centennial",
    "sg:classifiers":[
        {
            "category":"Mining & Drilling",
            "type":"Manufacturing & Wholesale Goods"
        }
    ],
    "sg:phone":"+1 303 779 2520",
    "sg:postcode":"80112",
    "sg:province":"CO",
    "sg:tags":[
        "development",
        "gas",
        "oil",
        "exploration"
    ],
    "sg:website":"www.apexpe.com",
    "wof:name":"Apex",
    "wof:placetype":"venue"
},
  "geometry": {"coordinates":[-104.902951,39.58831],"type":"Point"}
}