{
  "type": "Feature",
  "properties": {
    "iso:country":"US",
    "sg:address":"1512 Larimer Street",
    "sg:city":"Denver",
    "sg:classifiers":[
        {
            "category":"Coffee & Tea",
            "type":"Food & Drink"
        }
    ],
    "sg:phone":"+1 720 932 6572",
    "sg:postcode":"80202",
    "sg:province":"CO",
    "sg:website":"www.starbucks.com",
    "wof:name":"Starbucks Writer's Square #6657",
    "wof:placetype":"venue"
},
  "geometry": {"coordinates":[-104.998474,39.748399],"type":"Point"}
}