{
  "type": "Feature",
  "properties": {
    "iso:country":"US",
    "sg:address":"34229 Co Rd 64",
    "sg:city":"Crook",
    "sg:classifiers":[
        {
            "category":"Farming",
            "subcategory":"Farm & Veterinary Services",
            "type":"Manufacturing & Wholesale Goods"
        }
    ],
    "sg:phone":"+1 970 522 8121",
    "sg:postcode":"80726",
    "sg:province":"CO",
    "sg:tags":[
        "crop"
    ],
    "wof:name":"Lazy St Farms",
    "wof:placetype":"venue"
},
  "geometry": {"coordinates":[-102.91696899999999,40.893039],"type":"Point"}
}