{
  "type": "Feature",
  "properties": {
    "addr:full":"4673 S Vivian Ct Morrison CO 80465",
    "addr:housenumber":"4673",
    "addr:postcode":"80465",
    "addr:street":"S Vivian Ct",
    "iso:country":"US",
    "sg:address":"4673 S Vivian Ct",
    "sg:city":"Morrison",
    "sg:classifiers":[
        {
            "category":"Building & Trades",
            "subcategory":"Landscaping Services",
            "type":"Services"
        }
    ],
    "sg:phone":"+1 303 972 8836",
    "sg:postcode":"80465",
    "sg:province":"CO",
    "wof:name":"Greenblades Lawn Care Service",
    "wof:placetype":"venue"
},
  "geometry": {"coordinates":[-105.137725,39.630786],"type":"Point"}
}