{
  "type": "Feature",
  "properties": {
    "addr:full":"10108 S Stephen Pl Littleton CO 80130",
    "addr:housenumber":"10108",
    "addr:postcode":"80130",
    "addr:street":"S Stephen Pl",
    "iso:country":"US",
    "sg:address":"10108 S Stephen Pl",
    "sg:city":"Littleton",
    "sg:classifiers":[
        {
            "category":"Professional",
            "subcategory":"Art Services",
            "type":"Services"
        }
    ],
    "sg:phone":"+1 303 683 6683",
    "sg:postcode":"80130",
    "sg:province":"CO",
    "sg:tags":[
        "photographer"
    ],
    "wof:name":"Beth Schneider Photography",
    "wof:placetype":"venue"
},
  "geometry": {"coordinates":[-104.92341399999999,39.530571],"type":"Point"}
}