{
  "type": "Feature",
  "properties": {
    "iso:country":"US",
    "sg:address":"402 Norfolk St",
    "sg:city":"Aurora",
    "sg:classifiers":[
        {
            "category":"Manufacturing",
            "subcategory":"Tools & Machinery",
            "type":"Manufacturing & Wholesale Goods"
        }
    ],
    "sg:phone":"+1 303 340 4465",
    "sg:postcode":"80011",
    "sg:province":"CO",
    "sg:tags":[
        "map",
        "mfg",
        "plotting",
        "instrument"
    ],
    "wof:name":"Mucad USA Corporation",
    "wof:placetype":"venue"
},
  "geometry": {"coordinates":[-104.797923,39.725267],"type":"Point"}
}