{
  "type": "Feature",
  "properties": {
    "addr:full":"104 E Main St Cortez CO 81321",
    "addr:housenumber":"104",
    "addr:postcode":"81321",
    "addr:street":"E Main St",
    "iso:country":"US",
    "sg:address":"104 E Main St",
    "sg:city":"Cortez",
    "sg:classifiers":[
        {
            "category":"Restaurant",
            "type":"Food & Drink"
        }
    ],
    "sg:phone":"+1 970 565 9066",
    "sg:postcode":"81321",
    "sg:province":"CO",
    "sg:tags":[
        "drinking",
        "eating"
    ],
    "wof:name":"Antonio's",
    "wof:placetype":"venue"
},
  "geometry": {"coordinates":[-108.583797,37.34872],"type":"Point"}
}