{
  "type": "Feature",
  "properties": {
    "addr:full":"1601 25th Ave Greeley CO 80634",
    "addr:housenumber":"1601",
    "addr:postcode":"80634",
    "addr:street":"25Th Ave",
    "iso:country":"US",
    "sg:address":"1601 25th Ave",
    "sg:city":"Greeley",
    "sg:classifiers":[
        {
            "category":"Health Services",
            "subcategory":"Doctor",
            "type":"Services"
        }
    ],
    "sg:phone":"+1 970 353 4085",
    "sg:postcode":"80634",
    "sg:province":"CO",
    "sg:tags":[
        "physician",
        "surgeon"
    ],
    "wof:name":"Charepoo Urology Ctr",
    "wof:placetype":"venue"
},
  "geometry": {"coordinates":[-104.719238,40.413824],"type":"Point"}
}