{
  "type": "Feature",
  "properties": {
    "iso:country":"US",
    "sg:address":"1461 Birch St",
    "sg:city":"Denver",
    "sg:classifiers":[
        {
            "category":"Professional",
            "type":"Services"
        }
    ],
    "sg:phone":"+1 303 399 3087",
    "sg:postcode":"80220",
    "sg:province":"CO",
    "wof:name":"Robin Howe",
    "wof:placetype":"venue"
},
  "geometry": {"coordinates":[-104.93622999999999,39.738998],"type":"Point"}
}