{
  "type": "Feature",
  "properties": {
    "addr:full":"9700 E Alameda Ave Denver CO 80247",
    "addr:housenumber":"9700",
    "addr:postcode":"80247",
    "addr:street":"E Alameda Ave",
    "iso:country":"US",
    "sg:address":"9700 E Alameda Ave",
    "sg:city":"Denver",
    "sg:classifiers":[
        {
            "category":"Autos & Motor Vehicles",
            "subcategory":"Fuel & Gas Station",
            "type":"Retail Goods"
        }
    ],
    "sg:phone":"+1 303 363 1824",
    "sg:postcode":"80247",
    "sg:province":"CO",
    "sg:tags":[
        "station",
        "gasoline"
    ],
    "wof:name":"Sinclair Gas Station",
    "wof:placetype":"venue"
},
  "geometry": {"coordinates":[-104.870653,39.710169],"type":"Point"}
}