{
  "type": "Feature",
  "properties": {
    "addr:full":"3614 Sunflower Cir Longmont CO 80503",
    "addr:housenumber":"3614",
    "addr:postcode":"80503",
    "addr:street":"Sunflower Cir",
    "iso:country":"US",
    "sg:address":"3614 Sunflower Cir",
    "sg:city":"Longmont",
    "sg:classifiers":[
        {
            "category":"Shopping",
            "subcategory":"Gifts & Souvenirs",
            "type":"Retail Goods"
        }
    ],
    "sg:phone":"+1 303 776 1523",
    "sg:postcode":"80503",
    "sg:province":"CO",
    "wof:name":"Hillside Baskets",
    "wof:placetype":"venue"
},
  "geometry": {"coordinates":[-105.147328,40.142593],"type":"Point"}
}