{
  "type": "Feature",
  "properties": {
    "iso:country":"US",
    "sg:address":"5611 E Amherst Ave",
    "sg:city":"Denver",
    "sg:classifiers":[
        {
            "category":"Professional",
            "type":"Services"
        }
    ],
    "sg:phone":"+1 303 759 0984",
    "sg:postcode":"80222",
    "sg:province":"CO",
    "wof:name":"Van Otterloo Viola J",
    "wof:placetype":"venue"
},
  "geometry": {"coordinates":[-104.921555,39.666621],"type":"Point"}
}