{
  "type": "Feature",
  "properties": {
    "addr:full":"991 Ute Ave Aspen CO 81611",
    "addr:housenumber":"991",
    "addr:postcode":"81611",
    "addr:street":"Ute Ave",
    "iso:country":"US",
    "sg:address":"991 Ute Ave",
    "sg:city":"Aspen",
    "sg:classifiers":[
        {
            "category":"Education",
            "subcategory":"Special Training",
            "type":"Public Place"
        }
    ],
    "sg:phone":"+1 970 925 7099",
    "sg:postcode":"81611",
    "sg:province":"CO",
    "sg:tags":[
        "educational"
    ],
    "wof:name":"AIKI Works Inc",
    "wof:placetype":"venue"
},
  "geometry": {"coordinates":[-106.81467600000001,39.183417],"type":"Point"}
}