{
  "type": "Feature",
  "properties": {
    "addr:full":"2298 Broadway Grand Junction CO 81503",
    "addr:housenumber":"2298",
    "addr:postcode":"81503",
    "addr:street":"Broadway",
    "iso:country":"US",
    "sg:address":"2298 Broadway",
    "sg:city":"Grand Junction",
    "sg:classifiers":[
        {
            "category":"Banks & Credit Unions",
            "subcategory":"Bank",
            "type":"Services"
        }
    ],
    "sg:phone":"+1 970 255 6573",
    "sg:postcode":"81503",
    "sg:province":"CO",
    "sg:tags":[
        "loan",
        "real estate"
    ],
    "wof:name":"Alliance Mortgage",
    "wof:placetype":"venue"
},
  "geometry": {"coordinates":[-108.626367,39.07483],"type":"Point"}
}