{
  "type": "Feature",
  "properties": {
    "iso:country":"US",
    "sg:address":"6852 W 69th Ave",
    "sg:city":"Arvada",
    "sg:classifiers":[
        {
            "category":"Building & Trades",
            "subcategory":"Construction",
            "type":"Services"
        }
    ],
    "sg:phone":"+1 303 422 8418",
    "sg:postcode":"80003",
    "sg:province":"CO",
    "sg:tags":[
        "concrete",
        "contractor"
    ],
    "wof:name":"Cross Concrete",
    "wof:placetype":"venue"
},
  "geometry": {"coordinates":[-105.073024,39.821988],"type":"Point"}
}