{
  "type": "Feature",
  "properties": {
    "iso:country":"US",
    "sg:address":"2643 Bradbury Ct",
    "sg:city":"Fort Collins",
    "sg:classifiers":[
        {
            "category":"Shopping",
            "subcategory":"Clothing, Apparel, & Fashions",
            "type":"Retail Goods"
        }
    ],
    "sg:phone":"+1 720 359 8453",
    "sg:postcode":"80521",
    "sg:province":"CO",
    "wof:name":"Etc Cira",
    "wof:placetype":"venue"
},
  "geometry": {"coordinates":[-105.125733,40.569894],"type":"Point"}
}