{
  "type": "Feature",
  "properties": {
    "addr:full":"5676 N Union Blvd Colorado Springs CO 80918",
    "addr:housenumber":"5676",
    "addr:postcode":"80918",
    "addr:street":"N Union Blvd",
    "iso:country":"US",
    "sg:address":"5676 N Union Blvd",
    "sg:city":"Colorado Springs",
    "sg:classifiers":[
        {
            "category":"Food & Beverages",
            "subcategory":"Groceries & Convenience Stores",
            "type":"Retail Goods"
        }
    ],
    "sg:phone":"+1 719 598 8847",
    "sg:postcode":"80918",
    "sg:province":"CO",
    "wof:name":"KWIK Way Store Inc",
    "wof:placetype":"venue"
},
  "geometry": {"coordinates":[-104.775077,38.911287],"type":"Point"}
}