{
  "type": "Feature",
  "properties": {
    "iso:country":"US",
    "sg:address":"835 Main Ave",
    "sg:city":"Durango",
    "sg:classifiers":[
        {
            "category":"Real Estate",
            "subcategory":"Real Estate Agent",
            "type":"Services"
        }
    ],
    "sg:phone":"+1 970 375 0707",
    "sg:postcode":"81301",
    "sg:province":"CO",
    "wof:name":"Asa Appraisal Services",
    "wof:placetype":"venue"
},
  "geometry": {"coordinates":[-107.88090099999999,37.273042],"type":"Point"}
}