{
  "type": "Feature",
  "properties": {
    "iso:country":"US",
    "sg:address":"9956 W Remington Pl",
    "sg:city":"Littleton",
    "sg:classifiers":[
        {
            "category":"Retail",
            "subcategory":"Laundry & Dry Cleaning",
            "type":"Services"
        }
    ],
    "sg:phone":"+1 720 377 1562",
    "sg:postcode":"80128",
    "sg:province":"CO",
    "sg:tags":[
        "cleaners"
    ],
    "wof:name":"Dry Cleaning Station",
    "wof:placetype":"venue"
},
  "geometry": {"coordinates":[-105.108158,39.564543],"type":"Point"}
}