{
  "type": "Feature",
  "properties": {
    "addr:full":"6161 S Syracuse Way Englewood CO 80111",
    "addr:housenumber":"6161",
    "addr:postcode":"80111",
    "addr:street":"S Syracuse Way",
    "iso:country":"US",
    "sg:address":"6161 S Syracuse Way",
    "sg:city":"Englewood",
    "sg:classifiers":[
        {
            "category":"Professional",
            "subcategory":"Computer Services",
            "type":"Services"
        }
    ],
    "sg:phone":"+1 303 706 0990",
    "sg:postcode":"80111",
    "sg:province":"CO",
    "sg:tags":[
        "programing",
        "custom"
    ],
    "wof:name":"Microsource",
    "wof:placetype":"venue"
},
  "geometry": {"coordinates":[-104.899559,39.604158],"type":"Point"}
}