{
  "type": "Feature",
  "properties": {
    "addr:full":"1001 E 66th Ave Denver CO 80229",
    "addr:housenumber":"1001",
    "addr:postcode":"80229",
    "addr:street":"E 66Th Ave",
    "iso:country":"US",
    "sg:address":"1001 E 66th Ave",
    "sg:city":"Denver",
    "sg:classifiers":[
        {
            "category":"Government",
            "subcategory":"Office",
            "type":"Public Place"
        }
    ],
    "sg:phone":"+1 303 866 3887",
    "sg:postcode":"80229",
    "sg:province":"CO",
    "sg:tags":[
        "development"
    ],
    "wof:name":"Csia Central Svs Mail Ser",
    "wof:placetype":"venue"
},
  "geometry": {"coordinates":[-104.976027,39.816457],"type":"Point"}
}