{
  "type": "Feature",
  "properties": {
    "iso:country":"US",
    "sg:address":"531 E Main St",
    "sg:city":"Montrose",
    "sg:classifiers":[
        {
            "category":"Wholesale",
            "subcategory":"Medical Equipment & Supplies",
            "type":"Manufacturing & Wholesale Goods"
        }
    ],
    "sg:phone":"+1 970 240 9556",
    "sg:postcode":"81401",
    "sg:province":"CO",
    "wof:name":"Hartman Bros Med Oxgn & Eqp",
    "wof:placetype":"venue"
},
  "geometry": {"coordinates":[-107.87492,38.480743],"type":"Point"}
}