{
  "type": "Feature",
  "properties": {
    "iso:country":"US",
    "sg:address":"10 W Victory Way",
    "sg:city":"Craig",
    "sg:classifiers":[
        {
            "category":"Professional",
            "subcategory":"Computer Services",
            "type":"Services"
        }
    ],
    "sg:phone":"+1 970 824 7414",
    "sg:postcode":"81625",
    "sg:province":"CO",
    "sg:tags":[
        "consultant",
        "designer"
    ],
    "wof:name":"Solutions Oriented Systems",
    "wof:placetype":"venue"
},
  "geometry": {"coordinates":[-107.548423,40.514164],"type":"Point"}
}