{
  "type": "Feature",
  "properties": {
    "iso:country":"US",
    "sg:address":"401 N Timberline Rd",
    "sg:city":"Fort Collins",
    "sg:classifiers":[
        {
            "category":"Building & Trades",
            "subcategory":"Construction",
            "type":"Services"
        }
    ],
    "sg:phone":"+1 970 484 2293",
    "sg:postcode":"80524",
    "sg:province":"CO",
    "sg:tags":[
        "contractor"
    ],
    "wof:name":"Chavez Roofing",
    "wof:placetype":"venue"
},
  "geometry": {"coordinates":[-105.029398,40.591442],"type":"Point"}
}