{
  "type": "Feature",
  "properties": {
    "addr:full":"6430 E 39th Ave Denver CO 80207",
    "addr:housenumber":"6430",
    "addr:postcode":"80207",
    "addr:street":"E 39Th Ave",
    "iso:country":"US",
    "sg:address":"6430 E 39th Ave",
    "sg:city":"Denver",
    "sg:classifiers":[
        {
            "category":"Professional",
            "subcategory":"Art Services",
            "type":"Services"
        }
    ],
    "sg:phone":"+1 303 322 3246",
    "sg:postcode":"80207",
    "sg:province":"CO",
    "sg:tags":[
        "photographer"
    ],
    "wof:name":"Design & Image Photography",
    "wof:placetype":"venue"
},
  "geometry": {"coordinates":[-104.91674,39.770995],"type":"Point"}
}