{
  "type": "Feature",
  "properties": {
    "iso:country":"US",
    "sg:address":"128 S Sunset St",
    "sg:city":"Fort Collins",
    "sg:classifiers":[
        {
            "category":"Retail",
            "subcategory":"Repair Shop",
            "type":"Services"
        }
    ],
    "sg:phone":"+1 970 226 1744",
    "sg:postcode":"80521",
    "sg:province":"CO",
    "sg:tags":[
        "scooter",
        "motorcycle",
        "motor"
    ],
    "wof:name":"Rebel Choppers",
    "wof:placetype":"venue"
},
  "geometry": {"coordinates":[-105.125803,40.589056],"type":"Point"}
}