{
  "type": "Feature",
  "properties": {
    "iso:country":"US",
    "sg:address":"460 E 6th Ter",
    "sg:city":"Florence",
    "sg:classifiers":[
        {
            "category":"Building & Trades",
            "subcategory":"Construction",
            "type":"Services"
        }
    ],
    "sg:phone":"+1 719 784 6514",
    "sg:postcode":"81226",
    "sg:province":"CO",
    "sg:tags":[
        "hanging",
        "contractor"
    ],
    "wof:name":"Marathon Painting Inc",
    "wof:placetype":"venue"
},
  "geometry": {"coordinates":[-105.11199999999999,38.394175],"type":"Point"}
}