{
  "type": "Feature",
  "properties": {
    "iso:country":"US",
    "sg:address":"560 S Commercial Dr",
    "sg:city":"Grand Junction",
    "sg:classifiers":[
        {
            "category":"Home & Garden",
            "subcategory":"Building Materials",
            "type":"Retail Goods"
        }
    ],
    "sg:phone":"+1 970 243 8290",
    "sg:postcode":"81505",
    "sg:province":"CO",
    "sg:tags":[
        "door"
    ],
    "wof:name":"Quality Garage Doors",
    "wof:placetype":"venue"
},
  "geometry": {"coordinates":[-108.585342,39.086723],"type":"Point"}
}