{
  "type": "Feature",
  "properties": {
    "addr:full":"3104 F Rd Grand Junction CO 81504",
    "addr:housenumber":"3104",
    "addr:postcode":"81504",
    "addr:street":"F Rd",
    "iso:country":"US",
    "sg:address":"3104 F Rd",
    "sg:city":"Grand Junction",
    "sg:classifiers":[
        {
            "category":"Building & Trades",
            "subcategory":"Construction",
            "type":"Services"
        }
    ],
    "sg:phone":"+1 970 523 6551",
    "sg:postcode":"81504",
    "sg:province":"CO",
    "sg:tags":[
        "restoration",
        "cleaning",
        "patio",
        "deck"
    ],
    "wof:name":"S & N Pressure Wash",
    "wof:placetype":"venue"
},
  "geometry": {"coordinates":[-108.476415,39.091851],"type":"Point"}
}