{
  "type": "Feature",
  "properties": {
    "addr:full":"120 W Main St Naturita CO 81422",
    "addr:housenumber":"120",
    "addr:postcode":"81422",
    "addr:street":"W Main St",
    "iso:country":"US",
    "sg:address":"120 W Main St",
    "sg:city":"Naturita",
    "sg:classifiers":[
        {
            "category":"Restaurant",
            "type":"Food & Drink"
        }
    ],
    "sg:phone":"+1 970 865 2222",
    "sg:postcode":"81422",
    "sg:province":"CO",
    "wof:name":"Blondies Drive In & Cafe",
    "wof:placetype":"venue"
},
  "geometry": {"coordinates":[-108.56785000000001,38.21702],"type":"Point"}
}