{
  "type": "Feature",
  "properties": {
    "iso:country":"US",
    "sg:address":"3110 Elk River Rd",
    "sg:city":"Steamboat Spgs",
    "sg:classifiers":[
        {
            "category":"Home & Garden",
            "subcategory":"Building Materials",
            "type":"Retail Goods"
        }
    ],
    "sg:phone":"+1 970 879 2725",
    "sg:postcode":"80487",
    "sg:province":"CO",
    "sg:tags":[
        "glass",
        "window",
        "plate"
    ],
    "wof:name":"Neste Auto Glass",
    "wof:placetype":"venue"
},
  "geometry": {"coordinates":[-106.858125,40.513802],"type":"Point"}
}