{
  "type": "Feature",
  "properties": {
    "addr:full":"965 Pearl St Denver CO 80203",
    "addr:housenumber":"965",
    "addr:postcode":"80203",
    "addr:street":"Pearl St",
    "iso:country":"US",
    "sg:address":"965 Pearl St",
    "sg:city":"Denver",
    "sg:classifiers":[
        {
            "category":"Real Estate",
            "subcategory":"Real Estate Agent",
            "type":"Services"
        }
    ],
    "sg:phone":"+1 303 861 2442",
    "sg:postcode":"80203",
    "sg:province":"CO",
    "sg:tags":[
        "investment"
    ],
    "wof:name":"Tim Wayne",
    "wof:placetype":"venue"
},
  "geometry": {"coordinates":[-104.979902,39.730955],"type":"Point"}
}