{
  "type": "Feature",
  "properties": {
    "addr:full":"316 Elm St Sterling CO 80751",
    "addr:housenumber":"316",
    "addr:postcode":"80751",
    "addr:street":"Elm St",
    "iso:country":"US",
    "sg:address":"316 Elm St",
    "sg:city":"Sterling",
    "sg:classifiers":[
        {
            "category":"Retail",
            "subcategory":"Self-service Laundry",
            "type":"Services"
        }
    ],
    "sg:phone":"+1 970 522 7806",
    "sg:postcode":"80751",
    "sg:province":"CO",
    "wof:name":"Wash Place",
    "wof:placetype":"venue"
},
  "geometry": {"coordinates":[-103.20447799999999,40.629878],"type":"Point"}
}