{
  "type": "Feature",
  "properties": {
    "addr:full":"4158 Jason St Denver CO 80211",
    "addr:housenumber":"4158",
    "addr:postcode":"80211",
    "addr:street":"Jason St",
    "iso:country":"US",
    "sg:address":"4158 Jason St",
    "sg:city":"Denver",
    "sg:classifiers":[
        {
            "category":"Retail",
            "subcategory":"Auto Repair",
            "type":"Services"
        }
    ],
    "sg:phone":"+1 303 234 1677",
    "sg:postcode":"80211",
    "sg:province":"CO",
    "sg:tags":[
        "repairing",
        "automobile"
    ],
    "wof:name":"Ramiro's Auto Repair",
    "wof:placetype":"venue"
},
  "geometry": {"coordinates":[-104.999323,39.773487],"type":"Point"}
}