{
  "type": "Feature",
  "properties": {
    "addr:full":"13810 N 115th St Longmont CO 80504",
    "addr:housenumber":"13810",
    "addr:postcode":"80504",
    "addr:street":"N 115Th St",
    "iso:country":"US",
    "sg:address":"13810 N 115th St",
    "sg:city":"Longmont",
    "sg:classifiers":[
        {
            "category":"Farming",
            "subcategory":"Aquatic Farm",
            "type":"Manufacturing & Wholesale Goods"
        }
    ],
    "sg:phone":"+1 303 449 3474",
    "sg:postcode":"80504",
    "sg:province":"CO",
    "sg:tags":[
        "chemical",
        "specialist",
        "fish",
        "industry",
        "consultant"
    ],
    "wof:name":"Queen of The River Fish Co",
    "wof:placetype":"venue"
},
  "geometry": {"coordinates":[-105.083544,40.22077],"type":"Point"}
}