{
  "type": "Feature",
  "properties": {
    "addr:full":"4770 S Mobile Way Aurora CO 80015",
    "addr:housenumber":"4770",
    "addr:postcode":"80015",
    "addr:street":"S Mobile Way",
    "iso:country":"US",
    "sg:address":"4770 S Mobile Way",
    "sg:city":"Aurora",
    "sg:classifiers":[
        {
            "category":"Restaurant",
            "type":"Food & Drink"
        }
    ],
    "sg:phone":"+1 303 766 5888",
    "sg:postcode":"80015",
    "sg:province":"CO",
    "sg:tags":[
        "eating"
    ],
    "wof:name":"Sunshine Concessions LLC",
    "wof:placetype":"venue"
},
  "geometry": {"coordinates":[-104.797282,39.629804],"type":"Point"}
}