{
  "type": "Feature",
  "properties": {
    "iso:country":"US",
    "sg:address":"10025 E Girard Ave",
    "sg:city":"Denver",
    "sg:classifiers":[
        {
            "category":"Home & Garden",
            "subcategory":"Building Materials",
            "type":"Retail Goods"
        }
    ],
    "sg:phone":"+1 303 696 7196",
    "sg:postcode":"80231",
    "sg:province":"CO",
    "wof:name":"Prestige Floor",
    "wof:placetype":"venue"
},
  "geometry": {"coordinates":[-104.872147,39.654541],"type":"Point"}
}