{
  "type": "Feature",
  "properties": {
    "addr:full":"11901 E 30th Ave Aurora CO 80010",
    "addr:housenumber":"11901",
    "addr:postcode":"80010",
    "addr:street":"E 30Th Ave",
    "iso:country":"US",
    "sg:address":"11901 E 30th Ave",
    "sg:city":"Aurora",
    "sg:classifiers":[
        {
            "category":"Government",
            "subcategory":"Office",
            "type":"Public Place"
        }
    ],
    "sg:phone":"+1 303 361 6612",
    "sg:postcode":"80010",
    "sg:province":"CO",
    "sg:tags":[
        "processing",
        "center"
    ],
    "wof:name":"Processing Center",
    "wof:placetype":"venue"
},
  "geometry": {"coordinates":[-104.847934,39.759268],"type":"Point"}
}