{
  "type": "Feature",
  "properties": {
    "iso:country":"US",
    "sg:address":"949 Walnut St",
    "sg:city":"Boulder",
    "sg:classifiers":[
        {
            "category":"Personal",
            "subcategory":"Shoe Repair & Shine",
            "type":"Services"
        }
    ],
    "sg:phone":"+1 303 443 4580",
    "sg:postcode":"80302",
    "sg:province":"CO",
    "sg:tags":[
        "parlor"
    ],
    "wof:name":"Perrys Orthopedic Shoe Repair",
    "wof:placetype":"venue"
},
  "geometry": {"coordinates":[-105.282639,40.016305],"type":"Point"}
}