{
  "type": "Feature",
  "properties": {
    "addr:full":"926 W Cheyenne Rd Colorado Springs CO 80906",
    "addr:housenumber":"926",
    "addr:postcode":"80906",
    "addr:street":"W Cheyenne Rd",
    "iso:country":"US",
    "sg:address":"926 W Cheyenne Rd",
    "sg:city":"Colorado Springs",
    "sg:classifiers":[
        {
            "category":"Real Estate",
            "subcategory":"Real Estate Agent",
            "type":"Services"
        }
    ],
    "sg:phone":"+1 719 634 4202",
    "sg:postcode":"80906",
    "sg:province":"CO",
    "wof:name":"Justice Property Buyers LLC",
    "wof:placetype":"venue"
},
  "geometry": {"coordinates":[-104.84303800000001,38.800891],"type":"Point"}
}