{
  "type": "Feature",
  "properties": {
    "addr:full":"251 Berthoud Trl Broomfield CO 80020",
    "addr:housenumber":"251",
    "addr:postcode":"80020",
    "addr:street":"Berthoud Trl",
    "iso:country":"US",
    "sg:address":"251 Berthoud Trl",
    "sg:city":"Broomfield",
    "sg:classifiers":[
        {
            "category":"Manufacturing",
            "subcategory":"Printing",
            "type":"Manufacturing & Wholesale Goods"
        }
    ],
    "sg:phone":"+1 303 404 8664",
    "sg:postcode":"80020",
    "sg:province":"CO",
    "sg:tags":[
        "publishing"
    ],
    "wof:name":"Connolly Publications Inc",
    "wof:placetype":"venue"
},
  "geometry": {"coordinates":[-105.074078,39.945941],"type":"Point"}
}