{
  "type": "Feature",
  "properties": {
    "iso:country":"US",
    "sg:address":"9625 E Arapahoe Rd",
    "sg:city":"Englewood",
    "sg:classifiers":[
        {
            "category":"Restaurant",
            "type":"Food & Drink"
        }
    ],
    "sg:menulink":"http://www.allmenus.com/co/southwest-arapahoe/258595-samurai/menu/",
    "sg:phone":"+1 303 799 9991",
    "sg:postcode":"80112",
    "sg:province":"CO",
    "sg:tags":[
        "japanese",
        "asian"
    ],
    "wof:name":"Samurai",
    "wof:placetype":"venue"
},
  "geometry": {"coordinates":[-104.8767,39.595706],"type":"Point"}
}