{
  "type": "Feature",
  "properties": {
    "addr:full":"4415 W 35th Ave Denver CO 80212",
    "addr:housenumber":"4415",
    "addr:postcode":"80212",
    "addr:street":"W 35Th Ave",
    "iso:country":"US",
    "sg:address":"4415 W 35th Ave",
    "sg:city":"Denver",
    "sg:classifiers":[
        {
            "category":"Retail",
            "subcategory":"Laundry & Dry Cleaning",
            "type":"Services"
        }
    ],
    "sg:phone":"+1 720 234 3345",
    "sg:postcode":"80212",
    "sg:province":"CO",
    "sg:tags":[
        "chimney"
    ],
    "wof:name":"Town Country Chimney Swee",
    "wof:placetype":"venue"
},
  "geometry": {"coordinates":[-105.044152,39.765739],"type":"Point"}
}