{
  "type": "Feature",
  "properties": {
    "iso:country":"US",
    "sg:address":"310 State Hwy 56",
    "sg:city":"Berthoud",
    "sg:classifiers":[
        {
            "category":"Banks & Credit Unions",
            "subcategory":"Bank",
            "type":"Services"
        }
    ],
    "sg:phone":"+1 970 532 1800",
    "sg:postcode":"80513",
    "sg:province":"CO",
    "sg:website":"www.abtbank.com",
    "wof:name":"Adams Bank & Trust",
    "wof:placetype":"venue"
},
  "geometry": {"coordinates":[-105.04956799999999,40.305291],"type":"Point"}
}