{
  "type": "Feature",
  "properties": {
    "iso:country":"US",
    "sg:address":"3033 E 1st Ave",
    "sg:city":"Denver",
    "sg:classifiers":[
        {
            "category":"Real Estate",
            "subcategory":"Real Estate Agent",
            "type":"Services"
        }
    ],
    "sg:phone":"+1 303 355 7671",
    "sg:postcode":"80206",
    "sg:province":"CO",
    "wof:name":"Prestige Real Estate Group",
    "wof:placetype":"venue"
},
  "geometry": {"coordinates":[-104.951413,39.718243],"type":"Point"}
}