{
  "type": "Feature",
  "properties": {
    "addr:full":"1128 Main St Longmont CO 80501",
    "addr:housenumber":"1128",
    "addr:postcode":"80501",
    "addr:street":"Main St",
    "iso:country":"US",
    "sg:address":"1128 Main St",
    "sg:city":"Longmont",
    "sg:classifiers":[
        {
            "category":"Retail",
            "subcategory":"Auto Rental",
            "type":"Services"
        }
    ],
    "sg:phone":"+1 303 485 8884",
    "sg:postcode":"80501",
    "sg:province":"CO",
    "sg:tags":[
        "renting",
        "leasing",
        "trailer"
    ],
    "sg:website":"http://www.uhaul.com/Locations/Rentals-near-Longmont-CO-80501/049604",
    "wof:name":"U-Haul Neighborhood Dealer - Midtown Rent A Car",
    "wof:placetype":"venue"
},
  "geometry": {"coordinates":[-105.102425,40.178125],"type":"Point"}
}