{
  "type": "Feature",
  "properties": {
    "addr:full":"5350 Washington St Denver CO 80216",
    "addr:housenumber":"5350",
    "addr:postcode":"80216",
    "addr:street":"Washington St",
    "iso:country":"US",
    "sg:address":"5350 Washington St",
    "sg:city":"Denver",
    "sg:classifiers":[
        {
            "category":"Utilities",
            "subcategory":"Refuse",
            "type":"Services"
        }
    ],
    "sg:phone":"+1 303 296 3714",
    "sg:postcode":"80216",
    "sg:province":"CO",
    "sg:tags":[
        "waste",
        "system"
    ],
    "wof:name":"Frontier Mulch Company",
    "wof:placetype":"venue"
},
  "geometry": {"coordinates":[-104.97818700000001,39.792913],"type":"Point"}
}