{
  "type": "Feature",
  "properties": {
    "iso:country":"US",
    "sg:address":"200 S Kalamath St",
    "sg:city":"Denver",
    "sg:classifiers":[
        {
            "category":"Food & Beverages",
            "subcategory":"Liquor & Beverages",
            "type":"Retail Goods"
        },
        {
            "category":"Brewery",
            "type":"Food & Drink"
        }
    ],
    "sg:phone":"+1 303 296 7440",
    "sg:postcode":"80223",
    "sg:province":"CO",
    "sg:tags":[
        "beer",
        "spirit",
        "wine"
    ],
    "sg:website":"www.stranahans.com",
    "wof:name":"Stranahans Colorado Whiskey",
    "wof:placetype":"venue"
},
  "geometry": {"coordinates":[-104.998291,39.712238],"type":"Point"}
}