{
  "type": "Feature",
  "properties": {
    "iso:country":"US",
    "sg:address":"9100 W Quincy Ave",
    "sg:city":"Littleton",
    "sg:classifiers":[
        {
            "category":"Manufacturing",
            "subcategory":"Signs",
            "type":"Manufacturing & Wholesale Goods"
        }
    ],
    "sg:phone":"+1 303 973 0463",
    "sg:postcode":"80123",
    "sg:province":"CO",
    "sg:tags":[
        "specialty",
        "mfg"
    ],
    "wof:name":"Consolidated Sign Co",
    "wof:placetype":"venue"
},
  "geometry": {"coordinates":[-105.100061,39.638665],"type":"Point"}
}