{
  "type": "Feature",
  "properties": {
    "addr:full":"4210 Shining Way Colorado Springs CO 80916",
    "addr:housenumber":"4210",
    "addr:postcode":"80916",
    "addr:street":"Shining Way",
    "iso:country":"US",
    "sg:address":"4210 Shining Way",
    "sg:city":"Colorado Springs",
    "sg:classifiers":[
        {
            "category":"Local Transit",
            "type":"Transportation"
        }
    ],
    "sg:phone":"+1 719 339 4499",
    "sg:postcode":"80916",
    "sg:province":"CO",
    "sg:tags":[
        "passenger",
        "transport"
    ],
    "wof:name":"Redeem Transportation",
    "wof:placetype":"venue"
},
  "geometry": {"coordinates":[-104.749239,38.799965],"type":"Point"}
}