{
  "type": "Feature",
  "properties": {
    "addr:full":"6305 Naturita Trl Colorado Springs CO 80922",
    "addr:housenumber":"6305",
    "addr:postcode":"80922",
    "addr:street":"Naturita Trl",
    "iso:country":"US",
    "sg:address":"6305 Naturita Trl",
    "sg:city":"Colorado Springs",
    "sg:classifiers":[
        {
            "category":"Real Estate",
            "subcategory":"Real Estate Agent",
            "type":"Services"
        }
    ],
    "sg:phone":"+1 719 380 1486",
    "sg:postcode":"80922",
    "sg:province":"CO",
    "wof:name":"Southern Colorado Propert",
    "wof:placetype":"venue"
},
  "geometry": {"coordinates":[-104.70939,38.904847],"type":"Point"}
}