{
  "type": "Feature",
  "properties": {
    "iso:country":"US",
    "sg:address":"5595 Lakeshore Dr",
    "sg:city":"Littleton",
    "sg:classifiers":[
        {
            "category":"Manufacturing",
            "subcategory":"Printing",
            "type":"Manufacturing & Wholesale Goods"
        }
    ],
    "sg:phone":"+1 303 797 1122",
    "sg:postcode":"80123",
    "sg:province":"CO",
    "sg:tags":[
        "periodical"
    ],
    "wof:name":"Exclusively Littleton",
    "wof:placetype":"venue"
},
  "geometry": {"coordinates":[-105.044754,39.617492],"type":"Point"}
}