{
  "type": "Feature",
  "properties": {
    "addr:full":"1740 Sumac Ave Boulder CO 80304",
    "addr:housenumber":"1740",
    "addr:postcode":"80304",
    "addr:street":"Sumac Ave",
    "iso:country":"US",
    "sg:address":"1740 Sumac Ave",
    "sg:city":"Boulder",
    "sg:classifiers":[
        {
            "category":"Health Services",
            "subcategory":"Doctor",
            "type":"Services"
        }
    ],
    "sg:phone":"+1 720 565 1422",
    "sg:postcode":"80304",
    "sg:province":"CO",
    "sg:tags":[
        "physician",
        "surgeon"
    ],
    "wof:name":"Leland M Johnston MD",
    "wof:placetype":"venue"
},
  "geometry": {"coordinates":[-105.273202,40.050726],"type":"Point"}
}