{
  "type": "Feature",
  "properties": {
    "iso:country":"US",
    "sg:address":"1733 Swede Gulch Rd",
    "sg:city":"Golden",
    "sg:classifiers":[
        {
            "category":"Shopping",
            "subcategory":"Clothing, Apparel, & Fashions",
            "type":"Retail Goods"
        }
    ],
    "sg:phone":"+1 720 746 1767",
    "sg:postcode":"80401",
    "sg:province":"CO",
    "sg:tags":[
        "ready",
        "to",
        "wear"
    ],
    "wof:name":"Renatas Clothing",
    "wof:placetype":"venue"
},
  "geometry": {"coordinates":[-105.320211,39.690239],"type":"Point"}
}