{
  "type": "Feature",
  "properties": {
    "addr:full":"1616 17th Street Denver CO 80202",
    "addr:housenumber":"1616",
    "addr:postcode":"80202",
    "addr:street":"17Th Street",
    "iso:country":"US",
    "sg:address":"1616 17th Street",
    "sg:city":"Denver",
    "sg:classifiers":[
        {
            "category":"Organizations",
            "subcategory":"Non-profit Organization",
            "type":"Services"
        }
    ],
    "sg:phone":"+1 303 605 2885",
    "sg:postcode":"80202",
    "sg:province":"CO",
    "sg:tags":[
        "service/non-profit",
        "community"
    ],
    "sg:website":"www.concertsforkids.org",
    "wof:name":"Concerts For Kids",
    "wof:placetype":"venue"
},
  "geometry": {"coordinates":[-104.998997,39.752253],"type":"Point"}
}