{
  "type": "Feature",
  "properties": {
    "iso:country":"US",
    "sg:address":"5447 W Kentucky Ave",
    "sg:city":"Lakewood",
    "sg:classifiers":[
        {
            "category":"Building & Trades",
            "subcategory":"Locksmith",
            "type":"Services"
        }
    ],
    "sg:phone":"+1 303 242 3671",
    "sg:postcode":"80226",
    "sg:province":"CO",
    "sg:tags":[
        "key"
    ],
    "wof:name":"A & A 24 7 Immediate Locksmith",
    "wof:placetype":"venue"
},
  "geometry": {"coordinates":[-105.056499,39.700567],"type":"Point"}
}