{
  "type": "Feature",
  "properties": {
    "iso:country":"US",
    "sg:address":"101 Airport Rd",
    "sg:city":"Glenwood Springs",
    "sg:classifiers":[
        {
            "category":"Organizations",
            "subcategory":"Religious Organization",
            "type":"Services"
        }
    ],
    "sg:phone":"+1 970 945 0510",
    "sg:postcode":"81601",
    "sg:province":"CO",
    "sg:tags":[
        "church"
    ],
    "wof:name":"Kingdom Hall-Jehovah's Witness",
    "wof:placetype":"venue"
},
  "geometry": {"coordinates":[-107.316435,39.507616],"type":"Point"}
}