{
  "type": "Feature",
  "properties": {
    "addr:full":"1290 Cody St Denver CO 80215",
    "addr:housenumber":"1290",
    "addr:postcode":"80215",
    "addr:street":"Cody St",
    "iso:country":"US",
    "sg:address":"1290 Cody St",
    "sg:city":"Denver",
    "sg:classifiers":[
        {
            "category":"Organizations",
            "subcategory":"Community Association",
            "type":"Services"
        }
    ],
    "sg:phone":"+1 303 237 0620",
    "sg:postcode":"80215",
    "sg:province":"CO",
    "sg:tags":[
        "veteran",
        "fraternal"
    ],
    "wof:name":"Air Force Sergeants Assn",
    "wof:placetype":"venue"
},
  "geometry": {"coordinates":[-105.092499,39.733022],"type":"Point"}
}