{
  "type": "Feature",
  "properties": {
    "addr:full":"1720 Santa Fe Dr Pueblo CO 81006",
    "addr:housenumber":"1720",
    "addr:postcode":"81006",
    "addr:street":"Santa Fe Dr",
    "iso:country":"US",
    "sg:address":"1720 Santa Fe Dr",
    "sg:city":"Pueblo",
    "sg:classifiers":[
        {
            "category":"Cinema",
            "subcategory":"Movie Rental",
            "type":"Entertainment"
        }
    ],
    "sg:phone":"+1 719 404 0600",
    "sg:postcode":"81006",
    "sg:province":"CO",
    "sg:tags":[
        "leasing",
        "video",
        "disc",
        "tape"
    ],
    "wof:name":"Video HITS & Games",
    "wof:placetype":"venue"
},
  "geometry": {"coordinates":[-104.578329,38.245547],"type":"Point"}
}