{
  "type": "Feature",
  "properties": {
    "iso:country":"US",
    "sg:address":"3864 S Elm St",
    "sg:city":"Denver",
    "sg:classifiers":[
        {
            "category":"Building & Trades",
            "subcategory":"Construction",
            "type":"Services"
        }
    ],
    "sg:phone":"+1 303 756 4794",
    "sg:postcode":"80237",
    "sg:province":"CO",
    "sg:tags":[
        "general",
        "contractor"
    ],
    "wof:name":"Harold E Bergkamp Inc",
    "wof:placetype":"venue"
},
  "geometry": {"coordinates":[-104.93059700000001,39.647445],"type":"Point"}
}