{
  "type": "Feature",
  "properties": {
    "iso:country":"US",
    "sg:address":"28145 State Hwy 74",
    "sg:city":"Evergreen",
    "sg:classifiers":[
        {
            "category":"Banks & Credit Unions",
            "subcategory":"Investment Brokerage",
            "type":"Services"
        }
    ],
    "sg:phone":"+1 303 674 8579",
    "sg:postcode":"80439",
    "sg:province":"CO",
    "sg:tags":[
        "stock",
        "bond"
    ],
    "wof:name":"Linsco Private Ledger",
    "wof:placetype":"venue"
},
  "geometry": {"coordinates":[-105.317531,39.633762],"type":"Point"}
}