{
  "type": "Feature",
  "properties": {
    "addr:full":"2329 E Mulberry St Fort Collins CO 80524",
    "addr:housenumber":"2329",
    "addr:postcode":"80524",
    "addr:street":"E Mulberry St",
    "iso:country":"US",
    "sg:address":"2329 E Mulberry St",
    "sg:city":"Fort Collins",
    "sg:classifiers":[
        {
            "category":"Home & Garden",
            "subcategory":"Building Materials",
            "type":"Retail Goods"
        }
    ],
    "sg:phone":"+1 970 493 1225",
    "sg:postcode":"80524",
    "sg:province":"CO",
    "sg:tags":[
        "plumbing",
        "fixture",
        "supply"
    ],
    "wof:name":"RNR Supply",
    "wof:placetype":"venue"
},
  "geometry": {"coordinates":[-105.037515,40.580608],"type":"Point"}
}