{
  "type": "Feature",
  "properties": {
    "addr:full":"949 Quince Ave Boulder CO 80304",
    "addr:housenumber":"949",
    "addr:postcode":"80304",
    "addr:street":"Quince Ave",
    "iso:country":"US",
    "sg:address":"949 Quince Ave",
    "sg:city":"Boulder",
    "sg:classifiers":[
        {
            "category":"Food & Beverages",
            "subcategory":"Bakery",
            "type":"Retail Goods"
        }
    ],
    "sg:phone":"+1 303 449 0688",
    "sg:postcode":"80304",
    "sg:province":"CO",
    "wof:name":"Boulder Bread Co Inc",
    "wof:placetype":"venue"
},
  "geometry": {"coordinates":[-105.282087,40.04801],"type":"Point"}
}