{
  "type": "Feature",
  "properties": {
    "addr:full":"105 S Hollywood St Fort Collins CO 80521",
    "addr:housenumber":"105",
    "addr:postcode":"80521",
    "addr:street":"S Hollywood St",
    "iso:country":"US",
    "sg:address":"105 S Hollywood St",
    "sg:city":"Fort Collins",
    "sg:classifiers":[
        {
            "category":"Building & Trades",
            "subcategory":"Landscaping Services",
            "type":"Services"
        }
    ],
    "sg:phone":"+1 970 416 8404",
    "sg:postcode":"80521",
    "sg:province":"CO",
    "wof:name":"Niemanns Trees",
    "wof:placetype":"venue"
},
  "geometry": {"coordinates":[-105.129119,40.58544],"type":"Point"}
}