{
  "type": "Feature",
  "properties": {
    "addr:full":"2925 E Maplewood Ave Littleton CO 80121",
    "addr:housenumber":"2925",
    "addr:postcode":"80121",
    "addr:street":"E Maplewood Ave",
    "iso:country":"US",
    "sg:address":"2925 E Maplewood Ave",
    "sg:city":"Littleton",
    "sg:classifiers":[
        {
            "category":"Real Estate",
            "subcategory":"Real Estate Agent",
            "type":"Services"
        }
    ],
    "sg:phone":"+1 303 797 0837",
    "sg:postcode":"80121",
    "sg:province":"CO",
    "wof:name":"Behrens Real Estate Management",
    "wof:placetype":"venue"
},
  "geometry": {"coordinates":[-104.954256,39.603864],"type":"Point"}
}