{
  "type": "Feature",
  "properties": {
    "iso:country":"US",
    "sg:address":"205 S Mill St",
    "sg:city":"Aspen",
    "sg:classifiers":[
        {
            "category":"Real Estate",
            "subcategory":"Real Estate Agent",
            "type":"Services"
        }
    ],
    "sg:phone":"+1 970 920 2006",
    "sg:postcode":"81611",
    "sg:province":"CO",
    "wof:name":"Buyers Broker",
    "wof:placetype":"venue"
},
  "geometry": {"coordinates":[-106.81958899999999,39.189837],"type":"Point"}
}