{
  "type": "Feature",
  "properties": {
    "iso:country":"US",
    "sg:address":"2525 E 13th Ave",
    "sg:city":"Denver",
    "sg:classifiers":[
        {
            "category":"Health Services",
            "subcategory":"Doctor",
            "type":"Services"
        }
    ],
    "sg:phone":"+1 303 338 4545",
    "sg:postcode":"80206",
    "sg:province":"CO",
    "sg:website":"www.kaiserpermanente.org",
    "wof:name":"Kaiser Permanente Health Care Program",
    "wof:placetype":"venue"
},
  "geometry": {"coordinates":[-104.957162,39.736828],"type":"Point"}
}