{
  "type": "Feature",
  "properties": {
    "iso:country":"US",
    "sg:address":"8267 S Xenia Ct",
    "sg:city":"Centennial",
    "sg:classifiers":[
        {
            "category":"Arts & Performance",
            "subcategory":"Theater",
            "type":"Entertainment"
        }
    ],
    "sg:phone":"+1 303 770 7191",
    "sg:postcode":"80112",
    "sg:province":"CO",
    "sg:tags":[
        "musician"
    ],
    "wof:name":"Tina Lindsay Weddings",
    "wof:placetype":"venue"
},
  "geometry": {"coordinates":[-104.886708,39.567015],"type":"Point"}
}