{
  "type": "Feature",
  "properties": {
    "addr:full":"19160 Beacon Lite Rd Monument CO 80132",
    "addr:housenumber":"19160",
    "addr:postcode":"80132",
    "addr:street":"Beacon Lite Rd",
    "iso:country":"US",
    "sg:address":"19160 Beacon Lite Rd",
    "sg:city":"Monument",
    "sg:classifiers":[
        {
            "category":"Building & Trades",
            "subcategory":"Construction",
            "type":"Services"
        }
    ],
    "sg:phone":"+1 719 488 8561",
    "sg:postcode":"80132",
    "sg:province":"CO",
    "sg:tags":[
        "carpentry",
        "contractor"
    ],
    "wof:name":"Nemmers Construction",
    "wof:placetype":"venue"
},
  "geometry": {"coordinates":[-104.867867,39.110392],"type":"Point"}
}