{
  "type": "Feature",
  "properties": {
    "iso:country":"US",
    "sg:address":"3555 S Clarkson St",
    "sg:city":"Englewood",
    "sg:classifiers":[
        {
            "category":"Health Services",
            "subcategory":"Health Practitioner",
            "type":"Services"
        }
    ],
    "sg:phone":"+1 303 762 0653",
    "sg:postcode":"80113",
    "sg:province":"CO",
    "sg:tags":[
        "psychologist"
    ],
    "wof:name":"Diana Bray",
    "wof:placetype":"venue"
},
  "geometry": {"coordinates":[-104.97833900000001,39.652789],"type":"Point"}
}