{
  "type": "Feature",
  "properties": {
    "addr:full":"541 E 80th Ave Denver CO 80229",
    "addr:housenumber":"541",
    "addr:postcode":"80229",
    "addr:street":"E 80Th Ave",
    "iso:country":"US",
    "sg:address":"541 E 80th Ave",
    "sg:city":"Denver",
    "sg:classifiers":[
        {
            "category":"Retail",
            "subcategory":"Auto Repair",
            "type":"Services"
        }
    ],
    "sg:phone":"+1 303 287 0544",
    "sg:postcode":"80229",
    "sg:province":"CO",
    "sg:tags":[
        "repairing",
        "automobile"
    ],
    "wof:name":"Julian Auto Repair",
    "wof:placetype":"venue"
},
  "geometry": {"coordinates":[-104.979195,39.8418],"type":"Point"}
}