{
  "type": "Feature",
  "properties": {
    "addr:full":"11760 W 26th Ave Denver CO 80215",
    "addr:housenumber":"11760",
    "addr:postcode":"80215",
    "addr:street":"W 26Th Ave",
    "iso:country":"US",
    "sg:address":"11760 W 26th Ave",
    "sg:city":"Denver",
    "sg:classifiers":[
        {
            "category":"Building & Trades",
            "subcategory":"Construction",
            "type":"Services"
        }
    ],
    "sg:phone":"+1 303 274 4841",
    "sg:postcode":"80215",
    "sg:province":"CO",
    "sg:tags":[
        "house"
    ],
    "wof:name":"Finishing Touches",
    "wof:placetype":"venue"
},
  "geometry": {"coordinates":[-105.131236,39.754561],"type":"Point"}
}