{
  "type": "Feature",
  "properties": {
    "iso:country":"US",
    "sg:address":"5407 Marshall Street",
    "sg:city":"Arvada",
    "sg:classifiers":[
        {
            "category":"Professional",
            "subcategory":"Accounting & Tax Preparation",
            "type":"Services"
        }
    ],
    "sg:phone":"+1 303 424 3321",
    "sg:postcode":"80002",
    "sg:province":"CO",
    "sg:tags":[
        "accountant"
    ],
    "wof:name":"McQueen Edith B",
    "wof:placetype":"venue"
},
  "geometry": {"coordinates":[-105.06871099999999,39.794644],"type":"Point"}
}