{
  "type": "Feature",
  "properties": {
    "addr:full":"130 Grace Ave Woodland Park CO 80863",
    "addr:housenumber":"130",
    "addr:postcode":"80863",
    "addr:street":"Grace Ave",
    "iso:country":"US",
    "sg:address":"130 Grace Ave",
    "sg:city":"Woodland Park",
    "sg:classifiers":[
        {
            "category":"Freight",
            "type":"Transportation"
        }
    ],
    "sg:phone":"+1 719 687 6042",
    "sg:postcode":"80863",
    "sg:province":"CO",
    "sg:tags":[
        "commercial",
        "storage",
        "special"
    ],
    "wof:name":"A-Z Storage",
    "wof:placetype":"venue"
},
  "geometry": {"coordinates":[-105.051817,38.993684],"type":"Point"}
}