{
  "type": "Feature",
  "properties": {
    "addr:full":"6131 E Willowmore Ct Littleton CO 80130",
    "addr:housenumber":"6131",
    "addr:postcode":"80130",
    "addr:street":"E Willowmore Ct",
    "iso:country":"US",
    "sg:address":"6131 E Willowmore Ct",
    "sg:city":"Littleton",
    "sg:classifiers":[
        {
            "category":"Professional",
            "subcategory":"Business Services",
            "type":"Services"
        }
    ],
    "sg:phone":"+1 303 791 9551",
    "sg:postcode":"80130",
    "sg:province":"CO",
    "sg:tags":[
        "financial"
    ],
    "wof:name":"Successful Solutions Inc",
    "wof:placetype":"venue"
},
  "geometry": {"coordinates":[-104.917197,39.554147],"type":"Point"}
}