{
  "type": "Feature",
  "properties": {
    "iso:country":"US",
    "sg:address":"556 Main St",
    "sg:city":"Louisville",
    "sg:classifiers":[
        {
            "category":"Manufacturing",
            "subcategory":"Tools & Machinery",
            "type":"Manufacturing & Wholesale Goods"
        }
    ],
    "sg:phone":"+1 303 903 5706",
    "sg:postcode":"80027",
    "sg:province":"CO",
    "sg:tags":[
        "woodworking",
        "mfg"
    ],
    "wof:name":"Old Town Woodworks",
    "wof:placetype":"venue"
},
  "geometry": {"coordinates":[-105.132016,39.974288],"type":"Point"}
}