{
  "type": "Feature",
  "properties": {
    "iso:country":"US",
    "sg:address":"3330 S Glen Ave",
    "sg:city":"Glenwood Springs",
    "sg:classifiers":[
        {
            "category":"Building & Trades",
            "subcategory":"Construction",
            "type":"Services"
        }
    ],
    "sg:phone":"+1 970 945 8835",
    "sg:postcode":"81601",
    "sg:province":"CO",
    "wof:name":"Mor-Storage Sales",
    "wof:placetype":"venue"
},
  "geometry": {"coordinates":[-107.318523,39.517463],"type":"Point"}
}