{
  "type": "Feature",
  "properties": {
    "addr:full":"3260 Noble Ct Boulder CO 80301",
    "addr:housenumber":"3260",
    "addr:postcode":"80301",
    "addr:street":"Noble Ct",
    "iso:country":"US",
    "sg:address":"3260 Noble Ct",
    "sg:city":"Boulder",
    "sg:classifiers":[
        {
            "category":"Professional",
            "type":"Services"
        }
    ],
    "sg:phone":"+1 303 447 0114",
    "sg:postcode":"80301",
    "sg:province":"CO",
    "sg:tags":[
        "establishment"
    ],
    "wof:name":"Transformational Strategies",
    "wof:placetype":"venue"
},
  "geometry": {"coordinates":[-105.23886299999999,40.03254],"type":"Point"}
}