{
  "type": "Feature",
  "properties": {
    "addr:full":"107 Wolfensberger Rd Castle Rock CO 80109",
    "addr:housenumber":"107",
    "addr:postcode":"80109",
    "addr:street":"Wolfensberger Rd",
    "iso:country":"US",
    "sg:address":"107 Wolfensberger Rd",
    "sg:city":"Castle Rock",
    "sg:classifiers":[
        {
            "category":"Restaurant",
            "type":"Food & Drink"
        }
    ],
    "sg:menulink":"http://www.allmenus.com/co/castle-rock/207858-taco-bell/menu/",
    "sg:phone":"+1 303 688 8525",
    "sg:postcode":"80109",
    "sg:province":"CO",
    "sg:tags":[
        "mexican"
    ],
    "wof:name":"Taco Bell",
    "wof:placetype":"venue"
},
  "geometry": {"coordinates":[-104.896164,39.362859],"type":"Point"}
}