{
  "type": "Feature",
  "properties": {
    "addr:full":"4651 Tulsa Ct Denver CO 80239",
    "addr:housenumber":"4651",
    "addr:postcode":"80239",
    "addr:street":"Tulsa Ct",
    "iso:country":"US",
    "sg:address":"4651 Tulsa Ct",
    "sg:city":"Denver",
    "sg:classifiers":[
        {
            "category":"Organizations",
            "subcategory":"Religious Organization",
            "type":"Services"
        }
    ],
    "sg:phone":"+1 303 576 8408",
    "sg:postcode":"80239",
    "sg:province":"CO",
    "sg:tags":[
        "church"
    ],
    "wof:name":"Love Christian Fellowship",
    "wof:placetype":"venue"
},
  "geometry": {"coordinates":[-104.84044,39.782154],"type":"Point"}
}