{
  "type": "Feature",
  "properties": {
    "iso:country":"US",
    "sg:address":"3050 ILLINOIS ST",
    "sg:city":"GOLDEN",
    "sg:classifiers":[
        {
            "category":"Shopping",
            "subcategory":"Bicycles & Sporting Goods",
            "type":"Retail Goods"
        },
        {
            "category":"Sports & Exercise",
            "subcategory":"Golf",
            "type":"Entertainment"
        },
        {
            "category":"Organizations",
            "subcategory":"Membership Organization",
            "type":"Services"
        }
    ],
    "sg:phone":"+1 303 277 8750",
    "sg:postcode":"80401",
    "sg:province":"CO",
    "sg:tags":[
        "course",
        "club",
        "practice",
        "private",
        "equipment",
        "range",
        "supply"
    ],
    "sg:website":"http://www.fossiltrace.com",
    "wof:name":"Fossil Trace Golf Club",
    "wof:placetype":"venue"
},
  "geometry": {"coordinates":[-105.210991,39.735713],"type":"Point"}
}