{
  "type": "Feature",
  "properties": {
    "addr:full":"1120 Xenia St Denver CO 80220",
    "addr:housenumber":"1120",
    "addr:postcode":"80220",
    "addr:street":"Xenia St",
    "iso:country":"US",
    "sg:address":"1120 Xenia St",
    "sg:city":"Denver",
    "sg:classifiers":[
        {
            "category":"Building & Trades",
            "subcategory":"Construction",
            "type":"Services"
        }
    ],
    "sg:phone":"+1 303 322 9539",
    "sg:postcode":"80220",
    "sg:province":"CO",
    "sg:tags":[
        "concrete",
        "contractor"
    ],
    "wof:name":"Concrete Quinns",
    "wof:placetype":"venue"
},
  "geometry": {"coordinates":[-104.885792,39.733637],"type":"Point"}
}