{
  "type": "Feature",
  "properties": {
    "addr:full":"608 Main St Walsenburg CO 81089",
    "addr:housenumber":"608",
    "addr:postcode":"81089",
    "addr:street":"Main St",
    "iso:country":"US",
    "sg:address":"608 Main St",
    "sg:city":"Walsenburg",
    "sg:classifiers":[
        {
            "category":"Organizations",
            "subcategory":"Non-profit Organization",
            "type":"Services"
        }
    ],
    "sg:phone":"+1 719 738 2291",
    "sg:postcode":"81089",
    "sg:province":"CO",
    "sg:tags":[
        "charitable",
        "institution"
    ],
    "wof:name":"Dorcus Circle Clothing Bank",
    "wof:placetype":"venue"
},
  "geometry": {"coordinates":[-104.780749,37.623612],"type":"Point"}
}