{
  "type": "Feature",
  "properties": {
    "addr:full":"1521 State Hwy 209 Boone CO 81025",
    "addr:housenumber":"1521",
    "addr:postcode":"81025",
    "addr:street":"State Hwy 209",
    "iso:country":"US",
    "sg:address":"1521 State Hwy 209",
    "sg:city":"Boone",
    "sg:classifiers":[
        {
            "category":"Farming",
            "subcategory":"Livestock Farm",
            "type":"Manufacturing & Wholesale Goods"
        }
    ],
    "sg:phone":"+1 719 947 3230",
    "sg:postcode":"81025",
    "sg:province":"CO",
    "sg:tags":[
        "ranch",
        "animal",
        "general"
    ],
    "wof:name":"El Slash Land & Cattle LLC",
    "wof:placetype":"venue"
},
  "geometry": {"coordinates":[-104.26190099999999,38.228755],"type":"Point"}
}