{
  "type": "Feature",
  "properties": {
    "iso:country":"US",
    "sg:address":"2225 S Jasmine St",
    "sg:city":"Denver",
    "sg:classifiers":[
        {
            "category":"Organizations",
            "subcategory":"Professional Association",
            "type":"Services"
        }
    ],
    "sg:phone":"+1 720 274 2918",
    "sg:postcode":"80222",
    "sg:province":"CO",
    "wof:name":"Jasmine Condominium Assn",
    "wof:placetype":"venue"
},
  "geometry": {"coordinates":[-104.918798,39.674844],"type":"Point"}
}