{
  "type": "Feature",
  "properties": {
    "iso:country":"US",
    "sg:address":"20 Wood Haven Way",
    "sg:city":"Durango",
    "sg:classifiers":[
        {
            "category":"Building & Trades",
            "subcategory":"Construction",
            "type":"Services"
        }
    ],
    "sg:phone":"+1 970 385 4951",
    "sg:postcode":"81303",
    "sg:province":"CO",
    "sg:tags":[
        "house"
    ],
    "wof:name":"Brown Construction Bill",
    "wof:placetype":"venue"
},
  "geometry": {"coordinates":[-107.998462,37.266155],"type":"Point"}
}