{
  "type": "Feature",
  "properties": {
    "addr:full":"4415 S Newton St Denver CO 80236",
    "addr:housenumber":"4415",
    "addr:postcode":"80236",
    "addr:street":"S Newton St",
    "iso:country":"US",
    "sg:address":"4415 S Newton St",
    "sg:city":"Denver",
    "sg:classifiers":[
        {
            "category":"Building & Trades",
            "subcategory":"Construction",
            "type":"Services"
        }
    ],
    "sg:phone":"+1 303 795 6820",
    "sg:postcode":"80236",
    "sg:province":"CO",
    "sg:tags":[
        "concrete",
        "contractor"
    ],
    "wof:name":"Spinstar Concrete Inc",
    "wof:placetype":"venue"
},
  "geometry": {"coordinates":[-105.03680199999999,39.636811],"type":"Point"}
}