{
  "type": "Feature",
  "properties": {
    "addr:full":"1050 Co Rd Jj Fowler CO 81039",
    "addr:housenumber":"1050",
    "addr:postcode":"fowler;81039",
    "addr:street":"Co Rd",
    "iso:country":"US",
    "sg:address":"1050 Co Rd Jj",
    "sg:city":"Fowler",
    "sg:classifiers":[
        {
            "category":"Retail",
            "subcategory":"Veterinary Services",
            "type":"Services"
        }
    ],
    "sg:phone":"+1 719 263 4321",
    "sg:postcode":"81039",
    "sg:province":"CO",
    "wof:name":"Richard T Leone Dvm",
    "wof:placetype":"venue"
},
  "geometry": {"coordinates":[-104.05583300000001,38.092712],"type":"Point"}
}