{
  "type": "Feature",
  "properties": {
    "addr:full":"110 Broadway Denver CO 80203",
    "addr:housenumber":"110",
    "addr:postcode":"80203",
    "addr:street":"Broadway",
    "iso:country":"US",
    "sg:address":"110 Broadway",
    "sg:city":"Denver",
    "sg:classifiers":[
        {
            "category":"Cinema",
            "subcategory":"Movie Theater",
            "type":"Entertainment"
        }
    ],
    "sg:phone":"+1 303 744 6796",
    "sg:postcode":"80203",
    "sg:province":"CO",
    "sg:website":"www.landmarktheatres.com/Market/...",
    "wof:name":"Mayan Theater",
    "wof:placetype":"venue"
},
  "geometry": {"coordinates":[-104.98699999999999,39.7187],"type":"Point"}
}