{
  "type": "Feature",
  "properties": {
    "iso:country":"US",
    "sg:address":"231 Lincoln Ct",
    "sg:city":"Fort Collins",
    "sg:classifiers":[
        {
            "category":"Wholesale",
            "subcategory":"Auto Parts",
            "type":"Manufacturing & Wholesale Goods"
        }
    ],
    "sg:phone":"+1 970 482 1858",
    "sg:postcode":"80524",
    "sg:province":"CO",
    "wof:name":"Car Color",
    "wof:placetype":"venue"
},
  "geometry": {"coordinates":[-105.046182,40.584537],"type":"Point"}
}