{
  "type": "Feature",
  "properties": {
    "addr:full":"210 Offerson Rd Avon CO 81620",
    "addr:housenumber":"210",
    "addr:postcode":"81620",
    "addr:street":"Offerson Rd",
    "iso:country":"US",
    "sg:address":"210 Offerson Rd",
    "sg:city":"Avon",
    "sg:classifiers":[
        {
            "category":"Home & Garden",
            "subcategory":"Garden Supply",
            "type":"Retail Goods"
        }
    ],
    "sg:phone":"+1 970 845 9559",
    "sg:postcode":"81620",
    "sg:province":"CO",
    "sg:tags":[
        "tree",
        "christmas"
    ],
    "wof:name":"Noel The Christmas Shop",
    "wof:placetype":"venue"
},
  "geometry": {"coordinates":[-106.514551,39.605033],"type":"Point"}
}