{
  "type": "Feature",
  "properties": {
    "iso:country":"US",
    "sg:address":"407 Aabc",
    "sg:city":"Aspen",
    "sg:classifiers":[
        {
            "category":"Wholesale",
            "subcategory":"Stationery",
            "type":"Manufacturing & Wholesale Goods"
        }
    ],
    "sg:phone":"+1 970 925 6554",
    "sg:postcode":"81611",
    "sg:province":"CO",
    "sg:tags":[
        "paper",
        "product",
        "printing",
        "fine"
    ],
    "wof:name":"Chandler Woods Pulp & Paper Co",
    "wof:placetype":"venue"
},
  "geometry": {"coordinates":[-106.860367,39.218649],"type":"Point"}
}