{
  "type": "Feature",
  "properties": {
    "addr:full":"26 S Broadway Denver CO 80209",
    "addr:housenumber":"26",
    "addr:postcode":"80209",
    "addr:street":"S Broadway",
    "iso:country":"US",
    "sg:address":"26 S Broadway",
    "sg:city":"Denver",
    "sg:classifiers":[
        {
            "category":"Building & Trades",
            "subcategory":"Locksmith",
            "type":"Services"
        }
    ],
    "sg:phone":"+1 303 729 0681",
    "sg:postcode":"80209",
    "sg:province":"CO",
    "sg:tags":[
        "key"
    ],
    "wof:name":"All Around Locksmith",
    "wof:placetype":"venue"
},
  "geometry": {"coordinates":[-104.987337,39.716068],"type":"Point"}
}