{
  "type": "Feature",
  "properties": {
    "addr:full":"2409 Arapahoe St Denver CO 80205",
    "addr:housenumber":"2409",
    "addr:postcode":"80205",
    "addr:street":"Arapahoe St",
    "iso:country":"US",
    "sg:address":"2409 Arapahoe St",
    "sg:city":"Denver",
    "sg:classifiers":[
        {
            "category":"Education",
            "subcategory":"School",
            "type":"Public Place"
        }
    ],
    "sg:phone":"+1 303 292 0430",
    "sg:postcode":"80205",
    "sg:province":"CO",
    "sg:tags":[
        "high",
        "middle",
        "elementary"
    ],
    "wof:name":"Denver Venture School",
    "wof:placetype":"venue"
},
  "geometry": {"coordinates":[-104.986006,39.755513],"type":"Point"}
}