{
  "type": "Feature",
  "properties": {
    "addr:full":"3457 Ringsby Court Suite 101C Denver CO 80216",
    "addr:housenumber":"3457",
    "addr:postcode":"80216",
    "addr:street":"Ringsby Court Suite 101C",
    "iso:country":"US",
    "sg:address":"3457 Ringsby Court Suite 101C",
    "sg:city":"Denver",
    "sg:classifiers":[
        {
            "category":"Professional",
            "subcategory":"Advertising",
            "type":"Services"
        }
    ],
    "sg:phone":"+1 303 292 1414",
    "sg:postcode":"80216",
    "sg:province":"CO",
    "sg:tags":[
        "yield-managment",
        "online-advertising",
        "ad-network",
        "advertising-rep-firm",
        "online-ad-sales",
        "cpm-networks",
        "ad-agency"
    ],
    "sg:website":"http://www.altitudedigitalpartners.com",
    "wof:name":"Altitude Digital Partners",
    "wof:placetype":"venue"
},
  "geometry": {"coordinates":[-104.981531,39.772005],"type":"Point"}
}