{
  "type": "Feature",
  "properties": {
    "iso:country":"US",
    "sg:address":"12575 Wolff St",
    "sg:city":"Broomfield",
    "sg:classifiers":[
        {
            "category":"Insurance",
            "subcategory":"Insurance Agent",
            "type":"Services"
        }
    ],
    "sg:phone":"+1 303 464 1911",
    "sg:postcode":"80020",
    "sg:province":"CO",
    "wof:name":"Neil Deutsch Insurance Agency",
    "wof:placetype":"venue"
},
  "geometry": {"coordinates":[-105.04821699999999,39.924307],"type":"Point"}
}