{
  "type": "Feature",
  "properties": {
    "addr:full":"4000 Quebec St Denver CO 80216",
    "addr:housenumber":"4000",
    "addr:postcode":"80216",
    "addr:street":"Quebec St",
    "iso:country":"US",
    "sg:address":"4000 Quebec St",
    "sg:city":"Denver",
    "sg:classifiers":[
        {
            "category":"Banks & Credit Unions",
            "subcategory":"Bank",
            "type":"Services"
        }
    ],
    "sg:phone":"+1 303 388 8823",
    "sg:postcode":"80216",
    "sg:province":"CO",
    "wof:name":"Denver Postal Credit Union",
    "wof:placetype":"venue"
},
  "geometry": {"coordinates":[-104.902,39.772598],"type":"Point"}
}