{
  "type": "Feature",
  "properties": {
    "iso:country":"US",
    "sg:address":"1993 Meadow Vale Rd",
    "sg:city":"Longmont",
    "sg:classifiers":[
        {
            "category":"Professional",
            "type":"Services"
        }
    ],
    "sg:phone":"+1 303 678 1575",
    "sg:postcode":"80504",
    "sg:province":"CO",
    "wof:name":"Tonya T Bean",
    "wof:placetype":"venue"
},
  "geometry": {"coordinates":[-105.013685,40.166749],"type":"Point"}
}