{
  "type": "Feature",
  "properties": {
    "addr:full":"9568 S University Blvd Highlands Ranch CO 80126",
    "addr:housenumber":"9568",
    "addr:postcode":"80126",
    "addr:street":"S University Blvd",
    "iso:country":"US",
    "sg:address":"9568 S University Blvd",
    "sg:city":"Highlands Ranch",
    "sg:classifiers":[
        {
            "category":"Organizations",
            "subcategory":"Professional Association",
            "type":"Services"
        }
    ],
    "sg:phone":"+1 303 791 8958",
    "sg:postcode":"80126",
    "sg:province":"CO",
    "sg:website":"www.hrcaonline.org",
    "wof:name":"Highlands Ranch Community Assn",
    "wof:placetype":"venue"
},
  "geometry": {"coordinates":[-104.94246800000001,39.543656],"type":"Point"}
}