{
  "type": "Feature",
  "properties": {
    "addr:full":"2174 S Williams St Denver CO 80210",
    "addr:housenumber":"2174",
    "addr:postcode":"80210",
    "addr:street":"S Williams St",
    "iso:country":"US",
    "sg:address":"2174 S Williams St",
    "sg:city":"Denver",
    "sg:classifiers":[
        {
            "category":"Professional",
            "subcategory":"Art Services",
            "type":"Services"
        }
    ],
    "sg:phone":"+1 303 744 7411",
    "sg:postcode":"80210",
    "sg:province":"CO",
    "sg:tags":[
        "graphic",
        "designer"
    ],
    "wof:name":"Mark Kimbrel Design",
    "wof:placetype":"venue"
},
  "geometry": {"coordinates":[-104.966329,39.678034],"type":"Point"}
}