{
  "type": "Feature",
  "properties": {
    "addr:full":"6522 Fig St Arvada CO 80004",
    "addr:housenumber":"6522",
    "addr:postcode":"80004",
    "addr:street":"Fig St",
    "iso:country":"US",
    "sg:address":"6522 Fig St",
    "sg:city":"Arvada",
    "sg:classifiers":[
        {
            "category":"Recreation",
            "type":"Entertainment"
        }
    ],
    "sg:phone":"+1 303 237 8976",
    "sg:postcode":"80004",
    "sg:province":"CO",
    "sg:tags":[
        "instruction",
        "gymnastic"
    ],
    "wof:name":"Gymnastika",
    "wof:placetype":"venue"
},
  "geometry": {"coordinates":[-105.158323,39.814525],"type":"Point"}
}