{
  "type": "Feature",
  "properties": {
    "iso:country":"US",
    "sg:address":"28753 Hwy 160",
    "sg:city":"Durango",
    "sg:classifiers":[
        {
            "category":"Retail",
            "subcategory":"Auto Repair",
            "type":"Services"
        }
    ],
    "sg:phone":"+1 970 247 4651",
    "sg:postcode":"81301",
    "sg:province":"CO",
    "sg:tags":[
        "vehicle",
        "recreational",
        "towing",
        "general"
    ],
    "wof:name":"Aa American Auto Sales",
    "wof:placetype":"venue"
},
  "geometry": {"coordinates":[-107.824482,37.228023],"type":"Point"}
}