{
  "type": "Feature",
  "properties": {
    "iso:country":"US",
    "sg:address":"701 S Franklin St",
    "sg:city":"Denver",
    "sg:classifiers":[
        {
            "category":"Professional",
            "type":"Services"
        }
    ],
    "sg:phone":"+1 303 494 4242",
    "sg:postcode":"80209",
    "sg:province":"CO",
    "sg:website":"bcor.net/the-boot-camp-diet/",
    "wof:name":"The Boot Camp Diet",
    "wof:placetype":"venue"
},
  "geometry": {"coordinates":[-104.97104899999999,39.70025],"type":"Point"}
}