{
  "type": "Feature",
  "properties": {
    "addr:full":"929 38th Avenue Ct Greeley CO 80634",
    "addr:housenumber":"929",
    "addr:postcode":"80634",
    "addr:street":"38Th Avenue Ct",
    "iso:country":"US",
    "sg:address":"929 38th Avenue Ct",
    "sg:city":"Greeley",
    "sg:classifiers":[
        {
            "category":"Insurance",
            "subcategory":"Insurance Agent",
            "type":"Services"
        }
    ],
    "sg:phone":"+1 970 353 8900",
    "sg:postcode":"80634",
    "sg:province":"CO",
    "wof:name":"Farmers Insurance Group",
    "wof:placetype":"venue"
},
  "geometry": {"coordinates":[-104.74263500000001,40.423925],"type":"Point"}
}