{
  "type": "Feature",
  "properties": {
    "addr:full":"5655 Greenwood Plaza Blvd Greenwood Vlg CO 80111",
    "addr:housenumber":"5655",
    "addr:postcode":"co 80111",
    "addr:street":"Greenwood Plaza Blvd",
    "iso:country":"US",
    "sg:address":"5655 Greenwood Plaza Blvd",
    "sg:city":"Greenwood Vlg",
    "sg:classifiers":[
        {
            "category":"Banks & Credit Unions",
            "subcategory":"Bank",
            "type":"Services"
        }
    ],
    "sg:phone":"+1 720 488 6707",
    "sg:postcode":"80111",
    "sg:province":"CO",
    "sg:tags":[
        "loan",
        "real estate"
    ],
    "wof:name":"Landmark Financial Inc",
    "wof:placetype":"venue"
},
  "geometry": {"coordinates":[-104.89748299999999,39.613412],"type":"Point"}
}