{
  "type": "Feature",
  "properties": {
    "addr:full":"7156 E County Line Rd Littleton CO 80126",
    "addr:housenumber":"7156",
    "addr:postcode":"80126",
    "addr:street":"E County Line Rd",
    "iso:country":"US",
    "sg:address":"7156 E County Line Rd",
    "sg:city":"Littleton",
    "sg:classifiers":[
        {
            "category":"Restaurant",
            "type":"Food & Drink"
        }
    ],
    "sg:phone":"+1 303 721 7337",
    "sg:postcode":"80126",
    "sg:province":"CO",
    "sg:tags":[
        "style",
        "family"
    ],
    "sg:website":"http://www.lepeep.com",
    "wof:name":"Le Peep",
    "wof:placetype":"venue"
},
  "geometry": {"coordinates":[-104.906475,39.56593],"type":"Point"}
}