{
  "type": "Feature",
  "properties": {
    "iso:country":"US",
    "sg:address":"305 State St",
    "sg:city":"Trinidad",
    "sg:classifiers":[
        {
            "category":"Autos & Motor Vehicles",
            "subcategory":"Fuel & Gas Station",
            "type":"Retail Goods"
        }
    ],
    "sg:phone":"+1 719 846 3837",
    "sg:postcode":"81082",
    "sg:province":"CO",
    "sg:tags":[
        "station",
        "gasoline"
    ],
    "wof:name":"Black Diamond Petroleum",
    "wof:placetype":"venue"
},
  "geometry": {"coordinates":[-104.511509,37.169926],"type":"Point"}
}