{
  "type": "Feature",
  "properties": {
    "addr:full":"706 6th St Kersey CO 80644",
    "addr:housenumber":"706",
    "addr:postcode":"80644",
    "addr:street":"6Th St",
    "iso:country":"US",
    "sg:address":"706 6th St",
    "sg:city":"Kersey",
    "sg:classifiers":[
        {
            "category":"Manufacturing",
            "subcategory":"Signs",
            "type":"Manufacturing & Wholesale Goods"
        }
    ],
    "sg:phone":"+1 970 352 9254",
    "sg:postcode":"80644",
    "sg:province":"CO",
    "sg:tags":[
        "specialty",
        "mfg"
    ],
    "wof:name":"In His Rein Signs & Designs",
    "wof:placetype":"venue"
},
  "geometry": {"coordinates":[-104.558313,40.382109],"type":"Point"}
}