{
  "type": "Feature",
  "properties": {
    "addr:full":"9915 Wagner Ln Westminster CO 80031",
    "addr:housenumber":"9915",
    "addr:postcode":"80031",
    "addr:street":"Wagner Ln",
    "iso:country":"US",
    "sg:address":"9915 Wagner Ln",
    "sg:city":"Westminster",
    "sg:classifiers":[
        {
            "category":"Travel",
            "subcategory":"Travel Agent",
            "type":"Entertainment"
        }
    ],
    "sg:phone":"+1 303 469 4081",
    "sg:postcode":"80031",
    "sg:province":"CO",
    "sg:tags":[
        "agency"
    ],
    "wof:name":"Tabor Trvl Professionals Intl",
    "wof:placetype":"venue"
},
  "geometry": {"coordinates":[-105.05086799999999,39.878262],"type":"Point"}
}