{
  "type": "Feature",
  "properties": {
    "addr:full":"239 E Raven Ave Rangely CO 81648",
    "addr:housenumber":"239",
    "addr:postcode":"81648",
    "addr:street":"E Raven Ave",
    "iso:country":"US",
    "sg:address":"239 E Raven Ave",
    "sg:city":"Rangely",
    "sg:classifiers":[
        {
            "category":"Mining & Drilling",
            "type":"Manufacturing & Wholesale Goods"
        }
    ],
    "sg:phone":"+1 970 675 5518",
    "sg:postcode":"81648",
    "sg:province":"CO",
    "sg:tags":[
        "oil",
        "well"
    ],
    "wof:name":"Rocky Mountain Well Svc",
    "wof:placetype":"venue"
},
  "geometry": {"coordinates":[-108.800445,40.090324],"type":"Point"}
}