{
  "type": "Feature",
  "properties": {
    "iso:country":"US",
    "sg:address":"747 S Colorado Blvd",
    "sg:city":"Denver",
    "sg:classifiers":[
        {
            "category":"Building & Trades",
            "subcategory":"Locksmith",
            "type":"Services"
        }
    ],
    "sg:phone":"+1 970 514 7161",
    "sg:postcode":"80246",
    "sg:province":"CO",
    "sg:tags":[
        "key"
    ],
    "wof:name":"Lock and Lockout Service Denver",
    "wof:placetype":"venue"
},
  "geometry": {"coordinates":[-104.940953,39.703005],"type":"Point"}
}