{
  "type": "Feature",
  "properties": {
    "iso:country":"US",
    "sg:address":"1424 Main St",
    "sg:city":"Longmont",
    "sg:classifiers":[
        {
            "category":"Personal",
            "subcategory":"Barber",
            "type":"Services"
        }
    ],
    "sg:phone":"+1 303 772 7937",
    "sg:postcode":"80501",
    "sg:province":"CO",
    "wof:name":"Dick's Barber Shop",
    "wof:placetype":"venue"
},
  "geometry": {"coordinates":[-105.102284,40.182614],"type":"Point"}
}