{
  "type": "Feature",
  "properties": {
    "addr:full":"1019 W Cheyenne Rd Colorado Springs CO 80906",
    "addr:housenumber":"1019",
    "addr:postcode":"80906",
    "addr:street":"W Cheyenne Rd",
    "iso:country":"US",
    "sg:address":"1019 W Cheyenne Rd",
    "sg:city":"Colorado Springs",
    "sg:classifiers":[
        {
            "category":"Social Services",
            "subcategory":"Child Care",
            "type":"Services"
        }
    ],
    "sg:phone":"+1 719 632 2232",
    "sg:postcode":"80906",
    "sg:province":"CO",
    "sg:tags":[
        "center",
        "day"
    ],
    "wof:name":"Green Shade Schools Inc",
    "wof:placetype":"venue"
},
  "geometry": {"coordinates":[-104.846401,38.799471],"type":"Point"}
}