{
  "type": "Feature",
  "properties": {
    "addr:full":"219 53rd Ave Ct Greeley CO 80634",
    "addr:housenumber":"219",
    "addr:postcode":"80634",
    "addr:street":"53Rd Ave Ct",
    "iso:country":"US",
    "sg:address":"219 53rd Ave Ct",
    "sg:city":"Greeley",
    "sg:classifiers":[
        {
            "category":"Freight",
            "type":"Transportation"
        }
    ],
    "sg:phone":"+1 970 378 0680",
    "sg:postcode":"80634",
    "sg:province":"CO",
    "sg:tags":[
        "operator",
        "local",
        "trucking"
    ],
    "wof:name":"Unruh Trucking",
    "wof:placetype":"venue"
},
  "geometry": {"coordinates":[-104.767832,40.432445],"type":"Point"}
}