{
  "type": "Feature",
  "properties": {
    "iso:country":"US",
    "sg:address":"6836 S Broadway",
    "sg:city":"Centennial",
    "sg:classifiers":[
        {
            "category":"Building & Trades",
            "subcategory":"Cleaning & Sanitation",
            "type":"Services"
        }
    ],
    "sg:phone":"+1 303 798 6426",
    "sg:postcode":"80122",
    "sg:province":"CO",
    "sg:tags":[
        "window"
    ],
    "wof:name":"Mike The Window Cleaner",
    "wof:placetype":"venue"
},
  "geometry": {"coordinates":[-104.988202,39.592356],"type":"Point"}
}