{
  "type": "Feature",
  "properties": {
    "iso:country":"US",
    "sg:address":"400 Antelope Dr W",
    "sg:city":"Bennett",
    "sg:classifiers":[
        {
            "category":"Banks & Credit Unions",
            "subcategory":"Financial Services",
            "type":"Services"
        }
    ],
    "sg:phone":"+1 303 644 5539",
    "sg:postcode":"80102",
    "sg:province":"CO",
    "sg:tags":[
        "company",
        "holding"
    ],
    "wof:name":"T & D Holdings Inc",
    "wof:placetype":"venue"
},
  "geometry": {"coordinates":[-104.413282,39.707964],"type":"Point"}
}