{
  "type": "Feature",
  "properties": {
    "iso:country":"US",
    "sg:address":"6308 E 72nd Ave",
    "sg:city":"Commerce City",
    "sg:classifiers":[
        {
            "category":"Retail",
            "subcategory":"Repair Shop",
            "type":"Services"
        }
    ],
    "sg:phone":"+1 303 287 1406",
    "sg:postcode":"80022",
    "sg:province":"CO",
    "sg:tags":[
        "appliance",
        "used",
        "electrical",
        "merchandise"
    ],
    "wof:name":"Triple J Appliance Repair",
    "wof:placetype":"venue"
},
  "geometry": {"coordinates":[-104.91381699999999,39.827125],"type":"Point"}
}