{
  "type": "Feature",
  "properties": {
    "iso:country":"US",
    "sg:address":"7065 W Belmont Dr",
    "sg:city":"Littleton",
    "sg:classifiers":[
        {
            "category":"Bars & Pubs",
            "type":"Food & Drink"
        }
    ],
    "sg:phone":"+1 303 972 7299",
    "sg:postcode":"80123",
    "sg:province":"CO",
    "sg:tags":[
        "drinking"
    ],
    "wof:name":"Jjs Hallmark",
    "wof:placetype":"venue"
},
  "geometry": {"coordinates":[-105.077905,39.61997],"type":"Point"}
}