{
  "type": "Feature",
  "properties": {
    "iso:country":"US",
    "sg:address":"2881 North Ave",
    "sg:city":"Grand Junction",
    "sg:classifiers":[
        {
            "category":"Personal",
            "subcategory":"Beauty Salon",
            "type":"Services"
        }
    ],
    "sg:phone":"+1 970 254 1096",
    "sg:postcode":"81501",
    "sg:province":"CO",
    "wof:name":"Cost Cutters Family Hair Care",
    "wof:placetype":"venue"
},
  "geometry": {"coordinates":[-108.519177,39.077261],"type":"Point"}
}