{
  "type": "Feature",
  "properties": {
    "iso:country":"US",
    "sg:address":"749 Tanager Rd",
    "sg:city":"Longmont",
    "sg:classifiers":[
        {
            "category":"Professional",
            "subcategory":"Lawyer & Legal Services",
            "type":"Services"
        }
    ],
    "sg:phone":"+1 303 776 0880",
    "sg:postcode":"80517",
    "sg:province":"CO",
    "sg:tags":[
        "attorney"
    ],
    "wof:name":"Jack P Wolfe",
    "wof:placetype":"venue"
},
  "geometry": {"coordinates":[-105.557812,40.367389],"type":"Point"}
}