{
  "type": "Feature",
  "properties": {
    "addr:full":"3235 I-70 Business Loop Clifton CO 81520",
    "addr:housenumber":"3235",
    "addr:postcode":"81520",
    "addr:street":"I-70 Business Loop",
    "iso:country":"US",
    "sg:address":"3235 I-70 Business Loop",
    "sg:city":"Clifton",
    "sg:classifiers":[
        {
            "category":"Restaurant",
            "type":"Food & Drink"
        }
    ],
    "sg:menulink":"http://www.allmenus.com/co/clifton/128717-subway/menu/",
    "sg:phone":"+1 970 434 5290",
    "sg:postcode":"81520",
    "sg:province":"CO",
    "sg:tags":[
        "american",
        "sandwich"
    ],
    "wof:name":"Subway",
    "wof:placetype":"venue"
},
  "geometry": {"coordinates":[-108.45614,39.089203],"type":"Point"}
}