{
  "type": "Feature",
  "properties": {
    "addr:full":"12175 E Amherst Cir Aurora CO 80014",
    "addr:housenumber":"12175",
    "addr:postcode":"80014",
    "addr:street":"E Amherst Cir",
    "iso:country":"US",
    "sg:address":"12175 E Amherst Cir",
    "sg:city":"Aurora",
    "sg:classifiers":[
        {
            "category":"Personal",
            "subcategory":"Adult",
            "type":"Services"
        }
    ],
    "sg:phone":"+1 303 671 5511",
    "sg:postcode":"80014",
    "sg:province":"CO",
    "sg:tags":[
        "escort"
    ],
    "wof:name":"10 Xxx Escorts",
    "wof:placetype":"venue"
},
  "geometry": {"coordinates":[-104.84386600000001,39.666229],"type":"Point"}
}