{
  "type": "Feature",
  "properties": {
    "iso:country":"US",
    "sg:address":"112 W Main St",
    "sg:city":"Rangely",
    "sg:classifiers":[
        {
            "category":"Food & Beverages",
            "subcategory":"Liquor & Beverages",
            "type":"Retail Goods"
        }
    ],
    "sg:phone":"+1 970 675 5765",
    "sg:postcode":"81648",
    "sg:province":"CO",
    "sg:tags":[
        "alcoholic"
    ],
    "wof:name":"Sportsman Liquor",
    "wof:placetype":"venue"
},
  "geometry": {"coordinates":[-108.804458,40.087595],"type":"Point"}
}