{
  "type": "Feature",
  "properties": {
    "addr:full":"115 N Campbell Ave Holyoke CO 80734",
    "addr:housenumber":"115",
    "addr:postcode":"80734",
    "addr:street":"N Campbell Ave",
    "iso:country":"US",
    "sg:address":"115 N Campbell Ave",
    "sg:city":"Holyoke",
    "sg:classifiers":[
        {
            "category":"Utilities",
            "subcategory":"Mobile Phone",
            "type":"Services"
        }
    ],
    "sg:phone":"+1 970 854 4501",
    "sg:postcode":"80734",
    "sg:province":"CO",
    "sg:tags":[
        "telephone",
        "cellular"
    ],
    "wof:name":"Viaero Wireless",
    "wof:placetype":"venue"
},
  "geometry": {"coordinates":[-102.30074999999999,40.585971],"type":"Point"}
}