{
  "type": "Feature",
  "properties": {
    "iso:country":"US",
    "sg:address":"98 Inverness Dr E",
    "sg:city":"Englewood",
    "sg:classifiers":[
        {
            "category":"Utilities",
            "subcategory":"Telephone",
            "type":"Services"
        }
    ],
    "sg:phone":"+1 303 799 3638",
    "sg:postcode":"80112",
    "sg:province":"CO",
    "sg:tags":[
        "based",
        "internet"
    ],
    "wof:name":"Tectonic Network",
    "wof:placetype":"venue"
},
  "geometry": {"coordinates":[-104.86202400000001,39.579119],"type":"Point"}
}