{
  "type": "Feature",
  "properties": {
    "addr:full":"1226 Denise Dr Colorado Springs CO 80906",
    "addr:housenumber":"1226",
    "addr:postcode":"80906",
    "addr:street":"Denise Dr",
    "iso:country":"US",
    "sg:address":"1226 Denise Dr",
    "sg:city":"Colorado Springs",
    "sg:classifiers":[
        {
            "category":"Building & Trades",
            "subcategory":"Construction",
            "type":"Services"
        }
    ],
    "sg:phone":"+1 719 391 2710",
    "sg:postcode":"80906",
    "sg:province":"CO",
    "sg:tags":[
        "contractor"
    ],
    "wof:name":"Ralph Jensen Roofing",
    "wof:placetype":"venue"
},
  "geometry": {"coordinates":[-104.772536,38.769406],"type":"Point"}
}