{
  "type": "Feature",
  "properties": {
    "addr:full":"5954 S Lee Way Littleton CO 80127",
    "addr:housenumber":"5954",
    "addr:postcode":"80127",
    "addr:street":"S Lee Way",
    "iso:country":"US",
    "sg:address":"5954 S Lee Way",
    "sg:city":"Littleton",
    "sg:classifiers":[
        {
            "category":"Building & Trades",
            "subcategory":"Construction",
            "type":"Services"
        }
    ],
    "sg:phone":"+1 303 978 0905",
    "sg:postcode":"80127",
    "sg:province":"CO",
    "sg:tags":[
        "masonry",
        "contractor",
        "mason"
    ],
    "wof:name":"Scott Johnson Masonry Inc",
    "wof:placetype":"venue"
},
  "geometry": {"coordinates":[-105.11210800000001,39.608183],"type":"Point"}
}