{
  "type": "Feature",
  "properties": {
    "addr:full":"11831 E 33rd Ave Aurora CO 80010",
    "addr:housenumber":"11831",
    "addr:postcode":"80010",
    "addr:street":"E 33Rd Ave",
    "iso:country":"US",
    "sg:address":"11831 E 33rd Ave",
    "sg:city":"Aurora",
    "sg:classifiers":[
        {
            "category":"Building & Trades",
            "subcategory":"Cleaning & Sanitation",
            "type":"Services"
        }
    ],
    "sg:phone":"+1 303 360 5633",
    "sg:postcode":"80010",
    "sg:province":"CO",
    "sg:tags":[
        "janitor"
    ],
    "wof:name":"Pro Tech Cleaning",
    "wof:placetype":"venue"
},
  "geometry": {"coordinates":[-104.847286,39.763947],"type":"Point"}
}