{
  "type": "Feature",
  "properties": {
    "iso:country":"US",
    "sg:address":"4854 Brandon Creek Dr",
    "sg:city":"Boulder",
    "sg:classifiers":[
        {
            "category":"Building & Trades",
            "subcategory":"Construction",
            "type":"Services"
        }
    ],
    "sg:phone":"+1 303 544 1161",
    "sg:postcode":"80301",
    "sg:province":"CO",
    "sg:tags":[
        "house"
    ],
    "wof:name":"Home Design Gallery Ltd",
    "wof:placetype":"venue"
},
  "geometry": {"coordinates":[-105.19501099999999,40.063643],"type":"Point"}
}