{
  "type": "Feature",
  "properties": {
    "iso:country":"US",
    "sg:address":"2527 Platte Pl",
    "sg:city":"Colorado Springs",
    "sg:classifiers":[
        {
            "category":"Retail",
            "subcategory":"Auto Repair",
            "type":"Services"
        }
    ],
    "sg:phone":"+1 719 636 3888",
    "sg:postcode":"80909",
    "sg:province":"CO",
    "sg:tags":[
        "repairing",
        "automobile"
    ],
    "wof:name":"Pikes Peak Rovers",
    "wof:placetype":"venue"
},
  "geometry": {"coordinates":[-104.779613,38.836655],"type":"Point"}
}