{
  "type": "Feature",
  "properties": {
    "iso:country":"US",
    "sg:address":"729 North Ave",
    "sg:city":"Grand Junction",
    "sg:classifiers":[
        {
            "category":"Utilities",
            "subcategory":"Mobile Phone",
            "type":"Services"
        }
    ],
    "sg:phone":"+1 970 263 7443",
    "sg:postcode":"81501",
    "sg:province":"CO",
    "sg:tags":[
        "telephone",
        "cellular"
    ],
    "wof:name":"3D Wireless",
    "wof:placetype":"venue"
},
  "geometry": {"coordinates":[-108.55981199999999,39.077328],"type":"Point"}
}