{
  "type": "Feature",
  "properties": {
    "addr:full":"13828 Gleneagle Dr Colorado Springs CO 80921",
    "addr:housenumber":"13828",
    "addr:postcode":"80921",
    "addr:street":"Gleneagle Dr",
    "iso:country":"US",
    "sg:address":"13828 Gleneagle Dr",
    "sg:city":"Colorado Springs",
    "sg:classifiers":[
        {
            "category":"Health Services",
            "subcategory":"Chiropractor",
            "type":"Services"
        }
    ],
    "sg:phone":"+1 719 488 1232",
    "sg:postcode":"80921",
    "sg:province":"CO",
    "wof:name":"Bio-Health Ctr",
    "wof:placetype":"venue"
},
  "geometry": {"coordinates":[-104.83097600000001,39.03064],"type":"Point"}
}