{
  "type": "Feature",
  "properties": {
    "addr:full":"111 Ski Hill Rd Breckenridge CO 80424",
    "addr:housenumber":"111",
    "addr:postcode":"80424",
    "addr:street":"Ski Hill Rd",
    "iso:country":"US",
    "sg:address":"111 Ski Hill Rd",
    "sg:city":"Breckenridge",
    "sg:classifiers":[
        {
            "category":"Shopping",
            "subcategory":"Pharmacy",
            "type":"Retail Goods"
        }
    ],
    "sg:phone":"+1 970 453 6230",
    "sg:postcode":"80424",
    "sg:province":"CO",
    "wof:name":"Store",
    "wof:placetype":"venue"
},
  "geometry": {"coordinates":[-106.046857,39.482301],"type":"Point"}
}