{
  "type": "Feature",
  "properties": {
    "iso:country":"US",
    "sg:address":"1550 Elmira St",
    "sg:city":"Aurora",
    "sg:classifiers":[
        {
            "category":"Restaurant",
            "type":"Food & Drink"
        }
    ],
    "sg:phone":"+1 303 340 3244",
    "sg:postcode":"80010",
    "sg:province":"CO",
    "sg:tags":[
        "eating"
    ],
    "wof:name":"Grumpys Cafe",
    "wof:placetype":"venue"
},
  "geometry": {"coordinates":[-104.87280699999999,39.741071],"type":"Point"}
}