{
  "type": "Feature",
  "properties": {
    "iso:country":"US",
    "sg:address":"15493 E Orchard Pl",
    "sg:city":"Aurora",
    "sg:classifiers":[
        {
            "category":"Insurance",
            "subcategory":"Insurance Agent",
            "type":"Services"
        }
    ],
    "sg:phone":"+1 303 627 0768",
    "sg:postcode":"80016",
    "sg:province":"CO",
    "wof:name":"Quick Claims",
    "wof:placetype":"venue"
},
  "geometry": {"coordinates":[-104.809037,39.608502],"type":"Point"}
}