{
  "type": "Feature",
  "properties": {
    "iso:country":"US",
    "sg:address":"12335 Oregon Wagon Trl",
    "sg:city":"Elbert",
    "sg:classifiers":[
        {
            "category":"Shopping",
            "subcategory":"Catalog Store",
            "type":"Retail Goods"
        }
    ],
    "sg:phone":"+1 719 495 0798",
    "sg:postcode":"80106",
    "sg:province":"CO",
    "sg:tags":[
        "mail",
        "order"
    ],
    "wof:name":"Eagles Steve Ntiv Amrcn Rgalia",
    "wof:placetype":"venue"
},
  "geometry": {"coordinates":[-104.58757199999999,39.009953],"type":"Point"}
}