{
  "type": "Feature",
  "properties": {
    "addr:full":"880 3rd St Castle Rock CO 80104",
    "addr:housenumber":"880",
    "addr:postcode":"80104",
    "addr:street":"3Rd St",
    "iso:country":"US",
    "sg:address":"880 3rd St",
    "sg:city":"Castle Rock",
    "sg:classifiers":[
        {
            "category":"Place Of Worship",
            "subcategory":"Church",
            "type":"Public Place"
        }
    ],
    "sg:phone":"+1 303 660 9055",
    "sg:postcode":"80104",
    "sg:province":"CO",
    "sg:website":"www.cornerstonecastlerock.com/",
    "wof:name":"Cornerstone Community Church",
    "wof:placetype":"venue"
},
  "geometry": {"coordinates":[-104.852959,39.372162],"type":"Point"}
}