{
  "type": "Feature",
  "properties": {
    "iso:country":"US",
    "sg:address":"278 W Front St",
    "sg:city":"Byers",
    "sg:classifiers":[
        {
            "category":"Organizations",
            "subcategory":"Community Association",
            "type":"Services"
        }
    ],
    "sg:phone":"+1 303 822 9562",
    "sg:postcode":"80103",
    "sg:province":"CO",
    "wof:name":"Legion House",
    "wof:placetype":"venue"
},
  "geometry": {"coordinates":[-104.226996,39.709953],"type":"Point"}
}