{
  "type": "Feature",
  "properties": {
    "addr:full":"6595 W 14th Ave Lakewood CO 80214",
    "addr:housenumber":"6595",
    "addr:postcode":"80214",
    "addr:street":"W 14Th Ave",
    "iso:country":"US",
    "sg:address":"6595 W 14th Ave",
    "sg:city":"Lakewood",
    "sg:classifiers":[
        {
            "category":"Manufacturing",
            "subcategory":"Petroleum Products",
            "type":"Manufacturing & Wholesale Goods"
        }
    ],
    "sg:phone":"+1 303 205 0360",
    "sg:postcode":"80214",
    "sg:province":"CO",
    "sg:tags":[
        "fuel",
        "oil",
        "gas",
        "mfg"
    ],
    "wof:name":"Power Energy Fuels Inc",
    "wof:placetype":"venue"
},
  "geometry": {"coordinates":[-105.06953900000001,39.738617],"type":"Point"}
}