{
  "type": "Feature",
  "properties": {
    "addr:full":"2716 11th Ave Greeley CO 80631",
    "addr:housenumber":"2716",
    "addr:postcode":"80631",
    "addr:street":"11Th Ave",
    "iso:country":"US",
    "sg:address":"2716 11th Ave",
    "sg:city":"Greeley",
    "sg:classifiers":[
        {
            "category":"Cinema",
            "subcategory":"Movie Rental",
            "type":"Entertainment"
        }
    ],
    "sg:phone":"+1 970 351 0904",
    "sg:postcode":"80631",
    "sg:province":"CO",
    "sg:tags":[
        "video",
        "retail",
        "tape",
        "rent"
    ],
    "wof:name":"Hollywood Entertainment Corp",
    "wof:placetype":"venue"
},
  "geometry": {"coordinates":[-104.696836,40.392336],"type":"Point"}
}