{
  "type": "Feature",
  "properties": {
    "iso:country":"US",
    "sg:address":"581 County Line Rd",
    "sg:city":"Monument",
    "sg:classifiers":[
        {
            "category":"Manufacturing",
            "subcategory":"Food",
            "type":"Manufacturing & Wholesale Goods"
        }
    ],
    "sg:phone":"+1 719 481 6815",
    "sg:postcode":"80118",
    "sg:province":"CO",
    "sg:tags":[
        "product",
        "manufacturer"
    ],
    "wof:name":"Villa Pasta Co",
    "wof:placetype":"venue"
},
  "geometry": {"coordinates":[-104.87535800000001,39.129744],"type":"Point"}
}