{
  "type": "Feature",
  "properties": {
    "iso:country":"US",
    "sg:address":"1134 Westmoreland Rd",
    "sg:city":"Colorado Springs",
    "sg:classifiers":[
        {
            "category":"Real Estate",
            "subcategory":"Real Estate Operator",
            "type":"Services"
        }
    ],
    "sg:phone":"+1 719 599 3081",
    "sg:postcode":"80907",
    "sg:province":"CO",
    "sg:tags":[
        "building",
        "apartment"
    ],
    "wof:name":"Crestmoor Apartments",
    "wof:placetype":"venue"
},
  "geometry": {"coordinates":[-104.804186,38.886017],"type":"Point"}
}