{
  "type": "Feature",
  "properties": {
    "iso:country":"US",
    "sg:address":"34375 US Hwy 285",
    "sg:city":"Pine",
    "sg:classifiers":[
        {
            "category":"Shopping",
            "subcategory":"Bicycles & Sporting Goods",
            "type":"Retail Goods"
        }
    ],
    "sg:phone":"+1 303 816 0487",
    "sg:postcode":"80470",
    "sg:province":"CO",
    "sg:tags":[
        "tackle",
        "fishing"
    ],
    "wof:name":"Hatch Fly Shop The Inc",
    "wof:placetype":"venue"
},
  "geometry": {"coordinates":[-105.398195,39.464218],"type":"Point"}
}