{
  "type": "Feature",
  "properties": {
    "addr:full":"768 Hwy 133 Carbondale CO 81623",
    "addr:housenumber":"768",
    "addr:postcode":"81623",
    "addr:street":"Hwy 133",
    "iso:country":"US",
    "sg:address":"768 Hwy 133",
    "sg:city":"Carbondale",
    "sg:classifiers":[
        {
            "category":"Home & Garden",
            "subcategory":"Building Materials",
            "type":"Retail Goods"
        },
        {
            "category":"Wholesale",
            "subcategory":"Auto Parts",
            "type":"Manufacturing & Wholesale Goods"
        }
    ],
    "sg:phone":"+1 970 704 2287",
    "sg:postcode":"81623",
    "sg:province":"CO",
    "sg:tags":[
        "glass",
        "window",
        "plate"
    ],
    "wof:name":"Cracks & Racks Autoglass/Sport",
    "wof:placetype":"venue"
},
  "geometry": {"coordinates":[-107.22104299999999,39.40479],"type":"Point"}
}