{
  "type": "Feature",
  "properties": {
    "iso:country":"US",
    "sg:address":"210 E Elkhorn Ave",
    "sg:city":"Estes Park",
    "sg:classifiers":[
        {
            "category":"Shopping",
            "subcategory":"Clothing, Apparel, & Fashions",
            "type":"Retail Goods"
        }
    ],
    "sg:phone":"+1 970 586 7335",
    "sg:postcode":"80517",
    "sg:province":"CO",
    "sg:tags":[
        "furnishing"
    ],
    "wof:name":"Big Red Of The Rockies Sports",
    "wof:placetype":"venue"
},
  "geometry": {"coordinates":[-105.52103,40.376619],"type":"Point"}
}