{
  "type": "Feature",
  "properties": {
    "addr:full":"1410 W Vermijo Ave Colorado Springs CO 80904",
    "addr:housenumber":"1410",
    "addr:postcode":"80904",
    "addr:street":"W Vermijo Ave",
    "iso:country":"US",
    "sg:address":"1410 W Vermijo Ave",
    "sg:city":"Colorado Springs",
    "sg:classifiers":[
        {
            "category":"Building & Trades",
            "subcategory":"Electrical",
            "type":"Services"
        }
    ],
    "sg:phone":"+1 719 634 2276",
    "sg:postcode":"80904",
    "sg:province":"CO",
    "sg:tags":[
        "electric",
        "contractor"
    ],
    "wof:name":"Rockhill Electrical Systems",
    "wof:placetype":"venue"
},
  "geometry": {"coordinates":[-104.849833,38.837019],"type":"Point"}
}