{
  "type": "Feature",
  "properties": {
    "iso:country":"US",
    "sg:address":"887 Welch Ave",
    "sg:city":"Berthoud",
    "sg:classifiers":[
        {
            "category":"Building & Trades",
            "subcategory":"Construction",
            "type":"Services"
        }
    ],
    "sg:phone":"+1 970 532 5133",
    "sg:postcode":"80513",
    "sg:province":"CO",
    "sg:tags":[
        "general",
        "contractor"
    ],
    "wof:name":"Frank Piacentino",
    "wof:placetype":"venue"
},
  "geometry": {"coordinates":[-105.08710499999999,40.303758],"type":"Point"}
}