{
  "type": "Feature",
  "properties": {
    "addr:full":"3050 S Colorado Blvd Denver CO 80222",
    "addr:housenumber":"3050",
    "addr:postcode":"80222",
    "addr:street":"S Colorado Blvd",
    "iso:country":"US",
    "sg:address":"3050 S Colorado Blvd",
    "sg:city":"Denver",
    "sg:classifiers":[
        {
            "category":"Personal",
            "subcategory":"Massage",
            "type":"Services"
        }
    ],
    "sg:phone":"+1 303 726 0561",
    "sg:postcode":"80222",
    "sg:province":"CO",
    "wof:name":"Massage In The City Inc",
    "wof:placetype":"venue"
},
  "geometry": {"coordinates":[-104.940433,39.661848],"type":"Point"}
}