{
  "type": "Feature",
  "properties": {
    "addr:full":"2492 Co Rd 11 Erie CO 80516",
    "addr:housenumber":"2492;11",
    "addr:postcode":"80516",
    "addr:street":"Co Rd",
    "iso:country":"US",
    "sg:address":"2492 Co Rd 11",
    "sg:city":"Erie",
    "sg:phone":"+1 303 833 3077",
    "sg:postcode":"80516",
    "sg:province":"CO",
    "sg:tags":[
        "farm",
        "corn"
    ],
    "wof:name":"Johnston Farm",
    "wof:placetype":"venue"
},
  "geometry": {"coordinates":[-104.9614,40.036673],"type":"Point"}
}