{
  "type": "Feature",
  "properties": {
    "addr:full":"7585 W Arkansas Ave Lakewood CO 80232",
    "addr:housenumber":"7585",
    "addr:postcode":"80232",
    "addr:street":"W Arkansas Ave",
    "iso:country":"US",
    "sg:address":"7585 W Arkansas Ave",
    "sg:city":"Lakewood",
    "sg:classifiers":[
        {
            "category":"Organizations",
            "subcategory":"Non-profit Organization",
            "type":"Services"
        }
    ],
    "sg:phone":"+1 303 275 9523",
    "sg:postcode":"80232",
    "sg:province":"CO",
    "wof:name":"Citizens For Lakewoods Future",
    "wof:placetype":"venue"
},
  "geometry": {"coordinates":[-105.076965,39.691564],"type":"Point"}
}