{
  "type": "Feature",
  "properties": {
    "iso:country":"US",
    "sg:address":"300 Park Ave",
    "sg:city":"Fraser",
    "sg:classifiers":[
        {
            "category":"Freight",
            "type":"Transportation"
        }
    ],
    "sg:phone":"+1 970 726 4360",
    "sg:postcode":"80442",
    "sg:province":"CO",
    "sg:tags":[
        "commercial",
        "storage"
    ],
    "wof:name":"County Wide Mini-Storage",
    "wof:placetype":"venue"
},
  "geometry": {"coordinates":[-105.815668,39.949602],"type":"Point"}
}