{
  "type": "Feature",
  "properties": {
    "iso:country":"US",
    "sg:address":"4545 E 9th Ave",
    "sg:city":"Denver",
    "sg:classifiers":[
        {
            "category":"Health Services",
            "subcategory":"Doctor",
            "type":"Services"
        }
    ],
    "sg:phone":"+1 303 320 2278",
    "sg:postcode":"80220",
    "sg:province":"CO",
    "sg:tags":[
        "gynecology",
        "physician",
        "surgeon",
        "surgeons",
        "obstetrics"
    ],
    "wof:name":"Thomas J Hickman Obstetri",
    "wof:placetype":"venue"
},
  "geometry": {"coordinates":[-104.934622,39.73103],"type":"Point"}
}