{
  "type": "Feature",
  "properties": {
    "addr:full":"4737 Pearl St Boulder CO 80301",
    "addr:housenumber":"4737",
    "addr:postcode":"80301",
    "addr:street":"Pearl St",
    "iso:country":"US",
    "sg:address":"4737 Pearl St",
    "sg:city":"Boulder",
    "sg:classifiers":[
        {
            "category":"Parking",
            "type":"Transportation"
        }
    ],
    "sg:phone":"+1 303 449 7195",
    "sg:postcode":"80301",
    "sg:province":"CO",
    "sg:tags":[
        "garage"
    ],
    "wof:name":"First National Garage",
    "wof:placetype":"venue"
},
  "geometry": {"coordinates":[-105.238918,40.025688],"type":"Point"}
}