{
  "type": "Feature",
  "properties": {
    "iso:country":"US",
    "sg:address":"31717 E United Ave",
    "sg:city":"Pueblo",
    "sg:classifiers":[
        {
            "category":"Utilities",
            "subcategory":"Water",
            "type":"Services"
        }
    ],
    "sg:phone":"+1 719 948 2400",
    "sg:postcode":"81001",
    "sg:province":"CO",
    "sg:tags":[
        "company",
        "sewage"
    ],
    "wof:name":"Southeastern Colorado Water",
    "wof:placetype":"venue"
},
  "geometry": {"coordinates":[-104.491361,38.277026],"type":"Point"}
}