{
  "type": "Feature",
  "properties": {
    "addr:full":"1585 Steamboat Blvd Steamboat Spgs CO 80487",
    "addr:housenumber":"1585",
    "addr:postcode":"80487",
    "addr:street":"Steamboat Blvd;Spgs",
    "iso:country":"US",
    "sg:address":"1585 Steamboat Blvd",
    "sg:city":"Steamboat Spgs",
    "sg:classifiers":[
        {
            "category":"Health Services",
            "subcategory":"Health Practitioner",
            "type":"Services"
        }
    ],
    "sg:phone":"+1 970 879 8026",
    "sg:postcode":"80487",
    "sg:province":"CO",
    "sg:tags":[
        "therapist",
        "physical"
    ],
    "wof:name":"Kinetic Energy Physical",
    "wof:placetype":"venue"
},
  "geometry": {"coordinates":[-106.811547,40.463582],"type":"Point"}
}