{
  "type": "Feature",
  "properties": {
    "iso:country":"US",
    "sg:address":"1932 Glenisle Ave",
    "sg:city":"Durango",
    "sg:classifiers":[
        {
            "category":"Professional",
            "subcategory":"Accounting & Tax Preparation",
            "type":"Services"
        }
    ],
    "sg:phone":"+1 970 375 2322",
    "sg:postcode":"81301",
    "sg:province":"CO",
    "sg:tags":[
        "return",
        "filing"
    ],
    "wof:name":"Baca Tax Preparation",
    "wof:placetype":"venue"
},
  "geometry": {"coordinates":[-107.884833,37.285365],"type":"Point"}
}