{
  "type": "Feature",
  "properties": {
    "iso:country":"US",
    "sg:address":"5810 W 38th Ave",
    "sg:city":"Denver",
    "sg:classifiers":[
        {
            "category":"Banks & Credit Unions",
            "subcategory":"Bank",
            "type":"Services"
        }
    ],
    "sg:phone":"+1 303 423 7892",
    "sg:postcode":"80212",
    "sg:province":"CO",
    "sg:tags":[
        "federal"
    ],
    "wof:name":"Emmaus Lutheran Federal CU",
    "wof:placetype":"venue"
},
  "geometry": {"coordinates":[-105.062529,39.769309],"type":"Point"}
}