{
  "type": "Feature",
  "properties": {
    "iso:country":"US",
    "sg:address":"2323 S Troy St",
    "sg:city":"Aurora",
    "sg:classifiers":[
        {
            "category":"Real Estate",
            "subcategory":"Architect",
            "type":"Services"
        }
    ],
    "sg:phone":"+1 720 747 1900",
    "sg:postcode":"80014",
    "sg:province":"CO",
    "wof:name":"L M Consultants",
    "wof:placetype":"venue"
},
  "geometry": {"coordinates":[-104.839353,39.674703],"type":"Point"}
}