{
  "type": "Feature",
  "properties": {
    "addr:full":"5100 E 78th Ave Commerce City CO 80022",
    "addr:housenumber":"5100",
    "addr:postcode":"80022",
    "addr:street":"E 78Th Ave",
    "iso:country":"US",
    "sg:address":"5100 E 78th Ave",
    "sg:city":"Commerce City",
    "sg:classifiers":[
        {
            "category":"Freight",
            "type":"Transportation"
        }
    ],
    "sg:phone":"+1 303 289 3938",
    "sg:postcode":"80022",
    "sg:province":"CO",
    "sg:tags":[
        "dry",
        "bulk",
        "trucking"
    ],
    "wof:name":"Solar Transport",
    "wof:placetype":"venue"
},
  "geometry": {"coordinates":[-104.927139,39.838052],"type":"Point"}
}