{
  "type": "Feature",
  "properties": {
    "addr:full":"9032 E Amherst Dr Denver CO 80231",
    "addr:housenumber":"9032",
    "addr:postcode":"80231",
    "addr:street":"E Amherst Dr",
    "iso:country":"US",
    "sg:address":"9032 E Amherst Dr",
    "sg:city":"Denver",
    "sg:classifiers":[
        {
            "category":"Organizations",
            "subcategory":"Non-profit Organization",
            "type":"Services"
        }
    ],
    "sg:phone":"+1 303 695 6010",
    "sg:postcode":"80231",
    "sg:province":"CO",
    "sg:website":"www.colorado-recycles.org",
    "wof:name":"Colorado Recycles",
    "wof:placetype":"venue"
},
  "geometry": {"coordinates":[-104.881873,39.664699],"type":"Point"}
}