{
  "type": "Feature",
  "properties": {
    "addr:full":"720 Clay St Wray CO 80758",
    "addr:housenumber":"720",
    "addr:postcode":"80758",
    "addr:street":"Clay St",
    "iso:country":"US",
    "sg:address":"720 Clay St",
    "sg:city":"Wray",
    "sg:classifiers":[
        {
            "category":"Health Services",
            "subcategory":"Nursing And Care Facility",
            "type":"Services"
        }
    ],
    "sg:phone":"+1 970 332 5375",
    "sg:postcode":"80758",
    "sg:province":"CO",
    "sg:tags":[
        "skilled"
    ],
    "wof:name":"Cedardale Nursing Home",
    "wof:placetype":"venue"
},
  "geometry": {"coordinates":[-102.225509,40.07516],"type":"Point"}
}