{
  "type": "Feature",
  "properties": {
    "iso:country":"US",
    "sg:address":"44680 Co Rd 38",
    "sg:city":"Trinidad",
    "sg:classifiers":[
        {
            "category":"Government",
            "subcategory":"Office",
            "type":"Public Place"
        }
    ],
    "sg:phone":"+1 719 846 4610",
    "sg:postcode":"81082",
    "sg:province":"CO",
    "sg:tags":[
        "county",
        "govt",
        "program"
    ],
    "wof:name":"Las Animas County Airport Shop",
    "wof:placetype":"venue"
},
  "geometry": {"coordinates":[-104.348326,37.26311],"type":"Point"}
}