{
  "type": "Feature",
  "properties": {
    "iso:country":"US",
    "sg:address":"6310 Shoup Rd",
    "sg:city":"Colorado Springs",
    "sg:classifiers":[
        {
            "category":"Building & Trades",
            "subcategory":"Construction",
            "type":"Services"
        }
    ],
    "sg:phone":"+1 719 495 2158",
    "sg:postcode":"80908",
    "sg:province":"CO",
    "sg:tags":[
        "excavation",
        "contractor"
    ],
    "wof:name":"Havens Construction Orville",
    "wof:placetype":"venue"
},
  "geometry": {"coordinates":[-104.710278,39.012898],"type":"Point"}
}