{
  "type": "Feature",
  "properties": {
    "addr:full":"110 Adams St Monte Vista CO 81144",
    "addr:housenumber":"110",
    "addr:postcode":"81144",
    "addr:street":"Adams St",
    "iso:country":"US",
    "sg:address":"110 Adams St",
    "sg:city":"Monte Vista",
    "sg:classifiers":[
        {
            "category":"Sports & Exercise",
            "subcategory":"Gym",
            "type":"Entertainment"
        }
    ],
    "sg:phone":"+1 719 852 3020",
    "sg:postcode":"81144",
    "sg:province":"CO",
    "sg:tags":[
        "club",
        "health",
        "studio",
        "gymnasium"
    ],
    "wof:name":"Curves For Women",
    "wof:placetype":"venue"
},
  "geometry": {"coordinates":[-106.146642,37.580378],"type":"Point"}
}