{
  "type": "Feature",
  "properties": {
    "iso:country":"US",
    "sg:address":"2000 W 92nd Ave",
    "sg:city":"Denver",
    "sg:classifiers":[
        {
            "category":"Professional",
            "type":"Services"
        }
    ],
    "sg:phone":"+1 303 429 3802",
    "sg:postcode":"80260",
    "sg:province":"CO",
    "wof:name":"Advanced Asphalt and Seal Inc",
    "wof:placetype":"venue"
},
  "geometry": {"coordinates":[-105.012326,39.863481],"type":"Point"}
}