{
  "type": "Feature",
  "properties": {
    "iso:country":"US",
    "sg:address":"3700 Globeville Rd",
    "sg:city":"Denver",
    "sg:classifiers":[
        {
            "category":"Railroad",
            "type":"Transportation"
        }
    ],
    "sg:phone":"+1 303 480 6200",
    "sg:postcode":"80216",
    "sg:province":"CO",
    "sg:tags":[
        "operator",
        "line"
    ],
    "wof:name":"Burlington Northern",
    "wof:placetype":"venue"
},
  "geometry": {"coordinates":[-104.992476,39.7678],"type":"Point"}
}