{
  "type": "Feature",
  "properties": {
    "iso:country":"US",
    "sg:address":"1325 W 38th Ave",
    "sg:city":"Denver",
    "sg:classifiers":[
        {
            "category":"Insurance",
            "subcategory":"Insurance Agent",
            "type":"Services"
        }
    ],
    "sg:phone":"+1 303 455 0198",
    "sg:postcode":"80211",
    "sg:province":"CO",
    "wof:name":"ABC Insurance Inc",
    "wof:placetype":"venue"
},
  "geometry": {"coordinates":[-105.002683,39.76935],"type":"Point"}
}