{
  "type": "Feature",
  "properties": {
    "iso:country":"US",
    "sg:address":"9072 Ln 4 N",
    "sg:city":"Mosca",
    "sg:classifiers":[
        {
            "category":"Building & Trades",
            "subcategory":"Landscaping Services",
            "type":"Services"
        }
    ],
    "sg:phone":"+1 719 378 2026",
    "sg:postcode":"81146",
    "sg:province":"CO",
    "sg:tags":[
        "lawn",
        "garden"
    ],
    "wof:name":"Apex Landscaping",
    "wof:placetype":"venue"
},
  "geometry": {"coordinates":[-105.86923400000001,37.633043],"type":"Point"}
}