{
  "type": "Feature",
  "properties": {
    "addr:full":"1810 S Corona Ave Colorado Springs CO 80906",
    "addr:housenumber":"1810",
    "addr:postcode":"80906",
    "addr:street":"S Corona Ave",
    "iso:country":"US",
    "sg:address":"1810 S Corona Ave",
    "sg:city":"Colorado Springs",
    "sg:classifiers":[
        {
            "category":"Health Services",
            "subcategory":"Nursing And Care Facility",
            "type":"Services"
        },
        {
            "category":"Social Services",
            "subcategory":"Adult Care",
            "type":"Services"
        }
    ],
    "sg:phone":"+1 719 632 7444",
    "sg:postcode":"80906",
    "sg:province":"CO",
    "sg:tags":[
        "home",
        "retirement",
        "community",
        "residential"
    ],
    "wof:name":"Villa San Jose Inc",
    "wof:placetype":"venue"
},
  "geometry": {"coordinates":[-104.817719,38.808134],"type":"Point"}
}