{
  "type": "Feature",
  "properties": {
    "iso:country":"US",
    "sg:address":"10239 Royal Eagle St",
    "sg:city":"Littleton",
    "sg:classifiers":[
        {
            "category":"Shopping",
            "subcategory":"Computers & Home Electronics",
            "type":"Retail Goods"
        }
    ],
    "sg:phone":"+1 303 346 5074",
    "sg:postcode":"80129",
    "sg:province":"CO",
    "sg:tags":[
        "website",
        "printer",
        "color",
        "s",
        "design",
        "provides",
        "internet"
    ],
    "wof:name":"Xcen28",
    "wof:placetype":"venue"
},
  "geometry": {"coordinates":[-104.995062,39.529198],"type":"Point"}
}