{
  "type": "Feature",
  "properties": {
    "iso:country":"US",
    "sg:address":"16203 E Dorado Pl",
    "sg:city":"Aurora",
    "sg:classifiers":[
        {
            "category":"Building & Trades",
            "subcategory":"Construction",
            "type":"Services"
        }
    ],
    "sg:phone":"+1 303 693 2255",
    "sg:postcode":"80015",
    "sg:province":"CO",
    "sg:tags":[
        "home",
        "contractor"
    ],
    "wof:name":"Colorado Homes Ltd",
    "wof:placetype":"venue"
},
  "geometry": {"coordinates":[-104.79992900000001,39.613023],"type":"Point"}
}