{
  "type": "Feature",
  "properties": {
    "addr:full":"2401 Research Blvd Fort Collins CO 80526",
    "addr:housenumber":"2401",
    "addr:postcode":"80526",
    "addr:street":"Research Blvd",
    "iso:country":"US",
    "sg:address":"2401 Research Blvd",
    "sg:city":"Fort Collins",
    "sg:classifiers":[
        {
            "category":"Professional",
            "subcategory":"Testing Lab",
            "type":"Services"
        }
    ],
    "sg:phone":"+1 970 490 1414",
    "sg:postcode":"80526",
    "sg:province":"CO",
    "sg:tags":[
        "laboratory"
    ],
    "wof:name":"Technology Laboratory Inc",
    "wof:placetype":"venue"
},
  "geometry": {"coordinates":[-105.086247,40.554237],"type":"Point"}
}