{
  "type": "Feature",
  "properties": {
    "addr:full":"311 10th St Golden CO 80401",
    "addr:housenumber":"311",
    "addr:postcode":"80401",
    "addr:street":"10Th St",
    "iso:country":"US",
    "sg:address":"311 10th St",
    "sg:city":"Golden",
    "sg:classifiers":[
        {
            "category":"Manufacturing",
            "subcategory":"Food",
            "type":"Manufacturing & Wholesale Goods"
        }
    ],
    "sg:phone":"+1 303 279 6565",
    "sg:postcode":"80401",
    "sg:province":"CO",
    "sg:tags":[
        "brewer"
    ],
    "sg:website":"www.coors.com",
    "wof:name":"Molson Coors Brewing Co",
    "wof:placetype":"venue"
},
  "geometry": {"coordinates":[-105.219397,39.759627],"type":"Point"}
}