{
  "type": "Feature",
  "properties": {
    "iso:country":"US",
    "sg:address":"60911 Golden Ct",
    "sg:city":"Olathe",
    "sg:classifiers":[
        {
            "category":"Building & Trades",
            "subcategory":"Construction",
            "type":"Services"
        }
    ],
    "sg:phone":"+1 970 323 8823",
    "sg:postcode":"81425",
    "sg:province":"CO",
    "sg:tags":[
        "residential"
    ],
    "wof:name":"Hummingbird Construction",
    "wof:placetype":"venue"
},
  "geometry": {"coordinates":[-107.952163,38.567995],"type":"Point"}
}