{
  "type": "Feature",
  "properties": {
    "iso:country":"US",
    "sg:address":"1080 S Wadsworth Blvd",
    "sg:city":"Denver",
    "sg:classifiers":[
        {
            "category":"Restaurant",
            "type":"Food & Drink"
        }
    ],
    "sg:menulink":"http://www.allmenus.com/co/northeast-jefferson/25128-el-7-mares/menu/",
    "sg:phone":"+1 303 975 9906",
    "sg:postcode":"80226",
    "sg:province":"CO",
    "sg:tags":[
        "mexican"
    ],
    "wof:name":"El 7 Mares",
    "wof:placetype":"venue"
},
  "geometry": {"coordinates":[-105.080584,39.697635],"type":"Point"}
}