{
  "type": "Feature",
  "properties": {
    "addr:full":"3064 Whitman Dr Evergreen CO 80439",
    "addr:housenumber":"3064",
    "addr:postcode":"80439",
    "addr:street":"Whitman Dr",
    "iso:country":"US",
    "sg:address":"3064 Whitman Dr",
    "sg:city":"Evergreen",
    "sg:classifiers":[
        {
            "category":"Professional",
            "subcategory":"Management & Consulting",
            "type":"Services"
        }
    ],
    "sg:phone":"+1 303 697 9977",
    "sg:postcode":"80439",
    "sg:province":"CO",
    "sg:tags":[
        "accident",
        "reconstruction"
    ],
    "sg:website":"www.vectorscientific.com",
    "wof:name":"Vector Scientific Inc",
    "wof:placetype":"venue"
},
  "geometry": {"coordinates":[-105.35414,39.659622],"type":"Point"}
}