{
  "type": "Feature",
  "properties": {
    "addr:full":"5575 Dtc Pkwy Greenwood Vlg CO 80111",
    "addr:housenumber":"5575",
    "addr:postcode":"co 80111",
    "addr:street":"Dtc Pkwy",
    "iso:country":"US",
    "sg:address":"5575 Dtc Pkwy",
    "sg:city":"Greenwood Vlg",
    "sg:classifiers":[
        {
            "category":"Banks & Credit Unions",
            "subcategory":"Investment Brokerage",
            "type":"Services"
        }
    ],
    "sg:phone":"+1 303 721 1079",
    "sg:postcode":"80111",
    "sg:province":"CO",
    "sg:tags":[
        "advisory",
        "financial"
    ],
    "wof:name":"AIG Royal Alliance",
    "wof:placetype":"venue"
},
  "geometry": {"coordinates":[-104.892656,39.613423],"type":"Point"}
}