{
  "type": "Feature",
  "properties": {
    "iso:country":"US",
    "sg:address":"375 6th St",
    "sg:city":"Penrose",
    "sg:classifiers":[
        {
            "category":"Professional",
            "subcategory":"Engineering",
            "type":"Services"
        }
    ],
    "sg:phone":"+1 719 372 6965",
    "sg:postcode":"81240",
    "sg:province":"CO",
    "sg:tags":[
        "construction"
    ],
    "wof:name":"G&G Enterprises",
    "wof:placetype":"venue"
},
  "geometry": {"coordinates":[-105.036818,38.435899],"type":"Point"}
}