{
  "type": "Feature",
  "properties": {
    "addr:full":"2121 S Colorado Blvd Denver CO 80222",
    "addr:housenumber":"2121",
    "addr:postcode":"80222",
    "addr:street":"S Colorado Blvd",
    "iso:country":"US",
    "sg:address":"2121 S Colorado Blvd",
    "sg:city":"Denver",
    "sg:classifiers":[
        {
            "category":"Shopping",
            "subcategory":"Crafts & Fabrics",
            "type":"Retail Goods"
        }
    ],
    "sg:phone":"+1 303 758 8244",
    "sg:postcode":"80222",
    "sg:province":"CO",
    "sg:tags":[
        "art",
        "supply"
    ],
    "sg:website":"www.guirys.com",
    "wof:name":"Guiry's Color Source",
    "wof:placetype":"venue"
},
  "geometry": {"coordinates":[-104.941261,39.677108],"type":"Point"}
}