{
  "type": "Feature",
  "properties": {
    "iso:country":"US",
    "sg:address":"1360 W 120th Ave",
    "sg:city":"Denver",
    "sg:classifiers":[
        {
            "category":"Personal",
            "subcategory":"Tattoo Parlor",
            "type":"Services"
        }
    ],
    "sg:phone":"+1 303 438 9499",
    "sg:postcode":"80234",
    "sg:province":"CO",
    "sg:tags":[
        "tattooing"
    ],
    "wof:name":"Smoky Banana Tattoo",
    "wof:placetype":"venue"
},
  "geometry": {"coordinates":[-105.005094,39.91377],"type":"Point"}
}