{
  "type": "Feature",
  "properties": {
    "iso:country":"US",
    "sg:address":"2101 Market St",
    "sg:city":"Denver",
    "sg:classifiers":[
        {
            "category":"Retail",
            "subcategory":"Laundry & Dry Cleaning",
            "type":"Services"
        }
    ],
    "sg:phone":"+1 720 389 6073",
    "sg:postcode":"80205",
    "sg:province":"CO",
    "wof:name":"Twentyone 01 Cleaners",
    "wof:placetype":"venue"
},
  "geometry": {"coordinates":[-104.991569,39.755197],"type":"Point"}
}