{
  "type": "Feature",
  "properties": {
    "iso:country":"US",
    "sg:address":"9635 S Maroon Cir",
    "sg:city":"Englewood",
    "sg:classifiers":[
        {
            "category":"Professional",
            "type":"Services"
        }
    ],
    "sg:phone":"+1 303 222 7571",
    "sg:postcode":"80112",
    "sg:province":"CO",
    "wof:name":"Mark Berghoefer",
    "wof:placetype":"venue"
},
  "geometry": {"coordinates":[-104.86066099999999,39.542358],"type":"Point"}
}