{
  "type": "Feature",
  "properties": {
    "iso:country":"US",
    "sg:address":"105 Jefferson St",
    "sg:city":"Breckenridge",
    "sg:classifiers":[
        {
            "category":"Professional",
            "subcategory":"Computer Services",
            "type":"Services"
        }
    ],
    "sg:phone":"+1 970 453 7010",
    "sg:postcode":"80466",
    "sg:province":"CO",
    "sg:tags":[
        "internet"
    ],
    "wof:name":"Leapfrog Internet Svc LLC",
    "wof:placetype":"venue"
},
  "geometry": {"coordinates":[-105.51111400000001,39.962573],"type":"Point"}
}