{
  "type": "Feature",
  "properties": {
    "addr:full":"4651 S Broadway Englewood CO 80113",
    "addr:housenumber":"4651",
    "addr:postcode":"80113",
    "addr:street":"S Broadway",
    "iso:country":"US",
    "sg:address":"4651 S Broadway",
    "sg:city":"Englewood",
    "sg:classifiers":[
        {
            "category":"Professional",
            "type":"Services"
        }
    ],
    "sg:phone":"+1 303 783 9988",
    "sg:postcode":"80113",
    "sg:province":"CO",
    "wof:name":"Maaliki Motors",
    "wof:placetype":"venue"
},
  "geometry": {"coordinates":[-104.987987,39.632252],"type":"Point"}
}