{
  "type": "Feature",
  "properties": {
    "iso:country":"US",
    "sg:address":"5524 S Jasper Way",
    "sg:city":"Aurora",
    "sg:classifiers":[
        {
            "category":"Wholesale",
            "subcategory":"Machinery & Supplies",
            "type":"Manufacturing & Wholesale Goods"
        }
    ],
    "sg:phone":"+1 303 766 9164",
    "sg:postcode":"80015",
    "sg:province":"CO",
    "sg:tags":[
        "equipment",
        "retail",
        "gas",
        "oil"
    ],
    "wof:name":"Jensco Pipe and Equipment Inc",
    "wof:placetype":"venue"
},
  "geometry": {"coordinates":[-104.80351,39.616026],"type":"Point"}
}