{
  "type": "Feature",
  "properties": {
    "iso:country":"US",
    "sg:address":"1313 Sherman St",
    "sg:city":"Denver",
    "sg:classifiers":[
        {
            "category":"Government",
            "subcategory":"Office",
            "type":"Public Place"
        }
    ],
    "sg:phone":"+1 303 866 2321",
    "sg:postcode":"80203",
    "sg:province":"CO",
    "sg:tags":[
        "state"
    ],
    "wof:name":"Personnel Dept",
    "wof:placetype":"venue"
},
  "geometry": {"coordinates":[-104.98493499999999,39.737653],"type":"Point"}
}