{
  "type": "Feature",
  "properties": {
    "iso:country":"US",
    "sg:address":"110 N Harrison Ave",
    "sg:city":"Lafayette",
    "sg:classifiers":[
        {
            "category":"Museum",
            "type":"Entertainment"
        }
    ],
    "sg:phone":"+1 303 604 2424",
    "sg:postcode":"80026",
    "sg:province":"CO",
    "sg:website":"www.wowmuseum.com",
    "wof:name":"Wow Childrens Museum",
    "wof:placetype":"venue"
},
  "geometry": {"coordinates":[-105.08928,39.999109],"type":"Point"}
}