{
  "type": "Feature",
  "properties": {
    "addr:full":"4630 Pearl St Denver CO 80216",
    "addr:housenumber":"4630",
    "addr:postcode":"80216",
    "addr:street":"Pearl St",
    "iso:country":"US",
    "sg:address":"4630 Pearl St",
    "sg:city":"Denver",
    "sg:classifiers":[
        {
            "category":"Wholesale",
            "subcategory":"Construction Materials",
            "type":"Manufacturing & Wholesale Goods"
        }
    ],
    "sg:phone":"+1 303 789 5950",
    "sg:postcode":"80216",
    "sg:province":"CO",
    "wof:name":"Chairwright Watertec",
    "wof:placetype":"venue"
},
  "geometry": {"coordinates":[-104.980009,39.781318],"type":"Point"}
}