{
  "type": "Feature",
  "properties": {
    "addr:full":"10204 US Hwy 34 Grand Lake CO 80447",
    "addr:housenumber":"10204",
    "addr:postcode":"80447",
    "addr:street":"Us Hwy 34",
    "iso:country":"US",
    "sg:address":"10204 US Hwy 34",
    "sg:city":"Grand Lake",
    "sg:classifiers":[
        {
            "category":"Building & Trades",
            "subcategory":"Electrical",
            "type":"Services"
        }
    ],
    "sg:phone":"+1 970 627 8215",
    "sg:postcode":"80447",
    "sg:province":"CO",
    "sg:tags":[
        "electric",
        "contractor"
    ],
    "wof:name":"Grand Lake Electric & Heating",
    "wof:placetype":"venue"
},
  "geometry": {"coordinates":[-105.86865,40.198381],"type":"Point"}
}