{
  "type": "Feature",
  "properties": {
    "addr:full":"4852 Chambers Rd Denver CO 80239",
    "addr:housenumber":"4852",
    "addr:postcode":"80239",
    "addr:street":"Chambers Rd",
    "iso:country":"US",
    "sg:address":"4852 Chambers Rd",
    "sg:city":"Denver",
    "sg:classifiers":[
        {
            "category":"Wholesale",
            "subcategory":"Machinery & Supplies",
            "type":"Manufacturing & Wholesale Goods"
        }
    ],
    "sg:phone":"+1 303 373 5678",
    "sg:postcode":"80239",
    "sg:province":"CO",
    "sg:tags":[
        "salon",
        "beauty"
    ],
    "wof:name":"T N T Beauty Supply",
    "wof:placetype":"venue"
},
  "geometry": {"coordinates":[-104.809791,39.779029],"type":"Point"}
}