{
  "type": "Feature",
  "properties": {
    "addr:full":"11723 Co Rd 2 Brighton CO 80603",
    "addr:housenumber":"11723",
    "addr:postcode":"80603",
    "addr:street":"Co Rd 2",
    "iso:country":"US",
    "sg:address":"11723 Co Rd 2",
    "sg:city":"Brighton",
    "sg:classifiers":[
        {
            "category":"Home & Garden",
            "subcategory":"Garden Supply",
            "type":"Retail Goods"
        }
    ],
    "sg:phone":"+1 303 637 7020",
    "sg:postcode":"80603",
    "sg:province":"CO",
    "sg:tags":[
        "landscaping",
        "equipment"
    ],
    "wof:name":"Hall-Irwin Landscape Materials",
    "wof:placetype":"venue"
},
  "geometry": {"coordinates":[-104.83107800000001,40.000478],"type":"Point"}
}