{
  "type": "Feature",
  "properties": {
    "iso:country":"US",
    "sg:address":"9519 Hollydale Ct",
    "sg:city":"Colorado Springs",
    "sg:classifiers":[
        {
            "category":"Professional",
            "type":"Services"
        }
    ],
    "sg:phone":"+1 719 282 9132",
    "sg:postcode":"80920",
    "sg:province":"CO",
    "wof:name":"Santiago Vargas",
    "wof:placetype":"venue"
},
  "geometry": {"coordinates":[-104.77155,38.96876],"type":"Point"}
}