{
  "type": "Feature",
  "properties": {
    "iso:country":"US",
    "sg:address":"7844 S Magnolia Way",
    "sg:city":"Centennial",
    "sg:classifiers":[
        {
            "category":"Shopping Center",
            "type":"Public Place"
        }
    ],
    "sg:phone":"+1 303 771 5548",
    "sg:postcode":"80112",
    "sg:province":"CO",
    "sg:tags":[
        "mall"
    ],
    "wof:name":"Bonbeck Hl",
    "wof:placetype":"venue"
},
  "geometry": {"coordinates":[-104.912267,39.575647],"type":"Point"}
}