{
  "type": "Feature",
  "properties": {
    "iso:country":"US",
    "sg:address":"1235 Lake Plaza Dr",
    "sg:city":"Colorado Springs",
    "sg:classifiers":[
        {
            "category":"Banks & Credit Unions",
            "subcategory":"Bank",
            "type":"Services"
        }
    ],
    "sg:phone":"+1 719 226 2051",
    "sg:postcode":"80906",
    "sg:province":"CO",
    "sg:tags":[
        "banker",
        "mortgage"
    ],
    "wof:name":"Chase Manhattan",
    "wof:placetype":"venue"
},
  "geometry": {"coordinates":[-104.805937,38.793315],"type":"Point"}
}