{
  "type": "Feature",
  "properties": {
    "addr:full":"1539 Platte St Ste 207 Denver CO 80202",
    "addr:housenumber":"1539",
    "addr:postcode":"80202",
    "addr:street":"Platte St Ste 207",
    "iso:country":"US",
    "sg:address":"1539 Platte St Ste 207",
    "sg:city":"Denver",
    "sg:classifiers":[
        {
            "category":"Sports & Exercise",
            "subcategory":"Gym",
            "type":"Entertainment"
        }
    ],
    "sg:phone":"+1 303 477 0424",
    "sg:postcode":"80202",
    "sg:province":"CO",
    "sg:tags":[
        "yoga"
    ],
    "wof:name":"Root Yoga Center",
    "wof:placetype":"venue"
},
  "geometry": {"coordinates":[-105.008522,39.757081],"type":"Point"}
}