{
  "type": "Feature",
  "properties": {
    "iso:country":"US",
    "sg:address":"115 Main St",
    "sg:city":"Central City",
    "sg:classifiers":[
        {
            "category":"Shopping",
            "subcategory":"Clothing, Apparel, & Fashions",
            "type":"Retail Goods"
        },
        {
            "category":"Home & Garden",
            "subcategory":"Home Furnishings",
            "type":"Retail Goods"
        }
    ],
    "sg:phone":"+1 303 582 5524",
    "sg:postcode":"80422",
    "sg:province":"CO",
    "sg:tags":[
        "decor",
        "accessory"
    ],
    "wof:name":"Bevie Sue's Emporium",
    "wof:placetype":"venue"
},
  "geometry": {"coordinates":[-105.49365899999999,39.801456],"type":"Point"}
}