{
  "type": "Feature",
  "properties": {
    "addr:full":"504 N Grand Ave Pueblo CO 81003",
    "addr:housenumber":"504",
    "addr:postcode":"81003",
    "addr:street":"N Grand Ave",
    "iso:country":"US",
    "sg:address":"504 N Grand Ave",
    "sg:city":"Pueblo",
    "sg:classifiers":[
        {
            "category":"Shopping",
            "subcategory":"Computers & Home Electronics",
            "type":"Retail Goods"
        }
    ],
    "sg:phone":"+1 719 544 9407",
    "sg:postcode":"81003",
    "sg:province":"CO",
    "wof:name":"East Hat",
    "wof:placetype":"venue"
},
  "geometry": {"coordinates":[-104.611531,38.271963],"type":"Point"}
}