{
  "type": "Feature",
  "properties": {
    "addr:full":"1110 S Joliet St Aurora CO 80012",
    "addr:housenumber":"1110",
    "addr:postcode":"80012",
    "addr:street":"S Joliet St",
    "iso:country":"US",
    "sg:address":"1110 S Joliet St",
    "sg:city":"Aurora",
    "sg:classifiers":[
        {
            "category":"Real Estate",
            "subcategory":"Real Estate Operator",
            "type":"Services"
        }
    ],
    "sg:phone":"+1 303 755 4995",
    "sg:postcode":"80012",
    "sg:province":"CO",
    "sg:tags":[
        "apartment"
    ],
    "wof:name":"Buckingham Manor Apartments",
    "wof:placetype":"venue"
},
  "geometry": {"coordinates":[-104.861738,39.696405],"type":"Point"}
}