{
  "type": "Feature",
  "properties": {
    "addr:full":"1907 Glenisle Ave Durango CO 81301",
    "addr:housenumber":"1907",
    "addr:postcode":"co 81301",
    "addr:street":"Glenisle Ave",
    "iso:country":"US",
    "sg:address":"1907 Glenisle Ave",
    "sg:city":"Durango",
    "sg:classifiers":[
        {
            "category":"Communications",
            "type":"Services"
        }
    ],
    "sg:phone":"+1 970 385 0888",
    "sg:postcode":"81301",
    "sg:province":"CO",
    "sg:tags":[
        "communication"
    ],
    "wof:name":"Ferguson Communication",
    "wof:placetype":"venue"
},
  "geometry": {"coordinates":[-107.884985,37.285599],"type":"Point"}
}