{
  "type": "Feature",
  "properties": {
    "iso:country":"US",
    "sg:address":"19546 E Iowa Cir",
    "sg:city":"Aurora",
    "sg:classifiers":[
        {
            "category":"Insurance",
            "subcategory":"Insurance Agent",
            "type":"Services"
        }
    ],
    "sg:phone":"+1 303 751 4112",
    "sg:postcode":"80017",
    "sg:province":"CO",
    "sg:tags":[
        "legal"
    ],
    "wof:name":"J A Christensen & Associates",
    "wof:placetype":"venue"
},
  "geometry": {"coordinates":[-104.759854,39.688159],"type":"Point"}
}