{
  "type": "Feature",
  "properties": {
    "iso:country":"US",
    "sg:address":"1875 Lawrence St",
    "sg:city":"Denver",
    "sg:classifiers":[
        {
            "category":"Professional",
            "subcategory":"Lawyer & Legal Services",
            "type":"Services"
        }
    ],
    "sg:phone":"+1 303 634 4000",
    "sg:postcode":"80202",
    "sg:province":"CO",
    "wof:name":"Johnson Gregory W Atty",
    "wof:placetype":"venue"
},
  "geometry": {"coordinates":[-104.99299600000001,39.751099],"type":"Point"}
}