{
  "type": "Feature",
  "properties": {
    "iso:country":"US",
    "sg:address":"11626 W 71st Dr",
    "sg:city":"Arvada",
    "sg:classifiers":[
        {
            "category":"Professional",
            "type":"Services"
        }
    ],
    "sg:phone":"+1 303 940 9331",
    "sg:postcode":"80004",
    "sg:province":"CO",
    "wof:name":"Conifer 26664 LLC",
    "wof:placetype":"venue"
},
  "geometry": {"coordinates":[-105.13012999999999,39.824757],"type":"Point"}
}