{
  "type": "Feature",
  "properties": {
    "addr:full":"22 Roland Dr Bailey CO 80421",
    "addr:housenumber":"22",
    "addr:postcode":"80421",
    "addr:street":"Roland Dr",
    "iso:country":"US",
    "sg:address":"22 Roland Dr",
    "sg:city":"Bailey",
    "sg:classifiers":[
        {
            "category":"Food & Beverages",
            "subcategory":"Liquor & Beverages",
            "type":"Retail Goods"
        }
    ],
    "sg:phone":"+1 303 838 5862",
    "sg:postcode":"80421",
    "sg:province":"CO",
    "wof:name":"Bristlecone Liquor",
    "wof:placetype":"venue"
},
  "geometry": {"coordinates":[-105.41915,39.44228],"type":"Point"}
}