{
  "type": "Feature",
  "properties": {
    "iso:country":"US",
    "sg:address":"16367 S Townsend Ave",
    "sg:city":"Montrose",
    "sg:classifiers":[
        {
            "category":"Personal",
            "subcategory":"Beauty Salon",
            "type":"Services"
        }
    ],
    "sg:phone":"+1 970 249 2019",
    "sg:postcode":"81401",
    "sg:province":"CO",
    "wof:name":"Lasting Impressions Hair Dsgn",
    "wof:placetype":"venue"
},
  "geometry": {"coordinates":[-107.866302,38.45378],"type":"Point"}
}