{
  "type": "Feature",
  "properties": {
    "iso:country":"US",
    "sg:address":"51511 Amber Rd",
    "sg:city":"Delta",
    "sg:classifiers":[
        {
            "category":"Retail",
            "subcategory":"Animal Services",
            "type":"Services"
        }
    ],
    "sg:phone":"+1 970 240 0263",
    "sg:postcode":"81416",
    "sg:province":"CO",
    "wof:name":"Falkenhof Canibes",
    "wof:placetype":"venue"
},
  "geometry": {"coordinates":[-108.11832,38.66438],"type":"Point"}
}