{
  "type": "Feature",
  "properties": {
    "addr:full":"33 Still Forest Ln Woodland Park CO 80863",
    "addr:housenumber":"33",
    "addr:postcode":"80863",
    "addr:street":"Still Forest Ln",
    "iso:country":"US",
    "sg:address":"33 Still Forest Ln",
    "sg:city":"Woodland Park",
    "sg:classifiers":[
        {
            "category":"Building & Trades",
            "subcategory":"Construction",
            "type":"Services"
        }
    ],
    "sg:phone":"+1 719 632 5906",
    "sg:postcode":"80863",
    "sg:province":"CO",
    "sg:tags":[
        "painter"
    ],
    "wof:name":"Wesco Painting",
    "wof:placetype":"venue"
},
  "geometry": {"coordinates":[-105.08574299999999,38.975452],"type":"Point"}
}