{
  "type": "Feature",
  "properties": {
    "addr:full":"117 W Ryus Ave La Veta CO 81055",
    "addr:housenumber":"117",
    "addr:postcode":"81055",
    "addr:street":"W Ryus Ave",
    "iso:country":"US",
    "sg:address":"117 W Ryus Ave",
    "sg:city":"La Veta",
    "sg:classifiers":[
        {
            "category":"Government",
            "subcategory":"Post Office",
            "type":"Public Place"
        }
    ],
    "sg:phone":"+1 719 742 3733",
    "sg:postcode":"81055",
    "sg:province":"CO",
    "wof:name":"US Post Office",
    "wof:placetype":"venue"
},
  "geometry": {"coordinates":[-105.00935800000001,37.509034],"type":"Point"}
}