{
  "type": "Feature",
  "properties": {
    "addr:full":"8790 W Colfax Ave Lakewood CO 80215",
    "addr:housenumber":"8790",
    "addr:postcode":"80215",
    "addr:street":"W Colfax Ave",
    "iso:country":"US",
    "sg:address":"8790 W Colfax Ave",
    "sg:city":"Lakewood",
    "sg:classifiers":[
        {
            "category":"Sports & Exercise",
            "subcategory":"Gym",
            "type":"Entertainment"
        }
    ],
    "sg:phone":"+1 303 231 9992",
    "sg:postcode":"80215",
    "sg:province":"CO",
    "sg:tags":[
        "club",
        "health",
        "studio",
        "gymnasium"
    ],
    "wof:name":"Flex Gym Of Colorado",
    "wof:placetype":"venue"
},
  "geometry": {"coordinates":[-105.095073,39.740171],"type":"Point"}
}