{
  "type": "Feature",
  "properties": {
    "addr:full":"102 Tunnel Dr Canon City CO 81212",
    "addr:housenumber":"102",
    "addr:postcode":"81212",
    "addr:street":"Tunnel Dr",
    "iso:country":"US",
    "sg:address":"102 Tunnel Dr",
    "sg:city":"Canon City",
    "sg:classifiers":[
        {
            "category":"Home & Garden",
            "subcategory":"Building Materials",
            "type":"Retail Goods"
        }
    ],
    "sg:phone":"+1 719 276 5120",
    "sg:postcode":"81212",
    "sg:province":"CO",
    "sg:tags":[
        "mixed",
        "concrete"
    ],
    "wof:name":"Precision Pre-Mix",
    "wof:placetype":"venue"
},
  "geometry": {"coordinates":[-105.254605,38.437096],"type":"Point"}
}