{
  "type": "Feature",
  "properties": {
    "iso:country":"US",
    "sg:address":"7800 Smith Road",
    "sg:city":"Denver",
    "sg:classifiers":[
        {
            "category":"Restaurant",
            "type":"Food & Drink"
        }
    ],
    "sg:phone":"+1 720 974 7313",
    "sg:postcode":"80207",
    "sg:province":"CO",
    "wof:name":"Subway Sandwiches & Salads",
    "wof:placetype":"venue"
},
  "geometry": {"coordinates":[-104.897633,39.770923],"type":"Point"}
}