{
  "type": "Feature",
  "properties": {
    "addr:full":"10978 Co Rd 26 Cortez CO 81321",
    "addr:housenumber":"10978;26",
    "addr:postcode":"81321",
    "addr:street":"Co Rd",
    "iso:country":"US",
    "sg:address":"10978 Co Rd 26",
    "sg:city":"Cortez",
    "sg:classifiers":[
        {
            "category":"Personal",
            "subcategory":"Beauty Salon",
            "type":"Services"
        }
    ],
    "sg:phone":"+1 970 565 1184",
    "sg:postcode":"81321",
    "sg:province":"CO",
    "wof:name":"A Cut Above Beauty Academy",
    "wof:placetype":"venue"
},
  "geometry": {"coordinates":[-108.57267899999999,37.369379],"type":"Point"}
}