{
  "type": "Feature",
  "properties": {
    "iso:country":"US",
    "sg:address":"630 Main St",
    "sg:city":"Erie",
    "sg:classifiers":[
        {
            "category":"Shopping",
            "subcategory":"Tobacco",
            "type":"Retail Goods"
        }
    ],
    "sg:phone":"+1 303 833 2882",
    "sg:postcode":"80516",
    "sg:province":"CO",
    "sg:tags":[
        "cigarette",
        "cigar",
        "dealer"
    ],
    "wof:name":"Smoke Shanti",
    "wof:placetype":"venue"
},
  "geometry": {"coordinates":[-105.052824,40.05109],"type":"Point"}
}