{
  "type": "Feature",
  "properties": {
    "addr:full":"7750 N Union Blvd Colorado Springs CO 80920",
    "addr:housenumber":"7750",
    "addr:postcode":"80920",
    "addr:street":"N Union Blvd",
    "iso:country":"US",
    "sg:address":"7750 N Union Blvd",
    "sg:city":"Colorado Springs",
    "sg:classifiers":[
        {
            "category":"Social Services",
            "type":"Services"
        }
    ],
    "sg:phone":"+1 719 264 0718",
    "sg:postcode":"80920",
    "sg:province":"CO",
    "sg:tags":[
        "counseling"
    ],
    "wof:name":"Beyond Milestones Counseling",
    "wof:placetype":"venue"
},
  "geometry": {"coordinates":[-104.774035,38.945059],"type":"Point"}
}