{
  "type": "Feature",
  "properties": {
    "iso:country":"US",
    "sg:address":"705 S Main St",
    "sg:city":"Creede",
    "sg:classifiers":[
        {
            "category":"Real Estate",
            "subcategory":"Real Estate Agent",
            "type":"Services"
        }
    ],
    "sg:phone":"+1 719 658 2900",
    "sg:postcode":"81130",
    "sg:province":"CO",
    "sg:website":"www.rinconrealestate.com",
    "wof:name":"Rincon Real Estate",
    "wof:placetype":"venue"
},
  "geometry": {"coordinates":[-106.925386,37.846779],"type":"Point"}
}