{
  "type": "Feature",
  "properties": {
    "addr:full":"17581 E Eldorado Cir Aurora CO 80013",
    "addr:housenumber":"17581",
    "addr:postcode":"80013",
    "addr:street":"E Eldorado Cir",
    "iso:country":"US",
    "sg:address":"17581 E Eldorado Cir",
    "sg:city":"Aurora",
    "sg:classifiers":[
        {
            "category":"Shopping",
            "subcategory":"Florist",
            "type":"Retail Goods"
        }
    ],
    "sg:phone":"+1 303 927 7150",
    "sg:postcode":"80013",
    "sg:province":"CO",
    "wof:name":"Compass Rose Concierge",
    "wof:placetype":"venue"
},
  "geometry": {"coordinates":[-104.785145,39.65543],"type":"Point"}
}