{
  "type": "Feature",
  "properties": {
    "addr:full":"4825 Oakland St Denver CO 80239",
    "addr:housenumber":"4825",
    "addr:postcode":"80239",
    "addr:street":"Oakland St",
    "iso:country":"US",
    "sg:address":"4825 Oakland St",
    "sg:city":"Denver",
    "sg:classifiers":[
        {
            "category":"Manufacturing",
            "subcategory":"Printing",
            "type":"Manufacturing & Wholesale Goods"
        }
    ],
    "sg:phone":"+1 303 371 3600",
    "sg:postcode":"80239",
    "sg:province":"CO",
    "sg:tags":[
        "printer"
    ],
    "wof:name":"Hotchkiss Inc",
    "wof:placetype":"venue"
},
  "geometry": {"coordinates":[-104.850762,39.783687],"type":"Point"}
}