{
  "type": "Feature",
  "properties": {
    "addr:full":"80 Metcalf Rd Avon CO 81620",
    "addr:housenumber":"80",
    "addr:postcode":"81620",
    "addr:street":"Metcalf Rd",
    "iso:country":"US",
    "sg:address":"80 Metcalf Rd",
    "sg:city":"Avon",
    "sg:classifiers":[
        {
            "category":"Building & Trades",
            "subcategory":"Construction",
            "type":"Services"
        }
    ],
    "sg:phone":"+1 970 524 4500",
    "sg:postcode":"81620",
    "sg:province":"CO",
    "sg:tags":[
        "hanging",
        "contractor"
    ],
    "wof:name":"Swanepoel Painting Inc",
    "wof:placetype":"venue"
},
  "geometry": {"coordinates":[-106.53751699999999,39.643824],"type":"Point"}
}