{
  "type": "Feature",
  "properties": {
    "iso:country":"US",
    "sg:address":"1610 29th Avenue Pl # 100",
    "sg:city":"Greeley",
    "sg:classifiers":[
        {
            "category":"Social Services",
            "type":"Services"
        },
        {
            "category":"Personal",
            "type":"Services"
        }
    ],
    "sg:phone":"+1 970 405 9001",
    "sg:postcode":"80634",
    "sg:province":"CO",
    "sg:tags":[
        "family",
        "counselors-licensed",
        "individual",
        "marriage",
        "child",
        "professional",
        "counselor"
    ],
    "wof:name":"Hope Family Services Inc",
    "wof:placetype":"venue"
},
  "geometry": {"coordinates":[-104.728013,40.414499],"type":"Point"}
}