{
  "type": "Feature",
  "properties": {
    "iso:country":"US",
    "sg:address":"289 S Main St",
    "sg:city":"Creede",
    "sg:classifiers":[
        {
            "category":"Real Estate",
            "subcategory":"Real Estate Agent",
            "type":"Services"
        }
    ],
    "sg:phone":"+1 719 658 2262",
    "sg:postcode":"81130",
    "sg:province":"CO",
    "sg:website":"www.wcrealty.com",
    "wof:name":"Willow Creek Realty",
    "wof:placetype":"venue"
},
  "geometry": {"coordinates":[-106.926534,37.850969],"type":"Point"}
}