{
  "type": "Feature",
  "properties": {
    "iso:country":"US",
    "sg:address":"11411 Hwy 65",
    "sg:city":"Eckert",
    "sg:classifiers":[
        {
            "category":"Health Services",
            "subcategory":"Nursing And Care Facility",
            "type":"Services"
        }
    ],
    "sg:phone":"+1 970 835 3113",
    "sg:postcode":"81418",
    "sg:province":"CO",
    "sg:tags":[
        "home",
        "retirement",
        "community"
    ],
    "wof:name":"Horizons Healthcare",
    "wof:placetype":"venue"
},
  "geometry": {"coordinates":[-107.972098,38.828068],"type":"Point"}
}