{
  "type": "Feature",
  "properties": {
    "iso:country":"US",
    "sg:address":"1250 S Hover Rd",
    "sg:city":"Longmont",
    "sg:classifiers":[
        {
            "category":"Retail",
            "subcategory":"Portrait Studio",
            "type":"Services"
        }
    ],
    "sg:phone":"+1 303 684 0001",
    "sg:postcode":"80501",
    "sg:province":"CO",
    "sg:tags":[
        "photographer",
        "photo"
    ],
    "wof:name":"Picture It Studios",
    "wof:placetype":"venue"
},
  "geometry": {"coordinates":[-105.130709,40.144081],"type":"Point"}
}