{
  "type": "Feature",
  "properties": {
    "addr:full":"340 Lakeside Dr Pagosa Springs CO 81147",
    "addr:housenumber":"340",
    "addr:postcode":"81147",
    "addr:street":"Lakeside Dr",
    "iso:country":"US",
    "sg:address":"340 Lakeside Dr",
    "sg:city":"Pagosa Springs",
    "sg:classifiers":[
        {
            "category":"Wholesale",
            "subcategory":"Durable Goods & Equipment",
            "type":"Manufacturing & Wholesale Goods"
        }
    ],
    "sg:phone":"+1 970 731 4280",
    "sg:postcode":"81147",
    "sg:province":"CO",
    "sg:tags":[
        "representative",
        "manufacturer"
    ],
    "wof:name":"Alpine Componets",
    "wof:placetype":"venue"
},
  "geometry": {"coordinates":[-107.08783699999999,37.260488],"type":"Point"}
}