{
  "type": "Feature",
  "properties": {
    "iso:country":"US",
    "sg:address":"973 E Spaulding Ave",
    "sg:city":"Pueblo West",
    "sg:classifiers":[
        {
            "category":"Building & Trades",
            "subcategory":"Construction",
            "type":"Services"
        }
    ],
    "sg:phone":"+1 719 564 3772",
    "sg:postcode":"81007",
    "sg:province":"CO",
    "sg:tags":[
        "general",
        "contractor"
    ],
    "wof:name":"Zede Roofing",
    "wof:placetype":"venue"
},
  "geometry": {"coordinates":[-104.696958,38.319186],"type":"Point"}
}