{
  "type": "Feature",
  "properties": {
    "iso:country":"US",
    "sg:address":"421 Main St",
    "sg:city":"Windsor",
    "sg:classifiers":[
        {
            "category":"Professional",
            "subcategory":"Lawyer & Legal Services",
            "type":"Services"
        }
    ],
    "sg:phone":"+1 970 686 6005",
    "sg:postcode":"80550",
    "sg:province":"CO",
    "sg:tags":[
        "attorney"
    ],
    "wof:name":"Wick Campbell Bramer Ukasick",
    "wof:placetype":"venue"
},
  "geometry": {"coordinates":[-104.90255999999999,40.479819],"type":"Point"}
}