{
  "type": "Feature",
  "properties": {
    "iso:country":"US",
    "sg:address":"14599 US Hwy 287",
    "sg:city":"Laporte",
    "sg:classifiers":[
        {
            "category":"Professional",
            "subcategory":"Business Services",
            "type":"Services"
        }
    ],
    "sg:phone":"+1 970 493 4543",
    "sg:postcode":"80535",
    "sg:province":"CO",
    "sg:tags":[
        "interior",
        "consultant",
        "design",
        "decorator"
    ],
    "wof:name":"Ivy League Paint Finishes",
    "wof:placetype":"venue"
},
  "geometry": {"coordinates":[-105.18417599999999,40.765345],"type":"Point"}
}