{
  "type": "Feature",
  "properties": {
    "addr:full":"2525 S Broadway Denver CO 80210",
    "addr:housenumber":"2525",
    "addr:postcode":"80210",
    "addr:street":"S Broadway",
    "iso:country":"US",
    "sg:address":"2525 S Broadway",
    "sg:city":"Denver",
    "sg:classifiers":[
        {
            "category":"Wholesale",
            "subcategory":"Computers",
            "type":"Manufacturing & Wholesale Goods"
        }
    ],
    "sg:phone":"+1 720 570 1173",
    "sg:postcode":"80210",
    "sg:province":"CO",
    "wof:name":"Retriever Software",
    "wof:placetype":"venue"
},
  "geometry": {"coordinates":[-104.987443,39.670676],"type":"Point"}
}