{
  "type": "Feature",
  "properties": {
    "addr:full":"611 Eisenhauer St Grand Junction CO 81505",
    "addr:housenumber":"611",
    "addr:postcode":"81505",
    "addr:street":"Eisenhauer St",
    "iso:country":"US",
    "sg:address":"611 Eisenhauer St",
    "sg:city":"Grand Junction",
    "sg:classifiers":[
        {
            "category":"Wholesale",
            "subcategory":"Medical Equipment & Supplies",
            "type":"Manufacturing & Wholesale Goods"
        }
    ],
    "sg:phone":"+1 970 245 3845",
    "sg:postcode":"81505",
    "sg:province":"CO",
    "sg:tags":[
        "optical"
    ],
    "sg:website":"www.westconlens.com",
    "wof:name":"West Con Contact Lens",
    "wof:placetype":"venue"
},
  "geometry": {"coordinates":[-108.581907,39.093358],"type":"Point"}
}