{
  "type": "Feature",
  "properties": {
    "iso:country":"US",
    "sg:address":"7631 Monaco St",
    "sg:city":"Commerce City",
    "sg:classifiers":[
        {
            "category":"Education",
            "subcategory":"School",
            "type":"Public Place"
        }
    ],
    "sg:phone":"+1 303 287 0307",
    "sg:postcode":"80022",
    "sg:province":"CO",
    "wof:name":"Monaco Elementary 14",
    "wof:placetype":"venue"
},
  "geometry": {"coordinates":[-104.912745,39.83452],"type":"Point"}
}