{
  "type": "Feature",
  "properties": {
    "addr:full":"113 Cameron Dr Fort Collins CO 80525",
    "addr:housenumber":"113",
    "addr:postcode":"80525",
    "addr:street":"Cameron Dr",
    "iso:country":"US",
    "sg:address":"113 Cameron Dr",
    "sg:city":"Fort Collins",
    "sg:classifiers":[
        {
            "category":"Wholesale",
            "subcategory":"Office Equipment",
            "type":"Manufacturing & Wholesale Goods"
        },
        {
            "category":"Shopping",
            "type":"Retail Goods"
        }
    ],
    "sg:phone":"+1 970 493 2679",
    "sg:postcode":"80525",
    "sg:province":"CO",
    "sg:tags":[
        "machine",
        "duplicating",
        "merchandise",
        "copying"
    ],
    "wof:name":"Frontier Business Products Co",
    "wof:placetype":"venue"
},
  "geometry": {"coordinates":[-105.07912899999999,40.515158],"type":"Point"}
}