{
  "type": "Feature",
  "properties": {
    "iso:country":"US",
    "sg:address":"2560 Sheridan Boulevard",
    "sg:city":"Denver",
    "sg:classifiers":[
        {
            "category":"Health Services",
            "subcategory":"Dentist",
            "type":"Services"
        }
    ],
    "sg:phone":"+1 303 477 7700",
    "sg:postcode":"80214",
    "sg:province":"CO",
    "wof:name":"Cable Ryan G",
    "wof:placetype":"venue"
},
  "geometry": {"coordinates":[-105.053241,39.754136],"type":"Point"}
}