{
  "type": "Feature",
  "properties": {
    "iso:country":"US",
    "sg:address":"333 S Federal Boulevard",
    "sg:city":"Denver",
    "sg:classifiers":[
        {
            "category":"Professional",
            "subcategory":"Lawyer & Legal Services",
            "type":"Services"
        }
    ],
    "sg:phone":"+1 303 922 3448",
    "sg:postcode":"80219",
    "sg:province":"CO",
    "wof:name":"Carl Ream Attorney At Law",
    "wof:placetype":"venue"
},
  "geometry": {"coordinates":[-105.025087,39.710569],"type":"Point"}
}