{
  "type": "Feature",
  "properties": {
    "addr:full":"6501 Greenwood Plaza Blvd Greenwood Vlg CO 80111",
    "addr:housenumber":"6501",
    "addr:postcode":"co 80111",
    "addr:street":"Greenwood Plaza Blvd",
    "iso:country":"US",
    "sg:address":"6501 Greenwood Plaza Blvd",
    "sg:city":"Greenwood Vlg",
    "sg:classifiers":[
        {
            "category":"Real Estate",
            "subcategory":"Real Estate Services",
            "type":"Services"
        }
    ],
    "sg:phone":"+1 303 779 9555",
    "sg:postcode":"80111",
    "sg:province":"CO",
    "sg:tags":[
        "company",
        "title"
    ],
    "sg:website":"www.landam.com",
    "wof:name":"Lawyers Title",
    "wof:placetype":"venue"
},
  "geometry": {"coordinates":[-104.894853,39.598041],"type":"Point"}
}