{
  "type": "Feature",
  "properties": {
    "iso:country":"US",
    "sg:address":"6021 Greenwood Plaza Blvd",
    "sg:city":"Greenwood Vlg",
    "sg:classifiers":[
        {
            "category":"Insurance",
            "subcategory":"Insurance Agent",
            "type":"Services"
        }
    ],
    "sg:phone":"+1 720 489 7189",
    "sg:postcode":"80111",
    "sg:province":"CO",
    "wof:name":"Kahl & Assoc",
    "wof:placetype":"venue"
},
  "geometry": {"coordinates":[-104.89556,39.607583],"type":"Point"}
}