{
  "type": "Feature",
  "properties": {
    "iso:country":"US",
    "sg:address":"9567 S University Blvd",
    "sg:city":"Highlands Ranch",
    "sg:classifiers":[
        {
            "category":"Retail",
            "subcategory":"Laundry & Dry Cleaning",
            "type":"Services"
        }
    ],
    "sg:phone":"+1 303 683 0877",
    "sg:postcode":"80126",
    "sg:province":"CO",
    "sg:tags":[
        "cleaners"
    ],
    "wof:name":"Dry Cleaning Station",
    "wof:placetype":"venue"
},
  "geometry": {"coordinates":[-104.942526,39.543513],"type":"Point"}
}