{
  "type": "Feature",
  "properties": {
    "iso:country":"US",
    "sg:address":"2326 N Union Blvd",
    "sg:city":"Colorado Springs",
    "sg:classifiers":[
        {
            "category":"Professional",
            "type":"Services"
        }
    ],
    "sg:phone":"+1 719 444 8534",
    "sg:postcode":"80909",
    "sg:province":"CO",
    "wof:name":"Joseph S Craycraft",
    "wof:placetype":"venue"
},
  "geometry": {"coordinates":[-104.794206,38.865591],"type":"Point"}
}