{
  "type": "Feature",
  "properties": {
    "iso:country":"US",
    "sg:address":"1305 N Goff St",
    "sg:city":"Eads",
    "sg:classifiers":[
        {
            "category":"Government",
            "subcategory":"Court House",
            "type":"Public Place"
        },
        {
            "category":"Government",
            "subcategory":"Office",
            "type":"Public Place"
        }
    ],
    "sg:phone":"+1 719 438 5558",
    "sg:postcode":"81036",
    "sg:province":"CO",
    "sg:tags":[
        "county"
    ],
    "wof:name":"Kiowa County Court Clerk",
    "wof:placetype":"venue"
},
  "geometry": {"coordinates":[-102.780289,38.479975],"type":"Point"}
}