{
  "type": "Feature",
  "properties": {
    "iso:country":"US",
    "sg:address":"208 Midland Ave",
    "sg:city":"Basalt",
    "sg:classifiers":[
        {
            "category":"Building & Trades",
            "subcategory":"Landscaping Services",
            "type":"Services"
        }
    ],
    "sg:phone":"+1 970 927 2194",
    "sg:postcode":"81621",
    "sg:province":"CO",
    "sg:tags":[
        "designer",
        "landscape"
    ],
    "wof:name":"Greg Mozian & Assoc Inc",
    "wof:placetype":"venue"
},
  "geometry": {"coordinates":[-107.034206,39.369081],"type":"Point"}
}