{
  "type": "Feature",
  "properties": {
    "addr:full":"2548 S Broadway Denver CO 80210",
    "addr:housenumber":"2548",
    "addr:postcode":"80210",
    "addr:street":"S Broadway",
    "iso:country":"US",
    "sg:address":"2548 S Broadway",
    "sg:city":"Denver",
    "sg:classifiers":[
        {
            "category":"Personal",
            "type":"Services"
        }
    ],
    "sg:phone":"+1 303 888 9685",
    "sg:postcode":"80210",
    "sg:province":"CO",
    "sg:tags":[
        "therapist",
        "massage"
    ],
    "wof:name":"Muscle Mender",
    "wof:placetype":"venue"
},
  "geometry": {"coordinates":[-104.987509,39.670367],"type":"Point"}
}