{
  "type": "Feature",
  "properties": {
    "iso:country":"US",
    "sg:address":"911 Motor City Dr",
    "sg:city":"Colorado Springs",
    "sg:classifiers":[
        {
            "category":"Wholesale",
            "subcategory":"Motor Vehicles",
            "type":"Manufacturing & Wholesale Goods"
        }
    ],
    "sg:phone":"+1 719 633 9996",
    "sg:postcode":"80906",
    "sg:province":"CO",
    "sg:tags":[
        "car",
        "used",
        "sales"
    ],
    "wof:name":"Elite Motorcars",
    "wof:placetype":"venue"
},
  "geometry": {"coordinates":[-104.8334,38.817031],"type":"Point"}
}