{
  "type": "Feature",
  "properties": {
    "addr:full":"840 W Hampden Ave Englewood CO 80110",
    "addr:housenumber":"840",
    "addr:postcode":"80110",
    "addr:street":"W Hampden Ave",
    "iso:country":"US",
    "sg:address":"840 W Hampden Ave",
    "sg:city":"Englewood",
    "sg:classifiers":[
        {
            "category":"Retail",
            "subcategory":"Auto Repair",
            "type":"Services"
        }
    ],
    "sg:phone":"+1 303 761 1543",
    "sg:postcode":"80110",
    "sg:province":"CO",
    "sg:tags":[
        "repairing",
        "automobile"
    ],
    "wof:name":"Young's Tire & Svc Ctr",
    "wof:placetype":"venue"
},
  "geometry": {"coordinates":[-104.997786,39.653141],"type":"Point"}
}