{
  "type": "Feature",
  "properties": {
    "addr:full":"5334 Montebello Ln Colorado Springs CO 80918",
    "addr:housenumber":"5334",
    "addr:postcode":"80918",
    "addr:street":"Montebello Ln",
    "iso:country":"US",
    "sg:address":"5334 Montebello Ln",
    "sg:city":"Colorado Springs",
    "sg:classifiers":[
        {
            "category":"Real Estate",
            "subcategory":"Real Estate Agent",
            "type":"Services"
        }
    ],
    "sg:phone":"+1 719 599 4445",
    "sg:postcode":"80918",
    "sg:province":"CO",
    "wof:name":"Century 21",
    "wof:placetype":"venue"
},
  "geometry": {"coordinates":[-104.785572,38.909269],"type":"Point"}
}