{
  "type": "Feature",
  "properties": {
    "addr:full":"119 Co Rd 308 Dillon CO 80452",
    "addr:housenumber":"119;308",
    "addr:postcode":"80452",
    "addr:street":"Co Rd",
    "iso:country":"US",
    "sg:address":"119 Co Rd 308",
    "sg:city":"Dillon",
    "sg:classifiers":[
        {
            "category":"Building & Trades",
            "subcategory":"Construction",
            "type":"Services"
        }
    ],
    "sg:phone":"+1 970 468 1367",
    "sg:postcode":"80452",
    "sg:province":"CO",
    "sg:tags":[
        "general",
        "contractor"
    ],
    "sg:website":"www.isibuilders.com",
    "wof:name":"Infinite Scope Inc",
    "wof:placetype":"venue"
},
  "geometry": {"coordinates":[-105.599045,39.764428],"type":"Point"}
}