{
  "type": "Feature",
  "properties": {
    "addr:full":"525 N Main St Gunnison CO 81230",
    "addr:housenumber":"525",
    "addr:postcode":"81230",
    "addr:street":"N Main St",
    "iso:country":"US",
    "sg:address":"525 N Main St",
    "sg:city":"Gunnison",
    "sg:classifiers":[
        {
            "category":"Banks & Credit Unions",
            "subcategory":"Investment Brokerage",
            "type":"Services"
        }
    ],
    "sg:phone":"+1 970 641 0900",
    "sg:postcode":"81230",
    "sg:province":"CO",
    "sg:tags":[
        "security"
    ],
    "wof:name":"U Bs Financial Services",
    "wof:placetype":"venue"
},
  "geometry": {"coordinates":[-106.92698799999999,38.549651],"type":"Point"}
}