{
  "type": "Feature",
  "properties": {
    "iso:country":"US",
    "sg:address":"2630 S Tejon St",
    "sg:city":"Englewood",
    "sg:classifiers":[
        {
            "category":"Manufacturing",
            "subcategory":"Tools & Machinery",
            "type":"Manufacturing & Wholesale Goods"
        }
    ],
    "sg:phone":"+1 303 934 3092",
    "sg:postcode":"80110",
    "sg:province":"CO",
    "sg:tags":[
        "machine",
        "shop",
        "jobbing",
        "repair"
    ],
    "wof:name":"Professional Fabricators Inc",
    "wof:placetype":"venue"
},
  "geometry": {"coordinates":[-105.011072,39.669212],"type":"Point"}
}