{
  "type": "Feature",
  "properties": {
    "addr:full":"31 Riverboat Dr New Castle CO 81647",
    "addr:housenumber":"31",
    "addr:postcode":"81647",
    "addr:street":"Riverboat Dr",
    "iso:country":"US",
    "sg:address":"31 Riverboat Dr",
    "sg:city":"New Castle",
    "sg:classifiers":[
        {
            "category":"Building & Trades",
            "subcategory":"Construction",
            "type":"Services"
        }
    ],
    "sg:phone":"+1 970 984 2300",
    "sg:postcode":"81647",
    "sg:province":"CO",
    "sg:tags":[
        "fire",
        "restoration",
        "damage"
    ],
    "wof:name":"Craig's Custom Carpet Cleaning",
    "wof:placetype":"venue"
},
  "geometry": {"coordinates":[-107.47855300000001,39.569598],"type":"Point"}
}