{
  "type": "Feature",
  "properties": {
    "iso:country":"US",
    "sg:address":"621 E Industrial Blvd",
    "sg:city":"Pueblo",
    "sg:classifiers":[
        {
            "category":"Building & Trades",
            "subcategory":"Plumbing",
            "type":"Services"
        }
    ],
    "sg:phone":"+1 719 547 2013",
    "sg:postcode":"81007",
    "sg:province":"CO",
    "sg:tags":[
        "sheet",
        "metal",
        "contractor"
    ],
    "wof:name":"Marcks Sheet Metal Inc Shop",
    "wof:placetype":"venue"
},
  "geometry": {"coordinates":[-104.704324,38.329867],"type":"Point"}
}