{
  "type": "Feature",
  "properties": {
    "iso:country":"US",
    "sg:address":"5290 Arapahoe Ave",
    "sg:city":"Boulder",
    "sg:classifiers":[
        {
            "category":"Personal",
            "subcategory":"Beauty Salon",
            "type":"Services"
        }
    ],
    "sg:phone":"+1 303 444 5652",
    "sg:postcode":"80303",
    "sg:province":"CO",
    "wof:name":"East Street Salon",
    "wof:placetype":"venue"
},
  "geometry": {"coordinates":[-105.228298,40.014535],"type":"Point"}
}