{
  "type": "Feature",
  "properties": {
    "iso:country":"US",
    "sg:address":"9201 Oberon Rd",
    "sg:city":"Arvada",
    "sg:classifiers":[
        {
            "category":"Real Estate",
            "subcategory":"Real Estate Operator",
            "type":"Services"
        }
    ],
    "sg:phone":"+1 303 425 1331",
    "sg:postcode":"80004",
    "sg:province":"CO",
    "sg:tags":[
        "apartment"
    ],
    "wof:name":"Prospect Pointe Apartment",
    "wof:placetype":"venue"
},
  "geometry": {"coordinates":[-105.103019,39.816596],"type":"Point"}
}