{
  "type": "Feature",
  "properties": {
    "iso:country":"US",
    "sg:address":"17011 E Lincoln Ave",
    "sg:city":"Parker",
    "sg:classifiers":[
        {
            "category":"Home & Garden",
            "subcategory":"Garden Supply",
            "type":"Retail Goods"
        }
    ],
    "sg:phone":"+1 303 791 6050",
    "sg:postcode":"80134",
    "sg:province":"CO",
    "sg:tags":[
        "sprinkler"
    ],
    "wof:name":"Berndt Sprinklers & Landscape",
    "wof:placetype":"venue"
},
  "geometry": {"coordinates":[-104.791454,39.534105],"type":"Point"}
}