{
  "type": "Feature",
  "properties": {
    "iso:country":"US",
    "sg:address":"6792 US Hwy 36",
    "sg:city":"Estes Park",
    "sg:classifiers":[
        {
            "category":"Building & Trades",
            "subcategory":"Construction",
            "type":"Services"
        }
    ],
    "sg:phone":"+1 970 577 0182",
    "sg:postcode":"80517",
    "sg:province":"CO",
    "sg:tags":[
        "house"
    ],
    "wof:name":"Weber Homes",
    "wof:placetype":"venue"
},
  "geometry": {"coordinates":[-105.420974,40.323826],"type":"Point"}
}