{
  "type": "Feature",
  "properties": {
    "iso:country":"US",
    "sg:address":"1275 Grant Street",
    "sg:city":"Denver",
    "sg:classifiers":[
        {
            "category":"Restaurant",
            "type":"Food & Drink"
        }
    ],
    "sg:phone":"+1 303 837 9096",
    "sg:postcode":"80203",
    "sg:province":"CO",
    "wof:name":"Quizno's",
    "wof:placetype":"venue"
},
  "geometry": {"coordinates":[-104.983744,39.736328],"type":"Point"}
}