{
  "type": "Feature",
  "properties": {
    "iso:country":"US",
    "sg:address":"455 S Grand Mesa Dr",
    "sg:city":"Cedaredge",
    "sg:classifiers":[
        {
            "category":"Professional",
            "subcategory":"Accounting & Tax Preparation",
            "type":"Services"
        }
    ],
    "sg:phone":"+1 970 856 7550",
    "sg:postcode":"81413",
    "sg:province":"CO",
    "wof:name":"Blair & Associates PC",
    "wof:placetype":"venue"
},
  "geometry": {"coordinates":[-107.925372,38.896716],"type":"Point"}
}