{
  "type": "Feature",
  "properties": {
    "iso:country":"US",
    "sg:address":"18115 Sunburst Dr",
    "sg:city":"Monument",
    "sg:classifiers":[
        {
            "category":"Manufacturing",
            "subcategory":"Tools & Machinery",
            "type":"Manufacturing & Wholesale Goods"
        }
    ],
    "sg:phone":"+1 719 481 2067",
    "sg:postcode":"80132",
    "sg:province":"CO",
    "sg:tags":[
        "measuring",
        "instrument",
        "electrical",
        "mfg"
    ],
    "wof:name":"Dynomotive",
    "wof:placetype":"venue"
},
  "geometry": {"coordinates":[-104.89392599999999,39.093569],"type":"Point"}
}