{
  "type": "Feature",
  "properties": {
    "addr:full":"4858 Eagle Blvd Longmont CO 80504",
    "addr:housenumber":"4858",
    "addr:postcode":"80504",
    "addr:street":"Eagle Blvd",
    "iso:country":"US",
    "sg:address":"4858 Eagle Blvd",
    "sg:city":"Longmont",
    "sg:classifiers":[
        {
            "category":"Wholesale",
            "subcategory":"Drugs",
            "type":"Manufacturing & Wholesale Goods"
        }
    ],
    "sg:phone":"+1 720 652 9000",
    "sg:postcode":"80504",
    "sg:province":"CO",
    "wof:name":"Kings Natural Inc",
    "wof:placetype":"venue"
},
  "geometry": {"coordinates":[-104.96519600000001,40.123045],"type":"Point"}
}