{
  "type": "Feature",
  "properties": {
    "iso:country":"US",
    "sg:address":"7141 S Elm Ct",
    "sg:city":"Centennial",
    "sg:classifiers":[
        {
            "category":"Professional",
            "subcategory":"Art Services",
            "type":"Services"
        }
    ],
    "sg:phone":"+1 720 488 4000",
    "sg:postcode":"80122",
    "sg:province":"CO",
    "sg:tags":[
        "graphic",
        "designer"
    ],
    "wof:name":"Existence Studios Inc",
    "wof:placetype":"venue"
},
  "geometry": {"coordinates":[-104.92931799999999,39.586473],"type":"Point"}
}