{
  "type": "Feature",
  "properties": {
    "addr:full":"799 S Cole Ct Lakewood CO 80228",
    "addr:housenumber":"799",
    "addr:postcode":"80228",
    "addr:street":"S Cole Ct",
    "iso:country":"US",
    "sg:address":"799 S Cole Ct",
    "sg:city":"Lakewood",
    "sg:classifiers":[
        {
            "category":"Health Services",
            "subcategory":"Doctor",
            "type":"Services"
        }
    ],
    "sg:phone":"+1 303 989 1685",
    "sg:postcode":"80228",
    "sg:province":"CO",
    "sg:tags":[
        "clinic"
    ],
    "wof:name":"Dialysis Management Inc",
    "wof:placetype":"venue"
},
  "geometry": {"coordinates":[-105.15254899999999,39.703427],"type":"Point"}
}