{
  "type": "Feature",
  "properties": {
    "iso:country":"US",
    "sg:address":"7170 Pecos St",
    "sg:city":"Denver",
    "sg:classifiers":[
        {
            "category":"Food & Beverages",
            "subcategory":"Groceries & Convenience Stores",
            "type":"Retail Goods"
        }
    ],
    "sg:phone":"+1 303 412 7606",
    "sg:postcode":"80221",
    "sg:province":"CO",
    "wof:name":"Pecos Sunmart Inc",
    "wof:placetype":"venue"
},
  "geometry": {"coordinates":[-105.00602600000001,39.826793],"type":"Point"}
}