{
  "type": "Feature",
  "properties": {
    "iso:country":"US",
    "sg:address":"6928 W Chatfield Pl",
    "sg:city":"Littleton",
    "sg:classifiers":[
        {
            "category":"Manufacturing",
            "subcategory":"Printing",
            "type":"Manufacturing & Wholesale Goods"
        }
    ],
    "sg:phone":"+1 303 588 2445",
    "sg:postcode":"80128",
    "sg:province":"CO",
    "sg:tags":[
        "publishing"
    ],
    "wof:name":"Gus Dex",
    "wof:placetype":"venue"
},
  "geometry": {"coordinates":[-105.075096,39.565061],"type":"Point"}
}