{
  "type": "Feature",
  "properties": {
    "addr:full":"603 Co Rd 503 Bayfield CO 81122",
    "addr:housenumber":"603",
    "addr:postcode":"81122",
    "addr:street":"Co Rd 503",
    "iso:country":"US",
    "sg:address":"603 Co Rd 503",
    "sg:city":"Bayfield",
    "sg:classifiers":[
        {
            "category":"Professional",
            "type":"Services"
        }
    ],
    "sg:phone":"+1 970 884 7375",
    "sg:postcode":"81122",
    "sg:province":"CO",
    "wof:name":"Terence R Jeffries",
    "wof:placetype":"venue"
},
  "geometry": {"coordinates":[-107.692446,37.281764],"type":"Point"}
}