{
  "type": "Feature",
  "properties": {
    "iso:country":"US",
    "sg:address":"14125 E Radcliff Cir",
    "sg:city":"Aurora",
    "sg:classifiers":[
        {
            "category":"Shopping",
            "subcategory":"Hobbies, Toys, & Games",
            "type":"Retail Goods"
        }
    ],
    "sg:phone":"+1 303 627 8202",
    "sg:postcode":"80015",
    "sg:province":"CO",
    "wof:name":"Jabco Inc",
    "wof:placetype":"venue"
},
  "geometry": {"coordinates":[-104.820497,39.635134],"type":"Point"}
}