{
  "type": "Feature",
  "properties": {
    "iso:country":"US",
    "sg:address":"160 Inverness Dr W",
    "sg:city":"Englewood",
    "sg:classifiers":[
        {
            "category":"Professional",
            "subcategory":"Accounting & Tax Preparation",
            "type":"Services"
        }
    ],
    "sg:phone":"+1 303 799 1016",
    "sg:postcode":"80112",
    "sg:province":"CO",
    "sg:tags":[
        "accountant"
    ],
    "wof:name":"Ernst & Young",
    "wof:placetype":"venue"
},
  "geometry": {"coordinates":[-104.870828,39.571808],"type":"Point"}
}