{
  "type": "Feature",
  "properties": {
    "iso:country":"US",
    "sg:address":"4500 E 60th Ave",
    "sg:city":"Commerce City",
    "sg:classifiers":[
        {
            "category":"Home & Garden",
            "subcategory":"Mobile Homes",
            "type":"Retail Goods"
        },
        {
            "category":"Retail",
            "subcategory":"Auto Rental",
            "type":"Services"
        }
    ],
    "sg:phone":"+1 303 853 4266",
    "sg:postcode":"80022",
    "sg:province":"CO",
    "sg:tags":[
        "commercial",
        "trailer",
        "unit",
        "utility"
    ],
    "sg:website":"www.willscot.com",
    "wof:name":"Williams Scotsman Inc",
    "wof:placetype":"venue"
},
  "geometry": {"coordinates":[-104.93345100000001,39.805512],"type":"Point"}
}