{
  "type": "Feature",
  "properties": {
    "iso:country":"US",
    "sg:address":"3430 S Jellison Ct",
    "sg:city":"Denver",
    "sg:classifiers":[
        {
            "category":"Building & Trades",
            "subcategory":"Construction",
            "type":"Services"
        }
    ],
    "sg:phone":"+1 303 986 4705",
    "sg:postcode":"80227",
    "sg:province":"CO",
    "sg:tags":[
        "residential"
    ],
    "wof:name":"Diversified Housing",
    "wof:placetype":"venue"
},
  "geometry": {"coordinates":[-105.105514,39.654406],"type":"Point"}
}