{
  "type": "Feature",
  "properties": {
    "iso:country":"US",
    "sg:address":"3800 Weicker Dr",
    "sg:city":"Fort Collins",
    "sg:classifiers":[
        {
            "category":"Airline",
            "type":"Transportation"
        }
    ],
    "sg:phone":"+1 800 852 5957",
    "sg:postcode":"80524",
    "sg:province":"CO",
    "sg:tags":[
        "courier",
        "air"
    ],
    "wof:name":"Fedex",
    "wof:placetype":"venue"
},
  "geometry": {"coordinates":[-105.004891,40.583498],"type":"Point"}
}