{
  "type": "Feature",
  "properties": {
    "iso:country":"US",
    "sg:address":"7808 Cherry Creek South Dr",
    "sg:city":"Denver",
    "sg:classifiers":[
        {
            "category":"Retail",
            "subcategory":"Repair Shop",
            "type":"Services"
        }
    ],
    "sg:phone":"+1 720 213 0123",
    "sg:postcode":"80246",
    "sg:province":"CO",
    "sg:tags":[
        "related"
    ],
    "wof:name":"Comeg USA",
    "wof:placetype":"venue"
},
  "geometry": {"coordinates":[-104.901808,39.684126],"type":"Point"}
}