{
  "type": "Feature",
  "properties": {
    "addr:full":"609 Clinton St Ridgway CO 81432",
    "addr:housenumber":"609",
    "addr:postcode":"81432",
    "addr:street":"Clinton St",
    "iso:country":"US",
    "sg:address":"609 Clinton St",
    "sg:city":"Ridgway",
    "sg:classifiers":[
        {
            "category":"Organizations",
            "subcategory":"Community Association",
            "type":"Services"
        }
    ],
    "sg:phone":"+1 970 626 3820",
    "sg:postcode":"81432",
    "sg:province":"CO",
    "sg:tags":[
        "environmental",
        "org"
    ],
    "wof:name":"Institute Of Ecolonomics",
    "wof:placetype":"venue"
},
  "geometry": {"coordinates":[-107.758166,38.152515],"type":"Point"}
}