{
  "type": "Feature",
  "properties": {
    "iso:country":"US",
    "sg:address":"6554 S Piney Creek Cir",
    "sg:city":"Centennial",
    "sg:classifiers":[
        {
            "category":"Building & Trades",
            "subcategory":"Cleaning & Sanitation",
            "type":"Services"
        }
    ],
    "sg:phone":"+1 303 400 5231",
    "sg:postcode":"80016",
    "sg:province":"CO",
    "sg:tags":[
        "window"
    ],
    "wof:name":"Jack's Window Cleaning",
    "wof:placetype":"venue"
},
  "geometry": {"coordinates":[-104.770855,39.596889],"type":"Point"}
}