{
  "type": "Feature",
  "properties": {
    "addr:full":"504 2nd St Castle Rock CO 80104",
    "addr:housenumber":"504",
    "addr:postcode":"80104",
    "addr:street":"2Nd St",
    "iso:country":"US",
    "sg:address":"504 2nd St",
    "sg:city":"Castle Rock",
    "sg:classifiers":[
        {
            "category":"Personal",
            "subcategory":"Beauty Salon",
            "type":"Services"
        }
    ],
    "sg:phone":"+1 303 688 0204",
    "sg:postcode":"80104",
    "sg:province":"CO",
    "wof:name":"Wild Hair Co",
    "wof:placetype":"venue"
},
  "geometry": {"coordinates":[-104.856593,39.371298],"type":"Point"}
}