{
  "type": "Feature",
  "properties": {
    "iso:country":"US",
    "sg:address":"8340 S Sangre de Cristo Rd",
    "sg:city":"Littleton",
    "sg:classifiers":[
        {
            "category":"Health Services",
            "subcategory":"Doctor",
            "type":"Services"
        }
    ],
    "sg:phone":"+1 303 979 1234",
    "sg:postcode":"80127",
    "sg:province":"CO",
    "sg:tags":[
        "physician",
        "surgeon"
    ],
    "wof:name":"Littleton Pediatric Med Ctr",
    "wof:placetype":"venue"
},
  "geometry": {"coordinates":[-105.113473,39.568951],"type":"Point"}
}