{
  "type": "Feature",
  "properties": {
    "addr:full":"1485 S Lipan St Denver CO 80223",
    "addr:housenumber":"1485",
    "addr:postcode":"80223",
    "addr:street":"S Lipan St",
    "iso:country":"US",
    "sg:address":"1485 S Lipan St",
    "sg:city":"Denver",
    "sg:classifiers":[
        {
            "category":"Wholesale",
            "subcategory":"Construction Materials",
            "type":"Manufacturing & Wholesale Goods"
        },
        {
            "category":"Building & Trades",
            "subcategory":"Construction",
            "type":"Services"
        }
    ],
    "sg:phone":"+1 303 777 3091",
    "sg:postcode":"80223",
    "sg:province":"CO",
    "sg:tags":[
        "terrazzo",
        "slate",
        "tile",
        "granite",
        "brick",
        "marble"
    ],
    "wof:name":"Ace Tile & Terrazzo Inc",
    "wof:placetype":"venue"
},
  "geometry": {"coordinates":[-105.001648,39.691075],"type":"Point"}
}