{
  "type": "Feature",
  "properties": {
    "addr:full":"2984 Birch St Denver CO 80207",
    "addr:housenumber":"2984",
    "addr:postcode":"80207",
    "addr:street":"Birch St",
    "iso:country":"US",
    "sg:address":"2984 Birch St",
    "sg:city":"Denver",
    "sg:classifiers":[
        {
            "category":"Shopping",
            "subcategory":"Clothing, Apparel, & Fashions",
            "type":"Retail Goods"
        }
    ],
    "sg:phone":"+1 720 407 0462",
    "sg:postcode":"80207",
    "sg:province":"CO",
    "wof:name":"Truth In Clothing Inc",
    "wof:placetype":"venue"
},
  "geometry": {"coordinates":[-104.936049,39.758568],"type":"Point"}
}