{
  "type": "Feature",
  "properties": {
    "iso:country":"US",
    "sg:address":"2350 N Powers Blvd",
    "sg:city":"Colorado Springs",
    "sg:classifiers":[
        {
            "category":"Building & Trades",
            "subcategory":"Construction",
            "type":"Services"
        }
    ],
    "sg:phone":"+1 719 596 9390",
    "sg:postcode":"80915",
    "sg:province":"CO",
    "sg:tags":[
        "masonry",
        "contractor"
    ],
    "wof:name":"Tri Star Masonry Inc",
    "wof:placetype":"venue"
},
  "geometry": {"coordinates":[-104.720063,38.864568],"type":"Point"}
}