{
  "type": "Feature",
  "properties": {
    "addr:full":"360 Main St Delta CO 81416",
    "addr:housenumber":"360",
    "addr:postcode":"81416",
    "addr:street":"Main St",
    "iso:country":"US",
    "sg:address":"360 Main St",
    "sg:city":"Delta",
    "sg:classifiers":[
        {
            "category":"Sports & Exercise",
            "subcategory":"Golf",
            "type":"Entertainment"
        }
    ],
    "sg:phone":"+1 970 874 6262",
    "sg:postcode":"81416",
    "sg:province":"CO",
    "sg:tags":[
        "course",
        "public"
    ],
    "wof:name":"Devils Thumb Golf Club",
    "wof:placetype":"venue"
},
  "geometry": {"coordinates":[-108.07068700000001,38.742179],"type":"Point"}
}