{
  "type": "Feature",
  "properties": {
    "addr:full":"304 W 3rd St Wray CO 80758",
    "addr:housenumber":"304",
    "addr:postcode":"80758",
    "addr:street":"W 3Rd St",
    "iso:country":"US",
    "sg:address":"304 W 3rd St",
    "sg:city":"Wray",
    "sg:classifiers":[
        {
            "category":"Government",
            "subcategory":"Fire Station",
            "type":"Public Place"
        }
    ],
    "sg:phone":"+1 970 332 4086",
    "sg:postcode":"80758",
    "sg:province":"CO",
    "sg:tags":[
        "department"
    ],
    "wof:name":"WRAY Ambulance Svc",
    "wof:placetype":"venue"
},
  "geometry": {"coordinates":[-102.225415,40.078852],"type":"Point"}
}