{
  "type": "Feature",
  "properties": {
    "iso:country":"US",
    "sg:address":"2755 S Locust St",
    "sg:city":"Denver",
    "sg:classifiers":[
        {
            "category":"Government",
            "subcategory":"Office",
            "type":"Public Place"
        }
    ],
    "sg:phone":"+1 303 759 8840",
    "sg:postcode":"80222",
    "sg:province":"CO",
    "sg:tags":[
        "policy"
    ],
    "wof:name":"C PEC",
    "wof:placetype":"venue"
},
  "geometry": {"coordinates":[-104.915482,39.66527],"type":"Point"}
}