{
  "type": "Feature",
  "properties": {
    "iso:country":"US",
    "sg:address":"25667 Co Rd Ee",
    "sg:city":"Kit Carson",
    "sg:classifiers":[
        {
            "category":"Farming",
            "subcategory":"Livestock Farm",
            "type":"Manufacturing & Wholesale Goods"
        }
    ],
    "sg:phone":"+1 719 962 3423",
    "sg:postcode":"80825",
    "sg:province":"CO",
    "sg:tags":[
        "beef",
        "feedlot",
        "cattle"
    ],
    "wof:name":"Ka Koch and Company",
    "wof:placetype":"venue"
},
  "geometry": {"coordinates":[-102.693939,39.010438],"type":"Point"}
}