{
  "type": "Feature",
  "properties": {
    "iso:country":"US",
    "sg:address":"2909 43rd Ave",
    "sg:city":"Greeley",
    "sg:classifiers":[
        {
            "category":"Shopping",
            "subcategory":"Clothing, Apparel, & Fashions",
            "type":"Retail Goods"
        }
    ],
    "sg:phone":"+1 970 330 0177",
    "sg:postcode":"80634",
    "sg:province":"CO",
    "wof:name":"Rags To Riches",
    "wof:placetype":"venue"
},
  "geometry": {"coordinates":[-104.750337,40.390161],"type":"Point"}
}