{
  "type": "Feature",
  "properties": {
    "iso:country":"US",
    "sg:address":"2308 Willow Creek Dr",
    "sg:city":"Golden",
    "sg:classifiers":[
        {
            "category":"Home & Garden",
            "subcategory":"Building Materials",
            "type":"Retail Goods"
        }
    ],
    "sg:phone":"+1 303 271 1173",
    "sg:postcode":"80401",
    "sg:province":"CO",
    "sg:tags":[
        "windows",
        "siding",
        "construction"
    ],
    "wof:name":"Lt Pelt Consultants Corp",
    "wof:placetype":"venue"
},
  "geometry": {"coordinates":[-105.212126,39.746426],"type":"Point"}
}