{
  "type": "Feature",
  "properties": {
    "iso:country":"US",
    "sg:address":"7180 N Academy Blvd",
    "sg:city":"Colorado Springs",
    "sg:classifiers":[
        {
            "category":"Professional",
            "subcategory":"Computer Services",
            "type":"Services"
        }
    ],
    "sg:phone":"+1 719 532 9888",
    "sg:postcode":"80920",
    "sg:province":"CO",
    "sg:tags":[
        "repair"
    ],
    "wof:name":"P C Club Colorado",
    "wof:placetype":"venue"
},
  "geometry": {"coordinates":[-104.79736,38.934694],"type":"Point"}
}