{
  "type": "Feature",
  "properties": {
    "iso:country":"US",
    "sg:address":"1130 Alpine Dr",
    "sg:city":"Boulder",
    "sg:classifiers":[
        {
            "category":"Health Services",
            "subcategory":"Doctor",
            "type":"Services"
        }
    ],
    "sg:phone":"+1 303 447 1361",
    "sg:postcode":"80304",
    "sg:province":"CO",
    "sg:tags":[
        "clinic",
        "medical",
        "specialty",
        "outpatient"
    ],
    "sg:website":"www.drhern.com",
    "wof:name":"Boulder Abortion Clinic PC",
    "wof:placetype":"venue"
},
  "geometry": {"coordinates":[-105.282538,40.025441],"type":"Point"}
}