{
  "type": "Feature",
  "properties": {
    "iso:country":"US",
    "sg:address":"105 Polo Rd",
    "sg:city":"Glenwood Springs",
    "sg:classifiers":[
        {
            "category":"Professional",
            "type":"Services"
        }
    ],
    "sg:phone":"+1 970 945 0647",
    "sg:postcode":"81601",
    "sg:province":"CO",
    "wof:name":"Ardueser Family LLC",
    "wof:placetype":"venue"
},
  "geometry": {"coordinates":[-107.326257,39.534731],"type":"Point"}
}