{
  "type": "Feature",
  "properties": {
    "iso:country":"US",
    "sg:address":"42 Ash Ave",
    "sg:city":"Eaton",
    "sg:classifiers":[
        {
            "category":"Building & Trades",
            "subcategory":"Construction",
            "type":"Services"
        }
    ],
    "sg:phone":"+1 970 454 3533",
    "sg:postcode":"80615",
    "sg:province":"CO",
    "sg:tags":[
        "resurfacing",
        "laying",
        "refinishing",
        "floor"
    ],
    "wof:name":"Flynn Flooring",
    "wof:placetype":"venue"
},
  "geometry": {"coordinates":[-104.721047,40.525843],"type":"Point"}
}