{
  "type": "Feature",
  "properties": {
    "iso:country":"US",
    "sg:address":"1701 Bellaire St",
    "sg:city":"Denver",
    "sg:classifiers":[
        {
            "category":"Building & Trades",
            "subcategory":"Locksmith",
            "type":"Services"
        }
    ],
    "sg:phone":"+1 303 357 0228",
    "sg:postcode":"80220",
    "sg:province":"CO",
    "sg:tags":[
        "key"
    ],
    "wof:name":"0 0 24 7 Locksmith",
    "wof:placetype":"venue"
},
  "geometry": {"coordinates":[-104.937398,39.743692],"type":"Point"}
}