{
  "type": "Feature",
  "properties": {
    "iso:country":"US",
    "sg:address":"3801 Brighton Blvd",
    "sg:city":"Denver",
    "sg:classifiers":[
        {
            "category":"Wholesale",
            "subcategory":"Chemicals & Plastics",
            "type":"Manufacturing & Wholesale Goods"
        }
    ],
    "sg:phone":"+1 303 299 4330",
    "sg:postcode":"80216",
    "sg:province":"CO",
    "wof:name":"Pbg",
    "wof:placetype":"venue"
},
  "geometry": {"coordinates":[-104.97444299999999,39.773735],"type":"Point"}
}