{
  "type": "Feature",
  "properties": {
    "iso:country":"US",
    "sg:address":"7200 E Dry Creek Rd",
    "sg:city":"Centennial",
    "sg:classifiers":[
        {
            "category":"Wholesale",
            "subcategory":"Durable Goods & Equipment",
            "type":"Manufacturing & Wholesale Goods"
        }
    ],
    "sg:phone":"+1 303 741 5515",
    "sg:postcode":"80112",
    "sg:province":"CO",
    "sg:tags":[
        "representative",
        "manufacturer"
    ],
    "wof:name":"Pinnacle Sales Assoc",
    "wof:placetype":"venue"
},
  "geometry": {"coordinates":[-104.904267,39.580525],"type":"Point"}
}