{
  "type": "Feature",
  "properties": {
    "iso:country":"US",
    "sg:address":"38 S Selig Ave",
    "sg:city":"Montrose",
    "sg:classifiers":[
        {
            "category":"Personal",
            "subcategory":"Beauty Salon",
            "type":"Services"
        }
    ],
    "sg:phone":"+1 970 249 1975",
    "sg:postcode":"81401",
    "sg:province":"CO",
    "sg:tags":[
        "shop"
    ],
    "sg:website":"www.sindyssalonandspa.com",
    "wof:name":"Sindy's Salon & Spa",
    "wof:placetype":"venue"
},
  "geometry": {"coordinates":[-107.878528,38.477684],"type":"Point"}
}