{
  "type": "Feature",
  "properties": {
    "iso:country":"US",
    "sg:address":"1927 Panorama Dr",
    "sg:city":"Carbondale",
    "sg:classifiers":[
        {
            "category":"Building & Trades",
            "subcategory":"Construction",
            "type":"Services"
        }
    ],
    "sg:phone":"+1 970 704 0130",
    "sg:postcode":"81623",
    "sg:province":"CO",
    "sg:tags":[
        "house"
    ],
    "wof:name":"Ser Builders Inc",
    "wof:placetype":"venue"
},
  "geometry": {"coordinates":[-107.12793499999999,39.449935],"type":"Point"}
}