{
  "type": "Feature",
  "properties": {
    "iso:country":"US",
    "sg:address":"3045 Osceola St",
    "sg:city":"Denver",
    "sg:classifiers":[
        {
            "category":"Professional",
            "type":"Services"
        }
    ],
    "sg:phone":"+1 303 477 6032",
    "sg:postcode":"80212",
    "sg:province":"CO",
    "sg:tags":[
        "writer"
    ],
    "wof:name":"Wordsworth",
    "wof:placetype":"venue"
},
  "geometry": {"coordinates":[-105.03822599999999,39.761723],"type":"Point"}
}