{
  "type": "Feature",
  "properties": {
    "addr:full":"1201 Cumberland St Colorado Springs CO 80907",
    "addr:housenumber":"1201",
    "addr:postcode":"80907",
    "addr:street":"Cumberland St",
    "iso:country":"US",
    "sg:address":"1201 Cumberland St",
    "sg:city":"Colorado Springs",
    "sg:classifiers":[
        {
            "category":"Building & Trades",
            "subcategory":"Plumbing",
            "type":"Services"
        }
    ],
    "sg:phone":"+1 719 351 9977",
    "sg:postcode":"80907",
    "sg:province":"CO",
    "sg:tags":[
        "plumbing",
        "contractor"
    ],
    "wof:name":"Whitney Sewer & Drain Cleaning",
    "wof:placetype":"venue"
},
  "geometry": {"coordinates":[-104.800528,38.885881],"type":"Point"}
}