{
  "type": "Feature",
  "properties": {
    "iso:country":"US",
    "sg:address":"6976 Dudley Dr",
    "sg:city":"Arvada",
    "sg:classifiers":[
        {
            "category":"Building & Trades",
            "subcategory":"Cleaning & Sanitation",
            "type":"Services"
        }
    ],
    "sg:phone":"+1 303 431 9808",
    "sg:postcode":"80004",
    "sg:province":"CO",
    "sg:tags":[
        "maintenance"
    ],
    "wof:name":"Always Clean LLC",
    "wof:placetype":"venue"
},
  "geometry": {"coordinates":[-105.094925,39.823624],"type":"Point"}
}