{
  "type": "Feature",
  "properties": {
    "addr:full":"2892 Co Rd M Kirk CO 80824",
    "addr:housenumber":"2892",
    "addr:postcode":"80824",
    "addr:street":"Co Rd M Kirk",
    "iso:country":"US",
    "sg:address":"2892 Co Rd M",
    "sg:city":"Kirk",
    "sg:classifiers":[
        {
            "category":"Professional",
            "subcategory":"Business Services",
            "type":"Services"
        }
    ],
    "sg:phone":"+1 970 362 4393",
    "sg:postcode":"80824",
    "sg:province":"CO",
    "sg:tags":[
        "interior",
        "consultant",
        "design",
        "decorator"
    ],
    "wof:name":"Home Interiors & Gifts",
    "wof:placetype":"venue"
},
  "geometry": {"coordinates":[-102.591919,39.6113],"type":"Point"}
}