{
  "type": "Feature",
  "properties": {
    "iso:country":"US",
    "sg:address":"117 Meeker St",
    "sg:city":"Delta",
    "sg:classifiers":[
        {
            "category":"Banks & Credit Unions",
            "subcategory":"Investment Brokerage",
            "type":"Services"
        }
    ],
    "sg:phone":"+1 970 874 6352",
    "sg:postcode":"81416",
    "sg:province":"CO",
    "sg:tags":[
        "advisory",
        "financial"
    ],
    "wof:name":"Edwards Financial Svc",
    "wof:placetype":"venue"
},
  "geometry": {"coordinates":[-108.069597,38.745448],"type":"Point"}
}