{
  "type": "Feature",
  "properties": {
    "addr:full":"1420 Detroit St Denver CO 80206",
    "addr:housenumber":"1420",
    "addr:postcode":"80206",
    "addr:street":"Detroit St",
    "iso:country":"US",
    "sg:address":"1420 Detroit St",
    "sg:city":"Denver",
    "sg:classifiers":[
        {
            "category":"Wholesale",
            "subcategory":"Durable Goods & Equipment",
            "type":"Manufacturing & Wholesale Goods"
        }
    ],
    "sg:phone":"+1 303 321 6364",
    "sg:postcode":"80206",
    "sg:province":"CO",
    "sg:tags":[
        "representative",
        "manufacturer"
    ],
    "wof:name":"Colorado Lighting Svc",
    "wof:placetype":"venue"
},
  "geometry": {"coordinates":[-104.954087,39.739814],"type":"Point"}
}