{
  "type": "Feature",
  "properties": {
    "iso:country":"US",
    "sg:address":"3340 W Woodmen Rd",
    "sg:city":"Colorado Springs",
    "sg:classifiers":[
        {
            "category":"Professional",
            "subcategory":"Business Services",
            "type":"Services"
        },
        {
            "category":"Professional",
            "subcategory":"Management & Consulting",
            "type":"Services"
        }
    ],
    "sg:phone":"+1 719 532 0780",
    "sg:postcode":"80919",
    "sg:province":"CO",
    "wof:name":"Harvest Time",
    "wof:placetype":"venue"
},
  "geometry": {"coordinates":[-104.87559400000001,38.953417],"type":"Point"}
}