{
  "type": "Feature",
  "properties": {
    "addr:full":"107 Sioux Dr Berthoud CO 80513",
    "addr:housenumber":"107",
    "addr:postcode":"80513",
    "addr:street":"Sioux Dr",
    "iso:country":"US",
    "sg:address":"107 Sioux Dr",
    "sg:city":"Berthoud",
    "sg:classifiers":[
        {
            "category":"Professional",
            "type":"Services"
        }
    ],
    "sg:phone":"+1 970 532 1242",
    "sg:postcode":"80513",
    "sg:province":"CO",
    "wof:name":"Applied Innovative",
    "wof:placetype":"venue"
},
  "geometry": {"coordinates":[-105.092657,40.303842],"type":"Point"}
}