{
  "type": "Feature",
  "properties": {
    "iso:country":"US",
    "sg:address":"320 Cam del Rio",
    "sg:city":"Gunnison",
    "sg:classifiers":[
        {
            "category":"Professional",
            "type":"Services"
        }
    ],
    "sg:phone":"+1 970 641 3505",
    "sg:postcode":"81230",
    "sg:province":"CO",
    "wof:name":"Craig McBreen",
    "wof:placetype":"venue"
},
  "geometry": {"coordinates":[-106.959214,38.525955],"type":"Point"}
}