{
  "type": "Feature",
  "properties": {
    "addr:full":"213 W 3rd St La Junta CO 81050",
    "addr:housenumber":"213",
    "addr:postcode":"81050",
    "addr:street":"W 3Rd St",
    "iso:country":"US",
    "sg:address":"213 W 3rd St",
    "sg:city":"La Junta",
    "sg:classifiers":[
        {
            "category":"Retail",
            "subcategory":"Auto Repair",
            "type":"Services"
        }
    ],
    "sg:phone":"+1 719 384 7562",
    "sg:postcode":"81050",
    "sg:province":"CO",
    "sg:tags":[
        "body"
    ],
    "wof:name":"Rubys Auto Body Inc",
    "wof:placetype":"venue"
},
  "geometry": {"coordinates":[-103.546317,37.986007],"type":"Point"}
}