{
  "type": "Feature",
  "properties": {
    "iso:country":"US",
    "sg:address":"14913 Hwy 82",
    "sg:city":"Carbondale",
    "sg:classifiers":[
        {
            "category":"Sports & Exercise",
            "subcategory":"Golf",
            "type":"Entertainment"
        }
    ],
    "sg:phone":"+1 970 963 4410",
    "sg:postcode":"81623",
    "sg:province":"CO",
    "sg:tags":[
        "course"
    ],
    "wof:name":"Ranch At Roaring Fork Golf",
    "wof:placetype":"venue"
},
  "geometry": {"coordinates":[-107.15504900000001,39.407881],"type":"Point"}
}