{
  "type": "Feature",
  "properties": {
    "iso:country":"US",
    "sg:address":"150 St. Paul St",
    "sg:city":"Denver",
    "sg:classifiers":[
        {
            "category":"Fast Food",
            "type":"Food & Drink"
        }
    ],
    "sg:phone":"+1 303 333 8016",
    "sg:postcode":"80206",
    "sg:province":"CO",
    "sg:website":"www.bk.com",
    "wof:name":"Burger King",
    "wof:placetype":"venue"
},
  "geometry": {"coordinates":[-104.95066,39.718691],"type":"Point"}
}