{
  "type": "Feature",
  "properties": {
    "addr:full":"268 S Santa Fe Drive Denver CO 80223",
    "addr:housenumber":"268",
    "addr:postcode":"80223",
    "addr:street":"S Santa Fe Drive",
    "iso:country":"US",
    "sg:address":"268 S Santa Fe Drive",
    "sg:city":"Denver",
    "sg:classifiers":[
        {
            "category":"Retail",
            "subcategory":"Auto Repair",
            "type":"Services"
        }
    ],
    "sg:phone":"+1 303 722 5770",
    "sg:postcode":"80223",
    "sg:province":"CO",
    "wof:name":"Caraveo Body Shop",
    "wof:placetype":"venue"
},
  "geometry": {"coordinates":[-104.99735099999999,39.711813],"type":"Point"}
}