{
  "type": "Feature",
  "properties": {
    "addr:full":"85 Wheatridge Dr Pueblo CO 81005",
    "addr:housenumber":"85",
    "addr:postcode":"81005",
    "addr:street":"Wheatridge Dr",
    "iso:country":"US",
    "sg:address":"85 Wheatridge Dr",
    "sg:city":"Pueblo",
    "sg:classifiers":[
        {
            "category":"Shopping",
            "subcategory":"Computers & Home Electronics",
            "type":"Retail Goods"
        }
    ],
    "sg:phone":"+1 719 544 5646",
    "sg:postcode":"81005",
    "sg:province":"CO",
    "sg:tags":[
        "equipment",
        "dealer"
    ],
    "wof:name":"Matazak Computers Plus",
    "wof:placetype":"venue"
},
  "geometry": {"coordinates":[-104.644565,38.228525],"type":"Point"}
}