{
  "type": "Feature",
  "properties": {
    "iso:country":"US",
    "sg:address":"1121 Albion St Apt 210",
    "sg:city":"Denver",
    "sg:classifiers":[
        {
            "category":"Social Services",
            "subcategory":"Child Care",
            "type":"Services"
        }
    ],
    "sg:phone":"+1 720 214 0696",
    "sg:postcode":"80220",
    "sg:province":"CO",
    "sg:tags":[
        "nursery",
        "day"
    ],
    "wof:name":"Tiny Touch",
    "wof:placetype":"venue"
},
  "geometry": {"coordinates":[-104.939497,39.73319],"type":"Point"}
}