{
  "type": "Feature",
  "properties": {
    "iso:country":"US",
    "sg:address":"1601 Main St",
    "sg:city":"Alamosa",
    "sg:classifiers":[
        {
            "category":"Food & Beverages",
            "subcategory":"Groceries & Convenience Stores",
            "type":"Retail Goods"
        }
    ],
    "sg:phone":"+1 719 589 9434",
    "sg:postcode":"81101",
    "sg:province":"CO",
    "wof:name":"Pester Marketing Co",
    "wof:placetype":"venue"
},
  "geometry": {"coordinates":[-105.881849,37.46972],"type":"Point"}
}