{
  "type": "Feature",
  "properties": {
    "iso:country":"US",
    "sg:address":"2950 Jasmine St",
    "sg:city":"Denver",
    "sg:classifiers":[
        {
            "category":"Education",
            "subcategory":"School",
            "type":"Public Place"
        }
    ],
    "sg:phone":"+1 303 355 7359",
    "sg:postcode":"80207",
    "sg:province":"CO",
    "wof:name":"Hallett Elementary School",
    "wof:placetype":"venue"
},
  "geometry": {"coordinates":[-104.918685,39.759255],"type":"Point"}
}