{
  "type": "Feature",
  "properties": {
    "iso:country":"US",
    "sg:address":"1405 S 8th Ave",
    "sg:city":"Sterling",
    "sg:classifiers":[
        {
            "category":"Health Services",
            "subcategory":"Doctor",
            "type":"Services"
        }
    ],
    "sg:phone":"+1 970 522 3304",
    "sg:postcode":"80751",
    "sg:province":"CO",
    "sg:tags":[
        "physician",
        "medical",
        "surgeon"
    ],
    "wof:name":"Northeast Colorado Family Med",
    "wof:placetype":"venue"
},
  "geometry": {"coordinates":[-103.222295,40.61265],"type":"Point"}
}