{
  "type": "Feature",
  "properties": {
    "addr:full":"524 S Cascade Ave Colorado Springs CO 80903",
    "addr:housenumber":"524",
    "addr:postcode":"80903",
    "addr:street":"S Cascade Ave",
    "iso:country":"US",
    "sg:address":"524 S Cascade Ave",
    "sg:city":"Colorado Springs",
    "sg:classifiers":[
        {
            "category":"Real Estate",
            "subcategory":"Real Estate Operator",
            "type":"Services"
        }
    ],
    "sg:phone":"+1 719 520 1176",
    "sg:postcode":"80903",
    "sg:province":"CO",
    "sg:tags":[
        "building",
        "nonresidential"
    ],
    "wof:name":"Wolf Business Park LLC",
    "wof:placetype":"venue"
},
  "geometry": {"coordinates":[-104.825761,38.825721],"type":"Point"}
}