{
  "type": "Feature",
  "properties": {
    "addr:full":"236 Walnut St Fort Collins CO 80524",
    "addr:housenumber":"236",
    "addr:postcode":"80524",
    "addr:street":"Walnut St",
    "iso:country":"US",
    "sg:address":"236 Walnut St",
    "sg:city":"Fort Collins",
    "sg:classifiers":[
        {
            "category":"Shopping",
            "subcategory":"Jewelry",
            "type":"Retail Goods"
        }
    ],
    "sg:phone":"+1 970 407 1865",
    "sg:postcode":"80524",
    "sg:province":"CO",
    "sg:tags":[
        "jeweler"
    ],
    "wof:name":"Aurifex Fine Jewelers",
    "wof:placetype":"venue"
},
  "geometry": {"coordinates":[-105.07538,40.588151],"type":"Point"}
}