{
  "type": "Feature",
  "properties": {
    "iso:country":"US",
    "sg:address":"4921 Winewood Village Dr",
    "sg:city":"Colorado Springs",
    "sg:classifiers":[
        {
            "category":"Building & Trades",
            "subcategory":"Plumbing",
            "type":"Services"
        }
    ],
    "sg:phone":"+1 719 380 1600",
    "sg:postcode":"80917",
    "sg:province":"CO",
    "sg:tags":[
        "conditioning",
        "air",
        "system",
        "contractor"
    ],
    "wof:name":"Affordable Air Care Heating",
    "wof:placetype":"venue"
},
  "geometry": {"coordinates":[-104.741412,38.900901],"type":"Point"}
}