{
  "type": "Feature",
  "properties": {
    "iso:country":"US",
    "sg:address":"1274 Silver Tip Ln",
    "sg:city":"Evergreen",
    "sg:classifiers":[
        {
            "category":"Real Estate",
            "subcategory":"Developer",
            "type":"Services"
        }
    ],
    "sg:phone":"+1 303 674 7917",
    "sg:postcode":"80439",
    "sg:province":"CO",
    "wof:name":"Energy Projects Development LL",
    "wof:placetype":"venue"
},
  "geometry": {"coordinates":[-105.381438,39.68974],"type":"Point"}
}