{
  "type": "Feature",
  "properties": {
    "addr:full":"7070 W 117th Ave Broomfield CO 80020",
    "addr:housenumber":"7070",
    "addr:postcode":"80020",
    "addr:street":"W 117Th Ave",
    "iso:country":"US",
    "sg:address":"7070 W 117th Ave",
    "sg:city":"Broomfield",
    "sg:classifiers":[
        {
            "category":"Social Services",
            "type":"Services"
        }
    ],
    "sg:phone":"+1 303 410 0901",
    "sg:postcode":"80020",
    "sg:province":"CO",
    "sg:tags":[
        "organization",
        "welfare"
    ],
    "wof:name":"N Ice",
    "wof:placetype":"venue"
},
  "geometry": {"coordinates":[-105.074817,39.909804],"type":"Point"}
}