{
  "type": "Feature",
  "properties": {
    "iso:country":"US",
    "sg:address":"2210 36th St",
    "sg:city":"Evans",
    "sg:classifiers":[
        {
            "category":"Building & Trades",
            "subcategory":"Construction",
            "type":"Services"
        }
    ],
    "sg:phone":"+1 970 330 0547",
    "sg:postcode":"80620",
    "sg:province":"CO",
    "sg:tags":[
        "floor",
        "laying",
        "contractor"
    ],
    "wof:name":"Wbci Inc",
    "wof:placetype":"venue"
},
  "geometry": {"coordinates":[-104.715689,40.379448],"type":"Point"}
}