{
  "type": "Feature",
  "properties": {
    "iso:country":"US",
    "sg:address":"3730 Wheeling St",
    "sg:city":"Denver",
    "sg:classifiers":[
        {
            "category":"Autos & Motor Vehicles",
            "subcategory":"Automobile Sales",
            "type":"Retail Goods"
        }
    ],
    "sg:phone":"+1 720 374 2384",
    "sg:postcode":"80239",
    "sg:province":"CO",
    "wof:name":"Exstream Cars",
    "wof:placetype":"venue"
},
  "geometry": {"coordinates":[-104.83307600000001,39.767762],"type":"Point"}
}