{
  "type": "Feature",
  "properties": {
    "addr:full":"110 S Wilcox St Castle Rock CO 80104",
    "addr:housenumber":"110",
    "addr:postcode":"80104",
    "addr:street":"S Wilcox St",
    "iso:country":"US",
    "sg:address":"110 S Wilcox St",
    "sg:city":"Castle Rock",
    "sg:classifiers":[
        {
            "category":"Restaurant",
            "type":"Food & Drink"
        }
    ],
    "sg:menulink":"http://www.allmenus.com/co/castle-rock/128411-subway/menu/",
    "sg:phone":"+1 303 660 8124",
    "sg:postcode":"80104",
    "sg:province":"CO",
    "sg:tags":[
        "american",
        "sandwich"
    ],
    "wof:name":"Subway",
    "wof:placetype":"venue"
},
  "geometry": {"coordinates":[-104.860595,39.368182],"type":"Point"}
}