{
  "type": "Feature",
  "properties": {
    "iso:country":"US",
    "sg:address":"2062 S Monaco Parkway",
    "sg:city":"Denver",
    "sg:classifiers":[
        {
            "category":"Real Estate",
            "subcategory":"Real Estate Operator",
            "type":"Services"
        }
    ],
    "sg:phone":"+1 303 758 0285",
    "sg:postcode":"80224",
    "sg:province":"CO",
    "sg:tags":[
        "apartment"
    ],
    "sg:website":"www.skylineadvantage.com",
    "wof:name":"Monaco Parkway Apts",
    "wof:placetype":"venue"
},
  "geometry": {"coordinates":[-104.912725,39.679185],"type":"Point"}
}