{
  "type": "Feature",
  "properties": {
    "addr:full":"1023 Main Ave Flagler CO 80815",
    "addr:housenumber":"1023",
    "addr:postcode":"80815",
    "addr:street":"Main Ave",
    "iso:country":"US",
    "sg:address":"1023 Main Ave",
    "sg:city":"Flagler",
    "sg:classifiers":[
        {
            "category":"Wholesale",
            "subcategory":"Non-durable Goods",
            "type":"Manufacturing & Wholesale Goods"
        }
    ],
    "sg:phone":"+1 719 765 4304",
    "sg:postcode":"80815",
    "sg:province":"CO",
    "sg:tags":[
        "advertising"
    ],
    "wof:name":"Tumbleweed Advertising Spec",
    "wof:placetype":"venue"
},
  "geometry": {"coordinates":[-103.068776,39.301825],"type":"Point"}
}