{
  "type": "Feature",
  "properties": {
    "addr:full":"7077 Winchester Cir Boulder CO 80301",
    "addr:housenumber":"7077",
    "addr:postcode":"80301",
    "addr:street":"Winchester Cir",
    "iso:country":"US",
    "sg:address":"7077 Winchester Cir",
    "sg:city":"Boulder",
    "sg:classifiers":[
        {
            "category":"Manufacturing",
            "subcategory":"Printing",
            "type":"Manufacturing & Wholesale Goods"
        }
    ],
    "sg:phone":"+1 303 443 7250",
    "sg:postcode":"80301",
    "sg:province":"CO",
    "sg:tags":[
        "publisher"
    ],
    "sg:website":"www.paladin-press.com",
    "wof:name":"PALADIN Press",
    "wof:placetype":"venue"
},
  "geometry": {"coordinates":[-105.18886999999999,40.079111],"type":"Point"}
}