{
  "type": "Feature",
  "properties": {
    "iso:country":"US",
    "sg:address":"1310 College Ave",
    "sg:city":"Boulder",
    "sg:classifiers":[
        {
            "category":"Restaurant",
            "type":"Food & Drink"
        }
    ],
    "sg:phone":"+1 303 444 7763",
    "sg:postcode":"80302",
    "sg:province":"CO",
    "sg:tags":[
        "eating"
    ],
    "wof:name":"Shishkabob Supreme Inc",
    "wof:placetype":"venue"
},
  "geometry": {"coordinates":[-105.275103,40.007198],"type":"Point"}
}