{
  "type": "Feature",
  "properties": {
    "iso:country":"US",
    "sg:address":"1818 S Quebec St",
    "sg:city":"Denver",
    "sg:classifiers":[
        {
            "category":"Transit Center",
            "subcategory":"Passenger",
            "type":"Transportation"
        }
    ],
    "sg:phone":"+1 720 298 0004",
    "sg:postcode":"80231",
    "sg:province":"CO",
    "sg:website":"denveronyxlimo.com/#cid=yelp",
    "wof:name":"Onyx Limousine",
    "wof:placetype":"venue"
},
  "geometry": {"coordinates":[-104.903382,39.683556],"type":"Point"}
}