{
  "type": "Feature",
  "properties": {
    "iso:country":"US",
    "sg:address":"12933 E Cornell Ave",
    "sg:city":"Aurora",
    "sg:classifiers":[
        {
            "category":"Professional",
            "type":"Services"
        }
    ],
    "sg:phone":"+1 303 369 6023",
    "sg:postcode":"80014",
    "sg:province":"CO",
    "wof:name":"Karen Deger McChesney",
    "wof:placetype":"venue"
},
  "geometry": {"coordinates":[-104.839268,39.662768],"type":"Point"}
}