{
  "type": "Feature",
  "properties": {
    "iso:country":"US",
    "sg:address":"631 E Industrial Blvd",
    "sg:city":"Pueblo",
    "sg:classifiers":[
        {
            "category":"Building & Trades",
            "subcategory":"Construction",
            "type":"Services"
        }
    ],
    "sg:phone":"+1 719 547 0277",
    "sg:postcode":"81007",
    "sg:province":"CO",
    "sg:tags":[
        "covering",
        "contractor"
    ],
    "wof:name":"P & A Pntg & Coml Flr Coveri",
    "wof:placetype":"venue"
},
  "geometry": {"coordinates":[-104.705366,38.330811],"type":"Point"}
}