{
  "type": "Feature",
  "properties": {
    "iso:country":"US",
    "sg:address":"6109 US Hwy 287",
    "sg:city":"Laporte",
    "sg:classifiers":[
        {
            "category":"Recreation",
            "type":"Entertainment"
        }
    ],
    "sg:phone":"+1 970 484 7351",
    "sg:postcode":"80535",
    "sg:province":"CO",
    "sg:tags":[
        "stable"
    ],
    "wof:name":"Canyon Equine Ctr",
    "wof:placetype":"venue"
},
  "geometry": {"coordinates":[-105.18213299999999,40.656841],"type":"Point"}
}