{
  "type": "Feature",
  "properties": {
    "addr:full":"575 Penrose Blvd Colorado Springs CO 80906",
    "addr:housenumber":"575",
    "addr:postcode":"80906",
    "addr:street":"Penrose Blvd",
    "iso:country":"US",
    "sg:address":"575 Penrose Blvd",
    "sg:city":"Colorado Springs",
    "sg:classifiers":[
        {
            "category":"Professional",
            "type":"Services"
        }
    ],
    "sg:phone":"+1 719 471 0444",
    "sg:postcode":"80906",
    "sg:province":"CO",
    "wof:name":"Sheila Stvnson Rgan Foundation",
    "wof:placetype":"venue"
},
  "geometry": {"coordinates":[-104.853996,38.781101],"type":"Point"}
}