{
  "type": "Feature",
  "properties": {
    "addr:full":"5669 McWhinney Blvd Loveland CO 80538",
    "addr:housenumber":"5669",
    "addr:postcode":"80538",
    "addr:street":"Mcwhinney Blvd",
    "iso:country":"US",
    "sg:address":"5669 McWhinney Blvd",
    "sg:city":"Loveland",
    "sg:classifiers":[
        {
            "category":"Food & Beverages",
            "subcategory":"Candy",
            "type":"Retail Goods"
        }
    ],
    "sg:phone":"+1 970 593 0106",
    "sg:postcode":"80538",
    "sg:province":"CO",
    "sg:tags":[
        "confectionery"
    ],
    "wof:name":"Rocky Mountain Chocolate Fctry",
    "wof:placetype":"venue"
},
  "geometry": {"coordinates":[-104.99354099999999,40.41097],"type":"Point"}
}