{
  "type": "Feature",
  "properties": {
    "iso:country":"US",
    "sg:address":"2601 W 10th St",
    "sg:city":"Greeley",
    "sg:classifiers":[
        {
            "category":"Retail",
            "subcategory":"Animal Services",
            "type":"Services"
        }
    ],
    "sg:phone":"+1 970 351 6993",
    "sg:postcode":"80634",
    "sg:province":"CO",
    "sg:tags":[
        "pet",
        "grooming",
        "washing"
    ],
    "wof:name":"Best In Show Pet Grooming",
    "wof:placetype":"venue"
},
  "geometry": {"coordinates":[-104.72423499999999,40.422889],"type":"Point"}
}