{
  "type": "Feature",
  "properties": {
    "iso:country":"US",
    "sg:address":"910 Cook St",
    "sg:city":"Denver",
    "sg:classifiers":[
        {
            "category":"Professional",
            "type":"Services"
        }
    ],
    "sg:phone":"+1 303 399 6111",
    "sg:postcode":"80206",
    "sg:province":"CO",
    "wof:name":"Petal Connections",
    "wof:placetype":"venue"
},
  "geometry": {"coordinates":[-104.94721199999999,39.731933],"type":"Point"}
}