{
  "type": "Feature",
  "properties": {
    "iso:country":"US",
    "sg:address":"725 W Drake Rd",
    "sg:city":"Fort Collins",
    "sg:classifiers":[
        {
            "category":"Organizations",
            "subcategory":"Religious Organization",
            "type":"Services"
        }
    ],
    "sg:phone":"+1 970 223 5191",
    "sg:postcode":"80526",
    "sg:province":"CO",
    "sg:tags":[
        "synagogue"
    ],
    "sg:website":"www.congregationharshalom.org",
    "wof:name":"Congregation Har Shalom",
    "wof:placetype":"venue"
},
  "geometry": {"coordinates":[-105.089679,40.55259],"type":"Point"}
}