{
  "type": "Feature",
  "properties": {
    "addr:full":"27166 Mountain Park Rd Evergreen CO 80439",
    "addr:housenumber":"27166",
    "addr:postcode":"80439",
    "addr:street":"Mountain Park Rd",
    "iso:country":"US",
    "sg:address":"27166 Mountain Park Rd",
    "sg:city":"Evergreen",
    "sg:classifiers":[
        {
            "category":"Professional",
            "subcategory":"Business Services",
            "type":"Services"
        }
    ],
    "sg:phone":"+1 303 674 1600",
    "sg:postcode":"80439",
    "sg:province":"CO",
    "sg:tags":[
        "interior",
        "consultant",
        "design",
        "decorator"
    ],
    "wof:name":"Mullins Youngdahl Design Co",
    "wof:placetype":"venue"
},
  "geometry": {"coordinates":[-105.311125,39.627134],"type":"Point"}
}