{
  "type": "Feature",
  "properties": {
    "addr:full":"819 Colorado Boulevard Denver CO 80206",
    "addr:housenumber":"819",
    "addr:postcode":"80206",
    "addr:street":"Colorado Boulevard",
    "iso:country":"US",
    "sg:address":"819 Colorado Boulevard",
    "sg:city":"Denver",
    "sg:classifiers":[
        {
            "category":"Bars & Pubs",
            "type":"Food & Drink"
        }
    ],
    "sg:phone":"+1 720 524 8099",
    "sg:postcode":"80206",
    "sg:province":"CO",
    "wof:name":"The Bar Car",
    "wof:placetype":"venue"
},
  "geometry": {"coordinates":[-104.940804,39.729682],"type":"Point"}
}