{
  "type": "Feature",
  "properties": {
    "iso:country":"US",
    "sg:address":"8265 Steele St",
    "sg:city":"Denver",
    "sg:classifiers":[
        {
            "category":"Freight",
            "type":"Transportation"
        }
    ],
    "sg:phone":"+1 303 464 7223",
    "sg:postcode":"80229",
    "sg:province":"CO",
    "sg:tags":[
        "trucking"
    ],
    "sg:website":"www.foothillsrock.com",
    "wof:name":"Foothills Transport",
    "wof:placetype":"venue"
},
  "geometry": {"coordinates":[-104.949668,39.849489],"type":"Point"}
}