{
  "type": "Feature",
  "properties": {
    "iso:country":"US",
    "sg:address":"216 Racquette Dr",
    "sg:city":"Fort Collins",
    "sg:classifiers":[
        {
            "category":"Retail",
            "subcategory":"Auto Repair",
            "type":"Services"
        }
    ],
    "sg:phone":"+1 970 416 0497",
    "sg:postcode":"80524",
    "sg:province":"CO",
    "sg:tags":[
        "transmission"
    ],
    "wof:name":"Advanced Transmission & Clutch",
    "wof:placetype":"venue"
},
  "geometry": {"coordinates":[-105.04452499999999,40.588328],"type":"Point"}
}