{
  "type": "Feature",
  "properties": {
    "addr:full":"6145 Lehman Dr Colorado Springs CO 80918",
    "addr:housenumber":"6145",
    "addr:postcode":"80918",
    "addr:street":"Lehman Dr",
    "iso:country":"US",
    "sg:address":"6145 Lehman Dr",
    "sg:city":"Colorado Springs",
    "sg:classifiers":[
        {
            "category":"Organizations",
            "subcategory":"Membership Organization",
            "type":"Services"
        },
        {
            "category":"Professional",
            "subcategory":"Business Services",
            "type":"Services"
        }
    ],
    "sg:phone":"+1 719 548 1000",
    "sg:postcode":"80918",
    "sg:province":"CO",
    "sg:tags":[
        "lecture",
        "hospital",
        "bureau",
        "specialty",
        "seminar"
    ],
    "wof:name":"White Bison Inc",
    "wof:placetype":"venue"
},
  "geometry": {"coordinates":[-104.78962799999999,38.918824],"type":"Point"}
}