{
  "type": "Feature",
  "properties": {
    "addr:full":"8549 S Allison St Littleton CO 80128",
    "addr:housenumber":"8549",
    "addr:postcode":"80128",
    "addr:street":"S Allison St",
    "iso:country":"US",
    "sg:address":"8549 S Allison St",
    "sg:city":"Littleton",
    "sg:classifiers":[
        {
            "category":"Building & Trades",
            "subcategory":"Landscaping Services",
            "type":"Services"
        }
    ],
    "sg:phone":"+1 303 932 8853",
    "sg:postcode":"80128",
    "sg:province":"CO",
    "sg:tags":[
        "lawn",
        "maintenance",
        "grounds"
    ],
    "sg:website":"www.livingsoilandlawns.com",
    "wof:name":"Grassmaster Lawncare Inc",
    "wof:placetype":"venue"
},
  "geometry": {"coordinates":[-105.08817500000001,39.558425],"type":"Point"}
}