{
  "type": "Feature",
  "properties": {
    "addr:full":"5783 W 118th Pl Broomfield CO 80020",
    "addr:housenumber":"5783",
    "addr:postcode":"80020",
    "addr:street":"W 118Th Pl",
    "iso:country":"US",
    "sg:address":"5783 W 118th Pl",
    "sg:city":"Broomfield",
    "sg:classifiers":[
        {
            "category":"Wholesale",
            "subcategory":"Vending Machines",
            "type":"Manufacturing & Wholesale Goods"
        }
    ],
    "sg:phone":"+1 303 410 9002",
    "sg:postcode":"80020",
    "sg:province":"CO",
    "sg:tags":[
        "operator"
    ],
    "wof:name":"Smilin Piranha LLC",
    "wof:placetype":"venue"
},
  "geometry": {"coordinates":[-105.057742,39.911543],"type":"Point"}
}