{
  "type": "Feature",
  "properties": {
    "iso:country":"US",
    "sg:address":"431 S Larkspur Dr",
    "sg:city":"Castle Rock",
    "sg:classifiers":[
        {
            "category":"Building & Trades",
            "subcategory":"Construction",
            "type":"Services"
        }
    ],
    "sg:phone":"+1 303 829 3374",
    "sg:postcode":"80104",
    "sg:province":"CO",
    "sg:tags":[
        "repairing",
        "remodeling",
        "contractor"
    ],
    "wof:name":"De Young Brothers Construction",
    "wof:placetype":"venue"
},
  "geometry": {"coordinates":[-104.836635,39.367718],"type":"Point"}
}