{
  "type": "Feature",
  "properties": {
    "iso:country":"US",
    "sg:address":"1873 S Bellaire Street",
    "sg:city":"Denver",
    "sg:classifiers":[
        {
            "category":"Professional",
            "subcategory":"Accounting & Tax Preparation",
            "type":"Services"
        }
    ],
    "sg:phone":"+1 303 692 8044",
    "sg:postcode":"80222",
    "sg:province":"CO",
    "sg:tags":[
        "accountant"
    ],
    "wof:name":"Story & Company PC",
    "wof:placetype":"venue"
},
  "geometry": {"coordinates":[-104.93735,39.682563],"type":"Point"}
}