{
  "type": "Feature",
  "properties": {
    "iso:country":"US",
    "sg:address":"122 E Durant Ave",
    "sg:city":"Aspen",
    "sg:classifiers":[
        {
            "category":"Travel",
            "subcategory":"Hotels & Motels",
            "type":"Entertainment"
        }
    ],
    "sg:phone":"+1 970 925 8500",
    "sg:postcode":"81611",
    "sg:province":"CO",
    "sg:tags":[
        "operation"
    ],
    "wof:name":"Inverness Lodge",
    "wof:placetype":"venue"
},
  "geometry": {"coordinates":[-106.822929,39.188103],"type":"Point"}
}