{
  "type": "Feature",
  "properties": {
    "addr:full":"1852 S Wadsworth Blvd Lakewood CO 80232",
    "addr:housenumber":"1852",
    "addr:postcode":"80232",
    "addr:street":"S Wadsworth Blvd",
    "iso:country":"US",
    "sg:address":"1852 S Wadsworth Blvd",
    "sg:city":"Lakewood",
    "sg:classifiers":[
        {
            "category":"Personal",
            "subcategory":"Shoe Repair & Shine",
            "type":"Services"
        }
    ],
    "sg:phone":"+1 303 296 4785",
    "sg:postcode":"80232",
    "sg:province":"CO",
    "sg:tags":[
        "repairing",
        "boot"
    ],
    "wof:name":"Out Of Time Dry Cleaning Dlvry",
    "wof:placetype":"venue"
},
  "geometry": {"coordinates":[-105.081344,39.682622],"type":"Point"}
}