{
  "type": "Feature",
  "properties": {
    "iso:country":"US",
    "sg:address":"34230 US Hwy 385",
    "sg:city":"Wray",
    "sg:classifiers":[
        {
            "category":"Manufacturing",
            "subcategory":"Metals",
            "type":"Manufacturing & Wholesale Goods"
        },
        {
            "category":"Manufacturing",
            "subcategory":"Tools & Machinery",
            "type":"Manufacturing & Wholesale Goods"
        }
    ],
    "sg:phone":"+1 970 332 0999",
    "sg:postcode":"80758",
    "sg:province":"CO",
    "sg:tags":[
        "industrial",
        "mfg"
    ],
    "wof:name":"Ed's Machining & Fabrication",
    "wof:placetype":"venue"
},
  "geometry": {"coordinates":[-102.226732,40.066238],"type":"Point"}
}