{
  "type": "Feature",
  "properties": {
    "iso:country":"US",
    "sg:address":"406 Juanita St",
    "sg:city":"Colorado Springs",
    "sg:classifiers":[
        {
            "category":"Wholesale",
            "subcategory":"Machinery & Supplies",
            "type":"Manufacturing & Wholesale Goods"
        }
    ],
    "sg:phone":"+1 719 578 0177",
    "sg:postcode":"80909",
    "sg:province":"CO",
    "sg:tags":[
        "equipment",
        "establishment"
    ],
    "wof:name":"Cleaning Solutions Plus",
    "wof:placetype":"venue"
},
  "geometry": {"coordinates":[-104.774627,38.838471],"type":"Point"}
}