{
  "type": "Feature",
  "properties": {
    "iso:country":"US",
    "sg:address":"19705 Clubhouse Dr",
    "sg:city":"Parker",
    "sg:classifiers":[
        {
            "category":"Manufacturing",
            "subcategory":"Signs",
            "type":"Manufacturing & Wholesale Goods"
        }
    ],
    "sg:phone":"+1 303 699 5341",
    "sg:postcode":"80138",
    "sg:province":"CO",
    "sg:tags":[
        "specialty",
        "mfg"
    ],
    "wof:name":"Bear Facts Ad Products",
    "wof:placetype":"venue"
},
  "geometry": {"coordinates":[-104.76109099999999,39.511817],"type":"Point"}
}