{
  "type": "Feature",
  "properties": {
    "addr:full":"1455 US Hwy 287 Broomfield CO 80020",
    "addr:housenumber":"1455",
    "addr:postcode":"80020",
    "addr:street":"Us Hwy 287",
    "iso:country":"US",
    "sg:address":"1455 US Hwy 287",
    "sg:city":"Broomfield",
    "sg:classifiers":[
        {
            "category":"Wholesale",
            "subcategory":"Chemicals & Plastics",
            "type":"Manufacturing & Wholesale Goods"
        }
    ],
    "sg:phone":"+1 303 404 0203",
    "sg:postcode":"80020",
    "sg:province":"CO",
    "sg:tags":[
        "oxygen"
    ],
    "wof:name":"Colorado RT Svc",
    "wof:placetype":"venue"
},
  "geometry": {"coordinates":[-105.09092,39.935371],"type":"Point"}
}