{
  "type": "Feature",
  "properties": {
    "iso:country":"US",
    "sg:address":"3129 Redstone Ln",
    "sg:city":"Boulder",
    "sg:classifiers":[
        {
            "category":"Professional",
            "subcategory":"Art Services",
            "type":"Services"
        }
    ],
    "sg:phone":"+1 303 818 0456",
    "sg:postcode":"80305",
    "sg:province":"CO",
    "sg:tags":[
        "photographer"
    ],
    "wof:name":"Mark Doolittle Photography",
    "wof:placetype":"venue"
},
  "geometry": {"coordinates":[-105.25480399999999,39.966316],"type":"Point"}
}