{
  "type": "Feature",
  "properties": {
    "iso:country":"US",
    "sg:address":"2387 F Rd",
    "sg:city":"Grand Junction",
    "sg:classifiers":[
        {
            "category":"Banks & Credit Unions",
            "subcategory":"Bank",
            "type":"Services"
        }
    ],
    "sg:phone":"+1 970 683 3500",
    "sg:postcode":"81505",
    "sg:province":"CO",
    "wof:name":"Wells Fargo Hm Mtg",
    "wof:placetype":"venue"
},
  "geometry": {"coordinates":[-108.610484,39.094551],"type":"Point"}
}