{
  "type": "Feature",
  "properties": {
    "iso:country":"US",
    "sg:address":"3100 Marine St",
    "sg:city":"Boulder",
    "sg:classifiers":[
        {
            "category":"Government",
            "subcategory":"Office",
            "type":"Public Place"
        }
    ],
    "sg:phone":"+1 303 492 3774",
    "sg:postcode":"80303",
    "sg:province":"CO",
    "sg:tags":[
        "science",
        "space",
        "technology",
        "research"
    ],
    "wof:name":"Space Science Institute",
    "wof:placetype":"venue"
},
  "geometry": {"coordinates":[-105.248012,40.013625],"type":"Point"}
}