{
  "type": "Feature",
  "properties": {
    "addr:full":"9567 S University Blvd Highlands Ranch CO 80126",
    "addr:housenumber":"9567",
    "addr:postcode":"80126",
    "addr:street":"S University Blvd",
    "iso:country":"US",
    "sg:address":"9567 S University Blvd",
    "sg:city":"Highlands Ranch",
    "sg:classifiers":[
        {
            "category":"Shopping",
            "subcategory":"Gifts & Souvenirs",
            "type":"Retail Goods"
        }
    ],
    "sg:phone":"+1 303 346 7880",
    "sg:postcode":"80126",
    "sg:province":"CO",
    "sg:tags":[
        "product",
        "supply",
        "personal",
        "favor",
        "paper",
        "party"
    ],
    "sg:website":"www.partyamerica.com",
    "wof:name":"Party America",
    "wof:placetype":"venue"
},
  "geometry": {"coordinates":[-104.942526,39.543513],"type":"Point"}
}