{
  "type": "Feature",
  "properties": {
    "iso:country":"US",
    "sg:address":"928 N Jefferson Ave",
    "sg:city":"Loveland",
    "sg:classifiers":[
        {
            "category":"Wholesale",
            "subcategory":"Jewelry",
            "type":"Manufacturing & Wholesale Goods"
        }
    ],
    "sg:phone":"+1 970 461 1138",
    "sg:postcode":"80537",
    "sg:province":"CO",
    "sg:tags":[
        "stone"
    ],
    "wof:name":"Christine Lee Jewlry",
    "wof:placetype":"venue"
},
  "geometry": {"coordinates":[-105.071786,40.401869],"type":"Point"}
}