{
  "type": "Feature",
  "properties": {
    "addr:full":"821 Cottonwood Dr Loveland CO 80538",
    "addr:housenumber":"821",
    "addr:postcode":"80538",
    "addr:street":"Cottonwood Dr",
    "iso:country":"US",
    "sg:address":"821 Cottonwood Dr",
    "sg:city":"Loveland",
    "sg:classifiers":[
        {
            "category":"Building & Trades",
            "subcategory":"Construction",
            "type":"Services"
        }
    ],
    "sg:phone":"+1 970 667 6121",
    "sg:postcode":"80538",
    "sg:province":"CO",
    "sg:tags":[
        "hanging",
        "contractor"
    ],
    "wof:name":"Heidrick Painting Jim",
    "wof:placetype":"venue"
},
  "geometry": {"coordinates":[-105.087295,40.434128],"type":"Point"}
}