{
  "type": "Feature",
  "properties": {
    "addr:full":"10971 Puma Run Littleton CO 80125",
    "addr:housenumber":"10971",
    "addr:postcode":"80125",
    "addr:street":"Puma Run",
    "iso:country":"US",
    "sg:address":"10971 Puma Run",
    "sg:city":"Littleton",
    "sg:classifiers":[
        {
            "category":"Professional",
            "type":"Services"
        }
    ],
    "sg:phone":"+1 303 662 1991",
    "sg:postcode":"80125",
    "sg:province":"CO",
    "wof:name":"Torrent Energy",
    "wof:placetype":"venue"
},
  "geometry": {"coordinates":[-104.91541700000001,39.518832],"type":"Point"}
}