{
  "type": "Feature",
  "properties": {
    "addr:full":"258 S Taylor Ave Louisville CO 80027",
    "addr:housenumber":"258",
    "addr:postcode":"80027",
    "addr:street":"S Taylor Ave",
    "iso:country":"US",
    "sg:address":"258 S Taylor Ave",
    "sg:city":"Louisville",
    "sg:classifiers":[
        {
            "category":"Arena",
            "subcategory":"Sports Club",
            "type":"Entertainment"
        }
    ],
    "sg:phone":"+1 303 530 7811",
    "sg:postcode":"80027",
    "sg:province":"CO",
    "sg:tags":[
        "manager",
        "recruiter",
        "promoter"
    ],
    "sg:website":"www.sportstarprosales.com",
    "wof:name":"Sportstar USA",
    "wof:placetype":"venue"
},
  "geometry": {"coordinates":[-105.119598,39.966385],"type":"Point"}
}