{
  "type": "Feature",
  "properties": {
    "addr:full":"4420 Kano Dr Fort Collins CO 80526",
    "addr:postcode":"4420;80526",
    "addr:street":"Kano Dr",
    "iso:country":"US",
    "sg:address":"4420 Kano Dr",
    "sg:city":"Fort Collins",
    "sg:phone":"+1 970 204 4523",
    "sg:postcode":"80526",
    "sg:province":"CO",
    "sg:tags":[
        "on",
        "implement",
        "fax",
        "internet"
    ],
    "wof:name":"Faxtcom",
    "wof:placetype":"venue"
},
  "geometry": {"coordinates":[-105.16315,40.529005],"type":"Point"}
}