{
  "type": "Feature",
  "properties": {
    "iso:country":"US",
    "sg:address":"7230 W 118th Pl",
    "sg:city":"Broomfield",
    "sg:classifiers":[
        {
            "category":"Manufacturing",
            "subcategory":"Leather Goods",
            "type":"Manufacturing & Wholesale Goods"
        }
    ],
    "sg:phone":"+1 303 466 3035",
    "sg:postcode":"80020",
    "sg:province":"CO",
    "sg:tags":[
        "case"
    ],
    "wof:name":"Senco Cutting & Sewing",
    "wof:placetype":"venue"
},
  "geometry": {"coordinates":[-105.077904,39.91034],"type":"Point"}
}