{
  "type": "Feature",
  "properties": {
    "addr:full":"3811 75th St Boulder CO 80301",
    "addr:housenumber":"3811",
    "addr:postcode":"80301",
    "addr:street":"75Th St",
    "iso:country":"US",
    "sg:address":"3811 75th St",
    "sg:city":"Boulder",
    "sg:classifiers":[
        {
            "category":"Wholesale",
            "subcategory":"Machinery & Supplies",
            "type":"Manufacturing & Wholesale Goods"
        }
    ],
    "sg:phone":"+1 303 449 8210",
    "sg:postcode":"80301",
    "sg:province":"CO",
    "sg:tags":[
        "tractor"
    ],
    "wof:name":"Flessner Tractor Sales Inc",
    "wof:placetype":"venue"
},
  "geometry": {"coordinates":[-105.17838500000001,40.048722],"type":"Point"}
}