{
  "type": "Feature",
  "properties": {
    "iso:country":"US",
    "sg:address":"27750 State Hwy 74",
    "sg:city":"Evergreen",
    "sg:classifiers":[
        {
            "category":"Personal",
            "subcategory":"Beauty Salon",
            "type":"Services"
        }
    ],
    "sg:phone":"+1 303 670 0333",
    "sg:postcode":"80439",
    "sg:province":"CO",
    "wof:name":"Hair By Gigi",
    "wof:placetype":"venue"
},
  "geometry": {"coordinates":[-105.314774,39.637065],"type":"Point"}
}