{
  "type": "Feature",
  "properties": {
    "iso:country":"US",
    "sg:address":"300 Josephine St",
    "sg:city":"Denver",
    "sg:classifiers":[
        {
            "category":"Personal",
            "subcategory":"Beauty Salon",
            "type":"Services"
        }
    ],
    "sg:phone":"+1 303 393 1411",
    "sg:postcode":"80206",
    "sg:province":"CO",
    "sg:tags":[
        "hair"
    ],
    "sg:website":"www.maxhairsalon.com",
    "wof:name":"Max Salon of Cherry Creek",
    "wof:placetype":"venue"
},
  "geometry": {"coordinates":[-104.958217,39.720998],"type":"Point"}
}