{
  "type": "Feature",
  "properties": {
    "iso:country":"US",
    "sg:address":"511 Main St",
    "sg:city":"Alamosa",
    "sg:classifiers":[
        {
            "category":"Health Services",
            "subcategory":"Chiropractor",
            "type":"Services"
        }
    ],
    "sg:phone":"+1 719 589 5163",
    "sg:postcode":"81101",
    "sg:province":"CO",
    "wof:name":"Wiley Chiropractic Group",
    "wof:placetype":"venue"
},
  "geometry": {"coordinates":[-105.86544499999999,37.46832],"type":"Point"}
}