{
  "type": "Feature",
  "properties": {
    "addr:full":"1327 E 73rd Ave Denver CO 80229",
    "addr:housenumber":"1327",
    "addr:postcode":"80229",
    "addr:street":"E 73Rd Ave",
    "iso:country":"US",
    "sg:address":"1327 E 73rd Ave",
    "sg:city":"Denver",
    "sg:classifiers":[
        {
            "category":"Wholesale",
            "subcategory":"Plants",
            "type":"Manufacturing & Wholesale Goods"
        }
    ],
    "sg:phone":"+1 303 286 7194",
    "sg:postcode":"80229",
    "sg:province":"CO",
    "sg:tags":[
        "fresh",
        "flower"
    ],
    "wof:name":"ABC Bouquet West LLC",
    "wof:placetype":"venue"
},
  "geometry": {"coordinates":[-104.97714499999999,39.829128],"type":"Point"}
}