{
  "type": "Feature",
  "properties": {
    "iso:country":"US",
    "sg:address":"401 N Pagosa Blvd",
    "sg:city":"Pagosa Springs",
    "sg:classifiers":[
        {
            "category":"Professional",
            "subcategory":"Accounting & Tax Preparation",
            "type":"Services"
        }
    ],
    "sg:phone":"+1 970 264 4581",
    "sg:postcode":"81147",
    "sg:province":"CO",
    "sg:tags":[
        "return",
        "filing"
    ],
    "wof:name":"H & R Block",
    "wof:placetype":"venue"
},
  "geometry": {"coordinates":[-107.084677,37.257008],"type":"Point"}
}