{
  "type": "Feature",
  "properties": {
    "iso:country":"US",
    "sg:address":"8215 Mohawk Rd",
    "sg:city":"Colorado Springs",
    "sg:classifiers":[
        {
            "category":"Real Estate",
            "subcategory":"Real Estate Operator",
            "type":"Services"
        }
    ],
    "sg:phone":"+1 719 495 0287",
    "sg:postcode":"80908",
    "sg:province":"CO",
    "sg:tags":[
        "building",
        "livestock",
        "nonresidential"
    ],
    "wof:name":"P&D Associates",
    "wof:placetype":"venue"
},
  "geometry": {"coordinates":[-104.663911,38.94996],"type":"Point"}
}