{
  "type": "Feature",
  "properties": {
    "addr:full":"21601 Orleans Cir Commerce City CO 80022",
    "addr:housenumber":"21601",
    "addr:postcode":"80022",
    "addr:street":"Orleans Cir",
    "iso:country":"US",
    "sg:address":"21601 Orleans Cir",
    "sg:city":"Commerce City",
    "sg:classifiers":[
        {
            "category":"Home & Garden",
            "subcategory":"Carpets & Floor Coverings",
            "type":"Retail Goods"
        }
    ],
    "sg:phone":"+1 303 659 8049",
    "sg:postcode":"80022",
    "sg:province":"CO",
    "sg:tags":[
        "store"
    ],
    "wof:name":"Carpet Workshop",
    "wof:placetype":"venue"
},
  "geometry": {"coordinates":[-104.7336,39.908168],"type":"Point"}
}