{
  "type": "Feature",
  "properties": {
    "iso:country":"US",
    "sg:address":"9595 Nelson Rd Ste B",
    "sg:city":"Longmont",
    "sg:classifiers":[
        {
            "category":"Education",
            "subcategory":"University",
            "type":"Public Place"
        }
    ],
    "sg:phone":"+1 303 678 6238",
    "sg:postcode":"80501",
    "sg:province":"CO",
    "sg:tags":[
        "college"
    ],
    "sg:website":"http://www.co.boulder.co.us",
    "wof:name":"Colorado State University",
    "wof:placetype":"venue"
},
  "geometry": {"coordinates":[-105.126348,40.152382],"type":"Point"}
}