{
  "type": "Feature",
  "properties": {
    "iso:country":"US",
    "sg:address":"4173 E 126th Ave",
    "sg:city":"Thornton",
    "sg:classifiers":[
        {
            "category":"Freight",
            "type":"Transportation"
        }
    ],
    "sg:phone":"+1 303 530 4203",
    "sg:postcode":"80241",
    "sg:province":"CO",
    "sg:tags":[
        "mover"
    ],
    "wof:name":"Moving Made Easy Inc",
    "wof:placetype":"venue"
},
  "geometry": {"coordinates":[-104.939153,39.925214],"type":"Point"}
}