{
  "type": "Feature",
  "properties": {
    "iso:country":"US",
    "sg:address":"1549 Elk St",
    "sg:city":"Rock Springs",
    "sg:classifiers":[
        {
            "category":"Sports & Exercise",
            "subcategory":"Race Track",
            "type":"Entertainment"
        }
    ],
    "sg:phone":"+1 307 362 4723",
    "sg:postcode":"82901",
    "sg:province":"CO",
    "sg:tags":[
        "betting",
        "off",
        "operation"
    ],
    "wof:name":"Wyoming Horse Racing Inc",
    "wof:placetype":"venue"
},
  "geometry": {"coordinates":[-109.229432,41.606235],"type":"Point"}
}