{
  "type": "Feature",
  "properties": {
    "addr:full":"5666 N Academy Blvd Colorado Springs CO 80918",
    "addr:housenumber":"5666",
    "addr:postcode":"80918",
    "addr:street":"N Academy Blvd",
    "iso:country":"US",
    "sg:address":"5666 N Academy Blvd",
    "sg:city":"Colorado Springs",
    "sg:classifiers":[
        {
            "category":"Personal",
            "subcategory":"Beauty Salon",
            "type":"Services"
        }
    ],
    "sg:phone":"+1 719 593 7520",
    "sg:postcode":"80918",
    "sg:province":"CO",
    "wof:name":"Studio 6 Salon",
    "wof:placetype":"venue"
},
  "geometry": {"coordinates":[-104.788173,38.912556],"type":"Point"}
}