{
  "type": "Feature",
  "properties": {
    "iso:country":"US",
    "sg:address":"4340 US Hwy 160",
    "sg:city":"Monte Vista",
    "sg:classifiers":[
        {
            "category":"Travel",
            "subcategory":"Hotels & Motels",
            "type":"Entertainment"
        }
    ],
    "sg:phone":"+1 719 852 0438",
    "sg:postcode":"81144",
    "sg:province":"CO",
    "sg:tags":[
        "breakfast",
        "accommodation",
        "bed"
    ],
    "wof:name":"Windmill Bed & Breakfast",
    "wof:placetype":"venue"
},
  "geometry": {"coordinates":[-106.211305,37.597576],"type":"Point"}
}