{
  "type": "Feature",
  "properties": {
    "iso:country":"US",
    "sg:address":"1425 W Hwy 105",
    "sg:city":"Monument",
    "sg:classifiers":[
        {
            "category":"Retail",
            "subcategory":"Veterinary Services",
            "type":"Services"
        }
    ],
    "sg:phone":"+1 719 488 2501",
    "sg:postcode":"80132",
    "sg:province":"CO",
    "wof:name":"Woodmoor Veterinary Hospital",
    "wof:placetype":"venue"
},
  "geometry": {"coordinates":[-104.85184700000001,39.093018],"type":"Point"}
}