{
  "type": "Feature",
  "properties": {
    "iso:country":"US",
    "sg:address":"4616 NE Frontage Rd",
    "sg:city":"Fort Collins",
    "sg:classifiers":[
        {
            "category":"Education",
            "subcategory":"College",
            "type":"Public Place"
        }
    ],
    "sg:phone":"+1 970 491 2439",
    "sg:postcode":"80524",
    "sg:province":"CO",
    "sg:tags":[
        "university"
    ],
    "wof:name":"Colorado State University",
    "wof:placetype":"venue"
},
  "geometry": {"coordinates":[-105.00031199999999,40.641635],"type":"Point"}
}