{
  "type": "Feature",
  "properties": {
    "addr:full":"4632 S White Ct Littleton CO 80127",
    "addr:housenumber":"4632",
    "addr:postcode":"80127",
    "addr:street":"S White Ct",
    "iso:country":"US",
    "sg:address":"4632 S White Ct",
    "sg:city":"Littleton",
    "sg:classifiers":[
        {
            "category":"Building & Trades",
            "subcategory":"Construction",
            "type":"Services"
        }
    ],
    "sg:phone":"+1 303 972 4713",
    "sg:postcode":"80127",
    "sg:province":"CO",
    "sg:tags":[
        "contractor"
    ],
    "wof:name":"Clint Ek Co",
    "wof:placetype":"venue"
},
  "geometry": {"coordinates":[-105.113387,39.633439],"type":"Point"}
}