{
  "type": "Feature",
  "properties": {
    "addr:full":"6225 W 48th Avenue Wheat Ridge CO 80033",
    "addr:housenumber":"6225",
    "addr:postcode":"80033",
    "addr:street":"W 48Th Avenue",
    "iso:country":"US",
    "sg:address":"6225 W 48th Avenue",
    "sg:city":"Wheat Ridge",
    "sg:classifiers":[
        {
            "category":"Building & Trades",
            "subcategory":"Plumbing",
            "type":"Services"
        }
    ],
    "sg:phone":"+1 720 214 4077",
    "sg:postcode":"80033",
    "sg:province":"CO",
    "wof:name":"Fire and Ice Heating and Air",
    "wof:placetype":"venue"
},
  "geometry": {"coordinates":[-105.065166,39.783897],"type":"Point"}
}