{
  "type": "Feature",
  "properties": {
    "iso:country":"US",
    "sg:address":"30772 Southview Dr",
    "sg:city":"Evergreen",
    "sg:classifiers":[
        {
            "category":"Social Services",
            "type":"Services"
        }
    ],
    "sg:phone":"+1 303 674 2051",
    "sg:postcode":"80439",
    "sg:province":"CO",
    "sg:tags":[
        "counselor",
        "marriage",
        "family"
    ],
    "sg:website":"www.comskills.com",
    "wof:name":"Interpersonal Communications",
    "wof:placetype":"venue"
},
  "geometry": {"coordinates":[-105.350026,39.658276],"type":"Point"}
}