{
  "type": "Feature",
  "properties": {
    "iso:country":"US",
    "sg:address":"7281 E 96th Ave",
    "sg:city":"Henderson",
    "sg:classifiers":[
        {
            "category":"Autos & Motor Vehicles",
            "subcategory":"Automobile Sales",
            "type":"Retail Goods"
        }
    ],
    "sg:phone":"+1 720 488 9272",
    "sg:postcode":"80640",
    "sg:province":"CO",
    "sg:tags":[
        "truck"
    ],
    "wof:name":"United Equipment Funding",
    "wof:placetype":"venue"
},
  "geometry": {"coordinates":[-104.90977599999999,39.87084],"type":"Point"}
}