{
  "type": "Feature",
  "properties": {
    "addr:full":"2464 Downhill Dr Steamboat Spgs CO 80487",
    "addr:housenumber":"2464",
    "addr:postcode":"80487",
    "addr:street":"Downhill Dr;Spgs",
    "iso:country":"US",
    "sg:address":"2464 Downhill Dr",
    "sg:city":"Steamboat Spgs",
    "sg:classifiers":[
        {
            "category":"Shopping",
            "subcategory":"Computers & Home Electronics",
            "type":"Retail Goods"
        }
    ],
    "sg:phone":"+1 970 879 3338",
    "sg:postcode":"80487",
    "sg:province":"CO",
    "sg:tags":[
        "audio"
    ],
    "wof:name":"Audio Dynamics",
    "wof:placetype":"venue"
},
  "geometry": {"coordinates":[-106.862559,40.507516],"type":"Point"}
}