{
  "type": "Feature",
  "properties": {
    "addr:full":"274 Ponderosa St Castle Rock CO 80104",
    "addr:housenumber":"274",
    "addr:postcode":"80104",
    "addr:street":"Ponderosa St",
    "iso:country":"US",
    "sg:address":"274 Ponderosa St",
    "sg:city":"Castle Rock",
    "sg:classifiers":[
        {
            "category":"Building & Trades",
            "subcategory":"Landscaping Services",
            "type":"Services"
        }
    ],
    "sg:phone":"+1 303 984 1848",
    "sg:postcode":"80104",
    "sg:province":"CO",
    "wof:name":"Warren Landscape",
    "wof:placetype":"venue"
},
  "geometry": {"coordinates":[-104.804813,39.37156],"type":"Point"}
}