{
  "type": "Feature",
  "properties": {
    "addr:full":"1849 Main St Longmont CO 80504",
    "addr:housenumber":"1849",
    "addr:postcode":"80504",
    "addr:street":"Main St",
    "iso:country":"US",
    "sg:address":"1849 Main St",
    "sg:city":"Longmont",
    "sg:classifiers":[
        {
            "category":"Banks & Credit Unions",
            "subcategory":"Bank",
            "type":"Services"
        }
    ],
    "sg:phone":"+1 303 485 7070",
    "sg:postcode":"80504",
    "sg:province":"CO",
    "wof:name":"Compass Bank",
    "wof:placetype":"venue"
},
  "geometry": {"coordinates":[-105.102293,40.188568],"type":"Point"}
}