{
  "type": "Feature",
  "properties": {
    "iso:country":"US",
    "sg:address":"444 E Front St",
    "sg:city":"Byers",
    "sg:classifiers":[
        {
            "category":"Professional",
            "subcategory":"Management & Consulting",
            "type":"Services"
        }
    ],
    "sg:phone":"+1 303 822 5367",
    "sg:postcode":"80103",
    "sg:province":"CO",
    "sg:tags":[
        "consultant",
        "educational"
    ],
    "wof:name":"East Central Boces",
    "wof:placetype":"venue"
},
  "geometry": {"coordinates":[-104.216346,39.707794],"type":"Point"}
}