{
  "type": "Feature",
  "properties": {
    "iso:country":"US",
    "sg:address":"5500 W 2nd Street Rd",
    "sg:city":"Greeley",
    "sg:classifiers":[
        {
            "category":"Building & Trades",
            "subcategory":"Electrical",
            "type":"Services"
        }
    ],
    "sg:phone":"+1 970 506 0211",
    "sg:postcode":"80634",
    "sg:province":"CO",
    "sg:tags":[
        "electric",
        "contractor"
    ],
    "wof:name":"Mike Flatt Electric",
    "wof:placetype":"venue"
},
  "geometry": {"coordinates":[-104.77064900000001,40.431689],"type":"Point"}
}