{
  "type": "Feature",
  "properties": {
    "addr:full":"501 Charolais Cir Edwards CO 81632",
    "addr:housenumber":"501",
    "addr:postcode":"81632",
    "addr:street":"Charolais Cir",
    "iso:country":"US",
    "sg:address":"501 Charolais Cir",
    "sg:city":"Edwards",
    "sg:classifiers":[
        {
            "category":"Retail",
            "subcategory":"Veterinary Services",
            "type":"Services"
        }
    ],
    "sg:phone":"+1 970 926 3625",
    "sg:postcode":"81632",
    "sg:province":"CO",
    "sg:tags":[
        "veterinarian"
    ],
    "wof:name":"William A Nusz DVM",
    "wof:placetype":"venue"
},
  "geometry": {"coordinates":[-106.58204600000001,39.650478],"type":"Point"}
}