{
  "type": "Feature",
  "properties": {
    "addr:full":"40245 Co Rd 31 Ault CO 80610",
    "addr:housenumber":"31",
    "addr:postcode":"40245;80610",
    "addr:street":"Co Rd",
    "iso:country":"US",
    "sg:address":"40245 Co Rd 31",
    "sg:city":"Ault",
    "sg:classifiers":[
        {
            "category":"Wholesale",
            "subcategory":"Plants",
            "type":"Manufacturing & Wholesale Goods"
        }
    ],
    "sg:phone":"+1 970 834 1662",
    "sg:postcode":"80610",
    "sg:province":"CO",
    "sg:tags":[
        "supply"
    ],
    "wof:name":"Country Perennials",
    "wof:placetype":"venue"
},
  "geometry": {"coordinates":[-104.773624,40.588232],"type":"Point"}
}