{
  "type": "Feature",
  "properties": {
    "addr:full":"2331 E. Colfax Ave Denver CO 80206",
    "addr:housenumber":"2331",
    "addr:postcode":"80206",
    "addr:street":"E. Colfax Ave",
    "iso:country":"US",
    "sg:address":"2331 E. Colfax Ave",
    "sg:city":"Denver",
    "sg:classifiers":[
        {
            "category":"Personal",
            "subcategory":"Beauty Salon",
            "type":"Services"
        },
        {
            "category":"Personal",
            "subcategory":"Barber",
            "type":"Services"
        }
    ],
    "sg:phone":"+1 303 860 0900",
    "sg:postcode":"80206",
    "sg:province":"CO",
    "sg:tags":[
        "hair"
    ],
    "sg:website":"www.floydsbarbershop.com",
    "wof:name":"Floyd's 99 Barbershop",
    "wof:placetype":"venue"
},
  "geometry": {"coordinates":[-104.959221,39.740065],"type":"Point"}
}