{
  "type": "Feature",
  "properties": {
    "addr:full":"399 Perry St Ste 300 Castle Rock CO 80104",
    "addr:housenumber":"399",
    "addr:postcode":"80104",
    "addr:street":"Perry St Ste 300",
    "iso:country":"US",
    "sg:address":"399 Perry St Ste 300",
    "sg:city":"Castle Rock",
    "sg:classifiers":[
        {
            "category":"Professional",
            "subcategory":"Lawyer & Legal Services",
            "type":"Services"
        }
    ],
    "sg:phone":"+1 303 814 3700",
    "sg:postcode":"80104",
    "sg:province":"CO",
    "sg:website":"www.taublawyers.com",
    "wof:name":"Law Offices of Taub & Taub",
    "wof:placetype":"venue"
},
  "geometry": {"coordinates":[-104.85878700000001,39.373283],"type":"Point"}
}