{
  "type": "Feature",
  "properties": {
    "iso:country":"US",
    "sg:address":"5120 Snead Ct",
    "sg:city":"Fort Collins",
    "sg:classifiers":[
        {
            "category":"Banks & Credit Unions",
            "subcategory":"Bank",
            "type":"Services"
        }
    ],
    "sg:phone":"+1 970 282 8111",
    "sg:postcode":"80528",
    "sg:province":"CO",
    "sg:tags":[
        "broker",
        "mortgage"
    ],
    "wof:name":"Aspen-Net Investments Inc",
    "wof:placetype":"venue"
},
  "geometry": {"coordinates":[-104.981195,40.484556],"type":"Point"}
}