{
  "type": "Feature",
  "properties": {
    "iso:country":"US",
    "sg:address":"6804 Garfield Ave",
    "sg:city":"Loveland",
    "sg:classifiers":[
        {
            "category":"Retail",
            "subcategory":"Auto Repair",
            "type":"Services"
        }
    ],
    "sg:phone":"+1 970 667 4431",
    "sg:postcode":"80538",
    "sg:province":"CO",
    "sg:tags":[
        "transmission"
    ],
    "wof:name":"J C Transmission",
    "wof:placetype":"venue"
},
  "geometry": {"coordinates":[-105.07737299999999,40.465552],"type":"Point"}
}