{
  "type": "Feature",
  "properties": {
    "addr:full":"1283 S Vance St Denver CO 80232",
    "addr:housenumber":"1283",
    "addr:postcode":"80232",
    "addr:street":"S Vance St",
    "iso:country":"US",
    "sg:address":"1283 S Vance St",
    "sg:city":"Denver",
    "sg:classifiers":[
        {
            "category":"Shopping",
            "subcategory":"Gifts & Souvenirs",
            "type":"Retail Goods"
        }
    ],
    "sg:phone":"+1 303 986 1705",
    "sg:postcode":"80232",
    "sg:province":"CO",
    "wof:name":"Best Friends Baskets",
    "wof:placetype":"venue"
},
  "geometry": {"coordinates":[-105.07949499999999,39.69336],"type":"Point"}
}