{
  "type": "Feature",
  "properties": {
    "iso:country":"US",
    "sg:address":"3425 Eliot St",
    "sg:city":"Denver",
    "sg:classifiers":[
        {
            "category":"Building & Trades",
            "subcategory":"Landscaping Services",
            "type":"Services"
        }
    ],
    "sg:phone":"+1 303 477 7741",
    "sg:postcode":"80211",
    "sg:province":"CO",
    "sg:tags":[
        "landscape"
    ],
    "wof:name":"Blue Lotus Design Inc",
    "wof:placetype":"venue"
},
  "geometry": {"coordinates":[-105.023695,39.765327],"type":"Point"}
}