{
  "type": "Feature",
  "properties": {
    "iso:country":"US",
    "sg:address":"5817 N Nevada Ave",
    "sg:city":"Colorado Springs",
    "sg:classifiers":[
        {
            "category":"Autos & Motor Vehicles",
            "subcategory":"Recreational Vehicle Sales",
            "type":"Retail Goods"
        }
    ],
    "sg:phone":"+1 719 382 6630",
    "sg:postcode":"80918",
    "sg:province":"CO",
    "wof:name":"K & C R V",
    "wof:placetype":"venue"
},
  "geometry": {"coordinates":[-104.81478199999999,38.917755],"type":"Point"}
}