{
  "type": "Feature",
  "properties": {
    "addr:full":"274 Co Hwy 4115 Granby CO 80446",
    "addr:housenumber":"274",
    "addr:postcode":"4115;80446",
    "addr:street":"Co Hwy",
    "iso:country":"US",
    "sg:address":"274 Co Hwy 4115",
    "sg:city":"Granby",
    "sg:classifiers":[
        {
            "category":"Arts & Performance",
            "subcategory":"Theater",
            "type":"Entertainment"
        }
    ],
    "sg:phone":"+1 970 887 1488",
    "sg:postcode":"80446",
    "sg:province":"CO",
    "sg:tags":[
        "live",
        "music"
    ],
    "wof:name":"F & P Loomis",
    "wof:placetype":"venue"
},
  "geometry": {"coordinates":[-105.95914399999999,40.200835],"type":"Point"}
}