{
  "type": "Feature",
  "properties": {
    "iso:country":"US",
    "sg:address":"5 Mountain Birch",
    "sg:city":"Littleton",
    "sg:classifiers":[
        {
            "category":"Professional",
            "subcategory":"Accounting & Tax Preparation",
            "type":"Services"
        }
    ],
    "sg:phone":"+1 303 904 8703",
    "sg:postcode":"80127",
    "sg:province":"CO",
    "sg:tags":[
        "accountant"
    ],
    "wof:name":"Harris & Assoc PC",
    "wof:placetype":"venue"
},
  "geometry": {"coordinates":[-105.168566,39.586617],"type":"Point"}
}