{
  "type": "Feature",
  "properties": {
    "iso:country":"US",
    "sg:address":"1425 10th Ave",
    "sg:city":"Longmont",
    "sg:classifiers":[
        {
            "category":"Building & Trades",
            "subcategory":"Construction",
            "type":"Services"
        }
    ],
    "sg:phone":"+1 303 413 1896",
    "sg:postcode":"80501",
    "sg:province":"CO",
    "sg:tags":[
        "contractor"
    ],
    "wof:name":"G M B Metal Fabrication Co",
    "wof:placetype":"venue"
},
  "geometry": {"coordinates":[-105.116444,40.17575],"type":"Point"}
}