{
  "type": "Feature",
  "properties": {
    "iso:country":"US",
    "sg:address":"1900 Boise Ave",
    "sg:city":"Loveland",
    "sg:classifiers":[
        {
            "category":"Health Services",
            "subcategory":"Doctor",
            "type":"Services"
        }
    ],
    "sg:phone":"+1 970 669 0470",
    "sg:postcode":"80538",
    "sg:province":"CO",
    "sg:tags":[
        "medical"
    ],
    "wof:name":"Turner Donn M MD",
    "wof:placetype":"venue"
},
  "geometry": {"coordinates":[-105.05363199999999,40.414176],"type":"Point"}
}