{
  "type": "Feature",
  "properties": {
    "iso:country":"US",
    "sg:address":"1777 S Bellaire St",
    "sg:city":"Denver",
    "sg:classifiers":[
        {
            "category":"Education",
            "subcategory":"Vocational School",
            "type":"Public Place"
        }
    ],
    "sg:phone":"+1 303 757 7768",
    "sg:postcode":"80222",
    "sg:province":"CO",
    "sg:tags":[
        "training",
        "computer"
    ],
    "wof:name":"Scofield Business Svc",
    "wof:placetype":"venue"
},
  "geometry": {"coordinates":[-104.937399,39.684658],"type":"Point"}
}