{
  "type": "Feature",
  "properties": {
    "iso:country":"US",
    "sg:address":"1500 Main St",
    "sg:city":"Springfield",
    "sg:classifiers":[
        {
            "category":"Retail",
            "subcategory":"Veterinary Services",
            "type":"Services"
        }
    ],
    "sg:phone":"+1 719 523 6828",
    "sg:postcode":"81073",
    "sg:province":"CO",
    "sg:tags":[
        "veterinarian"
    ],
    "wof:name":"Southeast Colorado Veterinary",
    "wof:placetype":"venue"
},
  "geometry": {"coordinates":[-102.616518,37.398509],"type":"Point"}
}