{
  "type": "Feature",
  "properties": {
    "addr:full":"7198 W Frost Dr Littleton CO 80128",
    "addr:housenumber":"7198",
    "addr:postcode":"80128",
    "addr:street":"W Frost Dr",
    "iso:country":"US",
    "sg:address":"7198 W Frost Dr",
    "sg:city":"Littleton",
    "sg:classifiers":[
        {
            "category":"Autos & Motor Vehicles",
            "subcategory":"Automobile Sales",
            "type":"Retail Goods"
        }
    ],
    "sg:phone":"+1 303 973 7442",
    "sg:postcode":"80128",
    "sg:province":"CO",
    "sg:tags":[
        "used"
    ],
    "wof:name":"Currie Motors Inc",
    "wof:placetype":"venue"
},
  "geometry": {"coordinates":[-105.076994,39.585391],"type":"Point"}
}