{
  "type": "Feature",
  "properties": {
    "iso:country":"US",
    "sg:address":"7050 W Polk Pl",
    "sg:city":"Littleton",
    "sg:classifiers":[
        {
            "category":"Banks & Credit Unions",
            "subcategory":"Bank",
            "type":"Services"
        }
    ],
    "sg:phone":"+1 303 973 9719",
    "sg:postcode":"80123",
    "sg:province":"CO",
    "sg:tags":[
        "broker",
        "mortgage"
    ],
    "wof:name":"Chatfield Mortgage",
    "wof:placetype":"venue"
},
  "geometry": {"coordinates":[-105.076752,39.600591],"type":"Point"}
}