{
  "type": "Feature",
  "properties": {
    "iso:country":"US",
    "sg:address":"5417 Foothills Dr",
    "sg:city":"Berthoud",
    "sg:classifiers":[
        {
            "category":"Building & Trades",
            "subcategory":"Construction",
            "type":"Services"
        }
    ],
    "sg:phone":"+1 303 939 3243",
    "sg:postcode":"80513",
    "sg:province":"CO",
    "sg:tags":[
        "family",
        "general"
    ],
    "wof:name":"Pioneer General Cnstr LLC",
    "wof:placetype":"venue"
},
  "geometry": {"coordinates":[-105.17160699999999,40.289439],"type":"Point"}
}