{
  "type": "Feature",
  "properties": {
    "addr:full":"12632 Patton St Broomfield CO 80020",
    "addr:housenumber":"12632",
    "addr:postcode":"80020",
    "addr:street":"Patton St",
    "iso:country":"US",
    "sg:address":"12632 Patton St",
    "sg:city":"Broomfield",
    "sg:classifiers":[
        {
            "category":"Wholesale",
            "subcategory":"Construction Materials",
            "type":"Manufacturing & Wholesale Goods"
        }
    ],
    "sg:phone":"+1 720 887 8078",
    "sg:postcode":"80020",
    "sg:province":"CO",
    "wof:name":"A Keene View Windows",
    "wof:placetype":"venue"
},
  "geometry": {"coordinates":[-105.03922799999999,39.926402],"type":"Point"}
}