{
  "type": "Feature",
  "properties": {
    "addr:full":"810 Ranchette Pl Calhan CO 80808",
    "addr:housenumber":"810",
    "addr:postcode":"80808",
    "addr:street":"Ranchette Pl",
    "iso:country":"US",
    "sg:address":"810 Ranchette Pl",
    "sg:city":"Calhan",
    "sg:classifiers":[
        {
            "category":"Farming",
            "subcategory":"Livestock Farm",
            "type":"Manufacturing & Wholesale Goods"
        }
    ],
    "sg:phone":"+1 719 683 5023",
    "sg:postcode":"80808",
    "sg:province":"CO",
    "sg:tags":[
        "trail",
        "outfitter"
    ],
    "wof:name":"Cal-Elli Llamas",
    "wof:placetype":"venue"
},
  "geometry": {"coordinates":[-104.440071,38.845265],"type":"Point"}
}