{
  "type": "Feature",
  "properties": {
    "iso:country":"US",
    "sg:address":"1301 S Jason Street",
    "sg:city":"Denver",
    "sg:classifiers":[
        {
            "category":"Building & Trades",
            "subcategory":"Construction",
            "type":"Services"
        }
    ],
    "sg:phone":"+1 303 777 1337",
    "sg:postcode":"80223",
    "sg:province":"CO",
    "sg:tags":[
        "contractor"
    ],
    "wof:name":"Barnett",
    "wof:placetype":"venue"
},
  "geometry": {"coordinates":[-104.999199,39.693073],"type":"Point"}
}