{
  "type": "Feature",
  "properties": {
    "iso:country":"US",
    "sg:address":"7417 Grandview Ave",
    "sg:city":"Arvada",
    "sg:classifiers":[
        {
            "category":"Wholesale",
            "subcategory":"Durable Goods & Equipment",
            "type":"Manufacturing & Wholesale Goods"
        }
    ],
    "sg:phone":"+1 303 940 3440",
    "sg:postcode":"80002",
    "sg:province":"CO",
    "sg:tags":[
        "importer"
    ],
    "wof:name":"LA Casita Imports",
    "wof:placetype":"venue"
},
  "geometry": {"coordinates":[-105.07996199999999,39.799452],"type":"Point"}
}