{
  "type": "Feature",
  "properties": {
    "iso:country":"US",
    "sg:address":"14748 Quebec St",
    "sg:city":"Brighton",
    "sg:classifiers":[
        {
            "category":"Building & Trades",
            "subcategory":"Construction",
            "type":"Services"
        }
    ],
    "sg:phone":"+1 303 478 1863",
    "sg:postcode":"80602",
    "sg:province":"CO",
    "sg:tags":[
        "general",
        "contractor"
    ],
    "wof:name":"Regis Construction Inc",
    "wof:placetype":"venue"
},
  "geometry": {"coordinates":[-104.90283100000001,39.967272],"type":"Point"}
}