{
  "type": "Feature",
  "properties": {
    "addr:full":"2309 Pelota Dr Cortez CO 81321",
    "addr:housenumber":"2309",
    "addr:postcode":"81321",
    "addr:street":"Pelota Dr",
    "iso:country":"US",
    "sg:address":"2309 Pelota Dr",
    "sg:city":"Cortez",
    "sg:classifiers":[
        {
            "category":"Airport",
            "type":"Transportation"
        }
    ],
    "sg:phone":"+1 970 564 8484",
    "sg:postcode":"81321",
    "sg:province":"CO",
    "sg:tags":[
        "light",
        "lane",
        "work",
        "maintenance"
    ],
    "wof:name":"Aircraft Visual Guidance Inc",
    "wof:placetype":"venue"
},
  "geometry": {"coordinates":[-108.55519099999999,37.368494],"type":"Point"}
}