{
  "type": "Feature",
  "properties": {
    "iso:country":"US",
    "sg:address":"745 E Jefferson Ave",
    "sg:city":"Hayden",
    "sg:classifiers":[
        {
            "category":"Shopping",
            "subcategory":"Florist",
            "type":"Retail Goods"
        }
    ],
    "sg:phone":"+1 970 276 3065",
    "sg:postcode":"81639",
    "sg:province":"CO",
    "wof:name":"Timberline Candy Bouquet",
    "wof:placetype":"venue"
},
  "geometry": {"coordinates":[-107.24877499999999,40.49709],"type":"Point"}
}