{
  "type": "Feature",
  "properties": {
    "addr:full":"11600 E 51st Ave Denver CO 80239",
    "addr:housenumber":"11600",
    "addr:postcode":"80239",
    "addr:street":"E 51St Ave",
    "iso:country":"US",
    "sg:address":"11600 E 51st Ave",
    "sg:city":"Denver",
    "sg:classifiers":[
        {
            "category":"Manufacturing",
            "subcategory":"Rubber & Plastics",
            "type":"Manufacturing & Wholesale Goods"
        }
    ],
    "sg:phone":"+1 303 922 5563",
    "sg:postcode":"80239",
    "sg:province":"CO",
    "sg:website":"www.formtight.thomasregister.com",
    "wof:name":"FORM Tight",
    "wof:placetype":"venue"
},
  "geometry": {"coordinates":[-104.853633,39.790257],"type":"Point"}
}