{
  "type": "Feature",
  "properties": {
    "iso:country":"US",
    "sg:address":"2615 Commercial Way",
    "sg:city":"Rock Springs",
    "sg:classifiers":[
        {
            "category":"Travel",
            "subcategory":"Hotels & Motels",
            "type":"Entertainment"
        }
    ],
    "sg:phone":"+1 307 362 1850",
    "sg:postcode":"82901",
    "sg:province":"CO",
    "sg:tags":[
        "operation"
    ],
    "wof:name":"Motel 6",
    "wof:placetype":"venue"
},
  "geometry": {"coordinates":[-109.25532699999999,41.582031],"type":"Point"}
}