{
  "type": "Feature",
  "properties": {
    "iso:country":"US",
    "sg:address":"650 S Wadsworth Boulevard",
    "sg:city":"Lakewood",
    "sg:classifiers":[
        {
            "category":"Shopping",
            "subcategory":"Stationery & Office Supplies",
            "type":"Retail Goods"
        },
        {
            "category":"Wholesale",
            "subcategory":"Computers",
            "type":"Manufacturing & Wholesale Goods"
        }
    ],
    "sg:phone":"+1 303 727 8808",
    "sg:postcode":"80226",
    "sg:province":"CO",
    "sg:tags":[
        "equipment"
    ],
    "sg:website":"www.officedepot.com",
    "wof:name":"Office Depot",
    "wof:placetype":"venue"
},
  "geometry": {"coordinates":[-105.081529,39.70468],"type":"Point"}
}