{
  "type": "Feature",
  "properties": {
    "addr:full":"4705 Eugene Way Denver CO 80239",
    "addr:housenumber":"4705",
    "addr:postcode":"80239",
    "addr:street":"Eugene Way",
    "iso:country":"US",
    "sg:address":"4705 Eugene Way",
    "sg:city":"Denver",
    "sg:classifiers":[
        {
            "category":"Building & Trades",
            "subcategory":"Cleaning & Sanitation",
            "type":"Services"
        }
    ],
    "sg:phone":"+1 303 371 2632",
    "sg:postcode":"80239",
    "sg:province":"CO",
    "sg:tags":[
        "janitor"
    ],
    "wof:name":"Dave's Cleaning Svc",
    "wof:placetype":"venue"
},
  "geometry": {"coordinates":[-104.816863,39.779821],"type":"Point"}
}