{
  "type": "Feature",
  "properties": {
    "addr:full":"6328 S Turkey Creek Rd Morrison CO 80465",
    "addr:housenumber":"6328",
    "addr:postcode":"80465",
    "addr:street":"S Turkey Creek Rd",
    "iso:country":"US",
    "sg:address":"6328 S Turkey Creek Rd",
    "sg:city":"Morrison",
    "sg:classifiers":[
        {
            "category":"Autos & Motor Vehicles",
            "subcategory":"Fuel & Gas Station",
            "type":"Retail Goods"
        }
    ],
    "sg:phone":"+1 303 697 0559",
    "sg:postcode":"80465",
    "sg:province":"CO",
    "sg:tags":[
        "convenience",
        "station",
        "store"
    ],
    "wof:name":"Little Log Store",
    "wof:placetype":"venue"
},
  "geometry": {"coordinates":[-105.222919,39.602367],"type":"Point"}
}