{
  "type": "Feature",
  "properties": {
    "addr:full":"114 N 7th St Canon City CO 81212",
    "addr:housenumber":"114",
    "addr:postcode":"81212",
    "addr:street":"N 7Th St",
    "iso:country":"US",
    "sg:address":"114 N 7th St",
    "sg:city":"Canon City",
    "sg:classifiers":[
        {
            "category":"Insurance",
            "subcategory":"Insurance Agent",
            "type":"Services"
        }
    ],
    "sg:phone":"+1 719 275 0409",
    "sg:postcode":"81212",
    "sg:province":"CO",
    "wof:name":"Kens Insurance Agency",
    "wof:placetype":"venue"
},
  "geometry": {"coordinates":[-105.238304,38.442112],"type":"Point"}
}