{
  "type": "Feature",
  "properties": {
    "iso:country":"US",
    "sg:address":"29114 Co Rd 47",
    "sg:city":"Burlington",
    "sg:phone":"+1 719 346 7503",
    "sg:postcode":"80807",
    "sg:province":"CO",
    "sg:tags":[
        "farm",
        "wheat"
    ],
    "wof:name":"Smith Farms",
    "wof:placetype":"venue"
},
  "geometry": {"coordinates":[-102.296497,39.472489],"type":"Point"}
}