{
  "type": "Feature",
  "properties": {
    "iso:country":"US",
    "sg:address":"2409 E Pikes Peak Ave",
    "sg:city":"Colorado Springs",
    "sg:classifiers":[
        {
            "category":"Travel",
            "subcategory":"Hotels & Motels",
            "type":"Entertainment"
        }
    ],
    "sg:phone":"+1 719 471 0990",
    "sg:postcode":"80909",
    "sg:province":"CO",
    "sg:website":"www.rodewayinn.com",
    "wof:name":"Rodeway Inn",
    "wof:placetype":"venue"
},
  "geometry": {"coordinates":[-104.784857,38.832551],"type":"Point"}
}