{
  "type": "Feature",
  "properties": {
    "iso:country":"US",
    "sg:address":"2018 Columbine Ave",
    "sg:city":"Boulder",
    "sg:classifiers":[
        {
            "category":"Building & Trades",
            "subcategory":"Construction",
            "type":"Services"
        }
    ],
    "sg:phone":"+1 720 565 0423",
    "sg:postcode":"80302",
    "sg:province":"CO",
    "sg:tags":[
        "house"
    ],
    "wof:name":"Muller Construction",
    "wof:placetype":"venue"
},
  "geometry": {"coordinates":[-105.26689,39.999062],"type":"Point"}
}