{
  "type": "Feature",
  "properties": {
    "addr:full":"11154 N Donley Dr Parker CO 80138",
    "addr:housenumber":"11154",
    "addr:postcode":"80138",
    "addr:street":"N Donley Dr",
    "iso:country":"US",
    "sg:address":"11154 N Donley Dr",
    "sg:city":"Parker",
    "sg:classifiers":[
        {
            "category":"Wholesale",
            "subcategory":"Non-durable Goods",
            "type":"Manufacturing & Wholesale Goods"
        }
    ],
    "sg:phone":"+1 303 840 2493",
    "sg:postcode":"80138",
    "sg:province":"CO",
    "wof:name":"Jerl Mc Kinney Enterprises Inc",
    "wof:placetype":"venue"
},
  "geometry": {"coordinates":[-104.761689,39.523565],"type":"Point"}
}