{
  "type": "Feature",
  "properties": {
    "addr:full":"506 E Moreno Ave Colorado Springs CO 80903",
    "addr:housenumber":"506",
    "addr:postcode":"80903",
    "addr:street":"E Moreno Ave",
    "iso:country":"US",
    "sg:address":"506 E Moreno Ave",
    "sg:city":"Colorado Springs",
    "sg:classifiers":[
        {
            "category":"Social Services",
            "subcategory":"Child Care",
            "type":"Services"
        }
    ],
    "sg:phone":"+1 719 471 1930",
    "sg:postcode":"80903",
    "sg:province":"CO",
    "sg:tags":[
        "day"
    ],
    "wof:name":"Urban League Child Care Center",
    "wof:placetype":"venue"
},
  "geometry": {"coordinates":[-104.815685,38.825624],"type":"Point"}
}