{
  "type": "Feature",
  "properties": {
    "addr:full":"26714 State Hwy 17 Antonito CO 81120",
    "addr:housenumber":"26714",
    "addr:postcode":"81120",
    "addr:street":"State Hwy 17 Antonito",
    "iso:country":"US",
    "sg:address":"26714 State Hwy 17",
    "sg:city":"Antonito",
    "sg:classifiers":[
        {
            "category":"Travel",
            "subcategory":"Campground",
            "type":"Entertainment"
        }
    ],
    "sg:phone":"+1 719 376 5943",
    "sg:postcode":"81120",
    "sg:province":"CO",
    "wof:name":"Conejos River Campground",
    "wof:placetype":"venue"
},
  "geometry": {"coordinates":[-106.218025,37.067707],"type":"Point"}
}