{
  "type": "Feature",
  "properties": {
    "iso:country":"US",
    "sg:address":"336 E Elkhorn Ave",
    "sg:city":"Estes Park",
    "sg:classifiers":[
        {
            "category":"Food & Beverages",
            "subcategory":"Specialty",
            "type":"Retail Goods"
        }
    ],
    "sg:phone":"+1 970 586 2798",
    "sg:postcode":"80517",
    "sg:province":"CO",
    "sg:tags":[
        "gourmet",
        "shop"
    ],
    "wof:name":"A LA Carte Gourmet Shop",
    "wof:placetype":"venue"
},
  "geometry": {"coordinates":[-105.518553,40.377218],"type":"Point"}
}