{
  "type": "Feature",
  "properties": {
    "iso:country":"US",
    "sg:address":"3204 Pierson St",
    "sg:city":"Wheat Ridge",
    "sg:classifiers":[
        {
            "category":"Manufacturing",
            "subcategory":"Printing",
            "type":"Manufacturing & Wholesale Goods"
        }
    ],
    "sg:phone":"+1 303 235 0606",
    "sg:postcode":"80033",
    "sg:province":"CO",
    "sg:tags":[
        "lithographic",
        "commercial"
    ],
    "wof:name":"Linear Printing Pubg & Mus",
    "wof:placetype":"venue"
},
  "geometry": {"coordinates":[-105.12250400000001,39.763661],"type":"Point"}
}