{
  "type": "Feature",
  "properties": {
    "iso:country":"US",
    "sg:address":"15 Molas Dr",
    "sg:city":"Durango",
    "sg:classifiers":[
        {
            "category":"Building & Trades",
            "subcategory":"Electrical",
            "type":"Services"
        }
    ],
    "sg:phone":"+1 970 375 0013",
    "sg:postcode":"81301",
    "sg:province":"CO",
    "sg:tags":[
        "electrical",
        "contractor"
    ],
    "wof:name":"Omega Electric & Lighting In",
    "wof:placetype":"venue"
},
  "geometry": {"coordinates":[-107.852233,37.281712],"type":"Point"}
}