{
  "type": "Feature",
  "properties": {
    "addr:full":"134 Colorado Ave Stratton CO 80836",
    "addr:housenumber":"134",
    "addr:postcode":"80836",
    "addr:street":"Colorado Ave",
    "iso:country":"US",
    "sg:address":"134 Colorado Ave",
    "sg:city":"Stratton",
    "sg:classifiers":[
        {
            "category":"Home & Garden",
            "subcategory":"Carpets & Floor Coverings",
            "type":"Retail Goods"
        }
    ],
    "sg:phone":"+1 719 348 5547",
    "sg:postcode":"80836",
    "sg:province":"CO",
    "sg:tags":[
        "dealer",
        "rug"
    ],
    "wof:name":"Gambles",
    "wof:placetype":"venue"
},
  "geometry": {"coordinates":[-102.605042,39.305631],"type":"Point"}
}