{
  "type": "Feature",
  "properties": {
    "addr:full":"4001 Holly Street Suite 17 Denver CO 80216",
    "addr:housenumber":"4001;17",
    "addr:postcode":"80216",
    "addr:street":"Holly Street Suite",
    "iso:country":"US",
    "sg:address":"4001 Holly Street Suite 17",
    "sg:city":"Denver",
    "sg:classifiers":[
        {
            "category":"Shopping",
            "subcategory":"Crafts & Fabrics",
            "type":"Retail Goods"
        }
    ],
    "sg:phone":"+1 303 355 8543",
    "sg:postcode":"80216",
    "sg:province":"CO",
    "sg:tags":[
        "art",
        "supply"
    ],
    "sg:website":"www.arthardware.com",
    "wof:name":"Art Hardware",
    "wof:placetype":"venue"
},
  "geometry": {"coordinates":[-104.922296,39.771048],"type":"Point"}
}