{
  "type": "Feature",
  "properties": {
    "iso:country":"US",
    "sg:address":"711 Open Sky Ter",
    "sg:city":"Pueblo",
    "sg:classifiers":[
        {
            "category":"Retail",
            "subcategory":"Veterinary Services",
            "type":"Services"
        }
    ],
    "sg:phone":"+1 719 545 7936",
    "sg:postcode":"81006",
    "sg:province":"CO",
    "sg:tags":[
        "veterinarian"
    ],
    "wof:name":"Veterinary House Call Svc",
    "wof:placetype":"venue"
},
  "geometry": {"coordinates":[-104.544332,38.257356],"type":"Point"}
}