{
  "type": "Feature",
  "properties": {
    "iso:country":"US",
    "sg:address":"615 E South Boulder Rd",
    "sg:city":"Louisville",
    "sg:classifiers":[
        {
            "category":"Shopping",
            "subcategory":"Clothing, Apparel, & Fashions",
            "type":"Retail Goods"
        }
    ],
    "sg:phone":"+1 303 664 9200",
    "sg:postcode":"80027",
    "sg:province":"CO",
    "wof:name":"Albas Alterations",
    "wof:placetype":"venue"
},
  "geometry": {"coordinates":[-105.13507199999999,39.987072],"type":"Point"}
}