{
  "type": "Feature",
  "properties": {
    "addr:full":"1415 15th St Denver CO 80202",
    "addr:housenumber":"1415",
    "addr:postcode":"80202",
    "addr:street":"15Th St",
    "iso:country":"US",
    "sg:address":"1415 15th St",
    "sg:city":"Denver",
    "sg:classifiers":[
        {
            "category":"Restaurant",
            "type":"Food & Drink"
        }
    ],
    "sg:menulink":"http://www.allmenus.com/co/denver/6695-pf-changs/menu/",
    "sg:phone":"+1 303 260 7222",
    "sg:postcode":"80202",
    "sg:province":"CO",
    "sg:tags":[
        "japanese",
        "chinese",
        "asian"
    ],
    "wof:name":"P.F. Chang's",
    "wof:placetype":"venue"
},
  "geometry": {"coordinates":[-104.99965899999999,39.749052],"type":"Point"}
}