{
  "type": "Feature",
  "properties": {
    "iso:country":"US",
    "sg:address":"1005 S Upham St",
    "sg:city":"Denver",
    "sg:classifiers":[
        {
            "category":"Professional",
            "type":"Services"
        }
    ],
    "sg:phone":"+1 303 936 5322",
    "sg:postcode":"80226",
    "sg:province":"CO",
    "wof:name":"Randy Dirks",
    "wof:placetype":"venue"
},
  "geometry": {"coordinates":[-105.078361,39.69831],"type":"Point"}
}