{
  "type": "Feature",
  "properties": {
    "iso:country":"US",
    "sg:address":"5186 Youngfield Ct",
    "sg:city":"Arvada",
    "sg:classifiers":[
        {
            "category":"Building & Trades",
            "subcategory":"Construction",
            "type":"Services"
        }
    ],
    "sg:phone":"+1 303 940 6846",
    "sg:postcode":"80002",
    "sg:province":"CO",
    "sg:tags":[
        "remodeling"
    ],
    "wof:name":"Jakobs Kustom Homes Inc",
    "wof:placetype":"venue"
},
  "geometry": {"coordinates":[-105.143066,39.789514],"type":"Point"}
}