{
  "type": "Feature",
  "properties": {
    "iso:country":"US",
    "sg:address":"234 Lincoln Street",
    "sg:city":"Denver",
    "sg:classifiers":[
        {
            "category":"Real Estate",
            "subcategory":"Real Estate Operator",
            "type":"Services"
        }
    ],
    "sg:phone":"+1 303 744 9544",
    "sg:postcode":"80203",
    "sg:province":"CO",
    "sg:tags":[
        "apartment"
    ],
    "wof:name":"Lincoln Plaza Apartments",
    "wof:placetype":"venue"
},
  "geometry": {"coordinates":[-104.986217,39.719917],"type":"Point"}
}