{
  "type": "Feature",
  "properties": {
    "addr:full":"9520 E Colfax Ave Aurora CO 80010",
    "addr:housenumber":"9520",
    "addr:postcode":"80010",
    "addr:street":"E Colfax Ave",
    "iso:country":"US",
    "sg:address":"9520 E Colfax Ave",
    "sg:city":"Aurora",
    "sg:classifiers":[
        {
            "category":"Shopping",
            "subcategory":"Used Merchandise",
            "type":"Retail Goods"
        }
    ],
    "sg:phone":"+1 303 340 4461",
    "sg:postcode":"80010",
    "sg:province":"CO",
    "sg:tags":[
        "pawnbroker"
    ],
    "wof:name":"EZ Pawn Inc",
    "wof:placetype":"venue"
},
  "geometry": {"coordinates":[-104.87717600000001,39.740135],"type":"Point"}
}