{
  "type": "Feature",
  "properties": {
    "iso:country":"US",
    "sg:address":"308 W Elkhorn Ave",
    "sg:city":"Estes Park",
    "sg:classifiers":[
        {
            "category":"Professional",
            "type":"Services"
        }
    ],
    "sg:phone":"+1 970 577 7069",
    "sg:postcode":"80517",
    "sg:province":"CO",
    "wof:name":"Fantasy Tech",
    "wof:placetype":"venue"
},
  "geometry": {"coordinates":[-105.52724499999999,40.376355],"type":"Point"}
}