{
  "type": "Feature",
  "properties": {
    "addr:full":"645 Autumn Crest Cir Colorado Springs CO 80919",
    "addr:housenumber":"645",
    "addr:postcode":"80919",
    "addr:street":"Autumn Crest Cir",
    "iso:country":"US",
    "sg:address":"645 Autumn Crest Cir",
    "sg:city":"Colorado Springs",
    "sg:classifiers":[
        {
            "category":"Banks & Credit Unions",
            "subcategory":"Bank",
            "type":"Services"
        }
    ],
    "sg:phone":"+1 719 559 0543",
    "sg:postcode":"80919",
    "sg:province":"CO",
    "sg:tags":[
        "mortgage"
    ],
    "wof:name":"All About Mortgages",
    "wof:placetype":"venue"
},
  "geometry": {"coordinates":[-104.837552,38.905937],"type":"Point"}
}