{
  "type": "Feature",
  "properties": {
    "iso:country":"US",
    "sg:address":"8822 W Stanford Ave",
    "sg:city":"Littleton",
    "sg:classifiers":[
        {
            "category":"Manufacturing",
            "subcategory":"Tools & Machinery",
            "type":"Manufacturing & Wholesale Goods"
        }
    ],
    "sg:phone":"+1 303 978 1290",
    "sg:postcode":"80123",
    "sg:province":"CO",
    "sg:tags":[
        "machine",
        "mfg"
    ],
    "wof:name":"Louies Little Forge Inc",
    "wof:placetype":"venue"
},
  "geometry": {"coordinates":[-105.096684,39.634674],"type":"Point"}
}