{
  "type": "Feature",
  "properties": {
    "addr:full":"3635 W 100th Ave Westminster CO 80031",
    "addr:housenumber":"3635",
    "addr:postcode":"80031",
    "addr:street":"W 100Th Ave",
    "iso:country":"US",
    "sg:address":"3635 W 100th Ave",
    "sg:city":"Westminster",
    "sg:classifiers":[
        {
            "category":"Wholesale",
            "subcategory":"Electrical",
            "type":"Manufacturing & Wholesale Goods"
        }
    ],
    "sg:phone":"+1 303 438 5514",
    "sg:postcode":"80031",
    "sg:province":"CO",
    "sg:tags":[
        "wholesaler",
        "equipment",
        "parts",
        "electronic",
        "for"
    ],
    "wof:name":"Mc Rae & Associates",
    "wof:placetype":"venue"
},
  "geometry": {"coordinates":[-105.03607599999999,39.878441],"type":"Point"}
}