{
  "type": "Feature",
  "properties": {
    "iso:country":"US",
    "sg:address":"928 Cherokee Ave",
    "sg:city":"Fort Morgan",
    "sg:classifiers":[
        {
            "category":"Social Services",
            "subcategory":"Child Care",
            "type":"Services"
        }
    ],
    "sg:phone":"+1 970 867 2733",
    "sg:postcode":"80701",
    "sg:province":"CO",
    "wof:name":"Teena's Day Care",
    "wof:placetype":"venue"
},
  "geometry": {"coordinates":[-103.814329,40.241198],"type":"Point"}
}