{
  "type": "Feature",
  "properties": {
    "iso:country":"US",
    "sg:address":"2075 S. University Blvd",
    "sg:city":"Denver",
    "sg:classifiers":[
        {
            "category":"Food & Beverages",
            "subcategory":"Bakery",
            "type":"Retail Goods"
        }
    ],
    "sg:phone":"+1 303 282 7300",
    "sg:postcode":"80210",
    "sg:province":"CO",
    "sg:tags":[
        "sandwich"
    ],
    "wof:name":"Jimmy Johns",
    "wof:placetype":"venue"
},
  "geometry": {"coordinates":[-104.959767,39.679143],"type":"Point"}
}