{
  "type": "Feature",
  "properties": {
    "addr:full":"4375 Prairie Rose Cir Castle Rock CO 80109",
    "addr:housenumber":"4375",
    "addr:postcode":"80109",
    "addr:street":"Prairie Rose Cir",
    "iso:country":"US",
    "sg:address":"4375 Prairie Rose Cir",
    "sg:city":"Castle Rock",
    "sg:classifiers":[
        {
            "category":"Professional",
            "subcategory":"Computer Services",
            "type":"Services"
        }
    ],
    "sg:phone":"+1 303 688 8556",
    "sg:postcode":"80109",
    "sg:province":"CO",
    "sg:tags":[
        "repair"
    ],
    "wof:name":"Physician Computer Service",
    "wof:placetype":"venue"
},
  "geometry": {"coordinates":[-104.908923,39.391345],"type":"Point"}
}