{
  "type": "Feature",
  "properties": {
    "iso:country":"US",
    "sg:address":"458 W Pin High Dr",
    "sg:city":"Pueblo West",
    "sg:classifiers":[
        {
            "category":"Building & Trades",
            "subcategory":"Construction",
            "type":"Services"
        }
    ],
    "sg:phone":"+1 719 547 2547",
    "sg:postcode":"81007",
    "sg:province":"CO",
    "sg:tags":[
        "general",
        "contractor"
    ],
    "sg:website":"www.sperahomes.com",
    "wof:name":"Spera Homes Inc",
    "wof:placetype":"venue"
},
  "geometry": {"coordinates":[-104.757814,38.319594],"type":"Point"}
}