{
  "type": "Feature",
  "properties": {
    "iso:country":"US",
    "sg:address":"6164 S Lee St",
    "sg:city":"Littleton",
    "sg:classifiers":[
        {
            "category":"Banks & Credit Unions",
            "subcategory":"Bank",
            "type":"Services"
        }
    ],
    "sg:phone":"+1 720 981 9170",
    "sg:postcode":"80127",
    "sg:province":"CO",
    "sg:tags":[
        "loan",
        "real estate"
    ],
    "wof:name":"Colorado Mortgage Direct Inc",
    "wof:placetype":"venue"
},
  "geometry": {"coordinates":[-105.111996,39.604064],"type":"Point"}
}