{
  "type": "Feature",
  "properties": {
    "iso:country":"US",
    "sg:address":"935 Hale St",
    "sg:city":"Wray",
    "sg:classifiers":[
        {
            "category":"Freight",
            "type":"Transportation"
        }
    ],
    "sg:phone":"+1 970 332 4688",
    "sg:postcode":"80758",
    "sg:province":"CO",
    "sg:tags":[
        "operator",
        "local",
        "trucking"
    ],
    "wof:name":"Richards Trucking",
    "wof:placetype":"venue"
},
  "geometry": {"coordinates":[-102.23237399999999,40.072914],"type":"Point"}
}