{
  "type": "Feature",
  "properties": {
    "addr:full":"16528 E Prentice Pl Centennial CO 80015",
    "addr:housenumber":"16528",
    "addr:postcode":"80015",
    "addr:street":"E Prentice Pl",
    "iso:country":"US",
    "sg:address":"16528 E Prentice Pl",
    "sg:city":"Centennial",
    "sg:classifiers":[
        {
            "category":"Wholesale",
            "subcategory":"Durable Goods & Equipment",
            "type":"Manufacturing & Wholesale Goods"
        }
    ],
    "sg:phone":"+1 303 564 7100",
    "sg:postcode":"80015",
    "sg:province":"CO",
    "sg:tags":[
        "representative",
        "manufacturer"
    ],
    "wof:name":"Rooster Hill",
    "wof:placetype":"venue"
},
  "geometry": {"coordinates":[-104.795694,39.618647],"type":"Point"}
}