{
  "type": "Feature",
  "properties": {
    "iso:country":"US",
    "sg:address":"9005 Grant St",
    "sg:city":"Denver",
    "sg:classifiers":[
        {
            "category":"Health Services",
            "subcategory":"Hospital",
            "type":"Services"
        },
        {
            "category":"Health Services",
            "subcategory":"Clinic",
            "type":"Services"
        }
    ],
    "sg:phone":"+1 303 288 4694",
    "sg:postcode":"80229",
    "sg:province":"CO",
    "sg:tags":[
        "surgical",
        "center"
    ],
    "wof:name":"Musculoskeletal Surgery Center",
    "wof:placetype":"venue"
},
  "geometry": {"coordinates":[-104.982899,39.858936],"type":"Point"}
}