{
  "type": "Feature",
  "properties": {
    "iso:country":"US",
    "sg:address":"1919 E Main St",
    "sg:city":"Canon City",
    "sg:classifiers":[
        {
            "category":"Wholesale",
            "subcategory":"Motor Vehicles",
            "type":"Manufacturing & Wholesale Goods"
        },
        {
            "category":"Retail",
            "subcategory":"Auto Repair",
            "type":"Services"
        }
    ],
    "sg:phone":"+1 719 275 7028",
    "sg:postcode":"81212",
    "sg:province":"CO",
    "sg:tags":[
        "truck"
    ],
    "sg:website":"www.royalgorgetruckcenter.com",
    "wof:name":"Royal Gorge Truck Center Inc",
    "wof:placetype":"venue"
},
  "geometry": {"coordinates":[-105.21954100000001,38.446771],"type":"Point"}
}