{
  "type": "Feature",
  "properties": {
    "iso:country":"US",
    "sg:address":"1411 9th St",
    "sg:city":"Rock Springs",
    "sg:classifiers":[
        {
            "category":"Travel",
            "subcategory":"Hotels & Motels",
            "type":"Entertainment"
        }
    ],
    "sg:phone":"+1 307 362 1846",
    "sg:postcode":"82901",
    "sg:province":"CO",
    "sg:tags":[
        "operation"
    ],
    "wof:name":"Saddle Lite Motel Inc",
    "wof:placetype":"venue"
},
  "geometry": {"coordinates":[-109.209598,41.596965],"type":"Point"}
}