{
  "type": "Feature",
  "properties": {
    "addr:full":"625 E Burlington Ave Fort Morgan CO 80701",
    "addr:housenumber":"625",
    "addr:postcode":"80701",
    "addr:street":"E Burlington Ave",
    "iso:country":"US",
    "sg:address":"625 E Burlington Ave",
    "sg:city":"Fort Morgan",
    "sg:classifiers":[
        {
            "category":"Retail",
            "subcategory":"Auto Repair",
            "type":"Services"
        }
    ],
    "sg:phone":"+1 970 867 6192",
    "sg:postcode":"80701",
    "sg:province":"CO",
    "sg:tags":[
        "repairing",
        "automobile"
    ],
    "wof:name":"Medrano Auto Repair",
    "wof:placetype":"venue"
},
  "geometry": {"coordinates":[-103.79237999999999,40.246833],"type":"Point"}
}