{
  "type": "Feature",
  "properties": {
    "iso:country":"US",
    "sg:address":"109 W Main St",
    "sg:city":"Cortez",
    "sg:classifiers":[
        {
            "category":"Government",
            "subcategory":"Office",
            "type":"Public Place"
        }
    ],
    "sg:phone":"+1 970 565 3123",
    "sg:postcode":"81321",
    "sg:province":"CO",
    "sg:tags":[
        "executive"
    ],
    "wof:name":"Colorado Cooperative Extension",
    "wof:placetype":"venue"
},
  "geometry": {"coordinates":[-108.587743,37.348506],"type":"Point"}
}