{
  "type": "Feature",
  "properties": {
    "iso:country":"US",
    "sg:address":"3880 Elm St",
    "sg:city":"Denver",
    "sg:classifiers":[
        {
            "category":"Manufacturing",
            "subcategory":"Apparel",
            "type":"Manufacturing & Wholesale Goods"
        }
    ],
    "sg:phone":"+1 303 333 1761",
    "sg:postcode":"80207",
    "sg:province":"CO",
    "sg:tags":[
        "sewing",
        "contractor"
    ],
    "wof:name":"Tina Sewing",
    "wof:placetype":"venue"
},
  "geometry": {"coordinates":[-104.929256,39.770667],"type":"Point"}
}