{
  "type": "Feature",
  "properties": {
    "addr:full":"4790 Table Mesa Dr Boulder CO 80305",
    "addr:housenumber":"4790",
    "addr:postcode":"80305",
    "addr:street":"Table Mesa Dr",
    "iso:country":"US",
    "sg:address":"4790 Table Mesa Dr",
    "sg:city":"Boulder",
    "sg:classifiers":[
        {
            "category":"Professional",
            "subcategory":"Lawyer & Legal Services",
            "type":"Services"
        }
    ],
    "sg:phone":"+1 303 832 8400",
    "sg:postcode":"80305",
    "sg:province":"CO",
    "sg:tags":[
        "attorney"
    ],
    "wof:name":"James A Halpin Law Offices",
    "wof:placetype":"venue"
},
  "geometry": {"coordinates":[-105.239671,39.985686],"type":"Point"}
}