{
  "type": "Feature",
  "properties": {
    "iso:country":"US",
    "sg:address":"301 W 30th St",
    "sg:city":"Rifle",
    "sg:classifiers":[
        {
            "category":"Real Estate",
            "subcategory":"Real Estate Operator",
            "type":"Services"
        }
    ],
    "sg:phone":"+1 970 625 4669",
    "sg:postcode":"81650",
    "sg:province":"CO",
    "sg:tags":[
        "apartment"
    ],
    "wof:name":"Rimrock Apartments",
    "wof:placetype":"venue"
},
  "geometry": {"coordinates":[-107.777531,39.556743],"type":"Point"}
}