{
  "type": "Feature",
  "properties": {
    "addr:full":"814 E 19th Ave Denver CO 80218",
    "addr:housenumber":"814",
    "addr:postcode":"80218",
    "addr:street":"E 19Th Ave",
    "iso:country":"US",
    "sg:address":"814 E 19th Ave",
    "sg:city":"Denver",
    "sg:classifiers":[
        {
            "category":"Professional",
            "subcategory":"Art Services",
            "type":"Services"
        },
        {
            "category":"Professional",
            "subcategory":"Business Services",
            "type":"Services"
        }
    ],
    "sg:phone":"+1 303 832 1537",
    "sg:postcode":"80218",
    "sg:province":"CO",
    "sg:tags":[
        "development",
        "product",
        "graphic",
        "designers-industrial",
        "marketing",
        "commercial",
        "designer",
        "design"
    ],
    "sg:website":"http://www.carterdesign.com",
    "wof:name":"Carter Design Inc",
    "wof:placetype":"venue"
},
  "geometry": {"coordinates":[-104.97708900000001,39.746181],"type":"Point"}
}