{
  "type": "Feature",
  "properties": {
    "iso:country":"US",
    "sg:address":"12575 W Bayaud Ave",
    "sg:city":"Lakewood",
    "sg:classifiers":[
        {
            "category":"Organizations",
            "subcategory":"Professional Association",
            "type":"Services"
        }
    ],
    "sg:phone":"+1 303 986 2800",
    "sg:postcode":"80228",
    "sg:province":"CO",
    "sg:website":"www.aahanet.org",
    "wof:name":"American Animal Hospital Assn",
    "wof:placetype":"venue"
},
  "geometry": {"coordinates":[-105.138874,39.713905],"type":"Point"}
}