{
  "type": "Feature",
  "properties": {
    "addr:full":"3916 E Pikes Peak Ave Colorado Springs CO 80909",
    "addr:housenumber":"3916",
    "addr:postcode":"80909",
    "addr:street":"E Pikes Peak Ave",
    "iso:country":"US",
    "sg:address":"3916 E Pikes Peak Ave",
    "sg:city":"Colorado Springs",
    "sg:classifiers":[
        {
            "category":"Retail",
            "subcategory":"Laundry & Dry Cleaning",
            "type":"Services"
        }
    ],
    "sg:phone":"+1 719 574 9746",
    "sg:postcode":"80909",
    "sg:province":"CO",
    "sg:tags":[
        "cleaners",
        "rug",
        "carpet"
    ],
    "wof:name":"Liberty Carpet & Upholstery",
    "wof:placetype":"venue"
},
  "geometry": {"coordinates":[-104.7555,38.832016],"type":"Point"}
}