{
  "type": "Feature",
  "properties": {
    "iso:country":"US",
    "sg:address":"4625 E 68th Ave",
    "sg:city":"Commerce City",
    "sg:classifiers":[
        {
            "category":"Education",
            "subcategory":"School",
            "type":"Public Place"
        }
    ],
    "sg:phone":"+1 303 853 7704",
    "sg:postcode":"80022",
    "sg:province":"CO",
    "sg:tags":[
        "high"
    ],
    "wof:name":"Adams City High School",
    "wof:placetype":"venue"
},
  "geometry": {"coordinates":[-104.933533,39.820102],"type":"Point"}
}