{
  "type": "Feature",
  "properties": {
    "iso:country":"US",
    "sg:address":"12380 W 64th Ave",
    "sg:city":"Arvada",
    "sg:classifiers":[
        {
            "category":"Health Services",
            "subcategory":"Dentist",
            "type":"Services"
        }
    ],
    "sg:phone":"+1 303 421 7000",
    "sg:postcode":"80004",
    "sg:province":"CO",
    "sg:tags":[
        "dental",
        "clinic"
    ],
    "sg:website":"http://www.comfortdental.com",
    "wof:name":"Shaw, Sean, Dds - Comfort Dental",
    "wof:placetype":"venue"
},
  "geometry": {"coordinates":[-105.137654,39.812661],"type":"Point"}
}