{
  "type": "Feature",
  "properties": {
    "iso:country":"US",
    "sg:address":"326 44th Ave",
    "sg:city":"Greeley",
    "sg:classifiers":[
        {
            "category":"Professional",
            "type":"Services"
        }
    ],
    "sg:phone":"+1 970 330 1672",
    "sg:postcode":"80634",
    "sg:province":"CO",
    "wof:name":"Samson",
    "wof:placetype":"venue"
},
  "geometry": {"coordinates":[-104.75054,40.429576],"type":"Point"}
}