{
  "type": "Feature",
  "properties": {
    "addr:full":"889 E South Boulder Rd Louisville CO 80027",
    "addr:housenumber":"889 e",
    "addr:postcode":"80027",
    "addr:street":"South Boulder Rd",
    "iso:country":"US",
    "sg:address":"889 E South Boulder Rd",
    "sg:city":"Louisville",
    "sg:classifiers":[
        {
            "category":"Retail",
            "subcategory":"Veterinary Services",
            "type":"Services"
        }
    ],
    "sg:phone":"+1 303 666 4888",
    "sg:postcode":"80027",
    "sg:province":"CO",
    "wof:name":"Animal House Clinic",
    "wof:placetype":"venue"
},
  "geometry": {"coordinates":[-105.13378899999999,39.987065],"type":"Point"}
}