{
  "type": "Feature",
  "properties": {
    "addr:full":"5859 S Quintero Cir Aurora CO 80015",
    "addr:housenumber":"5859",
    "addr:postcode":"80015",
    "addr:street":"S Quintero Cir",
    "iso:country":"US",
    "sg:address":"5859 S Quintero Cir",
    "sg:city":"Aurora",
    "sg:classifiers":[
        {
            "category":"Building & Trades",
            "subcategory":"Construction",
            "type":"Services"
        }
    ],
    "sg:phone":"+1 303 680 0852",
    "sg:postcode":"80015",
    "sg:province":"CO",
    "sg:tags":[
        "contractor"
    ],
    "wof:name":"Calderon Masonry Inc",
    "wof:placetype":"venue"
},
  "geometry": {"coordinates":[-104.78869299999999,39.611237],"type":"Point"}
}