{
  "type": "Feature",
  "properties": {
    "addr:full":"5385 Hwy 348 Olathe CO 81425",
    "addr:housenumber":"5385",
    "addr:postcode":"81425",
    "addr:street":"Hwy 348",
    "iso:country":"US",
    "sg:address":"5385 Hwy 348",
    "sg:city":"Olathe",
    "sg:classifiers":[
        {
            "category":"Manufacturing",
            "subcategory":"Lumber",
            "type":"Manufacturing & Wholesale Goods"
        }
    ],
    "sg:phone":"+1 970 323 9167",
    "sg:postcode":"81425",
    "sg:province":"CO",
    "sg:tags":[
        "logging"
    ],
    "wof:name":"Crooked Creek Logging",
    "wof:placetype":"venue"
},
  "geometry": {"coordinates":[-108.058823,38.615579],"type":"Point"}
}