{
  "type": "Feature",
  "properties": {
    "iso:country":"US",
    "sg:address":"5253 E Essex Ave",
    "sg:city":"Castle Rock",
    "sg:classifiers":[
        {
            "category":"Professional",
            "type":"Services"
        }
    ],
    "sg:phone":"+1 303 660 8466",
    "sg:postcode":"80104",
    "sg:province":"CO",
    "wof:name":"Johnny Lloyd",
    "wof:placetype":"venue"
},
  "geometry": {"coordinates":[-104.80856300000001,39.365107],"type":"Point"}
}