{
  "type": "Feature",
  "properties": {
    "iso:country":"US",
    "sg:address":"517 Main St",
    "sg:city":"Walsenburg",
    "sg:classifiers":[
        {
            "category":"Professional",
            "subcategory":"Lawyer & Legal Services",
            "type":"Services"
        }
    ],
    "sg:phone":"+1 719 738 3535",
    "sg:postcode":"81089",
    "sg:province":"CO",
    "sg:tags":[
        "attorney"
    ],
    "wof:name":"Garrett Sheldon",
    "wof:placetype":"venue"
},
  "geometry": {"coordinates":[-104.781395,37.624459],"type":"Point"}
}