{
  "type": "Feature",
  "properties": {
    "addr:full":"6790 S Clermont St Centennial CO 80122",
    "addr:housenumber":"6790",
    "addr:postcode":"80122",
    "addr:street":"S Clermont St",
    "iso:country":"US",
    "sg:address":"6790 S Clermont St",
    "sg:city":"Centennial",
    "sg:classifiers":[
        {
            "category":"Banks & Credit Unions",
            "subcategory":"Bank",
            "type":"Services"
        }
    ],
    "sg:phone":"+1 720 493 4778",
    "sg:postcode":"80122",
    "sg:province":"CO",
    "sg:tags":[
        "loan",
        "real estate"
    ],
    "wof:name":"A Plus Processing Solutions",
    "wof:placetype":"venue"
},
  "geometry": {"coordinates":[-104.935468,39.592367],"type":"Point"}
}