{
  "type": "Feature",
  "properties": {
    "addr:full":"65930 Little Way Montrose CO 81401",
    "addr:housenumber":"65930",
    "addr:postcode":"81401",
    "addr:street":"Little Way",
    "iso:country":"US",
    "sg:address":"65930 Little Way",
    "sg:city":"Montrose",
    "sg:classifiers":[
        {
            "category":"Travel",
            "subcategory":"Travel Agent",
            "type":"Entertainment"
        }
    ],
    "sg:phone":"+1 970 252 9515",
    "sg:postcode":"81401",
    "sg:province":"CO",
    "sg:tags":[
        "operator",
        "tour"
    ],
    "wof:name":"Gold Hill Tours LLC",
    "wof:placetype":"venue"
},
  "geometry": {"coordinates":[-107.858367,38.505686],"type":"Point"}
}