{
  "type": "Feature",
  "properties": {
    "iso:country":"US",
    "sg:address":"2415 Lake Ave",
    "sg:city":"Pueblo",
    "sg:classifiers":[
        {
            "category":"Professional",
            "subcategory":"Business Services",
            "type":"Services"
        }
    ],
    "sg:phone":"+1 719 583 8428",
    "sg:postcode":"81004",
    "sg:province":"CO",
    "wof:name":"Nextep",
    "wof:placetype":"venue"
},
  "geometry": {"coordinates":[-104.625229,38.22605],"type":"Point"}
}