{
  "type": "Feature",
  "properties": {
    "iso:country":"US",
    "sg:address":"4705 McKinley Dr",
    "sg:city":"Boulder",
    "sg:classifiers":[
        {
            "category":"Building & Trades",
            "subcategory":"Construction",
            "type":"Services"
        }
    ],
    "sg:phone":"+1 303 447 0414",
    "sg:postcode":"80303",
    "sg:province":"CO",
    "sg:tags":[
        "general",
        "contractor"
    ],
    "wof:name":"Its Construction Inc",
    "wof:placetype":"venue"
},
  "geometry": {"coordinates":[-105.235406,40.012348],"type":"Point"}
}