{
  "type": "Feature",
  "properties": {
    "iso:country":"US",
    "sg:address":"777 S Wadsworth Blvd",
    "sg:city":"Lakewood",
    "sg:classifiers":[
        {
            "category":"Professional",
            "subcategory":"Advertising",
            "type":"Services"
        }
    ],
    "sg:phone":"+1 303 989 4614",
    "sg:postcode":"80226",
    "sg:province":"CO",
    "sg:tags":[
        "mailing",
        "shipping"
    ],
    "sg:website":"www.nationlist.com",
    "wof:name":"Nation-List Headquarters",
    "wof:placetype":"venue"
},
  "geometry": {"coordinates":[-105.08156700000001,39.70056],"type":"Point"}
}