{
  "type": "Feature",
  "properties": {
    "iso:country":"US",
    "sg:address":"7525 S Native Dancer Trl",
    "sg:city":"Evergreen",
    "sg:classifiers":[
        {
            "category":"Building & Trades",
            "subcategory":"Construction",
            "type":"Services"
        }
    ],
    "sg:phone":"+1 303 674 4676",
    "sg:postcode":"80439",
    "sg:province":"CO",
    "sg:tags":[
        "house"
    ],
    "wof:name":"Hiscorp Builder Group Inc",
    "wof:placetype":"venue"
},
  "geometry": {"coordinates":[-105.322692,39.578472],"type":"Point"}
}