{
  "type": "Feature",
  "properties": {
    "addr:full":"732 S Tejon St Colorado Springs CO 80903",
    "addr:housenumber":"732",
    "addr:postcode":"80903",
    "addr:street":"S Tejon St",
    "iso:country":"US",
    "sg:address":"732 S Tejon St",
    "sg:city":"Colorado Springs",
    "sg:classifiers":[
        {
            "category":"Home & Garden",
            "subcategory":"Household Appliances",
            "type":"Retail Goods"
        }
    ],
    "sg:phone":"+1 719 632 3508",
    "sg:postcode":"80903",
    "sg:province":"CO",
    "sg:tags":[
        "cleaners",
        "vacuum"
    ],
    "sg:website":"www.aerusonline.com",
    "wof:name":"Electrolux",
    "wof:placetype":"venue"
},
  "geometry": {"coordinates":[-104.824135,38.82355],"type":"Point"}
}