{
  "type": "Feature",
  "properties": {
    "addr:full":"409 Tia Juana St Colorado Springs CO 80909",
    "addr:housenumber":"409",
    "addr:postcode":"80909",
    "addr:street":"Tia Juana St",
    "iso:country":"US",
    "sg:address":"409 Tia Juana St",
    "sg:city":"Colorado Springs",
    "sg:classifiers":[
        {
            "category":"Building & Trades",
            "subcategory":"Construction",
            "type":"Services"
        }
    ],
    "sg:phone":"+1 719 634 1196",
    "sg:postcode":"80909",
    "sg:province":"CO",
    "sg:tags":[
        "house",
        "woodworker"
    ],
    "wof:name":"Accurate Image Co",
    "wof:placetype":"venue"
},
  "geometry": {"coordinates":[-104.77315,38.83845],"type":"Point"}
}