{
  "type": "Feature",
  "properties": {
    "iso:country":"US",
    "sg:address":"1545 Quail St",
    "sg:city":"Lakewood",
    "sg:classifiers":[
        {
            "category":"Personal",
            "subcategory":"Beauty Salon",
            "type":"Services"
        }
    ],
    "sg:phone":"+1 303 205 1871",
    "sg:postcode":"80215",
    "sg:province":"CO",
    "sg:tags":[
        "manicuring"
    ],
    "wof:name":"Diamond Nail",
    "wof:placetype":"venue"
},
  "geometry": {"coordinates":[-105.12374699999999,39.743451],"type":"Point"}
}