{
  "type": "Feature",
  "properties": {
    "addr:full":"137 N 5th St Grand Junction CO 81501",
    "addr:housenumber":"137",
    "addr:postcode":"81501",
    "addr:street":"N 5Th St",
    "iso:country":"US",
    "sg:address":"137 N 5th St",
    "sg:city":"Grand Junction",
    "sg:classifiers":[
        {
            "category":"Retail",
            "subcategory":"Photofinishing",
            "type":"Services"
        }
    ],
    "sg:phone":"+1 970 241 9425",
    "sg:postcode":"81501",
    "sg:province":"CO",
    "sg:tags":[
        "laboratory"
    ],
    "wof:name":"Snap Photo",
    "wof:placetype":"venue"
},
  "geometry": {"coordinates":[-108.56454100000001,39.067926],"type":"Point"}
}