{
  "type": "Feature",
  "properties": {
    "iso:country":"US",
    "sg:address":"2343 US Hwy 160",
    "sg:city":"Pagosa Springs",
    "sg:classifiers":[
        {
            "category":"Home & Garden",
            "subcategory":"Building Materials",
            "type":"Retail Goods"
        }
    ],
    "sg:phone":"+1 970 731 5564",
    "sg:postcode":"81147",
    "sg:province":"CO",
    "sg:tags":[
        "paint"
    ],
    "wof:name":"Storehouse Mini Storage",
    "wof:placetype":"venue"
},
  "geometry": {"coordinates":[-107.05264699999999,37.267672],"type":"Point"}
}