{
  "type": "Feature",
  "properties": {
    "addr:full":"2265 Albany Ct Loveland CO 80538",
    "addr:housenumber":"2265",
    "addr:postcode":"80538",
    "addr:street":"Albany Ct",
    "iso:country":"US",
    "sg:address":"2265 Albany Ct",
    "sg:city":"Loveland",
    "sg:classifiers":[
        {
            "category":"Shopping",
            "subcategory":"Used Merchandise",
            "type":"Retail Goods"
        },
        {
            "category":"Retail",
            "subcategory":"Repair Shop",
            "type":"Services"
        }
    ],
    "sg:phone":"+1 970 635 0313",
    "sg:postcode":"80538",
    "sg:province":"CO",
    "sg:tags":[
        "upholsterer"
    ],
    "wof:name":"Alexander's Antique Repair",
    "wof:placetype":"venue"
},
  "geometry": {"coordinates":[-105.05719499999999,40.415311],"type":"Point"}
}