{
  "type": "Feature",
  "properties": {
    "addr:full":"156 E Elkhorn Ave Estes Park CO 80517",
    "addr:housenumber":"156",
    "addr:postcode":"80517",
    "addr:street":"E Elkhorn Ave",
    "iso:country":"US",
    "sg:address":"156 E Elkhorn Ave",
    "sg:city":"Estes Park",
    "sg:classifiers":[
        {
            "category":"Shopping",
            "subcategory":"Bicycles & Sporting Goods",
            "type":"Retail Goods"
        }
    ],
    "sg:phone":"+1 970 586 2114",
    "sg:postcode":"80517",
    "sg:province":"CO",
    "sg:tags":[
        "equipment",
        "camping"
    ],
    "sg:website":"www.rmconnection.com",
    "wof:name":"Outdoor World Inc",
    "wof:placetype":"venue"
},
  "geometry": {"coordinates":[-105.522035,40.376451],"type":"Point"}
}