{
  "type": "Feature",
  "properties": {
    "addr:full":"919 Pearl St Boulder CO 80302",
    "addr:housenumber":"919",
    "addr:postcode":"80302",
    "addr:street":"Pearl St",
    "iso:country":"US",
    "sg:address":"919 Pearl St",
    "sg:city":"Boulder",
    "sg:classifiers":[
        {
            "category":"Restaurant",
            "type":"Food & Drink"
        }
    ],
    "sg:menulink":"http://www.allmenus.com/co/boulder/39956-chipotle/menu/",
    "sg:phone":"+1 303 544 9383",
    "sg:postcode":"80302",
    "sg:province":"CO",
    "sg:tags":[
        "mexican"
    ],
    "wof:name":"Chipotle",
    "wof:placetype":"venue"
},
  "geometry": {"coordinates":[-105.283367,40.017176],"type":"Point"}
}