{
  "type": "Feature",
  "properties": {
    "addr:full":"2310 Lakeview Ave Pueblo CO 81004",
    "addr:housenumber":"2310",
    "addr:postcode":"81004",
    "addr:street":"Lakeview Ave",
    "iso:country":"US",
    "sg:address":"2310 Lakeview Ave",
    "sg:city":"Pueblo",
    "sg:classifiers":[
        {
            "category":"Home & Garden",
            "subcategory":"Home Furnishings",
            "type":"Retail Goods"
        }
    ],
    "sg:phone":"+1 719 564 7192",
    "sg:postcode":"81004",
    "sg:province":"CO",
    "sg:tags":[
        "curtain",
        "made",
        "drapery"
    ],
    "wof:name":"Liz's Drapery & Interiors",
    "wof:placetype":"venue"
},
  "geometry": {"coordinates":[-104.638386,38.234926],"type":"Point"}
}