{
  "type": "Feature",
  "properties": {
    "addr:full":"185 S Santa Fe Dr Denver CO 80223",
    "addr:housenumber":"185",
    "addr:postcode":"80223",
    "addr:street":"S Santa Fe Dr",
    "iso:country":"US",
    "sg:address":"185 S Santa Fe Dr",
    "sg:city":"Denver",
    "sg:classifiers":[
        {
            "category":"Manufacturing",
            "subcategory":"Printing",
            "type":"Manufacturing & Wholesale Goods"
        }
    ],
    "sg:phone":"+1 303 722 5776",
    "sg:postcode":"80223",
    "sg:province":"CO",
    "sg:tags":[
        "letterpress"
    ],
    "wof:name":"Platte River Letterpress Inc",
    "wof:placetype":"venue"
},
  "geometry": {"coordinates":[-104.998636,39.71466],"type":"Point"}
}