{
  "type": "Feature",
  "properties": {
    "addr:full":"832 W Eisenhower Blvd Loveland CO 80537",
    "addr:housenumber":"832",
    "addr:postcode":"80537",
    "addr:street":"W Eisenhower Blvd",
    "iso:country":"US",
    "sg:address":"832 W Eisenhower Blvd",
    "sg:city":"Loveland",
    "sg:classifiers":[
        {
            "category":"Real Estate",
            "subcategory":"Real Estate Agent",
            "type":"Services"
        }
    ],
    "sg:phone":"+1 970 461 0899",
    "sg:postcode":"80537",
    "sg:province":"CO",
    "wof:name":"Halley Home Selling Team",
    "wof:placetype":"venue"
},
  "geometry": {"coordinates":[-105.08649200000001,40.404677],"type":"Point"}
}