{
  "type": "Feature",
  "properties": {
    "iso:country":"US",
    "sg:address":"701 Automation Dr",
    "sg:city":"Windsor",
    "sg:classifiers":[
        {
            "category":"Building & Trades",
            "subcategory":"Construction",
            "type":"Services"
        }
    ],
    "sg:phone":"+1 970 674 1650",
    "sg:postcode":"80550",
    "sg:province":"CO",
    "sg:tags":[
        "resurfacing",
        "laying",
        "refinishing",
        "floor"
    ],
    "wof:name":"Creative Touch Interiors",
    "wof:placetype":"venue"
},
  "geometry": {"coordinates":[-104.88679999999999,40.471426],"type":"Point"}
}