{
  "type": "Feature",
  "properties": {
    "addr:full":"2638 11th Ave Greeley CO 80631",
    "addr:housenumber":"2638",
    "addr:postcode":"80631",
    "addr:street":"11Th Ave",
    "iso:country":"US",
    "sg:address":"2638 11th Ave",
    "sg:city":"Greeley",
    "sg:classifiers":[
        {
            "category":"Shopping",
            "subcategory":"Florist",
            "type":"Retail Goods"
        }
    ],
    "sg:phone":"+1 970 352 7293",
    "sg:postcode":"80631",
    "sg:province":"CO",
    "sg:tags":[
        "flower",
        "gift"
    ],
    "wof:name":"Carol Lynns Gfts Flowers Fudge",
    "wof:placetype":"venue"
},
  "geometry": {"coordinates":[-104.696827,40.393637],"type":"Point"}
}