{
  "type": "Feature",
  "properties": {
    "iso:country":"US",
    "sg:address":"1325 Delaware St",
    "sg:city":"Denver",
    "sg:classifiers":[
        {
            "category":"Insurance",
            "subcategory":"Hazard Insurance",
            "type":"Services"
        }
    ],
    "sg:phone":"+1 303 623 2222",
    "sg:postcode":"80204",
    "sg:province":"CO",
    "sg:tags":[
        "bond"
    ],
    "wof:name":"Bailbond House",
    "wof:placetype":"venue"
},
  "geometry": {"coordinates":[-104.99300700000001,39.73806],"type":"Point"}
}