{
  "type": "Feature",
  "properties": {
    "addr:full":"1324 S Acoma St Denver CO 80223",
    "addr:housenumber":"1324",
    "addr:postcode":"80223",
    "addr:street":"S Acoma St",
    "iso:country":"US",
    "sg:address":"1324 S Acoma St",
    "sg:city":"Denver",
    "sg:classifiers":[
        {
            "category":"Food & Beverages",
            "subcategory":"Specialty",
            "type":"Retail Goods"
        }
    ],
    "sg:phone":"+1 303 777 5793",
    "sg:postcode":"80223",
    "sg:province":"CO",
    "wof:name":"Mother Nature Health Products",
    "wof:placetype":"venue"
},
  "geometry": {"coordinates":[-104.988617,39.691615],"type":"Point"}
}