{
  "type": "Feature",
  "properties": {
    "iso:country":"US",
    "sg:address":"3858 Wyandot St",
    "sg:city":"Denver",
    "sg:classifiers":[
        {
            "category":"Retail",
            "subcategory":"Auto Repair",
            "type":"Services"
        }
    ],
    "sg:phone":"+1 303 458 5865",
    "sg:postcode":"80211",
    "sg:province":"CO",
    "sg:tags":[
        "recreational",
        "vehicle"
    ],
    "wof:name":"Denver's #1 Mobile Rv Service",
    "wof:placetype":"venue"
},
  "geometry": {"coordinates":[-105.01450199999999,39.770014],"type":"Point"}
}