{
  "type": "Feature",
  "properties": {
    "iso:country":"US",
    "sg:address":"6909 S Holly Cir",
    "sg:city":"Englewood",
    "sg:classifiers":[
        {
            "category":"Wholesale",
            "subcategory":"Electrical",
            "type":"Manufacturing & Wholesale Goods"
        }
    ],
    "sg:phone":"+1 303 771 3230",
    "sg:postcode":"80112",
    "sg:province":"CO",
    "sg:tags":[
        "electronic"
    ],
    "wof:name":"G L X Inc",
    "wof:placetype":"venue"
},
  "geometry": {"coordinates":[-104.92156300000001,39.59219],"type":"Point"}
}