{
  "type": "Feature",
  "properties": {
    "iso:country":"US",
    "sg:address":"3805 Newland St",
    "sg:city":"Wheat Ridge",
    "sg:classifiers":[
        {
            "category":"Insurance",
            "subcategory":"Insurance Agent",
            "type":"Services"
        }
    ],
    "sg:phone":"+1 303 421 4550",
    "sg:postcode":"80033",
    "sg:province":"CO",
    "wof:name":"Farmers Insurance Group",
    "wof:placetype":"venue"
},
  "geometry": {"coordinates":[-105.069789,39.772947],"type":"Point"}
}