{
  "type": "Feature",
  "properties": {
    "addr:full":"1 Richardson Rd Castle Rock CO 80104",
    "addr:housenumber":"1",
    "addr:postcode":"80104",
    "addr:street":"Richardson Rd",
    "iso:country":"US",
    "sg:address":"1 Richardson Rd",
    "sg:city":"Castle Rock",
    "sg:classifiers":[
        {
            "category":"Real Estate",
            "subcategory":"Real Estate Agent",
            "type":"Services"
        }
    ],
    "sg:phone":"+1 303 688 5204",
    "sg:postcode":"80104",
    "sg:province":"CO",
    "wof:name":"John Hardin & Assoc",
    "wof:placetype":"venue"
},
  "geometry": {"coordinates":[-104.846615,39.371881],"type":"Point"}
}