{
  "type": "Feature",
  "properties": {
    "iso:country":"US",
    "sg:address":"12565 E Wesley Ave",
    "sg:city":"Aurora",
    "sg:classifiers":[
        {
            "category":"Utilities",
            "subcategory":"Mobile Phone",
            "type":"Services"
        }
    ],
    "sg:phone":"+1 303 693 0083",
    "sg:postcode":"80014",
    "sg:province":"CO",
    "sg:tags":[
        "communication",
        "radiotelephone"
    ],
    "wof:name":"Wavelink Wireless",
    "wof:placetype":"venue"
},
  "geometry": {"coordinates":[-104.84207499999999,39.673523],"type":"Point"}
}