{
  "type": "Feature",
  "properties": {
    "iso:country":"US",
    "sg:address":"803 5th St",
    "sg:city":"Greeley",
    "sg:classifiers":[
        {
            "category":"Food & Beverages",
            "subcategory":"Liquor & Beverages",
            "type":"Retail Goods"
        }
    ],
    "sg:phone":"+1 970 352 8824",
    "sg:postcode":"80631",
    "sg:province":"CO",
    "wof:name":"Liquor 4 Less",
    "wof:placetype":"venue"
},
  "geometry": {"coordinates":[-104.692543,40.428674],"type":"Point"}
}