{
  "type": "Feature",
  "properties": {
    "iso:country":"US",
    "sg:address":"131 State Hwy 91",
    "sg:city":"Leadville",
    "sg:classifiers":[
        {
            "category":"Recreation",
            "type":"Entertainment"
        }
    ],
    "sg:phone":"+1 719 486 1497",
    "sg:postcode":"80461",
    "sg:province":"CO",
    "sg:tags":[
        "stable"
    ],
    "wof:name":"Leadville Stables",
    "wof:placetype":"venue"
},
  "geometry": {"coordinates":[-106.291068,39.251417],"type":"Point"}
}