{
  "type": "Feature",
  "properties": {
    "iso:country":"US",
    "sg:address":"8025 Sheridan Blvd",
    "sg:city":"Arvada",
    "sg:classifiers":[
        {
            "category":"Retail",
            "subcategory":"Veterinary Services",
            "type":"Services"
        }
    ],
    "sg:phone":"+1 303 430 0919",
    "sg:postcode":"80003",
    "sg:province":"CO",
    "sg:tags":[
        "veterinarian"
    ],
    "wof:name":"Pets Vet",
    "wof:placetype":"venue"
},
  "geometry": {"coordinates":[-105.05330600000001,39.842525],"type":"Point"}
}