{
  "type": "Feature",
  "properties": {
    "addr:full":"10184 W Belleview Ave Littleton CO 80127",
    "addr:housenumber":"10184",
    "addr:postcode":"80127",
    "addr:street":"W Belleview Ave",
    "iso:country":"US",
    "sg:address":"10184 W Belleview Ave",
    "sg:city":"Littleton",
    "sg:classifiers":[
        {
            "category":"Insurance",
            "subcategory":"Insurance Agent",
            "type":"Services"
        }
    ],
    "sg:phone":"+1 303 973 6330",
    "sg:postcode":"80127",
    "sg:province":"CO",
    "sg:tags":[
        "accident"
    ],
    "wof:name":"Affordable Benefit Admnstrtrs",
    "wof:placetype":"venue"
},
  "geometry": {"coordinates":[-105.11017200000001,39.624146],"type":"Point"}
}