{
  "type": "Feature",
  "properties": {
    "iso:country":"US",
    "sg:address":"4800 Wadsworth Blvd",
    "sg:city":"Wheat Ridge",
    "sg:classifiers":[
        {
            "category":"Real Estate",
            "subcategory":"Real Estate Agent",
            "type":"Services"
        }
    ],
    "sg:phone":"+1 720 298 8378",
    "sg:postcode":"80033",
    "sg:province":"CO",
    "wof:name":"Prominent Real Estate & Prprty",
    "wof:placetype":"venue"
},
  "geometry": {"coordinates":[-105.08138,39.783041],"type":"Point"}
}