{
  "type": "Feature",
  "properties": {
    "iso:country":"US",
    "sg:address":"7945 E Amherst Ave",
    "sg:city":"Denver",
    "sg:classifiers":[
        {
            "category":"Professional",
            "subcategory":"Advertising",
            "type":"Services"
        }
    ],
    "sg:phone":"+1 303 256 7777",
    "sg:postcode":"80231",
    "sg:province":"CO",
    "sg:website":"www.promo-sol.com",
    "wof:name":"Promotional Solutions Inc",
    "wof:placetype":"venue"
},
  "geometry": {"coordinates":[-104.89736000000001,39.666658],"type":"Point"}
}