{
  "type": "Feature",
  "properties": {
    "addr:full":"2201 Dexter Street Denver CO 80207",
    "addr:housenumber":"2201",
    "addr:postcode":"80207",
    "addr:street":"Dexter Street",
    "iso:country":"US",
    "sg:address":"2201 Dexter Street",
    "sg:city":"Denver",
    "sg:classifiers":[
        {
            "category":"Organizations",
            "subcategory":"Religious Organization",
            "type":"Services"
        }
    ],
    "sg:phone":"+1 303 388 4395",
    "sg:postcode":"80207",
    "sg:province":"CO",
    "wof:name":"St Thomas Episcopal Church",
    "wof:placetype":"venue"
},
  "geometry": {"coordinates":[-104.932964,39.749616],"type":"Point"}
}