{
  "type": "Feature",
  "properties": {
    "addr:full":"2190 Sheridan Blvd Edgewater CO 80214",
    "addr:housenumber":"2190",
    "addr:postcode":"80214",
    "addr:street":"Sheridan Blvd",
    "iso:country":"US",
    "sg:address":"2190 Sheridan Blvd",
    "sg:city":"Edgewater",
    "sg:classifiers":[
        {
            "category":"Organizations",
            "subcategory":"Religious Organization",
            "type":"Services"
        }
    ],
    "sg:phone":"+1 303 935 3900",
    "sg:postcode":"80214",
    "sg:province":"CO",
    "sg:tags":[
        "church"
    ],
    "wof:name":"Notre Dame Catholic Church",
    "wof:placetype":"venue"
},
  "geometry": {"coordinates":[-105.053293,39.7477],"type":"Point"}
}