{
  "type": "Feature",
  "properties": {
    "addr:full":"2710 Walnut St Denver CO 80205",
    "addr:housenumber":"2710",
    "addr:postcode":"80205",
    "addr:street":"Walnut St",
    "iso:country":"US",
    "sg:address":"2710 Walnut St",
    "sg:city":"Denver",
    "sg:classifiers":[
        {
            "category":"Museum",
            "type":"Entertainment"
        }
    ],
    "sg:phone":"+1 303 458 6000",
    "sg:postcode":"80205",
    "sg:province":"CO",
    "sg:website":"www.giant-interactive.com",
    "wof:name":"Giant Interactive",
    "wof:placetype":"venue"
},
  "geometry": {"coordinates":[-104.98487900000001,39.760226],"type":"Point"}
}