{
  "type": "Feature",
  "properties": {
    "iso:country":"US",
    "sg:address":"1919 14th St",
    "sg:city":"Boulder",
    "sg:classifiers":[
        {
            "category":"Professional",
            "subcategory":"Art Services",
            "type":"Services"
        }
    ],
    "sg:phone":"+1 303 447 0780",
    "sg:postcode":"80302",
    "sg:province":"CO",
    "sg:tags":[
        "artist"
    ],
    "wof:name":"George Roche",
    "wof:placetype":"venue"
},
  "geometry": {"coordinates":[-105.277191,40.017639],"type":"Point"}
}