{
  "type": "Feature",
  "properties": {
    "iso:country":"US",
    "sg:address":"425 S Santa Fe Ave",
    "sg:city":"Pueblo",
    "sg:classifiers":[
        {
            "category":"Bars & Pubs",
            "type":"Food & Drink"
        }
    ],
    "sg:phone":"+1 719 542 9776",
    "sg:postcode":"81003",
    "sg:province":"CO",
    "sg:tags":[
        "club",
        "night"
    ],
    "wof:name":"Patsy's",
    "wof:placetype":"venue"
},
  "geometry": {"coordinates":[-104.606831,38.25935],"type":"Point"}
}