{
  "type": "Feature",
  "properties": {
    "iso:country":"US",
    "sg:address":"3760 Tejon St",
    "sg:city":"Denver",
    "sg:classifiers":[
        {
            "category":"Restaurant",
            "type":"Food & Drink"
        }
    ],
    "sg:phone":"+1 303 800 7020",
    "sg:postcode":"80211",
    "sg:province":"CO",
    "sg:tags":[
        "pizza",
        "italian"
    ],
    "sg:website":"http://www.gaetanositalian.com/index.html",
    "wof:name":"Gaetanos",
    "wof:placetype":"venue"
},
  "geometry": {"coordinates":[-105.011192,39.768803],"type":"Point"}
}