{
  "type": "Feature",
  "properties": {
    "addr:full":"7434 W 68th Ave Arvada CO 80003",
    "addr:housenumber":"7434",
    "addr:postcode":"80003",
    "addr:street":"W 68Th Ave",
    "iso:country":"US",
    "sg:address":"7434 W 68th Ave",
    "sg:city":"Arvada",
    "sg:classifiers":[
        {
            "category":"Building & Trades",
            "subcategory":"Plumbing",
            "type":"Services"
        }
    ],
    "sg:phone":"+1 303 463 8541",
    "sg:postcode":"80003",
    "sg:province":"CO",
    "sg:tags":[
        "conditioning",
        "air",
        "system",
        "contractor"
    ],
    "wof:name":"Jack Micek Heating & Cooling",
    "wof:placetype":"venue"
},
  "geometry": {"coordinates":[-105.080477,39.820047],"type":"Point"}
}