{
  "type": "Feature",
  "properties": {
    "addr:full":"6858 S Yosemite St Centennial CO 80112",
    "addr:housenumber":"6858",
    "addr:postcode":"80112",
    "addr:street":"S Yosemite St",
    "iso:country":"US",
    "sg:address":"6858 S Yosemite St",
    "sg:city":"Centennial",
    "sg:classifiers":[
        {
            "category":"Shopping",
            "subcategory":"Clothing, Apparel, & Fashions",
            "type":"Retail Goods"
        }
    ],
    "sg:phone":"+1 303 773 0769",
    "sg:postcode":"80112",
    "sg:province":"CO",
    "sg:tags":[
        "tailor"
    ],
    "wof:name":"Southgate Tailoring",
    "wof:placetype":"venue"
},
  "geometry": {"coordinates":[-104.88654200000001,39.591863],"type":"Point"}
}