{
  "type": "Feature",
  "properties": {
    "iso:country":"US",
    "sg:address":"12163 Sheridan Blvd",
    "sg:city":"Broomfield",
    "sg:classifiers":[
        {
            "category":"Shopping",
            "type":"Retail Goods"
        }
    ],
    "sg:phone":"+1 303 635 1540",
    "sg:postcode":"80020",
    "sg:province":"CO",
    "sg:tags":[
        "pet",
        "shop"
    ],
    "sg:website":"www.petco.com",
    "wof:name":"PETCO",
    "wof:placetype":"venue"
},
  "geometry": {"coordinates":[-105.05302500000001,39.914783],"type":"Point"}
}