{
  "type": "Feature",
  "properties": {
    "addr:full":"11176 E Baltic Dr Aurora CO 80014",
    "addr:housenumber":"11176",
    "addr:postcode":"80014",
    "addr:street":"E Baltic Dr",
    "iso:country":"US",
    "sg:address":"11176 E Baltic Dr",
    "sg:city":"Aurora",
    "sg:classifiers":[
        {
            "category":"Insurance",
            "subcategory":"Insurance Agent",
            "type":"Services"
        }
    ],
    "sg:phone":"+1 303 745 0544",
    "sg:postcode":"80014",
    "sg:province":"CO",
    "wof:name":"Alessandra Insurance Agency",
    "wof:placetype":"venue"
},
  "geometry": {"coordinates":[-104.857947,39.675252],"type":"Point"}
}