{
  "type": "Feature",
  "properties": {
    "iso:country":"US",
    "sg:address":"843 Lincoln Ave",
    "sg:city":"Steamboat Spgs",
    "sg:classifiers":[
        {
            "category":"Home & Garden",
            "subcategory":"Furniture",
            "type":"Retail Goods"
        }
    ],
    "sg:phone":"+1 970 879 1015",
    "sg:postcode":"80487",
    "sg:province":"CO",
    "wof:name":"White Hart Gallery",
    "wof:placetype":"venue"
},
  "geometry": {"coordinates":[-106.83535999999999,40.486435],"type":"Point"}
}