{
  "type": "Feature",
  "properties": {
    "addr:full":"133 Wilcox St Castle Rock CO 80104",
    "addr:housenumber":"133",
    "addr:postcode":"80104",
    "addr:street":"Wilcox St",
    "iso:country":"US",
    "sg:address":"133 Wilcox St",
    "sg:city":"Castle Rock",
    "sg:classifiers":[
        {
            "category":"Government",
            "subcategory":"Office",
            "type":"Public Place"
        }
    ],
    "sg:phone":"+1 720 733 0221",
    "sg:postcode":"80104",
    "sg:province":"CO",
    "sg:tags":[
        "armed",
        "force",
        "recruiting"
    ],
    "wof:name":"US Air Force Recruiting",
    "wof:placetype":"venue"
},
  "geometry": {"coordinates":[-104.86014400000001,39.370291],"type":"Point"}
}