{
  "type": "Feature",
  "properties": {
    "addr:full":"19230 US Hwy 138 Julesburg CO 80737",
    "addr:postcode":"19230;80737",
    "addr:street":"Us Hwy 138 Julesburg",
    "iso:country":"US",
    "sg:address":"19230 US Hwy 138",
    "sg:city":"Julesburg",
    "sg:classifiers":[
        {
            "category":"Freight",
            "type":"Transportation"
        }
    ],
    "sg:phone":"+1 970 474 2700",
    "sg:postcode":"80737",
    "sg:province":"CO",
    "sg:tags":[
        "trucking"
    ],
    "wof:name":"D & F Transport",
    "wof:placetype":"venue"
},
  "geometry": {"coordinates":[-102.280142,40.982604],"type":"Point"}
}