{
  "type": "Feature",
  "properties": {
    "addr:full":"3755 Evergreen Pkwy Evergreen CO 80439",
    "addr:housenumber":"3755",
    "addr:postcode":"80439",
    "addr:street":"Evergreen Pkwy",
    "iso:country":"US",
    "sg:address":"3755 Evergreen Pkwy",
    "sg:city":"Evergreen",
    "sg:classifiers":[
        {
            "category":"Home & Garden",
            "subcategory":"Furniture",
            "type":"Retail Goods"
        }
    ],
    "sg:phone":"+1 303 674 7870",
    "sg:postcode":"80439",
    "sg:province":"CO",
    "sg:tags":[
        "equipment",
        "kitchen",
        "cabinet"
    ],
    "sg:website":"www.kitchenbathctr.com",
    "wof:name":"Kitchen & Bath Ctr",
    "wof:placetype":"venue"
},
  "geometry": {"coordinates":[-105.341607,39.649094],"type":"Point"}
}