{
  "type": "Feature",
  "properties": {
    "iso:country":"US",
    "sg:address":"3400 Table Mesa Dr",
    "sg:city":"Boulder",
    "sg:classifiers":[
        {
            "category":"Real Estate",
            "subcategory":"Real Estate Agent",
            "type":"Services"
        }
    ],
    "sg:phone":"+1 303 494 1399",
    "sg:postcode":"80305",
    "sg:province":"CO",
    "wof:name":"Bremner & Associates Real Esta",
    "wof:placetype":"venue"
},
  "geometry": {"coordinates":[-105.251925,39.984169],"type":"Point"}
}