{
  "type": "Feature",
  "properties": {
    "addr:full":"14563 E 11th Ave Aurora CO 80011",
    "addr:housenumber":"14563",
    "addr:postcode":"80011",
    "addr:street":"E 11Th Ave",
    "iso:country":"US",
    "sg:address":"14563 E 11th Ave",
    "sg:city":"Aurora",
    "sg:classifiers":[
        {
            "category":"Building & Trades",
            "subcategory":"Construction",
            "type":"Services"
        }
    ],
    "sg:phone":"+1 303 343 0265",
    "sg:postcode":"80011",
    "sg:province":"CO",
    "sg:tags":[
        "house"
    ],
    "wof:name":"Model T Remodeling",
    "wof:placetype":"venue"
},
  "geometry": {"coordinates":[-104.817228,39.732458],"type":"Point"}
}