{
  "type": "Feature",
  "properties": {
    "iso:country":"US",
    "sg:address":"10120 Grant St",
    "sg:city":"Denver",
    "sg:classifiers":[
        {
            "category":"Retail",
            "subcategory":"Auto Repair",
            "type":"Services"
        }
    ],
    "sg:phone":"+1 303 451 8993",
    "sg:postcode":"80229",
    "sg:province":"CO",
    "sg:tags":[
        "body",
        "automobile",
        "painting"
    ],
    "wof:name":"Abra Auto Body & Glass",
    "wof:placetype":"venue"
},
  "geometry": {"coordinates":[-104.982364,39.880434],"type":"Point"}
}