{
  "type": "Feature",
  "properties": {
    "iso:country":"US",
    "sg:address":"1300 Ogden St",
    "sg:city":"Denver",
    "sg:classifiers":[
        {
            "category":"Building & Trades",
            "subcategory":"Locksmith",
            "type":"Services"
        }
    ],
    "sg:phone":"+1 303 323 1067",
    "sg:postcode":"80218",
    "sg:province":"CO",
    "sg:tags":[
        "key"
    ],
    "wof:name":"A Locksmith 0 1 24 Hour",
    "wof:placetype":"venue"
},
  "geometry": {"coordinates":[-104.97510200000001,39.736849],"type":"Point"}
}