{
  "type": "Feature",
  "properties": {
    "addr:full":"7730 S Broadway Littleton CO 80122",
    "addr:housenumber":"7730",
    "addr:postcode":"80122",
    "addr:street":"S Broadway",
    "iso:country":"US",
    "sg:address":"7730 S Broadway",
    "sg:city":"Littleton",
    "sg:classifiers":[
        {
            "category":"Health Services",
            "subcategory":"Doctor",
            "type":"Services"
        }
    ],
    "sg:phone":"+1 303 730 5895",
    "sg:postcode":"80122",
    "sg:province":"CO",
    "sg:tags":[
        "clinic"
    ],
    "wof:name":"Littleton Hospital Urgent Care",
    "wof:placetype":"venue"
},
  "geometry": {"coordinates":[-104.98832,39.578348],"type":"Point"}
}