{
  "type": "Feature",
  "properties": {
    "iso:country":"US",
    "sg:address":"590 Bryant St",
    "sg:city":"Denver",
    "sg:classifiers":[
        {
            "category":"Building & Trades",
            "subcategory":"Locksmith",
            "type":"Services"
        }
    ],
    "sg:phone":"+1 303 323 0131",
    "sg:postcode":"80204",
    "sg:province":"CO",
    "sg:tags":[
        "key"
    ],
    "wof:name":"A 24 Hour A Locksmith",
    "wof:placetype":"venue"
},
  "geometry": {"coordinates":[-105.018652,39.725093],"type":"Point"}
}