{
  "type": "Feature",
  "properties": {
    "addr:full":"701 Grand Ave Glenwood Springs CO 81601",
    "addr:housenumber":"701",
    "addr:postcode":"81601",
    "addr:street":"Grand Ave",
    "iso:country":"US",
    "sg:address":"701 Grand Ave",
    "sg:city":"Glenwood Springs",
    "sg:classifiers":[
        {
            "category":"Real Estate",
            "subcategory":"Architect",
            "type":"Services"
        }
    ],
    "sg:phone":"+1 970 945 1099",
    "sg:postcode":"81601",
    "sg:province":"CO",
    "wof:name":"Doug Harr Architecture",
    "wof:placetype":"venue"
},
  "geometry": {"coordinates":[-107.32466599999999,39.547847],"type":"Point"}
}