{
  "type": "Feature",
  "properties": {
    "addr:full":"6765 Garrison St Arvada CO 80004",
    "addr:housenumber":"6765",
    "addr:postcode":"80004",
    "addr:street":"Garrison St",
    "iso:country":"US",
    "sg:address":"6765 Garrison St",
    "sg:city":"Arvada",
    "sg:classifiers":[
        {
            "category":"Professional",
            "subcategory":"Management & Consulting",
            "type":"Services"
        }
    ],
    "sg:phone":"+1 303 422 5128",
    "sg:postcode":"80004",
    "sg:province":"CO",
    "sg:tags":[
        "consultant",
        "business"
    ],
    "wof:name":"E B Resource Solutions Inc",
    "wof:placetype":"venue"
},
  "geometry": {"coordinates":[-105.100326,39.819148],"type":"Point"}
}