{
  "type": "Feature",
  "properties": {
    "iso:country":"US",
    "sg:address":"12725 Abert Way",
    "sg:city":"Colorado Springs",
    "sg:classifiers":[
        {
            "category":"Building & Trades",
            "subcategory":"Construction",
            "type":"Services"
        }
    ],
    "sg:phone":"+1 719 599 5677",
    "sg:postcode":"80908",
    "sg:province":"CO",
    "sg:tags":[
        "house",
        "builder",
        "home"
    ],
    "wof:name":"Aspen Country Homes 5550",
    "wof:placetype":"venue"
},
  "geometry": {"coordinates":[-104.779122,39.023507],"type":"Point"}
}