{
  "type": "Feature",
  "properties": {
    "iso:country":"US",
    "sg:address":"2449 35th Ave",
    "sg:city":"Greeley",
    "sg:classifiers":[
        {
            "category":"Food & Beverages",
            "subcategory":"Groceries & Convenience Stores",
            "type":"Retail Goods"
        }
    ],
    "sg:phone":"+1 970 339 5040",
    "sg:postcode":"80634",
    "sg:province":"CO",
    "sg:tags":[
        "home",
        "auto",
        "supply"
    ],
    "wof:name":"Agland",
    "wof:placetype":"venue"
},
  "geometry": {"coordinates":[-104.73508,40.399107],"type":"Point"}
}