{
  "type": "Feature",
  "properties": {
    "iso:country":"US",
    "sg:address":"3855 E 151st Ave",
    "sg:city":"Brighton",
    "sg:classifiers":[
        {
            "category":"Building & Trades",
            "subcategory":"Construction",
            "type":"Services"
        }
    ],
    "sg:phone":"+1 303 451 0688",
    "sg:postcode":"80602",
    "sg:province":"CO",
    "sg:tags":[
        "concrete",
        "contractor",
        "general"
    ],
    "wof:name":"Horizon West Builders Inc",
    "wof:placetype":"venue"
},
  "geometry": {"coordinates":[-104.942812,39.970734],"type":"Point"}
}