{
  "type": "Feature",
  "properties": {
    "iso:country":"US",
    "sg:address":"1823 E Bijou St",
    "sg:city":"Colorado Springs",
    "sg:classifiers":[
        {
            "category":"Building & Trades",
            "subcategory":"Construction",
            "type":"Services"
        }
    ],
    "sg:phone":"+1 719 576 9931",
    "sg:postcode":"80909",
    "sg:province":"CO",
    "sg:tags":[
        "concrete",
        "contractor"
    ],
    "wof:name":"Clover Concrete Construction I",
    "wof:placetype":"venue"
},
  "geometry": {"coordinates":[-104.79403000000001,38.835678],"type":"Point"}
}