{
  "type": "Feature",
  "properties": {
    "addr:full":"12175 Old Pueblo Rd Fountain CO 80817",
    "addr:housenumber":"12175",
    "addr:postcode":"80817",
    "addr:street":"Old Pueblo Rd",
    "iso:country":"US",
    "sg:address":"12175 Old Pueblo Rd",
    "sg:city":"Fountain",
    "sg:classifiers":[
        {
            "category":"Building & Trades",
            "subcategory":"Construction",
            "type":"Services"
        }
    ],
    "sg:phone":"+1 719 382 7560",
    "sg:postcode":"80817",
    "sg:province":"CO",
    "sg:tags":[
        "house"
    ],
    "wof:name":"Designer Decks",
    "wof:placetype":"venue"
},
  "geometry": {"coordinates":[-104.691433,38.657715],"type":"Point"}
}