{
  "type": "Feature",
  "properties": {
    "iso:country":"US",
    "sg:address":"600 S Main St",
    "sg:city":"Longmont",
    "sg:classifiers":[
        {
            "category":"Retail",
            "subcategory":"Auto Repair",
            "type":"Services"
        }
    ],
    "sg:phone":"+1 303 702 9194",
    "sg:postcode":"80501",
    "sg:province":"CO",
    "sg:tags":[
        "repairing",
        "automobile"
    ],
    "wof:name":"Auto Repair Clinic",
    "wof:placetype":"venue"
},
  "geometry": {"coordinates":[-105.102469,40.153104],"type":"Point"}
}