{
  "type": "Feature",
  "properties": {
    "addr:full":"5080 Paris St Denver CO 80239",
    "addr:housenumber":"5080",
    "addr:postcode":"80239",
    "addr:street":"Paris St",
    "iso:country":"US",
    "sg:address":"5080 Paris St",
    "sg:city":"Denver",
    "sg:classifiers":[
        {
            "category":"Manufacturing",
            "subcategory":"Electronics",
            "type":"Manufacturing & Wholesale Goods"
        }
    ],
    "sg:phone":"+1 303 371 0208",
    "sg:postcode":"80239",
    "sg:province":"CO",
    "sg:tags":[
        "equipment",
        "mfg",
        "home"
    ],
    "wof:name":"Simulted Stone Speaker Systems",
    "wof:placetype":"venue"
},
  "geometry": {"coordinates":[-104.848816,39.786757],"type":"Point"}
}