{
  "type": "Feature",
  "properties": {
    "iso:country":"US",
    "sg:address":"1524 Grant St",
    "sg:city":"Denver",
    "sg:classifiers":[
        {
            "category":"Professional",
            "type":"Services"
        }
    ],
    "sg:phone":"+1 720 862 1573",
    "sg:postcode":"80203",
    "sg:province":"CO",
    "sg:tags":[
        "caterer"
    ],
    "sg:website":"emeraldgrillonline.com",
    "wof:name":"Emerald Grill & Catering",
    "wof:placetype":"venue"
},
  "geometry": {"coordinates":[-104.983586,39.740573],"type":"Point"}
}