{
  "type": "Feature",
  "properties": {
    "iso:country":"US",
    "sg:address":"10890 E Dartmouth Ave",
    "sg:city":"Denver",
    "sg:classifiers":[
        {
            "category":"Bars & Pubs",
            "type":"Food & Drink"
        },
        {
            "category":"Restaurant",
            "type":"Food & Drink"
        }
    ],
    "sg:phone":"+1 303 671 5324",
    "sg:postcode":"80014",
    "sg:province":"CO",
    "sg:tags":[
        "brew",
        "grill"
    ],
    "wof:name":"Moxies Bar and Grill",
    "wof:placetype":"venue"
},
  "geometry": {"coordinates":[-104.860303,39.660221],"type":"Point"}
}