{
  "type": "Feature",
  "properties": {
    "addr:full":"174 Co Rd 301 Parachute CO 81635",
    "addr:housenumber":"174;301",
    "addr:postcode":"81635",
    "addr:street":"Co Rd",
    "iso:country":"US",
    "sg:address":"174 Co Rd 301",
    "sg:city":"Parachute",
    "sg:classifiers":[
        {
            "category":"Mining & Drilling",
            "type":"Manufacturing & Wholesale Goods"
        }
    ],
    "sg:phone":"+1 970 319 1078",
    "sg:postcode":"81635",
    "sg:province":"CO",
    "sg:tags":[
        "field"
    ],
    "wof:name":"S & S Roustabout & Associates",
    "wof:placetype":"venue"
},
  "geometry": {"coordinates":[-108.03264799999999,39.455755],"type":"Point"}
}