{
  "type": "Feature",
  "properties": {
    "addr:full":"8702 Massey Cir Colorado Springs CO 80920",
    "addr:housenumber":"8702",
    "addr:postcode":"80920",
    "addr:street":"Massey Cir",
    "iso:country":"US",
    "sg:address":"8702 Massey Cir",
    "sg:city":"Colorado Springs",
    "sg:classifiers":[
        {
            "category":"Home & Garden",
            "subcategory":"Furniture",
            "type":"Retail Goods"
        }
    ],
    "sg:phone":"+1 719 282 8519",
    "sg:postcode":"80920",
    "sg:province":"CO",
    "wof:name":"Furniture & Wood Solutions LLC",
    "wof:placetype":"venue"
},
  "geometry": {"coordinates":[-104.726868,38.954527],"type":"Point"}
}