{
  "type": "Feature",
  "properties": {
    "addr:full":"1600 North Ave Grand Junction CO 81501",
    "addr:housenumber":"1600",
    "addr:postcode":"81501",
    "addr:street":"North Ave",
    "iso:country":"US",
    "sg:address":"1600 North Ave",
    "sg:city":"Grand Junction",
    "sg:classifiers":[
        {
            "category":"Travel",
            "subcategory":"Hotels & Motels",
            "type":"Entertainment"
        }
    ],
    "sg:phone":"+1 970 245 5770",
    "sg:postcode":"81501",
    "sg:province":"CO",
    "sg:tags":[
        "building",
        "residential",
        "operation",
        "commercial"
    ],
    "wof:name":"Peachtree Inn",
    "wof:placetype":"venue"
},
  "geometry": {"coordinates":[-108.543775,39.077387],"type":"Point"}
}