{
  "type": "Feature",
  "properties": {
    "iso:country":"US",
    "sg:address":"3200 Valmont Rd",
    "sg:city":"Boulder",
    "sg:classifiers":[
        {
            "category":"Retail",
            "subcategory":"Auto Repair",
            "type":"Services"
        }
    ],
    "sg:phone":"+1 303 938 1900",
    "sg:postcode":"80301",
    "sg:province":"CO",
    "sg:tags":[
        "repairing",
        "automobile"
    ],
    "wof:name":"Miles Auto Ctr",
    "wof:placetype":"venue"
},
  "geometry": {"coordinates":[-105.252139,40.029122],"type":"Point"}
}