{
  "type": "Feature",
  "properties": {
    "iso:country":"US",
    "sg:address":"22561 E Belleview Pl",
    "sg:city":"Aurora",
    "sg:classifiers":[
        {
            "category":"Shopping",
            "subcategory":"Bicycles & Sporting Goods",
            "type":"Retail Goods"
        }
    ],
    "sg:phone":"+1 303 400 6217",
    "sg:postcode":"80015",
    "sg:province":"CO",
    "wof:name":"Ali Zubair",
    "wof:placetype":"venue"
},
  "geometry": {"coordinates":[-104.72501,39.623477],"type":"Point"}
}