{
  "type": "Feature",
  "properties": {
    "iso:country":"US",
    "sg:address":"1244 Pine St",
    "sg:city":"Boulder",
    "sg:classifiers":[
        {
            "category":"Health Services",
            "subcategory":"Health Practitioner",
            "type":"Services"
        }
    ],
    "sg:phone":"+1 303 440 8810",
    "sg:postcode":"80302",
    "sg:province":"CO",
    "sg:tags":[
        "psychologist"
    ],
    "wof:name":"Cynthia L Divino PHD",
    "wof:placetype":"venue"
},
  "geometry": {"coordinates":[-105.28067,40.019912],"type":"Point"}
}