{
  "type": "Feature",
  "properties": {
    "iso:country":"US",
    "sg:address":"4917 Valley View Dr",
    "sg:city":"Mesa",
    "sg:classifiers":[
        {
            "category":"Building & Trades",
            "subcategory":"Construction",
            "type":"Services"
        }
    ],
    "sg:phone":"+1 970 268 5843",
    "sg:postcode":"81643",
    "sg:province":"CO",
    "sg:tags":[
        "general",
        "contractor"
    ],
    "wof:name":"Bell Construction",
    "wof:placetype":"venue"
},
  "geometry": {"coordinates":[-108.133903,39.072126],"type":"Point"}
}