{
  "type": "Feature",
  "properties": {
    "iso:country":"US",
    "sg:address":"1151 Rainier Dr",
    "sg:city":"Colorado Springs",
    "sg:classifiers":[
        {
            "category":"Building & Trades",
            "subcategory":"Construction",
            "type":"Services"
        }
    ],
    "sg:phone":"+1 719 473 7698",
    "sg:postcode":"80910",
    "sg:province":"CO",
    "sg:tags":[
        "house"
    ],
    "wof:name":"Emmanuel Painting & Remodel LL",
    "wof:placetype":"venue"
},
  "geometry": {"coordinates":[-104.77408200000001,38.817201],"type":"Point"}
}