{
  "type": "Feature",
  "properties": {
    "iso:country":"US",
    "sg:address":"1999 Broadway Ste 2605",
    "sg:city":"Denver",
    "sg:classifiers":[
        {
            "category":"Building & Trades",
            "subcategory":"Locksmith",
            "type":"Services"
        }
    ],
    "sg:phone":"+1 866 471 1834",
    "sg:postcode":"80202",
    "sg:province":"CO",
    "sg:tags":[
        "key"
    ],
    "wof:name":"24 Hour 7 Day Emergency Locksmith",
    "wof:placetype":"venue"
},
  "geometry": {"coordinates":[-104.987431,39.748641],"type":"Point"}
}