{
  "type": "Feature",
  "properties": {
    "addr:full":"110 E 9th St Durango CO 81301",
    "addr:housenumber":"110",
    "addr:postcode":"co 81301",
    "addr:street":"E 9Th St",
    "iso:country":"US",
    "sg:address":"110 E 9th St",
    "sg:city":"Durango",
    "sg:classifiers":[
        {
            "category":"Professional",
            "type":"Services"
        }
    ],
    "sg:phone":"+1 970 247 0974",
    "sg:postcode":"81301",
    "sg:province":"CO",
    "sg:tags":[
        "establishment"
    ],
    "wof:name":"Worldwatch Institute",
    "wof:placetype":"venue"
},
  "geometry": {"coordinates":[-107.880634,37.273298],"type":"Point"}
}