{
  "type": "Feature",
  "properties": {
    "iso:country":"US",
    "sg:address":"4432 Wellington Rd",
    "sg:city":"Boulder",
    "sg:classifiers":[
        {
            "category":"Wholesale",
            "subcategory":"Hardware",
            "type":"Manufacturing & Wholesale Goods"
        }
    ],
    "sg:phone":"+1 303 530 2574",
    "sg:postcode":"80301",
    "sg:province":"CO",
    "sg:tags":[
        "purifying",
        "cleaning",
        "air"
    ],
    "wof:name":"Quality Environmental Svc",
    "wof:placetype":"venue"
},
  "geometry": {"coordinates":[-105.212918,40.055687],"type":"Point"}
}