{
  "type": "Feature",
  "properties": {
    "iso:country":"US",
    "sg:address":"865 E Huntington Dr",
    "sg:city":"Littleton",
    "sg:classifiers":[
        {
            "category":"Wholesale",
            "subcategory":"Groceries",
            "type":"Manufacturing & Wholesale Goods"
        }
    ],
    "sg:phone":"+1 303 791 0463",
    "sg:postcode":"80126",
    "sg:province":"CO",
    "sg:tags":[
        "food",
        "broker"
    ],
    "wof:name":"Elite Marketing Inc",
    "wof:placetype":"venue"
},
  "geometry": {"coordinates":[-104.980187,39.534313],"type":"Point"}
}