{
  "type": "Feature",
  "properties": {
    "iso:country":"US",
    "sg:address":"1626 37th Avenue Pl",
    "sg:city":"Greeley",
    "sg:classifiers":[
        {
            "category":"Real Estate",
            "subcategory":"Real Estate Agent",
            "type":"Services"
        }
    ],
    "sg:phone":"+1 970 352 4232",
    "sg:postcode":"80634",
    "sg:province":"CO",
    "wof:name":"Absolute Appraisals Inc",
    "wof:placetype":"venue"
},
  "geometry": {"coordinates":[-104.740956,40.41049],"type":"Point"}
}