{
  "type": "Feature",
  "properties": {
    "iso:country":"US",
    "sg:address":"133 S 27th Ave",
    "sg:city":"Brighton",
    "sg:classifiers":[
        {
            "category":"Organizations",
            "subcategory":"Religious Organization",
            "type":"Services"
        }
    ],
    "sg:phone":"+1 303 659 9759",
    "sg:postcode":"80601",
    "sg:province":"CO",
    "sg:tags":[
        "church"
    ],
    "wof:name":"Pathway Assembly Of God",
    "wof:placetype":"venue"
},
  "geometry": {"coordinates":[-104.790065,39.984293],"type":"Point"}
}