{
  "type": "Feature",
  "properties": {
    "iso:country":"US",
    "sg:address":"2940 Shady Hollow W",
    "sg:city":"Boulder",
    "sg:classifiers":[
        {
            "category":"Restaurant",
            "type":"Food & Drink"
        }
    ],
    "sg:phone":"+1 303 444 8886",
    "sg:postcode":"80304",
    "sg:province":"CO",
    "wof:name":"China Town Express",
    "wof:placetype":"venue"
},
  "geometry": {"coordinates":[-105.261473,40.028518],"type":"Point"}
}