{
  "type": "Feature",
  "properties": {
    "addr:full":"917 Lincoln Ave Steamboat Spgs CO 80487",
    "addr:housenumber":"917",
    "addr:postcode":"80487",
    "addr:street":"Lincoln Ave;Spgs",
    "iso:country":"US",
    "sg:address":"917 Lincoln Ave",
    "sg:city":"Steamboat Spgs",
    "sg:classifiers":[
        {
            "category":"Restaurant",
            "type":"Food & Drink"
        }
    ],
    "sg:phone":"+1 970 879 2405",
    "sg:postcode":"80487",
    "sg:province":"CO",
    "sg:tags":[
        "pizza"
    ],
    "sg:website":"www.mazzolas.com",
    "wof:name":"Mazzola's Italian Restaurant",
    "wof:placetype":"venue"
},
  "geometry": {"coordinates":[-106.836536,40.487158],"type":"Point"}
}