{
  "type": "Feature",
  "properties": {
    "iso:country":"US",
    "sg:address":"5475 Peoria St",
    "sg:city":"Denver",
    "sg:classifiers":[
        {
            "category":"Professional",
            "subcategory":"Management & Consulting",
            "type":"Services"
        }
    ],
    "sg:phone":"+1 303 576 0305",
    "sg:postcode":"80239",
    "sg:province":"CO",
    "sg:tags":[
        "poultry",
        "seafood",
        "meat"
    ],
    "wof:name":"More Than Seafood Inc",
    "wof:placetype":"venue"
},
  "geometry": {"coordinates":[-104.847223,39.794742],"type":"Point"}
}