{
  "type": "Feature",
  "properties": {
    "addr:full":"9950 W Vassar Way Denver CO 80227",
    "addr:housenumber":"9950",
    "addr:postcode":"80227",
    "addr:street":"W Vassar Way",
    "iso:country":"US",
    "sg:address":"9950 W Vassar Way",
    "sg:city":"Denver",
    "sg:classifiers":[
        {
            "category":"Manufacturing",
            "subcategory":"Glass & Minerals",
            "type":"Manufacturing & Wholesale Goods"
        }
    ],
    "sg:phone":"+1 303 989 5496",
    "sg:postcode":"80227",
    "sg:province":"CO",
    "sg:tags":[
        "painting",
        "product",
        "oil",
        "art",
        "stain"
    ],
    "wof:name":"Lone Wolf Studios",
    "wof:placetype":"venue"
},
  "geometry": {"coordinates":[-105.108172,39.668481],"type":"Point"}
}