{
  "type": "Feature",
  "properties": {
    "addr:full":"3265 S Wadsworth Blvd Lakewood CO 80227",
    "addr:housenumber":"3265",
    "addr:postcode":"80227",
    "addr:street":"S Wadsworth Blvd",
    "iso:country":"US",
    "sg:address":"3265 S Wadsworth Blvd",
    "sg:city":"Lakewood",
    "sg:classifiers":[
        {
            "category":"Food & Beverages",
            "subcategory":"Bakery",
            "type":"Retail Goods"
        }
    ],
    "sg:phone":"+1 303 986 0430",
    "sg:postcode":"80227",
    "sg:province":"CO",
    "sg:tags":[
        "baker"
    ],
    "wof:name":"Sweet Traditions",
    "wof:placetype":"venue"
},
  "geometry": {"coordinates":[-105.081453,39.657627],"type":"Point"}
}