{
  "type": "Feature",
  "properties": {
    "iso:country":"US",
    "sg:address":"2654 S Broadway",
    "sg:city":"Denver",
    "sg:classifiers":[
        {
            "category":"Professional",
            "subcategory":"Business Services",
            "type":"Services"
        }
    ],
    "sg:phone":"+1 720 570 4545",
    "sg:postcode":"80210",
    "sg:province":"CO",
    "sg:tags":[
        "recording",
        "studio"
    ],
    "wof:name":"Grand Sound Studio",
    "wof:placetype":"venue"
},
  "geometry": {"coordinates":[-104.98750200000001,39.668675],"type":"Point"}
}