{
  "type": "Feature",
  "properties": {
    "iso:country":"US",
    "sg:address":"2243 Lamplight Ct",
    "sg:city":"Grand Junction",
    "sg:classifiers":[
        {
            "category":"Wholesale",
            "subcategory":"Electrical",
            "type":"Manufacturing & Wholesale Goods"
        }
    ],
    "sg:phone":"+1 970 243 2558",
    "sg:postcode":"81503",
    "sg:province":"CO",
    "sg:tags":[
        "telecommunication"
    ],
    "wof:name":"Custom Music & Communications",
    "wof:placetype":"venue"
},
  "geometry": {"coordinates":[-108.638221,39.087799],"type":"Point"}
}