{
  "type": "Feature",
  "properties": {
    "iso:country":"US",
    "sg:address":"6666 W Quincy Ave",
    "sg:city":"Denver",
    "sg:classifiers":[
        {
            "category":"Travel",
            "subcategory":"Travel Agent",
            "type":"Entertainment"
        }
    ],
    "sg:phone":"+1 303 794 1929",
    "sg:postcode":"80235",
    "sg:province":"CO",
    "sg:tags":[
        "agency",
        "bureau"
    ],
    "wof:name":"AWWA Travel Svc",
    "wof:placetype":"venue"
},
  "geometry": {"coordinates":[-105.069952,39.63867],"type":"Point"}
}