{
  "type": "Feature",
  "properties": {
    "addr:full":"11455 Washington St Denver CO 80233",
    "addr:housenumber":"11455",
    "addr:postcode":"80233",
    "addr:street":"Washington St",
    "iso:country":"US",
    "sg:address":"11455 Washington St",
    "sg:city":"Denver",
    "sg:classifiers":[
        {
            "category":"Shopping",
            "subcategory":"Optical Goods",
            "type":"Retail Goods"
        }
    ],
    "sg:phone":"+1 303 451 0789",
    "sg:postcode":"80233",
    "sg:province":"CO",
    "wof:name":"North Valley Optical",
    "wof:placetype":"venue"
},
  "geometry": {"coordinates":[-104.977859,39.903962],"type":"Point"}
}