{
  "type": "Feature",
  "properties": {
    "iso:country":"US",
    "sg:address":"1375 N Ellicott Hwy",
    "sg:city":"Calhan",
    "sg:classifiers":[
        {
            "category":"Home & Garden",
            "subcategory":"Building Materials",
            "type":"Retail Goods"
        }
    ],
    "sg:phone":"+1 719 683 4680",
    "sg:postcode":"80808",
    "sg:province":"CO",
    "sg:tags":[
        "door"
    ],
    "wof:name":"Appalachian Wood Works",
    "wof:placetype":"venue"
},
  "geometry": {"coordinates":[-104.387242,38.852135],"type":"Point"}
}