{
  "type": "Feature",
  "properties": {
    "iso:country":"US",
    "sg:address":"5453 Fox Run Blvd",
    "sg:city":"Longmont",
    "sg:classifiers":[
        {
            "category":"Building & Trades",
            "subcategory":"Construction",
            "type":"Services"
        }
    ],
    "sg:phone":"+1 303 772 7054",
    "sg:postcode":"80504",
    "sg:province":"CO",
    "sg:tags":[
        "house"
    ],
    "wof:name":"J&M Construction",
    "wof:placetype":"venue"
},
  "geometry": {"coordinates":[-104.952208,40.126468],"type":"Point"}
}