{
  "type": "Feature",
  "properties": {
    "iso:country":"US",
    "sg:address":"2425 Grand Ave",
    "sg:city":"Glenwood Springs",
    "sg:classifiers":[
        {
            "category":"Professional",
            "subcategory":"Accounting & Tax Preparation",
            "type":"Services"
        }
    ],
    "sg:phone":"+1 970 945 5678",
    "sg:postcode":"81601",
    "sg:province":"CO",
    "sg:tags":[
        "accountant"
    ],
    "wof:name":"CPA Svc Pro Inc",
    "wof:placetype":"venue"
},
  "geometry": {"coordinates":[-107.325424,39.52867],"type":"Point"}
}