{
  "type": "Feature",
  "properties": {
    "iso:country":"US",
    "sg:address":"19680 Oasis Ave",
    "sg:city":"Peyton",
    "sg:classifiers":[
        {
            "category":"Building & Trades",
            "subcategory":"Construction",
            "type":"Services"
        }
    ],
    "sg:phone":"+1 719 649 8911",
    "sg:postcode":"80831",
    "sg:province":"CO",
    "sg:tags":[
        "handyman"
    ],
    "wof:name":"High Plains Handyman & Mntnc",
    "wof:placetype":"venue"
},
  "geometry": {"coordinates":[-104.45604899999999,38.934272],"type":"Point"}
}