{
  "type": "Feature",
  "properties": {
    "addr:full":"140 Grand Ave Paonia CO 81428",
    "addr:housenumber":"140",
    "addr:postcode":"81428",
    "addr:street":"Grand Ave",
    "iso:country":"US",
    "sg:address":"140 Grand Ave",
    "sg:city":"Paonia",
    "sg:classifiers":[
        {
            "category":"Education",
            "subcategory":"Library",
            "type":"Public Place"
        }
    ],
    "sg:phone":"+1 970 527 3470",
    "sg:postcode":"81428",
    "sg:province":"CO",
    "wof:name":"Paonia Public Library",
    "wof:placetype":"venue"
},
  "geometry": {"coordinates":[-107.597926,38.86646],"type":"Point"}
}