{
  "type": "Feature",
  "properties": {
    "iso:country":"US",
    "sg:address":"2621 E Boulder St",
    "sg:city":"Colorado Springs",
    "sg:classifiers":[
        {
            "category":"Retail",
            "subcategory":"Auto Repair",
            "type":"Services"
        }
    ],
    "sg:phone":"+1 719 477 9716",
    "sg:postcode":"80909",
    "sg:province":"CO",
    "sg:tags":[
        "repairing",
        "automobile"
    ],
    "wof:name":"Wrench's Complete Auto Care",
    "wof:placetype":"venue"
},
  "geometry": {"coordinates":[-104.77777,38.838021],"type":"Point"}
}