{
  "type": "Feature",
  "properties": {
    "iso:country":"US",
    "sg:address":"30488 US Hwy 50",
    "sg:city":"La Junta",
    "sg:classifiers":[
        {
            "category":"Retail",
            "subcategory":"Veterinary Services",
            "type":"Services"
        }
    ],
    "sg:phone":"+1 719 384 8111",
    "sg:postcode":"81050",
    "sg:province":"CO",
    "wof:name":"Colorado Vet Clinic",
    "wof:placetype":"venue"
},
  "geometry": {"coordinates":[-103.516223,37.986227],"type":"Point"}
}