{
  "type": "Feature",
  "properties": {
    "addr:full":"1490 Lafayette Street Suite 407 Denver CO 80218",
    "addr:housenumber":"1490",
    "addr:postcode":"80218",
    "addr:street":"Lafayette Street Suite 407",
    "iso:country":"US",
    "sg:address":"1490 Lafayette Street Suite 407",
    "sg:city":"Denver",
    "sg:classifiers":[
        {
            "category":"Professional",
            "subcategory":"Lawyer & Legal Services",
            "type":"Services"
        }
    ],
    "sg:phone":"+1 303 832 2770",
    "sg:postcode":"80218",
    "sg:province":"CO",
    "wof:name":"Finck Barry Russell Attorney At Law",
    "wof:placetype":"venue"
},
  "geometry": {"coordinates":[-104.970675,39.739797],"type":"Point"}
}