{
  "type": "Feature",
  "properties": {
    "addr:full":"375 Federal Blvd Denver CO 80219",
    "addr:housenumber":"375",
    "addr:postcode":"80219",
    "addr:street":"Federal Blvd",
    "iso:country":"US",
    "sg:address":"375 Federal Blvd",
    "sg:city":"Denver",
    "sg:classifiers":[
        {
            "category":"Shopping",
            "subcategory":"Clothing, Apparel, & Fashions",
            "type":"Retail Goods"
        }
    ],
    "sg:phone":"+1 303 742 8822",
    "sg:postcode":"80219",
    "sg:province":"CO",
    "wof:name":"Latino's Fashion",
    "wof:placetype":"venue"
},
  "geometry": {"coordinates":[-105.025115,39.722899],"type":"Point"}
}