{
  "type": "Feature",
  "properties": {
    "addr:full":"414 S Robinson Ave Florence CO 81226",
    "addr:housenumber":"414",
    "addr:postcode":"81226",
    "addr:street":"S Robinson Ave",
    "iso:country":"US",
    "sg:address":"414 S Robinson Ave",
    "sg:city":"Florence",
    "sg:classifiers":[
        {
            "category":"Personal",
            "subcategory":"Beauty Salon",
            "type":"Services"
        }
    ],
    "sg:phone":"+1 719 276 1832",
    "sg:postcode":"81226",
    "sg:province":"CO",
    "sg:tags":[
        "manicuring"
    ],
    "wof:name":"All About Nails",
    "wof:placetype":"venue"
},
  "geometry": {"coordinates":[-105.11275999999999,38.385924],"type":"Point"}
}