{
  "type": "Feature",
  "properties": {
    "iso:country":"US",
    "sg:address":"13430 Co Rd 102",
    "sg:city":"Elbert",
    "sg:classifiers":[
        {
            "category":"Building & Trades",
            "subcategory":"Construction",
            "type":"Services"
        }
    ],
    "sg:phone":"+1 303 648 3163",
    "sg:postcode":"80106",
    "sg:province":"CO",
    "sg:tags":[
        "carpentry",
        "contractor"
    ],
    "wof:name":"RLM Frame & Trim",
    "wof:placetype":"venue"
},
  "geometry": {"coordinates":[-104.413245,39.237729],"type":"Point"}
}