{
  "type": "Feature",
  "properties": {
    "iso:country":"US",
    "sg:address":"715 16th St",
    "sg:city":"Denver",
    "sg:classifiers":[
        {
            "category":"Shopping",
            "subcategory":"Gifts & Souvenirs",
            "type":"Retail Goods"
        }
    ],
    "sg:phone":"+1 303 446 8640",
    "sg:postcode":"80211",
    "sg:province":"CO",
    "sg:tags":[
        "shop"
    ],
    "wof:name":"Wild West Of America",
    "wof:placetype":"venue"
},
  "geometry": {"coordinates":[-104.992935,39.745817],"type":"Point"}
}