{
  "type": "Feature",
  "properties": {
    "iso:country":"US",
    "sg:address":"9051 Harlan St",
    "sg:city":"Westminster",
    "sg:classifiers":[
        {
            "category":"Recreation",
            "subcategory":"Arcade",
            "type":"Entertainment"
        }
    ],
    "sg:phone":"+1 303 427 9336",
    "sg:postcode":"80031",
    "sg:province":"CO",
    "sg:tags":[
        "device",
        "operator",
        "amusement"
    ],
    "sg:website":"www.laserstorm.net",
    "wof:name":"Laser Storm",
    "wof:placetype":"venue"
},
  "geometry": {"coordinates":[-105.064007,39.858601],"type":"Point"}
}