{
  "type": "Feature",
  "properties": {
    "iso:country":"US",
    "sg:address":"119 Via Vallecito",
    "sg:city":"Manitou Springs",
    "sg:classifiers":[
        {
            "category":"Professional",
            "subcategory":"Research",
            "type":"Services"
        }
    ],
    "sg:phone":"+1 719 685 1575",
    "sg:postcode":"80829",
    "sg:province":"CO",
    "sg:tags":[
        "development",
        "marketing",
        "product"
    ],
    "wof:name":"Smith & Assoc LTD",
    "wof:placetype":"venue"
},
  "geometry": {"coordinates":[-104.896096,38.861521],"type":"Point"}
}