{
  "type": "Feature",
  "properties": {
    "iso:country":"US",
    "sg:address":"1865 W Union Ave",
    "sg:city":"Englewood",
    "sg:classifiers":[
        {
            "category":"Building & Trades",
            "subcategory":"Construction",
            "type":"Services"
        }
    ],
    "sg:phone":"+1 303 783 5407",
    "sg:postcode":"80110",
    "sg:province":"CO",
    "sg:tags":[
        "painter"
    ],
    "wof:name":"S & S Painting Inc",
    "wof:placetype":"venue"
},
  "geometry": {"coordinates":[-105.009508,39.632355],"type":"Point"}
}