{
  "type": "Feature",
  "properties": {
    "addr:full":"1109 Main St Limon CO 80828",
    "addr:housenumber":"1109",
    "addr:postcode":"80828",
    "addr:street":"Main St",
    "iso:country":"US",
    "sg:address":"1109 Main St",
    "sg:city":"Limon",
    "sg:phone":"+1 719 775 2846",
    "sg:postcode":"80828",
    "sg:province":"CO",
    "sg:tags":[
        "gas"
    ],
    "wof:name":"D-J Petroleum Inc",
    "wof:placetype":"venue"
},
  "geometry": {"coordinates":[-103.69068900000001,39.262824],"type":"Point"}
}