{
  "type": "Feature",
  "properties": {
    "iso:country":"US",
    "sg:address":"318 3rd St",
    "sg:city":"Las Animas",
    "sg:classifiers":[
        {
            "category":"Organizations",
            "subcategory":"Community Association",
            "type":"Services"
        }
    ],
    "sg:phone":"+1 719 456 2822",
    "sg:postcode":"81054",
    "sg:province":"CO",
    "sg:tags":[
        "fraternal"
    ],
    "wof:name":"Veterans Of Foreign Wars",
    "wof:placetype":"venue"
},
  "geometry": {"coordinates":[-103.221054,38.070412],"type":"Point"}
}