{
  "type": "Feature",
  "properties": {
    "iso:country":"US",
    "sg:address":"2465 S Downing Street Suite 109",
    "sg:city":"Denver",
    "sg:classifiers":[
        {
            "category":"Health Services",
            "subcategory":"Optometrist",
            "type":"Services"
        }
    ],
    "sg:phone":"+1 303 698 2020",
    "sg:postcode":"80210",
    "sg:province":"CO",
    "wof:name":"Low Vision Center",
    "wof:placetype":"venue"
},
  "geometry": {"coordinates":[-104.973463,39.671786],"type":"Point"}
}