{
  "type": "Feature",
  "properties": {
    "addr:full":"734 Chambers Ave Eagle CO 81631",
    "addr:housenumber":"734",
    "addr:postcode":"81631",
    "addr:street":"Chambers Ave",
    "iso:country":"US",
    "sg:address":"734 Chambers Ave",
    "sg:city":"Eagle",
    "sg:classifiers":[
        {
            "category":"Retail",
            "subcategory":"Veterinary Services",
            "type":"Services"
        }
    ],
    "sg:phone":"+1 970 328 5444",
    "sg:postcode":"81631",
    "sg:province":"CO",
    "sg:tags":[
        "veterinarian"
    ],
    "wof:name":"Castle Peak Veterinary Svc",
    "wof:placetype":"venue"
},
  "geometry": {"coordinates":[-106.82477900000001,39.659669],"type":"Point"}
}