{
  "type": "Feature",
  "properties": {
    "iso:country":"US",
    "sg:address":"8920 Ithaca Way",
    "sg:city":"Westminster",
    "sg:classifiers":[
        {
            "category":"Professional",
            "type":"Services"
        }
    ],
    "sg:phone":"+1 303 430 9298",
    "sg:postcode":"80031",
    "sg:province":"CO",
    "wof:name":"Sils Gem & Mineral",
    "wof:placetype":"venue"
},
  "geometry": {"coordinates":[-105.03044199999999,39.857624],"type":"Point"}
}