{
  "type": "Feature",
  "properties": {
    "iso:country":"US",
    "sg:address":"696 N Circle Dr",
    "sg:city":"Colorado Springs",
    "sg:classifiers":[
        {
            "category":"Professional",
            "subcategory":"Computer Services",
            "type":"Services"
        }
    ],
    "sg:phone":"+1 719 633 3244",
    "sg:postcode":"80909",
    "sg:province":"CO",
    "sg:tags":[
        "repair"
    ],
    "wof:name":"Fixingputers Inc",
    "wof:placetype":"venue"
},
  "geometry": {"coordinates":[-104.775909,38.841015],"type":"Point"}
}