{
  "type": "Feature",
  "properties": {
    "iso:country":"US",
    "sg:address":"1631 Wazee St",
    "sg:city":"Denver",
    "sg:classifiers":[
        {
            "category":"Building & Trades",
            "subcategory":"Locksmith",
            "type":"Services"
        }
    ],
    "sg:phone":"+1 303 457 1730",
    "sg:postcode":"80202",
    "sg:province":"CO",
    "sg:tags":[
        "key"
    ],
    "sg:website":"www.completelocksmith.com/?cid=d...",
    "wof:name":"Denver Locksmith - Complete Locksmith Denver",
    "wof:placetype":"venue"
},
  "geometry": {"coordinates":[-104.999711,39.751924],"type":"Point"}
}