{
  "type": "Feature",
  "properties": {
    "iso:country":"US",
    "sg:address":"807 Lincoln Ave",
    "sg:city":"Steamboat Spgs",
    "sg:classifiers":[
        {
            "category":"Home & Garden",
            "subcategory":"Furniture",
            "type":"Retail Goods"
        }
    ],
    "sg:phone":"+1 970 879 8377",
    "sg:postcode":"80487",
    "sg:province":"CO",
    "sg:website":"www.intothewest.com",
    "wof:name":"Into The West",
    "wof:placetype":"venue"
},
  "geometry": {"coordinates":[-106.83571600000001,40.486675],"type":"Point"}
}