{
  "type": "Feature",
  "properties": {
    "addr:full":"3200 W 72nd Ave Westminster CO 80030",
    "addr:housenumber":"3200",
    "addr:postcode":"80030",
    "addr:street":"W 72Nd Ave",
    "iso:country":"US",
    "sg:address":"3200 W 72nd Ave",
    "sg:city":"Westminster",
    "sg:classifiers":[
        {
            "category":"Professional",
            "type":"Services"
        }
    ],
    "sg:phone":"+1 303 650 0726",
    "sg:postcode":"80030",
    "sg:province":"CO",
    "wof:name":"Earth & Moon",
    "wof:placetype":"venue"
},
  "geometry": {"coordinates":[-105.029608,39.827278],"type":"Point"}
}