{
  "type": "Feature",
  "properties": {
    "addr:full":"12768 Co Rd 26 Cortez CO 81321",
    "addr:housenumber":"12768;26",
    "addr:postcode":"81321",
    "addr:street":"Co Rd",
    "iso:country":"US",
    "sg:address":"12768 Co Rd 26",
    "sg:city":"Cortez",
    "sg:phone":"+1 970 565 9512",
    "sg:postcode":"81321",
    "sg:province":"CO",
    "sg:tags":[
        "farm",
        "field",
        "crop"
    ],
    "wof:name":"Danny W Vankuren",
    "wof:placetype":"venue"
},
  "geometry": {"coordinates":[-108.57270699999999,37.398451],"type":"Point"}
}