{
  "type": "Feature",
  "properties": {
    "addr:full":"1301 Florida Rd Durango CO 81301",
    "addr:housenumber":"1301",
    "addr:postcode":"co 81301",
    "addr:street":"Florida Rd",
    "iso:country":"US",
    "sg:address":"1301 Florida Rd",
    "sg:city":"Durango",
    "sg:classifiers":[
        {
            "category":"Personal",
            "subcategory":"Beauty Salon",
            "type":"Services"
        }
    ],
    "sg:phone":"+1 970 259 6770",
    "sg:postcode":"81301",
    "sg:province":"CO",
    "wof:name":"Salon By Teri",
    "wof:placetype":"venue"
},
  "geometry": {"coordinates":[-107.85316,37.296059],"type":"Point"}
}