{
  "type": "Feature",
  "properties": {
    "addr:full":"5000 Butte St Boulder CO 80301",
    "addr:housenumber":"5000",
    "addr:postcode":"80301",
    "addr:street":"Butte St",
    "iso:country":"US",
    "sg:address":"5000 Butte St",
    "sg:city":"Boulder",
    "sg:classifiers":[
        {
            "category":"Building & Trades",
            "subcategory":"Construction",
            "type":"Services"
        }
    ],
    "sg:phone":"+1 303 448 9539",
    "sg:postcode":"80301",
    "sg:province":"CO",
    "sg:tags":[
        "contractor"
    ],
    "wof:name":"B & M Siding",
    "wof:placetype":"venue"
},
  "geometry": {"coordinates":[-105.23674099999999,40.031031],"type":"Point"}
}