{
  "type": "Feature",
  "properties": {
    "addr:full":"3114 New Castle Dr Loveland CO 80538",
    "addr:housenumber":"3114",
    "addr:postcode":"80538",
    "addr:street":"New Castle Dr",
    "iso:country":"US",
    "sg:address":"3114 New Castle Dr",
    "sg:city":"Loveland",
    "sg:classifiers":[
        {
            "category":"Wholesale",
            "subcategory":"Stationery",
            "type":"Manufacturing & Wholesale Goods"
        }
    ],
    "sg:phone":"+1 970 663 0708",
    "sg:postcode":"80538",
    "sg:province":"CO",
    "sg:tags":[
        "supply"
    ],
    "wof:name":"Graphic Forms & Supply Inc",
    "wof:placetype":"venue"
},
  "geometry": {"coordinates":[-105.11914299999999,40.425559],"type":"Point"}
}