{
  "type": "Feature",
  "properties": {
    "iso:country":"US",
    "sg:address":"441 Wadsworth Blvd Ste 220",
    "sg:city":"Lakewood",
    "sg:classifiers":[
        {
            "category":"Building & Trades",
            "subcategory":"Cleaning & Sanitation",
            "type":"Services"
        }
    ],
    "sg:phone":"+1 303 703 9784",
    "sg:postcode":"80226",
    "sg:province":"CO",
    "sg:tags":[
        "home",
        "carpet"
    ],
    "sg:website":"www.mollymaid.com",
    "wof:name":"Molly Maid South Central",
    "wof:placetype":"venue"
},
  "geometry": {"coordinates":[-105.082357,39.722883],"type":"Point"}
}