{
  "type": "Feature",
  "properties": {
    "addr:full":"2744 Rigel Dr Colorado Springs CO 80906",
    "addr:housenumber":"2744",
    "addr:postcode":"80906",
    "addr:street":"Rigel Dr",
    "iso:country":"US",
    "sg:address":"2744 Rigel Dr",
    "sg:city":"Colorado Springs",
    "sg:classifiers":[
        {
            "category":"Real Estate",
            "subcategory":"Real Estate Operator",
            "type":"Services"
        }
    ],
    "sg:phone":"+1 719 634 2822",
    "sg:postcode":"80906",
    "sg:province":"CO",
    "sg:tags":[
        "building",
        "nonresidential"
    ],
    "wof:name":"Asl Properties LLC",
    "wof:placetype":"venue"
},
  "geometry": {"coordinates":[-104.86887299999999,38.81972],"type":"Point"}
}