{
  "type": "Feature",
  "properties": {
    "iso:country":"US",
    "sg:address":"3249 Lands End Ave",
    "sg:city":"Clifton",
    "sg:classifiers":[
        {
            "category":"Building & Trades",
            "subcategory":"Construction",
            "type":"Services"
        }
    ],
    "sg:phone":"+1 970 523 1732",
    "sg:postcode":"81520",
    "sg:province":"CO",
    "sg:tags":[
        "hanging",
        "contractor"
    ],
    "wof:name":"Castle Rock Painting Drywall",
    "wof:placetype":"venue"
},
  "geometry": {"coordinates":[-108.45087100000001,39.071593],"type":"Point"}
}