{
  "type": "Feature",
  "properties": {
    "addr:full":"210 W Main St Cortez CO 81321",
    "addr:housenumber":"210",
    "addr:postcode":"81321",
    "addr:street":"W Main St",
    "iso:country":"US",
    "sg:address":"210 W Main St",
    "sg:city":"Cortez",
    "sg:classifiers":[
        {
            "category":"Shopping",
            "subcategory":"Discount & Variety Stores",
            "type":"Retail Goods"
        }
    ],
    "sg:phone":"+1 970 565 7885",
    "sg:postcode":"81321",
    "sg:province":"CO",
    "sg:tags":[
        "department"
    ],
    "wof:name":"Dollar Man Plus",
    "wof:placetype":"venue"
},
  "geometry": {"coordinates":[-108.588204,37.348655],"type":"Point"}
}