{
  "type": "Feature",
  "properties": {
    "addr:full":"613 W Platte Ave Fort Morgan CO 80701",
    "addr:housenumber":"613",
    "addr:postcode":"80701",
    "addr:street":"W Platte Ave",
    "iso:country":"US",
    "sg:address":"613 W Platte Ave",
    "sg:city":"Fort Morgan",
    "sg:classifiers":[
        {
            "category":"Food & Beverages",
            "subcategory":"Bakery",
            "type":"Retail Goods"
        }
    ],
    "sg:phone":"+1 970 867 8169",
    "sg:postcode":"80701",
    "sg:province":"CO",
    "sg:tags":[
        "eating"
    ],
    "wof:name":"Coffee Break Shop",
    "wof:placetype":"venue"
},
  "geometry": {"coordinates":[-103.809974,40.254089],"type":"Point"}
}