{
  "type": "Feature",
  "properties": {
    "addr:full":"59370 State Hwy 69 Westcliffe CO 81252",
    "addr:housenumber":"59370",
    "addr:postcode":"81252",
    "addr:street":"State Hwy 69",
    "iso:country":"US",
    "sg:address":"59370 State Hwy 69",
    "sg:city":"Westcliffe",
    "sg:classifiers":[
        {
            "category":"Autos & Motor Vehicles",
            "subcategory":"Automobile Sales",
            "type":"Retail Goods"
        }
    ],
    "sg:phone":"+1 719 783 2428",
    "sg:postcode":"81252",
    "sg:province":"CO",
    "sg:tags":[
        "classic"
    ],
    "wof:name":"Strong Motor Co",
    "wof:placetype":"venue"
},
  "geometry": {"coordinates":[-105.47508999999999,38.145359],"type":"Point"}
}