{
  "type": "Feature",
  "properties": {
    "iso:country":"US",
    "sg:address":"6576 Fenton St",
    "sg:city":"Arvada",
    "sg:classifiers":[
        {
            "category":"Building & Trades",
            "subcategory":"Construction",
            "type":"Services"
        }
    ],
    "sg:phone":"+1 303 452 7375",
    "sg:postcode":"80003",
    "sg:province":"CO",
    "sg:tags":[
        "contractor"
    ],
    "wof:name":"Affiliated Roof Brokers",
    "wof:placetype":"venue"
},
  "geometry": {"coordinates":[-105.060271,39.81474],"type":"Point"}
}