{
  "type": "Feature",
  "properties": {
    "iso:country":"US",
    "sg:address":"7780 S Broadway",
    "sg:city":"Littleton",
    "sg:classifiers":[
        {
            "category":"Shopping",
            "type":"Retail Goods"
        }
    ],
    "sg:phone":"+1 303 795 5587",
    "sg:postcode":"80122",
    "sg:province":"CO",
    "sg:tags":[
        "hearing",
        "equipment",
        "supply",
        "impaired"
    ],
    "wof:name":"Linda Fudge",
    "wof:placetype":"venue"
},
  "geometry": {"coordinates":[-104.988398,39.574006],"type":"Point"}
}