{
  "type": "Feature",
  "properties": {
    "addr:full":"917 Park Street Castle Rock CO 80109",
    "addr:housenumber":"917",
    "addr:postcode":"80109",
    "addr:street":"Park Street",
    "iso:country":"US",
    "sg:address":"917 Park Street",
    "sg:city":"Castle Rock",
    "sg:classifiers":[
        {
            "category":"Bars & Pubs",
            "subcategory":"Lounge",
            "type":"Food & Drink"
        }
    ],
    "sg:phone":"+1 303 663 6633",
    "sg:postcode":"80109",
    "sg:province":"CO",
    "sg:website":"www.bustybullfrog.com",
    "wof:name":"The Busty Bullfrog",
    "wof:placetype":"venue"
},
  "geometry": {"coordinates":[-104.86592400000001,39.37916],"type":"Point"}
}