{
  "type": "Feature",
  "properties": {
    "addr:full":"333 E 4th St Loveland CO 80537",
    "addr:housenumber":"333",
    "addr:postcode":"80537",
    "addr:street":"E 4Th St",
    "iso:country":"US",
    "sg:address":"333 E 4th St",
    "sg:city":"Loveland",
    "sg:classifiers":[
        {
            "category":"Manufacturing",
            "subcategory":"Wood Products",
            "type":"Manufacturing & Wholesale Goods"
        },
        {
            "category":"Building & Trades",
            "subcategory":"Construction",
            "type":"Services"
        }
    ],
    "sg:phone":"+1 970 667 4222",
    "sg:postcode":"80537",
    "sg:province":"CO",
    "sg:tags":[
        "mfg",
        "woodworker"
    ],
    "sg:website":"www.coloradoheirloom.com",
    "wof:name":"Colorado Heirloom Inc",
    "wof:placetype":"venue"
},
  "geometry": {"coordinates":[-105.072879,40.39551],"type":"Point"}
}