{
  "type": "Feature",
  "properties": {
    "iso:country":"US",
    "sg:address":"7595 Federal Blvd",
    "sg:city":"Westminster",
    "sg:classifiers":[
        {
            "category":"Organizations",
            "subcategory":"Religious Organization",
            "type":"Services"
        }
    ],
    "sg:phone":"+1 303 428 3594",
    "sg:postcode":"80030",
    "sg:province":"CO",
    "sg:tags":[
        "church"
    ],
    "wof:name":"Holy Trinity Catholic Church",
    "wof:placetype":"venue"
},
  "geometry": {"coordinates":[-105.02508,39.833887],"type":"Point"}
}