{
  "type": "Feature",
  "properties": {
    "addr:full":"1932 W 130th Dr Denver CO 80234",
    "addr:housenumber":"1932",
    "addr:postcode":"80234",
    "addr:street":"W 130Th Dr",
    "iso:country":"US",
    "sg:address":"1932 W 130th Dr",
    "sg:city":"Denver",
    "sg:classifiers":[
        {
            "category":"Recreation",
            "type":"Entertainment"
        }
    ],
    "sg:phone":"+1 303 284 0092",
    "sg:postcode":"80234",
    "sg:province":"CO",
    "sg:tags":[
        "camps-recreational"
    ],
    "wof:name":"Summit Vision",
    "wof:placetype":"venue"
},
  "geometry": {"coordinates":[-105.011019,39.933174],"type":"Point"}
}