{
  "type": "Feature",
  "properties": {
    "addr:full":"1906 Blake Ave Glenwood Springs CO 81601",
    "addr:housenumber":"1906",
    "addr:postcode":"81601",
    "addr:street":"Blake Ave",
    "iso:country":"US",
    "sg:address":"1906 Blake Ave",
    "sg:city":"Glenwood Springs",
    "sg:classifiers":[
        {
            "category":"Health Services",
            "subcategory":"Hospital",
            "type":"Services"
        },
        {
            "category":"Health Services",
            "subcategory":"Health Practitioner",
            "type":"Services"
        }
    ],
    "sg:phone":"+1 970 945 6535",
    "sg:postcode":"81601",
    "sg:province":"CO",
    "sg:tags":[
        "therapist",
        "physical"
    ],
    "sg:website":"www.vvh.org",
    "wof:name":"Valley View Hospital Rehab",
    "wof:placetype":"venue"
},
  "geometry": {"coordinates":[-107.322693,39.532806],"type":"Point"}
}