{
  "type": "Feature",
  "properties": {
    "addr:full":"2336 Interstate Ave Grand Junction CO 81505",
    "addr:housenumber":"2336",
    "addr:postcode":"81505",
    "addr:street":"Interstate Ave",
    "iso:country":"US",
    "sg:address":"2336 Interstate Ave",
    "sg:city":"Grand Junction",
    "sg:classifiers":[
        {
            "category":"Building & Trades",
            "subcategory":"Construction",
            "type":"Services"
        }
    ],
    "sg:phone":"+1 970 245 1000",
    "sg:postcode":"81505",
    "sg:province":"CO",
    "sg:tags":[
        "nonresidential"
    ],
    "wof:name":"Cover Allspace Co",
    "wof:placetype":"venue"
},
  "geometry": {"coordinates":[-108.62312300000001,39.112715],"type":"Point"}
}