{
  "type": "Feature",
  "properties": {
    "addr:full":"4446 W Ponds Dr Littleton CO 80123",
    "addr:housenumber":"4446",
    "addr:postcode":"80123",
    "addr:street":"W Ponds Dr",
    "iso:country":"US",
    "sg:address":"4446 W Ponds Dr",
    "sg:city":"Littleton",
    "sg:classifiers":[
        {
            "category":"Real Estate",
            "subcategory":"Real Estate Agent",
            "type":"Services"
        }
    ],
    "sg:phone":"+1 303 798 8923",
    "sg:postcode":"80123",
    "sg:province":"CO",
    "wof:name":"Richlea",
    "wof:placetype":"venue"
},
  "geometry": {"coordinates":[-105.047483,39.603454],"type":"Point"}
}