{
  "type": "Feature",
  "properties": {
    "iso:country":"US",
    "sg:address":"3040 Frazier Ln",
    "sg:city":"Colorado Springs",
    "sg:classifiers":[
        {
            "category":"Shopping",
            "subcategory":"Computers & Home Electronics",
            "type":"Retail Goods"
        }
    ],
    "sg:phone":"+1 719 570 6136",
    "sg:postcode":"80922",
    "sg:province":"CO",
    "sg:tags":[
        "software"
    ],
    "wof:name":"SAS Institute Inc",
    "wof:placetype":"venue"
},
  "geometry": {"coordinates":[-104.700371,38.874937],"type":"Point"}
}