{
  "type": "Feature",
  "properties": {
    "addr:full":"2203 Blake Ave Glenwood Springs CO 81601",
    "addr:housenumber":"2203",
    "addr:postcode":"81601",
    "addr:street":"Blake Ave",
    "iso:country":"US",
    "sg:address":"2203 Blake Ave",
    "sg:city":"Glenwood Springs",
    "sg:classifiers":[
        {
            "category":"Wholesale",
            "subcategory":"Electrical",
            "type":"Manufacturing & Wholesale Goods"
        }
    ],
    "sg:phone":"+1 970 945 4461",
    "sg:postcode":"81601",
    "sg:province":"CO",
    "sg:tags":[
        "telecommunication"
    ],
    "wof:name":"Mountain Resort Communications",
    "wof:placetype":"venue"
},
  "geometry": {"coordinates":[-107.322328,39.529596],"type":"Point"}
}