{
  "type": "Feature",
  "properties": {
    "iso:country":"US",
    "sg:address":"59768 Co Rd Gg",
    "sg:city":"Burlington",
    "sg:classifiers":[
        {
            "category":"Farming",
            "subcategory":"Livestock Farm",
            "type":"Manufacturing & Wholesale Goods"
        }
    ],
    "sg:phone":"+1 719 397 2449",
    "sg:postcode":"80807",
    "sg:province":"CO",
    "sg:tags":[
        "beef",
        "feedlot",
        "cattle"
    ],
    "wof:name":"Witzell Farms",
    "wof:placetype":"venue"
},
  "geometry": {"coordinates":[-102.060744,39.462575],"type":"Point"}
}