{
  "type": "Feature",
  "properties": {
    "iso:country":"US",
    "sg:address":"2412 Highway 6 and 50",
    "sg:city":"Grand Junction",
    "sg:classifiers":[
        {
            "category":"Bakery",
            "type":"Food & Drink"
        }
    ],
    "sg:menulink":"http://www.allmenus.com/co/grand-junction/119088-krispy-kreme/menu/",
    "sg:phone":"+1 970 242 5392",
    "sg:postcode":"81505",
    "sg:province":"CO",
    "sg:tags":[
        "american",
        "pastry"
    ],
    "wof:name":"Krispy Kreme",
    "wof:placetype":"venue"
},
  "geometry": {"coordinates":[-108.605254,39.089924],"type":"Point"}
}