{
  "type": "Feature",
  "properties": {
    "addr:full":"2130 Arapahoe Ave Boulder CO 80302",
    "addr:housenumber":"2130",
    "addr:postcode":"80302",
    "addr:street":"Arapahoe Ave",
    "iso:country":"US",
    "sg:address":"2130 Arapahoe Ave",
    "sg:city":"Boulder",
    "sg:classifiers":[
        {
            "category":"Shopping",
            "subcategory":"Books",
            "type":"Retail Goods"
        }
    ],
    "sg:phone":"+1 303 546 3544",
    "sg:postcode":"80302",
    "sg:province":"CO",
    "sg:tags":[
        "store"
    ],
    "wof:name":"Naropa Bookstore",
    "wof:placetype":"venue"
},
  "geometry": {"coordinates":[-105.266604,40.014411],"type":"Point"}
}