{
  "type": "Feature",
  "properties": {
    "addr:full":"601 Salida Way Unit B11 Aurora CO 80011",
    "addr:housenumber":"601;b11",
    "addr:postcode":"80011",
    "addr:street":"Salida Way",
    "iso:country":"US",
    "sg:address":"601 Salida Way Unit B11",
    "sg:city":"Aurora",
    "sg:classifiers":[
        {
            "category":"Health Services",
            "subcategory":"Dentist",
            "type":"Services"
        }
    ],
    "sg:phone":"+1 303 340 3330",
    "sg:postcode":"80011",
    "sg:province":"CO",
    "sg:tags":[
        "dental",
        "clinic"
    ],
    "sg:website":"http://www.dentrustdental.com",
    "wof:name":"Dentrust Dental",
    "wof:placetype":"venue"
},
  "geometry": {"coordinates":[-104.786079,39.725639],"type":"Point"}
}