{
  "type": "Feature",
  "properties": {
    "addr:full":"3627 E 88th Cir S Denver CO 80229",
    "addr:housenumber":"3627",
    "addr:postcode":"80229",
    "addr:street":"E 88Th Cir",
    "iso:country":"US",
    "sg:address":"3627 E 88th Cir S",
    "sg:city":"Denver",
    "sg:classifiers":[
        {
            "category":"Building & Trades",
            "subcategory":"Construction",
            "type":"Services"
        }
    ],
    "sg:phone":"+1 303 210 5816",
    "sg:postcode":"80229",
    "sg:province":"CO",
    "sg:tags":[
        "concrete",
        "contractor"
    ],
    "wof:name":"G & M Concrete",
    "wof:placetype":"venue"
},
  "geometry": {"coordinates":[-104.943393,39.856608],"type":"Point"}
}