{
  "type": "Feature",
  "properties": {
    "addr:full":"3345 W 64th Ave Denver CO 80221",
    "addr:housenumber":"3345",
    "addr:postcode":"80221",
    "addr:street":"W 64Th Ave",
    "iso:country":"US",
    "sg:address":"3345 W 64th Ave",
    "sg:city":"Denver",
    "sg:classifiers":[
        {
            "category":"Manufacturing",
            "subcategory":"Signs",
            "type":"Manufacturing & Wholesale Goods"
        }
    ],
    "sg:phone":"+1 303 427 6405",
    "sg:postcode":"80221",
    "sg:province":"CO",
    "sg:tags":[
        "specialty",
        "mfg"
    ],
    "wof:name":"Progressive Signs LLC",
    "wof:placetype":"venue"
},
  "geometry": {"coordinates":[-105.031476,39.812904],"type":"Point"}
}