{
  "type": "Feature",
  "properties": {
    "iso:country":"US",
    "sg:address":"2403 E 148th Dr",
    "sg:city":"Thornton",
    "sg:classifiers":[
        {
            "category":"Building & Trades",
            "subcategory":"Construction",
            "type":"Services"
        }
    ],
    "sg:phone":"+1 303 457 2303",
    "sg:postcode":"80602",
    "sg:province":"CO",
    "sg:tags":[
        "home",
        "builder"
    ],
    "wof:name":"Engle Homes",
    "wof:placetype":"venue"
},
  "geometry": {"coordinates":[-104.95823900000001,39.964751],"type":"Point"}
}