{
  "type": "Feature",
  "properties": {
    "iso:country":"US",
    "sg:address":"7436 S Eagle St",
    "sg:city":"Centennial",
    "sg:classifiers":[
        {
            "category":"Retail",
            "subcategory":"Auto Repair",
            "type":"Services"
        }
    ],
    "sg:phone":"+1 303 617 1125",
    "sg:postcode":"80112",
    "sg:province":"CO",
    "sg:tags":[
        "repairing",
        "automobile"
    ],
    "wof:name":"Hot Shots Automotive Inc",
    "wof:placetype":"venue"
},
  "geometry": {"coordinates":[-104.817643,39.585173],"type":"Point"}
}