{
  "type": "Feature",
  "properties": {
    "addr:full":"506 S 12th St Lamar CO 81052",
    "addr:housenumber":"506",
    "addr:postcode":"81052",
    "addr:street":"S 12Th St",
    "iso:country":"US",
    "sg:address":"506 S 12th St",
    "sg:city":"Lamar",
    "sg:classifiers":[
        {
            "category":"Real Estate",
            "subcategory":"Real Estate Operator",
            "type":"Services"
        }
    ],
    "sg:phone":"+1 719 336 8959",
    "sg:postcode":"81052",
    "sg:province":"CO",
    "sg:tags":[
        "apartment"
    ],
    "wof:name":"Decant Apts",
    "wof:placetype":"venue"
},
  "geometry": {"coordinates":[-102.62934799999999,38.084821],"type":"Point"}
}