{
  "type": "Feature",
  "properties": {
    "iso:country":"US",
    "sg:address":"252 E Cheyenne Mountain Blvd",
    "sg:city":"Colorado Springs",
    "sg:classifiers":[
        {
            "category":"Restaurant",
            "type":"Food & Drink"
        }
    ],
    "sg:menulink":"http://www.allmenus.com/co/colorado-springs/4486-hatch-cover/menu/",
    "sg:phone":"+1 719 955 2073",
    "sg:postcode":"80906",
    "sg:province":"CO",
    "sg:tags":[
        "american"
    ],
    "wof:name":"Hatch Cover",
    "wof:placetype":"venue"
},
  "geometry": {"coordinates":[-104.823042,38.789263],"type":"Point"}
}