{
  "type": "Feature",
  "properties": {
    "addr:full":"22111 Co Rd 150 Agate CO 80101",
    "addr:housenumber":"22111;150",
    "addr:postcode":"80101",
    "addr:street":"Co Rd;Agate",
    "iso:country":"US",
    "sg:address":"22111 Co Rd 150",
    "sg:city":"Agate",
    "sg:classifiers":[
        {
            "category":"Retail",
            "subcategory":"Veterinary Services",
            "type":"Services"
        }
    ],
    "sg:phone":"+1 303 621 2304",
    "sg:postcode":"80101",
    "sg:province":"CO",
    "wof:name":"Prairie Wind Animal Refuge",
    "wof:placetype":"venue"
},
  "geometry": {"coordinates":[-104.252529,39.404367],"type":"Point"}
}