{
  "type": "Feature",
  "properties": {
    "addr:full":"6795 E Tennessee Avenue Denver CO 80224",
    "addr:housenumber":"6795",
    "addr:postcode":"80224",
    "addr:street":"E Tennessee Avenue",
    "iso:country":"US",
    "sg:address":"6795 E Tennessee Avenue",
    "sg:city":"Denver",
    "sg:classifiers":[
        {
            "category":"Organizations",
            "subcategory":"Non-profit Organization",
            "type":"Services"
        }
    ],
    "sg:phone":"+1 303 321 6363",
    "sg:postcode":"80224",
    "sg:province":"CO",
    "sg:tags":[
        "service/non-profit",
        "community"
    ],
    "wof:name":"Parent Pathways",
    "wof:placetype":"venue"
},
  "geometry": {"coordinates":[-104.909592,39.698474],"type":"Point"}
}