{
  "type": "Feature",
  "properties": {
    "addr:full":"501 16th St Denver CO 80202",
    "addr:housenumber":"501",
    "addr:postcode":"80202",
    "addr:street":"16Th St",
    "iso:country":"US",
    "sg:address":"501 16th St",
    "sg:city":"Denver",
    "sg:classifiers":[
        {
            "category":"Restaurant",
            "type":"Food & Drink"
        }
    ],
    "sg:menulink":"http://www.allmenus.com/co/denver/214316-marlowes/menu/",
    "sg:phone":"+1 303 595 3700",
    "sg:postcode":"80202",
    "sg:province":"CO",
    "sg:tags":[
        "american"
    ],
    "wof:name":"Marlowe's",
    "wof:placetype":"venue"
},
  "geometry": {"coordinates":[-104.990393,39.743888],"type":"Point"}
}