{
  "type": "Feature",
  "properties": {
    "addr:full":"4830 Artistic Cir Colorado Springs CO 80917",
    "addr:housenumber":"4830",
    "addr:postcode":"80917",
    "addr:street":"Artistic Cir",
    "iso:country":"US",
    "sg:address":"4830 Artistic Cir",
    "sg:city":"Colorado Springs",
    "sg:classifiers":[
        {
            "category":"Arts & Performance",
            "subcategory":"Theater",
            "type":"Entertainment"
        }
    ],
    "sg:phone":"+1 719 637 9965",
    "sg:postcode":"80917",
    "sg:province":"CO",
    "sg:tags":[
        "magician"
    ],
    "wof:name":"Inspector Magic",
    "wof:placetype":"venue"
},
  "geometry": {"coordinates":[-104.73725,38.888835],"type":"Point"}
}