{
  "type": "Feature",
  "properties": {
    "iso:country":"US",
    "sg:address":"1213 N Circle Dr",
    "sg:city":"Colorado Springs",
    "sg:classifiers":[
        {
            "category":"Restaurant",
            "type":"Food & Drink"
        }
    ],
    "sg:phone":"+1 719 574 8336",
    "sg:postcode":"80909",
    "sg:province":"CO",
    "wof:name":"New Panda 2",
    "wof:placetype":"venue"
},
  "geometry": {"coordinates":[-104.775741,38.85057],"type":"Point"}
}