{
  "type": "Feature",
  "properties": {
    "addr:full":"265 S Parkside Dr Colorado Springs CO 80910",
    "addr:housenumber":"265",
    "addr:postcode":"80910",
    "addr:street":"S Parkside Dr",
    "iso:country":"US",
    "sg:address":"265 S Parkside Dr",
    "sg:city":"Colorado Springs",
    "sg:classifiers":[
        {
            "category":"Health Services",
            "subcategory":"Doctor",
            "type":"Services"
        }
    ],
    "sg:phone":"+1 719 471 9942",
    "sg:postcode":"80910",
    "sg:province":"CO",
    "sg:tags":[
        "medical"
    ],
    "wof:name":"Curry Ken L MD",
    "wof:placetype":"venue"
},
  "geometry": {"coordinates":[-104.788916,38.828635],"type":"Point"}
}