{
  "type": "Feature",
  "properties": {
    "addr:full":"35486 Co Rd 13 Elizabeth CO 80107",
    "addr:housenumber":"35486;13",
    "addr:postcode":"80107",
    "addr:street":"Co Rd",
    "iso:country":"US",
    "sg:address":"35486 Co Rd 13",
    "sg:city":"Elizabeth",
    "sg:classifiers":[
        {
            "category":"Building & Trades",
            "subcategory":"Landscaping Services",
            "type":"Services"
        }
    ],
    "sg:phone":"+1 303 688 5679",
    "sg:postcode":"80107",
    "sg:province":"CO",
    "sg:tags":[
        "tree"
    ],
    "wof:name":"Ponderosa Tree Co",
    "wof:placetype":"venue"
},
  "geometry": {"coordinates":[-104.606831,39.383501],"type":"Point"}
}