{
  "type": "Feature",
  "properties": {
    "addr:full":"1195 Junction St Durango CO 81301",
    "addr:housenumber":"1195",
    "addr:postcode":"co 81301",
    "addr:street":"Junction St",
    "iso:country":"US",
    "sg:address":"1195 Junction St",
    "sg:city":"Durango",
    "sg:classifiers":[
        {
            "category":"Autos & Motor Vehicles",
            "subcategory":"Automobile Sales",
            "type":"Retail Goods"
        }
    ],
    "sg:phone":"+1 970 385 9512",
    "sg:postcode":"81301",
    "sg:province":"CO",
    "sg:tags":[
        "car",
        "dealer"
    ],
    "wof:name":"New Country Chrysler",
    "wof:placetype":"venue"
},
  "geometry": {"coordinates":[-107.87795699999999,37.293678],"type":"Point"}
}