{
  "type": "Feature",
  "properties": {
    "addr:full":"103 N Ford St Golden CO 80403",
    "addr:housenumber":"103",
    "addr:postcode":"80403",
    "addr:street":"N Ford St",
    "iso:country":"US",
    "sg:address":"103 N Ford St",
    "sg:city":"Golden",
    "sg:classifiers":[
        {
            "category":"Organizations",
            "subcategory":"Religious Organization",
            "type":"Services"
        }
    ],
    "sg:phone":"+1 303 273 9613",
    "sg:postcode":"80403",
    "sg:province":"CO",
    "sg:tags":[
        "church"
    ],
    "wof:name":"Hillside Community Church",
    "wof:placetype":"venue"
},
  "geometry": {"coordinates":[-105.228298,39.766477],"type":"Point"}
}