{
  "type": "Feature",
  "properties": {
    "addr:full":"31901 Co Rd 3u Genoa CO 80818",
    "addr:housenumber":"31901",
    "addr:postcode":"80818",
    "addr:street":"Co Rd",
    "iso:country":"US",
    "sg:address":"31901 Co Rd 3u",
    "sg:city":"Genoa",
    "sg:phone":"+1 719 763 2331",
    "sg:postcode":"80818",
    "sg:province":"CO",
    "sg:tags":[
        "farm",
        "corn",
        "wheat"
    ],
    "wof:name":"Boyd Farms LLP",
    "wof:placetype":"venue"
},
  "geometry": {"coordinates":[-103.473967,39.433047],"type":"Point"}
}