{
  "type": "Feature",
  "properties": {
    "iso:country":"US",
    "sg:address":"6762 W Coal Mine Ave",
    "sg:city":"Littleton",
    "sg:classifiers":[
        {
            "category":"Shopping",
            "subcategory":"Tobacco",
            "type":"Retail Goods"
        }
    ],
    "sg:phone":"+1 720 981 4811",
    "sg:postcode":"80123",
    "sg:province":"CO",
    "sg:tags":[
        "cigarette",
        "cigar",
        "dealer"
    ],
    "wof:name":"Cigarette Store",
    "wof:placetype":"venue"
},
  "geometry": {"coordinates":[-105.06974200000001,39.595217],"type":"Point"}
}