{
  "type": "Feature",
  "properties": {
    "addr:full":"1021 E South Boulder Rd Louisville CO 80027",
    "addr:housenumber":"1021 e",
    "addr:postcode":"80027",
    "addr:street":"South Boulder Rd",
    "iso:country":"US",
    "sg:address":"1021 E South Boulder Rd",
    "sg:city":"Louisville",
    "sg:classifiers":[
        {
            "category":"Organizations",
            "subcategory":"Religious Organization",
            "type":"Services"
        }
    ],
    "sg:phone":"+1 303 673 9658",
    "sg:postcode":"80027",
    "sg:province":"CO",
    "sg:tags":[
        "church"
    ],
    "wof:name":"Zoe Ministries",
    "wof:placetype":"venue"
},
  "geometry": {"coordinates":[-105.128557,39.987024],"type":"Point"}
}