{
  "type": "Feature",
  "properties": {
    "addr:full":"929 W Colorado Ave Colorado Springs CO 80905",
    "addr:housenumber":"929",
    "addr:postcode":"80905",
    "addr:street":"W Colorado Ave",
    "iso:country":"US",
    "sg:address":"929 W Colorado Ave",
    "sg:city":"Colorado Springs",
    "sg:classifiers":[
        {
            "category":"Professional",
            "subcategory":"Business Services",
            "type":"Services"
        }
    ],
    "sg:phone":"+1 719 636 9300",
    "sg:postcode":"80905",
    "sg:province":"CO",
    "wof:name":"Macvan The Map Store",
    "wof:placetype":"venue"
},
  "geometry": {"coordinates":[-104.841368,38.834708],"type":"Point"}
}