{
  "type": "Feature",
  "properties": {
    "addr:full":"2600 W Alameda Ave Denver CO 80219",
    "addr:housenumber":"2600",
    "addr:postcode":"80219",
    "addr:street":"W Alameda Ave",
    "iso:country":"US",
    "sg:address":"2600 W Alameda Ave",
    "sg:city":"Denver",
    "sg:classifiers":[
        {
            "category":"Restaurant",
            "type":"Food & Drink"
        }
    ],
    "sg:phone":"+1 303 934 2859",
    "sg:postcode":"80219",
    "sg:province":"CO",
    "sg:tags":[
        "mexican",
        "eating"
    ],
    "wof:name":"Los DOS Toros",
    "wof:placetype":"venue"
},
  "geometry": {"coordinates":[-105.018395,39.710844],"type":"Point"}
}