{
  "type": "Feature",
  "properties": {
    "iso:country":"US",
    "sg:address":"1 Co Rd 103",
    "sg:city":"Hesperus",
    "sg:classifiers":[
        {
            "category":"Building & Trades",
            "subcategory":"Construction",
            "type":"Services"
        }
    ],
    "sg:phone":"+1 970 588 3338",
    "sg:postcode":"81326",
    "sg:province":"CO",
    "sg:tags":[
        "masonry",
        "contractor"
    ],
    "wof:name":"Eaton Enterprises",
    "wof:placetype":"venue"
},
  "geometry": {"coordinates":[-108.16469499999999,37.096841],"type":"Point"}
}