{
  "type": "Feature",
  "properties": {
    "iso:country":"US",
    "sg:address":"7240 E Euclid Dr",
    "sg:city":"Centennial",
    "sg:classifiers":[
        {
            "category":"Real Estate",
            "subcategory":"Real Estate Agent",
            "type":"Services"
        }
    ],
    "sg:phone":"+1 303 393 0993",
    "sg:postcode":"80111",
    "sg:province":"CO",
    "sg:tags":[
        "investment"
    ],
    "wof:name":"405 South Hollaand",
    "wof:placetype":"venue"
},
  "geometry": {"coordinates":[-104.904837,39.596207],"type":"Point"}
}