{
  "type": "Feature",
  "properties": {
    "addr:full":"3290 S Bannock St Englewood CO 80110",
    "addr:housenumber":"3290",
    "addr:postcode":"80110",
    "addr:street":"S Bannock St",
    "iso:country":"US",
    "sg:address":"3290 S Bannock St",
    "sg:city":"Englewood",
    "sg:classifiers":[
        {
            "category":"Shopping",
            "type":"Retail Goods"
        }
    ],
    "sg:phone":"+1 303 781 1812",
    "sg:postcode":"80110",
    "sg:province":"CO",
    "sg:tags":[
        "communications",
        "consulting",
        "equipment"
    ],
    "wof:name":"Analog To Digital",
    "wof:placetype":"venue"
},
  "geometry": {"coordinates":[-104.989914,39.658448],"type":"Point"}
}