{
  "type": "Feature",
  "properties": {
    "iso:country":"US",
    "sg:address":"2178 Railroad Ave",
    "sg:city":"Rifle",
    "sg:classifiers":[
        {
            "category":"Bars & Pubs",
            "type":"Food & Drink"
        },
        {
            "category":"Restaurant",
            "type":"Food & Drink"
        },
        {
            "category":"Bars & Pubs",
            "subcategory":"Lounge",
            "type":"Food & Drink"
        }
    ],
    "sg:phone":"+1 970 625 9300",
    "sg:postcode":"81650",
    "sg:province":"CO",
    "sg:tags":[
        "brew",
        "cocktail"
    ],
    "sg:website":"http://www.wingnutzbarandgrill.com",
    "wof:name":"Wing Nutz Bar And Grill",
    "wof:placetype":"venue"
},
  "geometry": {"coordinates":[-107.78346,39.546047],"type":"Point"}
}