{
  "type": "Feature",
  "properties": {
    "iso:country":"US",
    "sg:address":"324 Cheyenne St",
    "sg:city":"Fort Morgan",
    "sg:classifiers":[
        {
            "category":"Professional",
            "type":"Services"
        }
    ],
    "sg:phone":"+1 970 867 4903",
    "sg:postcode":"80701",
    "sg:province":"CO",
    "wof:name":"Anthony R Ponce",
    "wof:placetype":"venue"
},
  "geometry": {"coordinates":[-103.813733,40.242298],"type":"Point"}
}