{
  "type": "Feature",
  "properties": {
    "addr:full":"130 Elk Trail Rd Durango CO 81301",
    "addr:housenumber":"130",
    "addr:postcode":"co 81301",
    "addr:street":"Elk Trail Rd",
    "iso:country":"US",
    "sg:address":"130 Elk Trail Rd",
    "sg:city":"Durango",
    "sg:classifiers":[
        {
            "category":"Retail",
            "subcategory":"Auto Repair",
            "type":"Services"
        }
    ],
    "sg:phone":"+1 970 385 1716",
    "sg:postcode":"81301",
    "sg:province":"CO",
    "sg:tags":[
        "general",
        "supply"
    ],
    "wof:name":"Durango 4 X 4",
    "wof:placetype":"venue"
},
  "geometry": {"coordinates":[-107.86864,37.33387],"type":"Point"}
}