{
  "type": "Feature",
  "properties": {
    "iso:country":"US",
    "sg:address":"4896 Marshall St.",
    "sg:city":"Wheat Ridge",
    "sg:classifiers":[
        {
            "category":"Building & Trades",
            "subcategory":"Construction",
            "type":"Services"
        }
    ],
    "sg:phone":"+1 303 423 1982",
    "sg:postcode":"80033",
    "sg:province":"CO",
    "sg:tags":[
        "air",
        "heating",
        "conditioning/hvac"
    ],
    "sg:website":"e-comforthome.com",
    "wof:name":"Four Seasons Heating & Home Comfort Solutions",
    "wof:placetype":"venue"
},
  "geometry": {"coordinates":[-105.067941,39.785224],"type":"Point"}
}