{
  "type": "Feature",
  "properties": {
    "iso:country":"US",
    "sg:address":"338 W Riverside Dr",
    "sg:city":"Estes Park",
    "sg:classifiers":[
        {
            "category":"Shopping",
            "subcategory":"Bicycles & Sporting Goods",
            "type":"Retail Goods"
        }
    ],
    "sg:phone":"+1 970 586 2110",
    "sg:postcode":"80517",
    "sg:province":"CO",
    "sg:tags":[
        "tackle",
        "fishing"
    ],
    "wof:name":"Estes Angler",
    "wof:placetype":"venue"
},
  "geometry": {"coordinates":[-105.522949,40.37442],"type":"Point"}
}