{
  "type": "Feature",
  "properties": {
    "iso:country":"US",
    "sg:address":"7260 W 119th Pl",
    "sg:city":"Broomfield",
    "sg:classifiers":[
        {
            "category":"Retail",
            "subcategory":"Auto Repair",
            "type":"Services"
        }
    ],
    "sg:phone":"+1 303 426 6729",
    "sg:postcode":"80020",
    "sg:province":"CO",
    "sg:tags":[
        "repairing",
        "automobile"
    ],
    "wof:name":"Vehicle Service Ctr",
    "wof:placetype":"venue"
},
  "geometry": {"coordinates":[-105.077388,39.913289],"type":"Point"}
}