{
  "type": "Feature",
  "properties": {
    "iso:country":"US",
    "sg:address":"8505 W Mountain View Ln",
    "sg:city":"Littleton",
    "sg:classifiers":[
        {
            "category":"Building & Trades",
            "subcategory":"Construction",
            "type":"Services"
        }
    ],
    "sg:phone":"+1 303 278 7444",
    "sg:postcode":"80125",
    "sg:province":"CO",
    "sg:tags":[
        "concrete",
        "crushing"
    ],
    "wof:name":"Porta Crusher Inc",
    "wof:placetype":"venue"
},
  "geometry": {"coordinates":[-105.046544,39.520832],"type":"Point"}
}