{
  "type": "Feature",
  "properties": {
    "addr:full":"7395 S Knolls Way Centennial CO 80122",
    "addr:housenumber":"7395",
    "addr:postcode":"80122",
    "addr:street":"S Knolls Way",
    "iso:country":"US",
    "sg:address":"7395 S Knolls Way",
    "sg:city":"Centennial",
    "sg:classifiers":[
        {
            "category":"Professional",
            "subcategory":"Management & Consulting",
            "type":"Services"
        }
    ],
    "sg:phone":"+1 720 489 0302",
    "sg:postcode":"80122",
    "sg:province":"CO",
    "sg:tags":[
        "marketing",
        "program"
    ],
    "wof:name":"Sage Consultants LLC",
    "wof:placetype":"venue"
},
  "geometry": {"coordinates":[-104.957534,39.584016],"type":"Point"}
}