{
  "type": "Feature",
  "properties": {
    "addr:full":"1511 W Alameda Ave Denver CO 80223",
    "addr:housenumber":"1511",
    "addr:postcode":"80223",
    "addr:street":"W Alameda Ave",
    "iso:country":"US",
    "sg:address":"1511 W Alameda Ave",
    "sg:city":"Denver",
    "sg:classifiers":[
        {
            "category":"Personal",
            "subcategory":"Beauty Salon",
            "type":"Services"
        }
    ],
    "sg:phone":"+1 303 698 0571",
    "sg:postcode":"80223",
    "sg:province":"CO",
    "wof:name":"Celia's Health & Beauty Aids",
    "wof:placetype":"venue"
},
  "geometry": {"coordinates":[-105.01097300000001,39.711264],"type":"Point"}
}