{
  "type": "Feature",
  "properties": {
    "iso:country":"US",
    "sg:address":"2401 Ford St",
    "sg:city":"Golden",
    "sg:classifiers":[
        {
            "category":"Shopping",
            "subcategory":"Bicycles & Sporting Goods",
            "type":"Retail Goods"
        }
    ],
    "sg:phone":"+1 303 216 2000",
    "sg:postcode":"80401",
    "sg:province":"CO",
    "sg:website":"www.bigringcycles.com",
    "wof:name":"Big Ring Cycles",
    "wof:placetype":"venue"
},
  "geometry": {"coordinates":[-105.20987599999999,39.746609],"type":"Point"}
}