{
  "type": "Feature",
  "properties": {
    "iso:country":"US",
    "sg:address":"9960 Wadsworth Pkwy",
    "sg:city":"Broomfield",
    "sg:classifiers":[
        {
            "category":"Restaurant",
            "type":"Food & Drink"
        }
    ],
    "sg:menulink":"http://www.allmenus.com/co/northeast-jefferson/68950-rosatis-pizza/menu/",
    "sg:phone":"+1 303 464 7477",
    "sg:postcode":"80021",
    "sg:province":"CO",
    "sg:tags":[
        "american",
        "pizza"
    ],
    "wof:name":"Rosati's Pizza",
    "wof:placetype":"venue"
},
  "geometry": {"coordinates":[-105.093529,39.877593],"type":"Point"}
}