{
  "type": "Feature",
  "properties": {
    "addr:full":"4695 S Windermere St Englewood CO 80110",
    "addr:housenumber":"4695",
    "addr:postcode":"80110",
    "addr:street":"S Windermere St",
    "iso:country":"US",
    "sg:address":"4695 S Windermere St",
    "sg:city":"Englewood",
    "sg:classifiers":[
        {
            "category":"Wholesale",
            "subcategory":"Groceries",
            "type":"Manufacturing & Wholesale Goods"
        }
    ],
    "sg:phone":"+1 303 934 5848",
    "sg:postcode":"80110",
    "sg:province":"CO",
    "sg:tags":[
        "food",
        "snack",
        "sandwich",
        "mfg"
    ],
    "wof:name":"A & A Sandwich Company Inc",
    "wof:placetype":"venue"
},
  "geometry": {"coordinates":[-105.00675200000001,39.630344],"type":"Point"}
}