{
  "type": "Feature",
  "properties": {
    "iso:country":"US",
    "sg:address":"333 Airport Blvd",
    "sg:city":"Aurora",
    "sg:classifiers":[
        {
            "category":"Home & Garden",
            "subcategory":"Building Materials",
            "type":"Retail Goods"
        },
        {
            "category":"Building & Trades",
            "subcategory":"Construction",
            "type":"Services"
        }
    ],
    "sg:phone":"+1 720 579 0320",
    "sg:postcode":"80011",
    "sg:province":"CO",
    "sg:tags":[
        "glass",
        "window",
        "contractor",
        "plate"
    ],
    "wof:name":"Courtesy Glass Co",
    "wof:placetype":"venue"
},
  "geometry": {"coordinates":[-104.791239,39.720687],"type":"Point"}
}