{
  "type": "Feature",
  "properties": {
    "iso:country":"US",
    "sg:address":"1750 W Mississippi Ave",
    "sg:city":"Denver",
    "sg:classifiers":[
        {
            "category":"Restaurant",
            "type":"Food & Drink"
        }
    ],
    "sg:phone":"+1 303 937 3957",
    "sg:postcode":"80223",
    "sg:province":"CO",
    "wof:name":"Sagitario",
    "wof:placetype":"venue"
},
  "geometry": {"coordinates":[-105.00778200000001,39.696649],"type":"Point"}
}