{
  "type": "Feature",
  "properties": {
    "iso:country":"US",
    "sg:address":"5840 W 25th Ave",
    "sg:city":"Edgewater",
    "sg:classifiers":[
        {
            "category":"Banks & Credit Unions",
            "subcategory":"Bank",
            "type":"Services"
        }
    ],
    "sg:phone":"+1 720 974 6099",
    "sg:postcode":"80214",
    "sg:province":"CO",
    "sg:tags":[
        "loan",
        "real estate"
    ],
    "wof:name":"Cherry Creek Mtg Edgewater",
    "wof:placetype":"venue"
},
  "geometry": {"coordinates":[-105.06102,39.752941],"type":"Point"}
}