{
  "type": "Feature",
  "properties": {
    "addr:full":"348 E Bridge St Brighton CO 80601",
    "addr:housenumber":"348",
    "addr:postcode":"80601",
    "addr:street":"E Bridge St",
    "iso:country":"US",
    "sg:address":"348 E Bridge St",
    "sg:city":"Brighton",
    "sg:classifiers":[
        {
            "category":"Retail",
            "subcategory":"Auto Repair",
            "type":"Services"
        }
    ],
    "sg:phone":"+1 303 654 1314",
    "sg:postcode":"80601",
    "sg:province":"CO",
    "sg:tags":[
        "general"
    ],
    "wof:name":"Total Car Care Inc",
    "wof:placetype":"venue"
},
  "geometry": {"coordinates":[-104.81866599999999,39.986734],"type":"Point"}
}