{
  "type": "Feature",
  "properties": {
    "addr:full":"2121 S Oneida St Denver CO 80224",
    "addr:housenumber":"2121",
    "addr:postcode":"80224",
    "addr:street":"S Oneida St",
    "iso:country":"US",
    "sg:address":"2121 S Oneida St",
    "sg:city":"Denver",
    "sg:classifiers":[
        {
            "category":"Health Services",
            "subcategory":"Health Practitioner",
            "type":"Services"
        }
    ],
    "sg:phone":"+1 303 694 7484",
    "sg:postcode":"80224",
    "sg:province":"CO",
    "sg:tags":[
        "info",
        "eating",
        "disorder",
        "treatment"
    ],
    "wof:name":"New Directions Eating Disorder",
    "wof:placetype":"venue"
},
  "geometry": {"coordinates":[-104.908281,39.677731],"type":"Point"}
}