{
  "type": "Feature",
  "properties": {
    "iso:country":"US",
    "sg:address":"31625 Co Rd D",
    "sg:city":"Brush",
    "sg:classifiers":[
        {
            "category":"Mining & Drilling",
            "type":"Manufacturing & Wholesale Goods"
        }
    ],
    "sg:phone":"+1 970 842 4057",
    "sg:postcode":"80723",
    "sg:province":"CO",
    "sg:tags":[
        "field"
    ],
    "wof:name":"Albert Teter",
    "wof:placetype":"venue"
},
  "geometry": {"coordinates":[-103.562928,40.045562],"type":"Point"}
}