{
  "type": "Feature",
  "properties": {
    "iso:country":"US",
    "sg:address":"558 Court Rd",
    "sg:city":"Grand Junction",
    "sg:classifiers":[
        {
            "category":"Manufacturing",
            "subcategory":"Motor Vehicles & Parts",
            "type":"Manufacturing & Wholesale Goods"
        }
    ],
    "sg:phone":"+1 970 242 1685",
    "sg:postcode":"81501",
    "sg:province":"CO",
    "sg:tags":[
        "mfg",
        "trimming"
    ],
    "wof:name":"Julies Edgings",
    "wof:placetype":"venue"
},
  "geometry": {"coordinates":[-108.531845,39.085819],"type":"Point"}
}