{
  "type": "Feature",
  "properties": {
    "iso:country":"US",
    "sg:address":"5390 E 60th Ave",
    "sg:city":"Commerce City",
    "sg:classifiers":[
        {
            "category":"Building & Trades",
            "subcategory":"Construction",
            "type":"Services"
        }
    ],
    "sg:phone":"+1 303 287 7866",
    "sg:postcode":"80022",
    "sg:province":"CO",
    "sg:tags":[
        "siding",
        "contractor"
    ],
    "wof:name":"Jacob's Siding",
    "wof:placetype":"venue"
},
  "geometry": {"coordinates":[-104.925186,39.805497],"type":"Point"}
}