{
  "type": "Feature",
  "properties": {
    "addr:full":"113 Latigo Ln Canon City CO 81212",
    "addr:housenumber":"113",
    "addr:postcode":"81212",
    "addr:street":"Latigo Ln",
    "iso:country":"US",
    "sg:address":"113 Latigo Ln",
    "sg:city":"Canon City",
    "sg:classifiers":[
        {
            "category":"Shopping",
            "subcategory":"Jewelry",
            "type":"Retail Goods"
        }
    ],
    "sg:phone":"+1 719 276 2760",
    "sg:postcode":"81212",
    "sg:province":"CO",
    "sg:tags":[
        "material",
        "mfg"
    ],
    "wof:name":"Jewelers",
    "wof:placetype":"venue"
},
  "geometry": {"coordinates":[-105.18242499999999,38.448798],"type":"Point"}
}