{
  "type": "Feature",
  "properties": {
    "addr:full":"616 Holland St Clifton CO 81520",
    "addr:housenumber":"616",
    "addr:postcode":"81520",
    "addr:street":"Holland St",
    "iso:country":"US",
    "sg:address":"616 Holland St",
    "sg:city":"Clifton",
    "sg:classifiers":[
        {
            "category":"Building & Trades",
            "subcategory":"Construction",
            "type":"Services"
        }
    ],
    "sg:phone":"+1 970 434 8514",
    "sg:postcode":"81520",
    "sg:province":"CO",
    "sg:tags":[
        "tile",
        "installation",
        "contractor"
    ],
    "wof:name":"B and B Installation",
    "wof:placetype":"venue"
},
  "geometry": {"coordinates":[-108.446656,39.09386],"type":"Point"}
}