{
  "type": "Feature",
  "properties": {
    "addr:full":"7275 W Montview Ln Littleton CO 80125",
    "addr:housenumber":"7275",
    "addr:postcode":"80125",
    "addr:street":"W Montview Ln",
    "iso:country":"US",
    "sg:address":"7275 W Montview Ln",
    "sg:city":"Littleton",
    "sg:classifiers":[
        {
            "category":"Shopping",
            "type":"Retail Goods"
        }
    ],
    "sg:phone":"+1 303 791 0698",
    "sg:postcode":"80125",
    "sg:province":"CO",
    "sg:tags":[
        "merchandise"
    ],
    "wof:name":"Designs By De",
    "wof:placetype":"venue"
},
  "geometry": {"coordinates":[-105.022266,39.520638],"type":"Point"}
}