{
  "type": "Feature",
  "properties": {
    "iso:country":"US",
    "sg:address":"395 Orofino Dr",
    "sg:city":"Castle Rock",
    "sg:classifiers":[
        {
            "category":"Shopping",
            "type":"Retail Goods"
        }
    ],
    "sg:phone":"+1 303 663 4778",
    "sg:postcode":"80108",
    "sg:province":"CO",
    "sg:tags":[
        "miscellaneous",
        "store"
    ],
    "wof:name":"L G Designs",
    "wof:placetype":"venue"
},
  "geometry": {"coordinates":[-104.892842,39.430819],"type":"Point"}
}