{
  "type": "Feature",
  "properties": {
    "addr:full":"3005 Inspiration Dr Colorado Springs CO 80917",
    "addr:housenumber":"3005",
    "addr:postcode":"80917",
    "addr:street":"Inspiration Dr",
    "iso:country":"US",
    "sg:address":"3005 Inspiration Dr",
    "sg:city":"Colorado Springs",
    "sg:classifiers":[
        {
            "category":"Professional",
            "subcategory":"Management & Consulting",
            "type":"Services"
        }
    ],
    "sg:phone":"+1 719 226 2355",
    "sg:postcode":"80917",
    "sg:province":"CO",
    "sg:tags":[
        "business"
    ],
    "wof:name":"Qual-Tech Analysis",
    "wof:placetype":"venue"
},
  "geometry": {"coordinates":[-104.733527,38.875801],"type":"Point"}
}