{
  "type": "Feature",
  "properties": {
    "iso:country":"US",
    "sg:address":"512 N Chelton Rd",
    "sg:city":"Colorado Springs",
    "sg:classifiers":[
        {
            "category":"Restaurant",
            "type":"Food & Drink"
        }
    ],
    "sg:menulink":"http://www.allmenus.com/co/colorado-springs/97145-ihop/menu/",
    "sg:phone":"+1 719 632 5098",
    "sg:postcode":"80909",
    "sg:province":"CO",
    "sg:tags":[
        "sandwich",
        "salad",
        "burger",
        "soup",
        "american",
        "steakhouse",
        "wrap"
    ],
    "wof:name":"IHOP",
    "wof:placetype":"venue"
},
  "geometry": {"coordinates":[-104.767025,38.840616],"type":"Point"}
}