{
  "type": "Feature",
  "properties": {
    "iso:country":"US",
    "sg:address":"1626 Detroit Street",
    "sg:city":"Denver",
    "sg:classifiers":[
        {
            "category":"Building & Trades",
            "subcategory":"Construction",
            "type":"Services"
        }
    ],
    "sg:phone":"+1 303 736 6739",
    "sg:postcode":"80206",
    "sg:province":"CO",
    "sg:tags":[
        "contractor"
    ],
    "sg:website":"frontrange.archadeck.com",
    "wof:name":"Archadeck of front range",
    "wof:placetype":"venue"
},
  "geometry": {"coordinates":[-104.95445,39.742541],"type":"Point"}
}