{
  "type": "Feature",
  "properties": {
    "addr:full":"719 4th St Crested Butte CO 81224",
    "addr:housenumber":"719",
    "addr:postcode":"81224",
    "addr:street":"4Th St",
    "iso:country":"US",
    "sg:address":"719 4th St",
    "sg:city":"Crested Butte",
    "sg:classifiers":[
        {
            "category":"Freight",
            "type":"Transportation"
        }
    ],
    "sg:phone":"+1 970 349 0778",
    "sg:postcode":"81224",
    "sg:province":"CO",
    "sg:tags":[
        "commercial",
        "storage"
    ],
    "wof:name":"Drop Shop",
    "wof:placetype":"venue"
},
  "geometry": {"coordinates":[-106.984244,38.86675],"type":"Point"}
}