{
  "type": "Feature",
  "properties": {
    "iso:country":"US",
    "sg:address":"17417 Co Rd 30",
    "sg:city":"Stratton",
    "sg:classifiers":[
        {
            "category":"Professional",
            "type":"Services"
        }
    ],
    "sg:phone":"+1 719 348 5696",
    "sg:postcode":"80836",
    "sg:province":"CO",
    "wof:name":"James R Foose",
    "wof:placetype":"venue"
},
  "geometry": {"coordinates":[-102.614057,39.291249],"type":"Point"}
}