{
  "type": "Feature",
  "properties": {
    "addr:full":"3775 Quitman St Denver CO 80212",
    "addr:housenumber":"3775",
    "addr:postcode":"80212",
    "addr:street":"Quitman St",
    "iso:country":"US",
    "sg:address":"3775 Quitman St",
    "sg:city":"Denver",
    "sg:classifiers":[
        {
            "category":"Autos & Motor Vehicles",
            "subcategory":"Auto Supplies",
            "type":"Retail Goods"
        }
    ],
    "sg:phone":"+1 303 433 4477",
    "sg:postcode":"80212",
    "sg:province":"CO",
    "sg:tags":[
        "wheel",
        "tire",
        "accessory"
    ],
    "wof:name":"Hoops Tire & Wheels Inc",
    "wof:placetype":"venue"
},
  "geometry": {"coordinates":[-105.040569,39.76806],"type":"Point"}
}