{
  "type": "Feature",
  "properties": {
    "addr:full":"2201 E 101st Ave Denver CO 80229",
    "addr:housenumber":"2201",
    "addr:postcode":"80229",
    "addr:street":"E 101St Ave",
    "iso:country":"US",
    "sg:address":"2201 E 101st Ave",
    "sg:city":"Denver",
    "sg:classifiers":[
        {
            "category":"Building & Trades",
            "subcategory":"Construction",
            "type":"Services"
        }
    ],
    "sg:phone":"+1 303 280 1080",
    "sg:postcode":"80229",
    "sg:province":"CO",
    "sg:tags":[
        "house"
    ],
    "wof:name":"Maria Castro Construction",
    "wof:placetype":"venue"
},
  "geometry": {"coordinates":[-104.96119299999999,39.879175],"type":"Point"}
}