{
  "type": "Feature",
  "properties": {
    "iso:country":"US",
    "sg:address":"1097 Aspen Ave",
    "sg:city":"Craig",
    "sg:classifiers":[
        {
            "category":"Building & Trades",
            "subcategory":"Construction",
            "type":"Services"
        }
    ],
    "sg:phone":"+1 970 824 5993",
    "sg:postcode":"81625",
    "sg:province":"CO",
    "sg:tags":[
        "contractor"
    ],
    "wof:name":"JTH Contracting",
    "wof:placetype":"venue"
},
  "geometry": {"coordinates":[-107.577395,40.52575],"type":"Point"}
}