{
  "type": "Feature",
  "properties": {
    "addr:full":"400 Banner Trl Florissant CO 80816",
    "addr:housenumber":"400",
    "addr:postcode":"80816",
    "addr:street":"Banner Trl",
    "iso:country":"US",
    "sg:address":"400 Banner Trl",
    "sg:city":"Florissant",
    "sg:classifiers":[
        {
            "category":"Manufacturing",
            "subcategory":"Signs",
            "type":"Manufacturing & Wholesale Goods"
        }
    ],
    "sg:phone":"+1 719 687 2507",
    "sg:postcode":"80816",
    "sg:province":"CO",
    "sg:tags":[
        "advertising",
        "specialty"
    ],
    "wof:name":"Chandler Signs Inc",
    "wof:placetype":"venue"
},
  "geometry": {"coordinates":[-105.224138,38.919645],"type":"Point"}
}