{
  "type": "Feature",
  "properties": {
    "iso:country":"US",
    "sg:address":"7545 S University Blvd",
    "sg:city":"Littleton",
    "sg:classifiers":[
        {
            "category":"Personal",
            "subcategory":"Barber",
            "type":"Services"
        }
    ],
    "sg:phone":"+1 303 738 0231",
    "sg:postcode":"80122",
    "sg:province":"CO",
    "sg:website":"www.sportclips.com",
    "wof:name":"Sport Clips",
    "wof:placetype":"venue"
},
  "geometry": {"coordinates":[-104.960441,39.578448],"type":"Point"}
}