{
  "type": "Feature",
  "properties": {
    "iso:country":"US",
    "sg:address":"466 S Main St",
    "sg:city":"Creede",
    "sg:classifiers":[
        {
            "category":"Travel",
            "subcategory":"Hotels & Motels",
            "type":"Entertainment"
        }
    ],
    "sg:phone":"+1 719 658 0215",
    "sg:postcode":"81130",
    "sg:province":"CO",
    "sg:tags":[
        "breakfast",
        "accommodation",
        "bed"
    ],
    "sg:website":"www.blessingsinn.com",
    "wof:name":"Blessings Inn",
    "wof:placetype":"venue"
},
  "geometry": {"coordinates":[-106.92617199999999,37.849739],"type":"Point"}
}