{
  "type": "Feature",
  "properties": {
    "iso:country":"US",
    "sg:address":"635 Southpointe Ct",
    "sg:city":"Colorado Springs",
    "sg:classifiers":[
        {
            "category":"Health Services",
            "subcategory":"Doctor",
            "type":"Services"
        }
    ],
    "sg:phone":"+1 719 579 0560",
    "sg:postcode":"80906",
    "sg:province":"CO",
    "sg:tags":[
        "dentist"
    ],
    "wof:name":"Forrest H Faulconer DDS PC",
    "wof:placetype":"venue"
},
  "geometry": {"coordinates":[-104.81744999999999,38.796584],"type":"Point"}
}