{
  "type": "Feature",
  "properties": {
    "iso:country":"US",
    "sg:address":"1120 Ford St",
    "sg:city":"Colorado Springs",
    "sg:classifiers":[
        {
            "category":"Retail",
            "subcategory":"Auto Repair",
            "type":"Services"
        }
    ],
    "sg:phone":"+1 719 596 4818",
    "sg:postcode":"80915",
    "sg:province":"CO",
    "sg:tags":[
        "automotive",
        "general"
    ],
    "wof:name":"Bowers Auto Griffith Auto &",
    "wof:placetype":"venue"
},
  "geometry": {"coordinates":[-104.711932,38.848256],"type":"Point"}
}