{
  "type": "Feature",
  "properties": {
    "addr:full":"1745 Main St Longmont CO 80501",
    "addr:housenumber":"1745",
    "addr:postcode":"80501",
    "addr:street":"Main St",
    "iso:country":"US",
    "sg:address":"1745 Main St",
    "sg:city":"Longmont",
    "sg:classifiers":[
        {
            "category":"Cinema",
            "subcategory":"Movie Rental",
            "type":"Entertainment"
        }
    ],
    "sg:phone":"+1 303 772 0370",
    "sg:postcode":"80501",
    "sg:province":"CO",
    "sg:tags":[
        "leasing",
        "video",
        "disc",
        "tape"
    ],
    "wof:name":"Showtime USA",
    "wof:placetype":"venue"
},
  "geometry": {"coordinates":[-105.10234800000001,40.19219],"type":"Point"}
}