{
  "type": "Feature",
  "properties": {
    "iso:country":"US",
    "sg:address":"620 E Wiggins St",
    "sg:city":"Louisville",
    "sg:classifiers":[
        {
            "category":"Building & Trades",
            "subcategory":"Equipment Rental",
            "type":"Services"
        }
    ],
    "sg:phone":"+1 303 499 0919",
    "sg:postcode":"80027",
    "sg:province":"CO",
    "wof:name":"Brad & Nancy Snyder",
    "wof:placetype":"venue"
},
  "geometry": {"coordinates":[-105.15978699999999,39.94625],"type":"Point"}
}