{
  "type": "Feature",
  "properties": {
    "addr:full":"16080 Smith Rd Aurora CO 80011",
    "addr:housenumber":"16080",
    "addr:postcode":"80011",
    "addr:street":"Smith Rd",
    "iso:country":"US",
    "sg:address":"16080 Smith Rd",
    "sg:city":"Aurora",
    "sg:classifiers":[
        {
            "category":"Freight",
            "type":"Transportation"
        }
    ],
    "sg:phone":"+1 303 366 4950",
    "sg:postcode":"80011",
    "sg:province":"CO",
    "sg:tags":[
        "hauling",
        "trucking"
    ],
    "wof:name":"Knight Transportation Inc",
    "wof:placetype":"venue"
},
  "geometry": {"coordinates":[-104.801991,39.757332],"type":"Point"}
}