{
  "type": "Feature",
  "properties": {
    "addr:full":"808 Bob Blvd Brush CO 80723",
    "addr:housenumber":"808",
    "addr:postcode":"80723",
    "addr:street":"Bob Blvd",
    "iso:country":"US",
    "sg:address":"808 Bob Blvd",
    "sg:city":"Brush",
    "sg:classifiers":[
        {
            "category":"Building & Trades",
            "subcategory":"Plumbing",
            "type":"Services"
        }
    ],
    "sg:phone":"+1 970 842 0906",
    "sg:postcode":"80723",
    "sg:province":"CO",
    "sg:tags":[
        "contractor"
    ],
    "wof:name":"Royal Flush Plumbing Serv",
    "wof:placetype":"venue"
},
  "geometry": {"coordinates":[-103.65210500000001,40.261682],"type":"Point"}
}