{
  "type": "Feature",
  "properties": {
    "iso:country":"US",
    "sg:address":"22 W North St",
    "sg:city":"Cortez",
    "sg:classifiers":[
        {
            "category":"Health Services",
            "subcategory":"Doctor",
            "type":"Services"
        }
    ],
    "sg:phone":"+1 970 565 2424",
    "sg:postcode":"81321",
    "sg:province":"CO",
    "sg:tags":[
        "dentist"
    ],
    "wof:name":"Ronald A Barr DDS",
    "wof:placetype":"venue"
},
  "geometry": {"coordinates":[-108.58548399999999,37.349771],"type":"Point"}
}