{
  "type": "Feature",
  "properties": {
    "addr:full":"6003 S Akron Way Englewood CO 80111",
    "addr:housenumber":"6003",
    "addr:postcode":"80111",
    "addr:street":"S Akron Way",
    "iso:country":"US",
    "sg:address":"6003 S Akron Way",
    "sg:city":"Englewood",
    "sg:classifiers":[
        {
            "category":"Professional",
            "type":"Services"
        }
    ],
    "sg:phone":"+1 303 850 7518",
    "sg:postcode":"80111",
    "sg:province":"CO",
    "wof:name":"Mea 847 LLC",
    "wof:placetype":"venue"
},
  "geometry": {"coordinates":[-104.884587,39.607534],"type":"Point"}
}