{
  "type": "Feature",
  "properties": {
    "addr:full":"1502 S Tejon St Colorado Springs CO 80906",
    "addr:housenumber":"1502",
    "addr:postcode":"80906",
    "addr:street":"S Tejon St",
    "iso:country":"US",
    "sg:address":"1502 S Tejon St",
    "sg:city":"Colorado Springs",
    "sg:classifiers":[
        {
            "category":"Food & Beverages",
            "subcategory":"Groceries & Convenience Stores",
            "type":"Retail Goods"
        }
    ],
    "sg:phone":"+1 719 632 5717",
    "sg:postcode":"80906",
    "sg:province":"CO",
    "sg:tags":[
        "station",
        "gasoline"
    ],
    "wof:name":"Circle K Store",
    "wof:placetype":"venue"
},
  "geometry": {"coordinates":[-104.825159,38.811763],"type":"Point"}
}