{
  "type": "Feature",
  "properties": {
    "addr:full":"61924 W Oak Grove Rd Montrose CO 81401",
    "addr:housenumber":"61924",
    "addr:postcode":"81401",
    "addr:street":"W Oak Grove Rd",
    "iso:country":"US",
    "sg:address":"61924 W Oak Grove Rd",
    "sg:city":"Montrose",
    "sg:classifiers":[
        {
            "category":"Manufacturing",
            "subcategory":"Retail Goods",
            "type":"Manufacturing & Wholesale Goods"
        }
    ],
    "sg:phone":"+1 970 249 9510",
    "sg:postcode":"81401",
    "sg:province":"CO",
    "sg:tags":[
        "manufacturer"
    ],
    "wof:name":"North American Snowsnakes",
    "wof:placetype":"venue"
},
  "geometry": {"coordinates":[-107.932191,38.460175],"type":"Point"}
}