{
  "type": "Feature",
  "properties": {
    "iso:country":"US",
    "sg:address":"1111 W Victory Way",
    "sg:city":"Craig",
    "sg:classifiers":[
        {
            "category":"Shopping",
            "subcategory":"Clothing, Apparel, & Fashions",
            "type":"Retail Goods"
        }
    ],
    "sg:phone":"+1 970 824 8531",
    "sg:postcode":"81625",
    "sg:province":"CO",
    "sg:tags":[
        "western",
        "wear"
    ],
    "wof:name":"Corral West Ranchwear",
    "wof:placetype":"venue"
},
  "geometry": {"coordinates":[-107.56043200000001,40.514264],"type":"Point"}
}