{
  "type": "Feature",
  "properties": {
    "addr:full":"2116 Gaylord St Denver CO 80205",
    "addr:housenumber":"2116",
    "addr:postcode":"80205",
    "addr:street":"Gaylord St",
    "iso:country":"US",
    "sg:address":"2116 Gaylord St",
    "sg:city":"Denver",
    "sg:classifiers":[
        {
            "category":"Professional",
            "subcategory":"Lawyer & Legal Services",
            "type":"Services"
        }
    ],
    "sg:phone":"+1 303 320 4173",
    "sg:postcode":"80205",
    "sg:province":"CO",
    "wof:name":"Nulan Darrel Atty",
    "wof:placetype":"venue"
},
  "geometry": {"coordinates":[-104.960795,39.748409],"type":"Point"}
}