{
  "type": "Feature",
  "properties": {
    "iso:country":"US",
    "sg:address":"18172 Co Rd 1",
    "sg:city":"Florissant",
    "sg:classifiers":[
        {
            "category":"Education",
            "subcategory":"Library",
            "type":"Public Place"
        }
    ],
    "sg:phone":"+1 719 748 3939",
    "sg:postcode":"80816",
    "sg:province":"CO",
    "wof:name":"Florissant Public Library",
    "wof:placetype":"venue"
},
  "geometry": {"coordinates":[-105.288771,38.945096],"type":"Point"}
}