{
  "type": "Feature",
  "properties": {
    "addr:full":"4211 E 100th Ave Denver CO 80229",
    "addr:housenumber":"4211",
    "addr:postcode":"80229",
    "addr:street":"E 100Th Ave",
    "iso:country":"US",
    "sg:address":"4211 E 100th Ave",
    "sg:city":"Denver",
    "sg:classifiers":[
        {
            "category":"Building & Trades",
            "subcategory":"Plumbing",
            "type":"Services"
        }
    ],
    "sg:phone":"+1 303 288 3061",
    "sg:postcode":"80229",
    "sg:province":"CO",
    "sg:tags":[
        "contractor"
    ],
    "wof:name":"Mrr Heating Air",
    "wof:placetype":"venue"
},
  "geometry": {"coordinates":[-104.940161,39.877379],"type":"Point"}
}