{
  "type": "Feature",
  "properties": {
    "addr:full":"2551 Big Thompson Canyon Rd Drake CO 80515",
    "addr:housenumber":"2551",
    "addr:postcode":"80515",
    "addr:street":"Big Thompson Canyon Rd",
    "iso:country":"US",
    "sg:address":"2551 Big Thompson Canyon Rd",
    "sg:city":"Drake",
    "sg:classifiers":[
        {
            "category":"Building & Trades",
            "subcategory":"Electrical",
            "type":"Services"
        }
    ],
    "sg:phone":"+1 970 586 9214",
    "sg:postcode":"80515",
    "sg:province":"CO",
    "sg:tags":[
        "electrical",
        "contractor"
    ],
    "wof:name":"D K Electric Co",
    "wof:placetype":"venue"
},
  "geometry": {"coordinates":[-105.464389,40.389692],"type":"Point"}
}