{
  "type": "Feature",
  "properties": {
    "iso:country":"US",
    "sg:address":"525 Navajo Trl Dr",
    "sg:city":"Pagosa Springs",
    "sg:classifiers":[
        {
            "category":"Professional",
            "type":"Services"
        }
    ],
    "sg:phone":"+1 970 731 3800",
    "sg:postcode":"81147",
    "sg:province":"CO",
    "wof:name":"Four Corners Gallery Of Pagosa",
    "wof:placetype":"venue"
},
  "geometry": {"coordinates":[-107.07924800000001,37.254534],"type":"Point"}
}