{
  "type": "Feature",
  "properties": {
    "iso:country":"US",
    "sg:address":"581 Co Rd 241",
    "sg:city":"New Castle",
    "sg:classifiers":[
        {
            "category":"Travel",
            "subcategory":"Campground",
            "type":"Entertainment"
        }
    ],
    "sg:phone":"+1 970 984 2240",
    "sg:postcode":"81647",
    "sg:province":"CO",
    "wof:name":"New Castle Glenwood Spgs AOK",
    "wof:placetype":"venue"
},
  "geometry": {"coordinates":[-107.55667,39.591816],"type":"Point"}
}