{
  "type": "Feature",
  "properties": {
    "iso:country":"US",
    "sg:address":"1037 Cherokee Street",
    "sg:city":"Denver",
    "sg:classifiers":[
        {
            "category":"Real Estate",
            "subcategory":"Architect",
            "type":"Services"
        }
    ],
    "sg:phone":"+1 303 595 0491",
    "sg:postcode":"80204",
    "sg:province":"CO",
    "wof:name":"Christopher Carvell Architects",
    "wof:placetype":"venue"
},
  "geometry": {"coordinates":[-104.991801,39.732946],"type":"Point"}
}