{
  "type": "Feature",
  "properties": {
    "iso:country":"US",
    "sg:address":"4800 Hogan Dr",
    "sg:city":"Fort Collins",
    "sg:classifiers":[
        {
            "category":"Wholesale",
            "subcategory":"Durable Goods & Equipment",
            "type":"Manufacturing & Wholesale Goods"
        }
    ],
    "sg:phone":"+1 970 226 1544",
    "sg:postcode":"80525",
    "sg:province":"CO",
    "wof:name":"Ja International",
    "wof:placetype":"venue"
},
  "geometry": {"coordinates":[-105.068736,40.520708],"type":"Point"}
}