{
  "type": "Feature",
  "properties": {
    "addr:full":"3955 Newport St Denver CO 80207",
    "addr:housenumber":"3955",
    "addr:postcode":"80207",
    "addr:street":"Newport St",
    "iso:country":"US",
    "sg:address":"3955 Newport St",
    "sg:city":"Denver",
    "sg:classifiers":[
        {
            "category":"Shopping",
            "subcategory":"Discount & Variety Stores",
            "type":"Retail Goods"
        }
    ],
    "sg:phone":"+1 303 322 3112",
    "sg:postcode":"80207",
    "sg:province":"CO",
    "wof:name":"Ten Dollar Cellular",
    "wof:placetype":"venue"
},
  "geometry": {"coordinates":[-104.909874,39.772284],"type":"Point"}
}