{
  "type": "Feature",
  "properties": {
    "iso:country":"US",
    "sg:address":"6695 W 48th Ave",
    "sg:city":"Wheat Ridge",
    "sg:classifiers":[
        {
            "category":"Real Estate",
            "subcategory":"Architect",
            "type":"Services"
        }
    ],
    "sg:phone":"+1 303 403 1228",
    "sg:postcode":"80033",
    "sg:province":"CO",
    "sg:tags":[
        "construction",
        "management",
        "design",
        "architectural",
        "general"
    ],
    "sg:website":"www.tectonicdesignbuild.com",
    "wof:name":"Tectonic Management Group Inc",
    "wof:placetype":"venue"
},
  "geometry": {"coordinates":[-105.070436,39.783946],"type":"Point"}
}