{
  "type": "Feature",
  "properties": {
    "iso:country":"US",
    "sg:address":"3490 Kellogg Pl",
    "sg:city":"Westminster",
    "sg:classifiers":[
        {
            "category":"Retail",
            "subcategory":"Repair Shop",
            "type":"Services"
        }
    ],
    "sg:phone":"+1 303 426 8181",
    "sg:postcode":"80031",
    "sg:province":"CO",
    "sg:tags":[
        "taxidermist"
    ],
    "wof:name":"A J Forms & Taxidermy",
    "wof:placetype":"venue"
},
  "geometry": {"coordinates":[-105.03224400000001,39.868153],"type":"Point"}
}