{
  "type": "Feature",
  "properties": {
    "addr:full":"500 Interlocken Blvd Broomfield CO 80021",
    "addr:housenumber":"500",
    "addr:postcode":"80021",
    "addr:street":"Interlocken Blvd",
    "iso:country":"US",
    "sg:address":"500 Interlocken Blvd",
    "sg:city":"Broomfield",
    "sg:classifiers":[
        {
            "category":"Professional",
            "type":"Services"
        }
    ],
    "sg:phone":"+1 303 460 1220",
    "sg:postcode":"80021",
    "sg:province":"CO",
    "wof:name":"Presentation Services",
    "wof:placetype":"venue"
},
  "geometry": {"coordinates":[-105.119517,39.922669],"type":"Point"}
}