{
  "type": "Feature",
  "properties": {
    "addr:full":"7740 Darvey Ln Longmont CO 80504",
    "addr:housenumber":"7740",
    "addr:postcode":"80504",
    "addr:street":"Darvey Ln",
    "iso:country":"US",
    "sg:address":"7740 Darvey Ln",
    "sg:city":"Longmont",
    "sg:classifiers":[
        {
            "category":"Freight",
            "type":"Transportation"
        }
    ],
    "sg:phone":"+1 303 210 4740",
    "sg:postcode":"80504",
    "sg:province":"CO",
    "sg:tags":[
        "company",
        "local",
        "trucking"
    ],
    "wof:name":"Kdk Trucking LLC",
    "wof:placetype":"venue"
},
  "geometry": {"coordinates":[-105.118703,40.115575],"type":"Point"}
}