{
  "type": "Feature",
  "properties": {
    "iso:country":"US",
    "sg:address":"311 Main St",
    "sg:city":"Breckenridge",
    "sg:classifiers":[
        {
            "category":"Professional",
            "subcategory":"Management & Consulting",
            "type":"Services"
        }
    ],
    "sg:phone":"+1 970 453 0307",
    "sg:postcode":"80424",
    "sg:province":"CO",
    "sg:tags":[
        "consultant",
        "business"
    ],
    "wof:name":"JAS Enterprises Inc",
    "wof:placetype":"venue"
},
  "geometry": {"coordinates":[-106.04565599999999,39.478983],"type":"Point"}
}