{
  "type": "Feature",
  "properties": {
    "iso:country":"US",
    "sg:address":"574 Northgate Dr",
    "sg:city":"Grand Junction",
    "sg:classifiers":[
        {
            "category":"Shopping",
            "subcategory":"Gifts & Souvenirs",
            "type":"Retail Goods"
        }
    ],
    "sg:phone":"+1 970 243 3320",
    "sg:postcode":"81505",
    "sg:province":"CO",
    "sg:tags":[
        "shop"
    ],
    "wof:name":"Neat Stuff Inc",
    "wof:placetype":"venue"
},
  "geometry": {"coordinates":[-108.585908,39.088043],"type":"Point"}
}