{
  "type": "Feature",
  "properties": {
    "addr:full":"330 High Pointe Dr Fort Collins CO 80525",
    "addr:housenumber":"330",
    "addr:postcode":"80525",
    "addr:street":"High Pointe Dr",
    "iso:country":"US",
    "sg:address":"330 High Pointe Dr",
    "sg:city":"Fort Collins",
    "sg:classifiers":[
        {
            "category":"Professional",
            "subcategory":"Secretarial Services",
            "type":"Services"
        }
    ],
    "sg:phone":"+1 970 225 2736",
    "sg:postcode":"80525",
    "sg:province":"CO",
    "sg:tags":[
        "reporting",
        "court"
    ],
    "wof:name":"Accu Typing",
    "wof:placetype":"venue"
},
  "geometry": {"coordinates":[-105.071411,40.53188],"type":"Point"}
}