{
  "type": "Feature",
  "properties": {
    "iso:country":"US",
    "sg:address":"4112 Lakefront Dr",
    "sg:city":"Loveland",
    "sg:classifiers":[
        {
            "category":"Professional",
            "type":"Services"
        }
    ],
    "sg:phone":"+1 970 663 2989",
    "sg:postcode":"80537",
    "sg:province":"CO",
    "wof:name":"American Standard Inc",
    "wof:placetype":"venue"
},
  "geometry": {"coordinates":[-105.206468,40.347221],"type":"Point"}
}