{
  "type": "Feature",
  "properties": {
    "iso:country":"US",
    "sg:address":"202 S Mason St",
    "sg:city":"Fort Collins",
    "sg:classifiers":[
        {
            "category":"Personal",
            "subcategory":"Beauty Salon",
            "type":"Services"
        }
    ],
    "sg:phone":"+1 970 493 2570",
    "sg:postcode":"80524",
    "sg:province":"CO",
    "wof:name":"Gossip Central A Studio For",
    "wof:placetype":"venue"
},
  "geometry": {"coordinates":[-105.07890399999999,40.584254],"type":"Point"}
}