{
  "type": "Feature",
  "properties": {
    "iso:country":"US",
    "sg:address":"16611 E Ithaca Pl",
    "sg:city":"Aurora",
    "sg:classifiers":[
        {
            "category":"Building & Trades",
            "subcategory":"Construction",
            "type":"Services"
        }
    ],
    "sg:phone":"+1 303 617 0983",
    "sg:postcode":"80013",
    "sg:province":"CO",
    "sg:tags":[
        "hanging",
        "contractor"
    ],
    "wof:name":"Mc Namaras Painting",
    "wof:placetype":"venue"
},
  "geometry": {"coordinates":[-104.794695,39.652587],"type":"Point"}
}