{
  "type": "Feature",
  "properties": {
    "addr:full":"1035 S Federal Blvd Ste B Denver CO 80219",
    "addr:housenumber":"1035",
    "addr:postcode":"80219",
    "addr:street":"S Federal Blvd Ste B",
    "iso:country":"US",
    "sg:address":"1035 S Federal Blvd Ste B",
    "sg:city":"Denver",
    "sg:classifiers":[
        {
            "category":"Shopping",
            "subcategory":"Pharmacy",
            "type":"Retail Goods"
        }
    ],
    "sg:phone":"+1 303 975 1700",
    "sg:postcode":"80219",
    "sg:province":"CO",
    "sg:tags":[
        "drugstore"
    ],
    "wof:name":"Asia Pharmacy",
    "wof:placetype":"venue"
},
  "geometry": {"coordinates":[-105.02552,39.697734],"type":"Point"}
}