{
  "type": "Feature",
  "properties": {
    "iso:country":"US",
    "sg:address":"2140 S Holly St",
    "sg:city":"Denver",
    "sg:classifiers":[
        {
            "category":"Banks & Credit Unions",
            "subcategory":"Bank",
            "type":"Services"
        }
    ],
    "sg:phone":"+1 303 584 9360",
    "sg:postcode":"80222",
    "sg:province":"CO",
    "sg:tags":[
        "loan",
        "broker",
        "mortgage"
    ],
    "wof:name":"Sierra Funding Corp",
    "wof:placetype":"venue"
},
  "geometry": {"coordinates":[-104.922195,39.677694],"type":"Point"}
}