{
  "type": "Feature",
  "properties": {
    "addr:full":"704 Mountain View Rd Carbondale CO 81623",
    "addr:housenumber":"704",
    "addr:postcode":"81623",
    "addr:street":"Mountain View Rd",
    "iso:country":"US",
    "sg:address":"704 Mountain View Rd",
    "sg:city":"Carbondale",
    "sg:classifiers":[
        {
            "category":"Restaurant",
            "type":"Food & Drink"
        }
    ],
    "sg:phone":"+1 970 704 0298",
    "sg:postcode":"81623",
    "sg:province":"CO",
    "sg:tags":[
        "eating"
    ],
    "wof:name":"Creative Catering Inc",
    "wof:placetype":"venue"
},
  "geometry": {"coordinates":[-107.1009,39.433403],"type":"Point"}
}