{
  "type": "Feature",
  "properties": {
    "iso:country":"US",
    "sg:address":"1155 Kelly Johnson Blvd",
    "sg:city":"Colorado Springs",
    "sg:classifiers":[
        {
            "category":"Health Services",
            "subcategory":"Doctor",
            "type":"Services"
        }
    ],
    "sg:phone":"+1 719 534 9445",
    "sg:postcode":"80920",
    "sg:province":"CO",
    "sg:tags":[
        "dentist"
    ],
    "wof:name":"Mark V Allen DDS",
    "wof:placetype":"venue"
},
  "geometry": {"coordinates":[-104.8053,38.945258],"type":"Point"}
}