{
  "type": "Feature",
  "properties": {
    "addr:full":"3536 S Cherokee St Englewood CO 80110",
    "addr:housenumber":"3536",
    "addr:postcode":"80110",
    "addr:street":"S Cherokee St",
    "iso:country":"US",
    "sg:address":"3536 S Cherokee St",
    "sg:city":"Englewood",
    "sg:classifiers":[
        {
            "category":"Real Estate",
            "subcategory":"Real Estate Services",
            "type":"Services"
        },
        {
            "category":"Building & Trades",
            "subcategory":"Cleaning & Sanitation",
            "type":"Services"
        }
    ],
    "sg:phone":"+1 303 783 5181",
    "sg:postcode":"80110",
    "sg:province":"CO",
    "sg:tags":[
        "maintenance",
        "cleaners-interior"
    ],
    "wof:name":"Tahoe Maintenance",
    "wof:placetype":"venue"
},
  "geometry": {"coordinates":[-104.99124399999999,39.65269],"type":"Point"}
}