{
  "type": "Feature",
  "properties": {
    "iso:country":"US",
    "sg:address":"129 N 5th Ave",
    "sg:city":"Brighton",
    "sg:classifiers":[
        {
            "category":"Freight",
            "type":"Transportation"
        }
    ],
    "sg:phone":"+1 720 685 9437",
    "sg:postcode":"80601",
    "sg:province":"CO",
    "sg:tags":[
        "operator",
        "local",
        "trucking"
    ],
    "wof:name":"Luna Trucking",
    "wof:placetype":"venue"
},
  "geometry": {"coordinates":[-104.816849,39.989918],"type":"Point"}
}