{
  "type": "Feature",
  "properties": {
    "iso:country":"US",
    "sg:address":"1060 W Beaver Creek Blvd",
    "sg:city":"Avon",
    "sg:classifiers":[
        {
            "category":"Travel",
            "subcategory":"Hotels & Motels",
            "type":"Entertainment"
        }
    ],
    "sg:phone":"+1 970 748 4490",
    "sg:postcode":"81620",
    "sg:province":"CO",
    "sg:tags":[
        "resort"
    ],
    "wof:name":"East West Resorts Bachelor",
    "wof:placetype":"venue"
},
  "geometry": {"coordinates":[-106.53666699999999,39.636431],"type":"Point"}
}