{
  "type": "Feature",
  "properties": {
    "addr:full":"5870 S Kipling St Littleton CO 80127",
    "addr:housenumber":"5870",
    "addr:postcode":"80127",
    "addr:street":"S Kipling St",
    "iso:country":"US",
    "sg:address":"5870 S Kipling St",
    "sg:city":"Littleton",
    "sg:classifiers":[
        {
            "category":"Shopping",
            "subcategory":"Pharmacy",
            "type":"Retail Goods"
        }
    ],
    "sg:phone":"+1 303 973 4400",
    "sg:postcode":"80127",
    "sg:province":"CO",
    "sg:tags":[
        "drug",
        "store"
    ],
    "sg:website":"www.walgreens.com",
    "wof:name":"Walgreens",
    "wof:placetype":"venue"
},
  "geometry": {"coordinates":[-105.109886,39.611355],"type":"Point"}
}