{
  "type": "Feature",
  "properties": {
    "iso:country":"US",
    "sg:address":"6 Merritt Ct",
    "sg:city":"Pueblo",
    "sg:classifiers":[
        {
            "category":"Autos & Motor Vehicles",
            "subcategory":"Automobile Sales",
            "type":"Retail Goods"
        }
    ],
    "sg:phone":"+1 719 545 2120",
    "sg:postcode":"81001",
    "sg:province":"CO",
    "sg:tags":[
        "used"
    ],
    "wof:name":"B & R Auto Sales Inc",
    "wof:placetype":"venue"
},
  "geometry": {"coordinates":[-104.564036,38.270791],"type":"Point"}
}