{
  "type": "Feature",
  "properties": {
    "iso:country":"US",
    "sg:address":"405 Ridges Blvd",
    "sg:city":"Grand Junction",
    "sg:classifiers":[
        {
            "category":"Professional",
            "subcategory":"Lawyer & Legal Services",
            "type":"Services"
        }
    ],
    "sg:phone":"+1 970 245 4617",
    "sg:postcode":"81503",
    "sg:province":"CO",
    "wof:name":"Edward J Nugent PC",
    "wof:placetype":"venue"
},
  "geometry": {"coordinates":[-108.604175,39.06599],"type":"Point"}
}