{
  "type": "Feature",
  "properties": {
    "iso:country":"US",
    "sg:address":"723 S Pueblo Blvd",
    "sg:city":"Pueblo",
    "sg:classifiers":[
        {
            "category":"Food & Beverages",
            "subcategory":"Groceries & Convenience Stores",
            "type":"Retail Goods"
        }
    ],
    "sg:phone":"+1 719 564 6465",
    "sg:postcode":"81005",
    "sg:province":"CO",
    "wof:name":"First Stop",
    "wof:placetype":"venue"
},
  "geometry": {"coordinates":[-104.66156599999999,38.258293],"type":"Point"}
}