{
  "type": "Feature",
  "properties": {
    "iso:country":"US",
    "sg:address":"2545 Forsythia Dr",
    "sg:city":"Loveland",
    "sg:classifiers":[
        {
            "category":"Building & Trades",
            "subcategory":"Construction",
            "type":"Services"
        }
    ],
    "sg:phone":"+1 970 667 7656",
    "sg:postcode":"80537",
    "sg:province":"CO",
    "sg:tags":[
        "handyman"
    ],
    "wof:name":"ADY Enterprises",
    "wof:placetype":"venue"
},
  "geometry": {"coordinates":[-105.11130300000001,40.389563],"type":"Point"}
}