{
  "type": "Feature",
  "properties": {
    "addr:full":"2130 Hollow Brook Dr Colorado Springs CO 80918",
    "addr:housenumber":"2130",
    "addr:postcode":"80918",
    "addr:street":"Hollow Brook Dr",
    "iso:country":"US",
    "sg:address":"2130 Hollow Brook Dr",
    "sg:city":"Colorado Springs",
    "sg:classifiers":[
        {
            "category":"Health Services",
            "subcategory":"Doctor",
            "type":"Services"
        }
    ],
    "sg:phone":"+1 719 531 6778",
    "sg:postcode":"80918",
    "sg:province":"CO",
    "sg:tags":[
        "physician",
        "surgeon"
    ],
    "wof:name":"Center For Integrative Med",
    "wof:placetype":"venue"
},
  "geometry": {"coordinates":[-104.78802,38.92187],"type":"Point"}
}