{
  "type": "Feature",
  "properties": {
    "addr:full":"312 N 50th Avenue Pl Greeley CO 80634",
    "addr:housenumber":"312",
    "addr:postcode":"80634",
    "addr:street":"N 50Th Avenue Pl",
    "iso:country":"US",
    "sg:address":"312 N 50th Avenue Pl",
    "sg:city":"Greeley",
    "sg:classifiers":[
        {
            "category":"Real Estate",
            "subcategory":"Real Estate Operator",
            "type":"Services"
        }
    ],
    "sg:phone":"+1 970 378 7843",
    "sg:postcode":"80634",
    "sg:province":"CO",
    "sg:tags":[
        "apartment"
    ],
    "wof:name":"1708 8th Ave",
    "wof:placetype":"venue"
},
  "geometry": {"coordinates":[-104.763475,40.436906],"type":"Point"}
}