{
  "type": "Feature",
  "properties": {
    "iso:country":"US",
    "sg:address":"25 Lower Woodbridge Rd",
    "sg:city":"Snowmass Village",
    "sg:classifiers":[
        {
            "category":"Professional",
            "subcategory":"Business Services",
            "type":"Services"
        }
    ],
    "sg:phone":"+1 970 923 2644",
    "sg:postcode":"81615",
    "sg:province":"CO",
    "sg:tags":[
        "interior",
        "consultant",
        "design",
        "decorator"
    ],
    "wof:name":"Robert Trown Assoc",
    "wof:placetype":"venue"
},
  "geometry": {"coordinates":[-106.94062,39.21364],"type":"Point"}
}