{
  "type": "Feature",
  "properties": {
    "iso:country":"US",
    "sg:address":"603 Park Point Dr",
    "sg:city":"Golden",
    "sg:classifiers":[
        {
            "category":"Professional",
            "type":"Services"
        }
    ],
    "sg:phone":"+1 303 716 0355",
    "sg:postcode":"80401",
    "sg:province":"CO",
    "sg:tags":[
        "establishment"
    ],
    "wof:name":"Visionpartners",
    "wof:placetype":"venue"
},
  "geometry": {"coordinates":[-105.289394,39.708229],"type":"Point"}
}