{
  "type": "Feature",
  "properties": {
    "iso:country":"US",
    "sg:address":"1331 19th St",
    "sg:city":"Denver",
    "sg:classifiers":[
        {
            "category":"Government",
            "subcategory":"Fire Station",
            "type":"Public Place"
        }
    ],
    "sg:phone":"+1 303 295 4410",
    "sg:postcode":"80202",
    "sg:province":"CO",
    "sg:tags":[
        "protection"
    ],
    "wof:name":"Fire Dept- Line Shop",
    "wof:placetype":"venue"
},
  "geometry": {"coordinates":[-104.994373,39.752527],"type":"Point"}
}