{
  "type": "Feature",
  "properties": {
    "iso:country":"US",
    "sg:address":"1714 Santa Fe Dr",
    "sg:city":"Pueblo",
    "sg:classifiers":[
        {
            "category":"Manufacturing",
            "subcategory":"Furniture",
            "type":"Manufacturing & Wholesale Goods"
        }
    ],
    "sg:phone":"+1 719 542 2290",
    "sg:postcode":"81006",
    "sg:province":"CO",
    "sg:tags":[
        "repair",
        "wood",
        "mfg"
    ],
    "wof:name":"Custom By Crdnal Picture Frmng",
    "wof:placetype":"venue"
},
  "geometry": {"coordinates":[-104.578255,38.245546],"type":"Point"}
}