{
  "type": "Feature",
  "properties": {
    "iso:country":"US",
    "sg:address":"172 Stanley Circle Dr",
    "sg:city":"Estes Park",
    "sg:classifiers":[
        {
            "category":"Banks & Credit Unions",
            "subcategory":"Financial Services",
            "type":"Services"
        }
    ],
    "sg:phone":"+1 970 586 4766",
    "sg:postcode":"80517",
    "sg:province":"CO",
    "sg:tags":[
        "trust",
        "management"
    ],
    "wof:name":"Blanchar LLC",
    "wof:placetype":"venue"
},
  "geometry": {"coordinates":[-105.514534,40.373147],"type":"Point"}
}