{
  "type": "Feature",
  "properties": {
    "iso:country":"US",
    "sg:address":"801 E 4th Ave",
    "sg:city":"Longmont",
    "sg:classifiers":[
        {
            "category":"Manufacturing",
            "subcategory":"Tools & Machinery",
            "type":"Manufacturing & Wholesale Goods"
        }
    ],
    "sg:phone":"+1 720 652 9448",
    "sg:postcode":"80501",
    "sg:province":"CO",
    "sg:tags":[
        "machine",
        "shop"
    ],
    "wof:name":"Hartman Precision Machine Inc",
    "wof:placetype":"venue"
},
  "geometry": {"coordinates":[-105.076402,40.164001],"type":"Point"}
}