{
  "type": "Feature",
  "properties": {
    "addr:full":"7739 Co Rd 150 Salida CO 81201",
    "addr:housenumber":"7739",
    "addr:postcode":"81201",
    "addr:street":"Co Rd 150",
    "iso:country":"US",
    "sg:address":"7739 Co Rd 150",
    "sg:city":"Salida",
    "sg:classifiers":[
        {
            "category":"Retail",
            "subcategory":"Auto Repair",
            "type":"Services"
        }
    ],
    "sg:phone":"+1 719 539 9280",
    "sg:postcode":"81201",
    "sg:province":"CO",
    "sg:tags":[
        "body",
        "automobile",
        "painting"
    ],
    "wof:name":"Gunderman Auto Body",
    "wof:placetype":"venue"
},
  "geometry": {"coordinates":[-106.01944399999999,38.553872],"type":"Point"}
}