{
  "type": "Feature",
  "properties": {
    "iso:country":"US",
    "sg:address":"720 Main St",
    "sg:city":"Alamosa",
    "sg:classifiers":[
        {
            "category":"Banks & Credit Unions",
            "subcategory":"Bank",
            "type":"Services"
        }
    ],
    "sg:phone":"+1 719 589 6255",
    "sg:postcode":"81101",
    "sg:province":"CO",
    "wof:name":"First Southwest Bank",
    "wof:placetype":"venue"
},
  "geometry": {"coordinates":[-105.86845599999999,37.468106],"type":"Point"}
}