{
  "type": "Feature",
  "properties": {
    "addr:full":"7540 S Grant St Littleton CO 80122",
    "addr:housenumber":"7540",
    "addr:postcode":"80122",
    "addr:street":"S Grant St",
    "iso:country":"US",
    "sg:address":"7540 S Grant St",
    "sg:city":"Littleton",
    "sg:classifiers":[
        {
            "category":"Wholesale",
            "subcategory":"Apparel",
            "type":"Manufacturing & Wholesale Goods"
        },
        {
            "category":"Professional",
            "subcategory":"Business Services",
            "type":"Services"
        }
    ],
    "sg:phone":"+1 303 795 7432",
    "sg:postcode":"80122",
    "sg:province":"CO",
    "sg:tags":[
        "sportswear",
        "embroidery"
    ],
    "wof:name":"Outfitter Trading Co LLC",
    "wof:placetype":"venue"
},
  "geometry": {"coordinates":[-104.984407,39.579305],"type":"Point"}
}