{
  "type": "Feature",
  "properties": {
    "addr:full":"12449 W Idaho Dr Lakewood CO 80228",
    "addr:housenumber":"12449",
    "addr:postcode":"80228",
    "addr:street":"W Idaho Dr",
    "iso:country":"US",
    "sg:address":"12449 W Idaho Dr",
    "sg:city":"Lakewood",
    "sg:classifiers":[
        {
            "category":"Building & Trades",
            "subcategory":"Construction",
            "type":"Services"
        }
    ],
    "sg:phone":"+1 303 984 7324",
    "sg:postcode":"80228",
    "sg:province":"CO",
    "sg:tags":[
        "repairing",
        "remodeling",
        "contractor"
    ],
    "wof:name":"Blue Spruce Remodleing",
    "wof:placetype":"venue"
},
  "geometry": {"coordinates":[-105.14102200000001,39.689918],"type":"Point"}
}