{
  "type": "Feature",
  "properties": {
    "iso:country":"US",
    "sg:address":"5806 W Colfax Ave",
    "sg:city":"Denver",
    "sg:classifiers":[
        {
            "category":"Autos & Motor Vehicles",
            "subcategory":"Recreational Vehicle Sales",
            "type":"Retail Goods"
        }
    ],
    "sg:phone":"+1 303 237 0647",
    "sg:postcode":"80214",
    "sg:province":"CO",
    "sg:tags":[
        "shell",
        "camper"
    ],
    "wof:name":"A&A Topper Sales & Service Ctr",
    "wof:placetype":"venue"
},
  "geometry": {"coordinates":[-105.06135,39.740265],"type":"Point"}
}