{
  "type": "Feature",
  "properties": {
    "iso:country":"US",
    "sg:address":"312 Co Rd 250",
    "sg:city":"Durango",
    "sg:classifiers":[
        {
            "category":"Wholesale",
            "subcategory":"Electrical",
            "type":"Manufacturing & Wholesale Goods"
        }
    ],
    "sg:phone":"+1 970 247 5262",
    "sg:postcode":"81301",
    "sg:province":"CO",
    "sg:tags":[
        "telecommunication"
    ],
    "wof:name":"LA Plata Telephone Systems",
    "wof:placetype":"venue"
},
  "geometry": {"coordinates":[-107.847769,37.300463],"type":"Point"}
}