{
  "type": "Feature",
  "properties": {
    "iso:country":"US",
    "sg:address":"30278 US Hwy 40",
    "sg:city":"Steamboat Springs",
    "sg:classifiers":[
        {
            "category":"Retail",
            "subcategory":"Veterinary Services",
            "type":"Services"
        }
    ],
    "sg:phone":"+1 970 879 1049",
    "sg:postcode":"80487",
    "sg:province":"CO",
    "wof:name":"Steamboat Veterinary Hospital",
    "wof:placetype":"venue"
},
  "geometry": {"coordinates":[-106.670632,40.389122],"type":"Point"}
}