{
  "type": "Feature",
  "properties": {
    "iso:country":"US",
    "sg:address":"1397 W Briarwood Ave",
    "sg:city":"Littleton",
    "sg:classifiers":[
        {
            "category":"Food & Beverages",
            "subcategory":"Bakery",
            "type":"Retail Goods"
        }
    ],
    "sg:phone":"+1 303 794 6405",
    "sg:postcode":"80120",
    "sg:province":"CO",
    "wof:name":"Sugar-Less Sensations Inc",
    "wof:placetype":"venue"
},
  "geometry": {"coordinates":[-105.00308200000001,39.591665],"type":"Point"}
}