{
  "type": "Feature",
  "properties": {
    "iso:country":"US",
    "sg:address":"3650 S Oak St",
    "sg:city":"Denver",
    "sg:classifiers":[
        {
            "category":"Building & Trades",
            "subcategory":"Plumbing",
            "type":"Services"
        }
    ],
    "sg:phone":"+1 303 437 2273",
    "sg:postcode":"80235",
    "sg:province":"CO",
    "sg:tags":[
        "contractor"
    ],
    "wof:name":"Colorado Quality Hvac Inc",
    "wof:placetype":"venue"
},
  "geometry": {"coordinates":[-105.119006,39.649587],"type":"Point"}
}