{
  "type": "Feature",
  "properties": {
    "iso:country":"US",
    "sg:address":"11127 W Frost Ave",
    "sg:city":"Littleton",
    "sg:classifiers":[
        {
            "category":"Manufacturing",
            "subcategory":"Metals",
            "type":"Manufacturing & Wholesale Goods"
        }
    ],
    "sg:phone":"+1 303 978 9030",
    "sg:postcode":"80127",
    "sg:province":"CO",
    "sg:tags":[
        "metalwork",
        "architectural",
        "mfg"
    ],
    "wof:name":"Reid Metal Architecture",
    "wof:placetype":"venue"
},
  "geometry": {"coordinates":[-105.126349,39.585115],"type":"Point"}
}