{
  "type": "Feature",
  "properties": {
    "addr:full":"6570 Portner Dr Fort Collins CO 80525",
    "addr:housenumber":"6570",
    "addr:postcode":"80525",
    "addr:street":"Portner Dr",
    "iso:country":"US",
    "sg:address":"6570 Portner Dr",
    "sg:city":"Fort Collins",
    "sg:classifiers":[
        {
            "category":"Government",
            "subcategory":"Office",
            "type":"Public Place"
        }
    ],
    "sg:phone":"+1 970 224 6161",
    "sg:postcode":"80525",
    "sg:province":"CO",
    "sg:tags":[
        "village"
    ],
    "wof:name":"Fort Collins Transfort Bus",
    "wof:placetype":"venue"
},
  "geometry": {"coordinates":[-105.066239,40.495328],"type":"Point"}
}