{
  "type": "Feature",
  "properties": {
    "iso:country":"US",
    "sg:address":"937 W 44th St",
    "sg:city":"Loveland",
    "sg:classifiers":[
        {
            "category":"Building & Trades",
            "subcategory":"Construction",
            "type":"Services"
        }
    ],
    "sg:phone":"+1 970 663 7406",
    "sg:postcode":"80538",
    "sg:province":"CO",
    "sg:tags":[
        "house"
    ],
    "wof:name":"House Doctors Handyman SE",
    "wof:placetype":"venue"
},
  "geometry": {"coordinates":[-105.088981,40.4378],"type":"Point"}
}