{
  "type": "Feature",
  "properties": {
    "addr:full":"4100 Federal Boulevard Denver CO 80211",
    "addr:housenumber":"4100",
    "addr:postcode":"80211",
    "addr:street":"Federal Boulevard",
    "iso:country":"US",
    "sg:address":"4100 Federal Boulevard",
    "sg:city":"Denver",
    "sg:classifiers":[
        {
            "category":"Shopping",
            "subcategory":"Clothing, Apparel, & Fashions",
            "type":"Retail Goods"
        }
    ],
    "sg:phone":"+1 303 458 5025",
    "sg:postcode":"80211",
    "sg:province":"CO",
    "sg:tags":[
        "accessory",
        "clothing",
        "women's"
    ],
    "wof:name":"Las Rosas Boutique",
    "wof:placetype":"venue"
},
  "geometry": {"coordinates":[-105.02513,39.772916],"type":"Point"}
}