{
  "type": "Feature",
  "properties": {
    "iso:country":"US",
    "sg:address":"1250 Golden Cir",
    "sg:city":"Golden",
    "sg:classifiers":[
        {
            "category":"Shopping",
            "subcategory":"Bicycles & Sporting Goods",
            "type":"Retail Goods"
        }
    ],
    "sg:phone":"+1 303 277 0449",
    "sg:postcode":"80401",
    "sg:province":"CO",
    "wof:name":"Virtual Goods Express Inc",
    "wof:placetype":"venue"
},
  "geometry": {"coordinates":[-105.208872,39.727569],"type":"Point"}
}