{
  "type": "Feature",
  "properties": {
    "addr:full":"418 E Cooper Ave Aspen CO 81611",
    "addr:housenumber":"418",
    "addr:postcode":"81611",
    "addr:street":"E Cooper Ave",
    "iso:country":"US",
    "sg:address":"418 E Cooper Ave",
    "sg:city":"Aspen",
    "sg:classifiers":[
        {
            "category":"Building & Trades",
            "subcategory":"Construction",
            "type":"Services"
        }
    ],
    "sg:phone":"+1 970 925 4506",
    "sg:postcode":"81611",
    "sg:province":"CO",
    "sg:tags":[
        "planning",
        "remodeling",
        "kitchen"
    ],
    "wof:name":"Johnny Designs",
    "wof:placetype":"venue"
},
  "geometry": {"coordinates":[-106.819869,39.188313],"type":"Point"}
}