{
  "type": "Feature",
  "properties": {
    "iso:country":"US",
    "sg:address":"319 S Union Ave",
    "sg:city":"Pueblo",
    "sg:classifiers":[
        {
            "category":"Building & Trades",
            "subcategory":"Construction",
            "type":"Services"
        }
    ],
    "sg:phone":"+1 719 583 7866",
    "sg:postcode":"81003",
    "sg:province":"CO",
    "sg:tags":[
        "home",
        "builder"
    ],
    "wof:name":"Home Detention Systems",
    "wof:placetype":"venue"
},
  "geometry": {"coordinates":[-104.615855,38.262697],"type":"Point"}
}