{
  "type": "Feature",
  "properties": {
    "addr:full":"215 Adams St Denver CO 80206",
    "addr:housenumber":"215",
    "addr:postcode":"80206",
    "addr:street":"Adams St",
    "iso:country":"US",
    "sg:address":"215 Adams St",
    "sg:city":"Denver",
    "sg:classifiers":[
        {
            "category":"Wholesale",
            "subcategory":"Electrical",
            "type":"Manufacturing & Wholesale Goods"
        }
    ],
    "sg:phone":"+1 303 377 2000",
    "sg:postcode":"80206",
    "sg:province":"CO",
    "sg:tags":[
        "equipment"
    ],
    "wof:name":"Power Btry Cmpany-Manufacturer",
    "wof:placetype":"venue"
},
  "geometry": {"coordinates":[-104.94865900000001,39.720745],"type":"Point"}
}