{
  "type": "Feature",
  "properties": {
    "iso:country":"US",
    "sg:address":"7860 S Windermere Cir",
    "sg:city":"Littleton",
    "sg:classifiers":[
        {
            "category":"Building & Trades",
            "subcategory":"Landscaping Services",
            "type":"Services"
        }
    ],
    "sg:phone":"+1 303 734 1126",
    "sg:postcode":"80120",
    "sg:province":"CO",
    "sg:tags":[
        "designer",
        "landscape"
    ],
    "wof:name":"Camelot Design",
    "wof:placetype":"venue"
},
  "geometry": {"coordinates":[-105.009995,39.574854],"type":"Point"}
}