{
  "type": "Feature",
  "properties": {
    "iso:country":"US",
    "sg:address":"1220 Ouray Ave",
    "sg:city":"Grand Junction",
    "sg:classifiers":[
        {
            "category":"Organizations",
            "subcategory":"Religious Organization",
            "type":"Services"
        }
    ],
    "sg:phone":"+1 970 245 1399",
    "sg:postcode":"81501",
    "sg:province":"CO",
    "sg:tags":[
        "church"
    ],
    "wof:name":"Baha'i Faith Baha'i",
    "wof:placetype":"venue"
},
  "geometry": {"coordinates":[-108.551075,39.071452],"type":"Point"}
}