{
  "type": "Feature",
  "properties": {
    "addr:full":"4185 Co Rd Kk Idalia CO 80735",
    "addr:housenumber":"4185",
    "addr:postcode":"80735",
    "addr:street":"Co Rd",
    "iso:country":"US",
    "sg:address":"4185 Co Rd Kk",
    "sg:city":"Idalia",
    "sg:classifiers":[
        {
            "category":"Professional",
            "type":"Services"
        }
    ],
    "sg:phone":"+1 970 354 7252",
    "sg:postcode":"80735",
    "sg:province":"CO",
    "sg:tags":[
        "establishment"
    ],
    "wof:name":"Bureau Of Reclamation",
    "wof:placetype":"venue"
},
  "geometry": {"coordinates":[-102.177735,39.630695],"type":"Point"}
}