{
  "type": "Feature",
  "properties": {
    "addr:full":"1436 Winfield Dr Fort Collins CO 80526",
    "addr:housenumber":"1436",
    "addr:postcode":"80526",
    "addr:street":"Winfield Dr",
    "iso:country":"US",
    "sg:address":"1436 Winfield Dr",
    "sg:city":"Fort Collins",
    "sg:classifiers":[
        {
            "category":"Real Estate",
            "subcategory":"Real Estate Agent",
            "type":"Services"
        }
    ],
    "sg:phone":"+1 970 472 9428",
    "sg:postcode":"80526",
    "sg:province":"CO",
    "wof:name":"Nchp LLC",
    "wof:placetype":"venue"
},
  "geometry": {"coordinates":[-105.105092,40.561069],"type":"Point"}
}