{
  "type": "Feature",
  "properties": {
    "addr:full":"426 Violet St Golden CO 80401",
    "addr:housenumber":"426",
    "addr:postcode":"80401",
    "addr:street":"Violet St",
    "iso:country":"US",
    "sg:address":"426 Violet St",
    "sg:city":"Golden",
    "sg:classifiers":[
        {
            "category":"Food & Beverages",
            "subcategory":"Specialty",
            "type":"Retail Goods"
        }
    ],
    "sg:phone":"+1 303 984 1675",
    "sg:postcode":"80401",
    "sg:province":"CO",
    "sg:tags":[
        "bars",
        "espresso"
    ],
    "wof:name":"Rocky Mountain Espresso Svc",
    "wof:placetype":"venue"
},
  "geometry": {"coordinates":[-105.196961,39.721881],"type":"Point"}
}