{
  "type": "Feature",
  "properties": {
    "addr:full":"4465 Garrison St Wheat Ridge CO 80033",
    "addr:housenumber":"4465",
    "addr:postcode":"80033",
    "addr:street":"Garrison St",
    "iso:country":"US",
    "sg:address":"4465 Garrison St",
    "sg:city":"Wheat Ridge",
    "sg:classifiers":[
        {
            "category":"Retail",
            "subcategory":"Auto Repair",
            "type":"Services"
        }
    ],
    "sg:phone":"+1 303 425 7400",
    "sg:postcode":"80033",
    "sg:province":"CO",
    "sg:tags":[
        "repairing",
        "automobile"
    ],
    "wof:name":"Marchese Specialties",
    "wof:placetype":"venue"
},
  "geometry": {"coordinates":[-105.100301,39.779238],"type":"Point"}
}