{
  "type": "Feature",
  "properties": {
    "addr:full":"3847 Linda Vista Ln Colorado Springs CO 80907",
    "addr:housenumber":"3847",
    "addr:postcode":"80907",
    "addr:street":"Linda Vista Ln",
    "iso:country":"US",
    "sg:address":"3847 Linda Vista Ln",
    "sg:city":"Colorado Springs",
    "sg:classifiers":[
        {
            "category":"Manufacturing",
            "subcategory":"Metals",
            "type":"Manufacturing & Wholesale Goods"
        }
    ],
    "sg:phone":"+1 719 262 9101",
    "sg:postcode":"80907",
    "sg:province":"CO",
    "sg:tags":[
        "barrels",
        "drum"
    ],
    "wof:name":"Haz Drumz",
    "wof:placetype":"venue"
},
  "geometry": {"coordinates":[-104.80058,38.889169],"type":"Point"}
}