{
  "type": "Feature",
  "properties": {
    "iso:country":"US",
    "sg:address":"15734 W 6th Ave",
    "sg:city":"Golden",
    "sg:classifiers":[
        {
            "category":"Building & Trades",
            "subcategory":"Construction",
            "type":"Services"
        }
    ],
    "sg:phone":"+1 720 497 0288",
    "sg:postcode":"80401",
    "sg:province":"CO",
    "sg:tags":[
        "excavation",
        "contractor"
    ],
    "wof:name":"J B S Pipeline Contractors",
    "wof:placetype":"venue"
},
  "geometry": {"coordinates":[-105.176839,39.7252],"type":"Point"}
}