{
  "type": "Feature",
  "properties": {
    "iso:country":"US",
    "sg:address":"2727 W Hampden Ave",
    "sg:city":"Sheridan",
    "sg:classifiers":[
        {
            "category":"Professional",
            "type":"Services"
        }
    ],
    "sg:phone":"+1 303 777 4820",
    "sg:postcode":"80110",
    "sg:province":"CO",
    "sg:tags":[
        "establishment"
    ],
    "wof:name":"Poison Spyder Customs",
    "wof:placetype":"venue"
},
  "geometry": {"coordinates":[-105.021485,39.653351],"type":"Point"}
}