{
  "type": "Feature",
  "properties": {
    "iso:country":"US",
    "sg:address":"7520 Grant Pl",
    "sg:city":"Arvada",
    "sg:classifiers":[
        {
            "category":"Organizations",
            "subcategory":"Professional Association",
            "type":"Services"
        }
    ],
    "sg:phone":"+1 303 463 6555",
    "sg:postcode":"80002",
    "sg:province":"CO",
    "wof:name":"Midwest Electric",
    "wof:placetype":"venue"
},
  "geometry": {"coordinates":[-105.081211,39.801065],"type":"Point"}
}