{
  "type": "Feature",
  "properties": {
    "iso:country":"US",
    "sg:address":"6276 S Marion Way",
    "sg:city":"Littleton",
    "sg:classifiers":[
        {
            "category":"Health Services",
            "subcategory":"Hospital",
            "type":"Services"
        }
    ],
    "sg:phone":"+1 303 797 8907",
    "sg:postcode":"80121",
    "sg:province":"CO",
    "sg:tags":[
        "general"
    ],
    "wof:name":"Valerie Vroohees",
    "wof:placetype":"venue"
},
  "geometry": {"coordinates":[-104.974183,39.602505],"type":"Point"}
}