{
  "type": "Feature",
  "properties": {
    "iso:country":"US",
    "sg:address":"1708 15th St",
    "sg:city":"Boulder",
    "sg:classifiers":[
        {
            "category":"Shopping",
            "type":"Retail Goods"
        },
        {
            "category":"Manufacturing",
            "subcategory":"Wood Products",
            "type":"Manufacturing & Wholesale Goods"
        }
    ],
    "sg:phone":"+1 303 447 2841",
    "sg:postcode":"80302",
    "sg:province":"CO",
    "sg:tags":[
        "picture",
        "frame"
    ],
    "wof:name":"15th Street Studio Inc",
    "wof:placetype":"venue"
},
  "geometry": {"coordinates":[-105.274776,40.015153],"type":"Point"}
}