{
  "type": "Feature",
  "properties": {
    "addr:full":"7816 S Pierce Way Littleton CO 80128",
    "addr:housenumber":"7816",
    "addr:postcode":"80128",
    "addr:street":"S Pierce Way",
    "iso:country":"US",
    "sg:address":"7816 S Pierce Way",
    "sg:city":"Littleton",
    "sg:classifiers":[
        {
            "category":"Professional",
            "subcategory":"Advertising",
            "type":"Services"
        },
        {
            "category":"Wholesale",
            "subcategory":"Non-durable Goods",
            "type":"Manufacturing & Wholesale Goods"
        }
    ],
    "sg:phone":"+1 303 973 5771",
    "sg:postcode":"80128",
    "sg:province":"CO",
    "sg:website":"www.josephprice.com",
    "wof:name":"Joseph Price & Associates",
    "wof:placetype":"venue"
},
  "geometry": {"coordinates":[-105.073554,39.575139],"type":"Point"}
}