{
  "type": "Feature",
  "properties": {
    "iso:country":"US",
    "sg:address":"5193 S Liverpool Way",
    "sg:city":"Aurora",
    "sg:classifiers":[
        {
            "category":"Shopping",
            "subcategory":"Beauty & Cosmetics",
            "type":"Retail Goods"
        }
    ],
    "sg:phone":"+1 303 766 4739",
    "sg:postcode":"80015",
    "sg:province":"CO",
    "sg:tags":[
        "merchandise"
    ],
    "wof:name":"Rebecca Mars",
    "wof:placetype":"venue"
},
  "geometry": {"coordinates":[-104.74462200000001,39.620441],"type":"Point"}
}