{
  "type": "Feature",
  "properties": {
    "iso:country":"US",
    "sg:address":"2255 Outlook Trl",
    "sg:city":"Broomfield",
    "sg:classifiers":[
        {
            "category":"Manufacturing",
            "subcategory":"Retail Goods",
            "type":"Manufacturing & Wholesale Goods"
        }
    ],
    "sg:phone":"+1 303 464 0513",
    "sg:postcode":"80020",
    "sg:province":"CO",
    "sg:tags":[
        "equipment",
        "product",
        "industrial",
        "mfg"
    ],
    "wof:name":"Freedom Lifts Corp",
    "wof:placetype":"venue"
},
  "geometry": {"coordinates":[-105.072382,39.946467],"type":"Point"}
}