{
  "type": "Feature",
  "properties": {
    "iso:country":"US",
    "sg:address":"330 Hilltop Rd",
    "sg:city":"Palmer Lake",
    "sg:classifiers":[
        {
            "category":"Building & Trades",
            "subcategory":"Construction",
            "type":"Services"
        }
    ],
    "sg:phone":"+1 719 481 4556",
    "sg:postcode":"80132",
    "sg:province":"CO",
    "sg:tags":[
        "paving",
        "contractor"
    ],
    "wof:name":"All-Ways Paving",
    "wof:placetype":"venue"
},
  "geometry": {"coordinates":[-104.90605100000001,39.110559],"type":"Point"}
}