{
  "type": "Feature",
  "properties": {
    "iso:country":"US",
    "sg:address":"4932 S Robb Way",
    "sg:city":"Littleton",
    "sg:classifiers":[
        {
            "category":"Freight",
            "type":"Transportation"
        }
    ],
    "sg:phone":"+1 303 674 1234",
    "sg:postcode":"80127",
    "sg:province":"CO",
    "sg:tags":[
        "operator",
        "local",
        "trucking"
    ],
    "sg:website":"www.titan-trucking.com",
    "wof:name":"Titan Trucking Inc",
    "wof:placetype":"venue"
},
  "geometry": {"coordinates":[-105.126954,39.627161],"type":"Point"}
}