{
  "type": "Feature",
  "properties": {
    "addr:full":"40450 E Colorado Ave Bennett CO 80102",
    "addr:housenumber":"40450",
    "addr:postcode":"80102",
    "addr:street":"E Colorado Ave",
    "iso:country":"US",
    "sg:address":"40450 E Colorado Ave",
    "sg:city":"Bennett",
    "sg:classifiers":[
        {
            "category":"Building & Trades",
            "subcategory":"Landscaping Services",
            "type":"Services"
        }
    ],
    "sg:phone":"+1 303 644 5110",
    "sg:postcode":"80102",
    "sg:province":"CO",
    "wof:name":"Lawn and More LLC",
    "wof:placetype":"venue"
},
  "geometry": {"coordinates":[-104.512258,39.682375],"type":"Point"}
}