{
  "type": "Feature",
  "properties": {
    "addr:full":"1005 W Mulberry Ln Littleton CO 80129",
    "addr:housenumber":"1005",
    "addr:postcode":"80129",
    "addr:street":"W Mulberry Ln",
    "iso:country":"US",
    "sg:address":"1005 W Mulberry Ln",
    "sg:city":"Littleton",
    "sg:classifiers":[
        {
            "category":"Real Estate",
            "subcategory":"Real Estate Operator",
            "type":"Services"
        }
    ],
    "sg:phone":"+1 303 346 1234",
    "sg:postcode":"80129",
    "sg:province":"CO",
    "sg:tags":[
        "building",
        "nonresidential"
    ],
    "wof:name":"Assent Land & Properties Inc",
    "wof:placetype":"venue"
},
  "geometry": {"coordinates":[-105.00117400000001,39.541305],"type":"Point"}
}