{
  "type": "Feature",
  "properties": {
    "addr:full":"521 N Main St La Junta CO 81050",
    "addr:housenumber":"521",
    "addr:postcode":"81050",
    "addr:street":"N Main St",
    "iso:country":"US",
    "sg:address":"521 N Main St",
    "sg:city":"La Junta",
    "sg:classifiers":[
        {
            "category":"Retail",
            "subcategory":"Portrait Studio",
            "type":"Services"
        }
    ],
    "sg:phone":"+1 719 383 0222",
    "sg:postcode":"81050",
    "sg:province":"CO",
    "sg:tags":[
        "photography"
    ],
    "wof:name":"Main Street Photography",
    "wof:placetype":"venue"
},
  "geometry": {"coordinates":[-103.53125799999999,38.004127],"type":"Point"}
}