{
  "type": "Feature",
  "properties": {
    "addr:full":"115 N C St Salida CO 81201",
    "addr:housenumber":"115",
    "addr:postcode":"81201",
    "addr:street":"N C St",
    "iso:country":"US",
    "sg:address":"115 N C St",
    "sg:city":"Salida",
    "sg:classifiers":[
        {
            "category":"Shopping",
            "subcategory":"Jewelry",
            "type":"Retail Goods"
        }
    ],
    "sg:phone":"+1 719 539 2971",
    "sg:postcode":"81201",
    "sg:province":"CO",
    "sg:tags":[
        "jeweler"
    ],
    "wof:name":"Scavezze Studio",
    "wof:placetype":"venue"
},
  "geometry": {"coordinates":[-105.98817699999999,38.534615],"type":"Point"}
}