{
  "type": "Feature",
  "properties": {
    "iso:country":"US",
    "sg:address":"3366 S Broadway",
    "sg:city":"Englewood",
    "sg:classifiers":[
        {
            "category":"Wholesale",
            "subcategory":"Non-durable Goods",
            "type":"Manufacturing & Wholesale Goods"
        }
    ],
    "sg:phone":"+1 303 781 0343",
    "sg:postcode":"80113",
    "sg:province":"CO",
    "wof:name":"Farris Survival LLC",
    "wof:placetype":"venue"
},
  "geometry": {"coordinates":[-104.987516,39.655461],"type":"Point"}
}