{
  "type": "Feature",
  "properties": {
    "iso:country":"US",
    "sg:address":"101 N Broadway",
    "sg:city":"Cortez",
    "sg:classifiers":[
        {
            "category":"Autos & Motor Vehicles",
            "subcategory":"Automobile Sales",
            "type":"Retail Goods"
        }
    ],
    "sg:phone":"+1 970 565 6800",
    "sg:postcode":"81321",
    "sg:province":"CO",
    "sg:tags":[
        "snowmobile"
    ],
    "wof:name":"Outdoor Connection",
    "wof:placetype":"venue"
},
  "geometry": {"coordinates":[-108.591105,37.351806],"type":"Point"}
}