{
  "type": "Feature",
  "properties": {
    "addr:full":"459 Gateway Rd Snowmass CO 81654",
    "addr:housenumber":"459",
    "addr:postcode":"81654",
    "addr:street":"Gateway Rd",
    "iso:country":"US",
    "sg:address":"459 Gateway Rd",
    "sg:city":"Snowmass",
    "sg:classifiers":[
        {
            "category":"Building & Trades",
            "subcategory":"Construction",
            "type":"Services"
        }
    ],
    "sg:phone":"+1 970 927 2228",
    "sg:postcode":"81654",
    "sg:province":"CO",
    "sg:tags":[
        "dry wall",
        "contractor"
    ],
    "wof:name":"All City Contracting Inc",
    "wof:placetype":"venue"
},
  "geometry": {"coordinates":[-106.98541400000001,39.313833],"type":"Point"}
}