{
  "type": "Feature",
  "properties": {
    "iso:country":"US",
    "sg:address":"320 S Cedar Brook Rd",
    "sg:city":"Boulder",
    "sg:classifiers":[
        {
            "category":"Professional",
            "subcategory":"Management & Consulting",
            "type":"Services"
        }
    ],
    "sg:phone":"+1 303 447 0558",
    "sg:postcode":"80304",
    "sg:province":"CO",
    "sg:tags":[
        "for",
        "re",
        "manager",
        "organization",
        "seminar",
        "volunteer"
    ],
    "sg:website":"www.volunteermanagement.com",
    "wof:name":"Volunteer Management Assoc",
    "wof:placetype":"venue"
},
  "geometry": {"coordinates":[-105.300898,40.038907],"type":"Point"}
}