{
  "type": "Feature",
  "properties": {
    "addr:full":"500 Broadway St Eagle CO 81631",
    "addr:housenumber":"500",
    "addr:postcode":"81631",
    "addr:street":"Broadway St",
    "iso:country":"US",
    "sg:address":"500 Broadway St",
    "sg:city":"Eagle",
    "sg:classifiers":[
        {
            "category":"Government",
            "subcategory":"Office",
            "type":"Public Place"
        }
    ],
    "sg:phone":"+1 970 328 8880",
    "sg:postcode":"81631",
    "sg:province":"CO",
    "wof:name":"Eagle Facilities Management",
    "wof:placetype":"venue"
},
  "geometry": {"coordinates":[-106.827789,39.651984],"type":"Point"}
}