{
  "type": "Feature",
  "properties": {
    "addr:full":"1470 Simms St Lakewood CO 80401",
    "addr:housenumber":"1470",
    "addr:postcode":"80401",
    "addr:street":"Simms St",
    "iso:country":"US",
    "sg:address":"1470 Simms St",
    "sg:city":"Lakewood",
    "sg:classifiers":[
        {
            "category":"Autos & Motor Vehicles",
            "subcategory":"Fuel & Gas Station",
            "type":"Retail Goods"
        },
        {
            "category":"Building & Trades",
            "subcategory":"Plumbing",
            "type":"Services"
        },
        {
            "category":"Retail",
            "subcategory":"Auto Repair",
            "type":"Services"
        }
    ],
    "sg:phone":"+1 303 233 8024",
    "sg:postcode":"80401",
    "sg:province":"CO",
    "sg:tags":[
        "alternator",
        "engine",
        "installation",
        "radiator",
        "exchange",
        "automotive",
        "sale",
        "generators-automotive",
        "radiators-repairing",
        "rebuilding",
        "repairing",
        "road",
        "service-automotive"
    ],
    "sg:website":"http://www.coloradovolvorepair.com",
    "wof:name":"Lakewood Imports",
    "wof:placetype":"venue"
},
  "geometry": {"coordinates":[-105.12831300000001,39.739571],"type":"Point"}
}