{
  "type": "Feature",
  "properties": {
    "iso:country":"US",
    "sg:address":"2175 N Ellicott Hwy",
    "sg:city":"Genoa",
    "sg:classifiers":[
        {
            "category":"Building & Trades",
            "subcategory":"Electrical",
            "type":"Services"
        }
    ],
    "sg:phone":"+1 719 683 4866",
    "sg:postcode":"80808",
    "sg:province":"CO",
    "sg:tags":[
        "electric",
        "contractor"
    ],
    "wof:name":"Lenz Electric Inc",
    "wof:placetype":"venue"
},
  "geometry": {"coordinates":[-104.38727,38.863025],"type":"Point"}
}