{
  "type": "Feature",
  "properties": {
    "iso:country":"US",
    "sg:address":"4523 E Fenwood Pl",
    "sg:city":"Littleton",
    "sg:classifiers":[
        {
            "category":"Professional",
            "subcategory":"Engineering",
            "type":"Services"
        }
    ],
    "sg:phone":"+1 720 299 2545",
    "sg:postcode":"80130",
    "sg:province":"CO",
    "sg:tags":[
        "engineer"
    ],
    "wof:name":"Highland Frontier Consulting",
    "wof:placetype":"venue"
},
  "geometry": {"coordinates":[-104.936021,39.532565],"type":"Point"}
}