{
  "type": "Feature",
  "properties": {
    "addr:full":"1951 S Federal Blvd Denver CO 80219",
    "addr:housenumber":"1951",
    "addr:postcode":"80219",
    "addr:street":"S Federal Blvd",
    "iso:country":"US",
    "sg:address":"1951 S Federal Blvd",
    "sg:city":"Denver",
    "sg:classifiers":[
        {
            "category":"Shopping",
            "subcategory":"Discount & Variety Stores",
            "type":"Retail Goods"
        }
    ],
    "sg:phone":"+1 303 936 2799",
    "sg:postcode":"80219",
    "sg:province":"CO",
    "sg:website":"www.biglots.com",
    "wof:name":"Big Lots",
    "wof:placetype":"venue"
},
  "geometry": {"coordinates":[-105.025108,39.681406],"type":"Point"}
}