{
  "type": "Feature",
  "properties": {
    "addr:full":"3360 N el Paso St Colorado Springs CO 80907",
    "addr:housenumber":"3360",
    "addr:postcode":"80907",
    "addr:street":"N El Paso St",
    "iso:country":"US",
    "sg:address":"3360 N el Paso St",
    "sg:city":"Colorado Springs",
    "sg:classifiers":[
        {
            "category":"Building & Trades",
            "subcategory":"Construction",
            "type":"Services"
        }
    ],
    "sg:phone":"+1 719 442 2225",
    "sg:postcode":"80907",
    "sg:province":"CO",
    "sg:tags":[
        "contractor"
    ],
    "wof:name":"Braverman Jim Fine Furn Design",
    "wof:placetype":"venue"
},
  "geometry": {"coordinates":[-104.812798,38.881812],"type":"Point"}
}