{
  "type": "Feature",
  "properties": {
    "addr:full":"8121 1st St Wellington CO 80549",
    "addr:housenumber":"8121",
    "addr:postcode":"80549",
    "addr:street":"1St St",
    "iso:country":"US",
    "sg:address":"8121 1st St",
    "sg:city":"Wellington",
    "sg:classifiers":[
        {
            "category":"Autos & Motor Vehicles",
            "subcategory":"Automobile Sales",
            "type":"Retail Goods"
        }
    ],
    "sg:phone":"+1 970 568 1115",
    "sg:postcode":"80549",
    "sg:province":"CO",
    "sg:tags":[
        "classic"
    ],
    "wof:name":"Tower Automotive LTD",
    "wof:placetype":"venue"
},
  "geometry": {"coordinates":[-105.007671,40.702299],"type":"Point"}
}