{
  "type": "Feature",
  "properties": {
    "iso:country":"US",
    "sg:address":"3300 S Wadsworth Blvd",
    "sg:city":"Lakewood",
    "sg:classifiers":[
        {
            "category":"Retail",
            "subcategory":"Veterinary Services",
            "type":"Services"
        }
    ],
    "sg:phone":"+1 303 985 2836",
    "sg:postcode":"80227",
    "sg:province":"CO",
    "sg:tags":[
        "veterinarian"
    ],
    "wof:name":"Bear Creek Animal Hospital",
    "wof:placetype":"venue"
},
  "geometry": {"coordinates":[-105.081262,39.653403],"type":"Point"}
}