{
  "type": "Feature",
  "properties": {
    "iso:country":"US",
    "sg:address":"2360 Allyn Way",
    "sg:city":"Colorado Springs",
    "sg:classifiers":[
        {
            "category":"Building & Trades",
            "subcategory":"Construction",
            "type":"Services"
        }
    ],
    "sg:phone":"+1 719 491 3082",
    "sg:postcode":"80915",
    "sg:province":"CO",
    "sg:tags":[
        "handyman"
    ],
    "wof:name":"Greg's Handyman",
    "wof:placetype":"venue"
},
  "geometry": {"coordinates":[-104.700459,38.866074],"type":"Point"}
}