{
  "type": "Feature",
  "properties": {
    "iso:country":"US",
    "sg:address":"224 W 3rd St",
    "sg:city":"La Junta",
    "sg:classifiers":[
        {
            "category":"Health Services",
            "subcategory":"Health Practitioner",
            "type":"Services"
        }
    ],
    "sg:phone":"+1 719 384 5673",
    "sg:postcode":"81050",
    "sg:province":"CO",
    "sg:tags":[
        "physician"
    ],
    "wof:name":"Dr Love's Clinic-Alternative",
    "wof:placetype":"venue"
},
  "geometry": {"coordinates":[-103.54618499999999,37.985857],"type":"Point"}
}