{
  "type": "Feature",
  "properties": {
    "iso:country":"US",
    "sg:address":"1400 16th Street",
    "sg:city":"Denver",
    "sg:classifiers":[
        {
            "category":"Utilities",
            "type":"Services"
        }
    ],
    "sg:phone":"+1 720 904 0300",
    "sg:postcode":"80202",
    "sg:province":"CO",
    "sg:tags":[
        "provider",
        "internet"
    ],
    "wof:name":"Broadhop",
    "wof:placetype":"venue"
},
  "geometry": {"coordinates":[-104.99832600000001,39.749855],"type":"Point"}
}