{
  "type": "Feature",
  "properties": {
    "addr:full":"960 E Collins St Eaton CO 80615",
    "addr:housenumber":"960",
    "addr:postcode":"80615",
    "addr:street":"E Collins St",
    "iso:country":"US",
    "sg:address":"960 E Collins St",
    "sg:city":"Eaton",
    "sg:classifiers":[
        {
            "category":"Autos & Motor Vehicles",
            "subcategory":"Automobile Sales",
            "type":"Retail Goods"
        }
    ],
    "sg:phone":"+1 970 454 2100",
    "sg:postcode":"80615",
    "sg:province":"CO",
    "sg:tags":[
        "used",
        "parts"
    ],
    "sg:website":"www.carznparts.com",
    "wof:name":"Cars N Parts Inc",
    "wof:placetype":"venue"
},
  "geometry": {"coordinates":[-104.70160300000001,40.524285],"type":"Point"}
}