{
  "type": "Feature",
  "properties": {
    "iso:country":"US",
    "sg:address":"5754 Lamar St",
    "sg:city":"Arvada",
    "sg:classifiers":[
        {
            "category":"Wholesale",
            "subcategory":"Machinery & Supplies",
            "type":"Manufacturing & Wholesale Goods"
        }
    ],
    "sg:phone":"+1 303 424 3551",
    "sg:postcode":"80002",
    "sg:province":"CO",
    "sg:tags":[
        "water",
        "pump"
    ],
    "wof:name":"Denver Winpump Company",
    "wof:placetype":"venue"
},
  "geometry": {"coordinates":[-105.06722600000001,39.801312],"type":"Point"}
}