{
  "type": "Feature",
  "properties": {
    "iso:country":"US",
    "sg:address":"4463 Aaron Pl",
    "sg:city":"Boulder",
    "sg:classifiers":[
        {
            "category":"Professional",
            "type":"Services"
        }
    ],
    "sg:phone":"+1 303 497 1605",
    "sg:postcode":"80303",
    "sg:province":"CO",
    "wof:name":"R Sievering",
    "wof:placetype":"venue"
},
  "geometry": {"coordinates":[-105.238642,40.012505],"type":"Point"}
}