{
  "type": "Feature",
  "properties": {
    "addr:full":"2000 Iris Ave Boulder CO 80304",
    "addr:housenumber":"2000",
    "addr:postcode":"80304",
    "addr:street":"Iris Ave",
    "iso:country":"US",
    "sg:address":"2000 Iris Ave",
    "sg:city":"Boulder",
    "sg:classifiers":[
        {
            "category":"Professional",
            "subcategory":"Art Services",
            "type":"Services"
        },
        {
            "category":"Manufacturing",
            "subcategory":"Printing",
            "type":"Manufacturing & Wholesale Goods"
        }
    ],
    "sg:phone":"+1 303 444 6996",
    "sg:postcode":"80304",
    "sg:province":"CO",
    "sg:tags":[
        "graphic",
        "design",
        "typesetting"
    ],
    "wof:name":"One World Arts",
    "wof:placetype":"venue"
},
  "geometry": {"coordinates":[-105.268505,40.036421],"type":"Point"}
}