{
  "type": "Feature",
  "properties": {
    "addr:full":"610 Garrison St Denver CO 80215",
    "addr:housenumber":"610",
    "addr:postcode":"80215",
    "addr:street":"Garrison St",
    "iso:country":"US",
    "sg:address":"610 Garrison St",
    "sg:city":"Denver",
    "sg:classifiers":[
        {
            "category":"Communications",
            "subcategory":"Radio Station",
            "type":"Services"
        }
    ],
    "sg:phone":"+1 303 205 1234",
    "sg:postcode":"80215",
    "sg:province":"CO",
    "sg:tags":[
        "broadcast"
    ],
    "wof:name":"K-Love",
    "wof:placetype":"venue"
},
  "geometry": {"coordinates":[-105.10024900000001,39.725853],"type":"Point"}
}