{
  "type": "Feature",
  "properties": {
    "addr:full":"191 E Orchard Rd Littleton CO 80121",
    "addr:housenumber":"191",
    "addr:postcode":"80121",
    "addr:street":"E Orchard Rd",
    "iso:country":"US",
    "sg:address":"191 E Orchard Rd",
    "sg:city":"Littleton",
    "sg:classifiers":[
        {
            "category":"Education",
            "subcategory":"Special Training",
            "type":"Public Place"
        },
        {
            "category":"Health Services",
            "subcategory":"Doctor",
            "type":"Services"
        }
    ],
    "sg:phone":"+1 303 738 0101",
    "sg:postcode":"80121",
    "sg:province":"CO",
    "sg:tags":[
        "clinic"
    ],
    "wof:name":"Swedish Family Medicine Ctr",
    "wof:placetype":"venue"
},
  "geometry": {"coordinates":[-104.987492,39.609664],"type":"Point"}
}