{
  "type": "Feature",
  "properties": {
    "addr:full":"1635 Foxfire Rd Bayfield CO 81122",
    "addr:housenumber":"1635",
    "addr:postcode":"81122",
    "addr:street":"Foxfire Rd",
    "iso:country":"US",
    "sg:address":"1635 Foxfire Rd",
    "sg:city":"Bayfield",
    "sg:classifiers":[
        {
            "category":"Retail",
            "subcategory":"Animal Services",
            "type":"Services"
        }
    ],
    "sg:phone":"+1 970 884 5284",
    "sg:postcode":"81122",
    "sg:province":"CO",
    "sg:tags":[
        "pet",
        "boarding",
        "sitting"
    ],
    "wof:name":"Margaret Brooks Wild Haven",
    "wof:placetype":"venue"
},
  "geometry": {"coordinates":[-107.672265,37.249845],"type":"Point"}
}