{
  "type": "Feature",
  "properties": {
    "iso:country":"US",
    "sg:address":"406 E Colfax Ave",
    "sg:city":"Denver",
    "sg:classifiers":[
        {
            "category":"Restaurant",
            "type":"Food & Drink"
        }
    ],
    "sg:phone":"+1 303 620 9306",
    "sg:postcode":"80218",
    "sg:province":"CO",
    "wof:name":"Mt Everest Cafe",
    "wof:placetype":"venue"
},
  "geometry": {"coordinates":[-104.981769,39.739949],"type":"Point"}
}