{
  "type": "Feature",
  "properties": {
    "addr:full":"4652 Anaheim Ct Denver CO 80239",
    "addr:housenumber":"4652",
    "addr:postcode":"80239",
    "addr:street":"Anaheim Ct",
    "iso:country":"US",
    "sg:address":"4652 Anaheim Ct",
    "sg:city":"Denver",
    "sg:classifiers":[
        {
            "category":"Health Services",
            "subcategory":"Nursing And Care Facility",
            "type":"Services"
        }
    ],
    "sg:phone":"+1 303 373 9541",
    "sg:postcode":"80239",
    "sg:province":"CO",
    "sg:tags":[
        "home",
        "retirement",
        "community"
    ],
    "wof:name":"Mc Coy Prsnl Care Brding Home",
    "wof:placetype":"venue"
},
  "geometry": {"coordinates":[-104.834074,39.781176],"type":"Point"}
}