{
  "type": "Feature",
  "properties": {
    "addr:full":"281 Adams Ave Akron CO 80720",
    "addr:housenumber":"281",
    "addr:postcode":"80720",
    "addr:street":"Adams Ave",
    "iso:country":"US",
    "sg:address":"281 Adams Ave",
    "sg:city":"Akron",
    "sg:classifiers":[
        {
            "category":"Professional",
            "type":"Services"
        }
    ],
    "sg:phone":"+1 970 345 2330",
    "sg:postcode":"80720",
    "sg:province":"CO",
    "sg:tags":[
        "establishment"
    ],
    "wof:name":"Newstart Therapy",
    "wof:placetype":"venue"
},
  "geometry": {"coordinates":[-103.21428400000001,40.16033],"type":"Point"}
}