{
  "type": "Feature",
  "properties": {
    "addr:full":"3053 W 74th Ave Westminster CO 80030",
    "addr:housenumber":"3053",
    "addr:postcode":"80030",
    "addr:street":"W 74Th Ave",
    "iso:country":"US",
    "sg:address":"3053 W 74th Ave",
    "sg:city":"Westminster",
    "sg:classifiers":[
        {
            "category":"Food & Beverages",
            "subcategory":"Groceries & Convenience Stores",
            "type":"Retail Goods"
        }
    ],
    "sg:phone":"+1 720 540 5697",
    "sg:postcode":"80030",
    "sg:province":"CO",
    "sg:tags":[
        "grocer"
    ],
    "wof:name":"King Oriental Market",
    "wof:placetype":"venue"
},
  "geometry": {"coordinates":[-105.028983,39.830975],"type":"Point"}
}