{
  "type": "Feature",
  "properties": {
    "iso:country":"US",
    "sg:address":"3176 S Peoria Ct",
    "sg:city":"Aurora",
    "sg:classifiers":[
        {
            "category":"Real Estate",
            "subcategory":"Real Estate Services",
            "type":"Services"
        }
    ],
    "sg:phone":"+1 303 596 0566",
    "sg:postcode":"80014",
    "sg:province":"CO",
    "sg:tags":[
        "management"
    ],
    "wof:name":"Transit Management Holding Corp.",
    "wof:placetype":"venue"
},
  "geometry": {"coordinates":[-104.848019,39.658325],"type":"Point"}
}