{
  "type": "Feature",
  "properties": {
    "addr:full":"2715 S Prairie Ave Pueblo CO 81005",
    "addr:housenumber":"2715",
    "addr:postcode":"81005",
    "addr:street":"S Prairie Ave",
    "iso:country":"US",
    "sg:address":"2715 S Prairie Ave",
    "sg:city":"Pueblo",
    "sg:classifiers":[
        {
            "category":"Shopping",
            "type":"Retail Goods"
        },
        {
            "category":"Wholesale",
            "subcategory":"Sporting Goods",
            "type":"Manufacturing & Wholesale Goods"
        }
    ],
    "sg:phone":"+1 719 564 2918",
    "sg:postcode":"81005",
    "sg:province":"CO",
    "sg:tags":[
        "equipment",
        "law",
        "police",
        "enforcement",
        "supply"
    ],
    "wof:name":"T & N Police Equipment",
    "wof:placetype":"venue"
},
  "geometry": {"coordinates":[-104.643772,38.224322],"type":"Point"}
}