{
  "type": "Feature",
  "properties": {
    "iso:country":"US",
    "sg:address":"402 Tungsten Pl",
    "sg:city":"Longmont",
    "sg:classifiers":[
        {
            "category":"Professional",
            "type":"Services"
        }
    ],
    "sg:phone":"+1 303 772 1598",
    "sg:postcode":"80501",
    "sg:province":"CO",
    "sg:tags":[
        "establishment"
    ],
    "wof:name":"Bright Mornings",
    "wof:placetype":"venue"
},
  "geometry": {"coordinates":[-105.081836,40.179301],"type":"Point"}
}