{
  "type": "Feature",
  "properties": {
    "iso:country":"US",
    "sg:address":"570 S Broadway",
    "sg:city":"Denver",
    "sg:classifiers":[
        {
            "category":"Health Services",
            "subcategory":"Health Practitioner",
            "type":"Services"
        }
    ],
    "sg:phone":"+1 303 777 0320",
    "sg:postcode":"80209",
    "sg:province":"CO",
    "sg:tags":[
        "acupuncture"
    ],
    "sg:website":"www.MeetingPointAcupuncture.com",
    "wof:name":"Meeting Point Community Acupuncture",
    "wof:placetype":"venue"
},
  "geometry": {"coordinates":[-104.987158,39.706131],"type":"Point"}
}