{
  "type": "Feature",
  "properties": {
    "addr:full":"6545 Glade Park Dr Colorado Springs CO 80918",
    "addr:housenumber":"6545",
    "addr:postcode":"80918",
    "addr:street":"Glade Park Dr",
    "iso:country":"US",
    "sg:address":"6545 Glade Park Dr",
    "sg:city":"Colorado Springs",
    "sg:classifiers":[
        {
            "category":"Manufacturing",
            "subcategory":"Printing",
            "type":"Manufacturing & Wholesale Goods"
        }
    ],
    "sg:phone":"+1 719 532 1342",
    "sg:postcode":"80918",
    "sg:province":"CO",
    "sg:tags":[
        "commercial"
    ],
    "wof:name":"Acme Screen Printing",
    "wof:placetype":"venue"
},
  "geometry": {"coordinates":[-104.764655,38.926401],"type":"Point"}
}