{
  "type": "Feature",
  "properties": {
    "addr:full":"2050 Floral Dr Boulder CO 80304",
    "addr:housenumber":"2050",
    "addr:postcode":"80304",
    "addr:street":"Floral Dr",
    "iso:country":"US",
    "sg:address":"2050 Floral Dr",
    "sg:city":"Boulder",
    "sg:classifiers":[
        {
            "category":"Food & Beverages",
            "subcategory":"Groceries & Convenience Stores",
            "type":"Retail Goods"
        }
    ],
    "sg:phone":"+1 303 554 7000",
    "sg:postcode":"80304",
    "sg:province":"CO",
    "sg:tags":[
        "product"
    ],
    "wof:name":"Phil's Fresh Foods",
    "wof:placetype":"venue"
},
  "geometry": {"coordinates":[-105.270145,40.031008],"type":"Point"}
}