{
  "type": "Feature",
  "properties": {
    "iso:country":"US",
    "sg:address":"7201 E Wiltshire Ct",
    "sg:city":"Littleton",
    "sg:classifiers":[
        {
            "category":"Utilities",
            "subcategory":"Cable",
            "type":"Services"
        }
    ],
    "sg:phone":"+1 303 683 0321",
    "sg:postcode":"80130",
    "sg:province":"CO",
    "sg:tags":[
        "television"
    ],
    "wof:name":"Contec LP",
    "wof:placetype":"venue"
},
  "geometry": {"coordinates":[-104.905896,39.545173],"type":"Point"}
}