{
  "type": "Feature",
  "properties": {
    "iso:country":"US",
    "sg:address":"650 S Cherry St",
    "sg:city":"Denver",
    "sg:classifiers":[
        {
            "category":"Real Estate",
            "subcategory":"Developer",
            "type":"Services"
        }
    ],
    "sg:phone":"+1 303 321 8888",
    "sg:postcode":"80246",
    "sg:province":"CO",
    "sg:tags":[
        "development"
    ],
    "wof:name":"Bansbach Perry & Macy Inc",
    "wof:placetype":"venue"
},
  "geometry": {"coordinates":[-104.933635,39.704826],"type":"Point"}
}