{
  "type": "Feature",
  "properties": {
    "iso:country":"US",
    "sg:address":"1216 Walz Ave",
    "sg:city":"Glenwood Springs",
    "sg:classifiers":[
        {
            "category":"Banks & Credit Unions",
            "subcategory":"Bank",
            "type":"Services"
        }
    ],
    "sg:phone":"+1 970 945 5021",
    "sg:postcode":"81601",
    "sg:province":"CO",
    "sg:tags":[
        "loan",
        "real estate"
    ],
    "wof:name":"Sopris Investments",
    "wof:placetype":"venue"
},
  "geometry": {"coordinates":[-107.333229,39.542225],"type":"Point"}
}