{
  "type": "Feature",
  "properties": {
    "addr:full":"4901 W 93rd Ave Westminster CO 80031",
    "addr:housenumber":"4901",
    "addr:postcode":"80031",
    "addr:street":"W 93Rd Ave",
    "iso:country":"US",
    "sg:address":"4901 W 93rd Ave",
    "sg:city":"Westminster",
    "sg:classifiers":[
        {
            "category":"Wholesale",
            "subcategory":"Hardware",
            "type":"Manufacturing & Wholesale Goods"
        }
    ],
    "sg:phone":"+1 303 427 7878",
    "sg:postcode":"80031",
    "sg:province":"CO",
    "sg:tags":[
        "refrigeration"
    ],
    "wof:name":"Infinity Beverage Services",
    "wof:placetype":"venue"
},
  "geometry": {"coordinates":[-105.048588,39.865265],"type":"Point"}
}