{
  "type": "Feature",
  "properties": {
    "addr:full":"11693 Stoneybrooke St Parker CO 80138",
    "addr:postcode":"11693;80138",
    "addr:street":"Stoneybrooke St",
    "iso:country":"US",
    "sg:address":"11693 Stoneybrooke St",
    "sg:city":"Parker",
    "sg:classifiers":[
        {
            "category":"Banks & Credit Unions",
            "subcategory":"Investment Brokerage",
            "type":"Services"
        }
    ],
    "sg:phone":"+1 303 805 7273",
    "sg:postcode":"80138",
    "sg:province":"CO",
    "sg:tags":[
        "consultant",
        "planning",
        "financial"
    ],
    "wof:name":"William N Patton",
    "wof:placetype":"venue"
},
  "geometry": {"coordinates":[-104.71426700000001,39.505271],"type":"Point"}
}