{
  "type": "Feature",
  "properties": {
    "iso:country":"US",
    "sg:address":"315 E 4th St",
    "sg:city":"Loveland",
    "sg:classifiers":[
        {
            "category":"Shopping",
            "subcategory":"Gifts & Souvenirs",
            "type":"Retail Goods"
        }
    ],
    "sg:phone":"+1 970 663 9250",
    "sg:postcode":"80537",
    "sg:province":"CO",
    "wof:name":"Angels In Alley",
    "wof:placetype":"venue"
},
  "geometry": {"coordinates":[-105.073062,40.395513],"type":"Point"}
}