{
  "type": "Feature",
  "properties": {
    "iso:country":"US",
    "sg:address":"3920 Tennyson St",
    "sg:city":"Denver",
    "sg:classifiers":[
        {
            "category":"Communications",
            "subcategory":"Newspaper",
            "type":"Services"
        }
    ],
    "sg:phone":"+1 303 455 3870",
    "sg:postcode":"80212",
    "sg:province":"CO",
    "sg:tags":[
        "print",
        "medium"
    ],
    "wof:name":"Shot Magazine",
    "wof:placetype":"venue"
},
  "geometry": {"coordinates":[-105.04385,39.771236],"type":"Point"}
}