{
  "type": "Feature",
  "properties": {
    "addr:full":"1832 Forest Ave Durango CO 81301",
    "addr:housenumber":"1832",
    "addr:postcode":"co 81301",
    "addr:street":"Forest Ave",
    "iso:country":"US",
    "sg:address":"1832 Forest Ave",
    "sg:city":"Durango",
    "sg:classifiers":[
        {
            "category":"Building & Trades",
            "subcategory":"Construction",
            "type":"Services"
        }
    ],
    "sg:phone":"+1 970 259 1302",
    "sg:postcode":"81301",
    "sg:province":"CO",
    "sg:tags":[
        "house"
    ],
    "wof:name":"Alternative Construction",
    "wof:placetype":"venue"
},
  "geometry": {"coordinates":[-107.88367599999999,37.283814],"type":"Point"}
}