{
  "type": "Feature",
  "properties": {
    "iso:country":"US",
    "sg:address":"5863 Terminal Ave",
    "sg:city":"Colorado Springs",
    "sg:classifiers":[
        {
            "category":"Manufacturing",
            "subcategory":"Printing",
            "type":"Manufacturing & Wholesale Goods"
        }
    ],
    "sg:phone":"+1 719 380 0161",
    "sg:postcode":"80915",
    "sg:province":"CO",
    "sg:tags":[
        "lithographic",
        "commercial"
    ],
    "wof:name":"Telecom Printing Inc",
    "wof:placetype":"venue"
},
  "geometry": {"coordinates":[-104.720365,38.842013],"type":"Point"}
}