{
  "type": "Feature",
  "properties": {
    "iso:country":"US",
    "sg:address":"1863 Wazee St",
    "sg:city":"Denver",
    "sg:classifiers":[
        {
            "category":"Professional",
            "type":"Services"
        },
        {
            "category":"Professional",
            "subcategory":"Art Services",
            "type":"Services"
        }
    ],
    "sg:phone":"+1 720 989 1583",
    "sg:postcode":"80202",
    "sg:province":"CO",
    "sg:tags":[
        "photographer"
    ],
    "sg:website":"www.emilydunnphotography.com",
    "wof:name":"Emily Dunn Photography",
    "wof:placetype":"venue"
},
  "geometry": {"coordinates":[-104.996995,39.753952],"type":"Point"}
}