{
  "type": "Feature",
  "properties": {
    "iso:country":"US",
    "sg:address":"5311 Sanford Cir E",
    "sg:city":"Englewood",
    "sg:classifiers":[
        {
            "category":"Restaurant",
            "type":"Food & Drink"
        }
    ],
    "sg:phone":"+1 303 757 3208",
    "sg:postcode":"80110",
    "sg:province":"CO",
    "sg:tags":[
        "eating"
    ],
    "wof:name":"KFC Investments LLC",
    "wof:placetype":"venue"
},
  "geometry": {"coordinates":[-104.924809,39.643818],"type":"Point"}
}