{
  "type": "Feature",
  "properties": {
    "addr:full":"805 S Shields St Fort Collins CO 80521",
    "addr:housenumber":"805",
    "addr:postcode":"80521",
    "addr:street":"S Shields St",
    "iso:country":"US",
    "sg:address":"805 S Shields St",
    "sg:city":"Fort Collins",
    "sg:classifiers":[
        {
            "category":"Organizations",
            "subcategory":"Religious Organization",
            "type":"Services"
        }
    ],
    "sg:phone":"+1 970 221 0811",
    "sg:postcode":"80521",
    "sg:province":"CO",
    "sg:tags":[
        "church"
    ],
    "wof:name":"Metropolitan Community Church",
    "wof:placetype":"venue"
},
  "geometry": {"coordinates":[-105.096017,40.574648],"type":"Point"}
}