{
  "type": "Feature",
  "properties": {
    "addr:full":"3260 E Woodmen Rd Colorado Springs CO 80920",
    "addr:housenumber":"3260",
    "addr:postcode":"80920",
    "addr:street":"E Woodmen Rd",
    "iso:country":"US",
    "sg:address":"3260 E Woodmen Rd",
    "sg:city":"Colorado Springs",
    "sg:classifiers":[
        {
            "category":"Health Services",
            "subcategory":"Doctor",
            "type":"Services"
        }
    ],
    "sg:phone":"+1 719 262 0852",
    "sg:postcode":"80920",
    "sg:province":"CO",
    "sg:tags":[
        "physician",
        "surgeon"
    ],
    "wof:name":"Front Range Family Medicine",
    "wof:placetype":"venue"
},
  "geometry": {"coordinates":[-104.76542600000001,38.935405],"type":"Point"}
}