{
  "type": "Feature",
  "properties": {
    "iso:country":"US",
    "sg:address":"112 A St",
    "sg:city":"Cripple Creek",
    "sg:classifiers":[
        {
            "category":"Government",
            "subcategory":"Office",
            "type":"Public Place"
        }
    ],
    "sg:phone":"+1 719 689 2988",
    "sg:postcode":"80813",
    "sg:province":"CO",
    "wof:name":"Teller County Commissioners",
    "wof:placetype":"venue"
},
  "geometry": {"coordinates":[-105.182388,38.746904],"type":"Point"}
}