{
  "type": "Feature",
  "properties": {
    "addr:full":"3993 26th St Boulder CO 80304",
    "addr:housenumber":"3993",
    "addr:postcode":"80304",
    "addr:street":"26Th St",
    "iso:country":"US",
    "sg:address":"3993 26th St",
    "sg:city":"Boulder",
    "sg:classifiers":[
        {
            "category":"Education",
            "subcategory":"Dance Studio",
            "type":"Public Place"
        }
    ],
    "sg:phone":"+1 303 417 9518",
    "sg:postcode":"80304",
    "sg:province":"CO",
    "sg:tags":[
        "instruction",
        "dancing"
    ],
    "wof:name":"Dance Place",
    "wof:placetype":"venue"
},
  "geometry": {"coordinates":[-105.26334199999999,40.046893],"type":"Point"}
}