{
  "type": "Feature",
  "properties": {
    "addr:full":"205 W 5th St Delta CO 81416",
    "addr:housenumber":"205",
    "addr:postcode":"81416",
    "addr:street":"W 5Th St",
    "iso:country":"US",
    "sg:address":"205 W 5th St",
    "sg:city":"Delta",
    "sg:classifiers":[
        {
            "category":"Insurance",
            "subcategory":"Insurance Agent",
            "type":"Services"
        }
    ],
    "sg:phone":"+1 970 874 4337",
    "sg:postcode":"81416",
    "sg:province":"CO",
    "wof:name":"Farmers Union Insurance",
    "wof:placetype":"venue"
},
  "geometry": {"coordinates":[-108.072191,38.740418],"type":"Point"}
}