{
  "type": "Feature",
  "properties": {
    "iso:country":"US",
    "sg:address":"4665 Josephine St",
    "sg:city":"Denver",
    "sg:classifiers":[
        {
            "category":"Building & Trades",
            "subcategory":"Locksmith",
            "type":"Services"
        }
    ],
    "sg:phone":"+1 303 218 7294",
    "sg:postcode":"80216",
    "sg:province":"CO",
    "sg:tags":[
        "key"
    ],
    "wof:name":"Locksmith 24 Hours",
    "wof:placetype":"venue"
},
  "geometry": {"coordinates":[-104.95831800000001,39.781259],"type":"Point"}
}