{
  "type": "Feature",
  "properties": {
    "addr:full":"65 S Dudley St Denver CO 80226",
    "addr:housenumber":"65",
    "addr:postcode":"80226",
    "addr:street":"S Dudley St",
    "iso:country":"US",
    "sg:address":"65 S Dudley St",
    "sg:city":"Denver",
    "sg:classifiers":[
        {
            "category":"Professional",
            "type":"Services"
        }
    ],
    "sg:phone":"+1 303 237 6740",
    "sg:postcode":"80226",
    "sg:province":"CO",
    "wof:name":"B&L Brokers Inc",
    "wof:placetype":"venue"
},
  "geometry": {"coordinates":[-105.094994,39.715693],"type":"Point"}
}