{
  "type": "Feature",
  "properties": {
    "addr:full":"10715 E Chinook Trl Parker CO 80138",
    "addr:housenumber":"10715",
    "addr:postcode":"80138",
    "addr:street":"E Chinook Trl",
    "iso:country":"US",
    "sg:address":"10715 E Chinook Trl",
    "sg:city":"Parker",
    "sg:classifiers":[
        {
            "category":"Building & Trades",
            "subcategory":"Construction",
            "type":"Services"
        }
    ],
    "sg:phone":"+1 303 841 6541",
    "sg:postcode":"80138",
    "sg:province":"CO",
    "sg:tags":[
        "house"
    ],
    "wof:name":"David Peterson Const Inc",
    "wof:placetype":"venue"
},
  "geometry": {"coordinates":[-104.685348,39.479262],"type":"Point"}
}