{
  "type": "Feature",
  "properties": {
    "addr:full":"711 Manitou Ave Manitou Springs CO 80829",
    "addr:housenumber":"711",
    "addr:postcode":"80829",
    "addr:street":"Manitou Ave",
    "iso:country":"US",
    "sg:address":"711 Manitou Ave",
    "sg:city":"Manitou Springs",
    "sg:classifiers":[
        {
            "category":"Travel",
            "subcategory":"Hotels & Motels",
            "type":"Entertainment"
        },
        {
            "category":"Travel",
            "subcategory":"Bed & Breakfast",
            "type":"Entertainment"
        }
    ],
    "sg:phone":"+1 719 685 1277",
    "sg:postcode":"80829",
    "sg:province":"CO",
    "sg:website":"www.avenuehotelbandb.com",
    "wof:name":"Avenue Hotel Bed And Breakfast",
    "wof:placetype":"venue"
},
  "geometry": {"coordinates":[-104.914974,38.856739],"type":"Point"}
}