{
  "type": "Feature",
  "properties": {
    "iso:country":"US",
    "sg:address":"14 Inverness Dr E",
    "sg:city":"Englewood",
    "sg:classifiers":[
        {
            "category":"Insurance",
            "subcategory":"Insurance Agent",
            "type":"Services"
        }
    ],
    "sg:phone":"+1 303 799 1977",
    "sg:postcode":"80112",
    "sg:province":"CO",
    "wof:name":"Brandland Insurance",
    "wof:placetype":"venue"
},
  "geometry": {"coordinates":[-104.86219699999999,39.566915],"type":"Point"}
}