{
  "type": "Feature",
  "properties": {
    "iso:country":"US",
    "sg:address":"9032 W Ken Caryl Ave",
    "sg:city":"Littleton",
    "sg:classifiers":[
        {
            "category":"Food & Beverages",
            "subcategory":"Liquor & Beverages",
            "type":"Retail Goods"
        }
    ],
    "sg:phone":"+1 303 973 1207",
    "sg:postcode":"80128",
    "sg:province":"CO",
    "sg:tags":[
        "alcoholic"
    ],
    "wof:name":"Ken Caryl Liquors",
    "wof:placetype":"venue"
},
  "geometry": {"coordinates":[-105.100514,39.580651],"type":"Point"}
}