{
  "type": "Feature",
  "properties": {
    "iso:country":"US",
    "sg:address":"6279 W 38th Ave",
    "sg:city":"Wheat Ridge",
    "sg:classifiers":[
        {
            "category":"Real Estate",
            "subcategory":"Real Estate Agent",
            "type":"Services"
        }
    ],
    "sg:phone":"+1 303 422 1826",
    "sg:postcode":"80033",
    "sg:province":"CO",
    "wof:name":"Wedgwood & Associates",
    "wof:placetype":"venue"
},
  "geometry": {"coordinates":[-105.066613,39.76944],"type":"Point"}
}