{
  "type": "Feature",
  "properties": {
    "iso:country":"US",
    "sg:address":"7757 E 36th Ave",
    "sg:city":"Denver",
    "sg:classifiers":[
        {
            "category":"Shopping",
            "subcategory":"Party Supplies",
            "type":"Retail Goods"
        }
    ],
    "sg:phone":"+1 303 355 6223",
    "sg:postcode":"80238",
    "sg:province":"CO",
    "wof:name":"Party City",
    "wof:placetype":"venue"
},
  "geometry": {"coordinates":[-104.897919,39.767447],"type":"Point"}
}