{
  "type": "Feature",
  "properties": {
    "iso:country":"US",
    "sg:address":"4909 Pearl East Cir",
    "sg:city":"Boulder",
    "sg:classifiers":[
        {
            "category":"Professional",
            "subcategory":"Accounting & Tax Preparation",
            "type":"Services"
        }
    ],
    "sg:phone":"+1 303 444 0471",
    "sg:postcode":"80301",
    "sg:province":"CO",
    "sg:tags":[
        "accountant",
        "public",
        "certified"
    ],
    "wof:name":"Cbiz",
    "wof:placetype":"venue"
},
  "geometry": {"coordinates":[-105.240796,40.021594],"type":"Point"}
}