{
  "type": "Feature",
  "properties": {
    "addr:full":"8850 Yosemite St Henderson CO 80640",
    "addr:housenumber":"8850",
    "addr:postcode":"80640",
    "addr:street":"Yosemite St",
    "iso:country":"US",
    "sg:address":"8850 Yosemite St",
    "sg:city":"Henderson",
    "sg:classifiers":[
        {
            "category":"Wholesale",
            "subcategory":"Construction Materials",
            "type":"Manufacturing & Wholesale Goods"
        }
    ],
    "sg:phone":"+1 303 286 7772",
    "sg:postcode":"80640",
    "sg:province":"CO",
    "sg:tags":[
        "coal"
    ],
    "wof:name":"Isg Resources Inc",
    "wof:placetype":"venue"
},
  "geometry": {"coordinates":[-104.88426200000001,39.857264],"type":"Point"}
}