{
  "type": "Feature",
  "properties": {
    "addr:full":"1015 Hide A Way Ln Estes Park CO 80517",
    "addr:housenumber":"1015",
    "addr:postcode":"80517",
    "addr:street":"Hide A Way Ln",
    "iso:country":"US",
    "sg:address":"1015 Hide A Way Ln",
    "sg:city":"Estes Park",
    "sg:classifiers":[
        {
            "category":"Building & Trades",
            "subcategory":"Construction",
            "type":"Services"
        }
    ],
    "sg:phone":"+1 970 586 3550",
    "sg:postcode":"80517",
    "sg:province":"CO",
    "sg:tags":[
        "contractor"
    ],
    "wof:name":"Rehn Construction Inc",
    "wof:placetype":"venue"
},
  "geometry": {"coordinates":[-105.50660999999999,40.342464],"type":"Point"}
}