{
  "type": "Feature",
  "properties": {
    "iso:country":"US",
    "sg:address":"8156 W Eastman Pl",
    "sg:city":"Lakewood",
    "sg:classifiers":[
        {
            "category":"Professional",
            "subcategory":"Computer Services",
            "type":"Services"
        }
    ],
    "sg:phone":"+1 303 989 2959",
    "sg:postcode":"80227",
    "sg:province":"CO",
    "sg:tags":[
        "consultant",
        "designer"
    ],
    "wof:name":"C M Technology Consulting Corp",
    "wof:placetype":"venue"
},
  "geometry": {"coordinates":[-105.08655,39.658269],"type":"Point"}
}