{
  "type": "Feature",
  "properties": {
    "iso:country":"US",
    "sg:address":"2251 Barn Swallow Dr",
    "sg:city":"Longmont",
    "sg:classifiers":[
        {
            "category":"Manufacturing",
            "subcategory":"Printing",
            "type":"Manufacturing & Wholesale Goods"
        }
    ],
    "sg:phone":"+1 303 442 1661",
    "sg:postcode":"80504",
    "sg:province":"CO",
    "sg:tags":[
        "periodical"
    ],
    "wof:name":"O R Manager Inc",
    "wof:placetype":"venue"
},
  "geometry": {"coordinates":[-105.122106,40.133025],"type":"Point"}
}