{
  "type": "Feature",
  "properties": {
    "addr:full":"270 S Purcell Blvd Pueblo CO 81007",
    "addr:housenumber":"270",
    "addr:postcode":"81007",
    "addr:street":"S Purcell Blvd",
    "iso:country":"US",
    "sg:address":"270 S Purcell Blvd",
    "sg:city":"Pueblo",
    "sg:classifiers":[
        {
            "category":"Retail",
            "subcategory":"Animal Services",
            "type":"Services"
        }
    ],
    "sg:phone":"+1 719 647 2131",
    "sg:postcode":"81007",
    "sg:province":"CO",
    "wof:name":"Paw Cottage LLC",
    "wof:placetype":"venue"
},
  "geometry": {"coordinates":[-104.70489999999999,38.319345],"type":"Point"}
}