{
  "type": "Feature",
  "properties": {
    "addr:full":"1100 Steele St Denver CO 80206",
    "addr:housenumber":"1100",
    "addr:postcode":"80206",
    "addr:street":"Steele St",
    "iso:country":"US",
    "sg:address":"1100 Steele St",
    "sg:city":"Denver",
    "sg:classifiers":[
        {
            "category":"Communications",
            "type":"Services"
        }
    ],
    "sg:phone":"+1 303 321 7428",
    "sg:postcode":"80206",
    "sg:province":"CO",
    "wof:name":"Liaison Communications",
    "wof:placetype":"venue"
},
  "geometry": {"coordinates":[-104.949489,39.735126],"type":"Point"}
}