{
  "type": "Feature",
  "properties": {
    "iso:country":"US",
    "sg:address":"3093 Forrest Way",
    "sg:city":"Grand Junction",
    "sg:classifiers":[
        {
            "category":"Professional",
            "subcategory":"Lawyer & Legal Services",
            "type":"Services"
        }
    ],
    "sg:phone":"+1 970 434 7797",
    "sg:postcode":"81504",
    "sg:province":"CO",
    "sg:tags":[
        "naturalization",
        "immigration"
    ],
    "wof:name":"Grand Junction Migrant",
    "wof:placetype":"venue"
},
  "geometry": {"coordinates":[-108.468053,39.085756],"type":"Point"}
}