{
  "type": "Feature",
  "properties": {
    "addr:full":"108 S 11th St Canon City CO 81212",
    "addr:housenumber":"108",
    "addr:postcode":"81212",
    "addr:street":"S 11Th St",
    "iso:country":"US",
    "sg:address":"108 S 11th St",
    "sg:city":"Canon City",
    "sg:classifiers":[
        {
            "category":"Personal",
            "subcategory":"Barber",
            "type":"Services"
        }
    ],
    "sg:phone":"+1 719 275 6526",
    "sg:postcode":"81212",
    "sg:province":"CO",
    "wof:name":"Jack's Barber Shop",
    "wof:placetype":"venue"
},
  "geometry": {"coordinates":[-105.23283499999999,38.444192],"type":"Point"}
}