{
  "type": "Feature",
  "properties": {
    "iso:country":"US",
    "sg:address":"979 Galapago St",
    "sg:city":"Denver",
    "sg:classifiers":[
        {
            "category":"Professional",
            "type":"Services"
        }
    ],
    "sg:phone":"+1 303 534 0611",
    "sg:postcode":"80204",
    "sg:province":"CO",
    "sg:tags":[
        "establishment"
    ],
    "wof:name":"Martin Percival Sch-Irish",
    "wof:placetype":"venue"
},
  "geometry": {"coordinates":[-104.996493,39.730833],"type":"Point"}
}