{
  "type": "Feature",
  "properties": {
    "addr:full":"360 S Teller St Denver CO 80226",
    "addr:housenumber":"360",
    "addr:postcode":"80226",
    "addr:street":"S Teller St",
    "iso:country":"US",
    "sg:address":"360 S Teller St",
    "sg:city":"Denver",
    "sg:classifiers":[
        {
            "category":"Personal",
            "type":"Services"
        },
        {
            "category":"Sports & Exercise",
            "subcategory":"Gym",
            "type":"Entertainment"
        },
        {
            "category":"Arena",
            "subcategory":"Sports Club",
            "type":"Entertainment"
        }
    ],
    "sg:phone":"+1 303 857 5360",
    "sg:postcode":"80226",
    "sg:province":"CO",
    "sg:tags":[
        "trainer",
        "consultant",
        "gymnasium",
        "program",
        "health",
        "fitness",
        "physical"
    ],
    "sg:website":"http://clickserve.dartsearch.net/link/click?lid=43000000196565615",
    "wof:name":"Bally Total Fitness",
    "wof:placetype":"venue"
},
  "geometry": {"coordinates":[-105.076865,39.709918],"type":"Point"}
}