{
  "type": "Feature",
  "properties": {
    "iso:country":"US",
    "sg:address":"103 S Wahsatch Ave",
    "sg:city":"Colorado Springs",
    "sg:classifiers":[
        {
            "category":"Professional",
            "subcategory":"Lawyer & Legal Services",
            "type":"Services"
        }
    ],
    "sg:phone":"+1 719 638 8877",
    "sg:postcode":"80903",
    "sg:province":"CO",
    "sg:tags":[
        "attorney"
    ],
    "wof:name":"Angela S Boeck PC",
    "wof:placetype":"venue"
},
  "geometry": {"coordinates":[-104.818226,38.830926],"type":"Point"}
}