{
  "type": "Feature",
  "properties": {
    "addr:full":"8207 Flower Ct Arvada CO 80005",
    "addr:housenumber":"8207",
    "addr:postcode":"80005",
    "addr:street":"Flower Ct",
    "iso:country":"US",
    "sg:address":"8207 Flower Ct",
    "sg:city":"Arvada",
    "sg:classifiers":[
        {
            "category":"Personal",
            "subcategory":"Barber",
            "type":"Services"
        }
    ],
    "sg:phone":"+1 303 420 8789",
    "sg:postcode":"80005",
    "sg:province":"CO",
    "sg:tags":[
        "shop",
        "periodical"
    ],
    "wof:name":"His Creation",
    "wof:placetype":"venue"
},
  "geometry": {"coordinates":[-105.099671,39.844933],"type":"Point"}
}