{
  "type": "Feature",
  "properties": {
    "iso:country":"US",
    "sg:address":"967 Marion St",
    "sg:city":"Denver",
    "sg:classifiers":[
        {
            "category":"Real Estate",
            "subcategory":"Real Estate Agent",
            "type":"Services"
        }
    ],
    "sg:phone":"+1 303 864 9040",
    "sg:postcode":"80218",
    "sg:province":"CO",
    "sg:tags":[
        "management"
    ],
    "wof:name":"Denver Property Management",
    "wof:placetype":"venue"
},
  "geometry": {"coordinates":[-104.97187099999999,39.730984],"type":"Point"}
}