{
  "type": "Feature",
  "properties": {
    "iso:country":"US",
    "sg:address":"333 E Colfax Ave",
    "sg:city":"Denver",
    "sg:classifiers":[
        {
            "category":"Bars & Pubs",
            "type":"Food & Drink"
        },
        {
            "category":"Restaurant",
            "type":"Food & Drink"
        }
    ],
    "sg:menulink":"http://www.allmenus.com/co/denver/280967-wolfes-barbeque/menu/",
    "sg:phone":"+1 303 831 1500",
    "sg:postcode":"80203",
    "sg:province":"CO",
    "sg:tags":[
        "barbecue",
        "american"
    ],
    "wof:name":"Wolfe's Barbeque",
    "wof:placetype":"venue"
},
  "geometry": {"coordinates":[-104.98313899999999,39.740181],"type":"Point"}
}