{
  "type": "Feature",
  "properties": {
    "addr:full":"2475 Pheasant Trail Ct Grand Junction CO 81506",
    "addr:housenumber":"2475",
    "addr:postcode":"81506",
    "addr:street":"Pheasant Trail Ct",
    "iso:country":"US",
    "sg:address":"2475 Pheasant Trail Ct",
    "sg:city":"Grand Junction",
    "sg:classifiers":[
        {
            "category":"Building & Trades",
            "subcategory":"Construction",
            "type":"Services"
        }
    ],
    "sg:phone":"+1 970 241 7067",
    "sg:postcode":"81506",
    "sg:province":"CO",
    "sg:tags":[
        "home",
        "builder"
    ],
    "wof:name":"Mogensen & Assoc",
    "wof:placetype":"venue"
},
  "geometry": {"coordinates":[-108.537059,39.092617],"type":"Point"}
}