{
  "type": "Feature",
  "properties": {
    "addr:full":"1115 W 11th Avenue Denver CO 80204",
    "addr:housenumber":"1115",
    "addr:postcode":"80204",
    "addr:street":"W 11Th Avenue",
    "iso:country":"US",
    "sg:address":"1115 W 11th Avenue",
    "sg:city":"Denver",
    "sg:classifiers":[
        {
            "category":"Food & Beverages",
            "subcategory":"Groceries & Convenience Stores",
            "type":"Retail Goods"
        }
    ],
    "sg:phone":"+1 303 572 0076",
    "sg:postcode":"80204",
    "sg:province":"CO",
    "wof:name":"American Way Market",
    "wof:placetype":"venue"
},
  "geometry": {"coordinates":[-105.000305,39.733594],"type":"Point"}
}