{
  "type": "Feature",
  "properties": {
    "addr:full":"15 N Main St Brighton CO 80601",
    "addr:housenumber":"15",
    "addr:postcode":"80601",
    "addr:street":"N Main St",
    "iso:country":"US",
    "sg:address":"15 N Main St",
    "sg:city":"Brighton",
    "sg:classifiers":[
        {
            "category":"Food & Beverages",
            "subcategory":"Specialty",
            "type":"Retail Goods"
        }
    ],
    "sg:phone":"+1 303 655 9100",
    "sg:postcode":"80601",
    "sg:province":"CO",
    "sg:tags":[
        "health",
        "diet"
    ],
    "wof:name":"Nature's Harvest Health Store",
    "wof:placetype":"venue"
},
  "geometry": {"coordinates":[-104.821282,39.987757],"type":"Point"}
}