{
  "type": "Feature",
  "properties": {
    "iso:country":"US",
    "sg:address":"11900 W Colfax Ave",
    "sg:city":"Lakewood",
    "sg:classifiers":[
        {
            "category":"Building & Trades",
            "subcategory":"Equipment Rental",
            "type":"Services"
        }
    ],
    "sg:phone":"+1 303 232 7417",
    "sg:postcode":"80215",
    "sg:province":"CO",
    "sg:tags":[
        "yard"
    ],
    "sg:website":"www.atozrental.com",
    "wof:name":"A To Z Rental Ctr",
    "wof:placetype":"venue"
},
  "geometry": {"coordinates":[-105.13288799999999,39.740134],"type":"Point"}
}