{
  "type": "Feature",
  "properties": {
    "addr:full":"2 Garden Center Broomfield CO 80020",
    "addr:housenumber":"2",
    "addr:postcode":"80020",
    "addr:street":"Garden Center",
    "iso:country":"US",
    "sg:address":"2 Garden Center",
    "sg:city":"Broomfield",
    "sg:classifiers":[
        {
            "category":"Real Estate",
            "subcategory":"Real Estate Agent",
            "type":"Services"
        }
    ],
    "sg:phone":"+1 303 465 0006",
    "sg:postcode":"80020",
    "sg:province":"CO",
    "wof:name":"Avery Roth Assoc Inc",
    "wof:placetype":"venue"
},
  "geometry": {"coordinates":[-105.088273,39.923891],"type":"Point"}
}