{
  "type": "Feature",
  "properties": {
    "addr:full":"1538 E Harmony Rd Fort Collins CO 80525",
    "addr:housenumber":"1538",
    "addr:postcode":"80525",
    "addr:street":"E Harmony Rd",
    "iso:country":"US",
    "sg:address":"1538 E Harmony Rd",
    "sg:city":"Fort Collins",
    "sg:classifiers":[
        {
            "category":"Shopping",
            "subcategory":"Pharmacy",
            "type":"Retail Goods"
        }
    ],
    "sg:phone":"+1 970 267 9218",
    "sg:postcode":"80525",
    "sg:province":"CO",
    "sg:tags":[
        "drug",
        "store"
    ],
    "wof:name":"Longs Drugs 528",
    "wof:placetype":"venue"
},
  "geometry": {"coordinates":[-105.05342,40.523734],"type":"Point"}
}