{
  "type": "Feature",
  "properties": {
    "iso:country":"US",
    "sg:address":"925 N Powers Blvd",
    "sg:city":"Colorado Springs",
    "sg:classifiers":[
        {
            "category":"Autos & Motor Vehicles",
            "subcategory":"Automobile Sales",
            "type":"Retail Goods"
        }
    ],
    "sg:phone":"+1 719 574 6337",
    "sg:postcode":"80915",
    "sg:province":"CO",
    "sg:tags":[
        "car",
        "dealer"
    ],
    "wof:name":"D C's Auto Sales",
    "wof:placetype":"venue"
},
  "geometry": {"coordinates":[-104.720651,38.845704],"type":"Point"}
}