{
  "type": "Feature",
  "properties": {
    "addr:full":"466 Santa Fe Dr Denver CO 80204",
    "addr:housenumber":"466",
    "addr:postcode":"80204",
    "addr:street":"Santa Fe Dr",
    "iso:country":"US",
    "sg:address":"466 Santa Fe Dr",
    "sg:city":"Denver",
    "sg:classifiers":[
        {
            "category":"Retail",
            "subcategory":"Repair Shop",
            "type":"Services"
        }
    ],
    "sg:phone":"+1 303 436 1697",
    "sg:postcode":"80204",
    "sg:province":"CO",
    "sg:tags":[
        "taxidermist"
    ],
    "wof:name":"Lifelike Taxidermy Inc",
    "wof:placetype":"venue"
},
  "geometry": {"coordinates":[-104.998502,39.723053],"type":"Point"}
}