{
  "type": "Feature",
  "properties": {
    "addr:full":"3901 N Co Rd 25E Bellvue CO 80512",
    "addr:housenumber":"3901;25e",
    "addr:postcode":"80512",
    "addr:street":"N Co Rd",
    "iso:country":"US",
    "sg:address":"3901 N Co Rd 25E",
    "sg:city":"Bellvue",
    "sg:classifiers":[
        {
            "category":"Farming",
            "subcategory":"Livestock Farm",
            "type":"Manufacturing & Wholesale Goods"
        }
    ],
    "sg:phone":"+1 970 493 0741",
    "sg:postcode":"80512",
    "sg:province":"CO",
    "sg:tags":[
        "horse"
    ],
    "wof:name":"Gadsby Ranch",
    "wof:placetype":"venue"
},
  "geometry": {"coordinates":[-105.187073,40.644637],"type":"Point"}
}