{
  "type": "Feature",
  "properties": {
    "addr:full":"31544 US Hwy 34 Kersey CO 80644",
    "addr:postcode":"31544;80644",
    "addr:street":"Us Hwy 34",
    "iso:country":"US",
    "sg:address":"31544 US Hwy 34",
    "sg:city":"Kersey",
    "sg:classifiers":[
        {
            "category":"Professional",
            "type":"Services"
        }
    ],
    "sg:phone":"+1 970 352 8802",
    "sg:postcode":"80644",
    "sg:province":"CO",
    "wof:name":"Jake & ME",
    "wof:placetype":"venue"
},
  "geometry": {"coordinates":[-104.459035,40.347305],"type":"Point"}
}