{
  "type": "Feature",
  "properties": {
    "iso:country":"US",
    "sg:address":"1630 Welton St",
    "sg:city":"Denver",
    "sg:classifiers":[
        {
            "category":"Building & Trades",
            "subcategory":"Construction",
            "type":"Services"
        }
    ],
    "sg:phone":"+1 303 715 0999",
    "sg:postcode":"80205",
    "sg:province":"CO",
    "sg:tags":[
        "contractor"
    ],
    "wof:name":"Metco Fence Inc",
    "wof:placetype":"venue"
},
  "geometry": {"coordinates":[-104.990386,39.745104],"type":"Point"}
}