{
  "type": "Feature",
  "properties": {
    "iso:country":"US",
    "sg:address":"316 S Main St",
    "sg:city":"Lamar",
    "sg:classifiers":[
        {
            "category":"Insurance",
            "subcategory":"Insurance Agent",
            "type":"Services"
        }
    ],
    "sg:phone":"+1 719 336 9025",
    "sg:postcode":"81052",
    "sg:province":"CO",
    "wof:name":"Guaranty Insurance",
    "wof:placetype":"venue"
},
  "geometry": {"coordinates":[-102.61920499999999,38.086255],"type":"Point"}
}