{
  "type": "Feature",
  "properties": {
    "addr:full":"12 Boulder View Ln Boulder CO 80304",
    "addr:housenumber":"12",
    "addr:postcode":"80304",
    "addr:street":"Boulder View Ln",
    "iso:country":"US",
    "sg:address":"12 Boulder View Ln",
    "sg:city":"Boulder",
    "sg:classifiers":[
        {
            "category":"Real Estate",
            "subcategory":"Real Estate Agent",
            "type":"Services"
        }
    ],
    "sg:phone":"+1 720 406 9785",
    "sg:postcode":"80304",
    "sg:province":"CO",
    "wof:name":"Creston Property Management",
    "wof:placetype":"venue"
},
  "geometry": {"coordinates":[-105.298267,40.039301],"type":"Point"}
}