{
  "type": "Feature",
  "properties": {
    "iso:country":"US",
    "sg:address":"2101 S Downing Street",
    "sg:city":"Denver",
    "sg:classifiers":[
        {
            "category":"Restaurant",
            "type":"Food & Drink"
        }
    ],
    "sg:phone":"+1 303 777 6655",
    "sg:postcode":"80210",
    "sg:province":"CO",
    "sg:tags":[
        "pizza"
    ],
    "wof:name":"Domino's Pizza",
    "wof:placetype":"venue"
},
  "geometry": {"coordinates":[-104.973285,39.678344],"type":"Point"}
}