{
  "type": "Feature",
  "properties": {
    "iso:country":"US",
    "sg:address":"532 4th St",
    "sg:city":"Fairplay",
    "sg:classifiers":[
        {
            "category":"Recreation",
            "type":"Entertainment"
        }
    ],
    "sg:phone":"+1 719 836 3388",
    "sg:postcode":"80440",
    "sg:province":"CO",
    "sg:tags":[
        "stable"
    ],
    "wof:name":"C & M Outfitters",
    "wof:placetype":"venue"
},
  "geometry": {"coordinates":[-106.000191,39.228692],"type":"Point"}
}