{
  "type": "Feature",
  "properties": {
    "addr:full":"177 State Hwy 91 Leadville CO 80461",
    "addr:housenumber":"177",
    "addr:postcode":"80461",
    "addr:street":"State Hwy 91",
    "iso:country":"US",
    "sg:address":"177 State Hwy 91",
    "sg:city":"Leadville",
    "sg:classifiers":[
        {
            "category":"Health Services",
            "subcategory":"Doctor",
            "type":"Services"
        }
    ],
    "sg:phone":"+1 719 486 0053",
    "sg:postcode":"80461",
    "sg:province":"CO",
    "sg:tags":[
        "dentist"
    ],
    "wof:name":"Mountianview Dental",
    "wof:placetype":"venue"
},
  "geometry": {"coordinates":[-106.291854,39.251189],"type":"Point"}
}