{
  "type": "Feature",
  "properties": {
    "iso:country":"US",
    "sg:address":"303 E 17th Ave Ste 880",
    "sg:city":"Denver",
    "sg:classifiers":[
        {
            "category":"Professional",
            "subcategory":"Lawyer & Legal Services",
            "type":"Services"
        }
    ],
    "sg:phone":"+1 303 832 4357",
    "sg:postcode":"80203",
    "sg:province":"CO",
    "wof:name":"Berken & Associates",
    "wof:placetype":"venue"
},
  "geometry": {"coordinates":[-104.984001,39.743301],"type":"Point"}
}