{
  "type": "Feature",
  "properties": {
    "addr:full":"1619 Wood Ave Colorado Springs CO 80907",
    "addr:housenumber":"1619",
    "addr:postcode":"80907",
    "addr:street":"Wood Ave",
    "iso:country":"US",
    "sg:address":"1619 Wood Ave",
    "sg:city":"Colorado Springs",
    "sg:classifiers":[
        {
            "category":"Building & Trades",
            "subcategory":"Landscaping Services",
            "type":"Services"
        }
    ],
    "sg:phone":"+1 719 577 9890",
    "sg:postcode":"80907",
    "sg:province":"CO",
    "sg:tags":[
        "designer",
        "landscape"
    ],
    "wof:name":"Fawn Hayes Bell Landscape Arch",
    "wof:placetype":"venue"
},
  "geometry": {"coordinates":[-104.825855,38.857602],"type":"Point"}
}