{
  "type": "Feature",
  "properties": {
    "addr:full":"20 E Vermijo Ave Colorado Springs CO 80903",
    "addr:housenumber":"20",
    "addr:postcode":"80903",
    "addr:street":"E Vermijo Ave",
    "iso:country":"US",
    "sg:address":"20 E Vermijo Ave",
    "sg:city":"Colorado Springs",
    "sg:classifiers":[
        {
            "category":"Government",
            "subcategory":"Office",
            "type":"Public Place"
        }
    ],
    "sg:phone":"+1 719 448 7628",
    "sg:postcode":"80903",
    "sg:province":"CO",
    "wof:name":"Honorable Sylvia Manzanares",
    "wof:placetype":"venue"
},
  "geometry": {"coordinates":[-104.824039,38.829681],"type":"Point"}
}