{
  "type": "Feature",
  "properties": {
    "iso:country":"US",
    "sg:address":"1580 E Cheyenne Mountain Blvd",
    "sg:city":"Colorado Springs",
    "sg:classifiers":[
        {
            "category":"Health Services",
            "subcategory":"Doctor",
            "type":"Services"
        }
    ],
    "sg:phone":"+1 719 576 4247",
    "sg:postcode":"80906",
    "sg:province":"CO",
    "sg:tags":[
        "dentist"
    ],
    "wof:name":"Stephen G Seiler DDS",
    "wof:placetype":"venue"
},
  "geometry": {"coordinates":[-104.800042,38.792793],"type":"Point"}
}