{
  "type": "Feature",
  "properties": {
    "addr:full":"6516 S Ammons Ct Littleton CO 80123",
    "addr:housenumber":"6516",
    "addr:postcode":"80123",
    "addr:street":"S Ammons Ct",
    "iso:country":"US",
    "sg:address":"6516 S Ammons Ct",
    "sg:city":"Littleton",
    "sg:classifiers":[
        {
            "category":"Insurance",
            "subcategory":"Insurance Agent",
            "type":"Services"
        }
    ],
    "sg:phone":"+1 303 904 1630",
    "sg:postcode":"80123",
    "sg:province":"CO",
    "wof:name":"Hudspeth & Assoc Inc",
    "wof:placetype":"venue"
},
  "geometry": {"coordinates":[-105.088072,39.597973],"type":"Point"}
}