{
  "type": "Feature",
  "properties": {
    "addr:full":"15550 W 72nd Ave Arvada CO 80007",
    "addr:housenumber":"15550",
    "addr:postcode":"80007",
    "addr:street":"W 72Nd Ave",
    "iso:country":"US",
    "sg:address":"15550 W 72nd Ave",
    "sg:city":"Arvada",
    "sg:classifiers":[
        {
            "category":"Shopping",
            "subcategory":"Florist",
            "type":"Retail Goods"
        },
        {
            "category":"Professional",
            "subcategory":"Business Services",
            "type":"Services"
        }
    ],
    "sg:phone":"+1 303 422 3336",
    "sg:postcode":"80007",
    "sg:province":"CO",
    "sg:tags":[
        "plant",
        "design",
        "maintenance"
    ],
    "sg:website":"www.littleeden.com",
    "wof:name":"Little Eden Plant Scaping",
    "wof:placetype":"venue"
},
  "geometry": {"coordinates":[-105.171603,39.826972],"type":"Point"}
}