{
  "type": "Feature",
  "properties": {
    "iso:country":"US",
    "sg:address":"960 37th Avenue Ct",
    "sg:city":"Greeley",
    "sg:classifiers":[
        {
            "category":"Shopping",
            "subcategory":"Computers & Home Electronics",
            "type":"Retail Goods"
        }
    ],
    "sg:phone":"+1 970 353 8311",
    "sg:postcode":"80634",
    "sg:province":"CO",
    "sg:tags":[
        "software"
    ],
    "wof:name":"Excelsior Software Inc",
    "wof:placetype":"venue"
},
  "geometry": {"coordinates":[-104.74023,40.423458],"type":"Point"}
}