{
  "type": "Feature",
  "properties": {
    "addr:full":"143 N Chestnut St Trinidad CO 81082",
    "addr:housenumber":"143",
    "addr:postcode":"81082",
    "addr:street":"N Chestnut St",
    "iso:country":"US",
    "sg:address":"143 N Chestnut St",
    "sg:city":"Trinidad",
    "sg:classifiers":[
        {
            "category":"Retail",
            "subcategory":"Veterinary Services",
            "type":"Services"
        }
    ],
    "sg:phone":"+1 719 846 4440",
    "sg:postcode":"81082",
    "sg:province":"CO",
    "wof:name":"City Animal Control",
    "wof:placetype":"venue"
},
  "geometry": {"coordinates":[-104.503545,37.169936],"type":"Point"}
}