{
  "type": "Feature",
  "properties": {
    "addr:full":"3832 E Geddes Ave Centennial CO 80122",
    "addr:housenumber":"3832",
    "addr:postcode":"80122",
    "addr:street":"E Geddes Ave",
    "iso:country":"US",
    "sg:address":"3832 E Geddes Ave",
    "sg:city":"Centennial",
    "sg:classifiers":[
        {
            "category":"Professional",
            "type":"Services"
        }
    ],
    "sg:phone":"+1 303 290 0006",
    "sg:postcode":"80122",
    "sg:province":"CO",
    "sg:tags":[
        "establishment"
    ],
    "wof:name":"Abrams & Assoc",
    "wof:placetype":"venue"
},
  "geometry": {"coordinates":[-104.943764,39.584063],"type":"Point"}
}