{
  "type": "Feature",
  "properties": {
    "addr:full":"1100 E 18th Ave Denver CO 80218",
    "addr:housenumber":"1100",
    "addr:postcode":"80218",
    "addr:street":"E 18Th Ave",
    "iso:country":"US",
    "sg:address":"1100 E 18th Ave",
    "sg:city":"Denver",
    "sg:classifiers":[
        {
            "category":"Social Services",
            "type":"Services"
        }
    ],
    "sg:phone":"+1 303 860 7200",
    "sg:postcode":"80218",
    "sg:province":"CO",
    "sg:tags":[
        "organization",
        "welfare"
    ],
    "sg:website":"www.metrocarering.org",
    "wof:name":"Metro Care Ring",
    "wof:placetype":"venue"
},
  "geometry": {"coordinates":[-104.97212399999999,39.744825],"type":"Point"}
}