{
  "type": "Feature",
  "properties": {
    "addr:full":"2551 G Rd Grand Junction CO 81505",
    "addr:housenumber":"2551",
    "addr:postcode":"81505",
    "addr:street":"G Rd",
    "iso:country":"US",
    "sg:address":"2551 G Rd",
    "sg:city":"Grand Junction",
    "sg:classifiers":[
        {
            "category":"Building & Trades",
            "subcategory":"Construction",
            "type":"Services"
        }
    ],
    "sg:phone":"+1 970 241 9945",
    "sg:postcode":"81505",
    "sg:province":"CO",
    "sg:tags":[
        "house"
    ],
    "wof:name":"B&B Builders",
    "wof:placetype":"venue"
},
  "geometry": {"coordinates":[-108.58543,39.10627],"type":"Point"}
}