{
  "type": "Feature",
  "properties": {
    "addr:full":"114 Rimrock Dr Durango CO 81301",
    "addr:housenumber":"114",
    "addr:postcode":"co 81301",
    "addr:street":"Rimrock Dr",
    "iso:country":"US",
    "sg:address":"114 Rimrock Dr",
    "sg:city":"Durango",
    "sg:classifiers":[
        {
            "category":"Real Estate",
            "subcategory":"Real Estate Agent",
            "type":"Services"
        }
    ],
    "sg:phone":"+1 970 259 6202",
    "sg:postcode":"81301",
    "sg:province":"CO",
    "wof:name":"Walrich Realty Corp Nobma",
    "wof:placetype":"venue"
},
  "geometry": {"coordinates":[-107.83859699999999,37.423915],"type":"Point"}
}