{
  "type": "Feature",
  "properties": {
    "iso:country":"US",
    "sg:address":"1205 W Byers Pl",
    "sg:city":"Denver",
    "sg:classifiers":[
        {
            "category":"Shopping",
            "type":"Retail Goods"
        },
        {
            "category":"Wholesale",
            "subcategory":"Electrical",
            "type":"Manufacturing & Wholesale Goods"
        }
    ],
    "sg:phone":"+1 303 778 6225",
    "sg:postcode":"80223",
    "sg:province":"CO",
    "sg:tags":[
        "battery",
        "merchandise"
    ],
    "sg:website":"www.unitedpowerandbattery.com",
    "wof:name":"United Power & Battery Corp",
    "wof:placetype":"venue"
},
  "geometry": {"coordinates":[-105.003659,39.712218],"type":"Point"}
}