{
  "type": "Feature",
  "properties": {
    "iso:country":"US",
    "sg:address":"130 W Olive St",
    "sg:city":"Fort Collins",
    "sg:classifiers":[
        {
            "category":"Restaurant",
            "type":"Food & Drink"
        }
    ],
    "sg:menulink":"http://www.allmenus.com/co/fort-collins/124100-quiznos-sub/menu/",
    "sg:phone":"+1 970 482 1017",
    "sg:postcode":"80524",
    "sg:province":"CO",
    "sg:tags":[
        "wrap",
        "american",
        "sandwich"
    ],
    "wof:name":"Quiznos Sub",
    "wof:placetype":"venue"
},
  "geometry": {"coordinates":[-105.07845399999999,40.584645],"type":"Point"}
}