{
  "type": "Feature",
  "properties": {
    "addr:full":"78930 Us Highway 40 Winter Park CO 80482",
    "addr:postcode":"78930;80482",
    "addr:street":"Us Highway 40;Park",
    "iso:country":"US",
    "sg:address":"78930 Us Highway 40",
    "sg:city":"Winter Park",
    "sg:classifiers":[
        {
            "category":"Restaurant",
            "type":"Food & Drink"
        }
    ],
    "sg:menulink":"http://www.allmenus.com/co/granby/276155-the-green-olive/menu/",
    "sg:phone":"+1 970 726 4747",
    "sg:postcode":"80482",
    "sg:province":"CO",
    "sg:tags":[
        "american",
        "steakhouse",
        "italian"
    ],
    "wof:name":"The Green Olive",
    "wof:placetype":"venue"
},
  "geometry": {"coordinates":[-105.78466,39.918194],"type":"Point"}
}