{
  "type": "Feature",
  "properties": {
    "iso:country":"US",
    "sg:address":"215 E Foothills Pkwy",
    "sg:city":"Fort Collins",
    "sg:classifiers":[
        {
            "category":"Shopping",
            "type":"Retail Goods"
        }
    ],
    "sg:phone":"+1 970 225 2526",
    "sg:postcode":"80525",
    "sg:province":"CO",
    "sg:tags":[
        "eye",
        "sunglasses",
        "prescription",
        "glasses"
    ],
    "wof:name":"Eyes Have It Sunglasses",
    "wof:placetype":"venue"
},
  "geometry": {"coordinates":[-105.07463300000001,40.543772],"type":"Point"}
}