{
  "type": "Feature",
  "properties": {
    "addr:full":"76 Taildragger Durango CO 81303",
    "addr:housenumber":"76",
    "addr:postcode":"co 81303",
    "addr:street":"Taildragger Durango",
    "iso:country":"US",
    "sg:address":"76 Taildragger",
    "sg:city":"Durango",
    "sg:classifiers":[
        {
            "category":"Manufacturing",
            "subcategory":"Building Materials",
            "type":"Manufacturing & Wholesale Goods"
        }
    ],
    "sg:phone":"+1 970 259 7446",
    "sg:postcode":"81303",
    "sg:province":"CO",
    "sg:tags":[
        "woodwork",
        "mfg",
        "medal",
        "custom"
    ],
    "wof:name":"Wings",
    "wof:placetype":"venue"
},
  "geometry": {"coordinates":[-107.865686,37.204476],"type":"Point"}
}