{
  "type": "Feature",
  "properties": {
    "iso:country":"US",
    "sg:address":"42 Woodbridge Dr",
    "sg:city":"Colorado Springs",
    "sg:classifiers":[
        {
            "category":"Professional",
            "type":"Services"
        }
    ],
    "sg:phone":"+1 719 579 9410",
    "sg:postcode":"80906",
    "sg:province":"CO",
    "sg:tags":[
        "establishment"
    ],
    "wof:name":"Weber & Weber",
    "wof:placetype":"venue"
},
  "geometry": {"coordinates":[-104.82835799999999,38.776205],"type":"Point"}
}