{
  "type": "Feature",
  "properties": {
    "addr:full":"2913 58th Ave Greeley CO 80634",
    "addr:housenumber":"2913",
    "addr:postcode":"80634",
    "addr:street":"58Th Ave",
    "iso:country":"US",
    "sg:address":"2913 58th Ave",
    "sg:city":"Greeley",
    "sg:classifiers":[
        {
            "category":"Wholesale",
            "subcategory":"Durable Goods & Equipment",
            "type":"Manufacturing & Wholesale Goods"
        }
    ],
    "sg:phone":"+1 970 353 4637",
    "sg:postcode":"80634",
    "sg:province":"CO",
    "wof:name":"Nail Supply",
    "wof:placetype":"venue"
},
  "geometry": {"coordinates":[-104.77228700000001,40.387748],"type":"Point"}
}