{
  "type": "Feature",
  "properties": {
    "addr:full":"1614 Cheyenne Ave Loveland CO 80538",
    "addr:housenumber":"1614",
    "addr:postcode":"80538",
    "addr:street":"Cheyenne Ave",
    "iso:country":"US",
    "sg:address":"1614 Cheyenne Ave",
    "sg:city":"Loveland",
    "sg:classifiers":[
        {
            "category":"Shopping",
            "subcategory":"Computers & Home Electronics",
            "type":"Retail Goods"
        }
    ],
    "sg:phone":"+1 970 635 0322",
    "sg:postcode":"80538",
    "sg:province":"CO",
    "wof:name":"Lcs Computer Systems LLC",
    "wof:placetype":"venue"
},
  "geometry": {"coordinates":[-105.04979299999999,40.410103],"type":"Point"}
}