{
  "type": "Feature",
  "properties": {
    "iso:country":"US",
    "sg:address":"3555 Colorado Blvd",
    "sg:city":"Denver",
    "sg:classifiers":[
        {
            "category":"Government",
            "subcategory":"Police Station",
            "type":"Public Place"
        }
    ],
    "sg:phone":"+1 303 331 4090",
    "sg:postcode":"80205",
    "sg:province":"CO",
    "sg:tags":[
        "protection"
    ],
    "wof:name":"Police Dept",
    "wof:placetype":"venue"
},
  "geometry": {"coordinates":[-104.940572,39.76622],"type":"Point"}
}