{
  "type": "Feature",
  "properties": {
    "iso:country":"US",
    "sg:address":"10785 Quail Creek Dr",
    "sg:city":"Parker",
    "sg:classifiers":[
        {
            "category":"Professional",
            "type":"Services"
        }
    ],
    "sg:phone":"+1 303 841 7975",
    "sg:postcode":"80138",
    "sg:province":"CO",
    "wof:name":"P R Cutlip",
    "wof:placetype":"venue"
},
  "geometry": {"coordinates":[-104.728331,39.520298],"type":"Point"}
}