{
  "type": "Feature",
  "properties": {
    "iso:country":"US",
    "sg:address":"3596 Moline St",
    "sg:city":"Aurora",
    "sg:classifiers":[
        {
            "category":"Retail",
            "subcategory":"Auto Repair",
            "type":"Services"
        }
    ],
    "sg:phone":"+1 303 366 7867",
    "sg:postcode":"80010",
    "sg:province":"CO",
    "sg:tags":[
        "brake"
    ],
    "wof:name":"Brake Man",
    "wof:placetype":"venue"
},
  "geometry": {"coordinates":[-104.85463300000001,39.763861],"type":"Point"}
}