{
  "type": "Feature",
  "properties": {
    "addr:full":"1220 W Elizabeth St Fort Collins CO 80521",
    "addr:housenumber":"1220",
    "addr:postcode":"80521",
    "addr:street":"W Elizabeth St",
    "iso:country":"US",
    "sg:address":"1220 W Elizabeth St",
    "sg:city":"Fort Collins",
    "sg:classifiers":[
        {
            "category":"Real Estate",
            "subcategory":"Real Estate Agent",
            "type":"Services"
        }
    ],
    "sg:phone":"+1 970 472 8165",
    "sg:postcode":"80521",
    "sg:province":"CO",
    "sg:tags":[
        "property",
        "management"
    ],
    "wof:name":"Front Porch Property Services",
    "wof:placetype":"venue"
},
  "geometry": {"coordinates":[-105.098814,40.574714],"type":"Point"}
}