{
  "type": "Feature",
  "properties": {
    "iso:country":"US",
    "sg:address":"412 W 4th St",
    "sg:city":"Palisade",
    "sg:classifiers":[
        {
            "category":"Retail",
            "subcategory":"Repair Shop",
            "type":"Services"
        }
    ],
    "sg:phone":"+1 970 464 5844",
    "sg:postcode":"81526",
    "sg:province":"CO",
    "sg:tags":[
        "upholsterer"
    ],
    "wof:name":"Dave's Top Shop",
    "wof:placetype":"venue"
},
  "geometry": {"coordinates":[-108.35631100000001,39.109521],"type":"Point"}
}