{
  "type": "Feature",
  "properties": {
    "iso:country":"US",
    "sg:address":"7467 Bluefox Ct",
    "sg:city":"Lone Tree",
    "sg:classifiers":[
        {
            "category":"Professional",
            "type":"Services"
        }
    ],
    "sg:phone":"+1 303 799 0188",
    "sg:postcode":"80124",
    "sg:province":"CO",
    "sg:tags":[
        "establishment"
    ],
    "wof:name":"Burnett & Burnett",
    "wof:placetype":"venue"
},
  "geometry": {"coordinates":[-104.902531,39.547562],"type":"Point"}
}