{
  "type": "Feature",
  "properties": {
    "iso:country":"US",
    "sg:address":"1388 Rosemary Drive",
    "sg:city":"Castle Rock",
    "sg:classifiers":[
        {
            "category":"Banks & Credit Unions",
            "subcategory":"Financial Services",
            "type":"Services"
        }
    ],
    "sg:phone":"+1 720 733 2131",
    "sg:postcode":"80109",
    "sg:province":"CO",
    "sg:tags":[
        "broker",
        "mortgage"
    ],
    "wof:name":"123Quote",
    "wof:placetype":"venue"
},
  "geometry": {"coordinates":[-104.877735,39.387498],"type":"Point"}
}