{
  "type": "Feature",
  "properties": {
    "addr:full":"9862 Downing St Thornton CO 80229",
    "addr:housenumber":"9862",
    "addr:postcode":"80229",
    "addr:street":"Downing St",
    "iso:country":"US",
    "sg:address":"9862 Downing St",
    "sg:city":"Thornton",
    "sg:classifiers":[
        {
            "category":"Food & Beverages",
            "subcategory":"Specialty",
            "type":"Retail Goods"
        }
    ],
    "sg:phone":"+1 303 280 1961",
    "sg:postcode":"80229",
    "sg:province":"CO",
    "sg:tags":[
        "spice"
    ],
    "wof:name":"Watkins Products",
    "wof:placetype":"venue"
},
  "geometry": {"coordinates":[-104.97290599999999,39.876985],"type":"Point"}
}