{
  "type": "Feature",
  "properties": {
    "addr:full":"423 Emery Dr Longmont CO 80501",
    "addr:housenumber":"423",
    "addr:postcode":"80501",
    "addr:street":"Emery Dr",
    "iso:country":"US",
    "sg:address":"423 Emery Dr",
    "sg:city":"Longmont",
    "sg:classifiers":[
        {
            "category":"Professional",
            "type":"Services"
        }
    ],
    "sg:phone":"+1 303 776 8876",
    "sg:postcode":"80501",
    "sg:province":"CO",
    "wof:name":"Country Crafts By Peggy",
    "wof:placetype":"venue"
},
  "geometry": {"coordinates":[-105.09998,40.195508],"type":"Point"}
}