{
  "type": "Feature",
  "properties": {
    "addr:full":"616 Coffman St Longmont CO 80501",
    "addr:housenumber":"616",
    "addr:postcode":"80501",
    "addr:street":"Coffman St",
    "iso:country":"US",
    "sg:address":"616 Coffman St",
    "sg:city":"Longmont",
    "sg:classifiers":[
        {
            "category":"Shopping",
            "subcategory":"Musical Instruments",
            "type":"Retail Goods"
        }
    ],
    "sg:phone":"+1 303 651 6688",
    "sg:postcode":"80501",
    "sg:province":"CO",
    "wof:name":"Toneworks Music",
    "wof:placetype":"venue"
},
  "geometry": {"coordinates":[-105.103751,40.170399],"type":"Point"}
}