{
  "type": "Feature",
  "properties": {
    "iso:country":"US",
    "sg:address":"2065 E Main St",
    "sg:city":"Montrose",
    "sg:classifiers":[
        {
            "category":"Professional",
            "subcategory":"Computer Services",
            "type":"Services"
        }
    ],
    "sg:phone":"+1 970 240 1835",
    "sg:postcode":"81401",
    "sg:province":"CO",
    "sg:tags":[
        "internet"
    ],
    "wof:name":"AUTO Jobs",
    "wof:placetype":"venue"
},
  "geometry": {"coordinates":[-107.84898099999999,38.488825],"type":"Point"}
}