{
  "type": "Feature",
  "properties": {
    "iso:country":"US",
    "sg:address":"1404 Mountain Dr",
    "sg:city":"Glenwood Springs",
    "sg:classifiers":[
        {
            "category":"Building & Trades",
            "subcategory":"Construction",
            "type":"Services"
        }
    ],
    "sg:phone":"+1 970 945 2015",
    "sg:postcode":"81601",
    "sg:province":"CO",
    "sg:tags":[
        "contractor"
    ],
    "wof:name":"Steven Davis",
    "wof:placetype":"venue"
},
  "geometry": {"coordinates":[-107.311391,39.512104],"type":"Point"}
}