{
  "type": "Feature",
  "properties": {
    "iso:country":"US",
    "sg:address":"3700 Navajo St",
    "sg:city":"Denver",
    "sg:classifiers":[
        {
            "category":"Manufacturing",
            "subcategory":"Printing",
            "type":"Manufacturing & Wholesale Goods"
        }
    ],
    "sg:phone":"+1 303 458 8600",
    "sg:postcode":"80211",
    "sg:province":"CO",
    "sg:tags":[
        "press",
        "full",
        "commercial",
        "printer",
        "offset"
    ],
    "wof:name":"Tom's Press",
    "wof:placetype":"venue"
},
  "geometry": {"coordinates":[-105.004137,39.769287],"type":"Point"}
}