{
  "type": "Feature",
  "properties": {
    "addr:full":"756 Florida Rd Durango CO 81301",
    "addr:housenumber":"756",
    "addr:postcode":"co 81301",
    "addr:street":"Florida Rd",
    "iso:country":"US",
    "sg:address":"756 Florida Rd",
    "sg:city":"Durango",
    "sg:classifiers":[
        {
            "category":"Organizations",
            "subcategory":"Religious Organization",
            "type":"Services"
        }
    ],
    "sg:phone":"+1 970 247 3894",
    "sg:postcode":"81301",
    "sg:province":"CO",
    "sg:tags":[
        "church"
    ],
    "wof:name":"Bible Missionary Church",
    "wof:placetype":"venue"
},
  "geometry": {"coordinates":[-107.86506799999999,37.28838],"type":"Point"}
}