{
  "type": "Feature",
  "properties": {
    "iso:country":"US",
    "sg:address":"6435 Federal Blvd",
    "sg:city":"Denver",
    "sg:classifiers":[
        {
            "category":"Autos & Motor Vehicles",
            "subcategory":"Automobile Sales",
            "type":"Retail Goods"
        }
    ],
    "sg:phone":"+1 303 426 4410",
    "sg:postcode":"80221",
    "sg:province":"CO",
    "sg:tags":[
        "used"
    ],
    "wof:name":"Aristacar Auto Sales",
    "wof:placetype":"venue"
},
  "geometry": {"coordinates":[-105.025451,39.81306],"type":"Point"}
}