{
  "type": "Feature",
  "properties": {
    "addr:full":"8601 Zuni St Denver CO 80260",
    "addr:housenumber":"8601",
    "addr:postcode":"80260",
    "addr:street":"Zuni St",
    "iso:country":"US",
    "sg:address":"8601 Zuni St",
    "sg:city":"Denver",
    "sg:classifiers":[
        {
            "category":"Building & Trades",
            "subcategory":"Landscaping Services",
            "type":"Services"
        }
    ],
    "sg:phone":"+1 303 429 5130",
    "sg:postcode":"80260",
    "sg:province":"CO",
    "sg:tags":[
        "lawn",
        "landscape",
        "maintenance",
        "grounds"
    ],
    "wof:name":"City Farmers",
    "wof:placetype":"venue"
},
  "geometry": {"coordinates":[-105.015505,39.853001],"type":"Point"}
}