{
  "type": "Feature",
  "properties": {
    "addr:full":"19011 E Oxford Dr Aurora CO 80013",
    "addr:housenumber":"19011",
    "addr:postcode":"80013",
    "addr:street":"E Oxford Dr",
    "iso:country":"US",
    "sg:address":"19011 E Oxford Dr",
    "sg:city":"Aurora",
    "sg:classifiers":[
        {
            "category":"Organizations",
            "subcategory":"Non-profit Organization",
            "type":"Services"
        }
    ],
    "sg:phone":"+1 303 627 8546",
    "sg:postcode":"80013",
    "sg:province":"CO",
    "sg:tags":[
        "disability"
    ],
    "wof:name":"Maggiora Host Home",
    "wof:placetype":"venue"
},
  "geometry": {"coordinates":[-104.767526,39.642071],"type":"Point"}
}