{
  "type": "Feature",
  "properties": {
    "addr:full":"2216 Gaylord St Denver CO 80205",
    "addr:housenumber":"2216",
    "addr:postcode":"80205",
    "addr:street":"Gaylord St",
    "iso:country":"US",
    "sg:address":"2216 Gaylord St",
    "sg:city":"Denver",
    "sg:classifiers":[
        {
            "category":"Wholesale",
            "subcategory":"Groceries",
            "type":"Manufacturing & Wholesale Goods"
        }
    ],
    "sg:phone":"+1 303 394 1670",
    "sg:postcode":"80205",
    "sg:province":"CO",
    "sg:tags":[
        "coffee",
        "bean",
        "roast"
    ],
    "wof:name":"Spero Mountain Coffee",
    "wof:placetype":"venue"
},
  "geometry": {"coordinates":[-104.960919,39.750509],"type":"Point"}
}