{
  "type": "Feature",
  "properties": {
    "iso:country":"US",
    "sg:address":"9215 Ralston Rd",
    "sg:city":"Arvada",
    "sg:classifiers":[
        {
            "category":"Education",
            "subcategory":"School",
            "type":"Public Place"
        }
    ],
    "sg:phone":"+1 303 467 2295",
    "sg:postcode":"80002",
    "sg:province":"CO",
    "wof:name":"Excel Academy",
    "wof:placetype":"venue"
},
  "geometry": {"coordinates":[-105.102643,39.802115],"type":"Point"}
}