{
  "type": "Feature",
  "properties": {
    "iso:country":"US",
    "sg:address":"4360 Upham St",
    "sg:city":"Wheat Ridge",
    "sg:classifiers":[
        {
            "category":"Food & Beverages",
            "subcategory":"Candy",
            "type":"Retail Goods"
        }
    ],
    "sg:phone":"+1 303 424 3239",
    "sg:postcode":"80033",
    "sg:province":"CO",
    "wof:name":"Picadilly Pantry",
    "wof:placetype":"venue"
},
  "geometry": {"coordinates":[-105.077845,39.769833],"type":"Point"}
}