{
  "type": "Feature",
  "properties": {
    "addr:full":"1647 Pearl St Boulder CO 80302",
    "addr:housenumber":"1647",
    "addr:postcode":"80302",
    "addr:street":"Pearl St",
    "iso:country":"US",
    "sg:address":"1647 Pearl St",
    "sg:city":"Boulder",
    "sg:classifiers":[
        {
            "category":"Shopping",
            "subcategory":"Pharmacy",
            "type":"Retail Goods"
        }
    ],
    "sg:phone":"+1 303 442 5164",
    "sg:postcode":"80302",
    "sg:province":"CO",
    "sg:website":"www.pharmaca.com",
    "wof:name":"Pharmaca Integrative Pharmacy",
    "wof:placetype":"venue"
},
  "geometry": {"coordinates":[-105.273916,40.019191],"type":"Point"}
}