{
  "type": "Feature",
  "properties": {
    "iso:country":"US",
    "sg:address":"126 N Maple St",
    "sg:city":"Trinidad",
    "sg:classifiers":[
        {
            "category":"Retail",
            "subcategory":"Auto Repair",
            "type":"Services"
        }
    ],
    "sg:phone":"+1 719 846 6071",
    "sg:postcode":"81082",
    "sg:province":"CO",
    "sg:tags":[
        "body"
    ],
    "wof:name":"Corradino Auto Body & Radiator",
    "wof:placetype":"venue"
},
  "geometry": {"coordinates":[-104.504228,37.169293],"type":"Point"}
}