{
  "type": "Feature",
  "properties": {
    "iso:country":"US",
    "sg:address":"3949 E Arapahoe Rd",
    "sg:city":"Centennial",
    "sg:classifiers":[
        {
            "category":"Insurance",
            "subcategory":"Insurance Agent",
            "type":"Services"
        }
    ],
    "sg:phone":"+1 303 773 2019",
    "sg:postcode":"80122",
    "sg:province":"CO",
    "wof:name":"Allstate Insurance",
    "wof:placetype":"venue"
},
  "geometry": {"coordinates":[-104.943286,39.595249],"type":"Point"}
}