{
  "type": "Feature",
  "properties": {
    "addr:full":"6534 S Broadway Littleton CO 80121",
    "addr:housenumber":"6534",
    "addr:postcode":"80121",
    "addr:street":"S Broadway",
    "iso:country":"US",
    "sg:address":"6534 S Broadway",
    "sg:city":"Littleton",
    "sg:classifiers":[
        {
            "category":"Social Services",
            "type":"Services"
        }
    ],
    "sg:phone":"+1 303 758 5568",
    "sg:postcode":"80121",
    "sg:province":"CO",
    "sg:tags":[
        "counselor",
        "marriage",
        "family"
    ],
    "wof:name":"South Community Counseling Svc",
    "wof:placetype":"venue"
},
  "geometry": {"coordinates":[-104.98819399999999,39.600851],"type":"Point"}
}