{
  "type": "Feature",
  "properties": {
    "iso:country":"US",
    "sg:address":"4639 W A St",
    "sg:city":"Greeley",
    "sg:classifiers":[
        {
            "category":"Travel",
            "subcategory":"Travel Agent",
            "type":"Entertainment"
        }
    ],
    "sg:phone":"+1 970 356 5080",
    "sg:postcode":"80634",
    "sg:province":"CO",
    "sg:tags":[
        "agency"
    ],
    "wof:name":"Travel Points International",
    "wof:placetype":"venue"
},
  "geometry": {"coordinates":[-104.754651,40.434503],"type":"Point"}
}