{
  "type": "Feature",
  "properties": {
    "addr:full":"36442 US Hwy 24 Matheson CO 80830",
    "addr:postcode":"36442;80830",
    "addr:street":"Us Hwy 24 Matheson",
    "iso:country":"US",
    "sg:address":"36442 US Hwy 24",
    "sg:city":"Matheson",
    "sg:classifiers":[
        {
            "category":"Building & Trades",
            "subcategory":"Construction",
            "type":"Services"
        }
    ],
    "sg:phone":"+1 719 541 2867",
    "sg:postcode":"80830",
    "sg:province":"CO",
    "sg:tags":[
        "general",
        "contractor"
    ],
    "wof:name":"Gieck Construction",
    "wof:placetype":"venue"
},
  "geometry": {"coordinates":[-103.982096,39.169426],"type":"Point"}
}