{
  "type": "Feature",
  "properties": {
    "addr:full":"401 W 1st St Akron CO 80720",
    "addr:housenumber":"401",
    "addr:postcode":"80720",
    "addr:street":"W 1St St",
    "iso:country":"US",
    "sg:address":"401 W 1st St",
    "sg:city":"Akron",
    "sg:classifiers":[
        {
            "category":"Retail",
            "subcategory":"Auto Repair",
            "type":"Services"
        }
    ],
    "sg:phone":"+1 970 345 2772",
    "sg:postcode":"80720",
    "sg:province":"CO",
    "sg:tags":[
        "repairing",
        "automobile"
    ],
    "wof:name":"Frank's Auto Svc",
    "wof:placetype":"venue"
},
  "geometry": {"coordinates":[-103.21765600000001,40.159088],"type":"Point"}
}