{
  "type": "Feature",
  "properties": {
    "iso:country":"US",
    "sg:address":"180 Arapahoe",
    "sg:city":"Carbondale",
    "sg:classifiers":[
        {
            "category":"Home & Garden",
            "subcategory":"Building Materials",
            "type":"Retail Goods"
        }
    ],
    "sg:phone":"+1 970 963 7330",
    "sg:postcode":"81623",
    "sg:province":"CO",
    "sg:tags":[
        "windows"
    ],
    "wof:name":"J B Windows Specialties",
    "wof:placetype":"venue"
},
  "geometry": {"coordinates":[-107.089731,39.389263],"type":"Point"}
}