{
  "type": "Feature",
  "properties": {
    "iso:country":"US",
    "sg:address":"3033 Sumac St",
    "sg:city":"Fort Collins",
    "sg:classifiers":[
        {
            "category":"Professional",
            "type":"Services"
        }
    ],
    "sg:phone":"+1 970 472 5105",
    "sg:postcode":"80526",
    "sg:province":"CO",
    "wof:name":"Aragons Instlltn Plus",
    "wof:placetype":"venue"
},
  "geometry": {"coordinates":[-105.131956,40.564266],"type":"Point"}
}