{
  "type": "Feature",
  "properties": {
    "iso:country":"US",
    "sg:address":"6628 Delmonico Dr",
    "sg:city":"Colorado Springs",
    "sg:classifiers":[
        {
            "category":"Restaurant",
            "type":"Food & Drink"
        }
    ],
    "sg:phone":"+1 719 265 6556",
    "sg:postcode":"80919",
    "sg:province":"CO",
    "sg:tags":[
        "parlor",
        "ice",
        "cream"
    ],
    "wof:name":"Colorado City Creamery",
    "wof:placetype":"venue"
},
  "geometry": {"coordinates":[-104.829645,38.926468],"type":"Point"}
}