{
  "type": "Feature",
  "properties": {
    "iso:country":"US",
    "sg:address":"16688 W 73rd Dr",
    "sg:city":"Arvada",
    "sg:classifiers":[
        {
            "category":"Mining & Drilling",
            "type":"Manufacturing & Wholesale Goods"
        }
    ],
    "sg:phone":"+1 303 674 3100",
    "sg:postcode":"80007",
    "sg:province":"CO",
    "sg:tags":[
        "exploration"
    ],
    "wof:name":"Stolper Geologic Inc",
    "wof:placetype":"venue"
},
  "geometry": {"coordinates":[-105.187059,39.829521],"type":"Point"}
}