{
  "type": "Feature",
  "properties": {
    "iso:country":"US",
    "sg:address":"5990 S University Blvd",
    "sg:city":"Littleton",
    "sg:classifiers":[
        {
            "category":"Autos & Motor Vehicles",
            "subcategory":"Fuel & Gas Station",
            "type":"Retail Goods"
        }
    ],
    "sg:phone":"+1 303 730 1598",
    "sg:postcode":"80121",
    "sg:province":"CO",
    "sg:tags":[
        "station",
        "gasoline"
    ],
    "wof:name":"Star Mart",
    "wof:placetype":"venue"
},
  "geometry": {"coordinates":[-104.959948,39.607711],"type":"Point"}
}