{
  "type": "Feature",
  "properties": {
    "addr:full":"129 Lost Creek Ln Mountain Village CO 81435",
    "addr:housenumber":"129",
    "addr:postcode":"81435",
    "addr:street":"Lost Creek Ln",
    "iso:country":"US",
    "sg:address":"129 Lost Creek Ln",
    "sg:city":"Mountain Village",
    "sg:classifiers":[
        {
            "category":"Professional",
            "type":"Services"
        }
    ],
    "sg:phone":"+1 970 728 6280",
    "sg:postcode":"81435",
    "sg:province":"CO",
    "sg:tags":[
        "establishment"
    ],
    "wof:name":"Associates MK",
    "wof:placetype":"venue"
},
  "geometry": {"coordinates":[-107.846805,37.935075],"type":"Point"}
}