{
  "type": "Feature",
  "properties": {
    "iso:country":"US",
    "sg:address":"1970 Biron Rd",
    "sg:city":"Montrose",
    "sg:classifiers":[
        {
            "category":"Retail",
            "subcategory":"Photofinishing",
            "type":"Services"
        }
    ],
    "sg:phone":"+1 970 275 2641",
    "sg:postcode":"81401",
    "sg:province":"CO",
    "sg:tags":[
        "photo"
    ],
    "wof:name":"J P Imaging",
    "wof:placetype":"venue"
},
  "geometry": {"coordinates":[-107.837329,38.465286],"type":"Point"}
}