{
  "type": "Feature",
  "properties": {
    "addr:full":"9648 E Colfax Ave Aurora CO 80010",
    "addr:housenumber":"9648",
    "addr:postcode":"80010",
    "addr:street":"E Colfax Ave",
    "iso:country":"US",
    "sg:address":"9648 E Colfax Ave",
    "sg:city":"Aurora",
    "sg:classifiers":[
        {
            "category":"Professional",
            "subcategory":"Employment Agencies",
            "type":"Services"
        }
    ],
    "sg:phone":"+1 303 366 4642",
    "sg:postcode":"80010",
    "sg:province":"CO",
    "sg:tags":[
        "opportunity"
    ],
    "wof:name":"Labor Finders",
    "wof:placetype":"venue"
},
  "geometry": {"coordinates":[-104.876396,39.74021],"type":"Point"}
}