{
  "type": "Feature",
  "properties": {
    "addr:full":"10390 W 34th Ave Wheat Ridge CO 80033",
    "addr:housenumber":"10390",
    "addr:postcode":"80033",
    "addr:street":"W 34Th Ave",
    "iso:country":"US",
    "sg:address":"10390 W 34th Ave",
    "sg:city":"Wheat Ridge",
    "sg:classifiers":[
        {
            "category":"Professional",
            "subcategory":"Management & Consulting",
            "type":"Services"
        }
    ],
    "sg:phone":"+1 303 238 5622",
    "sg:postcode":"80033",
    "sg:province":"CO",
    "sg:tags":[
        "consultant"
    ],
    "wof:name":"Lesher Consulting",
    "wof:placetype":"venue"
},
  "geometry": {"coordinates":[-105.111395,39.764721],"type":"Point"}
}