{
  "type": "Feature",
  "properties": {
    "addr:full":"4448 Vista Dr Fort Collins CO 80526",
    "addr:housenumber":"4448",
    "addr:postcode":"80526",
    "addr:street":"Vista Dr",
    "iso:country":"US",
    "sg:address":"4448 Vista Dr",
    "sg:city":"Fort Collins",
    "sg:classifiers":[
        {
            "category":"Professional",
            "type":"Services"
        }
    ],
    "sg:phone":"+1 970 204 1843",
    "sg:postcode":"80526",
    "sg:province":"CO",
    "wof:name":"Things & Things & Things",
    "wof:placetype":"venue"
},
  "geometry": {"coordinates":[-105.111217,40.524539],"type":"Point"}
}