{
  "type": "Feature",
  "properties": {
    "iso:country":"US",
    "sg:address":"6571 Quebec St",
    "sg:city":"Commerce City",
    "sg:classifiers":[
        {
            "category":"Building & Trades",
            "subcategory":"Construction",
            "type":"Services"
        }
    ],
    "sg:phone":"+1 303 853 0638",
    "sg:postcode":"80022",
    "sg:province":"CO",
    "sg:tags":[
        "concrete",
        "contractor"
    ],
    "wof:name":"Tip Top Concrete",
    "wof:placetype":"venue"
},
  "geometry": {"coordinates":[-104.903566,39.815944],"type":"Point"}
}