{
  "type": "Feature",
  "properties": {
    "addr:full":"20116 Co Rd 3 Berthoud CO 80513",
    "addr:housenumber":"20116",
    "addr:postcode":"80513",
    "addr:street":"Co Rd 3",
    "iso:country":"US",
    "sg:address":"20116 Co Rd 3",
    "sg:city":"Berthoud",
    "sg:classifiers":[
        {
            "category":"Farming",
            "subcategory":"Farm",
            "type":"Manufacturing & Wholesale Goods"
        }
    ],
    "sg:phone":"+1 970 532 2004",
    "sg:postcode":"80513",
    "sg:province":"CO",
    "sg:tags":[
        "crop",
        "general"
    ],
    "wof:name":"Schaal Farms",
    "wof:placetype":"venue"
},
  "geometry": {"coordinates":[-105.03668500000001,40.293545],"type":"Point"}
}