{
  "type": "Feature",
  "properties": {
    "iso:country":"US",
    "sg:address":"1307 8th Ave",
    "sg:city":"Greeley",
    "sg:classifiers":[
        {
            "category":"Personal",
            "subcategory":"Beauty Salon",
            "type":"Services"
        }
    ],
    "sg:phone":"+1 970 356 1431",
    "sg:postcode":"80631",
    "sg:province":"CO",
    "wof:name":"Hair Wackers",
    "wof:placetype":"venue"
},
  "geometry": {"coordinates":[-104.69097600000001,40.417118],"type":"Point"}
}