{
  "type": "Feature",
  "properties": {
    "addr:full":"6075 S Lima St Englewood CO 80111",
    "addr:housenumber":"6075",
    "addr:postcode":"80111",
    "addr:street":"S Lima St",
    "iso:country":"US",
    "sg:address":"6075 S Lima St",
    "sg:city":"Englewood",
    "sg:classifiers":[
        {
            "category":"Shopping",
            "subcategory":"Gifts & Souvenirs",
            "type":"Retail Goods"
        }
    ],
    "sg:phone":"+1 303 773 3144",
    "sg:postcode":"80111",
    "sg:province":"CO",
    "wof:name":"Different Drummer Enterprises",
    "wof:placetype":"venue"
},
  "geometry": {"coordinates":[-104.857041,39.607375],"type":"Point"}
}