{
  "type": "Feature",
  "properties": {
    "iso:country":"US",
    "sg:address":"443 State Hwy 56",
    "sg:city":"Berthoud",
    "sg:classifiers":[
        {
            "category":"Food & Beverages",
            "subcategory":"Liquor & Beverages",
            "type":"Retail Goods"
        }
    ],
    "sg:phone":"+1 970 532 2756",
    "sg:postcode":"80513",
    "sg:province":"CO",
    "wof:name":"Log Cabin Liquors",
    "wof:placetype":"venue"
},
  "geometry": {"coordinates":[-105.04758099999999,40.305531],"type":"Point"}
}