{
  "type": "Feature",
  "properties": {
    "iso:country":"US",
    "sg:address":"914 Black Maple Dr",
    "sg:city":"Loveland",
    "sg:classifiers":[
        {
            "category":"Home & Garden",
            "subcategory":"Mobile Homes",
            "type":"Retail Goods"
        }
    ],
    "sg:phone":"+1 970 622 8081",
    "sg:postcode":"80538",
    "sg:province":"CO",
    "wof:name":"Dw Repo",
    "wof:placetype":"venue"
},
  "geometry": {"coordinates":[-105.089496,40.429439],"type":"Point"}
}