{
  "type": "Feature",
  "properties": {
    "iso:country":"US",
    "sg:address":"34058 US Hwy 285",
    "sg:city":"Villa Grove",
    "sg:classifiers":[
        {
            "category":"Shopping",
            "subcategory":"Discount & Variety Stores",
            "type":"Retail Goods"
        }
    ],
    "sg:phone":"+1 719 655 2242",
    "sg:postcode":"81143",
    "sg:province":"CO",
    "sg:tags":[
        "merchandise",
        "general"
    ],
    "wof:name":"Highland Station",
    "wof:placetype":"venue"
},
  "geometry": {"coordinates":[-105.947509,38.246255],"type":"Point"}
}