{
  "type": "Feature",
  "properties": {
    "addr:full":"4782 Skywriter Cir Colorado Springs CO 80922",
    "addr:postcode":"4782;80922",
    "addr:street":"Skywriter Cir",
    "iso:country":"US",
    "sg:address":"4782 Skywriter Cir",
    "sg:city":"Colorado Springs",
    "sg:classifiers":[
        {
            "category":"Building & Trades",
            "subcategory":"Cleaning & Sanitation",
            "type":"Services"
        }
    ],
    "sg:phone":"+1 719 651 4216",
    "sg:postcode":"80922",
    "sg:province":"CO",
    "sg:tags":[
        "janitor"
    ],
    "wof:name":"Tydall's Cleaning Svc",
    "wof:placetype":"venue"
},
  "geometry": {"coordinates":[-104.714088,38.899913],"type":"Point"}
}