{
  "type": "Feature",
  "properties": {
    "iso:country":"US",
    "sg:address":"361 2nd Ave",
    "sg:city":"Longmont",
    "sg:classifiers":[
        {
            "category":"Wholesale",
            "subcategory":"Plants",
            "type":"Manufacturing & Wholesale Goods"
        }
    ],
    "sg:phone":"+1 303 652 9093",
    "sg:postcode":"80501",
    "sg:province":"CO",
    "sg:tags":[
        "florist"
    ],
    "wof:name":"Tradewinds International",
    "wof:placetype":"venue"
},
  "geometry": {"coordinates":[-105.099244,40.161861],"type":"Point"}
}