{
  "type": "Feature",
  "properties": {
    "iso:country":"US",
    "sg:address":"6871 Fielding Cir",
    "sg:city":"Colorado Springs",
    "sg:classifiers":[
        {
            "category":"Retail",
            "subcategory":"Repair Shop",
            "type":"Services"
        }
    ],
    "sg:phone":"+1 719 390 4154",
    "sg:postcode":"80911",
    "sg:province":"CO",
    "sg:tags":[
        "equipment"
    ],
    "wof:name":"Stainless Repair Inc",
    "wof:placetype":"venue"
},
  "geometry": {"coordinates":[-104.69781500000001,38.730578],"type":"Point"}
}