{
  "type": "Feature",
  "properties": {
    "iso:country":"US",
    "sg:address":"380 Main St",
    "sg:city":"Longmont",
    "sg:classifiers":[
        {
            "category":"Banks & Credit Unions",
            "subcategory":"Bank",
            "type":"Services"
        }
    ],
    "sg:phone":"+1 303 652 5260",
    "sg:postcode":"80501",
    "sg:province":"CO",
    "sg:tags":[
        "loan",
        "real estate"
    ],
    "wof:name":"Equity Leadership Group",
    "wof:placetype":"venue"
},
  "geometry": {"coordinates":[-105.10244,40.164266],"type":"Point"}
}