{
  "type": "Feature",
  "properties": {
    "iso:country":"US",
    "sg:address":"2496 Hwy 6 and 50",
    "sg:city":"Grand Junction",
    "sg:classifiers":[
        {
            "category":"Autos & Motor Vehicles",
            "subcategory":"Automobile Sales",
            "type":"Retail Goods"
        }
    ],
    "sg:phone":"+1 970 241 2414",
    "sg:postcode":"81505",
    "sg:province":"CO",
    "sg:tags":[
        "dealer",
        "car",
        "used",
        "parts",
        "new"
    ],
    "wof:name":"Rocky Mountain Suburu",
    "wof:placetype":"venue"
},
  "geometry": {"coordinates":[-108.593497,39.084907],"type":"Point"}
}