{
  "type": "Feature",
  "properties": {
    "iso:country":"US",
    "sg:address":"801 Wyandot Street",
    "sg:city":"Denver",
    "sg:classifiers":[
        {
            "category":"Professional",
            "subcategory":"Computer Services",
            "type":"Services"
        }
    ],
    "sg:phone":"+1 303 756 9401",
    "sg:postcode":"80204",
    "sg:province":"CO",
    "sg:tags":[
        "repair"
    ],
    "wof:name":"Computer Concepts",
    "wof:placetype":"venue"
},
  "geometry": {"coordinates":[-105.014092,39.730311],"type":"Point"}
}