{
  "type": "Feature",
  "properties": {
    "addr:full":"854 Pearl St Denver CO 80203",
    "addr:housenumber":"854",
    "addr:postcode":"80203",
    "addr:street":"Pearl St",
    "iso:country":"US",
    "sg:address":"854 Pearl St",
    "sg:city":"Denver",
    "sg:classifiers":[
        {
            "category":"Recreation",
            "type":"Entertainment"
        }
    ],
    "sg:phone":"+1 303 839 8420",
    "sg:postcode":"80203",
    "sg:province":"CO",
    "sg:tags":[
        "instruction",
        "yoga"
    ],
    "wof:name":"Ananda Marga Inc",
    "wof:placetype":"venue"
},
  "geometry": {"coordinates":[-104.97985300000001,39.729675],"type":"Point"}
}