{
  "type": "Feature",
  "properties": {
    "addr:full":"14062 Denver West Pkwy Lakewood CO 80401",
    "addr:housenumber":"14062",
    "addr:postcode":"80401",
    "addr:street":"Denver West Pkwy",
    "iso:country":"US",
    "sg:address":"14062 Denver West Pkwy",
    "sg:city":"Lakewood",
    "sg:classifiers":[
        {
            "category":"Health Services",
            "subcategory":"Doctor",
            "type":"Services"
        }
    ],
    "sg:phone":"+1 303 278 2040",
    "sg:postcode":"80401",
    "sg:province":"CO",
    "sg:tags":[
        "physician",
        "surgeon"
    ],
    "wof:name":"Hollstic Neurology",
    "wof:placetype":"venue"
},
  "geometry": {"coordinates":[-105.157734,39.742866],"type":"Point"}
}