{
  "type": "Feature",
  "properties": {
    "iso:country":"US",
    "sg:address":"526 Lodge Pole Pl",
    "sg:city":"Loveland",
    "sg:classifiers":[
        {
            "category":"Building & Trades",
            "subcategory":"Construction",
            "type":"Services"
        }
    ],
    "sg:phone":"+1 970 667 4742",
    "sg:postcode":"80538",
    "sg:province":"CO",
    "sg:tags":[
        "floor",
        "laying",
        "contractor"
    ],
    "wof:name":"Sensational Flooring",
    "wof:placetype":"venue"
},
  "geometry": {"coordinates":[-105.069125,40.422257],"type":"Point"}
}