{
  "type": "Feature",
  "properties": {
    "addr:full":"2681 Fernwood Pl Broomfield CO 80020",
    "addr:housenumber":"2681",
    "addr:postcode":"80020",
    "addr:street":"Fernwood Pl",
    "iso:country":"US",
    "sg:address":"2681 Fernwood Pl",
    "sg:city":"Broomfield",
    "sg:classifiers":[
        {
            "category":"Professional",
            "subcategory":"Accounting & Tax Preparation",
            "type":"Services"
        }
    ],
    "sg:phone":"+1 303 469 5470",
    "sg:postcode":"80020",
    "sg:province":"CO",
    "sg:tags":[
        "accountant"
    ],
    "wof:name":"Paul A Rask CPA",
    "wof:placetype":"venue"
},
  "geometry": {"coordinates":[-105.01983199999999,39.927839],"type":"Point"}
}