{
  "type": "Feature",
  "properties": {
    "addr:full":"31246 Hwy 160 Durango CO 81303",
    "addr:housenumber":"31246",
    "addr:postcode":"co 81303",
    "addr:street":"Hwy 160",
    "iso:country":"US",
    "sg:address":"31246 Hwy 160",
    "sg:city":"Durango",
    "sg:classifiers":[
        {
            "category":"Building & Trades",
            "subcategory":"Electrical",
            "type":"Services"
        }
    ],
    "sg:phone":"+1 970 259 1353",
    "sg:postcode":"81303",
    "sg:province":"CO",
    "sg:tags":[
        "electric",
        "contractor"
    ],
    "wof:name":"Ron's Electric",
    "wof:placetype":"venue"
},
  "geometry": {"coordinates":[-107.782467,37.229692],"type":"Point"}
}