{
  "type": "Feature",
  "properties": {
    "iso:country":"US",
    "sg:address":"3205 Adams St",
    "sg:city":"Denver",
    "sg:classifiers":[
        {
            "category":"Organizations",
            "subcategory":"Religious Organization",
            "type":"Services"
        }
    ],
    "sg:phone":"+1 303 377 8983",
    "sg:postcode":"80205",
    "sg:province":"CO",
    "sg:tags":[
        "church"
    ],
    "wof:name":"Progressive Church-God-Christ",
    "wof:placetype":"venue"
},
  "geometry": {"coordinates":[-104.94880000000001,39.763164],"type":"Point"}
}