{
  "type": "Feature",
  "properties": {
    "addr:full":"40550 Co Rd 70 Briggsdale CO 80611",
    "addr:housenumber":"40550;70",
    "addr:postcode":"80611",
    "addr:street":"Co Rd",
    "iso:country":"US",
    "sg:address":"40550 Co Rd 70",
    "sg:city":"Briggsdale",
    "sg:classifiers":[
        {
            "category":"Shopping",
            "subcategory":"Computers & Home Electronics",
            "type":"Retail Goods"
        }
    ],
    "sg:phone":"+1 970 656 3885",
    "sg:postcode":"80611",
    "sg:province":"CO",
    "sg:tags":[
        "equipment",
        "electronic",
        "supply"
    ],
    "wof:name":"Ridnour Earthworks Inc",
    "wof:placetype":"venue"
},
  "geometry": {"coordinates":[-104.287899,40.493714],"type":"Point"}
}