{
  "type": "Feature",
  "properties": {
    "iso:country":"US",
    "sg:address":"6328 E County Line Rd",
    "sg:city":"Littleton",
    "sg:classifiers":[
        {
            "category":"Education",
            "subcategory":"Dance Studio",
            "type":"Public Place"
        }
    ],
    "sg:phone":"+1 303 221 1722",
    "sg:postcode":"80126",
    "sg:province":"CO",
    "sg:tags":[
        "instruction",
        "dancing"
    ],
    "wof:name":"Academy Of Colorado Ballet",
    "wof:placetype":"venue"
},
  "geometry": {"coordinates":[-104.92213,39.565988],"type":"Point"}
}