{
  "type": "Feature",
  "properties": {
    "addr:full":"320 Hidden Creek Dr Colorado Springs CO 80906",
    "addr:housenumber":"320",
    "addr:postcode":"80906",
    "addr:street":"Hidden Creek Dr",
    "iso:country":"US",
    "sg:address":"320 Hidden Creek Dr",
    "sg:city":"Colorado Springs",
    "sg:classifiers":[
        {
            "category":"Food & Beverages",
            "subcategory":"Specialty",
            "type":"Retail Goods"
        }
    ],
    "sg:phone":"+1 719 579 5500",
    "sg:postcode":"80906",
    "sg:province":"CO",
    "sg:tags":[
        "gourmet",
        "shop"
    ],
    "wof:name":"Pure Decadence Gourmet",
    "wof:placetype":"venue"
},
  "geometry": {"coordinates":[-104.835268,38.778114],"type":"Point"}
}