{
  "type": "Feature",
  "properties": {
    "iso:country":"US",
    "sg:address":"5310 Ward Rd",
    "sg:city":"Arvada",
    "sg:classifiers":[
        {
            "category":"Building & Trades",
            "subcategory":"Construction",
            "type":"Services"
        }
    ],
    "sg:phone":"+1 720 898 0268",
    "sg:postcode":"80002",
    "sg:province":"CO",
    "sg:tags":[
        "general",
        "restoration",
        "remodeling",
        "insurance",
        "contractor"
    ],
    "wof:name":"Rui Contractors",
    "wof:placetype":"venue"
},
  "geometry": {"coordinates":[-105.137907,39.79717],"type":"Point"}
}