{
  "type": "Feature",
  "properties": {
    "iso:country":"US",
    "sg:address":"11314 E US Hwy 160",
    "sg:city":"Alamosa",
    "sg:classifiers":[
        {
            "category":"Shopping",
            "subcategory":"Florist",
            "type":"Retail Goods"
        }
    ],
    "sg:phone":"+1 719 589 8349",
    "sg:postcode":"81101",
    "sg:province":"CO",
    "wof:name":"Tenderly Yours Floral Designs",
    "wof:placetype":"venue"
},
  "geometry": {"coordinates":[-105.83435,37.4734],"type":"Point"}
}