{
  "type": "Feature",
  "properties": {
    "iso:country":"US",
    "sg:address":"3385 S Tower Rd",
    "sg:city":"Aurora",
    "sg:classifiers":[
        {
            "category":"Autos & Motor Vehicles",
            "subcategory":"Fuel & Gas Station",
            "type":"Retail Goods"
        }
    ],
    "sg:phone":"+1 303 693 9966",
    "sg:postcode":"80013",
    "sg:province":"CO",
    "sg:tags":[
        "oil"
    ],
    "wof:name":"Phillips 66",
    "wof:placetype":"venue"
},
  "geometry": {"coordinates":[-104.772524,39.654973],"type":"Point"}
}