{
  "type": "Feature",
  "properties": {
    "iso:country":"US",
    "sg:address":"1425 N Wahsatch Ave",
    "sg:city":"Colorado Springs",
    "sg:classifiers":[
        {
            "category":"Building & Trades",
            "subcategory":"Landscaping Services",
            "type":"Services"
        }
    ],
    "sg:phone":"+1 719 635 7672",
    "sg:postcode":"80907",
    "sg:province":"CO",
    "wof:name":"Swiss Gardens",
    "wof:placetype":"venue"
},
  "geometry": {"coordinates":[-104.816945,38.855014],"type":"Point"}
}