{
  "type": "Feature",
  "properties": {
    "addr:full":"104 N 43rd Ave Greeley CO 80634",
    "addr:housenumber":"104",
    "addr:postcode":"80634",
    "addr:street":"N 43Rd Ave",
    "iso:country":"US",
    "sg:address":"104 N 43rd Ave",
    "sg:city":"Greeley",
    "sg:classifiers":[
        {
            "category":"Building & Trades",
            "subcategory":"Construction",
            "type":"Services"
        }
    ],
    "sg:phone":"+1 970 539 8351",
    "sg:postcode":"80634",
    "sg:province":"CO",
    "sg:tags":[
        "housing",
        "family",
        "contractor"
    ],
    "wof:name":"J L & Sons Construction Inc",
    "wof:placetype":"venue"
},
  "geometry": {"coordinates":[-104.74691,40.433019],"type":"Point"}
}