{
  "type": "Feature",
  "properties": {
    "iso:country":"US",
    "sg:address":"3621 Roberts Rd",
    "sg:city":"Colorado Springs",
    "sg:classifiers":[
        {
            "category":"Freight",
            "type":"Transportation"
        }
    ],
    "sg:phone":"+1 719 391 7874",
    "sg:postcode":"80907",
    "sg:province":"CO",
    "sg:tags":[
        "trucking"
    ],
    "sg:website":"www.gitrucking.com",
    "wof:name":"G I Trucking Co",
    "wof:placetype":"venue"
},
  "geometry": {"coordinates":[-104.818022,38.882294],"type":"Point"}
}