{
  "type": "Feature",
  "properties": {
    "addr:full":"638 Gilcrest Rd Colorado Springs CO 80906",
    "addr:housenumber":"638",
    "addr:postcode":"80906",
    "addr:street":"Gilcrest Rd",
    "iso:country":"US",
    "sg:address":"638 Gilcrest Rd",
    "sg:city":"Colorado Springs",
    "sg:classifiers":[
        {
            "category":"Professional",
            "subcategory":"Management & Consulting",
            "type":"Services"
        }
    ],
    "sg:phone":"+1 719 339 2054",
    "sg:postcode":"80906",
    "sg:province":"CO",
    "wof:name":"D & K Hotel Consulting Inc",
    "wof:placetype":"venue"
},
  "geometry": {"coordinates":[-104.814661,38.78803],"type":"Point"}
}