{
  "type": "Feature",
  "properties": {
    "addr:full":"2675 Akers Dr Colorado Springs CO 80922",
    "addr:housenumber":"2675",
    "addr:postcode":"80922",
    "addr:street":"Akers Dr",
    "iso:country":"US",
    "sg:address":"2675 Akers Dr",
    "sg:city":"Colorado Springs",
    "sg:classifiers":[
        {
            "category":"Professional",
            "subcategory":"Management & Consulting",
            "type":"Services"
        }
    ],
    "sg:phone":"+1 719 380 8373",
    "sg:postcode":"80922",
    "sg:province":"CO",
    "sg:tags":[
        "business"
    ],
    "wof:name":"Sunblest Management LLC",
    "wof:placetype":"venue"
},
  "geometry": {"coordinates":[-104.686313,38.868235],"type":"Point"}
}