{
  "type": "Feature",
  "properties": {
    "iso:country":"US",
    "sg:address":"303 Atwood St",
    "sg:city":"Longmont",
    "sg:classifiers":[
        {
            "category":"Organizations",
            "subcategory":"Membership Organization",
            "type":"Services"
        }
    ],
    "sg:phone":"+1 303 772 5529",
    "sg:postcode":"80501",
    "sg:province":"CO",
    "wof:name":"Our Center",
    "wof:placetype":"venue"
},
  "geometry": {"coordinates":[-105.09665200000001,40.165685],"type":"Point"}
}