{
  "type": "Feature",
  "properties": {
    "addr:full":"6528 Vivian St Arvada CO 80004",
    "addr:housenumber":"6528",
    "addr:postcode":"80004",
    "addr:street":"Vivian St",
    "iso:country":"US",
    "sg:address":"6528 Vivian St",
    "sg:city":"Arvada",
    "sg:classifiers":[
        {
            "category":"Building & Trades",
            "subcategory":"Construction",
            "type":"Services"
        }
    ],
    "sg:phone":"+1 303 423 9204",
    "sg:postcode":"80004",
    "sg:province":"CO",
    "sg:tags":[
        "excavation",
        "pipe",
        "laying",
        "contractor"
    ],
    "wof:name":"Piccolo Excavating",
    "wof:placetype":"venue"
},
  "geometry": {"coordinates":[-105.13676,39.815887],"type":"Point"}
}