{
  "type": "Feature",
  "properties": {
    "addr:full":"1007 Daniel Ave La Junta CO 81050",
    "addr:housenumber":"1007",
    "addr:postcode":"81050",
    "addr:street":"Daniel Ave",
    "iso:country":"US",
    "sg:address":"1007 Daniel Ave",
    "sg:city":"La Junta",
    "sg:classifiers":[
        {
            "category":"Shopping",
            "type":"Retail Goods"
        }
    ],
    "sg:phone":"+1 719 384 9242",
    "sg:postcode":"81050",
    "sg:province":"CO",
    "sg:tags":[
        "farm",
        "alfalfa",
        "implement",
        "corn",
        "farmer"
    ],
    "wof:name":"King Tractor",
    "wof:placetype":"venue"
},
  "geometry": {"coordinates":[-103.52800000000001,37.978353],"type":"Point"}
}