{
  "type": "Feature",
  "properties": {
    "iso:country":"US",
    "sg:address":"8895 S Miners St",
    "sg:city":"Littleton",
    "sg:classifiers":[
        {
            "category":"Building & Trades",
            "subcategory":"Construction",
            "type":"Services"
        }
    ],
    "sg:phone":"+1 720 344 9616",
    "sg:postcode":"80126",
    "sg:province":"CO",
    "sg:tags":[
        "house"
    ],
    "wof:name":"Castlestone Homes Inc",
    "wof:placetype":"venue"
},
  "geometry": {"coordinates":[-104.946354,39.553684],"type":"Point"}
}