{
  "type": "Feature",
  "properties": {
    "iso:country":"US",
    "sg:address":"6941 Zuni St",
    "sg:city":"Denver",
    "sg:classifiers":[
        {
            "category":"Retail",
            "subcategory":"Repair Shop",
            "type":"Services"
        }
    ],
    "sg:phone":"+1 303 429 2785",
    "sg:postcode":"80221",
    "sg:province":"CO",
    "sg:tags":[
        "lock",
        "locksmith"
    ],
    "wof:name":"Johnson's Key & Lock Svc",
    "wof:placetype":"venue"
},
  "geometry": {"coordinates":[-105.015179,39.82361],"type":"Point"}
}