{
  "type": "Feature",
  "properties": {
    "iso:country":"US",
    "sg:address":"3636 W 8th Ave",
    "sg:city":"Denver",
    "sg:classifiers":[
        {
            "category":"Building & Trades",
            "subcategory":"Construction",
            "type":"Services"
        }
    ],
    "sg:phone":"+1 303 534 1691",
    "sg:postcode":"80204",
    "sg:province":"CO",
    "sg:tags":[
        "sealcoating",
        "paving",
        "asphalt",
        "contractor"
    ],
    "wof:name":"Master Patch & Paving",
    "wof:placetype":"venue"
},
  "geometry": {"coordinates":[-105.034655,39.729321],"type":"Point"}
}