{
  "type": "Feature",
  "properties": {
    "addr:full":"9090 W 6th Ave Denver CO 80215",
    "addr:housenumber":"9090",
    "addr:postcode":"80215",
    "addr:street":"W 6Th Ave",
    "iso:country":"US",
    "sg:address":"9090 W 6th Ave",
    "sg:city":"Denver",
    "sg:classifiers":[
        {
            "category":"Restaurant",
            "type":"Food & Drink"
        }
    ],
    "sg:phone":"+1 303 232 4558",
    "sg:postcode":"80215",
    "sg:province":"CO",
    "wof:name":"Szechuan Chinese Restaurant",
    "wof:placetype":"venue"
},
  "geometry": {"coordinates":[-105.099116,39.725196],"type":"Point"}
}