{
  "type": "Feature",
  "properties": {
    "iso:country":"US",
    "sg:address":"3000 63rd St",
    "sg:city":"Boulder",
    "sg:classifiers":[
        {
            "category":"Building & Trades",
            "subcategory":"Construction",
            "type":"Services"
        }
    ],
    "sg:phone":"+1 303 449 1336",
    "sg:postcode":"80301",
    "sg:province":"CO",
    "sg:tags":[
        "home",
        "contractor",
        "general",
        "log",
        "mfg"
    ],
    "wof:name":"Timmerhus Inc",
    "wof:placetype":"venue"
},
  "geometry": {"coordinates":[-105.21120000000001,40.02514],"type":"Point"}
}