{
  "type": "Feature",
  "properties": {
    "addr:full":"8864 Maximus Dr Lone Tree CO 80124",
    "addr:postcode":"8864;80124",
    "addr:street":"Maximus Dr",
    "iso:country":"US",
    "sg:address":"8864 Maximus Dr",
    "sg:city":"Lone Tree",
    "sg:classifiers":[
        {
            "category":"Food & Beverages",
            "subcategory":"Liquor & Beverages",
            "type":"Retail Goods"
        }
    ],
    "sg:phone":"+1 303 754 0444",
    "sg:postcode":"80124",
    "sg:province":"CO",
    "sg:tags":[
        "store"
    ],
    "wof:name":"Meadow Liquors",
    "wof:placetype":"venue"
},
  "geometry": {"coordinates":[-104.885501,39.55491],"type":"Point"}
}