{
  "type": "Feature",
  "properties": {
    "iso:country":"US",
    "sg:address":"2009 S Pueblo Blvd",
    "sg:city":"Pueblo",
    "sg:classifiers":[
        {
            "category":"Shopping",
            "subcategory":"Shoes",
            "type":"Retail Goods"
        }
    ],
    "sg:phone":"+1 719 560 9520",
    "sg:postcode":"81005",
    "sg:province":"CO",
    "wof:name":"Payless Shoe Source",
    "wof:placetype":"venue"
},
  "geometry": {"coordinates":[-104.66246099999999,38.231154],"type":"Point"}
}