{
  "type": "Feature",
  "properties": {
    "iso:country":"US",
    "sg:address":"10577 W Robb Dr",
    "sg:city":"Broomfield",
    "sg:classifiers":[
        {
            "category":"Real Estate",
            "subcategory":"Real Estate Agent",
            "type":"Services"
        }
    ],
    "sg:phone":"+1 303 466 6067",
    "sg:postcode":"80021",
    "sg:province":"CO",
    "sg:tags":[
        "sales"
    ],
    "wof:name":"Purple Mountain Realty",
    "wof:placetype":"venue"
},
  "geometry": {"coordinates":[-105.125451,39.887629],"type":"Point"}
}