{
  "type": "Feature",
  "properties": {
    "addr:full":"10521 E Dorado Ave Englewood CO 80111",
    "addr:housenumber":"10521",
    "addr:postcode":"80111",
    "addr:street":"E Dorado Ave",
    "iso:country":"US",
    "sg:address":"10521 E Dorado Ave",
    "sg:city":"Englewood",
    "sg:classifiers":[
        {
            "category":"Professional",
            "subcategory":"Employment Agencies",
            "type":"Services"
        }
    ],
    "sg:phone":"+1 303 220 1667",
    "sg:postcode":"80111",
    "sg:province":"CO",
    "sg:tags":[
        "consultant",
        "search",
        "executive"
    ],
    "wof:name":"David L Henson Inc",
    "wof:placetype":"venue"
},
  "geometry": {"coordinates":[-104.866007,39.613251],"type":"Point"}
}