{
  "type": "Feature",
  "properties": {
    "addr:full":"7081 Brighton Blvd Commerce City CO 80022",
    "addr:housenumber":"7081",
    "addr:postcode":"80022",
    "addr:street":"Brighton Blvd",
    "iso:country":"US",
    "sg:address":"7081 Brighton Blvd",
    "sg:city":"Commerce City",
    "sg:classifiers":[
        {
            "category":"Wholesale",
            "subcategory":"Machinery & Supplies",
            "type":"Manufacturing & Wholesale Goods"
        }
    ],
    "sg:phone":"+1 303 853 0068",
    "sg:postcode":"80022",
    "sg:province":"CO",
    "sg:tags":[
        "heavy",
        "equipment",
        "construction",
        "industrial"
    ],
    "wof:name":"Rapid International Usa Inc",
    "wof:placetype":"venue"
},
  "geometry": {"coordinates":[-104.928634,39.824943],"type":"Point"}
}