{
  "type": "Feature",
  "properties": {
    "iso:country":"US",
    "sg:address":"25521 E Smoky Hill Rd",
    "sg:city":"Aurora",
    "sg:classifiers":[
        {
            "category":"Health Services",
            "subcategory":"Dentist",
            "type":"Services"
        }
    ],
    "sg:phone":"+1 720 457 9300",
    "sg:postcode":"80016",
    "sg:province":"CO",
    "sg:website":"http://www.yoursouthlandsmile.com",
    "wof:name":"Southland Smiles",
    "wof:placetype":"venue"
},
  "geometry": {"coordinates":[-104.67979200000001,39.580349],"type":"Point"}
}