{
  "type": "Feature",
  "properties": {
    "addr:full":"2038 Whitehorn Dr N Colorado Springs CO 80920",
    "addr:housenumber":"2038",
    "addr:postcode":"80920",
    "addr:street":"Whitehorn Dr N",
    "iso:country":"US",
    "sg:address":"2038 Whitehorn Dr N",
    "sg:city":"Colorado Springs",
    "sg:classifiers":[
        {
            "category":"Manufacturing",
            "subcategory":"Printing",
            "type":"Manufacturing & Wholesale Goods"
        }
    ],
    "sg:phone":"+1 719 528 7127",
    "sg:postcode":"80920",
    "sg:province":"CO",
    "sg:tags":[
        "screen"
    ],
    "wof:name":"Spectralix Screen Printing",
    "wof:placetype":"venue"
},
  "geometry": {"coordinates":[-104.79123,38.943591],"type":"Point"}
}