{
  "type": "Feature",
  "properties": {
    "addr:full":"816 Main St Louisville CO 80027",
    "addr:housenumber":"816",
    "addr:postcode":"80027",
    "addr:street":"Main St",
    "iso:country":"US",
    "sg:address":"816 Main St",
    "sg:city":"Louisville",
    "sg:classifiers":[
        {
            "category":"Restaurant",
            "type":"Food & Drink"
        }
    ],
    "sg:phone":"+1 303 673 9400",
    "sg:postcode":"80027",
    "sg:province":"CO",
    "sg:website":"www.pasquinis.com",
    "wof:name":"Pasquini's Restaurant",
    "wof:placetype":"venue"
},
  "geometry": {"coordinates":[-105.132071,39.97856],"type":"Point"}
}