{
  "type": "Feature",
  "properties": {
    "iso:country":"US",
    "sg:address":"1201 Terrace Rd",
    "sg:city":"Colorado Springs",
    "sg:classifiers":[
        {
            "category":"Building & Trades",
            "subcategory":"Construction",
            "type":"Services"
        },
        {
            "category":"Professional",
            "subcategory":"Management & Consulting",
            "type":"Services"
        }
    ],
    "sg:phone":"+1 719 520 9714",
    "sg:postcode":"80904",
    "sg:province":"CO",
    "sg:tags":[
        "house"
    ],
    "wof:name":"Stritzel Construction MGT Svc",
    "wof:placetype":"venue"
},
  "geometry": {"coordinates":[-104.83849499999999,38.849759],"type":"Point"}
}