{
  "type": "Feature",
  "properties": {
    "iso:country":"US",
    "sg:address":"12760 E Control Tower Rd",
    "sg:city":"Englewood",
    "sg:classifiers":[
        {
            "category":"Airport",
            "type":"Transportation"
        }
    ],
    "sg:phone":"+1 303 799 8386",
    "sg:postcode":"80112",
    "sg:province":"CO",
    "sg:tags":[
        "repair",
        "aircraft",
        "maintenance"
    ],
    "sg:website":"www.arapahoeaero.com",
    "wof:name":"Arapahoe Aero Inc",
    "wof:placetype":"venue"
},
  "geometry": {"coordinates":[-104.837608,39.574922],"type":"Point"}
}