{
  "type": "Feature",
  "properties": {
    "addr:full":"104 S 1st St Montrose CO 81401",
    "addr:housenumber":"104",
    "addr:postcode":"81401",
    "addr:street":"S 1St St",
    "iso:country":"US",
    "sg:address":"104 S 1st St",
    "sg:city":"Montrose",
    "sg:classifiers":[
        {
            "category":"Manufacturing",
            "subcategory":"Toys & Sporting Goods",
            "type":"Manufacturing & Wholesale Goods"
        }
    ],
    "sg:phone":"+1 970 240 3075",
    "sg:postcode":"81401",
    "sg:province":"CO",
    "sg:tags":[
        "various",
        "guide",
        "mfg"
    ],
    "wof:name":"Carltons Corporation Inc",
    "wof:placetype":"venue"
},
  "geometry": {"coordinates":[-107.87795800000001,38.477104],"type":"Point"}
}