{
  "type": "Feature",
  "properties": {
    "addr:full":"9241 Nagel Dr Denver CO 80229",
    "addr:housenumber":"9241",
    "addr:postcode":"80229",
    "addr:street":"Nagel Dr",
    "iso:country":"US",
    "sg:address":"9241 Nagel Dr",
    "sg:city":"Denver",
    "sg:classifiers":[
        {
            "category":"Manufacturing",
            "subcategory":"Metals",
            "type":"Manufacturing & Wholesale Goods"
        }
    ],
    "sg:phone":"+1 303 853 4801",
    "sg:postcode":"80229",
    "sg:province":"CO",
    "sg:tags":[
        "mfg",
        "metalwork",
        "structural"
    ],
    "wof:name":"Formanek Precision Works",
    "wof:placetype":"venue"
},
  "geometry": {"coordinates":[-104.96964800000001,39.864495],"type":"Point"}
}