{
  "type": "Feature",
  "properties": {
    "addr:full":"9804 Cook St Denver CO 80229",
    "addr:housenumber":"9804",
    "addr:postcode":"80229",
    "addr:street":"Cook St",
    "iso:country":"US",
    "sg:address":"9804 Cook St",
    "sg:city":"Denver",
    "sg:classifiers":[
        {
            "category":"Building & Trades",
            "subcategory":"Plumbing",
            "type":"Services"
        }
    ],
    "sg:phone":"+1 303 450 2687",
    "sg:postcode":"80229",
    "sg:province":"CO",
    "sg:tags":[
        "contractor"
    ],
    "wof:name":"Yoshida Hvac Inc",
    "wof:placetype":"venue"
},
  "geometry": {"coordinates":[-104.94725099999999,39.87444],"type":"Point"}
}