{
  "type": "Feature",
  "properties": {
    "addr:full":"12688 S Creekside Ct Parker CO 80134",
    "addr:housenumber":"12688",
    "addr:postcode":"80134",
    "addr:street":"S Creekside Ct",
    "iso:country":"US",
    "sg:address":"12688 S Creekside Ct",
    "sg:city":"Parker",
    "sg:classifiers":[
        {
            "category":"Shopping",
            "subcategory":"Gifts & Souvenirs",
            "type":"Retail Goods"
        }
    ],
    "sg:phone":"+1 303 805 7077",
    "sg:postcode":"80134",
    "sg:province":"CO",
    "wof:name":"Natures Greetings",
    "wof:placetype":"venue"
},
  "geometry": {"coordinates":[-104.766732,39.485999],"type":"Point"}
}