{
  "type": "Feature",
  "properties": {
    "iso:country":"US",
    "sg:address":"7914 W 90th Ave",
    "sg:city":"Broomfield",
    "sg:classifiers":[
        {
            "category":"Professional",
            "type":"Services"
        }
    ],
    "sg:phone":"+1 303 421 6455",
    "sg:postcode":"80021",
    "sg:province":"CO",
    "wof:name":"Karen Kjoller CMT",
    "wof:placetype":"venue"
},
  "geometry": {"coordinates":[-105.084631,39.859919],"type":"Point"}
}