{
  "type": "Feature",
  "properties": {
    "iso:country":"US",
    "sg:address":"1826 E Platte Ave",
    "sg:city":"Colorado Springs",
    "sg:classifiers":[
        {
            "category":"Professional",
            "subcategory":"Business Services",
            "type":"Services"
        }
    ],
    "sg:phone":"+1 719 442 2014",
    "sg:postcode":"80909",
    "sg:province":"CO",
    "sg:tags":[
        "information",
        "bureau",
        "convention"
    ],
    "sg:website":"www.iaff-ffm.com",
    "wof:name":"Fallen Firefighter Memorial",
    "wof:placetype":"venue"
},
  "geometry": {"coordinates":[-104.79400200000001,38.837251],"type":"Point"}
}