{
  "type": "Feature",
  "properties": {
    "iso:country":"US",
    "sg:address":"1 Columbia St",
    "sg:city":"Ward",
    "sg:classifiers":[
        {
            "category":"Government",
            "subcategory":"Post Office",
            "type":"Public Place"
        }
    ],
    "sg:phone":"+1 303 459 0255",
    "sg:postcode":"80481",
    "sg:province":"CO",
    "wof:name":"US Post Office",
    "wof:placetype":"venue"
},
  "geometry": {"coordinates":[-105.508359,40.071811],"type":"Point"}
}