{
  "type": "Feature",
  "properties": {
    "iso:country":"US",
    "sg:address":"316 E Main St",
    "sg:city":"Montrose",
    "sg:classifiers":[
        {
            "category":"Shopping",
            "subcategory":"Tobacco",
            "type":"Retail Goods"
        }
    ],
    "sg:phone":"+1 970 240 6094",
    "sg:postcode":"81401",
    "sg:province":"CO",
    "sg:tags":[
        "cigarette",
        "cigar",
        "dealer"
    ],
    "wof:name":"Tobacco Shop",
    "wof:placetype":"venue"
},
  "geometry": {"coordinates":[-107.876755,38.479291],"type":"Point"}
}