{
  "type": "Feature",
  "properties": {
    "iso:country":"US",
    "sg:address":"4695 Franklin St",
    "sg:city":"Denver",
    "sg:classifiers":[
        {
            "category":"Insurance",
            "subcategory":"Insurance Agent",
            "type":"Services"
        }
    ],
    "sg:phone":"+1 303 308 0360",
    "sg:postcode":"80216",
    "sg:province":"CO",
    "wof:name":"National Western Stock Show",
    "wof:placetype":"venue"
},
  "geometry": {"coordinates":[-104.96888,39.780838],"type":"Point"}
}