{
  "type": "Feature",
  "properties": {
    "iso:country":"US",
    "sg:address":"7649 Meade St",
    "sg:city":"Westminster",
    "sg:classifiers":[
        {
            "category":"Building & Trades",
            "subcategory":"Construction",
            "type":"Services"
        }
    ],
    "sg:phone":"+1 303 429 1147",
    "sg:postcode":"80030",
    "sg:province":"CO",
    "sg:tags":[
        "house"
    ],
    "wof:name":"Garnet Price",
    "wof:placetype":"venue"
},
  "geometry": {"coordinates":[-105.035951,39.835451],"type":"Point"}
}