{
  "type": "Feature",
  "properties": {
    "addr:full":"308 Main St Olathe CO 81425",
    "addr:housenumber":"308",
    "addr:postcode":"81425",
    "addr:street":"Main St",
    "iso:country":"US",
    "sg:address":"308 Main St",
    "sg:city":"Olathe",
    "sg:classifiers":[
        {
            "category":"Organizations",
            "subcategory":"Membership Organization",
            "type":"Services"
        }
    ],
    "sg:phone":"+1 970 323 5078",
    "sg:postcode":"81425",
    "sg:province":"CO",
    "wof:name":"Wic",
    "wof:placetype":"venue"
},
  "geometry": {"coordinates":[-107.983993,38.606297],"type":"Point"}
}