{
  "type": "Feature",
  "properties": {
    "addr:full":"1263 Giant Track Rd Estes Park CO 80517",
    "addr:housenumber":"1263",
    "addr:postcode":"80517",
    "addr:street":"Giant Track Rd",
    "iso:country":"US",
    "sg:address":"1263 Giant Track Rd",
    "sg:city":"Estes Park",
    "sg:classifiers":[
        {
            "category":"Building & Trades",
            "subcategory":"Construction",
            "type":"Services"
        }
    ],
    "sg:phone":"+1 970 586 8166",
    "sg:postcode":"80517",
    "sg:province":"CO",
    "sg:tags":[
        "contractor"
    ],
    "wof:name":"Pinecreek Furniture",
    "wof:placetype":"venue"
},
  "geometry": {"coordinates":[-105.545446,40.352146],"type":"Point"}
}