{
  "type": "Feature",
  "properties": {
    "iso:country":"US",
    "sg:address":"124 N 1st St",
    "sg:city":"Grand Junction",
    "sg:classifiers":[
        {
            "category":"Autos & Motor Vehicles",
            "subcategory":"Automobile Sales",
            "type":"Retail Goods"
        }
    ],
    "sg:phone":"+1 970 254 9842",
    "sg:postcode":"81501",
    "sg:province":"CO",
    "sg:tags":[
        "car",
        "used",
        "dealer"
    ],
    "wof:name":"Marconi's Auto Sales",
    "wof:placetype":"venue"
},
  "geometry": {"coordinates":[-108.570843,39.068067],"type":"Point"}
}