{
  "type": "Feature",
  "properties": {
    "iso:country":"US",
    "sg:address":"409 N Santa Fe Ave",
    "sg:city":"Pueblo",
    "sg:classifiers":[
        {
            "category":"Restaurant",
            "type":"Food & Drink"
        }
    ],
    "sg:phone":"+1 719 544 0733",
    "sg:postcode":"81003",
    "sg:province":"CO",
    "sg:tags":[
        "banquet",
        "rooms"
    ],
    "wof:name":"Nacho's Restaurant",
    "wof:placetype":"venue"
},
  "geometry": {"coordinates":[-104.607133,38.271515],"type":"Point"}
}