{
  "type": "Feature",
  "properties": {
    "addr:full":"100 York Gulch Rd Idaho Springs CO 80452",
    "addr:housenumber":"100",
    "addr:postcode":"80452",
    "addr:street":"York Gulch Rd",
    "iso:country":"US",
    "sg:address":"100 York Gulch Rd",
    "sg:city":"Idaho Springs",
    "sg:classifiers":[
        {
            "category":"Building & Trades",
            "subcategory":"Electrical",
            "type":"Services"
        }
    ],
    "sg:phone":"+1 303 567 2481",
    "sg:postcode":"80452",
    "sg:province":"CO",
    "sg:tags":[
        "electric",
        "contractor"
    ],
    "wof:name":"Noble Electrical Svc",
    "wof:placetype":"venue"
},
  "geometry": {"coordinates":[-105.558442,39.770172],"type":"Point"}
}