{
  "type": "Feature",
  "properties": {
    "iso:country":"US",
    "sg:address":"1000 N 9th St",
    "sg:city":"Grand Junction",
    "sg:classifiers":[
        {
            "category":"Organizations",
            "subcategory":"Labor Organization",
            "type":"Services"
        }
    ],
    "sg:phone":"+1 970 241 8929",
    "sg:postcode":"81501",
    "sg:province":"CO",
    "wof:name":"American Postal Wrkrs Unn 600",
    "wof:placetype":"venue"
},
  "geometry": {"coordinates":[-108.557683,39.077401],"type":"Point"}
}