{
  "type": "Feature",
  "properties": {
    "addr:full":"877 Cole St Golden CO 80401",
    "addr:housenumber":"877",
    "addr:postcode":"80401",
    "addr:street":"Cole St",
    "iso:country":"US",
    "sg:address":"877 Cole St",
    "sg:city":"Golden",
    "sg:classifiers":[
        {
            "category":"Building & Trades",
            "subcategory":"Construction",
            "type":"Services"
        }
    ],
    "sg:phone":"+1 303 232 8317",
    "sg:postcode":"80401",
    "sg:province":"CO",
    "sg:tags":[
        "concrete",
        "contractor",
        "work",
        "flat"
    ],
    "wof:name":"Wrightway Concrete Contractors",
    "wof:placetype":"venue"
},
  "geometry": {"coordinates":[-105.151832,39.730497],"type":"Point"}
}