{
  "type": "Feature",
  "properties": {
    "addr:full":"2779 Crossroads Blvd Grand Junction CO 81506",
    "addr:housenumber":"2779",
    "addr:postcode":"81506",
    "addr:street":"Crossroads Blvd",
    "iso:country":"US",
    "sg:address":"2779 Crossroads Blvd",
    "sg:city":"Grand Junction",
    "sg:classifiers":[
        {
            "category":"Insurance",
            "subcategory":"Insurance Agent",
            "type":"Services"
        }
    ],
    "sg:phone":"+1 970 256 6800",
    "sg:postcode":"81506",
    "sg:province":"CO",
    "wof:name":"State Farm Insurance",
    "wof:placetype":"venue"
},
  "geometry": {"coordinates":[-108.535712,39.114487],"type":"Point"}
}