{
  "type": "Feature",
  "properties": {
    "addr:full":"8077 Iris Ct Arvada CO 80005",
    "addr:housenumber":"8077",
    "addr:postcode":"80005",
    "addr:street":"Iris Ct",
    "iso:country":"US",
    "sg:address":"8077 Iris Ct",
    "sg:city":"Arvada",
    "sg:classifiers":[
        {
            "category":"Social Services",
            "subcategory":"Child Care",
            "type":"Services"
        }
    ],
    "sg:phone":"+1 303 467 0892",
    "sg:postcode":"80005",
    "sg:province":"CO",
    "sg:tags":[
        "day"
    ],
    "wof:name":"Happy Vallia Children Range",
    "wof:placetype":"venue"
},
  "geometry": {"coordinates":[-105.10569,39.843409],"type":"Point"}
}