{
  "type": "Feature",
  "properties": {
    "addr:full":"340 Hemlock St Broomfield CO 80020",
    "addr:housenumber":"340",
    "addr:postcode":"80020",
    "addr:street":"Hemlock St",
    "iso:country":"US",
    "sg:address":"340 Hemlock St",
    "sg:city":"Broomfield",
    "sg:classifiers":[
        {
            "category":"Building & Trades",
            "subcategory":"Construction",
            "type":"Services"
        }
    ],
    "sg:phone":"+1 303 464 9690",
    "sg:postcode":"80020",
    "sg:province":"CO",
    "sg:tags":[
        "house"
    ],
    "wof:name":"R Better Builders",
    "wof:placetype":"venue"
},
  "geometry": {"coordinates":[-105.080545,39.921015],"type":"Point"}
}