{
  "type": "Feature",
  "properties": {
    "iso:country":"US",
    "sg:address":"1115 Elkton Dr",
    "sg:city":"Colorado Springs",
    "sg:classifiers":[
        {
            "category":"Real Estate",
            "subcategory":"Real Estate Agent",
            "type":"Services"
        }
    ],
    "sg:phone":"+1 719 277 6636",
    "sg:postcode":"80907",
    "sg:province":"CO",
    "wof:name":"Community Real Est Group Inc",
    "wof:placetype":"venue"
},
  "geometry": {"coordinates":[-104.845279,38.899925],"type":"Point"}
}