{
  "type": "Feature",
  "properties": {
    "addr:full":"21333 Co Rd 40 La Salle CO 80645",
    "addr:housenumber":"21333",
    "addr:postcode":"80645",
    "addr:street":"Co Rd 40",
    "iso:country":"US",
    "sg:address":"21333 Co Rd 40",
    "sg:city":"La Salle",
    "sg:phone":"+1 970 284 6626",
    "sg:postcode":"80645",
    "sg:province":"CO",
    "sg:tags":[
        "farm",
        "field",
        "crop"
    ],
    "wof:name":"Oster Farm",
    "wof:placetype":"venue"
},
  "geometry": {"coordinates":[-104.653987,40.276043],"type":"Point"}
}