{
  "type": "Feature",
  "properties": {
    "iso:country":"US",
    "sg:address":"263 E 1st St",
    "sg:city":"Ault",
    "sg:classifiers":[
        {
            "category":"Home & Garden",
            "subcategory":"Building Materials",
            "type":"Retail Goods"
        }
    ],
    "sg:phone":"+1 970 834 1371",
    "sg:postcode":"80610",
    "sg:province":"CO",
    "sg:tags":[
        "lumber"
    ],
    "wof:name":"Sunrise Lumber Co",
    "wof:placetype":"venue"
},
  "geometry": {"coordinates":[-104.72971699999999,40.582386],"type":"Point"}
}