{
  "type": "Feature",
  "properties": {
    "iso:country":"US",
    "sg:address":"115 S 7th St",
    "sg:city":"Canon City",
    "sg:classifiers":[
        {
            "category":"Insurance",
            "subcategory":"Insurance Agent",
            "type":"Services"
        }
    ],
    "sg:phone":"+1 719 275 2373",
    "sg:postcode":"81212",
    "sg:province":"CO",
    "sg:tags":[
        "life",
        "carrier"
    ],
    "wof:name":"Farmers Union Insurance",
    "wof:placetype":"venue"
},
  "geometry": {"coordinates":[-105.23810400000001,38.441612],"type":"Point"}
}