{
  "type": "Feature",
  "properties": {
    "iso:country":"US",
    "sg:address":"2718 Bruchez Pkwy",
    "sg:city":"Denver",
    "sg:classifiers":[
        {
            "category":"Professional",
            "type":"Services"
        }
    ],
    "sg:phone":"+1 303 635 1537",
    "sg:postcode":"80234",
    "sg:province":"CO",
    "wof:name":"John Crouch Inc",
    "wof:placetype":"venue"
},
  "geometry": {"coordinates":[-105.02011400000001,39.889765],"type":"Point"}
}