{
  "type": "Feature",
  "properties": {
    "addr:full":"14534 E Asbury Ave Aurora CO 80014",
    "addr:housenumber":"14534",
    "addr:postcode":"80014",
    "addr:street":"E Asbury Ave",
    "iso:country":"US",
    "sg:address":"14534 E Asbury Ave",
    "sg:city":"Aurora",
    "sg:classifiers":[
        {
            "category":"Professional",
            "type":"Services"
        }
    ],
    "sg:phone":"+1 303 751 3610",
    "sg:postcode":"80014",
    "sg:province":"CO",
    "wof:name":"Patrick S Wing",
    "wof:placetype":"venue"
},
  "geometry": {"coordinates":[-104.817475,39.680553],"type":"Point"}
}