{
  "type": "Feature",
  "properties": {
    "iso:country":"US",
    "sg:address":"1005 S Mesa Ave",
    "sg:city":"Montrose",
    "sg:classifiers":[
        {
            "category":"Real Estate",
            "subcategory":"Real Estate Agent",
            "type":"Services"
        }
    ],
    "sg:phone":"+1 970 240 1601",
    "sg:postcode":"81401",
    "sg:province":"CO",
    "sg:tags":[
        "investment"
    ],
    "wof:name":"Brougham & Assoc",
    "wof:placetype":"venue"
},
  "geometry": {"coordinates":[-107.864507,38.473665],"type":"Point"}
}