{
  "type": "Feature",
  "properties": {
    "iso:country":"US",
    "sg:address":"6500 E 62nd Pl",
    "sg:city":"Commerce City",
    "sg:classifiers":[
        {
            "category":"Autos & Motor Vehicles",
            "subcategory":"Auto Supplies",
            "type":"Retail Goods"
        },
        {
            "category":"Retail",
            "subcategory":"Auto Repair",
            "type":"Services"
        }
    ],
    "sg:phone":"+1 303 287 1808",
    "sg:postcode":"80022",
    "sg:province":"CO",
    "sg:tags":[
        "tire"
    ],
    "wof:name":"Derby Service Inc",
    "wof:placetype":"venue"
},
  "geometry": {"coordinates":[-104.913002,39.809799],"type":"Point"}
}