{
  "type": "Feature",
  "properties": {
    "addr:full":"5445 W 115th Pl Broomfield CO 80020",
    "addr:housenumber":"5445",
    "addr:postcode":"80020",
    "addr:street":"W 115Th Pl",
    "iso:country":"US",
    "sg:address":"5445 W 115th Pl",
    "sg:city":"Broomfield",
    "sg:classifiers":[
        {
            "category":"Professional",
            "type":"Services"
        }
    ],
    "sg:phone":"+1 303 410 1776",
    "sg:postcode":"80020",
    "sg:province":"CO",
    "wof:name":"Eloy Retana LLC",
    "wof:placetype":"venue"
},
  "geometry": {"coordinates":[-105.055572,39.906709],"type":"Point"}
}