{
  "type": "Feature",
  "properties": {
    "addr:full":"2021 E 74th Ave Denver CO 80229",
    "addr:housenumber":"2021",
    "addr:postcode":"80229",
    "addr:street":"E 74Th Ave",
    "iso:country":"US",
    "sg:address":"2021 E 74th Ave",
    "sg:city":"Denver",
    "sg:classifiers":[
        {
            "category":"Autos & Motor Vehicles",
            "subcategory":"Auto Supplies",
            "type":"Retail Goods"
        }
    ],
    "sg:phone":"+1 303 286 8555",
    "sg:postcode":"80229",
    "sg:province":"CO",
    "wof:name":"Pole Position Racg & Rod Pdts",
    "wof:placetype":"venue"
},
  "geometry": {"coordinates":[-104.959371,39.830942],"type":"Point"}
}