{
  "type": "Feature",
  "properties": {
    "iso:country":"US",
    "sg:address":"4301 W. 44th Ave",
    "sg:city":"Denver",
    "sg:classifiers":[
        {
            "category":"Restaurant",
            "type":"Food & Drink"
        }
    ],
    "sg:phone":"+1 303 455 0484",
    "sg:postcode":"80212",
    "sg:province":"CO",
    "wof:name":"Tacos Japeneno",
    "wof:placetype":"venue"
},
  "geometry": {"coordinates":[-105.043072,39.776853],"type":"Point"}
}