{
  "type": "Feature",
  "properties": {
    "iso:country":"US",
    "sg:address":"5275 E Weaver Ave",
    "sg:city":"Littleton",
    "sg:classifiers":[
        {
            "category":"Professional",
            "type":"Services"
        }
    ],
    "sg:phone":"+1 303 741 0480",
    "sg:postcode":"80121",
    "sg:province":"CO",
    "wof:name":"James Deborah Isis Engrg LLC",
    "wof:placetype":"venue"
},
  "geometry": {"coordinates":[-104.927452,39.601657],"type":"Point"}
}