{
  "type": "Feature",
  "properties": {
    "iso:country":"US",
    "sg:address":"108 W 2nd St",
    "sg:city":"Delta",
    "sg:classifiers":[
        {
            "category":"Food & Beverages",
            "subcategory":"Dairy",
            "type":"Retail Goods"
        }
    ],
    "sg:phone":"+1 970 874 3716",
    "sg:postcode":"81416",
    "sg:province":"CO",
    "sg:tags":[
        "product"
    ],
    "wof:name":"Pizza To Limit",
    "wof:placetype":"venue"
},
  "geometry": {"coordinates":[-108.07142,38.744206],"type":"Point"}
}