{
  "type": "Feature",
  "properties": {
    "addr:full":"235 Cambridge St Brush CO 80723",
    "addr:housenumber":"235",
    "addr:postcode":"80723",
    "addr:street":"Cambridge St",
    "iso:country":"US",
    "sg:address":"235 Cambridge St",
    "sg:city":"Brush",
    "sg:classifiers":[
        {
            "category":"Social Services",
            "subcategory":"Adult Care",
            "type":"Services"
        }
    ],
    "sg:phone":"+1 970 842 5924",
    "sg:postcode":"80723",
    "sg:province":"CO",
    "sg:tags":[
        "home",
        "residential"
    ],
    "wof:name":"Cambridge House",
    "wof:placetype":"venue"
},
  "geometry": {"coordinates":[-103.647784,40.256547],"type":"Point"}
}