{
  "type": "Feature",
  "properties": {
    "addr:full":"396 W Palmer Lake Dr Pueblo West CO 81007",
    "addr:housenumber":"396",
    "addr:postcode":"81007",
    "addr:street":"W Palmer Lake Dr",
    "iso:country":"US",
    "sg:address":"396 W Palmer Lake Dr",
    "sg:city":"Pueblo West",
    "sg:classifiers":[
        {
            "category":"Retail",
            "subcategory":"Laundry & Dry Cleaning",
            "type":"Services"
        }
    ],
    "sg:phone":"+1 719 647 1545",
    "sg:postcode":"81007",
    "sg:province":"CO",
    "sg:tags":[
        "cleaners",
        "rug",
        "carpet"
    ],
    "wof:name":"Champion Chem-Dry",
    "wof:placetype":"venue"
},
  "geometry": {"coordinates":[-104.75712,38.317082],"type":"Point"}
}