{
  "type": "Feature",
  "properties": {
    "iso:country":"US",
    "sg:address":"302 E Adams Ave",
    "sg:city":"Pueblo",
    "sg:classifiers":[
        {
            "category":"Building & Trades",
            "subcategory":"Electrical",
            "type":"Services"
        }
    ],
    "sg:phone":"+1 719 542 2011",
    "sg:postcode":"81004",
    "sg:province":"CO",
    "sg:tags":[
        "electrical",
        "electric",
        "contractor"
    ],
    "wof:name":"Royse Electric Co Inc",
    "wof:placetype":"venue"
},
  "geometry": {"coordinates":[-104.625654,38.251582],"type":"Point"}
}