{
  "type": "Feature",
  "properties": {
    "iso:country":"US",
    "sg:address":"13280 E Mississippi Ave",
    "sg:city":"Aurora",
    "sg:classifiers":[
        {
            "category":"Building & Trades",
            "subcategory":"Construction",
            "type":"Services"
        }
    ],
    "sg:phone":"+1 303 369 5259",
    "sg:postcode":"80012",
    "sg:province":"CO",
    "sg:tags":[
        "resurfacing",
        "laying",
        "refinishing",
        "floor"
    ],
    "wof:name":"Coastal Flooring",
    "wof:placetype":"venue"
},
  "geometry": {"coordinates":[-104.834373,39.69654],"type":"Point"}
}