{
  "type": "Feature",
  "properties": {
    "iso:country":"US",
    "sg:address":"1275 S Teller St",
    "sg:city":"Lakewood",
    "sg:classifiers":[
        {
            "category":"Education",
            "subcategory":"School",
            "type":"Public Place"
        }
    ],
    "sg:phone":"+1 303 982 8370",
    "sg:postcode":"80232",
    "sg:province":"CO",
    "sg:tags":[
        "high",
        "middle",
        "elementary"
    ],
    "wof:name":"Schools Public",
    "wof:placetype":"venue"
},
  "geometry": {"coordinates":[-105.07749200000001,39.696707],"type":"Point"}
}