{
  "type": "Feature",
  "properties": {
    "iso:country":"US",
    "sg:address":"1765 S 8th St",
    "sg:city":"Colorado Springs",
    "sg:classifiers":[
        {
            "category":"Professional",
            "subcategory":"Detective & Security Services",
            "type":"Services"
        }
    ],
    "sg:phone":"+1 719 630 7672",
    "sg:postcode":"80906",
    "sg:province":"CO",
    "sg:tags":[
        "equipment",
        "electrical",
        "system"
    ],
    "wof:name":"F C I Security",
    "wof:placetype":"venue"
},
  "geometry": {"coordinates":[-104.84075900000001,38.805929],"type":"Point"}
}