{
  "type": "Feature",
  "properties": {
    "addr:full":"1422 Royal Gorge Blvd Canon City CO 81212",
    "addr:housenumber":"1422",
    "addr:postcode":"81212",
    "addr:street":"Royal Gorge Blvd",
    "iso:country":"US",
    "sg:address":"1422 Royal Gorge Blvd",
    "sg:city":"Canon City",
    "sg:classifiers":[
        {
            "category":"Retail",
            "subcategory":"Repair Shop",
            "type":"Services"
        }
    ],
    "sg:phone":"+1 719 275 7787",
    "sg:postcode":"81212",
    "sg:province":"CO",
    "sg:tags":[
        "lock",
        "locksmith"
    ],
    "wof:name":"Middick's Locksmith Shop",
    "wof:placetype":"venue"
},
  "geometry": {"coordinates":[-105.227384,38.445676],"type":"Point"}
}