{
  "type": "Feature",
  "properties": {
    "addr:full":"203 Debbie Cir Woodland Park CO 80863",
    "addr:housenumber":"203",
    "addr:postcode":"80863",
    "addr:street":"Debbie Cir",
    "iso:country":"US",
    "sg:address":"203 Debbie Cir",
    "sg:city":"Woodland Park",
    "sg:classifiers":[
        {
            "category":"Building & Trades",
            "subcategory":"Construction",
            "type":"Services"
        }
    ],
    "sg:phone":"+1 719 686 7482",
    "sg:postcode":"80863",
    "sg:province":"CO",
    "sg:tags":[
        "concrete",
        "contractor"
    ],
    "wof:name":"Double M Concrete",
    "wof:placetype":"venue"
},
  "geometry": {"coordinates":[-105.080696,38.961644],"type":"Point"}
}