{
  "type": "Feature",
  "properties": {
    "addr:full":"8055 W Bowles Ave Littleton CO 80123",
    "addr:housenumber":"8055",
    "addr:postcode":"80123",
    "addr:street":"W Bowles Ave",
    "iso:country":"US",
    "sg:address":"8055 W Bowles Ave",
    "sg:city":"Littleton",
    "sg:classifiers":[
        {
            "category":"Shopping",
            "subcategory":"Bicycles & Sporting Goods",
            "type":"Retail Goods"
        }
    ],
    "sg:phone":"+1 303 933 9005",
    "sg:postcode":"80123",
    "sg:province":"CO",
    "wof:name":"Gart Sports",
    "wof:placetype":"venue"
},
  "geometry": {"coordinates":[-105.088719,39.609797],"type":"Point"}
}