{
  "type": "Feature",
  "properties": {
    "addr:full":"3108 S Parker Rd Aurora CO 80014",
    "addr:housenumber":"3108",
    "addr:postcode":"80014",
    "addr:street":"S Parker Rd",
    "iso:country":"US",
    "sg:address":"3108 S Parker Rd",
    "sg:city":"Aurora",
    "sg:classifiers":[
        {
            "category":"Banks & Credit Unions",
            "subcategory":"Bank",
            "type":"Services"
        }
    ],
    "sg:phone":"+1 303 755 9140",
    "sg:postcode":"80014",
    "sg:province":"CO",
    "sg:tags":[
        "cashing",
        "check"
    ],
    "wof:name":"ACE Cash Express",
    "wof:placetype":"venue"
},
  "geometry": {"coordinates":[-104.853067,39.659914],"type":"Point"}
}