{
  "type": "Feature",
  "properties": {
    "addr:full":"1720 Kirkwood Dr Fort Collins CO 80525",
    "addr:housenumber":"1720",
    "addr:postcode":"80525",
    "addr:street":"Kirkwood Dr",
    "iso:country":"US",
    "sg:address":"1720 Kirkwood Dr",
    "sg:city":"Fort Collins",
    "sg:classifiers":[
        {
            "category":"Real Estate",
            "subcategory":"Real Estate Operator",
            "type":"Services"
        }
    ],
    "sg:phone":"+1 970 221 0945",
    "sg:postcode":"80525",
    "sg:province":"CO",
    "sg:tags":[
        "building",
        "apartment"
    ],
    "wof:name":"Parkwood East Apartments",
    "wof:placetype":"venue"
},
  "geometry": {"coordinates":[-105.044618,40.559431],"type":"Point"}
}