{
  "type": "Feature",
  "properties": {
    "addr:full":"5678 Eudora Street Commerce City CO 80022",
    "addr:housenumber":"5678",
    "addr:postcode":"80022",
    "addr:street":"Eudora Street",
    "iso:country":"US",
    "sg:address":"5678 Eudora Street",
    "sg:city":"Commerce City",
    "sg:classifiers":[
        {
            "category":"Home & Garden",
            "subcategory":"Hardware",
            "type":"Retail Goods"
        }
    ],
    "sg:phone":"+1 303 287 2121",
    "sg:postcode":"80022",
    "sg:province":"CO",
    "sg:tags":[
        "store"
    ],
    "wof:name":"Labor Saving Devices",
    "wof:placetype":"venue"
},
  "geometry": {"coordinates":[-104.93023700000001,39.801017],"type":"Point"}
}