{
  "type": "Feature",
  "properties": {
    "addr:full":"2922 Evergreen Pkwy Evergreen CO 80439",
    "addr:housenumber":"2922",
    "addr:postcode":"80439",
    "addr:street":"Evergreen Pkwy",
    "iso:country":"US",
    "sg:address":"2922 Evergreen Pkwy",
    "sg:city":"Evergreen",
    "sg:classifiers":[
        {
            "category":"Utilities",
            "subcategory":"Water",
            "type":"Services"
        }
    ],
    "sg:phone":"+1 303 674 3379",
    "sg:postcode":"80439",
    "sg:province":"CO",
    "sg:tags":[
        "company",
        "sewage"
    ],
    "wof:name":"Grant Water District",
    "wof:placetype":"venue"
},
  "geometry": {"coordinates":[-105.35411999999999,39.662031],"type":"Point"}
}