{
  "type": "Feature",
  "properties": {
    "addr:full":"2113 Squires St Longmont CO 80501",
    "addr:housenumber":"2113",
    "addr:postcode":"80501",
    "addr:street":"Squires St",
    "iso:country":"US",
    "sg:address":"2113 Squires St",
    "sg:city":"Longmont",
    "sg:classifiers":[
        {
            "category":"Building & Trades",
            "subcategory":"Construction",
            "type":"Services"
        }
    ],
    "sg:phone":"+1 303 651 1299",
    "sg:postcode":"80501",
    "sg:province":"CO",
    "sg:tags":[
        "hanging",
        "contractor"
    ],
    "wof:name":"Showalter Roofing & Repair",
    "wof:placetype":"venue"
},
  "geometry": {"coordinates":[-105.10856800000001,40.196045],"type":"Point"}
}