{
  "type": "Feature",
  "properties": {
    "iso:country":"US",
    "sg:address":"7522 S Pinery Parkway",
    "sg:city":"Parker",
    "sg:classifiers":[
        {
            "category":"Retail",
            "subcategory":"Animal Services",
            "type":"Services"
        }
    ],
    "sg:phone":"+1 303 841 5280",
    "sg:postcode":"80134",
    "sg:province":"CO",
    "sg:tags":[
        "pet"
    ],
    "wof:name":"Westmanton Stables",
    "wof:placetype":"venue"
},
  "geometry": {"coordinates":[-104.755297,39.440428],"type":"Point"}
}