{
  "type": "Feature",
  "properties": {
    "iso:country":"US",
    "sg:address":"255 Jack Boot Way",
    "sg:city":"Monument",
    "sg:classifiers":[
        {
            "category":"Food & Beverages",
            "subcategory":"Groceries & Convenience Stores",
            "type":"Retail Goods"
        }
    ],
    "sg:phone":"+1 719 488 2427",
    "sg:postcode":"80132",
    "sg:province":"CO",
    "wof:name":"Colorado River Trip",
    "wof:placetype":"venue"
},
  "geometry": {"coordinates":[-104.832004,39.087169],"type":"Point"}
}