{
  "type": "Feature",
  "properties": {
    "addr:full":"7134 S Eudora Ct Centennial CO 80122",
    "addr:housenumber":"7134",
    "addr:postcode":"80122",
    "addr:street":"S Eudora Ct",
    "iso:country":"US",
    "sg:address":"7134 S Eudora Ct",
    "sg:city":"Centennial",
    "sg:classifiers":[
        {
            "category":"Shopping",
            "subcategory":"Hobbies, Toys, & Games",
            "type":"Retail Goods"
        },
        {
            "category":"Shopping",
            "subcategory":"Gifts & Souvenirs",
            "type":"Retail Goods"
        }
    ],
    "sg:phone":"+1 303 730 9211",
    "sg:postcode":"80122",
    "sg:province":"CO",
    "sg:tags":[
        "basket"
    ],
    "wof:name":"Sun Spirit Baskets",
    "wof:placetype":"venue"
},
  "geometry": {"coordinates":[-104.93169899999999,39.586324],"type":"Point"}
}