{
  "type": "Feature",
  "properties": {
    "iso:country":"US",
    "sg:address":"3629 Star Ranch Rd",
    "sg:city":"Colorado Springs",
    "sg:classifiers":[
        {
            "category":"Restaurant",
            "type":"Food & Drink"
        }
    ],
    "sg:phone":"+1 719 579 8822",
    "sg:postcode":"80906",
    "sg:province":"CO",
    "sg:tags":[
        "eating"
    ],
    "wof:name":"China Doll Chinese Restaurant",
    "wof:placetype":"venue"
},
  "geometry": {"coordinates":[-104.816328,38.775891],"type":"Point"}
}