{
  "type": "Feature",
  "properties": {
    "iso:country":"US",
    "sg:address":"21880 Rinconada Rd",
    "sg:city":"Morrison",
    "sg:classifiers":[
        {
            "category":"Professional",
            "subcategory":"Employment Agencies",
            "type":"Services"
        }
    ],
    "sg:phone":"+1 303 955 3050",
    "sg:postcode":"80465",
    "sg:province":"CO",
    "sg:tags":[
        "consultant",
        "search",
        "executive"
    ],
    "wof:name":"Tradewind Solutions",
    "wof:placetype":"venue"
},
  "geometry": {"coordinates":[-105.24963099999999,39.590557],"type":"Point"}
}