{
  "type": "Feature",
  "properties": {
    "addr:full":"618 Salano Dr Colorado Springs CO 80906",
    "addr:housenumber":"618",
    "addr:postcode":"80906",
    "addr:street":"Salano Dr",
    "iso:country":"US",
    "sg:address":"618 Salano Dr",
    "sg:city":"Colorado Springs",
    "sg:classifiers":[
        {
            "category":"Building & Trades",
            "subcategory":"Electrical",
            "type":"Services"
        }
    ],
    "sg:phone":"+1 719 636 1922",
    "sg:postcode":"80906",
    "sg:province":"CO",
    "sg:tags":[
        "electric",
        "contractor"
    ],
    "wof:name":"Bob Cox Electric Inc",
    "wof:placetype":"venue"
},
  "geometry": {"coordinates":[-104.839108,38.809836],"type":"Point"}
}