{
  "type": "Feature",
  "properties": {
    "addr:full":"931 14th St Denver CO 80202",
    "addr:housenumber":"931",
    "addr:postcode":"80202",
    "addr:street":"14Th St",
    "iso:country":"US",
    "sg:address":"931 14th St",
    "sg:city":"Denver",
    "sg:classifiers":[
        {
            "category":"Restaurant",
            "type":"Food & Drink"
        }
    ],
    "sg:phone":"+1 303 888 7446",
    "sg:postcode":"80202",
    "sg:province":"CO",
    "sg:tags":[
        "eating"
    ],
    "wof:name":"Caffe Beans",
    "wof:placetype":"venue"
},
  "geometry": {"coordinates":[-104.996889,39.745174],"type":"Point"}
}