{
  "type": "Feature",
  "properties": {
    "iso:country":"US",
    "sg:address":"8435 W Capri Pl",
    "sg:city":"Littleton",
    "sg:classifiers":[
        {
            "category":"Real Estate",
            "subcategory":"Real Estate Agent",
            "type":"Services"
        }
    ],
    "sg:phone":"+1 303 948 8146",
    "sg:postcode":"80123",
    "sg:province":"CO",
    "sg:tags":[
        "inspection"
    ],
    "wof:name":"D P Inspections",
    "wof:placetype":"venue"
},
  "geometry": {"coordinates":[-105.09258,39.607148],"type":"Point"}
}