{
  "type": "Feature",
  "properties": {
    "iso:country":"US",
    "sg:address":"5081 S Florence Dr",
    "sg:city":"Englewood",
    "sg:classifiers":[
        {
            "category":"Real Estate",
            "subcategory":"Real Estate Agent",
            "type":"Services"
        }
    ],
    "sg:phone":"+1 303 771 1611",
    "sg:postcode":"80111",
    "sg:province":"CO",
    "wof:name":"Thomas Real Estate Company",
    "wof:placetype":"venue"
},
  "geometry": {"coordinates":[-104.871951,39.626036],"type":"Point"}
}