{
  "type": "Feature",
  "properties": {
    "addr:full":"4269 N Co Rd 13 Fort Collins CO 80524",
    "addr:housenumber":"4269;13",
    "addr:postcode":"80524",
    "addr:street":"N Co Rd",
    "iso:country":"US",
    "sg:address":"4269 N Co Rd 13",
    "sg:city":"Fort Collins",
    "sg:classifiers":[
        {
            "category":"Retail",
            "subcategory":"Animal Services",
            "type":"Services"
        }
    ],
    "sg:phone":"+1 970 484 9419",
    "sg:postcode":"80524",
    "sg:province":"CO",
    "wof:name":"Bowers Farm Inc",
    "wof:placetype":"venue"
},
  "geometry": {"coordinates":[-105.054807,40.648035],"type":"Point"}
}