{
  "type": "Feature",
  "properties": {
    "iso:country":"US",
    "sg:address":"4361 Loveland St",
    "sg:city":"Golden",
    "sg:classifiers":[
        {
            "category":"Manufacturing",
            "subcategory":"Wood Products",
            "type":"Manufacturing & Wholesale Goods"
        }
    ],
    "sg:phone":"+1 303 215 9441",
    "sg:postcode":"80403",
    "sg:province":"CO",
    "sg:tags":[
        "manufacture",
        "nailed",
        "box",
        "wooden",
        "specializing"
    ],
    "wof:name":"Denver Loveland Drawer Inc",
    "wof:placetype":"venue"
},
  "geometry": {"coordinates":[-105.172211,39.775966],"type":"Point"}
}