{
  "type": "Feature",
  "properties": {
    "addr:full":"3440 Youngfield St Wheat Ridge CO 80033",
    "addr:housenumber":"3440",
    "addr:postcode":"80033",
    "addr:street":"Youngfield St",
    "iso:country":"US",
    "sg:address":"3440 Youngfield St",
    "sg:city":"Wheat Ridge",
    "sg:classifiers":[
        {
            "category":"Building & Trades",
            "subcategory":"Construction",
            "type":"Services"
        }
    ],
    "sg:phone":"+1 303 378 9771",
    "sg:postcode":"80033",
    "sg:province":"CO",
    "wof:name":"Cjw International Inc",
    "wof:placetype":"venue"
},
  "geometry": {"coordinates":[-105.142426,39.76205],"type":"Point"}
}