{
  "type": "Feature",
  "properties": {
    "iso:country":"US",
    "sg:address":"330 W Kellogg St",
    "sg:city":"Holyoke",
    "sg:classifiers":[
        {
            "category":"Health Services",
            "subcategory":"Clinic",
            "type":"Services"
        }
    ],
    "sg:phone":"+1 970 854 3551",
    "sg:postcode":"80734",
    "sg:province":"CO",
    "sg:tags":[
        "home",
        "care"
    ],
    "wof:name":"Colorado Plains Home Health",
    "wof:placetype":"venue"
},
  "geometry": {"coordinates":[-102.305312,40.579515],"type":"Point"}
}