{
  "type": "Feature",
  "properties": {
    "iso:country":"US",
    "sg:address":"289 Main St",
    "sg:city":"Carbondale",
    "sg:classifiers":[
        {
            "category":"Personal",
            "subcategory":"Barber",
            "type":"Services"
        }
    ],
    "sg:phone":"+1 970 963 0293",
    "sg:postcode":"81623",
    "sg:province":"CO",
    "wof:name":"Barber Shoppe",
    "wof:placetype":"venue"
},
  "geometry": {"coordinates":[-107.208788,39.400604],"type":"Point"}
}