{
  "type": "Feature",
  "properties": {
    "addr:full":"201 Broadway Denver CO 80203",
    "addr:housenumber":"201",
    "addr:postcode":"80203",
    "addr:street":"Broadway",
    "iso:country":"US",
    "sg:address":"201 Broadway",
    "sg:city":"Denver",
    "sg:classifiers":[
        {
            "category":"Home & Garden",
            "subcategory":"Furniture",
            "type":"Retail Goods"
        }
    ],
    "sg:phone":"+1 303 777 5900",
    "sg:postcode":"80203",
    "sg:province":"CO",
    "sg:tags":[
        "outdoor"
    ],
    "wof:name":"Broadway Furniture Co Inc",
    "wof:placetype":"venue"
},
  "geometry": {"coordinates":[-104.98745,39.720943],"type":"Point"}
}