{
  "type": "Feature",
  "properties": {
    "addr:full":"6654 Timberline Rd Littleton CO 80130",
    "addr:housenumber":"6654",
    "addr:postcode":"80130",
    "addr:street":"Timberline Rd",
    "iso:country":"US",
    "sg:address":"6654 Timberline Rd",
    "sg:city":"Littleton",
    "sg:classifiers":[
        {
            "category":"Restaurant",
            "type":"Food & Drink"
        }
    ],
    "sg:menulink":"http://www.allmenus.com/co/sedalia/128831-subway/menu/",
    "sg:phone":"+1 720 344 4457",
    "sg:postcode":"80130",
    "sg:province":"CO",
    "sg:tags":[
        "american",
        "sandwich"
    ],
    "wof:name":"Subway",
    "wof:placetype":"venue"
},
  "geometry": {"coordinates":[-104.911371,39.541306],"type":"Point"}
}