{
  "type": "Feature",
  "properties": {
    "iso:country":"US",
    "sg:address":"399 W 11th Ave",
    "sg:city":"Denver",
    "sg:classifiers":[
        {
            "category":"Retail",
            "subcategory":"Auto Repair",
            "type":"Services"
        }
    ],
    "sg:phone":"+1 303 623 1854",
    "sg:postcode":"80204",
    "sg:province":"CO",
    "sg:tags":[
        "automobile"
    ],
    "sg:website":"www.boltscarcare.com",
    "wof:name":"Bolts Quality Car Care Inc",
    "wof:placetype":"venue"
},
  "geometry": {"coordinates":[-104.991649,39.733859],"type":"Point"}
}