{
  "type": "Feature",
  "properties": {
    "addr:full":"229 E Aspen Ave Fruita CO 81521",
    "addr:housenumber":"229",
    "addr:postcode":"81521",
    "addr:street":"E Aspen Ave",
    "iso:country":"US",
    "sg:address":"229 E Aspen Ave",
    "sg:city":"Fruita",
    "sg:classifiers":[
        {
            "category":"Restaurant",
            "type":"Food & Drink"
        }
    ],
    "sg:phone":"+1 970 858 9380",
    "sg:postcode":"81521",
    "sg:province":"CO",
    "wof:name":"Pancho's Villa II",
    "wof:placetype":"venue"
},
  "geometry": {"coordinates":[-108.732181,39.158953],"type":"Point"}
}