{
  "type": "Feature",
  "properties": {
    "addr:full":"5737 Pinon Dr Elizabeth CO 80107",
    "addr:housenumber":"5737",
    "addr:postcode":"80107",
    "addr:street":"Pinon Dr",
    "iso:country":"US",
    "sg:address":"5737 Pinon Dr",
    "sg:city":"Elizabeth",
    "sg:classifiers":[
        {
            "category":"Building & Trades",
            "subcategory":"Construction",
            "type":"Services"
        }
    ],
    "sg:phone":"+1 303 646 5765",
    "sg:postcode":"80107",
    "sg:province":"CO",
    "sg:tags":[
        "floor",
        "laying",
        "contractor"
    ],
    "wof:name":"Chad Privratsky Installation S",
    "wof:placetype":"venue"
},
  "geometry": {"coordinates":[-104.562084,39.370239],"type":"Point"}
}