{
  "type": "Feature",
  "properties": {
    "addr:full":"1400 Fairgrounds Rd Eagle CO 81631",
    "addr:housenumber":"1400",
    "addr:postcode":"81631",
    "addr:street":"Fairgrounds Rd",
    "iso:country":"US",
    "sg:address":"1400 Fairgrounds Rd",
    "sg:city":"Eagle",
    "sg:classifiers":[
        {
            "category":"Government",
            "subcategory":"Office",
            "type":"Public Place"
        }
    ],
    "sg:phone":"+1 970 328 3646",
    "sg:postcode":"81631",
    "sg:province":"CO",
    "wof:name":"Eagle County Fair & Rodeo",
    "wof:placetype":"venue"
},
  "geometry": {"coordinates":[-106.848339,39.652304],"type":"Point"}
}