{
  "type": "Feature",
  "properties": {
    "iso:country":"US",
    "sg:address":"5391 E Kensington Ave",
    "sg:city":"Castle Rock",
    "sg:classifiers":[
        {
            "category":"Wholesale",
            "subcategory":"Hardware",
            "type":"Manufacturing & Wholesale Goods"
        }
    ],
    "sg:phone":"+1 303 738 9360",
    "sg:postcode":"80104",
    "sg:province":"CO",
    "sg:tags":[
        "refrigerating"
    ],
    "wof:name":"Bob Kohler & Co",
    "wof:placetype":"venue"
},
  "geometry": {"coordinates":[-104.807596,39.362782],"type":"Point"}
}