{
  "type": "Feature",
  "properties": {
    "addr:full":"15195 E Hampden Ave Aurora CO 80014",
    "addr:housenumber":"15195",
    "addr:postcode":"80014",
    "addr:street":"E Hampden Ave",
    "iso:country":"US",
    "sg:address":"15195 E Hampden Ave",
    "sg:city":"Aurora",
    "sg:classifiers":[
        {
            "category":"Bakery",
            "type":"Food & Drink"
        }
    ],
    "sg:menulink":"http://www.allmenus.com/co/south-aurora/239507-winchells-doughnut-house/menu/",
    "sg:phone":"+1 303 693 3164",
    "sg:postcode":"80014",
    "sg:province":"CO",
    "sg:tags":[
        "smoothy",
        "juice",
        "american",
        "pastry"
    ],
    "wof:name":"Winchell's Doughnut House",
    "wof:placetype":"venue"
},
  "geometry": {"coordinates":[-104.811198,39.653145],"type":"Point"}
}