{
  "type": "Feature",
  "properties": {
    "addr:full":"5840 E Evans Ave Denver CO 80222",
    "addr:housenumber":"5840",
    "addr:postcode":"80222",
    "addr:street":"E Evans Ave",
    "iso:country":"US",
    "sg:address":"5840 E Evans Ave",
    "sg:city":"Denver",
    "sg:classifiers":[
        {
            "category":"Building & Trades",
            "subcategory":"Construction",
            "type":"Services"
        }
    ],
    "sg:phone":"+1 720 524 0840",
    "sg:postcode":"80222",
    "sg:province":"CO",
    "sg:tags":[
        "home",
        "improvement"
    ],
    "sg:website":"www.rebuildingdenver.org",
    "wof:name":"Rebuilding Together Metro",
    "wof:placetype":"venue"
},
  "geometry": {"coordinates":[-104.91902899999999,39.678379],"type":"Point"}
}