{
  "type": "Feature",
  "properties": {
    "iso:country":"US",
    "sg:address":"2524 S Prairie Ave",
    "sg:city":"Pueblo",
    "sg:classifiers":[
        {
            "category":"Building & Trades",
            "subcategory":"Construction",
            "type":"Services"
        }
    ],
    "sg:phone":"+1 719 564 2299",
    "sg:postcode":"81005",
    "sg:province":"CO",
    "sg:tags":[
        "contractor"
    ],
    "wof:name":"All Star Roofing & Gutters",
    "wof:placetype":"venue"
},
  "geometry": {"coordinates":[-104.64351499999999,38.22587],"type":"Point"}
}