{
  "type": "Feature",
  "properties": {
    "addr:full":"202 W Laurel St Fort Collins CO 80521",
    "addr:housenumber":"202",
    "addr:postcode":"80521",
    "addr:street":"W Laurel St",
    "iso:country":"US",
    "sg:address":"202 W Laurel St",
    "sg:city":"Fort Collins",
    "sg:classifiers":[
        {
            "category":"Shopping",
            "subcategory":"Bicycles & Sporting Goods",
            "type":"Retail Goods"
        }
    ],
    "sg:phone":"+1 970 482 6006",
    "sg:postcode":"80521",
    "sg:province":"CO",
    "sg:website":"www.leescyclery.com",
    "wof:name":"Lee's Cyclery",
    "wof:placetype":"venue"
},
  "geometry": {"coordinates":[-105.079373,40.578186],"type":"Point"}
}