{
  "type": "Feature",
  "properties": {
    "addr:full":"309 E New York Ave Gunnison CO 81230",
    "addr:housenumber":"309",
    "addr:postcode":"81230",
    "addr:street":"E New York Ave",
    "iso:country":"US",
    "sg:address":"309 E New York Ave",
    "sg:city":"Gunnison",
    "sg:classifiers":[
        {
            "category":"Health Services",
            "subcategory":"Chiropractor",
            "type":"Services"
        }
    ],
    "sg:phone":"+1 970 641 2525",
    "sg:postcode":"81230",
    "sg:province":"CO",
    "wof:name":"Gunnison Chiropractic Office",
    "wof:placetype":"venue"
},
  "geometry": {"coordinates":[-106.924277,38.543203],"type":"Point"}
}