{
  "type": "Feature",
  "properties": {
    "addr:full":"7460 Hwy 86 Kiowa CO 80117",
    "addr:housenumber":"7460",
    "addr:postcode":"80117",
    "addr:street":"Hwy 86",
    "iso:country":"US",
    "sg:address":"7460 Hwy 86",
    "sg:city":"Kiowa",
    "sg:classifiers":[
        {
            "category":"Wholesale",
            "subcategory":"Machinery & Supplies",
            "type":"Manufacturing & Wholesale Goods"
        }
    ],
    "sg:phone":"+1 303 688 3151",
    "sg:postcode":"80117",
    "sg:province":"CO",
    "sg:tags":[
        "tractor"
    ],
    "wof:name":"Stephen Equipment Co",
    "wof:placetype":"venue"
},
  "geometry": {"coordinates":[-104.526056,39.357051],"type":"Point"}
}