{
  "type": "Feature",
  "properties": {
    "addr:full":"405 Scranton Ave Pueblo CO 81004",
    "addr:housenumber":"405",
    "addr:postcode":"81004",
    "addr:street":"Scranton Ave",
    "iso:country":"US",
    "sg:address":"405 Scranton Ave",
    "sg:city":"Pueblo",
    "sg:classifiers":[
        {
            "category":"Home & Garden",
            "subcategory":"Building Materials",
            "type":"Retail Goods"
        }
    ],
    "sg:phone":"+1 719 240 1603",
    "sg:postcode":"81004",
    "sg:province":"CO",
    "wof:name":"Glass On Time",
    "wof:placetype":"venue"
},
  "geometry": {"coordinates":[-104.64056600000001,38.258631],"type":"Point"}
}