{
  "type": "Feature",
  "properties": {
    "iso:country":"US",
    "sg:address":"130 N Tejon St",
    "sg:city":"Colorado Springs",
    "sg:classifiers":[
        {
            "category":"Shopping",
            "subcategory":"Gifts & Souvenirs",
            "type":"Retail Goods"
        },
        {
            "category":"Shopping",
            "subcategory":"Clothing, Apparel, & Fashions",
            "type":"Retail Goods"
        }
    ],
    "sg:phone":"+1 719 635 2705",
    "sg:postcode":"80903",
    "sg:province":"CO",
    "sg:tags":[
        "shop",
        "home",
        "jewelry",
        "furnishing"
    ],
    "wof:name":"Wild At Heart Ltd",
    "wof:placetype":"venue"
},
  "geometry": {"coordinates":[-104.82345100000001,38.836262],"type":"Point"}
}