{
  "type": "Feature",
  "properties": {
    "addr:full":"260 Beaver Creek Pl Avon CO 81620",
    "addr:housenumber":"260",
    "addr:postcode":"81620",
    "addr:street":"Beaver Creek Pl",
    "iso:country":"US",
    "sg:address":"260 Beaver Creek Pl",
    "sg:city":"Avon",
    "sg:classifiers":[
        {
            "category":"Shopping",
            "subcategory":"Jewelry",
            "type":"Retail Goods"
        }
    ],
    "sg:phone":"+1 970 949 0539",
    "sg:postcode":"81620",
    "sg:province":"CO",
    "sg:tags":[
        "jeweler"
    ],
    "wof:name":"Alpen Gold Studio",
    "wof:placetype":"venue"
},
  "geometry": {"coordinates":[-106.519273,39.633841],"type":"Point"}
}