{
  "type": "Feature",
  "properties": {
    "iso:country":"US",
    "sg:address":"1360 Aviation Way",
    "sg:city":"Colorado Springs",
    "sg:classifiers":[
        {
            "category":"Building & Trades",
            "subcategory":"Equipment Rental",
            "type":"Services"
        }
    ],
    "sg:phone":"+1 719 351 8072",
    "sg:postcode":"80916",
    "sg:province":"CO",
    "sg:tags":[
        "aircraft",
        "leasing",
        "charter"
    ],
    "wof:name":"Integrity Air",
    "wof:placetype":"venue"
},
  "geometry": {"coordinates":[-104.72375,38.810503],"type":"Point"}
}