{
  "type": "Feature",
  "properties": {
    "addr:full":"15201 E Moncrieff Pl Aurora CO 80011",
    "addr:housenumber":"15201",
    "addr:postcode":"80011",
    "addr:street":"E Moncrieff Pl",
    "iso:country":"US",
    "sg:address":"15201 E Moncrieff Pl",
    "sg:city":"Aurora",
    "sg:classifiers":[
        {
            "category":"Manufacturing",
            "subcategory":"Tools & Machinery",
            "type":"Manufacturing & Wholesale Goods"
        }
    ],
    "sg:phone":"+1 303 373 9440",
    "sg:postcode":"80011",
    "sg:province":"CO",
    "sg:tags":[
        "machine",
        "mfg"
    ],
    "wof:name":"General Binding Corporation",
    "wof:placetype":"venue"
},
  "geometry": {"coordinates":[-104.81183799999999,39.762644],"type":"Point"}
}