{
  "type": "Feature",
  "properties": {
    "iso:country":"US",
    "sg:address":"200 W Foothills Pkwy",
    "sg:city":"Fort Collins",
    "sg:classifiers":[
        {
            "category":"Food & Beverages",
            "subcategory":"Specialty",
            "type":"Retail Goods"
        }
    ],
    "sg:phone":"+1 970 225 1400",
    "sg:postcode":"80525",
    "sg:province":"CO",
    "sg:tags":[
        "health",
        "diet"
    ],
    "sg:website":"www.wildoats.com",
    "wof:name":"Wild Oats",
    "wof:placetype":"venue"
},
  "geometry": {"coordinates":[-105.078164,40.543231],"type":"Point"}
}