{
  "type": "Feature",
  "properties": {
    "iso:country":"US",
    "sg:address":"1517 S Lemay Ave",
    "sg:city":"Fort Collins",
    "sg:classifiers":[
        {
            "category":"Professional",
            "subcategory":"Management & Consulting",
            "type":"Services"
        }
    ],
    "sg:phone":"+1 970 416 8985",
    "sg:postcode":"80524",
    "sg:province":"CO",
    "sg:tags":[
        "consultant"
    ],
    "wof:name":"Paragon Consulting Group",
    "wof:placetype":"venue"
},
  "geometry": {"coordinates":[-105.058003,40.568001],"type":"Point"}
}