{
  "type": "Feature",
  "properties": {
    "iso:country":"US",
    "sg:address":"319 Alpert Ave",
    "sg:city":"Fort Collins",
    "sg:classifiers":[
        {
            "category":"Manufacturing",
            "subcategory":"Lumber",
            "type":"Manufacturing & Wholesale Goods"
        }
    ],
    "sg:phone":"+1 970 498 9135",
    "sg:postcode":"80525",
    "sg:province":"CO",
    "sg:tags":[
        "forestry"
    ],
    "wof:name":"Carrie Hirod",
    "wof:placetype":"venue"
},
  "geometry": {"coordinates":[-105.07245,40.564284],"type":"Point"}
}