{
  "type": "Feature",
  "properties": {
    "addr:full":"1350 Grant St Denver CO 80203",
    "addr:housenumber":"1350",
    "addr:postcode":"80203",
    "addr:street":"Grant St",
    "iso:country":"US",
    "sg:address":"1350 Grant St",
    "sg:city":"Denver",
    "sg:classifiers":[
        {
            "category":"Wholesale",
            "subcategory":"Construction Materials",
            "type":"Manufacturing & Wholesale Goods"
        },
        {
            "category":"Building & Trades",
            "subcategory":"Construction",
            "type":"Services"
        }
    ],
    "sg:phone":"+1 303 440 7080",
    "sg:postcode":"80203",
    "sg:province":"CO",
    "sg:tags":[
        "fence"
    ],
    "wof:name":"Front Range Enterprises",
    "wof:placetype":"venue"
},
  "geometry": {"coordinates":[-104.98353,39.73762],"type":"Point"}
}