{
  "type": "Feature",
  "properties": {
    "addr:full":"505 E 4th St Loveland CO 80537",
    "addr:housenumber":"505",
    "addr:postcode":"80537",
    "addr:street":"E 4Th St",
    "iso:country":"US",
    "sg:address":"505 E 4th St",
    "sg:city":"Loveland",
    "sg:classifiers":[
        {
            "category":"Real Estate",
            "subcategory":"Real Estate Agent",
            "type":"Services"
        }
    ],
    "sg:phone":"+1 970 663 4212",
    "sg:postcode":"80537",
    "sg:province":"CO",
    "wof:name":"Jarna Culp & Assoc",
    "wof:placetype":"venue"
},
  "geometry": {"coordinates":[-105.070548,40.39548],"type":"Point"}
}