{
  "type": "Feature",
  "properties": {
    "addr:full":"85 Castle Dr Guffey CO 80820",
    "addr:housenumber":"85",
    "addr:postcode":"80820",
    "addr:street":"Castle Dr",
    "iso:country":"US",
    "sg:address":"85 Castle Dr",
    "sg:city":"Guffey",
    "sg:classifiers":[
        {
            "category":"Building & Trades",
            "subcategory":"Construction",
            "type":"Services"
        }
    ],
    "sg:phone":"+1 719 689 0844",
    "sg:postcode":"80820",
    "sg:province":"CO",
    "sg:tags":[
        "house"
    ],
    "wof:name":"Lee Construction Company Inc",
    "wof:placetype":"venue"
},
  "geometry": {"coordinates":[-105.434408,38.784171],"type":"Point"}
}