{
  "type": "Feature",
  "properties": {
    "addr:full":"1401 Sheridan Boulevard Lakewood CO 80214",
    "addr:housenumber":"1401",
    "addr:postcode":"80214",
    "addr:street":"Sheridan Boulevard",
    "iso:country":"US",
    "sg:address":"1401 Sheridan Boulevard",
    "sg:city":"Lakewood",
    "sg:classifiers":[
        {
            "category":"Autos & Motor Vehicles",
            "subcategory":"Fuel & Gas Station",
            "type":"Retail Goods"
        },
        {
            "category":"Food & Beverages",
            "subcategory":"Groceries & Convenience Stores",
            "type":"Retail Goods"
        }
    ],
    "sg:phone":"+1 303 462 1253",
    "sg:postcode":"80214",
    "sg:province":"CO",
    "wof:name":"1st Stop",
    "wof:placetype":"venue"
},
  "geometry": {"coordinates":[-105.053344,39.739186],"type":"Point"}
}