{
  "type": "Feature",
  "properties": {
    "addr:full":"14520 Co Rd 64 Greeley CO 80631",
    "addr:housenumber":"14520;64",
    "addr:postcode":"80631",
    "addr:street":"Co Rd",
    "iso:country":"US",
    "sg:address":"14520 Co Rd 64",
    "sg:city":"Greeley",
    "sg:classifiers":[
        {
            "category":"Manufacturing",
            "subcategory":"Chemicals & Compounds",
            "type":"Manufacturing & Wholesale Goods"
        }
    ],
    "sg:phone":"+1 970 356 8920",
    "sg:postcode":"80631",
    "sg:province":"CO",
    "sg:tags":[
        "pesticide",
        "ag"
    ],
    "sg:website":"www.uap.com",
    "wof:name":"Loveland Industries",
    "wof:placetype":"venue"
},
  "geometry": {"coordinates":[-104.781893,40.451998],"type":"Point"}
}