{
  "type": "Feature",
  "properties": {
    "iso:country":"US",
    "sg:address":"2054 W 17th St",
    "sg:city":"Loveland",
    "sg:classifiers":[
        {
            "category":"Building & Trades",
            "subcategory":"Cleaning & Sanitation",
            "type":"Services"
        }
    ],
    "sg:phone":"+1 970 667 1545",
    "sg:postcode":"80538",
    "sg:province":"CO",
    "sg:tags":[
        "house"
    ],
    "wof:name":"Maid In The USA",
    "wof:placetype":"venue"
},
  "geometry": {"coordinates":[-105.10444699999999,40.409641],"type":"Point"}
}