{
  "type": "Feature",
  "properties": {
    "iso:country":"US",
    "sg:address":"545 S Sherman St",
    "sg:city":"Denver",
    "sg:classifiers":[
        {
            "category":"Freight",
            "type":"Transportation"
        }
    ],
    "sg:phone":"+1 303 722 4777",
    "sg:postcode":"80209",
    "sg:province":"CO",
    "sg:tags":[
        "trucking"
    ],
    "wof:name":"Stanley Co Trucking",
    "wof:placetype":"venue"
},
  "geometry": {"coordinates":[-104.985223,39.706517],"type":"Point"}
}