{
  "type": "Feature",
  "properties": {
    "iso:country":"US",
    "sg:address":"2 Broadway",
    "sg:city":"Denver",
    "sg:classifiers":[
        {
            "category":"Personal",
            "subcategory":"Tattoo Parlor",
            "type":"Services"
        },
        {
            "category":"Personal",
            "subcategory":"Piercing",
            "type":"Services"
        }
    ],
    "sg:phone":"+1 303 765 5500",
    "sg:postcode":"80203",
    "sg:province":"CO",
    "wof:name":"Freaky's Tattoo and Body Piercing",
    "wof:placetype":"venue"
},
  "geometry": {"coordinates":[-104.987396,39.716656],"type":"Point"}
}