{
  "type": "Feature",
  "properties": {
    "addr:full":"5403 Hwy 86 Elizabeth CO 80107",
    "addr:housenumber":"5403",
    "addr:postcode":"80107",
    "addr:street":"Hwy 86",
    "iso:country":"US",
    "sg:address":"5403 Hwy 86",
    "sg:city":"Elizabeth",
    "sg:classifiers":[
        {
            "category":"Personal",
            "subcategory":"Beauty Salon",
            "type":"Services"
        }
    ],
    "sg:phone":"+1 303 646 3535",
    "sg:postcode":"80107",
    "sg:province":"CO",
    "wof:name":"Bella Visage Salon & Day Spa",
    "wof:placetype":"venue"
},
  "geometry": {"coordinates":[-104.565619,39.361266],"type":"Point"}
}