{
  "type": "Feature",
  "properties": {
    "addr:full":"4794 Eugene Way Denver CO 80239",
    "addr:housenumber":"4794",
    "addr:postcode":"80239",
    "addr:street":"Eugene Way",
    "iso:country":"US",
    "sg:address":"4794 Eugene Way",
    "sg:city":"Denver",
    "sg:classifiers":[
        {
            "category":"Banks & Credit Unions",
            "subcategory":"Investment Brokerage",
            "type":"Services"
        }
    ],
    "sg:phone":"+1 720 374 0906",
    "sg:postcode":"80239",
    "sg:province":"CO",
    "sg:tags":[
        "advisory",
        "financial"
    ],
    "wof:name":"T-3 Financial Svc",
    "wof:placetype":"venue"
},
  "geometry": {"coordinates":[-104.816266,39.780527],"type":"Point"}
}