{
  "type": "Feature",
  "properties": {
    "iso:country":"US",
    "sg:address":"10530 Ute Pass Ave",
    "sg:city":"Green Mountain Falls",
    "sg:classifiers":[
        {
            "category":"Bars & Pubs",
            "subcategory":"Nightclub",
            "type":"Food & Drink"
        }
    ],
    "sg:phone":"+1 719 684 2555",
    "sg:postcode":"80819",
    "sg:province":"CO",
    "sg:tags":[
        "nightlife"
    ],
    "wof:name":"Pine Gables Pub",
    "wof:placetype":"venue"
},
  "geometry": {"coordinates":[-105.015999,38.934799],"type":"Point"}
}