{
  "type": "Feature",
  "properties": {
    "iso:country":"US",
    "sg:address":"3023 N Hancock Ave",
    "sg:city":"Colorado Springs",
    "sg:classifiers":[
        {
            "category":"Autos & Motor Vehicles",
            "subcategory":"Automobile Sales",
            "type":"Retail Goods"
        }
    ],
    "sg:phone":"+1 719 632 3558",
    "sg:postcode":"80907",
    "sg:province":"CO",
    "sg:tags":[
        "car",
        "dealer"
    ],
    "wof:name":"Universe Auto",
    "wof:placetype":"venue"
},
  "geometry": {"coordinates":[-104.80341,38.874458],"type":"Point"}
}