{
  "type": "Feature",
  "properties": {
    "iso:country":"US",
    "sg:address":"14 Inverness Dr E",
    "sg:city":"Englewood",
    "sg:classifiers":[
        {
            "category":"Professional",
            "type":"Services"
        },
        {
            "category":"Manufacturing",
            "subcategory":"Printing",
            "type":"Manufacturing & Wholesale Goods"
        }
    ],
    "sg:phone":"+1 303 662 8165",
    "sg:postcode":"80112",
    "sg:province":"CO",
    "sg:tags":[
        "publisher",
        "guide"
    ],
    "wof:name":"National Directory of Children",
    "wof:placetype":"venue"
},
  "geometry": {"coordinates":[-104.86219699999999,39.566915],"type":"Point"}
}