{
  "type": "Feature",
  "properties": {
    "iso:country":"US",
    "sg:address":"16822 E Easter Way",
    "sg:city":"Aurora",
    "sg:classifiers":[
        {
            "category":"Professional",
            "type":"Services"
        }
    ],
    "sg:phone":"+1 303 680 0163",
    "sg:postcode":"80016",
    "sg:province":"CO",
    "wof:name":"Applique Society",
    "wof:placetype":"venue"
},
  "geometry": {"coordinates":[-104.793887,39.584654],"type":"Point"}
}