{
  "type": "Feature",
  "properties": {
    "iso:country":"US",
    "sg:address":"2575 Westen Rd",
    "sg:city":"Colorado Springs",
    "sg:classifiers":[
        {
            "category":"Professional",
            "subcategory":"Engineering",
            "type":"Services"
        }
    ],
    "sg:phone":"+1 719 392 8819",
    "sg:postcode":"80910",
    "sg:province":"CO",
    "sg:tags":[
        "engineer"
    ],
    "wof:name":"Titan Corp",
    "wof:placetype":"venue"
},
  "geometry": {"coordinates":[-104.777513,38.795547],"type":"Point"}
}