{
  "type": "Feature",
  "properties": {
    "addr:full":"7711 Academy Blvd Denver CO 80230",
    "addr:housenumber":"7711",
    "addr:postcode":"80230",
    "addr:street":"Academy Blvd",
    "iso:country":"US",
    "sg:address":"7711 Academy Blvd",
    "sg:city":"Denver",
    "sg:classifiers":[
        {
            "category":"Museum",
            "type":"Entertainment"
        }
    ],
    "sg:phone":"+1 303 344 9331",
    "sg:postcode":"80230",
    "sg:province":"CO",
    "wof:name":"Fantasy Of Flight Foundation",
    "wof:placetype":"venue"
},
  "geometry": {"coordinates":[-104.8972,39.718955],"type":"Point"}
}