{
  "type": "Feature",
  "properties": {
    "iso:country":"US",
    "sg:address":"1250 Newport Street",
    "sg:city":"Denver",
    "sg:classifiers":[
        {
            "category":"Education",
            "subcategory":"School",
            "type":"Public Place"
        },
        {
            "category":"Organizations",
            "subcategory":"Religious Organization",
            "type":"Services"
        }
    ],
    "sg:phone":"+1 303 333 8275",
    "sg:postcode":"80220",
    "sg:province":"CO",
    "sg:tags":[
        "high",
        "middle",
        "elementary"
    ],
    "wof:name":"Schools-Parochial",
    "wof:placetype":"venue"
},
  "geometry": {"coordinates":[-104.909217,39.736356],"type":"Point"}
}