{
  "type": "Feature",
  "properties": {
    "iso:country":"US",
    "sg:address":"6512 S Broadway",
    "sg:city":"Littleton",
    "sg:classifiers":[
        {
            "category":"Shopping",
            "subcategory":"Computers & Home Electronics",
            "type":"Retail Goods"
        }
    ],
    "sg:phone":"+1 303 794 3237",
    "sg:postcode":"80121",
    "sg:province":"CO",
    "sg:tags":[
        "television",
        "radio"
    ],
    "wof:name":"Bosley's TV",
    "wof:placetype":"venue"
},
  "geometry": {"coordinates":[-104.98811600000001,39.601171],"type":"Point"}
}