{
  "type": "Feature",
  "properties": {
    "iso:country":"US",
    "sg:address":"1314 Pecan St",
    "sg:city":"Colorado Springs",
    "sg:classifiers":[
        {
            "category":"Freight",
            "type":"Transportation"
        }
    ],
    "sg:phone":"+1 719 577 9780",
    "sg:postcode":"80904",
    "sg:province":"CO",
    "sg:tags":[
        "hauling",
        "trucking"
    ],
    "wof:name":"Specialty Transport",
    "wof:placetype":"venue"
},
  "geometry": {"coordinates":[-104.860529,38.833239],"type":"Point"}
}