{
  "type": "Feature",
  "properties": {
    "addr:full":"820 Latigo Loop Carbondale CO 81623",
    "addr:housenumber":"820",
    "addr:postcode":"81623",
    "addr:street":"Latigo Loop",
    "iso:country":"US",
    "sg:address":"820 Latigo Loop",
    "sg:city":"Carbondale",
    "sg:classifiers":[
        {
            "category":"Building & Trades",
            "subcategory":"Construction",
            "type":"Services"
        }
    ],
    "sg:phone":"+1 970 963 8514",
    "sg:postcode":"81623",
    "sg:province":"CO",
    "sg:tags":[
        "carpentry",
        "contractor"
    ],
    "wof:name":"Insight Construction",
    "wof:placetype":"venue"
},
  "geometry": {"coordinates":[-107.218,39.411901],"type":"Point"}
}