{
  "type": "Feature",
  "properties": {
    "iso:country":"US",
    "sg:address":"12307 E Tennessee Dr",
    "sg:city":"Aurora",
    "sg:classifiers":[
        {
            "category":"Shopping",
            "subcategory":"Computers & Home Electronics",
            "type":"Retail Goods"
        }
    ],
    "sg:phone":"+1 720 351 9269",
    "sg:postcode":"80012",
    "sg:province":"CO",
    "sg:tags":[
        "equipment",
        "dealer"
    ],
    "sg:website":"www.tastycomputers.com",
    "wof:name":"TASTYCOMPUTERS.COM",
    "wof:placetype":"venue"
},
  "geometry": {"coordinates":[-104.845259,39.698396],"type":"Point"}
}