{
  "type": "Feature",
  "properties": {
    "addr:full":"17678 Co Rd 24 Dolores CO 81323",
    "addr:housenumber":"17678;24",
    "addr:postcode":"81323",
    "addr:street":"Co Rd",
    "iso:country":"US",
    "sg:address":"17678 Co Rd 24",
    "sg:city":"Dolores",
    "sg:classifiers":[
        {
            "category":"Food & Beverages",
            "subcategory":"Specialty",
            "type":"Retail Goods"
        }
    ],
    "sg:phone":"+1 970 882 7310",
    "sg:postcode":"81323",
    "sg:province":"CO",
    "wof:name":"Herbal Fantasy",
    "wof:placetype":"venue"
},
  "geometry": {"coordinates":[-108.609869,37.465927],"type":"Point"}
}