{
  "type": "Feature",
  "properties": {
    "addr:full":"721 E 2nd Ave Durango CO 81301",
    "addr:housenumber":"721",
    "addr:postcode":"co 81301",
    "addr:street":"E 2Nd Ave",
    "iso:country":"US",
    "sg:address":"721 E 2nd Ave",
    "sg:city":"Durango",
    "sg:classifiers":[
        {
            "category":"Travel",
            "subcategory":"Hotels & Motels",
            "type":"Entertainment"
        }
    ],
    "sg:phone":"+1 970 385 1920",
    "sg:postcode":"81301",
    "sg:province":"CO",
    "sg:tags":[
        "breakfast",
        "bed"
    ],
    "wof:name":"Leland House",
    "wof:placetype":"venue"
},
  "geometry": {"coordinates":[-107.879874,37.271836],"type":"Point"}
}