{
  "type": "Feature",
  "properties": {
    "addr:full":"6700 S Colorado Blvd Centennial CO 80122",
    "addr:housenumber":"6700",
    "addr:postcode":"80122",
    "addr:street":"S Colorado Blvd",
    "iso:country":"US",
    "sg:address":"6700 S Colorado Blvd",
    "sg:city":"Centennial",
    "sg:classifiers":[
        {
            "category":"Organizations",
            "subcategory":"Religious Organization",
            "type":"Services"
        }
    ],
    "sg:phone":"+1 303 771 1443",
    "sg:postcode":"80122",
    "sg:province":"CO",
    "sg:tags":[
        "church"
    ],
    "sg:website":"www.faithcf.org",
    "wof:name":"Faith Community Fellowship",
    "wof:placetype":"venue"
},
  "geometry": {"coordinates":[-104.941407,39.593813],"type":"Point"}
}