{
  "type": "Feature",
  "properties": {
    "iso:country":"US",
    "sg:address":"6872 S Clermont Dr",
    "sg:city":"Centennial",
    "sg:classifiers":[
        {
            "category":"Professional",
            "subcategory":"Management & Consulting",
            "type":"Services"
        },
        {
            "category":"Manufacturing",
            "subcategory":"Printing",
            "type":"Manufacturing & Wholesale Goods"
        }
    ],
    "sg:phone":"+1 303 220 9406",
    "sg:postcode":"80122",
    "sg:province":"CO",
    "sg:tags":[
        "publishes",
        "relations",
        "advertising",
        "directory",
        "counselor",
        "public"
    ],
    "sg:website":"www.denvermediadirectory.com",
    "wof:name":"Kelly Communications",
    "wof:placetype":"venue"
},
  "geometry": {"coordinates":[-104.93373800000001,39.591606],"type":"Point"}
}