{
  "type": "Feature",
  "properties": {
    "iso:country":"US",
    "sg:address":"6453 Omaha Blvd",
    "sg:city":"Colorado Springs",
    "sg:classifiers":[
        {
            "category":"Personal",
            "type":"Services"
        }
    ],
    "sg:phone":"+1 719 572 6906",
    "sg:postcode":"80915",
    "sg:province":"CO",
    "sg:tags":[
        "therapist",
        "massage"
    ],
    "wof:name":"Omaha Oriental Therapy Massage",
    "wof:placetype":"venue"
},
  "geometry": {"coordinates":[-104.707792,38.853405],"type":"Point"}
}