{
  "type": "Feature",
  "properties": {
    "iso:country":"US",
    "sg:address":"895 S Monaco Pkwy",
    "sg:city":"Denver",
    "sg:classifiers":[
        {
            "category":"Health Services",
            "subcategory":"Nursing And Care Facility",
            "type":"Services"
        }
    ],
    "sg:phone":"+1 303 321 3110",
    "sg:postcode":"80224",
    "sg:province":"CO",
    "sg:tags":[
        "home",
        "convalescent"
    ],
    "wof:name":"Mariner Health Care Inc",
    "wof:placetype":"venue"
},
  "geometry": {"coordinates":[-104.912814,39.700959],"type":"Point"}
}