{
  "type": "Feature",
  "properties": {
    "addr:full":"8864 Wagner St Westminster CO 80031",
    "addr:housenumber":"8864",
    "addr:postcode":"80031",
    "addr:street":"Wagner St",
    "iso:country":"US",
    "sg:address":"8864 Wagner St",
    "sg:city":"Westminster",
    "sg:classifiers":[
        {
            "category":"Building & Trades",
            "subcategory":"Plumbing",
            "type":"Services"
        }
    ],
    "sg:phone":"+1 720 333 6095",
    "sg:postcode":"80031",
    "sg:province":"CO",
    "sg:tags":[
        "contractor"
    ],
    "wof:name":"Pvcs Plumbing",
    "wof:placetype":"venue"
},
  "geometry": {"coordinates":[-105.047864,39.857038],"type":"Point"}
}