{
  "type": "Feature",
  "properties": {
    "iso:country":"US",
    "sg:address":"2275 E Arapahoe Rd",
    "sg:city":"Centennial",
    "sg:classifiers":[
        {
            "category":"Health Services",
            "subcategory":"Chiropractor",
            "type":"Services"
        }
    ],
    "sg:phone":"+1 303 347 1502",
    "sg:postcode":"80122",
    "sg:province":"CO",
    "wof:name":"Carolyn Groff DC",
    "wof:placetype":"venue"
},
  "geometry": {"coordinates":[-104.96159,39.595249],"type":"Point"}
}