{
  "type": "Feature",
  "properties": {
    "iso:country":"US",
    "sg:address":"4445 Seesaw Cir",
    "sg:city":"Colorado Springs",
    "sg:classifiers":[
        {
            "category":"Real Estate",
            "subcategory":"Real Estate Operator",
            "type":"Services"
        }
    ],
    "sg:phone":"+1 719 574 6224",
    "sg:postcode":"80917",
    "sg:province":"CO",
    "sg:tags":[
        "building",
        "nonresidential"
    ],
    "wof:name":"Guthals Properties LLC",
    "wof:placetype":"venue"
},
  "geometry": {"coordinates":[-104.745518,38.880688],"type":"Point"}
}