{
  "type": "Feature",
  "properties": {
    "iso:country":"US",
    "sg:address":"125 N Troy Hill Rd",
    "sg:city":"Colorado Springs",
    "sg:classifiers":[
        {
            "category":"Manufacturing",
            "subcategory":"Metals",
            "type":"Manufacturing & Wholesale Goods"
        }
    ],
    "sg:phone":"+1 719 574 1282",
    "sg:postcode":"80916",
    "sg:province":"CO",
    "sg:tags":[
        "building",
        "storage",
        "container",
        "portable",
        "mfg"
    ],
    "wof:name":"Mobile Mini Inc",
    "wof:placetype":"venue"
},
  "geometry": {"coordinates":[-104.724637,38.834299],"type":"Point"}
}