{
  "type": "Feature",
  "properties": {
    "addr:full":"4063 Co Rd 6 Erie CO 80516",
    "addr:housenumber":"4063",
    "addr:postcode":"80516",
    "addr:street":"Co Rd 6",
    "iso:country":"US",
    "sg:address":"4063 Co Rd 6",
    "sg:city":"Erie",
    "sg:classifiers":[
        {
            "category":"Manufacturing",
            "subcategory":"Metals",
            "type":"Manufacturing & Wholesale Goods"
        },
        {
            "category":"Manufacturing",
            "subcategory":"Tools & Machinery",
            "type":"Manufacturing & Wholesale Goods"
        }
    ],
    "sg:phone":"+1 303 828 9074",
    "sg:postcode":"80516",
    "sg:province":"CO",
    "sg:tags":[
        "machine",
        "shop"
    ],
    "wof:name":"Thompson Machining",
    "wof:placetype":"venue"
},
  "geometry": {"coordinates":[-104.975094,40.030648],"type":"Point"}
}