{
  "type": "Feature",
  "properties": {
    "addr:full":"5719 Constitution Ave Colorado Springs CO 80915",
    "addr:housenumber":"5719",
    "addr:postcode":"80915",
    "addr:street":"Constitution Ave",
    "iso:country":"US",
    "sg:address":"5719 Constitution Ave",
    "sg:city":"Colorado Springs",
    "sg:classifiers":[
        {
            "category":"Professional",
            "subcategory":"Management & Consulting",
            "type":"Services"
        }
    ],
    "sg:phone":"+1 719 574 4111",
    "sg:postcode":"80915",
    "sg:province":"CO",
    "sg:tags":[
        "physical",
        "fitness"
    ],
    "wof:name":"Curves For Women",
    "wof:placetype":"venue"
},
  "geometry": {"coordinates":[-104.72226499999999,38.871595],"type":"Point"}
}