{
  "type": "Feature",
  "properties": {
    "addr:full":"102 Rubey Dr Golden CO 80403",
    "addr:housenumber":"102",
    "addr:postcode":"80403",
    "addr:street":"Rubey Dr",
    "iso:country":"US",
    "sg:address":"102 Rubey Dr",
    "sg:city":"Golden",
    "sg:classifiers":[
        {
            "category":"Deli",
            "type":"Food & Drink"
        }
    ],
    "sg:menulink":"http://www.allmenus.com/co/golden/125959-blimpie-subs--sandwiches/menu/",
    "sg:phone":"+1 303 215 0883",
    "sg:postcode":"80403",
    "sg:province":"CO",
    "sg:tags":[
        "wrap",
        "american",
        "sandwich"
    ],
    "wof:name":"Blimpie Subs & Sandwiches",
    "wof:placetype":"venue"
},
  "geometry": {"coordinates":[-105.232091,39.764422],"type":"Point"}
}