{
  "type": "Feature",
  "properties": {
    "addr:full":"815 E 17th Ave Longmont CO 80501",
    "addr:housenumber":"815",
    "addr:postcode":"80501",
    "addr:street":"E 17Th Ave",
    "iso:country":"US",
    "sg:address":"815 E 17th Ave",
    "sg:city":"Longmont",
    "sg:classifiers":[
        {
            "category":"Coffee & Tea",
            "type":"Food & Drink"
        }
    ],
    "sg:menulink":"http://www.allmenus.com/co/longmont/118317-starbucks-coffee/menu/",
    "sg:phone":"+1 720 494 9794",
    "sg:postcode":"80501",
    "sg:province":"CO",
    "sg:tags":[
        "american"
    ],
    "wof:name":"Starbucks Coffee",
    "wof:placetype":"venue"
},
  "geometry": {"coordinates":[-105.077639,40.188705],"type":"Point"}
}