{
  "type": "Feature",
  "properties": {
    "iso:country":"US",
    "sg:address":"818 S Dexter Street Apt 101",
    "sg:city":"Denver",
    "sg:classifiers":[
        {
            "category":"Real Estate",
            "subcategory":"Real Estate Operator",
            "type":"Services"
        }
    ],
    "sg:phone":"+1 303 759 1851",
    "sg:postcode":"80246",
    "sg:province":"CO",
    "sg:tags":[
        "apartment"
    ],
    "sg:website":"www.bluelineprop.com",
    "wof:name":"Cherry Creek Place",
    "wof:placetype":"venue"
},
  "geometry": {"coordinates":[-104.932248,39.701635],"type":"Point"}
}