{
  "type": "Feature",
  "properties": {
    "iso:country":"US",
    "sg:address":"304 Main St",
    "sg:city":"Breckenridge",
    "sg:classifiers":[
        {
            "category":"Professional",
            "subcategory":"Lawyer & Legal Services",
            "type":"Services"
        }
    ],
    "sg:phone":"+1 970 547 1997",
    "sg:postcode":"80424",
    "sg:province":"CO",
    "sg:tags":[
        "attorney"
    ],
    "wof:name":"Ernest Blake",
    "wof:placetype":"venue"
},
  "geometry": {"coordinates":[-106.046187,39.484573],"type":"Point"}
}