{
  "type": "Feature",
  "properties": {
    "addr:full":"10901 W Toller Dr Littleton CO 80127",
    "addr:housenumber":"10901",
    "addr:postcode":"80127",
    "addr:street":"W Toller Dr",
    "iso:country":"US",
    "sg:address":"10901 W Toller Dr",
    "sg:city":"Littleton",
    "sg:classifiers":[
        {
            "category":"Professional",
            "subcategory":"Business Services",
            "type":"Services"
        },
        {
            "category":"Wholesale",
            "subcategory":"Electrical",
            "type":"Manufacturing & Wholesale Goods"
        }
    ],
    "sg:phone":"+1 303 531 6000",
    "sg:postcode":"80127",
    "sg:province":"CO",
    "sg:tags":[
        "equipment",
        "datum",
        "telecommunication",
        "sales"
    ],
    "sg:website":"www.axesscomm.com",
    "wof:name":"Axess Communications",
    "wof:placetype":"venue"
},
  "geometry": {"coordinates":[-105.120062,39.558571],"type":"Point"}
}