{
  "type": "Feature",
  "properties": {
    "iso:country":"US",
    "sg:address":"373 97 Cir",
    "sg:city":"Breckenridge",
    "sg:classifiers":[
        {
            "category":"Building & Trades",
            "subcategory":"Construction",
            "type":"Services"
        }
    ],
    "sg:phone":"+1 970 547 1069",
    "sg:postcode":"80424",
    "sg:province":"CO",
    "sg:tags":[
        "resurfacing",
        "laying",
        "refinishing",
        "floor"
    ],
    "wof:name":"Hardwood Floors Inc",
    "wof:placetype":"venue"
},
  "geometry": {"coordinates":[-106.044905,39.417269],"type":"Point"}
}