{
  "type": "Feature",
  "properties": {
    "iso:country":"US",
    "sg:address":"6312 S Fiddlers Green Cir",
    "sg:city":"Englewood",
    "sg:classifiers":[
        {
            "category":"Building & Trades",
            "subcategory":"Construction",
            "type":"Services"
        }
    ],
    "sg:phone":"+1 303 799 6194",
    "sg:postcode":"80111",
    "sg:province":"CO",
    "sg:tags":[
        "house"
    ],
    "wof:name":"Ashcroft Homes",
    "wof:placetype":"venue"
},
  "geometry": {"coordinates":[-104.890475,39.60152],"type":"Point"}
}