{
  "type": "Feature",
  "properties": {
    "addr:full":"6647 W Colfax Ave Denver CO 80214",
    "addr:housenumber":"6647",
    "addr:postcode":"80214",
    "addr:street":"W Colfax Ave",
    "iso:country":"US",
    "sg:address":"6647 W Colfax Ave",
    "sg:city":"Denver",
    "sg:classifiers":[
        {
            "category":"Real Estate",
            "subcategory":"Real Estate Agent",
            "type":"Services"
        }
    ],
    "sg:phone":"+1 303 274 0447",
    "sg:postcode":"80214",
    "sg:province":"CO",
    "wof:name":"Burns Investment Properties",
    "wof:placetype":"venue"
},
  "geometry": {"coordinates":[-105.070352,39.740407],"type":"Point"}
}