{
  "type": "Feature",
  "properties": {
    "addr:full":"510 W 29th St Pueblo CO 81008",
    "addr:housenumber":"510",
    "addr:postcode":"81008",
    "addr:street":"W 29Th St",
    "iso:country":"US",
    "sg:address":"510 W 29th St",
    "sg:city":"Pueblo",
    "sg:classifiers":[
        {
            "category":"Banks & Credit Unions",
            "subcategory":"Bank",
            "type":"Services"
        }
    ],
    "sg:phone":"+1 719 565 4200",
    "sg:postcode":"81008",
    "sg:province":"CO",
    "sg:website":"www.fnb-colorado.com",
    "wof:name":"First National Bank-Colorado",
    "wof:placetype":"venue"
},
  "geometry": {"coordinates":[-104.614895,38.298036],"type":"Point"}
}