{
  "type": "Feature",
  "properties": {
    "iso:country":"US",
    "sg:address":"1201 16th Street",
    "sg:city":"Denver",
    "sg:classifiers":[
        {
            "category":"Shopping",
            "subcategory":"Optician",
            "type":"Retail Goods"
        },
        {
            "category":"Shopping Center",
            "type":"Public Place"
        }
    ],
    "sg:phone":"+1 303 825 0820",
    "sg:postcode":"80202",
    "sg:province":"CO",
    "sg:tags":[
        "eyewear"
    ],
    "wof:name":"Sunglass Retail",
    "wof:placetype":"venue"
},
  "geometry": {"coordinates":[-104.99574699999999,39.749758],"type":"Point"}
}