{
  "type": "Feature",
  "properties": {
    "addr:full":"3201 E Mulberry St Fort Collins CO 80524",
    "addr:housenumber":"3201",
    "addr:postcode":"80524",
    "addr:street":"E Mulberry St",
    "iso:country":"US",
    "sg:address":"3201 E Mulberry St",
    "sg:city":"Fort Collins",
    "sg:classifiers":[
        {
            "category":"Wholesale",
            "subcategory":"Hardware",
            "type":"Manufacturing & Wholesale Goods"
        }
    ],
    "sg:phone":"+1 970 482 9965",
    "sg:postcode":"80524",
    "sg:province":"CO",
    "sg:tags":[
        "fastener"
    ],
    "wof:name":"Fastenal Co",
    "wof:placetype":"venue"
},
  "geometry": {"coordinates":[-105.01750199999999,40.581106],"type":"Point"}
}