{
  "type": "Feature",
  "properties": {
    "iso:country":"US",
    "sg:address":"107 Main St",
    "sg:city":"San Luis",
    "sg:classifiers":[
        {
            "category":"Manufacturing",
            "subcategory":"Metals",
            "type":"Manufacturing & Wholesale Goods"
        }
    ],
    "sg:phone":"+1 719 672 3022",
    "sg:postcode":"81152",
    "sg:province":"CO",
    "sg:tags":[
        "foundry"
    ],
    "wof:name":"Huberto Sculpture Studio",
    "wof:placetype":"venue"
},
  "geometry": {"coordinates":[-105.428466,37.195334],"type":"Point"}
}