{
  "type": "Feature",
  "properties": {
    "iso:country":"US",
    "sg:address":"2205 Willow Tree Grove",
    "sg:city":"Colorado Springs",
    "sg:classifiers":[
        {
            "category":"Real Estate",
            "subcategory":"Real Estate Operator",
            "type":"Services"
        }
    ],
    "sg:phone":"+1 719 227 8720",
    "sg:postcode":"80910",
    "sg:province":"CO",
    "sg:tags":[
        "apartment"
    ],
    "wof:name":"Willows",
    "wof:placetype":"venue"
},
  "geometry": {"coordinates":[-104.78591400000001,38.829008],"type":"Point"}
}