{
  "type": "Feature",
  "properties": {
    "iso:country":"US",
    "sg:address":"8450 W 20th Ave",
    "sg:city":"Lakewood",
    "sg:classifiers":[
        {
            "category":"Building & Trades",
            "subcategory":"Construction",
            "type":"Services"
        }
    ],
    "sg:phone":"+1 303 985 8654",
    "sg:postcode":"80215",
    "sg:province":"CO",
    "sg:tags":[
        "general",
        "contractor"
    ],
    "wof:name":"Insulation Unlimited",
    "wof:placetype":"venue"
},
  "geometry": {"coordinates":[-105.091477,39.747443],"type":"Point"}
}