{
  "type": "Feature",
  "properties": {
    "addr:full":"31587 Broadmoor Dr Evergreen CO 80439",
    "addr:housenumber":"31587",
    "addr:postcode":"80439",
    "addr:street":"Broadmoor Dr",
    "iso:country":"US",
    "sg:address":"31587 Broadmoor Dr",
    "sg:city":"Evergreen",
    "sg:classifiers":[
        {
            "category":"Professional",
            "type":"Services"
        }
    ],
    "sg:phone":"+1 303 679 1617",
    "sg:postcode":"80439",
    "sg:province":"CO",
    "sg:tags":[
        "establishment"
    ],
    "wof:name":"Transcontinental Mineral",
    "wof:placetype":"venue"
},
  "geometry": {"coordinates":[-105.359477,39.683094],"type":"Point"}
}