{
  "type": "Feature",
  "properties": {
    "addr:full":"433 E 1st St Salida CO 81201",
    "addr:housenumber":"433",
    "addr:postcode":"81201",
    "addr:street":"E 1St St",
    "iso:country":"US",
    "sg:address":"433 E 1st St",
    "sg:city":"Salida",
    "sg:classifiers":[
        {
            "category":"Building & Trades",
            "subcategory":"Construction",
            "type":"Services"
        }
    ],
    "sg:phone":"+1 719 539 4011",
    "sg:postcode":"81201",
    "sg:province":"CO",
    "sg:tags":[
        "stucco",
        "contractor"
    ],
    "wof:name":"Remy Construction",
    "wof:placetype":"venue"
},
  "geometry": {"coordinates":[-105.988343,38.534075],"type":"Point"}
}