{
  "type": "Feature",
  "properties": {
    "iso:country":"US",
    "sg:address":"229 Vallejo St",
    "sg:city":"Denver",
    "sg:classifiers":[
        {
            "category":"Building & Trades",
            "subcategory":"Locksmith",
            "type":"Services"
        }
    ],
    "sg:phone":"+1 866 545 7506",
    "sg:postcode":"80223",
    "sg:province":"CO",
    "sg:tags":[
        "key"
    ],
    "wof:name":"24 7 Available Locksmith",
    "wof:placetype":"venue"
},
  "geometry": {"coordinates":[-105.013343,39.720506],"type":"Point"}
}