{
  "type": "Feature",
  "properties": {
    "addr:full":"30259 County Farm Rd Pueblo CO 81006",
    "addr:housenumber":"30259",
    "addr:postcode":"81006",
    "addr:street":"County Farm Rd",
    "iso:country":"US",
    "sg:address":"30259 County Farm Rd",
    "sg:city":"Pueblo",
    "sg:classifiers":[
        {
            "category":"Building & Trades",
            "subcategory":"Construction",
            "type":"Services"
        }
    ],
    "sg:phone":"+1 719 948 1338",
    "sg:postcode":"81006",
    "sg:province":"CO",
    "sg:tags":[
        "general",
        "contractor"
    ],
    "wof:name":"Purcell Construction",
    "wof:placetype":"venue"
},
  "geometry": {"coordinates":[-104.49813399999999,38.232169],"type":"Point"}
}