{
  "type": "Feature",
  "properties": {
    "iso:country":"US",
    "sg:address":"420 N Main St",
    "sg:city":"Lamar",
    "sg:classifiers":[
        {
            "category":"Building & Trades",
            "subcategory":"Plumbing",
            "type":"Services"
        }
    ],
    "sg:phone":"+1 719 336 2282",
    "sg:postcode":"81052",
    "sg:province":"CO",
    "sg:tags":[
        "heating",
        "contractor"
    ],
    "wof:name":"Frey Sales & Svc Inc",
    "wof:placetype":"venue"
},
  "geometry": {"coordinates":[-102.619513,38.094175],"type":"Point"}
}