{
  "type": "Feature",
  "properties": {
    "addr:full":"6451 Niagara St Commerce City CO 80022",
    "addr:housenumber":"6451",
    "addr:postcode":"80022",
    "addr:street":"Niagara St",
    "iso:country":"US",
    "sg:address":"6451 Niagara St",
    "sg:city":"Commerce City",
    "sg:classifiers":[
        {
            "category":"Professional",
            "type":"Services"
        }
    ],
    "sg:phone":"+1 303 288 5426",
    "sg:postcode":"80022",
    "sg:province":"CO",
    "wof:name":"Thomas E Baker",
    "wof:placetype":"venue"
},
  "geometry": {"coordinates":[-104.91001799999999,39.813993],"type":"Point"}
}