{
  "type": "Feature",
  "properties": {
    "addr:full":"2424 9th Ave Longmont CO 80503",
    "addr:housenumber":"2424",
    "addr:postcode":"80503",
    "addr:street":"9Th Ave",
    "iso:country":"US",
    "sg:address":"2424 9th Ave",
    "sg:city":"Longmont",
    "sg:classifiers":[
        {
            "category":"Real Estate",
            "subcategory":"Real Estate Operator",
            "type":"Services"
        }
    ],
    "sg:phone":"+1 303 772 8110",
    "sg:postcode":"80503",
    "sg:province":"CO",
    "sg:tags":[
        "building",
        "apartment"
    ],
    "wof:name":"Stone Bridge Apartments",
    "wof:placetype":"venue"
},
  "geometry": {"coordinates":[-105.130893,40.174032],"type":"Point"}
}