{
  "type": "Feature",
  "properties": {
    "iso:country":"US",
    "sg:address":"3120 Beacon St",
    "sg:city":"Colorado Springs",
    "sg:classifiers":[
        {
            "category":"Building & Trades",
            "subcategory":"Construction",
            "type":"Services"
        },
        {
            "category":"Wholesale",
            "subcategory":"Auto Parts",
            "type":"Manufacturing & Wholesale Goods"
        }
    ],
    "sg:phone":"+1 719 520 9943",
    "sg:postcode":"80907",
    "sg:province":"CO",
    "sg:tags":[
        "window",
        "contractor"
    ],
    "wof:name":"Rocky Mountain Autotint",
    "wof:placetype":"venue"
},
  "geometry": {"coordinates":[-104.82698600000001,38.877651],"type":"Point"}
}