{
  "type": "Feature",
  "properties": {
    "iso:country":"US",
    "sg:address":"146 N Elbert St",
    "sg:city":"Elizabeth",
    "sg:classifiers":[
        {
            "category":"Professional",
            "subcategory":"Accounting & Tax Preparation",
            "type":"Services"
        }
    ],
    "sg:phone":"+1 303 646 1120",
    "sg:postcode":"80107",
    "sg:province":"CO",
    "sg:tags":[
        "accountant"
    ],
    "wof:name":"Jones & Assoc LLC",
    "wof:placetype":"venue"
},
  "geometry": {"coordinates":[-104.59880800000001,39.361944],"type":"Point"}
}