{
  "type": "Feature",
  "properties": {
    "iso:country":"US",
    "sg:address":"10305 E Colfax Ave",
    "sg:city":"Aurora",
    "sg:classifiers":[
        {
            "category":"Banks & Credit Unions",
            "subcategory":"Bank",
            "type":"Services"
        }
    ],
    "sg:phone":"+1 303 360 6669",
    "sg:postcode":"80010",
    "sg:province":"CO",
    "sg:tags":[
        "cashing",
        "check"
    ],
    "wof:name":"Moneytree",
    "wof:placetype":"venue"
},
  "geometry": {"coordinates":[-104.86704899999999,39.740279],"type":"Point"}
}