{
  "type": "Feature",
  "properties": {
    "iso:country":"US",
    "sg:address":"15724 W 6th Ave",
    "sg:city":"Golden",
    "sg:classifiers":[
        {
            "category":"Freight",
            "type":"Transportation"
        }
    ],
    "sg:phone":"+1 303 790 7560",
    "sg:postcode":"80401",
    "sg:province":"CO",
    "sg:tags":[
        "general"
    ],
    "wof:name":"Foster Wheeler",
    "wof:placetype":"venue"
},
  "geometry": {"coordinates":[-105.176925,39.7252],"type":"Point"}
}