{
  "type": "Feature",
  "properties": {
    "addr:full":"1800 W Littleton Blvd Littleton CO 80120",
    "addr:housenumber":"1800",
    "addr:postcode":"80120",
    "addr:street":"W Littleton Blvd",
    "iso:country":"US",
    "sg:address":"1800 W Littleton Blvd",
    "sg:city":"Littleton",
    "sg:classifiers":[
        {
            "category":"Professional",
            "subcategory":"Lawyer & Legal Services",
            "type":"Services"
        }
    ],
    "sg:phone":"+1 303 795 1411",
    "sg:postcode":"80120",
    "sg:province":"CO",
    "sg:tags":[
        "attorney"
    ],
    "wof:name":"Sue A Jones Attorney At Law",
    "wof:placetype":"venue"
},
  "geometry": {"coordinates":[-105.01034300000001,39.613257],"type":"Point"}
}