{
  "type": "Feature",
  "properties": {
    "addr:full":"13450 Lafayette Ct Denver CO 80241",
    "addr:housenumber":"13450",
    "addr:postcode":"80241",
    "addr:street":"Lafayette Ct",
    "iso:country":"US",
    "sg:address":"13450 Lafayette Ct",
    "sg:city":"Denver",
    "sg:classifiers":[
        {
            "category":"Shopping",
            "type":"Retail Goods"
        }
    ],
    "sg:phone":"+1 720 205 9975",
    "sg:postcode":"80241",
    "sg:province":"CO",
    "sg:tags":[
        "merchandise"
    ],
    "wof:name":"Propet Sciences LLC",
    "wof:placetype":"venue"
},
  "geometry": {"coordinates":[-104.967288,39.938772],"type":"Point"}
}