{
  "type": "Feature",
  "properties": {
    "addr:full":"142 6th St Dacono CO 80514",
    "addr:housenumber":"142",
    "addr:postcode":"80514",
    "addr:street":"6Th St",
    "iso:country":"US",
    "sg:address":"142 6th St",
    "sg:city":"Dacono",
    "sg:classifiers":[
        {
            "category":"Shopping",
            "subcategory":"Bicycles & Sporting Goods",
            "type":"Retail Goods"
        }
    ],
    "sg:phone":"+1 303 833 4160",
    "sg:postcode":"80514",
    "sg:province":"CO",
    "wof:name":"Shalom Bikes",
    "wof:placetype":"venue"
},
  "geometry": {"coordinates":[-104.940715,40.085924],"type":"Point"}
}