{
  "type": "Feature",
  "properties": {
    "iso:country":"US",
    "sg:address":"10456 Longleaf Dr",
    "sg:city":"Parker",
    "sg:classifiers":[
        {
            "category":"Banks & Credit Unions",
            "subcategory":"Financial Services",
            "type":"Services"
        }
    ],
    "sg:phone":"+1 303 593 0417",
    "sg:postcode":"80134",
    "sg:province":"CO",
    "sg:tags":[
        "investor"
    ],
    "wof:name":"JD Capital Inc",
    "wof:placetype":"venue"
},
  "geometry": {"coordinates":[-104.79459,39.526211],"type":"Point"}
}