{
  "type": "Feature",
  "properties": {
    "iso:country":"US",
    "sg:address":"9900 E 51st Ave",
    "sg:city":"Denver",
    "sg:classifiers":[
        {
            "category":"Building & Trades",
            "subcategory":"Construction",
            "type":"Services"
        }
    ],
    "sg:phone":"+1 303 574 1552",
    "sg:postcode":"80238",
    "sg:province":"CO",
    "sg:tags":[
        "television",
        "telephone",
        "cable",
        "contractor"
    ],
    "wof:name":"Linx LLLP",
    "wof:placetype":"venue"
},
  "geometry": {"coordinates":[-104.88170700000001,39.790649],"type":"Point"}
}