{
  "type": "Feature",
  "properties": {
    "iso:country":"US",
    "sg:address":"715 Ventura St",
    "sg:city":"Aurora",
    "sg:classifiers":[
        {
            "category":"Manufacturing",
            "subcategory":"Metals",
            "type":"Manufacturing & Wholesale Goods"
        },
        {
            "category":"Building & Trades",
            "subcategory":"Construction",
            "type":"Services"
        }
    ],
    "sg:phone":"+1 303 367 4446",
    "sg:postcode":"80011",
    "sg:province":"CO",
    "sg:tags":[
        "coating",
        "flooring",
        "contractor"
    ],
    "sg:website":"www.highcountrycoatings.com",
    "wof:name":"High Country Coatings Inc",
    "wof:placetype":"venue"
},
  "geometry": {"coordinates":[-104.778802,39.727557],"type":"Point"}
}