{
  "type": "Feature",
  "properties": {
    "addr:full":"Prima Clinic 2150 W 29th Ave Suite 600 Denver CO 80211",
    "addr:housenumber":"2150",
    "addr:postcode":"80211",
    "addr:street":"W 29Th Ave Suite 600",
    "iso:country":"US",
    "sg:address":"Prima Clinic 2150 W 29th Ave Suite 600",
    "sg:city":"Denver",
    "sg:classifiers":[
        {
            "category":"Health Services",
            "subcategory":"Doctor",
            "type":"Services"
        }
    ],
    "sg:phone":"+1 303 331 6744",
    "sg:postcode":"80211",
    "sg:province":"CO",
    "sg:tags":[
        "dermatologist"
    ],
    "wof:name":"Lower Highlands Dermatology",
    "wof:placetype":"venue"
},
  "geometry": {"coordinates":[-105.01277,39.758126],"type":"Point"}
}