{
  "type": "Feature",
  "properties": {
    "iso:country":"US",
    "sg:address":"300 Nickel St",
    "sg:city":"Broomfield",
    "sg:classifiers":[
        {
            "category":"Shopping",
            "subcategory":"Department Store",
            "type":"Retail Goods"
        }
    ],
    "sg:phone":"+1 303 466 2244",
    "sg:postcode":"80020",
    "sg:province":"CO",
    "sg:tags":[
        "cleaner",
        "supply"
    ],
    "wof:name":"Broomfield Vacuum Center",
    "wof:placetype":"venue"
},
  "geometry": {"coordinates":[-105.08762400000001,39.920269],"type":"Point"}
}