{
  "type": "Feature",
  "properties": {
    "iso:country":"US",
    "sg:address":"2626 Durango Dr",
    "sg:city":"Colorado Springs",
    "sg:classifiers":[
        {
            "category":"Retail",
            "subcategory":"Repair Shop",
            "type":"Services"
        }
    ],
    "sg:phone":"+1 719 596 5817",
    "sg:postcode":"80910",
    "sg:province":"CO",
    "sg:tags":[
        "repairing",
        "piano",
        "refinishing"
    ],
    "wof:name":"King's Piano Sales & Svc",
    "wof:placetype":"venue"
},
  "geometry": {"coordinates":[-104.773515,38.794243],"type":"Point"}
}