{
  "type": "Feature",
  "properties": {
    "iso:country":"US",
    "sg:address":"2134 Curtis St",
    "sg:city":"Denver",
    "sg:classifiers":[
        {
            "category":"Real Estate",
            "subcategory":"Architect",
            "type":"Services"
        }
    ],
    "sg:phone":"+1 303 295 1418",
    "sg:postcode":"80205",
    "sg:province":"CO",
    "wof:name":"Architectural Alliance Group",
    "wof:placetype":"venue"
},
  "geometry": {"coordinates":[-104.987875,39.752416],"type":"Point"}
}