{
  "type": "Feature",
  "properties": {
    "addr:full":"2900 S College Ave Fort Collins CO 80525",
    "addr:housenumber":"2900",
    "addr:postcode":"80525",
    "addr:street":"S College Ave",
    "iso:country":"US",
    "sg:address":"2900 S College Ave",
    "sg:city":"Fort Collins",
    "sg:classifiers":[
        {
            "category":"Professional",
            "type":"Services"
        }
    ],
    "sg:phone":"+1 970 266 9890",
    "sg:postcode":"80525",
    "sg:province":"CO",
    "wof:name":"Cornerstone Safety Sy",
    "wof:placetype":"venue"
},
  "geometry": {"coordinates":[-105.076977,40.548098],"type":"Point"}
}