{
  "type": "Feature",
  "properties": {
    "addr:full":"385 S Kearney St Denver CO 80224",
    "addr:housenumber":"385",
    "addr:postcode":"80224",
    "addr:street":"S Kearney St",
    "iso:country":"US",
    "sg:address":"385 S Kearney St",
    "sg:city":"Denver",
    "sg:classifiers":[
        {
            "category":"Building & Trades",
            "subcategory":"Construction",
            "type":"Services"
        }
    ],
    "sg:phone":"+1 303 399 2642",
    "sg:postcode":"80224",
    "sg:province":"CO",
    "sg:tags":[
        "house",
        "nonresidential"
    ],
    "wof:name":"Continental Construction Co",
    "wof:placetype":"venue"
},
  "geometry": {"coordinates":[-104.917677,39.710898],"type":"Point"}
}