{
  "type": "Feature",
  "properties": {
    "iso:country":"US",
    "sg:address":"726 N 1st St",
    "sg:city":"Grand Junction",
    "sg:classifiers":[
        {
            "category":"Real Estate",
            "subcategory":"Real Estate Agent",
            "type":"Services"
        }
    ],
    "sg:phone":"+1 970 241 5073",
    "sg:postcode":"81501",
    "sg:province":"CO",
    "wof:name":"Wdd Properties Lllp",
    "wof:placetype":"venue"
},
  "geometry": {"coordinates":[-108.570813,39.074192],"type":"Point"}
}