{
  "type": "Feature",
  "properties": {
    "iso:country":"US",
    "sg:address":"2160 Hancock Expy",
    "sg:city":"Colorado Springs",
    "sg:classifiers":[
        {
            "category":"Freight",
            "type":"Transportation"
        }
    ],
    "sg:phone":"+1 719 392 3318",
    "sg:postcode":"80910",
    "sg:province":"CO",
    "sg:tags":[
        "operator",
        "local",
        "trucking"
    ],
    "wof:name":"Interstate Moving Services",
    "wof:placetype":"venue"
},
  "geometry": {"coordinates":[-104.78617800000001,38.80481],"type":"Point"}
}