{
  "type": "Feature",
  "properties": {
    "addr:full":"101 University Blvd Denver CO 80206",
    "addr:housenumber":"101",
    "addr:postcode":"80206",
    "addr:street":"University Blvd",
    "iso:country":"US",
    "sg:address":"101 University Blvd",
    "sg:city":"Denver",
    "sg:classifiers":[
        {
            "category":"Real Estate",
            "subcategory":"Real Estate Operator",
            "type":"Services"
        }
    ],
    "sg:phone":"+1 303 333 4474",
    "sg:postcode":"80206",
    "sg:province":"CO",
    "sg:tags":[
        "building",
        "nonresidential"
    ],
    "wof:name":"Coscan Property Mngmnt Inc",
    "wof:placetype":"venue"
},
  "geometry": {"coordinates":[-104.959439,39.719419],"type":"Point"}
}