{
  "type": "Feature",
  "properties": {
    "iso:country":"US",
    "sg:address":"225 E 16th Ave",
    "sg:city":"Denver",
    "sg:classifiers":[
        {
            "category":"Social Services",
            "subcategory":"Job Training",
            "type":"Services"
        }
    ],
    "sg:phone":"+1 303 863 7714",
    "sg:postcode":"80203",
    "sg:province":"CO",
    "sg:tags":[
        "career",
        "counseling",
        "vocational"
    ],
    "wof:name":"Robert E O'Connell",
    "wof:placetype":"venue"
},
  "geometry": {"coordinates":[-104.983886,39.74175],"type":"Point"}
}