{
  "type": "Feature",
  "properties": {
    "addr:full":"2390 S Lewiston St Aurora CO 80013",
    "addr:housenumber":"2390",
    "addr:postcode":"80013",
    "addr:street":"S Lewiston St",
    "iso:country":"US",
    "sg:address":"2390 S Lewiston St",
    "sg:city":"Aurora",
    "sg:classifiers":[
        {
            "category":"Shopping",
            "subcategory":"Gifts & Souvenirs",
            "type":"Retail Goods"
        }
    ],
    "sg:phone":"+1 303 743 8213",
    "sg:postcode":"80013",
    "sg:province":"CO",
    "sg:tags":[
        "shop"
    ],
    "wof:name":"Ana's Gift World",
    "wof:placetype":"venue"
},
  "geometry": {"coordinates":[-104.79871,39.673631],"type":"Point"}
}