{
  "type": "Feature",
  "properties": {
    "addr:full":"11839 Havana St Henderson CO 80640",
    "addr:housenumber":"11839",
    "addr:postcode":"80640",
    "addr:street":"Havana St",
    "iso:country":"US",
    "sg:address":"11839 Havana St",
    "sg:city":"Henderson",
    "sg:classifiers":[
        {
            "category":"Home & Garden",
            "subcategory":"Furniture",
            "type":"Retail Goods"
        }
    ],
    "sg:phone":"+1 303 574 9030",
    "sg:postcode":"80640",
    "sg:province":"CO",
    "sg:tags":[
        "mattress"
    ],
    "wof:name":"Mattress King",
    "wof:placetype":"venue"
},
  "geometry": {"coordinates":[-104.85843800000001,39.910599],"type":"Point"}
}