{
  "type": "Feature",
  "properties": {
    "addr:full":"1689 Jamaica St Aurora CO 80010",
    "addr:housenumber":"1689",
    "addr:postcode":"80010",
    "addr:street":"Jamaica St",
    "iso:country":"US",
    "sg:address":"1689 Jamaica St",
    "sg:city":"Aurora",
    "sg:classifiers":[
        {
            "category":"Social Services",
            "subcategory":"Child Care",
            "type":"Services"
        }
    ],
    "sg:phone":"+1 303 739 0776",
    "sg:postcode":"80010",
    "sg:province":"CO",
    "wof:name":"Little Miss Marker's Daycare",
    "wof:placetype":"venue"
},
  "geometry": {"coordinates":[-104.862354,39.742154],"type":"Point"}
}