{
  "type": "Feature",
  "properties": {
    "iso:country":"US",
    "sg:address":"5751 N Academy Blvd",
    "sg:city":"Colorado Springs",
    "sg:classifiers":[
        {
            "category":"Shopping",
            "subcategory":"Crafts & Fabrics",
            "type":"Retail Goods"
        }
    ],
    "sg:phone":"+1 719 594 4543",
    "sg:postcode":"80918",
    "sg:province":"CO",
    "sg:tags":[
        "embroidery"
    ],
    "wof:name":"Classic Embroidery & Notions",
    "wof:placetype":"venue"
},
  "geometry": {"coordinates":[-104.787559,38.91419],"type":"Point"}
}