{
  "type": "Feature",
  "properties": {
    "addr:full":"1230 N 12th St Grand Junction CO 81501",
    "addr:housenumber":"1230",
    "addr:postcode":"81501",
    "addr:street":"N 12Th St",
    "iso:country":"US",
    "sg:address":"1230 N 12th St",
    "sg:city":"Grand Junction",
    "sg:classifiers":[
        {
            "category":"Restaurant",
            "type":"Food & Drink"
        }
    ],
    "sg:menulink":"http://www.allmenus.com/co/grand-junction/102779-the-pita-pit/menu/",
    "sg:phone":"+1 970 242 7482",
    "sg:postcode":"81501",
    "sg:province":"CO",
    "sg:tags":[
        "salad",
        "soup",
        "eastern",
        "mediterranean",
        "middle",
        "american",
        "greek"
    ],
    "wof:name":"The Pita Pit",
    "wof:placetype":"venue"
},
  "geometry": {"coordinates":[-108.5523,39.078599],"type":"Point"}
}