{
  "type": "Feature",
  "properties": {
    "iso:country":"US",
    "sg:address":"857 S Lincoln Ave",
    "sg:city":"Loveland",
    "sg:classifiers":[
        {
            "category":"Restaurant",
            "type":"Food & Drink"
        }
    ],
    "sg:phone":"+1 970 663 4936",
    "sg:postcode":"80537",
    "sg:province":"CO",
    "sg:tags":[
        "eating"
    ],
    "wof:name":"Sonic Drive-In",
    "wof:placetype":"venue"
},
  "geometry": {"coordinates":[-105.07343299999999,40.383625],"type":"Point"}
}