{
  "type": "Feature",
  "properties": {
    "addr:full":"1280 W Browning Ave Woodland Park CO 80863",
    "addr:housenumber":"1280",
    "addr:postcode":"80863",
    "addr:street":"W Browning Ave",
    "iso:country":"US",
    "sg:address":"1280 W Browning Ave",
    "sg:city":"Woodland Park",
    "sg:classifiers":[
        {
            "category":"Banks & Credit Unions",
            "subcategory":"Bank",
            "type":"Services"
        }
    ],
    "sg:phone":"+1 719 687 3530",
    "sg:postcode":"80863",
    "sg:province":"CO",
    "sg:tags":[
        "financing"
    ],
    "wof:name":"Associates Commercial Corp",
    "wof:placetype":"venue"
},
  "geometry": {"coordinates":[-105.06995999999999,38.991981],"type":"Point"}
}