{
  "type": "Feature",
  "properties": {
    "iso:country":"US",
    "sg:address":"6662 Gunpark Dr",
    "sg:city":"Boulder",
    "sg:classifiers":[
        {
            "category":"Wholesale",
            "subcategory":"Furniture",
            "type":"Manufacturing & Wholesale Goods"
        }
    ],
    "sg:phone":"+1 303 527 1460",
    "sg:postcode":"80301",
    "sg:province":"CO",
    "sg:tags":[
        "equipment",
        "outdoor"
    ],
    "wof:name":"Lafuma America Inc",
    "wof:placetype":"venue"
},
  "geometry": {"coordinates":[-105.200946,40.069794],"type":"Point"}
}