{
  "type": "Feature",
  "properties": {
    "iso:country":"US",
    "sg:address":"633 S Broadway St",
    "sg:city":"Boulder",
    "sg:classifiers":[
        {
            "category":"Organizations",
            "subcategory":"Community Association",
            "type":"Services"
        }
    ],
    "sg:phone":"+1 303 554 7688",
    "sg:postcode":"80305",
    "sg:province":"CO",
    "sg:tags":[
        "club"
    ],
    "wof:name":"Colorado Mountain Club",
    "wof:placetype":"venue"
},
  "geometry": {"coordinates":[-105.24315300000001,39.977857],"type":"Point"}
}