{
  "type": "Feature",
  "properties": {
    "iso:country":"US",
    "sg:address":"690 Industrial Blvd",
    "sg:city":"Delta",
    "sg:classifiers":[
        {
            "category":"Government",
            "subcategory":"Office",
            "type":"Public Place"
        }
    ],
    "sg:phone":"+1 970 874 5726",
    "sg:postcode":"81416",
    "sg:province":"CO",
    "wof:name":"Usda Svc Ctr",
    "wof:placetype":"venue"
},
  "geometry": {"coordinates":[-108.034482,38.755452],"type":"Point"}
}