{
  "type": "Feature",
  "properties": {
    "iso:country":"US",
    "sg:address":"800 E Emma St",
    "sg:city":"Lafayette",
    "sg:classifiers":[
        {
            "category":"Wholesale",
            "subcategory":"Farm Supplies",
            "type":"Manufacturing & Wholesale Goods"
        }
    ],
    "sg:phone":"+1 303 665 5457",
    "sg:postcode":"80026",
    "sg:province":"CO",
    "sg:tags":[
        "manufacture",
        "saddlery",
        "product",
        "representative"
    ],
    "wof:name":"L a roe Inc",
    "wof:placetype":"venue"
},
  "geometry": {"coordinates":[-105.0792,39.99398],"type":"Point"}
}