{
  "type": "Feature",
  "properties": {
    "addr:full":"1455 Main St Windsor CO 80550",
    "addr:housenumber":"1455",
    "addr:postcode":"80550",
    "addr:street":"Main St",
    "iso:country":"US",
    "sg:address":"1455 Main St",
    "sg:city":"Windsor",
    "sg:classifiers":[
        {
            "category":"Health Services",
            "subcategory":"Doctor",
            "type":"Services"
        }
    ],
    "sg:phone":"+1 970 686 5655",
    "sg:postcode":"80550",
    "sg:province":"CO",
    "sg:tags":[
        "medical"
    ],
    "wof:name":"Mason R Anthony MD",
    "wof:placetype":"venue"
},
  "geometry": {"coordinates":[-104.92435399999999,40.47945],"type":"Point"}
}