{
  "type": "Feature",
  "properties": {
    "iso:country":"US",
    "sg:address":"123 Eureka St",
    "sg:city":"Central City",
    "sg:classifiers":[
        {
            "category":"Organizations",
            "subcategory":"Religious Organization",
            "type":"Services"
        }
    ],
    "sg:phone":"+1 303 582 5882",
    "sg:postcode":"80427",
    "sg:province":"CO",
    "sg:tags":[
        "church"
    ],
    "wof:name":"St James United Methodist Chr",
    "wof:placetype":"venue"
},
  "geometry": {"coordinates":[-105.513509,39.801479],"type":"Point"}
}