{
  "type": "Feature",
  "properties": {
    "addr:full":"602 Main St Silt CO 81652",
    "addr:housenumber":"602",
    "addr:postcode":"81652",
    "addr:street":"Main St",
    "iso:country":"US",
    "sg:address":"602 Main St",
    "sg:city":"Silt",
    "sg:classifiers":[
        {
            "category":"Building & Trades",
            "subcategory":"Construction",
            "type":"Services"
        }
    ],
    "sg:phone":"+1 970 876 5278",
    "sg:postcode":"81652",
    "sg:province":"CO",
    "sg:tags":[
        "floor",
        "laying",
        "contractor"
    ],
    "wof:name":"J & D Enterprises",
    "wof:placetype":"venue"
},
  "geometry": {"coordinates":[-107.65687200000001,39.547089],"type":"Point"}
}