{
  "type": "Feature",
  "properties": {
    "addr:full":"1281 S Akron Way Denver CO 80247",
    "addr:housenumber":"1281",
    "addr:postcode":"80247",
    "addr:street":"S Akron Way",
    "iso:country":"US",
    "sg:address":"1281 S Akron Way",
    "sg:city":"Denver",
    "sg:classifiers":[
        {
            "category":"Health Services",
            "subcategory":"Clinic",
            "type":"Services"
        }
    ],
    "sg:phone":"+1 303 756 0397",
    "sg:postcode":"80247",
    "sg:province":"CO",
    "sg:tags":[
        "center"
    ],
    "wof:name":"Stemc America Inc",
    "wof:placetype":"venue"
},
  "geometry": {"coordinates":[-104.88335600000001,39.693509],"type":"Point"}
}