{
  "type": "Feature",
  "properties": {
    "iso:country":"US",
    "sg:address":"1500 2nd St",
    "sg:city":"Greeley",
    "sg:classifiers":[
        {
            "category":"Government",
            "subcategory":"Office",
            "type":"Public Place"
        }
    ],
    "sg:phone":"+1 970 336 7211",
    "sg:postcode":"80631",
    "sg:province":"CO",
    "wof:name":"Weld County Custodian Bldgs",
    "wof:placetype":"venue"
},
  "geometry": {"coordinates":[-104.702533,40.432119],"type":"Point"}
}