{
  "type": "Feature",
  "properties": {
    "iso:country":"US",
    "sg:address":"7001 State Hwy 73",
    "sg:city":"Evergreen",
    "sg:classifiers":[
        {
            "category":"Building & Trades",
            "subcategory":"Construction",
            "type":"Services"
        }
    ],
    "sg:phone":"+1 303 670 9653",
    "sg:postcode":"80439",
    "sg:province":"CO",
    "sg:tags":[
        "general",
        "contractor"
    ],
    "wof:name":"Timberwolf Design & Cnstrctn",
    "wof:placetype":"venue"
},
  "geometry": {"coordinates":[-105.310008,39.587996],"type":"Point"}
}