{
  "type": "Feature",
  "properties": {
    "addr:full":"5220 W Mississippi Ave Lakewood CO 80226",
    "addr:housenumber":"5220",
    "addr:postcode":"80226",
    "addr:street":"W Mississippi Ave",
    "iso:country":"US",
    "sg:address":"5220 W Mississippi Ave",
    "sg:city":"Lakewood",
    "sg:classifiers":[
        {
            "category":"Shopping",
            "subcategory":"Pets & Pet Supplies",
            "type":"Retail Goods"
        }
    ],
    "sg:phone":"+1 303 936 1217",
    "sg:postcode":"80226",
    "sg:province":"CO",
    "sg:tags":[
        "store"
    ],
    "sg:website":"http://crittercove.net/main.html?src=%2F#1,0",
    "wof:name":"Critter Cove Pets & Supplies",
    "wof:placetype":"venue"
},
  "geometry": {"coordinates":[-105.054165,39.696798],"type":"Point"}
}