{
  "type": "Feature",
  "properties": {
    "iso:country":"US",
    "sg:address":"2037 Jerry Murphy Rd",
    "sg:city":"Pueblo",
    "sg:classifiers":[
        {
            "category":"Social Services",
            "type":"Services"
        }
    ],
    "sg:phone":"+1 719 544 3389",
    "sg:postcode":"81001",
    "sg:province":"CO",
    "sg:tags":[
        "counselor",
        "marriage",
        "family"
    ],
    "wof:name":"Rocky Mountain Counseling Ctr",
    "wof:placetype":"venue"
},
  "geometry": {"coordinates":[-104.59837899999999,38.304831],"type":"Point"}
}