{
  "type": "Feature",
  "properties": {
    "iso:country":"US",
    "sg:address":"425 W 115th Ave",
    "sg:city":"Denver",
    "sg:classifiers":[
        {
            "category":"Building & Trades",
            "subcategory":"Construction",
            "type":"Services"
        }
    ],
    "sg:phone":"+1 303 295 3175",
    "sg:postcode":"80234",
    "sg:province":"CO",
    "sg:tags":[
        "dry wall",
        "contractor"
    ],
    "wof:name":"Charter Drywall Denver Inc",
    "wof:placetype":"venue"
},
  "geometry": {"coordinates":[-104.992383,39.905693],"type":"Point"}
}