{
  "type": "Feature",
  "properties": {
    "addr:full":"4910 Fox St Denver CO 80216",
    "addr:housenumber":"4910",
    "addr:postcode":"80216",
    "addr:street":"Fox St",
    "iso:country":"US",
    "sg:address":"4910 Fox St",
    "sg:city":"Denver",
    "sg:classifiers":[
        {
            "category":"Professional",
            "subcategory":"Art Services",
            "type":"Services"
        }
    ],
    "sg:phone":"+1 303 292 0250",
    "sg:postcode":"80216",
    "sg:province":"CO",
    "sg:tags":[
        "photographer"
    ],
    "wof:name":"Eric Weber Photography",
    "wof:placetype":"venue"
},
  "geometry": {"coordinates":[-104.993797,39.785057],"type":"Point"}
}