{
  "type": "Feature",
  "properties": {
    "addr:full":"17055 E Ithaca Cir Aurora CO 80013",
    "addr:housenumber":"17055",
    "addr:postcode":"80013",
    "addr:street":"E Ithaca Cir",
    "iso:country":"US",
    "sg:address":"17055 E Ithaca Cir",
    "sg:city":"Aurora",
    "sg:classifiers":[
        {
            "category":"Building & Trades",
            "subcategory":"Construction",
            "type":"Services"
        }
    ],
    "sg:phone":"+1 303 680 8420",
    "sg:postcode":"80013",
    "sg:province":"CO",
    "sg:tags":[
        "residential",
        "remodeling"
    ],
    "wof:name":"Skyray Inc",
    "wof:placetype":"venue"
},
  "geometry": {"coordinates":[-104.790145,39.65141],"type":"Point"}
}