{
  "type": "Feature",
  "properties": {
    "iso:country":"US",
    "sg:address":"6435 Huron St",
    "sg:city":"Denver",
    "sg:classifiers":[
        {
            "category":"Freight",
            "type":"Transportation"
        }
    ],
    "sg:phone":"+1 303 412 1700",
    "sg:postcode":"80221",
    "sg:province":"CO",
    "sg:tags":[
        "operator",
        "truck",
        "trucking"
    ],
    "wof:name":"Voyager Express",
    "wof:placetype":"venue"
},
  "geometry": {"coordinates":[-104.996889,39.814363],"type":"Point"}
}