{
  "type": "Feature",
  "properties": {
    "iso:country":"US",
    "sg:address":"821 Roma Valley Dr",
    "sg:city":"Fort Collins",
    "sg:classifiers":[
        {
            "category":"Wholesale",
            "subcategory":"Computers",
            "type":"Manufacturing & Wholesale Goods"
        }
    ],
    "sg:phone":"+1 970 467 2839",
    "sg:postcode":"80525",
    "sg:province":"CO",
    "wof:name":"Criterion Systems LLC",
    "wof:placetype":"venue"
},
  "geometry": {"coordinates":[-105.062336,40.510019],"type":"Point"}
}