{
  "type": "Feature",
  "properties": {
    "iso:country":"US",
    "sg:address":"236 S 3rd St",
    "sg:city":"Montrose",
    "sg:classifiers":[
        {
            "category":"Building & Trades",
            "subcategory":"Construction",
            "type":"Services"
        }
    ],
    "sg:phone":"+1 970 249 9453",
    "sg:postcode":"81401",
    "sg:province":"CO",
    "sg:tags":[
        "specializing",
        "general",
        "commercial",
        "contractor"
    ],
    "wof:name":"Ridgway Valley Enterprises",
    "wof:placetype":"venue"
},
  "geometry": {"coordinates":[-107.875461,38.476137],"type":"Point"}
}