{
  "type": "Feature",
  "properties": {
    "addr:full":"430 S Fenton St Denver CO 80226",
    "addr:housenumber":"430",
    "addr:postcode":"80226",
    "addr:street":"S Fenton St",
    "iso:country":"US",
    "sg:address":"430 S Fenton St",
    "sg:city":"Denver",
    "sg:classifiers":[
        {
            "category":"Building & Trades",
            "subcategory":"Landscaping Services",
            "type":"Services"
        }
    ],
    "sg:phone":"+1 303 922 6008",
    "sg:postcode":"80226",
    "sg:province":"CO",
    "sg:tags":[
        "landscape",
        "contractor"
    ],
    "wof:name":"Our Family Tree & Landscaping",
    "wof:placetype":"venue"
},
  "geometry": {"coordinates":[-105.06026300000001,39.707934],"type":"Point"}
}