{
  "type": "Feature",
  "properties": {
    "addr:full":"8451 Wright St Arvada CO 80005",
    "addr:housenumber":"8451",
    "addr:postcode":"80005",
    "addr:street":"Wright St",
    "iso:country":"US",
    "sg:address":"8451 Wright St",
    "sg:city":"Arvada",
    "sg:classifiers":[
        {
            "category":"Professional",
            "type":"Services"
        }
    ],
    "sg:phone":"+1 303 420 6558",
    "sg:postcode":"80005",
    "sg:province":"CO",
    "wof:name":"Schmersal",
    "wof:placetype":"venue"
},
  "geometry": {"coordinates":[-105.14138800000001,39.850629],"type":"Point"}
}