{
  "type": "Feature",
  "properties": {
    "addr:full":"4430 N Co Rd 11C Loveland CO 80538",
    "addr:housenumber":"4430;11c",
    "addr:postcode":"80538",
    "addr:street":"N Co Rd",
    "iso:country":"US",
    "sg:address":"4430 N Co Rd 11C",
    "sg:city":"Loveland",
    "sg:classifiers":[
        {
            "category":"Recreation",
            "subcategory":"Marina",
            "type":"Entertainment"
        }
    ],
    "sg:phone":"+1 970 663 2797",
    "sg:postcode":"80538",
    "sg:province":"CO",
    "wof:name":"Boyd Lake Marina Inc",
    "wof:placetype":"venue"
},
  "geometry": {"coordinates":[-105.045444,40.4312],"type":"Point"}
}