{
  "type": "Feature",
  "properties": {
    "iso:country":"US",
    "sg:address":"3124 Cascade Ave",
    "sg:city":"Pueblo",
    "sg:classifiers":[
        {
            "category":"Building & Trades",
            "subcategory":"Plumbing",
            "type":"Services"
        }
    ],
    "sg:phone":"+1 719 545 9424",
    "sg:postcode":"81008",
    "sg:province":"CO",
    "sg:tags":[
        "septic"
    ],
    "wof:name":"Budget Sewer & Septic",
    "wof:placetype":"venue"
},
  "geometry": {"coordinates":[-104.627734,38.301852],"type":"Point"}
}