{
  "type": "Feature",
  "properties": {
    "iso:country":"US",
    "sg:address":"621 17th St",
    "sg:city":"Denver",
    "sg:classifiers":[
        {
            "category":"Professional",
            "subcategory":"Lawyer & Legal Services",
            "type":"Services"
        }
    ],
    "sg:phone":"+1 303 333 9810",
    "sg:postcode":"80293",
    "sg:province":"CO",
    "wof:name":"Feingold Jennifer Atty",
    "wof:placetype":"venue"
},
  "geometry": {"coordinates":[-104.990185,39.745661],"type":"Point"}
}