{
  "type": "Feature",
  "properties": {
    "addr:full":"201 Santa Fe Dr Denver CO 80204",
    "addr:housenumber":"201",
    "addr:postcode":"80204",
    "addr:street":"Santa Fe Dr",
    "iso:country":"US",
    "sg:address":"201 Santa Fe Dr",
    "sg:city":"Denver",
    "sg:classifiers":[
        {
            "category":"Home & Garden",
            "subcategory":"Building Materials",
            "type":"Retail Goods"
        }
    ],
    "sg:phone":"+1 303 825 2211",
    "sg:postcode":"80204",
    "sg:province":"CO",
    "sg:tags":[
        "cement"
    ],
    "sg:website":"www.riograndeco.com",
    "wof:name":"Rio Grande Co-Rebar Svc",
    "wof:placetype":"venue"
},
  "geometry": {"coordinates":[-104.99857799999999,39.720932],"type":"Point"}
}