{
  "type": "Feature",
  "properties": {
    "iso:country":"US",
    "sg:address":"1479 S Holly St",
    "sg:city":"Denver",
    "sg:classifiers":[
        {
            "category":"Health Services",
            "subcategory":"Clinic",
            "type":"Services"
        }
    ],
    "sg:phone":"+1 303 758 9114",
    "sg:postcode":"80222",
    "sg:province":"CO",
    "sg:tags":[
        "cannabis"
    ],
    "sg:website":"www.thecliniccolorado.com/",
    "wof:name":"The Clinic Alternative Medicine",
    "wof:placetype":"venue"
},
  "geometry": {"coordinates":[-104.922359,39.689588],"type":"Point"}
}