{
  "type": "Feature",
  "properties": {
    "iso:country":"US",
    "sg:address":"690 S Dahlia Cir",
    "sg:city":"Denver",
    "sg:classifiers":[
        {
            "category":"Real Estate",
            "subcategory":"Real Estate Operator",
            "type":"Services"
        }
    ],
    "sg:phone":"+1 303 331 6177",
    "sg:postcode":"80246",
    "sg:province":"CO",
    "sg:tags":[
        "apartment"
    ],
    "wof:name":"Heritage Creek Apts",
    "wof:placetype":"venue"
},
  "geometry": {"coordinates":[-104.931445,39.704336],"type":"Point"}
}