{
  "type": "Feature",
  "properties": {
    "addr:full":"2520 S Utica St Denver CO 80219",
    "addr:housenumber":"2520",
    "addr:postcode":"80219",
    "addr:street":"S Utica St",
    "iso:country":"US",
    "sg:address":"2520 S Utica St",
    "sg:city":"Denver",
    "sg:classifiers":[
        {
            "category":"Education",
            "subcategory":"School",
            "type":"Public Place"
        }
    ],
    "sg:phone":"+1 303 935 2489",
    "sg:postcode":"80219",
    "sg:province":"CO",
    "sg:tags":[
        "high",
        "middle",
        "elementary"
    ],
    "wof:name":"Schools Public",
    "wof:placetype":"venue"
},
  "geometry": {"coordinates":[-105.044792,39.672954],"type":"Point"}
}