{
  "type": "Feature",
  "properties": {
    "addr:full":"713 S Lemay Ave Fort Collins CO 80524",
    "addr:housenumber":"713",
    "addr:postcode":"80524",
    "addr:street":"S Lemay Ave",
    "iso:country":"US",
    "sg:address":"713 S Lemay Ave",
    "sg:city":"Fort Collins",
    "sg:classifiers":[
        {
            "category":"Banks & Credit Unions",
            "subcategory":"Bank",
            "type":"Services"
        }
    ],
    "sg:phone":"+1 970 490 2121",
    "sg:postcode":"80524",
    "sg:province":"CO",
    "sg:tags":[
        "commercial"
    ],
    "wof:name":"Centennial Bank Holdings",
    "wof:placetype":"venue"
},
  "geometry": {"coordinates":[-105.057954,40.576123],"type":"Point"}
}