{
  "type": "Feature",
  "properties": {
    "iso:country":"US",
    "sg:address":"20730 Co Rd 31",
    "sg:city":"La Salle",
    "sg:classifiers":[
        {
            "category":"Real Estate",
            "subcategory":"Real Estate Operator",
            "type":"Services"
        }
    ],
    "sg:phone":"+1 970 737 2256",
    "sg:postcode":"80645",
    "sg:province":"CO",
    "sg:tags":[
        "property",
        "lessor"
    ],
    "wof:name":"Ed Fritzler",
    "wof:placetype":"venue"
},
  "geometry": {"coordinates":[-104.77303999999999,40.29742],"type":"Point"}
}