{
  "type": "Feature",
  "properties": {
    "iso:country":"US",
    "sg:address":"5384 S Rifle Ct",
    "sg:city":"Aurora",
    "sg:classifiers":[
        {
            "category":"Building & Trades",
            "subcategory":"Construction",
            "type":"Services"
        }
    ],
    "sg:phone":"+1 303 766 2314",
    "sg:postcode":"80015",
    "sg:province":"CO",
    "sg:tags":[
        "hanging",
        "contractor"
    ],
    "wof:name":"Rocky Mountain Custom Walls",
    "wof:placetype":"venue"
},
  "geometry": {"coordinates":[-104.786068,39.619585],"type":"Point"}
}