{
  "type": "Feature",
  "properties": {
    "iso:country":"US",
    "sg:address":"7860 E Berry Pl",
    "sg:city":"Englewood",
    "sg:classifiers":[
        {
            "category":"Banks & Credit Unions",
            "subcategory":"Financial Services",
            "type":"Services"
        }
    ],
    "sg:phone":"+1 303 488 9983",
    "sg:postcode":"80111",
    "sg:province":"CO",
    "sg:tags":[
        "investment",
        "closed"
    ],
    "wof:name":"Fountainhead Resources Ltd A",
    "wof:placetype":"venue"
},
  "geometry": {"coordinates":[-104.898869,39.615615],"type":"Point"}
}