{
  "type": "Feature",
  "properties": {
    "iso:country":"US",
    "sg:address":"2577 E 79th Ave",
    "sg:city":"Denver",
    "sg:classifiers":[
        {
            "category":"Retail",
            "subcategory":"Auto Repair",
            "type":"Services"
        }
    ],
    "sg:phone":"+1 303 287 1722",
    "sg:postcode":"80229",
    "sg:province":"CO",
    "sg:tags":[
        "repairing",
        "automobile"
    ],
    "wof:name":"Penny Lane Salvage & Auto",
    "wof:placetype":"venue"
},
  "geometry": {"coordinates":[-104.955473,39.839953],"type":"Point"}
}