{
  "type": "Feature",
  "properties": {
    "addr:full":"7043 Stinson Dr Colorado Springs CO 80920",
    "addr:housenumber":"7043",
    "addr:postcode":"80920",
    "addr:street":"Stinson Dr",
    "iso:country":"US",
    "sg:address":"7043 Stinson Dr",
    "sg:city":"Colorado Springs",
    "sg:classifiers":[
        {
            "category":"Utilities",
            "subcategory":"Mobile Phone",
            "type":"Services"
        }
    ],
    "sg:phone":"+1 303 584 6382",
    "sg:postcode":"80920",
    "sg:province":"CO",
    "sg:tags":[
        "communication",
        "radiotelephone"
    ],
    "wof:name":"World Count",
    "wof:placetype":"venue"
},
  "geometry": {"coordinates":[-104.784452,38.933333],"type":"Point"}
}