{
  "type": "Feature",
  "properties": {
    "addr:full":"710 E 25th Ave Denver CO 80205",
    "addr:housenumber":"710",
    "addr:postcode":"80205",
    "addr:street":"E 25Th Ave",
    "iso:country":"US",
    "sg:address":"710 E 25th Ave",
    "sg:city":"Denver",
    "sg:classifiers":[
        {
            "category":"Education",
            "subcategory":"Junior College",
            "type":"Public Place"
        }
    ],
    "sg:phone":"+1 303 832 6393",
    "sg:postcode":"80205",
    "sg:province":"CO",
    "sg:tags":[
        "technical",
        "institute"
    ],
    "wof:name":"Institute-Global Scholarship",
    "wof:placetype":"venue"
},
  "geometry": {"coordinates":[-104.97705000000001,39.75316],"type":"Point"}
}