{
  "type": "Feature",
  "properties": {
    "iso:country":"US",
    "sg:address":"15375 State Hwy 144",
    "sg:city":"Fort Morgan",
    "sg:classifiers":[
        {
            "category":"Home & Garden",
            "subcategory":"Garden Supply",
            "type":"Retail Goods"
        }
    ],
    "sg:phone":"+1 970 867 6575",
    "sg:postcode":"80701",
    "sg:province":"CO",
    "sg:tags":[
        "lawn",
        "mower"
    ],
    "wof:name":"Denny's Small Engine & Saw Shp",
    "wof:placetype":"venue"
},
  "geometry": {"coordinates":[-103.860213,40.27605],"type":"Point"}
}