{
  "type": "Feature",
  "properties": {
    "addr:full":"5708 Ammons St Arvada CO 80002",
    "addr:postcode":"5708;80002",
    "addr:street":"Ammons St",
    "iso:country":"US",
    "sg:address":"5708 Ammons St",
    "sg:city":"Arvada",
    "sg:classifiers":[
        {
            "category":"Building & Trades",
            "subcategory":"Construction",
            "type":"Services"
        }
    ],
    "sg:phone":"+1 303 431 0860",
    "sg:postcode":"80002",
    "sg:province":"CO",
    "sg:tags":[
        "general",
        "contractor"
    ],
    "wof:name":"Pats Construction Service",
    "wof:placetype":"venue"
},
  "geometry": {"coordinates":[-105.087194,39.801872],"type":"Point"}
}