{
  "type": "Feature",
  "properties": {
    "addr:full":"34305 Ranchero Rd Evergreen CO 80439",
    "addr:housenumber":"34305",
    "addr:postcode":"80439",
    "addr:street":"Ranchero Rd",
    "iso:country":"US",
    "sg:address":"34305 Ranchero Rd",
    "sg:city":"Evergreen",
    "sg:classifiers":[
        {
            "category":"Professional",
            "subcategory":"Management & Consulting",
            "type":"Services"
        }
    ],
    "sg:phone":"+1 303 526 2992",
    "sg:postcode":"80439",
    "sg:province":"CO",
    "sg:tags":[
        "consultant",
        "resource",
        "human"
    ],
    "wof:name":"Management Source Inc",
    "wof:placetype":"venue"
},
  "geometry": {"coordinates":[-105.38974,39.700826],"type":"Point"}
}