{
  "type": "Feature",
  "properties": {
    "addr:full":"7175 W Jefferson Ave Lakewood CO 80235",
    "addr:housenumber":"7175",
    "addr:postcode":"80235",
    "addr:street":"W Jefferson Ave",
    "iso:country":"US",
    "sg:address":"7175 W Jefferson Ave",
    "sg:city":"Lakewood",
    "sg:classifiers":[
        {
            "category":"Banks & Credit Unions",
            "subcategory":"Bank",
            "type":"Services"
        }
    ],
    "sg:phone":"+1 303 468 8630",
    "sg:postcode":"80235",
    "sg:province":"CO",
    "sg:tags":[
        "financing"
    ],
    "wof:name":"Empowered Finance",
    "wof:placetype":"venue"
},
  "geometry": {"coordinates":[-105.078765,39.649996],"type":"Point"}
}