{
  "type": "Feature",
  "properties": {
    "addr:full":"4862 S Robb St Littleton CO 80127",
    "addr:housenumber":"4862",
    "addr:postcode":"80127",
    "addr:street":"S Robb St",
    "iso:country":"US",
    "sg:address":"4862 S Robb St",
    "sg:city":"Littleton",
    "sg:classifiers":[
        {
            "category":"Home & Garden",
            "subcategory":"Hardware",
            "type":"Retail Goods"
        }
    ],
    "sg:phone":"+1 303 933 2580",
    "sg:postcode":"80127",
    "sg:province":"CO",
    "sg:tags":[
        "snap",
        "tool",
        "dealer",
        "for"
    ],
    "wof:name":"Shipp Corp 1 Inc",
    "wof:placetype":"venue"
},
  "geometry": {"coordinates":[-105.12674,39.628654],"type":"Point"}
}