{
  "type": "Feature",
  "properties": {
    "addr:full":"475 Russell Blvd Denver CO 80229",
    "addr:housenumber":"475",
    "addr:postcode":"80229",
    "addr:street":"Russell Blvd",
    "iso:country":"US",
    "sg:address":"475 Russell Blvd",
    "sg:city":"Denver",
    "sg:classifiers":[
        {
            "category":"Shopping",
            "subcategory":"Beauty & Cosmetics",
            "type":"Retail Goods"
        }
    ],
    "sg:phone":"+1 303 280 3886",
    "sg:postcode":"80229",
    "sg:province":"CO",
    "sg:tags":[
        "merchandise"
    ],
    "wof:name":"Rich and Famous Perfumes",
    "wof:placetype":"venue"
},
  "geometry": {"coordinates":[-104.981143,39.860926],"type":"Point"}
}