{
  "type": "Feature",
  "properties": {
    "addr:full":"219 Riverwood Dr Alamosa CO 81101",
    "addr:housenumber":"219",
    "addr:postcode":"81101",
    "addr:street":"Riverwood Dr",
    "iso:country":"US",
    "sg:address":"219 Riverwood Dr",
    "sg:city":"Alamosa",
    "sg:classifiers":[
        {
            "category":"Professional",
            "subcategory":"Accounting & Tax Preparation",
            "type":"Services"
        }
    ],
    "sg:phone":"+1 719 589 1909",
    "sg:postcode":"81101",
    "sg:province":"CO",
    "sg:tags":[
        "bookkeeping",
        "general"
    ],
    "wof:name":"Accounting & Billing Solution",
    "wof:placetype":"venue"
},
  "geometry": {"coordinates":[-105.88924900000001,37.488806],"type":"Point"}
}