{
  "type": "Feature",
  "properties": {
    "addr:full":"3900 S Lipan St Englewood CO 80110",
    "addr:housenumber":"3900",
    "addr:postcode":"80110",
    "addr:street":"S Lipan St",
    "iso:country":"US",
    "sg:address":"3900 S Lipan St",
    "sg:city":"Englewood",
    "sg:classifiers":[
        {
            "category":"Professional",
            "subcategory":"Management & Consulting",
            "type":"Services"
        }
    ],
    "sg:phone":"+1 303 762 0821",
    "sg:postcode":"80110",
    "sg:province":"CO",
    "sg:tags":[
        "business"
    ],
    "wof:name":"R A K Consulting Inc",
    "wof:placetype":"venue"
},
  "geometry": {"coordinates":[-105.001814,39.644012],"type":"Point"}
}