{
  "type": "Feature",
  "properties": {
    "iso:country":"US",
    "sg:address":"14278 Co Rd 3",
    "sg:city":"Longmont",
    "sg:classifiers":[
        {
            "category":"Building & Trades",
            "subcategory":"Construction",
            "type":"Services"
        }
    ],
    "sg:phone":"+1 303 678 1782",
    "sg:postcode":"80504",
    "sg:province":"CO",
    "sg:tags":[
        "contractor"
    ],
    "wof:name":"Sun River",
    "wof:placetype":"venue"
},
  "geometry": {"coordinates":[-105.036311,40.207236],"type":"Point"}
}