{
  "type": "Feature",
  "properties": {
    "iso:country":"US",
    "sg:address":"9910 Wadsworth Pkwy",
    "sg:city":"Broomfield",
    "sg:classifiers":[
        {
            "category":"Banks & Credit Unions",
            "subcategory":"Bank",
            "type":"Services"
        }
    ],
    "sg:phone":"+1 303 635 2100",
    "sg:postcode":"80021",
    "sg:province":"CO",
    "sg:tags":[
        "loan"
    ],
    "wof:name":"Advance America",
    "wof:placetype":"venue"
},
  "geometry": {"coordinates":[-105.09504800000001,39.876749],"type":"Point"}
}