{
  "type": "Feature",
  "properties": {
    "addr:full":"1622 Race St Denver CO 80206",
    "addr:housenumber":"1622",
    "addr:postcode":"80206",
    "addr:street":"Race St",
    "iso:country":"US",
    "sg:address":"1622 Race St",
    "sg:city":"Denver",
    "sg:classifiers":[
        {
            "category":"Professional",
            "subcategory":"Lawyer & Legal Services",
            "type":"Services"
        }
    ],
    "sg:phone":"+1 303 333 8977",
    "sg:postcode":"80206",
    "sg:province":"CO",
    "sg:tags":[
        "attorney"
    ],
    "wof:name":"Jeanne Busacca Law Office",
    "wof:placetype":"venue"
},
  "geometry": {"coordinates":[-104.96339,39.742862],"type":"Point"}
}