{
  "type": "Feature",
  "properties": {
    "addr:full":"3350 N Union Blvd Colorado Springs CO 80907",
    "addr:housenumber":"3350",
    "addr:postcode":"80907",
    "addr:street":"N Union Blvd",
    "iso:country":"US",
    "sg:address":"3350 N Union Blvd",
    "sg:city":"Colorado Springs",
    "sg:classifiers":[
        {
            "category":"Wholesale",
            "subcategory":"Farm Supplies",
            "type":"Manufacturing & Wholesale Goods"
        }
    ],
    "sg:phone":"+1 719 596 1819",
    "sg:postcode":"80907",
    "sg:province":"CO",
    "sg:tags":[
        "regulation",
        "merchandise"
    ],
    "wof:name":"Wild Birds Unlimited",
    "wof:placetype":"venue"
},
  "geometry": {"coordinates":[-104.79529599999999,38.87788],"type":"Point"}
}