{
  "type": "Feature",
  "properties": {
    "iso:country":"US",
    "sg:address":"415 Main St",
    "sg:city":"Lyons",
    "sg:classifiers":[
        {
            "category":"Manufacturing",
            "subcategory":"Tools & Machinery",
            "type":"Manufacturing & Wholesale Goods"
        }
    ],
    "sg:phone":"+1 303 823 5902",
    "sg:postcode":"80540",
    "sg:province":"CO",
    "sg:tags":[
        "mold"
    ],
    "wof:name":"Horizon Precision Tooling",
    "wof:placetype":"venue"
},
  "geometry": {"coordinates":[-105.27145299999999,40.224623],"type":"Point"}
}