{
  "type": "Feature",
  "properties": {
    "addr:full":"25100 US Hwy 50 Pueblo CO 81006",
    "addr:housenumber":"25100",
    "addr:postcode":"81006",
    "addr:street":"Us Hwy 50",
    "iso:country":"US",
    "sg:address":"25100 US Hwy 50",
    "sg:city":"Pueblo",
    "sg:classifiers":[
        {
            "category":"Food & Beverages",
            "subcategory":"Groceries & Convenience Stores",
            "type":"Retail Goods"
        }
    ],
    "sg:phone":"+1 719 542 3360",
    "sg:postcode":"81006",
    "sg:province":"CO",
    "wof:name":"J R's Country Store",
    "wof:placetype":"venue"
},
  "geometry": {"coordinates":[-104.535876,38.274086],"type":"Point"}
}