{
  "type": "Feature",
  "properties": {
    "addr:full":"5482 Hwy 348 Olathe CO 81425",
    "addr:housenumber":"5482",
    "addr:postcode":"81425",
    "addr:street":"Hwy 348",
    "iso:country":"US",
    "sg:address":"5482 Hwy 348",
    "sg:city":"Olathe",
    "sg:classifiers":[
        {
            "category":"Manufacturing",
            "subcategory":"Food",
            "type":"Manufacturing & Wholesale Goods"
        }
    ],
    "sg:phone":"+1 970 323 6224",
    "sg:postcode":"81425",
    "sg:province":"CO",
    "sg:tags":[
        "winery"
    ],
    "wof:name":"Cottonwood Cellars Inc",
    "wof:placetype":"venue"
},
  "geometry": {"coordinates":[-108.05873,38.614155],"type":"Point"}
}