{
  "type": "Feature",
  "properties": {
    "addr:full":"5560 S Parker Rd Aurora CO 80015",
    "addr:housenumber":"5560",
    "addr:postcode":"80015",
    "addr:street":"S Parker Rd",
    "iso:country":"US",
    "sg:address":"5560 S Parker Rd",
    "sg:city":"Aurora",
    "sg:classifiers":[
        {
            "category":"Home & Garden",
            "subcategory":"Home Furnishings",
            "type":"Retail Goods"
        }
    ],
    "sg:phone":"+1 303 690 5600",
    "sg:postcode":"80015",
    "sg:province":"CO",
    "sg:tags":[
        "linen"
    ],
    "wof:name":"Bed Bath & Beyond",
    "wof:placetype":"venue"
},
  "geometry": {"coordinates":[-104.81846299999999,39.617243],"type":"Point"}
}