{
  "type": "Feature",
  "properties": {
    "iso:country":"US",
    "sg:address":"655 Weaver Park Rd",
    "sg:city":"Longmont",
    "sg:classifiers":[
        {
            "category":"Building & Trades",
            "subcategory":"Construction",
            "type":"Services"
        }
    ],
    "sg:phone":"+1 303 772 2607",
    "sg:postcode":"80501",
    "sg:province":"CO",
    "sg:tags":[
        "specializing",
        "new",
        "contractor",
        "general"
    ],
    "wof:name":"Daystar Enterprises",
    "wof:placetype":"venue"
},
  "geometry": {"coordinates":[-105.079795,40.162308],"type":"Point"}
}