{
  "type": "Feature",
  "properties": {
    "addr:full":"640 S Academy Blvd Colorado Springs CO 80910",
    "addr:housenumber":"640",
    "addr:postcode":"80910",
    "addr:street":"S Academy Blvd",
    "iso:country":"US",
    "sg:address":"640 S Academy Blvd",
    "sg:city":"Colorado Springs",
    "sg:classifiers":[
        {
            "category":"Professional",
            "subcategory":"Accounting & Tax Preparation",
            "type":"Services"
        }
    ],
    "sg:phone":"+1 719 622 0800",
    "sg:postcode":"80910",
    "sg:province":"CO",
    "sg:tags":[
        "return",
        "filing"
    ],
    "sg:website":"www.jacksonhewitt.com",
    "wof:name":"Jackson Hewitt Tax Svc",
    "wof:placetype":"venue"
},
  "geometry": {"coordinates":[-104.757544,38.824375],"type":"Point"}
}