{
  "type": "Feature",
  "properties": {
    "iso:country":"US",
    "sg:address":"717 Whedbee St",
    "sg:city":"Fort Collins",
    "sg:classifiers":[
        {
            "category":"Organizations",
            "subcategory":"Religious Organization",
            "type":"Services"
        }
    ],
    "sg:phone":"+1 970 484 4701",
    "sg:postcode":"80524",
    "sg:province":"CO",
    "sg:tags":[
        "church"
    ],
    "sg:website":"www.victoryfc.org",
    "wof:name":"Victory Chapel",
    "wof:placetype":"venue"
},
  "geometry": {"coordinates":[-105.070243,40.577626],"type":"Point"}
}