{
  "type": "Feature",
  "properties": {
    "iso:country":"US",
    "sg:address":"1234 S Uvalda St",
    "sg:city":"Aurora",
    "sg:classifiers":[
        {
            "category":"Communications",
            "subcategory":"Film & Video Production",
            "type":"Services"
        }
    ],
    "sg:phone":"+1 303 929 4649",
    "sg:postcode":"80012",
    "sg:province":"CO",
    "sg:tags":[
        "taping"
    ],
    "wof:name":"A Nu Vision Production",
    "wof:placetype":"venue"
},
  "geometry": {"coordinates":[-104.83875500000001,39.691943],"type":"Point"}
}