{
  "type": "Feature",
  "properties": {
    "iso:country":"US",
    "sg:address":"11611 E 51st Ave",
    "sg:city":"Denver",
    "sg:classifiers":[
        {
            "category":"Professional",
            "subcategory":"Advertising",
            "type":"Services"
        }
    ],
    "sg:phone":"+1 303 307 4203",
    "sg:postcode":"80239",
    "sg:province":"CO",
    "sg:tags":[
        "mailing",
        "shipping"
    ],
    "sg:website":"www.ontargetmail.net",
    "wof:name":"On Target Marketing LLC",
    "wof:placetype":"venue"
},
  "geometry": {"coordinates":[-104.853717,39.790407],"type":"Point"}
}