{
  "type": "Feature",
  "properties": {
    "addr:full":"Early Learning Cente Denver CO 80202",
    "addr:postcode":"80202",
    "iso:country":"US",
    "sg:address":"Early Learning Cente",
    "sg:city":"Denver",
    "sg:classifiers":[
        {
            "category":"Social Services",
            "subcategory":"Child Care",
            "type":"Services"
        },
        {
            "category":"Education",
            "subcategory":"Preschool",
            "type":"Public Place"
        },
        {
            "category":"Education",
            "subcategory":"School",
            "type":"Public Place"
        }
    ],
    "sg:phone":"+1 303 388 7012",
    "sg:postcode":"80202",
    "sg:province":"CO",
    "sg:tags":[
        "elementary",
        "day"
    ],
    "wof:name":"Augustana Lutheran Church Elca",
    "wof:placetype":"venue"
},
  "geometry": {"coordinates":[-104.99574699999999,39.749758],"type":"Point"}
}