{
  "type": "Feature",
  "properties": {
    "iso:country":"US",
    "sg:address":"6608 W Weaver Ave",
    "sg:city":"Littleton",
    "sg:classifiers":[
        {
            "category":"Wholesale",
            "subcategory":"Sporting Goods",
            "type":"Manufacturing & Wholesale Goods"
        }
    ],
    "sg:phone":"+1 303 794 6966",
    "sg:postcode":"80123",
    "sg:province":"CO",
    "wof:name":"J & M Sales Inc",
    "wof:placetype":"venue"
},
  "geometry": {"coordinates":[-105.071309,39.599351],"type":"Point"}
}