{
  "type": "Feature",
  "properties": {
    "iso:country":"US",
    "sg:address":"6931 Co Rd 77",
    "sg:city":"Roggen",
    "sg:classifiers":[
        {
            "category":"Organizations",
            "subcategory":"Community Association",
            "type":"Services"
        }
    ],
    "sg:phone":"+1 303 849 5263",
    "sg:postcode":"80652",
    "sg:province":"CO",
    "sg:tags":[
        "fraternal"
    ],
    "wof:name":"Knights Of Columbus",
    "wof:placetype":"venue"
},
  "geometry": {"coordinates":[-104.33850700000001,40.09313],"type":"Point"}
}