{
  "type": "Feature",
  "properties": {
    "addr:full":"20870 US Hwy 34 Fort Morgan CO 80701",
    "addr:postcode":"20870;80701",
    "addr:street":"Us Hwy 34",
    "iso:country":"US",
    "sg:address":"20870 US Hwy 34",
    "sg:city":"Fort Morgan",
    "sg:classifiers":[
        {
            "category":"Building & Trades",
            "subcategory":"Construction",
            "type":"Services"
        }
    ],
    "sg:phone":"+1 970 542 1700",
    "sg:postcode":"80701",
    "sg:province":"CO",
    "sg:tags":[
        "house"
    ],
    "wof:name":"Wardcraft Homes",
    "wof:placetype":"venue"
},
  "geometry": {"coordinates":[-103.756941,40.253898],"type":"Point"}
}