{
  "type": "Feature",
  "properties": {
    "addr:full":"6435 E 69th Pl Commerce City CO 80022",
    "addr:housenumber":"6435",
    "addr:postcode":"80022",
    "addr:street":"E 69Th Pl",
    "iso:country":"US",
    "sg:address":"6435 E 69th Pl",
    "sg:city":"Commerce City",
    "sg:classifiers":[
        {
            "category":"Local Transit",
            "type":"Transportation"
        }
    ],
    "sg:phone":"+1 303 594 7124",
    "sg:postcode":"80022",
    "sg:province":"CO",
    "sg:tags":[
        "airport"
    ],
    "wof:name":"Doncor Limousine",
    "wof:placetype":"venue"
},
  "geometry": {"coordinates":[-104.91301900000001,39.823198],"type":"Point"}
}