{
  "type": "Feature",
  "properties": {
    "iso:country":"US",
    "sg:address":"17022 E Arkansas Dr",
    "sg:city":"Aurora",
    "sg:classifiers":[
        {
            "category":"Retail",
            "subcategory":"Repair Shop",
            "type":"Services"
        }
    ],
    "sg:phone":"+1 303 524 3837",
    "sg:postcode":"80017",
    "sg:province":"CO",
    "sg:tags":[
        "freezers-repair",
        "refrigerator"
    ],
    "wof:name":"Victory Air, Inc",
    "wof:placetype":"venue"
},
  "geometry": {"coordinates":[-104.789798,39.691002],"type":"Point"}
}