{
  "type": "Feature",
  "properties": {
    "iso:country":"US",
    "sg:address":"1851 N Circle Dr",
    "sg:city":"Colorado Springs",
    "sg:classifiers":[
        {
            "category":"Retail",
            "subcategory":"Repair Shop",
            "type":"Services"
        }
    ],
    "sg:phone":"+1 719 475 2545",
    "sg:postcode":"80909",
    "sg:province":"CO",
    "sg:tags":[
        "repairing",
        "speaker"
    ],
    "wof:name":"SRS Enterprises",
    "wof:placetype":"venue"
},
  "geometry": {"coordinates":[-104.775666,38.857904],"type":"Point"}
}