{
  "type": "Feature",
  "properties": {
    "iso:country":"US",
    "sg:address":"5599 Nelson Rd",
    "sg:city":"Longmont",
    "sg:classifiers":[
        {
            "category":"Professional",
            "type":"Services"
        }
    ],
    "sg:phone":"+1 303 772 2207",
    "sg:postcode":"80503",
    "sg:province":"CO",
    "wof:name":"North Tollgate Ditch Co",
    "wof:placetype":"venue"
},
  "geometry": {"coordinates":[-105.221601,40.152279],"type":"Point"}
}