{
  "type": "Feature",
  "properties": {
    "iso:country":"US",
    "sg:address":"510 S Pierce Ave",
    "sg:city":"Louisville",
    "sg:classifiers":[
        {
            "category":"Professional",
            "subcategory":"Computer Services",
            "type":"Services"
        }
    ],
    "sg:phone":"+1 303 428 7253",
    "sg:postcode":"80027",
    "sg:province":"CO",
    "sg:tags":[
        "peripheral",
        "design",
        "system",
        "mfg"
    ],
    "wof:name":"Ccsi Inc",
    "wof:placetype":"venue"
},
  "geometry": {"coordinates":[-105.12194700000001,39.96228],"type":"Point"}
}