{
  "type": "Feature",
  "properties": {
    "addr:full":"4331 Blair Rd Whitewater CO 81527",
    "addr:housenumber":"4331",
    "addr:postcode":"81527",
    "addr:street":"Blair Rd",
    "iso:country":"US",
    "sg:address":"4331 Blair Rd",
    "sg:city":"Whitewater",
    "sg:classifiers":[
        {
            "category":"Recreation",
            "type":"Entertainment"
        }
    ],
    "sg:phone":"+1 970 242 4008",
    "sg:postcode":"81527",
    "sg:province":"CO",
    "sg:tags":[
        "stable"
    ],
    "wof:name":"Mt Garfield Riding Stables",
    "wof:placetype":"venue"
},
  "geometry": {"coordinates":[-108.41691299999999,38.971357],"type":"Point"}
}