{
  "type": "Feature",
  "properties": {
    "addr:full":"5616 S Gibraltar Way Aurora CO 80015",
    "addr:housenumber":"5616",
    "addr:postcode":"80015",
    "addr:street":"S Gibraltar Way",
    "iso:country":"US",
    "sg:address":"5616 S Gibraltar Way",
    "sg:city":"Aurora",
    "sg:classifiers":[
        {
            "category":"Manufacturing",
            "subcategory":"Tools & Machinery",
            "type":"Manufacturing & Wholesale Goods"
        }
    ],
    "sg:phone":"+1 720 870 0550",
    "sg:postcode":"80015",
    "sg:province":"CO",
    "sg:tags":[
        "industrial",
        "mfg"
    ],
    "wof:name":"Factek LLC",
    "wof:placetype":"venue"
},
  "geometry": {"coordinates":[-104.755094,39.615326],"type":"Point"}
}