{
  "type": "Feature",
  "properties": {
    "addr:full":"615 White Ave Grand Junction CO 81501",
    "addr:housenumber":"615",
    "addr:postcode":"81501",
    "addr:street":"White Ave",
    "iso:country":"US",
    "sg:address":"615 White Ave",
    "sg:city":"Grand Junction",
    "sg:classifiers":[
        {
            "category":"Banks & Credit Unions",
            "subcategory":"Bank",
            "type":"Services"
        }
    ],
    "sg:phone":"+1 970 255 6688",
    "sg:postcode":"81501",
    "sg:province":"CO",
    "sg:tags":[
        "loan",
        "broker"
    ],
    "wof:name":"C & C Lending",
    "wof:placetype":"venue"
},
  "geometry": {"coordinates":[-108.56123100000001,39.069196],"type":"Point"}
}