{
  "type": "Feature",
  "properties": {
    "iso:country":"US",
    "sg:address":"1358 Luna Dr",
    "sg:city":"Fountain",
    "sg:classifiers":[
        {
            "category":"Wholesale",
            "subcategory":"Non-durable Goods",
            "type":"Manufacturing & Wholesale Goods"
        }
    ],
    "sg:phone":"+1 719 390 7274",
    "sg:postcode":"80817",
    "sg:province":"CO",
    "sg:tags":[
        "specialty",
        "mfg"
    ],
    "wof:name":"Vernon Company",
    "wof:placetype":"venue"
},
  "geometry": {"coordinates":[-104.732947,38.732598],"type":"Point"}
}