{
  "type": "Feature",
  "properties": {
    "addr:full":"7197 Cherry St Commerce City CO 80022",
    "addr:housenumber":"7197",
    "addr:postcode":"80022",
    "addr:street":"Cherry St",
    "iso:country":"US",
    "sg:address":"7197 Cherry St",
    "sg:city":"Commerce City",
    "sg:classifiers":[
        {
            "category":"Railroad",
            "type":"Transportation"
        }
    ],
    "sg:phone":"+1 303 289 5564",
    "sg:postcode":"80022",
    "sg:province":"CO",
    "sg:tags":[
        "operator",
        "line"
    ],
    "wof:name":"R R Juhl Inc",
    "wof:placetype":"venue"
},
  "geometry": {"coordinates":[-104.933939,39.823652],"type":"Point"}
}