{
  "type": "Feature",
  "properties": {
    "iso:country":"US",
    "sg:address":"1600 Bluff St",
    "sg:city":"Delta",
    "sg:classifiers":[
        {
            "category":"Food & Beverages",
            "subcategory":"Groceries & Convenience Stores",
            "type":"Retail Goods"
        }
    ],
    "sg:phone":"+1 970 874 4728",
    "sg:postcode":"81416",
    "sg:province":"CO",
    "wof:name":"Stop & Save",
    "wof:placetype":"venue"
},
  "geometry": {"coordinates":[-108.06501,38.726462],"type":"Point"}
}