{
  "type": "Feature",
  "properties": {
    "iso:country":"US",
    "sg:address":"658 Apricot Ln",
    "sg:city":"Delta",
    "sg:classifiers":[
        {
            "category":"Restaurant",
            "type":"Food & Drink"
        }
    ],
    "sg:phone":"+1 970 874 2982",
    "sg:postcode":"81416",
    "sg:province":"CO",
    "sg:tags":[
        "eating"
    ],
    "wof:name":"Sem Chrean",
    "wof:placetype":"venue"
},
  "geometry": {"coordinates":[-108.030688,38.739983],"type":"Point"}
}