{
  "type": "Feature",
  "properties": {
    "addr:full":"3658 Milwaukee St Denver CO 80205",
    "addr:housenumber":"3658",
    "addr:postcode":"80205",
    "addr:street":"Milwaukee St",
    "iso:country":"US",
    "sg:address":"3658 Milwaukee St",
    "sg:city":"Denver",
    "sg:classifiers":[
        {
            "category":"Professional",
            "type":"Services"
        }
    ],
    "sg:phone":"+1 720 941 8472",
    "sg:postcode":"80205",
    "sg:province":"CO",
    "sg:tags":[
        "establishment"
    ],
    "wof:name":"Fuller & Co",
    "wof:placetype":"venue"
},
  "geometry": {"coordinates":[-104.952331,39.767409],"type":"Point"}
}