{
  "type": "Feature",
  "properties": {
    "iso:country":"US",
    "sg:address":"7301 Federal Blvd",
    "sg:city":"Westminster",
    "sg:classifiers":[
        {
            "category":"Banks & Credit Unions",
            "subcategory":"Bank",
            "type":"Services"
        }
    ],
    "sg:phone":"+1 303 759 0111",
    "sg:postcode":"80030",
    "sg:province":"CO",
    "sg:tags":[
        "state",
        "commercial"
    ],
    "sg:website":"www.bankone.com",
    "wof:name":"Bank One",
    "wof:placetype":"venue"
},
  "geometry": {"coordinates":[-105.025104,39.829048],"type":"Point"}
}