{
  "type": "Feature",
  "properties": {
    "iso:country":"US",
    "sg:address":"5291 E 60th Ave",
    "sg:city":"Commerce City",
    "sg:classifiers":[
        {
            "category":"Government",
            "subcategory":"Office",
            "type":"Public Place"
        }
    ],
    "sg:phone":"+1 303 289 3628",
    "sg:postcode":"80022",
    "sg:province":"CO",
    "sg:tags":[
        "city",
        "taxation"
    ],
    "sg:website":"www.ci.commerce-city.co.us",
    "wof:name":"Commerce City Sales Tax Info",
    "wof:placetype":"venue"
},
  "geometry": {"coordinates":[-104.928072,39.805624],"type":"Point"}
}