{
  "type": "Feature",
  "properties": {
    "addr:full":"12441 W Quinn Dr Morrison CO 80465",
    "addr:housenumber":"12441",
    "addr:postcode":"80465",
    "addr:street":"W Quinn Dr",
    "iso:country":"US",
    "sg:address":"12441 W Quinn Dr",
    "sg:city":"Morrison",
    "sg:classifiers":[
        {
            "category":"Building & Trades",
            "subcategory":"Landscaping Services",
            "type":"Services"
        }
    ],
    "sg:phone":"+1 303 904 9490",
    "sg:postcode":"80465",
    "sg:province":"CO",
    "wof:name":"Irriscape Inc",
    "wof:placetype":"venue"
},
  "geometry": {"coordinates":[-105.135498,39.638163],"type":"Point"}
}