{
  "type": "Feature",
  "properties": {
    "iso:country":"US",
    "sg:address":"590 Havana St",
    "sg:city":"Aurora",
    "sg:classifiers":[
        {
            "category":"Autos & Motor Vehicles",
            "subcategory":"Automobile Sales",
            "type":"Retail Goods"
        }
    ],
    "sg:phone":"+1 303 341 5500",
    "sg:postcode":"80010",
    "sg:province":"CO",
    "sg:tags":[
        "car",
        "dealer"
    ],
    "wof:name":"Kids Auto",
    "wof:placetype":"venue"
},
  "geometry": {"coordinates":[-104.865836,39.724221],"type":"Point"}
}