{
  "type": "Feature",
  "properties": {
    "addr:full":"125 E 32nd St Durango CO 81301",
    "addr:housenumber":"125",
    "addr:postcode":"co 81301",
    "addr:street":"E 32Nd St",
    "iso:country":"US",
    "sg:address":"125 E 32nd St",
    "sg:city":"Durango",
    "sg:classifiers":[
        {
            "category":"Banks & Credit Unions",
            "subcategory":"Bank",
            "type":"Services"
        }
    ],
    "sg:phone":"+1 970 375 0107",
    "sg:postcode":"81301",
    "sg:province":"CO",
    "sg:tags":[
        "loan",
        "real estate"
    ],
    "wof:name":"Capital Home Mortgage",
    "wof:placetype":"venue"
},
  "geometry": {"coordinates":[-107.870302,37.300501],"type":"Point"}
}