{
  "type": "Feature",
  "properties": {
    "iso:country":"US",
    "sg:address":"2124 Hooker St",
    "sg:city":"Denver",
    "sg:classifiers":[
        {
            "category":"Retail",
            "subcategory":"Veterinary Services",
            "type":"Services"
        }
    ],
    "sg:phone":"+1 303 604 9696",
    "sg:postcode":"80211",
    "sg:province":"CO",
    "wof:name":"Mobile Meow",
    "wof:placetype":"venue"
},
  "geometry": {"coordinates":[-105.02831,39.7497],"type":"Point"}
}