{
  "type": "Feature",
  "properties": {
    "iso:country":"US",
    "sg:address":"2331 Hampshire Ct",
    "sg:city":"Fort Collins",
    "sg:classifiers":[
        {
            "category":"Professional",
            "subcategory":"Management & Consulting",
            "type":"Services"
        }
    ],
    "sg:phone":"+1 970 482 7575",
    "sg:postcode":"80526",
    "sg:province":"CO",
    "sg:tags":[
        "accident",
        "reconstruction"
    ],
    "wof:name":"Colorado Collision Consultants",
    "wof:placetype":"venue"
},
  "geometry": {"coordinates":[-105.12023499999999,40.553305],"type":"Point"}
}