{
  "type": "Feature",
  "properties": {
    "addr:full":"333 E Durant Ave Aspen CO 81611",
    "addr:housenumber":"333",
    "addr:postcode":"81611",
    "addr:street":"E Durant Ave",
    "iso:country":"US",
    "sg:address":"333 E Durant Ave",
    "sg:city":"Aspen",
    "sg:classifiers":[
        {
            "category":"Recreation",
            "type":"Entertainment"
        }
    ],
    "sg:phone":"+1 970 925 3555",
    "sg:postcode":"81611",
    "sg:province":"CO",
    "sg:tags":[
        "amusement"
    ],
    "wof:name":"Altitude Body Performance Ctr",
    "wof:placetype":"venue"
},
  "geometry": {"coordinates":[-106.821169,39.187607],"type":"Point"}
}