{
  "type": "Feature",
  "properties": {
    "iso:country":"US",
    "sg:address":"1019 8th St",
    "sg:city":"Golden",
    "sg:classifiers":[
        {
            "category":"Professional",
            "type":"Services"
        }
    ],
    "sg:phone":"+1 303 278 8505",
    "sg:postcode":"80401",
    "sg:province":"CO",
    "sg:tags":[
        "geophysicist"
    ],
    "sg:website":"www.stratasearch.com",
    "wof:name":"Stratasearch Corp",
    "wof:placetype":"venue"
},
  "geometry": {"coordinates":[-105.22787599999999,39.757441],"type":"Point"}
}