{
  "type": "Feature",
  "properties": {
    "addr:full":"1393 S Santa Fe Dr Denver CO 80223",
    "addr:housenumber":"1393",
    "addr:postcode":"80223",
    "addr:street":"S Santa Fe Dr",
    "iso:country":"US",
    "sg:address":"1393 S Santa Fe Dr",
    "sg:city":"Denver",
    "sg:classifiers":[
        {
            "category":"Home & Garden",
            "subcategory":"Building Materials",
            "type":"Retail Goods"
        }
    ],
    "sg:phone":"+1 303 989 8895",
    "sg:postcode":"80223",
    "sg:province":"CO",
    "sg:tags":[
        "equipment",
        "fixture",
        "lighting"
    ],
    "sg:website":"www.foothillslighting.com",
    "wof:name":"Foothills Lighting and Supply",
    "wof:placetype":"venue"
},
  "geometry": {"coordinates":[-104.99240399999999,39.691613],"type":"Point"}
}