{
  "type": "Feature",
  "properties": {
    "iso:country":"US",
    "sg:address":"407 N Santa Fe Ave",
    "sg:city":"Pueblo",
    "sg:classifiers":[
        {
            "category":"Bars & Pubs",
            "type":"Food & Drink"
        }
    ],
    "sg:phone":"+1 719 562 9417",
    "sg:postcode":"81003",
    "sg:province":"CO",
    "wof:name":"Deluxe Tavern",
    "wof:placetype":"venue"
},
  "geometry": {"coordinates":[-104.607133,38.271533],"type":"Point"}
}