{
  "type": "Feature",
  "properties": {
    "iso:country":"US",
    "sg:address":"1577 Co Rd 27",
    "sg:city":"Brighton",
    "sg:classifiers":[
        {
            "category":"Freight",
            "type":"Transportation"
        }
    ],
    "sg:phone":"+1 303 659 1497",
    "sg:postcode":"80603",
    "sg:province":"CO",
    "sg:tags":[
        "commercial",
        "storage",
        "general"
    ],
    "wof:name":"Highway 85 Self Storage",
    "wof:placetype":"venue"
},
  "geometry": {"coordinates":[-104.81341399999999,40.010842],"type":"Point"}
}