{
  "type": "Feature",
  "properties": {
    "iso:country":"US",
    "sg:address":"512 W Co Rd 10E",
    "sg:city":"Berthoud",
    "sg:classifiers":[
        {
            "category":"Building & Trades",
            "subcategory":"Construction",
            "type":"Services"
        }
    ],
    "sg:phone":"+1 303 775 2711",
    "sg:postcode":"80513",
    "sg:province":"CO",
    "sg:tags":[
        "home",
        "general",
        "contractor"
    ],
    "wof:name":"Rick Construction LLC",
    "wof:placetype":"venue"
},
  "geometry": {"coordinates":[-105.07829,40.327105],"type":"Point"}
}