{
  "type": "Feature",
  "properties": {
    "iso:country":"US",
    "sg:address":"2731 S Colorado Boulevard",
    "sg:city":"Denver",
    "sg:classifiers":[
        {
            "category":"Shopping",
            "subcategory":"Jewelry",
            "type":"Retail Goods"
        }
    ],
    "sg:phone":"+1 303 759 0848",
    "sg:postcode":"80222",
    "sg:province":"CO",
    "wof:name":"Molberg's Jewelers",
    "wof:placetype":"venue"
},
  "geometry": {"coordinates":[-104.940603,39.666396],"type":"Point"}
}