{
  "type": "Feature",
  "properties": {
    "iso:country":"US",
    "sg:address":"1320 College Ave",
    "sg:city":"Boulder",
    "sg:classifiers":[
        {
            "category":"Restaurant",
            "type":"Food & Drink"
        }
    ],
    "sg:menulink":"http://www.allmenus.com/co/boulder/4019-illegal-petes/menu/",
    "sg:phone":"+1 303 444 3055",
    "sg:postcode":"80302",
    "sg:province":"CO",
    "sg:tags":[
        "american"
    ],
    "wof:name":"Illegal Petes",
    "wof:placetype":"venue"
},
  "geometry": {"coordinates":[-105.275768,40.007301],"type":"Point"}
}