{
  "type": "Feature",
  "properties": {
    "addr:full":"5650 W 29th Ave Denver CO 80214",
    "addr:housenumber":"5650",
    "addr:postcode":"80214",
    "addr:street":"W 29Th Ave",
    "iso:country":"US",
    "sg:address":"5650 W 29th Ave",
    "sg:city":"Denver",
    "sg:classifiers":[
        {
            "category":"Food & Beverages",
            "subcategory":"Meat & Fish",
            "type":"Retail Goods"
        }
    ],
    "sg:phone":"+1 303 233 0757",
    "sg:postcode":"80214",
    "sg:province":"CO",
    "wof:name":"Wheat Ridge Poultry & Meat",
    "wof:placetype":"venue"
},
  "geometry": {"coordinates":[-105.058555,39.758421],"type":"Point"}
}