{
  "type": "Feature",
  "properties": {
    "iso:country":"US",
    "sg:address":"1017 San Juan St",
    "sg:city":"Trinidad",
    "sg:classifiers":[
        {
            "category":"Banks & Credit Unions",
            "subcategory":"Financial Services",
            "type":"Services"
        }
    ],
    "sg:phone":"+1 719 846 3429",
    "sg:postcode":"81082",
    "sg:province":"CO",
    "sg:tags":[
        "company",
        "holding"
    ],
    "wof:name":"Alscott Holdings LLC",
    "wof:placetype":"venue"
},
  "geometry": {"coordinates":[-104.518325,37.172094],"type":"Point"}
}