{
  "type": "Feature",
  "properties": {
    "iso:country":"US",
    "sg:address":"16475 E 40th Cir",
    "sg:city":"Aurora",
    "sg:classifiers":[
        {
            "category":"Travel",
            "subcategory":"Hotels & Motels",
            "type":"Entertainment"
        }
    ],
    "sg:phone":"+1 303 371 9393",
    "sg:postcode":"80011",
    "sg:province":"CO",
    "sg:tags":[
        "lodging"
    ],
    "sg:website":"http://www.hiltongardeninn.com",
    "wof:name":"Hilton Garden Inn Denver Airport",
    "wof:placetype":"venue"
},
  "geometry": {"coordinates":[-104.796129,39.769505],"type":"Point"}
}