{
  "type": "Feature",
  "properties": {
    "addr:full":"1750 Deer Creek Rd Monument CO 80132",
    "addr:housenumber":"1750",
    "addr:postcode":"80132",
    "addr:street":"Deer Creek Rd",
    "iso:country":"US",
    "sg:address":"1750 Deer Creek Rd",
    "sg:city":"Monument",
    "sg:classifiers":[
        {
            "category":"Organizations",
            "subcategory":"Religious Organization",
            "type":"Services"
        }
    ],
    "sg:phone":"+1 719 481 3600",
    "sg:postcode":"80132",
    "sg:province":"CO",
    "sg:tags":[
        "church"
    ],
    "sg:website":"www.trilakeschapel.org",
    "wof:name":"Tri Lakes Chapel",
    "wof:placetype":"venue"
},
  "geometry": {"coordinates":[-104.859672,39.105314],"type":"Point"}
}