{
  "type": "Feature",
  "properties": {
    "iso:country":"US",
    "sg:address":"330 Cottonwood Dr",
    "sg:city":"Silt",
    "sg:classifiers":[
        {
            "category":"Retail",
            "subcategory":"Repair Shop",
            "type":"Services"
        }
    ],
    "sg:phone":"+1 970 876 0336",
    "sg:postcode":"81652",
    "sg:province":"CO",
    "sg:tags":[
        "irrigation",
        "system",
        "related"
    ],
    "wof:name":"Pfaff Services Inc",
    "wof:placetype":"venue"
},
  "geometry": {"coordinates":[-107.665757,39.548559],"type":"Point"}
}