{
  "type": "Feature",
  "properties": {
    "addr:full":"7689 N Union Blvd Colorado Springs CO 80920",
    "addr:housenumber":"7689",
    "addr:postcode":"80920",
    "addr:street":"N Union Blvd",
    "iso:country":"US",
    "sg:address":"7689 N Union Blvd",
    "sg:city":"Colorado Springs",
    "sg:classifiers":[
        {
            "category":"Sports & Exercise",
            "subcategory":"Gym",
            "type":"Entertainment"
        }
    ],
    "sg:phone":"+1 719 260 8123",
    "sg:postcode":"80920",
    "sg:province":"CO",
    "sg:tags":[
        "club",
        "health",
        "studio",
        "gymnasium"
    ],
    "wof:name":"Curves For Women",
    "wof:placetype":"venue"
},
  "geometry": {"coordinates":[-104.774996,38.942038],"type":"Point"}
}