{
  "type": "Feature",
  "properties": {
    "iso:country":"US",
    "sg:address":"1106 Alamo St",
    "sg:city":"Trinidad",
    "sg:classifiers":[
        {
            "category":"Food & Beverages",
            "subcategory":"Liquor & Beverages",
            "type":"Retail Goods"
        }
    ],
    "sg:phone":"+1 719 846 7242",
    "sg:postcode":"81082",
    "sg:province":"CO",
    "sg:tags":[
        "grocery"
    ],
    "wof:name":"Ringos Fishers Peak Sprmkt",
    "wof:placetype":"venue"
},
  "geometry": {"coordinates":[-104.494851,37.159678],"type":"Point"}
}