{
  "type": "Feature",
  "properties": {
    "iso:country":"US",
    "sg:address":"42063 Ridge Rd",
    "sg:city":"Parker",
    "sg:classifiers":[
        {
            "category":"Building & Trades",
            "subcategory":"Pest Control",
            "type":"Services"
        }
    ],
    "sg:phone":"+1 303 884 9100",
    "sg:postcode":"80105",
    "sg:province":"CO",
    "wof:name":"ADC Animal Damage Control",
    "wof:placetype":"venue"
},
  "geometry": {"coordinates":[-104.20431499999999,39.477053],"type":"Point"}
}