{
  "type": "Feature",
  "properties": {
    "iso:country":"US",
    "sg:address":"1400 Market St",
    "sg:city":"Denver",
    "sg:classifiers":[
        {
            "category":"Manufacturing",
            "subcategory":"Electronics",
            "type":"Manufacturing & Wholesale Goods"
        }
    ],
    "sg:phone":"+1 303 302 1510",
    "sg:postcode":"80202",
    "sg:province":"CO",
    "sg:tags":[
        "equipment",
        "mfg",
        "communication"
    ],
    "wof:name":"Actv Inc (del Corp)",
    "wof:placetype":"venue"
},
  "geometry": {"coordinates":[-104.999489,39.748937],"type":"Point"}
}