{
  "type": "Feature",
  "properties": {
    "addr:full":"1103 S Prairie Ave Pueblo CO 81005",
    "addr:housenumber":"1103",
    "addr:postcode":"81005",
    "addr:street":"S Prairie Ave",
    "iso:country":"US",
    "sg:address":"1103 S Prairie Ave",
    "sg:city":"Pueblo",
    "sg:classifiers":[
        {
            "category":"Food & Beverages",
            "subcategory":"Specialty",
            "type":"Retail Goods"
        },
        {
            "category":"Shopping",
            "subcategory":"Gifts & Souvenirs",
            "type":"Retail Goods"
        }
    ],
    "sg:phone":"+1 719 561 9113",
    "sg:postcode":"81005",
    "sg:province":"CO",
    "sg:tags":[
        "tea",
        "coffee"
    ],
    "wof:name":"Dee's Too Gourmet",
    "wof:placetype":"venue"
},
  "geometry": {"coordinates":[-104.643862,38.24588],"type":"Point"}
}