{
  "type": "Feature",
  "properties": {
    "addr:full":"47630 County Rd Yuma CO 80758",
    "addr:housenumber":"47630",
    "addr:postcode":"80758",
    "addr:street":"County Rd",
    "iso:country":"US",
    "sg:address":"47630 County Rd",
    "sg:city":"Yuma",
    "sg:phone":"+1 970 848 2921",
    "sg:postcode":"80758",
    "sg:province":"CO",
    "sg:tags":[
        "farm",
        "corn",
        "wheat"
    ],
    "wof:name":"Peggy Brophy",
    "wof:placetype":"venue"
},
  "geometry": {"coordinates":[-102.070582,40.251215],"type":"Point"}
}