{
  "type": "Feature",
  "properties": {
    "addr:full":"12553 S Wamblee Valley Rd Conifer CO 80433",
    "addr:housenumber":"12553",
    "addr:postcode":"80433",
    "addr:street":"S Wamblee Valley Rd",
    "iso:country":"US",
    "sg:address":"12553 S Wamblee Valley Rd",
    "sg:city":"Conifer",
    "sg:classifiers":[
        {
            "category":"Wholesale",
            "subcategory":"Medical Equipment & Supplies",
            "type":"Manufacturing & Wholesale Goods"
        }
    ],
    "sg:phone":"+1 303 838 2407",
    "sg:postcode":"80433",
    "sg:province":"CO",
    "wof:name":"Conifer Medical Products LLC",
    "wof:placetype":"venue"
},
  "geometry": {"coordinates":[-105.333848,39.488],"type":"Point"}
}