{
  "type": "Feature",
  "properties": {
    "iso:country":"US",
    "sg:address":"8071 Wadsworth Blvd",
    "sg:city":"Arvada",
    "sg:classifiers":[
        {
            "category":"Coffee & Tea",
            "type":"Food & Drink"
        }
    ],
    "sg:menulink":"http://www.allmenus.com/co/northeast-jefferson/118314-starbucks-coffee/menu/",
    "sg:phone":"+1 303 432 8187",
    "sg:postcode":"80003",
    "sg:province":"CO",
    "sg:tags":[
        "american"
    ],
    "wof:name":"Starbucks Coffee",
    "wof:placetype":"venue"
},
  "geometry": {"coordinates":[-105.08238,39.844282],"type":"Point"}
}