{
  "type": "Feature",
  "properties": {
    "iso:country":"US",
    "sg:address":"42198 Co Rd 10",
    "sg:city":"Roggen",
    "sg:classifiers":[
        {
            "category":"Farming",
            "subcategory":"Livestock Farm",
            "type":"Manufacturing & Wholesale Goods"
        }
    ],
    "sg:phone":"+1 303 849 5310",
    "sg:postcode":"80652",
    "sg:province":"CO",
    "sg:tags":[
        "animal",
        "general"
    ],
    "wof:name":"Ka Ba Ranch LLC",
    "wof:placetype":"venue"
},
  "geometry": {"coordinates":[-104.26158,40.058539],"type":"Point"}
}