{
  "type": "Feature",
  "properties": {
    "addr:full":"1020 N Institute St Colorado Springs CO 80903",
    "addr:housenumber":"1020",
    "addr:postcode":"80903",
    "addr:street":"N Institute St",
    "iso:country":"US",
    "sg:address":"1020 N Institute St",
    "sg:city":"Colorado Springs",
    "sg:classifiers":[
        {
            "category":"Freight",
            "type":"Transportation"
        }
    ],
    "sg:phone":"+1 719 630 1830",
    "sg:postcode":"80903",
    "sg:province":"CO",
    "sg:tags":[
        "operator",
        "local",
        "trucking"
    ],
    "wof:name":"Time Stretchers of America",
    "wof:placetype":"venue"
},
  "geometry": {"coordinates":[-104.807624,38.848427],"type":"Point"}
}