{
  "type": "Feature",
  "properties": {
    "addr:full":"10341 Newcombe St Broomfield CO 80021",
    "addr:housenumber":"10341",
    "addr:postcode":"80021",
    "addr:street":"Newcombe St",
    "iso:country":"US",
    "sg:address":"10341 Newcombe St",
    "sg:city":"Broomfield",
    "sg:classifiers":[
        {
            "category":"Building & Trades",
            "subcategory":"Construction",
            "type":"Services"
        }
    ],
    "sg:phone":"+1 303 460 9792",
    "sg:postcode":"80021",
    "sg:province":"CO",
    "sg:tags":[
        "house"
    ],
    "wof:name":"Metro Home Repair & Carpet Clg",
    "wof:placetype":"venue"
},
  "geometry": {"coordinates":[-105.119607,39.883262],"type":"Point"}
}