{
  "type": "Feature",
  "properties": {
    "iso:country":"US",
    "sg:address":"88 E Agate Ave",
    "sg:city":"Granby",
    "sg:classifiers":[
        {
            "category":"Food & Beverages",
            "subcategory":"Liquor & Beverages",
            "type":"Retail Goods"
        }
    ],
    "sg:phone":"+1 970 887 2318",
    "sg:postcode":"80446",
    "sg:province":"CO",
    "wof:name":"R & J Liquor",
    "wof:placetype":"venue"
},
  "geometry": {"coordinates":[-105.940939,40.085506],"type":"Point"}
}