{
  "type": "Feature",
  "properties": {
    "iso:country":"US",
    "sg:address":"295 Vaughn St",
    "sg:city":"Aurora",
    "sg:classifiers":[
        {
            "category":"Freight",
            "type":"Transportation"
        }
    ],
    "sg:phone":"+1 303 564 7398",
    "sg:postcode":"80011",
    "sg:province":"CO",
    "sg:tags":[
        "operator",
        "local",
        "trucking"
    ],
    "wof:name":"Rk Global Inc",
    "wof:placetype":"venue"
},
  "geometry": {"coordinates":[-104.831459,39.720125],"type":"Point"}
}