{
  "type": "Feature",
  "properties": {
    "iso:country":"US",
    "sg:address":"309 W 11th Ave",
    "sg:city":"Denver",
    "sg:classifiers":[
        {
            "category":"Restaurant",
            "type":"Food & Drink"
        }
    ],
    "sg:phone":"+1 720 475 1471",
    "sg:postcode":"80204",
    "sg:province":"CO",
    "sg:tags":[
        "pizza"
    ],
    "sg:website":"denverpizzaco.com/",
    "wof:name":"Denver Pizza Company",
    "wof:placetype":"venue"
},
  "geometry": {"coordinates":[-104.99189699999999,39.733878],"type":"Point"}
}