{
  "type": "Feature",
  "properties": {
    "addr:full":"6325 E Platte Ave Colorado Springs CO 80915",
    "addr:housenumber":"6325",
    "addr:postcode":"80915",
    "addr:street":"E Platte Ave",
    "iso:country":"US",
    "sg:address":"6325 E Platte Ave",
    "sg:city":"Colorado Springs",
    "sg:classifiers":[
        {
            "category":"Building & Trades",
            "subcategory":"Plumbing",
            "type":"Services"
        }
    ],
    "sg:phone":"+1 719 638 7341",
    "sg:postcode":"80915",
    "sg:province":"CO",
    "sg:tags":[
        "plumbing",
        "contractor"
    ],
    "wof:name":"B & L Plumbing Inc",
    "wof:placetype":"venue"
},
  "geometry": {"coordinates":[-104.708646,38.838857],"type":"Point"}
}