{
  "type": "Feature",
  "properties": {
    "iso:country":"US",
    "sg:address":"30290 San Isbel Rd",
    "sg:city":"Buena Vista",
    "sg:phone":"+1 719 395 6196",
    "sg:postcode":"81211",
    "sg:province":"CO",
    "sg:tags":[
        "irrigation",
        "system"
    ],
    "wof:name":"Litvay Golf",
    "wof:placetype":"venue"
},
  "geometry": {"coordinates":[-106.215592,38.865756],"type":"Point"}
}