{
  "type": "Feature",
  "properties": {
    "iso:country":"US",
    "sg:address":"702 Grand Ave",
    "sg:city":"Glenwood Springs",
    "sg:classifiers":[
        {
            "category":"Restaurant",
            "type":"Food & Drink"
        }
    ],
    "sg:phone":"+1 970 945 9059",
    "sg:postcode":"81601",
    "sg:province":"CO",
    "wof:name":"Pepponinos Dining Room",
    "wof:placetype":"venue"
},
  "geometry": {"coordinates":[-107.324594,39.547795],"type":"Point"}
}