{
  "type": "Feature",
  "properties": {
    "iso:country":"US",
    "sg:address":"2223 S Monaco Pkwy Ste E6",
    "sg:city":"Denver",
    "sg:classifiers":[
        {
            "category":"Personal",
            "subcategory":"Beauty Salon",
            "type":"Services"
        }
    ],
    "sg:phone":"+1 303 758 1000",
    "sg:postcode":"80222",
    "sg:province":"CO",
    "sg:tags":[
        "hair"
    ],
    "sg:website":"www.perfectcuts.us",
    "wof:name":"Perfect Cuts",
    "wof:placetype":"venue"
},
  "geometry": {"coordinates":[-104.914117,39.676285],"type":"Point"}
}