{
  "type": "Feature",
  "properties": {
    "iso:country":"US",
    "sg:address":"3991 Evergreen Pkwy Access Rd",
    "sg:city":"Evergreen",
    "sg:classifiers":[
        {
            "category":"Autos & Motor Vehicles",
            "subcategory":"Auto Supplies",
            "type":"Retail Goods"
        }
    ],
    "sg:phone":"+1 303 674 6661",
    "sg:postcode":"80439",
    "sg:province":"CO",
    "sg:tags":[
        "automobile",
        "parts"
    ],
    "wof:name":"Mountain Auto Parts Inc",
    "wof:placetype":"venue"
},
  "geometry": {"coordinates":[-105.332346,39.639056],"type":"Point"}
}