{
  "type": "Feature",
  "properties": {
    "iso:country":"US",
    "sg:address":"5795 W 52nd Ave",
    "sg:city":"Denver",
    "sg:classifiers":[
        {
            "category":"Wholesale",
            "subcategory":"Durable Goods & Equipment",
            "type":"Manufacturing & Wholesale Goods"
        }
    ],
    "sg:phone":"+1 303 940 8000",
    "sg:postcode":"80212",
    "sg:province":"CO",
    "sg:tags":[
        "importer"
    ],
    "sg:website":"www.archerglass.com",
    "wof:name":"Archer Decorative Glass Corp",
    "wof:placetype":"venue"
},
  "geometry": {"coordinates":[-105.061468,39.791149],"type":"Point"}
}