{
  "type": "Feature",
  "properties": {
    "iso:country":"US",
    "sg:address":"4929 Broadway St",
    "sg:city":"Boulder",
    "sg:classifiers":[
        {
            "category":"Building & Trades",
            "subcategory":"Construction",
            "type":"Services"
        }
    ],
    "sg:phone":"+1 303 443 1163",
    "sg:postcode":"80304",
    "sg:province":"CO",
    "sg:tags":[
        "dry wall",
        "contractor"
    ],
    "wof:name":"Drywall Dimensions Inc",
    "wof:placetype":"venue"
},
  "geometry": {"coordinates":[-105.281931,40.064843],"type":"Point"}
}