{
  "type": "Feature",
  "properties": {
    "addr:full":"924 S Arcadia St Colorado Springs CO 80903",
    "addr:housenumber":"924",
    "addr:postcode":"80903",
    "addr:street":"S Arcadia St",
    "iso:country":"US",
    "sg:address":"924 S Arcadia St",
    "sg:city":"Colorado Springs",
    "sg:classifiers":[
        {
            "category":"Home & Garden",
            "subcategory":"Building Materials",
            "type":"Retail Goods"
        }
    ],
    "sg:phone":"+1 719 634 5874",
    "sg:postcode":"80903",
    "sg:province":"CO",
    "wof:name":"Colorado Paint Specialists",
    "wof:placetype":"venue"
},
  "geometry": {"coordinates":[-104.809715,38.819925],"type":"Point"}
}