{
  "type": "Feature",
  "properties": {
    "addr:full":"12 N 33rd St Colorado Springs CO 80904",
    "addr:housenumber":"12",
    "addr:postcode":"80904",
    "addr:street":"N 33Rd St",
    "iso:country":"US",
    "sg:address":"12 N 33rd St",
    "sg:city":"Colorado Springs",
    "sg:classifiers":[
        {
            "category":"Professional",
            "type":"Services"
        }
    ],
    "sg:phone":"+1 719 520 3992",
    "sg:postcode":"80904",
    "sg:province":"CO",
    "wof:name":"Outsource Channel Executives I",
    "wof:placetype":"venue"
},
  "geometry": {"coordinates":[-104.876063,38.857045],"type":"Point"}
}