{
  "type": "Feature",
  "properties": {
    "iso:country":"US",
    "sg:address":"22445 Rd K",
    "sg:city":"Cortez",
    "sg:classifiers":[
        {
            "category":"Wholesale",
            "subcategory":"Home Furnishings",
            "type":"Manufacturing & Wholesale Goods"
        }
    ],
    "sg:phone":"+1 970 799 0185",
    "sg:postcode":"81321",
    "sg:province":"CO",
    "sg:tags":[
        "closet",
        "accessory"
    ],
    "wof:name":"Home Enhancement Systems",
    "wof:placetype":"venue"
},
  "geometry": {"coordinates":[-108.63001300000001,37.356781],"type":"Point"}
}