{
  "type": "Feature",
  "properties": {
    "iso:country":"US",
    "sg:address":"611 N Nevada Ave",
    "sg:city":"Colorado Springs",
    "sg:classifiers":[
        {
            "category":"Health Services",
            "subcategory":"Health Practitioner",
            "type":"Services"
        }
    ],
    "sg:phone":"+1 719 633 6313",
    "sg:postcode":"80903",
    "sg:province":"CO",
    "sg:tags":[
        "acupuncture"
    ],
    "wof:name":"Angela D Gainer",
    "wof:placetype":"venue"
},
  "geometry": {"coordinates":[-104.821128,38.842178],"type":"Point"}
}