{
  "type": "Feature",
  "properties": {
    "iso:country":"US",
    "sg:address":"2025 W Stanford Ave",
    "sg:city":"Englewood",
    "sg:classifiers":[
        {
            "category":"Building & Trades",
            "subcategory":"Construction",
            "type":"Services"
        }
    ],
    "sg:phone":"+1 303 762 6237",
    "sg:postcode":"80110",
    "sg:province":"CO",
    "sg:tags":[
        "concrete",
        "contractor"
    ],
    "wof:name":"Badger Contractors LLC",
    "wof:placetype":"venue"
},
  "geometry": {"coordinates":[-105.009066,39.634966],"type":"Point"}
}