{
  "type": "Feature",
  "properties": {
    "iso:country":"US",
    "sg:address":"7585 W Arkansas Ave",
    "sg:city":"Lakewood",
    "sg:classifiers":[
        {
            "category":"Retail",
            "subcategory":"Animal Services",
            "type":"Services"
        }
    ],
    "sg:phone":"+1 303 202 1899",
    "sg:postcode":"80232",
    "sg:province":"CO",
    "sg:tags":[
        "pet"
    ],
    "sg:website":"www.petscoopservices.com",
    "wof:name":"Pet Scoop Svc",
    "wof:placetype":"venue"
},
  "geometry": {"coordinates":[-105.076965,39.691564],"type":"Point"}
}