{
  "type": "Feature",
  "properties": {
    "iso:country":"US",
    "sg:address":"8625 Youngfield St",
    "sg:city":"Arvada",
    "sg:classifiers":[
        {
            "category":"Banks & Credit Unions",
            "subcategory":"Bank",
            "type":"Services"
        }
    ],
    "sg:phone":"+1 303 422 8348",
    "sg:postcode":"80005",
    "sg:province":"CO",
    "sg:tags":[
        "short",
        "institution",
        "business"
    ],
    "wof:name":"Scott Funding Company",
    "wof:placetype":"venue"
},
  "geometry": {"coordinates":[-105.14444899999999,39.854007],"type":"Point"}
}