{
  "type": "Feature",
  "properties": {
    "addr:full":"3950 Manhattan Ave Fort Collins CO 80526",
    "addr:housenumber":"3950",
    "addr:postcode":"80526",
    "addr:street":"Manhattan Ave",
    "iso:country":"US",
    "sg:address":"3950 Manhattan Ave",
    "sg:city":"Fort Collins",
    "sg:classifiers":[
        {
            "category":"Real Estate",
            "subcategory":"Real Estate Operator",
            "type":"Services"
        }
    ],
    "sg:phone":"+1 970 225 1810",
    "sg:postcode":"80526",
    "sg:province":"CO",
    "sg:tags":[
        "building",
        "apartment"
    ],
    "wof:name":"South Glen Village Apartments",
    "wof:placetype":"venue"
},
  "geometry": {"coordinates":[-105.084254,40.531333],"type":"Point"}
}