{
  "type": "Feature",
  "properties": {
    "iso:country":"US",
    "sg:address":"1643 S Ammons St",
    "sg:city":"Lakewood",
    "sg:classifiers":[
        {
            "category":"Personal",
            "subcategory":"Beauty Salon",
            "type":"Services"
        }
    ],
    "sg:phone":"+1 303 980 5021",
    "sg:postcode":"80232",
    "sg:province":"CO",
    "sg:tags":[
        "manicuring"
    ],
    "wof:name":"Angel's Nails",
    "wof:placetype":"venue"
},
  "geometry": {"coordinates":[-105.087204,39.687164],"type":"Point"}
}