{
  "type": "Feature",
  "properties": {
    "addr:full":"28170 Co Rd 13 Haxtun CO 80731",
    "addr:housenumber":"28170;13",
    "addr:postcode":"80731",
    "addr:street":"Co Rd",
    "iso:country":"US",
    "sg:address":"28170 Co Rd 13",
    "sg:city":"Haxtun",
    "sg:classifiers":[
        {
            "category":"Farming",
            "subcategory":"Poultry Farm",
            "type":"Manufacturing & Wholesale Goods"
        }
    ],
    "sg:phone":"+1 970 774 7147",
    "sg:postcode":"80731",
    "sg:province":"CO",
    "sg:tags":[
        "egg"
    ],
    "wof:name":"Rueter S Quail Farms",
    "wof:placetype":"venue"
},
  "geometry": {"coordinates":[-102.550774,40.63867],"type":"Point"}
}