{
  "type": "Feature",
  "properties": {
    "iso:country":"US",
    "sg:address":"5959 E 39th Avenue",
    "sg:city":"Denver",
    "sg:classifiers":[
        {
            "category":"Manufacturing",
            "subcategory":"Rubber & Plastics",
            "type":"Manufacturing & Wholesale Goods"
        },
        {
            "category":"Autos & Motor Vehicles",
            "subcategory":"Auto Supplies",
            "type":"Retail Goods"
        }
    ],
    "sg:phone":"+1 303 320 4725",
    "sg:postcode":"80207",
    "sg:province":"CO",
    "sg:tags":[
        "wheel",
        "tires-wholesale",
        "tire",
        "manufacturer"
    ],
    "sg:website":"www.foreetire.com",
    "wof:name":"Foree Tire Distributors",
    "wof:placetype":"venue"
},
  "geometry": {"coordinates":[-104.919167,39.771171],"type":"Point"}
}