{
  "type": "Feature",
  "properties": {
    "addr:full":"5050 Factory Shops Boulevard Castle Rock CO 80108",
    "addr:housenumber":"5050",
    "addr:postcode":"80108",
    "addr:street":"Factory Shops Boulevard",
    "iso:country":"US",
    "sg:address":"5050 Factory Shops Boulevard",
    "sg:city":"Castle Rock",
    "sg:classifiers":[
        {
            "category":"Shopping",
            "subcategory":"Department Store",
            "type":"Retail Goods"
        },
        {
            "category":"Sports & Exercise",
            "subcategory":"Bicycle Rental",
            "type":"Entertainment"
        }
    ],
    "sg:phone":"+1 303 814 6936",
    "sg:postcode":"80108",
    "sg:province":"CO",
    "sg:tags":[
        "wear"
    ],
    "sg:website":"www.pacsun.com",
    "wof:name":"Pacific Sunwear",
    "wof:placetype":"venue"
},
  "geometry": {"coordinates":[-104.87410300000001,39.412612],"type":"Point"}
}