{
  "type": "Feature",
  "properties": {
    "iso:country":"US",
    "sg:address":"88 Aspen Ln",
    "sg:city":"Crested Butte",
    "sg:classifiers":[
        {
            "category":"Recreation",
            "type":"Entertainment"
        }
    ],
    "sg:phone":"+1 970 349 5219",
    "sg:postcode":"81224",
    "sg:province":"CO",
    "sg:tags":[
        "guide"
    ],
    "sg:website":"www.jpmountainguide.com",
    "wof:name":"Adventures To The Edge",
    "wof:placetype":"venue"
},
  "geometry": {"coordinates":[-106.957868,38.856202],"type":"Point"}
}