{
  "type": "Feature",
  "properties": {
    "iso:country":"US",
    "sg:address":"8416 Federal Blvd",
    "sg:city":"Westminster",
    "sg:classifiers":[
        {
            "category":"Banks & Credit Unions",
            "subcategory":"Bank",
            "type":"Services"
        }
    ],
    "sg:phone":"+1 303 428 0202",
    "sg:postcode":"80031",
    "sg:province":"CO",
    "sg:tags":[
        "cashing",
        "check"
    ],
    "wof:name":"Loan Mart 3540",
    "wof:placetype":"venue"
},
  "geometry": {"coordinates":[-105.024756,39.850447],"type":"Point"}
}