{
  "type": "Feature",
  "properties": {
    "addr:full":"8120 Sheridan Blvd Arvada CO 80003",
    "addr:housenumber":"8120",
    "addr:postcode":"80003",
    "addr:street":"Sheridan Blvd",
    "iso:country":"US",
    "sg:address":"8120 Sheridan Blvd",
    "sg:city":"Arvada",
    "sg:classifiers":[
        {
            "category":"Health Services",
            "subcategory":"Doctor",
            "type":"Services"
        }
    ],
    "sg:phone":"+1 303 430 4200",
    "sg:postcode":"80003",
    "sg:province":"CO",
    "wof:name":"Front Rnge Orthdntic Spcalists",
    "wof:placetype":"venue"
},
  "geometry": {"coordinates":[-105.053309,39.844357],"type":"Point"}
}