{
  "type": "Feature",
  "properties": {
    "addr:full":"2333 N 6th St Grand Junction CO 81501",
    "addr:housenumber":"2333",
    "addr:postcode":"81501",
    "addr:street":"N 6Th St",
    "iso:country":"US",
    "sg:address":"2333 N 6th St",
    "sg:city":"Grand Junction",
    "sg:classifiers":[
        {
            "category":"Building & Trades",
            "subcategory":"Construction",
            "type":"Services"
        }
    ],
    "sg:phone":"+1 970 243 6220",
    "sg:postcode":"81501",
    "sg:province":"CO",
    "sg:tags":[
        "general",
        "contractor"
    ],
    "wof:name":"FCI Constructors Inc",
    "wof:placetype":"venue"
},
  "geometry": {"coordinates":[-108.56216499999999,39.08889],"type":"Point"}
}