{
  "type": "Feature",
  "properties": {
    "addr:full":"5801 Otero Ave Loveland CO 80538",
    "addr:housenumber":"5801",
    "addr:postcode":"80538",
    "addr:street":"Otero Ave",
    "iso:country":"US",
    "sg:address":"5801 Otero Ave",
    "sg:city":"Loveland",
    "sg:classifiers":[
        {
            "category":"Building & Trades",
            "subcategory":"Cleaning & Sanitation",
            "type":"Services"
        }
    ],
    "sg:phone":"+1 970 669 4431",
    "sg:postcode":"80538",
    "sg:province":"CO",
    "wof:name":"Double Touch Cleaning",
    "wof:placetype":"venue"
},
  "geometry": {"coordinates":[-105.18100800000001,40.452017],"type":"Point"}
}