{
  "type": "Feature",
  "properties": {
    "addr:full":"16961 E Quincy Ave Aurora CO 80015",
    "addr:housenumber":"16961 e",
    "addr:postcode":"80015",
    "addr:street":"Quincy Ave",
    "iso:country":"US",
    "sg:address":"16961 E Quincy Ave",
    "sg:city":"Aurora",
    "sg:classifiers":[
        {
            "category":"Restaurant",
            "type":"Food & Drink"
        }
    ],
    "sg:phone":"+1 303 693 1915",
    "sg:postcode":"80015",
    "sg:province":"CO",
    "sg:tags":[
        "drinking",
        "eating"
    ],
    "wof:name":"Bq Food & Spirits Inc",
    "wof:placetype":"venue"
},
  "geometry": {"coordinates":[-104.788697,39.638575],"type":"Point"}
}