{
  "type": "Feature",
  "properties": {
    "addr:full":"2991 S Tejon St Englewood CO 80110",
    "addr:housenumber":"2991",
    "addr:postcode":"80110",
    "addr:street":"S Tejon St",
    "iso:country":"US",
    "sg:address":"2991 S Tejon St",
    "sg:city":"Englewood",
    "sg:classifiers":[
        {
            "category":"Building & Trades",
            "subcategory":"Construction",
            "type":"Services"
        }
    ],
    "sg:phone":"+1 303 761 5306",
    "sg:postcode":"80110",
    "sg:province":"CO",
    "sg:tags":[
        "sheet",
        "metal",
        "contractor"
    ],
    "wof:name":"Misers Inc",
    "wof:placetype":"venue"
},
  "geometry": {"coordinates":[-105.01115799999999,39.664029],"type":"Point"}
}