{
  "type": "Feature",
  "properties": {
    "addr:full":"1784 N Rocky View Rd Castle Rock CO 80108",
    "addr:housenumber":"1784",
    "addr:postcode":"80108",
    "addr:street":"N Rocky View Rd",
    "iso:country":"US",
    "sg:address":"1784 N Rocky View Rd",
    "sg:city":"Castle Rock",
    "sg:classifiers":[
        {
            "category":"Building & Trades",
            "subcategory":"Equipment Rental",
            "type":"Services"
        }
    ],
    "sg:phone":"+1 303 663 9701",
    "sg:postcode":"80108",
    "sg:province":"CO",
    "sg:tags":[
        "audio",
        "leasing"
    ],
    "sg:website":"www.lightsourcedenver.com",
    "wof:name":"Light Source Denver",
    "wof:placetype":"venue"
},
  "geometry": {"coordinates":[-104.807406,39.386316],"type":"Point"}
}