{
  "type": "Feature",
  "properties": {
    "addr:full":"3334 W 4th Street Rd Greeley CO 80634",
    "addr:housenumber":"3334",
    "addr:postcode":"80634",
    "addr:street":"W 4Th Street Rd",
    "iso:country":"US",
    "sg:address":"3334 W 4th Street Rd",
    "sg:city":"Greeley",
    "sg:classifiers":[
        {
            "category":"Building & Trades",
            "subcategory":"Construction",
            "type":"Services"
        }
    ],
    "sg:phone":"+1 970 353 5586",
    "sg:postcode":"80634",
    "sg:province":"CO",
    "sg:tags":[
        "siding",
        "contractor"
    ],
    "wof:name":"Wolsey Construction",
    "wof:placetype":"venue"
},
  "geometry": {"coordinates":[-104.734413,40.429223],"type":"Point"}
}