{
  "type": "Feature",
  "properties": {
    "addr:full":"3642 Co Rd 20 Longmont CO 80504",
    "addr:housenumber":"3642;20",
    "addr:postcode":"80504",
    "addr:street":"Co Rd",
    "iso:country":"US",
    "sg:address":"3642 Co Rd 20",
    "sg:city":"Longmont",
    "sg:classifiers":[
        {
            "category":"Freight",
            "type":"Transportation"
        }
    ],
    "sg:phone":"+1 303 485 9915",
    "sg:postcode":"80504",
    "sg:province":"CO",
    "wof:name":"Schlieker Transportation LLC",
    "wof:placetype":"venue"
},
  "geometry": {"coordinates":[-104.98772200000001,40.131403],"type":"Point"}
}