{
  "type": "Feature",
  "properties": {
    "addr:full":"8622 W Arbor Ave Littleton CO 80123",
    "addr:housenumber":"8622",
    "addr:postcode":"80123",
    "addr:street":"W Arbor Ave",
    "iso:country":"US",
    "sg:address":"8622 W Arbor Ave",
    "sg:city":"Littleton",
    "sg:classifiers":[
        {
            "category":"Manufacturing",
            "subcategory":"Tools & Machinery",
            "type":"Manufacturing & Wholesale Goods"
        }
    ],
    "sg:phone":"+1 303 979 8296",
    "sg:postcode":"80123",
    "sg:province":"CO",
    "sg:tags":[
        "metalworking",
        "mfg"
    ],
    "wof:name":"Performance Cryogenics",
    "wof:placetype":"venue"
},
  "geometry": {"coordinates":[-105.093942,39.602742],"type":"Point"}
}