{
  "type": "Feature",
  "properties": {
    "addr:full":"740 Nolte Ct Colorado Springs CO 80916",
    "addr:housenumber":"740",
    "addr:postcode":"80916",
    "addr:street":"Nolte Ct",
    "iso:country":"US",
    "sg:address":"740 Nolte Ct",
    "sg:city":"Colorado Springs",
    "sg:classifiers":[
        {
            "category":"Shopping",
            "subcategory":"Jewelry",
            "type":"Retail Goods"
        }
    ],
    "sg:phone":"+1 719 637 1335",
    "sg:postcode":"80916",
    "sg:province":"CO",
    "sg:tags":[
        "food"
    ],
    "wof:name":"Robi & Assoc",
    "wof:placetype":"venue"
},
  "geometry": {"coordinates":[-104.730969,38.82104],"type":"Point"}
}