{
  "type": "Feature",
  "properties": {
    "iso:country":"US",
    "sg:address":"23159 Co Rd 43",
    "sg:city":"La Salle",
    "sg:classifiers":[
        {
            "category":"Wholesale",
            "subcategory":"Farm Supplies",
            "type":"Manufacturing & Wholesale Goods"
        }
    ],
    "sg:phone":"+1 970 284 5449",
    "sg:postcode":"80645",
    "sg:province":"CO",
    "sg:tags":[
        "livestock"
    ],
    "wof:name":"Rexford Rabbit Processing",
    "wof:placetype":"venue"
},
  "geometry": {"coordinates":[-104.65876900000001,40.339199],"type":"Point"}
}