{
  "type": "Feature",
  "properties": {
    "iso:country":"US",
    "sg:address":"291 Bridge St",
    "sg:city":"Vail",
    "sg:classifiers":[
        {
            "category":"Shopping",
            "subcategory":"Hobbies, Toys, & Games",
            "type":"Retail Goods"
        },
        {
            "category":"Shopping",
            "subcategory":"Clothing, Apparel, & Fashions",
            "type":"Retail Goods"
        }
    ],
    "sg:phone":"+1 970 476 4731",
    "sg:postcode":"81657",
    "sg:province":"CO",
    "sg:tags":[
        "wear"
    ],
    "wof:name":"Toy Store The",
    "wof:placetype":"venue"
},
  "geometry": {"coordinates":[-106.373741,39.640555],"type":"Point"}
}