{
  "type": "Feature",
  "properties": {
    "addr:full":"65 Sheridan Boulevard Lakewood CO 80226",
    "addr:housenumber":"65",
    "addr:postcode":"80226",
    "addr:street":"Sheridan Boulevard",
    "iso:country":"US",
    "sg:address":"65 Sheridan Boulevard",
    "sg:city":"Lakewood",
    "sg:classifiers":[
        {
            "category":"Food & Beverages",
            "subcategory":"Liquor & Beverages",
            "type":"Retail Goods"
        }
    ],
    "sg:phone":"+1 303 274 0908",
    "sg:postcode":"80226",
    "sg:province":"CO",
    "sg:tags":[
        "beer",
        "spirit",
        "wine"
    ],
    "wof:name":"Sheridan Fine Wine & Spirits",
    "wof:placetype":"venue"
},
  "geometry": {"coordinates":[-105.05336800000001,39.717608],"type":"Point"}
}