{
  "type": "Feature",
  "properties": {
    "iso:country":"US",
    "sg:address":"2925 S College Ave",
    "sg:city":"Fort Collins",
    "sg:classifiers":[
        {
            "category":"Recreation",
            "type":"Entertainment"
        }
    ],
    "sg:phone":"+1 970 207 0484",
    "sg:postcode":"80525",
    "sg:province":"CO",
    "sg:tags":[
        "martial",
        "arts",
        "instruction"
    ],
    "wof:name":"Front Range Traditional Karate",
    "wof:placetype":"venue"
},
  "geometry": {"coordinates":[-105.077125,40.548291],"type":"Point"}
}