{
  "type": "Feature",
  "properties": {
    "iso:country":"US",
    "sg:address":"131 Main St",
    "sg:city":"Breckenridge",
    "sg:classifiers":[
        {
            "category":"Food & Beverages",
            "subcategory":"Bakery",
            "type":"Retail Goods"
        }
    ],
    "sg:phone":"+1 970 453 2990",
    "sg:postcode":"80424",
    "sg:province":"CO",
    "sg:tags":[
        "baker"
    ],
    "wof:name":"Clint's Bakery & Coffe House",
    "wof:placetype":"venue"
},
  "geometry": {"coordinates":[-106.04615099999999,39.480503],"type":"Point"}
}