{
  "type": "Feature",
  "properties": {
    "iso:country":"US",
    "sg:address":"14777 Co Rd 52",
    "sg:city":"Burlington",
    "sg:phone":"+1 719 346 5494",
    "sg:postcode":"80807",
    "sg:province":"CO",
    "sg:tags":[
        "farm",
        "corn"
    ],
    "wof:name":"Penny Ranch",
    "wof:placetype":"venue"
},
  "geometry": {"coordinates":[-102.203548,39.244065],"type":"Point"}
}