{
  "type": "Feature",
  "properties": {
    "iso:country":"US",
    "sg:address":"4842 Franklin Dr",
    "sg:city":"Boulder",
    "sg:classifiers":[
        {
            "category":"Professional",
            "subcategory":"Engineering",
            "type":"Services"
        }
    ],
    "sg:phone":"+1 303 449 7266",
    "sg:postcode":"80301",
    "sg:province":"CO",
    "sg:tags":[
        "engineer"
    ],
    "wof:name":"Gehring & Gehring",
    "wof:placetype":"venue"
},
  "geometry": {"coordinates":[-105.24214499999999,40.032402],"type":"Point"}
}