{
  "type": "Feature",
  "properties": {
    "iso:country":"US",
    "sg:address":"212 W Illinois Ave",
    "sg:city":"Fountain",
    "sg:classifiers":[
        {
            "category":"Retail",
            "subcategory":"Repair Shop",
            "type":"Services"
        }
    ],
    "sg:phone":"+1 719 382 6153",
    "sg:postcode":"80817",
    "sg:province":"CO",
    "sg:tags":[
        "scooter",
        "motorcycle",
        "motor"
    ],
    "wof:name":"Chaps",
    "wof:placetype":"venue"
},
  "geometry": {"coordinates":[-104.702772,38.680733],"type":"Point"}
}