{
  "type": "Feature",
  "properties": {
    "addr:full":"728 N Main St Gunnison CO 81230",
    "addr:housenumber":"728",
    "addr:postcode":"81230",
    "addr:street":"N Main St",
    "iso:country":"US",
    "sg:address":"728 N Main St",
    "sg:city":"Gunnison",
    "sg:classifiers":[
        {
            "category":"Banks & Credit Unions",
            "subcategory":"Bank",
            "type":"Services"
        }
    ],
    "sg:phone":"+1 970 641 1191",
    "sg:postcode":"81230",
    "sg:province":"CO",
    "sg:tags":[
        "cashing",
        "check"
    ],
    "wof:name":"Check Into Cash",
    "wof:placetype":"venue"
},
  "geometry": {"coordinates":[-106.92683,38.552506],"type":"Point"}
}