{
  "type": "Feature",
  "properties": {
    "iso:country":"US",
    "sg:address":"1050 Wadsworth Blvd",
    "sg:city":"Lakewood",
    "sg:classifiers":[
        {
            "category":"Wholesale",
            "subcategory":"Computers",
            "type":"Manufacturing & Wholesale Goods"
        }
    ],
    "sg:phone":"+1 303 936 1570",
    "sg:postcode":"80214",
    "sg:province":"CO",
    "wof:name":"Altermedia",
    "wof:placetype":"venue"
},
  "geometry": {"coordinates":[-105.081152,39.733422],"type":"Point"}
}