{
  "type": "Feature",
  "properties": {
    "iso:country":"US",
    "sg:address":"221 E Fountain Blvd",
    "sg:city":"Colorado Springs",
    "sg:classifiers":[
        {
            "category":"Professional",
            "type":"Services"
        }
    ],
    "sg:phone":"+1 719 475 8920",
    "sg:postcode":"80903",
    "sg:province":"CO",
    "sg:tags":[
        "establishment"
    ],
    "wof:name":"Sassi Co",
    "wof:placetype":"venue"
},
  "geometry": {"coordinates":[-104.820403,38.821605],"type":"Point"}
}