{
  "type": "Feature",
  "properties": {
    "iso:country":"US",
    "sg:address":"502 Colorado Ave",
    "sg:city":"La Junta",
    "sg:classifiers":[
        {
            "category":"Home & Garden",
            "subcategory":"Household Appliances",
            "type":"Retail Goods"
        }
    ],
    "sg:phone":"+1 719 384 2532",
    "sg:postcode":"81050",
    "sg:province":"CO",
    "wof:name":"Kinder Morgan Inc",
    "wof:placetype":"venue"
},
  "geometry": {"coordinates":[-103.543147,37.983918],"type":"Point"}
}