{
  "type": "Feature",
  "properties": {
    "iso:country":"US",
    "sg:address":"232 E Vine Dr",
    "sg:city":"Fort Collins",
    "sg:classifiers":[
        {
            "category":"Real Estate",
            "subcategory":"Real Estate Agent",
            "type":"Services"
        }
    ],
    "sg:phone":"+1 970 416 1055",
    "sg:postcode":"80524",
    "sg:province":"CO",
    "wof:name":"Inverness Farm Realty",
    "wof:placetype":"venue"
},
  "geometry": {"coordinates":[-105.07080000000001,40.595965],"type":"Point"}
}