{
  "type": "Feature",
  "properties": {
    "iso:country":"US",
    "sg:address":"1213 Co Rd 330",
    "sg:city":"Ignacio",
    "sg:classifiers":[
        {
            "category":"Utilities",
            "subcategory":"Natural Gas",
            "type":"Services"
        }
    ],
    "sg:phone":"+1 970 883 2203",
    "sg:postcode":"81137",
    "sg:province":"CO",
    "wof:name":"Xcel Energy",
    "wof:placetype":"venue"
},
  "geometry": {"coordinates":[-107.51325199999999,37.04991],"type":"Point"}
}