{
  "type": "Feature",
  "properties": {
    "iso:country":"US",
    "sg:address":"22481 Pleasant Park Rd",
    "sg:city":"Conifer",
    "sg:classifiers":[
        {
            "category":"Manufacturing",
            "subcategory":"Retail Goods",
            "type":"Manufacturing & Wholesale Goods"
        }
    ],
    "sg:phone":"+1 303 697 1956",
    "sg:postcode":"80433",
    "sg:province":"CO",
    "sg:tags":[
        "product",
        "mfg"
    ],
    "wof:name":"Morris Donald",
    "wof:placetype":"venue"
},
  "geometry": {"coordinates":[-105.25937399999999,39.503803],"type":"Point"}
}