{
  "type": "Feature",
  "properties": {
    "addr:full":"1129 S Prairie Ave Pueblo CO 81005",
    "addr:housenumber":"1129",
    "addr:postcode":"81005",
    "addr:street":"S Prairie Ave",
    "iso:country":"US",
    "sg:address":"1129 S Prairie Ave",
    "sg:city":"Pueblo",
    "sg:classifiers":[
        {
            "category":"Shopping",
            "subcategory":"Used Merchandise",
            "type":"Retail Goods"
        }
    ],
    "sg:phone":"+1 719 560 0297",
    "sg:postcode":"81005",
    "sg:province":"CO",
    "sg:tags":[
        "shop",
        "thrift"
    ],
    "wof:name":"Goodwill Industries",
    "wof:placetype":"venue"
},
  "geometry": {"coordinates":[-104.643868,38.246363],"type":"Point"}
}