{
  "type": "Feature",
  "properties": {
    "iso:country":"US",
    "sg:address":"3300 S Lincoln St",
    "sg:city":"Englewood",
    "sg:classifiers":[
        {
            "category":"Education",
            "subcategory":"School",
            "type":"Public Place"
        }
    ],
    "sg:phone":"+1 303 789 0300",
    "sg:postcode":"80113",
    "sg:province":"CO",
    "wof:name":"St Louis School Cafeteria",
    "wof:placetype":"venue"
},
  "geometry": {"coordinates":[-104.986379,39.655],"type":"Point"}
}