{
  "type": "Feature",
  "properties": {
    "iso:country":"US",
    "sg:address":"1433 Main St",
    "sg:city":"Alamosa",
    "sg:classifiers":[
        {
            "category":"Personal",
            "subcategory":"Beauty Salon",
            "type":"Services"
        }
    ],
    "sg:phone":"+1 719 587 0271",
    "sg:postcode":"81101",
    "sg:province":"CO",
    "sg:tags":[
        "manicuring"
    ],
    "wof:name":"Jakes Custom Tattooing",
    "wof:placetype":"venue"
},
  "geometry": {"coordinates":[-105.878497,37.468387],"type":"Point"}
}