{
  "type": "Feature",
  "properties": {
    "addr:full":"7022 Silverhorn Dr Evergreen CO 80439",
    "addr:postcode":"7022;80439",
    "addr:street":"Silverhorn Dr",
    "iso:country":"US",
    "sg:address":"7022 Silverhorn Dr",
    "sg:city":"Evergreen",
    "sg:classifiers":[
        {
            "category":"Building & Trades",
            "subcategory":"Construction",
            "type":"Services"
        }
    ],
    "sg:phone":"+1 303 679 9585",
    "sg:postcode":"80439",
    "sg:province":"CO",
    "sg:tags":[
        "general",
        "contractor"
    ],
    "wof:name":"Tadraco",
    "wof:placetype":"venue"
},
  "geometry": {"coordinates":[-105.281879,39.591207],"type":"Point"}
}