{
  "type": "Feature",
  "properties": {
    "addr:full":"4600 Fernbrook Dr Loveland CO 80538",
    "addr:housenumber":"4600",
    "addr:postcode":"80538",
    "addr:street":"Fernbrook Dr",
    "iso:country":"US",
    "sg:address":"4600 Fernbrook Dr",
    "sg:city":"Loveland",
    "sg:phone":"+1 970 667 5658",
    "sg:postcode":"80538",
    "sg:province":"CO",
    "sg:tags":[
        "farm",
        "field",
        "crop"
    ],
    "wof:name":"Jerry Vesely",
    "wof:placetype":"venue"
},
  "geometry": {"coordinates":[-105.18983,40.43593],"type":"Point"}
}