{
  "type": "Feature",
  "properties": {
    "iso:country":"US",
    "sg:address":"4450 S Huron St",
    "sg:city":"Englewood",
    "sg:classifiers":[
        {
            "category":"Retail",
            "subcategory":"Repair Shop",
            "type":"Services"
        }
    ],
    "sg:phone":"+1 303 789 2700",
    "sg:postcode":"80110",
    "sg:province":"CO",
    "sg:tags":[
        "sharpening"
    ],
    "wof:name":"Hunter's Sharpening Inc",
    "wof:placetype":"venue"
},
  "geometry": {"coordinates":[-104.997258,39.634941],"type":"Point"}
}