{
  "type": "Feature",
  "properties": {
    "iso:country":"US",
    "sg:address":"1401 17th St",
    "sg:city":"Denver",
    "sg:classifiers":[
        {
            "category":"Insurance",
            "subcategory":"Health Insurance",
            "type":"Services"
        }
    ],
    "sg:phone":"+1 303 293 8955",
    "sg:postcode":"80202",
    "sg:province":"CO",
    "sg:tags":[
        "co"
    ],
    "wof:name":"From Life of Canada",
    "wof:placetype":"venue"
},
  "geometry": {"coordinates":[-104.99797100000001,39.751467],"type":"Point"}
}