{
  "type": "Feature",
  "properties": {
    "addr:full":"15163 E Hampden Ave Aurora CO 80014",
    "addr:housenumber":"15163",
    "addr:postcode":"80014",
    "addr:street":"E Hampden Ave",
    "iso:country":"US",
    "sg:address":"15163 E Hampden Ave",
    "sg:city":"Aurora",
    "sg:classifiers":[
        {
            "category":"Personal",
            "subcategory":"Beauty Salon",
            "type":"Services"
        }
    ],
    "sg:phone":"+1 303 766 0169",
    "sg:postcode":"80014",
    "sg:province":"CO",
    "sg:tags":[
        "manicuring"
    ],
    "wof:name":"Joann's Nails",
    "wof:placetype":"venue"
},
  "geometry": {"coordinates":[-104.81309,39.653084],"type":"Point"}
}