{
  "type": "Feature",
  "properties": {
    "iso:country":"US",
    "sg:address":"3890 E 104th Ave",
    "sg:city":"Denver",
    "sg:classifiers":[
        {
            "category":"Cinema",
            "subcategory":"Movie Rental",
            "type":"Entertainment"
        }
    ],
    "sg:phone":"+1 720 872 0731",
    "sg:postcode":"80233",
    "sg:province":"CO",
    "sg:tags":[
        "leasing",
        "video",
        "disc",
        "tape"
    ],
    "wof:name":"Blockbuster Video",
    "wof:placetype":"venue"
},
  "geometry": {"coordinates":[-104.944579,39.884791],"type":"Point"}
}