{
  "type": "Feature",
  "properties": {
    "addr:full":"9775 Blue Mountain Dr Golden CO 80403",
    "addr:housenumber":"9775",
    "addr:postcode":"80403",
    "addr:street":"Blue Mountain Dr",
    "iso:country":"US",
    "sg:address":"9775 Blue Mountain Dr",
    "sg:city":"Golden",
    "sg:classifiers":[
        {
            "category":"Government",
            "subcategory":"Fire Station",
            "type":"Public Place"
        }
    ],
    "sg:phone":"+1 303 642 0779",
    "sg:postcode":"80403",
    "sg:province":"CO",
    "sg:tags":[
        "protection"
    ],
    "wof:name":"CL Crk Cnyn Fire 3",
    "wof:placetype":"venue"
},
  "geometry": {"coordinates":[-105.27512900000001,39.873623],"type":"Point"}
}