{
  "type": "Feature",
  "properties": {
    "addr:full":"303 W Colfax Ave Denver CO 80204",
    "addr:housenumber":"303",
    "addr:postcode":"80204",
    "addr:street":"W Colfax Ave",
    "iso:country":"US",
    "sg:address":"303 W Colfax Ave",
    "sg:city":"Denver",
    "sg:classifiers":[
        {
            "category":"Government",
            "subcategory":"Office",
            "type":"Public Place"
        }
    ],
    "sg:phone":"+1 303 640 2678",
    "sg:postcode":"80204",
    "sg:province":"CO",
    "sg:tags":[
        "village"
    ],
    "wof:name":"Denver Art Culture & Film Comm",
    "wof:placetype":"venue"
},
  "geometry": {"coordinates":[-104.992898,39.740206],"type":"Point"}
}