{
  "type": "Feature",
  "properties": {
    "addr:full":"407 S Broadway Denver CO 80209",
    "addr:housenumber":"407",
    "addr:postcode":"80209",
    "addr:street":"S Broadway",
    "iso:country":"US",
    "sg:address":"407 S Broadway",
    "sg:city":"Denver",
    "sg:classifiers":[
        {
            "category":"Shopping",
            "subcategory":"Clothing, Apparel, & Fashions",
            "type":"Retail Goods"
        }
    ],
    "sg:phone":"+1 720 570 4868",
    "sg:postcode":"80209",
    "sg:province":"CO",
    "sg:tags":[
        "accessory"
    ],
    "wof:name":"Rainbow",
    "wof:placetype":"venue"
},
  "geometry": {"coordinates":[-104.987999,39.709202],"type":"Point"}
}