{
  "type": "Feature",
  "properties": {
    "iso:country":"US",
    "sg:address":"17241 Co Rd 24",
    "sg:city":"Dolores",
    "sg:classifiers":[
        {
            "category":"Shopping",
            "subcategory":"Bicycles & Sporting Goods",
            "type":"Retail Goods"
        }
    ],
    "sg:phone":"+1 970 882 4720",
    "sg:postcode":"81323",
    "sg:province":"CO",
    "sg:tags":[
        "hardwood",
        "mi",
        "gun",
        "gunsmith"
    ],
    "wof:name":"Riley's Gunstocks",
    "wof:placetype":"venue"
},
  "geometry": {"coordinates":[-108.61002499999999,37.460035],"type":"Point"}
}