{
  "type": "Feature",
  "properties": {
    "addr:full":"10950 W 100th Dr Broomfield CO 80021",
    "addr:housenumber":"10950",
    "addr:postcode":"80021",
    "addr:street":"W 100Th Dr",
    "iso:country":"US",
    "sg:address":"10950 W 100th Dr",
    "sg:city":"Broomfield",
    "sg:classifiers":[
        {
            "category":"Shopping",
            "subcategory":"Computers & Home Electronics",
            "type":"Retail Goods"
        }
    ],
    "sg:phone":"+1 303 410 9803",
    "sg:postcode":"80021",
    "sg:province":"CO",
    "sg:tags":[
        "software"
    ],
    "wof:name":"Accubid",
    "wof:placetype":"venue"
},
  "geometry": {"coordinates":[-105.12426499999999,39.878665],"type":"Point"}
}