{
  "type": "Feature",
  "properties": {
    "iso:country":"US",
    "sg:address":"9878 S Foxhill Cir",
    "sg:city":"Littleton",
    "sg:classifiers":[
        {
            "category":"Building & Trades",
            "subcategory":"Construction",
            "type":"Services"
        }
    ],
    "sg:phone":"+1 303 791 7217",
    "sg:postcode":"80129",
    "sg:province":"CO",
    "sg:tags":[
        "general",
        "contractor"
    ],
    "wof:name":"Orsmond Construction",
    "wof:placetype":"venue"
},
  "geometry": {"coordinates":[-105.02654,39.537925],"type":"Point"}
}