{
  "type": "Feature",
  "properties": {
    "iso:country":"US",
    "sg:address":"217 W Colorado Ave",
    "sg:city":"Telluride",
    "sg:classifiers":[
        {
            "category":"Restaurant",
            "type":"Food & Drink"
        }
    ],
    "sg:phone":"+1 970 728 4004",
    "sg:postcode":"81435",
    "sg:province":"CO",
    "sg:tags":[
        "delicatessen"
    ],
    "wof:name":"Deli Downstairs",
    "wof:placetype":"venue"
},
  "geometry": {"coordinates":[-107.812523,37.937681],"type":"Point"}
}