{
  "type": "Feature",
  "properties": {
    "iso:country":"US",
    "sg:address":"1601 S Pratt Pkwy",
    "sg:city":"Longmont",
    "sg:classifiers":[
        {
            "category":"Organizations",
            "subcategory":"Religious Organization",
            "type":"Services"
        }
    ],
    "sg:phone":"+1 303 776 1086",
    "sg:postcode":"80501",
    "sg:province":"CO",
    "sg:tags":[
        "church"
    ],
    "wof:name":"River Of Life Church",
    "wof:placetype":"venue"
},
  "geometry": {"coordinates":[-105.10991799999999,40.139143],"type":"Point"}
}