{
  "type": "Feature",
  "properties": {
    "iso:country":"US",
    "sg:address":"32950 Inverness Dr",
    "sg:city":"Evergreen",
    "sg:classifiers":[
        {
            "category":"Recreation",
            "type":"Entertainment"
        }
    ],
    "sg:phone":"+1 303 674 2622",
    "sg:postcode":"80439",
    "sg:province":"CO",
    "sg:tags":[
        "club",
        "membership"
    ],
    "wof:name":"Safari Club International",
    "wof:placetype":"venue"
},
  "geometry": {"coordinates":[-105.34725400000001,39.66604],"type":"Point"}
}