{
  "type": "Feature",
  "properties": {
    "iso:country":"US",
    "sg:address":"6400 S Fiddlers Green Cir",
    "sg:city":"Englewood",
    "sg:classifiers":[
        {
            "category":"Insurance",
            "subcategory":"Insurance Agent",
            "type":"Services"
        }
    ],
    "sg:phone":"+1 303 779 2524",
    "sg:postcode":"80111",
    "sg:province":"CO",
    "wof:name":"Cue Financial Group",
    "wof:placetype":"venue"
},
  "geometry": {"coordinates":[-104.890167,39.60013],"type":"Point"}
}