{
  "type": "Feature",
  "properties": {
    "iso:country":"US",
    "sg:address":"8500 W Crestline Ave",
    "sg:city":"Denver",
    "sg:classifiers":[
        {
            "category":"Food & Beverages",
            "subcategory":"Groceries & Convenience Stores",
            "type":"Retail Goods"
        }
    ],
    "sg:phone":"+1 303 933 2076",
    "sg:postcode":"80123",
    "sg:province":"CO",
    "wof:name":"Diamond Shamrock",
    "wof:placetype":"venue"
},
  "geometry": {"coordinates":[-105.092004,39.618255],"type":"Point"}
}