{
  "type": "Feature",
  "properties": {
    "addr:full":"9600 E Arapahoe Rd Greenwood Vlg CO 80112",
    "addr:housenumber":"9600",
    "addr:postcode":"co 80112",
    "addr:street":"E Arapahoe Rd",
    "iso:country":"US",
    "sg:address":"9600 E Arapahoe Rd",
    "sg:city":"Greenwood Vlg",
    "sg:classifiers":[
        {
            "category":"Professional",
            "subcategory":"Accounting & Tax Preparation",
            "type":"Services"
        }
    ],
    "sg:phone":"+1 303 316 7814",
    "sg:postcode":"80112",
    "sg:province":"CO",
    "sg:tags":[
        "bookkeeping",
        "general"
    ],
    "wof:name":"Azua Tax Svc",
    "wof:placetype":"venue"
},
  "geometry": {"coordinates":[-104.877183,39.594958],"type":"Point"}
}