{
  "type": "Feature",
  "properties": {
    "addr:full":"1302 State Hwy 135 Gunnison CO 81230",
    "addr:housenumber":"1302",
    "addr:postcode":"81230",
    "addr:street":"State Hwy 135",
    "iso:country":"US",
    "sg:address":"1302 State Hwy 135",
    "sg:city":"Gunnison",
    "sg:classifiers":[
        {
            "category":"Retail",
            "subcategory":"Repair Shop",
            "type":"Services"
        }
    ],
    "sg:phone":"+1 970 641 5236",
    "sg:postcode":"81230",
    "sg:province":"CO",
    "wof:name":"Scots Custom Canvas & Uphl",
    "wof:placetype":"venue"
},
  "geometry": {"coordinates":[-106.92694400000001,38.562084],"type":"Point"}
}