{
  "type": "Feature",
  "properties": {
    "iso:country":"US",
    "sg:address":"90 Inverness Cir E",
    "sg:city":"Englewood",
    "sg:classifiers":[
        {
            "category":"Wholesale",
            "subcategory":"Durable Goods & Equipment",
            "type":"Manufacturing & Wholesale Goods"
        }
    ],
    "sg:phone":"+1 303 792 9992",
    "sg:postcode":"80112",
    "sg:province":"CO",
    "sg:tags":[
        "importer"
    ],
    "wof:name":"Satellite Source",
    "wof:placetype":"venue"
},
  "geometry": {"coordinates":[-104.861407,39.577504],"type":"Point"}
}