{
  "type": "Feature",
  "properties": {
    "iso:country":"US",
    "sg:address":"60 W Bromley Ln",
    "sg:city":"Brighton",
    "sg:classifiers":[
        {
            "category":"Restaurant",
            "type":"Food & Drink"
        }
    ],
    "sg:menulink":"http://www.allmenus.com/co/brighton/128818-subway/menu/",
    "sg:phone":"+1 303 659 2803",
    "sg:postcode":"80601",
    "sg:province":"CO",
    "sg:tags":[
        "american",
        "sandwich"
    ],
    "wof:name":"Subway",
    "wof:placetype":"venue"
},
  "geometry": {"coordinates":[-104.82428899999999,39.970511],"type":"Point"}
}