{
  "type": "Feature",
  "properties": {
    "iso:country":"US",
    "sg:address":"1700 Emerson St.",
    "sg:city":"Denver",
    "sg:classifiers":[
        {
            "category":"Real Estate",
            "subcategory":"Real Estate Services",
            "type":"Services"
        }
    ],
    "sg:postcode":"80218",
    "sg:province":"CO",
    "sg:website":"www.emersonuptownlofts.com",
    "wof:name":"Emerson Uptown Lofts",
    "wof:placetype":"venue"
},
  "geometry": {"coordinates":[-104.975686,39.743575],"type":"Point"}
}