{
  "type": "Feature",
  "properties": {
    "iso:country":"US",
    "sg:address":"1601 E 19th Ave Ste 3950",
    "sg:city":"Denver",
    "sg:classifiers":[
        {
            "category":"Health Services",
            "subcategory":"Doctor",
            "type":"Services"
        }
    ],
    "sg:phone":"+1 303 832 8346",
    "sg:postcode":"80218",
    "sg:province":"CO",
    "wof:name":"Vein Clinic At the Vascular Institute of the Rocks",
    "wof:placetype":"venue"
},
  "geometry": {"coordinates":[-104.97399900000001,39.732101],"type":"Point"}
}