{
  "type": "Feature",
  "properties": {
    "iso:country":"US",
    "sg:address":"3934 Sandlewood Ln",
    "sg:city":"Pueblo",
    "sg:classifiers":[
        {
            "category":"Health Services",
            "subcategory":"Chiropractor",
            "type":"Services"
        }
    ],
    "sg:phone":"+1 719 564 2273",
    "sg:postcode":"81005",
    "sg:province":"CO",
    "wof:name":"Hiatt Walk-In Chiropractic",
    "wof:placetype":"venue"
},
  "geometry": {"coordinates":[-104.660404,38.231704],"type":"Point"}
}