{
  "type": "Feature",
  "properties": {
    "addr:full":"7334 S Alton Way Centennial CO 80112",
    "addr:housenumber":"7334",
    "addr:postcode":"80112",
    "addr:street":"S Alton Way",
    "iso:country":"US",
    "sg:address":"7334 S Alton Way",
    "sg:city":"Centennial",
    "sg:classifiers":[
        {
            "category":"Professional",
            "subcategory":"Art Services",
            "type":"Services"
        }
    ],
    "sg:phone":"+1 303 794 2200",
    "sg:postcode":"80112",
    "sg:province":"CO",
    "sg:tags":[
        "photographer"
    ],
    "wof:name":"Digital Imaging & Photography",
    "wof:placetype":"venue"
},
  "geometry": {"coordinates":[-104.88399,39.582395],"type":"Point"}
}