{
  "type": "Feature",
  "properties": {
    "iso:country":"US",
    "sg:address":"1220 Alpine St",
    "sg:city":"Longmont",
    "sg:classifiers":[
        {
            "category":"Manufacturing",
            "subcategory":"Pottery",
            "type":"Manufacturing & Wholesale Goods"
        }
    ],
    "sg:phone":"+1 303 651 3329",
    "sg:postcode":"80501",
    "sg:province":"CO",
    "sg:tags":[
        "product",
        "mfg"
    ],
    "sg:website":"www.douglasfeypottery.com",
    "wof:name":"Douglas Fey Pottery",
    "wof:placetype":"venue"
},
  "geometry": {"coordinates":[-105.08300300000001,40.18129],"type":"Point"}
}