{
  "type": "Feature",
  "properties": {
    "iso:country":"US",
    "sg:address":"5900 E Yale Ave",
    "sg:city":"Denver",
    "sg:classifiers":[
        {
            "category":"Organizations",
            "subcategory":"Religious Organization",
            "type":"Services"
        }
    ],
    "sg:phone":"+1 303 758 5900",
    "sg:postcode":"80222",
    "sg:province":"CO",
    "wof:name":"Calvary Apostolic Academy",
    "wof:placetype":"venue"
},
  "geometry": {"coordinates":[-104.91873200000001,39.66757],"type":"Point"}
}