{
  "type": "Feature",
  "properties": {
    "iso:country":"US",
    "sg:address":"19563 E Main St",
    "sg:city":"Parker",
    "sg:classifiers":[
        {
            "category":"Real Estate",
            "subcategory":"Real Estate Agent",
            "type":"Services"
        }
    ],
    "sg:phone":"+1 303 841 4897",
    "sg:postcode":"80138",
    "sg:province":"CO",
    "wof:name":"Service Realtors",
    "wof:placetype":"venue"
},
  "geometry": {"coordinates":[-104.760049,39.518225],"type":"Point"}
}