{
  "type": "Feature",
  "properties": {
    "iso:country":"US",
    "sg:address":"1525 Williams St",
    "sg:city":"Denver",
    "sg:classifiers":[
        {
            "category":"Retail",
            "subcategory":"Laundry & Dry Cleaning",
            "type":"Services"
        }
    ],
    "sg:phone":"+1 303 320 7670",
    "sg:postcode":"80218",
    "sg:province":"CO",
    "wof:name":"Spectrum Cleaners",
    "wof:placetype":"venue"
},
  "geometry": {"coordinates":[-104.966003,39.740398],"type":"Point"}
}