{
  "type": "Feature",
  "properties": {
    "iso:country":"US",
    "sg:address":"910 Greenbrier Dr",
    "sg:city":"Colorado Springs",
    "sg:classifiers":[
        {
            "category":"Building & Trades",
            "subcategory":"Construction",
            "type":"Services"
        }
    ],
    "sg:phone":"+1 719 591 5971",
    "sg:postcode":"80916",
    "sg:province":"CO",
    "sg:tags":[
        "hanging",
        "contractor"
    ],
    "wof:name":"Gsa Custom Painting",
    "wof:placetype":"venue"
},
  "geometry": {"coordinates":[-104.74407100000001,38.820584],"type":"Point"}
}