{
  "type": "Feature",
  "properties": {
    "addr:full":"37353 US Hwy 85 Eaton CO 80615",
    "addr:postcode":"37353;80615",
    "addr:street":"Us Hwy 85",
    "iso:country":"US",
    "sg:address":"37353 US Hwy 85",
    "sg:city":"Eaton",
    "sg:classifiers":[
        {
            "category":"Banks & Credit Unions",
            "subcategory":"Bank",
            "type":"Services"
        }
    ],
    "sg:phone":"+1 970 454 3361",
    "sg:postcode":"80615",
    "sg:province":"CO",
    "sg:tags":[
        "loan",
        "real estate"
    ],
    "wof:name":"Bowness Mortgage & Financial",
    "wof:placetype":"venue"
},
  "geometry": {"coordinates":[-104.717673,40.544927],"type":"Point"}
}