{
  "type": "Feature",
  "properties": {
    "addr:full":"680 S Gaylord St Denver CO 80209",
    "addr:housenumber":"680",
    "addr:postcode":"80209",
    "addr:street":"S Gaylord St",
    "iso:country":"US",
    "sg:address":"680 S Gaylord St",
    "sg:city":"Denver",
    "sg:classifiers":[
        {
            "category":"Professional",
            "type":"Services"
        }
    ],
    "sg:phone":"+1 303 778 8900",
    "sg:postcode":"80209",
    "sg:province":"CO",
    "wof:name":"Jamie Haas",
    "wof:placetype":"venue"
},
  "geometry": {"coordinates":[-104.961636,39.70534],"type":"Point"}
}