{
  "type": "Feature",
  "properties": {
    "addr:full":"999 Jasmine St Denver CO 80220",
    "addr:housenumber":"999",
    "addr:postcode":"80220",
    "addr:street":"Jasmine St",
    "iso:country":"US",
    "sg:address":"999 Jasmine St",
    "sg:city":"Denver",
    "sg:classifiers":[
        {
            "category":"Professional",
            "subcategory":"Management & Consulting",
            "type":"Services"
        }
    ],
    "sg:phone":"+1 303 320 0999",
    "sg:postcode":"80220",
    "sg:province":"CO",
    "sg:tags":[
        "consultant",
        "business"
    ],
    "wof:name":"Healthmarket Communications",
    "wof:placetype":"venue"
},
  "geometry": {"coordinates":[-104.918362,39.730481],"type":"Point"}
}