{
  "type": "Feature",
  "properties": {
    "iso:country":"US",
    "sg:address":"20 E Palmer Lake Dr",
    "sg:city":"Pueblo West",
    "sg:classifiers":[
        {
            "category":"Utilities",
            "subcategory":"Refuse",
            "type":"Services"
        }
    ],
    "sg:phone":"+1 719 547 3554",
    "sg:postcode":"81007",
    "sg:province":"CO",
    "sg:tags":[
        "disposal",
        "waste"
    ],
    "wof:name":"Pueblo West Metropolitan",
    "wof:placetype":"venue"
},
  "geometry": {"coordinates":[-104.73886299999999,38.316633],"type":"Point"}
}