{
  "type": "Feature",
  "properties": {
    "iso:country":"US",
    "sg:address":"215 1st St",
    "sg:city":"Ault",
    "sg:classifiers":[
        {
            "category":"Health Services",
            "subcategory":"Chiropractor",
            "type":"Services"
        }
    ],
    "sg:phone":"+1 970 834 2888",
    "sg:postcode":"80610",
    "sg:province":"CO",
    "wof:name":"Ault Chiropractic Clinic",
    "wof:placetype":"venue"
},
  "geometry": {"coordinates":[-104.73263799999999,40.58232],"type":"Point"}
}