{
  "type": "Feature",
  "properties": {
    "addr:full":"6088 State Hwy 93 Golden CO 80403",
    "addr:housenumber":"6088",
    "addr:postcode":"co 80403",
    "addr:street":"State Hwy 93",
    "iso:country":"US",
    "sg:address":"6088 State Hwy 93",
    "sg:city":"Golden",
    "sg:classifiers":[
        {
            "category":"Retail",
            "subcategory":"Animal Services",
            "type":"Services"
        }
    ],
    "sg:phone":"+1 303 279 8045",
    "sg:postcode":"80403",
    "sg:province":"CO",
    "wof:name":"Shonees Enterprises",
    "wof:placetype":"venue"
},
  "geometry": {"coordinates":[-105.22315,39.808488],"type":"Point"}
}