{
  "type": "Feature",
  "properties": {
    "addr:full":"9620 Fox St Denver CO 80260",
    "addr:housenumber":"9620",
    "addr:postcode":"80260",
    "addr:street":"Fox St",
    "iso:country":"US",
    "sg:address":"9620 Fox St",
    "sg:city":"Denver",
    "sg:classifiers":[
        {
            "category":"Home & Garden",
            "subcategory":"Household Appliances",
            "type":"Retail Goods"
        }
    ],
    "sg:phone":"+1 303 995 5063",
    "sg:postcode":"80260",
    "sg:province":"CO",
    "wof:name":"Rainbow Vaccum",
    "wof:placetype":"venue"
},
  "geometry": {"coordinates":[-104.99506,39.872933],"type":"Point"}
}