{
  "type": "Feature",
  "properties": {
    "iso:country":"US",
    "sg:address":"1540 Quail Lake Loop",
    "sg:city":"Colorado Springs",
    "sg:classifiers":[
        {
            "category":"Building & Trades",
            "subcategory":"Electrical",
            "type":"Services"
        },
        {
            "category":"Shopping",
            "subcategory":"Computers & Home Electronics",
            "type":"Retail Goods"
        }
    ],
    "sg:phone":"+1 719 540 8900",
    "sg:postcode":"80906",
    "sg:province":"CO",
    "sg:tags":[
        "electrical",
        "contractor",
        "audio",
        "comm",
        "mfg"
    ],
    "sg:website":"www.lvw.com",
    "wof:name":"L V W Electronics",
    "wof:placetype":"venue"
},
  "geometry": {"coordinates":[-104.80144300000001,38.789347],"type":"Point"}
}