{
  "type": "Feature",
  "properties": {
    "addr:full":"724 Planet Pl Denver CO 80260",
    "addr:housenumber":"724",
    "addr:postcode":"80260",
    "addr:street":"Planet Pl",
    "iso:country":"US",
    "sg:address":"724 Planet Pl",
    "sg:city":"Denver",
    "sg:classifiers":[
        {
            "category":"Building & Trades",
            "subcategory":"Construction",
            "type":"Services"
        }
    ],
    "sg:phone":"+1 303 429 3889",
    "sg:postcode":"80260",
    "sg:province":"CO",
    "sg:tags":[
        "house"
    ],
    "wof:name":"George Keathley Construction",
    "wof:placetype":"venue"
},
  "geometry": {"coordinates":[-104.99606799999999,39.853776],"type":"Point"}
}