{
  "type": "Feature",
  "properties": {
    "iso:country":"US",
    "sg:address":"11590 Black Forest Rd",
    "sg:city":"Colorado Springs",
    "sg:classifiers":[
        {
            "category":"Professional",
            "subcategory":"Accounting & Tax Preparation",
            "type":"Services"
        }
    ],
    "sg:phone":"+1 719 495 6153",
    "sg:postcode":"80908",
    "sg:province":"CO",
    "sg:tags":[
        "accountant"
    ],
    "wof:name":"Higham & Assoc",
    "wof:placetype":"venue"
},
  "geometry": {"coordinates":[-104.70043099999999,38.999535],"type":"Point"}
}