{
  "type": "Feature",
  "properties": {
    "iso:country":"US",
    "sg:address":"3017 Windridge Cir",
    "sg:city":"Littleton",
    "sg:classifiers":[
        {
            "category":"Professional",
            "type":"Services"
        }
    ],
    "sg:phone":"+1 303 471 2628",
    "sg:postcode":"80126",
    "sg:province":"CO",
    "wof:name":"Jenex Inc",
    "wof:placetype":"venue"
},
  "geometry": {"coordinates":[-104.952175,39.520307],"type":"Point"}
}