{
  "type": "Feature",
  "properties": {
    "iso:country":"US",
    "sg:address":"14151 Buckhorn Rd",
    "sg:city":"Loveland",
    "sg:classifiers":[
        {
            "category":"Manufacturing",
            "subcategory":"Food",
            "type":"Manufacturing & Wholesale Goods"
        }
    ],
    "sg:phone":"+1 970 224 2682",
    "sg:postcode":"80538",
    "sg:province":"CO",
    "sg:tags":[
        "mfg",
        "communion",
        "kit"
    ],
    "wof:name":"Altar Calling",
    "wof:placetype":"venue"
},
  "geometry": {"coordinates":[-105.266316,40.530394],"type":"Point"}
}