{
  "type": "Feature",
  "properties": {
    "iso:country":"US",
    "sg:address":"4785 Tejon St Ste 202",
    "sg:city":"Denver",
    "sg:classifiers":[
        {
            "category":"Communications",
            "subcategory":"Newspaper",
            "type":"Services"
        }
    ],
    "sg:phone":"+1 303 936 8556",
    "sg:postcode":"80211",
    "sg:province":"CO",
    "sg:website":"http://www.lavozcolorado.com",
    "wof:name":"La Voz Nueva",
    "wof:placetype":"venue"
},
  "geometry": {"coordinates":[-105.011124,39.783045],"type":"Point"}
}