{
  "type": "Feature",
  "properties": {
    "iso:country":"US",
    "sg:address":"1551 Wolff St",
    "sg:city":"Denver",
    "sg:classifiers":[
        {
            "category":"Real Estate",
            "subcategory":"Real Estate Operator",
            "type":"Services"
        }
    ],
    "sg:phone":"+1 303 534 2300",
    "sg:postcode":"80204",
    "sg:province":"CO",
    "sg:tags":[
        "apartment"
    ],
    "wof:name":"Villas At Sloane's Lake",
    "wof:placetype":"venue"
},
  "geometry": {"coordinates":[-105.048873,39.741289],"type":"Point"}
}