{
  "type": "Feature",
  "properties": {
    "addr:full":"758 Huebinger Dr Glenwood Springs CO 81601",
    "addr:housenumber":"758",
    "addr:postcode":"81601",
    "addr:street":"Huebinger Dr",
    "iso:country":"US",
    "sg:address":"758 Huebinger Dr",
    "sg:city":"Glenwood Springs",
    "sg:classifiers":[
        {
            "category":"Building & Trades",
            "subcategory":"Construction",
            "type":"Services"
        }
    ],
    "sg:phone":"+1 970 945 9495",
    "sg:postcode":"81601",
    "sg:province":"CO",
    "sg:tags":[
        "general",
        "contractor"
    ],
    "wof:name":"Colonna Construction Corp",
    "wof:placetype":"venue"
},
  "geometry": {"coordinates":[-107.29059700000001,39.470404],"type":"Point"}
}