{
  "type": "Feature",
  "properties": {
    "iso:country":"US",
    "sg:address":"1715 Monterey Rd",
    "sg:city":"Colorado Springs",
    "sg:classifiers":[
        {
            "category":"Real Estate",
            "subcategory":"Real Estate Agent",
            "type":"Services"
        }
    ],
    "sg:phone":"+1 719 634 8844",
    "sg:postcode":"80910",
    "sg:province":"CO",
    "wof:name":"Worldwide Realty Group LLC",
    "wof:placetype":"venue"
},
  "geometry": {"coordinates":[-104.779319,38.806084],"type":"Point"}
}