{
  "type": "Feature",
  "properties": {
    "addr:full":"14944 E Radcliff Dr Aurora CO 80015",
    "addr:housenumber":"14944",
    "addr:postcode":"80015",
    "addr:street":"E Radcliff Dr",
    "iso:country":"US",
    "sg:address":"14944 E Radcliff Dr",
    "sg:city":"Aurora",
    "sg:classifiers":[
        {
            "category":"Mining & Drilling",
            "type":"Manufacturing & Wholesale Goods"
        }
    ],
    "sg:phone":"+1 303 369 7487",
    "sg:postcode":"80015",
    "sg:province":"CO",
    "sg:tags":[
        "exploration"
    ],
    "wof:name":"Duncan Exploration Inc",
    "wof:placetype":"venue"
},
  "geometry": {"coordinates":[-104.81487300000001,39.636876],"type":"Point"}
}