{
  "type": "Feature",
  "properties": {
    "addr:full":"4900 S Wadsworth Blvd Lakewood CO 80123",
    "addr:housenumber":"4900",
    "addr:postcode":"80123",
    "addr:street":"S Wadsworth Blvd",
    "iso:country":"US",
    "sg:address":"4900 S Wadsworth Blvd",
    "sg:city":"Lakewood",
    "sg:classifiers":[
        {
            "category":"Real Estate",
            "subcategory":"Real Estate Agent",
            "type":"Services"
        }
    ],
    "sg:phone":"+1 303 978 9430",
    "sg:postcode":"80123",
    "sg:province":"CO",
    "wof:name":"Unique Property & Development",
    "wof:placetype":"venue"
},
  "geometry": {"coordinates":[-105.08172999999999,39.628225],"type":"Point"}
}