{
  "type": "Feature",
  "properties": {
    "addr:full":"1967 S Broadway Denver CO 80210",
    "addr:housenumber":"1967",
    "addr:postcode":"80210",
    "addr:street":"S Broadway",
    "iso:country":"US",
    "sg:address":"1967 S Broadway",
    "sg:city":"Denver",
    "sg:classifiers":[
        {
            "category":"Bars & Pubs",
            "subcategory":"Dive Bar",
            "type":"Food & Drink"
        }
    ],
    "sg:phone":"+1 303 722 0280",
    "sg:postcode":"80210",
    "sg:province":"CO",
    "wof:name":"Bushwacker's Saloon",
    "wof:placetype":"venue"
},
  "geometry": {"coordinates":[-104.98741200000001,39.680712],"type":"Point"}
}