{
  "type": "Feature",
  "properties": {
    "addr:full":"105 Sheridan Blvd Denver CO 80226",
    "addr:housenumber":"105",
    "addr:postcode":"80226",
    "addr:street":"Sheridan Blvd",
    "iso:country":"US",
    "sg:address":"105 Sheridan Blvd",
    "sg:city":"Denver",
    "sg:classifiers":[
        {
            "category":"Food & Beverages",
            "subcategory":"Groceries & Convenience Stores",
            "type":"Retail Goods"
        }
    ],
    "sg:phone":"+1 303 238 6764",
    "sg:postcode":"80226",
    "sg:province":"CO",
    "sg:tags":[
        "market"
    ],
    "wof:name":"Won's Market",
    "wof:placetype":"venue"
},
  "geometry": {"coordinates":[-105.053203,39.718463],"type":"Point"}
}