{
  "type": "Feature",
  "properties": {
    "iso:country":"US",
    "sg:address":"2501 S Colorado Boulevard",
    "sg:city":"Denver",
    "sg:classifiers":[
        {
            "category":"Travel",
            "subcategory":"Hotels & Motels",
            "type":"Entertainment"
        }
    ],
    "sg:phone":"+1 303 567 0948",
    "sg:postcode":"80222",
    "sg:province":"CO",
    "wof:name":"Columbine Motel",
    "wof:placetype":"venue"
},
  "geometry": {"coordinates":[-104.940619,39.669831],"type":"Point"}
}