{
  "type": "Feature",
  "properties": {
    "addr:full":"113 Denargo Market Denver CO 80216",
    "addr:housenumber":"113",
    "addr:postcode":"80216",
    "addr:street":"Denargo",
    "iso:country":"US",
    "sg:address":"113 Denargo Market",
    "sg:city":"Denver",
    "sg:classifiers":[
        {
            "category":"Wholesale",
            "subcategory":"Non-durable Goods",
            "type":"Manufacturing & Wholesale Goods"
        }
    ],
    "sg:phone":"+1 303 295 6539",
    "sg:postcode":"80216",
    "sg:province":"CO",
    "wof:name":"Bailey & Son's Distributing",
    "wof:placetype":"venue"
},
  "geometry": {"coordinates":[-104.990021,39.763124],"type":"Point"}
}