{
  "type": "Feature",
  "properties": {
    "addr:full":"29007 Upper Bear Creek Rd Evergreen CO 80439",
    "addr:housenumber":"29007",
    "addr:postcode":"80439",
    "addr:street":"Upper Bear Creek Rd",
    "iso:country":"US",
    "sg:address":"29007 Upper Bear Creek Rd",
    "sg:city":"Evergreen",
    "sg:classifiers":[
        {
            "category":"Shopping",
            "subcategory":"Florist",
            "type":"Retail Goods"
        }
    ],
    "sg:phone":"+1 303 674 9400",
    "sg:postcode":"80439",
    "sg:province":"CO",
    "wof:name":"Stems A Flower Shop",
    "wof:placetype":"venue"
},
  "geometry": {"coordinates":[-105.328715,39.633619],"type":"Point"}
}