{
  "type": "Feature",
  "properties": {
    "iso:country":"US",
    "sg:address":"11934 W Applewood Knolls Dr",
    "sg:city":"Denver",
    "sg:classifiers":[
        {
            "category":"Banks & Credit Unions",
            "subcategory":"Financial Services",
            "type":"Services"
        }
    ],
    "sg:phone":"+1 303 233 2703",
    "sg:postcode":"80215",
    "sg:province":"CO",
    "sg:tags":[
        "investor"
    ],
    "wof:name":"Tatsumoto Investments LLC",
    "wof:placetype":"venue"
},
  "geometry": {"coordinates":[-105.129189,39.755583],"type":"Point"}
}