{
  "type": "Feature",
  "properties": {
    "addr:full":"729 Pinewood Dr Lyons CO 80540",
    "addr:housenumber":"729",
    "addr:postcode":"80540",
    "addr:street":"Pinewood Dr",
    "iso:country":"US",
    "sg:address":"729 Pinewood Dr",
    "sg:city":"Lyons",
    "sg:classifiers":[
        {
            "category":"Restaurant",
            "type":"Food & Drink"
        }
    ],
    "sg:menulink":"http://www.allmenus.com/co/estes-park/276576-villa-tatra/menu/",
    "sg:phone":"+1 303 823 6819",
    "sg:postcode":"80540",
    "sg:province":"CO",
    "sg:tags":[
        "russian"
    ],
    "wof:name":"Villa Tatra",
    "wof:placetype":"venue"
},
  "geometry": {"coordinates":[-105.36007600000001,40.273591],"type":"Point"}
}