{
  "type": "Feature",
  "properties": {
    "iso:country":"US",
    "sg:address":"8100 Sunset Dr",
    "sg:city":"Denver",
    "sg:classifiers":[
        {
            "category":"Mining & Drilling",
            "type":"Manufacturing & Wholesale Goods"
        }
    ],
    "sg:phone":"+1 303 234 0664",
    "sg:postcode":"80214",
    "sg:province":"CO",
    "sg:tags":[
        "building",
        "landscaping",
        "remodeling"
    ],
    "wof:name":"Thomken Construction",
    "wof:placetype":"venue"
},
  "geometry": {"coordinates":[-105.087119,39.727907],"type":"Point"}
}