{
  "type": "Feature",
  "properties": {
    "iso:country":"US",
    "sg:address":"3280 Denargo St",
    "sg:city":"Denver",
    "sg:classifiers":[
        {
            "category":"Manufacturing",
            "subcategory":"Tools & Machinery",
            "type":"Manufacturing & Wholesale Goods"
        }
    ],
    "sg:phone":"+1 303 295 6000",
    "sg:postcode":"80216",
    "sg:province":"CO",
    "sg:tags":[
        "machine",
        "shop",
        "jobbing",
        "repair"
    ],
    "wof:name":"Denver Machine Shop Inc",
    "wof:placetype":"venue"
},
  "geometry": {"coordinates":[-104.990916,39.763435],"type":"Point"}
}