{
  "type": "Feature",
  "properties": {
    "iso:country":"US",
    "sg:address":"3018 W 22nd St",
    "sg:city":"Pueblo",
    "sg:classifiers":[
        {
            "category":"Professional",
            "type":"Services"
        }
    ],
    "sg:phone":"+1 719 543 7923",
    "sg:postcode":"81003",
    "sg:province":"CO",
    "sg:tags":[
        "establishment"
    ],
    "wof:name":"Costa Communities",
    "wof:placetype":"venue"
},
  "geometry": {"coordinates":[-104.657572,38.287223],"type":"Point"}
}