{
  "type": "Feature",
  "properties": {
    "addr:full":"3590 Hartsel Dr Colorado Springs CO 80920",
    "addr:housenumber":"3590",
    "addr:postcode":"80920",
    "addr:street":"Hartsel Dr",
    "iso:country":"US",
    "sg:address":"3590 Hartsel Dr",
    "sg:city":"Colorado Springs",
    "sg:classifiers":[
        {
            "category":"Personal",
            "subcategory":"Beauty Salon",
            "type":"Services"
        }
    ],
    "sg:phone":"+1 719 272 0113",
    "sg:postcode":"80920",
    "sg:province":"CO",
    "sg:tags":[
        "shop"
    ],
    "wof:name":"Attitudes Hair Salon",
    "wof:placetype":"venue"
},
  "geometry": {"coordinates":[-104.759468,38.938848],"type":"Point"}
}