{
  "type": "Feature",
  "properties": {
    "iso:country":"US",
    "sg:address":"10200 E Mississippi Ave",
    "sg:city":"Denver",
    "sg:classifiers":[
        {
            "category":"Home & Garden",
            "subcategory":"Home Furnishings",
            "type":"Retail Goods"
        }
    ],
    "sg:phone":"+1 303 751 6688",
    "sg:postcode":"80247",
    "sg:province":"CO",
    "wof:name":"Alfa Blinds",
    "wof:placetype":"venue"
},
  "geometry": {"coordinates":[-104.869733,39.696457],"type":"Point"}
}