{
  "type": "Feature",
  "properties": {
    "iso:country":"US",
    "sg:address":"5445 Dtc Pkwy",
    "sg:city":"Greenwood Vlg",
    "sg:classifiers":[
        {
            "category":"Shopping",
            "subcategory":"Computers & Home Electronics",
            "type":"Retail Goods"
        }
    ],
    "sg:phone":"+1 303 488 3430",
    "sg:postcode":"80111",
    "sg:province":"CO",
    "sg:tags":[
        "software"
    ],
    "wof:name":"People Soft Inc",
    "wof:placetype":"venue"
},
  "geometry": {"coordinates":[-104.896162,39.617378],"type":"Point"}
}