{
  "type": "Feature",
  "properties": {
    "iso:country":"US",
    "sg:address":"1405 Hawkridge Rd",
    "sg:city":"Eaton",
    "sg:classifiers":[
        {
            "category":"Building & Trades",
            "subcategory":"Construction",
            "type":"Services"
        }
    ],
    "sg:phone":"+1 970 454 3952",
    "sg:postcode":"80615",
    "sg:province":"CO",
    "sg:tags":[
        "hanging",
        "contractor"
    ],
    "wof:name":"H & H Lawn & Paint",
    "wof:placetype":"venue"
},
  "geometry": {"coordinates":[-104.697187,40.544912],"type":"Point"}
}