{
  "type": "Feature",
  "properties": {
    "addr:full":"6280 W Jefferson Pl Denver CO 80226",
    "addr:housenumber":"6280",
    "addr:postcode":"80226",
    "addr:street":"W Jefferson Pl",
    "iso:country":"US",
    "sg:address":"6280 W Jefferson Pl",
    "sg:city":"Denver",
    "sg:classifiers":[
        {
            "category":"Shopping",
            "subcategory":"Jewelry",
            "type":"Retail Goods"
        }
    ],
    "sg:phone":"+1 303 934 8884",
    "sg:postcode":"80226",
    "sg:province":"CO",
    "wof:name":"Silver Feather Jewelry",
    "wof:placetype":"venue"
},
  "geometry": {"coordinates":[-105.064932,39.704896],"type":"Point"}
}