{
  "type": "Feature",
  "properties": {
    "addr:full":"5508 S Hill St Littleton CO 80120",
    "addr:housenumber":"5508",
    "addr:postcode":"80120",
    "addr:street":"S Hill St",
    "iso:country":"US",
    "sg:address":"5508 S Hill St",
    "sg:city":"Littleton",
    "sg:classifiers":[
        {
            "category":"Home & Garden",
            "subcategory":"Carpets & Floor Coverings",
            "type":"Retail Goods"
        }
    ],
    "sg:phone":"+1 303 738 0265",
    "sg:postcode":"80120",
    "sg:province":"CO",
    "wof:name":"Bob Floorguy",
    "wof:placetype":"venue"
},
  "geometry": {"coordinates":[-105.014067,39.615388],"type":"Point"}
}