{
  "type": "Feature",
  "properties": {
    "addr:full":"2230 Oneida St Denver CO 80207",
    "addr:housenumber":"2230",
    "addr:postcode":"80207",
    "addr:street":"Oneida St",
    "iso:country":"US",
    "sg:address":"2230 Oneida St",
    "sg:city":"Denver",
    "sg:classifiers":[
        {
            "category":"Food & Beverages",
            "subcategory":"Liquor & Beverages",
            "type":"Retail Goods"
        }
    ],
    "sg:phone":"+1 303 388 3105",
    "sg:postcode":"80207",
    "sg:province":"CO",
    "sg:tags":[
        "alcoholic"
    ],
    "wof:name":"Oneida Liquors",
    "wof:placetype":"venue"
},
  "geometry": {"coordinates":[-104.90808800000001,39.750646],"type":"Point"}
}