{
  "type": "Feature",
  "properties": {
    "iso:country":"US",
    "sg:address":"5812 W Chestnut Ave",
    "sg:city":"Littleton",
    "sg:classifiers":[
        {
            "category":"Home & Garden",
            "subcategory":"Furniture",
            "type":"Retail Goods"
        }
    ],
    "sg:phone":"+1 303 932 7015",
    "sg:postcode":"80128",
    "sg:province":"CO",
    "sg:tags":[
        "water",
        "bed"
    ],
    "wof:name":"Wicken's Waterbed Delivery Svc",
    "wof:placetype":"venue"
},
  "geometry": {"coordinates":[-105.062833,39.569385],"type":"Point"}
}