{
  "type": "Feature",
  "properties": {
    "iso:country":"US",
    "sg:address":"136 S Main St",
    "sg:city":"Longmont",
    "sg:classifiers":[
        {
            "category":"Manufacturing",
            "subcategory":"Printing",
            "type":"Manufacturing & Wholesale Goods"
        }
    ],
    "sg:phone":"+1 303 651 3360",
    "sg:postcode":"80501",
    "sg:province":"CO",
    "sg:tags":[
        "lithographic",
        "commercial"
    ],
    "wof:name":"Rabbit Hill Graphics",
    "wof:placetype":"venue"
},
  "geometry": {"coordinates":[-105.10246100000001,40.156897],"type":"Point"}
}