{
  "type": "Feature",
  "properties": {
    "iso:country":"US",
    "sg:address":"3805 Wadsworth Boulevard",
    "sg:city":"Wheat Ridge",
    "sg:classifiers":[
        {
            "category":"Autos & Motor Vehicles",
            "subcategory":"Auto Supplies",
            "type":"Retail Goods"
        }
    ],
    "sg:phone":"+1 303 431 0404",
    "sg:postcode":"80033",
    "sg:province":"CO",
    "sg:tags":[
        "tire"
    ],
    "wof:name":"Midas Auto Service Experts",
    "wof:placetype":"venue"
},
  "geometry": {"coordinates":[-105.081581,39.769648],"type":"Point"}
}