{
  "type": "Feature",
  "properties": {
    "addr:full":"2104 E Lincoln Ave Fort Collins CO 80524",
    "addr:housenumber":"2104",
    "addr:postcode":"80524",
    "addr:street":"E Lincoln Ave",
    "iso:country":"US",
    "sg:address":"2104 E Lincoln Ave",
    "sg:city":"Fort Collins",
    "sg:classifiers":[
        {
            "category":"Building & Trades",
            "subcategory":"Construction",
            "type":"Services"
        }
    ],
    "sg:phone":"+1 970 493 1286",
    "sg:postcode":"80524",
    "sg:province":"CO",
    "sg:tags":[
        "contractor"
    ],
    "wof:name":"Connell Resources Inc Welding",
    "wof:placetype":"venue"
},
  "geometry": {"coordinates":[-105.039109,40.581411],"type":"Point"}
}