{
  "type": "Feature",
  "properties": {
    "addr:full":"1288 S Havana St Aurora CO 80012",
    "addr:housenumber":"1288",
    "addr:postcode":"80012",
    "addr:street":"S Havana St",
    "iso:country":"US",
    "sg:address":"1288 S Havana St",
    "sg:city":"Aurora",
    "sg:classifiers":[
        {
            "category":"Retail",
            "subcategory":"Portrait Studio",
            "type":"Services"
        }
    ],
    "sg:phone":"+1 303 696 8150",
    "sg:postcode":"80012",
    "sg:province":"CO",
    "sg:tags":[
        "photographer"
    ],
    "wof:name":"Focused Faces",
    "wof:placetype":"venue"
},
  "geometry": {"coordinates":[-104.865887,39.694838],"type":"Point"}
}