{
  "type": "Feature",
  "properties": {
    "iso:country":"US",
    "sg:address":"1452 P Rd",
    "sg:city":"Loma",
    "sg:phone":"+1 970 858 7483",
    "sg:postcode":"81524",
    "sg:province":"CO",
    "sg:tags":[
        "farm",
        "corn"
    ],
    "wof:name":"Mannel Farms",
    "wof:placetype":"venue"
},
  "geometry": {"coordinates":[-108.77578800000001,39.236743],"type":"Point"}
}