{
  "type": "Feature",
  "properties": {
    "addr:full":"8340 W Coal Mine Ave Littleton CO 80123",
    "addr:housenumber":"8340",
    "addr:postcode":"80123",
    "addr:street":"W Coal Mine Ave",
    "iso:country":"US",
    "sg:address":"8340 W Coal Mine Ave",
    "sg:city":"Littleton",
    "sg:classifiers":[
        {
            "category":"Banks & Credit Unions",
            "subcategory":"Investment Brokerage",
            "type":"Services"
        }
    ],
    "sg:phone":"+1 303 948 2032",
    "sg:postcode":"80123",
    "sg:province":"CO",
    "sg:tags":[
        "advisory"
    ],
    "wof:name":"B I Investments",
    "wof:placetype":"venue"
},
  "geometry": {"coordinates":[-105.087153,39.595135],"type":"Point"}
}