{
  "type": "Feature",
  "properties": {
    "iso:country":"US",
    "sg:address":"4372 S College Ave",
    "sg:city":"Fort Collins",
    "sg:classifiers":[
        {
            "category":"Personal",
            "subcategory":"Beauty Salon",
            "type":"Services"
        }
    ],
    "sg:phone":"+1 970 282 0964",
    "sg:postcode":"80525",
    "sg:province":"CO",
    "sg:tags":[
        "shop"
    ],
    "wof:name":"Supercuts",
    "wof:placetype":"venue"
},
  "geometry": {"coordinates":[-105.07699700000001,40.527595],"type":"Point"}
}