{
  "type": "Feature",
  "properties": {
    "iso:country":"US",
    "sg:address":"6027 W 32nd Ave",
    "sg:city":"Wheat Ridge",
    "sg:classifiers":[
        {
            "category":"Manufacturing",
            "subcategory":"Signs",
            "type":"Manufacturing & Wholesale Goods"
        }
    ],
    "sg:phone":"+1 303 232 8647",
    "sg:postcode":"80033",
    "sg:province":"CO",
    "sg:tags":[
        "commercial",
        "specialty",
        "mfg"
    ],
    "wof:name":"M G Graphics",
    "wof:placetype":"venue"
},
  "geometry": {"coordinates":[-105.063239,39.762166],"type":"Point"}
}