{
  "type": "Feature",
  "properties": {
    "iso:country":"US",
    "sg:address":"1785 Hanover St",
    "sg:city":"Aurora",
    "sg:classifiers":[
        {
            "category":"Real Estate",
            "subcategory":"Real Estate Services",
            "type":"Services"
        },
        {
            "category":"Building & Trades",
            "subcategory":"Cleaning & Sanitation",
            "type":"Services"
        }
    ],
    "sg:phone":"+1 303 571 9384",
    "sg:postcode":"80010",
    "sg:province":"CO",
    "sg:tags":[
        "maintenance",
        "cleaners-interior"
    ],
    "wof:name":"Hallelujah House Cleaning",
    "wof:placetype":"venue"
},
  "geometry": {"coordinates":[-104.867012,39.744547],"type":"Point"}
}