{
  "type": "Feature",
  "properties": {
    "iso:country":"US",
    "sg:address":"582 S Everett Ct",
    "sg:city":"Denver",
    "sg:classifiers":[
        {
            "category":"Real Estate",
            "subcategory":"Real Estate Operator",
            "type":"Services"
        }
    ],
    "sg:phone":"+1 303 988 6265",
    "sg:postcode":"80226",
    "sg:province":"CO",
    "sg:tags":[
        "building",
        "apartment"
    ],
    "wof:name":"Toni Lynn Apartments LLC",
    "wof:placetype":"venue"
},
  "geometry": {"coordinates":[-105.096346,39.70565],"type":"Point"}
}