{
  "type": "Feature",
  "properties": {
    "iso:country":"US",
    "sg:address":"210 W Oak St",
    "sg:city":"Fort Collins",
    "sg:classifiers":[
        {
            "category":"Insurance",
            "subcategory":"Insurance Agent",
            "type":"Services"
        }
    ],
    "sg:phone":"+1 970 495 1284",
    "sg:postcode":"80521",
    "sg:province":"CO",
    "wof:name":"First National Trust Div",
    "wof:placetype":"venue"
},
  "geometry": {"coordinates":[-105.07969199999999,40.585676],"type":"Point"}
}