{
  "type": "Feature",
  "properties": {
    "iso:country":"US",
    "sg:address":"321 Quail Dr",
    "sg:city":"Grand Junction",
    "sg:classifiers":[
        {
            "category":"Professional",
            "type":"Services"
        }
    ],
    "sg:phone":"+1 970 245 1195",
    "sg:postcode":"81503",
    "sg:province":"CO",
    "wof:name":"Thomas and Sun Inc",
    "wof:placetype":"venue"
},
  "geometry": {"coordinates":[-108.64729699999999,39.049176],"type":"Point"}
}