{
  "type": "Feature",
  "properties": {
    "addr:full":"5275 W 66th Avenue Arvada CO 80003",
    "addr:housenumber":"5275",
    "addr:postcode":"80003",
    "addr:street":"W 66Th Avenue",
    "iso:country":"US",
    "sg:address":"5275 W 66th Avenue",
    "sg:city":"Arvada",
    "sg:classifiers":[
        {
            "category":"Real Estate",
            "subcategory":"Real Estate Operator",
            "type":"Services"
        }
    ],
    "sg:phone":"+1 303 422 0228",
    "sg:postcode":"80003",
    "sg:province":"CO",
    "sg:tags":[
        "apartment"
    ],
    "wof:name":"Sheridan Ridge Townhomes",
    "wof:placetype":"venue"
},
  "geometry": {"coordinates":[-105.05405500000001,39.816301],"type":"Point"}
}