{
  "type": "Feature",
  "properties": {
    "addr:full":"26269 Old Grand Mesa Rd Cedaredge CO 81413",
    "addr:housenumber":"26269",
    "addr:postcode":"81413",
    "addr:street":"Old Grand Mesa Rd",
    "iso:country":"US",
    "sg:address":"26269 Old Grand Mesa Rd",
    "sg:city":"Cedaredge",
    "sg:classifiers":[
        {
            "category":"Travel",
            "subcategory":"Campground",
            "type":"Entertainment"
        }
    ],
    "sg:phone":"+1 970 856 3455",
    "sg:postcode":"81413",
    "sg:province":"CO",
    "sg:tags":[
        "camp"
    ],
    "wof:name":"Grand Mesa Christian Assn",
    "wof:placetype":"venue"
},
  "geometry": {"coordinates":[-107.94902399999999,39.038154],"type":"Point"}
}