{
  "type": "Feature",
  "properties": {
    "addr:full":"2192 W College Ave Englewood CO 80110",
    "addr:housenumber":"2192",
    "addr:postcode":"80110",
    "addr:street":"W College Ave",
    "iso:country":"US",
    "sg:address":"2192 W College Ave",
    "sg:city":"Englewood",
    "sg:classifiers":[
        {
            "category":"Education",
            "subcategory":"School",
            "type":"Public Place"
        }
    ],
    "sg:phone":"+1 303 937 9226",
    "sg:postcode":"80110",
    "sg:province":"CO",
    "wof:name":"Mad Monkey Project",
    "wof:placetype":"venue"
},
  "geometry": {"coordinates":[-105.013268,39.668403],"type":"Point"}
}