{
  "type": "Feature",
  "properties": {
    "addr:full":"400 San Juan St Trinidad CO 81082",
    "addr:housenumber":"400",
    "addr:postcode":"81082",
    "addr:street":"San Juan St",
    "iso:country":"US",
    "sg:address":"400 San Juan St",
    "sg:city":"Trinidad",
    "sg:classifiers":[
        {
            "category":"Real Estate",
            "subcategory":"Real Estate Operator",
            "type":"Services"
        }
    ],
    "sg:phone":"+1 719 846 4380",
    "sg:postcode":"81082",
    "sg:province":"CO",
    "sg:tags":[
        "mobile",
        "home",
        "site"
    ],
    "wof:name":"Lake Side Trailer Park",
    "wof:placetype":"venue"
},
  "geometry": {"coordinates":[-104.518325,37.166644],"type":"Point"}
}