{
  "type": "Feature",
  "properties": {
    "iso:country":"US",
    "sg:address":"3780 S Elati St",
    "sg:city":"Englewood",
    "sg:classifiers":[
        {
            "category":"Shopping",
            "subcategory":"Gifts & Souvenirs",
            "type":"Retail Goods"
        }
    ],
    "sg:phone":"+1 303 761 5047",
    "sg:postcode":"80110",
    "sg:province":"CO",
    "wof:name":"Kathies Import Chalet",
    "wof:placetype":"venue"
},
  "geometry": {"coordinates":[-104.99353499999999,39.647743],"type":"Point"}
}