{
  "type": "Feature",
  "properties": {
    "iso:country":"US",
    "sg:address":"6400 S Fiddlers Green Cir",
    "sg:city":"Englewood",
    "sg:classifiers":[
        {
            "category":"Utilities",
            "subcategory":"Telephone",
            "type":"Services"
        }
    ],
    "sg:phone":"+1 303 224 7400",
    "sg:postcode":"80111",
    "sg:province":"CO",
    "sg:tags":[
        "provider"
    ],
    "wof:name":"Getapproved Com LLC",
    "wof:placetype":"venue"
},
  "geometry": {"coordinates":[-104.89016700000001,39.60013],"type":"Point"}
}