{
  "type": "Feature",
  "properties": {
    "iso:country":"US",
    "sg:address":"2379 W Main St",
    "sg:city":"Littleton",
    "sg:classifiers":[
        {
            "category":"Shopping",
            "subcategory":"Bicycles & Sporting Goods",
            "type":"Retail Goods"
        }
    ],
    "sg:phone":"+1 303 798 6792",
    "sg:postcode":"80120",
    "sg:province":"CO",
    "sg:tags":[
        "firearm",
        "related"
    ],
    "wof:name":"Shootin Shop South",
    "wof:placetype":"venue"
},
  "geometry": {"coordinates":[-105.015497,39.613797],"type":"Point"}
}