{
  "type": "Feature",
  "properties": {
    "iso:country":"US",
    "sg:address":"1414 S Main St",
    "sg:city":"Delta",
    "sg:classifiers":[
        {
            "category":"Autos & Motor Vehicles",
            "subcategory":"Automobile Sales",
            "type":"Retail Goods"
        }
    ],
    "sg:phone":"+1 970 874 5589",
    "sg:postcode":"81416",
    "sg:province":"CO",
    "wof:name":"Brickyard Motors",
    "wof:placetype":"venue"
},
  "geometry": {"coordinates":[-108.067571,38.728277],"type":"Point"}
}