{
  "type": "Feature",
  "properties": {
    "iso:country":"US",
    "sg:address":"3256 F Rd",
    "sg:city":"Clifton",
    "sg:classifiers":[
        {
            "category":"Retail",
            "subcategory":"Veterinary Services",
            "type":"Services"
        }
    ],
    "sg:phone":"+1 970 434 0811",
    "sg:postcode":"81520",
    "sg:province":"CO",
    "wof:name":"Jean Fromm DVM",
    "wof:placetype":"venue"
},
  "geometry": {"coordinates":[-108.450247,39.091779],"type":"Point"}
}