{
  "type": "Feature",
  "properties": {
    "addr:full":"12550 W 64th Ave Arvada CO 80004",
    "addr:housenumber":"12550",
    "addr:postcode":"80004",
    "addr:street":"W 64Th Ave",
    "iso:country":"US",
    "sg:address":"12550 W 64th Ave",
    "sg:city":"Arvada",
    "sg:classifiers":[
        {
            "category":"Restaurant",
            "type":"Food & Drink"
        }
    ],
    "sg:menulink":"http://www.allmenus.com/co/northeast-jefferson/221706-chipotle/menu/",
    "sg:phone":"+1 303 432 1101",
    "sg:postcode":"80004",
    "sg:province":"CO",
    "sg:tags":[
        "mexican"
    ],
    "wof:name":"Chipotle",
    "wof:placetype":"venue"
},
  "geometry": {"coordinates":[-105.139458,39.811285],"type":"Point"}
}