{
  "type": "Feature",
  "properties": {
    "addr:full":"3180 E 88th Ave Denver CO 80229",
    "addr:housenumber":"3180",
    "addr:postcode":"80229",
    "addr:street":"E 88Th Ave",
    "iso:country":"US",
    "sg:address":"3180 E 88th Ave",
    "sg:city":"Denver",
    "sg:classifiers":[
        {
            "category":"Manufacturing",
            "subcategory":"Signs",
            "type":"Manufacturing & Wholesale Goods"
        }
    ],
    "sg:phone":"+1 303 289 3055",
    "sg:postcode":"80229",
    "sg:province":"CO",
    "sg:tags":[
        "specialty",
        "mfg"
    ],
    "wof:name":"Beech Graphics",
    "wof:placetype":"venue"
},
  "geometry": {"coordinates":[-104.953738,39.856058],"type":"Point"}
}