{
  "type": "Feature",
  "properties": {
    "iso:country":"US",
    "sg:address":"320 S Simms St",
    "sg:city":"Denver",
    "sg:classifiers":[
        {
            "category":"Building & Trades",
            "subcategory":"Construction",
            "type":"Services"
        }
    ],
    "sg:phone":"+1 303 716 3024",
    "sg:postcode":"80228",
    "sg:province":"CO",
    "sg:tags":[
        "house"
    ],
    "wof:name":"AB Construction & Inspection",
    "wof:placetype":"venue"
},
  "geometry": {"coordinates":[-105.128396,39.710249],"type":"Point"}
}