{
  "type": "Feature",
  "properties": {
    "addr:full":"644 Bean Ranch Rd Whitewater CO 81527",
    "addr:housenumber":"644",
    "addr:postcode":"81527",
    "addr:street":"Bean Ranch Rd",
    "iso:country":"US",
    "sg:address":"644 Bean Ranch Rd",
    "sg:city":"Whitewater",
    "sg:classifiers":[
        {
            "category":"Building & Trades",
            "subcategory":"Construction",
            "type":"Services"
        }
    ],
    "sg:phone":"+1 970 242 9235",
    "sg:postcode":"81527",
    "sg:province":"CO",
    "sg:tags":[
        "underground",
        "utility",
        "contractor"
    ],
    "wof:name":"Edex Construction Inc",
    "wof:placetype":"venue"
},
  "geometry": {"coordinates":[-108.39039,38.919051],"type":"Point"}
}