{
  "type": "Feature",
  "properties": {
    "iso:country":"US",
    "sg:address":"30979 Co Rd 64",
    "sg:city":"Gill",
    "sg:classifiers":[
        {
            "category":"Professional",
            "subcategory":"Business Services",
            "type":"Services"
        }
    ],
    "sg:phone":"+1 970 352 3755",
    "sg:postcode":"80624",
    "sg:province":"CO",
    "sg:tags":[
        "embroidery"
    ],
    "wof:name":"Duo Designs",
    "wof:placetype":"venue"
},
  "geometry": {"coordinates":[-104.48472099999999,40.450201],"type":"Point"}
}