{
  "type": "Feature",
  "properties": {
    "iso:country":"US",
    "sg:address":"23205 Co Rd 13",
    "sg:city":"Johnstown",
    "sg:classifiers":[
        {
            "category":"Utilities",
            "subcategory":"Water",
            "type":"Services"
        }
    ],
    "sg:phone":"+1 970 587 2230",
    "sg:postcode":"80534",
    "sg:province":"CO",
    "sg:tags":[
        "supply"
    ],
    "wof:name":"Johnstown Water Works",
    "wof:placetype":"venue"
},
  "geometry": {"coordinates":[-104.94179800000001,40.33586],"type":"Point"}
}