{
  "type": "Feature",
  "properties": {
    "iso:country":"US",
    "sg:address":"5171 Carr St",
    "sg:city":"Arvada",
    "sg:classifiers":[
        {
            "category":"Building & Trades",
            "subcategory":"Construction",
            "type":"Services"
        }
    ],
    "sg:phone":"+1 303 431 6972",
    "sg:postcode":"80002",
    "sg:province":"CO",
    "sg:tags":[
        "house"
    ],
    "wof:name":"Polish Craftsman Specialist",
    "wof:placetype":"venue"
},
  "geometry": {"coordinates":[-105.090851,39.790744],"type":"Point"}
}