{
  "type": "Feature",
  "properties": {
    "iso:country":"US",
    "sg:address":"2412 Lakeview Ave",
    "sg:city":"Pueblo",
    "sg:classifiers":[
        {
            "category":"Manufacturing",
            "subcategory":"Tools & Machinery",
            "type":"Manufacturing & Wholesale Goods"
        }
    ],
    "sg:phone":"+1 719 560 9307",
    "sg:postcode":"81004",
    "sg:province":"CO",
    "sg:tags":[
        "machine",
        "shop"
    ],
    "wof:name":"Crotty Metal Products",
    "wof:placetype":"venue"
},
  "geometry": {"coordinates":[-104.641271,38.234907],"type":"Point"}
}