{
  "type": "Feature",
  "properties": {
    "iso:country":"US",
    "sg:address":"2575 Glenwood Dr",
    "sg:city":"Boulder",
    "sg:classifiers":[
        {
            "category":"Organizations",
            "subcategory":"Religious Organization",
            "type":"Services"
        }
    ],
    "sg:phone":"+1 303 415 1025",
    "sg:postcode":"80304",
    "sg:province":"CO",
    "wof:name":"Jewish Family Svc",
    "wof:placetype":"venue"
},
  "geometry": {"coordinates":[-105.266552,40.033232],"type":"Point"}
}