{
  "type": "Feature",
  "properties": {
    "addr:full":"2826 S Gilpin St Denver CO 80210",
    "addr:housenumber":"2826",
    "addr:postcode":"80210",
    "addr:street":"S Gilpin St",
    "iso:country":"US",
    "sg:address":"2826 S Gilpin St",
    "sg:city":"Denver",
    "sg:classifiers":[
        {
            "category":"Professional",
            "subcategory":"Management & Consulting",
            "type":"Services"
        }
    ],
    "sg:phone":"+1 303 758 4497",
    "sg:postcode":"80210",
    "sg:province":"CO",
    "wof:name":"Family Challenge Group",
    "wof:placetype":"venue"
},
  "geometry": {"coordinates":[-104.967495,39.663882],"type":"Point"}
}