{
  "type": "Feature",
  "properties": {
    "addr:full":"3698 W 44th Avenue Denver CO 80211",
    "addr:housenumber":"3698",
    "addr:postcode":"80211",
    "addr:street":"W 44Th Avenue",
    "iso:country":"US",
    "sg:address":"3698 W 44th Avenue",
    "sg:city":"Denver",
    "sg:classifiers":[
        {
            "category":"Communications",
            "subcategory":"Television Station",
            "type":"Services"
        }
    ],
    "sg:phone":"+1 303 376 2200",
    "sg:postcode":"80211",
    "sg:province":"CO",
    "wof:name":"Denver City & County Government",
    "wof:placetype":"venue"
},
  "geometry": {"coordinates":[-105.035887,39.776665],"type":"Point"}
}