{
  "type": "Feature",
  "properties": {
    "iso:country":"US",
    "sg:address":"1919 14th St",
    "sg:city":"Boulder",
    "sg:classifiers":[
        {
            "category":"Banks & Credit Unions",
            "subcategory":"Financial Services",
            "type":"Services"
        }
    ],
    "sg:phone":"+1 303 544 1290",
    "sg:postcode":"80302",
    "sg:province":"CO",
    "sg:tags":[
        "company",
        "holding"
    ],
    "wof:name":"Willmax Holdings",
    "wof:placetype":"venue"
},
  "geometry": {"coordinates":[-105.277191,40.017639],"type":"Point"}
}