{
  "type": "Feature",
  "properties": {
    "iso:country":"US",
    "sg:address":"17999 W Colfax Ave",
    "sg:city":"Golden",
    "sg:classifiers":[
        {
            "category":"Bars & Pubs",
            "type":"Food & Drink"
        }
    ],
    "sg:phone":"+1 303 278 9000",
    "sg:postcode":"80401",
    "sg:province":"CO",
    "sg:tags":[
        "brew"
    ],
    "wof:name":"Susie's Bar & Grill",
    "wof:placetype":"venue"
},
  "geometry": {"coordinates":[-105.204941,39.719109],"type":"Point"}
}