{
  "type": "Feature",
  "properties": {
    "iso:country":"US",
    "sg:address":"2837 S Eastover St",
    "sg:city":"Bennett",
    "sg:classifiers":[
        {
            "category":"Building & Trades",
            "subcategory":"Plumbing",
            "type":"Services"
        }
    ],
    "sg:phone":"+1 303 367 1010",
    "sg:postcode":"80102",
    "sg:province":"CO",
    "sg:tags":[
        "plumbing",
        "contractor"
    ],
    "wof:name":"Maui Star Inc",
    "wof:placetype":"venue"
},
  "geometry": {"coordinates":[-104.42633600000001,39.668047],"type":"Point"}
}