{
  "type": "Feature",
  "properties": {
    "addr:full":"408 2nd St Kersey CO 80644",
    "addr:housenumber":"408",
    "addr:postcode":"80644",
    "addr:street":"2Nd St",
    "iso:country":"US",
    "sg:address":"408 2nd St",
    "sg:city":"Kersey",
    "sg:classifiers":[
        {
            "category":"Professional",
            "subcategory":"Computer Services",
            "type":"Services"
        }
    ],
    "sg:phone":"+1 970 353 5850",
    "sg:postcode":"80644",
    "sg:province":"CO",
    "sg:tags":[
        "repair"
    ],
    "wof:name":"Help Desk",
    "wof:placetype":"venue"
},
  "geometry": {"coordinates":[-104.56310499999999,40.385345],"type":"Point"}
}