{
  "type": "Feature",
  "properties": {
    "iso:country":"US",
    "sg:address":"2160 Ryeland Ln",
    "sg:city":"Fort Collins",
    "sg:classifiers":[
        {
            "category":"Professional",
            "type":"Services"
        }
    ],
    "sg:phone":"+1 970 416 6353",
    "sg:postcode":"80526",
    "sg:province":"CO",
    "sg:tags":[
        "writer"
    ],
    "wof:name":"Greenfire Creative LLC",
    "wof:placetype":"venue"
},
  "geometry": {"coordinates":[-105.12334199999999,40.559163],"type":"Point"}
}