{
  "type": "Feature",
  "properties": {
    "addr:full":"19 Niblick Ln Littleton CO 80123",
    "addr:housenumber":"19",
    "addr:postcode":"80123",
    "addr:street":"Niblick Ln",
    "iso:country":"US",
    "sg:address":"19 Niblick Ln",
    "sg:city":"Littleton",
    "sg:classifiers":[
        {
            "category":"Banks & Credit Unions",
            "subcategory":"Investment Brokerage",
            "type":"Services"
        }
    ],
    "sg:phone":"+1 303 795 8868",
    "sg:postcode":"80123",
    "sg:province":"CO",
    "sg:tags":[
        "consultant",
        "planning",
        "financial"
    ],
    "wof:name":"Greenbook Financial Svs",
    "wof:placetype":"venue"
},
  "geometry": {"coordinates":[-105.033884,39.603054],"type":"Point"}
}