{
  "type": "Feature",
  "properties": {
    "iso:country":"US",
    "sg:address":"517 Front St",
    "sg:city":"Fairplay",
    "sg:classifiers":[
        {
            "category":"Cinema",
            "subcategory":"Movie Rental",
            "type":"Entertainment"
        }
    ],
    "sg:phone":"+1 719 836 0255",
    "sg:postcode":"80440",
    "sg:province":"CO",
    "sg:tags":[
        "leasing",
        "video",
        "disc",
        "tape"
    ],
    "wof:name":"Windy Ridge Video & Feed",
    "wof:placetype":"venue"
},
  "geometry": {"coordinates":[-106.002354,39.223775],"type":"Point"}
}