{
  "type": "Feature",
  "properties": {
    "addr:full":"888 W Garden of the Gods Rd Colorado Springs CO 80907",
    "addr:housenumber":"888",
    "addr:postcode":"springs;80907",
    "addr:street":"W Garden Of The Gods Rd",
    "iso:country":"US",
    "sg:address":"888 W Garden of the Gods Rd",
    "sg:city":"Colorado Springs",
    "sg:classifiers":[
        {
            "category":"Organizations",
            "subcategory":"Non-profit Organization",
            "type":"Services"
        }
    ],
    "sg:phone":"+1 719 265 1867",
    "sg:postcode":"80907",
    "sg:province":"CO",
    "sg:tags":[
        "information",
        "alcoholism",
        "treatment"
    ],
    "wof:name":"Valley Hope Alcohol & Drug",
    "wof:placetype":"venue"
},
  "geometry": {"coordinates":[-104.842873,38.896763],"type":"Point"}
}