{
  "type": "Feature",
  "properties": {
    "iso:country":"US",
    "sg:address":"1360 Vine St",
    "sg:city":"Denver",
    "sg:classifiers":[
        {
            "category":"Education",
            "subcategory":"Preschool",
            "type":"Public Place"
        },
        {
            "category":"Education",
            "subcategory":"School",
            "type":"Public Place"
        }
    ],
    "sg:phone":"+1 303 399 1800",
    "sg:postcode":"80206",
    "sg:province":"CO",
    "sg:tags":[
        "elementary"
    ],
    "wof:name":"White Judith C Psyd",
    "wof:placetype":"venue"
},
  "geometry": {"coordinates":[-104.961998,39.738098],"type":"Point"}
}