{
  "type": "Feature",
  "properties": {
    "iso:country":"US",
    "sg:address":"8977 Spruce Mountain Rd",
    "sg:city":"Larkspur",
    "sg:classifiers":[
        {
            "category":"Real Estate",
            "subcategory":"Real Estate Agent",
            "type":"Services"
        }
    ],
    "sg:phone":"+1 303 681 1000",
    "sg:postcode":"80118",
    "sg:province":"CO",
    "sg:website":"www.secretproperties.com",
    "wof:name":"Realty World Results",
    "wof:placetype":"venue"
},
  "geometry": {"coordinates":[-104.88420499999999,39.23084],"type":"Point"}
}