{
  "type": "Feature",
  "properties": {
    "addr:full":"3810 Zurich Dr Colorado Springs CO 80920",
    "addr:housenumber":"3810",
    "addr:postcode":"80920",
    "addr:street":"Zurich Dr",
    "iso:country":"US",
    "sg:address":"3810 Zurich Dr",
    "sg:city":"Colorado Springs",
    "sg:classifiers":[
        {
            "category":"Manufacturing",
            "subcategory":"Tools & Machinery",
            "type":"Manufacturing & Wholesale Goods"
        }
    ],
    "sg:phone":"+1 719 282 0219",
    "sg:postcode":"80920",
    "sg:province":"CO",
    "sg:tags":[
        "equipment",
        "mfg"
    ],
    "wof:name":"Frisco Front Range Industrial",
    "wof:placetype":"venue"
},
  "geometry": {"coordinates":[-104.749478,38.959428],"type":"Point"}
}