{
  "type": "Feature",
  "properties": {
    "iso:country":"US",
    "sg:address":"8493 Nashua Cir",
    "sg:city":"Wellington",
    "sg:classifiers":[
        {
            "category":"Building & Trades",
            "subcategory":"Construction",
            "type":"Services"
        }
    ],
    "sg:phone":"+1 970 568 6349",
    "sg:postcode":"80549",
    "sg:province":"CO",
    "sg:tags":[
        "hanging",
        "contractor"
    ],
    "wof:name":"T&K Painting Contractors",
    "wof:placetype":"venue"
},
  "geometry": {"coordinates":[-105.01332499999999,40.706604],"type":"Point"}
}