{
  "type": "Feature",
  "properties": {
    "iso:country":"US",
    "sg:address":"20941 E Smoky Hill Rd",
    "sg:city":"Aurora",
    "sg:classifiers":[
        {
            "category":"Personal",
            "subcategory":"Beauty Salon",
            "type":"Services"
        }
    ],
    "sg:phone":"+1 303 690 1329",
    "sg:postcode":"80015",
    "sg:province":"CO",
    "wof:name":"Saddle Rock Salon",
    "wof:placetype":"venue"
},
  "geometry": {"coordinates":[-104.74182399999999,39.607433],"type":"Point"}
}