{
  "type": "Feature",
  "properties": {
    "iso:country":"US",
    "sg:address":"17947 E Berry Dr",
    "sg:city":"Aurora",
    "sg:classifiers":[
        {
            "category":"Wholesale",
            "subcategory":"Office Equipment",
            "type":"Manufacturing & Wholesale Goods"
        }
    ],
    "sg:phone":"+1 303 690 0172",
    "sg:postcode":"80015",
    "sg:province":"CO",
    "sg:tags":[
        "distributor",
        "computer",
        "related",
        "typewriter"
    ],
    "wof:name":"Typewriter Distr Liquidation",
    "wof:placetype":"venue"
},
  "geometry": {"coordinates":[-104.77761,39.615374],"type":"Point"}
}