{
  "type": "Feature",
  "properties": {
    "addr:full":"10798 Crystal Way Conifer CO 80465",
    "addr:housenumber":"10798",
    "addr:postcode":"80465",
    "addr:street":"Crystal Way",
    "iso:country":"US",
    "sg:address":"10798 Crystal Way",
    "sg:city":"Conifer",
    "sg:classifiers":[
        {
            "category":"Professional",
            "type":"Services"
        }
    ],
    "sg:phone":"+1 303 697 6698",
    "sg:postcode":"80465",
    "sg:province":"CO",
    "wof:name":"Nat Coalson Inc",
    "wof:placetype":"venue"
},
  "geometry": {"coordinates":[-105.245379,39.521761],"type":"Point"}
}