{
  "type": "Feature",
  "properties": {
    "iso:country":"US",
    "sg:address":"1549 Sherman Ave",
    "sg:city":"Canon City",
    "sg:classifiers":[
        {
            "category":"Professional",
            "subcategory":"Business Services",
            "type":"Services"
        }
    ],
    "sg:phone":"+1 719 275 7548",
    "sg:postcode":"81212",
    "sg:province":"CO",
    "sg:tags":[
        "process",
        "server"
    ],
    "wof:name":"Arkansas Valley Investigation",
    "wof:placetype":"venue"
},
  "geometry": {"coordinates":[-105.20987599999999,38.432211],"type":"Point"}
}