{
  "type": "Feature",
  "properties": {
    "iso:country":"US",
    "sg:address":"405 Chatfield Dr",
    "sg:city":"Colorado Springs",
    "sg:classifiers":[
        {
            "category":"Arts & Performance",
            "subcategory":"Theater",
            "type":"Entertainment"
        }
    ],
    "sg:phone":"+1 719 271 7112",
    "sg:postcode":"80911",
    "sg:province":"CO",
    "sg:tags":[
        "musician"
    ],
    "wof:name":"Robbie Lee Productions",
    "wof:placetype":"venue"
},
  "geometry": {"coordinates":[-104.739548,38.751898],"type":"Point"}
}