{
  "type": "Feature",
  "properties": {
    "addr:full":"3217 W Hampden Ave Englewood CO 80110",
    "addr:housenumber":"3217",
    "addr:postcode":"80110",
    "addr:street":"W Hampden Ave",
    "iso:country":"US",
    "sg:address":"3217 W Hampden Ave",
    "sg:city":"Englewood",
    "sg:classifiers":[
        {
            "category":"Health Services",
            "subcategory":"Medical Lab",
            "type":"Services"
        }
    ],
    "sg:phone":"+1 303 783 9965",
    "sg:postcode":"80110",
    "sg:province":"CO",
    "sg:tags":[
        "laboratory",
        "construction",
        "material",
        "testing"
    ],
    "wof:name":"CTS the Lab",
    "wof:placetype":"venue"
},
  "geometry": {"coordinates":[-105.028142,39.653361],"type":"Point"}
}