{
  "type": "Feature",
  "properties": {
    "addr:full":"222 Milwaukee Street Denver CO 80206",
    "addr:housenumber":"222",
    "addr:postcode":"80206",
    "addr:street":"Milwaukee Street",
    "iso:country":"US",
    "sg:address":"222 Milwaukee Street",
    "sg:city":"Denver",
    "sg:classifiers":[
        {
            "category":"Banks & Credit Unions",
            "subcategory":"Financial Services",
            "type":"Services"
        }
    ],
    "sg:phone":"+1 303 329 3479",
    "sg:postcode":"80206",
    "sg:province":"CO",
    "sg:tags":[
        "broker",
        "mortgage"
    ],
    "wof:name":"Regatta Capital",
    "wof:placetype":"venue"
},
  "geometry": {"coordinates":[-104.951711,39.734877],"type":"Point"}
}