{
  "type": "Feature",
  "properties": {
    "addr:full":"4427 S Xenophon Way Morrison CO 80465",
    "addr:housenumber":"4427",
    "addr:postcode":"80465",
    "addr:street":"S Xenophon Way",
    "iso:country":"US",
    "sg:address":"4427 S Xenophon Way",
    "sg:city":"Morrison",
    "sg:classifiers":[
        {
            "category":"Building & Trades",
            "subcategory":"Construction",
            "type":"Services"
        }
    ],
    "sg:phone":"+1 303 948 9281",
    "sg:postcode":"80465",
    "sg:province":"CO",
    "sg:tags":[
        "house"
    ],
    "wof:name":"R & G Renovation Creations",
    "wof:placetype":"venue"
},
  "geometry": {"coordinates":[-105.142072,39.63612],"type":"Point"}
}