{
  "type": "Feature",
  "properties": {
    "iso:country":"US",
    "sg:address":"7995 Federal Blvd",
    "sg:city":"Westminster",
    "sg:classifiers":[
        {
            "category":"Autos & Motor Vehicles",
            "subcategory":"Fuel & Gas Station",
            "type":"Retail Goods"
        }
    ],
    "sg:phone":"+1 303 426 8246",
    "sg:postcode":"80030",
    "sg:province":"CO",
    "sg:tags":[
        "oil"
    ],
    "wof:name":"Conoco Phillips",
    "wof:placetype":"venue"
},
  "geometry": {"coordinates":[-105.025059,39.839271],"type":"Point"}
}