{
  "type": "Feature",
  "properties": {
    "iso:country":"US",
    "sg:address":"13728 E Quincy Ave",
    "sg:city":"Aurora",
    "sg:classifiers":[
        {
            "category":"Food & Beverages",
            "subcategory":"Supermarket",
            "type":"Retail Goods"
        },
        {
            "category":"Food & Beverages",
            "subcategory":"Groceries & Convenience Stores",
            "type":"Retail Goods"
        }
    ],
    "sg:phone":"+1 303 699 1530",
    "sg:postcode":"80015",
    "sg:province":"CO",
    "sg:tags":[
        "super"
    ],
    "wof:name":"Eyropa Inc",
    "wof:placetype":"venue"
},
  "geometry": {"coordinates":[-104.828392,39.638514],"type":"Point"}
}