{
  "type": "Feature",
  "properties": {
    "addr:full":"1125 Fairfax St Denver CO 80220",
    "addr:housenumber":"1125",
    "addr:postcode":"80220",
    "addr:street":"Fairfax St",
    "iso:country":"US",
    "sg:address":"1125 Fairfax St",
    "sg:city":"Denver",
    "sg:classifiers":[
        {
            "category":"Manufacturing",
            "subcategory":"Jewelry",
            "type":"Manufacturing & Wholesale Goods"
        }
    ],
    "sg:phone":"+1 303 995 1232",
    "sg:postcode":"80220",
    "sg:province":"CO",
    "sg:tags":[
        "designer"
    ],
    "wof:name":"Ak Designs",
    "wof:placetype":"venue"
},
  "geometry": {"coordinates":[-104.92804700000001,39.733306],"type":"Point"}
}