{
  "type": "Feature",
  "properties": {
    "iso:country":"US",
    "sg:address":"1125 Fairfax St",
    "sg:city":"Denver",
    "sg:classifiers":[
        {
            "category":"Manufacturing",
            "subcategory":"Jewelry",
            "type":"Manufacturing & Wholesale Goods"
        }
    ],
    "sg:phone":"+1 303 995 1232",
    "sg:postcode":"80220",
    "sg:province":"CO",
    "sg:tags":[
        "designer"
    ],
    "wof:name":"Ak Designs",
    "wof:placetype":"venue"
},
  "geometry": {"coordinates":[-104.928047,39.733306],"type":"Point"}
}