{
  "type": "Feature",
  "properties": {
    "addr:full":"6929 Iris St Arvada CO 80004",
    "addr:housenumber":"6929",
    "addr:postcode":"80004",
    "addr:street":"Iris St",
    "iso:country":"US",
    "sg:address":"6929 Iris St",
    "sg:city":"Arvada",
    "sg:classifiers":[
        {
            "category":"Manufacturing",
            "subcategory":"Tools & Machinery",
            "type":"Manufacturing & Wholesale Goods"
        }
    ],
    "sg:phone":"+1 303 421 0993",
    "sg:postcode":"80004",
    "sg:province":"CO",
    "sg:tags":[
        "pumps-wholesale",
        "manufacturer",
        "fluid",
        "power",
        "mfg"
    ],
    "wof:name":"Musser Distributing",
    "wof:placetype":"venue"
},
  "geometry": {"coordinates":[-105.10678900000001,39.822287],"type":"Point"}
}