{
  "type": "Feature",
  "properties": {
    "iso:country":"US",
    "sg:address":"4193 S Dahlia St",
    "sg:city":"Englewood",
    "sg:classifiers":[
        {
            "category":"Utilities",
            "subcategory":"Water",
            "type":"Services"
        }
    ],
    "sg:phone":"+1 303 758 0646",
    "sg:postcode":"80113",
    "sg:province":"CO",
    "sg:tags":[
        "supply",
        "system",
        "sewerage"
    ],
    "wof:name":"Mansfel Hts Wtr Sanitation Dst",
    "wof:placetype":"venue"
},
  "geometry": {"coordinates":[-104.932091,39.641538],"type":"Point"}
}