{
  "type": "Feature",
  "properties": {
    "iso:country":"US",
    "sg:address":"448 N Main St",
    "sg:city":"Mancos",
    "sg:classifiers":[
        {
            "category":"Professional",
            "subcategory":"Management & Consulting",
            "type":"Services"
        }
    ],
    "sg:phone":"+1 970 533 1404",
    "sg:postcode":"81328",
    "sg:province":"CO",
    "sg:tags":[
        "skilled",
        "nursing"
    ],
    "wof:name":"C & G Health Care Management",
    "wof:placetype":"venue"
},
  "geometry": {"coordinates":[-108.28917,37.349319],"type":"Point"}
}