{
  "type": "Feature",
  "properties": {
    "iso:country":"US",
    "sg:address":"214 W Colorado Ave",
    "sg:city":"Colorado Springs",
    "sg:classifiers":[
        {
            "category":"Shopping",
            "subcategory":"Computers & Home Electronics",
            "type":"Retail Goods"
        }
    ],
    "sg:phone":"+1 719 227 1400",
    "sg:postcode":"80903",
    "sg:province":"CO",
    "sg:tags":[
        "equipment",
        "dealer"
    ],
    "sg:website":"www.smartmicro.com",
    "wof:name":"Surplus Max Intl Inc",
    "wof:placetype":"venue"
},
  "geometry": {"coordinates":[-104.829331,38.832705],"type":"Point"}
}