{
  "type": "Feature",
  "properties": {
    "iso:country":"US",
    "sg:address":"3421 W Dartmouth Ave",
    "sg:city":"Denver",
    "sg:classifiers":[
        {
            "category":"Professional",
            "type":"Services"
        }
    ],
    "sg:phone":"+1 303 922 4035",
    "sg:postcode":"80236",
    "sg:province":"CO",
    "wof:name":"Stephen C Thomason",
    "wof:placetype":"venue"
},
  "geometry": {"coordinates":[-105.03330099999999,39.661275],"type":"Point"}
}