{
  "type": "Feature",
  "properties": {
    "addr:full":"2552 W 65th Pl Denver CO 80221",
    "addr:housenumber":"2552",
    "addr:postcode":"80221",
    "addr:street":"W 65Th Pl",
    "iso:country":"US",
    "sg:address":"2552 W 65th Pl",
    "sg:city":"Denver",
    "sg:classifiers":[
        {
            "category":"Organizations",
            "subcategory":"Religious Organization",
            "type":"Services"
        }
    ],
    "sg:phone":"+1 303 428 5681",
    "sg:postcode":"80221",
    "sg:province":"CO",
    "sg:tags":[
        "church"
    ],
    "wof:name":"North Denver Apostolic Church",
    "wof:placetype":"venue"
},
  "geometry": {"coordinates":[-105.018568,39.81566],"type":"Point"}
}