{
  "type": "Feature",
  "properties": {
    "addr:full":"7017 W Elmhurst Ave Littleton CO 80128",
    "addr:housenumber":"7017",
    "addr:postcode":"80128",
    "addr:street":"W Elmhurst Ave",
    "iso:country":"US",
    "sg:address":"7017 W Elmhurst Ave",
    "sg:city":"Littleton",
    "sg:classifiers":[
        {
            "category":"Shopping",
            "subcategory":"Computers & Home Electronics",
            "type":"Retail Goods"
        }
    ],
    "sg:phone":"+1 303 771 0539",
    "sg:postcode":"80128",
    "sg:province":"CO",
    "sg:tags":[
        "software"
    ],
    "sg:website":"www.ndyn.com",
    "wof:name":"Enterprise Engineering Inc",
    "wof:placetype":"venue"
},
  "geometry": {"coordinates":[-105.075672,39.572149],"type":"Point"}
}