{
  "type": "Feature",
  "properties": {
    "addr:full":"7101 Dry Creek Ct Longmont CO 80503",
    "addr:housenumber":"7101",
    "addr:postcode":"80503",
    "addr:street":"Dry Creek Ct",
    "iso:country":"US",
    "sg:address":"7101 Dry Creek Ct",
    "sg:city":"Longmont",
    "sg:classifiers":[
        {
            "category":"Professional",
            "type":"Services"
        }
    ],
    "sg:phone":"+1 303 459 1108",
    "sg:postcode":"80503",
    "sg:province":"CO",
    "wof:name":"Main Street Carpentr",
    "wof:placetype":"venue"
},
  "geometry": {"coordinates":[-105.165571,40.104278],"type":"Point"}
}