{
  "type": "Feature",
  "properties": {
    "iso:country":"US",
    "sg:address":"2508 11th Ave",
    "sg:city":"Greeley",
    "sg:classifiers":[
        {
            "category":"Restaurant",
            "type":"Food & Drink"
        }
    ],
    "sg:menulink":"http://www.allmenus.com/co/greeley/96081-taco-johns/menu/",
    "sg:phone":"+1 970 352 5438",
    "sg:postcode":"80631",
    "sg:province":"CO",
    "sg:tags":[
        "american",
        "mexican"
    ],
    "wof:name":"Taco John's",
    "wof:placetype":"venue"
},
  "geometry": {"coordinates":[-104.696564,40.396947],"type":"Point"}
}