{
  "type": "Feature",
  "properties": {
    "iso:country":"US",
    "sg:address":"522 Boone Ave",
    "sg:city":"Buena Vista",
    "sg:classifiers":[
        {
            "category":"Retail",
            "subcategory":"Self-service Laundry",
            "type":"Services"
        }
    ],
    "sg:phone":"+1 719 395 6757",
    "sg:postcode":"81252",
    "sg:province":"CO",
    "wof:name":"Missing Sock Laundry",
    "wof:placetype":"venue"
},
  "geometry": {"coordinates":[-105.27967200000001,38.226016],"type":"Point"}
}