{
  "type": "Feature",
  "properties": {
    "iso:country":"US",
    "sg:address":"2460 I- 70 Business Lp",
    "sg:city":"Grand Junction",
    "sg:classifiers":[
        {
            "category":"Wholesale",
            "subcategory":"Electrical",
            "type":"Manufacturing & Wholesale Goods"
        }
    ],
    "sg:phone":"+1 970 245 0063",
    "sg:postcode":"81501",
    "sg:province":"CO",
    "sg:tags":[
        "telecommunication"
    ],
    "wof:name":"T J Communication",
    "wof:placetype":"venue"
},
  "geometry": {"coordinates":[-108.53396600000001,39.069007],"type":"Point"}
}