{
  "type": "Feature",
  "properties": {
    "iso:country":"US",
    "sg:address":"9604 W Sunrise Ave",
    "sg:city":"Littleton",
    "sg:classifiers":[
        {
            "category":"Banks & Credit Unions",
            "subcategory":"Bank",
            "type":"Services"
        }
    ],
    "sg:phone":"+1 303 471 5989",
    "sg:postcode":"80125",
    "sg:province":"CO",
    "sg:tags":[
        "broker",
        "mortgage"
    ],
    "wof:name":"Colorado Prof HM Mortgages LLC",
    "wof:placetype":"venue"
},
  "geometry": {"coordinates":[-105.065181,39.520887],"type":"Point"}
}