{
  "type": "Feature",
  "properties": {
    "iso:country":"US",
    "sg:address":"3926 Umatilla St",
    "sg:city":"Denver",
    "sg:classifiers":[
        {
            "category":"Shopping",
            "subcategory":"Hobbies, Toys, & Games",
            "type":"Retail Goods"
        }
    ],
    "sg:phone":"+1 303 964 9800",
    "sg:postcode":"80211",
    "sg:province":"CO",
    "sg:tags":[
        "hobby",
        "model",
        "shop"
    ],
    "wof:name":"Colorado Ultimate Association Inc",
    "wof:placetype":"venue"
},
  "geometry": {"coordinates":[-105.012356,39.770838],"type":"Point"}
}