{
  "type": "Feature",
  "properties": {
    "iso:country":"US",
    "sg:address":"60 W Bromley Ln",
    "sg:city":"Brighton",
    "sg:classifiers":[
        {
            "category":"Personal",
            "subcategory":"Beauty Salon",
            "type":"Services"
        }
    ],
    "sg:phone":"+1 303 655 9334",
    "sg:postcode":"80601",
    "sg:province":"CO",
    "wof:name":"Cost Cutters Family Hair Care",
    "wof:placetype":"venue"
},
  "geometry": {"coordinates":[-104.82396900000001,39.972224],"type":"Point"}
}