{
  "type": "Feature",
  "properties": {
    "iso:country":"US",
    "sg:address":"8022 Southpark Cir",
    "sg:city":"Littleton",
    "sg:classifiers":[
        {
            "category":"Education",
            "subcategory":"Vocational School",
            "type":"Public Place"
        }
    ],
    "sg:phone":"+1 303 797 9393",
    "sg:postcode":"80120",
    "sg:province":"CO",
    "sg:tags":[
        "training",
        "business"
    ],
    "wof:name":"N C T I",
    "wof:placetype":"venue"
},
  "geometry": {"coordinates":[-105.026122,39.568815],"type":"Point"}
}