{
  "type": "Feature",
  "properties": {
    "addr:full":"3996 E Evans Ave Denver CO 80210",
    "addr:housenumber":"3996",
    "addr:postcode":"80210",
    "addr:street":"E Evans Ave",
    "iso:country":"US",
    "sg:address":"3996 E Evans Ave",
    "sg:city":"Denver",
    "sg:classifiers":[
        {
            "category":"Autos & Motor Vehicles",
            "subcategory":"Fuel & Gas Station",
            "type":"Retail Goods"
        }
    ],
    "sg:phone":"+1 303 758 1684",
    "sg:postcode":"80210",
    "sg:province":"CO",
    "sg:tags":[
        "station",
        "gasoline"
    ],
    "wof:name":"BP",
    "wof:placetype":"venue"
},
  "geometry": {"coordinates":[-104.942504,39.678302],"type":"Point"}
}