{
  "type": "Feature",
  "properties": {
    "addr:full":"8501 W Bowles Ave Littleton CO 80123",
    "addr:housenumber":"8501",
    "addr:postcode":"80123",
    "addr:street":"W Bowles Ave",
    "iso:country":"US",
    "sg:address":"8501 W Bowles Ave",
    "sg:city":"Littleton",
    "sg:classifiers":[
        {
            "category":"Coffee & Tea",
            "type":"Food & Drink"
        },
        {
            "category":"Bakery",
            "type":"Food & Drink"
        }
    ],
    "sg:menulink":"http://www.allmenus.com/co/northeast-jefferson/137020-seattles-best-coffee/menu/",
    "sg:phone":"+1 303 933 6787",
    "sg:postcode":"80123",
    "sg:province":"CO",
    "sg:tags":[
        "american",
        "diner",
        "pastry"
    ],
    "wof:name":"Seattle's Best Coffee",
    "wof:placetype":"venue"
},
  "geometry": {"coordinates":[-105.096006,39.612034],"type":"Point"}
}