{
  "type": "Feature",
  "properties": {
    "iso:country":"US",
    "sg:address":"10450 Owens St",
    "sg:city":"Broomfield",
    "sg:classifiers":[
        {
            "category":"Home & Garden",
            "subcategory":"Garden Supply",
            "type":"Retail Goods"
        }
    ],
    "sg:phone":"+1 303 466 7830",
    "sg:postcode":"80021",
    "sg:province":"CO",
    "sg:tags":[
        "sprinkler"
    ],
    "wof:name":"Buffalo Sprinkler Co",
    "wof:placetype":"venue"
},
  "geometry": {"coordinates":[-105.125372,39.886526],"type":"Point"}
}