{
  "type": "Feature",
  "properties": {
    "iso:country":"US",
    "sg:address":"5590 Havana St",
    "sg:city":"Denver",
    "sg:classifiers":[
        {
            "category":"Personal",
            "type":"Services"
        }
    ],
    "sg:phone":"+1 720 374 2330",
    "sg:postcode":"80239",
    "sg:province":"CO",
    "sg:tags":[
        "durable",
        "good"
    ],
    "wof:name":"Colorado Sun",
    "wof:placetype":"venue"
},
  "geometry": {"coordinates":[-104.86584999999999,39.797102],"type":"Point"}
}