{
  "type": "Feature",
  "properties": {
    "iso:country":"US",
    "sg:address":"2833 Dublin Blvd",
    "sg:city":"Colorado Springs",
    "sg:classifiers":[
        {
            "category":"Personal",
            "type":"Services"
        }
    ],
    "sg:phone":"+1 719 535 9988",
    "sg:postcode":"80918",
    "sg:province":"CO",
    "sg:tags":[
        "program",
        "physical",
        "exercise",
        "fitness"
    ],
    "wof:name":"Why Weight",
    "wof:placetype":"venue"
},
  "geometry": {"coordinates":[-104.774597,38.925751],"type":"Point"}
}