{
  "type": "Feature",
  "properties": {
    "addr:full":"12415 N Dumont Way Littleton CO 80125",
    "addr:housenumber":"12415",
    "addr:postcode":"80125",
    "addr:street":"N Dumont Way",
    "iso:country":"US",
    "sg:address":"12415 N Dumont Way",
    "sg:city":"Littleton",
    "sg:classifiers":[
        {
            "category":"Home & Garden",
            "subcategory":"Building Materials",
            "type":"Retail Goods"
        }
    ],
    "sg:phone":"+1 303 432 9400",
    "sg:postcode":"80125",
    "sg:province":"CO",
    "sg:tags":[
        "glass",
        "window",
        "plate"
    ],
    "wof:name":"Douglas County Glass",
    "wof:placetype":"venue"
},
  "geometry": {"coordinates":[-105.03970700000001,39.542203],"type":"Point"}
}