{
  "type": "Feature",
  "properties": {
    "addr:full":"2246 Larimer St Denver CO 80205",
    "addr:housenumber":"2246",
    "addr:postcode":"80205",
    "addr:street":"Larimer St",
    "iso:country":"US",
    "sg:address":"2246 Larimer St",
    "sg:city":"Denver",
    "sg:classifiers":[
        {
            "category":"Shopping",
            "subcategory":"Pawn Shop",
            "type":"Retail Goods"
        }
    ],
    "sg:phone":"+1 303 294 9008",
    "sg:postcode":"80205",
    "sg:province":"CO",
    "wof:name":"Ez Pawn",
    "wof:placetype":"venue"
},
  "geometry": {"coordinates":[-104.989487,39.755158],"type":"Point"}
}