{
  "type": "Feature",
  "properties": {
    "iso:country":"US",
    "sg:address":"3155 Dartmouth Ave",
    "sg:city":"Boulder",
    "sg:classifiers":[
        {
            "category":"Food & Beverages",
            "subcategory":"Liquor & Beverages",
            "type":"Retail Goods"
        }
    ],
    "sg:phone":"+1 303 543 7757",
    "sg:postcode":"80305",
    "sg:province":"CO",
    "sg:tags":[
        "alcoholic"
    ],
    "wof:name":"Bottle Belt Industries Inc",
    "wof:placetype":"venue"
},
  "geometry": {"coordinates":[-105.255408,39.989662],"type":"Point"}
}