{
  "type": "Feature",
  "properties": {
    "iso:country":"US",
    "sg:address":"1821 Pioneer Rd",
    "sg:city":"Pueblo",
    "sg:classifiers":[
        {
            "category":"Home & Garden",
            "subcategory":"Building Materials",
            "type":"Retail Goods"
        }
    ],
    "sg:phone":"+1 719 543 2195",
    "sg:postcode":"81008",
    "sg:province":"CO",
    "wof:name":"Cimarron Glass Inc",
    "wof:placetype":"venue"
},
  "geometry": {"coordinates":[-104.629839,38.317849],"type":"Point"}
}