{
  "type": "Feature",
  "properties": {
    "addr:full":"600 Kilmer St Golden CO 80401",
    "addr:housenumber":"600",
    "addr:postcode":"80401",
    "addr:street":"Kilmer St",
    "iso:country":"US",
    "sg:address":"600 Kilmer St",
    "sg:city":"Golden",
    "sg:classifiers":[
        {
            "category":"Building & Trades",
            "subcategory":"Landscaping Services",
            "type":"Services"
        }
    ],
    "sg:phone":"+1 303 237 0570",
    "sg:postcode":"80401",
    "sg:province":"CO",
    "wof:name":"Advanced Tree & Lawn Concepts",
    "wof:placetype":"venue"
},
  "geometry": {"coordinates":[-105.17140000000001,39.727326],"type":"Point"}
}