{
  "type": "Feature",
  "properties": {
    "addr:full":"1150 W 135th Dr Denver CO 80234",
    "addr:housenumber":"1150",
    "addr:postcode":"80234",
    "addr:street":"W 135Th Dr",
    "iso:country":"US",
    "sg:address":"1150 W 135th Dr",
    "sg:city":"Denver",
    "sg:classifiers":[
        {
            "category":"Building & Trades",
            "subcategory":"Plumbing",
            "type":"Services"
        }
    ],
    "sg:phone":"+1 303 920 9466",
    "sg:postcode":"80234",
    "sg:province":"CO",
    "sg:tags":[
        "contractor"
    ],
    "wof:name":"Absolute Heating and Cooling",
    "wof:placetype":"venue"
},
  "geometry": {"coordinates":[-105.002056,39.941545],"type":"Point"}
}