{
  "type": "Feature",
  "properties": {
    "iso:country":"US",
    "sg:address":"6936 N Academy Blvd",
    "sg:city":"Colorado Springs",
    "sg:classifiers":[
        {
            "category":"Personal",
            "subcategory":"Beauty Salon",
            "type":"Services"
        }
    ],
    "sg:phone":"+1 719 266 8861",
    "sg:postcode":"80918",
    "sg:province":"CO",
    "sg:tags":[
        "manicuring"
    ],
    "wof:name":"Woodmen Nails",
    "wof:placetype":"venue"
},
  "geometry": {"coordinates":[-104.79531,38.931144],"type":"Point"}
}