{
  "type": "Feature",
  "properties": {
    "iso:country":"US",
    "sg:address":"176 S Potomac St",
    "sg:city":"Aurora",
    "sg:classifiers":[
        {
            "category":"Retail",
            "subcategory":"Veterinary Services",
            "type":"Services"
        }
    ],
    "sg:phone":"+1 303 343 8796",
    "sg:postcode":"80012",
    "sg:province":"CO",
    "sg:tags":[
        "clinic",
        "veterinarian",
        "hospital"
    ],
    "wof:name":"Altos Veterinary Clinic",
    "wof:placetype":"venue"
},
  "geometry": {"coordinates":[-104.82830300000001,39.713408],"type":"Point"}
}