{
  "type": "Feature",
  "properties": {
    "iso:country":"US",
    "sg:address":"418 8th St SE",
    "sg:city":"Loveland",
    "sg:classifiers":[
        {
            "category":"Recreation",
            "type":"Entertainment"
        }
    ],
    "sg:phone":"+1 970 227 4227",
    "sg:postcode":"80537",
    "sg:province":"CO",
    "sg:tags":[
        "instruction",
        "yoga"
    ],
    "wof:name":"Yoga By Merlin",
    "wof:placetype":"venue"
},
  "geometry": {"coordinates":[-105.073228,40.38556],"type":"Point"}
}