{
  "type": "Feature",
  "properties": {
    "addr:full":"2703 W 100th Ave Denver CO 80260",
    "addr:housenumber":"2703",
    "addr:postcode":"80260",
    "addr:street":"W 100Th Ave",
    "iso:country":"US",
    "sg:address":"2703 W 100th Ave",
    "sg:city":"Denver",
    "sg:classifiers":[
        {
            "category":"Building & Trades",
            "subcategory":"Electrical",
            "type":"Services"
        }
    ],
    "sg:phone":"+1 303 438 8970",
    "sg:postcode":"80260",
    "sg:province":"CO",
    "sg:tags":[
        "electrical",
        "contractor"
    ],
    "wof:name":"Shadow Creek Installation",
    "wof:placetype":"venue"
},
  "geometry": {"coordinates":[-105.020203,39.879177],"type":"Point"}
}