{
  "type": "Feature",
  "properties": {
    "iso:country":"US",
    "sg:address":"955 N Powers Blvd",
    "sg:city":"Colorado Springs",
    "sg:classifiers":[
        {
            "category":"Personal",
            "type":"Services"
        }
    ],
    "sg:phone":"+1 719 597 4783",
    "sg:postcode":"80915",
    "sg:province":"CO",
    "sg:tags":[
        "therapist",
        "massage"
    ],
    "wof:name":"Oriental Spa Massage",
    "wof:placetype":"venue"
},
  "geometry": {"coordinates":[-104.72059,38.846707],"type":"Point"}
}