{
  "type": "Feature",
  "properties": {
    "iso:country":"US",
    "sg:address":"2600 S Parker Rd",
    "sg:city":"Aurora",
    "sg:classifiers":[
        {
            "category":"Personal",
            "subcategory":"Beauty Salon",
            "type":"Services"
        }
    ],
    "sg:phone":"+1 303 597 5997",
    "sg:postcode":"80014",
    "sg:province":"CO",
    "sg:tags":[
        "treatment",
        "skin"
    ],
    "wof:name":"Beauty Spirit Wellness Ctr",
    "wof:placetype":"venue"
},
  "geometry": {"coordinates":[-104.863944,39.66928],"type":"Point"}
}