{
  "type": "Feature",
  "properties": {
    "iso:country":"US",
    "sg:address":"6400 Utica St",
    "sg:city":"Arvada",
    "sg:classifiers":[
        {
            "category":"Building & Trades",
            "subcategory":"Locksmith",
            "type":"Services"
        }
    ],
    "sg:phone":"+1 303 542 0124",
    "sg:postcode":"80003",
    "sg:province":"CO",
    "sg:tags":[
        "key"
    ],
    "wof:name":"A Locksmith 0 1 24 Hour",
    "wof:placetype":"venue"
},
  "geometry": {"coordinates":[-105.045041,39.81284],"type":"Point"}
}