{
  "type": "Feature",
  "properties": {
    "addr:full":"323 3rd Ave Longmont CO 80501",
    "addr:housenumber":"323",
    "addr:postcode":"80501",
    "addr:street":"3Rd Ave",
    "iso:country":"US",
    "sg:address":"323 3rd Ave",
    "sg:city":"Longmont",
    "sg:classifiers":[
        {
            "category":"Organizations",
            "subcategory":"Religious Organization",
            "type":"Services"
        }
    ],
    "sg:phone":"+1 303 775 3431",
    "sg:postcode":"80501",
    "sg:province":"CO",
    "sg:tags":[
        "spiritualist"
    ],
    "wof:name":"True Nature Ctr-For Sprt Heal",
    "wof:placetype":"venue"
},
  "geometry": {"coordinates":[-105.099554,40.163861],"type":"Point"}
}