{
  "type": "Feature",
  "properties": {
    "addr:full":"1056 S 88th St Louisville CO 80027",
    "addr:housenumber":"1056",
    "addr:postcode":"80027",
    "addr:street":"S 88Th St",
    "iso:country":"US",
    "sg:address":"1056 S 88th St",
    "sg:city":"Louisville",
    "sg:classifiers":[
        {
            "category":"Health Services",
            "subcategory":"Doctor",
            "type":"Services"
        }
    ],
    "sg:phone":"+1 303 604 0710",
    "sg:postcode":"80027",
    "sg:province":"CO",
    "sg:tags":[
        "dentist"
    ],
    "wof:name":"Young Dntistry For Children PC",
    "wof:placetype":"venue"
},
  "geometry": {"coordinates":[-105.146698,39.953499],"type":"Point"}
}