{
  "type": "Feature",
  "properties": {
    "iso:country":"US",
    "sg:address":"2701 Hwy 50",
    "sg:city":"Grand Junction",
    "sg:classifiers":[
        {
            "category":"Bars & Pubs",
            "type":"Food & Drink"
        }
    ],
    "sg:phone":"+1 970 242 9897",
    "sg:postcode":"81503",
    "sg:province":"CO",
    "sg:tags":[
        "drinking"
    ],
    "wof:name":"Thunder Mountain Tavern",
    "wof:placetype":"venue"
},
  "geometry": {"coordinates":[-108.550353,39.042293],"type":"Point"}
}