{
  "type": "Feature",
  "properties": {
    "addr:full":"6865 S Quebec St Centennial CO 80112",
    "addr:housenumber":"6865",
    "addr:postcode":"80112",
    "addr:street":"S Quebec St",
    "iso:country":"US",
    "sg:address":"6865 S Quebec St",
    "sg:city":"Centennial",
    "sg:classifiers":[
        {
            "category":"Social Services",
            "subcategory":"Child Care",
            "type":"Services"
        }
    ],
    "sg:phone":"+1 303 771 4202",
    "sg:postcode":"80112",
    "sg:province":"CO",
    "sg:tags":[
        "kindergarten",
        "academic",
        "school",
        "day",
        "preschool"
    ],
    "wof:name":"Willows Child Learning Centers",
    "wof:placetype":"venue"
},
  "geometry": {"coordinates":[-104.90427800000001,39.592448],"type":"Point"}
}