{
  "type": "Feature",
  "properties": {
    "addr:full":"14244 US Hwy 34 Fort Morgan CO 80701",
    "addr:housenumber":"14244",
    "addr:postcode":"80701",
    "addr:street":"Us Hwy 34",
    "iso:country":"US",
    "sg:address":"14244 US Hwy 34",
    "sg:city":"Fort Morgan",
    "sg:classifiers":[
        {
            "category":"Sports & Exercise",
            "subcategory":"Gym",
            "type":"Entertainment"
        }
    ],
    "sg:phone":"+1 970 542 0999",
    "sg:postcode":"80701",
    "sg:province":"CO",
    "sg:tags":[
        "spa",
        "health"
    ],
    "wof:name":"Fuji Health Spa",
    "wof:placetype":"venue"
},
  "geometry": {"coordinates":[-103.880027,40.25413],"type":"Point"}
}