{
  "type": "Feature",
  "properties": {
    "iso:country":"US",
    "sg:address":"1708 S 9th St",
    "sg:city":"Lamar",
    "sg:classifiers":[
        {
            "category":"Shopping",
            "type":"Retail Goods"
        }
    ],
    "sg:phone":"+1 719 336 3444",
    "sg:postcode":"81052",
    "sg:province":"CO",
    "sg:tags":[
        "miscellaneous",
        "store"
    ],
    "wof:name":"9th Street Style Shoppe",
    "wof:placetype":"venue"
},
  "geometry": {"coordinates":[-102.62531,38.07306],"type":"Point"}
}