{
  "type": "Feature",
  "properties": {
    "iso:country":"US",
    "sg:address":"2541 Chilson Ln",
    "sg:city":"Colorado Springs",
    "sg:classifiers":[
        {
            "category":"Food & Beverages",
            "subcategory":"Specialty",
            "type":"Retail Goods"
        }
    ],
    "sg:phone":"+1 719 630 1038",
    "sg:postcode":"80904",
    "sg:province":"CO",
    "wof:name":"Optimum Nutrition LLC",
    "wof:placetype":"venue"
},
  "geometry": {"coordinates":[-104.862094,38.878295],"type":"Point"}
}