{
  "type": "Feature",
  "properties": {
    "iso:country":"US",
    "sg:address":"48 E Beaver Creek Blvd",
    "sg:city":"Avon",
    "sg:classifiers":[
        {
            "category":"Freight",
            "type":"Transportation"
        }
    ],
    "sg:phone":"+1 970 748 1095",
    "sg:postcode":"81620",
    "sg:province":"CO",
    "sg:tags":[
        "consultant"
    ],
    "wof:name":"John C Martin Assoc LLC",
    "wof:placetype":"venue"
},
  "geometry": {"coordinates":[-106.520545,39.634761],"type":"Point"}
}