{
  "type": "Feature",
  "properties": {
    "iso:country":"US",
    "sg:address":"29002 Crossroads Ln",
    "sg:city":"Evergreen",
    "sg:classifiers":[
        {
            "category":"Retail",
            "subcategory":"Car Wash",
            "type":"Services"
        }
    ],
    "sg:phone":"+1 303 526 9989",
    "sg:postcode":"80401",
    "sg:province":"CO",
    "sg:tags":[
        "polishing",
        "washing"
    ],
    "wof:name":"Evergreen Car Wash & Detail",
    "wof:placetype":"venue"
},
  "geometry": {"coordinates":[-105.329808,39.699432],"type":"Point"}
}