{
  "type": "Feature",
  "properties": {
    "addr:full":"255 Anglers Dr Steamboat Spgs CO 80487",
    "addr:housenumber":"255",
    "addr:postcode":"80487",
    "addr:street":"Anglers Dr;Spgs",
    "iso:country":"US",
    "sg:address":"255 Anglers Dr",
    "sg:city":"Steamboat Spgs",
    "sg:classifiers":[
        {
            "category":"Restaurant",
            "type":"Food & Drink"
        }
    ],
    "sg:phone":"+1 970 871 1303",
    "sg:postcode":"80487",
    "sg:province":"CO",
    "sg:tags":[
        "shop",
        "coffee",
        "eating"
    ],
    "wof:name":"Starbucks",
    "wof:placetype":"venue"
},
  "geometry": {"coordinates":[-106.825914,40.467567],"type":"Point"}
}