{
  "type": "Feature",
  "properties": {
    "addr:full":"7878 W 80th Pl Arvada CO 80005",
    "addr:housenumber":"7878",
    "addr:postcode":"80005",
    "addr:street":"W 80Th Pl",
    "iso:country":"US",
    "sg:address":"7878 W 80th Pl",
    "sg:city":"Arvada",
    "sg:classifiers":[
        {
            "category":"Insurance",
            "subcategory":"Insurance Agent",
            "type":"Services"
        }
    ],
    "sg:phone":"+1 303 424 5519",
    "sg:postcode":"80005",
    "sg:province":"CO",
    "wof:name":"Schroeder Insurance",
    "wof:placetype":"venue"
},
  "geometry": {"coordinates":[-105.08569,39.84232],"type":"Point"}
}