{
  "type": "Feature",
  "properties": {
    "addr:full":"338 2nd St Frederick CO 80530",
    "addr:housenumber":"338",
    "addr:postcode":"80530",
    "addr:street":"2Nd St",
    "iso:country":"US",
    "sg:address":"338 2nd St",
    "sg:city":"Frederick",
    "sg:classifiers":[
        {
            "category":"Farming",
            "subcategory":"Nursery",
            "type":"Manufacturing & Wholesale Goods"
        }
    ],
    "sg:phone":"+1 303 833 2016",
    "sg:postcode":"80530",
    "sg:province":"CO",
    "sg:tags":[
        "turf"
    ],
    "wof:name":"JMI Turf",
    "wof:placetype":"venue"
},
  "geometry": {"coordinates":[-104.937715,40.10125],"type":"Point"}
}