{
  "type": "Feature",
  "properties": {
    "iso:country":"US",
    "sg:address":"4827 Thunderbird Dr",
    "sg:city":"Boulder",
    "sg:classifiers":[
        {
            "category":"Real Estate",
            "subcategory":"Real Estate Operator",
            "type":"Services"
        }
    ],
    "sg:phone":"+1 303 494 3004",
    "sg:postcode":"80303",
    "sg:province":"CO",
    "sg:tags":[
        "apartment"
    ],
    "wof:name":"Tyrol Apartments",
    "wof:placetype":"venue"
},
  "geometry": {"coordinates":[-105.23397199999999,39.99575],"type":"Point"}
}