{
  "type": "Feature",
  "properties": {
    "addr:full":"775 Castle Dr Eagle CO 81631",
    "addr:housenumber":"775",
    "addr:postcode":"81631",
    "addr:street":"Castle Dr",
    "iso:country":"US",
    "sg:address":"775 Castle Dr",
    "sg:city":"Eagle",
    "sg:classifiers":[
        {
            "category":"Utilities",
            "subcategory":"Electric",
            "type":"Services"
        }
    ],
    "sg:phone":"+1 970 328 6360",
    "sg:postcode":"81631",
    "sg:province":"CO",
    "sg:website":"www.holycross.com",
    "wof:name":"Holy Cross Energy",
    "wof:placetype":"venue"
},
  "geometry": {"coordinates":[-106.834272,39.648909],"type":"Point"}
}