{
  "type": "Feature",
  "properties": {
    "iso:country":"US",
    "sg:address":"318 Charles St",
    "sg:city":"Buena Vista",
    "sg:classifiers":[
        {
            "category":"Retail",
            "subcategory":"Laundry & Dry Cleaning",
            "type":"Services"
        }
    ],
    "sg:phone":"+1 719 395 4780",
    "sg:postcode":"81211",
    "sg:province":"CO",
    "sg:tags":[
        "cleaners"
    ],
    "wof:name":"Neighborhood Cleaners",
    "wof:placetype":"venue"
},
  "geometry": {"coordinates":[-106.131203,38.838521],"type":"Point"}
}