{
  "type": "Feature",
  "properties": {
    "iso:country":"US",
    "sg:address":"5621 Arapahoe Ave",
    "sg:city":"Boulder",
    "sg:classifiers":[
        {
            "category":"Health Services",
            "subcategory":"Clinic",
            "type":"Services"
        }
    ],
    "sg:phone":"+1 303 440 5181",
    "sg:postcode":"80303",
    "sg:province":"CO",
    "sg:tags":[
        "information",
        "medical"
    ],
    "sg:website":"www.miqs.com",
    "wof:name":"MIQS Inc",
    "wof:placetype":"venue"
},
  "geometry": {"coordinates":[-105.22122899999999,40.014778],"type":"Point"}
}