{
  "type": "Feature",
  "properties": {
    "iso:country":"US",
    "sg:address":"6506 Charter Dr",
    "sg:city":"Colorado Springs",
    "sg:classifiers":[
        {
            "category":"Building & Trades",
            "subcategory":"Construction",
            "type":"Services"
        }
    ],
    "sg:phone":"+1 719 266 6746",
    "sg:postcode":"80918",
    "sg:province":"CO",
    "sg:tags":[
        "builder",
        "stair"
    ],
    "wof:name":"Greg Grimes Custom Stair-Trim",
    "wof:placetype":"venue"
},
  "geometry": {"coordinates":[-104.778659,38.926711],"type":"Point"}
}