{
  "type": "Feature",
  "properties": {
    "addr:full":"519 16th St Denver CO 80211",
    "addr:housenumber":"519",
    "addr:postcode":"80211",
    "addr:street":"16Th St",
    "iso:country":"US",
    "sg:address":"519 16th St",
    "sg:city":"Denver",
    "sg:classifiers":[
        {
            "category":"Restaurant",
            "type":"Food & Drink"
        }
    ],
    "sg:phone":"+1 303 893 1236",
    "sg:postcode":"80211",
    "sg:province":"CO",
    "sg:tags":[
        "management"
    ],
    "sg:website":"www.premierventuresinc.com",
    "wof:name":"Premier Ventures Inc",
    "wof:placetype":"venue"
},
  "geometry": {"coordinates":[-104.99114400000001,39.744435],"type":"Point"}
}