{
  "type": "Feature",
  "properties": {
    "iso:country":"US",
    "sg:address":"5343 Sandpiper Ave",
    "sg:city":"Castle Rock",
    "sg:classifiers":[
        {
            "category":"Professional",
            "subcategory":"Computer Services",
            "type":"Services"
        }
    ],
    "sg:phone":"+1 303 660 1454",
    "sg:postcode":"80104",
    "sg:province":"CO",
    "sg:tags":[
        "consulting",
        "asset",
        "recovery",
        "related",
        "sal"
    ],
    "wof:name":"Small Business Computers",
    "wof:placetype":"venue"
},
  "geometry": {"coordinates":[-104.80683399999999,39.370768],"type":"Point"}
}