{
  "type": "Feature",
  "properties": {
    "addr:full":"710 S Tejon St Colorado Springs CO 80903",
    "addr:housenumber":"710",
    "addr:postcode":"80903",
    "addr:street":"S Tejon St",
    "iso:country":"US",
    "sg:address":"710 S Tejon St",
    "sg:city":"Colorado Springs",
    "sg:classifiers":[
        {
            "category":"Organizations",
            "subcategory":"Non-profit Organization",
            "type":"Services"
        }
    ],
    "sg:phone":"+1 719 578 3150",
    "sg:postcode":"80903",
    "sg:province":"CO",
    "sg:tags":[
        "information",
        "alcoholism",
        "treatment"
    ],
    "wof:name":"Alcohol & Drug Treatment",
    "wof:placetype":"venue"
},
  "geometry": {"coordinates":[-104.824153,38.823239],"type":"Point"}
}