{
  "type": "Feature",
  "properties": {
    "addr:full":"The Retro Room 2034 Larimer St Denver CO 80205",
    "addr:housenumber":"2034",
    "addr:postcode":"80205",
    "addr:street":"Larimer St",
    "iso:country":"US",
    "sg:address":"The Retro Room 2034 Larimer St",
    "sg:city":"Denver",
    "sg:classifiers":[
        {
            "category":"Personal",
            "subcategory":"Beauty Salon",
            "type":"Services"
        }
    ],
    "sg:phone":"+1 262 894 3977",
    "sg:postcode":"80205",
    "sg:province":"CO",
    "sg:tags":[
        "hair",
        "makeup",
        "artist"
    ],
    "sg:website":"www.myspace.com/myhairtrip",
    "wof:name":"My Hair Trip - Nicole Herrera",
    "wof:placetype":"venue"
},
  "geometry": {"coordinates":[-104.991674,39.753264],"type":"Point"}
}