{
  "type": "Feature",
  "properties": {
    "addr:full":"950 S Cherry Street Suite 702 Denver CO 80246",
    "addr:housenumber":"950",
    "addr:postcode":"80246",
    "addr:street":"S Cherry Street Suite 702",
    "iso:country":"US",
    "sg:address":"950 S Cherry Street Suite 702",
    "sg:city":"Denver",
    "sg:classifiers":[
        {
            "category":"Professional",
            "subcategory":"Lawyer & Legal Services",
            "type":"Services"
        }
    ],
    "sg:phone":"+1 303 782 0600",
    "sg:postcode":"80246",
    "sg:province":"CO",
    "sg:tags":[
        "divorce",
        "law",
        "family"
    ],
    "wof:name":"Rivera Jennifer A & Associates",
    "wof:placetype":"venue"
},
  "geometry": {"coordinates":[-104.931669,39.699447],"type":"Point"}
}