{
  "type": "Feature",
  "properties": {
    "iso:country":"US",
    "sg:address":"2250 S Oneida St",
    "sg:city":"Denver",
    "sg:classifiers":[
        {
            "category":"Organizations",
            "subcategory":"Non-profit Organization",
            "type":"Services"
        }
    ],
    "sg:phone":"+1 303 757 8008",
    "sg:postcode":"80224",
    "sg:province":"CO",
    "sg:website":"www.rup.org",
    "wof:name":"Roundup Fellowship",
    "wof:placetype":"venue"
},
  "geometry": {"coordinates":[-104.908806,39.676127],"type":"Point"}
}