{
  "type": "Feature",
  "properties": {
    "iso:country":"US",
    "sg:address":"17725 Appaloosa Rd",
    "sg:city":"Monument",
    "sg:classifiers":[
        {
            "category":"Building & Trades",
            "subcategory":"Construction",
            "type":"Services"
        }
    ],
    "sg:phone":"+1 719 481 3467",
    "sg:postcode":"80132",
    "sg:province":"CO",
    "sg:tags":[
        "excavating",
        "contractor"
    ],
    "wof:name":"Vickery Excavation",
    "wof:placetype":"venue"
},
  "geometry": {"coordinates":[-104.778153,39.087948],"type":"Point"}
}