{
  "type": "Feature",
  "properties": {
    "addr:full":"5947 Co Rd 5 Fraser CO 80480",
    "addr:housenumber":"5947",
    "addr:postcode":"80480",
    "addr:street":"Co Rd 5 Fraser",
    "iso:country":"US",
    "sg:address":"5947 Co Rd 5",
    "sg:city":"Fraser",
    "sg:classifiers":[
        {
            "category":"Wholesale",
            "subcategory":"Electrical",
            "type":"Manufacturing & Wholesale Goods"
        }
    ],
    "sg:phone":"+1 970 726 9898",
    "sg:postcode":"80480",
    "sg:province":"CO",
    "sg:tags":[
        "control",
        "security",
        "system"
    ],
    "wof:name":"Sasquatch Alarms & Comm",
    "wof:placetype":"venue"
},
  "geometry": {"coordinates":[-106.51349,40.618108],"type":"Point"}
}