{
  "type": "Feature",
  "properties": {
    "iso:country":"US",
    "sg:address":"238 E Colorado Ave",
    "sg:city":"Telluride",
    "sg:classifiers":[
        {
            "category":"Real Estate",
            "subcategory":"Real Estate Agent",
            "type":"Services"
        }
    ],
    "sg:phone":"+1 970 728 1075",
    "sg:postcode":"81435",
    "sg:province":"CO",
    "sg:tags":[
        "appraiser"
    ],
    "wof:name":"San Miguel Appraisal",
    "wof:placetype":"venue"
},
  "geometry": {"coordinates":[-107.80950300000001,37.936726],"type":"Point"}
}