{
  "type": "Feature",
  "properties": {
    "addr:full":"2362 S Tabor Way Lakewood CO 80228",
    "addr:housenumber":"2362",
    "addr:postcode":"80228",
    "addr:street":"S Tabor Way",
    "iso:country":"US",
    "sg:address":"2362 S Tabor Way",
    "sg:city":"Lakewood",
    "sg:classifiers":[
        {
            "category":"Real Estate",
            "subcategory":"Real Estate Agent",
            "type":"Services"
        }
    ],
    "sg:phone":"+1 303 980 4331",
    "sg:postcode":"80228",
    "sg:province":"CO",
    "wof:name":"Q Connexion",
    "wof:placetype":"venue"
},
  "geometry": {"coordinates":[-105.131546,39.673879],"type":"Point"}
}