{
  "type": "Feature",
  "properties": {
    "addr:full":"9742 E Colfax Ave Aurora CO 80010",
    "addr:housenumber":"9742",
    "addr:postcode":"80010",
    "addr:street":"E Colfax Ave",
    "iso:country":"US",
    "sg:address":"9742 E Colfax Ave",
    "sg:city":"Aurora",
    "sg:classifiers":[
        {
            "category":"Restaurant",
            "type":"Food & Drink"
        }
    ],
    "sg:menulink":"http://www.allmenus.com/co/south-aurora/282333-la-cueva/menu/",
    "sg:phone":"+1 303 367 1422",
    "sg:postcode":"80010",
    "sg:province":"CO",
    "sg:tags":[
        "mexican"
    ],
    "wof:name":"LA Cueva",
    "wof:placetype":"venue"
},
  "geometry": {"coordinates":[-104.87441099999999,39.740098],"type":"Point"}
}