{
  "type": "Feature",
  "properties": {
    "iso:country":"US",
    "sg:address":"4606 S Van Gordon Ct",
    "sg:city":"Morrison",
    "sg:classifiers":[
        {
            "category":"Building & Trades",
            "subcategory":"Construction",
            "type":"Services"
        }
    ],
    "sg:phone":"+1 720 981 3718",
    "sg:postcode":"80465",
    "sg:province":"CO",
    "sg:tags":[
        "house"
    ],
    "wof:name":"Coates Woodworking",
    "wof:placetype":"venue"
},
  "geometry": {"coordinates":[-105.136197,39.631645],"type":"Point"}
}