{
  "type": "Feature",
  "properties": {
    "addr:full":"994 W Dillon Rd Louisville CO 80027",
    "addr:housenumber":"994",
    "addr:postcode":"80027",
    "addr:street":"W Dillon Rd",
    "iso:country":"US",
    "sg:address":"994 W Dillon Rd",
    "sg:city":"Louisville",
    "sg:classifiers":[
        {
            "category":"Restaurant",
            "type":"Food & Drink"
        }
    ],
    "sg:phone":"+1 720 890 8456",
    "sg:postcode":"80027",
    "sg:province":"CO",
    "sg:tags":[
        "eating"
    ],
    "wof:name":"Old Santa Fe Mexican Grille",
    "wof:placetype":"venue"
},
  "geometry": {"coordinates":[-105.161507,39.959605],"type":"Point"}
}