{
  "type": "Feature",
  "properties": {
    "addr:full":"6205 S Santa Fe Dr Littleton CO 80120",
    "addr:housenumber":"6205",
    "addr:postcode":"80120",
    "addr:street":"S Santa Fe Dr",
    "iso:country":"US",
    "sg:address":"6205 S Santa Fe Dr",
    "sg:city":"Littleton",
    "sg:classifiers":[
        {
            "category":"Personal",
            "subcategory":"Beauty Salon",
            "type":"Services"
        }
    ],
    "sg:phone":"+1 720 283 7202",
    "sg:postcode":"80120",
    "sg:province":"CO",
    "wof:name":"Cutting Room Hair Studio",
    "wof:placetype":"venue"
},
  "geometry": {"coordinates":[-105.02025500000001,39.602558],"type":"Point"}
}