{
  "type": "Feature",
  "properties": {
    "iso:country":"US",
    "sg:address":"5534 Stone Church Ct",
    "sg:city":"Loveland",
    "sg:classifiers":[
        {
            "category":"Professional",
            "type":"Services"
        }
    ],
    "sg:phone":"+1 970 635 2539",
    "sg:postcode":"80537",
    "sg:province":"CO",
    "wof:name":"Jess R Rodriguez Jr",
    "wof:placetype":"venue"
},
  "geometry": {"coordinates":[-105.15325199999999,40.392132],"type":"Point"}
}