{
  "type": "Feature",
  "properties": {
    "iso:country":"US",
    "sg:address":"2702 Patterson Rd",
    "sg:city":"Grand Junction",
    "sg:classifiers":[
        {
            "category":"Organizations",
            "subcategory":"Religious Organization",
            "type":"Services"
        }
    ],
    "sg:phone":"+1 970 243 9285",
    "sg:postcode":"81506",
    "sg:province":"CO",
    "sg:tags":[
        "church"
    ],
    "sg:website":"www.bookcliffbaptist.org",
    "wof:name":"Bookcliff Baptist Church Inc",
    "wof:placetype":"venue"
},
  "geometry": {"coordinates":[-108.552353,39.091854],"type":"Point"}
}