{
  "type": "Feature",
  "properties": {
    "addr:full":"360 7th St S Rifle CO 81650",
    "addr:housenumber":"360",
    "addr:postcode":"81650",
    "addr:street":"7Th St S",
    "iso:country":"US",
    "sg:address":"360 7th St S",
    "sg:city":"Rifle",
    "sg:classifiers":[
        {
            "category":"Building & Trades",
            "subcategory":"Construction",
            "type":"Services"
        }
    ],
    "sg:phone":"+1 970 625 2286",
    "sg:postcode":"81650",
    "sg:province":"CO",
    "sg:tags":[
        "road",
        "contractor"
    ],
    "wof:name":"TRANSPORTATION-Highway Mntnc",
    "wof:placetype":"venue"
},
  "geometry": {"coordinates":[-107.777912,39.522642],"type":"Point"}
}