{
  "type": "Feature",
  "properties": {
    "addr:full":"2621 S Parker Rd Aurora CO 80014",
    "addr:housenumber":"2621",
    "addr:postcode":"80014",
    "addr:street":"S Parker Rd",
    "iso:country":"US",
    "sg:address":"2621 S Parker Rd",
    "sg:city":"Aurora",
    "sg:classifiers":[
        {
            "category":"Shopping",
            "subcategory":"Optical Goods",
            "type":"Retail Goods"
        },
        {
            "category":"Health Services",
            "subcategory":"Optometrist",
            "type":"Services"
        }
    ],
    "sg:phone":"+1 303 752 2662",
    "sg:postcode":"80014",
    "sg:province":"CO",
    "wof:name":"A Look Optical",
    "wof:placetype":"venue"
},
  "geometry": {"coordinates":[-104.864367,39.669504],"type":"Point"}
}