{
  "type": "Feature",
  "properties": {
    "iso:country":"US",
    "sg:address":"3800 O St",
    "sg:city":"Greeley",
    "sg:classifiers":[
        {
            "category":"Home & Garden",
            "subcategory":"Building Materials",
            "type":"Retail Goods"
        }
    ],
    "sg:phone":"+1 970 392 1333",
    "sg:postcode":"80631",
    "sg:province":"CO",
    "sg:tags":[
        "mixed",
        "concrete"
    ],
    "wof:name":"Star Ready Mix",
    "wof:placetype":"venue"
},
  "geometry": {"coordinates":[-104.742777,40.45551],"type":"Point"}
}