{
  "type": "Feature",
  "properties": {
    "addr:full":"316 del Clair Rd Fort Collins CO 80525",
    "addr:housenumber":"316",
    "addr:postcode":"80525",
    "addr:street":"Del Clair Rd",
    "iso:country":"US",
    "sg:address":"316 del Clair Rd",
    "sg:city":"Fort Collins",
    "sg:classifiers":[
        {
            "category":"Professional",
            "type":"Services"
        },
        {
            "category":"Social Services",
            "type":"Services"
        }
    ],
    "sg:phone":"+1 970 416 0828",
    "sg:postcode":"80525",
    "sg:province":"CO",
    "sg:tags":[
        "counselor",
        "marriage",
        "family"
    ],
    "wof:name":"Growth Unlimited Prof LLC",
    "wof:placetype":"venue"
},
  "geometry": {"coordinates":[-105.074461,40.547594],"type":"Point"}
}