{
  "type": "Feature",
  "properties": {
    "addr:full":"12645 E Evans Cir Aurora CO 80014",
    "addr:housenumber":"12645",
    "addr:postcode":"80014",
    "addr:street":"E Evans Cir",
    "iso:country":"US",
    "sg:address":"12645 E Evans Cir",
    "sg:city":"Aurora",
    "sg:classifiers":[
        {
            "category":"Wholesale",
            "subcategory":"Electrical",
            "type":"Manufacturing & Wholesale Goods"
        }
    ],
    "sg:phone":"+1 303 695 1990",
    "sg:postcode":"80014",
    "sg:province":"CO",
    "sg:tags":[
        "electronic",
        "representative"
    ],
    "wof:name":"High Tech Assoc",
    "wof:placetype":"venue"
},
  "geometry": {"coordinates":[-104.84073600000001,39.676751],"type":"Point"}
}