{
  "type": "Feature",
  "properties": {
    "iso:country":"US",
    "sg:address":"3010 Niagara St",
    "sg:city":"Denver",
    "sg:classifiers":[
        {
            "category":"Shopping",
            "type":"Retail Goods"
        }
    ],
    "sg:phone":"+1 303 336 9500",
    "sg:postcode":"80207",
    "sg:province":"CO",
    "sg:tags":[
        "art",
        "gallery",
        "dealer"
    ],
    "wof:name":"Picture That",
    "wof:placetype":"venue"
},
  "geometry": {"coordinates":[-104.91049599999999,39.761732],"type":"Point"}
}