{
  "type": "Feature",
  "properties": {
    "addr:full":"5555 Boatworks Dr Littleton CO 80126",
    "addr:postcode":"5555;80126",
    "addr:street":"Boatworks Dr",
    "iso:country":"US",
    "sg:address":"5555 Boatworks Dr",
    "sg:city":"Littleton",
    "sg:classifiers":[
        {
            "category":"Food & Beverages",
            "subcategory":"Liquor & Beverages",
            "type":"Retail Goods"
        }
    ],
    "sg:phone":"+1 303 224 0444",
    "sg:postcode":"80126",
    "sg:province":"CO",
    "sg:website":"www.davidsonsliquors.com",
    "wof:name":"Davidsons Liquor Inc",
    "wof:placetype":"venue"
},
  "geometry": {"coordinates":[-104.92356700000001,39.565038],"type":"Point"}
}