{
  "type": "Feature",
  "properties": {
    "addr:full":"5729 S Sicily St Aurora CO 80015",
    "addr:housenumber":"5729",
    "addr:postcode":"80015",
    "addr:street":"S Sicily St",
    "iso:country":"US",
    "sg:address":"5729 S Sicily St",
    "sg:city":"Aurora",
    "sg:classifiers":[
        {
            "category":"Shopping",
            "subcategory":"Florist",
            "type":"Retail Goods"
        }
    ],
    "sg:phone":"+1 303 680 4664",
    "sg:postcode":"80015",
    "sg:province":"CO",
    "wof:name":"Valentine Florist",
    "wof:placetype":"venue"
},
  "geometry": {"coordinates":[-104.727102,39.611366],"type":"Point"}
}