{
  "type": "Feature",
  "properties": {
    "addr:full":"451 W Girard Ave Englewood CO 80110",
    "addr:housenumber":"451",
    "addr:postcode":"80110",
    "addr:street":"W Girard Ave",
    "iso:country":"US",
    "sg:address":"451 W Girard Ave",
    "sg:city":"Englewood",
    "sg:classifiers":[
        {
            "category":"Restaurant",
            "type":"Food & Drink"
        }
    ],
    "sg:phone":"+1 303 781 5335",
    "sg:postcode":"80110",
    "sg:province":"CO",
    "sg:tags":[
        "caterer"
    ],
    "wof:name":"Pauls Catering",
    "wof:placetype":"venue"
},
  "geometry": {"coordinates":[-104.99279799999999,39.655317],"type":"Point"}
}