{
  "type": "Feature",
  "properties": {
    "iso:country":"US",
    "sg:address":"12021 Pennsylvania St",
    "sg:city":"Thornton",
    "sg:classifiers":[
        {
            "category":"Insurance",
            "subcategory":"Insurance Agent",
            "type":"Services"
        }
    ],
    "sg:phone":"+1 303 280 5200",
    "sg:postcode":"80241",
    "sg:province":"CO",
    "wof:name":"W Mark Finger Insurance Inc",
    "wof:placetype":"venue"
},
  "geometry": {"coordinates":[-104.97797199999999,39.919351],"type":"Point"}
}