{
  "type": "Feature",
  "properties": {
    "addr:full":"26025 Valley Vw Steamboat Springs CO 80487",
    "addr:housenumber":"26025",
    "addr:postcode":"80487",
    "addr:street":"Valley Vw",
    "iso:country":"US",
    "sg:address":"26025 Valley Vw",
    "sg:city":"Steamboat Springs",
    "sg:classifiers":[
        {
            "category":"Banks & Credit Unions",
            "subcategory":"Financial Services",
            "type":"Services"
        }
    ],
    "sg:phone":"+1 970 871 7934",
    "sg:postcode":"80487",
    "sg:province":"CO",
    "sg:tags":[
        "trust",
        "investment",
        "real estate"
    ],
    "wof:name":"Keystone Investments",
    "wof:placetype":"venue"
},
  "geometry": {"coordinates":[-106.805926,40.481035],"type":"Point"}
}