{
  "type": "Feature",
  "properties": {
    "iso:country":"US",
    "sg:address":"1730 E Evans Ave",
    "sg:city":"Denver",
    "sg:classifiers":[
        {
            "category":"Coffee & Tea",
            "type":"Food & Drink"
        }
    ],
    "sg:phone":"+1 720 570 2166",
    "sg:postcode":"80210",
    "sg:province":"CO",
    "sg:website":"www.kaladicoffee.com",
    "wof:name":"Kaladi Brothers Coffee",
    "wof:placetype":"venue"
},
  "geometry": {"coordinates":[-104.967003,39.678398],"type":"Point"}
}