{
  "type": "Feature",
  "properties": {
    "iso:country":"US",
    "sg:address":"4460 W 29th Ave",
    "sg:city":"Denver",
    "sg:classifiers":[
        {
            "category":"Retail",
            "subcategory":"Auto Rental",
            "type":"Services"
        }
    ],
    "sg:phone":"+1 303 650 1941",
    "sg:postcode":"80212",
    "sg:province":"CO",
    "sg:tags":[
        "renting",
        "truck",
        "leasing"
    ],
    "wof:name":"U-Haul Co",
    "wof:placetype":"venue"
},
  "geometry": {"coordinates":[-105.04470499999999,39.75842],"type":"Point"}
}