{
  "type": "Feature",
  "properties": {
    "iso:country":"US",
    "sg:address":"1302 S Parker Rd",
    "sg:city":"Denver",
    "sg:classifiers":[
        {
            "category":"Travel",
            "subcategory":"Travel Agent",
            "type":"Entertainment"
        }
    ],
    "sg:phone":"+1 303 283 0880",
    "sg:postcode":"80231",
    "sg:province":"CO",
    "sg:tags":[
        "agency"
    ],
    "wof:name":"Globetrekker Travel",
    "wof:placetype":"venue"
},
  "geometry": {"coordinates":[-104.891752,39.691259],"type":"Point"}
}