{
  "type": "Feature",
  "properties": {
    "addr:full":"33399 Hwy 160 Durango CO 81301",
    "addr:housenumber":"33399",
    "addr:postcode":"co 81301",
    "addr:street":"Hwy 160",
    "iso:country":"US",
    "sg:address":"33399 Hwy 160",
    "sg:city":"Durango",
    "sg:classifiers":[
        {
            "category":"Building & Trades",
            "subcategory":"Construction",
            "type":"Services"
        }
    ],
    "sg:phone":"+1 970 247 1948",
    "sg:postcode":"81301",
    "sg:province":"CO",
    "sg:tags":[
        "product",
        "paving",
        "asphalt",
        "contractor"
    ],
    "wof:name":"M Leeder Construction Inc",
    "wof:placetype":"venue"
},
  "geometry": {"coordinates":[-107.749658,37.229177],"type":"Point"}
}