{
  "type": "Feature",
  "properties": {
    "addr:full":"1017 S Gaylord Street Denver CO 80209",
    "addr:housenumber":"1017",
    "addr:postcode":"80209",
    "addr:street":"S Gaylord Street",
    "iso:country":"US",
    "sg:address":"1017 S Gaylord Street",
    "sg:city":"Denver",
    "sg:classifiers":[
        {
            "category":"Personal",
            "subcategory":"Skin Care",
            "type":"Services"
        }
    ],
    "sg:phone":"+1 303 722 6767",
    "sg:postcode":"80209",
    "sg:province":"CO",
    "wof:name":"Gail Wise Skin Care",
    "wof:placetype":"venue"
},
  "geometry": {"coordinates":[-104.96174600000001,39.698111],"type":"Point"}
}