{
  "type": "Feature",
  "properties": {
    "iso:country":"US",
    "sg:address":"10 N Pythian Ave",
    "sg:city":"Montrose",
    "sg:classifiers":[
        {
            "category":"Shopping",
            "subcategory":"Books",
            "type":"Retail Goods"
        }
    ],
    "sg:phone":"+1 970 252 1036",
    "sg:postcode":"81401",
    "sg:province":"CO",
    "sg:tags":[
        "dealer"
    ],
    "wof:name":"Read Alot Bookshop",
    "wof:placetype":"venue"
},
  "geometry": {"coordinates":[-107.870183,38.485212],"type":"Point"}
}