{
  "type": "Feature",
  "properties": {
    "addr:full":"646 Grand Ave Eagle CO 81631",
    "addr:housenumber":"646",
    "addr:postcode":"81631",
    "addr:street":"Grand Ave",
    "iso:country":"US",
    "sg:address":"646 Grand Ave",
    "sg:city":"Eagle",
    "sg:classifiers":[
        {
            "category":"Real Estate",
            "subcategory":"Real Estate Agent",
            "type":"Services"
        }
    ],
    "sg:phone":"+1 970 328 2339",
    "sg:postcode":"81631",
    "sg:province":"CO",
    "wof:name":"Eagle Valley Properties",
    "wof:placetype":"venue"
},
  "geometry": {"coordinates":[-106.834513,39.650126],"type":"Point"}
}