{
  "type": "Feature",
  "properties": {
    "addr:full":"14311 E 144th Ave Brighton CO 80601",
    "addr:housenumber":"14311",
    "addr:postcode":"80601",
    "addr:street":"E 144Th Ave",
    "iso:country":"US",
    "sg:address":"14311 E 144th Ave",
    "sg:city":"Brighton",
    "sg:classifiers":[
        {
            "category":"Farming",
            "subcategory":"Nursery",
            "type":"Manufacturing & Wholesale Goods"
        }
    ],
    "sg:phone":"+1 720 685 7752",
    "sg:postcode":"80601",
    "sg:province":"CO",
    "sg:tags":[
        "greenhouse"
    ],
    "wof:name":"Tagawa Greenhouse Inc",
    "wof:placetype":"venue"
},
  "geometry": {"coordinates":[-104.82504900000001,39.957888],"type":"Point"}
}