{
  "type": "Feature",
  "properties": {
    "iso:country":"US",
    "sg:address":"21516 Hwy 160",
    "sg:city":"Durango",
    "sg:classifiers":[
        {
            "category":"Home & Garden",
            "subcategory":"Home Furnishings",
            "type":"Retail Goods"
        }
    ],
    "sg:phone":"+1 970 375 1771",
    "sg:postcode":"81303",
    "sg:province":"CO",
    "sg:tags":[
        "bathroom",
        "fixture",
        "accessory"
    ],
    "wof:name":"S W Designs Of Colorado",
    "wof:placetype":"venue"
},
  "geometry": {"coordinates":[-107.894756,37.270443],"type":"Point"}
}