{
  "type": "Feature",
  "properties": {
    "addr:full":"14452 W 44th Ave Golden CO 80403",
    "addr:housenumber":"14452",
    "addr:postcode":"80403",
    "addr:street":"W 44Th Ave",
    "iso:country":"US",
    "sg:address":"14452 W 44th Ave",
    "sg:city":"Golden",
    "sg:classifiers":[
        {
            "category":"Freight",
            "type":"Transportation"
        }
    ],
    "sg:phone":"+1 303 384 1115",
    "sg:postcode":"80403",
    "sg:province":"CO",
    "sg:tags":[
        "arrangement"
    ],
    "wof:name":"Exel Transportation Services",
    "wof:placetype":"venue"
},
  "geometry": {"coordinates":[-105.16104900000001,39.776115],"type":"Point"}
}