{
  "type": "Feature",
  "properties": {
    "iso:country":"US",
    "sg:address":"405 E 2nd St",
    "sg:city":"Leadville",
    "sg:classifiers":[
        {
            "category":"Building & Trades",
            "subcategory":"Plumbing",
            "type":"Services"
        }
    ],
    "sg:phone":"+1 719 486 9885",
    "sg:postcode":"80461",
    "sg:province":"CO",
    "sg:tags":[
        "contractor"
    ],
    "wof:name":"Taylor Plumbing & Heating LLC",
    "wof:placetype":"venue"
},
  "geometry": {"coordinates":[-106.285094,39.246401],"type":"Point"}
}