{
  "type": "Feature",
  "properties": {
    "addr:full":"1081 Indian Peak Rd Golden CO 80403",
    "addr:housenumber":"1081",
    "addr:postcode":"80403",
    "addr:street":"Indian Peak Rd",
    "iso:country":"US",
    "sg:address":"1081 Indian Peak Rd",
    "sg:city":"Golden",
    "sg:classifiers":[
        {
            "category":"Building & Trades",
            "subcategory":"Construction",
            "type":"Services"
        }
    ],
    "sg:phone":"+1 303 642 7276",
    "sg:postcode":"80403",
    "sg:province":"CO",
    "sg:tags":[
        "contractor"
    ],
    "wof:name":"Tight Seal Roofing & Siding",
    "wof:placetype":"venue"
},
  "geometry": {"coordinates":[-105.39722999999999,39.920968],"type":"Point"}
}