{
  "type": "Feature",
  "properties": {
    "iso:country":"US",
    "sg:address":"9409 US Hwy 85",
    "sg:city":"Littleton",
    "sg:classifiers":[
        {
            "category":"Recreation",
            "type":"Entertainment"
        }
    ],
    "sg:phone":"+1 303 346 9600",
    "sg:postcode":"80125",
    "sg:province":"CO",
    "sg:tags":[
        "repair",
        "motorcycle",
        "se"
    ],
    "wof:name":"Rocky Mountain Powersports",
    "wof:placetype":"venue"
},
  "geometry": {"coordinates":[-105.009871,39.500901],"type":"Point"}
}