{
  "type": "Feature",
  "properties": {
    "iso:country":"US",
    "sg:address":"1218 Hoffman Mill Rd",
    "sg:city":"Fort Collins",
    "sg:classifiers":[
        {
            "category":"Building & Trades",
            "subcategory":"Electrical",
            "type":"Services"
        }
    ],
    "sg:phone":"+1 970 493 0956",
    "sg:postcode":"80524",
    "sg:province":"CO",
    "sg:tags":[
        "electrical",
        "contractor"
    ],
    "wof:name":"The Electric Shop Ltd",
    "wof:placetype":"venue"
},
  "geometry": {"coordinates":[-105.049755,40.575193],"type":"Point"}
}