{
  "type": "Feature",
  "properties": {
    "iso:country":"US",
    "sg:address":"3665 John F Kennedy Pkwy",
    "sg:city":"Fort Collins",
    "sg:classifiers":[
        {
            "category":"Real Estate",
            "subcategory":"Real Estate Services",
            "type":"Services"
        }
    ],
    "sg:phone":"+1 970 226 4399",
    "sg:postcode":"80525",
    "sg:province":"CO",
    "sg:tags":[
        "company",
        "title"
    ],
    "sg:website":"www.stewart.com",
    "wof:name":"Stewart Title Co",
    "wof:placetype":"venue"
},
  "geometry": {"coordinates":[-105.074315,40.532614],"type":"Point"}
}