{
  "type": "Feature",
  "properties": {
    "addr:full":"3375 34th St Boulder CO 80301",
    "addr:housenumber":"3375",
    "addr:postcode":"80301",
    "addr:street":"34Th St",
    "iso:country":"US",
    "sg:address":"3375 34th St",
    "sg:city":"Boulder",
    "sg:classifiers":[
        {
            "category":"Social Services",
            "subcategory":"Adult Care",
            "type":"Services"
        }
    ],
    "sg:phone":"+1 303 473 0333",
    "sg:postcode":"80301",
    "sg:province":"CO",
    "sg:tags":[
        "home",
        "residential"
    ],
    "wof:name":"Alterra Wynwood",
    "wof:placetype":"venue"
},
  "geometry": {"coordinates":[-105.249019,40.035661],"type":"Point"}
}