{
  "type": "Feature",
  "properties": {
    "iso:country":"US",
    "sg:address":"730 S Jason St Ste 30",
    "sg:city":"Denver",
    "sg:classifiers":[
        {
            "category":"Home & Garden",
            "subcategory":"Building Materials",
            "type":"Retail Goods"
        }
    ],
    "sg:phone":"+1 303 282 8317",
    "sg:postcode":"80223",
    "sg:province":"CO",
    "sg:tags":[
        "supply"
    ],
    "sg:website":"coloradogranite.com",
    "wof:name":"Granite Direct Inc",
    "wof:placetype":"venue"
},
  "geometry": {"coordinates":[-104.999256,39.704017],"type":"Point"}
}