{
  "type": "Feature",
  "properties": {
    "iso:country":"US",
    "sg:address":"1017 S Federal Blvd",
    "sg:city":"Denver",
    "sg:classifiers":[
        {
            "category":"Cinema",
            "subcategory":"Movie Rental",
            "type":"Entertainment"
        }
    ],
    "sg:phone":"+1 303 936 5208",
    "sg:postcode":"80219",
    "sg:province":"CO",
    "sg:tags":[
        "leasing",
        "video",
        "disc",
        "tape"
    ],
    "wof:name":"Sunrise Video",
    "wof:placetype":"venue"
},
  "geometry": {"coordinates":[-105.02513999999999,39.697046],"type":"Point"}
}