{
  "type": "Feature",
  "properties": {
    "iso:country":"US",
    "sg:address":"313 3rd St",
    "sg:city":"Crested Butte",
    "sg:classifiers":[
        {
            "category":"Restaurant",
            "type":"Food & Drink"
        }
    ],
    "sg:phone":"+1 970 349 7291",
    "sg:postcode":"81224",
    "sg:province":"CO",
    "wof:name":"Ginger Cafe",
    "wof:placetype":"venue"
},
  "geometry": {"coordinates":[-106.98587999999999,38.870547],"type":"Point"}
}