{
  "type": "Feature",
  "properties": {
    "iso:country":"US",
    "sg:address":"911 10th St",
    "sg:city":"Golden",
    "sg:classifiers":[
        {
            "category":"Government",
            "subcategory":"Office",
            "type":"Public Place"
        }
    ],
    "sg:phone":"+1 303 384 8014",
    "sg:postcode":"80401",
    "sg:province":"CO",
    "sg:tags":[
        "village"
    ],
    "wof:name":"Golden City Election Info",
    "wof:placetype":"venue"
},
  "geometry": {"coordinates":[-105.22372900000001,39.75733],"type":"Point"}
}