{
  "type": "Feature",
  "properties": {
    "addr:full":"1400 S Collyer St Longmont CO 80501",
    "addr:housenumber":"1400",
    "addr:postcode":"80501",
    "addr:street":"S Collyer St",
    "iso:country":"US",
    "sg:address":"1400 S Collyer St",
    "sg:city":"Longmont",
    "sg:classifiers":[
        {
            "category":"Real Estate",
            "subcategory":"Developer",
            "type":"Services"
        },
        {
            "category":"Real Estate",
            "subcategory":"Real Estate Operator",
            "type":"Services"
        }
    ],
    "sg:phone":"+1 303 776 9631",
    "sg:postcode":"80501",
    "sg:province":"CO",
    "sg:tags":[
        "mobile",
        "home",
        "park"
    ],
    "wof:name":"Countryside Village Longmont",
    "wof:placetype":"venue"
},
  "geometry": {"coordinates":[-105.098214,40.138062],"type":"Point"}
}