{
  "type": "Feature",
  "properties": {
    "addr:full":"2550 S Parker Rd Aurora CO 80014",
    "addr:housenumber":"2550",
    "addr:postcode":"80014",
    "addr:street":"S Parker Rd",
    "iso:country":"US",
    "sg:address":"2550 S Parker Rd",
    "sg:city":"Aurora",
    "sg:classifiers":[
        {
            "category":"Banks & Credit Unions",
            "subcategory":"Bank",
            "type":"Services"
        }
    ],
    "sg:phone":"+1 303 861 8811",
    "sg:postcode":"80014",
    "sg:province":"CO",
    "wof:name":"Wells Fargo Bank",
    "wof:placetype":"venue"
},
  "geometry": {"coordinates":[-104.86284499999999,39.668458],"type":"Point"}
}