{
  "type": "Feature",
  "properties": {
    "iso:country":"US",
    "sg:address":"26518 Co Rd 49",
    "sg:city":"Greeley",
    "sg:classifiers":[
        {
            "category":"Personal",
            "subcategory":"Beauty Salon",
            "type":"Services"
        }
    ],
    "sg:phone":"+1 970 352 2393",
    "sg:postcode":"80631",
    "sg:province":"CO",
    "wof:name":"Cyndie Kramer Permanent Makeup",
    "wof:placetype":"venue"
},
  "geometry": {"coordinates":[-104.601826,40.384708],"type":"Point"}
}