{
  "type": "Feature",
  "properties": {
    "addr:full":"216 N 7th St New Castle CO 81647",
    "addr:housenumber":"216",
    "addr:postcode":"81647",
    "addr:street":"N 7Th St",
    "iso:country":"US",
    "sg:address":"216 N 7th St",
    "sg:city":"New Castle",
    "sg:classifiers":[
        {
            "category":"Arts & Performance",
            "subcategory":"Theater",
            "type":"Entertainment"
        }
    ],
    "sg:phone":"+1 970 984 0926",
    "sg:postcode":"81647",
    "sg:province":"CO",
    "sg:tags":[
        "entertainer",
        "business"
    ],
    "wof:name":"Karaoke Crush",
    "wof:placetype":"venue"
},
  "geometry": {"coordinates":[-107.54007300000001,39.57474],"type":"Point"}
}