{
  "type": "Feature",
  "properties": {
    "iso:country":"US",
    "sg:address":"310 Skylark Way",
    "sg:city":"Boulder",
    "sg:classifiers":[
        {
            "category":"Professional",
            "type":"Services"
        }
    ],
    "sg:phone":"+1 303 499 4977",
    "sg:postcode":"80303",
    "sg:province":"CO",
    "wof:name":"Robert M Jickling",
    "wof:placetype":"venue"
},
  "geometry": {"coordinates":[-105.178479,39.993115],"type":"Point"}
}