{
  "type": "Feature",
  "properties": {
    "addr:full":"1440 Black Canyon Rd Crawford CO 81415",
    "addr:housenumber":"1440",
    "addr:postcode":"81415",
    "addr:street":"Black Canyon Rd",
    "iso:country":"US",
    "sg:address":"1440 Black Canyon Rd",
    "sg:city":"Crawford",
    "sg:classifiers":[
        {
            "category":"Utilities",
            "subcategory":"Water",
            "type":"Services"
        }
    ],
    "sg:phone":"+1 970 921 7211",
    "sg:postcode":"81415",
    "sg:province":"CO",
    "sg:tags":[
        "supply"
    ],
    "wof:name":"Fruitland Domestic Water Co",
    "wof:placetype":"venue"
},
  "geometry": {"coordinates":[-107.618236,38.678335],"type":"Point"}
}