{
  "type": "Feature",
  "properties": {
    "addr:full":"16526 Keystone Blvd Parker CO 80134",
    "addr:housenumber":"16526",
    "addr:postcode":"80134",
    "addr:street":"Keystone Blvd",
    "iso:country":"US",
    "sg:address":"16526 Keystone Blvd",
    "sg:city":"Parker",
    "sg:classifiers":[
        {
            "category":"Insurance",
            "subcategory":"Insurance Agent",
            "type":"Services"
        }
    ],
    "sg:phone":"+1 303 520 8196",
    "sg:postcode":"80134",
    "sg:province":"CO",
    "wof:name":"American Family Insurance",
    "wof:placetype":"venue"
},
  "geometry": {"coordinates":[-104.79997400000001,39.530635],"type":"Point"}
}