{
  "type": "Feature",
  "properties": {
    "addr:full":"3405 Penrose Pl Boulder CO 80301",
    "addr:housenumber":"3405",
    "addr:postcode":"80301",
    "addr:street":"Penrose Pl",
    "iso:country":"US",
    "sg:address":"3405 Penrose Pl",
    "sg:city":"Boulder",
    "sg:classifiers":[
        {
            "category":"Health Services",
            "subcategory":"Health Practitioner",
            "type":"Services"
        }
    ],
    "sg:phone":"+1 303 449 8480",
    "sg:postcode":"80301",
    "sg:province":"CO",
    "sg:tags":[
        "acupuncture"
    ],
    "wof:name":"Acupuncture & Chinese Herblst",
    "wof:placetype":"venue"
},
  "geometry": {"coordinates":[-105.247449,40.037601],"type":"Point"}
}