{
  "type": "Feature",
  "properties": {
    "iso:country":"US",
    "sg:address":"35519 Cheyenne Trl",
    "sg:city":"Elizabeth",
    "sg:classifiers":[
        {
            "category":"Manufacturing",
            "subcategory":"Printing",
            "type":"Manufacturing & Wholesale Goods"
        }
    ],
    "sg:phone":"+1 303 646 5044",
    "sg:postcode":"80107",
    "sg:province":"CO",
    "sg:tags":[
        "newspaper"
    ],
    "wof:name":"High Plains Rider",
    "wof:placetype":"venue"
},
  "geometry": {"coordinates":[-104.641457,39.387638],"type":"Point"}
}