{
  "type": "Feature",
  "properties": {
    "addr:full":"9785 S Maroon Cir Centennial CO 80112",
    "addr:housenumber":"9785",
    "addr:postcode":"80112",
    "addr:street":"S Maroon Cir",
    "iso:country":"US",
    "sg:address":"9785 S Maroon Cir",
    "sg:city":"Centennial",
    "sg:classifiers":[
        {
            "category":"Real Estate",
            "subcategory":"Developer",
            "type":"Services"
        },
        {
            "category":"Real Estate",
            "subcategory":"Real Estate Agent",
            "type":"Services"
        }
    ],
    "sg:phone":"+1 303 790 4737",
    "sg:postcode":"80112",
    "sg:province":"CO",
    "sg:website":"www.panattoni.com",
    "wof:name":"Panattoni Development Co LLC",
    "wof:placetype":"venue"
},
  "geometry": {"coordinates":[-104.85748599999999,39.540022],"type":"Point"}
}