{
  "type": "Feature",
  "properties": {
    "addr:full":"945 E Rainbow Blvd Salida CO 81201",
    "addr:housenumber":"945",
    "addr:postcode":"81201",
    "addr:street":"E Rainbow Blvd",
    "iso:country":"US",
    "sg:address":"945 E Rainbow Blvd",
    "sg:city":"Salida",
    "sg:classifiers":[
        {
            "category":"Home & Garden",
            "subcategory":"Building Materials",
            "type":"Retail Goods"
        }
    ],
    "sg:phone":"+1 719 395 8225",
    "sg:postcode":"81201",
    "sg:province":"CO",
    "wof:name":"Thankful Harvest Stained Glass",
    "wof:placetype":"venue"
},
  "geometry": {"coordinates":[-105.99132299999999,38.523991],"type":"Point"}
}