{
  "type": "Feature",
  "properties": {
    "iso:country":"US",
    "sg:address":"1634 York Rd",
    "sg:city":"Colorado Springs",
    "sg:classifiers":[
        {
            "category":"Health Services",
            "subcategory":"Doctor",
            "type":"Services"
        }
    ],
    "sg:phone":"+1 719 522 0800",
    "sg:postcode":"80918",
    "sg:province":"CO",
    "wof:name":"Comfort Dental",
    "wof:placetype":"venue"
},
  "geometry": {"coordinates":[-104.795523,38.929925],"type":"Point"}
}