{
  "type": "Feature",
  "properties": {
    "addr:full":"6847 W 53rd Pl Arvada CO 80002",
    "addr:housenumber":"6847",
    "addr:postcode":"80002",
    "addr:street":"W 53Rd Pl",
    "iso:country":"US",
    "sg:address":"6847 W 53rd Pl",
    "sg:city":"Arvada",
    "sg:classifiers":[
        {
            "category":"Building & Trades",
            "subcategory":"Electrical",
            "type":"Services"
        }
    ],
    "sg:phone":"+1 303 432 1698",
    "sg:postcode":"80002",
    "sg:province":"CO",
    "sg:tags":[
        "electrical",
        "contractor"
    ],
    "wof:name":"Philip King",
    "wof:placetype":"venue"
},
  "geometry": {"coordinates":[-105.073695,39.793542],"type":"Point"}
}