{
  "type": "Feature",
  "properties": {
    "iso:country":"US",
    "sg:address":"378 Ridgeway Dr",
    "sg:city":"Grand Junction",
    "sg:classifiers":[
        {
            "category":"Retail",
            "subcategory":"Repair Shop",
            "type":"Services"
        }
    ],
    "sg:phone":"+1 970 255 0417",
    "sg:postcode":"81503",
    "sg:province":"CO",
    "sg:tags":[
        "repairing",
        "piano",
        "refinishing"
    ],
    "wof:name":"Merrill Piano Svc",
    "wof:placetype":"venue"
},
  "geometry": {"coordinates":[-108.60536500000001,39.062728],"type":"Point"}
}