{
  "type": "Feature",
  "properties": {
    "iso:country":"US",
    "sg:address":"15992 Longmeadow Ln",
    "sg:city":"Colorado Springs",
    "sg:classifiers":[
        {
            "category":"Education",
            "subcategory":"Special Training",
            "type":"Public Place"
        }
    ],
    "sg:phone":"+1 719 484 0246",
    "sg:postcode":"80921",
    "sg:province":"CO",
    "sg:tags":[
        "educational"
    ],
    "wof:name":"Home School Advantage",
    "wof:placetype":"venue"
},
  "geometry": {"coordinates":[-104.799505,39.065538],"type":"Point"}
}