{
  "type": "Feature",
  "properties": {
    "iso:country":"US",
    "sg:address":"324 Edison St",
    "sg:city":"Brush",
    "sg:classifiers":[
        {
            "category":"Real Estate",
            "subcategory":"Real Estate Operator",
            "type":"Services"
        }
    ],
    "sg:phone":"+1 970 842 2478",
    "sg:postcode":"80723",
    "sg:province":"CO",
    "sg:tags":[
        "mobile",
        "home",
        "community"
    ],
    "wof:name":"Meadow Mobile Home Park",
    "wof:placetype":"venue"
},
  "geometry": {"coordinates":[-103.622067,40.255248],"type":"Point"}
}