{
  "type": "Feature",
  "properties": {
    "addr:full":"21956 Co Rd 7 Idalia CO 80735",
    "addr:housenumber":"21956",
    "addr:postcode":"80735",
    "addr:street":"Co Rd 7 Idalia",
    "iso:country":"US",
    "sg:address":"21956 Co Rd 7",
    "sg:city":"Idalia",
    "sg:classifiers":[
        {
            "category":"Farming",
            "subcategory":"Farm",
            "type":"Manufacturing & Wholesale Goods"
        }
    ],
    "sg:phone":"+1 970 354 7344",
    "sg:postcode":"80735",
    "sg:province":"CO",
    "sg:tags":[
        "crop",
        "general"
    ],
    "wof:name":"Beckman Farms",
    "wof:placetype":"venue"
},
  "geometry": {"coordinates":[-102.39807999999999,39.672171],"type":"Point"}
}