{
  "type": "Feature",
  "properties": {
    "iso:country":"US",
    "sg:address":"2505 W 2nd Ave",
    "sg:city":"Denver",
    "sg:classifiers":[
        {
            "category":"Retail",
            "subcategory":"Auto Repair",
            "type":"Services"
        },
        {
            "category":"Wholesale",
            "subcategory":"Auto Parts",
            "type":"Manufacturing & Wholesale Goods"
        }
    ],
    "sg:phone":"+1 303 937 1700",
    "sg:postcode":"80219",
    "sg:province":"CO",
    "sg:tags":[
        "automobile",
        "used",
        "electric"
    ],
    "wof:name":"Automotive Exchange & Supply",
    "wof:placetype":"venue"
},
  "geometry": {"coordinates":[-105.01859399999999,39.720332],"type":"Point"}
}