{
  "type": "Feature",
  "properties": {
    "addr:full":"1739 Terry St Longmont CO 80501",
    "addr:housenumber":"1739",
    "addr:postcode":"80501",
    "addr:street":"Terry St",
    "iso:country":"US",
    "sg:address":"1739 Terry St",
    "sg:city":"Longmont",
    "sg:classifiers":[
        {
            "category":"Insurance",
            "subcategory":"Insurance Agent",
            "type":"Services"
        }
    ],
    "sg:phone":"+1 303 651 9889",
    "sg:postcode":"80501",
    "sg:province":"CO",
    "wof:name":"Oxford Insurance",
    "wof:placetype":"venue"
},
  "geometry": {"coordinates":[-105.104748,40.1897],"type":"Point"}
}