{
  "type": "Feature",
  "properties": {
    "addr:full":"11505 US Hwy 24 Divide CO 80814",
    "addr:housenumber":"11505",
    "addr:postcode":"80814",
    "addr:street":"Us Hwy 24 Divide",
    "iso:country":"US",
    "sg:address":"11505 US Hwy 24",
    "sg:city":"Divide",
    "sg:classifiers":[
        {
            "category":"Home & Garden",
            "subcategory":"Home Furnishings",
            "type":"Retail Goods"
        }
    ],
    "sg:phone":"+1 719 687 8857",
    "sg:postcode":"80814",
    "sg:province":"CO",
    "sg:tags":[
        "stove",
        "wood",
        "burning"
    ],
    "wof:name":"Country Hearths LLC",
    "wof:placetype":"venue"
},
  "geometry": {"coordinates":[-105.146368,38.947424],"type":"Point"}
}