{
  "type": "Feature",
  "properties": {
    "iso:country":"US",
    "sg:address":"18692 Pony Express Dr",
    "sg:city":"Parker",
    "sg:classifiers":[
        {
            "category":"Social Services",
            "subcategory":"Child Care",
            "type":"Services"
        }
    ],
    "sg:phone":"+1 303 840 5300",
    "sg:postcode":"80134",
    "sg:province":"CO",
    "sg:tags":[
        "day"
    ],
    "sg:website":"www.primroseschools.com",
    "wof:name":"Primrose School Of Parker",
    "wof:placetype":"venue"
},
  "geometry": {"coordinates":[-104.775277,39.521557],"type":"Point"}
}