{
  "type": "Feature",
  "properties": {
    "iso:country":"US",
    "sg:address":"5306 S Bannock St",
    "sg:city":"Littleton",
    "sg:classifiers":[
        {
            "category":"Building & Trades",
            "subcategory":"Cleaning & Sanitation",
            "type":"Services"
        }
    ],
    "sg:phone":"+1 303 795 9999",
    "sg:postcode":"80120",
    "sg:province":"CO",
    "sg:tags":[
        "window"
    ],
    "wof:name":"Fish Window Cleaning",
    "wof:placetype":"venue"
},
  "geometry": {"coordinates":[-104.990261,39.619667],"type":"Point"}
}