{
  "type": "Feature",
  "properties": {
    "addr:full":"1440 Brickyard Rd Golden CO 80403",
    "addr:housenumber":"1440",
    "addr:postcode":"80403",
    "addr:street":"Brickyard Rd",
    "iso:country":"US",
    "sg:address":"1440 Brickyard Rd",
    "sg:city":"Golden",
    "sg:classifiers":[
        {
            "category":"Manufacturing",
            "subcategory":"Metals",
            "type":"Manufacturing & Wholesale Goods"
        }
    ],
    "sg:phone":"+1 303 278 9296",
    "sg:postcode":"80403",
    "sg:province":"CO",
    "sg:tags":[
        "tool",
        "mfg",
        "hand"
    ],
    "wof:name":"Hartmeister Laboratories Inc",
    "wof:placetype":"venue"
},
  "geometry": {"coordinates":[-105.235849,39.780243],"type":"Point"}
}