{
  "type": "Feature",
  "properties": {
    "addr:full":"259 S College Ave Fort Collins CO 80524",
    "addr:housenumber":"259",
    "addr:postcode":"80524",
    "addr:street":"S College Ave",
    "iso:country":"US",
    "sg:address":"259 S College Ave",
    "sg:city":"Fort Collins",
    "sg:classifiers":[
        {
            "category":"Travel",
            "subcategory":"Hotels & Motels",
            "type":"Entertainment"
        }
    ],
    "sg:phone":"+1 970 484 3883",
    "sg:postcode":"80524",
    "sg:province":"CO",
    "sg:website":"www.thearmstronghotel.com",
    "wof:name":"Armstrong Hotel",
    "wof:placetype":"venue"
},
  "geometry": {"coordinates":[-105.077116,40.585025],"type":"Point"}
}