{
  "type": "Feature",
  "properties": {
    "iso:country":"US",
    "sg:address":"216 Monroe St",
    "sg:city":"Denver",
    "sg:classifiers":[
        {
            "category":"Professional",
            "type":"Services"
        }
    ],
    "sg:phone":"+1 303 333 0240",
    "sg:postcode":"80206",
    "sg:province":"CO",
    "wof:name":"Marc N Geman",
    "wof:placetype":"venue"
},
  "geometry": {"coordinates":[-104.944885,39.720713],"type":"Point"}
}