{
  "type": "Feature",
  "properties": {
    "iso:country":"US",
    "sg:address":"1608 Champa St",
    "sg:city":"Denver",
    "sg:classifiers":[
        {
            "category":"Personal",
            "subcategory":"Beauty Salon",
            "type":"Services"
        },
        {
            "category":"Personal",
            "subcategory":"Barber",
            "type":"Services"
        }
    ],
    "sg:phone":"+1 303 623 6600",
    "sg:postcode":"80202",
    "sg:province":"CO",
    "sg:tags":[
        "hair"
    ],
    "sg:website":"www.floydsbarbershop.com",
    "wof:name":"Floyd's Barber Shop",
    "wof:placetype":"venue"
},
  "geometry": {"coordinates":[-104.993782,39.746656],"type":"Point"}
}