{
  "type": "Feature",
  "properties": {
    "addr:full":"7845 E Gunnison Pl Denver CO 80231",
    "addr:housenumber":"7845",
    "addr:postcode":"80231",
    "addr:street":"E Gunnison Pl",
    "iso:country":"US",
    "sg:address":"7845 E Gunnison Pl",
    "sg:city":"Denver",
    "sg:classifiers":[
        {
            "category":"Professional",
            "subcategory":"Lawyer & Legal Services",
            "type":"Services"
        }
    ],
    "sg:phone":"+1 303 696 8101",
    "sg:postcode":"80231",
    "sg:province":"CO",
    "sg:tags":[
        "divorce",
        "assistance"
    ],
    "sg:website":"www.fisherseminars.com",
    "wof:name":"Fisher Seminars LLC",
    "wof:placetype":"venue"
},
  "geometry": {"coordinates":[-104.897526,39.68889],"type":"Point"}
}