{
  "type": "Feature",
  "properties": {
    "iso:country":"US",
    "sg:address":"1910 North Ave",
    "sg:city":"Grand Junction",
    "sg:classifiers":[
        {
            "category":"Restaurant",
            "type":"Food & Drink"
        }
    ],
    "sg:menulink":"http://www.allmenus.com/co/grand-junction/109289-village-inn/menu/",
    "sg:phone":"+1 970 243 5467",
    "sg:postcode":"81501",
    "sg:province":"CO",
    "sg:tags":[
        "new",
        "american"
    ],
    "wof:name":"Village Inn",
    "wof:placetype":"venue"
},
  "geometry": {"coordinates":[-108.54224499999999,39.077425],"type":"Point"}
}