{
  "type": "Feature",
  "properties": {
    "addr:full":"1001 Cleveland Ave Loveland CO 80537",
    "addr:housenumber":"1001",
    "addr:postcode":"80537",
    "addr:street":"Cleveland Ave",
    "iso:country":"US",
    "sg:address":"1001 Cleveland Ave",
    "sg:city":"Loveland",
    "sg:classifiers":[
        {
            "category":"Insurance",
            "subcategory":"Insurance Agent",
            "type":"Services"
        }
    ],
    "sg:phone":"+1 970 622 8553",
    "sg:postcode":"80537",
    "sg:province":"CO",
    "wof:name":"Pitmon Insurance",
    "wof:placetype":"venue"
},
  "geometry": {"coordinates":[-105.074456,40.402671],"type":"Point"}
}