{
  "type": "Feature",
  "properties": {
    "addr:full":"4543 Bella Dr Colorado Springs CO 80918",
    "addr:housenumber":"4543",
    "addr:postcode":"80918",
    "addr:street":"Bella Dr",
    "iso:country":"US",
    "sg:address":"4543 Bella Dr",
    "sg:city":"Colorado Springs",
    "sg:classifiers":[
        {
            "category":"Wholesale",
            "subcategory":"Vending Machines",
            "type":"Manufacturing & Wholesale Goods"
        }
    ],
    "sg:phone":"+1 719 548 1263",
    "sg:postcode":"80918",
    "sg:province":"CO",
    "sg:tags":[
        "operator"
    ],
    "wof:name":"Cdp Vending LLC",
    "wof:placetype":"venue"
},
  "geometry": {"coordinates":[-104.758713,38.897896],"type":"Point"}
}