{
  "type": "Feature",
  "properties": {
    "iso:country":"US",
    "sg:address":"822 Grand Ave",
    "sg:city":"Glenwood Springs",
    "sg:classifiers":[
        {
            "category":"Shopping",
            "subcategory":"Crafts & Fabrics",
            "type":"Retail Goods"
        }
    ],
    "sg:phone":"+1 970 945 5900",
    "sg:postcode":"81601",
    "sg:province":"CO",
    "sg:tags":[
        "shop",
        "household",
        "sewing",
        "appliance"
    ],
    "sg:website":"www.glenwoodsew.com",
    "wof:name":"Glenwood Sewing Center",
    "wof:placetype":"venue"
},
  "geometry": {"coordinates":[-107.32468,39.546417],"type":"Point"}
}