{
  "type": "Feature",
  "properties": {
    "iso:country":"US",
    "sg:address":"4855 Ricara Dr",
    "sg:city":"Boulder",
    "sg:classifiers":[
        {
            "category":"Shopping",
            "subcategory":"Gifts & Souvenirs",
            "type":"Retail Goods"
        }
    ],
    "sg:phone":"+1 303 499 1683",
    "sg:postcode":"80303",
    "sg:province":"CO",
    "wof:name":"Disabled American Veterans St",
    "wof:placetype":"venue"
},
  "geometry": {"coordinates":[-105.23254900000001,39.992323],"type":"Point"}
}