{
  "type": "Feature",
  "properties": {
    "iso:country":"US",
    "sg:address":"260 Park St",
    "sg:city":"Gypsum",
    "sg:classifiers":[
        {
            "category":"Professional",
            "type":"Services"
        }
    ],
    "sg:phone":"+1 970 524 1950",
    "sg:postcode":"81637",
    "sg:province":"CO",
    "wof:name":"Flow Heat Inc",
    "wof:placetype":"venue"
},
  "geometry": {"coordinates":[-106.958716,39.64451],"type":"Point"}
}