{
  "type": "Feature",
  "properties": {
    "addr:full":"710 Kipling St Denver CO 80215",
    "addr:housenumber":"710",
    "addr:postcode":"80215",
    "addr:street":"Kipling St",
    "iso:country":"US",
    "sg:address":"710 Kipling St",
    "sg:city":"Denver",
    "sg:classifiers":[
        {
            "category":"Insurance",
            "subcategory":"Insurance Agent",
            "type":"Services"
        }
    ],
    "sg:phone":"+1 303 238 4489",
    "sg:postcode":"80215",
    "sg:province":"CO",
    "wof:name":"Thielen Chad & Assoc LLC",
    "wof:placetype":"venue"
},
  "geometry": {"coordinates":[-105.10963099999999,39.726753],"type":"Point"}
}