{
  "type": "Feature",
  "properties": {
    "iso:country":"US",
    "sg:address":"701 Geneva St",
    "sg:city":"Aurora",
    "sg:classifiers":[
        {
            "category":"Building & Trades",
            "subcategory":"Construction",
            "type":"Services"
        }
    ],
    "sg:phone":"+1 303 367 9924",
    "sg:postcode":"80010",
    "sg:province":"CO",
    "sg:tags":[
        "house"
    ],
    "wof:name":"Azteca Construction",
    "wof:placetype":"venue"
},
  "geometry": {"coordinates":[-104.868267,39.729215],"type":"Point"}
}