{
  "type": "Feature",
  "properties": {
    "addr:full":"7899 S Lincoln Ct Littleton CO 80122",
    "addr:housenumber":"7899",
    "addr:postcode":"80122",
    "addr:street":"S Lincoln Ct",
    "iso:country":"US",
    "sg:address":"7899 S Lincoln Ct",
    "sg:city":"Littleton",
    "sg:classifiers":[
        {
            "category":"Professional",
            "subcategory":"Management & Consulting",
            "type":"Services"
        }
    ],
    "sg:phone":"+1 720 283 8182",
    "sg:postcode":"80122",
    "sg:province":"CO",
    "sg:tags":[
        "transportation",
        "vertical"
    ],
    "wof:name":"Lerch Bates North America",
    "wof:placetype":"venue"
},
  "geometry": {"coordinates":[-104.987374,39.573488],"type":"Point"}
}