{
  "type": "Feature",
  "properties": {
    "addr:full":"1125 Twinberry Ct Fort Collins CO 80525",
    "addr:housenumber":"1125",
    "addr:postcode":"80525",
    "addr:street":"Twinberry Ct",
    "iso:country":"US",
    "sg:address":"1125 Twinberry Ct",
    "sg:city":"Fort Collins",
    "sg:classifiers":[
        {
            "category":"Building & Trades",
            "subcategory":"Construction",
            "type":"Services"
        }
    ],
    "sg:phone":"+1 970 226 1830",
    "sg:postcode":"80525",
    "sg:province":"CO",
    "sg:tags":[
        "industrial",
        "floor",
        "commercial",
        "contractor",
        "also",
        "painting"
    ],
    "wof:name":"Four Seasons Painting",
    "wof:placetype":"venue"
},
  "geometry": {"coordinates":[-105.05692999999999,40.513904],"type":"Point"}
}