{
  "type": "Feature",
  "properties": {
    "iso:country":"US",
    "sg:address":"2369 S Trenton Way",
    "sg:city":"Denver",
    "sg:classifiers":[
        {
            "category":"Professional",
            "type":"Services"
        }
    ],
    "sg:phone":"+1 303 338 8874",
    "sg:postcode":"80231",
    "sg:province":"CO",
    "wof:name":"Presentations Services",
    "wof:placetype":"venue"
},
  "geometry": {"coordinates":[-104.896506,39.673122],"type":"Point"}
}