{
  "type": "Feature",
  "properties": {
    "iso:country":"US",
    "sg:address":"1643 Boulder St",
    "sg:city":"Denver",
    "sg:classifiers":[
        {
            "category":"Communications",
            "subcategory":"News Services",
            "type":"Services"
        }
    ],
    "sg:phone":"+1 303 526 5888",
    "sg:postcode":"80211",
    "sg:province":"CO",
    "wof:name":"Consumer Advantage News Ntwrk",
    "wof:placetype":"venue"
},
  "geometry": {"coordinates":[-105.010469,39.759368],"type":"Point"}
}