{
  "type": "Feature",
  "properties": {
    "iso:country":"US",
    "sg:address":"500 Geneva St",
    "sg:city":"Aurora",
    "sg:classifiers":[
        {
            "category":"Shopping",
            "subcategory":"Pharmacy",
            "type":"Retail Goods"
        }
    ],
    "sg:phone":"+1 303 364 9311",
    "sg:postcode":"80010",
    "sg:province":"CO",
    "wof:name":"Camellia Healthcare Center",
    "wof:placetype":"venue"
},
  "geometry": {"coordinates":[-104.86820299999999,39.720836],"type":"Point"}
}