{
  "type": "Feature",
  "properties": {
    "iso:country":"US",
    "sg:address":"15592 E Batavia Dr",
    "sg:city":"Aurora",
    "sg:classifiers":[
        {
            "category":"Manufacturing",
            "subcategory":"Electronics",
            "type":"Manufacturing & Wholesale Goods"
        }
    ],
    "sg:phone":"+1 303 344 1883",
    "sg:postcode":"80011",
    "sg:province":"CO",
    "sg:tags":[
        "equipment",
        "signal",
        "electronic",
        "mfg"
    ],
    "wof:name":"Fogg System Company Inc",
    "wof:placetype":"venue"
},
  "geometry": {"coordinates":[-104.807817,39.742465],"type":"Point"}
}