{
  "type": "Feature",
  "properties": {
    "iso:country":"US",
    "sg:address":"7507 East 36th Ave",
    "sg:city":"Denver",
    "sg:classifiers":[
        {
            "category":"Shopping",
            "subcategory":"Mobile Phones",
            "type":"Retail Goods"
        }
    ],
    "sg:postcode":"80238",
    "sg:province":"CO",
    "wof:name":"AT&T",
    "wof:placetype":"venue"
},
  "geometry": {"coordinates":[-104.900593,39.767437],"type":"Point"}
}