{
  "type": "Feature",
  "properties": {
    "addr:full":"6294 W Mississippi Ave Denver CO 80226",
    "addr:housenumber":"6294",
    "addr:postcode":"80226",
    "addr:street":"W Mississippi Ave",
    "iso:country":"US",
    "sg:address":"6294 W Mississippi Ave",
    "sg:city":"Denver",
    "sg:classifiers":[
        {
            "category":"Home & Garden",
            "subcategory":"Building Materials",
            "type":"Retail Goods"
        }
    ],
    "sg:phone":"+1 303 975 9973",
    "sg:postcode":"80226",
    "sg:province":"CO",
    "wof:name":"Consolidated Auto Glass Inc",
    "wof:placetype":"venue"
},
  "geometry": {"coordinates":[-105.06416,39.696645],"type":"Point"}
}