{
  "type": "Feature",
  "properties": {
    "iso:country":"US",
    "sg:address":"5400 W Jewell Avenue Suite 2",
    "sg:city":"Lakewood",
    "sg:classifiers":[
        {
            "category":"Health Services",
            "subcategory":"Chiropractor",
            "type":"Services"
        }
    ],
    "sg:phone":"+1 303 989 2252",
    "sg:postcode":"80232",
    "sg:province":"CO",
    "wof:name":"Debroder Charles F Dr",
    "wof:placetype":"venue"
},
  "geometry": {"coordinates":[-105.05626700000001,39.682257],"type":"Point"}
}