{
  "type": "Feature",
  "properties": {
    "iso:country":"US",
    "sg:address":"7204 Fairway Ln",
    "sg:city":"Parker",
    "sg:classifiers":[
        {
            "category":"Building & Trades",
            "subcategory":"Construction",
            "type":"Services"
        }
    ],
    "sg:phone":"+1 303 840 7057",
    "sg:postcode":"80134",
    "sg:province":"CO",
    "sg:tags":[
        "house"
    ],
    "wof:name":"Dimensions Diversified Inc",
    "wof:placetype":"venue"
},
  "geometry": {"coordinates":[-104.748137,39.455006],"type":"Point"}
}