{
  "type": "Feature",
  "properties": {
    "addr:full":"8200 S Quebec St Centennial CO 80112",
    "addr:housenumber":"8200",
    "addr:postcode":"80112",
    "addr:street":"S Quebec St",
    "iso:country":"US",
    "sg:address":"8200 S Quebec St",
    "sg:city":"Centennial",
    "sg:classifiers":[
        {
            "category":"Food & Beverages",
            "subcategory":"Specialty",
            "type":"Retail Goods"
        }
    ],
    "sg:phone":"+1 303 471 8040",
    "sg:postcode":"80112",
    "sg:province":"CO",
    "sg:tags":[
        "health",
        "diet"
    ],
    "wof:name":"Low Carb Cravings",
    "wof:placetype":"venue"
},
  "geometry": {"coordinates":[-104.904321,39.566816],"type":"Point"}
}