{
  "type": "Feature",
  "properties": {
    "addr:full":"7900 W 44th Ave Wheat Ridge CO 80033",
    "addr:housenumber":"7900",
    "addr:postcode":"80033",
    "addr:street":"W 44Th Ave",
    "iso:country":"US",
    "sg:address":"7900 W 44th Ave",
    "sg:city":"Wheat Ridge",
    "sg:classifiers":[
        {
            "category":"Health Services",
            "subcategory":"Doctor",
            "type":"Services"
        }
    ],
    "sg:phone":"+1 303 422 3813",
    "sg:postcode":"80033",
    "sg:province":"CO",
    "sg:tags":[
        "dentist"
    ],
    "wof:name":"Christopher Heiny DDS",
    "wof:placetype":"venue"
},
  "geometry": {"coordinates":[-105.086004,39.776627],"type":"Point"}
}