{
  "type": "Feature",
  "properties": {
    "addr:full":"502 Grant St Fort Morgan CO 80701",
    "addr:housenumber":"502",
    "addr:postcode":"morgan;80701",
    "addr:street":"Grant St",
    "iso:country":"US",
    "sg:address":"502 Grant St",
    "sg:city":"Fort Morgan",
    "sg:classifiers":[
        {
            "category":"Banks & Credit Unions",
            "subcategory":"Financial Services",
            "type":"Services"
        }
    ],
    "sg:phone":"+1 970 542 9310",
    "sg:postcode":"80701",
    "sg:province":"CO",
    "sg:tags":[
        "group",
        "investment",
        "private"
    ],
    "wof:name":"Cameo One",
    "wof:placetype":"venue"
},
  "geometry": {"coordinates":[-103.79365300000001,40.253948],"type":"Point"}
}