{
  "type": "Feature",
  "properties": {
    "iso:country":"US",
    "sg:address":"14001 W 32nd Ave",
    "sg:city":"Golden",
    "sg:classifiers":[
        {
            "category":"Sports & Exercise",
            "subcategory":"Golf",
            "type":"Entertainment"
        }
    ],
    "sg:phone":"+1 303 279 3003",
    "sg:postcode":"80401",
    "sg:province":"CO",
    "sg:tags":[
        "course"
    ],
    "sg:website":"www.americangolf.com",
    "wof:name":"Applewood Golf Course",
    "wof:placetype":"venue"
},
  "geometry": {"coordinates":[-105.16128399999999,39.76172],"type":"Point"}
}