{
  "type": "Feature",
  "properties": {
    "addr:full":"18973 E 44th Ave Denver CO 80249",
    "addr:housenumber":"18973",
    "addr:postcode":"80249",
    "addr:street":"E 44Th Ave",
    "iso:country":"US",
    "sg:address":"18973 E 44th Ave",
    "sg:city":"Denver",
    "sg:classifiers":[
        {
            "category":"Home & Garden",
            "subcategory":"Home Furnishings",
            "type":"Retail Goods"
        }
    ],
    "sg:phone":"+1 303 371 4781",
    "sg:postcode":"80249",
    "sg:province":"CO",
    "wof:name":"Its My Turn",
    "wof:placetype":"venue"
},
  "geometry": {"coordinates":[-104.766262,39.776718],"type":"Point"}
}