{
  "type": "Feature",
  "properties": {
    "addr:full":"5066 Cottonwood Dr Boulder CO 80301",
    "addr:housenumber":"5066",
    "addr:postcode":"80301",
    "addr:street":"Cottonwood Dr",
    "iso:country":"US",
    "sg:address":"5066 Cottonwood Dr",
    "sg:city":"Boulder",
    "sg:classifiers":[
        {
            "category":"Real Estate",
            "subcategory":"Real Estate Agent",
            "type":"Services"
        }
    ],
    "sg:phone":"+1 303 581 0606",
    "sg:postcode":"80301",
    "sg:province":"CO",
    "wof:name":"Colorado Living Real Estate",
    "wof:placetype":"venue"
},
  "geometry": {"coordinates":[-105.193443,40.067231],"type":"Point"}
}