{
  "type": "Feature",
  "properties": {
    "addr:full":"3501 S Mason St Fort Collins CO 80525",
    "addr:housenumber":"3501",
    "addr:postcode":"80525",
    "addr:street":"S Mason St",
    "iso:country":"US",
    "sg:address":"3501 S Mason St",
    "sg:city":"Fort Collins",
    "sg:classifiers":[
        {
            "category":"Building & Trades",
            "subcategory":"Plumbing",
            "type":"Services"
        }
    ],
    "sg:phone":"+1 970 226 4633",
    "sg:postcode":"80525",
    "sg:province":"CO",
    "sg:tags":[
        "contractor"
    ],
    "wof:name":"Holter Plumbing & Heating",
    "wof:placetype":"venue"
},
  "geometry": {"coordinates":[-105.079061,40.539089],"type":"Point"}
}