{
  "type": "Feature",
  "properties": {
    "iso:country":"US",
    "sg:address":"13946 W 22nd Ave",
    "sg:city":"Golden",
    "sg:classifiers":[
        {
            "category":"Professional",
            "subcategory":"Management & Consulting",
            "type":"Services"
        }
    ],
    "sg:phone":"+1 303 273 0578",
    "sg:postcode":"80401",
    "sg:province":"CO",
    "sg:tags":[
        "fuel"
    ],
    "wof:name":"Ross Connections Inc",
    "wof:placetype":"venue"
},
  "geometry": {"coordinates":[-105.154617,39.750184],"type":"Point"}
}