{
  "type": "Feature",
  "properties": {
    "iso:country":"US",
    "sg:address":"111 Main",
    "sg:city":"Black Hawk",
    "sg:classifiers":[
        {
            "category":"Casinos & Gambling",
            "type":"Entertainment"
        }
    ],
    "sg:phone":"+1 303 278 1114",
    "sg:postcode":"80422",
    "sg:province":"CO",
    "wof:name":"Gilpin Casino",
    "wof:placetype":"venue"
},
  "geometry": {"coordinates":[-105.509003,39.799801],"type":"Point"}
}