{
  "type": "Feature",
  "properties": {
    "addr:full":"2902 S Glen Ave Glenwood Springs CO 81601",
    "addr:housenumber":"2902",
    "addr:postcode":"81601",
    "addr:street":"S Glen Ave",
    "iso:country":"US",
    "sg:address":"2902 S Glen Ave",
    "sg:city":"Glenwood Springs",
    "sg:classifiers":[
        {
            "category":"Wholesale",
            "subcategory":"Machinery & Supplies",
            "type":"Manufacturing & Wholesale Goods"
        }
    ],
    "sg:phone":"+1 970 947 0113",
    "sg:postcode":"81601",
    "sg:province":"CO",
    "sg:tags":[
        "equipment",
        "industrial"
    ],
    "wof:name":"Short Stop Food & Gas",
    "wof:placetype":"venue"
},
  "geometry": {"coordinates":[-107.321703,39.522488],"type":"Point"}
}