{
  "type": "Feature",
  "properties": {
    "iso:country":"US",
    "sg:address":"2676 W Alamo Ave",
    "sg:city":"Littleton",
    "sg:classifiers":[
        {
            "category":"Insurance",
            "subcategory":"Insurance Agent",
            "type":"Services"
        }
    ],
    "sg:phone":"+1 303 794 1282",
    "sg:postcode":"80120",
    "sg:province":"CO",
    "wof:name":"Riley Cgi-Clark",
    "wof:placetype":"venue"
},
  "geometry": {"coordinates":[-105.019023,39.612725],"type":"Point"}
}