{
  "type": "Feature",
  "properties": {
    "addr:full":"985 Meadow Dr Rock Springs CO 82901",
    "addr:housenumber":"985",
    "addr:postcode":"82901",
    "addr:street":"Meadow Dr",
    "iso:country":"US",
    "sg:address":"985 Meadow Dr",
    "sg:city":"Rock Springs",
    "sg:classifiers":[
        {
            "category":"Organizations",
            "subcategory":"Religious Organization",
            "type":"Services"
        }
    ],
    "sg:phone":"+1 307 352 3589",
    "sg:postcode":"82901",
    "sg:province":"CO",
    "wof:name":"Temple Transport",
    "wof:placetype":"venue"
},
  "geometry": {"coordinates":[-109.264945,41.646565],"type":"Point"}
}