{
  "type": "Feature",
  "properties": {
    "addr:full":"7551 W Alameda Ave Lakewood CO 80226",
    "addr:housenumber":"7551",
    "addr:postcode":"80226",
    "addr:street":"W Alameda Ave",
    "iso:country":"US",
    "sg:address":"7551 W Alameda Ave",
    "sg:city":"Lakewood",
    "sg:classifiers":[
        {
            "category":"Mining & Drilling",
            "type":"Manufacturing & Wholesale Goods"
        }
    ],
    "sg:phone":"+1 303 922 0590",
    "sg:postcode":"80226",
    "sg:province":"CO",
    "sg:tags":[
        "development",
        "gas",
        "oil",
        "exploration"
    ],
    "wof:name":"Aeon Energy",
    "wof:placetype":"venue"
},
  "geometry": {"coordinates":[-105.080482,39.711093],"type":"Point"}
}