{
  "type": "Feature",
  "properties": {
    "addr:full":"4888 Chambers Rd Denver CO 80239",
    "addr:housenumber":"4888",
    "addr:postcode":"80239",
    "addr:street":"Chambers Rd",
    "iso:country":"US",
    "sg:address":"4888 Chambers Rd",
    "sg:city":"Denver",
    "sg:classifiers":[
        {
            "category":"Shopping",
            "subcategory":"Tobacco",
            "type":"Retail Goods"
        }
    ],
    "sg:phone":"+1 303 576 8432",
    "sg:postcode":"80239",
    "sg:province":"CO",
    "sg:tags":[
        "cigarette",
        "cigar",
        "dealer"
    ],
    "wof:name":"Cigarette Store",
    "wof:placetype":"venue"
},
  "geometry": {"coordinates":[-104.80979600000001,39.778591],"type":"Point"}
}