{
  "type": "Feature",
  "properties": {
    "addr:full":"4715 Wing Shadow Vw Manitou Springs CO 80829",
    "addr:housenumber":"4715",
    "addr:postcode":"80829",
    "addr:street":"Wing Shadow Vw",
    "iso:country":"US",
    "sg:address":"4715 Wing Shadow Vw",
    "sg:city":"Manitou Springs",
    "sg:classifiers":[
        {
            "category":"Professional",
            "type":"Services"
        }
    ],
    "sg:phone":"+1 719 685 0900",
    "sg:postcode":"80829",
    "sg:province":"CO",
    "wof:name":"Wendy Matuszewski",
    "wof:placetype":"venue"
},
  "geometry": {"coordinates":[-104.919611,38.832782],"type":"Point"}
}