{
  "type": "Feature",
  "properties": {
    "addr:full":"470 Race St Denver CO 80206",
    "addr:housenumber":"470",
    "addr:postcode":"80206",
    "addr:street":"Race St",
    "iso:country":"US",
    "sg:address":"470 Race St",
    "sg:city":"Denver",
    "sg:classifiers":[
        {
            "category":"Banks & Credit Unions",
            "subcategory":"Financial Services",
            "type":"Services"
        }
    ],
    "sg:phone":"+1 303 355 8222",
    "sg:postcode":"80206",
    "sg:province":"CO",
    "sg:tags":[
        "company",
        "investment",
        "holding"
    ],
    "wof:name":"Pfeifley Company LLC",
    "wof:placetype":"venue"
},
  "geometry": {"coordinates":[-104.96338799999999,39.723284],"type":"Point"}
}