{
  "type": "Feature",
  "properties": {
    "iso:country":"US",
    "sg:address":"6787 Serena Ave",
    "sg:city":"Castle Rock",
    "sg:classifiers":[
        {
            "category":"Insurance",
            "subcategory":"Insurance Agent",
            "type":"Services"
        }
    ],
    "sg:phone":"+1 303 730 6883",
    "sg:postcode":"80108",
    "sg:province":"CO",
    "wof:name":"R L Inzer & Co",
    "wof:placetype":"venue"
},
  "geometry": {"coordinates":[-104.910242,39.49134],"type":"Point"}
}