{
  "type": "Feature",
  "properties": {
    "addr:full":"3528 Evergreen Pkwy Evergreen CO 80439",
    "addr:housenumber":"3528",
    "addr:postcode":"80439",
    "addr:street":"Evergreen Pkwy",
    "iso:country":"US",
    "sg:address":"3528 Evergreen Pkwy",
    "sg:city":"Evergreen",
    "sg:classifiers":[
        {
            "category":"Professional",
            "subcategory":"Research",
            "type":"Services"
        }
    ],
    "sg:phone":"+1 303 670 2875",
    "sg:postcode":"80439",
    "sg:province":"CO",
    "sg:tags":[
        "environmental",
        "ecological"
    ],
    "sg:website":"www.pelorusenbiotech.com",
    "wof:name":"Pelorus Environment",
    "wof:placetype":"venue"
},
  "geometry": {"coordinates":[-105.342676,39.650266],"type":"Point"}
}