{
  "type": "Feature",
  "properties": {
    "addr:full":"124 E 10th St Salida CO 81201",
    "addr:housenumber":"124",
    "addr:postcode":"81201",
    "addr:street":"E 10Th St",
    "iso:country":"US",
    "sg:address":"124 E 10th St",
    "sg:city":"Salida",
    "sg:classifiers":[
        {
            "category":"Real Estate",
            "subcategory":"Real Estate Agent",
            "type":"Services"
        }
    ],
    "sg:phone":"+1 719 530 0760",
    "sg:postcode":"81201",
    "sg:province":"CO",
    "sg:tags":[
        "inspection"
    ],
    "wof:name":"Affordable Home Inspection",
    "wof:placetype":"venue"
},
  "geometry": {"coordinates":[-105.998684,38.528439],"type":"Point"}
}