{
  "type": "Feature",
  "properties": {
    "addr:full":"738 Santa Fe Dr Denver CO 80204",
    "addr:housenumber":"738",
    "addr:postcode":"80204",
    "addr:street":"Santa Fe Dr",
    "iso:country":"US",
    "sg:address":"738 Santa Fe Dr",
    "sg:city":"Denver",
    "sg:classifiers":[
        {
            "category":"Professional",
            "type":"Services"
        },
        {
            "category":"Professional",
            "subcategory":"Art Services",
            "type":"Services"
        }
    ],
    "sg:phone":"+1 303 777 8900",
    "sg:postcode":"80204",
    "sg:province":"CO",
    "sg:tags":[
        "graphic",
        "designer"
    ],
    "wof:name":"Chronos Creative LLC",
    "wof:placetype":"venue"
},
  "geometry": {"coordinates":[-104.99853299999999,39.728289],"type":"Point"}
}