{
  "type": "Feature",
  "properties": {
    "iso:country":"US",
    "sg:address":"9605 W 49th Ave",
    "sg:city":"Wheat Ridge",
    "sg:classifiers":[
        {
            "category":"Professional",
            "subcategory":"Management & Consulting",
            "type":"Services"
        }
    ],
    "sg:phone":"+1 303 534 0388",
    "sg:postcode":"80033",
    "sg:province":"CO",
    "sg:tags":[
        "consultant",
        "business"
    ],
    "wof:name":"R T Welter & Assoc",
    "wof:placetype":"venue"
},
  "geometry": {"coordinates":[-105.106167,39.785739],"type":"Point"}
}