{
  "type": "Feature",
  "properties": {
    "addr:full":"1717 Welch St Fort Collins CO 80525",
    "addr:housenumber":"1717",
    "addr:postcode":"80525",
    "addr:street":"Welch St",
    "iso:country":"US",
    "sg:address":"1717 Welch St",
    "sg:city":"Fort Collins",
    "sg:classifiers":[
        {
            "category":"Real Estate",
            "subcategory":"Real Estate Operator",
            "type":"Services"
        }
    ],
    "sg:phone":"+1 970 493 4250",
    "sg:postcode":"80525",
    "sg:province":"CO",
    "sg:tags":[
        "building",
        "apartment"
    ],
    "wof:name":"Brookview Apartments",
    "wof:placetype":"venue"
},
  "geometry": {"coordinates":[-105.05378399999999,40.563323],"type":"Point"}
}