{
  "type": "Feature",
  "properties": {
    "iso:country":"US",
    "sg:address":"13145 Co Rd 502",
    "sg:city":"Bayfield",
    "sg:classifiers":[
        {
            "category":"Building & Trades",
            "subcategory":"Landscaping Services",
            "type":"Services"
        }
    ],
    "sg:phone":"+1 970 884 7277",
    "sg:postcode":"81122",
    "sg:province":"CO",
    "sg:tags":[
        "lawn",
        "maintenance",
        "grounds"
    ],
    "wof:name":"Accent Lawns",
    "wof:placetype":"venue"
},
  "geometry": {"coordinates":[-107.647108,37.320935],"type":"Point"}
}