{
  "type": "Feature",
  "properties": {
    "iso:country":"US",
    "sg:address":"3050 Industrial Ln",
    "sg:city":"Broomfield",
    "sg:classifiers":[
        {
            "category":"Professional",
            "type":"Services"
        }
    ],
    "sg:phone":"+1 303 469 2221",
    "sg:postcode":"80020",
    "sg:province":"CO",
    "wof:name":"B5 Inc",
    "wof:placetype":"venue"
},
  "geometry": {"coordinates":[-105.10672,39.923089],"type":"Point"}
}