{
  "type": "Feature",
  "properties": {
    "addr:full":"1920 Vindicator Dr Colorado Springs CO 80919",
    "addr:housenumber":"1920",
    "addr:postcode":"80919",
    "addr:street":"Vindicator Dr",
    "iso:country":"US",
    "sg:address":"1920 Vindicator Dr",
    "sg:city":"Colorado Springs",
    "sg:classifiers":[
        {
            "category":"Banks & Credit Unions",
            "subcategory":"Bank",
            "type":"Services"
        }
    ],
    "sg:phone":"+1 719 260 9847",
    "sg:postcode":"80919",
    "sg:province":"CO",
    "sg:tags":[
        "loan"
    ],
    "wof:name":"Neighborhood Lending",
    "wof:placetype":"venue"
},
  "geometry": {"coordinates":[-104.862037,38.928464],"type":"Point"}
}