{
  "type": "Feature",
  "properties": {
    "iso:country":"US",
    "sg:address":"4500 W Colfax Ave",
    "sg:city":"Denver",
    "sg:classifiers":[
        {
            "category":"Shopping",
            "subcategory":"Florist",
            "type":"Retail Goods"
        }
    ],
    "sg:phone":"+1 303 623 9396",
    "sg:postcode":"80204",
    "sg:province":"CO",
    "wof:name":"Laluna's Flowers & Gift Market",
    "wof:placetype":"venue"
},
  "geometry": {"coordinates":[-105.04634299999999,39.740351],"type":"Point"}
}