{
  "type": "Feature",
  "properties": {
    "addr:full":"6735 Pawnee Cir Colorado Springs CO 80915",
    "addr:housenumber":"6735",
    "addr:postcode":"80915",
    "addr:street":"Pawnee Cir",
    "iso:country":"US",
    "sg:address":"6735 Pawnee Cir",
    "sg:city":"Colorado Springs",
    "sg:classifiers":[
        {
            "category":"Building & Trades",
            "subcategory":"Plumbing",
            "type":"Services"
        }
    ],
    "sg:phone":"+1 719 572 0021",
    "sg:postcode":"80915",
    "sg:province":"CO",
    "sg:tags":[
        "contractor"
    ],
    "wof:name":"R J Price Plumbing & Heating",
    "wof:placetype":"venue"
},
  "geometry": {"coordinates":[-104.702381,38.856972],"type":"Point"}
}