{
  "type": "Feature",
  "properties": {
    "iso:country":"US",
    "sg:address":"1555 Blake St",
    "sg:city":"Denver",
    "sg:classifiers":[
        {
            "category":"Fast Food",
            "type":"Food & Drink"
        }
    ],
    "sg:phone":"+1 720 524 4345",
    "sg:postcode":"80202",
    "sg:province":"CO",
    "sg:tags":[
        "burger"
    ],
    "sg:website":"www.hburgerco.com",
    "wof:name":"HBurger Co",
    "wof:placetype":"venue"
},
  "geometry": {"coordinates":[-104.999416,39.750366],"type":"Point"}
}