{
  "type": "Feature",
  "properties": {
    "addr:full":"6401 Sheridan Blvd Arvada CO 80003",
    "addr:housenumber":"6401",
    "addr:postcode":"80003",
    "addr:street":"Sheridan Blvd",
    "iso:country":"US",
    "sg:address":"6401 Sheridan Blvd",
    "sg:city":"Arvada",
    "sg:classifiers":[
        {
            "category":"Retail",
            "subcategory":"Auto Repair",
            "type":"Services"
        }
    ],
    "sg:phone":"+1 303 432 9701",
    "sg:postcode":"80003",
    "sg:province":"CO",
    "sg:tags":[
        "automotive"
    ],
    "wof:name":"Just Brakes",
    "wof:placetype":"venue"
},
  "geometry": {"coordinates":[-105.053251,39.814529],"type":"Point"}
}