{
  "type": "Feature",
  "properties": {
    "iso:country":"US",
    "sg:address":"1201 N Main St",
    "sg:city":"Lamar",
    "sg:classifiers":[
        {
            "category":"Travel",
            "subcategory":"Hotels & Motels",
            "type":"Entertainment"
        }
    ],
    "sg:phone":"+1 719 336 7471",
    "sg:postcode":"81052",
    "sg:province":"CO",
    "wof:name":"Lamar Inn",
    "wof:placetype":"venue"
},
  "geometry": {"coordinates":[-102.618466,38.100671],"type":"Point"}
}