{
  "type": "Feature",
  "properties": {
    "addr:full":"12360 Hwy 666 Cortez CO 81321",
    "addr:housenumber":"12360",
    "addr:postcode":"81321",
    "addr:street":"Hwy 666",
    "iso:country":"US",
    "sg:address":"12360 Hwy 666",
    "sg:city":"Cortez",
    "sg:phone":"+1 970 564 1199",
    "sg:postcode":"81321",
    "sg:province":"CO",
    "sg:tags":[
        "gas",
        "product",
        "petroleum"
    ],
    "wof:name":"Country Gas",
    "wof:placetype":"venue"
},
  "geometry": {"coordinates":[-108.614242,37.390421],"type":"Point"}
}