{
  "type": "Feature",
  "properties": {
    "addr:full":"6033 Barnes Rd Colorado Springs CO 80922",
    "addr:housenumber":"6033",
    "addr:postcode":"80922",
    "addr:street":"Barnes Rd",
    "iso:country":"US",
    "sg:address":"6033 Barnes Rd",
    "sg:city":"Colorado Springs",
    "sg:classifiers":[
        {
            "category":"Restaurant",
            "type":"Food & Drink"
        }
    ],
    "sg:menulink":"http://www.allmenus.com/co/elsmere/69506-dominos-pizza/menu/",
    "sg:phone":"+1 719 574 3900",
    "sg:postcode":"80922",
    "sg:province":"CO",
    "sg:tags":[
        "american",
        "wing",
        "pizza"
    ],
    "wof:name":"Domino's Pizza",
    "wof:placetype":"venue"
},
  "geometry": {"coordinates":[-104.716742,38.893553],"type":"Point"}
}