{
  "type": "Feature",
  "properties": {
    "addr:full":"211 N Academy Blvd Colorado Springs CO 80909",
    "addr:housenumber":"211",
    "addr:postcode":"80909",
    "addr:street":"N Academy Blvd",
    "iso:country":"US",
    "sg:address":"211 N Academy Blvd",
    "sg:city":"Colorado Springs",
    "sg:classifiers":[
        {
            "category":"Retail",
            "subcategory":"Repair Shop",
            "type":"Services"
        }
    ],
    "sg:phone":"+1 719 570 1175",
    "sg:postcode":"80909",
    "sg:province":"CO",
    "sg:tags":[
        "electrical"
    ],
    "wof:name":"Kirby Vacuum Parts & Svc Ctr",
    "wof:placetype":"venue"
},
  "geometry": {"coordinates":[-104.757324,38.837135],"type":"Point"}
}