{
  "type": "Feature",
  "properties": {
    "addr:full":"113 S Main St Fountain CO 80817",
    "addr:housenumber":"113",
    "addr:postcode":"80817",
    "addr:street":"S Main St",
    "iso:country":"US",
    "sg:address":"113 S Main St",
    "sg:city":"Fountain",
    "sg:classifiers":[
        {
            "category":"Cinema",
            "subcategory":"Movie Rental",
            "type":"Entertainment"
        }
    ],
    "sg:phone":"+1 719 382 7590",
    "sg:postcode":"80817",
    "sg:province":"CO",
    "sg:tags":[
        "leasing",
        "video",
        "disc",
        "tape"
    ],
    "wof:name":"Fountain Video",
    "wof:placetype":"venue"
},
  "geometry": {"coordinates":[-104.700734,38.682746],"type":"Point"}
}