{
  "type": "Feature",
  "properties": {
    "addr:full":"11380 Peaceful Valley Rd Colorado Springs CO 80925",
    "addr:housenumber":"11380",
    "addr:postcode":"80925",
    "addr:street":"Peaceful Valley Rd",
    "iso:country":"US",
    "sg:address":"11380 Peaceful Valley Rd",
    "sg:city":"Colorado Springs",
    "sg:classifiers":[
        {
            "category":"Building & Trades",
            "subcategory":"Landscaping Services",
            "type":"Services"
        }
    ],
    "sg:phone":"+1 719 382 3888",
    "sg:postcode":"80925",
    "sg:province":"CO",
    "sg:tags":[
        "tree"
    ],
    "wof:name":"Aaires Tree Svc",
    "wof:placetype":"venue"
},
  "geometry": {"coordinates":[-104.61495499999999,38.728487],"type":"Point"}
}