{
  "type": "Feature",
  "properties": {
    "addr:full":"4651 State Hwy 73 Evergreen CO 80439",
    "addr:housenumber":"4651",
    "addr:postcode":"80439",
    "addr:street":"State Hwy 73",
    "iso:country":"US",
    "sg:address":"4651 State Hwy 73",
    "sg:city":"Evergreen",
    "sg:classifiers":[
        {
            "category":"Building & Trades",
            "subcategory":"Cleaning & Sanitation",
            "type":"Services"
        }
    ],
    "sg:phone":"+1 303 674 0718",
    "sg:postcode":"80439",
    "sg:province":"CO",
    "sg:tags":[
        "window"
    ],
    "wof:name":"A-1 Window Cleaning",
    "wof:placetype":"venue"
},
  "geometry": {"coordinates":[-105.321158,39.632223],"type":"Point"}
}