{
  "type": "Feature",
  "properties": {
    "addr:full":"900 Milky Way Denver CO 80260",
    "addr:housenumber":"900",
    "addr:postcode":"80260",
    "addr:street":"Milky Way",
    "iso:country":"US",
    "sg:address":"900 Milky Way",
    "sg:city":"Denver",
    "sg:classifiers":[
        {
            "category":"Organizations",
            "subcategory":"Labor Organization",
            "type":"Services"
        }
    ],
    "sg:phone":"+1 303 427 2834",
    "sg:postcode":"80260",
    "sg:province":"CO",
    "wof:name":"Millwright Mill Cabinet Local",
    "wof:placetype":"venue"
},
  "geometry": {"coordinates":[-104.996662,39.853055],"type":"Point"}
}