{
  "type": "Feature",
  "properties": {
    "iso:country":"US",
    "sg:address":"3220 Country Club Pkwy",
    "sg:city":"Castle Rock",
    "sg:classifiers":[
        {
            "category":"Insurance",
            "subcategory":"Insurance Agent",
            "type":"Services"
        }
    ],
    "sg:phone":"+1 303 660 4411",
    "sg:postcode":"80108",
    "sg:province":"CO",
    "wof:name":"Employee Benefit Design Inc",
    "wof:placetype":"venue"
},
  "geometry": {"coordinates":[-104.913573,39.445247],"type":"Point"}
}