{
  "type": "Feature",
  "properties": {
    "addr:full":"3735 Co Rd 21 Fort Lupton CO 80621",
    "addr:housenumber":"3735;21",
    "addr:postcode":"80621",
    "addr:street":"Co Rd;Fort Lupton",
    "iso:country":"US",
    "sg:address":"3735 Co Rd 21",
    "sg:city":"Fort Lupton",
    "sg:classifiers":[
        {
            "category":"Building & Trades",
            "subcategory":"Construction",
            "type":"Services"
        }
    ],
    "sg:phone":"+1 303 637 9590",
    "sg:postcode":"80621",
    "sg:province":"CO",
    "sg:tags":[
        "contractor"
    ],
    "wof:name":"Porter Contracting Inc",
    "wof:placetype":"venue"
},
  "geometry": {"coordinates":[-104.867402,40.054867],"type":"Point"}
}