{
  "type": "Feature",
  "properties": {
    "iso:country":"US",
    "sg:address":"801 Chestnut Ave",
    "sg:city":"Rocky Ford",
    "sg:classifiers":[
        {
            "category":"Social Services",
            "subcategory":"Job Training",
            "type":"Services"
        }
    ],
    "sg:phone":"+1 719 254 3396",
    "sg:postcode":"81067",
    "sg:province":"CO",
    "sg:tags":[
        "rehab",
        "government"
    ],
    "wof:name":"Colorado Employment Div",
    "wof:placetype":"venue"
},
  "geometry": {"coordinates":[-103.720636,38.056225],"type":"Point"}
}