{
  "type": "Feature",
  "properties": {
    "iso:country":"US",
    "sg:address":"905 W Victory Way",
    "sg:city":"Craig",
    "sg:classifiers":[
        {
            "category":"Restaurant",
            "type":"Food & Drink"
        }
    ],
    "sg:phone":"+1 970 824 5159",
    "sg:postcode":"81625",
    "sg:province":"CO",
    "wof:name":"Windy City Dogs & Beef",
    "wof:placetype":"venue"
},
  "geometry": {"coordinates":[-107.55797099999999,40.514273],"type":"Point"}
}