{
  "type": "Feature",
  "properties": {
    "addr:full":"378 Main St Limon CO 80828",
    "addr:housenumber":"378",
    "addr:postcode":"80828",
    "addr:street":"Main St",
    "iso:country":"US",
    "sg:address":"378 Main St",
    "sg:city":"Limon",
    "sg:classifiers":[
        {
            "category":"Autos & Motor Vehicles",
            "subcategory":"Fuel & Gas Station",
            "type":"Retail Goods"
        }
    ],
    "sg:phone":"+1 719 775 9797",
    "sg:postcode":"80828",
    "sg:province":"CO",
    "sg:tags":[
        "oil"
    ],
    "wof:name":"Stone Oil Co",
    "wof:placetype":"venue"
},
  "geometry": {"coordinates":[-103.68081100000001,39.263115],"type":"Point"}
}