{
  "type": "Feature",
  "properties": {
    "iso:country":"US",
    "sg:address":"6186 N Elbert Pl",
    "sg:city":"Parker",
    "sg:classifiers":[
        {
            "category":"Real Estate",
            "subcategory":"Real Estate Agent",
            "type":"Services"
        }
    ],
    "sg:phone":"+1 303 840 7509",
    "sg:postcode":"80134",
    "sg:province":"CO",
    "wof:name":"Re/Max",
    "wof:placetype":"venue"
},
  "geometry": {"coordinates":[-104.715205,39.451652],"type":"Point"}
}