{
  "type": "Feature",
  "properties": {
    "addr:full":"745 Wuthering Heights Dr Colorado Springs CO 80921",
    "addr:housenumber":"745",
    "addr:postcode":"80921",
    "addr:street":"Wuthering Heights Dr",
    "iso:country":"US",
    "sg:address":"745 Wuthering Heights Dr",
    "sg:city":"Colorado Springs",
    "sg:classifiers":[
        {
            "category":"Building & Trades",
            "subcategory":"Construction",
            "type":"Services"
        }
    ],
    "sg:phone":"+1 719 641 3770",
    "sg:postcode":"80921",
    "sg:province":"CO",
    "wof:name":"Colorado Canyon Cnstr LLC",
    "wof:placetype":"venue"
},
  "geometry": {"coordinates":[-104.813338,39.050563],"type":"Point"}
}