{
  "type": "Feature",
  "properties": {
    "addr:full":"10238 State Hwy 172 Ignacio CO 81137",
    "addr:housenumber":"10238",
    "addr:postcode":"81137",
    "addr:street":"State Hwy 172 Ignacio",
    "iso:country":"US",
    "sg:address":"10238 State Hwy 172",
    "sg:city":"Ignacio",
    "sg:classifiers":[
        {
            "category":"Manufacturing",
            "subcategory":"Metals",
            "type":"Manufacturing & Wholesale Goods"
        }
    ],
    "sg:phone":"+1 970 749 8098",
    "sg:postcode":"81137",
    "sg:province":"CO",
    "sg:tags":[
        "tool",
        "mfg"
    ],
    "wof:name":"Snap-On Tools",
    "wof:placetype":"venue"
},
  "geometry": {"coordinates":[-107.675273,37.169434],"type":"Point"}
}