{
  "type": "Feature",
  "properties": {
    "iso:country":"US",
    "sg:address":"2569 W Main St",
    "sg:city":"Littleton",
    "sg:classifiers":[
        {
            "category":"Shopping",
            "subcategory":"Clothing, Apparel, & Fashions",
            "type":"Retail Goods"
        }
    ],
    "sg:phone":"+1 303 730 7778",
    "sg:postcode":"80120",
    "sg:province":"CO",
    "wof:name":"Austin Hauck Company Inc",
    "wof:placetype":"venue"
},
  "geometry": {"coordinates":[-105.018384,39.613807],"type":"Point"}
}