{
  "type": "Feature",
  "properties": {
    "addr:full":"6398 S Josephine Way Littleton CO 80121",
    "addr:housenumber":"6398",
    "addr:postcode":"80121",
    "addr:street":"S Josephine Way",
    "iso:country":"US",
    "sg:address":"6398 S Josephine Way",
    "sg:city":"Littleton",
    "sg:classifiers":[
        {
            "category":"Professional",
            "type":"Services"
        }
    ],
    "sg:phone":"+1 303 797 6664",
    "sg:postcode":"80121",
    "sg:province":"CO",
    "wof:name":"MA Sabet & Co Inc",
    "wof:placetype":"venue"
},
  "geometry": {"coordinates":[-104.95696,39.601786],"type":"Point"}
}