{
  "type": "Feature",
  "properties": {
    "addr:full":"323 S 14th St Colorado Springs CO 80904",
    "addr:housenumber":"323",
    "addr:postcode":"80904",
    "addr:street":"S 14Th St",
    "iso:country":"US",
    "sg:address":"323 S 14th St",
    "sg:city":"Colorado Springs",
    "sg:classifiers":[
        {
            "category":"Retail",
            "subcategory":"Auto Repair",
            "type":"Services"
        }
    ],
    "sg:phone":"+1 719 578 0516",
    "sg:postcode":"80904",
    "sg:province":"CO",
    "sg:tags":[
        "repairing",
        "automobile"
    ],
    "wof:name":"Bob's Foreign Car Performance",
    "wof:placetype":"venue"
},
  "geometry": {"coordinates":[-104.84872,38.836072],"type":"Point"}
}