{
  "type": "Feature",
  "properties": {
    "addr:full":"327 Colorado Ave Pueblo CO 81004",
    "addr:housenumber":"327",
    "addr:postcode":"81004",
    "addr:street":"Colorado Ave",
    "iso:country":"US",
    "sg:address":"327 Colorado Ave",
    "sg:city":"Pueblo",
    "sg:classifiers":[
        {
            "category":"Real Estate",
            "subcategory":"Real Estate Agent",
            "type":"Services"
        }
    ],
    "sg:phone":"+1 719 544 7220",
    "sg:postcode":"81004",
    "sg:province":"CO",
    "wof:name":"Young & Assoc",
    "wof:placetype":"venue"
},
  "geometry": {"coordinates":[-104.62478900000001,38.257042],"type":"Point"}
}