{
  "type": "Feature",
  "properties": {
    "iso:country":"US",
    "sg:address":"73 Jameson Dr",
    "sg:city":"Durango",
    "sg:classifiers":[
        {
            "category":"Building & Trades",
            "subcategory":"Electrical",
            "type":"Services"
        }
    ],
    "sg:phone":"+1 970 247 5195",
    "sg:postcode":"81301",
    "sg:province":"CO",
    "sg:tags":[
        "electric",
        "contractor"
    ],
    "wof:name":"Puckett Electric Co",
    "wof:placetype":"venue"
},
  "geometry": {"coordinates":[-107.862861,37.291404],"type":"Point"}
}