{
  "type": "Feature",
  "properties": {
    "addr:full":"7460 W 38th Ave Wheat Ridge CO 80033",
    "addr:housenumber":"7460",
    "addr:postcode":"80033",
    "addr:street":"W 38Th Ave",
    "iso:country":"US",
    "sg:address":"7460 W 38th Ave",
    "sg:city":"Wheat Ridge",
    "sg:classifiers":[
        {
            "category":"Personal",
            "subcategory":"Beauty Salon",
            "type":"Services"
        }
    ],
    "sg:phone":"+1 303 423 6998",
    "sg:postcode":"80033",
    "sg:province":"CO",
    "sg:tags":[
        "hair"
    ],
    "sg:website":"www.salonalessandra.com/",
    "wof:name":"Alessandra's Salon",
    "wof:placetype":"venue"
},
  "geometry": {"coordinates":[-105.080541,39.769336],"type":"Point"}
}