{
  "type": "Feature",
  "properties": {
    "addr:full":"311 W 3rd St Palisade CO 81526",
    "addr:housenumber":"311",
    "addr:postcode":"81526",
    "addr:street":"W 3Rd St",
    "iso:country":"US",
    "sg:address":"311 W 3rd St",
    "sg:city":"Palisade",
    "sg:classifiers":[
        {
            "category":"Insurance",
            "subcategory":"Insurance Agent",
            "type":"Services"
        }
    ],
    "sg:phone":"+1 970 464 5661",
    "sg:postcode":"81526",
    "sg:province":"CO",
    "wof:name":"Knode & Assoc Insurance",
    "wof:placetype":"venue"
},
  "geometry": {"coordinates":[-108.353489,39.110131],"type":"Point"}
}