{
  "type": "Feature",
  "properties": {
    "addr:full":"1935 Independence Dr Colorado Springs CO 80920",
    "addr:housenumber":"1935",
    "addr:postcode":"80920",
    "addr:street":"Independence Dr",
    "iso:country":"US",
    "sg:address":"1935 Independence Dr",
    "sg:city":"Colorado Springs",
    "sg:classifiers":[
        {
            "category":"Building & Trades",
            "subcategory":"Landscaping Services",
            "type":"Services"
        }
    ],
    "sg:phone":"+1 719 243 5082",
    "sg:postcode":"80920",
    "sg:province":"CO",
    "sg:tags":[
        "tree"
    ],
    "wof:name":"Colorado Tree Experts",
    "wof:placetype":"venue"
},
  "geometry": {"coordinates":[-104.791068,38.942674],"type":"Point"}
}