{
  "type": "Feature",
  "properties": {
    "iso:country":"US",
    "sg:address":"2721 Larimer St",
    "sg:city":"Denver",
    "sg:classifiers":[
        {
            "category":"Bars & Pubs",
            "subcategory":"Lounge",
            "type":"Food & Drink"
        },
        {
            "category":"Arts & Performance",
            "subcategory":"Music",
            "type":"Entertainment"
        }
    ],
    "sg:phone":"+1 303 291 1007",
    "sg:postcode":"80204",
    "sg:province":"CO",
    "sg:tags":[
        "venue"
    ],
    "sg:website":"www.larimerlounge.com/",
    "wof:name":"Larimer Lounge",
    "wof:placetype":"venue"
},
  "geometry": {"coordinates":[-104.98400100000001,39.7598],"type":"Point"}
}