{
  "type": "Feature",
  "properties": {
    "addr:full":"2331 Broadway St Boulder CO 80304",
    "addr:housenumber":"2331",
    "addr:postcode":"80304",
    "addr:street":"Broadway St",
    "iso:country":"US",
    "sg:address":"2331 Broadway St",
    "sg:city":"Boulder",
    "sg:classifiers":[
        {
            "category":"Building & Trades",
            "subcategory":"Construction",
            "type":"Services"
        }
    ],
    "sg:phone":"+1 720 565 0382",
    "sg:postcode":"80304",
    "sg:province":"CO",
    "sg:tags":[
        "layer",
        "carpet"
    ],
    "wof:name":"Snow Lion Professional Carpet",
    "wof:placetype":"venue"
},
  "geometry": {"coordinates":[-105.28127499999999,40.021389],"type":"Point"}
}