{
  "type": "Feature",
  "properties": {
    "addr:full":"5335 W 48th Avenue Denver CO 80212",
    "addr:housenumber":"5335",
    "addr:postcode":"80212",
    "addr:street":"W 48Th Avenue",
    "iso:country":"US",
    "sg:address":"5335 W 48th Avenue",
    "sg:city":"Denver",
    "sg:classifiers":[
        {
            "category":"Professional",
            "subcategory":"Accounting & Tax Preparation",
            "type":"Services"
        }
    ],
    "sg:phone":"+1 303 455 7323",
    "sg:postcode":"80212",
    "sg:province":"CO",
    "sg:tags":[
        "accountant"
    ],
    "wof:name":"Pittenger Gracey Dudden PC",
    "wof:placetype":"venue"
},
  "geometry": {"coordinates":[-105.054816,39.783827],"type":"Point"}
}