{
  "type": "Feature",
  "properties": {
    "addr:full":"4500 Montview Blvd Denver CO 80207",
    "addr:housenumber":"4500",
    "addr:postcode":"80207",
    "addr:street":"Montview Blvd",
    "iso:country":"US",
    "sg:address":"4500 Montview Blvd",
    "sg:city":"Denver",
    "sg:classifiers":[
        {
            "category":"Professional",
            "type":"Services"
        }
    ],
    "sg:phone":"+1 303 377 9934",
    "sg:postcode":"80207",
    "sg:province":"CO",
    "wof:name":"Cognence Inc",
    "wof:placetype":"venue"
},
  "geometry": {"coordinates":[-104.935052,39.747398],"type":"Point"}
}