{
  "type": "Feature",
  "properties": {
    "addr:full":"3300 Airport Rd Boulder CO 80301",
    "addr:housenumber":"3300",
    "addr:postcode":"80301",
    "addr:street":"Airport Rd",
    "iso:country":"US",
    "sg:address":"3300 Airport Rd",
    "sg:city":"Boulder",
    "sg:classifiers":[
        {
            "category":"Professional",
            "subcategory":"Management & Consulting",
            "type":"Services"
        },
        {
            "category":"Wholesale",
            "subcategory":"Electrical",
            "type":"Manufacturing & Wholesale Goods"
        }
    ],
    "sg:phone":"+1 303 225 4625",
    "sg:postcode":"80301",
    "sg:province":"CO",
    "sg:tags":[
        "computer",
        "consultant",
        "custom",
        "program",
        "aviation",
        "electronic"
    ],
    "wof:name":"Contrail Services",
    "wof:placetype":"venue"
},
  "geometry": {"coordinates":[-105.233288,40.034646],"type":"Point"}
}