{
  "type": "Feature",
  "properties": {
    "addr:full":"434 Judson St Longmont CO 80501",
    "addr:housenumber":"434",
    "addr:postcode":"80501",
    "addr:street":"Judson St",
    "iso:country":"US",
    "sg:address":"434 Judson St",
    "sg:city":"Longmont",
    "sg:classifiers":[
        {
            "category":"Building & Trades",
            "subcategory":"Construction",
            "type":"Services"
        }
    ],
    "sg:phone":"+1 303 772 2829",
    "sg:postcode":"80501",
    "sg:province":"CO",
    "sg:tags":[
        "hanging",
        "contractor"
    ],
    "wof:name":"Kolby Decorating",
    "wof:placetype":"venue"
},
  "geometry": {"coordinates":[-105.11772999999999,40.169772],"type":"Point"}
}