{
  "type": "Feature",
  "properties": {
    "addr:full":"2726 Sierra Vista Rd Grand Junction CO 81503",
    "addr:housenumber":"2726",
    "addr:postcode":"81503",
    "addr:street":"Sierra Vista Rd",
    "iso:country":"US",
    "sg:address":"2726 Sierra Vista Rd",
    "sg:city":"Grand Junction",
    "sg:classifiers":[
        {
            "category":"Building & Trades",
            "subcategory":"Construction",
            "type":"Services"
        }
    ],
    "sg:phone":"+1 970 241 6592",
    "sg:postcode":"81503",
    "sg:province":"CO",
    "sg:tags":[
        "concrete",
        "contractor"
    ],
    "wof:name":"Canyon Wren Curbing LLC",
    "wof:placetype":"venue"
},
  "geometry": {"coordinates":[-108.547421,39.032634],"type":"Point"}
}