{
  "type": "Feature",
  "properties": {
    "iso:country":"US",
    "sg:address":"207 E 11th St",
    "sg:city":"Durango",
    "sg:classifiers":[
        {
            "category":"Insurance",
            "subcategory":"Insurance Agent",
            "type":"Services"
        }
    ],
    "sg:phone":"+1 970 247 3105",
    "sg:postcode":"81301",
    "sg:province":"CO",
    "wof:name":"State Farm Insurance",
    "wof:placetype":"venue"
},
  "geometry": {"coordinates":[-107.878561,37.275324],"type":"Point"}
}