{
  "type": "Feature",
  "properties": {
    "addr:full":"1025 S Perry Street Suite 105 Castle Rock CO 80104",
    "addr:housenumber":"1025",
    "addr:postcode":"80104",
    "addr:street":"S Perry Street Suite 105",
    "iso:country":"US",
    "sg:address":"1025 S Perry Street Suite 105",
    "sg:city":"Castle Rock",
    "sg:classifiers":[
        {
            "category":"Health Services",
            "subcategory":"Dentist",
            "type":"Services"
        }
    ],
    "sg:phone":"+1 303 841 5500",
    "sg:postcode":"80104",
    "sg:province":"CO",
    "sg:tags":[
        "orthodontist"
    ],
    "sg:website":"www.parkerorthodontics.com",
    "wof:name":"Parker Orthodontics",
    "wof:placetype":"venue"
},
  "geometry": {"coordinates":[-104.86104,39.365005],"type":"Point"}
}