{
  "type": "Feature",
  "properties": {
    "addr:full":"8031 Wadsworth Blvd Arvada CO 80003",
    "addr:housenumber":"8031",
    "addr:postcode":"80003",
    "addr:street":"Wadsworth Blvd",
    "iso:country":"US",
    "sg:address":"8031 Wadsworth Blvd",
    "sg:city":"Arvada",
    "sg:classifiers":[
        {
            "category":"Restaurant",
            "type":"Food & Drink"
        }
    ],
    "sg:menulink":"http://www.allmenus.com/co/northeast-jefferson/40735-qdoba/menu/",
    "sg:phone":"+1 720 898 1850",
    "sg:postcode":"80003",
    "sg:province":"CO",
    "sg:tags":[
        "mexican"
    ],
    "wof:name":"Qdoba",
    "wof:placetype":"venue"
},
  "geometry": {"coordinates":[-105.08201699999999,39.842694],"type":"Point"}
}