{
  "type": "Feature",
  "properties": {
    "iso:country":"US",
    "sg:address":"818 Owl Dr",
    "sg:city":"Louisville",
    "sg:classifiers":[
        {
            "category":"Real Estate",
            "subcategory":"Real Estate Agent",
            "type":"Services"
        }
    ],
    "sg:phone":"+1 303 499 3930",
    "sg:postcode":"80027",
    "sg:province":"CO",
    "sg:tags":[
        "appraiser"
    ],
    "wof:name":"B Saunders Brooks",
    "wof:placetype":"venue"
},
  "geometry": {"coordinates":[-105.152344,39.975625],"type":"Point"}
}