{
  "type": "Feature",
  "properties": {
    "iso:country":"US",
    "sg:address":"15109 E Greenwood Pl",
    "sg:city":"Aurora",
    "sg:classifiers":[
        {
            "category":"Professional",
            "subcategory":"Art Services",
            "type":"Services"
        }
    ],
    "sg:phone":"+1 303 693 9883",
    "sg:postcode":"80014",
    "sg:province":"CO",
    "sg:tags":[
        "commercial",
        "design"
    ],
    "wof:name":"Timeless Design",
    "wof:placetype":"venue"
},
  "geometry": {"coordinates":[-104.81149600000001,39.656366],"type":"Point"}
}