{
  "type": "Feature",
  "properties": {
    "iso:country":"US",
    "sg:address":"148 Becker Cir",
    "sg:city":"Johnstown",
    "sg:classifiers":[
        {
            "category":"Professional",
            "type":"Services"
        }
    ],
    "sg:phone":"+1 970 587 9074",
    "sg:postcode":"80534",
    "sg:province":"CO",
    "sg:tags":[
        "establishment"
    ],
    "wof:name":"Att Cits",
    "wof:placetype":"venue"
},
  "geometry": {"coordinates":[-104.95292600000001,40.337902],"type":"Point"}
}