{
  "type": "Feature",
  "properties": {
    "iso:country":"US",
    "sg:address":"4239 N Nevada Ave",
    "sg:city":"Colorado Springs",
    "sg:classifiers":[
        {
            "category":"Home & Garden",
            "subcategory":"Mobile Homes",
            "type":"Retail Goods"
        }
    ],
    "sg:phone":"+1 719 536 9386",
    "sg:postcode":"80907",
    "sg:province":"CO",
    "sg:tags":[
        "manufactured",
        "dealer",
        "modular"
    ],
    "wof:name":"Homes By Jan",
    "wof:placetype":"venue"
},
  "geometry": {"coordinates":[-104.81871700000001,38.893676],"type":"Point"}
}