{
  "type": "Feature",
  "properties": {
    "addr:full":"2498 Industrial Blvd Grand Junction CO 81505",
    "addr:housenumber":"2498",
    "addr:postcode":"81505",
    "addr:street":"Industrial Blvd",
    "iso:country":"US",
    "sg:address":"2498 Industrial Blvd",
    "sg:city":"Grand Junction",
    "sg:classifiers":[
        {
            "category":"Building & Trades",
            "subcategory":"Construction",
            "type":"Services"
        }
    ],
    "sg:phone":"+1 970 245 7503",
    "sg:postcode":"81505",
    "sg:province":"CO",
    "sg:tags":[
        "on",
        "welding",
        "site",
        "contractor"
    ],
    "wof:name":"T L Lafferty Welding",
    "wof:placetype":"venue"
},
  "geometry": {"coordinates":[-108.598815,39.089141],"type":"Point"}
}