{
  "type": "Feature",
  "properties": {
    "iso:country":"US",
    "sg:address":"1401 Wewatta St 102",
    "sg:city":"Denver",
    "sg:classifiers":[
        {
            "category":"Travel",
            "subcategory":"Travel Agent",
            "type":"Entertainment"
        }
    ],
    "sg:phone":"+1 303 620 9800",
    "sg:postcode":"80202",
    "sg:province":"CO",
    "sg:website":"writertravelone.com",
    "wof:name":"Writer Travel One",
    "wof:placetype":"venue"
},
  "geometry": {"coordinates":[-105.00421299999999,39.751067],"type":"Point"}
}