{
  "type": "Feature",
  "properties": {
    "addr:full":"335 Juanita St Colorado Springs CO 80909",
    "addr:housenumber":"335",
    "addr:postcode":"80909",
    "addr:street":"Juanita St",
    "iso:country":"US",
    "sg:address":"335 Juanita St",
    "sg:city":"Colorado Springs",
    "sg:classifiers":[
        {
            "category":"Wholesale",
            "subcategory":"Auto Parts",
            "type":"Manufacturing & Wholesale Goods"
        }
    ],
    "sg:phone":"+1 719 473 3171",
    "sg:postcode":"80909",
    "sg:province":"CO",
    "sg:tags":[
        "paint",
        "product",
        "related"
    ],
    "wof:name":"Finishmaster Inc",
    "wof:placetype":"venue"
},
  "geometry": {"coordinates":[-104.774477,38.836741],"type":"Point"}
}