{
  "type": "Feature",
  "properties": {
    "iso:country":"US",
    "sg:address":"34951 Co Rd 3h",
    "sg:city":"Genoa",
    "sg:classifiers":[
        {
            "category":"Freight",
            "type":"Transportation"
        }
    ],
    "sg:phone":"+1 719 763 2006",
    "sg:postcode":"80818",
    "sg:province":"CO",
    "wof:name":"James William Logistics LLP",
    "wof:placetype":"venue"
},
  "geometry": {"coordinates":[-103.417548,39.287386],"type":"Point"}
}