{
  "type": "Feature",
  "properties": {
    "addr:full":"3700 Galley Rd Colorado Springs CO 80909",
    "addr:housenumber":"3700",
    "addr:postcode":"80909",
    "addr:street":"Galley Rd",
    "iso:country":"US",
    "sg:address":"3700 Galley Rd",
    "sg:city":"Colorado Springs",
    "sg:classifiers":[
        {
            "category":"Social Services",
            "type":"Services"
        }
    ],
    "sg:phone":"+1 719 591 2609",
    "sg:postcode":"80909",
    "sg:province":"CO",
    "sg:tags":[
        "clinic",
        "individual",
        "specialty",
        "family",
        "outpatient"
    ],
    "wof:name":"Colorado Springs Pregnancy Ctr",
    "wof:placetype":"venue"
},
  "geometry": {"coordinates":[-104.759381,38.847065],"type":"Point"}
}