{
  "type": "Feature",
  "properties": {
    "addr:full":"871 Cooley Mesa Rd Gypsum CO 81637",
    "addr:housenumber":"871",
    "addr:postcode":"81637",
    "addr:street":"Cooley Mesa Rd",
    "iso:country":"US",
    "sg:address":"871 Cooley Mesa Rd",
    "sg:city":"Gypsum",
    "sg:classifiers":[
        {
            "category":"Government",
            "subcategory":"Office",
            "type":"Public Place"
        }
    ],
    "sg:phone":"+1 970 524 0490",
    "sg:postcode":"81637",
    "sg:province":"CO",
    "sg:tags":[
        "policy"
    ],
    "wof:name":"User Fee Airport-Eagle Co",
    "wof:placetype":"venue"
},
  "geometry": {"coordinates":[-106.932715,39.638269],"type":"Point"}
}