{
  "type": "Feature",
  "properties": {
    "iso:country":"US",
    "sg:address":"102 Rock Bridge Ct",
    "sg:city":"Windsor",
    "sg:classifiers":[
        {
            "category":"Shopping",
            "subcategory":"Optical Goods",
            "type":"Retail Goods"
        }
    ],
    "sg:phone":"+1 970 674 9741",
    "sg:postcode":"80550",
    "sg:province":"CO",
    "wof:name":"Vista Optical 7800 Greenl",
    "wof:placetype":"venue"
},
  "geometry": {"coordinates":[-104.894487,40.461176],"type":"Point"}
}