{
  "type": "Feature",
  "properties": {
    "addr:full":"201 S 5th St Lamar CO 81052",
    "addr:housenumber":"201",
    "addr:postcode":"81052",
    "addr:street":"S 5Th St",
    "iso:country":"US",
    "sg:address":"201 S 5th St",
    "sg:city":"Lamar",
    "sg:classifiers":[
        {
            "category":"Banks & Credit Unions",
            "subcategory":"Bank",
            "type":"Services"
        }
    ],
    "sg:phone":"+1 719 336 7474",
    "sg:postcode":"81052",
    "sg:province":"CO",
    "sg:tags":[
        "loan"
    ],
    "wof:name":"Farm Credit",
    "wof:placetype":"venue"
},
  "geometry": {"coordinates":[-102.620565,38.088153],"type":"Point"}
}