{
  "type": "Feature",
  "properties": {
    "addr:full":"992 S Peoria St Aurora CO 80012",
    "addr:housenumber":"992",
    "addr:postcode":"80012",
    "addr:street":"S Peoria St",
    "iso:country":"US",
    "sg:address":"992 S Peoria St",
    "sg:city":"Aurora",
    "sg:classifiers":[
        {
            "category":"Retail",
            "subcategory":"Laundry & Dry Cleaning",
            "type":"Services"
        }
    ],
    "sg:phone":"+1 303 340 4039",
    "sg:postcode":"80012",
    "sg:province":"CO",
    "sg:tags":[
        "cleaners"
    ],
    "wof:name":"New Look Cleaners",
    "wof:placetype":"venue"
},
  "geometry": {"coordinates":[-104.84709599999999,39.699814],"type":"Point"}
}