{
  "type": "Feature",
  "properties": {
    "iso:country":"US",
    "sg:address":"1730 Gaylord St",
    "sg:city":"Denver",
    "sg:classifiers":[
        {
            "category":"Professional",
            "type":"Services"
        },
        {
            "category":"Professional",
            "subcategory":"Lawyer & Legal Services",
            "type":"Services"
        }
    ],
    "sg:phone":"+1 303 733 1088",
    "sg:postcode":"80206",
    "sg:province":"CO",
    "sg:tags":[
        "attorney"
    ],
    "sg:website":"www.martinstclair.com",
    "wof:name":"Martin & St Clair Attourneys",
    "wof:placetype":"venue"
},
  "geometry": {"coordinates":[-104.960927,39.744316],"type":"Point"}
}