{
  "type": "Feature",
  "properties": {
    "iso:country":"US",
    "sg:address":"4801 W Colfax Ave",
    "sg:city":"Denver",
    "sg:classifiers":[
        {
            "category":"Retail",
            "subcategory":"Car Wash",
            "type":"Services"
        }
    ],
    "sg:phone":"+1 303 534 8993",
    "sg:postcode":"80204",
    "sg:province":"CO",
    "sg:tags":[
        "automobile",
        "detail",
        "clean"
    ],
    "wof:name":"Amys Fine Auto Detail",
    "wof:placetype":"venue"
},
  "geometry": {"coordinates":[-105.049813,39.740349],"type":"Point"}
}