{
  "type": "Feature",
  "properties": {
    "iso:country":"US",
    "sg:address":"363 S Oneida Way",
    "sg:city":"Denver",
    "sg:classifiers":[
        {
            "category":"Building & Trades",
            "subcategory":"Plumbing",
            "type":"Services"
        }
    ],
    "sg:phone":"+1 303 388 1550",
    "sg:postcode":"80224",
    "sg:province":"CO",
    "sg:tags":[
        "repair",
        "electrical",
        "contractor"
    ],
    "wof:name":"Jay Kay Associates",
    "wof:placetype":"venue"
},
  "geometry": {"coordinates":[-104.90769400000001,39.708699],"type":"Point"}
}