{
  "type": "Feature",
  "properties": {
    "iso:country":"US",
    "sg:address":"5380 Federal Boulevard",
    "sg:city":"Denver",
    "sg:classifiers":[
        {
            "category":"Autos & Motor Vehicles",
            "subcategory":"Auto Supplies",
            "type":"Retail Goods"
        }
    ],
    "sg:phone":"+1 303 561 3609",
    "sg:postcode":"80221",
    "sg:province":"CO",
    "sg:tags":[
        "tire"
    ],
    "wof:name":"Adams County Custom Wheels",
    "wof:placetype":"venue"
},
  "geometry": {"coordinates":[-105.02499,39.794447],"type":"Point"}
}