{
  "type": "Feature",
  "properties": {
    "addr:full":"1635 Co Rd 302 Parachute CO 81635",
    "addr:housenumber":"1635",
    "addr:postcode":"302;81635",
    "addr:street":"Co Rd",
    "iso:country":"US",
    "sg:address":"1635 Co Rd 302",
    "sg:city":"Parachute",
    "sg:classifiers":[
        {
            "category":"Banks & Credit Unions",
            "subcategory":"Financial Services",
            "type":"Services"
        }
    ],
    "sg:phone":"+1 970 285 9783",
    "sg:postcode":"81635",
    "sg:province":"CO",
    "sg:tags":[
        "company",
        "holding"
    ],
    "wof:name":"Mithril Enterprises",
    "wof:placetype":"venue"
},
  "geometry": {"coordinates":[-108.001249,39.437765],"type":"Point"}
}