{
  "type": "Feature",
  "properties": {
    "iso:country":"US",
    "sg:address":"449 S 3rd St",
    "sg:city":"Montrose",
    "sg:classifiers":[
        {
            "category":"Wholesale",
            "subcategory":"Construction Materials",
            "type":"Manufacturing & Wholesale Goods"
        }
    ],
    "sg:phone":"+1 970 249 5133",
    "sg:postcode":"81401",
    "sg:province":"CO",
    "wof:name":"Real Log Homes",
    "wof:placetype":"venue"
},
  "geometry": {"coordinates":[-107.87352199999999,38.477609],"type":"Point"}
}