{
  "type": "Feature",
  "properties": {
    "addr:full":"5374 Desert Mountain Ct Boulder CO 80301",
    "addr:housenumber":"5374",
    "addr:postcode":"80301",
    "addr:street":"Desert Mountain Ct",
    "iso:country":"US",
    "sg:address":"5374 Desert Mountain Ct",
    "sg:city":"Boulder",
    "sg:classifiers":[
        {
            "category":"Professional",
            "subcategory":"Management & Consulting",
            "type":"Services"
        }
    ],
    "sg:phone":"+1 303 581 9700",
    "sg:postcode":"80301",
    "sg:province":"CO",
    "sg:tags":[
        "consultant",
        "business"
    ],
    "wof:name":"Worldwide Consulting LLC",
    "wof:placetype":"venue"
},
  "geometry": {"coordinates":[-105.179456,40.072412],"type":"Point"}
}