{
  "type": "Feature",
  "properties": {
    "iso:country":"US",
    "sg:address":"1292 Main St",
    "sg:city":"Windsor",
    "sg:classifiers":[
        {
            "category":"Health Services",
            "subcategory":"Optometrist",
            "type":"Services"
        }
    ],
    "sg:phone":"+1 970 686 6066",
    "sg:postcode":"80550",
    "sg:province":"CO",
    "wof:name":"Vision Revision",
    "wof:placetype":"venue"
},
  "geometry": {"coordinates":[-104.920467,40.479627],"type":"Point"}
}