{
  "type": "Feature",
  "properties": {
    "addr:full":"440 Strathmore Ln Lafayette CO 80026",
    "addr:housenumber":"440",
    "addr:postcode":"80026",
    "addr:street":"Strathmore Ln",
    "iso:country":"US",
    "sg:address":"440 Strathmore Ln",
    "sg:city":"Lafayette",
    "sg:classifiers":[
        {
            "category":"Real Estate",
            "subcategory":"Real Estate Operator",
            "type":"Services"
        }
    ],
    "sg:phone":"+1 303 665 7779",
    "sg:postcode":"80026",
    "sg:province":"CO",
    "sg:tags":[
        "apartment",
        "complex"
    ],
    "wof:name":"Strathmore Park APT Homes LLC",
    "wof:placetype":"venue"
},
  "geometry": {"coordinates":[-105.086872,39.989334],"type":"Point"}
}