{
  "type": "Feature",
  "properties": {
    "iso:country":"US",
    "sg:address":"124 S el Paso St",
    "sg:city":"Colorado Springs",
    "sg:classifiers":[
        {
            "category":"Retail",
            "subcategory":"Auto Repair",
            "type":"Services"
        }
    ],
    "sg:phone":"+1 719 473 9490",
    "sg:postcode":"80903",
    "sg:province":"CO",
    "sg:tags":[
        "wheel",
        "axle",
        "alignment"
    ],
    "wof:name":"Newbill's Alignment Svc Inc",
    "wof:placetype":"venue"
},
  "geometry": {"coordinates":[-104.81317300000001,38.831821],"type":"Point"}
}