{
  "type": "Feature",
  "properties": {
    "addr:full":"6545 Athletic Ave Colorado Springs CO 80911",
    "addr:housenumber":"6545",
    "addr:postcode":"80911",
    "addr:street":"Athletic Ave",
    "iso:country":"US",
    "sg:address":"6545 Athletic Ave",
    "sg:city":"Colorado Springs",
    "sg:classifiers":[
        {
            "category":"Building & Trades",
            "subcategory":"Construction",
            "type":"Services"
        }
    ],
    "sg:phone":"+1 719 390 0937",
    "sg:postcode":"80911",
    "sg:province":"CO",
    "sg:tags":[
        "hauling",
        "dirt"
    ],
    "wof:name":"Ghl Trucking",
    "wof:placetype":"venue"
},
  "geometry": {"coordinates":[-104.705671,38.724537],"type":"Point"}
}