{
  "type": "Feature",
  "properties": {
    "addr:full":"1201 Kings Crown Rd Woodland Park CO 80863",
    "addr:housenumber":"1201",
    "addr:postcode":"80863",
    "addr:street":"Kings Crown Rd",
    "iso:country":"US",
    "sg:address":"1201 Kings Crown Rd",
    "sg:city":"Woodland Park",
    "sg:classifiers":[
        {
            "category":"Shopping",
            "subcategory":"Clothing, Apparel, & Fashions",
            "type":"Retail Goods"
        }
    ],
    "sg:phone":"+1 719 687 1132",
    "sg:postcode":"80863",
    "sg:province":"CO",
    "sg:tags":[
        "family"
    ],
    "wof:name":"Maxx LLC",
    "wof:placetype":"venue"
},
  "geometry": {"coordinates":[-105.032346,38.985432],"type":"Point"}
}