{
  "type": "Feature",
  "properties": {
    "iso:country":"US",
    "sg:address":"674 Santa Fe Dr",
    "sg:city":"Denver",
    "sg:classifiers":[
        {
            "category":"Personal",
            "subcategory":"Tattoo Parlor",
            "type":"Services"
        }
    ],
    "sg:phone":"+1 720 904 8904",
    "sg:postcode":"80204",
    "sg:province":"CO",
    "sg:website":"tribetattoo.com",
    "wof:name":"Tribe Tattoo",
    "wof:placetype":"venue"
},
  "geometry": {"coordinates":[-104.998285,39.727031],"type":"Point"}
}