{
  "type": "Feature",
  "properties": {
    "iso:country":"US",
    "sg:address":"299 Detroit St Studio 104",
    "sg:city":"Denver",
    "sg:classifiers":[
        {
            "category":"Personal",
            "subcategory":"Beauty Salon",
            "type":"Services"
        },
        {
            "category":"Personal",
            "subcategory":"Hair Removal",
            "type":"Services"
        }
    ],
    "sg:phone":"+1 720 937 0918",
    "sg:postcode":"80206",
    "sg:province":"CO",
    "sg:website":"www.lhshoppe.com",
    "wof:name":"Little Hair Shoppe",
    "wof:placetype":"venue"
},
  "geometry": {"coordinates":[-104.95464699999999,39.720972],"type":"Point"}
}