{
  "type": "Feature",
  "properties": {
    "addr:full":"1520 Virginia St Idaho Springs CO 80452",
    "addr:housenumber":"1520",
    "addr:postcode":"80452",
    "addr:street":"Virginia St",
    "iso:country":"US",
    "sg:address":"1520 Virginia St",
    "sg:city":"Idaho Springs",
    "sg:classifiers":[
        {
            "category":"Shopping",
            "subcategory":"Catalog Store",
            "type":"Retail Goods"
        }
    ],
    "sg:phone":"+1 303 567 1749",
    "sg:postcode":"80452",
    "sg:province":"CO",
    "sg:tags":[
        "mail",
        "house"
    ],
    "wof:name":"A Period Interior",
    "wof:placetype":"venue"
},
  "geometry": {"coordinates":[-105.516964,39.743268],"type":"Point"}
}