{
  "type": "Feature",
  "properties": {
    "addr:full":"6941 N Hillridge Pl Parker CO 80134",
    "addr:housenumber":"6941",
    "addr:postcode":"80134",
    "addr:street":"N Hillridge Pl",
    "iso:country":"US",
    "sg:address":"6941 N Hillridge Pl",
    "sg:city":"Parker",
    "sg:classifiers":[
        {
            "category":"Real Estate",
            "subcategory":"Real Estate Operator",
            "type":"Services"
        }
    ],
    "sg:phone":"+1 303 841 6347",
    "sg:postcode":"80134",
    "sg:province":"CO",
    "sg:tags":[
        "condominium"
    ],
    "wof:name":"R & E Lodging",
    "wof:placetype":"venue"
},
  "geometry": {"coordinates":[-104.73697,39.462755],"type":"Point"}
}