{
  "type": "Feature",
  "properties": {
    "addr:full":"7200 E Dry Creek Rd Englewood CO 80112",
    "addr:housenumber":"7200",
    "addr:postcode":"80112",
    "addr:street":"E Dry Creek Rd",
    "iso:country":"US",
    "sg:address":"7200 E Dry Creek Rd",
    "sg:city":"Englewood",
    "sg:classifiers":[
        {
            "category":"Insurance",
            "subcategory":"Insurance Agent",
            "type":"Services"
        }
    ],
    "sg:phone":"+1 303 721 9889",
    "sg:postcode":"80112",
    "sg:province":"CO",
    "wof:name":"Allstate",
    "wof:placetype":"venue"
},
  "geometry": {"coordinates":[-104.904267,39.580525],"type":"Point"}
}