{
  "type": "Feature",
  "properties": {
    "iso:country":"US",
    "sg:address":"1555 Clarkson St",
    "sg:city":"Denver",
    "sg:classifiers":[
        {
            "category":"Professional",
            "type":"Services"
        }
    ],
    "sg:phone":"+1 303 837 8738",
    "sg:postcode":"80218",
    "sg:province":"CO",
    "sg:tags":[
        "establishment"
    ],
    "wof:name":"Redwood Toxicology Inc",
    "wof:placetype":"venue"
},
  "geometry": {"coordinates":[-104.977557,39.741665],"type":"Point"}
}