{
  "type": "Feature",
  "properties": {
    "addr:full":"507 Dodge St Delta CO 81416",
    "addr:housenumber":"507",
    "addr:postcode":"81416",
    "addr:street":"Dodge St",
    "iso:country":"US",
    "sg:address":"507 Dodge St",
    "sg:city":"Delta",
    "sg:classifiers":[
        {
            "category":"Health Services",
            "subcategory":"Doctor",
            "type":"Services"
        }
    ],
    "sg:phone":"+1 970 874 8051",
    "sg:postcode":"81416",
    "sg:province":"CO",
    "sg:tags":[
        "dentist"
    ],
    "wof:name":"Delta County Orthodontics",
    "wof:placetype":"venue"
},
  "geometry": {"coordinates":[-108.07362000000001,38.74025],"type":"Point"}
}