{
  "type": "Feature",
  "properties": {
    "addr:full":"8420 de Soto Dr Denver CO 80229",
    "addr:housenumber":"8420",
    "addr:postcode":"80229",
    "addr:street":"De Soto Dr",
    "iso:country":"US",
    "sg:address":"8420 de Soto Dr",
    "sg:city":"Denver",
    "sg:classifiers":[
        {
            "category":"Building & Trades",
            "subcategory":"Construction",
            "type":"Services"
        }
    ],
    "sg:phone":"+1 303 287 3979",
    "sg:postcode":"80229",
    "sg:province":"CO",
    "sg:tags":[
        "contractor"
    ],
    "wof:name":"Champion Drywall Services Inc",
    "wof:placetype":"venue"
},
  "geometry": {"coordinates":[-104.973917,39.850401],"type":"Point"}
}