{
  "type": "Feature",
  "properties": {
    "addr:full":"12050 E 45th Ave Denver CO 80239",
    "addr:housenumber":"12050",
    "addr:postcode":"80239",
    "addr:street":"E 45Th Ave",
    "iso:country":"US",
    "sg:address":"12050 E 45th Ave",
    "sg:city":"Denver",
    "sg:classifiers":[
        {
            "category":"Manufacturing",
            "subcategory":"Chemicals & Compounds",
            "type":"Manufacturing & Wholesale Goods"
        }
    ],
    "sg:phone":"+1 303 660 8615",
    "sg:postcode":"80239",
    "sg:province":"CO",
    "sg:tags":[
        "adhesive",
        "sealant"
    ],
    "wof:name":"Ellsworth Adhesive Systems",
    "wof:placetype":"venue"
},
  "geometry": {"coordinates":[-104.84864399999999,39.777959],"type":"Point"}
}