{
  "type": "Feature",
  "properties": {
    "iso:country":"US",
    "sg:address":"18101 E Vassar Pl",
    "sg:city":"Aurora",
    "sg:classifiers":[
        {
            "category":"Education",
            "subcategory":"School",
            "type":"Public Place"
        }
    ],
    "sg:phone":"+1 303 752 3772",
    "sg:postcode":"80013",
    "sg:province":"CO",
    "sg:website":"www.aps.k12.co.us/vassar",
    "wof:name":"Vassar Elementary School",
    "wof:placetype":"venue"
},
  "geometry": {"coordinates":[-104.776645,39.669281],"type":"Point"}
}