{
  "type": "Feature",
  "properties": {
    "iso:country":"US",
    "sg:address":"6391 S Hudson St",
    "sg:city":"Littleton",
    "sg:classifiers":[
        {
            "category":"Real Estate",
            "subcategory":"Real Estate Agent",
            "type":"Services"
        }
    ],
    "sg:phone":"+1 303 770 3834",
    "sg:postcode":"80121",
    "sg:province":"CO",
    "wof:name":"Services In Colorado Appraisal",
    "wof:placetype":"venue"
},
  "geometry": {"coordinates":[-104.92371199999999,39.600548],"type":"Point"}
}