{
  "type": "Feature",
  "properties": {
    "addr:full":"15934 W 67th Pl Arvada CO 80007",
    "addr:housenumber":"15934",
    "addr:postcode":"80007",
    "addr:street":"W 67Th Pl",
    "iso:country":"US",
    "sg:address":"15934 W 67th Pl",
    "sg:city":"Arvada",
    "sg:classifiers":[
        {
            "category":"Manufacturing",
            "subcategory":"Printing",
            "type":"Manufacturing & Wholesale Goods"
        }
    ],
    "sg:phone":"+1 303 420 5380",
    "sg:postcode":"80007",
    "sg:province":"CO",
    "sg:tags":[
        "publishing"
    ],
    "wof:name":"Eric Lee Wade Smith",
    "wof:placetype":"venue"
},
  "geometry": {"coordinates":[-105.17663,39.819236],"type":"Point"}
}