{
  "type": "Feature",
  "properties": {
    "addr:full":"808 Roadrunner Ct Loveland CO 80537",
    "addr:housenumber":"808",
    "addr:postcode":"80537",
    "addr:street":"Roadrunner Ct",
    "iso:country":"US",
    "sg:address":"808 Roadrunner Ct",
    "sg:city":"Loveland",
    "sg:classifiers":[
        {
            "category":"Recreation",
            "type":"Entertainment"
        }
    ],
    "sg:phone":"+1 970 679 2525",
    "sg:postcode":"80537",
    "sg:province":"CO",
    "wof:name":"Gymkats Booster Club",
    "wof:placetype":"venue"
},
  "geometry": {"coordinates":[-105.013311,40.384373],"type":"Point"}
}