{
  "type": "Feature",
  "properties": {
    "iso:country":"US",
    "sg:address":"7373 W Jefferson Ave #102",
    "sg:city":"Lakewood",
    "sg:classifiers":[
        {
            "category":"Health Services",
            "subcategory":"Doctor",
            "type":"Services"
        }
    ],
    "sg:phone":"+1 303 988 5252",
    "sg:postcode":"80235",
    "sg:province":"CO",
    "sg:tags":[
        "physician",
        "pediatrics",
        "family",
        "practice",
        "surgeons",
        "medicine"
    ],
    "wof:name":"Academy Park Pediatrics PC",
    "wof:placetype":"venue"
},
  "geometry": {"coordinates":[-105.078502,39.649979],"type":"Point"}
}