{
  "type": "Feature",
  "properties": {
    "addr:full":"20450 Beacon Lite Rd Monument CO 80132",
    "addr:housenumber":"20450",
    "addr:postcode":"80132",
    "addr:street":"Beacon Lite Rd",
    "iso:country":"US",
    "sg:address":"20450 Beacon Lite Rd",
    "sg:city":"Monument",
    "sg:classifiers":[
        {
            "category":"Organizations",
            "subcategory":"Religious Organization",
            "type":"Services"
        }
    ],
    "sg:phone":"+1 719 488 9613",
    "sg:postcode":"80132",
    "sg:province":"CO",
    "sg:tags":[
        "church"
    ],
    "wof:name":"Tri-Lakes Church Of Christ",
    "wof:placetype":"venue"
},
  "geometry": {"coordinates":[-104.86776999999999,39.128305],"type":"Point"}
}