{
  "type": "Feature",
  "properties": {
    "addr:full":"4880 Quentin St Denver CO 80239",
    "addr:housenumber":"4880",
    "addr:postcode":"80239",
    "addr:street":"Quentin St",
    "iso:country":"US",
    "sg:address":"4880 Quentin St",
    "sg:city":"Denver",
    "sg:classifiers":[
        {
            "category":"Personal",
            "subcategory":"Adult",
            "type":"Services"
        }
    ],
    "sg:phone":"+1 303 574 1953",
    "sg:postcode":"80239",
    "sg:province":"CO",
    "sg:tags":[
        "escort"
    ],
    "wof:name":"Supreme Entertainment",
    "wof:placetype":"venue"
},
  "geometry": {"coordinates":[-104.844885,39.785729],"type":"Point"}
}