{
  "type": "Feature",
  "properties": {
    "addr:full":"475 Main St Longmont CO 80501",
    "addr:housenumber":"475",
    "addr:postcode":"80501",
    "addr:street":"Main St",
    "iso:country":"US",
    "sg:address":"475 Main St",
    "sg:city":"Longmont",
    "sg:classifiers":[
        {
            "category":"Restaurant",
            "type":"Food & Drink"
        }
    ],
    "sg:phone":"+1 720 652 0966",
    "sg:postcode":"80501",
    "sg:province":"CO",
    "wof:name":"August Morning",
    "wof:placetype":"venue"
},
  "geometry": {"coordinates":[-105.102586,40.166131],"type":"Point"}
}