{
  "type": "Feature",
  "properties": {
    "addr:full":"7606 N Union Blvd Colorado Springs CO 80920",
    "addr:housenumber":"7606",
    "addr:postcode":"80920",
    "addr:street":"N Union Blvd",
    "iso:country":"US",
    "sg:address":"7606 N Union Blvd",
    "sg:city":"Colorado Springs",
    "sg:classifiers":[
        {
            "category":"Health Services",
            "subcategory":"Doctor",
            "type":"Services"
        }
    ],
    "sg:phone":"+1 719 535 9990",
    "sg:postcode":"80920",
    "sg:province":"CO",
    "sg:tags":[
        "physician",
        "surgeon"
    ],
    "wof:name":"Institute Of Plastic Surgery",
    "wof:placetype":"venue"
},
  "geometry": {"coordinates":[-104.774292,38.944097],"type":"Point"}
}