{
  "type": "Feature",
  "properties": {
    "addr:full":"511 N 30th St Colorado Springs CO 80904",
    "addr:housenumber":"511",
    "addr:postcode":"80904",
    "addr:street":"N 30Th St",
    "iso:country":"US",
    "sg:address":"511 N 30th St",
    "sg:city":"Colorado Springs",
    "sg:classifiers":[
        {
            "category":"Restaurant",
            "type":"Food & Drink"
        }
    ],
    "sg:phone":"+1 719 578 2968",
    "sg:postcode":"80904",
    "sg:province":"CO",
    "sg:tags":[
        "eating"
    ],
    "wof:name":"Texas Tamales",
    "wof:placetype":"venue"
},
  "geometry": {"coordinates":[-104.86509700000001,38.856682],"type":"Point"}
}