{
  "type": "Feature",
  "properties": {
    "iso:country":"US",
    "sg:address":"5801 W 44th Ave Suite A-104",
    "sg:city":"Denver",
    "sg:classifiers":[
        {
            "category":"Shopping",
            "subcategory":"Clothing, Apparel, & Fashions",
            "type":"Retail Goods"
        }
    ],
    "sg:phone":"+1 303 477 0078",
    "sg:postcode":"80212",
    "sg:province":"CO",
    "sg:tags":[
        "clothing",
        "store"
    ],
    "wof:name":"El Pueblito",
    "wof:placetype":"venue"
},
  "geometry": {"coordinates":[-105.060181,39.776588],"type":"Point"}
}