{
  "type": "Feature",
  "properties": {
    "iso:country":"US",
    "sg:address":"1950 S Corona St",
    "sg:city":"Denver",
    "sg:classifiers":[
        {
            "category":"Professional",
            "type":"Services"
        }
    ],
    "sg:phone":"+1 303 777 3451",
    "sg:postcode":"80210",
    "sg:province":"CO",
    "wof:name":"Brian Omohundro",
    "wof:placetype":"venue"
},
  "geometry": {"coordinates":[-104.97449400000001,39.681268],"type":"Point"}
}