{
  "type": "Feature",
  "properties": {
    "iso:country":"US",
    "sg:address":"273 Wayward Wind Rd",
    "sg:city":"Divide",
    "sg:classifiers":[
        {
            "category":"Building & Trades",
            "subcategory":"Construction",
            "type":"Services"
        }
    ],
    "sg:phone":"+1 719 687 7823",
    "sg:postcode":"80814",
    "sg:province":"CO",
    "sg:tags":[
        "house"
    ],
    "wof:name":"Black Hawk Trades",
    "wof:placetype":"venue"
},
  "geometry": {"coordinates":[-105.203998,38.969311],"type":"Point"}
}