{
  "type": "Feature",
  "properties": {
    "iso:country":"US",
    "sg:address":"675 State Hwy 115",
    "sg:city":"Penrose",
    "sg:classifiers":[
        {
            "category":"Restaurant",
            "type":"Food & Drink"
        }
    ],
    "sg:phone":"+1 719 372 3012",
    "sg:postcode":"81240",
    "sg:province":"CO",
    "wof:name":"Coyote's Coffee Den",
    "wof:placetype":"venue"
},
  "geometry": {"coordinates":[-105.024027,38.433092],"type":"Point"}
}