{
  "type": "Feature",
  "properties": {
    "iso:country":"US",
    "sg:address":"8540 E 160th Ave",
    "sg:city":"Brighton",
    "sg:classifiers":[
        {
            "category":"Professional",
            "type":"Services"
        }
    ],
    "sg:phone":"+1 303 654 0679",
    "sg:postcode":"80602",
    "sg:province":"CO",
    "wof:name":"J Carroll Brumley Ltd Partnr",
    "wof:placetype":"venue"
},
  "geometry": {"coordinates":[-104.89709000000001,39.98661],"type":"Point"}
}