{
  "type": "Feature",
  "properties": {
    "iso:country":"US",
    "sg:address":"8886 Washington St",
    "sg:city":"Denver",
    "sg:classifiers":[
        {
            "category":"Restaurant",
            "type":"Food & Drink"
        }
    ],
    "sg:phone":"+1 303 287 6875",
    "sg:postcode":"80229",
    "sg:province":"CO",
    "sg:tags":[
        "cafe"
    ],
    "wof:name":"Thornton Cafe",
    "wof:placetype":"venue"
},
  "geometry": {"coordinates":[-104.977729,39.85868],"type":"Point"}
}