{
  "type": "Feature",
  "properties": {
    "iso:country":"US",
    "sg:address":"724 S Pearl St",
    "sg:city":"Denver",
    "sg:classifiers":[
        {
            "category":"Building & Trades",
            "subcategory":"Locksmith",
            "type":"Services"
        }
    ],
    "sg:phone":"+1 303 218 6555",
    "sg:postcode":"80209",
    "sg:province":"CO",
    "sg:tags":[
        "key"
    ],
    "wof:name":"Dcc Locksmith",
    "wof:placetype":"venue"
},
  "geometry": {"coordinates":[-104.980255,39.703482],"type":"Point"}
}