{
  "type": "Feature",
  "properties": {
    "addr:full":"1201 S Parker Rd Denver CO 80231",
    "addr:housenumber":"1201",
    "addr:postcode":"80231",
    "addr:street":"S Parker Rd",
    "iso:country":"US",
    "sg:address":"1201 S Parker Rd",
    "sg:city":"Denver",
    "sg:classifiers":[
        {
            "category":"Wholesale",
            "subcategory":"Motor Vehicles",
            "type":"Manufacturing & Wholesale Goods"
        }
    ],
    "sg:phone":"+1 303 751 1918",
    "sg:postcode":"80231",
    "sg:province":"CO",
    "sg:tags":[
        "automobile",
        "truck",
        "broker"
    ],
    "wof:name":"Woods & Assoc-Dealer",
    "wof:placetype":"venue"
},
  "geometry": {"coordinates":[-104.89664399999999,39.695822],"type":"Point"}
}