{
  "type": "Feature",
  "properties": {
    "iso:country":"US",
    "sg:address":"3000 E 1st Ave",
    "sg:city":"Denver",
    "sg:classifiers":[
        {
            "category":"Restaurant",
            "type":"Food & Drink"
        }
    ],
    "sg:phone":"+1 303 388 3604",
    "sg:postcode":"80206",
    "sg:province":"CO",
    "sg:tags":[
        "pizza"
    ],
    "sg:website":"www.sbarro.com",
    "wof:name":"Sbarro",
    "wof:placetype":"venue"
},
  "geometry": {"coordinates":[-104.953258,39.718043],"type":"Point"}
}