{
  "type": "Feature",
  "properties": {
    "addr:full":"32141 S Railway St Wray CO 80758",
    "addr:housenumber":"32141",
    "addr:postcode":"80758",
    "addr:street":"S Railway St",
    "iso:country":"US",
    "sg:address":"32141 S Railway St",
    "sg:city":"Wray",
    "sg:classifiers":[
        {
            "category":"Retail",
            "subcategory":"Auto Repair",
            "type":"Services"
        }
    ],
    "sg:phone":"+1 970 332 4650",
    "sg:postcode":"80758",
    "sg:province":"CO",
    "sg:tags":[
        "repairing",
        "automobile"
    ],
    "wof:name":"Evereadys Auto Ctr",
    "wof:placetype":"venue"
},
  "geometry": {"coordinates":[-102.209005,40.082646],"type":"Point"}
}