{
  "type": "Feature",
  "properties": {
    "iso:country":"US",
    "sg:address":"1410 N Jefferson Ave",
    "sg:city":"Loveland",
    "sg:classifiers":[
        {
            "category":"Wholesale",
            "subcategory":"Auto Parts",
            "type":"Manufacturing & Wholesale Goods"
        }
    ],
    "sg:phone":"+1 970 669 5714",
    "sg:postcode":"80538",
    "sg:province":"CO",
    "sg:tags":[
        "body",
        "shop",
        "automobile"
    ],
    "wof:name":"Ed's Auto Paint & Supply Inc",
    "wof:placetype":"venue"
},
  "geometry": {"coordinates":[-105.071657,40.408941],"type":"Point"}
}