{
  "type": "Feature",
  "properties": {
    "iso:country":"US",
    "sg:address":"2717 E Louisiana Ave",
    "sg:city":"Denver",
    "sg:classifiers":[
        {
            "category":"Building & Trades",
            "subcategory":"Construction",
            "type":"Services"
        }
    ],
    "sg:phone":"+1 720 353 4317",
    "sg:postcode":"80210",
    "sg:province":"CO",
    "sg:tags":[
        "contractor"
    ],
    "wof:name":"Timberleaf Construction",
    "wof:placetype":"venue"
},
  "geometry": {"coordinates":[-104.954575,39.693086],"type":"Point"}
}