{
  "type": "Feature",
  "properties": {
    "iso:country":"US",
    "sg:address":"32940 Co Rd 5",
    "sg:city":"Fowler",
    "sg:classifiers":[
        {
            "category":"Farming",
            "subcategory":"Farm",
            "type":"Manufacturing & Wholesale Goods"
        }
    ],
    "sg:phone":"+1 719 263 5635",
    "sg:postcode":"81039",
    "sg:province":"CO",
    "sg:tags":[
        "crop",
        "general"
    ],
    "wof:name":"Blakes Farms",
    "wof:placetype":"venue"
},
  "geometry": {"coordinates":[-103.985883,38.111585],"type":"Point"}
}