{
  "type": "Feature",
  "properties": {
    "iso:country":"US",
    "sg:address":"10771 E Easter Ave",
    "sg:city":"Centennial",
    "sg:classifiers":[
        {
            "category":"Health Services",
            "subcategory":"Clinic",
            "type":"Services"
        }
    ],
    "sg:phone":"+1 303 770 5710",
    "sg:postcode":"80112",
    "sg:province":"CO",
    "wof:name":"Cnic Healthcare Solutions",
    "wof:placetype":"venue"
},
  "geometry": {"coordinates":[-104.86309799999999,39.587851],"type":"Point"}
}