{
  "type": "Feature",
  "properties": {
    "addr:full":"1001 Bannock St Denver CO 80204",
    "addr:housenumber":"1001",
    "addr:postcode":"80204",
    "addr:street":"Bannock St",
    "iso:country":"US",
    "sg:address":"1001 Bannock St",
    "sg:city":"Denver",
    "sg:classifiers":[
        {
            "category":"Shopping",
            "subcategory":"Computers & Home Electronics",
            "type":"Retail Goods"
        }
    ],
    "sg:phone":"+1 303 629 1312",
    "sg:postcode":"80204",
    "sg:province":"CO",
    "wof:name":"Fistell's Electronics Supply Co",
    "wof:placetype":"venue"
},
  "geometry": {"coordinates":[-104.989998,39.732601],"type":"Point"}
}