{
  "type": "Feature",
  "properties": {
    "iso:country":"US",
    "sg:address":"3030 E 2nd Avenue",
    "sg:city":"Denver",
    "sg:classifiers":[
        {
            "category":"Restaurant",
            "type":"Food & Drink"
        }
    ],
    "sg:phone":"+1 303 322 7827",
    "sg:postcode":"80206",
    "sg:province":"CO",
    "wof:name":"Quizno's Subs",
    "wof:placetype":"venue"
},
  "geometry": {"coordinates":[-104.951826,39.719372],"type":"Point"}
}