{
  "type": "Feature",
  "properties": {
    "addr:full":"4545 Austin Bluffs Pkwy Colorado Springs CO 80918",
    "addr:housenumber":"4545",
    "addr:postcode":"80918",
    "addr:street":"Austin Bluffs Pkwy",
    "iso:country":"US",
    "sg:address":"4545 Austin Bluffs Pkwy",
    "sg:city":"Colorado Springs",
    "sg:classifiers":[
        {
            "category":"Personal",
            "subcategory":"Beauty Salon",
            "type":"Services"
        }
    ],
    "sg:phone":"+1 719 596 7058",
    "sg:postcode":"80918",
    "sg:province":"CO",
    "wof:name":"Tanyeals Salon & Spa",
    "wof:placetype":"venue"
},
  "geometry": {"coordinates":[-104.746866,38.897752],"type":"Point"}
}