{
  "type": "Feature",
  "properties": {
    "iso:country":"US",
    "sg:address":"9545 Damon Dr",
    "sg:city":"Denver",
    "sg:classifiers":[
        {
            "category":"Building & Trades",
            "subcategory":"Construction",
            "type":"Services"
        }
    ],
    "sg:phone":"+1 303 429 7644",
    "sg:postcode":"80260",
    "sg:province":"CO",
    "sg:tags":[
        "contractor"
    ],
    "wof:name":"Woodconcerns",
    "wof:placetype":"venue"
},
  "geometry": {"coordinates":[-104.99133399999999,39.870994],"type":"Point"}
}