{
  "type": "Feature",
  "properties": {
    "iso:country":"US",
    "sg:address":"11815 W Pleasant Ave",
    "sg:city":"Golden",
    "sg:classifiers":[
        {
            "category":"Building & Trades",
            "subcategory":"Construction",
            "type":"Services"
        }
    ],
    "sg:phone":"+1 303 232 9110",
    "sg:postcode":"80401",
    "sg:province":"CO",
    "sg:tags":[
        "tile",
        "dealer",
        "contractor"
    ],
    "wof:name":"Floormaster Floor Covering Svc",
    "wof:placetype":"venue"
},
  "geometry": {"coordinates":[-105.130021,39.735434],"type":"Point"}
}