{
  "type": "Feature",
  "properties": {
    "iso:country":"US",
    "sg:address":"2880 Folsom St",
    "sg:city":"Boulder",
    "sg:classifiers":[
        {
            "category":"Shopping",
            "subcategory":"Pharmacy",
            "type":"Retail Goods"
        }
    ],
    "sg:phone":"+1 303 440 4200",
    "sg:postcode":"80304",
    "sg:province":"CO",
    "sg:tags":[
        "drug",
        "store"
    ],
    "wof:name":"Goose Creek Pharmacy Ltd",
    "wof:placetype":"venue"
},
  "geometry": {"coordinates":[-105.263049,40.028779],"type":"Point"}
}