{
  "type": "Feature",
  "properties": {
    "addr:full":"40 Stagecoach Trl Elizabeth CO 80107",
    "addr:housenumber":"40",
    "addr:postcode":"80107",
    "addr:street":"Stagecoach Trl",
    "iso:country":"US",
    "sg:address":"40 Stagecoach Trl",
    "sg:city":"Elizabeth",
    "sg:classifiers":[
        {
            "category":"Building & Trades",
            "subcategory":"Construction",
            "type":"Services"
        }
    ],
    "sg:phone":"+1 303 646 0703",
    "sg:postcode":"80107",
    "sg:province":"CO",
    "sg:tags":[
        "house"
    ],
    "wof:name":"Starlane Construction",
    "wof:placetype":"venue"
},
  "geometry": {"coordinates":[-104.66070499999999,39.411607],"type":"Point"}
}