{
  "type": "Feature",
  "properties": {
    "iso:country":"US",
    "sg:address":"2528 Ginny Way",
    "sg:city":"Lafayette",
    "sg:classifiers":[
        {
            "category":"Shopping",
            "subcategory":"Crafts & Fabrics",
            "type":"Retail Goods"
        }
    ],
    "sg:phone":"+1 303 604 0508",
    "sg:postcode":"80026",
    "sg:province":"CO",
    "sg:tags":[
        "sewing"
    ],
    "wof:name":"Everything Quilts Inc",
    "wof:placetype":"venue"
},
  "geometry": {"coordinates":[-105.12693,40.021275],"type":"Point"}
}