{
  "type": "Feature",
  "properties": {
    "addr:full":"9550 Co Rd Dd Idalia CO 80735",
    "addr:housenumber":"9550",
    "addr:postcode":"80735",
    "addr:street":"Co Rd",
    "iso:country":"US",
    "sg:address":"9550 Co Rd Dd",
    "sg:city":"Idalia",
    "sg:classifiers":[
        {
            "category":"Recreation",
            "type":"Entertainment"
        }
    ],
    "sg:phone":"+1 970 354 7356",
    "sg:postcode":"80735",
    "sg:province":"CO",
    "sg:tags":[
        "hall",
        "auditorium"
    ],
    "wof:name":"Homestead Hall",
    "wof:placetype":"venue"
},
  "geometry": {"coordinates":[-102.291911,39.712852],"type":"Point"}
}