{
  "type": "Feature",
  "properties": {
    "iso:country":"US",
    "sg:address":"5333 Red Rock Dr",
    "sg:city":"Larkspur",
    "sg:classifiers":[
        {
            "category":"Professional",
            "type":"Services"
        }
    ],
    "sg:phone":"+1 303 681 2763",
    "sg:postcode":"80118",
    "sg:province":"CO",
    "wof:name":"Final Resolution LLC",
    "wof:placetype":"venue"
},
  "geometry": {"coordinates":[-104.983414,39.249773],"type":"Point"}
}