{
  "type": "Feature",
  "properties": {
    "iso:country":"US",
    "sg:address":"7845 Montane Dr",
    "sg:city":"Colorado Springs",
    "sg:classifiers":[
        {
            "category":"Building & Trades",
            "subcategory":"Construction",
            "type":"Services"
        }
    ],
    "sg:phone":"+1 719 593 8519",
    "sg:postcode":"80920",
    "sg:province":"CO",
    "sg:tags":[
        "finishing",
        "wood",
        "painting",
        "contractor"
    ],
    "wof:name":"Liberty Custom Painting",
    "wof:placetype":"venue"
},
  "geometry": {"coordinates":[-104.75448,38.943472],"type":"Point"}
}