{
  "type": "Feature",
  "properties": {
    "addr:full":"411 E Camrose Pl Pueblo CO 81007",
    "addr:housenumber":"411",
    "addr:postcode":"81007",
    "addr:street":"E Camrose Pl",
    "iso:country":"US",
    "sg:address":"411 E Camrose Pl",
    "sg:city":"Pueblo",
    "sg:classifiers":[
        {
            "category":"Professional",
            "type":"Services"
        }
    ],
    "sg:phone":"+1 719 566 3652",
    "sg:postcode":"81007",
    "sg:province":"CO",
    "wof:name":"Adam C Tozer",
    "wof:placetype":"venue"
},
  "geometry": {"coordinates":[-104.72111,38.310196],"type":"Point"}
}