{
  "type": "Feature",
  "properties": {
    "addr:full":"8505 S Park Meadows Center Dr Lone Tree CO 80124",
    "addr:housenumber":"8505",
    "addr:postcode":"80124",
    "addr:street":"S Park Meadows Center Dr",
    "iso:country":"US",
    "sg:address":"8505 S Park Meadows Center Dr",
    "sg:city":"Lone Tree",
    "sg:classifiers":[
        {
            "category":"Shopping",
            "subcategory":"Shoes",
            "type":"Retail Goods"
        }
    ],
    "sg:phone":"+1 303 790 7105",
    "sg:postcode":"80124",
    "sg:province":"CO",
    "wof:name":"Easy Spirit Shoe Store",
    "wof:placetype":"venue"
},
  "geometry": {"coordinates":[-104.87267199999999,39.562196],"type":"Point"}
}