{
  "type": "Feature",
  "properties": {
    "addr:full":"7425 S Peoria St Englewood CO 80112",
    "addr:housenumber":"7425",
    "addr:postcode":"80112",
    "addr:street":"S Peoria St",
    "iso:country":"US",
    "sg:address":"7425 S Peoria St",
    "sg:city":"Englewood",
    "sg:classifiers":[
        {
            "category":"Travel",
            "subcategory":"Travel Agent",
            "type":"Entertainment"
        }
    ],
    "sg:phone":"+1 303 799 3852",
    "sg:postcode":"80112",
    "sg:province":"CO",
    "sg:tags":[
        "ticket",
        "agency",
        "airline"
    ],
    "wof:name":"Us West Flight Operations",
    "wof:placetype":"venue"
},
  "geometry": {"coordinates":[-104.84554300000001,39.581848],"type":"Point"}
}