{
  "type": "Feature",
  "properties": {
    "addr:full":"400 College Rd Lamar CO 81052",
    "addr:housenumber":"400",
    "addr:postcode":"81052",
    "addr:street":"College Rd",
    "iso:country":"US",
    "sg:address":"400 College Rd",
    "sg:city":"Lamar",
    "sg:classifiers":[
        {
            "category":"Real Estate",
            "subcategory":"Real Estate Operator",
            "type":"Services"
        }
    ],
    "sg:phone":"+1 719 336 4096",
    "sg:postcode":"81052",
    "sg:province":"CO",
    "sg:tags":[
        "apartment",
        "complex"
    ],
    "wof:name":"Normandy Gardens",
    "wof:placetype":"venue"
},
  "geometry": {"coordinates":[-102.61060000000001,38.056132],"type":"Point"}
}