{
  "type": "Feature",
  "properties": {
    "addr:full":"204 Park Ave Basalt CO 81621",
    "addr:housenumber":"204",
    "addr:postcode":"81621",
    "addr:street":"Park Ave",
    "iso:country":"US",
    "sg:address":"204 Park Ave",
    "sg:city":"Basalt",
    "sg:classifiers":[
        {
            "category":"Building & Trades",
            "subcategory":"Construction",
            "type":"Services"
        }
    ],
    "sg:phone":"+1 970 927 2228",
    "sg:postcode":"81621",
    "sg:province":"CO",
    "sg:tags":[
        "contractor"
    ],
    "wof:name":"All City Contracting Inc",
    "wof:placetype":"venue"
},
  "geometry": {"coordinates":[-107.08201200000001,39.374873],"type":"Point"}
}