{
  "type": "Feature",
  "properties": {
    "addr:full":"9760 S Hackberry St Littleton CO 80129",
    "addr:housenumber":"9760",
    "addr:postcode":"80129",
    "addr:street":"S Hackberry St",
    "iso:country":"US",
    "sg:address":"9760 S Hackberry St",
    "sg:city":"Littleton",
    "sg:classifiers":[
        {
            "category":"Organizations",
            "subcategory":"Religious Organization",
            "type":"Services"
        }
    ],
    "sg:phone":"+1 303 791 8791",
    "sg:postcode":"80129",
    "sg:province":"CO",
    "sg:tags":[
        "church"
    ],
    "wof:name":"Skyview Presbyterian",
    "wof:placetype":"venue"
},
  "geometry": {"coordinates":[-105.01916799999999,39.53883],"type":"Point"}
}