{
  "type": "Feature",
  "properties": {
    "addr:full":"36 Research Dr Pueblo West CO 81007",
    "addr:housenumber":"36",
    "addr:postcode":"81007",
    "addr:street":"Research Dr",
    "iso:country":"US",
    "sg:address":"36 Research Dr",
    "sg:city":"Pueblo West",
    "sg:classifiers":[
        {
            "category":"Wholesale",
            "subcategory":"Sporting Goods",
            "type":"Manufacturing & Wholesale Goods"
        },
        {
            "category":"Shopping",
            "subcategory":"Bicycles & Sporting Goods",
            "type":"Retail Goods"
        }
    ],
    "sg:phone":"+1 719 547 7110",
    "sg:postcode":"81007",
    "sg:province":"CO",
    "wof:name":"Quick Hit Inc",
    "wof:placetype":"venue"
},
  "geometry": {"coordinates":[-104.73457999999999,38.335684],"type":"Point"}
}