{
  "type": "Feature",
  "properties": {
    "iso:country":"US",
    "sg:address":"23808 Hwy 172",
    "sg:city":"Ignacio",
    "sg:classifiers":[
        {
            "category":"Farming",
            "subcategory":"Livestock Farm",
            "type":"Manufacturing & Wholesale Goods"
        }
    ],
    "sg:phone":"+1 970 563 9383",
    "sg:postcode":"81137",
    "sg:province":"CO",
    "sg:tags":[
        "llama"
    ],
    "wof:name":"LA Boca Llamas",
    "wof:placetype":"venue"
},
  "geometry": {"coordinates":[-107.604783,37.014362],"type":"Point"}
}