{
  "type": "Feature",
  "properties": {
    "addr:full":"900 Maine St Eads CO 81036",
    "addr:housenumber":"900",
    "addr:postcode":"81036",
    "addr:street":"Maine St",
    "iso:country":"US",
    "sg:address":"900 Maine St",
    "sg:city":"Eads",
    "sg:classifiers":[
        {
            "category":"Education",
            "subcategory":"School",
            "type":"Public Place"
        }
    ],
    "sg:phone":"+1 719 438 2216",
    "sg:postcode":"81036",
    "sg:province":"CO",
    "wof:name":"Eads Elementary",
    "wof:placetype":"venue"
},
  "geometry": {"coordinates":[-102.78166899999999,38.483979],"type":"Point"}
}