{
  "type": "Feature",
  "properties": {
    "addr:full":"203 1st St Ault CO 80610",
    "addr:housenumber":"203",
    "addr:postcode":"80610",
    "addr:street":"1St St",
    "iso:country":"US",
    "sg:address":"203 1st St",
    "sg:city":"Ault",
    "sg:classifiers":[
        {
            "category":"Government",
            "subcategory":"Police Station",
            "type":"Public Place"
        }
    ],
    "sg:phone":"+1 970 834 2852",
    "sg:postcode":"80610",
    "sg:province":"CO",
    "sg:tags":[
        "department"
    ],
    "wof:name":"Ault Town Police Dept",
    "wof:placetype":"venue"
},
  "geometry": {"coordinates":[-104.73169,40.58234],"type":"Point"}
}