{
  "type": "Feature",
  "properties": {
    "iso:country":"US",
    "sg:address":"634 Breeze St",
    "sg:city":"Craig",
    "sg:classifiers":[
        {
            "category":"Social Services",
            "subcategory":"Adult Care",
            "type":"Services"
        }
    ],
    "sg:phone":"+1 970 826 2828",
    "sg:postcode":"81625",
    "sg:province":"CO",
    "sg:tags":[
        "home",
        "residential"
    ],
    "wof:name":"Jewel",
    "wof:placetype":"venue"
},
  "geometry": {"coordinates":[-107.54852,40.51607],"type":"Point"}
}