{
  "type": "Feature",
  "properties": {
    "iso:country":"US",
    "sg:address":"7582 Dusk St",
    "sg:city":"Littleton",
    "sg:classifiers":[
        {
            "category":"Professional",
            "subcategory":"Computer Services",
            "type":"Services"
        }
    ],
    "sg:phone":"+1 303 979 4471",
    "sg:postcode":"80125",
    "sg:province":"CO",
    "sg:tags":[
        "internet"
    ],
    "wof:name":"Aleyard",
    "wof:placetype":"venue"
},
  "geometry": {"coordinates":[-105.077545,39.472595],"type":"Point"}
}