{
  "type": "Feature",
  "properties": {
    "addr:full":"2002 E Platte Ave Colorado Springs CO 80909",
    "addr:housenumber":"2002",
    "addr:postcode":"80909",
    "addr:street":"E Platte Ave",
    "iso:country":"US",
    "sg:address":"2002 E Platte Ave",
    "sg:city":"Colorado Springs",
    "sg:classifiers":[
        {
            "category":"Manufacturing",
            "subcategory":"Apparel",
            "type":"Manufacturing & Wholesale Goods"
        }
    ],
    "sg:phone":"+1 719 271 4723",
    "sg:postcode":"80909",
    "sg:province":"CO",
    "sg:tags":[
        "riding",
        "tack"
    ],
    "wof:name":"Z Tack Diamond Inc",
    "wof:placetype":"venue"
},
  "geometry": {"coordinates":[-104.79134999999999,38.837177],"type":"Point"}
}