{
  "type": "Feature",
  "properties": {
    "iso:country":"US",
    "sg:address":"18498 E Colfax Ave",
    "sg:city":"Aurora",
    "sg:classifiers":[
        {
            "category":"Shopping",
            "subcategory":"Bicycles & Sporting Goods",
            "type":"Retail Goods"
        }
    ],
    "sg:phone":"+1 303 367 1680",
    "sg:postcode":"80011",
    "sg:province":"CO",
    "sg:tags":[
        "gun",
        "gunsmith"
    ],
    "wof:name":"Robert's Firearms Co",
    "wof:placetype":"venue"
},
  "geometry": {"coordinates":[-104.77337199999999,39.740252],"type":"Point"}
}