{
  "type": "Feature",
  "properties": {
    "addr:full":"120 S Main St Holly CO 81047",
    "addr:housenumber":"120",
    "addr:postcode":"81047",
    "addr:street":"S Main St",
    "iso:country":"US",
    "sg:address":"120 S Main St",
    "sg:city":"Holly",
    "sg:classifiers":[
        {
            "category":"Bars & Pubs",
            "type":"Food & Drink"
        }
    ],
    "sg:phone":"+1 719 537 6272",
    "sg:postcode":"81047",
    "sg:province":"CO",
    "wof:name":"Toni's Restaurant & Lounge",
    "wof:placetype":"venue"
},
  "geometry": {"coordinates":[-102.12273399999999,38.053036],"type":"Point"}
}