{
  "type": "Feature",
  "properties": {
    "iso:country":"US",
    "sg:address":"200 Quebec St",
    "sg:city":"Denver",
    "sg:classifiers":[
        {
            "category":"Restaurant",
            "type":"Food & Drink"
        }
    ],
    "sg:phone":"+1 720 532 5999",
    "sg:postcode":"80230",
    "sg:province":"CO",
    "sg:tags":[
        "fusion",
        "asian"
    ],
    "sg:website":"www.peiwei.com",
    "wof:name":"Pei Wei Asian Diner",
    "wof:placetype":"venue"
},
  "geometry": {"coordinates":[-104.903547,39.719997],"type":"Point"}
}