{
  "type": "Feature",
  "properties": {
    "addr:full":"2796 S Broadway Englewood CO 80113",
    "addr:housenumber":"2796",
    "addr:postcode":"80113",
    "addr:street":"S Broadway",
    "iso:country":"US",
    "sg:address":"2796 S Broadway",
    "sg:city":"Englewood",
    "sg:classifiers":[
        {
            "category":"Building & Trades",
            "subcategory":"Locksmith",
            "type":"Services"
        }
    ],
    "sg:phone":"+1 866 844 8465",
    "sg:postcode":"80113",
    "sg:province":"CO",
    "sg:tags":[
        "key"
    ],
    "wof:name":"24 Hour Emergency Locksmith",
    "wof:placetype":"venue"
},
  "geometry": {"coordinates":[-104.987381,39.665895],"type":"Point"}
}