{
  "type": "Feature",
  "properties": {
    "iso:country":"US",
    "sg:address":"402 Kim Dr",
    "sg:city":"Silt",
    "sg:classifiers":[
        {
            "category":"Building & Trades",
            "subcategory":"Construction",
            "type":"Services"
        }
    ],
    "sg:phone":"+1 970 876 2945",
    "sg:postcode":"81652",
    "sg:province":"CO",
    "sg:tags":[
        "house"
    ],
    "wof:name":"Centrad Builders Inc",
    "wof:placetype":"venue"
},
  "geometry": {"coordinates":[-107.644194,39.550498],"type":"Point"}
}