{
  "type": "Feature",
  "properties": {
    "iso:country":"US",
    "sg:address":"2253 S Duffield Ave",
    "sg:city":"Loveland",
    "sg:classifiers":[
        {
            "category":"Building & Trades",
            "subcategory":"Construction",
            "type":"Services"
        }
    ],
    "sg:phone":"+1 970 461 2913",
    "sg:postcode":"80537",
    "sg:province":"CO",
    "sg:tags":[
        "contractor"
    ],
    "wof:name":"Able & Ben Installation & RPS",
    "wof:placetype":"venue"
},
  "geometry": {"coordinates":[-105.09348300000001,40.370906],"type":"Point"}
}