{
  "type": "Feature",
  "properties": {
    "iso:country":"US",
    "sg:address":"1055 S Fox St",
    "sg:city":"Denver",
    "sg:classifiers":[
        {
            "category":"Wholesale",
            "subcategory":"Groceries",
            "type":"Manufacturing & Wholesale Goods"
        }
    ],
    "sg:phone":"+1 303 715 3867",
    "sg:postcode":"80223",
    "sg:province":"CO",
    "sg:tags":[
        "food",
        "product"
    ],
    "wof:name":"Happiness",
    "wof:placetype":"venue"
},
  "geometry": {"coordinates":[-104.994534,39.698043],"type":"Point"}
}