{
  "type": "Feature",
  "properties": {
    "addr:full":"590 Orchard St Golden CO 80401",
    "addr:housenumber":"590",
    "addr:postcode":"80401",
    "addr:street":"Orchard St",
    "iso:country":"US",
    "sg:address":"590 Orchard St",
    "sg:city":"Golden",
    "sg:classifiers":[
        {
            "category":"Home & Garden",
            "subcategory":"Building Materials",
            "type":"Retail Goods"
        }
    ],
    "sg:phone":"+1 303 278 9503",
    "sg:postcode":"80401",
    "sg:province":"CO",
    "wof:name":"Cedarcraft Inc",
    "wof:placetype":"venue"
},
  "geometry": {"coordinates":[-105.17950399999999,39.723208],"type":"Point"}
}