{
  "type": "Feature",
  "properties": {
    "iso:country":"US",
    "sg:address":"2200 W Alameda Ave",
    "sg:city":"Denver",
    "sg:classifiers":[
        {
            "category":"Banks & Credit Unions",
            "subcategory":"Bank",
            "type":"Services"
        }
    ],
    "sg:phone":"+1 303 936 4271",
    "sg:postcode":"80223",
    "sg:province":"CO",
    "sg:tags":[
        "broker",
        "mortgage"
    ],
    "wof:name":"Lilly Financial Services LLC",
    "wof:placetype":"venue"
},
  "geometry": {"coordinates":[-105.012807,39.711109],"type":"Point"}
}