{
  "type": "Feature",
  "properties": {
    "iso:country":"US",
    "sg:address":"12203 E Iliff Ave",
    "sg:city":"Aurora",
    "sg:classifiers":[
        {
            "category":"Restaurant",
            "type":"Food & Drink"
        }
    ],
    "sg:menulink":"http://www.allmenus.com/co/south-aurora/124071-quiznos-sub/menu/",
    "sg:phone":"+1 720 747 9411",
    "sg:postcode":"80014",
    "sg:province":"CO",
    "sg:tags":[
        "wrap",
        "american",
        "sandwich"
    ],
    "wof:name":"Quiznos Sub",
    "wof:placetype":"venue"
},
  "geometry": {"coordinates":[-104.845191,39.674914],"type":"Point"}
}