{
  "type": "Feature",
  "properties": {
    "iso:country":"US",
    "sg:address":"460 Snow Mesa Ct",
    "sg:city":"Grand Junction",
    "sg:classifiers":[
        {
            "category":"Real Estate",
            "subcategory":"Developer",
            "type":"Services"
        }
    ],
    "sg:phone":"+1 970 242 9482",
    "sg:postcode":"81503",
    "sg:province":"CO",
    "wof:name":"Seasons At Tiara Rado Assoc",
    "wof:placetype":"venue"
},
  "geometry": {"coordinates":[-108.667332,39.071842],"type":"Point"}
}