{
  "type": "Feature",
  "properties": {
    "iso:country":"US",
    "sg:address":"328 E Platte Ave",
    "sg:city":"Colorado Springs",
    "sg:classifiers":[
        {
            "category":"Food & Beverages",
            "subcategory":"Groceries & Convenience Stores",
            "type":"Retail Goods"
        }
    ],
    "sg:phone":"+1 719 634 4066",
    "sg:postcode":"80903",
    "sg:province":"CO",
    "wof:name":"7-Eleven",
    "wof:placetype":"venue"
},
  "geometry": {"coordinates":[-104.817964,38.838013],"type":"Point"}
}