{
  "type": "Feature",
  "properties": {
    "iso:country":"US",
    "sg:address":"1901 Santa Fe Trl",
    "sg:city":"Trinidad",
    "sg:classifiers":[
        {
            "category":"Bars & Pubs",
            "type":"Food & Drink"
        }
    ],
    "sg:phone":"+1 719 846 9049",
    "sg:postcode":"81082",
    "sg:province":"CO",
    "sg:tags":[
        "drinking"
    ],
    "wof:name":"El Rancho Bar & Cafe",
    "wof:placetype":"venue"
},
  "geometry": {"coordinates":[-104.511959,37.151419],"type":"Point"}
}