{
  "type": "Feature",
  "properties": {
    "iso:country":"US",
    "sg:address":"550 Alter St",
    "sg:city":"Broomfield",
    "sg:classifiers":[
        {
            "category":"Restaurant",
            "type":"Food & Drink"
        }
    ],
    "sg:menulink":"http://www.allmenus.com/co/broomfield/207856-taco-bell/menu/",
    "sg:phone":"+1 303 460 7307",
    "sg:postcode":"80020",
    "sg:province":"CO",
    "sg:tags":[
        "mexican"
    ],
    "wof:name":"Taco Bell",
    "wof:placetype":"venue"
},
  "geometry": {"coordinates":[-105.09141099999999,39.924477],"type":"Point"}
}