{
  "type": "Feature",
  "properties": {
    "addr:full":"3433 Walnut St Denver CO 80205",
    "addr:housenumber":"3433",
    "addr:postcode":"80205",
    "addr:street":"Walnut St",
    "iso:country":"US",
    "sg:address":"3433 Walnut St",
    "sg:city":"Denver",
    "sg:classifiers":[
        {
            "category":"Manufacturing",
            "subcategory":"Glass & Minerals",
            "type":"Manufacturing & Wholesale Goods"
        }
    ],
    "sg:phone":"+1 303 294 0731",
    "sg:postcode":"80205",
    "sg:province":"CO",
    "sg:tags":[
        "installs",
        "granite",
        "mills",
        "marble"
    ],
    "wof:name":"Victor Marble Company Inc",
    "wof:placetype":"venue"
},
  "geometry": {"coordinates":[-104.975773,39.767371],"type":"Point"}
}