{
  "type": "Feature",
  "properties": {
    "addr:full":"1027 Telleen Ave Erie CO 80516",
    "addr:housenumber":"1027",
    "addr:postcode":"80516",
    "addr:street":"Telleen Ave",
    "iso:country":"US",
    "sg:address":"1027 Telleen Ave",
    "sg:city":"Erie",
    "sg:classifiers":[
        {
            "category":"Retail",
            "subcategory":"Auto Repair",
            "type":"Services"
        }
    ],
    "sg:phone":"+1 303 665 4320",
    "sg:postcode":"80516",
    "sg:province":"CO",
    "sg:tags":[
        "repairing",
        "automobile"
    ],
    "wof:name":"Lafayette Import Car Care Inc",
    "wof:placetype":"venue"
},
  "geometry": {"coordinates":[-105.059263,40.046044],"type":"Point"}
}