{
  "type": "Feature",
  "properties": {
    "iso:country":"US",
    "sg:address":"925 Stargate Dr",
    "sg:city":"Colorado Springs",
    "sg:classifiers":[
        {
            "category":"Banks & Credit Unions",
            "subcategory":"Bank",
            "type":"Services"
        }
    ],
    "sg:phone":"+1 719 390 7430",
    "sg:postcode":"80911",
    "sg:province":"CO",
    "sg:tags":[
        "mortgage"
    ],
    "wof:name":"Siggi Mortgages LLC",
    "wof:placetype":"venue"
},
  "geometry": {"coordinates":[-104.723383,38.757039],"type":"Point"}
}