{
  "type": "Feature",
  "properties": {
    "addr:full":"707 Main St Limon CO 80828",
    "addr:housenumber":"707",
    "addr:postcode":"80828",
    "addr:street":"Main St",
    "iso:country":"US",
    "sg:address":"707 Main St",
    "sg:city":"Limon",
    "sg:classifiers":[
        {
            "category":"Food & Beverages",
            "subcategory":"Groceries & Convenience Stores",
            "type":"Retail Goods"
        }
    ],
    "sg:phone":"+1 719 775 2522",
    "sg:postcode":"80828",
    "sg:province":"CO",
    "wof:name":"Loaf N Jug 64",
    "wof:placetype":"venue"
},
  "geometry": {"coordinates":[-103.685316,39.262846],"type":"Point"}
}