{
  "type": "Feature",
  "properties": {
    "addr:full":"866 Derbishire Rd Jefferson CO 80456",
    "addr:housenumber":"866",
    "addr:postcode":"80456",
    "addr:street":"Derbishire Rd",
    "iso:country":"US",
    "sg:address":"866 Derbishire Rd",
    "sg:city":"Jefferson",
    "sg:classifiers":[
        {
            "category":"Wholesale",
            "subcategory":"Machinery & Supplies",
            "type":"Manufacturing & Wholesale Goods"
        }
    ],
    "sg:phone":"+1 719 836 0700",
    "sg:postcode":"80456",
    "sg:province":"CO",
    "sg:tags":[
        "industrial",
        "miscellaneous"
    ],
    "wof:name":"Processing Control Equipment",
    "wof:placetype":"venue"
},
  "geometry": {"coordinates":[-105.640753,39.269571],"type":"Point"}
}