{
  "type": "Feature",
  "properties": {
    "addr:full":"804 E 4th St Pueblo CO 81001",
    "addr:housenumber":"804",
    "addr:postcode":"81001",
    "addr:street":"E 4Th St",
    "iso:country":"US",
    "sg:address":"804 E 4th St",
    "sg:city":"Pueblo",
    "sg:classifiers":[
        {
            "category":"Food & Beverages",
            "subcategory":"Groceries & Convenience Stores",
            "type":"Retail Goods"
        }
    ],
    "sg:phone":"+1 719 543 7265",
    "sg:postcode":"81001",
    "sg:province":"CO",
    "wof:name":"7-Eleven",
    "wof:placetype":"venue"
},
  "geometry": {"coordinates":[-104.59527199999999,38.270862],"type":"Point"}
}