{
  "type": "Feature",
  "properties": {
    "addr:full":"745 Quebec St Denver CO 80220",
    "addr:housenumber":"745",
    "addr:postcode":"80220",
    "addr:street":"Quebec St",
    "iso:country":"US",
    "sg:address":"745 Quebec St",
    "sg:city":"Denver",
    "sg:classifiers":[
        {
            "category":"Restaurant",
            "type":"Food & Drink"
        }
    ],
    "sg:phone":"+1 303 329 2921",
    "sg:postcode":"80220",
    "sg:province":"CO",
    "sg:tags":[
        "eating",
        "chinese"
    ],
    "wof:name":"Moon Gate Asian Grill",
    "wof:placetype":"venue"
},
  "geometry": {"coordinates":[-104.903999,39.727901],"type":"Point"}
}