{
  "type": "Feature",
  "properties": {
    "addr:full":"13490 E Mississippi Ave Aurora CO 80012",
    "addr:housenumber":"13490",
    "addr:postcode":"80012",
    "addr:street":"E Mississippi Ave",
    "iso:country":"US",
    "sg:address":"13490 E Mississippi Ave",
    "sg:city":"Aurora",
    "sg:classifiers":[
        {
            "category":"Food & Beverages",
            "subcategory":"Liquor & Beverages",
            "type":"Retail Goods"
        }
    ],
    "sg:phone":"+1 303 671 9190",
    "sg:postcode":"80012",
    "sg:province":"CO",
    "wof:name":"A J Liquor",
    "wof:placetype":"venue"
},
  "geometry": {"coordinates":[-104.832352,39.696541],"type":"Point"}
}