{
  "type": "Feature",
  "properties": {
    "addr:full":"4411 Lawrence Ln Laporte CO 80535",
    "addr:housenumber":"4411",
    "addr:postcode":"80535",
    "addr:street":"Lawrence Ln",
    "iso:country":"US",
    "sg:address":"4411 Lawrence Ln",
    "sg:city":"Laporte",
    "sg:classifiers":[
        {
            "category":"Social Services",
            "subcategory":"Child Care",
            "type":"Services"
        }
    ],
    "sg:phone":"+1 970 221 5467",
    "sg:postcode":"80535",
    "sg:province":"CO",
    "wof:name":"Jelly Beans Day Care Inc",
    "wof:placetype":"venue"
},
  "geometry": {"coordinates":[-105.161647,40.635848],"type":"Point"}
}