{
  "type": "Feature",
  "properties": {
    "iso:country":"US",
    "sg:address":"1399 S Wadsworth Blvd",
    "sg:city":"Lakewood",
    "sg:classifiers":[
        {
            "category":"Building & Trades",
            "subcategory":"Locksmith",
            "type":"Services"
        }
    ],
    "sg:phone":"+1 303 209 7831",
    "sg:postcode":"80232",
    "sg:province":"CO",
    "sg:tags":[
        "key"
    ],
    "wof:name":"AAA 15 Minutes Colorado Locksmith",
    "wof:placetype":"venue"
},
  "geometry": {"coordinates":[-105.081708,39.690969],"type":"Point"}
}