{
  "type": "Feature",
  "properties": {
    "addr:full":"1399 S Wadsworth Blvd Lakewood CO 80232",
    "addr:housenumber":"1399",
    "addr:postcode":"80232",
    "addr:street":"S Wadsworth Blvd",
    "iso:country":"US",
    "sg:address":"1399 S Wadsworth Blvd",
    "sg:city":"Lakewood",
    "sg:classifiers":[
        {
            "category":"Building & Trades",
            "subcategory":"Locksmith",
            "type":"Services"
        }
    ],
    "sg:phone":"+1 303 209 7831",
    "sg:postcode":"80232",
    "sg:province":"CO",
    "sg:tags":[
        "key"
    ],
    "wof:name":"AAA 15 Minutes Colorado Locksmith",
    "wof:placetype":"venue"
},
  "geometry": {"coordinates":[-105.08170800000001,39.690969],"type":"Point"}
}