{
  "type": "Feature",
  "properties": {
    "addr:full":"2505 S College Ave Fort Collins CO 80525",
    "addr:housenumber":"2505",
    "addr:postcode":"80525",
    "addr:street":"S College Ave",
    "iso:country":"US",
    "sg:address":"2505 S College Ave",
    "sg:city":"Fort Collins",
    "sg:classifiers":[
        {
            "category":"Shopping",
            "subcategory":"Computers & Home Electronics",
            "type":"Retail Goods"
        }
    ],
    "sg:phone":"+1 970 482 2383",
    "sg:postcode":"80525",
    "sg:province":"CO",
    "sg:website":"www.tenaska.com",
    "wof:name":"Radio Shack",
    "wof:placetype":"venue"
},
  "geometry": {"coordinates":[-105.077077,40.553612],"type":"Point"}
}