{
  "type": "Feature",
  "properties": {
    "addr:full":"6335 Tuckerman Ln Colorado Springs CO 80918",
    "addr:housenumber":"6335",
    "addr:postcode":"80918",
    "addr:street":"Tuckerman Ln",
    "iso:country":"US",
    "sg:address":"6335 Tuckerman Ln",
    "sg:city":"Colorado Springs",
    "sg:classifiers":[
        {
            "category":"Building & Trades",
            "subcategory":"Construction",
            "type":"Services"
        }
    ],
    "sg:phone":"+1 719 260 7414",
    "sg:postcode":"80918",
    "sg:province":"CO",
    "sg:tags":[
        "roofing",
        "contractor"
    ],
    "wof:name":"A Plus Roofing",
    "wof:placetype":"venue"
},
  "geometry": {"coordinates":[-104.781159,38.923393],"type":"Point"}
}