{
  "type": "Feature",
  "properties": {
    "iso:country":"US",
    "sg:address":"200 S Aspen St",
    "sg:city":"Aspen",
    "sg:classifiers":[
        {
            "category":"Travel",
            "subcategory":"Hotels & Motels",
            "type":"Entertainment"
        }
    ],
    "sg:phone":"+1 970 925 6246",
    "sg:postcode":"81611",
    "sg:province":"CO",
    "sg:tags":[
        "operation"
    ],
    "sg:website":"www.hotellenado.com",
    "wof:name":"Hotel Lenado",
    "wof:placetype":"venue"
},
  "geometry": {"coordinates":[-106.821867,39.190346],"type":"Point"}
}