{
  "type": "Feature",
  "properties": {
    "iso:country":"US",
    "sg:address":"726 Wade Rd",
    "sg:city":"Longmont",
    "sg:classifiers":[
        {
            "category":"Building & Trades",
            "subcategory":"Construction",
            "type":"Services"
        }
    ],
    "sg:phone":"+1 303 485 7104",
    "sg:postcode":"80503",
    "sg:province":"CO",
    "sg:tags":[
        "house"
    ],
    "wof:name":"Turtle Creek Construction",
    "wof:placetype":"venue"
},
  "geometry": {"coordinates":[-105.141035,40.172265],"type":"Point"}
}