{
  "type": "Feature",
  "properties": {
    "iso:country":"US",
    "sg:address":"218 N 6th Ave",
    "sg:city":"Brighton",
    "sg:classifiers":[
        {
            "category":"Organizations",
            "subcategory":"Religious Organization",
            "type":"Services"
        }
    ],
    "sg:phone":"+1 303 659 6411",
    "sg:postcode":"80601",
    "sg:province":"CO",
    "sg:tags":[
        "church"
    ],
    "wof:name":"First Foursquare Church",
    "wof:placetype":"venue"
},
  "geometry": {"coordinates":[-104.815363,39.991921],"type":"Point"}
}