{
  "type": "Feature",
  "properties": {
    "iso:country":"US",
    "sg:address":"248 Shavano Ave",
    "sg:city":"Salida",
    "sg:classifiers":[
        {
            "category":"Building & Trades",
            "subcategory":"Construction",
            "type":"Services"
        }
    ],
    "sg:phone":"+1 719 539 2630",
    "sg:postcode":"81201",
    "sg:province":"CO",
    "sg:tags":[
        "contractor"
    ],
    "wof:name":"Seamless Solutions",
    "wof:placetype":"venue"
},
  "geometry": {"coordinates":[-106.001132,38.538643],"type":"Point"}
}