{
  "type": "Feature",
  "properties": {
    "addr:full":"6725 E 19th Ave Denver CO 80220",
    "addr:housenumber":"6725",
    "addr:postcode":"80220",
    "addr:street":"E 19Th Ave",
    "iso:country":"US",
    "sg:address":"6725 E 19th Ave",
    "sg:city":"Denver",
    "sg:classifiers":[
        {
            "category":"Building & Trades",
            "subcategory":"Construction",
            "type":"Services"
        }
    ],
    "sg:phone":"+1 303 393 6019",
    "sg:postcode":"80220",
    "sg:province":"CO",
    "sg:tags":[
        "house"
    ],
    "wof:name":"Grand Traverse Builders Inc",
    "wof:placetype":"venue"
},
  "geometry": {"coordinates":[-104.909637,39.746308],"type":"Point"}
}