{
  "type": "Feature",
  "properties": {
    "addr:full":"280 W 14th Ave Denver CO 80204",
    "addr:housenumber":"280",
    "addr:postcode":"80204",
    "addr:street":"W 14Th Ave",
    "iso:country":"US",
    "sg:address":"280 W 14th Ave",
    "sg:city":"Denver",
    "sg:classifiers":[
        {
            "category":"Government",
            "subcategory":"Office",
            "type":"Public Place"
        }
    ],
    "sg:phone":"+1 720 913 0352",
    "sg:postcode":"80204",
    "sg:province":"CO",
    "sg:tags":[
        "city",
        "resource",
        "human"
    ],
    "wof:name":"Denver Child Care Initiatives",
    "wof:placetype":"venue"
},
  "geometry": {"coordinates":[-104.990505,39.738372],"type":"Point"}
}