{
  "type": "Feature",
  "properties": {
    "iso:country":"US",
    "sg:address":"146 Poplar Way",
    "sg:city":"Hotchkiss",
    "sg:classifiers":[
        {
            "category":"Shopping",
            "subcategory":"Gifts & Souvenirs",
            "type":"Retail Goods"
        }
    ],
    "sg:phone":"+1 970 872 4104",
    "sg:postcode":"81419",
    "sg:province":"CO",
    "wof:name":"Gifts Decor More",
    "wof:placetype":"venue"
},
  "geometry": {"coordinates":[-107.721954,38.807158],"type":"Point"}
}