{
  "type": "Feature",
  "properties": {
    "iso:country":"US",
    "sg:address":"9745 E Hampden Ave",
    "sg:city":"Denver",
    "sg:classifiers":[
        {
            "category":"Health Services",
            "subcategory":"Health Practitioner",
            "type":"Services"
        }
    ],
    "sg:phone":"+1 303 752 7159",
    "sg:postcode":"80231",
    "sg:province":"CO",
    "sg:tags":[
        "psychologist"
    ],
    "wof:name":"John J Kregarman",
    "wof:placetype":"venue"
},
  "geometry": {"coordinates":[-104.872311,39.653113],"type":"Point"}
}