{
  "type": "Feature",
  "properties": {
    "addr:full":"7360 W 52nd Ave Arvada CO 80002",
    "addr:housenumber":"7360",
    "addr:postcode":"80002",
    "addr:street":"W 52Nd Ave",
    "iso:country":"US",
    "sg:address":"7360 W 52nd Ave",
    "sg:city":"Arvada",
    "sg:classifiers":[
        {
            "category":"Food & Beverages",
            "subcategory":"Specialty",
            "type":"Retail Goods"
        }
    ],
    "sg:phone":"+1 303 940 3442",
    "sg:postcode":"80002",
    "sg:province":"CO",
    "wof:name":"GNC",
    "wof:placetype":"venue"
},
  "geometry": {"coordinates":[-105.07708700000001,39.791002],"type":"Point"}
}