{
  "type": "Feature",
  "properties": {
    "iso:country":"US",
    "sg:address":"4765 S Logan St",
    "sg:city":"Englewood",
    "sg:classifiers":[
        {
            "category":"Professional",
            "type":"Services"
        }
    ],
    "sg:phone":"+1 303 789 7539",
    "sg:postcode":"80113",
    "sg:province":"CO",
    "wof:name":"Lewis Miek & Co",
    "wof:placetype":"venue"
},
  "geometry": {"coordinates":[-104.98329,39.630712],"type":"Point"}
}