{
  "type": "Feature",
  "properties": {
    "addr:full":"3204 Wadsworth Blvd Wheat Ridge CO 80033",
    "addr:housenumber":"3204",
    "addr:postcode":"80033",
    "addr:street":"Wadsworth Blvd",
    "iso:country":"US",
    "sg:address":"3204 Wadsworth Blvd",
    "sg:city":"Wheat Ridge",
    "sg:classifiers":[
        {
            "category":"Banks & Credit Unions",
            "subcategory":"Investment Brokerage",
            "type":"Services"
        }
    ],
    "sg:phone":"+1 303 274 7474",
    "sg:postcode":"80033",
    "sg:province":"CO",
    "sg:tags":[
        "advisory",
        "financial"
    ],
    "wof:name":"Evergreen Financial Inc",
    "wof:placetype":"venue"
},
  "geometry": {"coordinates":[-105.081377,39.763839],"type":"Point"}
}