{
  "type": "Feature",
  "properties": {
    "iso:country":"US",
    "sg:address":"6277 E Mineral Pl",
    "sg:city":"Englewood",
    "sg:classifiers":[
        {
            "category":"Shopping",
            "subcategory":"Jewelry",
            "type":"Retail Goods"
        }
    ],
    "sg:phone":"+1 303 770 7155",
    "sg:postcode":"80112",
    "sg:province":"CO",
    "wof:name":"Treasure Trader",
    "wof:placetype":"venue"
},
  "geometry": {"coordinates":[-104.91566899999999,39.572245],"type":"Point"}
}