{
  "type": "Feature",
  "properties": {
    "iso:country":"US",
    "sg:address":"3406 Navajo St",
    "sg:city":"Denver",
    "sg:classifiers":[
        {
            "category":"Food & Beverages",
            "subcategory":"Liquor & Beverages",
            "type":"Retail Goods"
        }
    ],
    "sg:phone":"+1 720 855 6757",
    "sg:postcode":"80211",
    "sg:province":"CO",
    "wof:name":"Latino Liquors",
    "wof:placetype":"venue"
},
  "geometry": {"coordinates":[-105.004053,39.765568],"type":"Point"}
}