{
  "type": "Feature",
  "properties": {
    "addr:full":"1242 South Broadway Denver CO 80210",
    "addr:housenumber":"1242",
    "addr:postcode":"80210",
    "addr:street":"South Broadway",
    "iso:country":"US",
    "sg:address":"1242 South Broadway",
    "sg:city":"Denver",
    "sg:classifiers":[
        {
            "category":"Personal",
            "type":"Services"
        }
    ],
    "sg:phone":"+1 303 350 9441",
    "sg:postcode":"80210",
    "sg:province":"CO",
    "sg:tags":[
        "party",
        "planning",
        "event",
        "wedding"
    ],
    "sg:website":"alexanevents.com",
    "wof:name":"Alexan Events",
    "wof:placetype":"venue"
},
  "geometry": {"coordinates":[-104.987436,39.693825],"type":"Point"}
}