{
  "type": "Feature",
  "properties": {
    "iso:country":"US",
    "sg:address":"3027 W Oakland Dr",
    "sg:city":"Sedalia",
    "sg:classifiers":[
        {
            "category":"Building & Trades",
            "subcategory":"Construction",
            "type":"Services"
        }
    ],
    "sg:phone":"+1 303 688 6288",
    "sg:postcode":"80135",
    "sg:province":"CO",
    "sg:tags":[
        "concrete",
        "contractor"
    ],
    "wof:name":"Rdc Concrete",
    "wof:placetype":"venue"
},
  "geometry": {"coordinates":[-104.94919899999999,39.381093],"type":"Point"}
}