{
  "type": "Feature",
  "properties": {
    "iso:country":"US",
    "sg:address":"3000 W 13th St",
    "sg:city":"Greeley",
    "sg:classifiers":[
        {
            "category":"Education",
            "subcategory":"School",
            "type":"Public Place"
        }
    ],
    "sg:phone":"+1 970 348 2200",
    "sg:postcode":"80634",
    "sg:province":"CO",
    "sg:website":"www.greeleyschools.org",
    "wof:name":"Scott Elementary School",
    "wof:placetype":"venue"
},
  "geometry": {"coordinates":[-104.73079799999999,40.418352],"type":"Point"}
}