{
  "type": "Feature",
  "properties": {
    "addr:full":"3 Burgundy St Littleton CO 80126",
    "addr:housenumber":"3",
    "addr:postcode":"80126",
    "addr:street":"Burgundy St",
    "iso:country":"US",
    "sg:address":"3 Burgundy St",
    "sg:city":"Littleton",
    "sg:classifiers":[
        {
            "category":"Professional",
            "subcategory":"Advertising",
            "type":"Services"
        }
    ],
    "sg:phone":"+1 720 201 0017",
    "sg:postcode":"80126",
    "sg:province":"CO",
    "sg:tags":[
        "counselor"
    ],
    "wof:name":"Onyx Entertainment",
    "wof:placetype":"venue"
},
  "geometry": {"coordinates":[-104.990681,39.546309],"type":"Point"}
}