{
  "type": "Feature",
  "properties": {
    "addr:full":"846 Forest Rd Vail CO 81657",
    "addr:housenumber":"846",
    "addr:postcode":"81657",
    "addr:street":"Forest Rd",
    "iso:country":"US",
    "sg:address":"846 Forest Rd",
    "sg:city":"Vail",
    "sg:classifiers":[
        {
            "category":"Utilities",
            "subcategory":"Water",
            "type":"Services"
        }
    ],
    "sg:phone":"+1 970 476 7480",
    "sg:postcode":"81657",
    "sg:province":"CO",
    "sg:tags":[
        "company",
        "sewage"
    ],
    "sg:website":"www.erwsd.org",
    "wof:name":"Eagle River Water & Sanitation",
    "wof:placetype":"venue"
},
  "geometry": {"coordinates":[-106.394111,39.641702],"type":"Point"}
}