{
  "type": "Feature",
  "properties": {
    "iso:country":"US",
    "sg:address":"9221 W Ken Caryl Ave",
    "sg:city":"Littleton",
    "sg:classifiers":[
        {
            "category":"Freight",
            "type":"Transportation"
        }
    ],
    "sg:phone":"+1 303 972 7867",
    "sg:postcode":"80128",
    "sg:province":"CO",
    "sg:tags":[
        "commercial",
        "storage"
    ],
    "wof:name":"Stor N Lock Self Storage",
    "wof:placetype":"venue"
},
  "geometry": {"coordinates":[-105.101922,39.580794],"type":"Point"}
}