{
  "type": "Feature",
  "properties": {
    "iso:country":"US",
    "sg:address":"106 S Mill St",
    "sg:city":"Aspen",
    "sg:classifiers":[
        {
            "category":"Professional",
            "subcategory":"Management & Consulting",
            "type":"Services"
        }
    ],
    "sg:phone":"+1 970 920 7556",
    "sg:postcode":"81611",
    "sg:province":"CO",
    "sg:tags":[
        "consultant",
        "business"
    ],
    "wof:name":"Strategic Business Development",
    "wof:placetype":"venue"
},
  "geometry": {"coordinates":[-106.819157,39.190606],"type":"Point"}
}