{
  "type": "Feature",
  "properties": {
    "addr:full":"525 S Pueblo Blvd Pueblo CO 81005",
    "addr:housenumber":"525",
    "addr:postcode":"81005",
    "addr:street":"S Pueblo Blvd",
    "iso:country":"US",
    "sg:address":"525 S Pueblo Blvd",
    "sg:city":"Pueblo",
    "sg:classifiers":[
        {
            "category":"Restaurant",
            "type":"Food & Drink"
        }
    ],
    "sg:phone":"+1 719 564 0690",
    "sg:postcode":"81005",
    "sg:province":"CO",
    "sg:tags":[
        "eating"
    ],
    "wof:name":"Mi Ranchito Mexican Restaurant",
    "wof:placetype":"venue"
},
  "geometry": {"coordinates":[-104.661761,38.254836],"type":"Point"}
}