{
  "type": "Feature",
  "properties": {
    "addr:full":"810 Park Avenue W Denver CO 80205",
    "addr:housenumber":"810",
    "addr:postcode":"80205",
    "addr:street":"Park Avenue W",
    "iso:country":"US",
    "sg:address":"810 Park Avenue W",
    "sg:city":"Denver",
    "sg:classifiers":[
        {
            "category":"Restaurant",
            "type":"Food & Drink"
        }
    ],
    "sg:phone":"+1 303 293 3716",
    "sg:postcode":"80205",
    "sg:province":"CO",
    "wof:name":"Taqueria Emanuel",
    "wof:placetype":"venue"
},
  "geometry": {"coordinates":[-104.984799,39.75268],"type":"Point"}
}