{
  "type": "Feature",
  "properties": {
    "iso:country":"US",
    "sg:address":"2708 Gap Rd",
    "sg:city":"Black Hawk",
    "sg:classifiers":[
        {
            "category":"Professional",
            "type":"Services"
        }
    ],
    "sg:phone":"+1 303 582 5284",
    "sg:postcode":"80403",
    "sg:province":"CO",
    "sg:tags":[
        "establishment"
    ],
    "wof:name":"Golden Gate Canyon State Park",
    "wof:placetype":"venue"
},
  "geometry": {"coordinates":[-105.44238300000001,39.874143],"type":"Point"}
}