{
  "type": "Feature",
  "properties": {
    "addr:full":"351 Paradise Cir Woodland Park CO 80863",
    "addr:housenumber":"351",
    "addr:postcode":"80863",
    "addr:street":"Paradise Cir",
    "iso:country":"US",
    "sg:address":"351 Paradise Cir",
    "sg:city":"Woodland Park",
    "sg:classifiers":[
        {
            "category":"Real Estate",
            "subcategory":"Real Estate Agent",
            "type":"Services"
        }
    ],
    "sg:phone":"+1 719 686 1569",
    "sg:postcode":"80863",
    "sg:province":"CO",
    "sg:tags":[
        "appraiser",
        "business"
    ],
    "wof:name":"J P Appraisals",
    "wof:placetype":"venue"
},
  "geometry": {"coordinates":[-105.043736,38.985651],"type":"Point"}
}