{
  "type": "Feature",
  "properties": {
    "iso:country":"US",
    "sg:address":"1601 Pennsylvania St",
    "sg:city":"Denver",
    "sg:classifiers":[
        {
            "category":"Parking",
            "type":"Transportation"
        }
    ],
    "sg:phone":"+1 303 832 4721",
    "sg:postcode":"80203",
    "sg:province":"CO",
    "sg:tags":[
        "garage"
    ],
    "wof:name":"Hall & Hall Auto Parks",
    "wof:placetype":"venue"
},
  "geometry": {"coordinates":[-104.981084,39.743271],"type":"Point"}
}