{
  "type": "Feature",
  "properties": {
    "iso:country":"US",
    "sg:address":"4840 Ingalls St",
    "sg:city":"Wheat Ridge",
    "sg:classifiers":[
        {
            "category":"Manufacturing",
            "subcategory":"Retail Goods",
            "type":"Manufacturing & Wholesale Goods"
        }
    ],
    "sg:phone":"+1 303 463 1559",
    "sg:postcode":"80033",
    "sg:province":"CO",
    "sg:tags":[
        "assembly",
        "fabricating"
    ],
    "wof:name":"A Garcia",
    "wof:placetype":"venue"
},
  "geometry": {"coordinates":[-105.063698,39.785493],"type":"Point"}
}