{
  "type": "Feature",
  "properties": {
    "iso:country":"US",
    "sg:address":"101 Widefield Blvd",
    "sg:city":"Colorado Springs",
    "sg:classifiers":[
        {
            "category":"Shopping",
            "subcategory":"Florist",
            "type":"Retail Goods"
        }
    ],
    "sg:phone":"+1 719 392 4699",
    "sg:postcode":"80911",
    "sg:province":"CO",
    "wof:name":"A Dusty Rose",
    "wof:placetype":"venue"
},
  "geometry": {"coordinates":[-104.72734800000001,38.734985],"type":"Point"}
}