{
  "type": "Feature",
  "properties": {
    "iso:country":"US",
    "sg:address":"429 N Commercial St",
    "sg:city":"Trinidad",
    "sg:classifiers":[
        {
            "category":"Shopping",
            "subcategory":"Catalog Store",
            "type":"Retail Goods"
        }
    ],
    "sg:phone":"+1 719 846 3744",
    "sg:postcode":"81082",
    "sg:province":"CO",
    "sg:tags":[
        "mail",
        "order"
    ],
    "wof:name":"J C Penney Catalog",
    "wof:placetype":"venue"
},
  "geometry": {"coordinates":[-104.507137,37.171806],"type":"Point"}
}