{
  "type": "Feature",
  "properties": {
    "iso:country":"US",
    "sg:address":"627 Grand Ave",
    "sg:city":"Grand Junction",
    "sg:classifiers":[
        {
            "category":"Retail",
            "subcategory":"Photofinishing",
            "type":"Services"
        }
    ],
    "sg:phone":"+1 970 243 9030",
    "sg:postcode":"81501",
    "sg:province":"CO",
    "sg:tags":[
        "photo",
        "finishing"
    ],
    "wof:name":"Photec Custom Photo Lab",
    "wof:placetype":"venue"
},
  "geometry": {"coordinates":[-108.561463,39.070242],"type":"Point"}
}