{
  "type": "Feature",
  "properties": {
    "iso:country":"US",
    "sg:address":"102 S 5th St",
    "sg:city":"Grand Junction",
    "sg:classifiers":[
        {
            "category":"Recreation",
            "type":"Entertainment"
        }
    ],
    "sg:phone":"+1 970 255 8029",
    "sg:postcode":"81501",
    "sg:province":"CO",
    "sg:tags":[
        "instruction",
        "yoga"
    ],
    "wof:name":"Academy Of Yoga",
    "wof:placetype":"venue"
},
  "geometry": {"coordinates":[-108.564395,39.066352],"type":"Point"}
}