{
  "type": "Feature",
  "properties": {
    "iso:country":"US",
    "sg:address":"1223 28th Ave",
    "sg:city":"Greeley",
    "sg:classifiers":[
        {
            "category":"Professional",
            "subcategory":"Testing Lab",
            "type":"Services"
        }
    ],
    "sg:phone":"+1 970 353 9818",
    "sg:postcode":"80634",
    "sg:province":"CO",
    "sg:tags":[
        "laboratory"
    ],
    "wof:name":"Colorado Dhia",
    "wof:placetype":"venue"
},
  "geometry": {"coordinates":[-104.724844,40.418831],"type":"Point"}
}