{
  "type": "Feature",
  "properties": {
    "iso:country":"US",
    "sg:address":"222 Wolfensberger Road",
    "sg:city":"Castle Rock",
    "sg:classifiers":[
        {
            "category":"Restaurant",
            "type":"Food & Drink"
        }
    ],
    "sg:phone":"+1 303 660 5066",
    "sg:postcode":"80109",
    "sg:province":"CO",
    "sg:website":"www.wafflehouse.com",
    "wof:name":"Waffle House",
    "wof:placetype":"venue"
},
  "geometry": {"coordinates":[-104.862094,39.38032],"type":"Point"}
}