{
  "type": "Feature",
  "properties": {
    "iso:country":"US",
    "sg:address":"5977 Templeton Gap Rd",
    "sg:city":"Colorado Springs",
    "sg:classifiers":[
        {
            "category":"Retail",
            "subcategory":"Animal Services",
            "type":"Services"
        }
    ],
    "sg:phone":"+1 719 591 0066",
    "sg:postcode":"80923",
    "sg:province":"CO",
    "wof:name":"Rampart Kennels",
    "wof:placetype":"venue"
},
  "geometry": {"coordinates":[-104.724129,38.919154],"type":"Point"}
}