{
  "type": "Feature",
  "properties": {
    "iso:country":"US",
    "sg:address":"1546 Loma Linda Dr",
    "sg:city":"Pagosa Springs",
    "sg:classifiers":[
        {
            "category":"Shopping",
            "subcategory":"Gifts & Souvenirs",
            "type":"Retail Goods"
        }
    ],
    "sg:phone":"+1 970 264 0132",
    "sg:postcode":"81147",
    "sg:province":"CO",
    "wof:name":"Magic Touch Crafts",
    "wof:placetype":"venue"
},
  "geometry": {"coordinates":[-106.98375,37.193927],"type":"Point"}
}