{
  "type": "Feature",
  "properties": {
    "iso:country":"US",
    "sg:address":"231 Milwaukee St",
    "sg:city":"Denver",
    "sg:classifiers":[
        {
            "category":"Wholesale",
            "subcategory":"Electrical",
            "type":"Manufacturing & Wholesale Goods"
        }
    ],
    "sg:phone":"+1 303 468 2077",
    "sg:postcode":"80206",
    "sg:province":"CO",
    "sg:tags":[
        "control",
        "security",
        "system"
    ],
    "wof:name":"DMS Security Group",
    "wof:placetype":"venue"
},
  "geometry": {"coordinates":[-104.95227800000001,39.720494],"type":"Point"}
}