{
  "type": "Feature",
  "properties": {
    "iso:country":"US",
    "sg:address":"8575 E Arapahoe Rd",
    "sg:city":"Greenwood Vlg",
    "sg:classifiers":[
        {
            "category":"Retail",
            "subcategory":"Photofinishing",
            "type":"Services"
        }
    ],
    "sg:phone":"+1 303 740 0903",
    "sg:postcode":"80112",
    "sg:province":"CO",
    "sg:tags":[
        "photo",
        "finishing"
    ],
    "wof:name":"Club Photo",
    "wof:placetype":"venue"
},
  "geometry": {"coordinates":[-104.89257600000001,39.595112],"type":"Point"}
}