{
  "type": "Feature",
  "properties": {
    "addr:full":"6850 W 52nd Ave Ste 101 Arvada CO 80002",
    "addr:housenumber":"6850",
    "addr:postcode":"80002",
    "addr:street":"W 52Nd Ave Ste 101",
    "iso:country":"US",
    "sg:address":"6850 W 52nd Ave Ste 101",
    "sg:city":"Arvada",
    "sg:classifiers":[
        {
            "category":"Banks & Credit Unions",
            "subcategory":"Financial Services",
            "type":"Services"
        }
    ],
    "sg:phone":"+1 303 422 6500",
    "sg:postcode":"80002",
    "sg:province":"CO",
    "sg:tags":[
        "broker",
        "mortgage"
    ],
    "wof:name":"Venture Financial",
    "wof:placetype":"venue"
},
  "geometry": {"coordinates":[-105.0728,39.788686],"type":"Point"}
}