{
  "type": "Feature",
  "properties": {
    "addr:full":"111 N Union Ave Pueblo CO 81003",
    "addr:housenumber":"111",
    "addr:postcode":"81003",
    "addr:street":"N Union Ave",
    "iso:country":"US",
    "sg:address":"111 N Union Ave",
    "sg:city":"Pueblo",
    "sg:classifiers":[
        {
            "category":"Shopping",
            "subcategory":"Clothing, Apparel, & Fashions",
            "type":"Retail Goods"
        }
    ],
    "sg:phone":"+1 719 545 1665",
    "sg:postcode":"81003",
    "sg:province":"CO",
    "sg:tags":[
        "shop",
        "bridal"
    ],
    "wof:name":"Forever Yours Bridal Boutique",
    "wof:placetype":"venue"
},
  "geometry": {"coordinates":[-104.61206199999999,38.265677],"type":"Point"}
}