{
  "type": "Feature",
  "properties": {
    "iso:country":"US",
    "sg:address":"2764 Compass Dr",
    "sg:city":"Grand Junction",
    "sg:classifiers":[
        {
            "category":"Real Estate",
            "subcategory":"Architect",
            "type":"Services"
        }
    ],
    "sg:phone":"+1 970 245 6093",
    "sg:postcode":"81506",
    "sg:province":"CO",
    "wof:name":"Genesis Designs Architecture",
    "wof:placetype":"venue"
},
  "geometry": {"coordinates":[-108.54051800000001,39.116436],"type":"Point"}
}