{
  "type": "Feature",
  "properties": {
    "addr:full":"2050 S Downing St Denver CO 80210",
    "addr:housenumber":"2050",
    "addr:postcode":"80210",
    "addr:street":"S Downing St",
    "iso:country":"US",
    "sg:address":"2050 S Downing St",
    "sg:city":"Denver",
    "sg:classifiers":[
        {
            "category":"Banks & Credit Unions",
            "subcategory":"Bank",
            "type":"Services"
        }
    ],
    "sg:phone":"+1 303 202 5521",
    "sg:postcode":"80210",
    "sg:province":"CO",
    "wof:name":"Commercial Federal Bank",
    "wof:placetype":"venue"
},
  "geometry": {"coordinates":[-104.973349,39.679439],"type":"Point"}
}