{
  "type": "Feature",
  "properties": {
    "addr:full":"1050 S Nutmeg St Bennett CO 80102",
    "addr:housenumber":"1050",
    "addr:postcode":"80102",
    "addr:street":"S Nutmeg St",
    "iso:country":"US",
    "sg:address":"1050 S Nutmeg St",
    "sg:city":"Bennett",
    "sg:classifiers":[
        {
            "category":"Wholesale",
            "subcategory":"Durable Goods & Equipment",
            "type":"Manufacturing & Wholesale Goods"
        }
    ],
    "sg:phone":"+1 303 644 4282",
    "sg:postcode":"80102",
    "sg:province":"CO",
    "sg:tags":[
        "importer"
    ],
    "wof:name":"Lost Creek Tractor Sales",
    "wof:placetype":"venue"
},
  "geometry": {"coordinates":[-104.513626,39.696469],"type":"Point"}
}