{
  "type": "Feature",
  "properties": {
    "iso:country":"US",
    "sg:address":"140 Sam Grange Ct",
    "sg:city":"Carbondale",
    "sg:classifiers":[
        {
            "category":"Manufacturing",
            "subcategory":"Motor Vehicles & Parts",
            "type":"Manufacturing & Wholesale Goods"
        }
    ],
    "sg:phone":"+1 970 963 0601",
    "sg:postcode":"81623",
    "sg:province":"CO",
    "sg:tags":[
        "equipment",
        "transportation",
        "mfg"
    ],
    "wof:name":"Kanchana Products Inc",
    "wof:placetype":"venue"
},
  "geometry": {"coordinates":[-107.096791,39.435533],"type":"Point"}
}