{
  "type": "Feature",
  "properties": {
    "iso:country":"US",
    "sg:address":"2955 Muleshoe Dr",
    "sg:city":"Colorado Springs",
    "sg:classifiers":[
        {
            "category":"Banks & Credit Unions",
            "subcategory":"Investment Brokerage",
            "type":"Services"
        }
    ],
    "sg:phone":"+1 719 380 9216",
    "sg:postcode":"80922",
    "sg:province":"CO",
    "sg:tags":[
        "security"
    ],
    "wof:name":"Edward Jones 39100",
    "wof:placetype":"venue"
},
  "geometry": {"coordinates":[-104.709773,38.874811],"type":"Point"}
}