{
  "type": "Feature",
  "properties": {
    "addr:full":"122 S el Paso St Colorado Springs CO 80903",
    "addr:housenumber":"122",
    "addr:postcode":"80903",
    "addr:street":"S El Paso St",
    "iso:country":"US",
    "sg:address":"122 S el Paso St",
    "sg:city":"Colorado Springs",
    "sg:classifiers":[
        {
            "category":"Retail",
            "subcategory":"Auto Repair",
            "type":"Services"
        }
    ],
    "sg:phone":"+1 719 635 2652",
    "sg:postcode":"80903",
    "sg:province":"CO",
    "sg:tags":[
        "general"
    ],
    "wof:name":"Top Tech Auto",
    "wof:placetype":"venue"
},
  "geometry": {"coordinates":[-104.813175,38.831789],"type":"Point"}
}