{
  "type": "Feature",
  "properties": {
    "iso:country":"US",
    "sg:address":"2028 SE Frontage Rd",
    "sg:city":"Fort Collins",
    "sg:classifiers":[
        {
            "category":"Wholesale",
            "subcategory":"Metals & Minerals",
            "type":"Manufacturing & Wholesale Goods"
        }
    ],
    "sg:phone":"+1 970 482 5225",
    "sg:postcode":"80525",
    "sg:province":"CO",
    "sg:tags":[
        "equipment",
        "industrial",
        "co",
        "center"
    ],
    "wof:name":"Jackson Brooks & Company",
    "wof:placetype":"venue"
},
  "geometry": {"coordinates":[-105.00085799999999,40.560774],"type":"Point"}
}