{
  "type": "Feature",
  "properties": {
    "addr:full":"248 Wild Irishman Rd Dillon CO 80435",
    "addr:housenumber":"248",
    "addr:postcode":"80435",
    "addr:street":"Wild Irishman Rd",
    "iso:country":"US",
    "sg:address":"248 Wild Irishman Rd",
    "sg:city":"Dillon",
    "sg:classifiers":[
        {
            "category":"Banks & Credit Unions",
            "subcategory":"Bank",
            "type":"Services"
        }
    ],
    "sg:phone":"+1 970 468 7573",
    "sg:postcode":"80435",
    "sg:province":"CO",
    "sg:tags":[
        "broker",
        "mortgage"
    ],
    "wof:name":"King Laurie Mortgage Brk Inc",
    "wof:placetype":"venue"
},
  "geometry": {"coordinates":[-105.976399,39.601559],"type":"Point"}
}