{
  "type": "Feature",
  "properties": {
    "iso:country":"US",
    "sg:address":"188 Inverness Dr W",
    "sg:city":"Englewood",
    "sg:classifiers":[
        {
            "category":"Shopping",
            "subcategory":"Computers & Home Electronics",
            "type":"Retail Goods"
        }
    ],
    "sg:phone":"+1 303 524 1208",
    "sg:postcode":"80112",
    "sg:province":"CO",
    "sg:tags":[
        "software"
    ],
    "wof:name":"Healthtrio",
    "wof:placetype":"venue"
},
  "geometry": {"coordinates":[-104.87078700000001,39.57299],"type":"Point"}
}