{
  "type": "Feature",
  "properties": {
    "iso:country":"US",
    "sg:address":"93 Co Hwy 397",
    "sg:city":"Kremmling",
    "sg:classifiers":[
        {
            "category":"Building & Trades",
            "subcategory":"Construction",
            "type":"Services"
        }
    ],
    "sg:phone":"+1 970 724 3742",
    "sg:postcode":"80459",
    "sg:province":"CO",
    "sg:tags":[
        "general",
        "contractor"
    ],
    "wof:name":"DMJ General Contractors Inc",
    "wof:placetype":"venue"
},
  "geometry": {"coordinates":[-106.349284,40.049542],"type":"Point"}
}