{
  "type": "Feature",
  "properties": {
    "iso:country":"US",
    "sg:address":"2785 N Speer Blvd Ste 210",
    "sg:city":"Denver",
    "sg:classifiers":[
        {
            "category":"Insurance",
            "subcategory":"Title Insurance",
            "type":"Services"
        }
    ],
    "sg:phone":"+1 303 984 1408",
    "sg:postcode":"80211",
    "sg:province":"CO",
    "sg:tags":[
        "mortgage"
    ],
    "sg:website":"http://www.commonwealthca.com",
    "wof:name":"Commonwealth Land Title",
    "wof:placetype":"venue"
},
  "geometry": {"coordinates":[-105.017487,39.756888],"type":"Point"}
}