{
  "type": "Feature",
  "properties": {
    "addr:full":"43754 W US Hwy 50 Canon City CO 81212",
    "addr:housenumber":"43754",
    "addr:postcode":"81212",
    "addr:street":"W Us Hwy 50",
    "iso:country":"US",
    "sg:address":"43754 W US Hwy 50",
    "sg:city":"Canon City",
    "sg:classifiers":[
        {
            "category":"Retail",
            "subcategory":"Portrait Studio",
            "type":"Services"
        }
    ],
    "sg:phone":"+1 719 269 3968",
    "sg:postcode":"81212",
    "sg:province":"CO",
    "sg:tags":[
        "photo"
    ],
    "wof:name":"Kreski Enterprises",
    "wof:placetype":"venue"
},
  "geometry": {"coordinates":[-105.34624700000001,38.498029],"type":"Point"}
}