{
  "type": "Feature",
  "properties": {
    "addr:full":"2077 N Hwy 83 Franktown CO 80116",
    "addr:housenumber":"2077",
    "addr:postcode":"80116",
    "addr:street":"N Hwy 83",
    "iso:country":"US",
    "sg:address":"2077 N Hwy 83",
    "sg:city":"Franktown",
    "sg:classifiers":[
        {
            "category":"Bars & Pubs",
            "type":"Food & Drink"
        }
    ],
    "sg:phone":"+1 303 660 3773",
    "sg:postcode":"80116",
    "sg:province":"CO",
    "sg:website":"www.stagecoachsaloon.com",
    "wof:name":"Stagecoach",
    "wof:placetype":"venue"
},
  "geometry": {"coordinates":[-104.753956,39.394054],"type":"Point"}
}