{
  "type": "Feature",
  "properties": {
    "iso:country":"US",
    "sg:address":"18308 W 58th Pl",
    "sg:city":"Golden",
    "sg:classifiers":[
        {
            "category":"Real Estate",
            "subcategory":"Real Estate Agent",
            "type":"Services"
        }
    ],
    "sg:phone":"+1 303 384 9744",
    "sg:postcode":"80403",
    "sg:province":"CO",
    "wof:name":"Jaf Realtyconsultng",
    "wof:placetype":"venue"
},
  "geometry": {"coordinates":[-105.205744,39.803004],"type":"Point"}
}