{
  "type": "Feature",
  "properties": {
    "iso:country":"US",
    "sg:address":"8700 Turnpike Dr",
    "sg:city":"Westminster",
    "sg:classifiers":[
        {
            "category":"Education",
            "subcategory":"College",
            "type":"Public Place"
        }
    ],
    "sg:phone":"+1 303 487 7115",
    "sg:postcode":"80031",
    "sg:province":"CO",
    "wof:name":"Turnpike Learning Center",
    "wof:placetype":"venue"
},
  "geometry": {"coordinates":[-105.051483,39.85376],"type":"Point"}
}