{
  "type": "Feature",
  "properties": {
    "addr:full":"604 Marina Dr Grand Lake CO 80447",
    "addr:housenumber":"604",
    "addr:postcode":"80447",
    "addr:street":"Marina Dr",
    "iso:country":"US",
    "sg:address":"604 Marina Dr",
    "sg:city":"Grand Lake",
    "sg:classifiers":[
        {
            "category":"Restaurant",
            "type":"Food & Drink"
        }
    ],
    "sg:menulink":"http://www.allmenus.com/co/granby/276583-daven-haven-lodge-backstreet-steakhouse/menu/",
    "sg:phone":"+1 970 627 8144",
    "sg:postcode":"80447",
    "sg:province":"CO",
    "sg:tags":[
        "american",
        "steakhouse"
    ],
    "wof:name":"Daven Haven Lodge Backstreet Steakhouse",
    "wof:placetype":"venue"
},
  "geometry": {"coordinates":[-105.82713099999999,40.249274],"type":"Point"}
}