{
  "type": "Feature",
  "properties": {
    "iso:country":"US",
    "sg:address":"7953 S Clayton Cir",
    "sg:city":"Littleton",
    "sg:classifiers":[
        {
            "category":"Manufacturing",
            "subcategory":"Retail Goods",
            "type":"Manufacturing & Wholesale Goods"
        }
    ],
    "sg:phone":"+1 303 770 7337",
    "sg:postcode":"80122",
    "sg:province":"CO",
    "sg:tags":[
        "lead",
        "mfg"
    ],
    "wof:name":"Art Accents Ltd",
    "wof:placetype":"venue"
},
  "geometry": {"coordinates":[-104.954475,39.572281],"type":"Point"}
}