{
  "type": "Feature",
  "properties": {
    "iso:country":"US",
    "sg:address":"418 Harrison Ave",
    "sg:city":"Leadville",
    "sg:classifiers":[
        {
            "category":"Organizations",
            "subcategory":"Non-profit Organization",
            "type":"Services"
        }
    ],
    "sg:phone":"+1 719 486 2564",
    "sg:postcode":"80461",
    "sg:province":"CO",
    "sg:tags":[
        "alternative",
        "abortion"
    ],
    "wof:name":"Cornerstone Pregnancy Resource",
    "wof:placetype":"venue"
},
  "geometry": {"coordinates":[-106.29135100000001,39.247453],"type":"Point"}
}