{
  "type": "Feature",
  "properties": {
    "addr:full":"510 Santa Fe Dr Denver CO 80304",
    "addr:housenumber":"510",
    "addr:postcode":"80304",
    "addr:street":"Santa Fe Dr",
    "iso:country":"US",
    "sg:address":"510 Santa Fe Dr",
    "sg:city":"Denver",
    "sg:classifiers":[
        {
            "category":"Arts & Performance",
            "subcategory":"Art Gallery",
            "type":"Entertainment"
        }
    ],
    "sg:phone":"+1 303 765 5116",
    "sg:postcode":"80304",
    "sg:province":"CO",
    "wof:name":"Arco Iris Jewelry and Gallery",
    "wof:placetype":"venue"
},
  "geometry": {"coordinates":[-104.998295,39.724558],"type":"Point"}
}