{
  "type": "Feature",
  "properties": {
    "iso:country":"US",
    "sg:address":"3102 S Logan St",
    "sg:city":"Englewood",
    "sg:classifiers":[
        {
            "category":"Building & Trades",
            "subcategory":"Landscaping Services",
            "type":"Services"
        }
    ],
    "sg:phone":"+1 303 744 0910",
    "sg:postcode":"80113",
    "sg:province":"CO",
    "sg:tags":[
        "tree"
    ],
    "wof:name":"Rick's Lawn & Tree Svc",
    "wof:placetype":"venue"
},
  "geometry": {"coordinates":[-104.982849,39.658652],"type":"Point"}
}