{
  "type": "Feature",
  "properties": {
    "iso:country":"US",
    "sg:address":"267 6th St",
    "sg:city":"Meeker",
    "sg:classifiers":[
        {
            "category":"Health Services",
            "subcategory":"Hospital",
            "type":"Services"
        }
    ],
    "sg:phone":"+1 970 878 5112",
    "sg:postcode":"81641",
    "sg:province":"CO",
    "sg:tags":[
        "mental"
    ],
    "wof:name":"Rio Blanco Mental Health Ctr",
    "wof:placetype":"venue"
},
  "geometry": {"coordinates":[-107.913579,40.036602],"type":"Point"}
}