{
  "type": "Feature",
  "properties": {
    "iso:country":"US",
    "sg:address":"12405 E Mississippi Ave",
    "sg:city":"Aurora",
    "sg:classifiers":[
        {
            "category":"Restaurant",
            "type":"Food & Drink"
        }
    ],
    "sg:menulink":"http://www.allmenus.com/co/south-aurora/124080-quiznos-sub/menu/",
    "sg:phone":"+1 303 341 2000",
    "sg:postcode":"80012",
    "sg:province":"CO",
    "sg:tags":[
        "wrap",
        "american",
        "sandwich"
    ],
    "wof:name":"Quiznos Sub",
    "wof:placetype":"venue"
},
  "geometry": {"coordinates":[-104.84487799999999,39.696678],"type":"Point"}
}