{
  "type": "Feature",
  "properties": {
    "addr:full":"858 SE Frontage Rd Fort Collins CO 80524",
    "addr:housenumber":"858",
    "addr:postcode":"80524",
    "addr:street":"Se Frontage Rd",
    "iso:country":"US",
    "sg:address":"858 SE Frontage Rd",
    "sg:city":"Fort Collins",
    "sg:classifiers":[
        {
            "category":"Autos & Motor Vehicles",
            "subcategory":"Motorcycle Sales",
            "type":"Retail Goods"
        }
    ],
    "sg:phone":"+1 970 493 8881",
    "sg:postcode":"80524",
    "sg:province":"CO",
    "sg:tags":[
        "repair"
    ],
    "sg:website":"www.interstatehonda.com",
    "wof:name":"Interstate Honda",
    "wof:placetype":"venue"
},
  "geometry": {"coordinates":[-105.000866,40.576151],"type":"Point"}
}