{
  "type": "Feature",
  "properties": {
    "iso:country":"US",
    "sg:address":"724 Main St",
    "sg:city":"Delta",
    "sg:classifiers":[
        {
            "category":"Real Estate",
            "subcategory":"Real Estate Agent",
            "type":"Services"
        }
    ],
    "sg:phone":"+1 970 874 4727",
    "sg:postcode":"81416",
    "sg:province":"CO",
    "wof:name":"Delta County Board of Realtors",
    "wof:placetype":"venue"
},
  "geometry": {"coordinates":[-108.070611,38.73742],"type":"Point"}
}