{
  "type": "Feature",
  "properties": {
    "addr:full":"2833 S Colorado Blvd Denver CO 80222",
    "addr:housenumber":"2833",
    "addr:postcode":"80222",
    "addr:street":"S Colorado Blvd",
    "iso:country":"US",
    "sg:address":"2833 S Colorado Blvd",
    "sg:city":"Denver",
    "sg:classifiers":[
        {
            "category":"Education",
            "subcategory":"Special Training",
            "type":"Public Place"
        }
    ],
    "sg:phone":"+1 303 782 0940",
    "sg:postcode":"80222",
    "sg:province":"CO",
    "sg:tags":[
        "program"
    ],
    "wof:name":"B H Richards & Assoc",
    "wof:placetype":"venue"
},
  "geometry": {"coordinates":[-104.940758,39.66379],"type":"Point"}
}