{
  "type": "Feature",
  "properties": {
    "addr:full":"2120 Academy Cir Colorado Springs CO 80909",
    "addr:housenumber":"2120",
    "addr:postcode":"80909",
    "addr:street":"Academy Cir",
    "iso:country":"US",
    "sg:address":"2120 Academy Cir",
    "sg:city":"Colorado Springs",
    "sg:classifiers":[
        {
            "category":"Insurance",
            "subcategory":"Insurance Agent",
            "type":"Services"
        }
    ],
    "sg:phone":"+1 719 596 7172",
    "sg:postcode":"80909",
    "sg:province":"CO",
    "wof:name":"Farmers Insurance Group",
    "wof:placetype":"venue"
},
  "geometry": {"coordinates":[-104.755848,38.862783],"type":"Point"}
}