{
  "type": "Feature",
  "properties": {
    "iso:country":"US",
    "sg:address":"7860 E Berry Pl",
    "sg:city":"Englewood",
    "sg:classifiers":[
        {
            "category":"Wholesale",
            "subcategory":"Electrical",
            "type":"Manufacturing & Wholesale Goods"
        }
    ],
    "sg:phone":"+1 303 488 0220",
    "sg:postcode":"80111",
    "sg:province":"CO",
    "sg:tags":[
        "electronic"
    ],
    "wof:name":"Technical Mktg Specialists",
    "wof:placetype":"venue"
},
  "geometry": {"coordinates":[-104.898869,39.615615],"type":"Point"}
}