{
  "type": "Feature",
  "properties": {
    "iso:country":"US",
    "sg:address":"1395 Northridge Rd",
    "sg:city":"Littleton",
    "sg:classifiers":[
        {
            "category":"Wholesale",
            "subcategory":"Durable Goods & Equipment",
            "type":"Manufacturing & Wholesale Goods"
        }
    ],
    "sg:phone":"+1 303 791 2671",
    "sg:postcode":"80126",
    "sg:province":"CO",
    "sg:tags":[
        "record",
        "phonograph"
    ],
    "wof:name":"Music Design Inc",
    "wof:placetype":"venue"
},
  "geometry": {"coordinates":[-104.97156200000001,39.560525],"type":"Point"}
}