{
  "type": "Feature",
  "properties": {
    "addr:full":"1321 E 12th Avenue Apt 2 Denver CO 80218",
    "addr:housenumber":"1321;2",
    "addr:postcode":"80218",
    "addr:street":"E 12Th Avenue Apt",
    "iso:country":"US",
    "sg:address":"1321 E 12th Avenue Apt 2",
    "sg:city":"Denver",
    "sg:classifiers":[
        {
            "category":"Professional",
            "subcategory":"Art Services",
            "type":"Services"
        }
    ],
    "sg:phone":"+1 303 832 7115",
    "sg:postcode":"80218",
    "sg:province":"CO",
    "sg:tags":[
        "photographer"
    ],
    "sg:website":"shaffphotography.com",
    "wof:name":"Suzanne Shaff Photography",
    "wof:placetype":"venue"
},
  "geometry": {"coordinates":[-104.971563,39.735204],"type":"Point"}
}