{
  "type": "Feature",
  "properties": {
    "addr:full":"2694 Comanche Creek Dr Brighton CO 80601",
    "addr:housenumber":"2694",
    "addr:postcode":"80601",
    "addr:street":"Comanche Creek Dr",
    "iso:country":"US",
    "sg:address":"2694 Comanche Creek Dr",
    "sg:city":"Brighton",
    "sg:classifiers":[
        {
            "category":"Professional",
            "type":"Services"
        }
    ],
    "sg:phone":"+1 303 655 1692",
    "sg:postcode":"80601",
    "sg:province":"CO",
    "wof:name":"Mikawa LLC",
    "wof:placetype":"venue"
},
  "geometry": {"coordinates":[-104.792226,39.978277],"type":"Point"}
}