{
  "type": "Feature",
  "properties": {
    "iso:country":"US",
    "sg:address":"755 Parfet St",
    "sg:city":"Lakewood",
    "sg:classifiers":[
        {
            "category":"Professional",
            "subcategory":"Business Services",
            "type":"Services"
        }
    ],
    "sg:phone":"+1 303 425 7021",
    "sg:postcode":"80215",
    "sg:province":"CO",
    "sg:tags":[
        "cashing",
        "protection",
        "check",
        "system"
    ],
    "wof:name":"Check Rite",
    "wof:placetype":"venue"
},
  "geometry": {"coordinates":[-105.119518,39.727634],"type":"Point"}
}