{
  "type": "Feature",
  "properties": {
    "iso:country":"US",
    "sg:address":"7720 Allison St",
    "sg:city":"Arvada",
    "sg:classifiers":[
        {
            "category":"Health Services",
            "subcategory":"Nursing And Care Facility",
            "type":"Services"
        }
    ],
    "sg:phone":"+1 303 423 8100",
    "sg:postcode":"80005",
    "sg:province":"CO",
    "wof:name":"Sterling House of Arvada",
    "wof:placetype":"venue"
},
  "geometry": {"coordinates":[-105.085965,39.837752],"type":"Point"}
}