{
  "type": "Feature",
  "properties": {
    "addr:full":"2730 Oro Blanco Dr Colorado Springs CO 80917",
    "addr:housenumber":"2730",
    "addr:postcode":"80917",
    "addr:street":"Oro Blanco Dr",
    "iso:country":"US",
    "sg:address":"2730 Oro Blanco Dr",
    "sg:city":"Colorado Springs",
    "sg:classifiers":[
        {
            "category":"Personal",
            "type":"Services"
        }
    ],
    "sg:phone":"+1 719 597 9890",
    "sg:postcode":"80917",
    "sg:province":"CO",
    "sg:tags":[
        "therapist",
        "massage"
    ],
    "wof:name":"Diversified Mobile Massage",
    "wof:placetype":"venue"
},
  "geometry": {"coordinates":[-104.73661,38.87146],"type":"Point"}
}