{
  "type": "Feature",
  "properties": {
    "iso:country":"US",
    "sg:address":"135 E 13th St",
    "sg:city":"Leadville",
    "sg:classifiers":[
        {
            "category":"Real Estate",
            "subcategory":"Real Estate Agent",
            "type":"Services"
        }
    ],
    "sg:phone":"+1 719 486 1866",
    "sg:postcode":"80461",
    "sg:province":"CO",
    "wof:name":"United Country/Alpine Realty",
    "wof:placetype":"venue"
},
  "geometry": {"coordinates":[-106.292311,39.254538],"type":"Point"}
}