{
  "type": "Feature",
  "properties": {
    "iso:country":"US",
    "sg:address":"912 Clark Rd",
    "sg:city":"Bailey",
    "sg:classifiers":[
        {
            "category":"Professional",
            "type":"Services"
        }
    ],
    "sg:phone":"+1 303 816 9203",
    "sg:postcode":"80421",
    "sg:province":"CO",
    "wof:name":"Randall J Zuniga Inc",
    "wof:placetype":"venue"
},
  "geometry": {"coordinates":[-105.531374,39.508776],"type":"Point"}
}