{
  "type": "Feature",
  "properties": {
    "addr:full":"109 Willow Dr Lyons CO 80540",
    "addr:housenumber":"109",
    "addr:postcode":"80540",
    "addr:street":"Willow Dr",
    "iso:country":"US",
    "sg:address":"109 Willow Dr",
    "sg:city":"Lyons",
    "sg:classifiers":[
        {
            "category":"Professional",
            "type":"Services"
        }
    ],
    "sg:phone":"+1 303 823 6369",
    "sg:postcode":"80540",
    "sg:province":"CO",
    "sg:tags":[
        "establishment"
    ],
    "wof:name":"Big Elk Meadows Assoc",
    "wof:placetype":"venue"
},
  "geometry": {"coordinates":[-105.423649,40.263008],"type":"Point"}
}