{
  "type": "Feature",
  "properties": {
    "iso:country":"US",
    "sg:address":"8121 S Allison Ct",
    "sg:city":"Littleton",
    "sg:classifiers":[
        {
            "category":"Manufacturing",
            "subcategory":"Motor Vehicles & Parts",
            "type":"Manufacturing & Wholesale Goods"
        }
    ],
    "sg:phone":"+1 303 979 4429",
    "sg:postcode":"80128",
    "sg:province":"CO",
    "sg:tags":[
        "mfg"
    ],
    "wof:name":"Eaglepicher Incorporated",
    "wof:placetype":"venue"
},
  "geometry": {"coordinates":[-105.08674499999999,39.568328],"type":"Point"}
}