{
  "type": "Feature",
  "properties": {
    "addr:full":"1035 E Main St Montrose CO 81401",
    "addr:housenumber":"1035",
    "addr:postcode":"81401",
    "addr:street":"E Main St",
    "iso:country":"US",
    "sg:address":"1035 E Main St",
    "sg:city":"Montrose",
    "sg:classifiers":[
        {
            "category":"Restaurant",
            "type":"Food & Drink"
        }
    ],
    "sg:phone":"+1 970 249 3339",
    "sg:postcode":"81401",
    "sg:province":"CO",
    "wof:name":"Mc Donald's",
    "wof:placetype":"venue"
},
  "geometry": {"coordinates":[-107.869827,38.484272],"type":"Point"}
}