{
  "type": "Feature",
  "properties": {
    "addr:full":"1709 Rangeview Dr Fort Collins CO 80524",
    "addr:housenumber":"1709",
    "addr:postcode":"80524",
    "addr:street":"Rangeview Dr",
    "iso:country":"US",
    "sg:address":"1709 Rangeview Dr",
    "sg:city":"Fort Collins",
    "sg:classifiers":[
        {
            "category":"Building & Trades",
            "subcategory":"Equipment Rental",
            "type":"Services"
        }
    ],
    "sg:phone":"+1 970 495 6715",
    "sg:postcode":"80524",
    "sg:province":"CO",
    "sg:tags":[
        "leasing"
    ],
    "wof:name":"Moby Leasing Inc",
    "wof:placetype":"venue"
},
  "geometry": {"coordinates":[-105.044966,40.613361],"type":"Point"}
}