{
  "type": "Feature",
  "properties": {
    "iso:country":"US",
    "sg:address":"3307 S College Ave",
    "sg:city":"Fort Collins",
    "sg:classifiers":[
        {
            "category":"Insurance",
            "subcategory":"Insurance Agent",
            "type":"Services"
        }
    ],
    "sg:phone":"+1 970 206 1808",
    "sg:postcode":"80525",
    "sg:province":"CO",
    "wof:name":"Poudre Valley Insurance Co",
    "wof:placetype":"venue"
},
  "geometry": {"coordinates":[-105.07718800000001,40.540123],"type":"Point"}
}