{
  "type": "Feature",
  "properties": {
    "iso:country":"US",
    "sg:address":"7326 S Yosemite St",
    "sg:city":"Englewood",
    "sg:classifiers":[
        {
            "category":"Freight",
            "type":"Transportation"
        }
    ],
    "sg:phone":"+1 303 843 9711",
    "sg:postcode":"80112",
    "sg:province":"CO",
    "sg:tags":[
        "special"
    ],
    "wof:name":"Riteplace Self Storage",
    "wof:placetype":"venue"
},
  "geometry": {"coordinates":[-104.88555700000001,39.582716],"type":"Point"}
}