{
  "type": "Feature",
  "properties": {
    "iso:country":"US",
    "sg:address":"8301 W 50th Ave",
    "sg:city":"Arvada",
    "sg:classifiers":[
        {
            "category":"Real Estate",
            "subcategory":"Real Estate Operator",
            "type":"Services"
        }
    ],
    "sg:phone":"+1 303 905 2445",
    "sg:postcode":"80002",
    "sg:province":"CO",
    "sg:tags":[
        "building",
        "nonresidential"
    ],
    "wof:name":"Rls Chase Properties LLC",
    "wof:placetype":"venue"
},
  "geometry": {"coordinates":[-105.088081,39.787573],"type":"Point"}
}