{
  "type": "Feature",
  "properties": {
    "addr:full":"3401 W Kentucky Ave Denver CO 80219",
    "addr:housenumber":"3401",
    "addr:postcode":"80219",
    "addr:street":"W Kentucky Ave",
    "iso:country":"US",
    "sg:address":"3401 W Kentucky Ave",
    "sg:city":"Denver",
    "sg:classifiers":[
        {
            "category":"Real Estate",
            "subcategory":"Real Estate Agent",
            "type":"Services"
        }
    ],
    "sg:phone":"+1 303 935 6214",
    "sg:postcode":"80219",
    "sg:province":"CO",
    "sg:tags":[
        "authorities",
        "housing"
    ],
    "wof:name":"Denver Housing Auth Westwood",
    "wof:placetype":"venue"
},
  "geometry": {"coordinates":[-105.031116,39.700416],"type":"Point"}
}