{
  "type": "Feature",
  "properties": {
    "addr:full":"1909 Silversage Ct Estes Park CO 80517",
    "addr:housenumber":"1909",
    "addr:postcode":"80517",
    "addr:street":"Silversage Ct",
    "iso:country":"US",
    "sg:address":"1909 Silversage Ct",
    "sg:city":"Estes Park",
    "sg:classifiers":[
        {
            "category":"Shopping",
            "subcategory":"Gifts & Souvenirs",
            "type":"Retail Goods"
        }
    ],
    "sg:phone":"+1 970 586 9123",
    "sg:postcode":"80517",
    "sg:province":"CO",
    "wof:name":"Mickeys Sports Cards Inc",
    "wof:placetype":"venue"
},
  "geometry": {"coordinates":[-105.55623300000001,40.333297],"type":"Point"}
}