{
  "type": "Feature",
  "properties": {
    "iso:country":"US",
    "sg:address":"737 Denver Ave",
    "sg:city":"Fort Lupton",
    "sg:classifiers":[
        {
            "category":"Coffee & Tea",
            "type":"Food & Drink"
        },
        {
            "category":"Food & Beverages",
            "subcategory":"Bakery",
            "type":"Retail Goods"
        },
        {
            "category":"Bakery",
            "type":"Food & Drink"
        },
        {
            "category":"Donuts",
            "type":"Food & Drink"
        }
    ],
    "sg:menulink":"http://www.allmenus.com/co/fort-lupton/231164-daylight-donuts/menu/",
    "sg:phone":"+1 303 857 2909",
    "sg:postcode":"80621",
    "sg:province":"CO",
    "sg:tags":[
        "tea",
        "coffee",
        "bakery",
        "american",
        "pastry"
    ],
    "wof:name":"Daylight Donuts",
    "wof:placetype":"venue"
},
  "geometry": {"coordinates":[-104.81052099999999,40.086524],"type":"Point"}
}