{
  "type": "Feature",
  "properties": {
    "addr:full":"10140 W Colfax Ave Lakewood CO 80215",
    "addr:housenumber":"10140",
    "addr:postcode":"80215",
    "addr:street":"W Colfax Ave",
    "iso:country":"US",
    "sg:address":"10140 W Colfax Ave",
    "sg:city":"Lakewood",
    "sg:classifiers":[
        {
            "category":"Shopping",
            "subcategory":"Beauty & Cosmetics",
            "type":"Retail Goods"
        }
    ],
    "sg:phone":"+1 303 238 0488",
    "sg:postcode":"80215",
    "sg:province":"CO",
    "sg:tags":[
        "equipment",
        "supply"
    ],
    "sg:website":"http://www.walgreens.com/default.jsp?ec=iyp_yellowpages_trademark",
    "wof:name":"Walgreens Pharmacies",
    "wof:placetype":"venue"
},
  "geometry": {"coordinates":[-105.111441,39.740134],"type":"Point"}
}