{
  "type": "Feature",
  "properties": {
    "addr:full":"8223 S Quebec St Englewood CO 80112",
    "addr:housenumber":"8223",
    "addr:postcode":"80112",
    "addr:street":"S Quebec St",
    "iso:country":"US",
    "sg:address":"8223 S Quebec St",
    "sg:city":"Englewood",
    "sg:classifiers":[
        {
            "category":"Restaurant",
            "type":"Food & Drink"
        }
    ],
    "sg:phone":"+1 303 488 0099",
    "sg:postcode":"80112",
    "sg:province":"CO",
    "sg:tags":[
        "eating"
    ],
    "wof:name":"Subway",
    "wof:placetype":"venue"
},
  "geometry": {"coordinates":[-104.90442899999999,39.567175],"type":"Point"}
}