{
  "type": "Feature",
  "properties": {
    "iso:country":"US",
    "sg:address":"621 17th St",
    "sg:city":"Denver",
    "sg:classifiers":[
        {
            "category":"Professional",
            "subcategory":"Engineering",
            "type":"Services"
        }
    ],
    "sg:phone":"+1 303 295 6670",
    "sg:postcode":"80202",
    "sg:province":"CO",
    "wof:name":"RE Tech + Inc",
    "wof:placetype":"venue"
},
  "geometry": {"coordinates":[-104.990736,39.746033],"type":"Point"}
}