{
  "type": "Feature",
  "properties": {
    "iso:country":"US",
    "sg:address":"1410 Grant St Ste C106",
    "sg:city":"Denver",
    "sg:classifiers":[
        {
            "category":"Health Services",
            "subcategory":"Health Practitioner",
            "type":"Services"
        }
    ],
    "sg:phone":"+1 303 832 0973",
    "sg:postcode":"80203",
    "sg:province":"CO",
    "sg:tags":[
        "therapy",
        "physical"
    ],
    "wof:name":"Therapyhelp Inc",
    "wof:placetype":"venue"
},
  "geometry": {"coordinates":[-104.983391,39.738613],"type":"Point"}
}