{
  "type": "Feature",
  "properties": {
    "addr:full":"326 Bross St Longmont CO 80501",
    "addr:housenumber":"326",
    "addr:postcode":"80501",
    "addr:street":"Bross St",
    "iso:country":"US",
    "sg:address":"326 Bross St",
    "sg:city":"Longmont",
    "sg:classifiers":[
        {
            "category":"Professional",
            "type":"Services"
        }
    ],
    "sg:phone":"+1 303 678 9470",
    "sg:postcode":"80501",
    "sg:province":"CO",
    "wof:name":"Senior Resource Inc",
    "wof:placetype":"venue"
},
  "geometry": {"coordinates":[-105.10847,40.16536],"type":"Point"}
}