{
  "type": "Feature",
  "properties": {
    "iso:country":"US",
    "sg:address":"2080 W Barberry Pl",
    "sg:city":"Denver",
    "sg:classifiers":[
        {
            "category":"Manufacturing",
            "subcategory":"Rubber & Plastics",
            "type":"Manufacturing & Wholesale Goods"
        }
    ],
    "sg:phone":"+1 303 571 5310",
    "sg:postcode":"80204",
    "sg:province":"CO",
    "sg:website":"www.plasticsupplyinc.com",
    "wof:name":"Plastic Supply & Fabrication",
    "wof:placetype":"venue"
},
  "geometry": {"coordinates":[-105.011877,39.730114],"type":"Point"}
}