{
  "type": "Feature",
  "properties": {
    "iso:country":"US",
    "sg:address":"675 E 20th St",
    "sg:city":"Greeley",
    "sg:classifiers":[
        {
            "category":"Organizations",
            "subcategory":"Religious Organization",
            "type":"Services"
        }
    ],
    "sg:phone":"+1 970 352 5563",
    "sg:postcode":"80631",
    "sg:province":"CO",
    "sg:tags":[
        "church"
    ],
    "wof:name":"Christ Christian Church",
    "wof:placetype":"venue"
},
  "geometry": {"coordinates":[-104.6709,40.406537],"type":"Point"}
}