{
  "type": "Feature",
  "properties": {
    "addr:full":"1033 S Gaylord St Denver CO 80209",
    "addr:housenumber":"1033",
    "addr:postcode":"80209",
    "addr:street":"S Gaylord St",
    "iso:country":"US",
    "sg:address":"1033 S Gaylord St",
    "sg:city":"Denver",
    "sg:classifiers":[
        {
            "category":"Manufacturing",
            "subcategory":"Leather Goods",
            "type":"Manufacturing & Wholesale Goods"
        }
    ],
    "sg:phone":"+1 303 744 0200",
    "sg:postcode":"80209",
    "sg:province":"CO",
    "sg:tags":[
        "mfg"
    ],
    "wof:name":"Team 2000",
    "wof:placetype":"venue"
},
  "geometry": {"coordinates":[-104.961817,39.697177],"type":"Point"}
}