{
  "type": "Feature",
  "properties": {
    "iso:country":"US",
    "sg:address":"24 Inverness Pl E",
    "sg:city":"Englewood",
    "sg:classifiers":[
        {
            "category":"Shopping",
            "subcategory":"Computers & Home Electronics",
            "type":"Retail Goods"
        }
    ],
    "sg:phone":"+1 303 790 0852",
    "sg:postcode":"80112",
    "sg:province":"CO",
    "sg:tags":[
        "equipment",
        "dealer"
    ],
    "wof:name":"Hewlett-Packard Co",
    "wof:placetype":"venue"
},
  "geometry": {"coordinates":[-104.860033,39.570698],"type":"Point"}
}