{
  "type": "Feature",
  "properties": {
    "iso:country":"US",
    "sg:address":"2750 Glenwood Dr",
    "sg:city":"Boulder",
    "sg:classifiers":[
        {
            "category":"Restaurant",
            "type":"Food & Drink"
        },
        {
            "category":"Food & Beverages",
            "subcategory":"Bakery",
            "type":"Retail Goods"
        }
    ],
    "sg:phone":"+1 303 447 2220",
    "sg:postcode":"80301",
    "sg:province":"CO",
    "sg:tags":[
        "shop",
        "donut",
        "coffee"
    ],
    "wof:name":"Daylight Donuts",
    "wof:placetype":"venue"
},
  "geometry": {"coordinates":[-105.25851,40.032746],"type":"Point"}
}