{
  "type": "Feature",
  "properties": {
    "addr:full":"300 Nickel St Ste 1 Broomfield CO 80020",
    "addr:housenumber":"300",
    "addr:postcode":"80020",
    "addr:street":"Nickel St Ste 1",
    "iso:country":"US",
    "sg:address":"300 Nickel St Ste 1",
    "sg:city":"Broomfield",
    "sg:classifiers":[
        {
            "category":"Restaurant",
            "type":"Food & Drink"
        }
    ],
    "sg:phone":"+1 303 466 6868",
    "sg:postcode":"80020",
    "sg:province":"CO",
    "sg:tags":[
        "asian",
        "chinese",
        "pan"
    ],
    "wof:name":"Great Wall",
    "wof:placetype":"venue"
},
  "geometry": {"coordinates":[-105.08762400000001,39.920269],"type":"Point"}
}