{
  "type": "Feature",
  "properties": {
    "addr:full":"2695 Davos Trl Vail CO 81657",
    "addr:postcode":"2695;81657",
    "addr:street":"Trl",
    "iso:country":"US",
    "sg:address":"2695 Davos Trl",
    "sg:city":"Vail",
    "sg:classifiers":[
        {
            "category":"Building & Trades",
            "subcategory":"Construction",
            "type":"Services"
        }
    ],
    "sg:phone":"+1 970 479 7350",
    "sg:postcode":"81657",
    "sg:province":"CO",
    "sg:tags":[
        "general",
        "contractor"
    ],
    "wof:name":"Division Six Construction",
    "wof:placetype":"venue"
},
  "geometry": {"coordinates":[-106.428725,39.62496],"type":"Point"}
}