{
  "type": "Feature",
  "properties": {
    "iso:country":"US",
    "sg:address":"9332 Berrey Ln",
    "sg:city":"Colorado Springs",
    "sg:classifiers":[
        {
            "category":"Building & Trades",
            "subcategory":"Construction",
            "type":"Services"
        }
    ],
    "sg:phone":"+1 719 390 7501",
    "sg:postcode":"80925",
    "sg:province":"CO",
    "sg:tags":[
        "house"
    ],
    "wof:name":"Creek Stone Homes",
    "wof:placetype":"venue"
},
  "geometry": {"coordinates":[-104.65091,38.73936],"type":"Point"}
}