{
  "type": "Feature",
  "properties": {
    "addr:full":"1526 E Harmony Rd Fort Collins CO 80525",
    "addr:housenumber":"1526",
    "addr:postcode":"80525",
    "addr:street":"E Harmony Rd",
    "iso:country":"US",
    "sg:address":"1526 E Harmony Rd",
    "sg:city":"Fort Collins",
    "sg:classifiers":[
        {
            "category":"Cinema",
            "subcategory":"Movie Rental",
            "type":"Entertainment"
        }
    ],
    "sg:phone":"+1 970 223 4697",
    "sg:postcode":"80525",
    "sg:province":"CO",
    "sg:tags":[
        "leasing",
        "video",
        "disc",
        "tape"
    ],
    "wof:name":"Blockbuster Video",
    "wof:placetype":"venue"
},
  "geometry": {"coordinates":[-105.05342,40.523734],"type":"Point"}
}