{
  "type": "Feature",
  "properties": {
    "addr:full":"10814 Mountshire Cir Littleton CO 80126",
    "addr:housenumber":"10814",
    "addr:postcode":"80126",
    "addr:street":"Mountshire Cir",
    "iso:country":"US",
    "sg:address":"10814 Mountshire Cir",
    "sg:city":"Littleton",
    "sg:classifiers":[
        {
            "category":"Shopping",
            "subcategory":"Hobbies, Toys, & Games",
            "type":"Retail Goods"
        }
    ],
    "sg:phone":"+1 303 973 2415",
    "sg:postcode":"80126",
    "sg:province":"CO",
    "wof:name":"M M Toys",
    "wof:placetype":"venue"
},
  "geometry": {"coordinates":[-104.956147,39.51973],"type":"Point"}
}