{
  "type": "Feature",
  "properties": {
    "iso:country":"US",
    "sg:address":"19325 Draco Dr",
    "sg:city":"Monument",
    "sg:classifiers":[
        {
            "category":"Professional",
            "type":"Services"
        }
    ],
    "sg:phone":"+1 719 481 9442",
    "sg:postcode":"80132",
    "sg:province":"CO",
    "wof:name":"Finn & Finn LLC",
    "wof:placetype":"venue"
},
  "geometry": {"coordinates":[-104.87528399999999,39.111937],"type":"Point"}
}