{
  "type": "Feature",
  "properties": {
    "iso:country":"US",
    "sg:address":"298 Park Ave",
    "sg:city":"Basalt",
    "sg:classifiers":[
        {
            "category":"Building & Trades",
            "subcategory":"Electrical",
            "type":"Services"
        }
    ],
    "sg:phone":"+1 970 927 4122",
    "sg:postcode":"81621",
    "sg:province":"CO",
    "sg:tags":[
        "electric",
        "contractor"
    ],
    "wof:name":"24/7 Electric Inc",
    "wof:placetype":"venue"
},
  "geometry": {"coordinates":[-107.07934899999999,39.374937],"type":"Point"}
}