{
  "type": "Feature",
  "properties": {
    "iso:country":"US",
    "sg:address":"2525 N 8th St",
    "sg:city":"Grand Junction",
    "sg:classifiers":[
        {
            "category":"Health Services",
            "subcategory":"Doctor",
            "type":"Services"
        }
    ],
    "sg:phone":"+1 970 241 1313",
    "sg:postcode":"81501",
    "sg:province":"CO",
    "sg:tags":[
        "dentist"
    ],
    "wof:name":"Glen R Dean DDS Inc",
    "wof:placetype":"venue"
},
  "geometry": {"coordinates":[-108.55801,39.090748],"type":"Point"}
}