{
  "type": "Feature",
  "properties": {
    "addr:full":"19105 Hwy 82 Carbondale CO 81623",
    "addr:housenumber":"19105",
    "addr:postcode":"81623",
    "addr:street":"Hwy 82",
    "iso:country":"US",
    "sg:address":"19105 Hwy 82",
    "sg:city":"Carbondale",
    "sg:classifiers":[
        {
            "category":"Food & Beverages",
            "subcategory":"Liquor & Beverages",
            "type":"Retail Goods"
        }
    ],
    "sg:phone":"+1 970 963 2466",
    "sg:postcode":"81623",
    "sg:province":"CO",
    "sg:tags":[
        "beer",
        "ale",
        "alcoholic"
    ],
    "wof:name":"El Jebel Liquors",
    "wof:placetype":"venue"
},
  "geometry": {"coordinates":[-107.11372299999999,39.401557],"type":"Point"}
}