{
  "type": "Feature",
  "properties": {
    "addr:full":"2235 S Downing St Denver CO 80210",
    "addr:housenumber":"2235",
    "addr:postcode":"80210",
    "addr:street":"S Downing St",
    "iso:country":"US",
    "sg:address":"2235 S Downing St",
    "sg:city":"Denver",
    "sg:classifiers":[
        {
            "category":"Building & Trades",
            "subcategory":"Construction",
            "type":"Services"
        }
    ],
    "sg:phone":"+1 303 777 3657",
    "sg:postcode":"80210",
    "sg:province":"CO",
    "sg:tags":[
        "residential"
    ],
    "wof:name":"Robert V Doubek Construction",
    "wof:placetype":"venue"
},
  "geometry": {"coordinates":[-104.973545,39.675515],"type":"Point"}
}