{
  "type": "Feature",
  "properties": {
    "iso:country":"US",
    "sg:address":"480 Main St",
    "sg:city":"Ouray",
    "sg:classifiers":[
        {
            "category":"Travel",
            "subcategory":"Hotels & Motels",
            "type":"Entertainment"
        }
    ],
    "sg:phone":"+1 970 325 7252",
    "sg:postcode":"81427",
    "sg:province":"CO",
    "sg:tags":[
        "breakfast",
        "accommodation",
        "bed"
    ],
    "wof:name":"Angel Ridge Ranch Hawks Drift",
    "wof:placetype":"venue"
},
  "geometry": {"coordinates":[-107.67159100000001,38.021187],"type":"Point"}
}