{
  "type": "Feature",
  "properties": {
    "iso:country":"US",
    "sg:address":"5321 S Geneva Way",
    "sg:city":"Englewood",
    "sg:classifiers":[
        {
            "category":"Real Estate",
            "subcategory":"Real Estate Agent",
            "type":"Services"
        }
    ],
    "sg:phone":"+1 303 796 8239",
    "sg:postcode":"80111",
    "sg:province":"CO",
    "wof:name":"Hector Real Estate Ltd",
    "wof:placetype":"venue"
},
  "geometry": {"coordinates":[-104.869528,39.619735],"type":"Point"}
}