{
  "type": "Feature",
  "properties": {
    "iso:country":"US",
    "sg:address":"6630 Monaco St",
    "sg:city":"Commerce City",
    "sg:classifiers":[
        {
            "category":"Wholesale",
            "subcategory":"Vending Machines",
            "type":"Manufacturing & Wholesale Goods"
        },
        {
            "category":"Professional",
            "subcategory":"Management & Consulting",
            "type":"Services"
        }
    ],
    "sg:phone":"+1 303 289 4501",
    "sg:postcode":"80022",
    "sg:province":"CO",
    "sg:tags":[
        "operator",
        "coffee",
        "brewing",
        "devices",
        "business"
    ],
    "wof:name":"Better Brewed Beverages Inc",
    "wof:placetype":"venue"
},
  "geometry": {"coordinates":[-104.912808,39.81744],"type":"Point"}
}