{
  "type": "Feature",
  "properties": {
    "iso:country":"US",
    "sg:address":"1099 18th Street",
    "sg:city":"Denver",
    "sg:classifiers":[
        {
            "category":"Coffee & Tea",
            "type":"Food & Drink"
        }
    ],
    "sg:phone":"+1 303 292 3265",
    "sg:postcode":"80202",
    "sg:province":"CO",
    "sg:website":"www.dazbog.com",
    "wof:name":"Dazbog Coffee",
    "wof:placetype":"venue"
},
  "geometry": {"coordinates":[-104.99329,39.749724],"type":"Point"}
}