{
  "type": "Feature",
  "properties": {
    "addr:full":"2380 Dayton St Aurora CO 80010",
    "addr:housenumber":"2380",
    "addr:postcode":"80010",
    "addr:street":"Dayton St",
    "iso:country":"US",
    "sg:address":"2380 Dayton St",
    "sg:city":"Aurora",
    "sg:classifiers":[
        {
            "category":"Building & Trades",
            "subcategory":"Plumbing",
            "type":"Services"
        }
    ],
    "sg:phone":"+1 303 344 4400",
    "sg:postcode":"80010",
    "sg:province":"CO",
    "sg:tags":[
        "plumbing",
        "contractor",
        "supply"
    ],
    "wof:name":"Aurora Huddleston Plumbing Inc",
    "wof:placetype":"venue"
},
  "geometry": {"coordinates":[-104.875147,39.752162],"type":"Point"}
}