{
  "type": "Feature",
  "properties": {
    "addr:full":"5221 W Colfax Ave Lakewood CO 80214",
    "addr:housenumber":"5221",
    "addr:postcode":"80214",
    "addr:street":"W Colfax Ave",
    "iso:country":"US",
    "sg:address":"5221 W Colfax Ave",
    "sg:city":"Lakewood",
    "sg:classifiers":[
        {
            "category":"Building & Trades",
            "subcategory":"Locksmith",
            "type":"Services"
        }
    ],
    "sg:phone":"+1 303 542 0288",
    "sg:postcode":"80214",
    "sg:province":"CO",
    "sg:tags":[
        "key"
    ],
    "wof:name":"All Around Lockmith",
    "wof:placetype":"venue"
},
  "geometry": {"coordinates":[-105.05342,39.740537],"type":"Point"}
}