{
  "type": "Feature",
  "properties": {
    "iso:country":"US",
    "sg:address":"5206 Allison St",
    "sg:city":"Arvada",
    "sg:classifiers":[
        {
            "category":"Real Estate",
            "subcategory":"Real Estate Operator",
            "type":"Services"
        }
    ],
    "sg:phone":"+1 303 467 0537",
    "sg:postcode":"80002",
    "sg:province":"CO",
    "sg:tags":[
        "apartment"
    ],
    "wof:name":"Allison Court Apartment",
    "wof:placetype":"venue"
},
  "geometry": {"coordinates":[-105.08602999999999,39.792877],"type":"Point"}
}