{
  "type": "Feature",
  "properties": {
    "addr:full":"8895 Tappy Toorie Cir Littleton CO 80129",
    "addr:housenumber":"8895",
    "addr:postcode":"80129",
    "addr:street":"Tappy Toorie Cir",
    "iso:country":"US",
    "sg:address":"8895 Tappy Toorie Cir",
    "sg:city":"Littleton",
    "sg:classifiers":[
        {
            "category":"Professional",
            "subcategory":"Management & Consulting",
            "type":"Services"
        }
    ],
    "sg:phone":"+1 303 791 1042",
    "sg:postcode":"80129",
    "sg:province":"CO",
    "sg:tags":[
        "consultant",
        "business"
    ],
    "wof:name":"Maraia & Assoc Inc",
    "wof:placetype":"venue"
},
  "geometry": {"coordinates":[-105.012888,39.553634],"type":"Point"}
}