{
  "type": "Feature",
  "properties": {
    "iso:country":"US",
    "sg:address":"2171 Summit St",
    "sg:city":"Franktown",
    "sg:classifiers":[
        {
            "category":"Building & Trades",
            "subcategory":"Construction",
            "type":"Services"
        }
    ],
    "sg:phone":"+1 303 688 2614",
    "sg:postcode":"80116",
    "sg:province":"CO",
    "sg:tags":[
        "house"
    ],
    "wof:name":"Kim Pedersen Const Co",
    "wof:placetype":"venue"
},
  "geometry": {"coordinates":[-104.672776,39.332971],"type":"Point"}
}