{
  "type": "Feature",
  "properties": {
    "iso:country":"US",
    "sg:address":"8870 Chipita Park Rd",
    "sg:city":"Cascade",
    "sg:classifiers":[
        {
            "category":"Professional",
            "type":"Services"
        }
    ],
    "sg:phone":"+1 719 684 9725",
    "sg:postcode":"80809",
    "sg:province":"CO",
    "wof:name":"A Jem LLC",
    "wof:placetype":"venue"
},
  "geometry": {"coordinates":[-104.983655,38.915469],"type":"Point"}
}