{
  "type": "Feature",
  "properties": {
    "addr:full":"3462 Larimer St Denver CO 80205",
    "addr:housenumber":"3462",
    "addr:postcode":"80205",
    "addr:street":"Larimer St",
    "iso:country":"US",
    "sg:address":"3462 Larimer St",
    "sg:city":"Denver",
    "sg:classifiers":[
        {
            "category":"Restaurant",
            "type":"Food & Drink"
        }
    ],
    "sg:phone":"+1 303 295 1000",
    "sg:postcode":"80205",
    "sg:province":"CO",
    "sg:tags":[
        "caterer"
    ],
    "wof:name":"Larimer Street Express",
    "wof:placetype":"venue"
},
  "geometry": {"coordinates":[-104.97508999999999,39.766309],"type":"Point"}
}