{
  "type": "Feature",
  "properties": {
    "addr:full":"17998 E Pacific Pl Aurora CO 80013",
    "addr:housenumber":"17998",
    "addr:postcode":"80013",
    "addr:street":"E Pacific Pl",
    "iso:country":"US",
    "sg:address":"17998 E Pacific Pl",
    "sg:city":"Aurora",
    "sg:classifiers":[
        {
            "category":"Restaurant",
            "type":"Food & Drink"
        }
    ],
    "sg:phone":"+1 303 503 4401",
    "sg:postcode":"80013",
    "sg:province":"CO",
    "sg:tags":[
        "eating"
    ],
    "wof:name":"Cheers Mobile Catering",
    "wof:placetype":"venue"
},
  "geometry": {"coordinates":[-104.779588,39.678842],"type":"Point"}
}