{
  "type": "Feature",
  "properties": {
    "addr:full":"9587 S Queenscliffe Dr Littleton CO 80130",
    "addr:housenumber":"9587",
    "addr:postcode":"80130",
    "addr:street":"S Queenscliffe Dr",
    "iso:country":"US",
    "sg:address":"9587 S Queenscliffe Dr",
    "sg:city":"Littleton",
    "sg:classifiers":[
        {
            "category":"Insurance",
            "subcategory":"Insurance Agent",
            "type":"Services"
        }
    ],
    "sg:phone":"+1 303 471 5509",
    "sg:postcode":"80130",
    "sg:province":"CO",
    "wof:name":"Jeff Gardner Insurance Agency",
    "wof:placetype":"venue"
},
  "geometry": {"coordinates":[-104.929546,39.541513],"type":"Point"}
}