{
  "type": "Feature",
  "properties": {
    "iso:country":"US",
    "sg:address":"3022 Evergreen Pkwy",
    "sg:city":"Evergreen",
    "sg:classifiers":[
        {
            "category":"Retail",
            "subcategory":"Auto Repair",
            "type":"Services"
        }
    ],
    "sg:phone":"+1 303 674 2960",
    "sg:postcode":"80439",
    "sg:province":"CO",
    "sg:tags":[
        "repairing",
        "automobile"
    ],
    "wof:name":"Jeff's Auto Repair",
    "wof:placetype":"venue"
},
  "geometry": {"coordinates":[-105.352451,39.659754],"type":"Point"}
}