{
  "type": "Feature",
  "properties": {
    "addr:full":"2499 S Colorado Boulevard Denver CO 80222",
    "addr:housenumber":"2499",
    "addr:postcode":"80222",
    "addr:street":"S Colorado Boulevard",
    "iso:country":"US",
    "sg:address":"2499 S Colorado Boulevard",
    "sg:city":"Denver",
    "sg:classifiers":[
        {
            "category":"Real Estate",
            "subcategory":"Real Estate Operator",
            "type":"Services"
        }
    ],
    "sg:phone":"+1 303 756 5444",
    "sg:postcode":"80222",
    "sg:province":"CO",
    "sg:tags":[
        "apartment"
    ],
    "wof:name":"Wellshire Arms Apts",
    "wof:placetype":"venue"
},
  "geometry": {"coordinates":[-104.940793,39.671751],"type":"Point"}
}