{
  "type": "Feature",
  "properties": {
    "addr:full":"61429 E Co Rd 42 Strasburg CO 80136",
    "addr:housenumber":"61429;42",
    "addr:postcode":"80136",
    "addr:street":"E Co Rd",
    "iso:country":"US",
    "sg:address":"61429 E Co Rd 42",
    "sg:city":"Strasburg",
    "sg:classifiers":[
        {
            "category":"Farming",
            "subcategory":"Farm",
            "type":"Manufacturing & Wholesale Goods"
        }
    ],
    "sg:phone":"+1 303 822 5221",
    "sg:postcode":"80136",
    "sg:province":"CO",
    "sg:tags":[
        "crop",
        "general"
    ],
    "wof:name":"Walter Keen",
    "wof:placetype":"venue"
},
  "geometry": {"coordinates":[-104.286959,39.59379],"type":"Point"}
}