{
  "type": "Feature",
  "properties": {
    "addr:full":"5137a S Yosemite St Englewood CO 80111",
    "addr:housenumber":"5137a",
    "addr:postcode":"80111",
    "addr:street":"S Yosemite St",
    "iso:country":"US",
    "sg:address":"5137a S Yosemite St",
    "sg:city":"Englewood",
    "sg:classifiers":[
        {
            "category":"Restaurant",
            "type":"Food & Drink"
        }
    ],
    "sg:menulink":"http://www.allmenus.com/co/southwest-arapahoe/124515-quiznos-sub/menu/",
    "sg:phone":"+1 720 482 9767",
    "sg:postcode":"80111",
    "sg:province":"CO",
    "sg:tags":[
        "wrap",
        "american",
        "sandwich"
    ],
    "wof:name":"Quiznos Sub",
    "wof:placetype":"venue"
},
  "geometry": {"coordinates":[-104.885372,39.622941],"type":"Point"}
}