{
  "type": "Feature",
  "properties": {
    "iso:country":"US",
    "sg:address":"406 E Colfax Ave",
    "sg:city":"Denver",
    "sg:classifiers":[
        {
            "category":"Restaurant",
            "type":"Food & Drink"
        }
    ],
    "sg:phone":"+1 303 860 7600",
    "sg:postcode":"80203",
    "sg:province":"CO",
    "sg:tags":[
        "chinese"
    ],
    "wof:name":"China Kitchen",
    "wof:placetype":"venue"
},
  "geometry": {"coordinates":[-104.982257,39.740046],"type":"Point"}
}