{
  "type": "Feature",
  "properties": {
    "iso:country":"US",
    "sg:address":"701 Cam del Rio",
    "sg:city":"Durango",
    "sg:classifiers":[
        {
            "category":"Real Estate",
            "subcategory":"Architect",
            "type":"Services"
        }
    ],
    "sg:phone":"+1 970 259 6966",
    "sg:postcode":"81303",
    "sg:province":"CO",
    "wof:name":"Robinson Associates Inc",
    "wof:placetype":"venue"
},
  "geometry": {"coordinates":[-107.883681,37.272881],"type":"Point"}
}