{
  "type": "Feature",
  "properties": {
    "iso:country":"US",
    "sg:address":"2075 S University Blvd Ste 216",
    "sg:city":"Denver",
    "sg:classifiers":[
        {
            "category":"Retail",
            "subcategory":"Repair Shop",
            "type":"Services"
        },
        {
            "category":"Building & Trades",
            "subcategory":"Construction",
            "type":"Services"
        }
    ],
    "sg:phone":"+1 303 452 6467",
    "sg:postcode":"80210",
    "sg:province":"CO",
    "sg:tags":[
        "reupholstery",
        "contractor",
        "furniture"
    ],
    "wof:name":"Home Improvements of Colorado",
    "wof:placetype":"venue"
},
  "geometry": {"coordinates":[-104.959525,39.679071],"type":"Point"}
}