{
  "type": "Feature",
  "properties": {
    "iso:country":"US",
    "sg:address":"9107 Co Rd Kk",
    "sg:city":"Manzanola",
    "sg:phone":"+1 719 462 5660",
    "sg:postcode":"81058",
    "sg:province":"CO",
    "sg:tags":[
        "farm",
        "corn"
    ],
    "wof:name":"Van Sickle William H Farm",
    "wof:placetype":"venue"
},
  "geometry": {"coordinates":[-103.910552,38.112494],"type":"Point"}
}