{
  "type": "Feature",
  "properties": {
    "addr:full":"6537 E 72nd Pl Commerce City CO 80022",
    "addr:housenumber":"6537",
    "addr:postcode":"80022",
    "addr:street":"E 72Nd Pl",
    "iso:country":"US",
    "sg:address":"6537 E 72nd Pl",
    "sg:city":"Commerce City",
    "sg:classifiers":[
        {
            "category":"Health Services",
            "subcategory":"Doctor",
            "type":"Services"
        }
    ],
    "sg:phone":"+1 303 288 6877",
    "sg:postcode":"80022",
    "sg:province":"CO",
    "sg:tags":[
        "dentist"
    ],
    "wof:name":"Commerce City Dental Center",
    "wof:placetype":"venue"
},
  "geometry": {"coordinates":[-104.911091,39.82833],"type":"Point"}
}