{
  "type": "Feature",
  "properties": {
    "iso:country":"US",
    "sg:address":"761 Burning Mountain Ave",
    "sg:city":"New Castle",
    "sg:classifiers":[
        {
            "category":"Personal",
            "subcategory":"Beauty Salon",
            "type":"Services"
        }
    ],
    "sg:phone":"+1 970 984 9730",
    "sg:postcode":"81647",
    "sg:province":"CO",
    "wof:name":"Einnoc's Salon",
    "wof:placetype":"venue"
},
  "geometry": {"coordinates":[-107.52497700000001,39.570761],"type":"Point"}
}