{
  "type": "Feature",
  "properties": {
    "iso:country":"US",
    "sg:address":"7033 E 49th Ave",
    "sg:city":"Commerce City",
    "sg:classifiers":[
        {
            "category":"Food & Beverages",
            "subcategory":"Meat & Fish",
            "type":"Retail Goods"
        }
    ],
    "sg:phone":"+1 303 287 2856",
    "sg:postcode":"80022",
    "sg:province":"CO",
    "sg:tags":[
        "shop"
    ],
    "wof:name":"Speedy Foods",
    "wof:placetype":"venue"
},
  "geometry": {"coordinates":[-104.906998,39.785301],"type":"Point"}
}