{
  "type": "Feature",
  "properties": {
    "iso:country":"US",
    "sg:address":"1805 Shea Center Dr",
    "sg:city":"Littleton",
    "sg:classifiers":[
        {
            "category":"Real Estate",
            "subcategory":"Real Estate Services",
            "type":"Services"
        }
    ],
    "sg:phone":"+1 303 730 1833",
    "sg:postcode":"80129",
    "sg:province":"CO",
    "sg:tags":[
        "company",
        "title"
    ],
    "wof:name":"Security Title Guaranty Co",
    "wof:placetype":"venue"
},
  "geometry": {"coordinates":[-105.008816,39.553201],"type":"Point"}
}