{
  "type": "Feature",
  "properties": {
    "iso:country":"US",
    "sg:address":"2010 16th St",
    "sg:city":"Greeley",
    "sg:classifiers":[
        {
            "category":"Health Services",
            "subcategory":"Doctor",
            "type":"Services"
        }
    ],
    "sg:phone":"+1 970 351 7722",
    "sg:postcode":"80631",
    "sg:province":"CO",
    "sg:tags":[
        "physician",
        "surgeon",
        "medical"
    ],
    "wof:name":"Stanley O Edwards MD",
    "wof:placetype":"venue"
},
  "geometry": {"coordinates":[-104.712036,40.413776],"type":"Point"}
}