{
  "type": "Feature",
  "properties": {
    "addr:full":"10654 US Hwy 6 Gypsum CO 81637",
    "addr:housenumber":"10654",
    "addr:postcode":"81637",
    "addr:street":"Us Hwy 6 Gypsum",
    "iso:country":"US",
    "sg:address":"10654 US Hwy 6",
    "sg:city":"Gypsum",
    "sg:classifiers":[
        {
            "category":"Utilities",
            "subcategory":"Fuel Oil & Lpg",
            "type":"Services"
        }
    ],
    "sg:phone":"+1 970 524 7763",
    "sg:postcode":"81637",
    "sg:province":"CO",
    "sg:tags":[
        "liquefied",
        "gas",
        "petroleum"
    ],
    "wof:name":"AmeriGas",
    "wof:placetype":"venue"
},
  "geometry": {"coordinates":[-106.940128,39.646719],"type":"Point"}
}