{
  "type": "Feature",
  "properties": {
    "iso:country":"US",
    "sg:address":"1050 Walnut Street Suite 210",
    "sg:city":"Boulder",
    "sg:classifiers":[
        {
            "category":"Professional",
            "subcategory":"Computer Services",
            "type":"Services"
        }
    ],
    "sg:postcode":"80302",
    "sg:province":"CO",
    "sg:website":"http://www.themandelbrotproject.com/",
    "wof:name":"Mandelbrot Project",
    "wof:placetype":"venue"
},
  "geometry": {"coordinates":[-105.28134,40.016419],"type":"Point"}
}