{
  "type": "Feature",
  "properties": {
    "addr:full":"1000 Maxwell Ave Boulder CO 80304",
    "addr:housenumber":"1000",
    "addr:postcode":"80304",
    "addr:street":"Maxwell Ave",
    "iso:country":"US",
    "sg:address":"1000 Maxwell Ave",
    "sg:city":"Boulder",
    "sg:classifiers":[
        {
            "category":"Building & Trades",
            "subcategory":"Construction",
            "type":"Services"
        }
    ],
    "sg:phone":"+1 720 406 7617",
    "sg:postcode":"80304",
    "sg:province":"CO",
    "sg:tags":[
        "hanging",
        "contractor"
    ],
    "wof:name":"ONeill & Maclean Painting",
    "wof:placetype":"venue"
},
  "geometry": {"coordinates":[-105.28130400000001,40.021789],"type":"Point"}
}