{
  "type": "Feature",
  "properties": {
    "addr:full":"77 W Airport Rd Aspen CO 81611",
    "addr:housenumber":"77",
    "addr:postcode":"81611",
    "addr:street":"W Airport Rd",
    "iso:country":"US",
    "sg:address":"77 W Airport Rd",
    "sg:city":"Aspen",
    "sg:classifiers":[
        {
            "category":"Building & Trades",
            "subcategory":"Equipment Rental",
            "type":"Services"
        }
    ],
    "sg:phone":"+1 970 925 7510",
    "sg:postcode":"81611",
    "sg:province":"CO",
    "sg:tags":[
        "aircraft",
        "leasing",
        "charter"
    ],
    "sg:website":"www.richmor.com",
    "wof:name":"Richmor Aviation",
    "wof:placetype":"venue"
},
  "geometry": {"coordinates":[-106.86346399999999,39.219499],"type":"Point"}
}