{
  "type": "Feature",
  "properties": {
    "iso:country":"US",
    "sg:address":"1511 E 24th St",
    "sg:city":"Greeley",
    "sg:classifiers":[
        {
            "category":"Building & Trades",
            "subcategory":"Construction",
            "type":"Services"
        }
    ],
    "sg:phone":"+1 970 356 4288",
    "sg:postcode":"80631",
    "sg:province":"CO",
    "sg:tags":[
        "dirt",
        "contractor"
    ],
    "wof:name":"J & Ks Inc",
    "wof:placetype":"venue"
},
  "geometry": {"coordinates":[-104.650148,40.399323],"type":"Point"}
}