{
  "type": "Feature",
  "properties": {
    "addr:full":"109 Main St Breckenridge CO 80424",
    "addr:housenumber":"109",
    "addr:postcode":"80424",
    "addr:street":"Main St",
    "iso:country":"US",
    "sg:address":"109 Main St",
    "sg:city":"Breckenridge",
    "sg:classifiers":[
        {
            "category":"Travel",
            "subcategory":"Hotels & Motels",
            "type":"Entertainment"
        }
    ],
    "sg:phone":"+1 970 453 8200",
    "sg:postcode":"80424",
    "sg:province":"CO",
    "sg:tags":[
        "resort"
    ],
    "sg:website":"www.skivillagelodging.com",
    "wof:name":"Ski Village Resorts",
    "wof:placetype":"venue"
},
  "geometry": {"coordinates":[-106.046201,39.481705],"type":"Point"}
}