{
  "type": "Feature",
  "properties": {
    "iso:country":"US",
    "sg:address":"1208 Bristlecone Pl",
    "sg:city":"Loveland",
    "sg:classifiers":[
        {
            "category":"Home & Garden",
            "subcategory":"Carpets & Floor Coverings",
            "type":"Retail Goods"
        }
    ],
    "sg:phone":"+1 970 669 9686",
    "sg:postcode":"80538",
    "sg:province":"CO",
    "wof:name":"Dillons Carpet Service",
    "wof:placetype":"venue"
},
  "geometry": {"coordinates":[-105.09406199999999,40.431269],"type":"Point"}
}