{
  "type": "Feature",
  "properties": {
    "iso:country":"US",
    "sg:address":"304 W Coal Creek Dr",
    "sg:city":"Louisville",
    "sg:classifiers":[
        {
            "category":"Building & Trades",
            "subcategory":"Construction",
            "type":"Services"
        }
    ],
    "sg:phone":"+1 303 913 1686",
    "sg:postcode":"80027",
    "sg:province":"CO",
    "sg:tags":[
        "nonresidential"
    ],
    "wof:name":"Blackhawk Construction",
    "wof:placetype":"venue"
},
  "geometry": {"coordinates":[-105.170587,39.953988],"type":"Point"}
}