{
  "type": "Feature",
  "properties": {
    "iso:country":"US",
    "sg:address":"2505 W 2nd Ave",
    "sg:city":"Denver",
    "sg:classifiers":[
        {
            "category":"Building & Trades",
            "subcategory":"Locksmith",
            "type":"Services"
        }
    ],
    "sg:phone":"+1 303 218 2491",
    "sg:postcode":"80219",
    "sg:province":"CO",
    "sg:tags":[
        "key"
    ],
    "wof:name":"Sherman and Sons 24 Hr Emerg Locksmith",
    "wof:placetype":"venue"
},
  "geometry": {"coordinates":[-105.01693299999999,39.720397],"type":"Point"}
}