{
  "type": "Feature",
  "properties": {
    "addr:full":"4200 Monaco St Denver CO 80216",
    "addr:housenumber":"4200",
    "addr:postcode":"80216",
    "addr:street":"Monaco St",
    "iso:country":"US",
    "sg:address":"4200 Monaco St",
    "sg:city":"Denver",
    "sg:classifiers":[
        {
            "category":"Freight",
            "type":"Transportation"
        }
    ],
    "sg:phone":"+1 303 780 5440",
    "sg:postcode":"80216",
    "sg:province":"CO",
    "sg:tags":[
        "warehouse"
    ],
    "wof:name":"Kraft Foods",
    "wof:placetype":"venue"
},
  "geometry": {"coordinates":[-104.91288299999999,39.776759],"type":"Point"}
}