{
  "type": "Feature",
  "properties": {
    "addr:full":"229 Prospect St Fort Morgan CO 80701",
    "addr:housenumber":"229",
    "addr:postcode":"morgan;80701",
    "addr:street":"Prospect St",
    "iso:country":"US",
    "sg:address":"229 Prospect St",
    "sg:city":"Fort Morgan",
    "sg:phone":"+1 970 867 2222",
    "sg:postcode":"80701",
    "sg:province":"CO",
    "sg:tags":[
        "irrigation",
        "company"
    ],
    "wof:name":"Bijou Irrigation District & Co",
    "wof:placetype":"venue"
},
  "geometry": {"coordinates":[-103.798576,40.249459],"type":"Point"}
}