{
  "type": "Feature",
  "properties": {
    "addr:full":"5438 S Iola Way Englewood CO 80111",
    "addr:housenumber":"5438",
    "addr:postcode":"80111",
    "addr:street":"S Iola Way",
    "iso:country":"US",
    "sg:address":"5438 S Iola Way",
    "sg:city":"Englewood",
    "sg:classifiers":[
        {
            "category":"Personal",
            "type":"Services"
        }
    ],
    "sg:phone":"+1 303 779 0395",
    "sg:postcode":"80111",
    "sg:province":"CO",
    "sg:tags":[
        "consultant",
        "wedding"
    ],
    "wof:name":"Weddings Etc",
    "wof:placetype":"venue"
},
  "geometry": {"coordinates":[-104.864705,39.617343],"type":"Point"}
}