{
  "type": "Feature",
  "properties": {
    "addr:full":"29940 Chestnut Dr Evergreen CO 80439",
    "addr:housenumber":"29940",
    "addr:postcode":"80439",
    "addr:street":"Chestnut Dr",
    "iso:country":"US",
    "sg:address":"29940 Chestnut Dr",
    "sg:city":"Evergreen",
    "sg:classifiers":[
        {
            "category":"Building & Trades",
            "subcategory":"Construction",
            "type":"Services"
        }
    ],
    "sg:phone":"+1 303 674 8280",
    "sg:postcode":"80439",
    "sg:province":"CO",
    "sg:tags":[
        "house"
    ],
    "wof:name":"Petri Building Design",
    "wof:placetype":"venue"
},
  "geometry": {"coordinates":[-105.33649,39.657366],"type":"Point"}
}