{
  "type": "Feature",
  "properties": {
    "addr:full":"2327 E 3rd Ave Denver CO 80206",
    "addr:housenumber":"2327",
    "addr:postcode":"80206",
    "addr:street":"E 3Rd Ave",
    "iso:country":"US",
    "sg:address":"2327 E 3rd Ave",
    "sg:city":"Denver",
    "sg:classifiers":[
        {
            "category":"Personal",
            "subcategory":"Beauty Salon",
            "type":"Services"
        }
    ],
    "sg:phone":"+1 303 333 5518",
    "sg:postcode":"80206",
    "sg:province":"CO",
    "sg:tags":[
        "manicuring"
    ],
    "wof:name":"Yaya",
    "wof:placetype":"venue"
},
  "geometry": {"coordinates":[-104.95837,39.721053],"type":"Point"}
}