{
  "type": "Feature",
  "properties": {
    "addr:full":"420 Co Rd 64 Craig CO 81625",
    "addr:housenumber":"420;64",
    "addr:postcode":"81625",
    "addr:street":"Co Rd",
    "iso:country":"US",
    "sg:address":"420 Co Rd 64",
    "sg:city":"Craig",
    "sg:classifiers":[
        {
            "category":"Wholesale",
            "subcategory":"Meat",
            "type":"Manufacturing & Wholesale Goods"
        }
    ],
    "sg:phone":"+1 970 824 3855",
    "sg:postcode":"81625",
    "sg:province":"CO",
    "sg:tags":[
        "product"
    ],
    "wof:name":"Brothers Processing",
    "wof:placetype":"venue"
},
  "geometry": {"coordinates":[-107.6186,40.517459],"type":"Point"}
}