{
  "type": "Feature",
  "properties": {
    "addr:full":"51 W Flatiron Crossing Dr Broomfield CO 80021",
    "addr:housenumber":"51",
    "addr:postcode":"80021",
    "addr:street":"W Flatiron Crossing Dr",
    "iso:country":"US",
    "sg:address":"51 W Flatiron Crossing Dr",
    "sg:city":"Broomfield",
    "sg:classifiers":[
        {
            "category":"Shopping",
            "type":"Retail Goods"
        }
    ],
    "sg:phone":"+1 720 887 1010",
    "sg:postcode":"80021",
    "sg:province":"CO",
    "sg:tags":[
        "merchandise"
    ],
    "wof:name":"Lord & Taylor",
    "wof:placetype":"venue"
},
  "geometry": {"coordinates":[-105.13003999999999,39.930566],"type":"Point"}
}