{
  "type": "Feature",
  "properties": {
    "iso:country":"US",
    "sg:address":"720 Hallam Ave",
    "sg:city":"Colorado Springs",
    "sg:classifiers":[
        {
            "category":"Building & Trades",
            "subcategory":"Plumbing",
            "type":"Services"
        }
    ],
    "sg:phone":"+1 719 390 4123",
    "sg:postcode":"80911",
    "sg:province":"CO",
    "sg:tags":[
        "plumbing",
        "contractor"
    ],
    "wof:name":"Medina Plumbing",
    "wof:placetype":"venue"
},
  "geometry": {"coordinates":[-104.738845,38.755422],"type":"Point"}
}