{
  "type": "Feature",
  "properties": {
    "iso:country":"US",
    "sg:address":"50 River Oaks Ln",
    "sg:city":"Basalt",
    "sg:classifiers":[
        {
            "category":"Real Estate",
            "subcategory":"Architect",
            "type":"Services"
        }
    ],
    "sg:phone":"+1 970 927 7656",
    "sg:postcode":"81621",
    "sg:province":"CO",
    "wof:name":"Mary A Avjian Architects",
    "wof:placetype":"venue"
},
  "geometry": {"coordinates":[-107.079548,39.372274],"type":"Point"}
}