{
  "type": "Feature",
  "properties": {
    "addr:full":"4323 N Academy Blvd Colorado Springs CO 80918",
    "addr:housenumber":"4323",
    "addr:postcode":"80918",
    "addr:street":"N Academy Blvd",
    "iso:country":"US",
    "sg:address":"4323 N Academy Blvd",
    "sg:city":"Colorado Springs",
    "sg:classifiers":[
        {
            "category":"Shopping",
            "subcategory":"Used Merchandise",
            "type":"Retail Goods"
        }
    ],
    "sg:phone":"+1 719 260 0725",
    "sg:postcode":"80918",
    "sg:province":"CO",
    "wof:name":"Lets Make A Deal LLC",
    "wof:placetype":"venue"
},
  "geometry": {"coordinates":[-104.759407,38.895411],"type":"Point"}
}