{
  "type": "Feature",
  "properties": {
    "iso:country":"US",
    "sg:address":"835 Glenwood Ave",
    "sg:city":"Grand Junction",
    "sg:classifiers":[
        {
            "category":"Professional",
            "subcategory":"Business Services",
            "type":"Services"
        }
    ],
    "sg:phone":"+1 970 243 2158",
    "sg:postcode":"81501",
    "sg:province":"CO",
    "sg:tags":[
        "translator",
        "interpreter"
    ],
    "wof:name":"Glp Translation & Interpreting",
    "wof:placetype":"venue"
},
  "geometry": {"coordinates":[-108.55931200000001,39.07825],"type":"Point"}
}