{
  "type": "Feature",
  "properties": {
    "addr:full":"549 Dennison Ave Fort Collins CO 80526",
    "addr:housenumber":"549",
    "addr:postcode":"80526",
    "addr:street":"Dennison Ave",
    "iso:country":"US",
    "sg:address":"549 Dennison Ave",
    "sg:city":"Fort Collins",
    "sg:classifiers":[
        {
            "category":"Building & Trades",
            "subcategory":"Construction",
            "type":"Services"
        }
    ],
    "sg:phone":"+1 970 225 1576",
    "sg:postcode":"80526",
    "sg:province":"CO",
    "sg:tags":[
        "carpentry",
        "contractor"
    ],
    "wof:name":"Infinity Home Improvement",
    "wof:placetype":"venue"
},
  "geometry": {"coordinates":[-105.08553499999999,40.534329],"type":"Point"}
}