{
  "type": "Feature",
  "properties": {
    "iso:country":"US",
    "sg:address":"4840 Broadway",
    "sg:city":"Denver",
    "sg:classifiers":[
        {
            "category":"Wholesale",
            "subcategory":"Machinery & Supplies",
            "type":"Manufacturing & Wholesale Goods"
        }
    ],
    "sg:phone":"+1 303 294 0226",
    "sg:postcode":"80216",
    "sg:province":"CO",
    "sg:tags":[
        "equipment",
        "layer",
        "carpet"
    ],
    "sg:website":"www.mountaintradesupply.com",
    "wof:name":"Mountain Trade Supply Inc",
    "wof:placetype":"venue"
},
  "geometry": {"coordinates":[-104.98751300000001,39.784951],"type":"Point"}
}