{
  "type": "Feature",
  "properties": {
    "addr:full":"2551 W 84th Ave Westminster CO 80031",
    "addr:housenumber":"2551",
    "addr:postcode":"80031",
    "addr:street":"W 84Th Ave",
    "iso:country":"US",
    "sg:address":"2551 W 84th Ave",
    "sg:city":"Westminster",
    "sg:classifiers":[
        {
            "category":"Health Services",
            "subcategory":"Doctor",
            "type":"Services"
        }
    ],
    "sg:phone":"+1 303 426 2090",
    "sg:postcode":"80031",
    "sg:province":"CO",
    "sg:tags":[
        "physician",
        "surgeon"
    ],
    "wof:name":"Western Anesthesia",
    "wof:placetype":"venue"
},
  "geometry": {"coordinates":[-105.018992,39.849133],"type":"Point"}
}