{
  "type": "Feature",
  "properties": {
    "addr:full":"118 W Tomichi Ave Gunnison CO 81230",
    "addr:housenumber":"118",
    "addr:postcode":"81230",
    "addr:street":"W Tomichi Ave",
    "iso:country":"US",
    "sg:address":"118 W Tomichi Ave",
    "sg:city":"Gunnison",
    "sg:classifiers":[
        {
            "category":"Shopping",
            "subcategory":"Clothing, Apparel, & Fashions",
            "type":"Retail Goods"
        }
    ],
    "sg:phone":"+1 970 641 4442",
    "sg:postcode":"81230",
    "sg:province":"CO",
    "wof:name":"Rose Petal Out West",
    "wof:placetype":"venue"
},
  "geometry": {"coordinates":[-106.92789,38.544476],"type":"Point"}
}