{
  "type": "Feature",
  "properties": {
    "addr:full":"9341 York St Denver CO 80229",
    "addr:housenumber":"9341",
    "addr:postcode":"80229",
    "addr:street":"York St",
    "iso:country":"US",
    "sg:address":"9341 York St",
    "sg:city":"Denver",
    "sg:classifiers":[
        {
            "category":"Freight",
            "type":"Transportation"
        }
    ],
    "sg:phone":"+1 303 288 2952",
    "sg:postcode":"80229",
    "sg:province":"CO",
    "sg:tags":[
        "operator",
        "local",
        "trucking"
    ],
    "wof:name":"Harpers Trucking LLC",
    "wof:placetype":"venue"
},
  "geometry": {"coordinates":[-104.95907200000001,39.866251],"type":"Point"}
}