{
  "type": "Feature",
  "properties": {
    "addr:full":"4393 S Santa Fe Dr Englewood CO 80110",
    "addr:housenumber":"4393",
    "addr:postcode":"80110",
    "addr:street":"S Santa Fe Dr",
    "iso:country":"US",
    "sg:address":"4393 S Santa Fe Dr",
    "sg:city":"Englewood",
    "sg:classifiers":[
        {
            "category":"Autos & Motor Vehicles",
            "subcategory":"Auto Supplies",
            "type":"Retail Goods"
        },
        {
            "category":"Wholesale",
            "subcategory":"Auto Parts",
            "type":"Manufacturing & Wholesale Goods"
        }
    ],
    "sg:phone":"+1 303 781 7859",
    "sg:postcode":"80110",
    "sg:province":"CO",
    "sg:tags":[
        "repair",
        "used",
        "general",
        "automotive",
        "automobile"
    ],
    "sg:website":"www.svigelauto.com",
    "wof:name":"Svigels Used Auto Parts Inc",
    "wof:placetype":"venue"
},
  "geometry": {"coordinates":[-105.007728,39.636411],"type":"Point"}
}