{
  "type": "Feature",
  "properties": {
    "iso:country":"US",
    "sg:address":"565 S 15th Dr",
    "sg:city":"Brighton",
    "sg:classifiers":[
        {
            "category":"Shopping",
            "subcategory":"Used Merchandise",
            "type":"Retail Goods"
        }
    ],
    "sg:phone":"+1 303 659 6360",
    "sg:postcode":"80601",
    "sg:province":"CO",
    "wof:name":"Radiance",
    "wof:placetype":"venue"
},
  "geometry": {"coordinates":[-104.80260699999999,39.976951],"type":"Point"}
}