{
  "type": "Feature",
  "properties": {
    "iso:country":"US",
    "sg:address":"425 Main St",
    "sg:city":"Sterling",
    "sg:classifiers":[
        {
            "category":"Shopping",
            "subcategory":"Beauty & Cosmetics",
            "type":"Retail Goods"
        }
    ],
    "sg:phone":"+1 970 522 2258",
    "sg:postcode":"80751",
    "sg:province":"CO",
    "sg:tags":[
        "shop",
        "merchandise"
    ],
    "wof:name":"Merle Norman Cosmetics",
    "wof:placetype":"venue"
},
  "geometry": {"coordinates":[-103.211251,40.624946],"type":"Point"}
}