{
  "type": "Feature",
  "properties": {
    "addr:full":"395 S 8th St Colorado Springs CO 80905",
    "addr:housenumber":"395",
    "addr:postcode":"80905",
    "addr:street":"S 8Th St",
    "iso:country":"US",
    "sg:address":"395 S 8th St",
    "sg:city":"Colorado Springs",
    "sg:classifiers":[
        {
            "category":"Restaurant",
            "type":"Food & Drink"
        }
    ],
    "sg:phone":"+1 719 633 5646",
    "sg:postcode":"80905",
    "sg:province":"CO",
    "wof:name":"Waffle House",
    "wof:placetype":"venue"
},
  "geometry": {"coordinates":[-104.84065200000001,38.828673],"type":"Point"}
}