{
  "type": "Feature",
  "properties": {
    "addr:full":"3231 Castle Butte Dr Castle Rock CO 80109",
    "addr:housenumber":"3231",
    "addr:postcode":"80109",
    "addr:street":"Castle Butte Dr",
    "iso:country":"US",
    "sg:address":"3231 Castle Butte Dr",
    "sg:city":"Castle Rock",
    "sg:classifiers":[
        {
            "category":"Building & Trades",
            "subcategory":"Construction",
            "type":"Services"
        }
    ],
    "sg:phone":"+1 303 681 3036",
    "sg:postcode":"80109",
    "sg:province":"CO",
    "sg:tags":[
        "carpentry",
        "contractor"
    ],
    "wof:name":"Rick Craft Cabinets",
    "wof:placetype":"venue"
},
  "geometry": {"coordinates":[-104.92085400000001,39.329499],"type":"Point"}
}