{
  "type": "Feature",
  "properties": {
    "addr:full":"10221 Foxwood Pl Elizabeth CO 80107",
    "addr:housenumber":"10221",
    "addr:postcode":"80107",
    "addr:street":"Foxwood Pl",
    "iso:country":"US",
    "sg:address":"10221 Foxwood Pl",
    "sg:city":"Elizabeth",
    "sg:classifiers":[
        {
            "category":"Professional",
            "subcategory":"Art Services",
            "type":"Services"
        },
        {
            "category":"Manufacturing",
            "subcategory":"Printing",
            "type":"Manufacturing & Wholesale Goods"
        }
    ],
    "sg:phone":"+1 303 805 5744",
    "sg:postcode":"80107",
    "sg:province":"CO",
    "sg:tags":[
        "photographer",
        "lithographic",
        "commercial"
    ],
    "wof:name":"Quick Print Photo Svc",
    "wof:placetype":"venue"
},
  "geometry": {"coordinates":[-104.47327799999999,39.537112],"type":"Point"}
}