{
  "type": "Feature",
  "properties": {
    "iso:country":"US",
    "sg:address":"315 N 5th St",
    "sg:city":"Manassa",
    "sg:classifiers":[
        {
            "category":"Shopping",
            "type":"Retail Goods"
        }
    ],
    "sg:phone":"+1 719 843 0707",
    "sg:postcode":"81141",
    "sg:province":"CO",
    "sg:tags":[
        "monument"
    ],
    "wof:name":"Sowards Monument Co",
    "wof:placetype":"venue"
},
  "geometry": {"coordinates":[-105.937296,37.17882],"type":"Point"}
}