{
  "type": "Feature",
  "properties": {
    "addr:full":"7458 W Chenango Pl Littleton CO 80123",
    "addr:housenumber":"7458",
    "addr:postcode":"80123",
    "addr:street":"W Chenango Pl",
    "iso:country":"US",
    "sg:address":"7458 W Chenango Pl",
    "sg:city":"Littleton",
    "sg:classifiers":[
        {
            "category":"Real Estate",
            "subcategory":"Real Estate Agent",
            "type":"Services"
        }
    ],
    "sg:phone":"+1 303 797 9552",
    "sg:postcode":"80123",
    "sg:province":"CO",
    "wof:name":"Zone Properties",
    "wof:placetype":"venue"
},
  "geometry": {"coordinates":[-105.079274,39.625742],"type":"Point"}
}