{
  "type": "Feature",
  "properties": {
    "iso:country":"US",
    "sg:address":"810 12th St",
    "sg:city":"Greeley",
    "sg:classifiers":[
        {
            "category":"Health Services",
            "subcategory":"Doctor",
            "type":"Services"
        },
        {
            "category":"Social Services",
            "type":"Services"
        },
        {
            "category":"Personal",
            "type":"Services"
        }
    ],
    "sg:phone":"+1 970 352 2857",
    "sg:postcode":"80631",
    "sg:province":"CO",
    "sg:tags":[
        "family",
        "professional",
        "counselors-licensed",
        "psychologist",
        "individual",
        "marriage",
        "child",
        "counseling",
        "counselor"
    ],
    "wof:name":"Connie Ann Jamason",
    "wof:placetype":"venue"
},
  "geometry": {"coordinates":[-104.691058,40.419813],"type":"Point"}
}