{
  "type": "Feature",
  "properties": {
    "iso:country":"US",
    "sg:address":"56620 E Colfax Ave",
    "sg:city":"Strasburg",
    "sg:classifiers":[
        {
            "category":"Personal",
            "subcategory":"Beauty Salon",
            "type":"Services"
        }
    ],
    "sg:phone":"+1 303 622 4247",
    "sg:postcode":"80136",
    "sg:province":"CO",
    "wof:name":"Country Class Salon & Boutique",
    "wof:placetype":"venue"
},
  "geometry": {"coordinates":[-104.32476200000001,39.738431],"type":"Point"}
}