{
  "type": "Feature",
  "properties": {
    "addr:full":"49 Vista St South Fork CO 81154",
    "addr:housenumber":"49",
    "addr:postcode":"81154",
    "addr:street":"Vista St",
    "iso:country":"US",
    "sg:address":"49 Vista St",
    "sg:city":"South Fork",
    "sg:classifiers":[
        {
            "category":"Recreation",
            "type":"Entertainment"
        }
    ],
    "sg:phone":"+1 719 873 5960",
    "sg:postcode":"81154",
    "sg:province":"CO",
    "sg:tags":[
        "equipment",
        "skiing"
    ],
    "wof:name":"Frosty's Ski Shop",
    "wof:placetype":"venue"
},
  "geometry": {"coordinates":[-106.64309299999999,37.667928],"type":"Point"}
}