{
  "type": "Feature",
  "properties": {
    "addr:full":"28 Aspenwood Ln Evergreen CO 80439",
    "addr:housenumber":"28",
    "addr:postcode":"80439",
    "addr:street":"Aspenwood Ln",
    "iso:country":"US",
    "sg:address":"28 Aspenwood Ln",
    "sg:city":"Evergreen",
    "sg:classifiers":[
        {
            "category":"Building & Trades",
            "subcategory":"Construction",
            "type":"Services"
        }
    ],
    "sg:phone":"+1 303 679 9949",
    "sg:postcode":"80439",
    "sg:province":"CO",
    "sg:tags":[
        "contractor"
    ],
    "wof:name":"Alpine Restorations",
    "wof:placetype":"venue"
},
  "geometry": {"coordinates":[-105.410647,39.675388],"type":"Point"}
}