{
  "type": "Feature",
  "properties": {
    "addr:full":"58843 Co Rd X Burlington CO 80807",
    "addr:housenumber":"58843",
    "addr:postcode":"80807",
    "addr:street":"Co Rd X",
    "iso:country":"US",
    "sg:address":"58843 Co Rd X",
    "sg:city":"Burlington",
    "sg:classifiers":[
        {
            "category":"Farming",
            "subcategory":"Farm",
            "type":"Manufacturing & Wholesale Goods"
        }
    ],
    "sg:phone":"+1 719 397 2249",
    "sg:postcode":"80807",
    "sg:province":"CO",
    "wof:name":"Randy Phillips",
    "wof:placetype":"venue"
},
  "geometry": {"coordinates":[-102.08540600000001,39.331319],"type":"Point"}
}