{
  "type": "Feature",
  "properties": {
    "iso:country":"US",
    "sg:address":"1080 W 69th Ave",
    "sg:city":"Denver",
    "sg:classifiers":[
        {
            "category":"Health Services",
            "subcategory":"Nursing And Care Facility",
            "type":"Services"
        }
    ],
    "sg:phone":"+1 303 429 0188",
    "sg:postcode":"80221",
    "sg:province":"CO",
    "sg:tags":[
        "home",
        "retirement",
        "community"
    ],
    "wof:name":"Casa Redonda De Vigil",
    "wof:placetype":"venue"
},
  "geometry": {"coordinates":[-105.001042,39.821808],"type":"Point"}
}