{
  "type": "Feature",
  "properties": {
    "iso:country":"US",
    "sg:address":"5910 E County Line Rd",
    "sg:city":"Littleton",
    "sg:classifiers":[
        {
            "category":"Retail",
            "subcategory":"Auto Repair",
            "type":"Services"
        }
    ],
    "sg:phone":"+1 303 721 0600",
    "sg:postcode":"80126",
    "sg:province":"CO",
    "sg:tags":[
        "automotive",
        "general"
    ],
    "wof:name":"Automotive Engineering Svcs",
    "wof:placetype":"venue"
},
  "geometry": {"coordinates":[-104.918915,39.565972],"type":"Point"}
}