{
  "type": "Feature",
  "properties": {
    "iso:country":"US",
    "sg:address":"2501 King St",
    "sg:city":"Colorado Springs",
    "sg:classifiers":[
        {
            "category":"Professional",
            "type":"Services"
        }
    ],
    "sg:phone":"+1 719 475 1632",
    "sg:postcode":"80904",
    "sg:province":"CO",
    "wof:name":"Where Heart Is Community",
    "wof:placetype":"venue"
},
  "geometry": {"coordinates":[-104.857179,38.855608],"type":"Point"}
}