{
  "type": "Feature",
  "properties": {
    "addr:full":"10253 W 80th Ave Arvada CO 80005",
    "addr:housenumber":"10253",
    "addr:postcode":"80005",
    "addr:street":"W 80Th Ave",
    "iso:country":"US",
    "sg:address":"10253 W 80th Ave",
    "sg:city":"Arvada",
    "sg:classifiers":[
        {
            "category":"Building & Trades",
            "subcategory":"Construction",
            "type":"Services"
        }
    ],
    "sg:phone":"+1 303 467 0028",
    "sg:postcode":"80005",
    "sg:province":"CO",
    "sg:tags":[
        "contractor"
    ],
    "wof:name":"Walt Pierce Drywall LLC",
    "wof:placetype":"venue"
},
  "geometry": {"coordinates":[-105.11439900000001,39.842071],"type":"Point"}
}