{
  "type": "Feature",
  "properties": {
    "addr:full":"12601 Country Meadows Dr Parker CO 80134",
    "addr:housenumber":"12601",
    "addr:postcode":"80134",
    "addr:street":"Country Meadows Dr",
    "iso:country":"US",
    "sg:address":"12601 Country Meadows Dr",
    "sg:city":"Parker",
    "sg:classifiers":[
        {
            "category":"Food & Beverages",
            "subcategory":"Groceries & Convenience Stores",
            "type":"Retail Goods"
        }
    ],
    "sg:phone":"+1 303 841 6083",
    "sg:postcode":"80134",
    "sg:province":"CO",
    "wof:name":"Plaza Delicatessen",
    "wof:placetype":"venue"
},
  "geometry": {"coordinates":[-104.76395100000001,39.495465],"type":"Point"}
}