{
  "type": "Feature",
  "properties": {
    "iso:country":"US",
    "sg:address":"5280 Carr St",
    "sg:city":"Arvada",
    "sg:classifiers":[
        {
            "category":"Wholesale",
            "subcategory":"Plants",
            "type":"Manufacturing & Wholesale Goods"
        }
    ],
    "sg:phone":"+1 303 424 7420",
    "sg:postcode":"80002",
    "sg:province":"CO",
    "sg:tags":[
        "supply"
    ],
    "wof:name":"Calabrese Greenhouse",
    "wof:placetype":"venue"
},
  "geometry": {"coordinates":[-105.090737,39.793178],"type":"Point"}
}