{
  "type": "Feature",
  "properties": {
    "iso:country":"US",
    "sg:address":"67 Spirit Lake Rd",
    "sg:city":"Pine",
    "sg:classifiers":[
        {
            "category":"Professional",
            "subcategory":"Business Services",
            "type":"Services"
        }
    ],
    "sg:phone":"+1 303 384 2116",
    "sg:postcode":"80470",
    "sg:province":"CO",
    "sg:tags":[
        "environmental",
        "ecological",
        "product"
    ],
    "wof:name":"Patricia B Buckley",
    "wof:placetype":"venue"
},
  "geometry": {"coordinates":[-105.427475,39.478951],"type":"Point"}
}