{
  "type": "Feature",
  "properties": {
    "iso:country":"US",
    "sg:address":"895 N 5th Ave",
    "sg:city":"Brighton",
    "sg:classifiers":[
        {
            "category":"Building & Trades",
            "subcategory":"Construction",
            "type":"Services"
        }
    ],
    "sg:phone":"+1 303 655 1475",
    "sg:postcode":"80603",
    "sg:province":"CO",
    "sg:tags":[
        "excavating",
        "contractor"
    ],
    "wof:name":"Badger Daylighting Rocky Mtn",
    "wof:placetype":"venue"
},
  "geometry": {"coordinates":[-104.81725900000001,40.004788],"type":"Point"}
}