{
  "type": "Feature",
  "properties": {
    "addr:full":"420 Ponderosa Dr Boulder CO 80303",
    "addr:housenumber":"420",
    "addr:postcode":"80303",
    "addr:street":"Ponderosa Dr",
    "iso:country":"US",
    "sg:address":"420 Ponderosa Dr",
    "sg:city":"Boulder",
    "sg:classifiers":[
        {
            "category":"Wholesale",
            "subcategory":"Machinery & Supplies",
            "type":"Manufacturing & Wholesale Goods"
        }
    ],
    "sg:phone":"+1 303 499 3191",
    "sg:postcode":"80303",
    "sg:province":"CO",
    "sg:tags":[
        "test",
        "equipment",
        "electronic"
    ],
    "wof:name":"Astec International LLC",
    "wof:placetype":"venue"
},
  "geometry": {"coordinates":[-105.171707,39.984555],"type":"Point"}
}