{
  "type": "Feature",
  "properties": {
    "iso:country":"US",
    "sg:address":"4 Carson Cir",
    "sg:city":"Fountain",
    "sg:classifiers":[
        {
            "category":"Manufacturing",
            "subcategory":"Glass & Minerals",
            "type":"Manufacturing & Wholesale Goods"
        }
    ],
    "sg:phone":"+1 719 391 1404",
    "sg:postcode":"80817",
    "sg:province":"CO",
    "sg:tags":[
        "product",
        "ceramic"
    ],
    "wof:name":"Stinebeck Industries",
    "wof:placetype":"venue"
},
  "geometry": {"coordinates":[-104.728216,38.732072],"type":"Point"}
}