{
  "type": "Feature",
  "properties": {
    "iso:country":"US",
    "sg:address":"4167 S Sherman St",
    "sg:city":"Englewood",
    "sg:classifiers":[
        {
            "category":"Building & Trades",
            "subcategory":"Construction",
            "type":"Services"
        }
    ],
    "sg:phone":"+1 303 985 8494",
    "sg:postcode":"80113",
    "sg:province":"CO",
    "sg:tags":[
        "house"
    ],
    "wof:name":"Mark T Green Construction LLC",
    "wof:placetype":"venue"
},
  "geometry": {"coordinates":[-104.985468,39.641591],"type":"Point"}
}