{
  "type": "Feature",
  "properties": {
    "iso:country":"US",
    "sg:address":"603 S el Paso St",
    "sg:city":"Colorado Springs",
    "sg:classifiers":[
        {
            "category":"Personal",
            "subcategory":"Barber",
            "type":"Services"
        }
    ],
    "sg:phone":"+1 719 632 0027",
    "sg:postcode":"80903",
    "sg:province":"CO",
    "wof:name":"Mr G's Hair Design Studios",
    "wof:placetype":"venue"
},
  "geometry": {"coordinates":[-104.81330199999999,38.824155],"type":"Point"}
}