{
  "type": "Feature",
  "properties": {
    "iso:country":"US",
    "sg:address":"215 W 10th St",
    "sg:city":"Pueblo",
    "sg:classifiers":[
        {
            "category":"Government",
            "subcategory":"Office",
            "type":"Public Place"
        }
    ],
    "sg:phone":"+1 719 583 6629",
    "sg:postcode":"81003",
    "sg:province":"CO",
    "wof:name":"Pueblo County Recorder",
    "wof:placetype":"venue"
},
  "geometry": {"coordinates":[-104.610034,38.276247],"type":"Point"}
}