{
  "type": "Feature",
  "properties": {
    "addr:full":"7826 N Academy Blvd Colorado Springs CO 80920",
    "addr:housenumber":"7826",
    "addr:postcode":"80920",
    "addr:street":"N Academy Blvd",
    "iso:country":"US",
    "sg:address":"7826 N Academy Blvd",
    "sg:city":"Colorado Springs",
    "sg:classifiers":[
        {
            "category":"Insurance",
            "subcategory":"Insurance Agent",
            "type":"Services"
        }
    ],
    "sg:phone":"+1 719 260 5626",
    "sg:postcode":"80920",
    "sg:province":"CO",
    "wof:name":"American Family Insurance",
    "wof:placetype":"venue"
},
  "geometry": {"coordinates":[-104.80146499999999,38.945924],"type":"Point"}
}