{
  "type": "Feature",
  "properties": {
    "addr:full":"8475 W Fairview Ave Littleton CO 80128",
    "addr:housenumber":"8475",
    "addr:postcode":"80128",
    "addr:street":"W Fairview Ave",
    "iso:country":"US",
    "sg:address":"8475 W Fairview Ave",
    "sg:city":"Littleton",
    "sg:classifiers":[
        {
            "category":"Building & Trades",
            "subcategory":"Plumbing",
            "type":"Services"
        }
    ],
    "sg:phone":"+1 303 932 2922",
    "sg:postcode":"80128",
    "sg:province":"CO",
    "sg:tags":[
        "boiler",
        "cleaning"
    ],
    "wof:name":"Industrial Burner Svc Inc",
    "wof:placetype":"venue"
},
  "geometry": {"coordinates":[-105.09296000000001,39.577175],"type":"Point"}
}