{
  "type": "Feature",
  "properties": {
    "addr:full":"5114 Herndon Cir Colorado Springs CO 80920",
    "addr:housenumber":"5114",
    "addr:postcode":"80920",
    "addr:street":"Herndon Cir",
    "iso:country":"US",
    "sg:address":"5114 Herndon Cir",
    "sg:city":"Colorado Springs",
    "sg:classifiers":[
        {
            "category":"Freight",
            "type":"Transportation"
        }
    ],
    "sg:phone":"+1 719 282 8222",
    "sg:postcode":"80920",
    "sg:province":"CO",
    "sg:tags":[
        "trucking"
    ],
    "wof:name":"Tkl Trucking Inc",
    "wof:placetype":"venue"
},
  "geometry": {"coordinates":[-104.730592,38.948975],"type":"Point"}
}