{
  "type": "Feature",
  "properties": {
    "iso:country":"US",
    "sg:address":"503 N Main St",
    "sg:city":"Pueblo",
    "sg:phone":"+1 719 544 8584",
    "sg:postcode":"81003",
    "sg:province":"CO",
    "sg:tags":[
        "irrigation",
        "system"
    ],
    "wof:name":"Bessemer Irrigating Ditch Co",
    "wof:placetype":"venue"
},
  "geometry": {"coordinates":[-104.608692,38.272479],"type":"Point"}
}