{
  "type": "Feature",
  "properties": {
    "addr:full":"549 Main St Grand Junction CO 81501",
    "addr:housenumber":"549",
    "addr:postcode":"81501",
    "addr:street":"Main St",
    "iso:country":"US",
    "sg:address":"549 Main St",
    "sg:city":"Grand Junction",
    "sg:classifiers":[
        {
            "category":"Shopping",
            "subcategory":"Bicycles & Sporting Goods",
            "type":"Retail Goods"
        }
    ],
    "sg:phone":"+1 970 245 7939",
    "sg:postcode":"81501",
    "sg:province":"CO",
    "wof:name":"Brown Cycles",
    "wof:placetype":"venue"
},
  "geometry": {"coordinates":[-108.56356599999999,39.06726],"type":"Point"}
}