{
  "type": "Feature",
  "properties": {
    "iso:country":"US",
    "sg:address":"6901 E Arkansas Ave",
    "sg:city":"Denver",
    "sg:classifiers":[
        {
            "category":"Professional",
            "subcategory":"Computer Services",
            "type":"Services"
        }
    ],
    "sg:phone":"+1 303 756 4565",
    "sg:postcode":"80224",
    "sg:province":"CO",
    "sg:tags":[
        "datum"
    ],
    "sg:website":"www.equitech-inc.com",
    "wof:name":"Equitech Computer Systems Inc",
    "wof:placetype":"venue"
},
  "geometry": {"coordinates":[-104.904273,39.691041],"type":"Point"}
}