{
  "type": "Feature",
  "properties": {
    "iso:country":"US",
    "sg:address":"5770 W Louisiana Ave",
    "sg:city":"Denver",
    "sg:classifiers":[
        {
            "category":"Building & Trades",
            "subcategory":"Plumbing",
            "type":"Services"
        }
    ],
    "sg:phone":"+1 303 936 5064",
    "sg:postcode":"80232",
    "sg:province":"CO",
    "sg:tags":[
        "contractor"
    ],
    "wof:name":"Frasier Valley Plumbing & Htg",
    "wof:placetype":"venue"
},
  "geometry": {"coordinates":[-105.06074700000001,39.692692],"type":"Point"}
}