{
  "type": "Feature",
  "properties": {
    "iso:country":"US",
    "sg:address":"601 Greenwood Ave",
    "sg:city":"Canon City",
    "sg:classifiers":[
        {
            "category":"Social Services",
            "subcategory":"Job Training",
            "type":"Services"
        }
    ],
    "sg:phone":"+1 719 275 1616",
    "sg:postcode":"81212",
    "sg:province":"CO",
    "sg:tags":[
        "rehabilitation"
    ],
    "wof:name":"Starpoint",
    "wof:placetype":"venue"
},
  "geometry": {"coordinates":[-105.23934,38.44338],"type":"Point"}
}