{
  "type": "Feature",
  "properties": {
    "addr:full":"25833 Co Rd 44 Kersey CO 80644",
    "addr:housenumber":"25833;44",
    "addr:postcode":"80644",
    "addr:street":"Co Rd",
    "iso:country":"US",
    "sg:address":"25833 Co Rd 44",
    "sg:city":"Kersey",
    "sg:classifiers":[
        {
            "category":"Freight",
            "type":"Transportation"
        }
    ],
    "sg:phone":"+1 970 284 5831",
    "sg:postcode":"80644",
    "sg:province":"CO",
    "sg:tags":[
        "operator",
        "trucking"
    ],
    "wof:name":"Bar 7 Transportation",
    "wof:placetype":"venue"
},
  "geometry": {"coordinates":[-104.56818699999999,40.305105],"type":"Point"}
}