{
  "type": "Feature",
  "properties": {
    "addr:full":"426 W 1st St Trinidad CO 81082",
    "addr:housenumber":"426",
    "addr:postcode":"81082",
    "addr:street":"W 1St St",
    "iso:country":"US",
    "sg:address":"426 W 1st St",
    "sg:city":"Trinidad",
    "sg:classifiers":[
        {
            "category":"Building & Trades",
            "subcategory":"Construction",
            "type":"Services"
        }
    ],
    "sg:phone":"+1 719 846 7320",
    "sg:postcode":"81082",
    "sg:province":"CO",
    "sg:tags":[
        "excavation",
        "contractor"
    ],
    "wof:name":"Jh Excavating",
    "wof:placetype":"venue"
},
  "geometry": {"coordinates":[-104.507711,37.166534],"type":"Point"}
}