{
  "type": "Feature",
  "properties": {
    "addr:full":"6810 E Lake Cir Englewood CO 80111",
    "addr:housenumber":"6810",
    "addr:postcode":"80111",
    "addr:street":"E Lake Cir",
    "iso:country":"US",
    "sg:address":"6810 E Lake Cir",
    "sg:city":"Englewood",
    "sg:classifiers":[
        {
            "category":"Autos & Motor Vehicles",
            "subcategory":"Auto Supplies",
            "type":"Retail Goods"
        }
    ],
    "sg:phone":"+1 303 850 7322",
    "sg:postcode":"80111",
    "sg:province":"CO",
    "wof:name":"Greenlight SCM Liability C",
    "wof:placetype":"venue"
},
  "geometry": {"coordinates":[-104.910476,39.60705],"type":"Point"}
}