{
  "type": "Feature",
  "properties": {
    "iso:country":"US",
    "sg:address":"23919 High Meadow Dr",
    "sg:city":"Golden",
    "sg:classifiers":[
        {
            "category":"Banks & Credit Unions",
            "subcategory":"Financial Services",
            "type":"Services"
        }
    ],
    "sg:phone":"+1 720 746 1864",
    "sg:postcode":"80401",
    "sg:province":"CO",
    "sg:tags":[
        "investor"
    ],
    "wof:name":"Stsc Investments LLC",
    "wof:placetype":"venue"
},
  "geometry": {"coordinates":[-105.269981,39.699528],"type":"Point"}
}