{
  "type": "Feature",
  "properties": {
    "addr:full":"3880 S Jason St Englewood CO 80110",
    "addr:housenumber":"3880",
    "addr:postcode":"80110",
    "addr:street":"S Jason St",
    "iso:country":"US",
    "sg:address":"3880 S Jason St",
    "sg:city":"Englewood",
    "sg:classifiers":[
        {
            "category":"Retail",
            "subcategory":"Auto Repair",
            "type":"Services"
        }
    ],
    "sg:phone":"+1 303 806 6374",
    "sg:postcode":"80110",
    "sg:province":"CO",
    "sg:tags":[
        "repairing",
        "automobile"
    ],
    "wof:name":"Team Centrix",
    "wof:placetype":"venue"
},
  "geometry": {"coordinates":[-104.99934399999999,39.64728],"type":"Point"}
}