{
  "type": "Feature",
  "properties": {
    "iso:country":"US",
    "sg:address":"938 N College Ave",
    "sg:city":"Fort Collins",
    "sg:classifiers":[
        {
            "category":"Autos & Motor Vehicles",
            "subcategory":"Automobile Sales",
            "type":"Retail Goods"
        }
    ],
    "sg:phone":"+1 970 224 1310",
    "sg:postcode":"80524",
    "sg:province":"CO",
    "sg:tags":[
        "car",
        "dealer"
    ],
    "wof:name":"One Stop Auto Finance",
    "wof:placetype":"venue"
},
  "geometry": {"coordinates":[-105.076577,40.599506],"type":"Point"}
}