{
  "type": "Feature",
  "properties": {
    "addr:full":"72339 US Hwy 40 Tabernash CO 80478",
    "addr:postcode":"72339;80478",
    "addr:street":"Us Hwy 40",
    "iso:country":"US",
    "sg:address":"72339 US Hwy 40",
    "sg:city":"Tabernash",
    "sg:classifiers":[
        {
            "category":"Shopping",
            "subcategory":"Florist",
            "type":"Retail Goods"
        }
    ],
    "sg:phone":"+1 970 726 1273",
    "sg:postcode":"80478",
    "sg:province":"CO",
    "wof:name":"Margaret's Garden",
    "wof:placetype":"venue"
},
  "geometry": {"coordinates":[-105.84261600000001,39.992349],"type":"Point"}
}