{
  "type": "Feature",
  "properties": {
    "addr:full":"108 E Cheyenne Rd Colorado Springs CO 80906",
    "addr:housenumber":"108",
    "addr:postcode":"80906",
    "addr:street":"E Cheyenne Rd",
    "iso:country":"US",
    "sg:address":"108 E Cheyenne Rd",
    "sg:city":"Colorado Springs",
    "sg:classifiers":[
        {
            "category":"Personal",
            "type":"Services"
        }
    ],
    "sg:phone":"+1 719 237 2665",
    "sg:postcode":"80906",
    "sg:province":"CO",
    "sg:tags":[
        "therapist",
        "massage"
    ],
    "wof:name":"Clinical Massage Therapy",
    "wof:placetype":"venue"
},
  "geometry": {"coordinates":[-104.82602300000001,38.806704],"type":"Point"}
}