{
  "type": "Feature",
  "properties": {
    "iso:country":"US",
    "sg:address":"85 S Everett St",
    "sg:city":"Lakewood",
    "sg:classifiers":[
        {
            "category":"Professional",
            "subcategory":"Advertising",
            "type":"Services"
        },
        {
            "category":"Retail",
            "subcategory":"Repair Shop",
            "type":"Services"
        },
        {
            "category":"Manufacturing",
            "subcategory":"Signs",
            "type":"Manufacturing & Wholesale Goods"
        }
    ],
    "sg:phone":"+1 303 237 0393",
    "sg:postcode":"80226",
    "sg:province":"CO",
    "sg:tags":[
        "signs-erectors",
        "hanger",
        "specialty",
        "signs-maintenance"
    ],
    "wof:name":"Metro Signs Services",
    "wof:placetype":"venue"
},
  "geometry": {"coordinates":[-105.096938,39.715098],"type":"Point"}
}