{
  "type": "Feature",
  "properties": {
    "addr:full":"9132 W 81st Ln Arvada CO 80005",
    "addr:housenumber":"9132",
    "addr:postcode":"80005",
    "addr:street":"W 81St Ln",
    "iso:country":"US",
    "sg:address":"9132 W 81st Ln",
    "sg:city":"Arvada",
    "sg:classifiers":[
        {
            "category":"Home & Garden",
            "subcategory":"Carpets & Floor Coverings",
            "type":"Retail Goods"
        }
    ],
    "sg:phone":"+1 303 431 5127",
    "sg:postcode":"80005",
    "sg:province":"CO",
    "sg:tags":[
        "drapery"
    ],
    "wof:name":"Front Range Carpets Interiors",
    "wof:placetype":"venue"
},
  "geometry": {"coordinates":[-105.099412,39.84397],"type":"Point"}
}