{
  "type": "Feature",
  "properties": {
    "iso:country":"US",
    "sg:address":"451 W Agate Ave",
    "sg:city":"Granby",
    "sg:classifiers":[
        {
            "category":"Home & Garden",
            "subcategory":"Hardware",
            "type":"Retail Goods"
        }
    ],
    "sg:phone":"+1 970 887 9003",
    "sg:postcode":"80446",
    "sg:province":"CO",
    "wof:name":"Country Ace Hardware",
    "wof:placetype":"venue"
},
  "geometry": {"coordinates":[-105.946983,40.086291],"type":"Point"}
}