{
  "type": "Feature",
  "properties": {
    "iso:country":"US",
    "sg:address":"311 Detroit St",
    "sg:city":"Denver",
    "sg:classifiers":[
        {
            "category":"Arts & Performance",
            "subcategory":"Art Gallery",
            "type":"Entertainment"
        }
    ],
    "sg:phone":"+1 303 355 7711",
    "sg:postcode":"80206",
    "sg:province":"CO",
    "sg:website":"www.tamoneillfinearts.com",
    "wof:name":"Tam O'Neill Fine Arts",
    "wof:placetype":"venue"
},
  "geometry": {"coordinates":[-104.9546,39.721154],"type":"Point"}
}