{
  "type": "Feature",
  "properties": {
    "iso:country":"US",
    "sg:address":"211 Luxury Ln",
    "sg:city":"Colorado Springs",
    "sg:phone":"+1 719 488 4282",
    "sg:postcode":"80921",
    "sg:province":"CO",
    "sg:tags":[
        "shelving"
    ],
    "wof:name":"Colorado Material Handling",
    "wof:placetype":"venue"
},
  "geometry": {"coordinates":[-104.829712,39.031747],"type":"Point"}
}