{
  "type": "Feature",
  "properties": {
    "iso:country":"US",
    "sg:address":"2121 S Oneida St",
    "sg:city":"Denver",
    "sg:classifiers":[
        {
            "category":"Social Services",
            "type":"Services"
        }
    ],
    "sg:phone":"+1 303 388 7075",
    "sg:postcode":"80224",
    "sg:province":"CO",
    "sg:tags":[
        "counselor",
        "marriage",
        "family"
    ],
    "wof:name":"Affordable Counseling",
    "wof:placetype":"venue"
},
  "geometry": {"coordinates":[-104.908281,39.677731],"type":"Point"}
}