{
  "type": "Feature",
  "properties": {
    "addr:full":"14765 State Hwy 14 Sterling CO 80751",
    "addr:housenumber":"14765",
    "addr:postcode":"80751",
    "addr:street":"State Hwy 14",
    "iso:country":"US",
    "sg:address":"14765 State Hwy 14",
    "sg:city":"Sterling",
    "sg:classifiers":[
        {
            "category":"Mining & Drilling",
            "type":"Manufacturing & Wholesale Goods"
        }
    ],
    "sg:phone":"+1 970 522 8387",
    "sg:postcode":"80751",
    "sg:province":"CO",
    "sg:tags":[
        "field",
        "oil"
    ],
    "wof:name":"Pick Testers",
    "wof:placetype":"venue"
},
  "geometry": {"coordinates":[-103.30095900000001,40.62391],"type":"Point"}
}