{
  "type": "Feature",
  "properties": {
    "iso:country":"US",
    "sg:address":"1153 S Prairie Ave",
    "sg:city":"Pueblo",
    "sg:classifiers":[
        {
            "category":"Food & Beverages",
            "subcategory":"Groceries & Convenience Stores",
            "type":"Retail Goods"
        }
    ],
    "sg:phone":"+1 719 564 8680",
    "sg:postcode":"81005",
    "sg:province":"CO",
    "sg:tags":[
        "grocer"
    ],
    "wof:name":"Avanza",
    "wof:placetype":"venue"
},
  "geometry": {"coordinates":[-104.64387499999999,38.246809],"type":"Point"}
}