{
  "type": "Feature",
  "properties": {
    "addr:full":"977 Queen St Aspen CO 81611",
    "addr:housenumber":"977",
    "addr:postcode":"81611",
    "addr:street":"Queen St",
    "iso:country":"US",
    "sg:address":"977 Queen St",
    "sg:city":"Aspen",
    "sg:classifiers":[
        {
            "category":"Restaurant",
            "type":"Food & Drink"
        }
    ],
    "sg:phone":"+1 970 925 2718",
    "sg:postcode":"81611",
    "sg:province":"CO",
    "sg:tags":[
        "eating"
    ],
    "wof:name":"Pks Popcorn Wagon",
    "wof:placetype":"venue"
},
  "geometry": {"coordinates":[-106.813334,39.189619],"type":"Point"}
}