{
  "type": "Feature",
  "properties": {
    "iso:country":"US",
    "sg:address":"4500 E 9th Ave",
    "sg:city":"Denver",
    "sg:classifiers":[
        {
            "category":"Health Services",
            "subcategory":"Doctor",
            "type":"Services"
        }
    ],
    "sg:phone":"+1 303 399 3315",
    "sg:postcode":"80220",
    "sg:province":"CO",
    "wof:name":"Fertility & Family Planning Associates",
    "wof:placetype":"venue"
},
  "geometry": {"coordinates":[-104.934998,39.730999],"type":"Point"}
}