{
  "type": "Feature",
  "properties": {
    "iso:country":"US",
    "sg:address":"143 Co Rd 9 S",
    "sg:city":"Alpine",
    "sg:classifiers":[
        {
            "category":"Autos & Motor Vehicles",
            "subcategory":"Automobile Sales",
            "type":"Retail Goods"
        }
    ],
    "sg:phone":"+1 201 784 0030",
    "sg:postcode":"81101",
    "sg:province":"CO",
    "sg:tags":[
        "classic"
    ],
    "wof:name":"Cars Of Yesterday Sales",
    "wof:placetype":"venue"
},
  "geometry": {"coordinates":[-106.036812,37.444398],"type":"Point"}
}