{
  "type": "Feature",
  "properties": {
    "iso:country":"US",
    "sg:address":"4785 Elati St Ste 40",
    "sg:city":"Denver",
    "sg:classifiers":[
        {
            "category":"Building & Trades",
            "subcategory":"Equipment Rental",
            "type":"Services"
        }
    ],
    "sg:phone":"+1 303 341 0202",
    "sg:postcode":"80216",
    "sg:province":"CO",
    "sg:tags":[
        "supplies-renting",
        "hospital",
        "wheelchairs-rental"
    ],
    "sg:website":"http://www.allcare.com",
    "wof:name":"Aerocare",
    "wof:placetype":"venue"
},
  "geometry": {"coordinates":[-104.992622,39.783029],"type":"Point"}
}