{
  "type": "Feature",
  "properties": {
    "iso:country":"US",
    "sg:address":"7751 S Carr St",
    "sg:city":"Littleton",
    "sg:classifiers":[
        {
            "category":"Building & Trades",
            "subcategory":"Construction",
            "type":"Services"
        }
    ],
    "sg:phone":"+1 303 948 4988",
    "sg:postcode":"80128",
    "sg:province":"CO",
    "sg:tags":[
        "house"
    ],
    "wof:name":"Bc Log Homes",
    "wof:placetype":"venue"
},
  "geometry": {"coordinates":[-105.091536,39.575158],"type":"Point"}
}