{
  "type": "Feature",
  "properties": {
    "iso:country":"US",
    "sg:address":"220 Smith St",
    "sg:city":"Fort Collins",
    "sg:classifiers":[
        {
            "category":"Insurance",
            "subcategory":"Insurance Agent",
            "type":"Services"
        }
    ],
    "sg:phone":"+1 970 484 2805",
    "sg:postcode":"80524",
    "sg:province":"CO",
    "sg:tags":[
        "agency"
    ],
    "wof:name":"John C Beckett & Associates",
    "wof:placetype":"venue"
},
  "geometry": {"coordinates":[-105.068251,40.584327],"type":"Point"}
}