{
  "type": "Feature",
  "properties": {
    "iso:country":"US",
    "sg:address":"3686 State Hwy 46",
    "sg:city":"Golden",
    "sg:classifiers":[
        {
            "category":"Retail",
            "subcategory":"Animal Services",
            "type":"Services"
        }
    ],
    "sg:phone":"+1 303 582 1662",
    "sg:postcode":"80403",
    "sg:province":"CO",
    "wof:name":"Anne Handy",
    "wof:placetype":"venue"
},
  "geometry": {"coordinates":[-105.475649,39.838934],"type":"Point"}
}