{
  "type": "Feature",
  "properties": {
    "iso:country":"US",
    "sg:address":"1780 S Bellaire Street Suite 330",
    "sg:city":"Denver",
    "sg:classifiers":[
        {
            "category":"Professional",
            "subcategory":"Accounting & Tax Preparation",
            "type":"Services"
        }
    ],
    "sg:phone":"+1 303 991 3311",
    "sg:postcode":"80222",
    "sg:province":"CO",
    "sg:tags":[
        "accountant"
    ],
    "wof:name":"Hess Consulting",
    "wof:placetype":"venue"
},
  "geometry": {"coordinates":[-104.937264,39.684428],"type":"Point"}
}