{
  "type": "Feature",
  "properties": {
    "addr:full":"43052 Cottonwood Creek Rd Crawford CO 81415",
    "addr:housenumber":"43052",
    "addr:postcode":"81415",
    "addr:street":"Cottonwood Creek Rd",
    "iso:country":"US",
    "sg:address":"43052 Cottonwood Creek Rd",
    "sg:city":"Crawford",
    "sg:classifiers":[
        {
            "category":"Building & Trades",
            "subcategory":"Landscaping Services",
            "type":"Services"
        }
    ],
    "sg:phone":"+1 970 921 3656",
    "sg:postcode":"81415",
    "sg:province":"CO",
    "sg:tags":[
        "tree"
    ],
    "wof:name":"Black Canyon Arbor",
    "wof:placetype":"venue"
},
  "geometry": {"coordinates":[-107.558154,38.729033],"type":"Point"}
}