{
  "type": "Feature",
  "properties": {
    "addr:full":"1421 Park Ave Kremmling CO 80459",
    "addr:housenumber":"1421",
    "addr:postcode":"80459",
    "addr:street":"Park Ave",
    "iso:country":"US",
    "sg:address":"1421 Park Ave",
    "sg:city":"Kremmling",
    "sg:classifiers":[
        {
            "category":"Freight",
            "type":"Transportation"
        }
    ],
    "sg:phone":"+1 970 724 3457",
    "sg:postcode":"80459",
    "sg:province":"CO",
    "wof:name":"Home James Transportation",
    "wof:placetype":"venue"
},
  "geometry": {"coordinates":[-106.380673,40.058564],"type":"Point"}
}