{
  "type": "Feature",
  "properties": {
    "iso:country":"US",
    "sg:address":"10471 S Parker Rd",
    "sg:city":"Parker",
    "sg:classifiers":[
        {
            "category":"Autos & Motor Vehicles",
            "subcategory":"Auto Supplies",
            "type":"Retail Goods"
        }
    ],
    "sg:phone":"+1 303 841 2800",
    "sg:postcode":"80134",
    "sg:province":"CO",
    "sg:tags":[
        "automobile",
        "parts"
    ],
    "wof:name":"Carquest Auto Parts",
    "wof:placetype":"venue"
},
  "geometry": {"coordinates":[-104.764972,39.516968],"type":"Point"}
}