{
  "type": "Feature",
  "properties": {
    "addr:full":"9100 N Co Rd 15 Fort Collins CO 80524",
    "addr:housenumber":"9100;15",
    "addr:postcode":"80524",
    "addr:street":"N Co Rd",
    "iso:country":"US",
    "sg:address":"9100 N Co Rd 15",
    "sg:city":"Fort Collins",
    "sg:classifiers":[
        {
            "category":"Retail",
            "subcategory":"Animal Services",
            "type":"Services"
        }
    ],
    "sg:phone":"+1 970 568 0135",
    "sg:postcode":"80524",
    "sg:province":"CO",
    "wof:name":"Fort Collins Protection Dogs",
    "wof:placetype":"venue"
},
  "geometry": {"coordinates":[-105.069187,40.714497],"type":"Point"}
}