{
  "type": "Feature",
  "properties": {
    "iso:country":"US",
    "sg:address":"143 Union Blvd",
    "sg:city":"Denver",
    "sg:classifiers":[
        {
            "category":"Professional",
            "type":"Services"
        },
        {
            "category":"Professional",
            "subcategory":"Management & Consulting",
            "type":"Services"
        }
    ],
    "sg:phone":"+1 303 984 7137",
    "sg:postcode":"80228",
    "sg:province":"CO",
    "sg:tags":[
        "marketing",
        "establishment"
    ],
    "wof:name":"Trippe Marino Inc",
    "wof:placetype":"venue"
},
  "geometry": {"coordinates":[-105.133245,39.71556],"type":"Point"}
}