{
  "type": "Feature",
  "properties": {
    "addr:full":"2613 Ridgecrest Rd Fort Collins CO 80524",
    "addr:housenumber":"2613",
    "addr:postcode":"80524",
    "addr:street":"Ridgecrest Rd",
    "iso:country":"US",
    "sg:address":"2613 Ridgecrest Rd",
    "sg:city":"Fort Collins",
    "sg:classifiers":[
        {
            "category":"Manufacturing",
            "subcategory":"Printing",
            "type":"Manufacturing & Wholesale Goods"
        }
    ],
    "sg:phone":"+1 970 490 8914",
    "sg:postcode":"80524",
    "sg:province":"CO",
    "sg:tags":[
        "screen"
    ],
    "wof:name":"Absolute Graphics Inc",
    "wof:placetype":"venue"
},
  "geometry": {"coordinates":[-105.066231,40.624312],"type":"Point"}
}