{
  "type": "Feature",
  "properties": {
    "iso:country":"US",
    "sg:address":"2625 S Miller Dr",
    "sg:city":"Denver",
    "sg:classifiers":[
        {
            "category":"Food & Beverages",
            "subcategory":"Groceries & Convenience Stores",
            "type":"Retail Goods"
        }
    ],
    "sg:phone":"+1 303 716 2686",
    "sg:postcode":"80227",
    "sg:province":"CO",
    "wof:name":"Di Dis Market",
    "wof:placetype":"venue"
},
  "geometry": {"coordinates":[-105.115357,39.665838],"type":"Point"}
}