{
  "type": "Feature",
  "properties": {
    "addr:full":"762 W 5th Ave Springfield CO 81073",
    "addr:housenumber":"762",
    "addr:postcode":"81073",
    "addr:street":"W 5Th Ave",
    "iso:country":"US",
    "sg:address":"762 W 5th Ave",
    "sg:city":"Springfield",
    "sg:classifiers":[
        {
            "category":"Farming",
            "subcategory":"Farm & Veterinary Services",
            "type":"Manufacturing & Wholesale Goods"
        }
    ],
    "sg:phone":"+1 719 523 4648",
    "sg:postcode":"81073",
    "sg:province":"CO",
    "sg:tags":[
        "aerial",
        "applicator",
        "crop"
    ],
    "wof:name":"Danny Self Aerial Spraying",
    "wof:placetype":"venue"
},
  "geometry": {"coordinates":[-102.624195,37.409218],"type":"Point"}
}