{
  "type": "Feature",
  "properties": {
    "iso:country":"US",
    "sg:address":"2400 S Tejon St",
    "sg:city":"Englewood",
    "sg:classifiers":[
        {
            "category":"Autos & Motor Vehicles",
            "subcategory":"Automobile Sales",
            "type":"Retail Goods"
        },
        {
            "category":"Autos & Motor Vehicles",
            "subcategory":"Auto Supplies",
            "type":"Retail Goods"
        }
    ],
    "sg:phone":"+1 303 934 9326",
    "sg:postcode":"80110",
    "sg:province":"CO",
    "sg:tags":[
        "wheel",
        "transmission",
        "part",
        "salvage",
        "transmissions-other"
    ],
    "sg:website":"http://www.fairautoparts.com",
    "wof:name":"Fair Auto & Truck Parts",
    "wof:placetype":"venue"
},
  "geometry": {"coordinates":[-105.011009,39.67318],"type":"Point"}
}