{
  "type": "Feature",
  "properties": {
    "addr:full":"1475 Forest St Denver CO 80220",
    "addr:housenumber":"1475",
    "addr:postcode":"80220",
    "addr:street":"Forest St",
    "iso:country":"US",
    "sg:address":"1475 Forest St",
    "sg:city":"Denver",
    "sg:classifiers":[
        {
            "category":"Freight",
            "type":"Transportation"
        }
    ],
    "sg:phone":"+1 303 321 3855",
    "sg:postcode":"80220",
    "sg:province":"CO",
    "sg:tags":[
        "general"
    ],
    "wof:name":"Rocky Mountain Warehouse",
    "wof:placetype":"venue"
},
  "geometry": {"coordinates":[-104.92698900000001,39.738746],"type":"Point"}
}