{
  "type": "Feature",
  "properties": {
    "iso:country":"US",
    "sg:address":"8927 Washington St",
    "sg:city":"Thornton",
    "sg:classifiers":[
        {
            "category":"Retail",
            "subcategory":"Animal Services",
            "type":"Services"
        }
    ],
    "sg:phone":"+1 303 287 2383",
    "sg:postcode":"80229",
    "sg:province":"CO",
    "sg:tags":[
        "pet",
        "grooming",
        "washing"
    ],
    "wof:name":"Clip N Yip",
    "wof:placetype":"venue"
},
  "geometry": {"coordinates":[-104.978042,39.857938],"type":"Point"}
}