{
  "type": "Feature",
  "properties": {
    "iso:country":"US",
    "sg:address":"814 9th St",
    "sg:city":"Greeley",
    "sg:classifiers":[
        {
            "category":"Social Services",
            "type":"Services"
        }
    ],
    "sg:phone":"+1 970 356 6751",
    "sg:postcode":"80631",
    "sg:province":"CO",
    "wof:name":"Child Abuse Intervention Inc",
    "wof:placetype":"venue"
},
  "geometry": {"coordinates":[-104.69244999999999,40.42384],"type":"Point"}
}