{
  "type": "Feature",
  "properties": {
    "iso:country":"US",
    "sg:address":"222 W Bridge St",
    "sg:city":"Hotchkiss",
    "sg:classifiers":[
        {
            "category":"Government",
            "subcategory":"Office",
            "type":"Public Place"
        }
    ],
    "sg:phone":"+1 970 872 3039",
    "sg:postcode":"81419",
    "sg:province":"CO",
    "sg:tags":[
        "village"
    ],
    "wof:name":"Hotchkiss Town Shop",
    "wof:placetype":"venue"
},
  "geometry": {"coordinates":[-107.723913,38.799048],"type":"Point"}
}