{
  "type": "Feature",
  "properties": {
    "iso:country":"US",
    "sg:address":"275 Main St",
    "sg:city":"Edwards",
    "sg:classifiers":[
        {
            "category":"Professional",
            "subcategory":"Engineering",
            "type":"Services"
        }
    ],
    "sg:phone":"+1 970 926 9088",
    "sg:postcode":"81641",
    "sg:province":"CO",
    "sg:tags":[
        "engineer"
    ],
    "wof:name":"LKP Engineering Inc",
    "wof:placetype":"venue"
},
  "geometry": {"coordinates":[-107.909019,40.038209],"type":"Point"}
}