{
  "type": "Feature",
  "properties": {
    "iso:country":"US",
    "sg:address":"56481 E Colfax Ave",
    "sg:city":"Strasburg",
    "sg:classifiers":[
        {
            "category":"Real Estate",
            "subcategory":"Real Estate Agent",
            "type":"Services"
        }
    ],
    "sg:phone":"+1 303 622 9227",
    "sg:postcode":"80136",
    "sg:province":"CO",
    "wof:name":"Centennial Realty & Land Co",
    "wof:placetype":"venue"
},
  "geometry": {"coordinates":[-104.324839,39.738355],"type":"Point"}
}