{
  "type": "Feature",
  "properties": {
    "addr:full":"13034 E 14th Ave Aurora CO 80011",
    "addr:housenumber":"13034",
    "addr:postcode":"80011",
    "addr:street":"E 14Th Ave",
    "iso:country":"US",
    "sg:address":"13034 E 14th Ave",
    "sg:city":"Aurora",
    "sg:classifiers":[
        {
            "category":"Building & Trades",
            "subcategory":"Construction",
            "type":"Services"
        }
    ],
    "sg:phone":"+1 720 857 9378",
    "sg:postcode":"80011",
    "sg:province":"CO",
    "sg:tags":[
        "contractor"
    ],
    "wof:name":"Berny Roofing",
    "wof:placetype":"venue"
},
  "geometry": {"coordinates":[-104.83583900000001,39.738836],"type":"Point"}
}