{
  "type": "Feature",
  "properties": {
    "addr:full":"171 W 6th St Glenwood Springs CO 81601",
    "addr:housenumber":"171",
    "addr:postcode":"81601",
    "addr:street":"W 6Th St",
    "iso:country":"US",
    "sg:address":"171 W 6th St",
    "sg:city":"Glenwood Springs",
    "sg:classifiers":[
        {
            "category":"Travel",
            "subcategory":"Hotels & Motels",
            "type":"Entertainment"
        }
    ],
    "sg:phone":"+1 970 945 8535",
    "sg:postcode":"81601",
    "sg:province":"CO",
    "sg:tags":[
        "operation"
    ],
    "wof:name":"Best Western Inn",
    "wof:placetype":"venue"
},
  "geometry": {"coordinates":[-107.329656,39.553529],"type":"Point"}
}