{
  "type": "Feature",
  "properties": {
    "iso:country":"US",
    "sg:address":"5000 E 120th Pl",
    "sg:city":"Denver",
    "sg:classifiers":[
        {
            "category":"Professional",
            "type":"Services"
        }
    ],
    "sg:phone":"+1 303 455 6200",
    "sg:postcode":"80241",
    "sg:province":"CO",
    "wof:name":"James Stanek",
    "wof:placetype":"venue"
},
  "geometry": {"coordinates":[-104.927853,39.91448],"type":"Point"}
}