{
  "type": "Feature",
  "properties": {
    "addr:full":"315 Main St Ordway CO 81063",
    "addr:housenumber":"315",
    "addr:postcode":"81063",
    "addr:street":"Main St",
    "iso:country":"US",
    "sg:address":"315 Main St",
    "sg:city":"Ordway",
    "sg:classifiers":[
        {
            "category":"Government",
            "subcategory":"Office",
            "type":"Public Place"
        }
    ],
    "sg:phone":"+1 719 267 3134",
    "sg:postcode":"81063",
    "sg:province":"CO",
    "sg:tags":[
        "village"
    ],
    "wof:name":"Ordway Clerk",
    "wof:placetype":"venue"
},
  "geometry": {"coordinates":[-103.756531,38.218801],"type":"Point"}
}