{
  "type": "Feature",
  "properties": {
    "addr:full":"1515 Chipeta Ave Grand Junction CO 81501",
    "addr:housenumber":"1515",
    "addr:postcode":"81501",
    "addr:street":"Chipeta Ave",
    "iso:country":"US",
    "sg:address":"1515 Chipeta Ave",
    "sg:city":"Grand Junction",
    "sg:classifiers":[
        {
            "category":"Professional",
            "type":"Services"
        }
    ],
    "sg:phone":"+1 970 242 3241",
    "sg:postcode":"81501",
    "sg:province":"CO",
    "wof:name":"Crystal Clear Drdm Inc",
    "wof:placetype":"venue"
},
  "geometry": {"coordinates":[-108.546706,39.072262],"type":"Point"}
}