{
  "type": "Feature",
  "properties": {
    "iso:country":"US",
    "sg:address":"7002 S Revere Pkwy",
    "sg:city":"Englewood",
    "sg:classifiers":[
        {
            "category":"Wholesale",
            "subcategory":"Wine & Distilled Alcoholic Beverages",
            "type":"Manufacturing & Wholesale Goods"
        }
    ],
    "sg:phone":"+1 303 799 4858",
    "sg:postcode":"80112",
    "sg:province":"CO",
    "wof:name":"House of Seagram",
    "wof:placetype":"venue"
},
  "geometry": {"coordinates":[-104.842394,39.589925],"type":"Point"}
}