{
  "type": "Feature",
  "properties": {
    "iso:country":"US",
    "sg:address":"9085 E Mineral Cir",
    "sg:city":"Centennial",
    "sg:classifiers":[
        {
            "category":"Shopping",
            "subcategory":"Computers & Home Electronics",
            "type":"Retail Goods"
        }
    ],
    "sg:phone":"+1 303 703 1510",
    "sg:postcode":"80112",
    "sg:province":"CO",
    "sg:tags":[
        "software"
    ],
    "sg:website":"www.prototest.com",
    "wof:name":"Proto Test",
    "wof:placetype":"venue"
},
  "geometry": {"coordinates":[-104.88394599999999,39.576157],"type":"Point"}
}