{
  "type": "Feature",
  "properties": {
    "iso:country":"US",
    "sg:address":"4334 Austin Bluffs Pkwy",
    "sg:city":"Colorado Springs",
    "sg:classifiers":[
        {
            "category":"Home & Garden",
            "subcategory":"Household Appliances",
            "type":"Retail Goods"
        },
        {
            "category":"Retail",
            "subcategory":"Repair Shop",
            "type":"Services"
        }
    ],
    "sg:phone":"+1 719 599 3333",
    "sg:postcode":"80918",
    "sg:province":"CO",
    "sg:tags":[
        "cleaners",
        "parts",
        "vacuum"
    ],
    "wof:name":"Austin Bluffs Vacuum Center",
    "wof:placetype":"venue"
},
  "geometry": {"coordinates":[-104.748109,38.896865],"type":"Point"}
}