{
  "type": "Feature",
  "properties": {
    "addr:full":"1506 Westshore Dr Loveland CO 80538",
    "addr:housenumber":"1506",
    "addr:postcode":"80538",
    "addr:street":"Westshore Dr",
    "iso:country":"US",
    "sg:address":"1506 Westshore Dr",
    "sg:city":"Loveland",
    "sg:classifiers":[
        {
            "category":"Building & Trades",
            "subcategory":"Construction",
            "type":"Services"
        }
    ],
    "sg:phone":"+1 970 613 0031",
    "sg:postcode":"80538",
    "sg:province":"CO",
    "sg:tags":[
        "residential"
    ],
    "wof:name":"CRC Development LLC",
    "wof:placetype":"venue"
},
  "geometry": {"coordinates":[-105.09671400000001,40.410043],"type":"Point"}
}