{
  "type": "Feature",
  "properties": {
    "addr:full":"3210 Applewood St Grand Junction CO 81506",
    "addr:housenumber":"3210",
    "addr:postcode":"81506",
    "addr:street":"Applewood St",
    "iso:country":"US",
    "sg:address":"3210 Applewood St",
    "sg:city":"Grand Junction",
    "sg:classifiers":[
        {
            "category":"Shopping",
            "subcategory":"Bicycles & Sporting Goods",
            "type":"Retail Goods"
        }
    ],
    "sg:phone":"+1 970 242 9134",
    "sg:postcode":"81506",
    "sg:province":"CO",
    "wof:name":"T Recs Inc",
    "wof:placetype":"venue"
},
  "geometry": {"coordinates":[-108.537761,39.096585],"type":"Point"}
}