{
  "type": "Feature",
  "properties": {
    "iso:country":"US",
    "sg:address":"383 W 37th St",
    "sg:city":"Loveland",
    "sg:classifiers":[
        {
            "category":"Professional",
            "subcategory":"Accounting & Tax Preparation",
            "type":"Services"
        }
    ],
    "sg:phone":"+1 970 667 1771",
    "sg:postcode":"80538",
    "sg:province":"CO",
    "sg:tags":[
        "payroll"
    ],
    "wof:name":"Premium Payroll & Bookkeeping",
    "wof:placetype":"venue"
},
  "geometry": {"coordinates":[-105.082183,40.43055],"type":"Point"}
}