{
  "type": "Feature",
  "properties": {
    "iso:country":"US",
    "sg:address":"786 Big Elk Rd",
    "sg:city":"Ignacio",
    "sg:classifiers":[
        {
            "category":"Building & Trades",
            "subcategory":"Construction",
            "type":"Services"
        }
    ],
    "sg:phone":"+1 970 883 3290",
    "sg:postcode":"81137",
    "sg:province":"CO",
    "sg:tags":[
        "house"
    ],
    "wof:name":"Solid Rock Builders",
    "wof:placetype":"venue"
},
  "geometry": {"coordinates":[-107.510763,37.048288],"type":"Point"}
}