{
  "type": "Feature",
  "properties": {
    "addr:full":"7840 Pecos St Denver CO 80221",
    "addr:housenumber":"7840",
    "addr:postcode":"80221",
    "addr:street":"Pecos St",
    "iso:country":"US",
    "sg:address":"7840 Pecos St",
    "sg:city":"Denver",
    "sg:classifiers":[
        {
            "category":"Social Services",
            "type":"Services"
        }
    ],
    "sg:phone":"+1 303 853 3400",
    "sg:postcode":"80221",
    "sg:province":"CO",
    "wof:name":"Adolescent Day Treatment",
    "wof:placetype":"venue"
},
  "geometry": {"coordinates":[-105.005932,39.838236],"type":"Point"}
}