{
  "type": "Feature",
  "properties": {
    "addr:full":"1221 S Clarkson Street Suite 208 Denver CO 80210",
    "addr:housenumber":"1221",
    "addr:postcode":"80210",
    "addr:street":"S Clarkson Street Suite 208",
    "iso:country":"US",
    "sg:address":"1221 S Clarkson Street Suite 208",
    "sg:city":"Denver",
    "sg:classifiers":[
        {
            "category":"Professional",
            "subcategory":"Employment Agencies",
            "type":"Services"
        }
    ],
    "sg:phone":"+1 303 398 6035",
    "sg:postcode":"80210",
    "sg:province":"CO",
    "wof:name":"Hirepotential",
    "wof:placetype":"venue"
},
  "geometry": {"coordinates":[-104.97811400000001,39.694559],"type":"Point"}
}