{
  "type": "Feature",
  "properties": {
    "addr:full":"2691 E 121st Pl Denver CO 80241",
    "addr:housenumber":"2691",
    "addr:postcode":"80241",
    "addr:street":"E 121St Pl",
    "iso:country":"US",
    "sg:address":"2691 E 121st Pl",
    "sg:city":"Denver",
    "sg:classifiers":[
        {
            "category":"Shopping",
            "subcategory":"Gifts & Souvenirs",
            "type":"Retail Goods"
        }
    ],
    "sg:phone":"+1 303 920 4499",
    "sg:postcode":"80241",
    "sg:province":"CO",
    "wof:name":"About Baskets Inc",
    "wof:placetype":"venue"
},
  "geometry": {"coordinates":[-104.95332500000001,39.917189],"type":"Point"}
}