{
  "type": "Feature",
  "properties": {
    "iso:country":"US",
    "sg:address":"4827 S Killarney Ct",
    "sg:city":"Aurora",
    "sg:classifiers":[
        {
            "category":"Professional",
            "subcategory":"Accounting & Tax Preparation",
            "type":"Services"
        }
    ],
    "sg:phone":"+1 303 980 1592",
    "sg:postcode":"80015",
    "sg:province":"CO",
    "sg:tags":[
        "accountant"
    ],
    "wof:name":"Puca & Assoc Inc",
    "wof:placetype":"venue"
},
  "geometry": {"coordinates":[-104.747463,39.628875],"type":"Point"}
}