{
  "type": "Feature",
  "properties": {
    "iso:country":"US",
    "sg:address":"830 Lashley St",
    "sg:city":"Longmont",
    "sg:classifiers":[
        {
            "category":"Banks & Credit Unions",
            "subcategory":"Bank",
            "type":"Services"
        }
    ],
    "sg:phone":"+1 303 776 4866",
    "sg:postcode":"80501",
    "sg:province":"CO",
    "sg:tags":[
        "depository",
        "banking",
        "check",
        "cashing"
    ],
    "wof:name":"Correas International Co Inc",
    "wof:placetype":"venue"
},
  "geometry": {"coordinates":[-105.08822499999999,40.173573],"type":"Point"}
}