{
  "type": "Feature",
  "properties": {
    "iso:country":"US",
    "sg:address":"2977 North Ave",
    "sg:city":"Grand Junction",
    "sg:classifiers":[
        {
            "category":"Food & Beverages",
            "subcategory":"Groceries & Convenience Stores",
            "type":"Retail Goods"
        }
    ],
    "sg:phone":"+1 970 242 1202",
    "sg:postcode":"81504",
    "sg:province":"CO",
    "wof:name":"Go-Fer Foods",
    "wof:placetype":"venue"
},
  "geometry": {"coordinates":[-108.500343,39.077456],"type":"Point"}
}