{
  "type": "Feature",
  "properties": {
    "addr:full":"725 S 5th St Grand Junction CO 81501",
    "addr:housenumber":"725",
    "addr:postcode":"81501",
    "addr:street":"S 5Th St",
    "iso:country":"US",
    "sg:address":"725 S 5th St",
    "sg:city":"Grand Junction",
    "sg:phone":"+1 970 242 8118",
    "sg:postcode":"81501",
    "sg:province":"CO",
    "sg:tags":[
        "oil",
        "gasoline"
    ],
    "wof:name":"Grand Valley Oil & Fuel",
    "wof:placetype":"venue"
},
  "geometry": {"coordinates":[-108.56452899999999,39.060896],"type":"Point"}
}