{
  "type": "Feature",
  "properties": {
    "addr:full":"11650 Wadsworth Blvd Broomfield CO 80020",
    "addr:housenumber":"11650",
    "addr:postcode":"80020",
    "addr:street":"Wadsworth Blvd",
    "iso:country":"US",
    "sg:address":"11650 Wadsworth Blvd",
    "sg:city":"Broomfield",
    "sg:classifiers":[
        {
            "category":"Freight",
            "type":"Transportation"
        }
    ],
    "sg:phone":"+1 303 438 9577",
    "sg:postcode":"80020",
    "sg:province":"CO",
    "sg:tags":[
        "commercial",
        "storage"
    ],
    "wof:name":"Wadsworth Mini Storage",
    "wof:placetype":"venue"
},
  "geometry": {"coordinates":[-105.081022,39.909025],"type":"Point"}
}