{
  "type": "Feature",
  "properties": {
    "addr:full":"5051 Sierra Vista Rd Alamosa CO 81101",
    "addr:housenumber":"5051",
    "addr:postcode":"vista;81101",
    "addr:street":"Sierra;Rd",
    "iso:country":"US",
    "sg:address":"5051 Sierra Vista Rd",
    "sg:city":"Alamosa",
    "sg:classifiers":[
        {
            "category":"Government",
            "subcategory":"Fire Station",
            "type":"Public Place"
        }
    ],
    "sg:phone":"+1 719 589 2375",
    "sg:postcode":"81101",
    "sg:province":"CO",
    "sg:tags":[
        "protection",
        "merchandise"
    ],
    "wof:name":"SLV Fire Protection",
    "wof:placetype":"venue"
},
  "geometry": {"coordinates":[-105.94077,37.502606],"type":"Point"}
}