{
  "type": "Feature",
  "properties": {
    "iso:country":"US",
    "sg:address":"6200 Greenwood Plaza Blvd",
    "sg:city":"Greenwood Vlg",
    "sg:classifiers":[
        {
            "category":"Professional",
            "type":"Services"
        }
    ],
    "sg:phone":"+1 303 874 5153",
    "sg:postcode":"80111",
    "sg:province":"CO",
    "sg:tags":[
        "establishment"
    ],
    "wof:name":"Tenor Networks",
    "wof:placetype":"venue"
},
  "geometry": {"coordinates":[-104.894848,39.603383],"type":"Point"}
}