{
  "type": "Feature",
  "properties": {
    "addr:full":"2935 Elizabeth St Denver CO 80205",
    "addr:housenumber":"2935",
    "addr:postcode":"80205",
    "addr:street":"Elizabeth St",
    "iso:country":"US",
    "sg:address":"2935 Elizabeth St",
    "sg:city":"Denver",
    "sg:classifiers":[
        {
            "category":"Building & Trades",
            "subcategory":"Locksmith",
            "type":"Services"
        }
    ],
    "sg:phone":"+1 303 217 8592",
    "sg:postcode":"80205",
    "sg:province":"CO",
    "sg:tags":[
        "key"
    ],
    "wof:name":"Locksmith 1 Always",
    "wof:placetype":"venue"
},
  "geometry": {"coordinates":[-104.956278,39.759093],"type":"Point"}
}