{
  "type": "Feature",
  "properties": {
    "iso:country":"US",
    "sg:address":"654 Spruce St",
    "sg:city":"Red Cliff",
    "sg:classifiers":[
        {
            "category":"Shopping",
            "subcategory":"News",
            "type":"Retail Goods"
        }
    ],
    "sg:phone":"+1 970 827 5680",
    "sg:postcode":"81649",
    "sg:province":"CO",
    "sg:tags":[
        "dealer"
    ],
    "wof:name":"News Vail",
    "wof:placetype":"venue"
},
  "geometry": {"coordinates":[-106.369882,39.508618],"type":"Point"}
}