{
  "type": "Feature",
  "properties": {
    "iso:country":"US",
    "sg:address":"1075 Clogger Ln",
    "sg:city":"Fountain",
    "sg:classifiers":[
        {
            "category":"Organizations",
            "subcategory":"Religious Organization",
            "type":"Services"
        }
    ],
    "sg:phone":"+1 719 382 3022",
    "sg:postcode":"80817",
    "sg:province":"CO",
    "sg:tags":[
        "church"
    ],
    "wof:name":"Fountain Faith Fellowship",
    "wof:placetype":"venue"
},
  "geometry": {"coordinates":[-104.678816,38.666807],"type":"Point"}
}