{
  "type": "Feature",
  "properties": {
    "iso:country":"US",
    "sg:address":"12 S Holman Way",
    "sg:city":"Golden",
    "sg:classifiers":[
        {
            "category":"Real Estate",
            "subcategory":"Real Estate Operator",
            "type":"Services"
        }
    ],
    "sg:phone":"+1 303 278 9563",
    "sg:postcode":"80401",
    "sg:province":"CO",
    "sg:tags":[
        "apartment"
    ],
    "wof:name":"Cliffs At 6th Avenue West",
    "wof:placetype":"venue"
},
  "geometry": {"coordinates":[-105.16382299999999,39.717647],"type":"Point"}
}