{
  "type": "Feature",
  "properties": {
    "iso:country":"US",
    "sg:address":"11170 Peaceful Valley Rd",
    "sg:city":"Colorado Springs",
    "sg:classifiers":[
        {
            "category":"Shopping",
            "type":"Retail Goods"
        }
    ],
    "sg:phone":"+1 719 382 8277",
    "sg:postcode":"80925",
    "sg:province":"CO",
    "sg:tags":[
        "merchandise",
        "business",
        "real estate"
    ],
    "wof:name":"Front Range Auctions",
    "wof:placetype":"venue"
},
  "geometry": {"coordinates":[-104.61971200000001,38.728485],"type":"Point"}
}