{
  "type": "Feature",
  "properties": {
    "addr:full":"4825 S Lemay Ave Fort Collins CO 80525",
    "addr:housenumber":"4825",
    "addr:postcode":"80525",
    "addr:street":"S Lemay Ave",
    "iso:country":"US",
    "sg:address":"4825 S Lemay Ave",
    "sg:city":"Fort Collins",
    "sg:classifiers":[
        {
            "category":"Organizations",
            "subcategory":"Religious Organization",
            "type":"Services"
        }
    ],
    "sg:phone":"+1 970 223 6507",
    "sg:postcode":"80525",
    "sg:province":"CO",
    "wof:name":"Evangelical Covenant Church",
    "wof:placetype":"venue"
},
  "geometry": {"coordinates":[-105.058125,40.519292],"type":"Point"}
}