{
  "type": "Feature",
  "properties": {
    "iso:country":"US",
    "sg:address":"2229 Larimer St",
    "sg:city":"Denver",
    "sg:classifiers":[
        {
            "category":"Personal",
            "subcategory":"Tattoo Parlor",
            "type":"Services"
        }
    ],
    "sg:phone":"+1 303 296 0447",
    "sg:postcode":"80205",
    "sg:province":"CO",
    "wof:name":"Old Larimer Street Tattoo",
    "wof:placetype":"venue"
},
  "geometry": {"coordinates":[-104.989926,39.755204],"type":"Point"}
}