{
  "type": "Feature",
  "properties": {
    "addr:full":"1660 S Albion St Denver CO 80222",
    "addr:housenumber":"1660",
    "addr:postcode":"80222",
    "addr:street":"S Albion St",
    "iso:country":"US",
    "sg:address":"1660 S Albion St",
    "sg:city":"Denver",
    "sg:classifiers":[
        {
            "category":"Real Estate",
            "subcategory":"Real Estate Agent",
            "type":"Services"
        }
    ],
    "sg:phone":"+1 303 333 9000",
    "sg:postcode":"80222",
    "sg:province":"CO",
    "sg:tags":[
        "investment"
    ],
    "sg:website":"www.netleasedrealestate.com",
    "wof:name":"Fourteen Hundred Group",
    "wof:placetype":"venue"
},
  "geometry": {"coordinates":[-104.93938799999999,39.686246],"type":"Point"}
}