{
  "type": "Feature",
  "properties": {
    "addr:full":"124 Niagara St Denver CO 80220",
    "addr:housenumber":"124",
    "addr:postcode":"80220",
    "addr:street":"Niagara St",
    "iso:country":"US",
    "sg:address":"124 Niagara St",
    "sg:city":"Denver",
    "sg:classifiers":[
        {
            "category":"Building & Trades",
            "subcategory":"Construction",
            "type":"Services"
        }
    ],
    "sg:phone":"+1 720 435 2757",
    "sg:postcode":"80220",
    "sg:province":"CO",
    "sg:tags":[
        "handyman"
    ],
    "sg:website":"www.gogreenenergysolutions.net",
    "wof:name":"Green Energy Solutions",
    "wof:placetype":"venue"
},
  "geometry": {"coordinates":[-104.91039499999999,39.718861],"type":"Point"}
}