{
  "type": "Feature",
  "properties": {
    "addr:full":"1911 Pearl St Boulder CO 80302",
    "addr:housenumber":"1911",
    "addr:postcode":"80302",
    "addr:street":"Pearl St",
    "iso:country":"US",
    "sg:address":"1911 Pearl St",
    "sg:city":"Boulder",
    "sg:classifiers":[
        {
            "category":"Shopping",
            "subcategory":"Stationery & Office Supplies",
            "type":"Retail Goods"
        },
        {
            "category":"Shopping",
            "subcategory":"Gifts & Souvenirs",
            "type":"Retail Goods"
        }
    ],
    "sg:phone":"+1 303 443 1606",
    "sg:postcode":"80302",
    "sg:province":"CO",
    "sg:tags":[
        "stationer",
        "invitation"
    ],
    "wof:name":"Envelope Please The",
    "wof:placetype":"venue"
},
  "geometry": {"coordinates":[-105.269643,40.020016],"type":"Point"}
}