{
  "type": "Feature",
  "properties": {
    "iso:country":"US",
    "sg:address":"305 Comanche St",
    "sg:city":"Kiowa",
    "sg:classifiers":[
        {
            "category":"Real Estate",
            "subcategory":"Real Estate Services",
            "type":"Services"
        }
    ],
    "sg:phone":"+1 303 621 2079",
    "sg:postcode":"80117",
    "sg:province":"CO",
    "sg:tags":[
        "company",
        "title"
    ],
    "wof:name":"Elbert County Abstract & Title",
    "wof:placetype":"venue"
},
  "geometry": {"coordinates":[-104.466086,39.346662],"type":"Point"}
}