{
  "type": "Feature",
  "properties": {
    "addr:full":"691 Corporate Circle Golden CO 80401",
    "addr:housenumber":"691",
    "addr:postcode":"80401",
    "addr:street":"Corporate Circle",
    "iso:country":"US",
    "sg:address":"691 Corporate Circle",
    "sg:city":"Golden",
    "sg:classifiers":[
        {
            "category":"Professional",
            "subcategory":"Computer Services",
            "type":"Services"
        }
    ],
    "sg:phone":"+1 877 946 4487",
    "sg:postcode":"80401",
    "sg:province":"CO",
    "sg:tags":[
        "marketing-automation",
        "demand-generation",
        "b2b-marketing",
        "b2c-marketing",
        "lead-generation",
        "optimization",
        "analytics",
        "email-marketing",
        "lead-scoring",
        "lead-nurturing",
        "drip-marketing",
        "saas",
        "web-intelligence",
        "visitor-tracking"
    ],
    "sg:website":"http://www.Net-Results.com",
    "wof:name":"Net-Results",
    "wof:placetype":"venue"
},
  "geometry": {"coordinates":[-105.19422400000001,39.718006],"type":"Point"}
}