{
  "type": "Feature",
  "properties": {
    "addr:full":"7575 E Arkansas Ave Denver CO 80231",
    "addr:housenumber":"7575",
    "addr:postcode":"80231",
    "addr:street":"E Arkansas Ave",
    "iso:country":"US",
    "sg:address":"7575 E Arkansas Ave",
    "sg:city":"Denver",
    "sg:classifiers":[
        {
            "category":"Building & Trades",
            "subcategory":"Locksmith",
            "type":"Services"
        }
    ],
    "sg:phone":"+1 303 242 3005",
    "sg:postcode":"80231",
    "sg:province":"CO",
    "sg:tags":[
        "key"
    ],
    "wof:name":"Numero Uno 24 Hr Locksmith",
    "wof:placetype":"venue"
},
  "geometry": {"coordinates":[-104.901242,39.691767],"type":"Point"}
}