{
  "type": "Feature",
  "properties": {
    "iso:country":"US",
    "sg:address":"2249 Old Quarry Rd",
    "sg:city":"Golden",
    "sg:classifiers":[
        {
            "category":"Building & Trades",
            "subcategory":"Construction",
            "type":"Services"
        }
    ],
    "sg:phone":"+1 303 274 0727",
    "sg:postcode":"80401",
    "sg:province":"CO",
    "sg:tags":[
        "concrete",
        "contractor"
    ],
    "wof:name":"Jeffco Concrete",
    "wof:placetype":"venue"
},
  "geometry": {"coordinates":[-105.159198,39.750633],"type":"Point"}
}