{
  "type": "Feature",
  "properties": {
    "addr:full":"5255 W 98th Ave Broomfield CO 80020",
    "addr:housenumber":"5255",
    "addr:postcode":"80020",
    "addr:street":"W 98Th Ave",
    "iso:country":"US",
    "sg:address":"5255 W 98th Ave",
    "sg:city":"Broomfield",
    "sg:classifiers":[
        {
            "category":"Education",
            "subcategory":"School",
            "type":"Public Place"
        }
    ],
    "sg:phone":"+1 303 466 1673",
    "sg:postcode":"80020",
    "sg:province":"CO",
    "wof:name":"Hyland Christian School",
    "wof:placetype":"venue"
},
  "geometry": {"coordinates":[-105.059741,39.874577],"type":"Point"}
}