{
  "type": "Feature",
  "properties": {
    "iso:country":"US",
    "sg:address":"4891 Independence St",
    "sg:city":"Wheat Ridge",
    "sg:classifiers":[
        {
            "category":"Professional",
            "subcategory":"Accounting & Tax Preparation",
            "type":"Services"
        }
    ],
    "sg:phone":"+1 303 456 1120",
    "sg:postcode":"80033",
    "sg:province":"CO",
    "sg:tags":[
        "accountant"
    ],
    "wof:name":"Newbill & Co",
    "wof:placetype":"venue"
},
  "geometry": {"coordinates":[-105.104916,39.78439],"type":"Point"}
}