{
  "type": "Feature",
  "properties": {
    "iso:country":"US",
    "sg:address":"9330 Sheridan Blvd",
    "sg:city":"Westminster",
    "sg:classifiers":[
        {
            "category":"Shopping",
            "type":"Retail Goods"
        }
    ],
    "sg:phone":"+1 303 650 2229",
    "sg:postcode":"80031",
    "sg:province":"CO",
    "sg:tags":[
        "baby",
        "infant",
        "furniture",
        "clothing",
        "supply"
    ],
    "wof:name":"Babies R Us",
    "wof:placetype":"venue"
},
  "geometry": {"coordinates":[-105.05313099999999,39.864544],"type":"Point"}
}