{
  "type": "Feature",
  "properties": {
    "addr:full":"2263 Linden Dr Boulder CO 80304",
    "addr:housenumber":"2263",
    "addr:postcode":"80304",
    "addr:street":"Linden Dr",
    "iso:country":"US",
    "sg:address":"2263 Linden Dr",
    "sg:city":"Boulder",
    "sg:classifiers":[
        {
            "category":"Building & Trades",
            "subcategory":"Construction",
            "type":"Services"
        }
    ],
    "sg:phone":"+1 303 442 4031",
    "sg:postcode":"80304",
    "sg:province":"CO",
    "sg:tags":[
        "specializing",
        "roofing",
        "work",
        "contractor"
    ],
    "sg:website":"www.thomsenroofing.com",
    "wof:name":"Thomsen Roofing Inc",
    "wof:placetype":"venue"
},
  "geometry": {"coordinates":[-105.31249800000001,40.050481],"type":"Point"}
}