{
  "type": "Feature",
  "properties": {
    "iso:country":"US",
    "sg:address":"5911 S Middlefield Rd",
    "sg:city":"Littleton",
    "sg:classifiers":[
        {
            "category":"Health Services",
            "subcategory":"Health Practitioner",
            "type":"Services"
        }
    ],
    "sg:phone":"+1 303 738 2278",
    "sg:postcode":"80123",
    "sg:province":"CO",
    "sg:tags":[
        "acupuncture"
    ],
    "wof:name":"Anna Y Tsang Acupuncture",
    "wof:placetype":"venue"
},
  "geometry": {"coordinates":[-105.035076,39.608446],"type":"Point"}
}