{
  "type": "Feature",
  "properties": {
    "addr:full":"679 Garrison St Denver CO 80215",
    "addr:housenumber":"679",
    "addr:postcode":"80215",
    "addr:street":"Garrison St",
    "iso:country":"US",
    "sg:address":"679 Garrison St",
    "sg:city":"Denver",
    "sg:classifiers":[
        {
            "category":"Professional",
            "type":"Services"
        }
    ],
    "sg:phone":"+1 303 238 5306",
    "sg:postcode":"80215",
    "sg:province":"CO",
    "wof:name":"Aaron L Yarnell",
    "wof:placetype":"venue"
},
  "geometry": {"coordinates":[-105.10031600000001,39.726283],"type":"Point"}
}