{
  "type": "Feature",
  "properties": {
    "addr:full":"2880 Folsom St Boulder CO 80304",
    "addr:housenumber":"2880",
    "addr:postcode":"80304",
    "addr:street":"Folsom St",
    "iso:country":"US",
    "sg:address":"2880 Folsom St",
    "sg:city":"Boulder",
    "sg:classifiers":[
        {
            "category":"Health Services",
            "subcategory":"Doctor",
            "type":"Services"
        }
    ],
    "sg:phone":"+1 303 449 1792",
    "sg:postcode":"80304",
    "sg:province":"CO",
    "wof:name":"Joel L Schaffer DDS A PC",
    "wof:placetype":"venue"
},
  "geometry": {"coordinates":[-105.263049,40.028779],"type":"Point"}
}