{
  "type": "Feature",
  "properties": {
    "addr:full":"204 E Baseline Rd Lafayette CO 80026",
    "addr:housenumber":"204",
    "addr:postcode":"80026",
    "addr:street":"E Baseline Rd",
    "iso:country":"US",
    "sg:address":"204 E Baseline Rd",
    "sg:city":"Lafayette",
    "sg:classifiers":[
        {
            "category":"Health Services",
            "subcategory":"Doctor",
            "type":"Services"
        }
    ],
    "sg:phone":"+1 303 665 4000",
    "sg:postcode":"80026",
    "sg:province":"CO",
    "sg:tags":[
        "dentist"
    ],
    "wof:name":"Mark L Belford DDS",
    "wof:placetype":"venue"
},
  "geometry": {"coordinates":[-105.088104,40.000138],"type":"Point"}
}