{
  "type": "Feature",
  "properties": {
    "iso:country":"US",
    "sg:address":"37495 Co Rd 63",
    "sg:city":"Galeton",
    "sg:classifiers":[
        {
            "category":"Farming",
            "subcategory":"Farm",
            "type":"Manufacturing & Wholesale Goods"
        }
    ],
    "sg:phone":"+1 970 656 3450",
    "sg:postcode":"80622",
    "sg:province":"CO",
    "wof:name":"Kimseys Kritter Farm",
    "wof:placetype":"venue"
},
  "geometry": {"coordinates":[-104.470316,40.54394],"type":"Point"}
}