{
  "type": "Feature",
  "properties": {
    "addr:full":"9996 W Bowles Ave Littleton CO 80123",
    "addr:housenumber":"9996",
    "addr:postcode":"80123",
    "addr:street":"W Bowles Ave",
    "iso:country":"US",
    "sg:address":"9996 W Bowles Ave",
    "sg:city":"Littleton",
    "sg:classifiers":[
        {
            "category":"Professional",
            "subcategory":"Lawyer & Legal Services",
            "type":"Services"
        }
    ],
    "sg:phone":"+1 303 948 3600",
    "sg:postcode":"80123",
    "sg:province":"CO",
    "sg:tags":[
        "attorney"
    ],
    "wof:name":"Stephen D Foster",
    "wof:placetype":"venue"
},
  "geometry": {"coordinates":[-105.108206,39.609652],"type":"Point"}
}