{
  "type": "Feature",
  "properties": {
    "addr:full":"5085 Brian Dr Parker CO 80134",
    "addr:housenumber":"5085",
    "addr:postcode":"80134",
    "addr:street":"Brian Dr",
    "iso:country":"US",
    "sg:address":"5085 Brian Dr",
    "sg:city":"Parker",
    "sg:classifiers":[
        {
            "category":"Wholesale",
            "subcategory":"Electrical",
            "type":"Manufacturing & Wholesale Goods"
        }
    ],
    "sg:phone":"+1 303 841 3159",
    "sg:postcode":"80134",
    "sg:province":"CO",
    "wof:name":"Creative Iron Inc",
    "wof:placetype":"venue"
},
  "geometry": {"coordinates":[-104.79207100000001,39.500372],"type":"Point"}
}