{
  "type": "Feature",
  "properties": {
    "addr:full":"516 S Emerson St Denver CO 80209",
    "addr:housenumber":"516",
    "addr:postcode":"80209",
    "addr:street":"S Emerson St",
    "iso:country":"US",
    "sg:address":"516 S Emerson St",
    "sg:city":"Denver",
    "sg:classifiers":[
        {
            "category":"Wholesale",
            "subcategory":"Apparel",
            "type":"Manufacturing & Wholesale Goods"
        }
    ],
    "sg:phone":"+1 303 777 5996",
    "sg:postcode":"80209",
    "sg:province":"CO",
    "sg:tags":[
        "clothing"
    ],
    "wof:name":"Duwest Clothing Co",
    "wof:placetype":"venue"
},
  "geometry": {"coordinates":[-104.976837,39.705964],"type":"Point"}
}