{
  "type": "Feature",
  "properties": {
    "addr:full":"1124 Santa Fe Dr Denver CO 80204",
    "addr:housenumber":"1124",
    "addr:postcode":"80204",
    "addr:street":"Santa Fe Dr",
    "iso:country":"US",
    "sg:address":"1124 Santa Fe Dr",
    "sg:city":"Denver",
    "sg:classifiers":[
        {
            "category":"Manufacturing",
            "subcategory":"Retail Goods",
            "type":"Manufacturing & Wholesale Goods"
        }
    ],
    "sg:phone":"+1 303 825 8150",
    "sg:postcode":"80204",
    "sg:province":"CO",
    "sg:tags":[
        "theatrical",
        "product",
        "mfg"
    ],
    "wof:name":"Theatre Group",
    "wof:placetype":"venue"
},
  "geometry": {"coordinates":[-104.998593,39.734879],"type":"Point"}
}