{
  "type": "Feature",
  "properties": {
    "addr:full":"315 E Dean St Aspen CO 81611",
    "addr:housenumber":"315",
    "addr:postcode":"81611",
    "addr:street":"E Dean St",
    "iso:country":"US",
    "sg:address":"315 E Dean St",
    "sg:city":"Aspen",
    "sg:classifiers":[
        {
            "category":"Travel",
            "subcategory":"Hotels & Motels",
            "type":"Entertainment"
        }
    ],
    "sg:phone":"+1 970 920 3300",
    "sg:postcode":"81611",
    "sg:province":"CO",
    "sg:website":"www.stregisaspen.com",
    "wof:name":"St Regis Aspen",
    "wof:placetype":"venue"
},
  "geometry": {"coordinates":[-106.821504,39.187208],"type":"Point"}
}