{
  "type": "Feature",
  "properties": {
    "iso:country":"US",
    "sg:address":"1110 Somerset St",
    "sg:city":"Lafayette",
    "sg:classifiers":[
        {
            "category":"Health Services",
            "subcategory":"Clinic",
            "type":"Services"
        }
    ],
    "sg:phone":"+1 303 666 9415",
    "sg:postcode":"80026",
    "sg:province":"CO",
    "wof:name":"Five Pillars Healthcare",
    "wof:placetype":"venue"
},
  "geometry": {"coordinates":[-105.10407499999999,39.997547],"type":"Point"}
}