{
  "type": "Feature",
  "properties": {
    "addr:full":"63 Inverness Dr E Englewood CO 80112",
    "addr:housenumber":"63",
    "addr:postcode":"80112",
    "addr:street":"Inverness Dr E",
    "iso:country":"US",
    "sg:address":"63 Inverness Dr E",
    "sg:city":"Englewood",
    "sg:classifiers":[
        {
            "category":"Social Services",
            "type":"Services"
        }
    ],
    "sg:phone":"+1 303 792 9900",
    "sg:postcode":"80112",
    "sg:province":"CO",
    "sg:tags":[
        "organization",
        "humane",
        "association",
        "welfare"
    ],
    "sg:website":"www.americanhumane.org",
    "wof:name":"American Humane Association",
    "wof:placetype":"venue"
},
  "geometry": {"coordinates":[-104.856779,39.578821],"type":"Point"}
}