{
  "type": "Feature",
  "properties": {
    "iso:country":"US",
    "sg:address":"15150 Co Rd T",
    "sg:city":"La Jara",
    "sg:classifiers":[
        {
            "category":"Utilities",
            "subcategory":"Fuel Oil & Lpg",
            "type":"Services"
        }
    ],
    "sg:phone":"+1 719 274 5102",
    "sg:postcode":"81140",
    "sg:province":"CO",
    "sg:tags":[
        "equipment",
        "liquefied",
        "gas",
        "petroleum"
    ],
    "wof:name":"Conejos Propane Bountiful",
    "wof:placetype":"venue"
},
  "geometry": {"coordinates":[-105.97473100000001,37.225625],"type":"Point"}
}