{
  "type": "Feature",
  "properties": {
    "addr:full":"7632 Emerald Ave Fort Collins CO 80525",
    "addr:housenumber":"7632",
    "addr:postcode":"80525",
    "addr:street":"Emerald Ave",
    "iso:country":"US",
    "sg:address":"7632 Emerald Ave",
    "sg:city":"Fort Collins",
    "sg:classifiers":[
        {
            "category":"Communications",
            "type":"Services"
        }
    ],
    "sg:phone":"+1 970 663 7340",
    "sg:postcode":"80525",
    "sg:province":"CO",
    "wof:name":"Corner Stone Tower Svc",
    "wof:placetype":"venue"
},
  "geometry": {"coordinates":[-105.066534,40.479164],"type":"Point"}
}