{
  "type": "Feature",
  "properties": {
    "iso:country":"US",
    "sg:address":"1350 Alpine Dr",
    "sg:city":"Boulder",
    "sg:classifiers":[
        {
            "category":"Retail",
            "subcategory":"Photofinishing",
            "type":"Services"
        }
    ],
    "sg:phone":"+1 303 499 6963",
    "sg:postcode":"80304",
    "sg:province":"CO",
    "sg:tags":[
        "photo",
        "finishing"
    ],
    "wof:name":"Photo Finish",
    "wof:placetype":"venue"
},
  "geometry": {"coordinates":[-105.27882700000001,40.025432],"type":"Point"}
}