{
  "type": "Feature",
  "properties": {
    "addr:full":"109 W 3rd St Palisade CO 81526",
    "addr:housenumber":"109",
    "addr:postcode":"81526",
    "addr:street":"W 3Rd St",
    "iso:country":"US",
    "sg:address":"109 W 3rd St",
    "sg:city":"Palisade",
    "sg:classifiers":[
        {
            "category":"Health Services",
            "subcategory":"Doctor",
            "type":"Services"
        }
    ],
    "sg:phone":"+1 970 464 7272",
    "sg:postcode":"81526",
    "sg:province":"CO",
    "sg:tags":[
        "dentist"
    ],
    "wof:name":"Ralph Kibler DDS",
    "wof:placetype":"venue"
},
  "geometry": {"coordinates":[-108.35099099999999,39.110232],"type":"Point"}
}