{
  "type": "Feature",
  "properties": {
    "addr:full":"11930 W 44th Ave Wheat Ridge CO 80033",
    "addr:housenumber":"11930",
    "addr:postcode":"80033",
    "addr:street":"W 44Th Ave",
    "iso:country":"US",
    "sg:address":"11930 W 44th Ave",
    "sg:city":"Wheat Ridge",
    "sg:classifiers":[
        {
            "category":"Real Estate",
            "subcategory":"Real Estate Agent",
            "type":"Services"
        }
    ],
    "sg:phone":"+1 303 420 1531",
    "sg:postcode":"80033",
    "sg:province":"CO",
    "sg:tags":[
        "investment"
    ],
    "wof:name":"Alexis Investment Corp",
    "wof:placetype":"venue"
},
  "geometry": {"coordinates":[-105.135689,39.778224],"type":"Point"}
}