{
  "type": "Feature",
  "properties": {
    "iso:country":"US",
    "sg:address":"303 San Juan Ave",
    "sg:city":"Alamosa",
    "sg:classifiers":[
        {
            "category":"Social Services",
            "type":"Services"
        }
    ],
    "sg:phone":"+1 719 589 5800",
    "sg:postcode":"81101",
    "sg:province":"CO",
    "sg:tags":[
        "counselor",
        "marriage",
        "family"
    ],
    "wof:name":"San Luis Valley Counseling",
    "wof:placetype":"venue"
},
  "geometry": {"coordinates":[-105.86722399999999,37.470362],"type":"Point"}
}