{
  "type": "Feature",
  "properties": {
    "addr:full":"7675 E Union Ave Denver CO 80237",
    "addr:housenumber":"7675",
    "addr:postcode":"80237",
    "addr:street":"E Union Ave",
    "iso:country":"US",
    "sg:address":"7675 E Union Ave",
    "sg:city":"Denver",
    "sg:classifiers":[
        {
            "category":"Travel",
            "subcategory":"Hotels & Motels",
            "type":"Entertainment"
        }
    ],
    "sg:phone":"+1 303 770 4200",
    "sg:postcode":"80237",
    "sg:province":"CO",
    "sg:website":"www.wyndman.com",
    "wof:name":"Wyndham Denver Tech",
    "wof:placetype":"venue"
},
  "geometry": {"coordinates":[-104.90303,39.628471],"type":"Point"}
}