{
  "type": "Feature",
  "properties": {
    "addr:full":"435 S Fig Way Denver CO 80228",
    "addr:housenumber":"435",
    "addr:postcode":"80228",
    "addr:street":"S Fig Way",
    "iso:country":"US",
    "sg:address":"435 S Fig Way",
    "sg:city":"Denver",
    "sg:classifiers":[
        {
            "category":"Building & Trades",
            "subcategory":"Construction",
            "type":"Services"
        }
    ],
    "sg:phone":"+1 303 426 8575",
    "sg:postcode":"80228",
    "sg:province":"CO",
    "sg:tags":[
        "roofing",
        "contractor"
    ],
    "wof:name":"Indepndent Rofg Spcialists LLC",
    "wof:placetype":"venue"
},
  "geometry": {"coordinates":[-105.158502,39.708364],"type":"Point"}
}