{
  "type": "Feature",
  "properties": {
    "addr:full":"505 Popes Bluff Trl Colorado Springs CO 80907",
    "addr:housenumber":"505",
    "addr:postcode":"80907",
    "addr:street":"Popes Bluff Trl",
    "iso:country":"US",
    "sg:address":"505 Popes Bluff Trl",
    "sg:city":"Colorado Springs",
    "sg:classifiers":[
        {
            "category":"Travel",
            "subcategory":"Hotels & Motels",
            "type":"Entertainment"
        }
    ],
    "sg:phone":"+1 719 598 7656",
    "sg:postcode":"80907",
    "sg:province":"CO",
    "wof:name":"Park Plaza Garden of The Gods",
    "wof:placetype":"venue"
},
  "geometry": {"coordinates":[-104.832764,38.898216],"type":"Point"}
}