{
  "type": "Feature",
  "properties": {
    "iso:country":"US",
    "sg:address":"21628 Co Rd 23",
    "sg:city":"Fort Morgan",
    "sg:classifiers":[
        {
            "category":"Farming",
            "subcategory":"Farm",
            "type":"Manufacturing & Wholesale Goods"
        }
    ],
    "sg:phone":"+1 970 867 2117",
    "sg:postcode":"80701",
    "sg:province":"CO",
    "sg:tags":[
        "crop",
        "general"
    ],
    "wof:name":"Meyer Livestock",
    "wof:placetype":"venue"
},
  "geometry": {"coordinates":[-103.716007,40.315904],"type":"Point"}
}