{
  "type": "Feature",
  "properties": {
    "iso:country":"US",
    "sg:address":"3586 S Elkhart St",
    "sg:city":"Aurora",
    "sg:classifiers":[
        {
            "category":"Farming",
            "subcategory":"Livestock Farm",
            "type":"Manufacturing & Wholesale Goods"
        }
    ],
    "sg:phone":"+1 303 660 8133",
    "sg:postcode":"80014",
    "sg:province":"CO",
    "sg:tags":[
        "animal",
        "general"
    ],
    "wof:name":"Castlewood Ranch LLC",
    "wof:placetype":"venue"
},
  "geometry": {"coordinates":[-104.81541300000001,39.650581],"type":"Point"}
}