{
  "type": "Feature",
  "properties": {
    "iso:country":"US",
    "sg:address":"208 Main St",
    "sg:city":"Sterling",
    "sg:classifiers":[
        {
            "category":"Shopping",
            "subcategory":"Jewelry",
            "type":"Retail Goods"
        }
    ],
    "sg:phone":"+1 970 522 2587",
    "sg:postcode":"80751",
    "sg:province":"CO",
    "sg:tags":[
        "jeweler"
    ],
    "wof:name":"Rominger Jewelry & Gifts",
    "wof:placetype":"venue"
},
  "geometry": {"coordinates":[-103.208315,40.623882],"type":"Point"}
}