{
  "type": "Feature",
  "properties": {
    "iso:country":"US",
    "sg:address":"2309 Ponderosa Ct",
    "sg:city":"Fort Collins",
    "sg:classifiers":[
        {
            "category":"Home & Garden",
            "subcategory":"Building Materials",
            "type":"Retail Goods"
        }
    ],
    "sg:phone":"+1 970 495 0462",
    "sg:postcode":"80521",
    "sg:province":"CO",
    "sg:tags":[
        "glass",
        "leaded"
    ],
    "wof:name":"Glass By Fox",
    "wof:placetype":"venue"
},
  "geometry": {"coordinates":[-105.11971,40.580315],"type":"Point"}
}