{
  "type": "Feature",
  "properties": {
    "iso:country":"US",
    "sg:address":"831 Phelps St",
    "sg:city":"Sterling",
    "sg:classifiers":[
        {
            "category":"Recreation",
            "subcategory":"Arcade",
            "type":"Entertainment"
        }
    ],
    "sg:phone":"+1 970 522 0726",
    "sg:postcode":"80751",
    "sg:province":"CO",
    "wof:name":"Bonz's Arcade",
    "wof:placetype":"venue"
},
  "geometry": {"coordinates":[-103.225275,40.622313],"type":"Point"}
}