{
  "type": "Feature",
  "properties": {
    "iso:country":"US",
    "sg:address":"40633 D Rd",
    "sg:city":"Crawford",
    "sg:classifiers":[
        {
            "category":"Professional",
            "subcategory":"Business Services",
            "type":"Services"
        }
    ],
    "sg:phone":"+1 970 921 3131",
    "sg:postcode":"81415",
    "sg:province":"CO",
    "sg:tags":[
        "water",
        "hauling"
    ],
    "wof:name":"Bob's Water Hauling Svc",
    "wof:placetype":"venue"
},
  "geometry": {"coordinates":[-107.589258,38.697433],"type":"Point"}
}