{
  "type": "Feature",
  "properties": {
    "addr:full":"1 Browning Ave Ignacio CO 81137",
    "addr:housenumber":"1",
    "addr:postcode":"81137",
    "addr:street":"Browning Ave Ignacio",
    "iso:country":"US",
    "sg:address":"1 Browning Ave",
    "sg:city":"Ignacio",
    "sg:classifiers":[
        {
            "category":"Personal",
            "subcategory":"Beauty Salon",
            "type":"Services"
        }
    ],
    "sg:phone":"+1 970 563 9267",
    "sg:postcode":"81137",
    "sg:province":"CO",
    "wof:name":"Custom Cuts",
    "wof:placetype":"venue"
},
  "geometry": {"coordinates":[-107.634432,37.120388],"type":"Point"}
}