{
  "type": "Feature",
  "properties": {
    "iso:country":"US",
    "sg:address":"1712 Briargate Ct",
    "sg:city":"Fort Collins",
    "sg:classifiers":[
        {
            "category":"Building & Trades",
            "subcategory":"Electrical",
            "type":"Services"
        }
    ],
    "sg:phone":"+1 970 567 7607",
    "sg:postcode":"80526",
    "sg:province":"CO",
    "sg:tags":[
        "electrical",
        "contractor"
    ],
    "wof:name":"Vigilant Recognition Imaging",
    "wof:placetype":"venue"
},
  "geometry": {"coordinates":[-105.10832499999999,40.524714],"type":"Point"}
}