{
  "type": "Feature",
  "properties": {
    "addr:full":"2505 Lanyon Dr Longmont CO 80503",
    "addr:housenumber":"2505",
    "addr:postcode":"80503",
    "addr:street":"Lanyon Dr",
    "iso:country":"US",
    "sg:address":"2505 Lanyon Dr",
    "sg:city":"Longmont",
    "sg:classifiers":[
        {
            "category":"Retail",
            "subcategory":"Repair Shop",
            "type":"Services"
        }
    ],
    "sg:phone":"+1 303 651 3410",
    "sg:postcode":"80503",
    "sg:province":"CO",
    "wof:name":"Creation Painting Inc",
    "wof:placetype":"venue"
},
  "geometry": {"coordinates":[-105.13607399999999,40.179293],"type":"Point"}
}