{
  "type": "Feature",
  "properties": {
    "iso:country":"US",
    "sg:address":"490 Rampart Range Rd",
    "sg:city":"Woodland Park",
    "sg:classifiers":[
        {
            "category":"Health Services",
            "subcategory":"Chiropractor",
            "type":"Services"
        }
    ],
    "sg:phone":"+1 719 687 6096",
    "sg:postcode":"80863",
    "sg:province":"CO",
    "wof:name":"Powell Chiropractic Clinic",
    "wof:placetype":"venue"
},
  "geometry": {"coordinates":[-105.046941,38.997449],"type":"Point"}
}