{
  "type": "Feature",
  "properties": {
    "addr:full":"140 SW 2nd Ave Cedaredge CO 81413",
    "addr:housenumber":"140",
    "addr:postcode":"81413",
    "addr:street":"Sw 2Nd Ave",
    "iso:country":"US",
    "sg:address":"140 SW 2nd Ave",
    "sg:city":"Cedaredge",
    "sg:classifiers":[
        {
            "category":"Local Transit",
            "type":"Transportation"
        }
    ],
    "sg:phone":"+1 970 856 8951",
    "sg:postcode":"81413",
    "sg:province":"CO",
    "sg:tags":[
        "ambulance"
    ],
    "wof:name":"Delta County Ambulance Dist",
    "wof:placetype":"venue"
},
  "geometry": {"coordinates":[-107.925468,38.899482],"type":"Point"}
}