{
  "type": "Feature",
  "properties": {
    "addr:full":"9868 W 60th Ave Arvada CO 80004",
    "addr:housenumber":"9868",
    "addr:postcode":"80004",
    "addr:street":"W 60Th Ave",
    "iso:country":"US",
    "sg:address":"9868 W 60th Ave",
    "sg:city":"Arvada",
    "sg:classifiers":[
        {
            "category":"Freight",
            "type":"Transportation"
        }
    ],
    "sg:phone":"+1 303 423 6647",
    "sg:postcode":"80004",
    "sg:province":"CO",
    "sg:tags":[
        "shipping",
        "agent"
    ],
    "wof:name":"East-West Express",
    "wof:placetype":"venue"
},
  "geometry": {"coordinates":[-105.109261,39.805804],"type":"Point"}
}