{
  "type": "Feature",
  "properties": {
    "addr:full":"312 Hollyberry Ln Boulder CO 80305",
    "addr:housenumber":"312",
    "addr:postcode":"80305",
    "addr:street":"Hollyberry Ln",
    "iso:country":"US",
    "sg:address":"312 Hollyberry Ln",
    "sg:city":"Boulder",
    "sg:classifiers":[
        {
            "category":"Airline",
            "type":"Transportation"
        }
    ],
    "sg:phone":"+1 303 499 3339",
    "sg:postcode":"80305",
    "sg:province":"CO",
    "sg:tags":[
        "helicopter"
    ],
    "wof:name":"Pegasus Helicopters Inc",
    "wof:placetype":"venue"
},
  "geometry": {"coordinates":[-105.271535,39.988469],"type":"Point"}
}