{
  "type": "Feature",
  "properties": {
    "addr:full":"8390 E Crescent Pkwy Englewood CO 80111",
    "addr:housenumber":"8390",
    "addr:postcode":"80111",
    "addr:street":"E Crescent Pkwy",
    "iso:country":"US",
    "sg:address":"8390 E Crescent Pkwy",
    "sg:city":"Englewood",
    "sg:classifiers":[
        {
            "category":"Travel",
            "subcategory":"Travel Agent",
            "type":"Entertainment"
        }
    ],
    "sg:phone":"+1 303 796 3696",
    "sg:postcode":"80111",
    "sg:province":"CO",
    "sg:tags":[
        "agency"
    ],
    "wof:name":"Edr Travel",
    "wof:placetype":"venue"
},
  "geometry": {"coordinates":[-104.891768,39.623649],"type":"Point"}
}