{
  "type": "Feature",
  "properties": {
    "iso:country":"US",
    "sg:address":"240 S Broadway St Ste 102",
    "sg:city":"Denver",
    "sg:classifiers":[
        {
            "category":"Professional",
            "subcategory":"Art Services",
            "type":"Services"
        }
    ],
    "sg:phone":"+1 303 809 5235",
    "sg:postcode":"80209",
    "sg:province":"CO",
    "sg:tags":[
        "photographer"
    ],
    "sg:website":"www.i2photos.com/",
    "wof:name":"Impact Images",
    "wof:placetype":"venue"
},
  "geometry": {"coordinates":[-104.987225,39.712196],"type":"Point"}
}