{
  "type": "Feature",
  "properties": {
    "iso:country":"US",
    "sg:address":"314 Elbert St",
    "sg:city":"Castle Rock",
    "sg:classifiers":[
        {
            "category":"Building & Trades",
            "subcategory":"Construction",
            "type":"Services"
        }
    ],
    "sg:phone":"+1 303 663 7146",
    "sg:postcode":"80104",
    "sg:province":"CO",
    "sg:tags":[
        "contractor"
    ],
    "wof:name":"Randy Riggan",
    "wof:placetype":"venue"
},
  "geometry": {"coordinates":[-104.862595,39.373169],"type":"Point"}
}