{
  "type": "Feature",
  "properties": {
    "addr:full":"77 S Ogden Street Denver CO 80209",
    "addr:housenumber":"77",
    "addr:postcode":"80209",
    "addr:street":"S Ogden Street",
    "iso:country":"US",
    "sg:address":"77 S Ogden Street",
    "sg:city":"Denver",
    "sg:classifiers":[
        {
            "category":"Real Estate",
            "subcategory":"Real Estate Operator",
            "type":"Services"
        }
    ],
    "sg:phone":"+1 303 744 3181",
    "sg:postcode":"80209",
    "sg:province":"CO",
    "sg:tags":[
        "apartment"
    ],
    "sg:website":"www.stokesandcompany.com",
    "wof:name":"Brittany House Apts",
    "wof:placetype":"venue"
},
  "geometry": {"coordinates":[-104.975746,39.715127],"type":"Point"}
}