{
  "type": "Feature",
  "properties": {
    "addr:full":"1060 Mariposa Dr Durango CO 81301",
    "addr:housenumber":"1060",
    "addr:postcode":"co 81301",
    "addr:street":"Mariposa Dr",
    "iso:country":"US",
    "sg:address":"1060 Mariposa Dr",
    "sg:city":"Durango",
    "sg:classifiers":[
        {
            "category":"Building & Trades",
            "subcategory":"Construction",
            "type":"Services"
        }
    ],
    "sg:phone":"+1 970 259 5030",
    "sg:postcode":"81301",
    "sg:province":"CO",
    "sg:tags":[
        "house"
    ],
    "wof:name":"JW Construction",
    "wof:placetype":"venue"
},
  "geometry": {"coordinates":[-107.81230499999999,37.237418],"type":"Point"}
}