{
  "type": "Feature",
  "properties": {
    "iso:country":"US",
    "sg:address":"603 S Public Rd",
    "sg:city":"Lafayette",
    "sg:classifiers":[
        {
            "category":"Government",
            "subcategory":"Post Office",
            "type":"Public Place"
        }
    ],
    "sg:phone":"+1 303 926 1044",
    "sg:postcode":"80026",
    "sg:province":"CO",
    "sg:tags":[
        "postal",
        "us"
    ],
    "wof:name":"US Post Office",
    "wof:placetype":"venue"
},
  "geometry": {"coordinates":[-105.090535,39.993844],"type":"Point"}
}