{
  "type": "Feature",
  "properties": {
    "addr:full":"16911 Co Rd 20.5 Atwood CO 80751",
    "addr:housenumber":"16911",
    "addr:postcode":"80751",
    "addr:street":"Co Rd",
    "iso:country":"US",
    "sg:address":"16911 Co Rd 20.5",
    "sg:city":"Atwood",
    "sg:classifiers":[
        {
            "category":"Farming",
            "subcategory":"Farm",
            "type":"Manufacturing & Wholesale Goods"
        }
    ],
    "sg:phone":"+1 970 522 4367",
    "sg:postcode":"80751",
    "sg:province":"CO",
    "sg:tags":[
        "sugarcane",
        "general"
    ],
    "wof:name":"Baseggio Brothers",
    "wof:placetype":"venue"
},
  "geometry": {"coordinates":[-103.26428300000001,40.573292],"type":"Point"}
}