{
  "type": "Feature",
  "properties": {
    "addr:full":"421 B St Rock Springs CO 82901",
    "addr:housenumber":"421",
    "addr:postcode":"82901",
    "addr:street":"B St",
    "iso:country":"US",
    "sg:address":"421 B St",
    "sg:city":"Rock Springs",
    "sg:classifiers":[
        {
            "category":"Government",
            "subcategory":"Office",
            "type":"Public Place"
        }
    ],
    "sg:phone":"+1 307 352 6608",
    "sg:postcode":"82901",
    "sg:province":"CO",
    "wof:name":"Sweetwater County Coroner",
    "wof:placetype":"venue"
},
  "geometry": {"coordinates":[-109.218924,41.583264],"type":"Point"}
}