{
  "type": "Feature",
  "properties": {
    "iso:country":"US",
    "sg:address":"6600 E 74th Ave",
    "sg:city":"Commerce City",
    "sg:classifiers":[
        {
            "category":"Retail",
            "subcategory":"Auto Repair",
            "type":"Services"
        }
    ],
    "sg:phone":"+1 303 287 7013",
    "sg:postcode":"80022",
    "sg:province":"CO",
    "sg:tags":[
        "repairing",
        "automobile"
    ],
    "wof:name":"Joe's Auto Svc",
    "wof:placetype":"venue"
},
  "geometry": {"coordinates":[-104.909273,39.830951],"type":"Point"}
}