{
  "type": "Feature",
  "properties": {
    "addr:full":"5779 N Academy Blvd Colorado Springs CO 80918",
    "addr:housenumber":"5779",
    "addr:postcode":"80918",
    "addr:street":"N Academy Blvd",
    "iso:country":"US",
    "sg:address":"5779 N Academy Blvd",
    "sg:city":"Colorado Springs",
    "sg:classifiers":[
        {
            "category":"Real Estate",
            "subcategory":"Real Estate Operator",
            "type":"Services"
        }
    ],
    "sg:phone":"+1 719 531 0903",
    "sg:postcode":"80918",
    "sg:province":"CO",
    "sg:tags":[
        "building",
        "nonresidential"
    ],
    "wof:name":"Erindale Shopping Ctr Lsg Off",
    "wof:placetype":"venue"
},
  "geometry": {"coordinates":[-104.78765199999999,38.913779],"type":"Point"}
}