{
  "type": "Feature",
  "properties": {
    "iso:country":"US",
    "sg:address":"1960 Billings St",
    "sg:city":"Aurora",
    "sg:classifiers":[
        {
            "category":"Professional",
            "type":"Services"
        }
    ],
    "sg:phone":"+1 720 275 5068",
    "sg:postcode":"80011",
    "sg:province":"CO",
    "wof:name":"Maria Rivera",
    "wof:placetype":"venue"
},
  "geometry": {"coordinates":[-104.82461499999999,39.745194],"type":"Point"}
}