{
  "type": "Feature",
  "properties": {
    "iso:country":"US",
    "sg:address":"982 S Richfield Way",
    "sg:city":"Aurora",
    "sg:classifiers":[
        {
            "category":"Building & Trades",
            "subcategory":"Construction",
            "type":"Services"
        }
    ],
    "sg:phone":"+1 303 632 5661",
    "sg:postcode":"80017",
    "sg:province":"CO",
    "sg:tags":[
        "house"
    ],
    "wof:name":"Luz Arrow Remodeling Co",
    "wof:placetype":"venue"
},
  "geometry": {"coordinates":[-104.785864,39.697272],"type":"Point"}
}