{
  "type": "Feature",
  "properties": {
    "iso:country":"US",
    "sg:address":"1800 Grant St",
    "sg:city":"Denver",
    "sg:classifiers":[
        {
            "category":"Professional",
            "subcategory":"Accounting & Tax Preparation",
            "type":"Services"
        }
    ],
    "sg:phone":"+1 303 894 3807",
    "sg:postcode":"80203",
    "sg:province":"CO",
    "sg:tags":[
        "return"
    ],
    "wof:name":"Barclay Tolen & Lenneman",
    "wof:placetype":"venue"
},
  "geometry": {"coordinates":[-104.98358899999999,39.746182],"type":"Point"}
}