{
  "type": "Feature",
  "properties": {
    "addr:full":"2222 S Albion St Denver CO 80222",
    "addr:housenumber":"2222",
    "addr:postcode":"80222",
    "addr:street":"S Albion St",
    "iso:country":"US",
    "sg:address":"2222 S Albion St",
    "sg:city":"Denver",
    "sg:classifiers":[
        {
            "category":"Professional",
            "type":"Services"
        }
    ],
    "sg:phone":"+1 303 759 0339",
    "sg:postcode":"80222",
    "sg:province":"CO",
    "sg:tags":[
        "establishment"
    ],
    "wof:name":"B Gebhart & Assoc Inc",
    "wof:placetype":"venue"
},
  "geometry": {"coordinates":[-104.93951800000001,39.675226],"type":"Point"}
}