{
  "type": "Feature",
  "properties": {
    "addr:full":"3597 S Pearl St Englewood CO 80113",
    "addr:housenumber":"3597",
    "addr:postcode":"80113",
    "addr:street":"S Pearl St",
    "iso:country":"US",
    "sg:address":"3597 S Pearl St",
    "sg:city":"Englewood",
    "sg:classifiers":[
        {
            "category":"Health Services",
            "subcategory":"Doctor",
            "type":"Services"
        }
    ],
    "sg:phone":"+1 303 781 6722",
    "sg:postcode":"80113",
    "sg:province":"CO",
    "sg:tags":[
        "dentist"
    ],
    "wof:name":"Walter H West DDS",
    "wof:placetype":"venue"
},
  "geometry": {"coordinates":[-104.980614,39.653102],"type":"Point"}
}