{
  "type": "Feature",
  "properties": {
    "iso:country":"US",
    "sg:address":"99 S Sheridan Boulevard",
    "sg:city":"Lakewood",
    "sg:classifiers":[
        {
            "category":"Food & Beverages",
            "subcategory":"Liquor & Beverages",
            "type":"Retail Goods"
        }
    ],
    "sg:phone":"+1 303 234 1047",
    "sg:postcode":"80226",
    "sg:province":"CO",
    "sg:tags":[
        "beer",
        "spirit",
        "wine"
    ],
    "wof:name":"Alameda Liquor",
    "wof:placetype":"venue"
},
  "geometry": {"coordinates":[-105.0531,39.715303],"type":"Point"}
}