{
  "type": "Feature",
  "properties": {
    "addr:full":"4335 Airport Rd Colorado Springs CO 80916",
    "addr:housenumber":"4335",
    "addr:postcode":"80916",
    "addr:street":"Airport Rd",
    "iso:country":"US",
    "sg:address":"4335 Airport Rd",
    "sg:city":"Colorado Springs",
    "sg:classifiers":[
        {
            "category":"Food & Beverages",
            "subcategory":"Groceries & Convenience Stores",
            "type":"Retail Goods"
        }
    ],
    "sg:phone":"+1 719 597 2525",
    "sg:postcode":"80916",
    "sg:province":"CO",
    "wof:name":"Loaf 'n Jug",
    "wof:placetype":"venue"
},
  "geometry": {"coordinates":[-104.748215,38.825225],"type":"Point"}
}