{
  "type": "Feature",
  "properties": {
    "iso:country":"US",
    "sg:address":"2805 Broadway St",
    "sg:city":"Boulder",
    "sg:classifiers":[
        {
            "category":"Manufacturing",
            "subcategory":"Tools & Machinery",
            "type":"Manufacturing & Wholesale Goods"
        }
    ],
    "sg:phone":"+1 303 546 6400",
    "sg:postcode":"80304",
    "sg:province":"CO",
    "sg:tags":[
        "instrument",
        "mfg"
    ],
    "wof:name":"Team Medical",
    "wof:placetype":"venue"
},
  "geometry": {"coordinates":[-105.282169,40.027949],"type":"Point"}
}