{
  "type": "Feature",
  "properties": {
    "iso:country":"US",
    "sg:address":"603 S el Paso St",
    "sg:city":"Colorado Springs",
    "sg:classifiers":[
        {
            "category":"Shopping",
            "subcategory":"Clothing, Apparel, & Fashions",
            "type":"Retail Goods"
        }
    ],
    "sg:phone":"+1 719 634 9814",
    "sg:postcode":"80903",
    "sg:province":"CO",
    "sg:tags":[
        "shop",
        "family"
    ],
    "wof:name":"Boutique Buty By Wilma Tamara",
    "wof:placetype":"venue"
},
  "geometry": {"coordinates":[-104.81330199999999,38.824155],"type":"Point"}
}