{
  "type": "Feature",
  "properties": {
    "iso:country":"US",
    "sg:address":"9802 Carmel Ct",
    "sg:city":"Lone Tree",
    "sg:classifiers":[
        {
            "category":"Professional",
            "subcategory":"Business Services",
            "type":"Services"
        }
    ],
    "sg:phone":"+1 303 768 9694",
    "sg:postcode":"80124",
    "sg:province":"CO",
    "sg:tags":[
        "embroidery"
    ],
    "wof:name":"Denver Promotions",
    "wof:placetype":"venue"
},
  "geometry": {"coordinates":[-104.890334,39.538286],"type":"Point"}
}