{
  "type": "Feature",
  "properties": {
    "iso:country":"US",
    "sg:address":"330 E Colfax Ave",
    "sg:city":"Denver",
    "sg:classifiers":[
        {
            "category":"Health Services",
            "subcategory":"Clinic",
            "type":"Services"
        }
    ],
    "sg:phone":"+1 720 524 4657",
    "sg:postcode":"80203",
    "sg:province":"CO",
    "sg:tags":[
        "cannabis"
    ],
    "wof:name":"Good Chemistry",
    "wof:placetype":"venue"
},
  "geometry": {"coordinates":[-104.982733,39.740007],"type":"Point"}
}