{
  "type": "Feature",
  "properties": {
    "iso:country":"US",
    "sg:address":"1 2nd Ave",
    "sg:city":"Grand Junction",
    "sg:classifiers":[
        {
            "category":"Shopping",
            "type":"Retail Goods"
        }
    ],
    "sg:phone":"+1 970 245 2526",
    "sg:postcode":"81501",
    "sg:province":"CO",
    "sg:tags":[
        "pet",
        "shop"
    ],
    "wof:name":"J & M Aquatics & Pet Ctr",
    "wof:placetype":"venue"
},
  "geometry": {"coordinates":[-108.558559,39.061187],"type":"Point"}
}