{
  "type": "Feature",
  "properties": {
    "iso:country":"US",
    "sg:address":"2300 E 120th Ave",
    "sg:city":"Denver",
    "sg:classifiers":[
        {
            "category":"Insurance",
            "subcategory":"Insurance Agent",
            "type":"Services"
        }
    ],
    "sg:phone":"+1 303 452 1893",
    "sg:postcode":"80233",
    "sg:province":"CO",
    "wof:name":"Affordable American Insurance",
    "wof:placetype":"venue"
},
  "geometry": {"coordinates":[-104.958168,39.913807],"type":"Point"}
}