{
  "type": "Feature",
  "properties": {
    "addr:full":"798 Huebinger Dr Glenwood Springs CO 81601",
    "addr:housenumber":"798",
    "addr:postcode":"81601",
    "addr:street":"Huebinger Dr",
    "iso:country":"US",
    "sg:address":"798 Huebinger Dr",
    "sg:city":"Glenwood Springs",
    "sg:classifiers":[
        {
            "category":"Professional",
            "type":"Services"
        }
    ],
    "sg:phone":"+1 970 947 9231",
    "sg:postcode":"81601",
    "sg:province":"CO",
    "sg:tags":[
        "establishment"
    ],
    "wof:name":"Hines & Hines",
    "wof:placetype":"venue"
},
  "geometry": {"coordinates":[-107.29042699999999,39.470401],"type":"Point"}
}