{
  "type": "Feature",
  "properties": {
    "addr:full":"7951 W Mississippi Avenue Lakewood CO 80226",
    "addr:housenumber":"7951",
    "addr:postcode":"80226",
    "addr:street":"W Mississippi Avenue",
    "iso:country":"US",
    "sg:address":"7951 W Mississippi Avenue",
    "sg:city":"Lakewood",
    "sg:classifiers":[
        {
            "category":"Food & Beverages",
            "subcategory":"Liquor & Beverages",
            "type":"Retail Goods"
        }
    ],
    "sg:phone":"+1 303 985 3399",
    "sg:postcode":"80226",
    "sg:province":"CO",
    "sg:tags":[
        "beer",
        "spirit",
        "wine"
    ],
    "wof:name":"C & M Vending Company",
    "wof:placetype":"venue"
},
  "geometry": {"coordinates":[-105.085667,39.696559],"type":"Point"}
}