{
  "type": "Feature",
  "properties": {
    "addr:full":"9722 E 16th Ave Aurora CO 80010",
    "addr:housenumber":"9722",
    "addr:postcode":"80010",
    "addr:street":"E 16Th Ave",
    "iso:country":"US",
    "sg:address":"9722 E 16th Ave",
    "sg:city":"Aurora",
    "sg:classifiers":[
        {
            "category":"Professional",
            "subcategory":"Management & Consulting",
            "type":"Services"
        }
    ],
    "sg:phone":"+1 303 340 0548",
    "sg:postcode":"80010",
    "sg:province":"CO",
    "sg:tags":[
        "food"
    ],
    "wof:name":"Pak One LLC",
    "wof:placetype":"venue"
},
  "geometry": {"coordinates":[-104.87424300000001,39.741895],"type":"Point"}
}