{
  "type": "Feature",
  "properties": {
    "iso:country":"US",
    "sg:address":"1600 1600 Rd",
    "sg:city":"Delta",
    "sg:phone":"+1 970 874 9892",
    "sg:postcode":"81416",
    "sg:province":"CO",
    "sg:tags":[
        "farm"
    ],
    "wof:name":"Hilltop Farms",
    "wof:placetype":"venue"
},
  "geometry": {"coordinates":[-108.059231,38.686049],"type":"Point"}
}