{
  "type": "Feature",
  "properties": {
    "addr:full":"915 Grand Ave Glenwood Springs CO 81601",
    "addr:housenumber":"915",
    "addr:postcode":"81601",
    "addr:street":"Grand Ave",
    "iso:country":"US",
    "sg:address":"915 Grand Ave",
    "sg:city":"Glenwood Springs",
    "sg:classifiers":[
        {
            "category":"Cinema",
            "subcategory":"Movie Theater",
            "type":"Entertainment"
        }
    ],
    "sg:phone":"+1 970 945 4000",
    "sg:postcode":"81601",
    "sg:province":"CO",
    "wof:name":"Springs Theatre",
    "wof:placetype":"venue"
},
  "geometry": {"coordinates":[-107.32487500000001,39.545204],"type":"Point"}
}