{
  "type": "Feature",
  "properties": {
    "iso:country":"US",
    "sg:address":"132 E Main St",
    "sg:city":"Trinidad",
    "sg:classifiers":[
        {
            "category":"Organizations",
            "subcategory":"Community Association",
            "type":"Services"
        }
    ],
    "sg:phone":"+1 719 846 2861",
    "sg:postcode":"81082",
    "sg:province":"CO",
    "sg:tags":[
        "fraternal"
    ],
    "wof:name":"Masonic Lodge",
    "wof:placetype":"venue"
},
  "geometry": {"coordinates":[-104.50458399999999,37.16881],"type":"Point"}
}