{
  "type": "Feature",
  "properties": {
    "iso:country":"US",
    "sg:address":"622 Main St",
    "sg:city":"Canon City",
    "sg:classifiers":[
        {
            "category":"Shopping",
            "subcategory":"Clothing, Apparel, & Fashions",
            "type":"Retail Goods"
        }
    ],
    "sg:phone":"+1 719 269 7262",
    "sg:postcode":"81212",
    "sg:province":"CO",
    "wof:name":"Beach Club",
    "wof:placetype":"venue"
},
  "geometry": {"coordinates":[-105.23835800000001,38.441566],"type":"Point"}
}