{
  "type": "Feature",
  "properties": {
    "addr:full":"1351 W 121st Ave Denver CO 80234",
    "addr:housenumber":"1351",
    "addr:postcode":"80234",
    "addr:street":"W 121St Ave",
    "iso:country":"US",
    "sg:address":"1351 W 121st Ave",
    "sg:city":"Denver",
    "sg:classifiers":[
        {
            "category":"Wholesale",
            "subcategory":"Electrical",
            "type":"Manufacturing & Wholesale Goods"
        }
    ],
    "sg:phone":"+1 303 438 8088",
    "sg:postcode":"80234",
    "sg:province":"CO",
    "sg:tags":[
        "fire",
        "alarm",
        "system"
    ],
    "wof:name":"Fire Detection Systems",
    "wof:placetype":"venue"
},
  "geometry": {"coordinates":[-105.00264199999999,39.916058],"type":"Point"}
}