{
  "type": "Feature",
  "properties": {
    "iso:country":"US",
    "sg:address":"1614 27th Ave",
    "sg:city":"Greeley",
    "sg:classifiers":[
        {
            "category":"Government",
            "subcategory":"Office",
            "type":"Public Place"
        }
    ],
    "sg:phone":"+1 970 351 6081",
    "sg:postcode":"80634",
    "sg:province":"CO",
    "sg:tags":[
        "national",
        "security"
    ],
    "wof:name":"Civil Air Patrol Inc",
    "wof:placetype":"venue"
},
  "geometry": {"coordinates":[-104.72218100000001,40.413805],"type":"Point"}
}