{
  "type": "Feature",
  "properties": {
    "addr:full":"320 W 10th St Pueblo CO 81003",
    "addr:housenumber":"320",
    "addr:postcode":"81003",
    "addr:street":"W 10Th St",
    "iso:country":"US",
    "sg:address":"320 W 10th St",
    "sg:city":"Pueblo",
    "sg:classifiers":[
        {
            "category":"Government",
            "subcategory":"Office",
            "type":"Public Place"
        }
    ],
    "sg:phone":"+1 719 583 7118",
    "sg:postcode":"81003",
    "sg:province":"CO",
    "wof:name":"Honorable Clint Smith",
    "wof:placetype":"venue"
},
  "geometry": {"coordinates":[-104.611451,38.27608],"type":"Point"}
}