{
  "type": "Feature",
  "properties": {
    "iso:country":"US",
    "sg:address":"1244 Pine St",
    "sg:city":"Boulder",
    "sg:classifiers":[
        {
            "category":"Health Services",
            "subcategory":"Health Practitioner",
            "type":"Services"
        }
    ],
    "sg:phone":"+1 303 413 1740",
    "sg:postcode":"80302",
    "sg:province":"CO",
    "sg:tags":[
        "psychotherapist"
    ],
    "wof:name":"A Karen Lynch",
    "wof:placetype":"venue"
},
  "geometry": {"coordinates":[-105.28067,40.019912],"type":"Point"}
}