{
  "type": "Feature",
  "properties": {
    "iso:country":"US",
    "sg:address":"950 W Dry Creek Rd",
    "sg:city":"Littleton",
    "sg:classifiers":[
        {
            "category":"Professional",
            "type":"Services"
        }
    ],
    "sg:phone":"+1 303 730 3038",
    "sg:postcode":"80120",
    "sg:province":"CO",
    "wof:name":"Excel Soccer US Inc",
    "wof:placetype":"venue"
},
  "geometry": {"coordinates":[-104.996813,39.579412],"type":"Point"}
}