{
  "type": "Feature",
  "properties": {
    "addr:full":"4601 Castor Dr Pueblo CO 81001",
    "addr:housenumber":"4601",
    "addr:postcode":"81001",
    "addr:street":"Castor Dr",
    "iso:country":"US",
    "sg:address":"4601 Castor Dr",
    "sg:city":"Pueblo",
    "sg:classifiers":[
        {
            "category":"Banks & Credit Unions",
            "subcategory":"Investment Brokerage",
            "type":"Services"
        }
    ],
    "sg:phone":"+1 719 253 0458",
    "sg:postcode":"81001",
    "sg:province":"CO",
    "wof:name":"Hart Investments",
    "wof:placetype":"venue"
},
  "geometry": {"coordinates":[-104.597989,38.318625],"type":"Point"}
}