{
  "type": "Feature",
  "properties": {
    "iso:country":"US",
    "sg:address":"1776 6th Ave",
    "sg:city":"Greeley",
    "sg:classifiers":[
        {
            "category":"Social Services",
            "subcategory":"Job Training",
            "type":"Services"
        }
    ],
    "sg:phone":"+1 970 351 7223",
    "sg:postcode":"80631",
    "sg:province":"CO",
    "sg:tags":[
        "rehabilitation"
    ],
    "wof:name":"Residential Treatment Ctr",
    "wof:placetype":"venue"
},
  "geometry": {"coordinates":[-104.687304,40.410932],"type":"Point"}
}