{
  "type": "Feature",
  "properties": {
    "addr:full":"4113 S Andes Way Aurora CO 80013",
    "addr:housenumber":"4113",
    "addr:postcode":"80013",
    "addr:street":"S Andes Way",
    "iso:country":"US",
    "sg:address":"4113 S Andes Way",
    "sg:city":"Aurora",
    "sg:classifiers":[
        {
            "category":"Food & Beverages",
            "subcategory":"Groceries & Convenience Stores",
            "type":"Retail Goods"
        }
    ],
    "sg:phone":"+1 303 690 9126",
    "sg:postcode":"80013",
    "sg:province":"CO",
    "wof:name":"Lucky 7 Records Inc",
    "wof:placetype":"venue"
},
  "geometry": {"coordinates":[-104.770904,39.642394],"type":"Point"}
}