{
  "type": "Feature",
  "properties": {
    "addr:full":"306 Creekside Dr Frisco CO 80443",
    "addr:housenumber":"306",
    "addr:postcode":"80443",
    "addr:street":"Creekside Dr",
    "iso:country":"US",
    "sg:address":"306 Creekside Dr",
    "sg:city":"Frisco",
    "sg:classifiers":[
        {
            "category":"Recreation",
            "type":"Entertainment"
        }
    ],
    "sg:phone":"+1 970 453 1520",
    "sg:postcode":"80443",
    "sg:province":"CO",
    "sg:tags":[
        "tours",
        "sightseeing"
    ],
    "wof:name":"Two Below Zero Dinner Sleigh",
    "wof:placetype":"venue"
},
  "geometry": {"coordinates":[-106.098727,39.57883],"type":"Point"}
}