{
  "type": "Feature",
  "properties": {
    "iso:country":"US",
    "sg:address":"537 Kalamath Street",
    "sg:city":"Denver",
    "sg:classifiers":[
        {
            "category":"Shopping",
            "subcategory":"Computers & Home Electronics",
            "type":"Retail Goods"
        }
    ],
    "sg:phone":"+1 303 388 9898",
    "sg:postcode":"80204",
    "sg:province":"CO",
    "wof:name":"High Definition Design",
    "wof:placetype":"venue"
},
  "geometry": {"coordinates":[-105.000332,39.72489],"type":"Point"}
}