{
  "type": "Feature",
  "properties": {
    "addr:full":"521 S Pueblo Blvd Pueblo CO 81005",
    "addr:housenumber":"521",
    "addr:postcode":"81005",
    "addr:street":"S Pueblo Blvd",
    "iso:country":"US",
    "sg:address":"521 S Pueblo Blvd",
    "sg:city":"Pueblo",
    "sg:classifiers":[
        {
            "category":"Bars & Pubs",
            "type":"Food & Drink"
        },
        {
            "category":"Travel",
            "subcategory":"Bed & Breakfast",
            "type":"Entertainment"
        }
    ],
    "sg:phone":"+1 719 561 2251",
    "sg:postcode":"81005",
    "sg:province":"CO",
    "sg:tags":[
        "tavern",
        "inn"
    ],
    "wof:name":"Fairway Inn",
    "wof:placetype":"venue"
},
  "geometry": {"coordinates":[-104.661496,38.257867],"type":"Point"}
}