{
  "type": "Feature",
  "properties": {
    "iso:country":"US",
    "sg:address":"725 Palomar Ln",
    "sg:city":"Colorado Springs",
    "sg:classifiers":[
        {
            "category":"Travel",
            "subcategory":"Travel Agent",
            "type":"Entertainment"
        }
    ],
    "sg:phone":"+1 719 633 8554",
    "sg:postcode":"80906",
    "sg:province":"CO",
    "sg:tags":[
        "tours",
        "promoter"
    ],
    "wof:name":"Colorado 600",
    "wof:placetype":"venue"
},
  "geometry": {"coordinates":[-104.87326,38.82234],"type":"Point"}
}