{
  "type": "Feature",
  "properties": {
    "iso:country":"US",
    "sg:address":"270 S Broadway",
    "sg:city":"Denver",
    "sg:classifiers":[
        {
            "category":"Retail",
            "subcategory":"Auto Rental",
            "type":"Services"
        }
    ],
    "sg:phone":"+1 303 733 2218",
    "sg:postcode":"80209",
    "sg:province":"CO",
    "sg:tags":[
        "renting",
        "automobile"
    ],
    "wof:name":"A-Courtesy Rent A Car",
    "wof:placetype":"venue"
},
  "geometry": {"coordinates":[-104.987543,39.71299],"type":"Point"}
}