{
  "type": "Feature",
  "properties": {
    "addr:full":"3985 Vrain St Denver CO 80212",
    "addr:housenumber":"3985",
    "addr:postcode":"80212",
    "addr:street":"Vrain St",
    "iso:country":"US",
    "sg:address":"3985 Vrain St",
    "sg:city":"Denver",
    "sg:classifiers":[
        {
            "category":"Wholesale",
            "subcategory":"Vending Machines",
            "type":"Manufacturing & Wholesale Goods"
        }
    ],
    "sg:phone":"+1 303 458 7714",
    "sg:postcode":"80212",
    "sg:province":"CO",
    "sg:tags":[
        "operator"
    ],
    "wof:name":"Rays Vending",
    "wof:placetype":"venue"
},
  "geometry": {"coordinates":[-105.046357,39.772183],"type":"Point"}
}