{
  "type": "Feature",
  "properties": {
    "addr:full":"1130 W 124th Ave Denver CO 80234",
    "addr:housenumber":"1130",
    "addr:postcode":"80234",
    "addr:street":"W 124Th Ave",
    "iso:country":"US",
    "sg:address":"1130 W 124th Ave",
    "sg:city":"Denver",
    "sg:classifiers":[
        {
            "category":"Professional",
            "type":"Services"
        }
    ],
    "sg:phone":"+1 303 280 1659",
    "sg:postcode":"80234",
    "sg:province":"CO",
    "wof:name":"Quinzos",
    "wof:placetype":"venue"
},
  "geometry": {"coordinates":[-104.996827,39.922025],"type":"Point"}
}