{
  "type": "Feature",
  "properties": {
    "addr:full":"2709 Accolade Cir Colorado Springs CO 80916",
    "addr:housenumber":"2709",
    "addr:postcode":"80916",
    "addr:street":"Accolade Cir",
    "iso:country":"US",
    "sg:address":"2709 Accolade Cir",
    "sg:city":"Colorado Springs",
    "sg:classifiers":[
        {
            "category":"Professional",
            "type":"Services"
        }
    ],
    "sg:phone":"+1 719 390 6830",
    "sg:postcode":"80916",
    "sg:province":"CO",
    "wof:name":"Robert L Kraker",
    "wof:placetype":"venue"
},
  "geometry": {"coordinates":[-104.73313899999999,38.791569],"type":"Point"}
}