{
  "type": "Feature",
  "properties": {
    "iso:country":"US",
    "sg:address":"3440 N Carefree Cir",
    "sg:city":"Colorado Springs",
    "sg:classifiers":[
        {
            "category":"Bars & Pubs",
            "type":"Food & Drink"
        }
    ],
    "sg:phone":"+1 719 550 9721",
    "sg:postcode":"80917",
    "sg:province":"CO",
    "sg:tags":[
        "drinking"
    ],
    "wof:name":"Lounge In The Village",
    "wof:placetype":"venue"
},
  "geometry": {"coordinates":[-104.760637,38.882445],"type":"Point"}
}