{
  "type": "Feature",
  "properties": {
    "addr:full":"330 W 152nd Ave Broomfield CO 80023",
    "addr:housenumber":"330",
    "addr:postcode":"80023",
    "addr:street":"W 152Nd Ave",
    "iso:country":"US",
    "sg:address":"330 W 152nd Ave",
    "sg:city":"Broomfield",
    "sg:classifiers":[
        {
            "category":"Organizations",
            "subcategory":"Religious Organization",
            "type":"Services"
        }
    ],
    "sg:phone":"+1 303 452 7973",
    "sg:postcode":"80023",
    "sg:province":"CO",
    "sg:tags":[
        "church"
    ],
    "sg:website":"www.cog7.org",
    "wof:name":"General Conf-Cog Seventh Day",
    "wof:placetype":"venue"
},
  "geometry": {"coordinates":[-104.990116,39.971978],"type":"Point"}
}