{
  "type": "Feature",
  "properties": {
    "addr:full":"15294 E 8th Ave Aurora CO 80011",
    "addr:housenumber":"15294",
    "addr:postcode":"80011",
    "addr:street":"E 8Th Ave",
    "iso:country":"US",
    "sg:address":"15294 E 8th Ave",
    "sg:city":"Aurora",
    "sg:classifiers":[
        {
            "category":"Real Estate",
            "subcategory":"Real Estate Services",
            "type":"Services"
        },
        {
            "category":"Building & Trades",
            "subcategory":"Cleaning & Sanitation",
            "type":"Services"
        }
    ],
    "sg:phone":"+1 303 537 4432",
    "sg:postcode":"80011",
    "sg:province":"CO",
    "sg:tags":[
        "maintenance",
        "cleaners-interior"
    ],
    "wof:name":"Lord And Hughey S Maintenance And Janito",
    "wof:placetype":"venue"
},
  "geometry": {"coordinates":[-104.810114,39.72865],"type":"Point"}
}