{
  "type": "Feature",
  "properties": {
    "addr:full":"12201 E Arapahoe Rd Centennial CO 80112",
    "addr:housenumber":"12201",
    "addr:postcode":"80112",
    "addr:street":"E Arapahoe Rd",
    "iso:country":"US",
    "sg:address":"12201 E Arapahoe Rd",
    "sg:city":"Centennial",
    "sg:classifiers":[
        {
            "category":"Insurance",
            "subcategory":"Insurance Agent",
            "type":"Services"
        }
    ],
    "sg:phone":"+1 303 257 1281",
    "sg:postcode":"80112",
    "sg:province":"CO",
    "wof:name":"American Family Insurance",
    "wof:placetype":"venue"
},
  "geometry": {"coordinates":[-104.841286,39.595128],"type":"Point"}
}