{
  "type": "Feature",
  "properties": {
    "iso:country":"US",
    "sg:address":"8333 Mummy Range Dr",
    "sg:city":"Fort Collins",
    "sg:classifiers":[
        {
            "category":"Real Estate",
            "subcategory":"Real Estate Agent",
            "type":"Services"
        }
    ],
    "sg:phone":"+1 970 203 0626",
    "sg:postcode":"80528",
    "sg:province":"CO",
    "wof:name":"K&D Realty LLC",
    "wof:placetype":"venue"
},
  "geometry": {"coordinates":[-104.993448,40.468648],"type":"Point"}
}