{
  "type": "Feature",
  "properties": {
    "iso:country":"US",
    "sg:address":"7377 S Hudson Way",
    "sg:city":"Littleton",
    "sg:classifiers":[
        {
            "category":"Building & Trades",
            "subcategory":"Landscaping Services",
            "type":"Services"
        }
    ],
    "sg:phone":"+1 303 771 9424",
    "sg:postcode":"80122",
    "sg:province":"CO",
    "wof:name":"Emerald City Lawn Service LLC",
    "wof:placetype":"venue"
},
  "geometry": {"coordinates":[-104.923992,39.583099],"type":"Point"}
}