{
  "type": "Feature",
  "properties": {
    "addr:full":"4721 S Pierson Way Littleton CO 80127",
    "addr:housenumber":"4721",
    "addr:postcode":"80127",
    "addr:street":"S Pierson Way",
    "iso:country":"US",
    "sg:address":"4721 S Pierson Way",
    "sg:city":"Littleton",
    "sg:classifiers":[
        {
            "category":"Building & Trades",
            "subcategory":"Cleaning & Sanitation",
            "type":"Services"
        }
    ],
    "sg:phone":"+1 303 972 5888",
    "sg:postcode":"80127",
    "sg:province":"CO",
    "sg:tags":[
        "janitor"
    ],
    "wof:name":"Midnight Express Svc Co",
    "wof:placetype":"venue"
},
  "geometry": {"coordinates":[-105.121984,39.628795],"type":"Point"}
}