{
  "type": "Feature",
  "properties": {
    "addr:full":"10707 W Roxbury Ave Littleton CO 80127",
    "addr:housenumber":"10707",
    "addr:postcode":"80127",
    "addr:street":"W Roxbury Ave",
    "iso:country":"US",
    "sg:address":"10707 W Roxbury Ave",
    "sg:city":"Littleton",
    "sg:classifiers":[
        {
            "category":"Professional",
            "subcategory":"Management & Consulting",
            "type":"Services"
        }
    ],
    "sg:phone":"+1 303 933 2227",
    "sg:postcode":"80127",
    "sg:province":"CO",
    "sg:tags":[
        "health",
        "care"
    ],
    "wof:name":"American Applied Technology",
    "wof:placetype":"venue"
},
  "geometry": {"coordinates":[-105.11915,39.587585],"type":"Point"}
}