{
  "type": "Feature",
  "properties": {
    "addr:full":"481 W Jamison Pl Littleton CO 80120",
    "addr:housenumber":"481",
    "addr:postcode":"80120",
    "addr:street":"W Jamison Pl",
    "iso:country":"US",
    "sg:address":"481 W Jamison Pl",
    "sg:city":"Littleton",
    "sg:classifiers":[
        {
            "category":"Manufacturing",
            "subcategory":"Textiles",
            "type":"Manufacturing & Wholesale Goods"
        }
    ],
    "sg:phone":"+1 303 347 9524",
    "sg:postcode":"80120",
    "sg:province":"CO",
    "sg:tags":[
        "mill",
        "knit",
        "outerwear"
    ],
    "wof:name":"Mount Royal Trading",
    "wof:placetype":"venue"
},
  "geometry": {"coordinates":[-104.993652,39.577117],"type":"Point"}
}