{
  "type": "Feature",
  "properties": {
    "iso:country":"US",
    "sg:address":"4422 Cherokee St",
    "sg:city":"Denver",
    "sg:classifiers":[
        {
            "category":"Retail",
            "subcategory":"Repair Shop",
            "type":"Services"
        }
    ],
    "sg:phone":"+1 303 477 9168",
    "sg:postcode":"80216",
    "sg:province":"CO",
    "sg:tags":[
        "machine"
    ],
    "wof:name":"Machine Research",
    "wof:placetype":"venue"
},
  "geometry": {"coordinates":[-104.99115500000001,39.777027],"type":"Point"}
}