{
  "type": "Feature",
  "properties": {
    "addr:full":"8795 Ralston Rd Arvada CO 80002",
    "addr:housenumber":"8795",
    "addr:postcode":"80002",
    "addr:street":"Ralston Rd",
    "iso:country":"US",
    "sg:address":"8795 Ralston Rd",
    "sg:city":"Arvada",
    "sg:classifiers":[
        {
            "category":"Professional",
            "type":"Services"
        }
    ],
    "sg:phone":"+1 303 200 0470",
    "sg:postcode":"80002",
    "sg:province":"CO",
    "wof:name":"Henry T Fiddler",
    "wof:placetype":"venue"
},
  "geometry": {"coordinates":[-105.09472599999999,39.802127],"type":"Point"}
}