{
  "type": "Feature",
  "properties": {
    "addr:full":"905 W Garden of the Gods Rd Colorado Springs CO 80907",
    "addr:housenumber":"905",
    "addr:postcode":"springs;80907",
    "addr:street":"W Garden Of The Gods Rd",
    "iso:country":"US",
    "sg:address":"905 W Garden of the Gods Rd",
    "sg:city":"Colorado Springs",
    "sg:classifiers":[
        {
            "category":"Manufacturing",
            "subcategory":"Tools & Machinery",
            "type":"Manufacturing & Wholesale Goods"
        }
    ],
    "sg:phone":"+1 719 264 0069",
    "sg:postcode":"80907",
    "sg:province":"CO",
    "sg:tags":[
        "machine",
        "shop"
    ],
    "wof:name":"CNC Technical Solutions",
    "wof:placetype":"venue"
},
  "geometry": {"coordinates":[-104.84050999999999,38.896646],"type":"Point"}
}