{
  "type": "Feature",
  "properties": {
    "addr:full":"2082 13th St Steamboat Spgs CO 80487",
    "addr:housenumber":"2082",
    "addr:postcode":"80487",
    "addr:street":"13Th St Steamboat Spgs",
    "iso:country":"US",
    "sg:address":"2082 13th St",
    "sg:city":"Steamboat Spgs",
    "sg:classifiers":[
        {
            "category":"Building & Trades",
            "subcategory":"Construction",
            "type":"Services"
        }
    ],
    "sg:phone":"+1 970 871 9232",
    "sg:postcode":"80487",
    "sg:province":"CO",
    "sg:tags":[
        "excavating",
        "contractor"
    ],
    "sg:website":"www.greatwesternearthworks.com",
    "wof:name":"Great Western Earth Works",
    "wof:placetype":"venue"
},
  "geometry": {"coordinates":[-106.85809500000001,40.495499],"type":"Point"}
}