{
  "type": "Feature",
  "properties": {
    "iso:country":"US",
    "sg:address":"6300 S Main St",
    "sg:city":"Aurora",
    "sg:classifiers":[
        {
            "category":"Banks & Credit Unions",
            "subcategory":"Investment Brokerage",
            "type":"Services"
        },
        {
            "category":"Shopping",
            "subcategory":"Music",
            "type":"Retail Goods"
        },
        {
            "category":"Shopping",
            "subcategory":"Computers & Home Electronics",
            "type":"Retail Goods"
        },
        {
            "category":"Shopping",
            "subcategory":"Gifts & Souvenirs",
            "type":"Retail Goods"
        },
        {
            "category":"Utilities",
            "subcategory":"Mobile Phone",
            "type":"Services"
        },
        {
            "category":"Communications",
            "subcategory":"Film & Video Production",
            "type":"Services"
        },
        {
            "category":"Shopping",
            "subcategory":"Books",
            "type":"Retail Goods"
        },
        {
            "category":"Wholesale",
            "subcategory":"Books, Periodicals, & Newspapers",
            "type":"Manufacturing & Wholesale Goods"
        }
    ],
    "sg:phone":"+1 303 766 3069",
    "sg:postcode":"80016",
    "sg:province":"CO",
    "sg:tags":[
        "shop",
        "educational",
        "dvd",
        "material",
        "sale",
        "hotspot",
        "dvds-rental",
        "record",
        "magazine",
        "tapes-wholesale",
        "tape",
        "cd's",
        "wi-fi",
        "store",
        "manufacturer"
    ],
    "sg:website":"http://store-locator.barnesandnoble.com/store/2245",
    "wof:name":"Barnes & Noble Booksellers",
    "wof:placetype":"venue"
},
  "geometry": {"coordinates":[-104.708946,39.60273],"type":"Point"}
}