{
  "type": "Feature",
  "properties": {
    "addr:full":"412 S Tejon St Colorado Springs CO 80903",
    "addr:housenumber":"412",
    "addr:postcode":"80903",
    "addr:street":"S Tejon St",
    "iso:country":"US",
    "sg:address":"412 S Tejon St",
    "sg:city":"Colorado Springs",
    "sg:classifiers":[
        {
            "category":"Professional",
            "subcategory":"Employment Agencies",
            "type":"Services"
        }
    ],
    "sg:phone":"+1 719 632 1883",
    "sg:postcode":"80903",
    "sg:province":"CO",
    "sg:tags":[
        "opportunity"
    ],
    "wof:name":"Labor Ready Inc",
    "wof:placetype":"venue"
},
  "geometry": {"coordinates":[-104.82395,38.827031],"type":"Point"}
}