{
  "type": "Feature",
  "properties": {
    "iso:country":"US",
    "sg:address":"2619 Spruce St",
    "sg:city":"Boulder",
    "sg:classifiers":[
        {
            "category":"Professional",
            "subcategory":"Engineering",
            "type":"Services"
        }
    ],
    "sg:phone":"+1 303 444 3620",
    "sg:postcode":"80302",
    "sg:province":"CO",
    "sg:tags":[
        "consultant",
        "structural"
    ],
    "sg:website":"www.ana-usa.com",
    "wof:name":"Atkinson-Noland & Assoc",
    "wof:placetype":"venue"
},
  "geometry": {"coordinates":[-105.25991,40.023177],"type":"Point"}
}