{
  "type": "Feature",
  "properties": {
    "iso:country":"US",
    "sg:address":"700 Main Ave",
    "sg:city":"Durango",
    "sg:classifiers":[
        {
            "category":"Banks & Credit Unions",
            "subcategory":"Bank",
            "type":"Services"
        }
    ],
    "sg:phone":"+1 970 375 3274",
    "sg:postcode":"81301",
    "sg:province":"CO",
    "sg:tags":[
        "escrow"
    ],
    "wof:name":"Animas Escrow",
    "wof:placetype":"venue"
},
  "geometry": {"coordinates":[-107.881052,37.272317],"type":"Point"}
}