{
  "type": "Feature",
  "properties": {
    "addr:full":"1458 Quince St Denver CO 80220",
    "addr:housenumber":"1458",
    "addr:postcode":"80220",
    "addr:street":"Quince St",
    "iso:country":"US",
    "sg:address":"1458 Quince St",
    "sg:city":"Denver",
    "sg:classifiers":[
        {
            "category":"Building & Trades",
            "subcategory":"Construction",
            "type":"Services"
        }
    ],
    "sg:phone":"+1 303 388 0115",
    "sg:postcode":"80220",
    "sg:province":"CO",
    "sg:tags":[
        "nonresidential"
    ],
    "wof:name":"New Vega Enterprises LTD",
    "wof:placetype":"venue"
},
  "geometry": {"coordinates":[-104.902244,39.739297],"type":"Point"}
}