{
  "type": "Feature",
  "properties": {
    "addr:full":"15794 E Gunnison Pl Aurora CO 80017",
    "addr:housenumber":"15794",
    "addr:postcode":"80017",
    "addr:street":"E Gunnison Pl",
    "iso:country":"US",
    "sg:address":"15794 E Gunnison Pl",
    "sg:city":"Aurora",
    "sg:classifiers":[
        {
            "category":"Shopping",
            "type":"Retail Goods"
        }
    ],
    "sg:phone":"+1 303 751 1414",
    "sg:postcode":"80017",
    "sg:province":"CO",
    "sg:tags":[
        "merchandise"
    ],
    "wof:name":"Littleton My Mart Inc",
    "wof:placetype":"venue"
},
  "geometry": {"coordinates":[-104.8035,39.688704],"type":"Point"}
}