{
  "type": "Feature",
  "properties": {
    "iso:country":"US",
    "sg:address":"7425 Sengbeil Rd",
    "sg:city":"Yoder",
    "sg:classifiers":[
        {
            "category":"Autos & Motor Vehicles",
            "subcategory":"Automobile Sales",
            "type":"Retail Goods"
        }
    ],
    "sg:phone":"+1 719 541 4445",
    "sg:postcode":"80864",
    "sg:province":"CO",
    "sg:tags":[
        "equipment",
        "aircraft",
        "parts",
        "supply"
    ],
    "wof:name":"Just Plane Parts",
    "wof:placetype":"venue"
},
  "geometry": {"coordinates":[-104.183857,38.940332],"type":"Point"}
}