{
  "type": "Feature",
  "properties": {
    "iso:country":"US",
    "sg:address":"5353 W Dartmouth Ave",
    "sg:city":"Denver",
    "sg:classifiers":[
        {
            "category":"Professional",
            "subcategory":"Lawyer & Legal Services",
            "type":"Services"
        }
    ],
    "sg:phone":"+1 303 989 6655",
    "sg:postcode":"80227",
    "sg:province":"CO",
    "wof:name":"Pickard & Waters PC",
    "wof:placetype":"venue"
},
  "geometry": {"coordinates":[-105.054131,39.65622],"type":"Point"}
}