{
  "type": "Feature",
  "properties": {
    "iso:country":"US",
    "sg:address":"4350 Wadsworth Blvd Ste 440",
    "sg:city":"Wheat Ridge",
    "sg:classifiers":[
        {
            "category":"Health Services",
            "subcategory":"Doctor",
            "type":"Services"
        }
    ],
    "sg:phone":"+1 303 467 1400",
    "sg:postcode":"80033",
    "sg:province":"CO",
    "wof:name":"Olsen Robert MD",
    "wof:placetype":"venue"
},
  "geometry": {"coordinates":[-105.080773,39.775829],"type":"Point"}
}