{
  "type": "Feature",
  "properties": {
    "addr:full":"845 Coal Creek Cir Louisville CO 80027",
    "addr:housenumber":"845",
    "addr:postcode":"80027",
    "addr:street":"Coal Creek Cir",
    "iso:country":"US",
    "sg:address":"845 Coal Creek Cir",
    "sg:city":"Louisville",
    "sg:classifiers":[
        {
            "category":"Professional",
            "subcategory":"Research",
            "type":"Services"
        }
    ],
    "sg:phone":"+1 303 991 1970",
    "sg:postcode":"80027",
    "sg:province":"CO",
    "wof:name":"BCM Advanced Research",
    "wof:placetype":"venue"
},
  "geometry": {"coordinates":[-105.158676,39.957847],"type":"Point"}
}