{
  "type": "Feature",
  "properties": {
    "addr:full":"1421 Greene St Silverton CO 81433",
    "addr:housenumber":"1421",
    "addr:postcode":"81433",
    "addr:street":"Greene St",
    "iso:country":"US",
    "sg:address":"1421 Greene St",
    "sg:city":"Silverton",
    "sg:classifiers":[
        {
            "category":"Restaurant",
            "type":"Food & Drink"
        }
    ],
    "sg:phone":"+1 970 387 5768",
    "sg:postcode":"81433",
    "sg:province":"CO",
    "wof:name":"Kendall Mountain Cafe",
    "wof:placetype":"venue"
},
  "geometry": {"coordinates":[-107.66228599999999,37.814036],"type":"Point"}
}