{
  "type": "Feature",
  "properties": {
    "addr:full":"90 Commander Spr Boulder CO 80302",
    "addr:housenumber":"90",
    "addr:postcode":"80302",
    "addr:street":"Commander Spr",
    "iso:country":"US",
    "sg:address":"90 Commander Spr",
    "sg:city":"Boulder",
    "sg:classifiers":[
        {
            "category":"Professional",
            "type":"Services"
        }
    ],
    "sg:phone":"+1 303 443 3700",
    "sg:postcode":"80302",
    "sg:province":"CO",
    "sg:tags":[
        "geophysicist"
    ],
    "wof:name":"Trac",
    "wof:placetype":"venue"
},
  "geometry": {"coordinates":[-105.333979,40.038478],"type":"Point"}
}