{
  "type": "Feature",
  "properties": {
    "iso:country":"US",
    "sg:address":"90 Commander Spr",
    "sg:city":"Boulder",
    "sg:classifiers":[
        {
            "category":"Professional",
            "type":"Services"
        }
    ],
    "sg:phone":"+1 303 443 3700",
    "sg:postcode":"80302",
    "sg:province":"CO",
    "sg:tags":[
        "geophysicist"
    ],
    "wof:name":"Trac",
    "wof:placetype":"venue"
},
  "geometry": {"coordinates":[-105.333979,40.038478],"type":"Point"}
}