{
  "type": "Feature",
  "properties": {
    "addr:full":"500 27th St Greeley CO 80631",
    "addr:housenumber":"500",
    "addr:postcode":"80631",
    "addr:street":"27Th St",
    "iso:country":"US",
    "sg:address":"500 27th St",
    "sg:city":"Greeley",
    "sg:classifiers":[
        {
            "category":"Home & Garden",
            "subcategory":"Building Materials",
            "type":"Retail Goods"
        }
    ],
    "sg:phone":"+1 970 356 9000",
    "sg:postcode":"80631",
    "sg:province":"CO",
    "wof:name":"BMC West Building Materials",
    "wof:placetype":"venue"
},
  "geometry": {"coordinates":[-104.68728299999999,40.39458],"type":"Point"}
}