{
  "type": "Feature",
  "properties": {
    "iso:country":"US",
    "sg:address":"1833 S Pueblo Blvd",
    "sg:city":"Pueblo",
    "sg:classifiers":[
        {
            "category":"Personal",
            "subcategory":"Beauty Salon",
            "type":"Services"
        }
    ],
    "sg:phone":"+1 719 566 1990",
    "sg:postcode":"81005",
    "sg:province":"CO",
    "wof:name":"Cost Cutters Family Hair Care",
    "wof:placetype":"venue"
},
  "geometry": {"coordinates":[-104.66248299999999,38.237967],"type":"Point"}
}