{
  "type": "Feature",
  "properties": {
    "iso:country":"US",
    "sg:address":"10755 E Exposition Ave",
    "sg:city":"Aurora",
    "sg:classifiers":[
        {
            "category":"Building & Trades",
            "subcategory":"Construction",
            "type":"Services"
        }
    ],
    "sg:phone":"+1 303 367 4049",
    "sg:postcode":"80012",
    "sg:province":"CO",
    "sg:tags":[
        "hanging",
        "contractor"
    ],
    "wof:name":"Delfino Ortega Painting Servic",
    "wof:placetype":"venue"
},
  "geometry": {"coordinates":[-104.859692,39.703899],"type":"Point"}
}