{
  "type": "Feature",
  "properties": {
    "iso:country":"US",
    "sg:address":"28406 Hwy 160",
    "sg:city":"Durango",
    "sg:classifiers":[
        {
            "category":"Autos & Motor Vehicles",
            "subcategory":"Automobile Sales",
            "type":"Retail Goods"
        }
    ],
    "sg:phone":"+1 970 247 5000",
    "sg:postcode":"81303",
    "sg:province":"CO",
    "sg:tags":[
        "car",
        "dealer"
    ],
    "wof:name":"Skyway Auto Inc",
    "wof:placetype":"venue"
},
  "geometry": {"coordinates":[-107.83170800000001,37.228938],"type":"Point"}
}