{
  "type": "Feature",
  "properties": {
    "addr:full":"462 Lewis St Pagosa Springs CO 81147",
    "addr:housenumber":"462",
    "addr:postcode":"81147",
    "addr:street":"Lewis St",
    "iso:country":"US",
    "sg:address":"462 Lewis St",
    "sg:city":"Pagosa Springs",
    "sg:classifiers":[
        {
            "category":"Mining & Drilling",
            "type":"Manufacturing & Wholesale Goods"
        }
    ],
    "sg:phone":"+1 970 264 0170",
    "sg:postcode":"81147",
    "sg:province":"CO",
    "sg:tags":[
        "oil",
        "gas",
        "producer"
    ],
    "wof:name":"Rio Chama Petroleum Inc",
    "wof:placetype":"venue"
},
  "geometry": {"coordinates":[-107.012334,37.267328],"type":"Point"}
}