{
  "type": "Feature",
  "properties": {
    "addr:full":"2805 Wilderness Pl Boulder CO 80301",
    "addr:housenumber":"2805",
    "addr:postcode":"80301",
    "addr:street":"Wilderness Pl",
    "iso:country":"US",
    "sg:address":"2805 Wilderness Pl",
    "sg:city":"Boulder",
    "sg:classifiers":[
        {
            "category":"Professional",
            "subcategory":"Advertising",
            "type":"Services"
        }
    ],
    "sg:phone":"+1 303 442 4399",
    "sg:postcode":"80301",
    "sg:province":"CO",
    "sg:tags":[
        "mailing",
        "shipping"
    ],
    "wof:name":"World Post Direct",
    "wof:placetype":"venue"
},
  "geometry": {"coordinates":[-105.248885,40.025975],"type":"Point"}
}