{
  "type": "Feature",
  "properties": {
    "iso:country":"US",
    "sg:address":"1248 Railroad Ave",
    "sg:city":"Rifle",
    "sg:classifiers":[
        {
            "category":"Utilities",
            "subcategory":"Mobile Phone",
            "type":"Services"
        }
    ],
    "sg:phone":"+1 970 625 8776",
    "sg:postcode":"81650",
    "sg:province":"CO",
    "sg:tags":[
        "communication",
        "radiotelephone"
    ],
    "wof:name":"Phonesrus LLC",
    "wof:placetype":"venue"
},
  "geometry": {"coordinates":[-107.80119999999999,39.529565],"type":"Point"}
}