{
  "type": "Feature",
  "properties": {
    "addr:full":"1953 Senecio Dr Larkspur CO 80118",
    "addr:housenumber":"1953",
    "addr:postcode":"80118",
    "addr:street":"Senecio Dr",
    "iso:country":"US",
    "sg:address":"1953 Senecio Dr",
    "sg:city":"Larkspur",
    "sg:classifiers":[
        {
            "category":"Professional",
            "subcategory":"Art Services",
            "type":"Services"
        }
    ],
    "sg:phone":"+1 303 681 3452",
    "sg:postcode":"80118",
    "sg:province":"CO",
    "sg:tags":[
        "graphic",
        "designer"
    ],
    "wof:name":"Visual West",
    "wof:placetype":"venue"
},
  "geometry": {"coordinates":[-104.922218,39.259],"type":"Point"}
}