{
  "type": "Feature",
  "properties": {
    "addr:full":"5650 Lowell Blvd Denver CO 80221",
    "addr:housenumber":"5650",
    "addr:postcode":"80221",
    "addr:street":"Lowell Blvd",
    "iso:country":"US",
    "sg:address":"5650 Lowell Blvd",
    "sg:city":"Denver",
    "sg:classifiers":[
        {
            "category":"Home & Garden",
            "subcategory":"Carpets & Floor Coverings",
            "type":"Retail Goods"
        }
    ],
    "sg:phone":"+1 303 800 1615",
    "sg:postcode":"80221",
    "sg:province":"CO",
    "sg:tags":[
        "flooring"
    ],
    "wof:name":"T & T Flooring",
    "wof:placetype":"venue"
},
  "geometry": {"coordinates":[-105.03451,39.799895],"type":"Point"}
}