{
  "type": "Feature",
  "properties": {
    "addr:full":"954 E 2nd Ave Durango CO 81301",
    "addr:housenumber":"954",
    "addr:postcode":"co 81301",
    "addr:street":"E 2Nd Ave",
    "iso:country":"US",
    "sg:address":"954 E 2nd Ave",
    "sg:city":"Durango",
    "sg:classifiers":[
        {
            "category":"Banks & Credit Unions",
            "subcategory":"Bank",
            "type":"Services"
        }
    ],
    "sg:phone":"+1 970 375 6309",
    "sg:postcode":"81301",
    "sg:province":"CO",
    "sg:tags":[
        "loan",
        "real estate"
    ],
    "wof:name":"American Mountain Mortgage",
    "wof:placetype":"venue"
},
  "geometry": {"coordinates":[-107.879104,37.273574],"type":"Point"}
}