{
  "type": "Feature",
  "properties": {
    "iso:country":"US",
    "sg:address":"9686 Fairwood St",
    "sg:city":"Littleton",
    "sg:classifiers":[
        {
            "category":"Building & Trades",
            "subcategory":"Construction",
            "type":"Services"
        }
    ],
    "sg:phone":"+1 303 984 1019",
    "sg:postcode":"80125",
    "sg:province":"CO",
    "sg:tags":[
        "house"
    ],
    "wof:name":"Vance Remodeling",
    "wof:placetype":"venue"
},
  "geometry": {"coordinates":[-105.067526,39.475416],"type":"Point"}
}