{
  "type": "Feature",
  "properties": {
    "addr:full":"1474 Yampa Ave Craig CO 81625",
    "addr:housenumber":"1474",
    "addr:postcode":"81625",
    "addr:street":"Yampa Ave",
    "iso:country":"US",
    "sg:address":"1474 Yampa Ave",
    "sg:city":"Craig",
    "sg:classifiers":[
        {
            "category":"Shopping",
            "subcategory":"Bicycles & Sporting Goods",
            "type":"Retail Goods"
        }
    ],
    "sg:phone":"+1 970 824 7974",
    "sg:postcode":"81625",
    "sg:province":"CO",
    "wof:name":"Mr BS Pro Shop",
    "wof:placetype":"venue"
},
  "geometry": {"coordinates":[-107.547,40.53191],"type":"Point"}
}