{
  "type": "Feature",
  "properties": {
    "addr:full":"7005 W Kentucky Ave Denver CO 80226",
    "addr:housenumber":"7005",
    "addr:postcode":"80226",
    "addr:street":"W Kentucky Ave",
    "iso:country":"US",
    "sg:address":"7005 W Kentucky Ave",
    "sg:city":"Denver",
    "sg:classifiers":[
        {
            "category":"Shopping",
            "subcategory":"Gifts & Souvenirs",
            "type":"Retail Goods"
        }
    ],
    "sg:phone":"+1 303 936 5065",
    "sg:postcode":"80226",
    "sg:province":"CO",
    "wof:name":"Products By Choice Inc",
    "wof:placetype":"venue"
},
  "geometry": {"coordinates":[-105.076167,39.699916],"type":"Point"}
}