{
  "type": "Feature",
  "properties": {
    "iso:country":"US",
    "sg:address":"7307 Grandview Ave",
    "sg:city":"Arvada",
    "sg:classifiers":[
        {
            "category":"Organizations",
            "subcategory":"Non-profit Organization",
            "type":"Services"
        }
    ],
    "sg:phone":"+1 303 420 6100",
    "sg:postcode":"80002",
    "sg:province":"CO",
    "sg:tags":[
        "service/non-profit",
        "community"
    ],
    "wof:name":"Historic Olde Town Arvada",
    "wof:placetype":"venue"
},
  "geometry": {"coordinates":[-105.077682,39.800631],"type":"Point"}
}