{
  "type": "Feature",
  "properties": {
    "iso:country":"US",
    "sg:address":"1115 E Main St",
    "sg:city":"Cortez",
    "sg:classifiers":[
        {
            "category":"Manufacturing",
            "subcategory":"Glass & Minerals",
            "type":"Manufacturing & Wholesale Goods"
        }
    ],
    "sg:phone":"+1 970 564 1212",
    "sg:postcode":"81321",
    "sg:province":"CO",
    "sg:tags":[
        "ready",
        "concrete",
        "mfg"
    ],
    "wof:name":"Crystal Mini Mix LLC",
    "wof:placetype":"venue"
},
  "geometry": {"coordinates":[-108.570803,37.348777],"type":"Point"}
}