{
  "type": "Feature",
  "properties": {
    "iso:country":"US",
    "sg:address":"4704 Harlan St",
    "sg:city":"Denver",
    "sg:classifiers":[
        {
            "category":"Professional",
            "subcategory":"Accounting & Tax Preparation",
            "type":"Services"
        }
    ],
    "sg:phone":"+1 720 854 0370",
    "sg:postcode":"80212",
    "sg:province":"CO",
    "sg:tags":[
        "bookkeeping",
        "general"
    ],
    "wof:name":"Affordable Bookkeeping Svc",
    "wof:placetype":"venue"
},
  "geometry": {"coordinates":[-105.062506,39.782972],"type":"Point"}
}