{
  "type": "Feature",
  "properties": {
    "iso:country":"US",
    "sg:address":"1503 Grant St",
    "sg:city":"Denver",
    "sg:classifiers":[
        {
            "category":"Professional",
            "subcategory":"Detective & Security Services",
            "type":"Services"
        }
    ],
    "sg:phone":"+1 720 356 0417",
    "sg:postcode":"80203",
    "sg:province":"CO",
    "sg:tags":[
        "system"
    ],
    "sg:website":"homesecurityofdenver.com/",
    "wof:name":"Denver ADT Dealer",
    "wof:placetype":"venue"
},
  "geometry": {"coordinates":[-104.983619,39.740128],"type":"Point"}
}