{
  "type": "Feature",
  "properties": {
    "addr:full":"6425 Brighton Blvd Commerce City CO 80022",
    "addr:housenumber":"6425",
    "addr:postcode":"80022",
    "addr:street":"Brighton Blvd",
    "iso:country":"US",
    "sg:address":"6425 Brighton Blvd",
    "sg:city":"Commerce City",
    "sg:classifiers":[
        {
            "category":"Manufacturing",
            "subcategory":"Tools & Machinery",
            "type":"Manufacturing & Wholesale Goods"
        }
    ],
    "sg:phone":"+1 303 288 9366",
    "sg:postcode":"80022",
    "sg:province":"CO",
    "sg:tags":[
        "machine",
        "shop",
        "jobbing",
        "repair"
    ],
    "wof:name":"Eason Service System Inc",
    "wof:placetype":"venue"
},
  "geometry": {"coordinates":[-104.935198,39.815727],"type":"Point"}
}