{
  "type": "Feature",
  "properties": {
    "addr:full":"4745 Boardwalk Dr Fort Collins CO 80525",
    "addr:housenumber":"4745",
    "addr:postcode":"80525",
    "addr:street":"Boardwalk Dr",
    "iso:country":"US",
    "sg:address":"4745 Boardwalk Dr",
    "sg:city":"Fort Collins",
    "sg:classifiers":[
        {
            "category":"Personal",
            "type":"Services"
        }
    ],
    "sg:phone":"+1 970 206 1696",
    "sg:postcode":"80525",
    "sg:province":"CO",
    "sg:tags":[
        "therapist",
        "massage"
    ],
    "wof:name":"Barbara King & Assoc",
    "wof:placetype":"venue"
},
  "geometry": {"coordinates":[-105.065445,40.523115],"type":"Point"}
}