{
  "type": "Feature",
  "properties": {
    "iso:country":"US",
    "sg:address":"204 Mount View Ln",
    "sg:city":"Colorado Springs",
    "sg:classifiers":[
        {
            "category":"Restaurant",
            "type":"Food & Drink"
        }
    ],
    "sg:menulink":"http://www.allmenus.com/co/colorado-springs/69504-dominos-pizza/menu/",
    "sg:phone":"+1 719 598 8800",
    "sg:postcode":"80907",
    "sg:province":"CO",
    "sg:tags":[
        "american",
        "wing",
        "pizza"
    ],
    "wof:name":"Domino's Pizza",
    "wof:placetype":"venue"
},
  "geometry": {"coordinates":[-104.818336,38.890016],"type":"Point"}
}