{
  "type": "Feature",
  "properties": {
    "addr:full":"207 N Wahsatch Ave Colorado Springs CO 80903",
    "addr:housenumber":"207",
    "addr:postcode":"80903",
    "addr:street":"N Wahsatch Ave",
    "iso:country":"US",
    "sg:address":"207 N Wahsatch Ave",
    "sg:city":"Colorado Springs",
    "sg:classifiers":[
        {
            "category":"Restaurant",
            "type":"Food & Drink"
        }
    ],
    "sg:phone":"+1 719 634 7589",
    "sg:postcode":"80903",
    "sg:province":"CO",
    "sg:tags":[
        "eating"
    ],
    "wof:name":"McDonalds",
    "wof:placetype":"venue"
},
  "geometry": {"coordinates":[-104.817814,38.837844],"type":"Point"}
}