{
  "type": "Feature",
  "properties": {
    "addr:full":"7069 Pecos St Denver CO 80221",
    "addr:housenumber":"7069",
    "addr:postcode":"80221",
    "addr:street":"Pecos St",
    "iso:country":"US",
    "sg:address":"7069 Pecos St",
    "sg:city":"Denver",
    "sg:classifiers":[
        {
            "category":"Bars & Pubs",
            "type":"Food & Drink"
        }
    ],
    "sg:phone":"+1 303 428 0425",
    "sg:postcode":"80221",
    "sg:province":"CO",
    "sg:tags":[
        "drinking"
    ],
    "wof:name":"Stein's Tavern",
    "wof:placetype":"venue"
},
  "geometry": {"coordinates":[-105.006309,39.824553],"type":"Point"}
}