{
  "type": "Feature",
  "properties": {
    "iso:country":"US",
    "sg:address":"255 Union Blvd Suite 300",
    "sg:city":"Lakewood",
    "sg:classifiers":[
        {
            "category":"Health Services",
            "subcategory":"Doctor",
            "type":"Services"
        },
        {
            "category":"Health Services",
            "subcategory":"Clinic",
            "type":"Services"
        },
        {
            "category":"Health Services",
            "subcategory":"Nursing And Care Facility",
            "type":"Services"
        },
        {
            "category":"Community Center",
            "type":"Public Place"
        },
        {
            "category":"Health Services",
            "subcategory":"Hospital",
            "type":"Services"
        }
    ],
    "sg:phone":"+1 303 800 2980",
    "sg:postcode":"80228",
    "sg:province":"CO",
    "sg:tags":[
        "physician",
        "pediatrics-emergency",
        "emergency",
        "medical",
        "surgeons",
        "medicine"
    ],
    "sg:website":"http://rockymountainurgentcare.com/index.php",
    "wof:name":"Rocky Mountain Urgent Care",
    "wof:placetype":"venue"
},
  "geometry": {"coordinates":[-105.132594,39.718529],"type":"Point"}
}