{
  "type": "Feature",
  "properties": {
    "iso:country":"US",
    "sg:address":"787 Wadsworth Blvd",
    "sg:city":"Denver",
    "sg:classifiers":[
        {
            "category":"Retail",
            "subcategory":"Auto Repair",
            "type":"Services"
        }
    ],
    "sg:phone":"+1 303 232 6222",
    "sg:postcode":"80214",
    "sg:province":"CO",
    "sg:tags":[
        "body",
        "leather",
        "restoration",
        "automobile",
        "classic"
    ],
    "wof:name":"Auto Weave Upholstery West",
    "wof:placetype":"venue"
},
  "geometry": {"coordinates":[-105.081559,39.729574],"type":"Point"}
}