{
  "type": "Feature",
  "properties": {
    "addr:full":"10536 Pompey Way Denver CO 80234",
    "addr:housenumber":"10536",
    "addr:postcode":"80234",
    "addr:street":"Pompey Way",
    "iso:country":"US",
    "sg:address":"10536 Pompey Way",
    "sg:city":"Denver",
    "sg:classifiers":[
        {
            "category":"Wholesale",
            "subcategory":"Durable Goods & Equipment",
            "type":"Manufacturing & Wholesale Goods"
        }
    ],
    "sg:phone":"+1 303 452 0935",
    "sg:postcode":"80234",
    "sg:province":"CO",
    "wof:name":"Dg Supplies",
    "wof:placetype":"venue"
},
  "geometry": {"coordinates":[-105.00818200000001,39.888638],"type":"Point"}
}