{
  "type": "Feature",
  "properties": {
    "iso:country":"US",
    "sg:address":"1182 Beard Creek Rd",
    "sg:city":"Edwards",
    "sg:classifiers":[
        {
            "category":"Real Estate",
            "subcategory":"Developer",
            "type":"Services"
        }
    ],
    "sg:phone":"+1 970 926 4938",
    "sg:postcode":"81632",
    "sg:province":"CO",
    "wof:name":"Cliver Development Co",
    "wof:placetype":"venue"
},
  "geometry": {"coordinates":[-106.598732,39.659186],"type":"Point"}
}