{
  "type": "Feature",
  "properties": {
    "iso:country":"US",
    "sg:address":"1534 11th Ave",
    "sg:city":"Greeley",
    "sg:classifiers":[
        {
            "category":"Organizations",
            "subcategory":"Membership Organization",
            "type":"Services"
        }
    ],
    "sg:phone":"+1 970 353 2835",
    "sg:postcode":"80631",
    "sg:province":"CO",
    "wof:name":"Laam",
    "wof:placetype":"venue"
},
  "geometry": {"coordinates":[-104.696265,40.414441],"type":"Point"}
}