{
  "type": "Feature",
  "properties": {
    "iso:country":"US",
    "sg:address":"143 Union Blvd",
    "sg:city":"Lakewood",
    "sg:classifiers":[
        {
            "category":"Wholesale",
            "subcategory":"Machinery & Supplies",
            "type":"Manufacturing & Wholesale Goods"
        }
    ],
    "sg:phone":"+1 303 716 9580",
    "sg:postcode":"80228",
    "sg:province":"CO",
    "sg:tags":[
        "equipment",
        "printing"
    ],
    "wof:name":"GFX International",
    "wof:placetype":"venue"
},
  "geometry": {"coordinates":[-105.133245,39.71556],"type":"Point"}
}