{
  "type": "Feature",
  "properties": {
    "addr:full":"216 E 3rd Ave Yuma CO 80759",
    "addr:housenumber":"216",
    "addr:postcode":"80759",
    "addr:street":"E 3Rd Ave",
    "iso:country":"US",
    "sg:address":"216 E 3rd Ave",
    "sg:city":"Yuma",
    "sg:classifiers":[
        {
            "category":"Government",
            "subcategory":"Fire Station",
            "type":"Public Place"
        }
    ],
    "sg:phone":"+1 970 848 5441",
    "sg:postcode":"80759",
    "sg:province":"CO",
    "sg:tags":[
        "department"
    ],
    "wof:name":"Yuma City Fire Dept",
    "wof:placetype":"venue"
},
  "geometry": {"coordinates":[-102.72221999999999,40.123379],"type":"Point"}
}