{
  "type": "Feature",
  "properties": {
    "addr:full":"13 Inverness Way S Englewood CO 80112",
    "addr:housenumber":"13",
    "addr:postcode":"englewood;80112",
    "addr:street":"Inverness Way S",
    "iso:country":"US",
    "sg:address":"13 Inverness Way S",
    "sg:city":"Englewood",
    "sg:classifiers":[
        {
            "category":"Manufacturing",
            "subcategory":"Tools & Machinery",
            "type":"Manufacturing & Wholesale Goods"
        }
    ],
    "sg:phone":"+1 303 799 6640",
    "sg:postcode":"80112",
    "sg:province":"CO",
    "sg:tags":[
        "transformer",
        "fiber",
        "relay",
        "electric",
        "optic",
        "mfg",
        "equipment"
    ],
    "sg:website":"www.e-maxinstruments.com",
    "wof:name":"E-Max Instruments Inc",
    "wof:placetype":"venue"
},
  "geometry": {"coordinates":[-104.860598,39.566258],"type":"Point"}
}