{
  "type": "Feature",
  "properties": {
    "iso:country":"US",
    "sg:address":"2012 W Co Rd 56",
    "sg:city":"Fort Collins",
    "sg:classifiers":[
        {
            "category":"Building & Trades",
            "subcategory":"Construction",
            "type":"Services"
        }
    ],
    "sg:phone":"+1 970 221 1424",
    "sg:postcode":"80524",
    "sg:province":"CO",
    "sg:tags":[
        "contractor"
    ],
    "wof:name":"Cook Restoration & Remodeling",
    "wof:placetype":"venue"
},
  "geometry": {"coordinates":[-105.111469,40.654655],"type":"Point"}
}