{
  "type": "Feature",
  "properties": {
    "iso:country":"US",
    "sg:address":"995 W Garden of the Gods Rd",
    "sg:city":"Colorado Springs",
    "sg:classifiers":[
        {
            "category":"Wholesale",
            "subcategory":"Home Furnishings",
            "type":"Manufacturing & Wholesale Goods"
        },
        {
            "category":"Home & Garden",
            "subcategory":"Carpets & Floor Coverings",
            "type":"Retail Goods"
        }
    ],
    "sg:phone":"+1 719 593 9390",
    "sg:postcode":"80907",
    "sg:province":"CO",
    "sg:tags":[
        "installation",
        "i",
        "rug",
        "also",
        "window",
        "dealer"
    ],
    "sg:website":"www.interior-exterior.com",
    "wof:name":"Interiors Exteriors",
    "wof:placetype":"venue"
},
  "geometry": {"coordinates":[-104.839202,38.896663],"type":"Point"}
}