{
  "type": "Feature",
  "properties": {
    "iso:country":"US",
    "sg:address":"7608 N Union Blvd",
    "sg:city":"Colorado Springs",
    "sg:classifiers":[
        {
            "category":"Health Services",
            "subcategory":"Doctor",
            "type":"Services"
        }
    ],
    "sg:phone":"+1 719 548 0700",
    "sg:postcode":"80920",
    "sg:province":"CO",
    "sg:tags":[
        "medical"
    ],
    "wof:name":"Clark Douglas P MD",
    "wof:placetype":"venue"
},
  "geometry": {"coordinates":[-104.774303,38.944045],"type":"Point"}
}