{
  "type": "Feature",
  "properties": {
    "iso:country":"US",
    "sg:address":"4800 Joliet St",
    "sg:city":"Denver",
    "sg:classifiers":[
        {
            "category":"Manufacturing",
            "subcategory":"Rubber & Plastics",
            "type":"Manufacturing & Wholesale Goods"
        }
    ],
    "sg:phone":"+1 303 371 9422",
    "sg:postcode":"80239",
    "sg:province":"CO",
    "sg:tags":[
        "plastics-finished-wholesale",
        "manufacturer"
    ],
    "sg:website":"http://www.maccourt.com",
    "wof:name":"Shipping Division",
    "wof:placetype":"venue"
},
  "geometry": {"coordinates":[-104.86133100000001,39.786418],"type":"Point"}
}