{
  "type": "Feature",
  "properties": {
    "iso:country":"US",
    "sg:address":"5453 Manhart St",
    "sg:city":"Sedalia",
    "sg:classifiers":[
        {
            "category":"Bars & Pubs",
            "type":"Food & Drink"
        }
    ],
    "sg:phone":"+1 303 688 9967",
    "sg:postcode":"80135",
    "sg:province":"CO",
    "wof:name":"Bud's Cafe & Bar",
    "wof:placetype":"venue"
},
  "geometry": {"coordinates":[-104.962259,39.437381],"type":"Point"}
}