{
  "type": "Feature",
  "properties": {
    "addr:full":"911 S Saint Vrain Ave Estes Park CO 80517",
    "addr:housenumber":"911",
    "addr:postcode":"80517",
    "addr:street":"S Saint Vrain Ave",
    "iso:country":"US",
    "sg:address":"911 S Saint Vrain Ave",
    "sg:city":"Estes Park",
    "sg:classifiers":[
        {
            "category":"Building & Trades",
            "subcategory":"Construction",
            "type":"Services"
        }
    ],
    "sg:phone":"+1 970 586 3145",
    "sg:postcode":"80517",
    "sg:province":"CO",
    "sg:tags":[
        "contractor"
    ],
    "wof:name":"Harold Dannels & Sons Inc",
    "wof:placetype":"venue"
},
  "geometry": {"coordinates":[-105.503597,40.364531],"type":"Point"}
}