{
  "type": "Feature",
  "properties": {
    "iso:country":"US",
    "sg:address":"211 Hwy 92",
    "sg:city":"Delta",
    "sg:classifiers":[
        {
            "category":"Retail",
            "subcategory":"Auto Rental",
            "type":"Services"
        }
    ],
    "sg:phone":"+1 970 874 8420",
    "sg:postcode":"81416",
    "sg:province":"CO",
    "sg:tags":[
        "renting",
        "truck",
        "leasing"
    ],
    "wof:name":"Budget Truck Rental",
    "wof:placetype":"venue"
},
  "geometry": {"coordinates":[-108.068218,38.746046],"type":"Point"}
}