{
  "type": "Feature",
  "properties": {
    "addr:full":"925 Ptarmigan Cir Loveland CO 80538",
    "addr:housenumber":"925",
    "addr:postcode":"80538",
    "addr:street":"Ptarmigan Cir",
    "iso:country":"US",
    "sg:address":"925 Ptarmigan Cir",
    "sg:city":"Loveland",
    "sg:classifiers":[
        {
            "category":"Building & Trades",
            "subcategory":"Construction",
            "type":"Services"
        }
    ],
    "sg:phone":"+1 970 669 7422",
    "sg:postcode":"80538",
    "sg:province":"CO",
    "sg:tags":[
        "hanging",
        "painter",
        "contractor"
    ],
    "wof:name":"Loveland Painting Company",
    "wof:placetype":"venue"
},
  "geometry": {"coordinates":[-105.066537,40.449525],"type":"Point"}
}