{
  "type": "Feature",
  "properties": {
    "iso:country":"US",
    "sg:address":"7550 W Yale Ave",
    "sg:city":"Denver",
    "sg:classifiers":[
        {
            "category":"Professional",
            "type":"Services"
        }
    ],
    "sg:phone":"+1 303 986 1201",
    "sg:postcode":"80227",
    "sg:province":"CO",
    "wof:name":"Judy Woods",
    "wof:placetype":"venue"
},
  "geometry": {"coordinates":[-105.08023900000001,39.66767],"type":"Point"}
}