{
  "type": "Feature",
  "properties": {
    "iso:country":"US",
    "sg:address":"1947 S Wadsworth Blvd",
    "sg:city":"Denver",
    "sg:classifiers":[
        {
            "category":"Restaurant",
            "type":"Food & Drink"
        }
    ],
    "sg:phone":"+1 303 984 1675",
    "sg:postcode":"80227",
    "sg:province":"CO",
    "sg:tags":[
        "machine",
        "repair",
        "espresso"
    ],
    "wof:name":"Rocky Mountian Espresso Svc",
    "wof:placetype":"venue"
},
  "geometry": {"coordinates":[-105.08153299999999,39.679488],"type":"Point"}
}