{
  "type": "Feature",
  "properties": {
    "iso:country":"US",
    "sg:address":"5 Benthaven Pl",
    "sg:city":"Boulder",
    "sg:classifiers":[
        {
            "category":"Manufacturing",
            "subcategory":"Printing",
            "type":"Manufacturing & Wholesale Goods"
        }
    ],
    "sg:phone":"+1 720 304 3490",
    "sg:postcode":"80305",
    "sg:province":"CO",
    "sg:tags":[
        "publishing"
    ],
    "wof:name":"Mace Associates",
    "wof:placetype":"venue"
},
  "geometry": {"coordinates":[-105.260508,39.974076],"type":"Point"}
}