{
  "type": "Feature",
  "properties": {
    "iso:country":"US",
    "sg:address":"1620 W 74th Way",
    "sg:city":"Denver",
    "sg:classifiers":[
        {
            "category":"Personal",
            "subcategory":"Beauty Salon",
            "type":"Services"
        }
    ],
    "sg:phone":"+1 303 427 0333",
    "sg:postcode":"80221",
    "sg:province":"CO",
    "wof:name":"Aracely Beauty Salon",
    "wof:placetype":"venue"
},
  "geometry": {"coordinates":[-105.006203,39.831893],"type":"Point"}
}