{
  "type": "Feature",
  "properties": {
    "iso:country":"US",
    "sg:address":"4610 Parmalee Gulch Rd",
    "sg:city":"Indian Hills",
    "sg:classifiers":[
        {
            "category":"Professional",
            "type":"Services"
        }
    ],
    "sg:phone":"+1 303 697 1018",
    "sg:postcode":"80454",
    "sg:province":"CO",
    "sg:tags":[
        "establishment"
    ],
    "wof:name":"St Anne's In The Hills",
    "wof:placetype":"venue"
},
  "geometry": {"coordinates":[-105.256488,39.63065],"type":"Point"}
}