{
  "type": "Feature",
  "properties": {
    "iso:country":"US",
    "sg:address":"7005 E 46th Avenue Dr",
    "sg:city":"Denver",
    "sg:classifiers":[
        {
            "category":"Food & Beverages",
            "subcategory":"Groceries & Convenience Stores",
            "type":"Retail Goods"
        }
    ],
    "sg:phone":"+1 303 393 0323",
    "sg:postcode":"80216",
    "sg:province":"CO",
    "wof:name":"7-Eleven",
    "wof:placetype":"venue"
},
  "geometry": {"coordinates":[-104.906132,39.780951],"type":"Point"}
}