{
  "type": "Feature",
  "properties": {
    "iso:country":"US",
    "sg:address":"1106 N 31st St",
    "sg:city":"Colorado Springs",
    "sg:classifiers":[
        {
            "category":"Building & Trades",
            "subcategory":"Construction",
            "type":"Services"
        }
    ],
    "sg:phone":"+1 719 447 0412",
    "sg:postcode":"80904",
    "sg:province":"CO",
    "sg:tags":[
        "house"
    ],
    "wof:name":"Smileys Home Repair Services",
    "wof:placetype":"venue"
},
  "geometry": {"coordinates":[-104.868734,38.868989],"type":"Point"}
}