{
  "type": "Feature",
  "properties": {
    "iso:country":"US",
    "sg:address":"3561 Hidden Valley Rd",
    "sg:city":"Sedalia",
    "sg:classifiers":[
        {
            "category":"Wholesale",
            "subcategory":"Drugs",
            "type":"Manufacturing & Wholesale Goods"
        }
    ],
    "sg:phone":"+1 303 663 1290",
    "sg:postcode":"80135",
    "sg:province":"CO",
    "sg:tags":[
        "sundries"
    ],
    "wof:name":"Mountain View Marketing Inc",
    "wof:placetype":"venue"
},
  "geometry": {"coordinates":[-105.031138,39.309194],"type":"Point"}
}