{
  "type": "Feature",
  "properties": {
    "iso:country":"US",
    "sg:address":"174 Edlun Rd",
    "sg:city":"Grand Junction",
    "sg:classifiers":[
        {
            "category":"Social Services",
            "subcategory":"Adult Care",
            "type":"Services"
        }
    ],
    "sg:phone":"+1 970 434 8240",
    "sg:postcode":"81503",
    "sg:province":"CO",
    "sg:tags":[
        "home",
        "residential"
    ],
    "wof:name":"Family Care Assisted Living",
    "wof:placetype":"venue"
},
  "geometry": {"coordinates":[-108.530253,39.030289],"type":"Point"}
}