{
  "type": "Feature",
  "properties": {
    "addr:full":"3600 N Garfield Ave Loveland CO 80538",
    "addr:housenumber":"3600",
    "addr:postcode":"80538",
    "addr:street":"N Garfield Ave",
    "iso:country":"US",
    "sg:address":"3600 N Garfield Ave",
    "sg:city":"Loveland",
    "sg:classifiers":[
        {
            "category":"Autos & Motor Vehicles",
            "subcategory":"Automobile Sales",
            "type":"Retail Goods"
        }
    ],
    "sg:phone":"+1 970 669 3280",
    "sg:postcode":"80538",
    "sg:province":"CO",
    "sg:tags":[
        "car",
        "dealer"
    ],
    "wof:name":"Falcon Motors",
    "wof:placetype":"venue"
},
  "geometry": {"coordinates":[-105.07749099999999,40.429184],"type":"Point"}
}