{
  "type": "Feature",
  "properties": {
    "addr:full":"402 S Tejon St Colorado Springs CO 80903",
    "addr:housenumber":"402",
    "addr:postcode":"80903",
    "addr:street":"S Tejon St",
    "iso:country":"US",
    "sg:address":"402 S Tejon St",
    "sg:city":"Colorado Springs",
    "sg:classifiers":[
        {
            "category":"Retail",
            "subcategory":"Auto Repair",
            "type":"Services"
        }
    ],
    "sg:phone":"+1 719 632 1552",
    "sg:postcode":"80903",
    "sg:province":"CO",
    "sg:tags":[
        "automotive",
        "general"
    ],
    "wof:name":"Al Demark Auto Service",
    "wof:placetype":"venue"
},
  "geometry": {"coordinates":[-104.82395699999999,38.826892],"type":"Point"}
}