{
  "type": "Feature",
  "properties": {
    "iso:country":"US",
    "sg:address":"7758 Devonshire Way",
    "sg:city":"Boulder",
    "sg:classifiers":[
        {
            "category":"Building & Trades",
            "subcategory":"Landscaping Services",
            "type":"Services"
        }
    ],
    "sg:phone":"+1 303 516 0900",
    "sg:postcode":"80301",
    "sg:province":"CO",
    "sg:tags":[
        "lawn",
        "landscape"
    ],
    "wof:name":"Landplans Inc",
    "wof:placetype":"venue"
},
  "geometry": {"coordinates":[-105.17181100000001,40.058756],"type":"Point"}
}