{
  "type": "Feature",
  "properties": {
    "addr:full":"2323 Co Rd 203 Durango CO 81301",
    "addr:housenumber":"2323;203",
    "addr:postcode":"co 81301",
    "addr:street":"Co Rd",
    "iso:country":"US",
    "sg:address":"2323 Co Rd 203",
    "sg:city":"Durango",
    "sg:classifiers":[
        {
            "category":"Building & Trades",
            "subcategory":"Construction",
            "type":"Services"
        }
    ],
    "sg:phone":"+1 970 259 9252",
    "sg:postcode":"81301",
    "sg:province":"CO",
    "sg:tags":[
        "concrete",
        "contractor"
    ],
    "wof:name":"Advanced Concrete Solutions",
    "wof:placetype":"venue"
},
  "geometry": {"coordinates":[-107.855018,37.334554],"type":"Point"}
}