{
  "type": "Feature",
  "properties": {
    "iso:country":"US",
    "sg:address":"2252 Clear Creek Dr",
    "sg:city":"Loveland",
    "sg:classifiers":[
        {
            "category":"Professional",
            "subcategory":"Computer Services",
            "type":"Services"
        }
    ],
    "sg:phone":"+1 970 635 9030",
    "sg:postcode":"80538",
    "sg:province":"CO",
    "sg:tags":[
        "home",
        "consulting",
        "page",
        "dev",
        "internet"
    ],
    "wof:name":"Bakonet Enterprises Inc",
    "wof:placetype":"venue"
},
  "geometry": {"coordinates":[-105.119793,40.415264],"type":"Point"}
}