{
  "type": "Feature",
  "properties": {
    "iso:country":"US",
    "sg:address":"1451 S Murray Blvd",
    "sg:city":"Colorado Springs",
    "sg:classifiers":[
        {
            "category":"Personal",
            "subcategory":"Beauty Salon",
            "type":"Services"
        }
    ],
    "sg:phone":"+1 719 622 1421",
    "sg:postcode":"80916",
    "sg:province":"CO",
    "wof:name":"Supercuts",
    "wof:placetype":"venue"
},
  "geometry": {"coordinates":[-104.748368,38.81292],"type":"Point"}
}