{
  "type": "Feature",
  "properties": {
    "iso:country":"US",
    "sg:address":"115 S Ingalls St",
    "sg:city":"Lakewood",
    "sg:classifiers":[
        {
            "category":"Professional",
            "type":"Services"
        }
    ],
    "sg:phone":"+1 303 445 9713",
    "sg:postcode":"80226",
    "sg:province":"CO",
    "wof:name":"Cpr Ancillary Svc",
    "wof:placetype":"venue"
},
  "geometry": {"coordinates":[-105.063935,39.713196],"type":"Point"}
}