{
  "type": "Feature",
  "properties": {
    "addr:full":"4316 Co Rd 240 Durango CO 81301",
    "addr:housenumber":"4316;240",
    "addr:postcode":"co 81301",
    "addr:street":"Co Rd",
    "iso:country":"US",
    "sg:address":"4316 Co Rd 240",
    "sg:city":"Durango",
    "sg:classifiers":[
        {
            "category":"Freight",
            "type":"Transportation"
        }
    ],
    "sg:phone":"+1 970 385 7857",
    "sg:postcode":"81301",
    "sg:province":"CO",
    "sg:tags":[
        "operator",
        "local",
        "trucking"
    ],
    "wof:name":"Road Runners Delivery",
    "wof:placetype":"venue"
},
  "geometry": {"coordinates":[-107.81168700000001,37.310242],"type":"Point"}
}