{
  "type": "Feature",
  "properties": {
    "addr:full":"2240 Dallas St Aurora CO 80010",
    "addr:housenumber":"2240",
    "addr:postcode":"80010",
    "addr:street":"Dallas St",
    "iso:country":"US",
    "sg:address":"2240 Dallas St",
    "sg:city":"Aurora",
    "sg:classifiers":[
        {
            "category":"Real Estate",
            "subcategory":"Real Estate Operator",
            "type":"Services"
        }
    ],
    "sg:phone":"+1 303 364 8180",
    "sg:postcode":"80010",
    "sg:province":"CO",
    "sg:tags":[
        "building",
        "apartment"
    ],
    "wof:name":"Lane Park Apartments",
    "wof:placetype":"venue"
},
  "geometry": {"coordinates":[-104.87631,39.750347],"type":"Point"}
}