{
  "type": "Feature",
  "properties": {
    "iso:country":"US",
    "sg:address":"3160 W Pimlico Dr",
    "sg:city":"Englewood",
    "sg:classifiers":[
        {
            "category":"Building & Trades",
            "subcategory":"Electrical",
            "type":"Services"
        }
    ],
    "sg:phone":"+1 303 795 1676",
    "sg:postcode":"80110",
    "sg:province":"CO",
    "sg:tags":[
        "electrical",
        "electric",
        "contractor"
    ],
    "wof:name":"A J Electric Systems Inc",
    "wof:placetype":"venue"
},
  "geometry": {"coordinates":[-105.02760499999999,39.632524],"type":"Point"}
}