{
  "type": "Feature",
  "properties": {
    "addr:full":"34018 Co Rd 39 Eaton CO 80615",
    "addr:housenumber":"39",
    "addr:postcode":"34018;80615",
    "addr:street":"Co Rd;Eaton",
    "iso:country":"US",
    "sg:address":"34018 Co Rd 39",
    "sg:city":"Eaton",
    "sg:classifiers":[
        {
            "category":"Farming",
            "subcategory":"Farm",
            "type":"Manufacturing & Wholesale Goods"
        }
    ],
    "sg:phone":"+1 970 352 5685",
    "sg:postcode":"80615",
    "sg:province":"CO",
    "wof:name":"Antholz Family LP",
    "wof:placetype":"venue"
},
  "geometry": {"coordinates":[-104.69678500000001,40.509427],"type":"Point"}
}