{
  "type": "Feature",
  "properties": {
    "iso:country":"US",
    "sg:address":"280 S Santa Fe Dr",
    "sg:city":"Denver",
    "sg:classifiers":[
        {
            "category":"Wholesale",
            "subcategory":"Hardware",
            "type":"Manufacturing & Wholesale Goods"
        }
    ],
    "sg:phone":"+1 303 744 3423",
    "sg:postcode":"80223",
    "sg:province":"CO",
    "sg:tags":[
        "plumbing",
        "fixture",
        "supply"
    ],
    "wof:name":"Dahl Denver Hydronics Speclist",
    "wof:placetype":"venue"
},
  "geometry": {"coordinates":[-104.997331,39.711896],"type":"Point"}
}