{
  "type": "Feature",
  "properties": {
    "iso:country":"US",
    "sg:address":"304 Cleveland Ave",
    "sg:city":"Loveland",
    "sg:classifiers":[
        {
            "category":"Restaurant",
            "type":"Food & Drink"
        }
    ],
    "sg:phone":"+1 970 663 4500",
    "sg:postcode":"80537",
    "sg:province":"CO",
    "wof:name":"Cactus Grill South",
    "wof:placetype":"venue"
},
  "geometry": {"coordinates":[-105.074465,40.395425],"type":"Point"}
}