{
  "type": "Feature",
  "properties": {
    "addr:full":"14723 Co Rd 32 Sterling CO 80751",
    "addr:housenumber":"14723;32",
    "addr:postcode":"80751",
    "addr:street":"Co Rd",
    "iso:country":"US",
    "sg:address":"14723 Co Rd 32",
    "sg:city":"Sterling",
    "sg:classifiers":[
        {
            "category":"Farming",
            "subcategory":"Livestock Farm",
            "type":"Manufacturing & Wholesale Goods"
        },
        {
            "category":"Farming",
            "subcategory":"Farm & Veterinary Services",
            "type":"Manufacturing & Wholesale Goods"
        }
    ],
    "sg:phone":"+1 970 522 1988",
    "sg:postcode":"80751",
    "sg:province":"CO",
    "sg:tags":[
        "breeder",
        "beef",
        "feedlot",
        "cattle"
    ],
    "wof:name":"Wheeler Cattle Co LLC",
    "wof:placetype":"venue"
},
  "geometry": {"coordinates":[-103.30207299999999,40.653129],"type":"Point"}
}