{
  "type": "Feature",
  "properties": {
    "addr:full":"555 S Kipling St Lakewood CO 80226",
    "addr:housenumber":"555",
    "addr:postcode":"80226",
    "addr:street":"S Kipling St",
    "iso:country":"US",
    "sg:address":"555 S Kipling St",
    "sg:city":"Lakewood",
    "sg:classifiers":[
        {
            "category":"Social Services",
            "subcategory":"Child Care",
            "type":"Services"
        }
    ],
    "sg:phone":"+1 303 236 9400",
    "sg:postcode":"80226",
    "sg:province":"CO",
    "wof:name":"Clever Kids Learning Ctr",
    "wof:placetype":"venue"
},
  "geometry": {"coordinates":[-105.109723,39.705239],"type":"Point"}
}