{
  "type": "Feature",
  "properties": {
    "iso:country":"US",
    "sg:address":"14645 Roller Coaster Rd",
    "sg:city":"Colorado Springs",
    "sg:classifiers":[
        {
            "category":"Real Estate",
            "subcategory":"Real Estate Agent",
            "type":"Services"
        }
    ],
    "sg:phone":"+1 719 488 1473",
    "sg:postcode":"80921",
    "sg:province":"CO",
    "sg:tags":[
        "investment"
    ],
    "wof:name":"Commercial Locators Plus",
    "wof:placetype":"venue"
},
  "geometry": {"coordinates":[-104.78479400000001,39.042781],"type":"Point"}
}