{
  "type": "Feature",
  "properties": {
    "addr:full":"7650 S Steele St Centennial CO 80122",
    "addr:housenumber":"7650",
    "addr:postcode":"80122",
    "addr:street":"S Steele St",
    "iso:country":"US",
    "sg:address":"7650 S Steele St",
    "sg:city":"Centennial",
    "sg:classifiers":[
        {
            "category":"Real Estate",
            "subcategory":"Real Estate Agent",
            "type":"Services"
        }
    ],
    "sg:phone":"+1 303 770 2110",
    "sg:postcode":"80122",
    "sg:province":"CO",
    "sg:tags":[
        "consultant"
    ],
    "wof:name":"T W Anderson & Co",
    "wof:placetype":"venue"
},
  "geometry": {"coordinates":[-104.950309,39.577398],"type":"Point"}
}