{
  "type": "Feature",
  "properties": {
    "iso:country":"US",
    "sg:address":"1111 S Taos Way",
    "sg:city":"Denver",
    "sg:classifiers":[
        {
            "category":"Professional",
            "subcategory":"Lawyer & Legal Services",
            "type":"Services"
        }
    ],
    "sg:phone":"+1 303 922 0300",
    "sg:postcode":"80223",
    "sg:province":"CO",
    "sg:tags":[
        "attorney"
    ],
    "wof:name":"F Lee Maes Law Office",
    "wof:placetype":"venue"
},
  "geometry": {"coordinates":[-105.011008,39.694912],"type":"Point"}
}