{
  "type": "Feature",
  "properties": {
    "iso:country":"US",
    "sg:address":"2743 S Shoshone St",
    "sg:city":"Englewood",
    "sg:classifiers":[
        {
            "category":"Retail",
            "subcategory":"Auto Repair",
            "type":"Services"
        }
    ],
    "sg:phone":"+1 303 789 1433",
    "sg:postcode":"80110",
    "sg:province":"CO",
    "sg:tags":[
        "automobile",
        "restoration",
        "classic"
    ],
    "wof:name":"Automotive Decadence LLC",
    "wof:placetype":"venue"
},
  "geometry": {"coordinates":[-105.009952,39.664928],"type":"Point"}
}