{
  "type": "Feature",
  "properties": {
    "addr:full":"401 E Chester St Lafayette CO 80026",
    "addr:housenumber":"401",
    "addr:postcode":"80026",
    "addr:street":"E Chester St",
    "iso:country":"US",
    "sg:address":"401 E Chester St",
    "sg:city":"Lafayette",
    "sg:classifiers":[
        {
            "category":"Retail",
            "subcategory":"Animal Services",
            "type":"Services"
        }
    ],
    "sg:phone":"+1 303 665 8255",
    "sg:postcode":"80026",
    "sg:province":"CO",
    "wof:name":"Ds9 Inc",
    "wof:placetype":"venue"
},
  "geometry": {"coordinates":[-105.08630100000001,39.995265],"type":"Point"}
}