{
  "type": "Feature",
  "properties": {
    "iso:country":"US",
    "sg:address":"605 US Hwy 287",
    "sg:city":"Berthoud",
    "sg:classifiers":[
        {
            "category":"Manufacturing",
            "subcategory":"Tools & Machinery",
            "type":"Manufacturing & Wholesale Goods"
        }
    ],
    "sg:phone":"+1 970 532 3711",
    "sg:postcode":"80513",
    "sg:province":"CO",
    "sg:tags":[
        "industrial",
        "truck"
    ],
    "wof:name":"High Country Proco",
    "wof:placetype":"venue"
},
  "geometry": {"coordinates":[-105.08246,40.305043],"type":"Point"}
}