{
  "type": "Feature",
  "properties": {
    "addr:full":"4995 Co Rd 509 Bayfield CO 81122",
    "addr:housenumber":"4995",
    "addr:postcode":"81122",
    "addr:street":"Co Rd 509",
    "iso:country":"US",
    "sg:address":"4995 Co Rd 509",
    "sg:city":"Bayfield",
    "sg:classifiers":[
        {
            "category":"Organizations",
            "subcategory":"Religious Organization",
            "type":"Services"
        }
    ],
    "sg:phone":"+1 970 884 0547",
    "sg:postcode":"81122",
    "sg:province":"CO",
    "sg:tags":[
        "church"
    ],
    "wof:name":"Bayfield Christian Church",
    "wof:placetype":"venue"
},
  "geometry": {"coordinates":[-107.61108299999999,37.226163],"type":"Point"}
}