{
  "type": "Feature",
  "properties": {
    "addr:full":"4216 Sweetgrass Dr Loveland CO 80537",
    "addr:housenumber":"4216",
    "addr:postcode":"80537",
    "addr:street":"Sweetgrass Dr",
    "iso:country":"US",
    "sg:address":"4216 Sweetgrass Dr",
    "sg:city":"Loveland",
    "sg:classifiers":[
        {
            "category":"Wholesale",
            "subcategory":"Electrical",
            "type":"Manufacturing & Wholesale Goods"
        }
    ],
    "sg:phone":"+1 970 493 0886",
    "sg:postcode":"80537",
    "sg:province":"CO",
    "sg:tags":[
        "telecommunication"
    ],
    "wof:name":"Front Range Communications Inc",
    "wof:placetype":"venue"
},
  "geometry": {"coordinates":[-105.138137,40.377143],"type":"Point"}
}