{
  "type": "Feature",
  "properties": {
    "iso:country":"US",
    "sg:address":"5050 Factory Shops Blvd Ste F50",
    "sg:city":"Castle Rock",
    "sg:classifiers":[
        {
            "category":"Shopping",
            "subcategory":"Department Store",
            "type":"Retail Goods"
        },
        {
            "category":"Restaurant",
            "type":"Food & Drink"
        }
    ],
    "sg:phone":"+1 303 688 1577",
    "sg:postcode":"80108",
    "sg:province":"CO",
    "sg:website":"www.subway.com",
    "wof:name":"Subway Sandwiches & Salads",
    "wof:placetype":"venue"
},
  "geometry": {"coordinates":[-104.87263,39.41372],"type":"Point"}
}