{
  "type": "Feature",
  "properties": {
    "iso:country":"US",
    "sg:address":"5445 Dtc Pkwy",
    "sg:city":"Greenwood Vlg",
    "sg:classifiers":[
        {
            "category":"Professional",
            "subcategory":"Accounting & Tax Preparation",
            "type":"Services"
        }
    ],
    "sg:phone":"+1 303 771 7851",
    "sg:postcode":"80111",
    "sg:province":"CO",
    "sg:tags":[
        "accountant"
    ],
    "wof:name":"David L Germeroth CPA",
    "wof:placetype":"venue"
},
  "geometry": {"coordinates":[-104.896162,39.617378],"type":"Point"}
}