{
  "type": "Feature",
  "properties": {
    "addr:full":"2649 E Mulberry St Fort Collins CO 80524",
    "addr:housenumber":"2649",
    "addr:postcode":"80524",
    "addr:street":"E Mulberry St",
    "iso:country":"US",
    "sg:address":"2649 E Mulberry St",
    "sg:city":"Fort Collins",
    "sg:classifiers":[
        {
            "category":"Autos & Motor Vehicles",
            "subcategory":"Auto Supplies",
            "type":"Retail Goods"
        }
    ],
    "sg:phone":"+1 970 416 1234",
    "sg:postcode":"80524",
    "sg:province":"CO",
    "sg:tags":[
        "four",
        "wheel",
        "drive",
        "accessory"
    ],
    "wof:name":"MTO Suspension & Fabrication",
    "wof:placetype":"venue"
},
  "geometry": {"coordinates":[-105.031318,40.58091],"type":"Point"}
}