{
  "type": "Feature",
  "properties": {
    "iso:country":"US",
    "sg:address":"1441 18th Street Suite 100",
    "sg:city":"Denver",
    "sg:classifiers":[
        {
            "category":"Professional",
            "subcategory":"Lawyer & Legal Services",
            "type":"Services"
        }
    ],
    "sg:phone":"+1 303 296 8100",
    "sg:postcode":"80202",
    "sg:province":"CO",
    "wof:name":"Hill & Robbins",
    "wof:placetype":"venue"
},
  "geometry": {"coordinates":[-104.996221,39.752022],"type":"Point"}
}