{
  "type": "Feature",
  "properties": {
    "addr:full":"13701 W Jewell Ave # 205 Lakewood CO 80228",
    "addr:housenumber":"13701",
    "addr:postcode":"80228",
    "addr:street":"W Jewell Ave # 205",
    "iso:country":"US",
    "sg:address":"13701 W Jewell Ave # 205",
    "sg:city":"Lakewood",
    "sg:classifiers":[
        {
            "category":"Insurance",
            "subcategory":"Hazard Insurance",
            "type":"Services"
        }
    ],
    "sg:phone":"+1 303 984 8500",
    "sg:postcode":"80228",
    "sg:province":"CO",
    "sg:tags":[
        "commercial",
        "business"
    ],
    "wof:name":"Metsker Insurance Associates",
    "wof:placetype":"venue"
},
  "geometry": {"coordinates":[-105.154938,39.681889],"type":"Point"}
}