{
  "type": "Feature",
  "properties": {
    "iso:country":"US",
    "sg:address":"7233 S Yukon St",
    "sg:city":"Littleton",
    "sg:classifiers":[
        {
            "category":"Building & Trades",
            "subcategory":"Construction",
            "type":"Services"
        }
    ],
    "sg:phone":"+1 303 979 8990",
    "sg:postcode":"80128",
    "sg:province":"CO",
    "sg:tags":[
        "roofing"
    ],
    "wof:name":"Tip-Top Roofing",
    "wof:placetype":"venue"
},
  "geometry": {"coordinates":[-105.083405,39.586962],"type":"Point"}
}