{
  "type": "Feature",
  "properties": {
    "iso:country":"US",
    "sg:address":"4755 Paris St",
    "sg:city":"Denver",
    "sg:classifiers":[
        {
            "category":"Insurance",
            "subcategory":"Insurance Agent",
            "type":"Services"
        },
        {
            "category":"Insurance",
            "subcategory":"Hazard Insurance",
            "type":"Services"
        },
        {
            "category":"Insurance",
            "subcategory":"Title Insurance",
            "type":"Services"
        }
    ],
    "sg:phone":"+1 303 534 2930",
    "sg:postcode":"80239",
    "sg:province":"CO",
    "sg:tags":[
        "auto",
        "homeowner"
    ],
    "sg:website":"http://apps.amfam.com/agentlocator/AVALDEZ?sourceid=yp3",
    "wof:name":"American Family Insurance- Art Valdez Agency",
    "wof:placetype":"venue"
},
  "geometry": {"coordinates":[-104.848946,39.782399],"type":"Point"}
}