{
  "type": "Feature",
  "properties": {
    "addr:full":"4012 Cleveland Ave Wellington CO 80549",
    "addr:housenumber":"4012",
    "addr:postcode":"80549",
    "addr:street":"Cleveland Ave",
    "iso:country":"US",
    "sg:address":"4012 Cleveland Ave",
    "sg:city":"Wellington",
    "sg:classifiers":[
        {
            "category":"Building & Trades",
            "subcategory":"Landscaping Services",
            "type":"Services"
        }
    ],
    "sg:phone":"+1 970 568 7561",
    "sg:postcode":"80549",
    "sg:province":"CO",
    "sg:tags":[
        "sod",
        "sodding"
    ],
    "wof:name":"Bats Erosion Systems LLC",
    "wof:placetype":"venue"
},
  "geometry": {"coordinates":[-105.001992,40.703948],"type":"Point"}
}