{
  "type": "Feature",
  "properties": {
    "iso:country":"US",
    "sg:address":"9290 E 107th Ave",
    "sg:city":"Henderson",
    "sg:classifiers":[
        {
            "category":"Education",
            "subcategory":"School",
            "type":"Public Place"
        }
    ],
    "sg:phone":"+1 303 468 0160",
    "sg:postcode":"80640",
    "sg:province":"CO",
    "sg:website":"www.brightoncharter.org",
    "wof:name":"Belle Creek Charter School",
    "wof:placetype":"venue"
},
  "geometry": {"coordinates":[-104.880261,39.892186],"type":"Point"}
}