{
  "type": "Feature",
  "properties": {
    "addr:full":"32431 Co Rd 5 Fowler CO 81039",
    "addr:housenumber":"32431",
    "addr:postcode":"81039",
    "addr:street":"Co Rd 5",
    "iso:country":"US",
    "sg:address":"32431 Co Rd 5",
    "sg:city":"Fowler",
    "sg:classifiers":[
        {
            "category":"Farming",
            "subcategory":"Livestock Farm",
            "type":"Manufacturing & Wholesale Goods"
        }
    ],
    "sg:phone":"+1 719 263 5520",
    "sg:postcode":"81039",
    "sg:province":"CO",
    "sg:tags":[
        "beef",
        "corn",
        "crop",
        "field",
        "cattle",
        "feedlot"
    ],
    "wof:name":"Baker Brothers",
    "wof:placetype":"venue"
},
  "geometry": {"coordinates":[-103.986088,38.102483],"type":"Point"}
}