{
  "type": "Feature",
  "properties": {
    "iso:country":"US",
    "sg:address":"2065 E 116th Ave",
    "sg:city":"Denver",
    "sg:classifiers":[
        {
            "category":"Building & Trades",
            "subcategory":"Construction",
            "type":"Services"
        }
    ],
    "sg:phone":"+1 303 457 4048",
    "sg:postcode":"80233",
    "sg:province":"CO",
    "sg:tags":[
        "hanging"
    ],
    "wof:name":"AAA Dry Wall Repair",
    "wof:placetype":"venue"
},
  "geometry": {"coordinates":[-104.962765,39.90641],"type":"Point"}
}