{
  "type": "Feature",
  "properties": {
    "addr:full":"711 Harrison Ave Leadville CO 80461",
    "addr:housenumber":"711",
    "addr:postcode":"80461",
    "addr:street":"Harrison Ave",
    "iso:country":"US",
    "sg:address":"711 Harrison Ave",
    "sg:city":"Leadville",
    "sg:classifiers":[
        {
            "category":"Shopping",
            "subcategory":"Stationery & Office Supplies",
            "type":"Retail Goods"
        }
    ],
    "sg:phone":"+1 719 486 3244",
    "sg:postcode":"80461",
    "sg:province":"CO",
    "sg:tags":[
        "form"
    ],
    "wof:name":"Telegraph Office The",
    "wof:placetype":"venue"
},
  "geometry": {"coordinates":[-106.292547,39.250308],"type":"Point"}
}