{
  "type": "Feature",
  "properties": {
    "addr:full":"608 N Co Rd 31 Berthoud CO 80513",
    "addr:housenumber":"608;31",
    "addr:postcode":"80513",
    "addr:street":"N Co Rd",
    "iso:country":"US",
    "sg:address":"608 N Co Rd 31",
    "sg:city":"Berthoud",
    "sg:classifiers":[
        {
            "category":"Banks & Credit Unions",
            "subcategory":"Investment Brokerage",
            "type":"Services"
        }
    ],
    "sg:phone":"+1 970 532 5339",
    "sg:postcode":"80513",
    "sg:province":"CO",
    "wof:name":"County Line Land Investments",
    "wof:placetype":"venue"
},
  "geometry": {"coordinates":[-105.22032799999999,40.306348],"type":"Point"}
}