{
  "type": "Feature",
  "properties": {
    "iso:country":"US",
    "sg:address":"146 Madison St Ste 101",
    "sg:city":"Denver",
    "sg:classifiers":[
        {
            "category":"Building & Trades",
            "subcategory":"Construction",
            "type":"Services"
        }
    ],
    "sg:phone":"+1 303 321 0550",
    "sg:postcode":"80206",
    "sg:province":"CO",
    "sg:tags":[
        "air",
        "heating",
        "conditioning/hvac"
    ],
    "sg:website":"www.teeginc.com/home.html",
    "wof:name":"Tucker Environmental Engineering",
    "wof:placetype":"venue"
},
  "geometry": {"coordinates":[-104.945825,39.718678],"type":"Point"}
}