{
  "type": "Feature",
  "properties": {
    "iso:country":"US",
    "sg:address":"30070 State Hwy 24",
    "sg:city":"Buena Vista",
    "sg:classifiers":[
        {
            "category":"Building & Trades",
            "subcategory":"Equipment Rental",
            "type":"Services"
        }
    ],
    "sg:phone":"+1 719 395 6041",
    "sg:postcode":"81211",
    "sg:province":"CO",
    "sg:tags":[
        "yard"
    ],
    "wof:name":"Buena Vista Tool & Equipment",
    "wof:placetype":"venue"
},
  "geometry": {"coordinates":[-106.141891,38.856472],"type":"Point"}
}