{
  "type": "Feature",
  "properties": {
    "iso:country":"US",
    "sg:address":"401 Colorado Ave",
    "sg:city":"La Junta",
    "sg:classifiers":[
        {
            "category":"Shopping",
            "subcategory":"Tobacco",
            "type":"Retail Goods"
        }
    ],
    "sg:phone":"+1 719 384 8533",
    "sg:postcode":"81050",
    "sg:province":"CO",
    "sg:tags":[
        "cigarette",
        "cigar",
        "dealer"
    ],
    "wof:name":"Smoker Friendly",
    "wof:placetype":"venue"
},
  "geometry": {"coordinates":[-103.543088,37.984946],"type":"Point"}
}