{
  "type": "Feature",
  "properties": {
    "iso:country":"US",
    "sg:address":"2616 W Colorado Ave",
    "sg:city":"Colorado Springs",
    "sg:classifiers":[
        {
            "category":"Shopping",
            "subcategory":"Gifts & Souvenirs",
            "type":"Retail Goods"
        }
    ],
    "sg:phone":"+1 719 471 7420",
    "sg:postcode":"80904",
    "sg:province":"CO",
    "sg:tags":[
        "shop"
    ],
    "wof:name":"Celtic Mercantile",
    "wof:placetype":"venue"
},
  "geometry": {"coordinates":[-104.865402,38.848907],"type":"Point"}
}