{
  "type": "Feature",
  "properties": {
    "addr:full":"999 Co Rd 207 Durango CO 81301",
    "addr:housenumber":"999;207",
    "addr:postcode":"co 81301",
    "addr:street":"Co Rd",
    "iso:country":"US",
    "sg:address":"999 Co Rd 207",
    "sg:city":"Durango",
    "sg:classifiers":[
        {
            "category":"Travel",
            "subcategory":"Hotels & Motels",
            "type":"Entertainment"
        }
    ],
    "sg:phone":"+1 970 259 1226",
    "sg:postcode":"81301",
    "sg:province":"CO",
    "sg:tags":[
        "breakfast",
        "accommodation",
        "bed"
    ],
    "sg:website":"www.lightnercreekinn.com",
    "wof:name":"Lightner Creek Inn B & B",
    "wof:placetype":"venue"
},
  "geometry": {"coordinates":[-107.938253,37.291273],"type":"Point"}
}