{
  "type": "Feature",
  "properties": {
    "iso:country":"US",
    "sg:address":"6545 E Ithaca Pl",
    "sg:city":"Denver",
    "sg:classifiers":[
        {
            "category":"Professional",
            "subcategory":"Art Services",
            "type":"Services"
        }
    ],
    "sg:phone":"+1 303 759 8852",
    "sg:postcode":"80237",
    "sg:province":"CO",
    "sg:tags":[
        "formal",
        "provides",
        "writing"
    ],
    "wof:name":"Imagine Scribe Service Corp",
    "wof:placetype":"venue"
},
  "geometry": {"coordinates":[-104.909476,39.652037],"type":"Point"}
}