{
  "type": "Feature",
  "properties": {
    "addr:full":"7257 S Revere Pkwy Englewood CO 80112",
    "addr:housenumber":"7257",
    "addr:postcode":"80112",
    "addr:street":"S Revere Pkwy",
    "iso:country":"US",
    "sg:address":"7257 S Revere Pkwy",
    "sg:city":"Englewood",
    "sg:classifiers":[
        {
            "category":"Local Transit",
            "type":"Transportation"
        }
    ],
    "sg:phone":"+1 303 790 0175",
    "sg:postcode":"80112",
    "sg:province":"CO",
    "sg:tags":[
        "passenger"
    ],
    "wof:name":"Admire Limousine Svcs",
    "wof:placetype":"venue"
},
  "geometry": {"coordinates":[-104.841583,39.584941],"type":"Point"}
}