{
  "type": "Feature",
  "properties": {
    "addr:full":"8360 Moore Ct Arvada CO 80005",
    "addr:housenumber":"8360",
    "addr:postcode":"80005",
    "addr:street":"Moore Ct",
    "iso:country":"US",
    "sg:address":"8360 Moore Ct",
    "sg:city":"Arvada",
    "sg:classifiers":[
        {
            "category":"Building & Trades",
            "subcategory":"Construction",
            "type":"Services"
        }
    ],
    "sg:phone":"+1 303 940 4716",
    "sg:postcode":"80005",
    "sg:province":"CO",
    "sg:tags":[
        "remodeling",
        "contractor"
    ],
    "wof:name":"Aloha State Builders",
    "wof:placetype":"venue"
},
  "geometry": {"coordinates":[-105.11725800000001,39.84989],"type":"Point"}
}