{
  "type": "Feature",
  "properties": {
    "iso:country":"US",
    "sg:address":"121 S Main St",
    "sg:city":"Yuma",
    "sg:classifiers":[
        {
            "category":"Shopping",
            "subcategory":"Gifts & Souvenirs",
            "type":"Retail Goods"
        }
    ],
    "sg:phone":"+1 970 848 0415",
    "sg:postcode":"80759",
    "sg:province":"CO",
    "sg:tags":[
        "shop"
    ],
    "wof:name":"Yuma Gift & Variety",
    "wof:placetype":"venue"
},
  "geometry": {"coordinates":[-102.72369999999999,40.125095],"type":"Point"}
}