{
  "type": "Feature",
  "properties": {
    "iso:country":"US",
    "sg:address":"3242 S Bahama St",
    "sg:city":"Aurora",
    "sg:classifiers":[
        {
            "category":"Shopping",
            "subcategory":"Discount & Variety Stores",
            "type":"Retail Goods"
        }
    ],
    "sg:phone":"+1 303 699 7504",
    "sg:postcode":"80013",
    "sg:province":"CO",
    "wof:name":"Sanrio Surprises",
    "wof:placetype":"venue"
},
  "geometry": {"coordinates":[-104.76833499999999,39.657459],"type":"Point"}
}