{
  "type": "Feature",
  "properties": {
    "iso:country":"US",
    "sg:address":"6 Kreg Ln",
    "sg:city":"Manitou Springs",
    "sg:classifiers":[
        {
            "category":"Restaurant",
            "type":"Food & Drink"
        }
    ],
    "sg:phone":"+1 719 685 4648",
    "sg:postcode":"80829",
    "sg:province":"CO",
    "sg:tags":[
        "eating"
    ],
    "wof:name":"Pizza Warehouse Llc",
    "wof:placetype":"venue"
},
  "geometry": {"coordinates":[-104.896728,38.843202],"type":"Point"}
}