{
  "type": "Feature",
  "properties": {
    "addr:full":"4479 Fortune Cir S Colorado Springs CO 80917",
    "addr:housenumber":"4479",
    "addr:postcode":"springs;80917",
    "addr:street":"Fortune Cir S",
    "iso:country":"US",
    "sg:address":"4479 Fortune Cir S",
    "sg:city":"Colorado Springs",
    "sg:classifiers":[
        {
            "category":"Building & Trades",
            "subcategory":"Landscaping Services",
            "type":"Services"
        }
    ],
    "sg:phone":"+1 719 380 8894",
    "sg:postcode":"80917",
    "sg:province":"CO",
    "sg:tags":[
        "landscape"
    ],
    "wof:name":"Superior Systems Inc",
    "wof:placetype":"venue"
},
  "geometry": {"coordinates":[-104.744709,38.887196],"type":"Point"}
}