{
  "type": "Feature",
  "properties": {
    "addr:full":"3809 E Mulberry St Fort Collins CO 80524",
    "addr:housenumber":"3809",
    "addr:postcode":"80524",
    "addr:street":"E Mulberry St",
    "iso:country":"US",
    "sg:address":"3809 E Mulberry St",
    "sg:city":"Fort Collins",
    "sg:classifiers":[
        {
            "category":"Banks & Credit Unions",
            "subcategory":"Bank",
            "type":"Services"
        }
    ],
    "sg:phone":"+1 970 407 1819",
    "sg:postcode":"80524",
    "sg:province":"CO",
    "sg:tags":[
        "cashing",
        "check"
    ],
    "wof:name":"Cash Resources",
    "wof:placetype":"venue"
},
  "geometry": {"coordinates":[-105.012452,40.581058],"type":"Point"}
}