{
  "type": "Feature",
  "properties": {
    "addr:full":"1710 W Uintah St Colorado Springs CO 80904",
    "addr:housenumber":"1710",
    "addr:postcode":"80904",
    "addr:street":"W Uintah St",
    "iso:country":"US",
    "sg:address":"1710 W Uintah St",
    "sg:city":"Colorado Springs",
    "sg:classifiers":[
        {
            "category":"Restaurant",
            "type":"Food & Drink"
        }
    ],
    "sg:menulink":"http://www.allmenus.com/co/colorado-springs/81055-papa-johns-pizza/menu/",
    "sg:phone":"+1 719 632 7272",
    "sg:postcode":"80904",
    "sg:province":"CO",
    "sg:tags":[
        "american",
        "pizza"
    ],
    "wof:name":"Papa John's Pizza",
    "wof:placetype":"venue"
},
  "geometry": {"coordinates":[-104.84677499999999,38.848315],"type":"Point"}
}