{
  "type": "Feature",
  "properties": {
    "iso:country":"US",
    "sg:address":"301 Main St",
    "sg:city":"Frisco",
    "sg:classifiers":[
        {
            "category":"Food & Beverages",
            "subcategory":"Groceries & Convenience Stores",
            "type":"Retail Goods"
        }
    ],
    "sg:phone":"+1 970 668 5535",
    "sg:postcode":"80443",
    "sg:province":"CO",
    "sg:tags":[
        "grocer"
    ],
    "wof:name":"Alpine Natural Foods",
    "wof:placetype":"venue"
},
  "geometry": {"coordinates":[-106.11029000000001,39.575275],"type":"Point"}
}