{
  "type": "Feature",
  "properties": {
    "iso:country":"US",
    "sg:address":"11979 E 1st Pl",
    "sg:city":"Aurora",
    "sg:classifiers":[
        {
            "category":"Banks & Credit Unions",
            "subcategory":"Bank",
            "type":"Services"
        }
    ],
    "sg:phone":"+1 720 859 6990",
    "sg:postcode":"80011",
    "sg:province":"CO",
    "sg:tags":[
        "loan",
        "mortgage"
    ],
    "wof:name":"Momentum Financial Services, Inc",
    "wof:placetype":"venue"
},
  "geometry": {"coordinates":[-104.84891500000001,39.71881],"type":"Point"}
}