{
  "type": "Feature",
  "properties": {
    "addr:full":"258 Broadway Denver CO 80203",
    "addr:housenumber":"258",
    "addr:postcode":"80203",
    "addr:street":"Broadway",
    "iso:country":"US",
    "sg:address":"258 Broadway",
    "sg:city":"Denver",
    "sg:classifiers":[
        {
            "category":"Shopping",
            "subcategory":"Bicycles & Sporting Goods",
            "type":"Retail Goods"
        }
    ],
    "sg:phone":"+1 303 777 5657",
    "sg:postcode":"80203",
    "sg:province":"CO",
    "sg:tags":[
        "gun",
        "gunsmith"
    ],
    "wof:name":"French's Gun Shop",
    "wof:placetype":"venue"
},
  "geometry": {"coordinates":[-104.987399,39.720008],"type":"Point"}
}