{
  "type": "Feature",
  "properties": {
    "iso:country":"US",
    "sg:address":"4990 Nome St",
    "sg:city":"Denver",
    "sg:classifiers":[
        {
            "category":"Manufacturing",
            "subcategory":"Tools & Machinery",
            "type":"Manufacturing & Wholesale Goods"
        }
    ],
    "sg:phone":"+1 303 373 9333",
    "sg:postcode":"80239",
    "sg:province":"CO",
    "sg:tags":[
        "equipment",
        "peripheral",
        "computer",
        "mfg"
    ],
    "wof:name":"Avus Systems Peripherals",
    "wof:placetype":"venue"
},
  "geometry": {"coordinates":[-104.85259600000001,39.788384],"type":"Point"}
}