{
  "type": "Feature",
  "properties": {
    "addr:full":"216 Clayton St Brush CO 80723",
    "addr:housenumber":"216",
    "addr:postcode":"80723",
    "addr:street":"Clayton St",
    "iso:country":"US",
    "sg:address":"216 Clayton St",
    "sg:city":"Brush",
    "sg:classifiers":[
        {
            "category":"Insurance",
            "subcategory":"Insurance Agent",
            "type":"Services"
        }
    ],
    "sg:phone":"+1 970 842 2831",
    "sg:postcode":"80723",
    "sg:province":"CO",
    "sg:website":"www.ingmirephillips.com",
    "wof:name":"Ingmire Phillips Insurance Inc",
    "wof:placetype":"venue"
},
  "geometry": {"coordinates":[-103.623223,40.256183],"type":"Point"}
}