{
  "type": "Feature",
  "properties": {
    "iso:country":"US",
    "sg:address":"5203 Federal Blvd",
    "sg:city":"Denver",
    "sg:classifiers":[
        {
            "category":"Wholesale",
            "subcategory":"Scrap",
            "type":"Manufacturing & Wholesale Goods"
        },
        {
            "category":"Shopping",
            "type":"Retail Goods"
        }
    ],
    "sg:phone":"+1 303 477 0909",
    "sg:postcode":"80221",
    "sg:province":"CO",
    "sg:tags":[
        "box",
        "merchandise"
    ],
    "wof:name":"Johnson Box And Barrel Co",
    "wof:placetype":"venue"
},
  "geometry": {"coordinates":[-105.025192,39.791431],"type":"Point"}
}