{
  "type": "Feature",
  "properties": {
    "iso:country":"US",
    "sg:address":"8221 S Holly St",
    "sg:city":"Centennial",
    "sg:classifiers":[
        {
            "category":"Personal",
            "subcategory":"Beauty Salon",
            "type":"Services"
        }
    ],
    "sg:phone":"+1 303 779 9920",
    "sg:postcode":"80122",
    "sg:province":"CO",
    "sg:tags":[
        "manicuring"
    ],
    "wof:name":"Pat Dyszel Manicures & Pedicur",
    "wof:placetype":"venue"
},
  "geometry": {"coordinates":[-104.922866,39.566572],"type":"Point"}
}