{
  "type": "Feature",
  "properties": {
    "iso:country":"US",
    "sg:address":"2906 W Prospect Rd",
    "sg:city":"Fort Collins",
    "sg:classifiers":[
        {
            "category":"Freight",
            "type":"Transportation"
        }
    ],
    "sg:phone":"+1 970 484 8870",
    "sg:postcode":"80526",
    "sg:province":"CO",
    "sg:tags":[
        "trucking"
    ],
    "wof:name":"Jim Trucking",
    "wof:placetype":"venue"
},
  "geometry": {"coordinates":[-105.131327,40.567818],"type":"Point"}
}