{
  "type": "Feature",
  "properties": {
    "iso:country":"US",
    "sg:address":"2689 S Broadway",
    "sg:city":"Denver",
    "sg:classifiers":[
        {
            "category":"Autos & Motor Vehicles",
            "subcategory":"Automobile Sales",
            "type":"Retail Goods"
        }
    ],
    "sg:phone":"+1 303 698 9722",
    "sg:postcode":"80210",
    "sg:province":"CO",
    "sg:tags":[
        "used"
    ],
    "wof:name":"Joes Cars LLC",
    "wof:placetype":"venue"
},
  "geometry": {"coordinates":[-104.987657,39.6693],"type":"Point"}
}