{
  "type": "Feature",
  "properties": {
    "addr:full":"1500 S Pearl St Denver CO 80210",
    "addr:housenumber":"1500",
    "addr:postcode":"80210",
    "addr:street":"S Pearl St",
    "iso:country":"US",
    "sg:address":"1500 S Pearl St",
    "sg:city":"Denver",
    "sg:classifiers":[
        {
            "category":"Building & Trades",
            "subcategory":"Landscaping Services",
            "type":"Services"
        }
    ],
    "sg:phone":"+1 303 470 2855",
    "sg:postcode":"80210",
    "sg:province":"CO",
    "sg:tags":[
        "designer",
        "landscape"
    ],
    "wof:name":"Sage Design Group LLC",
    "wof:placetype":"venue"
},
  "geometry": {"coordinates":[-104.980442,39.68758],"type":"Point"}
}