{
  "type": "Feature",
  "properties": {
    "iso:country":"US",
    "sg:address":"123 Emma Rd",
    "sg:city":"Basalt",
    "sg:classifiers":[
        {
            "category":"Restaurant",
            "type":"Food & Drink"
        }
    ],
    "sg:phone":"+1 970 927 3855",
    "sg:postcode":"81621",
    "sg:province":"CO",
    "wof:name":"Ho Palace Chinese Restaurant",
    "wof:placetype":"venue"
},
  "geometry": {"coordinates":[-107.03429,39.365323],"type":"Point"}
}