{
  "type": "Feature",
  "properties": {
    "addr:full":"315 Youngs Gulch Rd Bellvue CO 80512",
    "addr:housenumber":"315",
    "addr:postcode":"80512",
    "addr:street":"Youngs Gulch Rd",
    "iso:country":"US",
    "sg:address":"315 Youngs Gulch Rd",
    "sg:city":"Bellvue",
    "sg:classifiers":[
        {
            "category":"Building & Trades",
            "subcategory":"Construction",
            "type":"Services"
        }
    ],
    "sg:phone":"+1 970 493 7472",
    "sg:postcode":"80512",
    "sg:province":"CO",
    "sg:tags":[
        "contractor"
    ],
    "wof:name":"Wolf Roofing",
    "wof:placetype":"venue"
},
  "geometry": {"coordinates":[-105.336927,40.652436],"type":"Point"}
}