{
  "type": "Feature",
  "properties": {
    "iso:country":"US",
    "sg:address":"28357 US Hwy 50",
    "sg:city":"Gunnison",
    "sg:classifiers":[
        {
            "category":"Travel",
            "subcategory":"Campground",
            "type":"Entertainment"
        }
    ],
    "sg:phone":"+1 970 641 0477",
    "sg:postcode":"81230",
    "sg:province":"CO",
    "wof:name":"Gunnison Lakeside Resort Inc",
    "wof:placetype":"venue"
},
  "geometry": {"coordinates":[-107.111189,38.483375],"type":"Point"}
}