{
  "type": "Feature",
  "properties": {
    "addr:full":"905 Weiss Dr Steamboat Spgs CO 80487",
    "addr:housenumber":"905",
    "addr:postcode":"80487",
    "addr:street":"Weiss Dr;Spgs",
    "iso:country":"US",
    "sg:address":"905 Weiss Dr",
    "sg:city":"Steamboat Spgs",
    "sg:classifiers":[
        {
            "category":"Food & Beverages",
            "subcategory":"Groceries & Convenience Stores",
            "type":"Retail Goods"
        }
    ],
    "sg:phone":"+1 970 879 8477",
    "sg:postcode":"80487",
    "sg:province":"CO",
    "wof:name":"Southside Station",
    "wof:placetype":"venue"
},
  "geometry": {"coordinates":[-106.81638,40.448492],"type":"Point"}
}