{
  "type": "Feature",
  "properties": {
    "addr:full":"38 Colard Ln Lyons CO 80540",
    "addr:housenumber":"38",
    "addr:postcode":"80540",
    "addr:street":"Colard Ln",
    "iso:country":"US",
    "sg:address":"38 Colard Ln",
    "sg:city":"Lyons",
    "sg:classifiers":[
        {
            "category":"Professional",
            "type":"Services"
        }
    ],
    "sg:phone":"+1 303 823 6893",
    "sg:postcode":"80540",
    "sg:province":"CO",
    "wof:name":"Aroma Erotica",
    "wof:placetype":"venue"
},
  "geometry": {"coordinates":[-105.291444,40.267006],"type":"Point"}
}