{
  "type": "Feature",
  "properties": {
    "iso:country":"US",
    "sg:address":"3200 E 16th Ave",
    "sg:city":"Denver",
    "sg:classifiers":[
        {
            "category":"Building & Trades",
            "subcategory":"Locksmith",
            "type":"Services"
        }
    ],
    "sg:phone":"+1 303 876 0090",
    "sg:postcode":"80206",
    "sg:province":"CO",
    "sg:tags":[
        "key"
    ],
    "wof:name":"A Locksmith A 24 7",
    "wof:placetype":"venue"
},
  "geometry": {"coordinates":[-104.95002,39.741853],"type":"Point"}
}