{
  "type": "Feature",
  "properties": {
    "iso:country":"US",
    "sg:address":"484 N Murray Blvd",
    "sg:city":"Colorado Springs",
    "sg:classifiers":[
        {
            "category":"Shopping",
            "subcategory":"Used Merchandise",
            "type":"Retail Goods"
        }
    ],
    "sg:phone":"+1 719 574 9855",
    "sg:postcode":"80916",
    "sg:province":"CO",
    "wof:name":"EZ Pawn 325",
    "wof:placetype":"venue"
},
  "geometry": {"coordinates":[-104.748127,38.837941],"type":"Point"}
}