{
  "type": "Feature",
  "properties": {
    "iso:country":"US",
    "sg:address":"729 Emerson St",
    "sg:city":"Denver",
    "sg:classifiers":[
        {
            "category":"Manufacturing",
            "subcategory":"Jewelry",
            "type":"Manufacturing & Wholesale Goods"
        }
    ],
    "sg:phone":"+1 303 831 6228",
    "sg:postcode":"80218",
    "sg:province":"CO",
    "sg:tags":[
        "precious",
        "metal",
        "mfg"
    ],
    "wof:name":"Emily Greer Designs",
    "wof:placetype":"venue"
},
  "geometry": {"coordinates":[-104.976485,39.728556],"type":"Point"}
}