{
  "type": "Feature",
  "properties": {
    "addr:full":"9232 Virginia Pl Denver CO 80226",
    "addr:housenumber":"9232",
    "addr:postcode":"80226",
    "addr:street":"Virginia Pl",
    "iso:country":"US",
    "sg:address":"9232 Virginia Pl",
    "sg:city":"Denver",
    "sg:classifiers":[
        {
            "category":"Building & Trades",
            "subcategory":"Landscaping Services",
            "type":"Services"
        }
    ],
    "sg:phone":"+1 303 763 7653",
    "sg:postcode":"80226",
    "sg:province":"CO",
    "sg:tags":[
        "landscape"
    ],
    "wof:name":"Steven Watts",
    "wof:placetype":"venue"
},
  "geometry": {"coordinates":[-105.100784,39.708536],"type":"Point"}
}