{
  "type": "Feature",
  "properties": {
    "addr:full":"4110 S Irving St Denver CO 80236",
    "addr:housenumber":"4110",
    "addr:postcode":"80236",
    "addr:street":"S Irving St",
    "iso:country":"US",
    "sg:address":"4110 S Irving St",
    "sg:city":"Denver",
    "sg:classifiers":[
        {
            "category":"Building & Trades",
            "subcategory":"Construction",
            "type":"Services"
        }
    ],
    "sg:phone":"+1 720 495 5978",
    "sg:postcode":"80236",
    "sg:province":"CO",
    "sg:tags":[
        "house"
    ],
    "wof:name":"New Creation Remodeling",
    "wof:placetype":"venue"
},
  "geometry": {"coordinates":[-105.029855,39.640664],"type":"Point"}
}