{
  "type": "Feature",
  "properties": {
    "addr:full":"18998 Co Rd 11 Kirk CO 80824",
    "addr:housenumber":"18998;11",
    "addr:postcode":"kirk;80824",
    "addr:street":"Co Rd",
    "iso:country":"US",
    "sg:address":"18998 Co Rd 11",
    "sg:city":"Kirk",
    "sg:classifiers":[
        {
            "category":"Farming",
            "subcategory":"Farm & Veterinary Services",
            "type":"Manufacturing & Wholesale Goods"
        }
    ],
    "sg:phone":"+1 970 354 7460",
    "sg:postcode":"80824",
    "sg:province":"CO",
    "sg:tags":[
        "livestock"
    ],
    "wof:name":"Mann Slaughterhouse",
    "wof:placetype":"venue"
},
  "geometry": {"coordinates":[-102.463212,39.730152],"type":"Point"}
}