{
  "type": "Feature",
  "properties": {
    "addr:full":"1400 28th St Denver CO 80205",
    "addr:housenumber":"1400",
    "addr:postcode":"80205",
    "addr:street":"28Th St",
    "iso:country":"US",
    "sg:address":"1400 28th St",
    "sg:city":"Denver",
    "sg:classifiers":[
        {
            "category":"Health Services",
            "subcategory":"Doctor",
            "type":"Services"
        }
    ],
    "sg:phone":"+1 303 442 8625",
    "sg:postcode":"80205",
    "sg:province":"CO",
    "wof:name":"Ted C Kawulok",
    "wof:placetype":"venue"
},
  "geometry": {"coordinates":[-104.983869,39.761146],"type":"Point"}
}