{
  "type": "Feature",
  "properties": {
    "addr:full":"4255 Carson St Denver CO 80239",
    "addr:housenumber":"4255",
    "addr:postcode":"80239",
    "addr:street":"Carson St",
    "iso:country":"US",
    "sg:address":"4255 Carson St",
    "sg:city":"Denver",
    "sg:classifiers":[
        {
            "category":"Professional",
            "subcategory":"Advertising",
            "type":"Services"
        }
    ],
    "sg:phone":"+1 303 373 1866",
    "sg:postcode":"80239",
    "sg:province":"CO",
    "sg:tags":[
        "mail",
        "direct"
    ],
    "wof:name":"Address Pro Inc",
    "wof:placetype":"venue"
},
  "geometry": {"coordinates":[-104.834744,39.774849],"type":"Point"}
}