{
  "type": "Feature",
  "properties": {
    "iso:country":"US",
    "sg:address":"2506 W 29th Ave",
    "sg:city":"Denver",
    "sg:classifiers":[
        {
            "category":"Banks & Credit Unions",
            "subcategory":"Bank",
            "type":"Services"
        }
    ],
    "sg:phone":"+1 303 561 1911",
    "sg:postcode":"80211",
    "sg:province":"CO",
    "sg:tags":[
        "company",
        "trust"
    ],
    "wof:name":"Mc Laughlin Family Trusts",
    "wof:placetype":"venue"
},
  "geometry": {"coordinates":[-105.01930900000001,39.758435],"type":"Point"}
}