{
  "type": "Feature",
  "properties": {
    "iso:country":"US",
    "sg:address":"9232 Park Meadows Dr",
    "sg:city":"Lone Tree",
    "sg:classifiers":[
        {
            "category":"Restaurant",
            "type":"Food & Drink"
        }
    ],
    "sg:phone":"+1 303 768 9088",
    "sg:postcode":"80124",
    "sg:province":"CO",
    "sg:website":"www.ufeedme.com",
    "wof:name":"John Holly's Asian Cafe",
    "wof:placetype":"venue"
},
  "geometry": {"coordinates":[-104.881711,39.554646],"type":"Point"}
}