{
  "type": "Feature",
  "properties": {
    "iso:country":"US",
    "sg:address":"478 W Happy Canyon Rd",
    "sg:city":"Castle Rock",
    "sg:classifiers":[
        {
            "category":"Organizations",
            "subcategory":"Professional Association",
            "type":"Services"
        },
        {
            "category":"Organizations",
            "subcategory":"Community Association",
            "type":"Services"
        }
    ],
    "sg:phone":"+1 303 814 1345",
    "sg:postcode":"80108",
    "sg:province":"CO",
    "sg:tags":[
        "real estate"
    ],
    "sg:website":"www.castlepinesvillage.org",
    "wof:name":"Castle Pines Homes Assn Inc",
    "wof:placetype":"venue"
},
  "geometry": {"coordinates":[-104.891204,39.434669],"type":"Point"}
}