{
  "type": "Feature",
  "properties": {
    "iso:country":"US",
    "sg:address":"5441 Boeing Dr",
    "sg:city":"Loveland",
    "sg:classifiers":[
        {
            "category":"Professional",
            "subcategory":"Engineering",
            "type":"Services"
        }
    ],
    "sg:phone":"+1 970 612 0337",
    "sg:postcode":"80538",
    "sg:province":"CO",
    "sg:tags":[
        "engineer"
    ],
    "wof:name":"Sole Engineering",
    "wof:placetype":"venue"
},
  "geometry": {"coordinates":[-105.000086,40.451656],"type":"Point"}
}