{
  "type": "Feature",
  "properties": {
    "iso:country":"US",
    "sg:address":"7705 Wadsworth Blvd",
    "sg:city":"Arvada",
    "sg:classifiers":[
        {
            "category":"Health Services",
            "subcategory":"Chiropractor",
            "type":"Services"
        }
    ],
    "sg:phone":"+1 303 421 3639",
    "sg:postcode":"80003",
    "sg:province":"CO",
    "wof:name":"Steven L Peterson DC",
    "wof:placetype":"venue"
},
  "geometry": {"coordinates":[-105.081768,39.835739],"type":"Point"}
}