{
  "type": "Feature",
  "properties": {
    "iso:country":"US",
    "sg:address":"5601 W 88th Ave",
    "sg:city":"Westminster",
    "sg:classifiers":[
        {
            "category":"Shopping",
            "subcategory":"Clothing, Apparel, & Fashions",
            "type":"Retail Goods"
        }
    ],
    "sg:phone":"+1 720 540 8052",
    "sg:postcode":"80031",
    "sg:province":"CO",
    "sg:tags":[
        "leather"
    ],
    "wof:name":"Ab Leather",
    "wof:placetype":"venue"
},
  "geometry": {"coordinates":[-105.060013,39.856531],"type":"Point"}
}