{
  "type": "Feature",
  "properties": {
    "iso:country":"US",
    "sg:address":"2121 W 73rd Pl",
    "sg:city":"Denver",
    "sg:classifiers":[
        {
            "category":"Building & Trades",
            "subcategory":"Plumbing",
            "type":"Services"
        }
    ],
    "sg:phone":"+1 303 650 9329",
    "sg:postcode":"80221",
    "sg:province":"CO",
    "sg:tags":[
        "contractor"
    ],
    "wof:name":"Thompson Heating AC",
    "wof:placetype":"venue"
},
  "geometry": {"coordinates":[-105.01439999999999,39.830146],"type":"Point"}
}