{
  "type": "Feature",
  "properties": {
    "iso:country":"US",
    "sg:address":"3501 11th Ave",
    "sg:city":"Evans",
    "sg:classifiers":[
        {
            "category":"Retail",
            "subcategory":"Funeral Services",
            "type":"Services"
        }
    ],
    "sg:phone":"+1 970 330 6824",
    "sg:postcode":"80620",
    "sg:province":"CO",
    "sg:tags":[
        "director"
    ],
    "wof:name":"Moser Funeral & Cremation Svc",
    "wof:placetype":"venue"
},
  "geometry": {"coordinates":[-104.69673,40.378827],"type":"Point"}
}