{
  "type": "Feature",
  "properties": {
    "iso:country":"US",
    "sg:address":"9791 Titan Park Cir",
    "sg:city":"Littleton",
    "sg:classifiers":[
        {
            "category":"Building & Trades",
            "subcategory":"Landscaping Services",
            "type":"Services"
        }
    ],
    "sg:phone":"+1 303 791 7428",
    "sg:postcode":"80125",
    "sg:province":"CO",
    "sg:tags":[
        "landscape",
        "contractor"
    ],
    "wof:name":"Nylund Landscaping Inc",
    "wof:placetype":"venue"
},
  "geometry": {"coordinates":[-105.019373,39.50127],"type":"Point"}
}