{
  "type": "Feature",
  "properties": {
    "iso:country":"US",
    "sg:address":"6025 E Parkway Dr",
    "sg:city":"Commerce City",
    "sg:classifiers":[
        {
            "category":"Professional",
            "subcategory":"Accounting & Tax Preparation",
            "type":"Services"
        }
    ],
    "sg:phone":"+1 303 287 9629",
    "sg:postcode":"80022",
    "sg:province":"CO",
    "sg:tags":[
        "return",
        "filing"
    ],
    "sg:website":"www.hrblock.com",
    "wof:name":"H & R Block Tax Svc",
    "wof:placetype":"venue"
},
  "geometry": {"coordinates":[-104.93028,39.806441],"type":"Point"}
}