{
  "type": "Feature",
  "properties": {
    "iso:country":"US",
    "sg:address":"5955 Sheridan Blvd",
    "sg:city":"Arvada",
    "sg:classifiers":[
        {
            "category":"Manufacturing",
            "subcategory":"Tools & Machinery",
            "type":"Manufacturing & Wholesale Goods"
        }
    ],
    "sg:phone":"+1 303 423 2012",
    "sg:postcode":"80003",
    "sg:province":"CO",
    "sg:tags":[
        "machine",
        "shop"
    ],
    "wof:name":"Salco Inc",
    "wof:placetype":"venue"
},
  "geometry": {"coordinates":[-105.05292799999999,39.80402],"type":"Point"}
}