{
  "type": "Feature",
  "properties": {
    "iso:country":"US",
    "sg:address":"7441 E Iliff Avenue",
    "sg:city":"Denver",
    "sg:classifiers":[
        {
            "category":"Retail",
            "subcategory":"Laundry & Dry Cleaning",
            "type":"Services"
        }
    ],
    "sg:phone":"+1 303 369 6161",
    "sg:postcode":"80231",
    "sg:province":"CO",
    "wof:name":"Cp Cleaners",
    "wof:placetype":"venue"
},
  "geometry": {"coordinates":[-104.902269,39.675705],"type":"Point"}
}