{
  "type": "Feature",
  "properties": {
    "addr:full":"1510 W Eisenhower Blvd Loveland CO 80537",
    "addr:housenumber":"1510",
    "addr:postcode":"80537",
    "addr:street":"W Eisenhower Blvd",
    "iso:country":"US",
    "sg:address":"1510 W Eisenhower Blvd",
    "sg:city":"Loveland",
    "sg:classifiers":[
        {
            "category":"Coffee & Tea",
            "type":"Food & Drink"
        }
    ],
    "sg:menulink":"http://www.allmenus.com/co/loveland/118114-starbucks-coffee/menu/",
    "sg:phone":"+1 970 663 1827",
    "sg:postcode":"80537",
    "sg:province":"CO",
    "sg:tags":[
        "american"
    ],
    "wof:name":"Starbucks Coffee",
    "wof:placetype":"venue"
},
  "geometry": {"coordinates":[-105.098646,40.4069],"type":"Point"}
}