{
  "type": "Feature",
  "properties": {
    "addr:full":"14111 E Alameda Ave Aurora CO 80012",
    "addr:housenumber":"14111",
    "addr:postcode":"80012",
    "addr:street":"E Alameda Ave",
    "iso:country":"US",
    "sg:address":"14111 E Alameda Ave",
    "sg:city":"Aurora",
    "sg:classifiers":[
        {
            "category":"Insurance",
            "subcategory":"Insurance Agent",
            "type":"Services"
        }
    ],
    "sg:phone":"+1 303 360 7534",
    "sg:postcode":"80012",
    "sg:province":"CO",
    "wof:name":"AFLAC",
    "wof:placetype":"venue"
},
  "geometry": {"coordinates":[-104.826635,39.71116],"type":"Point"}
}