{
  "type": "Feature",
  "properties": {
    "iso:country":"US",
    "sg:address":"3635 Quivas St",
    "sg:city":"Denver",
    "sg:classifiers":[
        {
            "category":"Education",
            "subcategory":"School",
            "type":"Public Place"
        }
    ],
    "sg:phone":"+1 303 433 3336",
    "sg:postcode":"80211",
    "sg:province":"CO",
    "sg:tags":[
        "high",
        "middle",
        "elementary"
    ],
    "wof:name":"Schools Public",
    "wof:placetype":"venue"
},
  "geometry": {"coordinates":[-105.008185,39.767267],"type":"Point"}
}