{
  "type": "Feature",
  "properties": {
    "iso:country":"US",
    "sg:address":"8480 E Orchard Rd",
    "sg:city":"Englewood",
    "sg:classifiers":[
        {
            "category":"Professional",
            "subcategory":"Computer Services",
            "type":"Services"
        }
    ],
    "sg:phone":"+1 303 566 6500",
    "sg:postcode":"80111",
    "sg:province":"CO",
    "sg:tags":[
        "development",
        "software"
    ],
    "wof:name":"Hyperspace Communications",
    "wof:placetype":"venue"
},
  "geometry": {"coordinates":[-104.891206,39.609241],"type":"Point"}
}