{
  "type": "Feature",
  "properties": {
    "addr:full":"2152 E 88th Ave Denver CO 80229",
    "addr:housenumber":"2152",
    "addr:postcode":"80229",
    "addr:street":"E 88Th Ave",
    "iso:country":"US",
    "sg:address":"2152 E 88th Ave",
    "sg:city":"Denver",
    "sg:classifiers":[
        {
            "category":"Personal",
            "type":"Services"
        }
    ],
    "sg:phone":"+1 303 227 0400",
    "sg:postcode":"80229",
    "sg:province":"CO",
    "sg:tags":[
        "therapist",
        "massage"
    ],
    "wof:name":"Free-Well",
    "wof:placetype":"venue"
},
  "geometry": {"coordinates":[-104.96145199999999,39.856038],"type":"Point"}
}