{
  "type": "Feature",
  "properties": {
    "addr:full":"291 Broadway Ave Alamosa CO 81101",
    "addr:housenumber":"291",
    "addr:postcode":"81101",
    "addr:street":"Broadway Ave",
    "iso:country":"US",
    "sg:address":"291 Broadway Ave",
    "sg:city":"Alamosa",
    "sg:classifiers":[
        {
            "category":"Shopping",
            "subcategory":"Shoes",
            "type":"Retail Goods"
        }
    ],
    "sg:phone":"+1 719 589 5444",
    "sg:postcode":"81101",
    "sg:province":"CO",
    "sg:tags":[
        "repair",
        "sporting",
        "r"
    ],
    "wof:name":"Alsbaugh Leather Goods",
    "wof:placetype":"venue"
},
  "geometry": {"coordinates":[-105.859717,37.470899],"type":"Point"}
}