{
  "type": "Feature",
  "properties": {
    "addr:full":"5909 N Nevada Ave Colorado Springs CO 80918",
    "addr:housenumber":"5909",
    "addr:postcode":"80918",
    "addr:street":"N Nevada Ave",
    "iso:country":"US",
    "sg:address":"5909 N Nevada Ave",
    "sg:city":"Colorado Springs",
    "sg:classifiers":[
        {
            "category":"Shopping",
            "type":"Retail Goods"
        }
    ],
    "sg:phone":"+1 719 598 7726",
    "sg:postcode":"80918",
    "sg:province":"CO",
    "sg:tags":[
        "spa",
        "hot",
        "tub"
    ],
    "wof:name":"Premiere Management",
    "wof:placetype":"venue"
},
  "geometry": {"coordinates":[-104.815286,38.914712],"type":"Point"}
}