{
  "type": "Feature",
  "properties": {
    "iso:country":"US",
    "sg:address":"266 S 4th St",
    "sg:city":"Carbondale",
    "sg:classifiers":[
        {
            "category":"Building & Trades",
            "subcategory":"Construction",
            "type":"Services"
        }
    ],
    "sg:phone":"+1 970 963 4073",
    "sg:postcode":"81623",
    "sg:province":"CO",
    "sg:tags":[
        "house",
        "architectural"
    ],
    "wof:name":"Strawbuild",
    "wof:placetype":"venue"
},
  "geometry": {"coordinates":[-107.211175,39.398284],"type":"Point"}
}