{
  "type": "Feature",
  "properties": {
    "iso:country":"US",
    "sg:address":"1016 Sunnyside Rd",
    "sg:city":"Montrose",
    "sg:classifiers":[
        {
            "category":"Professional",
            "subcategory":"Computer Services",
            "type":"Services"
        }
    ],
    "sg:phone":"+1 970 252 1543",
    "sg:postcode":"81401",
    "sg:province":"CO",
    "sg:tags":[
        "repair"
    ],
    "wof:name":"D 2 Enterprises",
    "wof:placetype":"venue"
},
  "geometry": {"coordinates":[-107.859876,38.47442],"type":"Point"}
}