{
  "type": "Feature",
  "properties": {
    "iso:country":"US",
    "sg:address":"145 E Mountain Ave",
    "sg:city":"Fort Collins",
    "sg:classifiers":[
        {
            "category":"Education",
            "subcategory":"Vocational School",
            "type":"Public Place"
        }
    ],
    "sg:phone":"+1 970 482 7494",
    "sg:postcode":"80524",
    "sg:province":"CO",
    "sg:tags":[
        "training",
        "computer"
    ],
    "wof:name":"Prepress Solutions",
    "wof:placetype":"venue"
},
  "geometry": {"coordinates":[-105.076908,40.586954],"type":"Point"}
}