{
  "type": "Feature",
  "properties": {
    "iso:country":"US",
    "sg:address":"880 E 68th Ave",
    "sg:city":"Denver",
    "sg:classifiers":[
        {
            "category":"Building & Trades",
            "subcategory":"Construction",
            "type":"Services"
        }
    ],
    "sg:phone":"+1 303 288 2890",
    "sg:postcode":"80229",
    "sg:province":"CO",
    "sg:tags":[
        "general",
        "contractor"
    ],
    "wof:name":"Ed's Elite Construction",
    "wof:placetype":"venue"
},
  "geometry": {"coordinates":[-104.974909,39.819907],"type":"Point"}
}