{
  "type": "Feature",
  "properties": {
    "iso:country":"US",
    "sg:address":"101 S Indiana St",
    "sg:city":"Walsh",
    "sg:classifiers":[
        {
            "category":"Organizations",
            "subcategory":"Religious Organization",
            "type":"Services"
        }
    ],
    "sg:phone":"+1 719 324 5875",
    "sg:postcode":"81090",
    "sg:province":"CO",
    "sg:tags":[
        "church"
    ],
    "wof:name":"Walsh Baptist Church",
    "wof:placetype":"venue"
},
  "geometry": {"coordinates":[-102.27556199999999,37.383784],"type":"Point"}
}