{
  "type": "Feature",
  "properties": {
    "iso:country":"US",
    "sg:address":"65 S Cherokee Street",
    "sg:city":"Denver",
    "sg:classifiers":[
        {
            "category":"Retail",
            "subcategory":"Auto Repair",
            "type":"Services"
        }
    ],
    "sg:phone":"+1 303 722 2808",
    "sg:postcode":"80223",
    "sg:province":"CO",
    "sg:website":"www.astroautomotive.com",
    "wof:name":"Astro Automotive",
    "wof:placetype":"venue"
},
  "geometry": {"coordinates":[-104.992086,39.715081],"type":"Point"}
}