{
  "type": "Feature",
  "properties": {
    "iso:country":"US",
    "sg:address":"443 S Saint Vrain Ave",
    "sg:city":"Estes Park",
    "sg:classifiers":[
        {
            "category":"Shopping",
            "subcategory":"Florist",
            "type":"Retail Goods"
        }
    ],
    "sg:phone":"+1 970 577 1740",
    "sg:postcode":"80517",
    "sg:province":"CO",
    "wof:name":"Karens Flowers Of Estes Park",
    "wof:placetype":"venue"
},
  "geometry": {"coordinates":[-105.505951,40.371142],"type":"Point"}
}