{
  "type": "Feature",
  "properties": {
    "iso:country":"US",
    "sg:address":"531 E Lionshead Cir",
    "sg:city":"Vail",
    "sg:classifiers":[
        {
            "category":"Recreation",
            "type":"Entertainment"
        },
        {
            "category":"Shopping",
            "subcategory":"Clothing, Apparel, & Fashions",
            "type":"Retail Goods"
        }
    ],
    "sg:phone":"+1 970 476 1718",
    "sg:postcode":"81657",
    "sg:province":"CO",
    "sg:tags":[
        "bicycle",
        "rental",
        "equipment",
        "rent",
        "skiing",
        "concession",
        "sport",
        "ski"
    ],
    "sg:website":"www.performancesports.net",
    "wof:name":"Performance Sports Inc",
    "wof:placetype":"venue"
},
  "geometry": {"coordinates":[-106.38686300000001,39.644048],"type":"Point"}
}