{
  "type": "Feature",
  "properties": {
    "addr:full":"65 S Quitman St Denver CO 80219",
    "addr:housenumber":"65",
    "addr:postcode":"80219",
    "addr:street":"S Quitman St",
    "iso:country":"US",
    "sg:address":"65 S Quitman St",
    "sg:city":"Denver",
    "sg:classifiers":[
        {
            "category":"Home & Garden",
            "subcategory":"Building Materials",
            "type":"Retail Goods"
        },
        {
            "category":"Building & Trades",
            "subcategory":"Construction",
            "type":"Services"
        }
    ],
    "sg:phone":"+1 720 933 9676",
    "sg:postcode":"80219",
    "sg:province":"CO",
    "sg:tags":[
        "industrial",
        "contractor",
        "concrete",
        "contractors-commercial",
        "staining",
        "masonry",
        "fence-sales"
    ],
    "wof:name":"Green Works Concrete & Landscaping",
    "wof:placetype":"venue"
},
  "geometry": {"coordinates":[-105.040896,39.71551],"type":"Point"}
}