{
  "type": "Feature",
  "properties": {
    "addr:full":"915 Deborah Dr Loveland CO 80537",
    "addr:housenumber":"915",
    "addr:postcode":"80537",
    "addr:street":"Deborah Dr",
    "iso:country":"US",
    "sg:address":"915 Deborah Dr",
    "sg:city":"Loveland",
    "sg:classifiers":[
        {
            "category":"Education",
            "subcategory":"School",
            "type":"Public Place"
        }
    ],
    "sg:phone":"+1 970 613 5500",
    "sg:postcode":"80537",
    "sg:province":"CO",
    "wof:name":"B F Kitchen K-5",
    "wof:placetype":"venue"
},
  "geometry": {"coordinates":[-105.090718,40.374163],"type":"Point"}
}