{
  "type": "Feature",
  "properties": {
    "iso:country":"US",
    "sg:address":"719 Mariposa St",
    "sg:city":"Denver",
    "sg:classifiers":[
        {
            "category":"Building & Trades",
            "subcategory":"Electrical",
            "type":"Services"
        }
    ],
    "sg:phone":"+1 303 944 8132",
    "sg:postcode":"80204",
    "sg:province":"CO",
    "sg:tags":[
        "electrical",
        "electric",
        "contractor"
    ],
    "wof:name":"Blue Line Electric Inc",
    "wof:placetype":"venue"
},
  "geometry": {"coordinates":[-105.00291900000001,39.728608],"type":"Point"}
}