{
  "type": "Feature",
  "properties": {
    "addr:full":"2267 Hiawatha Ct Fort Collins CO 80525",
    "addr:housenumber":"2267",
    "addr:postcode":"80525",
    "addr:street":"Hiawatha Ct",
    "iso:country":"US",
    "sg:address":"2267 Hiawatha Ct",
    "sg:city":"Fort Collins",
    "sg:classifiers":[
        {
            "category":"Professional",
            "subcategory":"Accounting & Tax Preparation",
            "type":"Services"
        }
    ],
    "sg:phone":"+1 970 224 1822",
    "sg:postcode":"80525",
    "sg:province":"CO",
    "sg:tags":[
        "accountant"
    ],
    "wof:name":"Ron Glick CPA",
    "wof:placetype":"venue"
},
  "geometry": {"coordinates":[-105.06051100000001,40.557963],"type":"Point"}
}