{
  "type": "Feature",
  "properties": {
    "iso:country":"US",
    "sg:address":"2996 D Rd",
    "sg:city":"Grand Junction",
    "sg:classifiers":[
        {
            "category":"Food & Beverages",
            "subcategory":"Liquor & Beverages",
            "type":"Retail Goods"
        }
    ],
    "sg:phone":"+1 970 243 0768",
    "sg:postcode":"81504",
    "sg:province":"CO",
    "sg:tags":[
        "alcoholic"
    ],
    "wof:name":"Kokopelli Liquors",
    "wof:placetype":"venue"
},
  "geometry": {"coordinates":[-108.497845,39.06284],"type":"Point"}
}