{
  "type": "Feature",
  "properties": {
    "addr:full":"3801 Weicker Dr Fort Collins CO 80524",
    "addr:housenumber":"3801",
    "addr:postcode":"80524",
    "addr:street":"Weicker Dr",
    "iso:country":"US",
    "sg:address":"3801 Weicker Dr",
    "sg:city":"Fort Collins",
    "sg:classifiers":[
        {
            "category":"Building & Trades",
            "subcategory":"Construction",
            "type":"Services"
        }
    ],
    "sg:phone":"+1 970 484 5355",
    "sg:postcode":"80524",
    "sg:province":"CO",
    "wof:name":"DMD Construction",
    "wof:placetype":"venue"
},
  "geometry": {"coordinates":[-105.004891,40.583498],"type":"Point"}
}