{
  "type": "Feature",
  "properties": {
    "iso:country":"US",
    "sg:address":"3801 Weicker Dr",
    "sg:city":"Fort Collins",
    "sg:classifiers":[
        {
            "category":"Building & Trades",
            "subcategory":"Construction",
            "type":"Services"
        }
    ],
    "sg:phone":"+1 970 484 5355",
    "sg:postcode":"80524",
    "sg:province":"CO",
    "wof:name":"DMD Construction",
    "wof:placetype":"venue"
},
  "geometry": {"coordinates":[-105.004891,40.583498],"type":"Point"}
}