{
  "type": "Feature",
  "properties": {
    "iso:country":"US",
    "sg:address":"10285 Ridge Rd",
    "sg:city":"Wheat Ridge",
    "sg:classifiers":[
        {
            "category":"Government",
            "subcategory":"Office",
            "type":"Public Place"
        }
    ],
    "sg:phone":"+1 303 424 7791",
    "sg:postcode":"80033",
    "sg:province":"CO",
    "sg:tags":[
        "human"
    ],
    "wof:name":"Wheat Ridge Regional Center",
    "wof:placetype":"venue"
},
  "geometry": {"coordinates":[-105.109267,39.793096],"type":"Point"}
}