{
  "type": "Feature",
  "properties": {
    "iso:country":"US",
    "sg:address":"430 N 4th St",
    "sg:city":"Montrose",
    "sg:classifiers":[
        {
            "category":"Building & Trades",
            "subcategory":"Electrical",
            "type":"Services"
        }
    ],
    "sg:phone":"+1 970 249 6522",
    "sg:postcode":"81401",
    "sg:province":"CO",
    "sg:tags":[
        "electric",
        "contractor"
    ],
    "wof:name":"Steele Electric Ltd Lblty Co",
    "wof:placetype":"venue"
},
  "geometry": {"coordinates":[-107.879279,38.482987],"type":"Point"}
}