{
  "type": "Feature",
  "properties": {
    "iso:country":"US",
    "sg:address":"34469 State Hwy 145",
    "sg:city":"Norwood",
    "sg:classifiers":[
        {
            "category":"Organizations",
            "subcategory":"Religious Organization",
            "type":"Services"
        }
    ],
    "sg:phone":"+1 970 327 4454",
    "sg:postcode":"81423",
    "sg:province":"CO",
    "sg:tags":[
        "church"
    ],
    "wof:name":"Canyon Chapel Ministries",
    "wof:placetype":"venue"
},
  "geometry": {"coordinates":[-108.18577500000001,38.101708],"type":"Point"}
}