{
  "type": "Feature",
  "properties": {
    "iso:country":"US",
    "sg:address":"3500 Forest Street",
    "sg:city":"Denver",
    "sg:classifiers":[
        {
            "category":"Organizations",
            "subcategory":"Religious Organization",
            "type":"Services"
        }
    ],
    "sg:phone":"+1 303 322 2677",
    "sg:postcode":"80207",
    "sg:province":"CO",
    "wof:name":"Park East Church of Christ",
    "wof:placetype":"venue"
},
  "geometry": {"coordinates":[-104.92682499999999,39.765733],"type":"Point"}
}