{
  "type": "Feature",
  "properties": {
    "iso:country":"US",
    "sg:address":"215 S Pecos St",
    "sg:city":"Denver",
    "sg:classifiers":[
        {
            "category":"Wholesale",
            "subcategory":"Groceries",
            "type":"Manufacturing & Wholesale Goods"
        }
    ],
    "sg:phone":"+1 303 698 0971",
    "sg:postcode":"80223",
    "sg:province":"CO",
    "sg:tags":[
        "food",
        "product",
        "mexican"
    ],
    "sg:website":"www.nmdist.com",
    "wof:name":"New Mexico Distributing",
    "wof:placetype":"venue"
},
  "geometry": {"coordinates":[-105.00662199999999,39.712802],"type":"Point"}
}