{
  "type": "Feature",
  "properties": {
    "iso:country":"US",
    "sg:address":"2546 15th Street",
    "sg:city":"Denver",
    "sg:classifiers":[
        {
            "category":"Arts & Performance",
            "subcategory":"Art Gallery",
            "type":"Entertainment"
        }
    ],
    "sg:phone":"+1 720 932 8720",
    "sg:postcode":"80211",
    "sg:province":"CO",
    "wof:name":"Alchemy the Art of Transforming Business",
    "wof:placetype":"venue"
},
  "geometry": {"coordinates":[-105.010973,39.757967],"type":"Point"}
}