{
  "type": "Feature",
  "properties": {
    "addr:full":"401 W Meadow Rd Durango CO 81303",
    "addr:housenumber":"401",
    "addr:postcode":"co 81303",
    "addr:street":"W Meadow Rd",
    "iso:country":"US",
    "sg:address":"401 W Meadow Rd",
    "sg:city":"Durango",
    "sg:classifiers":[
        {
            "category":"Shopping",
            "subcategory":"Catalog Store",
            "type":"Retail Goods"
        }
    ],
    "sg:phone":"+1 970 259 3998",
    "sg:postcode":"81303",
    "sg:province":"CO",
    "sg:tags":[
        "air",
        "equipment",
        "allergy",
        "cleaning",
        "purification"
    ],
    "wof:name":"Absolute Air Clrs & Purifiers",
    "wof:placetype":"venue"
},
  "geometry": {"coordinates":[-107.7897,37.204702],"type":"Point"}
}