{
  "type": "Feature",
  "properties": {
    "iso:country":"US",
    "sg:address":"623 14th St",
    "sg:city":"Golden",
    "sg:classifiers":[
        {
            "category":"Professional",
            "type":"Services"
        }
    ],
    "sg:phone":"+1 303 279 5900",
    "sg:postcode":"80401",
    "sg:province":"CO",
    "sg:tags":[
        "establishment"
    ],
    "wof:name":"Sport & Science National Edctn",
    "wof:placetype":"venue"
},
  "geometry": {"coordinates":[-105.218474,39.754449],"type":"Point"}
}