{
  "type": "Feature",
  "properties": {
    "addr:full":"8179 E Windwood Way Parker CO 80134",
    "addr:housenumber":"8179",
    "addr:postcode":"80134",
    "addr:street":"E Windwood Way",
    "iso:country":"US",
    "sg:address":"8179 E Windwood Way",
    "sg:city":"Parker",
    "sg:classifiers":[
        {
            "category":"Building & Trades",
            "subcategory":"Construction",
            "type":"Services"
        }
    ],
    "sg:phone":"+1 303 324 3221",
    "sg:postcode":"80134",
    "sg:province":"CO",
    "sg:tags":[
        "house"
    ],
    "wof:name":"Sindt Construction Inc",
    "wof:placetype":"venue"
},
  "geometry": {"coordinates":[-104.733349,39.458611],"type":"Point"}
}