{
  "type": "Feature",
  "properties": {
    "iso:country":"US",
    "sg:address":"6726 S Revere Pkwy",
    "sg:city":"Centennial",
    "sg:classifiers":[
        {
            "category":"Health Services",
            "subcategory":"Doctor",
            "type":"Services"
        }
    ],
    "sg:phone":"+1 303 649 9688",
    "sg:postcode":"80112",
    "sg:province":"CO",
    "sg:tags":[
        "physician",
        "surgeon"
    ],
    "wof:name":"Stand Up Mri Of America",
    "wof:placetype":"venue"
},
  "geometry": {"coordinates":[-104.840354,39.594461],"type":"Point"}
}