{
  "type": "Feature",
  "properties": {
    "iso:country":"US",
    "sg:address":"3325 G Rd",
    "sg:city":"Clifton",
    "sg:classifiers":[
        {
            "category":"Manufacturing",
            "subcategory":"Textiles",
            "type":"Manufacturing & Wholesale Goods"
        }
    ],
    "sg:phone":"+1 970 434 4357",
    "sg:postcode":"81520",
    "sg:province":"CO",
    "sg:tags":[
        "mill",
        "fabric"
    ],
    "wof:name":"Willie Bilt Manufacturing",
    "wof:placetype":"venue"
},
  "geometry": {"coordinates":[-108.42963899999999,39.10615],"type":"Point"}
}