{
  "type": "Feature",
  "properties": {
    "iso:country":"US",
    "sg:address":"400 Inverness Dr S",
    "sg:city":"Englewood",
    "sg:classifiers":[
        {
            "category":"Banks & Credit Unions",
            "subcategory":"Investment Brokerage",
            "type":"Services"
        }
    ],
    "sg:phone":"+1 303 486 5847",
    "sg:postcode":"80112",
    "sg:province":"CO",
    "wof:name":"Fidelity Investments",
    "wof:placetype":"venue"
},
  "geometry": {"coordinates":[-104.86650400000001,39.566001],"type":"Point"}
}