{
  "type": "Feature",
  "properties": {
    "addr:full":"761 Valley Ct Grand Junction CO 81505",
    "addr:housenumber":"761",
    "addr:postcode":"81505",
    "addr:street":"Valley Ct",
    "iso:country":"US",
    "sg:address":"761 Valley Ct",
    "sg:city":"Grand Junction",
    "sg:classifiers":[
        {
            "category":"Freight",
            "type":"Transportation"
        }
    ],
    "sg:phone":"+1 970 243 4012",
    "sg:postcode":"81505",
    "sg:province":"CO",
    "sg:tags":[
        "recreational",
        "vehicle"
    ],
    "wof:name":"I 70 Maxi Storage LLC",
    "wof:placetype":"venue"
},
  "geometry": {"coordinates":[-108.649957,39.115301],"type":"Point"}
}