{
  "type": "Feature",
  "properties": {
    "iso:country":"US",
    "sg:address":"6255 W 52nd Avenue",
    "sg:city":"Arvada",
    "sg:classifiers":[
        {
            "category":"Building & Trades",
            "subcategory":"Construction",
            "type":"Services"
        }
    ],
    "sg:phone":"+1 303 467 0909",
    "sg:postcode":"80002",
    "sg:province":"CO",
    "sg:tags":[
        "contractor"
    ],
    "wof:name":"Ricor",
    "wof:placetype":"venue"
},
  "geometry": {"coordinates":[-105.06562,39.790979],"type":"Point"}
}