{
  "type": "Feature",
  "properties": {
    "addr:full":"5016 S Malaya Way Aurora CO 80015",
    "addr:housenumber":"5016",
    "addr:postcode":"80015",
    "addr:street":"S Malaya Way",
    "iso:country":"US",
    "sg:address":"5016 S Malaya Way",
    "sg:city":"Aurora",
    "sg:classifiers":[
        {
            "category":"Professional",
            "type":"Services"
        }
    ],
    "sg:phone":"+1 303 699 9629",
    "sg:postcode":"80015",
    "sg:province":"CO",
    "wof:name":"Kim Youn M Sound TEC",
    "wof:placetype":"venue"
},
  "geometry": {"coordinates":[-104.74596099999999,39.625226],"type":"Point"}
}