{
  "type": "Feature",
  "properties": {
    "iso:country":"US",
    "sg:address":"212 10th Ave",
    "sg:city":"Greeley",
    "sg:phone":"+1 970 352 1504",
    "sg:postcode":"80631",
    "sg:province":"CO",
    "sg:tags":[
        "product",
        "petroleum"
    ],
    "wof:name":"All Star Gas Corporation",
    "wof:placetype":"venue"
},
  "geometry": {"coordinates":[-104.69428499999999,40.431465],"type":"Point"}
}