{
  "type": "Feature",
  "properties": {
    "iso:country":"US",
    "sg:address":"555 US Hwy 287",
    "sg:city":"Broomfield",
    "sg:classifiers":[
        {
            "category":"Retail",
            "subcategory":"Animal Services",
            "type":"Services"
        }
    ],
    "sg:phone":"+1 303 466 1188",
    "sg:postcode":"80020",
    "sg:province":"CO",
    "sg:tags":[
        "pet",
        "grooming",
        "washing"
    ],
    "wof:name":"Classic Clip",
    "wof:placetype":"venue"
},
  "geometry": {"coordinates":[-105.090959,39.924426],"type":"Point"}
}