{
  "type": "Feature",
  "properties": {
    "iso:country":"US",
    "sg:address":"2700 W 6th Ave",
    "sg:city":"Denver",
    "sg:classifiers":[
        {
            "category":"Wholesale",
            "subcategory":"Hardware",
            "type":"Manufacturing & Wholesale Goods"
        }
    ],
    "sg:phone":"+1 303 623 1236",
    "sg:postcode":"80204",
    "sg:province":"CO",
    "sg:tags":[
        "refrigeration",
        "con"
    ],
    "wof:name":"Sid Harveys 130",
    "wof:placetype":"venue"
},
  "geometry": {"coordinates":[-105.02075600000001,39.725678],"type":"Point"}
}