{
  "type": "Feature",
  "properties": {
    "iso:country":"US",
    "sg:address":"10600 W 50th Ave",
    "sg:city":"Wheat Ridge",
    "sg:classifiers":[
        {
            "category":"Wholesale",
            "subcategory":"Machinery & Supplies",
            "type":"Manufacturing & Wholesale Goods"
        },
        {
            "category":"Manufacturing",
            "subcategory":"Tools & Machinery",
            "type":"Manufacturing & Wholesale Goods"
        }
    ],
    "sg:phone":"+1 303 425 3255",
    "sg:postcode":"80033",
    "sg:province":"CO",
    "sg:tags":[
        "industrial",
        "washing",
        "pressure",
        "industry",
        "mfg",
        "equipment"
    ],
    "sg:website":"www.kem-o-kleen.com",
    "wof:name":"Kem-O-Kleen",
    "wof:placetype":"venue"
},
  "geometry": {"coordinates":[-105.117683,39.787346],"type":"Point"}
}