{
  "type": "Feature",
  "properties": {
    "addr:full":"7527 E Iliff Ave Denver CO 80231",
    "addr:housenumber":"7527",
    "addr:postcode":"80231",
    "addr:street":"E Iliff Ave",
    "iso:country":"US",
    "sg:address":"7527 E Iliff Ave",
    "sg:city":"Denver",
    "sg:classifiers":[
        {
            "category":"Health Services",
            "subcategory":"Optometrist",
            "type":"Services"
        }
    ],
    "sg:phone":"+1 303 745 7496",
    "sg:postcode":"80231",
    "sg:province":"CO",
    "wof:name":"Imart",
    "wof:placetype":"venue"
},
  "geometry": {"coordinates":[-104.901782,39.675378],"type":"Point"}
}