{
  "type": "Feature",
  "properties": {
    "iso:country":"US",
    "sg:address":"3533 Tejon St",
    "sg:city":"Denver",
    "sg:classifiers":[
        {
            "category":"Cinema",
            "subcategory":"Movie Rental",
            "type":"Entertainment"
        },
        {
            "category":"Shopping",
            "subcategory":"Books",
            "type":"Retail Goods"
        }
    ],
    "sg:phone":"+1 303 573 6810",
    "sg:postcode":"80211",
    "sg:province":"CO",
    "sg:tags":[
        "game",
        "bookstore",
        "video"
    ],
    "wof:name":"Rio De Agua Viva",
    "wof:placetype":"venue"
},
  "geometry": {"coordinates":[-105.011536,39.76619],"type":"Point"}
}