{
  "type": "Feature",
  "properties": {
    "iso:country":"US",
    "sg:address":"10001 W Asbury Ave",
    "sg:city":"Denver",
    "sg:classifiers":[
        {
            "category":"Home & Garden",
            "subcategory":"Household Appliances",
            "type":"Retail Goods"
        },
        {
            "category":"Shopping",
            "type":"Retail Goods"
        }
    ],
    "sg:phone":"+1 303 989 7500",
    "sg:postcode":"80227",
    "sg:province":"CO",
    "sg:tags":[
        "merchandise"
    ],
    "wof:name":"Maytag Store",
    "wof:placetype":"venue"
},
  "geometry": {"coordinates":[-105.112989,39.680124],"type":"Point"}
}