{
  "type": "Feature",
  "properties": {
    "addr:full":"720 N Main St Rocky Ford CO 81067",
    "addr:housenumber":"720",
    "addr:postcode":"81067",
    "addr:street":"N Main St",
    "iso:country":"US",
    "sg:address":"720 N Main St",
    "sg:city":"Rocky Ford",
    "sg:classifiers":[
        {
            "category":"Government",
            "subcategory":"Office",
            "type":"Public Place"
        }
    ],
    "sg:phone":"+1 719 254 6531",
    "sg:postcode":"81067",
    "sg:province":"CO",
    "sg:tags":[
        "state",
        "security"
    ],
    "wof:name":"National Guard",
    "wof:placetype":"venue"
},
  "geometry": {"coordinates":[-103.716955,38.057094],"type":"Point"}
}