{
  "type": "Feature",
  "properties": {
    "iso:country":"US",
    "sg:address":"3517 F Rd",
    "sg:city":"Clifton",
    "sg:classifiers":[
        {
            "category":"Building & Trades",
            "subcategory":"Plumbing",
            "type":"Services"
        }
    ],
    "sg:phone":"+1 970 464 5008",
    "sg:postcode":"81520",
    "sg:province":"CO",
    "sg:tags":[
        "contractor"
    ],
    "wof:name":"Day or Night Heating & Co",
    "wof:placetype":"venue"
},
  "geometry": {"coordinates":[-108.400756,39.091665],"type":"Point"}
}