{
  "type": "Feature",
  "properties": {
    "addr:full":"8700 W Colfax Ave Unit G Lakewood CO 80215",
    "addr:housenumber":"8700",
    "addr:postcode":"80215",
    "addr:street":"W Colfax Ave Unit G",
    "iso:country":"US",
    "sg:address":"8700 W Colfax Ave Unit G",
    "sg:city":"Lakewood",
    "sg:classifiers":[
        {
            "category":"Home & Garden",
            "subcategory":"Building Materials",
            "type":"Retail Goods"
        },
        {
            "category":"Building & Trades",
            "subcategory":"Construction",
            "type":"Services"
        }
    ],
    "sg:phone":"+1 720 253 1089",
    "sg:postcode":"80215",
    "sg:province":"CO",
    "sg:tags":[
        "bathroom",
        "altering",
        "handyman",
        "improvement",
        "planning",
        "contractor",
        "remodeling",
        "kitchen"
    ],
    "sg:website":"http://www.a-plus-home-improvement.com",
    "wof:name":"A Plus Handyman Home Improvement Services",
    "wof:placetype":"venue"
},
  "geometry": {"coordinates":[-105.094143,39.740189],"type":"Point"}
}