{
  "type": "Feature",
  "properties": {
    "addr:full":"890 Hemlock Way Broomfield CO 80020",
    "addr:housenumber":"890",
    "addr:postcode":"80020",
    "addr:street":"Hemlock Way",
    "iso:country":"US",
    "sg:address":"890 Hemlock Way",
    "sg:city":"Broomfield",
    "sg:classifiers":[
        {
            "category":"Recreation",
            "type":"Entertainment"
        }
    ],
    "sg:phone":"+1 303 469 1243",
    "sg:postcode":"80020",
    "sg:province":"CO",
    "sg:tags":[
        "balloon"
    ],
    "wof:name":"Aero-Cruise Balloon Adventures",
    "wof:placetype":"venue"
},
  "geometry": {"coordinates":[-105.082109,39.926399],"type":"Point"}
}