{
  "type": "Feature",
  "properties": {
    "iso:country":"US",
    "sg:address":"10332 Erin Pl",
    "sg:city":"Littleton",
    "sg:classifiers":[
        {
            "category":"Professional",
            "type":"Services"
        }
    ],
    "sg:phone":"+1 303 662 0731",
    "sg:postcode":"80124",
    "sg:province":"CO",
    "wof:name":"McNallycolorado LLC",
    "wof:placetype":"venue"
},
  "geometry": {"coordinates":[-104.89970099999999,39.528214],"type":"Point"}
}