{
  "type": "Feature",
  "properties": {
    "iso:country":"US",
    "sg:address":"15718 E Center Pl",
    "sg:city":"Aurora",
    "sg:classifiers":[
        {
            "category":"Real Estate",
            "subcategory":"Real Estate Services",
            "type":"Services"
        },
        {
            "category":"Building & Trades",
            "subcategory":"Cleaning & Sanitation",
            "type":"Services"
        }
    ],
    "sg:phone":"+1 303 368 9482",
    "sg:postcode":"80017",
    "sg:province":"CO",
    "sg:tags":[
        "maintenance",
        "cleaners-interior"
    ],
    "wof:name":"Arapahoe Maintenance Specialists Inc",
    "wof:placetype":"venue"
},
  "geometry": {"coordinates":[-104.804734,39.704647],"type":"Point"}
}