{
  "type": "Feature",
  "properties": {
    "iso:country":"US",
    "sg:address":"3265 S Wadsworth Blvd",
    "sg:city":"Lakewood",
    "sg:classifiers":[
        {
            "category":"Social Services",
            "subcategory":"Child Care",
            "type":"Services"
        }
    ],
    "sg:phone":"+1 303 989 3961",
    "sg:postcode":"80227",
    "sg:province":"CO",
    "wof:name":"A Child's View Preschool",
    "wof:placetype":"venue"
},
  "geometry": {"coordinates":[-105.081453,39.657627],"type":"Point"}
}