{
  "type": "Feature",
  "properties": {
    "addr:full":"700 E Main St Montrose CO 81401",
    "addr:housenumber":"700",
    "addr:postcode":"81401",
    "addr:street":"E Main St",
    "iso:country":"US",
    "sg:address":"700 E Main St",
    "sg:city":"Montrose",
    "sg:classifiers":[
        {
            "category":"Professional",
            "subcategory":"Business Services",
            "type":"Services"
        }
    ],
    "sg:phone":"+1 970 249 5366",
    "sg:postcode":"81401",
    "sg:province":"CO",
    "sg:tags":[
        "information",
        "bureau",
        "convention"
    ],
    "wof:name":"Old Hundred Mine Tour",
    "wof:placetype":"venue"
},
  "geometry": {"coordinates":[-107.87244699999999,38.482402],"type":"Point"}
}