{
  "type": "Feature",
  "properties": {
    "iso:country":"US",
    "sg:address":"3755 Meadow Ridge Dr",
    "sg:city":"Colorado Springs",
    "sg:classifiers":[
        {
            "category":"Education",
            "subcategory":"School",
            "type":"Public Place"
        }
    ],
    "sg:phone":"+1 719 594 0102",
    "sg:postcode":"80920",
    "sg:province":"CO",
    "sg:website":"www.d20.co.edu",
    "wof:name":"Frontier Elementary School",
    "wof:placetype":"venue"
},
  "geometry": {"coordinates":[-104.754623,38.947497],"type":"Point"}
}