{
  "type": "Feature",
  "properties": {
    "iso:country":"US",
    "sg:address":"518 17th St",
    "sg:city":"Denver",
    "sg:classifiers":[
        {
            "category":"Organizations",
            "subcategory":"Community Association",
            "type":"Services"
        }
    ],
    "sg:phone":"+1 303 825 0195",
    "sg:postcode":"80202",
    "sg:province":"CO",
    "sg:tags":[
        "club"
    ],
    "wof:name":"Denver Club",
    "wof:placetype":"venue"
},
  "geometry": {"coordinates":[-104.990022,39.745271],"type":"Point"}
}