{
  "type": "Feature",
  "properties": {
    "addr:full":"111 E Pikes Peak Ave Colorado Springs CO 80903",
    "addr:housenumber":"111",
    "addr:postcode":"80903",
    "addr:street":"E Pikes Peak Ave",
    "iso:country":"US",
    "sg:address":"111 E Pikes Peak Ave",
    "sg:city":"Colorado Springs",
    "sg:classifiers":[
        {
            "category":"Restaurant",
            "type":"Food & Drink"
        }
    ],
    "sg:phone":"+1 719 632 0299",
    "sg:postcode":"80903",
    "sg:province":"CO",
    "sg:tags":[
        "parlor",
        "ice",
        "cream"
    ],
    "sg:website":"www.joshandjohns.com",
    "wof:name":"Josh & John's Naturally",
    "wof:placetype":"venue"
},
  "geometry": {"coordinates":[-104.821512,38.833642],"type":"Point"}
}