{
  "type": "Feature",
  "properties": {
    "addr:full":"526 W Rockrimmon Blvd Colorado Springs CO 80919",
    "addr:housenumber":"526",
    "addr:postcode":"80919",
    "addr:street":"W Rockrimmon Blvd",
    "iso:country":"US",
    "sg:address":"526 W Rockrimmon Blvd",
    "sg:city":"Colorado Springs",
    "sg:classifiers":[
        {
            "category":"Building & Trades",
            "subcategory":"Construction",
            "type":"Services"
        }
    ],
    "sg:phone":"+1 719 559 2282",
    "sg:postcode":"80919",
    "sg:province":"CO",
    "sg:tags":[
        "resurfacing",
        "laying",
        "refinishing",
        "floor"
    ],
    "wof:name":"Custom Hardwood Flooring Inc",
    "wof:placetype":"venue"
},
  "geometry": {"coordinates":[-104.835291,38.92914],"type":"Point"}
}