{
  "type": "Feature",
  "properties": {
    "iso:country":"US",
    "sg:address":"2808 E 6th Ave",
    "sg:city":"Denver",
    "sg:classifiers":[
        {
            "category":"Shopping",
            "subcategory":"Baby Store",
            "type":"Retail Goods"
        },
        {
            "category":"Shopping",
            "subcategory":"Clothing, Apparel, & Fashions",
            "type":"Retail Goods"
        }
    ],
    "sg:phone":"+1 720 287 1372",
    "sg:postcode":"80206",
    "sg:province":"CO",
    "sg:tags":[
        "children's",
        "clothing",
        "gear",
        "furniture"
    ],
    "sg:website":"www.nestdenver.com",
    "wof:name":"Nest",
    "wof:placetype":"venue"
},
  "geometry": {"coordinates":[-104.954284,39.725583],"type":"Point"}
}