{
  "type": "Feature",
  "properties": {
    "iso:country":"US",
    "sg:address":"13865 Co Rd 33.6",
    "sg:city":"Mancos",
    "sg:classifiers":[
        {
            "category":"Shopping",
            "subcategory":"Florist",
            "type":"Retail Goods"
        }
    ],
    "sg:phone":"+1 970 882 3149",
    "sg:postcode":"81328",
    "sg:province":"CO",
    "wof:name":"Amigo Floral",
    "wof:placetype":"venue"
},
  "geometry": {"coordinates":[-108.434421,37.414933],"type":"Point"}
}