{
  "type": "Feature",
  "properties": {
    "iso:country":"US",
    "sg:address":"204 S 24th St",
    "sg:city":"Colorado Springs",
    "sg:classifiers":[
        {
            "category":"Travel",
            "subcategory":"Travel Agent",
            "type":"Entertainment"
        }
    ],
    "sg:phone":"+1 719 633 6399",
    "sg:postcode":"80904",
    "sg:province":"CO",
    "sg:tags":[
        "operator",
        "bicycle",
        "tour",
        "tours"
    ],
    "sg:website":"www.bikithikit.com",
    "wof:name":"Challenge Unlimited Ltd",
    "wof:placetype":"venue"
},
  "geometry": {"coordinates":[-104.862619,38.844938],"type":"Point"}
}