{
  "type": "Feature",
  "properties": {
    "addr:full":"112 S Spruce St Gunnison CO 81230",
    "addr:housenumber":"112",
    "addr:postcode":"81230",
    "addr:street":"S Spruce St",
    "iso:country":"US",
    "sg:address":"112 S Spruce St",
    "sg:city":"Gunnison",
    "sg:classifiers":[
        {
            "category":"Food & Beverages",
            "subcategory":"Groceries & Convenience Stores",
            "type":"Retail Goods"
        }
    ],
    "sg:phone":"+1 970 641 0787",
    "sg:postcode":"81230",
    "sg:province":"CO",
    "wof:name":"Safeway",
    "wof:placetype":"venue"
},
  "geometry": {"coordinates":[-106.930722,38.544222],"type":"Point"}
}