{
  "type": "Feature",
  "properties": {
    "addr:full":"1404 S 9th Ave Sterling CO 80751",
    "addr:housenumber":"1404",
    "addr:postcode":"80751",
    "addr:street":"S 9Th Ave",
    "iso:country":"US",
    "sg:address":"1404 S 9th Ave",
    "sg:city":"Sterling",
    "sg:classifiers":[
        {
            "category":"Organizations",
            "subcategory":"Religious Organization",
            "type":"Services"
        }
    ],
    "sg:phone":"+1 970 522 3408",
    "sg:postcode":"80751",
    "sg:province":"CO",
    "sg:tags":[
        "church"
    ],
    "wof:name":"Peace Lutheran Church",
    "wof:placetype":"venue"
},
  "geometry": {"coordinates":[-103.224954,40.611884],"type":"Point"}
}