{
  "type": "Feature",
  "properties": {
    "iso:country":"US",
    "sg:address":"2186 S Clarkson St",
    "sg:city":"Denver",
    "sg:classifiers":[
        {
            "category":"Manufacturing",
            "subcategory":"Printing",
            "type":"Manufacturing & Wholesale Goods"
        }
    ],
    "sg:phone":"+1 303 744 3877",
    "sg:postcode":"80210",
    "sg:province":"CO",
    "sg:tags":[
        "multimedia"
    ],
    "sg:website":"www.3dce.com",
    "wof:name":"3 Design Comms Engineering",
    "wof:placetype":"venue"
},
  "geometry": {"coordinates":[-104.978054,39.678307],"type":"Point"}
}