{
  "type": "Feature",
  "properties": {
    "addr:full":"7243 S Harrison Way Littleton CO 80122",
    "addr:housenumber":"7243",
    "addr:postcode":"80122",
    "addr:street":"S Harrison Way",
    "iso:country":"US",
    "sg:address":"7243 S Harrison Way",
    "sg:city":"Littleton",
    "sg:classifiers":[
        {
            "category":"Freight",
            "type":"Transportation"
        }
    ],
    "sg:phone":"+1 720 493 5050",
    "sg:postcode":"80122",
    "sg:province":"CO",
    "sg:tags":[
        "fixed",
        "motor",
        "facility"
    ],
    "wof:name":"Encore Home Inspecitons",
    "wof:placetype":"venue"
},
  "geometry": {"coordinates":[-104.943083,39.585847],"type":"Point"}
}