{
  "type": "Feature",
  "properties": {
    "iso:country":"US",
    "sg:address":"12170 Sand Pl",
    "sg:city":"Peyton",
    "sg:classifiers":[
        {
            "category":"Manufacturing",
            "subcategory":"Furniture",
            "type":"Manufacturing & Wholesale Goods"
        }
    ],
    "sg:phone":"+1 719 683 2479",
    "sg:postcode":"80831",
    "sg:province":"CO",
    "sg:tags":[
        "household",
        "metal",
        "mfg"
    ],
    "wof:name":"Weld O Rama Studio",
    "wof:placetype":"venue"
},
  "geometry": {"coordinates":[-104.604688,38.8952],"type":"Point"}
}