{
  "type": "Feature",
  "properties": {
    "iso:country":"US",
    "sg:address":"1233 Sherman Dr",
    "sg:city":"Longmont",
    "sg:classifiers":[
        {
            "category":"Professional",
            "subcategory":"Engineering",
            "type":"Services"
        },
        {
            "category":"Professional",
            "subcategory":"Research",
            "type":"Services"
        }
    ],
    "sg:phone":"+1 303 651 0277",
    "sg:postcode":"80501",
    "sg:province":"CO",
    "sg:tags":[
        "development",
        "i",
        "peripheral",
        "computer",
        "primarily",
        "electronic"
    ],
    "wof:name":"Mountain Engineering II Inc",
    "wof:placetype":"venue"
},
  "geometry": {"coordinates":[-105.115151,40.152875],"type":"Point"}
}