{
  "type": "Feature",
  "properties": {
    "addr:full":"110 S 25th St Colorado Springs CO 80904",
    "addr:housenumber":"110",
    "addr:postcode":"80904",
    "addr:street":"S 25Th St",
    "iso:country":"US",
    "sg:address":"110 S 25th St",
    "sg:city":"Colorado Springs",
    "sg:classifiers":[
        {
            "category":"Shopping",
            "subcategory":"Clothing, Apparel, & Fashions",
            "type":"Retail Goods"
        }
    ],
    "sg:phone":"+1 719 634 2866",
    "sg:postcode":"80904",
    "sg:province":"CO",
    "sg:tags":[
        "uniform",
        "supply"
    ],
    "wof:name":"Sno-White Linen & Uniform Rntl",
    "wof:placetype":"venue"
},
  "geometry": {"coordinates":[-104.863393,38.846595],"type":"Point"}
}