{
  "type": "Feature",
  "properties": {
    "iso:country":"US",
    "sg:address":"2520 W Colorado Ave",
    "sg:city":"Colorado Springs",
    "sg:classifiers":[
        {
            "category":"Shopping",
            "subcategory":"Gifts & Souvenirs",
            "type":"Retail Goods"
        }
    ],
    "sg:phone":"+1 719 447 8844",
    "sg:postcode":"80904",
    "sg:province":"CO",
    "sg:tags":[
        "shop"
    ],
    "wof:name":"Bernideen's",
    "wof:placetype":"venue"
},
  "geometry": {"coordinates":[-104.863823,38.84798],"type":"Point"}
}