{
  "type": "Feature",
  "properties": {
    "addr:full":"6855 S Dayton St Englewood CO 80112",
    "addr:housenumber":"6855",
    "addr:postcode":"80112",
    "addr:street":"S Dayton St",
    "iso:country":"US",
    "sg:address":"6855 S Dayton St",
    "sg:city":"Englewood",
    "sg:classifiers":[
        {
            "category":"Government",
            "subcategory":"Post Office",
            "type":"Public Place"
        }
    ],
    "sg:phone":"+1 303 000 1111",
    "sg:postcode":"80112",
    "sg:province":"CO",
    "sg:tags":[
        "postal",
        "us"
    ],
    "wof:name":"US Post Office",
    "wof:placetype":"venue"
},
  "geometry": {"coordinates":[-104.87625300000001,39.591965],"type":"Point"}
}