{
  "type": "Feature",
  "properties": {
    "addr:full":"2207 Mapleton Ave Boulder CO 80304",
    "addr:housenumber":"2207",
    "addr:postcode":"80304",
    "addr:street":"Mapleton Ave",
    "iso:country":"US",
    "sg:address":"2207 Mapleton Ave",
    "sg:city":"Boulder",
    "sg:classifiers":[
        {
            "category":"Real Estate",
            "subcategory":"Architect",
            "type":"Services"
        }
    ],
    "sg:phone":"+1 303 443 4414",
    "sg:postcode":"80304",
    "sg:province":"CO",
    "wof:name":"Montgomery Partnership",
    "wof:placetype":"venue"
},
  "geometry": {"coordinates":[-105.26667500000001,40.023927],"type":"Point"}
}