{
  "type": "Feature",
  "properties": {
    "iso:country":"US",
    "sg:address":"860 Commercial Ln",
    "sg:city":"Palmer Lake",
    "sg:classifiers":[
        {
            "category":"Shopping",
            "type":"Retail Goods"
        }
    ],
    "sg:phone":"+1 303 681 9156",
    "sg:postcode":"80133",
    "sg:province":"CO",
    "sg:tags":[
        "merchandise"
    ],
    "sg:website":"www.chiropatient.com",
    "wof:name":"Patient Media Inc",
    "wof:placetype":"venue"
},
  "geometry": {"coordinates":[-104.880518,39.102505],"type":"Point"}
}