{
  "type": "Feature",
  "properties": {
    "addr:full":"6232 S Ash Cir W Centennial CO 80121",
    "addr:housenumber":"6232",
    "addr:postcode":"80121",
    "addr:street":"S Ash Cir W",
    "iso:country":"US",
    "sg:address":"6232 S Ash Cir W",
    "sg:city":"Centennial",
    "sg:classifiers":[
        {
            "category":"Banks & Credit Unions",
            "subcategory":"Bank",
            "type":"Services"
        }
    ],
    "sg:phone":"+1 303 220 9529",
    "sg:postcode":"80121",
    "sg:province":"CO",
    "sg:tags":[
        "loan"
    ],
    "wof:name":"KDJ Financial Inc",
    "wof:placetype":"venue"
},
  "geometry": {"coordinates":[-104.939092,39.603235],"type":"Point"}
}