{
  "type": "Feature",
  "properties": {
    "addr:full":"1601 Pearl St. Suite 200 Boulder CO 80302",
    "addr:housenumber":"1601",
    "addr:postcode":"80302",
    "addr:street":"Pearl St. Suite 200",
    "iso:country":"US",
    "sg:address":"1601 Pearl St. Suite 200",
    "sg:city":"Boulder",
    "sg:classifiers":[
        {
            "category":"Professional",
            "subcategory":"Computer Services",
            "type":"Services"
        }
    ],
    "sg:phone":"+1 646 657 9837",
    "sg:postcode":"80302",
    "sg:province":"CO",
    "sg:tags":[
        "music",
        "analytics",
        "techstars09"
    ],
    "sg:website":"http://www.nextbigsound.com",
    "wof:name":"Next Big Sound",
    "wof:placetype":"venue"
},
  "geometry": {"coordinates":[-105.273428,40.019239],"type":"Point"}
}