{
  "type": "Feature",
  "properties": {
    "addr:full":"5863 Marion Dr Denver CO 80216",
    "addr:housenumber":"5863",
    "addr:postcode":"80216",
    "addr:street":"Marion Dr",
    "iso:country":"US",
    "sg:address":"5863 Marion Dr",
    "sg:city":"Denver",
    "sg:classifiers":[
        {
            "category":"Building & Trades",
            "subcategory":"Construction",
            "type":"Services"
        }
    ],
    "sg:phone":"+1 303 202 1000",
    "sg:postcode":"80216",
    "sg:province":"CO",
    "sg:tags":[
        "contractor"
    ],
    "wof:name":"Ozark Fence",
    "wof:placetype":"venue"
},
  "geometry": {"coordinates":[-104.971715,39.804332],"type":"Point"}
}