{
  "type": "Feature",
  "properties": {
    "iso:country":"US",
    "sg:address":"801 S Public Rd",
    "sg:city":"Lafayette",
    "sg:classifiers":[
        {
            "category":"Insurance",
            "subcategory":"Insurance Agent",
            "type":"Services"
        }
    ],
    "sg:phone":"+1 303 665 3304",
    "sg:postcode":"80026",
    "sg:province":"CO",
    "wof:name":"American Family Insurance",
    "wof:placetype":"venue"
},
  "geometry": {"coordinates":[-105.09056099999999,39.992119],"type":"Point"}
}