{
  "type": "Feature",
  "properties": {
    "iso:country":"US",
    "sg:address":"3121 Cherryridge Rd",
    "sg:city":"Englewood",
    "sg:classifiers":[
        {
            "category":"Mining & Drilling",
            "type":"Manufacturing & Wholesale Goods"
        }
    ],
    "sg:phone":"+1 303 761 9965",
    "sg:postcode":"80113",
    "sg:province":"CO",
    "sg:tags":[
        "crude",
        "production",
        "gas"
    ],
    "wof:name":"Wildrose Resources Corporation",
    "wof:placetype":"venue"
},
  "geometry": {"coordinates":[-104.953383,39.634391],"type":"Point"}
}