{
  "type": "Feature",
  "properties": {
    "iso:country":"US",
    "sg:address":"444 S Emerson St",
    "sg:city":"Denver",
    "sg:classifiers":[
        {
            "category":"Manufacturing",
            "subcategory":"Printing",
            "type":"Manufacturing & Wholesale Goods"
        }
    ],
    "sg:phone":"+1 303 722 0308",
    "sg:postcode":"80209",
    "sg:province":"CO",
    "sg:tags":[
        "publishing",
        "business"
    ],
    "wof:name":"National Drctry of Prcss Srvrs",
    "wof:placetype":"venue"
},
  "geometry": {"coordinates":[-104.97681300000001,39.708293],"type":"Point"}
}