{
  "type": "Feature",
  "properties": {
    "addr:full":"1609 Jefferson Ave Louisville CO 80027",
    "addr:housenumber":"1609",
    "addr:postcode":"80027",
    "addr:street":"Jefferson Ave",
    "iso:country":"US",
    "sg:address":"1609 Jefferson Ave",
    "sg:city":"Louisville",
    "sg:classifiers":[
        {
            "category":"Personal",
            "type":"Services"
        }
    ],
    "sg:phone":"+1 303 543 7616",
    "sg:postcode":"80027",
    "sg:province":"CO",
    "sg:tags":[
        "therapist",
        "massage"
    ],
    "sg:website":"www.tenaska.com",
    "wof:name":"Seeing Hands Therapeutic Mssg",
    "wof:placetype":"venue"
},
  "geometry": {"coordinates":[-105.134928,39.986881],"type":"Point"}
}