{
  "type": "Feature",
  "properties": {
    "addr:full":"1221 E Elizabeth St Fort Collins CO 80524",
    "addr:housenumber":"1221",
    "addr:postcode":"80524",
    "addr:street":"E Elizabeth St",
    "iso:country":"US",
    "sg:address":"1221 E Elizabeth St",
    "sg:city":"Fort Collins",
    "sg:classifiers":[
        {
            "category":"Health Services",
            "subcategory":"Medical Lab",
            "type":"Services"
        }
    ],
    "sg:phone":"+1 970 221 2467",
    "sg:postcode":"80524",
    "sg:province":"CO",
    "sg:tags":[
        "laboratory"
    ],
    "wof:name":"LCAI",
    "wof:placetype":"venue"
},
  "geometry": {"coordinates":[-105.054396,40.574217],"type":"Point"}
}