{
  "type": "Feature",
  "properties": {
    "iso:country":"US",
    "sg:address":"1630 Delta Rd",
    "sg:city":"Colorado Springs",
    "sg:classifiers":[
        {
            "category":"Real Estate",
            "subcategory":"Real Estate Agent",
            "type":"Services"
        }
    ],
    "sg:phone":"+1 719 331 7402",
    "sg:postcode":"80920",
    "sg:province":"CO",
    "sg:tags":[
        "inspection"
    ],
    "wof:name":"Attic To Basement Home Inspctn",
    "wof:placetype":"venue"
},
  "geometry": {"coordinates":[-104.796953,38.975395],"type":"Point"}
}