{
  "type": "Feature",
  "properties": {
    "addr:full":"1523 N Chelton Rd Colorado Springs CO 80909",
    "addr:housenumber":"1523",
    "addr:postcode":"80909",
    "addr:street":"N Chelton Rd",
    "iso:country":"US",
    "sg:address":"1523 N Chelton Rd",
    "sg:city":"Colorado Springs",
    "sg:classifiers":[
        {
            "category":"Retail",
            "subcategory":"Laundry & Dry Cleaning",
            "type":"Services"
        }
    ],
    "sg:phone":"+1 719 447 1007",
    "sg:postcode":"80909",
    "sg:province":"CO",
    "sg:tags":[
        "cleaners",
        "rug",
        "carpet"
    ],
    "wof:name":"Mountain Fresh Carpet Care",
    "wof:placetype":"venue"
},
  "geometry": {"coordinates":[-104.765326,38.858149],"type":"Point"}
}