{
  "type": "Feature",
  "properties": {
    "addr:full":"13875 Dogleg Ln Broomfield CO 80023",
    "addr:postcode":"13875;80023",
    "addr:street":"Dogleg Ln",
    "iso:country":"US",
    "sg:address":"13875 Dogleg Ln",
    "sg:city":"Broomfield",
    "sg:classifiers":[
        {
            "category":"Professional",
            "type":"Services"
        }
    ],
    "sg:phone":"+1 303 464 9469",
    "sg:postcode":"80023",
    "sg:province":"CO",
    "wof:name":"Robert Kelso",
    "wof:placetype":"venue"
},
  "geometry": {"coordinates":[-105.03632500000001,39.948388],"type":"Point"}
}