{
  "type": "Feature",
  "properties": {
    "addr:full":"1123 E Phipps Ct Littleton CO 80126",
    "addr:housenumber":"1123",
    "addr:postcode":"80126",
    "addr:street":"E Phipps Ct",
    "iso:country":"US",
    "sg:address":"1123 E Phipps Ct",
    "sg:city":"Littleton",
    "sg:classifiers":[
        {
            "category":"Professional",
            "type":"Services"
        }
    ],
    "sg:phone":"+1 303 925 0542",
    "sg:postcode":"80126",
    "sg:province":"CO",
    "wof:name":"Valle Grande Resources LLC",
    "wof:placetype":"venue"
},
  "geometry": {"coordinates":[-104.975494,39.535282],"type":"Point"}
}