{
  "type": "Feature",
  "properties": {
    "addr:full":"3895 N River Rd Palisade CO 81526",
    "addr:housenumber":"3895",
    "addr:postcode":"81526",
    "addr:street":"N River Rd",
    "iso:country":"US",
    "sg:address":"3895 N River Rd",
    "sg:city":"Palisade",
    "sg:classifiers":[
        {
            "category":"Wholesale",
            "subcategory":"Plants",
            "type":"Manufacturing & Wholesale Goods"
        },
        {
            "category":"Farming",
            "subcategory":"Nursery",
            "type":"Manufacturing & Wholesale Goods"
        }
    ],
    "sg:phone":"+1 970 464 7485",
    "sg:postcode":"81526",
    "sg:province":"CO",
    "sg:tags":[
        "supp",
        "ornamental",
        "tree"
    ],
    "sg:website":"www.palisadegreenhouse.com",
    "wof:name":"Palisade Greenhouse Inc",
    "wof:placetype":"venue"
},
  "geometry": {"coordinates":[-108.33221500000001,39.115195],"type":"Point"}
}