{
  "type": "Feature",
  "properties": {
    "addr:full":"1106 13th St Boulder CO 80302",
    "addr:housenumber":"1106",
    "addr:postcode":"80302",
    "addr:street":"13Th St",
    "iso:country":"US",
    "sg:address":"1106 13th St",
    "sg:city":"Boulder",
    "sg:classifiers":[
        {
            "category":"Shopping",
            "subcategory":"Clothing, Apparel, & Fashions",
            "type":"Retail Goods"
        }
    ],
    "sg:phone":"+1 303 442 2540",
    "sg:postcode":"80302",
    "sg:province":"CO",
    "sg:tags":[
        "alteration"
    ],
    "wof:name":"Budget Alteration & Tailoring",
    "wof:placetype":"venue"
},
  "geometry": {"coordinates":[-105.27618099999999,40.007815],"type":"Point"}
}