{
  "type": "Feature",
  "properties": {
    "addr:full":"45 Union Blvd Denver CO 80228",
    "addr:housenumber":"45",
    "addr:postcode":"80228",
    "addr:street":"Union Blvd",
    "iso:country":"US",
    "sg:address":"45 Union Blvd",
    "sg:city":"Denver",
    "sg:classifiers":[
        {
            "category":"Restaurant",
            "type":"Food & Drink"
        }
    ],
    "sg:menulink":"http://www.allmenus.com/co/northeast-jefferson/74896-pizza-hut/menu/",
    "sg:phone":"+1 303 989 9598",
    "sg:postcode":"80228",
    "sg:province":"CO",
    "sg:tags":[
        "american",
        "pizza"
    ],
    "wof:name":"Pizza Hut",
    "wof:placetype":"venue"
},
  "geometry": {"coordinates":[-105.13378400000001,39.715297],"type":"Point"}
}