{
  "type": "Feature",
  "properties": {
    "addr:full":"2247 Kearney St Denver CO 80207",
    "addr:housenumber":"2247",
    "addr:postcode":"80207",
    "addr:street":"Kearney St",
    "iso:country":"US",
    "sg:address":"2247 Kearney St",
    "sg:city":"Denver",
    "sg:classifiers":[
        {
            "category":"Arena",
            "subcategory":"Sports Club",
            "type":"Entertainment"
        }
    ],
    "sg:phone":"+1 303 399 5858",
    "sg:postcode":"80207",
    "sg:province":"CO",
    "sg:tags":[
        "soccer"
    ],
    "wof:name":"Denver Soccer Club",
    "wof:placetype":"venue"
},
  "geometry": {"coordinates":[-104.917626,39.750228],"type":"Point"}
}