{
  "type": "Feature",
  "properties": {
    "addr:full":"10973 Simms St Broomfield CO 80021",
    "addr:housenumber":"10973",
    "addr:postcode":"80021",
    "addr:street":"Simms St",
    "iso:country":"US",
    "sg:address":"10973 Simms St",
    "sg:city":"Broomfield",
    "sg:classifiers":[
        {
            "category":"Building & Trades",
            "subcategory":"Locksmith",
            "type":"Services"
        }
    ],
    "sg:phone":"+1 720 890 8798",
    "sg:postcode":"80021",
    "sg:province":"CO",
    "sg:tags":[
        "lock",
        "industrial",
        "locksmiths-commercial"
    ],
    "wof:name":"0 O Emergency Locksmith",
    "wof:placetype":"venue"
},
  "geometry": {"coordinates":[-105.12867199999999,39.895817],"type":"Point"}
}