{
  "type": "Feature",
  "properties": {
    "addr:full":"5273 W 64th Ave Arvada CO 80003",
    "addr:housenumber":"5273",
    "addr:postcode":"80003",
    "addr:street":"W 64Th Ave",
    "iso:country":"US",
    "sg:address":"5273 W 64th Ave",
    "sg:city":"Arvada",
    "sg:classifiers":[
        {
            "category":"Personal",
            "subcategory":"Beauty Salon",
            "type":"Services"
        }
    ],
    "sg:phone":"+1 303 940 9937",
    "sg:postcode":"80003",
    "sg:province":"CO",
    "sg:tags":[
        "manicuring"
    ],
    "wof:name":"Fashion Nail",
    "wof:placetype":"venue"
},
  "geometry": {"coordinates":[-105.054963,39.812862],"type":"Point"}
}