{
  "type": "Feature",
  "properties": {
    "iso:country":"US",
    "sg:address":"5085 Umatilla St",
    "sg:city":"Denver",
    "sg:classifiers":[
        {
            "category":"Autos & Motor Vehicles",
            "subcategory":"Motorcycle Sales",
            "type":"Retail Goods"
        }
    ],
    "sg:phone":"+1 303 736 2418",
    "sg:postcode":"80221",
    "sg:province":"CO",
    "wof:name":"Pig Pen Industries",
    "wof:placetype":"venue"
},
  "geometry": {"coordinates":[-105.012521,39.788967],"type":"Point"}
}