{
  "type": "Feature",
  "properties": {
    "iso:country":"US",
    "sg:address":"8205 S Holly St",
    "sg:city":"Centennial",
    "sg:classifiers":[
        {
            "category":"Retail",
            "subcategory":"Veterinary Services",
            "type":"Services"
        }
    ],
    "sg:phone":"+1 303 779 5525",
    "sg:postcode":"80122",
    "sg:province":"CO",
    "sg:tags":[
        "veterinarian"
    ],
    "wof:name":"Companion Animal Veterinary",
    "wof:placetype":"venue"
},
  "geometry": {"coordinates":[-104.922828,39.566161],"type":"Point"}
}