{
  "type": "Feature",
  "properties": {
    "iso:country":"US",
    "sg:address":"2925 W 13th St",
    "sg:city":"Greeley",
    "sg:classifiers":[
        {
            "category":"Shopping",
            "type":"Retail Goods"
        }
    ],
    "sg:phone":"+1 970 353 1010",
    "sg:postcode":"80634",
    "sg:province":"CO",
    "sg:tags":[
        "cosmetic",
        "perfume"
    ],
    "wof:name":"Mary Kay Cosmetics",
    "wof:placetype":"venue"
},
  "geometry": {"coordinates":[-104.726506,40.418379],"type":"Point"}
}