{
  "type": "Feature",
  "properties": {
    "iso:country":"US",
    "sg:address":"5315 W Mississippi Ave",
    "sg:city":"Denver",
    "sg:classifiers":[
        {
            "category":"Building & Trades",
            "subcategory":"Pest Control",
            "type":"Services"
        }
    ],
    "sg:phone":"+1 303 975 4300",
    "sg:postcode":"80226",
    "sg:province":"CO",
    "wof:name":"Wash Park Care",
    "wof:placetype":"venue"
},
  "geometry": {"coordinates":[-105.057028,39.696853],"type":"Point"}
}