{
  "type": "Feature",
  "properties": {
    "iso:country":"US",
    "sg:address":"300 S Jackson St Suite 570",
    "sg:city":"Denver",
    "sg:classifiers":[
        {
            "category":"Professional",
            "subcategory":"Lawyer & Legal Services",
            "type":"Services"
        }
    ],
    "sg:phone":"+1 720 880 5088",
    "sg:postcode":"80209",
    "sg:province":"CO",
    "sg:tags":[
        "divorce",
        "law",
        "family"
    ],
    "sg:website":"www.denverfamilies.com",
    "wof:name":"Johnson Sauer Legal Group",
    "wof:placetype":"venue"
},
  "geometry": {"coordinates":[-104.942194,39.710968],"type":"Point"}
}