{
  "type": "Feature",
  "properties": {
    "iso:country":"US",
    "sg:address":"930 Duke St",
    "sg:city":"Trinidad",
    "sg:classifiers":[
        {
            "category":"Home & Garden",
            "subcategory":"Building Materials",
            "type":"Retail Goods"
        }
    ],
    "sg:phone":"+1 719 846 1511",
    "sg:postcode":"81082",
    "sg:province":"CO",
    "sg:tags":[
        "glass",
        "window",
        "plate"
    ],
    "wof:name":"Startek II Mobile Windshield",
    "wof:placetype":"venue"
},
  "geometry": {"coordinates":[-104.520825,37.172261],"type":"Point"}
}