{
  "type": "Feature",
  "properties": {
    "addr:full":"264 Fulford Dr Eagle CO 81631",
    "addr:housenumber":"264",
    "addr:postcode":"81631",
    "addr:street":"Fulford Dr",
    "iso:country":"US",
    "sg:address":"264 Fulford Dr",
    "sg:city":"Eagle",
    "sg:classifiers":[
        {
            "category":"Home & Garden",
            "subcategory":"Home Furnishings",
            "type":"Retail Goods"
        }
    ],
    "sg:phone":"+1 970 328 7112",
    "sg:postcode":"81631",
    "sg:province":"CO",
    "sg:tags":[
        "beveled",
        "glass",
        "ornamental"
    ],
    "wof:name":"Jacklyn Enterprises Inc",
    "wof:placetype":"venue"
},
  "geometry": {"coordinates":[-106.810456,39.649757],"type":"Point"}
}