{
  "type": "Feature",
  "properties": {
    "addr:full":"142 1st St Frederick CO 80530",
    "addr:housenumber":"142",
    "addr:postcode":"80530",
    "addr:street":"1St St",
    "iso:country":"US",
    "sg:address":"142 1st St",
    "sg:city":"Frederick",
    "sg:classifiers":[
        {
            "category":"Personal",
            "type":"Services"
        }
    ],
    "sg:phone":"+1 303 833 6680",
    "sg:postcode":"80530",
    "sg:province":"CO",
    "sg:tags":[
        "therapist",
        "massage"
    ],
    "wof:name":"Heeling Hands",
    "wof:placetype":"venue"
},
  "geometry": {"coordinates":[-104.94115600000001,40.102172],"type":"Point"}
}