{
  "type": "Feature",
  "properties": {
    "addr:full":"3535 S Lafayette St Englewood CO 80113",
    "addr:housenumber":"3535",
    "addr:postcode":"80113",
    "addr:street":"S Lafayette St",
    "iso:country":"US",
    "sg:address":"3535 S Lafayette St",
    "sg:city":"Englewood",
    "sg:classifiers":[
        {
            "category":"Health Services",
            "subcategory":"Health Practitioner",
            "type":"Services"
        }
    ],
    "sg:phone":"+1 303 996 0389",
    "sg:postcode":"80113",
    "sg:province":"CO",
    "sg:tags":[
        "therapist",
        "physical"
    ],
    "wof:name":"Back To Motion",
    "wof:placetype":"venue"
},
  "geometry": {"coordinates":[-104.97124700000001,39.652162],"type":"Point"}
}