{
  "type": "Feature",
  "properties": {
    "iso:country":"US",
    "sg:address":"19660 E Dove Creek Pl",
    "sg:city":"Parker",
    "sg:classifiers":[
        {
            "category":"Building & Trades",
            "subcategory":"Plumbing",
            "type":"Services"
        }
    ],
    "sg:phone":"+1 303 840 7594",
    "sg:postcode":"80134",
    "sg:province":"CO",
    "sg:tags":[
        "contractor"
    ],
    "wof:name":"Trademaster Plumbing",
    "wof:placetype":"venue"
},
  "geometry": {"coordinates":[-104.759992,39.486815],"type":"Point"}
}