{
  "type": "Feature",
  "properties": {
    "addr:full":"14100 E Jewell Ave Aurora CO 80012",
    "addr:housenumber":"14100",
    "addr:postcode":"80012",
    "addr:street":"E Jewell Ave",
    "iso:country":"US",
    "sg:address":"14100 E Jewell Ave",
    "sg:city":"Aurora",
    "sg:classifiers":[
        {
            "category":"Health Services",
            "subcategory":"Health Practitioner",
            "type":"Services"
        }
    ],
    "sg:phone":"+1 303 337 7866",
    "sg:postcode":"80012",
    "sg:province":"CO",
    "wof:name":"Theraphysics Partners of Colo",
    "wof:placetype":"venue"
},
  "geometry": {"coordinates":[-104.82149099999999,39.682098],"type":"Point"}
}