{
  "type": "Feature",
  "properties": {
    "iso:country":"US",
    "sg:address":"2300 15th St",
    "sg:city":"Denver",
    "sg:classifiers":[
        {
            "category":"Real Estate",
            "subcategory":"Real Estate Operator",
            "type":"Services"
        }
    ],
    "sg:phone":"+1 303 458 5457",
    "sg:postcode":"80202",
    "sg:province":"CO",
    "sg:tags":[
        "building",
        "parks",
        "nonresidential"
    ],
    "wof:name":"Riverpoint Building",
    "wof:placetype":"venue"
},
  "geometry": {"coordinates":[-105.00771899999999,39.755264],"type":"Point"}
}