{
  "type": "Feature",
  "properties": {
    "iso:country":"US",
    "sg:address":"1526 Cole Boulevard",
    "sg:city":"Lakewood",
    "sg:classifiers":[
        {
            "category":"Professional",
            "subcategory":"Computer Services",
            "type":"Services"
        }
    ],
    "sg:phone":"+1 800 228 2554",
    "sg:postcode":"80401",
    "sg:province":"CO",
    "sg:tags":[
        "conferencing",
        "video-conferencing",
        "audio-conferencing",
        "web-conferencing",
        "conference-calls"
    ],
    "sg:website":"http://www.actconferencing.com",
    "wof:name":"ACT Conferencing",
    "wof:placetype":"venue"
},
  "geometry": {"coordinates":[-105.155984,39.740549],"type":"Point"}
}