{
  "type": "Feature",
  "properties": {
    "iso:country":"US",
    "sg:address":"4414 Martindale Ave",
    "sg:city":"Cascade",
    "sg:classifiers":[
        {
            "category":"Wholesale",
            "subcategory":"Drugs",
            "type":"Manufacturing & Wholesale Goods"
        }
    ],
    "sg:phone":"+1 970 626 4363",
    "sg:postcode":"80809",
    "sg:province":"CO",
    "sg:tags":[
        "skin",
        "product",
        "supplement",
        "health",
        "care"
    ],
    "wof:name":"Shankara Inc",
    "wof:placetype":"venue"
},
  "geometry": {"coordinates":[-104.974127,38.896573],"type":"Point"}
}