{
  "type": "Feature",
  "properties": {
    "iso:country":"US",
    "sg:address":"12558 Meridian Rd",
    "sg:city":"Elbert",
    "sg:classifiers":[
        {
            "category":"Home & Garden",
            "subcategory":"Hardware",
            "type":"Retail Goods"
        }
    ],
    "sg:phone":"+1 719 495 4747",
    "sg:postcode":"80106",
    "sg:province":"CO",
    "sg:tags":[
        "saw"
    ],
    "wof:name":"Ayer's Saw Shop",
    "wof:placetype":"venue"
},
  "geometry": {"coordinates":[-104.607643,39.015816],"type":"Point"}
}