{
  "type": "Feature",
  "properties": {
    "addr:full":"1059 North Ave Grand Junction CO 81501",
    "addr:housenumber":"1059",
    "addr:postcode":"81501",
    "addr:street":"North Ave",
    "iso:country":"US",
    "sg:address":"1059 North Ave",
    "sg:city":"Grand Junction",
    "sg:classifiers":[
        {
            "category":"Professional",
            "type":"Services"
        }
    ],
    "sg:phone":"+1 970 263 0273",
    "sg:postcode":"81501",
    "sg:province":"CO",
    "sg:tags":[
        "establishment"
    ],
    "wof:name":"Democratic Congressional",
    "wof:placetype":"venue"
},
  "geometry": {"coordinates":[-108.55569199999999,39.077324],"type":"Point"}
}