{
  "type": "Feature",
  "properties": {
    "iso:country":"US",
    "sg:address":"501 E Iowa Ave",
    "sg:city":"Fountain",
    "sg:classifiers":[
        {
            "category":"Real Estate",
            "subcategory":"Real Estate Agent",
            "type":"Services"
        }
    ],
    "sg:phone":"+1 719 382 5639",
    "sg:postcode":"80817",
    "sg:province":"CO",
    "sg:tags":[
        "authorities",
        "housing"
    ],
    "wof:name":"Fountain Housing Authority",
    "wof:placetype":"venue"
},
  "geometry": {"coordinates":[-104.695503,38.683932],"type":"Point"}
}