{
  "type": "Feature",
  "properties": {
    "addr:full":"14215 Mead St Longmont CO 80504",
    "addr:housenumber":"14215",
    "addr:postcode":"80504",
    "addr:street":"Mead St",
    "iso:country":"US",
    "sg:address":"14215 Mead St",
    "sg:city":"Longmont",
    "sg:classifiers":[
        {
            "category":"Professional",
            "type":"Services"
        }
    ],
    "sg:phone":"+1 303 893 4338",
    "sg:postcode":"80504",
    "sg:province":"CO",
    "wof:name":"Wellstar Corp",
    "wof:placetype":"venue"
},
  "geometry": {"coordinates":[-104.97455100000001,40.207444],"type":"Point"}
}