{
  "type": "Feature",
  "properties": {
    "iso:country":"US",
    "sg:address":"18998 Co Rd 18",
    "sg:city":"Sanford",
    "sg:classifiers":[
        {
            "category":"Freight",
            "type":"Transportation"
        }
    ],
    "sg:phone":"+1 719 274 0116",
    "sg:postcode":"81151",
    "sg:province":"CO",
    "sg:tags":[
        "operator",
        "trucking"
    ],
    "wof:name":"Gary G Hensley",
    "wof:placetype":"venue"
},
  "geometry": {"coordinates":[-105.928265,37.268218],"type":"Point"}
}