{
  "type": "Feature",
  "properties": {
    "addr:full":"2044 Clinton St Aurora CO 80010",
    "addr:housenumber":"2044",
    "addr:postcode":"80010",
    "addr:street":"Clinton St",
    "iso:country":"US",
    "sg:address":"2044 Clinton St",
    "sg:city":"Aurora",
    "sg:classifiers":[
        {
            "category":"Restaurant",
            "type":"Food & Drink"
        }
    ],
    "sg:phone":"+1 303 343 4715",
    "sg:postcode":"80010",
    "sg:province":"CO",
    "sg:tags":[
        "eating"
    ],
    "wof:name":"Afrikiko Restaurant",
    "wof:placetype":"venue"
},
  "geometry": {"coordinates":[-104.877493,39.748866],"type":"Point"}
}