{
  "type": "Feature",
  "properties": {
    "iso:country":"US",
    "sg:address":"13821 Sable Blvd",
    "sg:city":"Brighton",
    "sg:classifiers":[
        {
            "category":"Manufacturing",
            "subcategory":"Retail Goods",
            "type":"Manufacturing & Wholesale Goods"
        }
    ],
    "sg:phone":"+1 303 659 0681",
    "sg:postcode":"80601",
    "sg:province":"CO",
    "sg:tags":[
        "marker",
        "mfg",
        "plastic"
    ],
    "sg:website":"www.ritcheytags.com",
    "wof:name":"Ritchey Manufacturing Co",
    "wof:placetype":"venue"
},
  "geometry": {"coordinates":[-104.818359,39.944203],"type":"Point"}
}