{
  "type": "Feature",
  "properties": {
    "addr:full":"1537 Platte St Denver CO 80202",
    "addr:housenumber":"1537",
    "addr:postcode":"80202",
    "addr:street":"Platte St",
    "iso:country":"US",
    "sg:address":"1537 Platte St",
    "sg:city":"Denver",
    "sg:classifiers":[
        {
            "category":"Food & Beverages",
            "subcategory":"Specialty",
            "type":"Retail Goods"
        }
    ],
    "sg:phone":"+1 303 477 3322",
    "sg:postcode":"80202",
    "sg:province":"CO",
    "sg:tags":[
        "spice"
    ],
    "sg:website":"www.savoryspiceshop.com",
    "wof:name":"Savory Spice Shop",
    "wof:placetype":"venue"
},
  "geometry": {"coordinates":[-105.00874899999999,39.757212],"type":"Point"}
}