{
  "type": "Feature",
  "properties": {
    "iso:country":"US",
    "sg:address":"101 N 4th St",
    "sg:city":"Lamar",
    "sg:classifiers":[
        {
            "category":"Food & Beverages",
            "subcategory":"Specialty",
            "type":"Retail Goods"
        }
    ],
    "sg:phone":"+1 719 336 4001",
    "sg:postcode":"81052",
    "sg:province":"CO",
    "sg:tags":[
        "health"
    ],
    "wof:name":"Marples Country Market",
    "wof:placetype":"venue"
},
  "geometry": {"coordinates":[-102.61809599999999,38.09137],"type":"Point"}
}