{
  "type": "Feature",
  "properties": {
    "addr:full":"6138 US Hwy 287 Laporte CO 80535",
    "addr:housenumber":"6138",
    "addr:postcode":"80535",
    "addr:street":"Us Hwy 287",
    "iso:country":"US",
    "sg:address":"6138 US Hwy 287",
    "sg:city":"Laporte",
    "sg:classifiers":[
        {
            "category":"Building & Trades",
            "subcategory":"Construction",
            "type":"Services"
        }
    ],
    "sg:phone":"+1 970 419 8487",
    "sg:postcode":"80535",
    "sg:province":"CO",
    "sg:tags":[
        "house"
    ],
    "wof:name":"Hardy Reichert Homes & Decor",
    "wof:placetype":"venue"
},
  "geometry": {"coordinates":[-105.188554,40.663685],"type":"Point"}
}