{
  "type": "Feature",
  "properties": {
    "addr:full":"11528 Pine Grove Ln Parker CO 80138",
    "addr:housenumber":"11528",
    "addr:postcode":"80138",
    "addr:street":"Pine Grove Ln",
    "iso:country":"US",
    "sg:address":"11528 Pine Grove Ln",
    "sg:city":"Parker",
    "sg:classifiers":[
        {
            "category":"Building & Trades",
            "subcategory":"Construction",
            "type":"Services"
        }
    ],
    "sg:phone":"+1 303 840 0931",
    "sg:postcode":"80138",
    "sg:province":"CO",
    "sg:tags":[
        "concrete",
        "contractor"
    ],
    "wof:name":"P C Construction",
    "wof:placetype":"venue"
},
  "geometry": {"coordinates":[-104.748707,39.503443],"type":"Point"}
}