{
  "type": "Feature",
  "properties": {
    "iso:country":"US",
    "sg:address":"14101 E Evans Ave",
    "sg:city":"Aurora",
    "sg:classifiers":[
        {
            "category":"Restaurant",
            "type":"Food & Drink"
        }
    ],
    "sg:menulink":"http://www.allmenus.com/co/south-aurora/53716-shinjuku/menu/",
    "sg:phone":"+1 303 750 7979",
    "sg:postcode":"80014",
    "sg:province":"CO",
    "sg:tags":[
        "japanese",
        "asian"
    ],
    "wof:name":"Shinjuku",
    "wof:placetype":"venue"
},
  "geometry": {"coordinates":[-104.822445,39.679825],"type":"Point"}
}