{
  "type": "Feature",
  "properties": {
    "iso:country":"US",
    "sg:address":"8418 Princeton St",
    "sg:city":"Westminster",
    "sg:classifiers":[
        {
            "category":"Professional",
            "subcategory":"Management & Consulting",
            "type":"Services"
        }
    ],
    "sg:phone":"+1 303 429 3377",
    "sg:postcode":"80031",
    "sg:province":"CO",
    "sg:tags":[
        "retail",
        "direct",
        "sales"
    ],
    "wof:name":"Parties By Design",
    "wof:placetype":"venue"
},
  "geometry": {"coordinates":[-105.043815,39.851354],"type":"Point"}
}