{
  "type": "Feature",
  "properties": {
    "addr:full":"3600 Mitchell Dr Fort Collins CO 80525",
    "addr:housenumber":"3600",
    "addr:postcode":"80525",
    "addr:street":"Mitchell Dr",
    "iso:country":"US",
    "sg:address":"3600 Mitchell Dr",
    "sg:city":"Fort Collins",
    "sg:classifiers":[
        {
            "category":"Home & Garden",
            "subcategory":"Carpets & Floor Coverings",
            "type":"Retail Goods"
        }
    ],
    "sg:phone":"+1 970 266 2684",
    "sg:postcode":"80525",
    "sg:province":"CO",
    "sg:tags":[
        "con"
    ],
    "wof:name":"Floor Store In Fort Collins",
    "wof:placetype":"venue"
},
  "geometry": {"coordinates":[-105.075542,40.538084],"type":"Point"}
}