{
  "type": "Feature",
  "properties": {
    "addr:full":"3650 S Federal Blvd Englewood CO 80110",
    "addr:housenumber":"3650",
    "addr:postcode":"80110",
    "addr:street":"S Federal Blvd",
    "iso:country":"US",
    "sg:address":"3650 S Federal Blvd",
    "sg:city":"Englewood",
    "sg:classifiers":[
        {
            "category":"Building & Trades",
            "subcategory":"Construction",
            "type":"Services"
        }
    ],
    "sg:phone":"+1 303 762 9517",
    "sg:postcode":"80110",
    "sg:province":"CO",
    "sg:tags":[
        "carpentry",
        "contractor"
    ],
    "wof:name":"Skb Enterprises",
    "wof:placetype":"venue"
},
  "geometry": {"coordinates":[-105.02522,39.650301],"type":"Point"}
}