{
  "type": "Feature",
  "properties": {
    "iso:country":"US",
    "sg:address":"9515 Sorrel Rd",
    "sg:city":"Castle Rock",
    "sg:classifiers":[
        {
            "category":"Manufacturing",
            "subcategory":"Toys & Sporting Goods",
            "type":"Manufacturing & Wholesale Goods"
        }
    ],
    "sg:phone":"+1 303 882 3581",
    "sg:postcode":"80108",
    "sg:province":"CO",
    "sg:tags":[
        "mfg"
    ],
    "wof:name":"Eva Loeffler",
    "wof:placetype":"venue"
},
  "geometry": {"coordinates":[-104.883763,39.49998],"type":"Point"}
}