{
  "type": "Feature",
  "properties": {
    "addr:full":"13201 W 43rd Dr Golden CO 80403",
    "addr:housenumber":"13201",
    "addr:postcode":"80403",
    "addr:street":"W 43Rd Dr",
    "iso:country":"US",
    "sg:address":"13201 W 43rd Dr",
    "sg:city":"Golden",
    "sg:classifiers":[
        {
            "category":"Retail",
            "subcategory":"Car Wash",
            "type":"Services"
        }
    ],
    "sg:phone":"+1 303 279 1933",
    "sg:postcode":"80403",
    "sg:province":"CO",
    "sg:tags":[
        "automobile",
        "detail",
        "clean"
    ],
    "sg:website":"www.eddiesautodetailing.com",
    "wof:name":"Eddie's Auto Detailing",
    "wof:placetype":"venue"
},
  "geometry": {"coordinates":[-105.150509,39.776012],"type":"Point"}
}