{
  "type": "Feature",
  "properties": {
    "iso:country":"US",
    "sg:address":"1544 Race St",
    "sg:city":"Denver",
    "sg:classifiers":[
        {
            "category":"Professional",
            "subcategory":"Lawyer & Legal Services",
            "type":"Services"
        }
    ],
    "sg:phone":"+1 303 831 0707",
    "sg:postcode":"80206",
    "sg:province":"CO",
    "wof:name":"Sussman Ann L Atty",
    "wof:placetype":"venue"
},
  "geometry": {"coordinates":[-104.962997,39.7407],"type":"Point"}
}