{
  "type": "Feature",
  "properties": {
    "iso:country":"US",
    "sg:address":"6221 S Santa Fe Dr",
    "sg:city":"Littleton",
    "sg:classifiers":[
        {
            "category":"Recreation",
            "type":"Entertainment"
        }
    ],
    "sg:phone":"+1 303 795 3474",
    "sg:postcode":"80120",
    "sg:province":"CO",
    "wof:name":"Bobby Hix Guide Service",
    "wof:placetype":"venue"
},
  "geometry": {"coordinates":[-105.020228,39.602884],"type":"Point"}
}