{
  "type": "Feature",
  "properties": {
    "iso:country":"US",
    "sg:address":"3631 N Stone Ave",
    "sg:city":"Colorado Springs",
    "sg:classifiers":[
        {
            "category":"Manufacturing",
            "subcategory":"Tools & Machinery",
            "type":"Manufacturing & Wholesale Goods"
        }
    ],
    "sg:phone":"+1 719 578 8893",
    "sg:postcode":"80907",
    "sg:province":"CO",
    "sg:tags":[
        "optical"
    ],
    "sg:website":"www.magnisight.com",
    "wof:name":"Magnisight Inc",
    "wof:placetype":"venue"
},
  "geometry": {"coordinates":[-104.815825,38.882452],"type":"Point"}
}