{
  "type": "Feature",
  "properties": {
    "addr:full":"641 Columbine Ave Estes Park CO 80517",
    "addr:housenumber":"641",
    "addr:postcode":"80517",
    "addr:street":"Columbine Ave",
    "iso:country":"US",
    "sg:address":"641 Columbine Ave",
    "sg:city":"Estes Park",
    "sg:classifiers":[
        {
            "category":"Professional",
            "type":"Services"
        }
    ],
    "sg:phone":"+1 970 586 3905",
    "sg:postcode":"80517",
    "sg:province":"CO",
    "sg:tags":[
        "establishment"
    ],
    "wof:name":"Forget Me Not Adventures",
    "wof:placetype":"venue"
},
  "geometry": {"coordinates":[-105.51196299999999,40.367934],"type":"Point"}
}