{
  "type": "Feature",
  "properties": {
    "iso:country":"US",
    "sg:address":"31017 Old Sopris Rd",
    "sg:city":"Trinidad",
    "sg:classifiers":[
        {
            "category":"Wholesale",
            "subcategory":"Durable Goods & Equipment",
            "type":"Manufacturing & Wholesale Goods"
        }
    ],
    "sg:phone":"+1 719 845 1900",
    "sg:postcode":"81082",
    "sg:province":"CO",
    "sg:tags":[
        "representative",
        "manufacturer"
    ],
    "wof:name":"TMA",
    "wof:placetype":"venue"
},
  "geometry": {"coordinates":[-104.537933,37.126404],"type":"Point"}
}