{
  "type": "Feature",
  "properties": {
    "iso:country":"US",
    "sg:address":"6610 S Broadway",
    "sg:city":"Centennial",
    "sg:classifiers":[
        {
            "category":"Professional",
            "type":"Services"
        }
    ],
    "sg:phone":"+1 303 794 2117",
    "sg:postcode":"80121",
    "sg:province":"CO",
    "sg:tags":[
        "establishment"
    ],
    "wof:name":"Wagner & Metzger",
    "wof:placetype":"venue"
},
  "geometry": {"coordinates":[-104.98821,39.595294],"type":"Point"}
}