{
  "type": "Feature",
  "properties": {
    "addr:full":"728 E 26th Ave Denver CO 80205",
    "addr:housenumber":"728",
    "addr:postcode":"80205",
    "addr:street":"E 26Th Ave",
    "iso:country":"US",
    "sg:address":"728 E 26th Ave",
    "sg:city":"Denver",
    "sg:classifiers":[
        {
            "category":"Retail",
            "subcategory":"Auto Repair",
            "type":"Services"
        }
    ],
    "sg:phone":"+1 303 831 9479",
    "sg:postcode":"80205",
    "sg:province":"CO",
    "sg:tags":[
        "repairing",
        "automobile"
    ],
    "wof:name":"Affordable Automotive",
    "wof:placetype":"venue"
},
  "geometry": {"coordinates":[-104.97742700000001,39.75464],"type":"Point"}
}