{
  "type": "Feature",
  "properties": {
    "addr:full":"7801 W 8th Ave Denver CO 80214",
    "addr:housenumber":"7801",
    "addr:postcode":"80214",
    "addr:street":"W 8Th Ave",
    "iso:country":"US",
    "sg:address":"7801 W 8th Ave",
    "sg:city":"Denver",
    "sg:classifiers":[
        {
            "category":"Shopping",
            "subcategory":"Florist",
            "type":"Retail Goods"
        }
    ],
    "sg:phone":"+1 303 232 5323",
    "sg:postcode":"80214",
    "sg:province":"CO",
    "wof:name":"Disners Floral",
    "wof:placetype":"venue"
},
  "geometry": {"coordinates":[-105.086135,39.72851],"type":"Point"}
}