{
  "type": "Feature",
  "properties": {
    "iso:country":"US",
    "sg:address":"2500 Arapahoe St",
    "sg:city":"Denver",
    "sg:classifiers":[
        {
            "category":"Home & Garden",
            "subcategory":"Furniture",
            "type":"Retail Goods"
        }
    ],
    "sg:phone":"+1 303 451 1969",
    "sg:postcode":"80205",
    "sg:province":"CO",
    "wof:name":"Boulder Furniture",
    "wof:placetype":"venue"
},
  "geometry": {"coordinates":[-104.983593,39.757215],"type":"Point"}
}