{
  "type": "Feature",
  "properties": {
    "iso:country":"US",
    "sg:address":"1155 S Havana St",
    "sg:city":"Aurora",
    "sg:classifiers":[
        {
            "category":"Professional",
            "subcategory":"Art Services",
            "type":"Services"
        }
    ],
    "sg:phone":"+1 303 507 7400",
    "sg:postcode":"80012",
    "sg:province":"CO",
    "sg:tags":[
        "graphic",
        "designer"
    ],
    "wof:name":"Donald Faast",
    "wof:placetype":"venue"
},
  "geometry": {"coordinates":[-104.86603700000001,39.692836],"type":"Point"}
}