{
  "type": "Feature",
  "properties": {
    "iso:country":"US",
    "sg:address":"405 W 5th St",
    "sg:city":"Delta",
    "sg:classifiers":[
        {
            "category":"Wholesale",
            "subcategory":"Farm Supplies",
            "type":"Manufacturing & Wholesale Goods"
        },
        {
            "category":"Shopping",
            "type":"Retail Goods"
        }
    ],
    "sg:phone":"+1 970 874 8376",
    "sg:postcode":"81416",
    "sg:province":"CO",
    "sg:tags":[
        "feed",
        "merchandise"
    ],
    "wof:name":"Sisson's Feed & Seed",
    "wof:placetype":"venue"
},
  "geometry": {"coordinates":[-108.076331,38.740379],"type":"Point"}
}