{
  "type": "Feature",
  "properties": {
    "iso:country":"US",
    "sg:address":"516 W Eisenhower Blvd",
    "sg:city":"Loveland",
    "sg:classifiers":[
        {
            "category":"Food & Beverages",
            "subcategory":"Specialty",
            "type":"Retail Goods"
        },
        {
            "category":"Restaurant",
            "type":"Food & Drink"
        }
    ],
    "sg:phone":"+1 970 593 9691",
    "sg:postcode":"80537",
    "sg:province":"CO",
    "sg:tags":[
        "tea",
        "coffee",
        "eating"
    ],
    "wof:name":"Dallabetta's Lakeside Cafe",
    "wof:placetype":"venue"
},
  "geometry": {"coordinates":[-105.082566,40.405685],"type":"Point"}
}