{
  "type": "Feature",
  "properties": {
    "iso:country":"US",
    "sg:address":"19533 Hwy 392",
    "sg:city":"Greeley",
    "sg:classifiers":[
        {
            "category":"Freight",
            "type":"Transportation"
        }
    ],
    "sg:phone":"+1 970 356 9537",
    "sg:postcode":"80631",
    "sg:province":"CO",
    "sg:tags":[
        "local",
        "trucking"
    ],
    "wof:name":"Ditter Brothers Hauling Svcs",
    "wof:placetype":"venue"
},
  "geometry": {"coordinates":[-104.69679499999999,40.480979],"type":"Point"}
}