{
  "type": "Feature",
  "properties": {
    "iso:country":"US",
    "sg:address":"89 W Littleton Blvd Ste A",
    "sg:city":"Littleton",
    "sg:classifiers":[
        {
            "category":"Building & Trades",
            "subcategory":"Construction",
            "type":"Services"
        }
    ],
    "sg:phone":"+1 303 794 0490",
    "sg:postcode":"80120",
    "sg:province":"CO",
    "sg:tags":[
        "windows-repair",
        "installation",
        "replacement"
    ],
    "sg:website":"http://www.windowsfouryourhome.com",
    "wof:name":"Gravina's Window Ctr",
    "wof:placetype":"venue"
},
  "geometry": {"coordinates":[-104.989132,39.613275],"type":"Point"}
}