{
  "type": "Feature",
  "properties": {
    "iso:country":"US",
    "sg:address":"10350 Co Rd 120",
    "sg:city":"Salida",
    "sg:classifiers":[
        {
            "category":"Government",
            "subcategory":"Office",
            "type":"Public Place"
        }
    ],
    "sg:phone":"+1 719 539 3696",
    "sg:postcode":"81201",
    "sg:province":"CO",
    "sg:tags":[
        "state",
        "program"
    ],
    "wof:name":"Transportation Dept",
    "wof:placetype":"venue"
},
  "geometry": {"coordinates":[-106.06558200000001,38.517587],"type":"Point"}
}