{
  "type": "Feature",
  "properties": {
    "iso:country":"US",
    "sg:address":"955 Bannock Street",
    "sg:city":"Denver",
    "sg:classifiers":[
        {
            "category":"Professional",
            "subcategory":"Lawyer & Legal Services",
            "type":"Services"
        }
    ],
    "sg:phone":"+1 303 825 3033",
    "sg:postcode":"80204",
    "sg:province":"CO",
    "wof:name":"Demirali Law Firm PC",
    "wof:placetype":"venue"
},
  "geometry": {"coordinates":[-104.990399,39.731243],"type":"Point"}
}