{
  "type": "Feature",
  "properties": {
    "iso:country":"US",
    "sg:address":"8000 E Belleview Ave",
    "sg:city":"Englewood",
    "sg:classifiers":[
        {
            "category":"Shopping",
            "subcategory":"Clothing, Apparel, & Fashions",
            "type":"Retail Goods"
        }
    ],
    "sg:phone":"+1 303 770 9840",
    "sg:postcode":"80111",
    "sg:province":"CO",
    "wof:name":"Bricken Barry",
    "wof:placetype":"venue"
},
  "geometry": {"coordinates":[-104.89687000000001,39.624044],"type":"Point"}
}