{
  "type": "Feature",
  "properties": {
    "iso:country":"US",
    "sg:address":"1484 W 104th Ave",
    "sg:city":"Northglenn",
    "sg:classifiers":[
        {
            "category":"Health Services",
            "subcategory":"Chiropractor",
            "type":"Services"
        }
    ],
    "sg:phone":"+1 303 252 4580",
    "sg:postcode":"80234",
    "sg:province":"CO",
    "wof:name":"Classic Chiropractic",
    "wof:placetype":"venue"
},
  "geometry": {"coordinates":[-105.004643,39.884982],"type":"Point"}
}