{
  "type": "Feature",
  "properties": {
    "addr:full":"2201 E Asbury Ave Denver CO 80210",
    "addr:housenumber":"2201",
    "addr:postcode":"80210",
    "addr:street":"E Asbury Ave",
    "iso:country":"US",
    "sg:address":"2201 E Asbury Ave",
    "sg:city":"Denver",
    "sg:classifiers":[
        {
            "category":"Sports & Exercise",
            "subcategory":"Gym",
            "type":"Entertainment"
        },
        {
            "category":"Sports & Exercise",
            "subcategory":"Swimming Pool",
            "type":"Entertainment"
        }
    ],
    "sg:phone":"+1 303 871 3845",
    "sg:postcode":"80210",
    "sg:province":"CO",
    "sg:website":"recreation.du.edu/membership/?ma...",
    "wof:name":"Coors Fitness Center",
    "wof:placetype":"venue"
},
  "geometry": {"coordinates":[-104.96195299999999,39.682564],"type":"Point"}
}