{
  "type": "Feature",
  "properties": {
    "iso:country":"US",
    "sg:address":"5808 Franklin Street",
    "sg:city":"Denver",
    "sg:classifiers":[
        {
            "category":"Building & Trades",
            "subcategory":"Plumbing",
            "type":"Services"
        }
    ],
    "sg:phone":"+1 303 988 4166",
    "sg:postcode":"80216",
    "sg:province":"CO",
    "wof:name":"Drain Doctor",
    "wof:placetype":"venue"
},
  "geometry": {"coordinates":[-104.968559,39.802688],"type":"Point"}
}