{
  "type": "Feature",
  "properties": {
    "iso:country":"US",
    "sg:address":"1904 Main St",
    "sg:city":"Ouray",
    "sg:classifiers":[
        {
            "category":"Travel",
            "subcategory":"Hotels & Motels",
            "type":"Entertainment"
        }
    ],
    "sg:phone":"+1 970 325 0431",
    "sg:postcode":"81427",
    "sg:province":"CO",
    "wof:name":"Elkhorn Log Cabins",
    "wof:placetype":"venue"
},
  "geometry": {"coordinates":[-107.679418,38.039548],"type":"Point"}
}