{
  "type": "Feature",
  "properties": {
    "iso:country":"US",
    "sg:address":"7720 Calawba Ct",
    "sg:city":"Denver",
    "sg:classifiers":[
        {
            "category":"Retail",
            "subcategory":"Auto Rental",
            "type":"Services"
        }
    ],
    "sg:phone":"+1 303 342 7350",
    "sg:postcode":"80249",
    "sg:province":"CO",
    "sg:tags":[
        "car",
        "leasing"
    ],
    "wof:name":"Enterprise Lsg Co of Denver",
    "wof:placetype":"venue"
},
  "geometry": {"coordinates":[-104.712425,39.83339],"type":"Point"}
}