{
  "type": "Feature",
  "properties": {
    "addr:full":"1020 NE Frontage Rd Fort Collins CO 80524",
    "addr:housenumber":"1020",
    "addr:postcode":"80524",
    "addr:street":"Ne Frontage Rd",
    "iso:country":"US",
    "sg:address":"1020 NE Frontage Rd",
    "sg:city":"Fort Collins",
    "sg:phone":"+1 970 482 8001",
    "sg:postcode":"80524",
    "sg:province":"CO",
    "sg:tags":[
        "farm",
        "field",
        "crop"
    ],
    "wof:name":"Fort Collins Feed",
    "wof:placetype":"venue"
},
  "geometry": {"coordinates":[-105.000916,40.601693],"type":"Point"}
}