{
  "type": "Feature",
  "properties": {
    "addr:full":"2173 S Eaton Street Denver CO 80227",
    "addr:housenumber":"2173",
    "addr:postcode":"80227",
    "addr:street":"S Eaton Street",
    "iso:country":"US",
    "sg:address":"2173 S Eaton Street",
    "sg:city":"Denver",
    "sg:classifiers":[
        {
            "category":"Real Estate",
            "subcategory":"Real Estate Operator",
            "type":"Services"
        }
    ],
    "sg:phone":"+1 303 985 2119",
    "sg:postcode":"80227",
    "sg:province":"CO",
    "sg:tags":[
        "apartment"
    ],
    "wof:name":"Sheridan South Apartments",
    "wof:placetype":"venue"
},
  "geometry": {"coordinates":[-105.058266,39.676019],"type":"Point"}
}