{
  "type": "Feature",
  "properties": {
    "iso:country":"US",
    "sg:address":"7200 E Dry Creek Rd",
    "sg:city":"Centennial",
    "sg:classifiers":[
        {
            "category":"Building & Trades",
            "subcategory":"Construction",
            "type":"Services"
        }
    ],
    "sg:phone":"+1 303 770 6614",
    "sg:postcode":"80112",
    "sg:province":"CO",
    "sg:tags":[
        "carpentry",
        "general",
        "contractor"
    ],
    "wof:name":"West Star Framing Inc",
    "wof:placetype":"venue"
},
  "geometry": {"coordinates":[-104.904267,39.580525],"type":"Point"}
}