{
  "type": "Feature",
  "properties": {
    "addr:full":"1777 S Harrison St Denver CO 80210",
    "addr:housenumber":"1777",
    "addr:postcode":"80210",
    "addr:street":"S Harrison St",
    "iso:country":"US",
    "sg:address":"1777 S Harrison St",
    "sg:city":"Denver",
    "sg:classifiers":[
        {
            "category":"Insurance",
            "subcategory":"Insurance Agent",
            "type":"Services"
        }
    ],
    "sg:phone":"+1 303 693 4449",
    "sg:postcode":"80210",
    "sg:province":"CO",
    "wof:name":"Farmers Insurance Group",
    "wof:placetype":"venue"
},
  "geometry": {"coordinates":[-104.941897,39.685379],"type":"Point"}
}