{
  "type": "Feature",
  "properties": {
    "iso:country":"US",
    "sg:address":"6345 Ashridge Ct",
    "sg:city":"Colorado Springs",
    "sg:classifiers":[
        {
            "category":"Social Services",
            "subcategory":"Child Care",
            "type":"Services"
        }
    ],
    "sg:phone":"+1 719 591 8747",
    "sg:postcode":"80922",
    "sg:province":"CO",
    "wof:name":"Debbie's Home Child Care",
    "wof:placetype":"venue"
},
  "geometry": {"coordinates":[-104.71092299999999,38.900585],"type":"Point"}
}