{
  "type": "Feature",
  "properties": {
    "iso:country":"US",
    "sg:address":"2502 Foresight Cir",
    "sg:city":"Grand Junction",
    "sg:classifiers":[
        {
            "category":"Utilities",
            "subcategory":"Telephone",
            "type":"Services"
        }
    ],
    "sg:phone":"+1 970 245 8750",
    "sg:postcode":"81505",
    "sg:province":"CO",
    "sg:tags":[
        "communications"
    ],
    "wof:name":"AT&T",
    "wof:placetype":"venue"
},
  "geometry": {"coordinates":[-108.58651500000001,39.092779],"type":"Point"}
}