{
  "type": "Feature",
  "properties": {
    "addr:full":"6920 W 38th Ave Wheat Ridge CO 80033",
    "addr:housenumber":"6920",
    "addr:postcode":"80033",
    "addr:street":"W 38Th Ave",
    "iso:country":"US",
    "sg:address":"6920 W 38th Ave",
    "sg:city":"Wheat Ridge",
    "sg:classifiers":[
        {
            "category":"Restaurant",
            "type":"Food & Drink"
        }
    ],
    "sg:phone":"+1 303 422 6600",
    "sg:postcode":"80033",
    "sg:province":"CO",
    "wof:name":"Marcs Restaurant & Catering",
    "wof:placetype":"venue"
},
  "geometry": {"coordinates":[-105.07419400000001,39.769297],"type":"Point"}
}