{
  "type": "Feature",
  "properties": {
    "iso:country":"US",
    "sg:address":"429 W 10th St",
    "sg:city":"Pueblo",
    "sg:classifiers":[
        {
            "category":"Social Services",
            "type":"Services"
        }
    ],
    "sg:phone":"+1 719 544 4233",
    "sg:postcode":"81003",
    "sg:province":"CO",
    "sg:tags":[
        "counselor",
        "marriage",
        "family"
    ],
    "sg:website":"www.pueblocharities.org",
    "wof:name":"Catholic Charities Diocese",
    "wof:placetype":"venue"
},
  "geometry": {"coordinates":[-104.612864,38.276216],"type":"Point"}
}