{
  "type": "Feature",
  "properties": {
    "iso:country":"US",
    "sg:address":"3397 S Lafayette St",
    "sg:city":"Englewood",
    "sg:classifiers":[
        {
            "category":"Shopping",
            "subcategory":"Catalog Store",
            "type":"Retail Goods"
        }
    ],
    "sg:phone":"+1 303 761 4050",
    "sg:postcode":"80113",
    "sg:province":"CO",
    "sg:tags":[
        "mail",
        "house"
    ],
    "wof:name":"Dave Kurz Studio",
    "wof:placetype":"venue"
},
  "geometry": {"coordinates":[-104.971197,39.656805],"type":"Point"}
}