{
  "type": "Feature",
  "properties": {
    "iso:country":"US",
    "sg:address":"999 Decatur St",
    "sg:city":"Denver",
    "sg:classifiers":[
        {
            "category":"Social Services",
            "type":"Services"
        }
    ],
    "sg:phone":"+1 303 623 6514",
    "sg:postcode":"80204",
    "sg:province":"CO",
    "sg:tags":[
        "organization",
        "welfare"
    ],
    "wof:name":"Family Homestead",
    "wof:placetype":"venue"
},
  "geometry": {"coordinates":[-105.021733,39.731201],"type":"Point"}
}