{
  "type": "Feature",
  "properties": {
    "iso:country":"US",
    "sg:address":"410 Sierra Vista Way",
    "sg:city":"Gunnison",
    "sg:classifiers":[
        {
            "category":"Building & Trades",
            "subcategory":"Plumbing",
            "type":"Services"
        }
    ],
    "sg:phone":"+1 970 641 2880",
    "sg:postcode":"81230",
    "sg:province":"CO",
    "sg:tags":[
        "contractor"
    ],
    "wof:name":"Costanzo Plumbing & Heating",
    "wof:placetype":"venue"
},
  "geometry": {"coordinates":[-106.929265,38.59144],"type":"Point"}
}