{
  "type": "Feature",
  "properties": {
    "addr:full":"309 3rd St Castle Rock CO 80104",
    "addr:housenumber":"309",
    "addr:postcode":"80104",
    "addr:street":"3Rd St",
    "iso:country":"US",
    "sg:address":"309 3rd St",
    "sg:city":"Castle Rock",
    "sg:classifiers":[
        {
            "category":"Building & Trades",
            "subcategory":"Construction",
            "type":"Services"
        }
    ],
    "sg:phone":"+1 303 688 4199",
    "sg:postcode":"80104",
    "sg:province":"CO",
    "sg:tags":[
        "carpentry",
        "contractor"
    ],
    "wof:name":"Columbine Kitchen & Bath",
    "wof:placetype":"venue"
},
  "geometry": {"coordinates":[-104.85947299999999,39.372326],"type":"Point"}
}