{
  "type": "Feature",
  "properties": {
    "iso:country":"US",
    "sg:address":"16498 E Rice Pl",
    "sg:city":"Aurora",
    "sg:classifiers":[
        {
            "category":"Wholesale",
            "subcategory":"Furniture",
            "type":"Manufacturing & Wholesale Goods"
        }
    ],
    "sg:phone":"+1 720 886 9151",
    "sg:postcode":"80015",
    "sg:province":"CO",
    "wof:name":"Wright Line",
    "wof:placetype":"venue"
},
  "geometry": {"coordinates":[-104.797062,39.637128],"type":"Point"}
}