{
  "type": "Feature",
  "properties": {
    "iso:country":"US",
    "sg:address":"2664 E Co Rd 3 S",
    "sg:city":"Monte Vista",
    "sg:classifiers":[
        {
            "category":"Manufacturing",
            "subcategory":"Tools & Machinery",
            "type":"Manufacturing & Wholesale Goods"
        }
    ],
    "sg:phone":"+1 719 852 5884",
    "sg:postcode":"81144",
    "sg:province":"CO",
    "sg:tags":[
        "farm",
        "mfg"
    ],
    "wof:name":"Brian David",
    "wof:placetype":"venue"
},
  "geometry": {"coordinates":[-106.100537,37.53129],"type":"Point"}
}