{
  "type": "Feature",
  "properties": {
    "iso:country":"US",
    "sg:address":"1015 N 7th St",
    "sg:city":"Grand Junction",
    "sg:classifiers":[
        {
            "category":"Real Estate",
            "subcategory":"Real Estate Agent",
            "type":"Services"
        }
    ],
    "sg:phone":"+1 970 242 3647",
    "sg:postcode":"81501",
    "sg:province":"CO",
    "sg:tags":[
        "manager",
        "e"
    ],
    "wof:name":"GMAC",
    "wof:placetype":"venue"
},
  "geometry": {"coordinates":[-108.56112400000001,39.077256],"type":"Point"}
}