{
  "type": "Feature",
  "properties": {
    "iso:country":"US",
    "sg:address":"1050 17th St",
    "sg:city":"Denver",
    "sg:classifiers":[
        {
            "category":"Banks & Credit Unions",
            "subcategory":"Investment Brokerage",
            "type":"Services"
        }
    ],
    "sg:phone":"+1 303 297 9338",
    "sg:postcode":"80202",
    "sg:province":"CO",
    "sg:tags":[
        "merger",
        "acquisition"
    ],
    "wof:name":"International Acquisitions",
    "wof:placetype":"venue"
},
  "geometry": {"coordinates":[-104.994139,39.748402],"type":"Point"}
}