{
  "type": "Feature",
  "properties": {
    "addr:full":"1542 Sunset Ln Grand Junction CO 81505",
    "addr:housenumber":"1542",
    "addr:postcode":"81505",
    "addr:street":"Sunset Ln",
    "iso:country":"US",
    "sg:address":"1542 Sunset Ln",
    "sg:city":"Grand Junction",
    "sg:classifiers":[
        {
            "category":"Building & Trades",
            "subcategory":"Construction",
            "type":"Services"
        }
    ],
    "sg:phone":"+1 970 234 0081",
    "sg:postcode":"81505",
    "sg:province":"CO",
    "sg:tags":[
        "house"
    ],
    "wof:name":"Diamond East",
    "wof:placetype":"venue"
},
  "geometry": {"coordinates":[-108.57379899999999,39.081006],"type":"Point"}
}