{
  "type": "Feature",
  "properties": {
    "iso:country":"US",
    "sg:address":"960 Sherman St Apt 1D",
    "sg:city":"Denver",
    "sg:classifiers":[
        {
            "category":"Communications",
            "subcategory":"Film & Video Production",
            "type":"Services"
        }
    ],
    "sg:phone":"+1 303 839 5492",
    "sg:postcode":"80203",
    "sg:province":"CO",
    "sg:tags":[
        "tv",
        "radio",
        "companies-film"
    ],
    "sg:website":"http://www.stabioproductions.com",
    "wof:name":"Stabio Productions",
    "wof:placetype":"venue"
},
  "geometry": {"coordinates":[-104.984854,39.731424],"type":"Point"}
}