{
  "type": "Feature",
  "properties": {
    "addr:full":"495 S Zuni Street Denver CO 80223",
    "addr:housenumber":"495",
    "addr:postcode":"80223",
    "addr:street":"S Zuni Street",
    "iso:country":"US",
    "sg:address":"495 S Zuni Street",
    "sg:city":"Denver",
    "sg:classifiers":[
        {
            "category":"Organizations",
            "subcategory":"Religious Organization",
            "type":"Services"
        }
    ],
    "sg:phone":"+1 303 935 9185",
    "sg:postcode":"80223",
    "sg:province":"CO",
    "wof:name":"Church of Jesus Christ of Latter-Day Saints",
    "wof:placetype":"venue"
},
  "geometry": {"coordinates":[-105.01554299999999,39.707994],"type":"Point"}
}