{
  "type": "Feature",
  "properties": {
    "addr:full":"10851 E Parker Rd Parker CO 80138",
    "addr:housenumber":"10851",
    "addr:postcode":"80138",
    "addr:street":"E Parker Rd",
    "iso:country":"US",
    "sg:address":"10851 E Parker Rd",
    "sg:city":"Parker",
    "sg:classifiers":[
        {
            "category":"Farming",
            "subcategory":"Livestock Farm",
            "type":"Manufacturing & Wholesale Goods"
        }
    ],
    "sg:phone":"+1 303 841 2224",
    "sg:postcode":"80138",
    "sg:province":"CO",
    "sg:tags":[
        "beef",
        "cattle",
        "real estate",
        "feedlot"
    ],
    "wof:name":"Ausfahl Land Co Lllp",
    "wof:placetype":"venue"
},
  "geometry": {"coordinates":[-104.68003400000001,39.521727],"type":"Point"}
}