{
  "type": "Feature",
  "properties": {
    "iso:country":"US",
    "sg:address":"5671 S Nevada St",
    "sg:city":"Littleton",
    "sg:classifiers":[
        {
            "category":"Food & Beverages",
            "subcategory":"Groceries & Convenience Stores",
            "type":"Retail Goods"
        },
        {
            "category":"Shopping",
            "subcategory":"Gifts & Souvenirs",
            "type":"Retail Goods"
        }
    ],
    "sg:phone":"+1 303 730 8521",
    "sg:postcode":"80120",
    "sg:province":"CO",
    "sg:tags":[
        "shop"
    ],
    "wof:name":"Willow An Artisans Market Inc",
    "wof:placetype":"venue"
},
  "geometry": {"coordinates":[-105.017366,39.614862],"type":"Point"}
}