{
  "type": "Feature",
  "properties": {
    "addr:full":"2525 Mountview Dr Pueblo CO 81008",
    "addr:housenumber":"2525",
    "addr:postcode":"81008",
    "addr:street":"Mountview Dr",
    "iso:country":"US",
    "sg:address":"2525 Mountview Dr",
    "sg:city":"Pueblo",
    "sg:classifiers":[
        {
            "category":"Government",
            "subcategory":"Office",
            "type":"Public Place"
        },
        {
            "category":"Education",
            "subcategory":"School",
            "type":"Public Place"
        }
    ],
    "sg:phone":"+1 719 549 7339",
    "sg:postcode":"81008",
    "sg:province":"CO",
    "sg:tags":[
        "educational",
        "program",
        "administrative",
        "secondary"
    ],
    "sg:website":"www.centennialbulldogs.org",
    "wof:name":"Centennial High School",
    "wof:placetype":"venue"
},
  "geometry": {"coordinates":[-104.638649,38.303391],"type":"Point"}
}