{
  "type": "Feature",
  "properties": {
    "iso:country":"US",
    "sg:address":"2144 Rainier Ct",
    "sg:city":"Grand Junction",
    "sg:classifiers":[
        {
            "category":"Shopping",
            "type":"Retail Goods"
        }
    ],
    "sg:phone":"+1 970 245 0910",
    "sg:postcode":"81503",
    "sg:province":"CO",
    "sg:tags":[
        "miscellaneous",
        "store"
    ],
    "wof:name":"Andrew Zanski Svc",
    "wof:placetype":"venue"
},
  "geometry": {"coordinates":[-108.65244,39.09422],"type":"Point"}
}