{
  "type": "Feature",
  "properties": {
    "iso:country":"US",
    "sg:address":"621 17th Street Suite 1800",
    "sg:city":"Denver",
    "sg:classifiers":[
        {
            "category":"Wholesale",
            "subcategory":"Computers",
            "type":"Manufacturing & Wholesale Goods"
        }
    ],
    "sg:phone":"+1 303 292 4555",
    "sg:postcode":"80293",
    "sg:province":"CO",
    "wof:name":"Digitally Unique",
    "wof:placetype":"venue"
},
  "geometry": {"coordinates":[-104.990498,39.745613],"type":"Point"}
}