{
  "type": "Feature",
  "properties": {
    "addr:full":"434 Edwards Village Blvd Edwards CO 81632",
    "addr:housenumber":"434",
    "addr:postcode":"81632",
    "addr:street":"Edwards Village Blvd",
    "iso:country":"US",
    "sg:address":"434 Edwards Village Blvd",
    "sg:city":"Edwards",
    "sg:classifiers":[
        {
            "category":"Travel",
            "subcategory":"Travel Agent",
            "type":"Entertainment"
        }
    ],
    "sg:phone":"+1 970 845 9000",
    "sg:postcode":"81632",
    "sg:province":"CO",
    "sg:tags":[
        "agency",
        "bureau"
    ],
    "wof:name":"CME Travel",
    "wof:placetype":"venue"
},
  "geometry": {"coordinates":[-106.60193200000001,39.643514],"type":"Point"}
}