{
  "type": "Feature",
  "properties": {
    "iso:country":"US",
    "sg:address":"14779 E Chenango Pl",
    "sg:city":"Aurora",
    "sg:classifiers":[
        {
            "category":"Professional",
            "type":"Services"
        }
    ],
    "sg:phone":"+1 303 627 7393",
    "sg:postcode":"80015",
    "sg:province":"CO",
    "wof:name":"Hungerford",
    "wof:placetype":"venue"
},
  "geometry": {"coordinates":[-104.81638,39.627751],"type":"Point"}
}