{
  "type": "Feature",
  "properties": {
    "iso:country":"US",
    "sg:address":"1157 Forest Edge Rd",
    "sg:city":"Woodland Park",
    "sg:classifiers":[
        {
            "category":"Home & Garden",
            "subcategory":"Hardware",
            "type":"Retail Goods"
        }
    ],
    "sg:phone":"+1 719 687 8055",
    "sg:postcode":"80863",
    "sg:province":"CO",
    "wof:name":"Bio True Technologies LLC",
    "wof:placetype":"venue"
},
  "geometry": {"coordinates":[-105.042891,39.003289],"type":"Point"}
}