{
  "type": "Feature",
  "properties": {
    "iso:country":"US",
    "sg:address":"290 Fillmore St",
    "sg:city":"Denver",
    "sg:classifiers":[
        {
            "category":"Shopping",
            "subcategory":"Jewelry",
            "type":"Retail Goods"
        }
    ],
    "sg:phone":"+1 303 377 1701",
    "sg:postcode":"80206",
    "sg:province":"CO",
    "sg:tags":[
        "precious",
        "metal",
        "mfg"
    ],
    "wof:name":"Object Design",
    "wof:placetype":"venue"
},
  "geometry": {"coordinates":[-104.953343,39.719538],"type":"Point"}
}