{
  "type": "Feature",
  "properties": {
    "addr:full":"3750 E 8th Ave Denver CO 80206",
    "addr:housenumber":"3750",
    "addr:postcode":"80206",
    "addr:street":"E 8Th Ave",
    "iso:country":"US",
    "sg:address":"3750 E 8th Ave",
    "sg:city":"Denver",
    "sg:classifiers":[
        {
            "category":"Building & Trades",
            "subcategory":"Locksmith",
            "type":"Services"
        }
    ],
    "sg:phone":"+1 303 305 0150",
    "sg:postcode":"80206",
    "sg:province":"CO",
    "sg:tags":[
        "key"
    ],
    "wof:name":"All Around Lockmith",
    "wof:placetype":"venue"
},
  "geometry": {"coordinates":[-104.94344100000001,39.728988],"type":"Point"}
}