{
  "type": "Feature",
  "properties": {
    "addr:full":"10485 Hoyt St Broomfield CO 80021",
    "addr:housenumber":"10485",
    "addr:postcode":"80021",
    "addr:street":"Hoyt St",
    "iso:country":"US",
    "sg:address":"10485 Hoyt St",
    "sg:city":"Broomfield",
    "sg:classifiers":[
        {
            "category":"Wholesale",
            "subcategory":"Hardware",
            "type":"Manufacturing & Wholesale Goods"
        }
    ],
    "sg:phone":"+1 303 438 5883",
    "sg:postcode":"80021",
    "sg:province":"CO",
    "sg:tags":[
        "refrigerating"
    ],
    "wof:name":"Cold Creek Refrigeration",
    "wof:placetype":"venue"
},
  "geometry": {"coordinates":[-105.102907,39.888401],"type":"Point"}
}