{
  "type": "Feature",
  "properties": {
    "iso:country":"US",
    "sg:address":"3486 S Broadway",
    "sg:city":"Englewood",
    "sg:classifiers":[
        {
            "category":"Insurance",
            "subcategory":"Insurance Agent",
            "type":"Services"
        }
    ],
    "sg:phone":"+1 303 788 1632",
    "sg:postcode":"80113",
    "sg:province":"CO",
    "wof:name":"American Family Insurance",
    "wof:placetype":"venue"
},
  "geometry": {"coordinates":[-104.987532,39.654775],"type":"Point"}
}