{
  "type": "Feature",
  "properties": {
    "iso:country":"US",
    "sg:address":"4730 W 127th Pl",
    "sg:city":"Broomfield",
    "sg:classifiers":[
        {
            "category":"Professional",
            "subcategory":"Computer Services",
            "type":"Services"
        }
    ],
    "sg:phone":"+1 303 438 9365",
    "sg:postcode":"80020",
    "sg:province":"CO",
    "sg:tags":[
        "repair"
    ],
    "sg:website":"www.tektrekcs.com",
    "wof:name":"Tektrek Computer Svc",
    "wof:placetype":"venue"
},
  "geometry": {"coordinates":[-105.04697,39.92687],"type":"Point"}
}