{
  "type": "Feature",
  "properties": {
    "addr:full":"11013 Northglenn Dr Denver CO 80233",
    "addr:housenumber":"11013",
    "addr:postcode":"80233",
    "addr:street":"Northglenn Dr",
    "iso:country":"US",
    "sg:address":"11013 Northglenn Dr",
    "sg:city":"Denver",
    "sg:classifiers":[
        {
            "category":"Manufacturing",
            "subcategory":"Lumber",
            "type":"Manufacturing & Wholesale Goods"
        }
    ],
    "sg:phone":"+1 303 451 6280",
    "sg:postcode":"80233",
    "sg:province":"CO",
    "sg:tags":[
        "hardwood",
        "mill"
    ],
    "wof:name":"Gary Eversman Classic Custom",
    "wof:placetype":"venue"
},
  "geometry": {"coordinates":[-104.986676,39.896803],"type":"Point"}
}