{
  "type": "Feature",
  "properties": {
    "addr:full":"3790 W 112th Ave Westminster CO 80031",
    "addr:housenumber":"3790",
    "addr:postcode":"80031",
    "addr:street":"W 112Th Ave",
    "iso:country":"US",
    "sg:address":"3790 W 112th Ave",
    "sg:city":"Westminster",
    "sg:classifiers":[
        {
            "category":"Professional",
            "type":"Services"
        }
    ],
    "sg:phone":"+1 303 439 2559",
    "sg:postcode":"80031",
    "sg:province":"CO",
    "wof:name":"Dents By Hand",
    "wof:placetype":"venue"
},
  "geometry": {"coordinates":[-105.041647,39.8996],"type":"Point"}
}