{
  "type": "Feature",
  "properties": {
    "addr:full":"6228 Wild Plum Dr Loveland CO 80537",
    "addr:housenumber":"6228",
    "addr:postcode":"80537",
    "addr:street":"Wild Plum Dr",
    "iso:country":"US",
    "sg:address":"6228 Wild Plum Dr",
    "sg:city":"Loveland",
    "sg:classifiers":[
        {
            "category":"Autos & Motor Vehicles",
            "subcategory":"Automobile Sales",
            "type":"Retail Goods"
        }
    ],
    "sg:phone":"+1 970 227 9706",
    "sg:postcode":"80537",
    "sg:province":"CO",
    "sg:tags":[
        "used"
    ],
    "wof:name":"Johns Doug Sales Inc",
    "wof:placetype":"venue"
},
  "geometry": {"coordinates":[-105.16562,40.360421],"type":"Point"}
}