{
  "type": "Feature",
  "properties": {
    "addr:full":"620 E Rodeo Rd Gypsum CO 81648",
    "addr:housenumber":"620",
    "addr:postcode":"81648",
    "addr:street":"E Rodeo Rd",
    "iso:country":"US",
    "sg:address":"620 E Rodeo Rd",
    "sg:city":"Gypsum",
    "sg:classifiers":[
        {
            "category":"Health Services",
            "subcategory":"Doctor",
            "type":"Services"
        }
    ],
    "sg:phone":"+1 970 524 1105",
    "sg:postcode":"81648",
    "sg:province":"CO",
    "sg:tags":[
        "dentist"
    ],
    "wof:name":"Steve Oakson DDS",
    "wof:placetype":"venue"
},
  "geometry": {"coordinates":[-108.796047,40.092402],"type":"Point"}
}