{
  "type": "Feature",
  "properties": {
    "addr:full":"1224 W Littleton Blvd Littleton CO 80120",
    "addr:housenumber":"1224",
    "addr:postcode":"80120",
    "addr:street":"W Littleton Blvd",
    "iso:country":"US",
    "sg:address":"1224 W Littleton Blvd",
    "sg:city":"Littleton",
    "sg:classifiers":[
        {
            "category":"Personal",
            "subcategory":"Beauty Salon",
            "type":"Services"
        }
    ],
    "sg:phone":"+1 303 795 1335",
    "sg:postcode":"80120",
    "sg:province":"CO",
    "sg:tags":[
        "shop"
    ],
    "wof:name":"Reggie's II Hair Styling",
    "wof:placetype":"venue"
},
  "geometry": {"coordinates":[-105.002804,39.613139],"type":"Point"}
}