{
  "type": "Feature",
  "properties": {
    "iso:country":"US",
    "sg:address":"115 E Main St",
    "sg:city":"Florence",
    "sg:classifiers":[
        {
            "category":"Wholesale",
            "subcategory":"Office Equipment",
            "type":"Manufacturing & Wholesale Goods"
        }
    ],
    "sg:phone":"+1 719 784 4991",
    "sg:postcode":"81226",
    "sg:province":"CO",
    "sg:tags":[
        "credit"
    ],
    "sg:website":"www.peakcardservices.com",
    "wof:name":"Peak Card Svc",
    "wof:placetype":"venue"
},
  "geometry": {"coordinates":[-105.117582,38.38997],"type":"Point"}
}