{
  "type": "Feature",
  "properties": {
    "iso:country":"US",
    "sg:address":"7152 S Blackhawk St",
    "sg:city":"Englewood",
    "sg:classifiers":[
        {
            "category":"Freight",
            "type":"Transportation"
        },
        {
            "category":"Professional",
            "type":"Services"
        }
    ],
    "sg:phone":"+1 303 693 7755",
    "sg:postcode":"80112",
    "sg:province":"CO",
    "sg:tags":[
        "commercial",
        "storage"
    ],
    "wof:name":"Colorado Custom Coach Stor LLC",
    "wof:placetype":"venue"
},
  "geometry": {"coordinates":[-104.824849,39.584523],"type":"Point"}
}