{
  "type": "Feature",
  "properties": {
    "iso:country":"US",
    "sg:address":"6425 W 52nd Ave",
    "sg:city":"Arvada",
    "sg:classifiers":[
        {
            "category":"Building & Trades",
            "subcategory":"Equipment Rental",
            "type":"Services"
        },
        {
            "category":"Building & Trades",
            "subcategory":"Construction",
            "type":"Services"
        }
    ],
    "sg:phone":"+1 303 422 0622",
    "sg:postcode":"80002",
    "sg:province":"CO",
    "sg:tags":[
        "steel",
        "crane",
        "erection",
        "erectors",
        "contractor"
    ],
    "wof:name":"Ridge Erection Company",
    "wof:placetype":"venue"
},
  "geometry": {"coordinates":[-105.06856500000001,39.791171],"type":"Point"}
}