{
  "type": "Feature",
  "properties": {
    "iso:country":"US",
    "sg:address":"2020 E Evans Avenue",
    "sg:city":"Denver",
    "sg:classifiers":[
        {
            "category":"Education",
            "subcategory":"University",
            "type":"Public Place"
        }
    ],
    "sg:phone":"+1 303 871 7420",
    "sg:postcode":"80210",
    "sg:province":"CO",
    "sg:tags":[
        "college"
    ],
    "wof:name":"University of Denver",
    "wof:placetype":"venue"
},
  "geometry": {"coordinates":[-104.963336,39.678277],"type":"Point"}
}