{
  "type": "Feature",
  "properties": {
    "iso:country":"US",
    "sg:address":"6225 W 48th Ave",
    "sg:city":"Wheat Ridge",
    "sg:classifiers":[
        {
            "category":"Building & Trades",
            "subcategory":"Plumbing",
            "type":"Services"
        }
    ],
    "sg:phone":"+1 303 940 8381",
    "sg:postcode":"80033",
    "sg:province":"CO",
    "sg:tags":[
        "plumbing",
        "contractor"
    ],
    "wof:name":"K B Plumbing",
    "wof:placetype":"venue"
},
  "geometry": {"coordinates":[-105.06609,39.78401],"type":"Point"}
}