{
  "type": "Feature",
  "properties": {
    "addr:full":"755 N 4th St Grand Junction CO 81501",
    "addr:housenumber":"755",
    "addr:postcode":"81501",
    "addr:street":"N 4Th St",
    "iso:country":"US",
    "sg:address":"755 N 4th St",
    "sg:city":"Grand Junction",
    "sg:classifiers":[
        {
            "category":"Organizations",
            "subcategory":"Religious Organization",
            "type":"Services"
        }
    ],
    "sg:phone":"+1 970 242 2184",
    "sg:postcode":"81501",
    "sg:province":"CO",
    "sg:tags":[
        "church"
    ],
    "wof:name":"First Church Of God",
    "wof:placetype":"venue"
},
  "geometry": {"coordinates":[-108.566236,39.073884],"type":"Point"}
}