{
  "type": "Feature",
  "properties": {
    "addr:full":"2625 E 3rd Avenue Denver CO 80206",
    "addr:housenumber":"2625",
    "addr:postcode":"80206",
    "addr:street":"E 3Rd Avenue",
    "iso:country":"US",
    "sg:address":"2625 E 3rd Avenue",
    "sg:city":"Denver",
    "sg:classifiers":[
        {
            "category":"Shopping",
            "subcategory":"Jewelry",
            "type":"Retail Goods"
        }
    ],
    "sg:phone":"+1 303 355 5858",
    "sg:postcode":"80206",
    "sg:province":"CO",
    "wof:name":"Gnat Original Designs",
    "wof:placetype":"venue"
},
  "geometry": {"coordinates":[-104.951711,39.734877],"type":"Point"}
}