{
  "type": "Feature",
  "properties": {
    "iso:country":"US",
    "sg:address":"2945 Galley Rd",
    "sg:city":"Colorado Springs",
    "sg:classifiers":[
        {
            "category":"Bars & Pubs",
            "type":"Food & Drink"
        }
    ],
    "sg:phone":"+1 719 573 0711",
    "sg:postcode":"80909",
    "sg:province":"CO",
    "sg:tags":[
        "club",
        "night"
    ],
    "wof:name":"Purple Rose Nite Club LLC",
    "wof:placetype":"venue"
},
  "geometry": {"coordinates":[-104.774384,38.847087],"type":"Point"}
}