{
  "type": "Feature",
  "properties": {
    "addr:full":"1800 E Pavilion Pl Montrose CO 81401",
    "addr:housenumber":"1800",
    "addr:postcode":"81401",
    "addr:street":"E Pavilion Pl",
    "iso:country":"US",
    "sg:address":"1800 E Pavilion Pl",
    "sg:city":"Montrose",
    "sg:classifiers":[
        {
            "category":"Health Services",
            "subcategory":"Doctor",
            "type":"Services"
        }
    ],
    "sg:phone":"+1 970 249 1210",
    "sg:postcode":"81401",
    "sg:province":"CO",
    "sg:tags":[
        "physician",
        "surgeon"
    ],
    "wof:name":"Co West Ophthalmology Assoc",
    "wof:placetype":"venue"
},
  "geometry": {"coordinates":[-107.849996,38.466628],"type":"Point"}
}