{
  "type": "Feature",
  "properties": {
    "iso:country":"US",
    "sg:address":"1475 Donald Rd",
    "sg:city":"Colorado Springs",
    "sg:classifiers":[
        {
            "category":"Building & Trades",
            "subcategory":"Plumbing",
            "type":"Services"
        }
    ],
    "sg:phone":"+1 719 339 7949",
    "sg:postcode":"80930",
    "sg:province":"CO",
    "sg:tags":[
        "refrigeration",
        "contractor"
    ],
    "wof:name":"Rogers Heating & Cooling",
    "wof:placetype":"venue"
},
  "geometry": {"coordinates":[-104.54376600000001,38.85228],"type":"Point"}
}