{
  "type": "Feature",
  "properties": {
    "iso:country":"US",
    "sg:address":"195 Edgemont Blvd",
    "sg:city":"Alamosa",
    "sg:classifiers":[
        {
            "category":"Real Estate",
            "subcategory":"Real Estate Operator",
            "type":"Services"
        }
    ],
    "sg:phone":"+1 719 589 5395",
    "sg:postcode":"81101",
    "sg:province":"CO",
    "sg:tags":[
        "building",
        "nonresidential"
    ],
    "wof:name":"Main Group Realty LLC",
    "wof:placetype":"venue"
},
  "geometry": {"coordinates":[-105.880844,37.471539],"type":"Point"}
}