{
  "type": "Feature",
  "properties": {
    "addr:full":"13180 W 43rd Dr Golden CO 80403",
    "addr:housenumber":"13180",
    "addr:postcode":"80403",
    "addr:street":"W 43Rd Dr",
    "iso:country":"US",
    "sg:address":"13180 W 43rd Dr",
    "sg:city":"Golden",
    "sg:classifiers":[
        {
            "category":"Professional",
            "subcategory":"Computer Services",
            "type":"Services"
        }
    ],
    "sg:phone":"+1 303 202 9599",
    "sg:postcode":"80403",
    "sg:province":"CO",
    "sg:tags":[
        "electronic",
        "programing",
        "custom"
    ],
    "sg:website":"www.rapportinc.com",
    "wof:name":"Rapport Inc",
    "wof:placetype":"venue"
},
  "geometry": {"coordinates":[-105.150593,39.775791],"type":"Point"}
}