{
  "type": "Feature",
  "properties": {
    "iso:country":"US",
    "sg:address":"5803 Leetsdale Dr",
    "sg:city":"Denver",
    "sg:classifiers":[
        {
            "category":"Retail",
            "subcategory":"Laundry & Dry Cleaning",
            "type":"Services"
        }
    ],
    "sg:phone":"+1 303 320 6290",
    "sg:postcode":"80224",
    "sg:province":"CO",
    "wof:name":"Continental Cleaners",
    "wof:placetype":"venue"
},
  "geometry": {"coordinates":[-104.92088099999999,39.707002],"type":"Point"}
}