{
  "type": "Feature",
  "properties": {
    "iso:country":"US",
    "sg:address":"131 S Union Ave",
    "sg:city":"Pueblo",
    "sg:classifiers":[
        {
            "category":"Professional",
            "subcategory":"Lawyer & Legal Services",
            "type":"Services"
        }
    ],
    "sg:phone":"+1 719 542 6388",
    "sg:postcode":"81003",
    "sg:province":"CO",
    "sg:tags":[
        "attorney"
    ],
    "wof:name":"Daniel C Kender",
    "wof:placetype":"venue"
},
  "geometry": {"coordinates":[-104.613411,38.264672],"type":"Point"}
}