{
  "type": "Feature",
  "properties": {
    "iso:country":"US",
    "sg:address":"8858 W 65th Ave",
    "sg:city":"Arvada",
    "sg:classifiers":[
        {
            "category":"Building & Trades",
            "subcategory":"Plumbing",
            "type":"Services"
        }
    ],
    "sg:phone":"+1 303 431 5538",
    "sg:postcode":"80004",
    "sg:province":"CO",
    "sg:tags":[
        "plumbing",
        "contractor"
    ],
    "wof:name":"Meridian Plumbing & Heating",
    "wof:placetype":"venue"
},
  "geometry": {"coordinates":[-105.09605500000001,39.815312],"type":"Point"}
}