{
  "type": "Feature",
  "properties": {
    "iso:country":"US",
    "sg:address":"8605 Lamar Dr",
    "sg:city":"Arvada",
    "sg:classifiers":[
        {
            "category":"Professional",
            "type":"Services"
        }
    ],
    "sg:phone":"+1 303 421 2697",
    "sg:postcode":"80003",
    "sg:province":"CO",
    "wof:name":"Pl Grundin Meco",
    "wof:placetype":"venue"
},
  "geometry": {"coordinates":[-105.065195,39.853337],"type":"Point"}
}