{
  "type": "Feature",
  "properties": {
    "iso:country":"US",
    "sg:address":"3790 S Eaton St",
    "sg:city":"Denver",
    "sg:classifiers":[
        {
            "category":"Farming",
            "subcategory":"Farm",
            "type":"Manufacturing & Wholesale Goods"
        }
    ],
    "sg:phone":"+1 303 969 0073",
    "sg:postcode":"80235",
    "sg:province":"CO",
    "wof:name":"Metro Farms",
    "wof:placetype":"venue"
},
  "geometry": {"coordinates":[-105.058262,39.649185],"type":"Point"}
}