{
  "type": "Feature",
  "properties": {
    "addr:full":"119 W 3rd St Palisade CO 81526",
    "addr:housenumber":"119",
    "addr:postcode":"81526",
    "addr:street":"W 3Rd St",
    "iso:country":"US",
    "sg:address":"119 W 3rd St",
    "sg:city":"Palisade",
    "sg:classifiers":[
        {
            "category":"Professional",
            "type":"Services"
        }
    ],
    "sg:phone":"+1 970 464 0691",
    "sg:postcode":"81526",
    "sg:province":"CO",
    "sg:tags":[
        "establishment"
    ],
    "wof:name":"PRM Assoc",
    "wof:placetype":"venue"
},
  "geometry": {"coordinates":[-108.351084,39.110233],"type":"Point"}
}