{
  "type": "Feature",
  "properties": {
    "iso:country":"US",
    "sg:address":"4030 S Inca St",
    "sg:city":"Englewood",
    "sg:classifiers":[
        {
            "category":"Wholesale",
            "subcategory":"Vending Machines",
            "type":"Manufacturing & Wholesale Goods"
        }
    ],
    "sg:phone":"+1 303 503 4154",
    "sg:postcode":"80110",
    "sg:province":"CO",
    "sg:tags":[
        "operator",
        "cafeteria"
    ],
    "wof:name":"Beehive Food & Vending",
    "wof:placetype":"venue"
},
  "geometry": {"coordinates":[-104.99820699999999,39.644556],"type":"Point"}
}