{
  "type": "Feature",
  "properties": {
    "addr:full":"130 W 5th St Leadville CO 80461",
    "addr:housenumber":"130",
    "addr:postcode":"80461",
    "addr:street":"W 5Th St",
    "iso:country":"US",
    "sg:address":"130 W 5th St",
    "sg:city":"Leadville",
    "sg:classifiers":[
        {
            "category":"Government",
            "subcategory":"Post Office",
            "type":"Public Place"
        }
    ],
    "sg:phone":"+1 719 486 9397",
    "sg:postcode":"80461",
    "sg:province":"CO",
    "wof:name":"US Post Office",
    "wof:placetype":"venue"
},
  "geometry": {"coordinates":[-106.29222300000001,39.247794],"type":"Point"}
}