{
  "type": "Feature",
  "properties": {
    "iso:country":"US",
    "sg:address":"13851 E Harvard Ave",
    "sg:city":"Aurora",
    "sg:classifiers":[
        {
            "category":"Travel",
            "subcategory":"Hotels & Motels",
            "type":"Entertainment"
        }
    ],
    "sg:phone":"+1 303 745 6700",
    "sg:postcode":"80014",
    "sg:province":"CO",
    "sg:tags":[
        "operation"
    ],
    "wof:name":"Fairfield Inn",
    "wof:placetype":"venue"
},
  "geometry": {"coordinates":[-104.826885,39.671835],"type":"Point"}
}