{
  "type": "Feature",
  "properties": {
    "addr:full":"10262 W 59th Ave Arvada CO 80004",
    "addr:housenumber":"10262",
    "addr:postcode":"80004",
    "addr:street":"W 59Th Ave",
    "iso:country":"US",
    "sg:address":"10262 W 59th Ave",
    "sg:city":"Arvada",
    "sg:classifiers":[
        {
            "category":"Building & Trades",
            "subcategory":"Construction",
            "type":"Services"
        }
    ],
    "sg:phone":"+1 303 432 8734",
    "sg:postcode":"80004",
    "sg:province":"CO",
    "sg:tags":[
        "contractor"
    ],
    "wof:name":"O K Tile and Marble",
    "wof:placetype":"venue"
},
  "geometry": {"coordinates":[-105.11340300000001,39.803987],"type":"Point"}
}