{
  "type": "Feature",
  "properties": {
    "addr:full":"3498 S Broadway Englewood CO 80113",
    "addr:housenumber":"3498",
    "addr:postcode":"80113",
    "addr:street":"S Broadway",
    "iso:country":"US",
    "sg:address":"3498 S Broadway",
    "sg:city":"Englewood",
    "sg:classifiers":[
        {
            "category":"Shopping",
            "subcategory":"Hobbies, Toys, & Games",
            "type":"Retail Goods"
        }
    ],
    "sg:phone":"+1 303 781 4223",
    "sg:postcode":"80113",
    "sg:province":"CO",
    "sg:tags":[
        "supply",
        "instruction",
        "doll"
    ],
    "wof:name":"Doll Shop",
    "wof:placetype":"venue"
},
  "geometry": {"coordinates":[-104.98759200000001,39.655001],"type":"Point"}
}