{
  "type": "Feature",
  "properties": {
    "addr:full":"2860 Bryant St Denver CO 80211",
    "addr:housenumber":"2860",
    "addr:postcode":"80211",
    "addr:street":"Bryant St",
    "iso:country":"US",
    "sg:address":"2860 Bryant St",
    "sg:city":"Denver",
    "sg:classifiers":[
        {
            "category":"Social Services",
            "type":"Services"
        }
    ],
    "sg:phone":"+1 303 455 5991",
    "sg:postcode":"80211",
    "sg:province":"CO",
    "sg:tags":[
        "counselor",
        "marriage",
        "family"
    ],
    "wof:name":"Sue Torfin",
    "wof:placetype":"venue"
},
  "geometry": {"coordinates":[-105.019231,39.758253],"type":"Point"}
}