{
  "type": "Feature",
  "properties": {
    "iso:country":"US",
    "sg:address":"2401 S University Blvd",
    "sg:city":"Denver",
    "sg:classifiers":[
        {
            "category":"Restaurant",
            "type":"Food & Drink"
        }
    ],
    "sg:phone":"+1 303 733 8250",
    "sg:postcode":"80210",
    "sg:province":"CO",
    "sg:tags":[
        "chinese"
    ],
    "wof:name":"Hong Kong Cafe",
    "wof:placetype":"venue"
},
  "geometry": {"coordinates":[-104.959735,39.672813],"type":"Point"}
}