{
  "type": "Feature",
  "properties": {
    "iso:country":"US",
    "sg:address":"3833 Quay St",
    "sg:city":"Wheat Ridge",
    "sg:classifiers":[
        {
            "category":"Insurance",
            "subcategory":"Insurance Agent",
            "type":"Services"
        }
    ],
    "sg:phone":"+1 303 431 1240",
    "sg:postcode":"80033",
    "sg:province":"CO",
    "sg:tags":[
        "broker"
    ],
    "wof:name":"Consolidated Insurance Group",
    "wof:placetype":"venue"
},
  "geometry": {"coordinates":[-105.073319,39.772619],"type":"Point"}
}