{
  "type": "Feature",
  "properties": {
    "addr:full":"724 Fulton St Aurora CO 80010",
    "addr:housenumber":"724",
    "addr:postcode":"80010",
    "addr:street":"Fulton St",
    "iso:country":"US",
    "sg:address":"724 Fulton St",
    "sg:city":"Aurora",
    "sg:classifiers":[
        {
            "category":"Professional",
            "type":"Services"
        }
    ],
    "sg:phone":"+1 303 366 5206",
    "sg:postcode":"80010",
    "sg:province":"CO",
    "wof:name":"Michele Hinneberg",
    "wof:placetype":"venue"
},
  "geometry": {"coordinates":[-104.870548,39.72648],"type":"Point"}
}