{
  "type": "Feature",
  "properties": {
    "addr:full":"171 S Van Gordon St Denver CO 80228",
    "addr:housenumber":"171",
    "addr:postcode":"80228",
    "addr:street":"S Van Gordon St",
    "iso:country":"US",
    "sg:address":"171 S Van Gordon St",
    "sg:city":"Denver",
    "sg:classifiers":[
        {
            "category":"Manufacturing",
            "subcategory":"Retail Goods",
            "type":"Manufacturing & Wholesale Goods"
        },
        {
            "category":"Professional",
            "subcategory":"Computer Services",
            "type":"Services"
        }
    ],
    "sg:phone":"+1 303 940 5511",
    "sg:postcode":"80228",
    "sg:province":"CO",
    "sg:tags":[
        "print",
        "repair",
        "cartridge",
        "mfg"
    ],
    "wof:name":"Imaging Resolutions Inc",
    "wof:placetype":"venue"
},
  "geometry": {"coordinates":[-105.138059,39.713115],"type":"Point"}
}