{
  "type": "Feature",
  "properties": {
    "addr:full":"11705 Airport Way Broomfield CO 80021",
    "addr:housenumber":"11705",
    "addr:postcode":"80021",
    "addr:street":"Airport Way",
    "iso:country":"US",
    "sg:address":"11705 Airport Way",
    "sg:city":"Broomfield",
    "sg:classifiers":[
        {
            "category":"Autos & Motor Vehicles",
            "subcategory":"Automobile Sales",
            "type":"Retail Goods"
        }
    ],
    "sg:phone":"+1 303 635 1762",
    "sg:postcode":"80021",
    "sg:province":"CO",
    "wof:name":"Telavia Managemnt",
    "wof:placetype":"venue"
},
  "geometry": {"coordinates":[-105.108997,39.911763],"type":"Point"}
}