{
  "type": "Feature",
  "properties": {
    "iso:country":"US",
    "sg:address":"1297 Main St",
    "sg:city":"Windsor",
    "sg:classifiers":[
        {
            "category":"Personal",
            "subcategory":"Beauty Salon",
            "type":"Services"
        }
    ],
    "sg:phone":"+1 970 686 5686",
    "sg:postcode":"80550",
    "sg:province":"CO",
    "wof:name":"Dee Dee's A Family Hair Salon",
    "wof:placetype":"venue"
},
  "geometry": {"coordinates":[-104.92115,40.479617],"type":"Point"}
}