{
  "type": "Feature",
  "properties": {
    "iso:country":"US",
    "sg:address":"2442 Bluff St",
    "sg:city":"Boulder",
    "sg:classifiers":[
        {
            "category":"Utilities",
            "subcategory":"Telephone",
            "type":"Services"
        }
    ],
    "sg:phone":"+1 303 668 4111",
    "sg:postcode":"80304",
    "sg:province":"CO",
    "sg:tags":[
        "communications"
    ],
    "wof:name":"Airspeed Broadband",
    "wof:placetype":"venue"
},
  "geometry": {"coordinates":[-105.26463800000001,40.025214],"type":"Point"}
}