{
  "type": "Feature",
  "properties": {
    "addr:full":"720 E Durant Ave Aspen CO 81611",
    "addr:housenumber":"720",
    "addr:postcode":"81611",
    "addr:street":"E Durant Ave",
    "iso:country":"US",
    "sg:address":"720 E Durant Ave",
    "sg:city":"Aspen",
    "sg:classifiers":[
        {
            "category":"Real Estate",
            "subcategory":"Real Estate Agent",
            "type":"Services"
        }
    ],
    "sg:phone":"+1 970 925 1470",
    "sg:postcode":"81611",
    "sg:province":"CO",
    "wof:name":"Carrie Wells",
    "wof:placetype":"venue"
},
  "geometry": {"coordinates":[-106.816631,39.186822],"type":"Point"}
}