{
  "type": "Feature",
  "properties": {
    "iso:country":"US",
    "sg:address":"7148 E County Line Rd Ste 1",
    "sg:city":"Littleton",
    "sg:classifiers":[
        {
            "category":"Personal",
            "subcategory":"Beauty Salon",
            "type":"Services"
        }
    ],
    "sg:phone":"+1 720 488 8817",
    "sg:postcode":"80126",
    "sg:province":"CO",
    "sg:tags":[
        "hair",
        "accessory",
        "stylist",
        "supply"
    ],
    "sg:website":"http://www.icoloru.com",
    "wof:name":"I Color U",
    "wof:placetype":"venue"
},
  "geometry": {"coordinates":[-104.906499,39.56593],"type":"Point"}
}