{
  "type": "Feature",
  "properties": {
    "iso:country":"US",
    "sg:address":"1260 Market St",
    "sg:city":"Norwood",
    "sg:classifiers":[
        {
            "category":"Building & Trades",
            "subcategory":"Electrical",
            "type":"Services"
        }
    ],
    "sg:phone":"+1 970 327 4234",
    "sg:postcode":"81423",
    "sg:province":"CO",
    "sg:tags":[
        "electric",
        "contractor"
    ],
    "wof:name":"Odle Electric Svc",
    "wof:placetype":"venue"
},
  "geometry": {"coordinates":[-108.288466,38.130197],"type":"Point"}
}