{
  "type": "Feature",
  "properties": {
    "iso:country":"US",
    "sg:address":"2424 Hwy 6 and 50",
    "sg:city":"Grand Junction",
    "sg:classifiers":[
        {
            "category":"Shopping",
            "subcategory":"Clothing, Apparel, & Fashions",
            "type":"Retail Goods"
        }
    ],
    "sg:phone":"+1 970 243 5450",
    "sg:postcode":"81505",
    "sg:province":"CO",
    "wof:name":"Claires",
    "wof:placetype":"venue"
},
  "geometry": {"coordinates":[-108.60289,39.088955],"type":"Point"}
}