{
  "type": "Feature",
  "properties": {
    "iso:country":"US",
    "sg:address":"5436 S Riviera Way",
    "sg:city":"Aurora",
    "sg:classifiers":[
        {
            "category":"Education",
            "subcategory":"School",
            "type":"Public Place"
        }
    ],
    "sg:phone":"+1 720 886 1385",
    "sg:postcode":"80015",
    "sg:province":"CO",
    "wof:name":"I Team Outback",
    "wof:placetype":"venue"
},
  "geometry": {"coordinates":[-104.738704,39.619046],"type":"Point"}
}