{
  "type": "Feature",
  "properties": {
    "iso:country":"US",
    "sg:address":"11899 Paint Mine Rd",
    "sg:city":"Calhan",
    "sg:classifiers":[
        {
            "category":"Professional",
            "type":"Services"
        }
    ],
    "sg:phone":"+1 719 347 3280",
    "sg:postcode":"80808",
    "sg:province":"CO",
    "wof:name":"Robert J Haver",
    "wof:placetype":"venue"
},
  "geometry": {"coordinates":[-104.271582,39.004563],"type":"Point"}
}