{
  "type": "Feature",
  "properties": {
    "addr:full":"4633 S Fraser Ct Aurora CO 80015",
    "addr:housenumber":"4633",
    "addr:postcode":"80015",
    "addr:street":"S Fraser Ct",
    "iso:country":"US",
    "sg:address":"4633 S Fraser Ct",
    "sg:city":"Aurora",
    "sg:classifiers":[
        {
            "category":"Shopping",
            "subcategory":"Catalog Store",
            "type":"Retail Goods"
        },
        {
            "category":"Shopping",
            "subcategory":"Bicycles & Sporting Goods",
            "type":"Retail Goods"
        }
    ],
    "sg:phone":"+1 303 699 8121",
    "sg:postcode":"80015",
    "sg:province":"CO",
    "sg:tags":[
        "mail",
        "house"
    ],
    "wof:name":"J Foust Sports & Gear",
    "wof:placetype":"venue"
},
  "geometry": {"coordinates":[-104.81163100000001,39.632074],"type":"Point"}
}