{
  "type": "Feature",
  "properties": {
    "addr:full":"2330 Dunbar Ct Longmont CO 80501",
    "addr:housenumber":"2330",
    "addr:postcode":"80501",
    "addr:street":"Dunbar Ct",
    "iso:country":"US",
    "sg:address":"2330 Dunbar Ct",
    "sg:city":"Longmont",
    "sg:classifiers":[
        {
            "category":"Freight",
            "type":"Transportation"
        }
    ],
    "sg:phone":"+1 303 772 4399",
    "sg:postcode":"80501",
    "sg:province":"CO",
    "sg:tags":[
        "operator",
        "local",
        "trucking"
    ],
    "wof:name":"Arthur Kent Trucking",
    "wof:placetype":"venue"
},
  "geometry": {"coordinates":[-105.117356,40.199927],"type":"Point"}
}