{
  "type": "Feature",
  "properties": {
    "addr:full":"428 S 9th St Canon City CO 81212",
    "addr:housenumber":"428",
    "addr:postcode":"81212",
    "addr:street":"S 9Th St",
    "iso:country":"US",
    "sg:address":"428 S 9th St",
    "sg:city":"Canon City",
    "sg:classifiers":[
        {
            "category":"Retail",
            "subcategory":"Auto Rental",
            "type":"Services"
        }
    ],
    "sg:phone":"+1 719 269 1097",
    "sg:postcode":"81212",
    "sg:province":"CO",
    "sg:tags":[
        "renting",
        "truck",
        "leasing"
    ],
    "wof:name":"U-Haul Co",
    "wof:placetype":"venue"
},
  "geometry": {"coordinates":[-105.233379,38.440207],"type":"Point"}
}