{
  "type": "Feature",
  "properties": {
    "addr:full":"1885 Elk River Plz Steamboat Spgs CO 80487",
    "addr:housenumber":"1885",
    "addr:postcode":"80487",
    "addr:street":"Elk;Plz;Spgs",
    "iso:country":"US",
    "sg:address":"1885 Elk River Plz",
    "sg:city":"Steamboat Spgs",
    "sg:classifiers":[
        {
            "category":"Insurance",
            "subcategory":"Insurance Agent",
            "type":"Services"
        }
    ],
    "sg:phone":"+1 970 879 2355",
    "sg:postcode":"80487",
    "sg:province":"CO",
    "wof:name":"Brunton Insurance",
    "wof:placetype":"venue"
},
  "geometry": {"coordinates":[-106.855769,40.502362],"type":"Point"}
}