{
  "type": "Feature",
  "properties": {
    "iso:country":"US",
    "sg:address":"1713 E Lincoln Ave",
    "sg:city":"Fort Collins",
    "sg:classifiers":[
        {
            "category":"Building & Trades",
            "subcategory":"Electrical",
            "type":"Services"
        }
    ],
    "sg:phone":"+1 970 482 5218",
    "sg:postcode":"80524",
    "sg:province":"CO",
    "sg:tags":[
        "electrical",
        "electric",
        "contractor"
    ],
    "wof:name":"Glanz Electrical Contracting",
    "wof:placetype":"venue"
},
  "geometry": {"coordinates":[-105.043548,40.583276],"type":"Point"}
}