{
  "type": "Feature",
  "properties": {
    "iso:country":"US",
    "sg:address":"851 E Hwy 224",
    "sg:city":"Denver",
    "sg:classifiers":[
        {
            "category":"Retail",
            "subcategory":"Repair Shop",
            "type":"Services"
        }
    ],
    "sg:phone":"+1 303 287 2607",
    "sg:postcode":"80229",
    "sg:province":"CO",
    "sg:tags":[
        "automotive",
        "sales",
        "equipment"
    ],
    "wof:name":"Rocky Mountain CFC Eqp Svc",
    "wof:placetype":"venue"
},
  "geometry": {"coordinates":[-104.97122400000001,39.82529],"type":"Point"}
}