{
  "type": "Feature",
  "properties": {
    "iso:country":"US",
    "sg:address":"1900 Mount Zion Dr",
    "sg:city":"Golden",
    "sg:classifiers":[
        {
            "category":"Shopping",
            "subcategory":"Jewelry",
            "type":"Retail Goods"
        }
    ],
    "sg:phone":"+1 303 278 1845",
    "sg:postcode":"80401",
    "sg:province":"CO",
    "sg:tags":[
        "item",
        "other",
        "watch",
        "gift",
        "linen"
    ],
    "wof:name":"Yaz Jewelry and Gifts",
    "wof:placetype":"venue"
},
  "geometry": {"coordinates":[-105.22892899999999,39.746936],"type":"Point"}
}