{
  "type": "Feature",
  "properties": {
    "iso:country":"US",
    "sg:address":"13995 E Bellewood Dr",
    "sg:city":"Aurora",
    "sg:classifiers":[
        {
            "category":"Banks & Credit Unions",
            "subcategory":"Investment Brokerage",
            "type":"Services"
        }
    ],
    "sg:phone":"+1 303 699 0435",
    "sg:postcode":"80015",
    "sg:province":"CO",
    "sg:tags":[
        "commodity"
    ],
    "wof:name":"Lorand",
    "wof:placetype":"venue"
},
  "geometry": {"coordinates":[-104.82825699999999,39.62536],"type":"Point"}
}