{
  "type": "Feature",
  "properties": {
    "addr:full":"718 Main St Blanca CO 81123",
    "addr:housenumber":"718",
    "addr:postcode":"81123",
    "addr:street":"Main St",
    "iso:country":"US",
    "sg:address":"718 Main St",
    "sg:city":"Blanca",
    "sg:classifiers":[
        {
            "category":"Shopping",
            "type":"Retail Goods"
        }
    ],
    "sg:phone":"+1 719 379 2787",
    "sg:postcode":"81123",
    "sg:province":"CO",
    "sg:tags":[
        "merchandise"
    ],
    "wof:name":"Forest Tango Art Works",
    "wof:placetype":"venue"
},
  "geometry": {"coordinates":[-105.51521,37.435618],"type":"Point"}
}