{
  "type": "Feature",
  "properties": {
    "iso:country":"US",
    "sg:address":"56 Market Dr",
    "sg:city":"Eagle",
    "sg:classifiers":[
        {
            "category":"Shopping",
            "subcategory":"Used Merchandise",
            "type":"Retail Goods"
        },
        {
            "category":"Home & Garden",
            "subcategory":"Furniture",
            "type":"Retail Goods"
        }
    ],
    "sg:phone":"+1 970 328 1664",
    "sg:postcode":"81631",
    "sg:province":"CO",
    "sg:tags":[
        "shop",
        "consignment"
    ],
    "wof:name":"Treasures Quality Consignments",
    "wof:placetype":"venue"
},
  "geometry": {"coordinates":[-106.827096,39.662016],"type":"Point"}
}