{
  "type": "Feature",
  "properties": {
    "iso:country":"US",
    "sg:address":"15 S Wilcox St",
    "sg:city":"Castle Rock",
    "sg:classifiers":[
        {
            "category":"Manufacturing",
            "subcategory":"Chemicals & Compounds",
            "type":"Manufacturing & Wholesale Goods"
        }
    ],
    "sg:phone":"+1 303 841 9601",
    "sg:postcode":"80104",
    "sg:province":"CO",
    "sg:tags":[
        "preparation",
        "toilet",
        "mfg"
    ],
    "wof:name":"Tracy Copeland",
    "wof:placetype":"venue"
},
  "geometry": {"coordinates":[-104.86040300000001,39.368551],"type":"Point"}
}