{
  "type": "Feature",
  "properties": {
    "iso:country":"US",
    "sg:address":"11287 Ranch Pl",
    "sg:city":"Denver",
    "sg:classifiers":[
        {
            "category":"Professional",
            "subcategory":"Art Services",
            "type":"Services"
        }
    ],
    "sg:phone":"+1 303 465 1994",
    "sg:postcode":"80234",
    "sg:province":"CO",
    "sg:tags":[
        "photographer"
    ],
    "wof:name":"Dale Swenarton Photographics",
    "wof:placetype":"venue"
},
  "geometry": {"coordinates":[-105.012033,39.901472],"type":"Point"}
}