{
  "type": "Feature",
  "properties": {
    "addr:full":"19355 Elbert Rd Elbert CO 80106",
    "addr:housenumber":"19355",
    "addr:postcode":"80106",
    "addr:street":"Elbert Rd",
    "iso:country":"US",
    "sg:address":"19355 Elbert Rd",
    "sg:city":"Elbert",
    "sg:phone":"+1 719 749 9898",
    "sg:postcode":"80106",
    "sg:province":"CO",
    "sg:tags":[
        "gas"
    ],
    "wof:name":"American Propane",
    "wof:placetype":"venue"
},
  "geometry": {"coordinates":[-104.551908,39.112725],"type":"Point"}
}