{
  "type": "Feature",
  "properties": {
    "iso:country":"US",
    "sg:address":"5685 N Academy Blvd",
    "sg:city":"Colorado Springs",
    "sg:classifiers":[
        {
            "category":"Shopping",
            "type":"Retail Goods"
        }
    ],
    "sg:phone":"+1 719 264 9177",
    "sg:postcode":"80918",
    "sg:province":"CO",
    "sg:tags":[
        "merchandise"
    ],
    "wof:name":"Picture It Framed LLC",
    "wof:placetype":"venue"
},
  "geometry": {"coordinates":[-104.78805800000001,38.912271],"type":"Point"}
}