{
  "type": "Feature",
  "properties": {
    "addr:full":"310 Ash St Wray CO 80758",
    "addr:housenumber":"310",
    "addr:postcode":"80758",
    "addr:street":"Ash St",
    "iso:country":"US",
    "sg:address":"310 Ash St",
    "sg:city":"Wray",
    "sg:classifiers":[
        {
            "category":"Government",
            "subcategory":"Office",
            "type":"Public Place"
        }
    ],
    "sg:phone":"+1 970 332 5897",
    "sg:postcode":"80758",
    "sg:province":"CO",
    "wof:name":"Yuma County Motor Vehicle Dept",
    "wof:placetype":"venue"
},
  "geometry": {"coordinates":[-102.220652,40.078833],"type":"Point"}
}