{
  "type": "Feature",
  "properties": {
    "addr:full":"460 Harrison Ave Leadville CO 80461",
    "addr:housenumber":"460",
    "addr:postcode":"80461",
    "addr:street":"Harrison Ave",
    "iso:country":"US",
    "sg:address":"460 Harrison Ave",
    "sg:city":"Leadville",
    "sg:classifiers":[
        {
            "category":"Shopping",
            "subcategory":"Gifts & Souvenirs",
            "type":"Retail Goods"
        }
    ],
    "sg:phone":"+1 719 486 3718",
    "sg:postcode":"80461",
    "sg:province":"CO",
    "sg:tags":[
        "shop"
    ],
    "wof:name":"Memory Maker",
    "wof:placetype":"venue"
},
  "geometry": {"coordinates":[-106.291541,39.247989],"type":"Point"}
}