{
  "type": "Feature",
  "properties": {
    "addr:full":"601 E 64th Ave Denver CO 80229",
    "addr:housenumber":"601",
    "addr:postcode":"80229",
    "addr:street":"E 64Th Ave",
    "iso:country":"US",
    "sg:address":"601 E 64th Ave",
    "sg:city":"Denver",
    "sg:classifiers":[
        {
            "category":"Education",
            "subcategory":"University",
            "type":"Public Place"
        }
    ],
    "sg:phone":"+1 303 653 1960",
    "sg:postcode":"80229",
    "sg:province":"CO",
    "sg:tags":[
        "college"
    ],
    "wof:name":"Schools Public",
    "wof:placetype":"venue"
},
  "geometry": {"coordinates":[-104.979055,39.812905],"type":"Point"}
}