{
  "type": "Feature",
  "properties": {
    "addr:full":"1514 Old Squaw Pass Rd Evergreen CO 80439",
    "addr:housenumber":"1514",
    "addr:postcode":"80439",
    "addr:street":"Old Squaw Pass Rd",
    "iso:country":"US",
    "sg:address":"1514 Old Squaw Pass Rd",
    "sg:city":"Evergreen",
    "sg:classifiers":[
        {
            "category":"Building & Trades",
            "subcategory":"Construction",
            "type":"Services"
        }
    ],
    "sg:phone":"+1 303 674 6829",
    "sg:postcode":"80439",
    "sg:province":"CO",
    "sg:tags":[
        "house"
    ],
    "wof:name":"David Grasso Construction",
    "wof:placetype":"venue"
},
  "geometry": {"coordinates":[-105.40880199999999,39.691984],"type":"Point"}
}