{
  "type": "Feature",
  "properties": {
    "iso:country":"US",
    "sg:address":"10492 Co Rd 49",
    "sg:city":"Cheyenne Wells",
    "sg:classifiers":[
        {
            "category":"Organizations",
            "subcategory":"Religious Organization",
            "type":"Services"
        }
    ],
    "sg:phone":"+1 719 767 5549",
    "sg:postcode":"80810",
    "sg:province":"CO",
    "sg:tags":[
        "church"
    ],
    "wof:name":"Church Of Christ",
    "wof:placetype":"venue"
},
  "geometry": {"coordinates":[-102.25813599999999,38.762222],"type":"Point"}
}