{
  "type": "Feature",
  "properties": {
    "iso:country":"US",
    "sg:address":"9841 Co Rd 59",
    "sg:city":"Sterling",
    "sg:classifiers":[
        {
            "category":"Communications",
            "subcategory":"Television Station",
            "type":"Services"
        }
    ],
    "sg:phone":"+1 970 522 2729",
    "sg:postcode":"80751",
    "sg:province":"CO",
    "sg:tags":[
        "broadcasting",
        "co"
    ],
    "wof:name":"KUPN",
    "wof:placetype":"venue"
},
  "geometry": {"coordinates":[-103.028648,40.563058],"type":"Point"}
}