{
  "type": "Feature",
  "properties": {
    "addr:full":"3409 S Zuni St Sheridan CO 80110",
    "addr:housenumber":"3409",
    "addr:postcode":"80110",
    "addr:street":"S Zuni St",
    "iso:country":"US",
    "sg:address":"3409 S Zuni St",
    "sg:city":"Sheridan",
    "sg:classifiers":[
        {
            "category":"Wholesale",
            "subcategory":"Electrical",
            "type":"Manufacturing & Wholesale Goods"
        }
    ],
    "sg:phone":"+1 303 781 4085",
    "sg:postcode":"80110",
    "sg:province":"CO",
    "sg:tags":[
        "electric",
        "motor"
    ],
    "wof:name":"Electric Motor Rebuilders",
    "wof:placetype":"venue"
},
  "geometry": {"coordinates":[-105.015914,39.653789],"type":"Point"}
}