{
  "type": "Feature",
  "properties": {
    "addr:full":"451 E 58th Avenue Suite 2569 Denver CO 80216",
    "addr:housenumber":"451",
    "addr:postcode":"80216",
    "addr:street":"E 58Th Avenue Suite 2569",
    "iso:country":"US",
    "sg:address":"451 E 58th Avenue Suite 2569",
    "sg:city":"Denver",
    "sg:classifiers":[
        {
            "category":"Shopping",
            "subcategory":"Jewelry",
            "type":"Retail Goods"
        }
    ],
    "sg:phone":"+1 303 295 2082",
    "sg:postcode":"80216",
    "sg:province":"CO",
    "wof:name":"Select Lines International",
    "wof:placetype":"venue"
},
  "geometry": {"coordinates":[-104.980445,39.801991],"type":"Point"}
}