{
  "type": "Feature",
  "properties": {
    "addr:full":"2730 N 9th St Canon City CO 81212",
    "addr:housenumber":"2730",
    "addr:postcode":"81212",
    "addr:street":"N 9Th St",
    "iso:country":"US",
    "sg:address":"2730 N 9th St",
    "sg:city":"Canon City",
    "sg:classifiers":[
        {
            "category":"Building & Trades",
            "subcategory":"Construction",
            "type":"Services"
        }
    ],
    "sg:phone":"+1 719 275 3862",
    "sg:postcode":"81212",
    "sg:province":"CO",
    "sg:tags":[
        "house"
    ],
    "wof:name":"Cornella Builders",
    "wof:placetype":"venue"
},
  "geometry": {"coordinates":[-105.238688,38.464862],"type":"Point"}
}