{
  "type": "Feature",
  "properties": {
    "iso:country":"US",
    "sg:address":"6640 Gunpark Dr",
    "sg:city":"Boulder",
    "sg:classifiers":[
        {
            "category":"Wholesale",
            "subcategory":"Electrical",
            "type":"Manufacturing & Wholesale Goods"
        },
        {
            "category":"Wholesale",
            "subcategory":"Durable Goods & Equipment",
            "type":"Manufacturing & Wholesale Goods"
        }
    ],
    "sg:phone":"+1 303 581 4141",
    "sg:postcode":"80301",
    "sg:province":"CO",
    "sg:tags":[
        "electronic",
        "representative",
        "manufacturer"
    ],
    "wof:name":"AMI Semiconductor Inc",
    "wof:placetype":"venue"
},
  "geometry": {"coordinates":[-105.200112,40.069803],"type":"Point"}
}