{
  "type": "Feature",
  "properties": {
    "addr:full":"17722 S Golden Rd Golden CO 80401",
    "addr:housenumber":"17722",
    "addr:postcode":"80401",
    "addr:street":"S Golden Rd",
    "iso:country":"US",
    "sg:address":"17722 S Golden Rd",
    "sg:city":"Golden",
    "sg:classifiers":[
        {
            "category":"Shopping",
            "subcategory":"Used Merchandise",
            "type":"Retail Goods"
        }
    ],
    "sg:phone":"+1 303 271 9991",
    "sg:postcode":"80401",
    "sg:province":"CO",
    "sg:website":"www.goodwilldenver.org",
    "wof:name":"Goodwill Industries",
    "wof:placetype":"venue"
},
  "geometry": {"coordinates":[-105.20014999999999,39.741585],"type":"Point"}
}