{
  "type": "Feature",
  "properties": {
    "addr:full":"1655 Springcrest Rd Colorado Springs CO 80920",
    "addr:housenumber":"1655",
    "addr:postcode":"80920",
    "addr:street":"Springcrest Rd",
    "iso:country":"US",
    "sg:address":"1655 Springcrest Rd",
    "sg:city":"Colorado Springs",
    "sg:classifiers":[
        {
            "category":"Education",
            "subcategory":"School",
            "type":"Public Place"
        }
    ],
    "sg:phone":"+1 719 598 2246",
    "sg:postcode":"80920",
    "sg:province":"CO",
    "wof:name":"Mountain View Elem School",
    "wof:placetype":"venue"
},
  "geometry": {"coordinates":[-104.79796899999999,38.969358],"type":"Point"}
}