{
  "type": "Feature",
  "properties": {
    "iso:country":"US",
    "sg:address":"3250 S Newcombe St",
    "sg:city":"Denver",
    "sg:classifiers":[
        {
            "category":"Manufacturing",
            "subcategory":"Food",
            "type":"Manufacturing & Wholesale Goods"
        }
    ],
    "sg:phone":"+1 720 963 0555",
    "sg:postcode":"80227",
    "sg:province":"CO",
    "sg:tags":[
        "product",
        "mfg"
    ],
    "wof:name":"Dwarf Mountain Chocolates LLC",
    "wof:placetype":"venue"
},
  "geometry": {"coordinates":[-105.11803999999999,39.657187],"type":"Point"}
}