{
  "type": "Feature",
  "properties": {
    "addr:full":"3737 Canterbury Cir Broomfield CO 80020",
    "addr:housenumber":"3737",
    "addr:postcode":"80020",
    "addr:street":"Canterbury Cir",
    "iso:country":"US",
    "sg:address":"3737 Canterbury Cir",
    "sg:city":"Broomfield",
    "sg:classifiers":[
        {
            "category":"Building & Trades",
            "subcategory":"Construction",
            "type":"Services"
        }
    ],
    "sg:phone":"+1 303 375 1849",
    "sg:postcode":"80020",
    "sg:province":"CO",
    "sg:tags":[
        "project"
    ],
    "wof:name":"Pinnacle Construction",
    "wof:placetype":"venue"
},
  "geometry": {"coordinates":[-105.037564,39.92685],"type":"Point"}
}