{
  "type": "Feature",
  "properties": {
    "addr:full":"301 Main St Fort Morgan CO 80701",
    "addr:housenumber":"301",
    "addr:postcode":"80701",
    "addr:street":"Main St",
    "iso:country":"US",
    "sg:address":"301 Main St",
    "sg:city":"Fort Morgan",
    "sg:classifiers":[
        {
            "category":"Shopping",
            "subcategory":"Discount & Variety Stores",
            "type":"Retail Goods"
        }
    ],
    "sg:phone":"+1 970 867 8566",
    "sg:postcode":"80701",
    "sg:province":"CO",
    "sg:tags":[
        "merchandise",
        "general"
    ],
    "wof:name":"Fort Morgan Hardware",
    "wof:placetype":"venue"
},
  "geometry": {"coordinates":[-103.80149400000001,40.251239],"type":"Point"}
}