{
  "type": "Feature",
  "properties": {
    "addr:full":"611 22nd St Denver CO 80205",
    "addr:housenumber":"611",
    "addr:postcode":"80205",
    "addr:street":"22Nd St",
    "iso:country":"US",
    "sg:address":"611 22nd St",
    "sg:city":"Denver",
    "sg:classifiers":[
        {
            "category":"Shopping",
            "subcategory":"Shoes",
            "type":"Retail Goods"
        }
    ],
    "sg:phone":"+1 303 291 0854",
    "sg:postcode":"80205",
    "sg:province":"CO",
    "wof:name":"Zcoil",
    "wof:placetype":"venue"
},
  "geometry": {"coordinates":[-104.98480000000001,39.750771],"type":"Point"}
}