{
  "type": "Feature",
  "properties": {
    "addr:full":"1699 S Colorado Boulevard Denver CO 80222",
    "addr:housenumber":"1699",
    "addr:postcode":"80222",
    "addr:street":"S Colorado Boulevard",
    "iso:country":"US",
    "sg:address":"1699 S Colorado Boulevard",
    "sg:city":"Denver",
    "sg:classifiers":[
        {
            "category":"Restaurant",
            "type":"Food & Drink"
        }
    ],
    "sg:phone":"+1 303 756 6030",
    "sg:postcode":"80222",
    "sg:province":"CO",
    "sg:website":"www.quiznos.com",
    "wof:name":"Quizno's Subs",
    "wof:placetype":"venue"
},
  "geometry": {"coordinates":[-104.94085200000001,39.685585],"type":"Point"}
}