{
  "type": "Feature",
  "properties": {
    "iso:country":"US",
    "sg:address":"1271 Elmwood Ct",
    "sg:city":"Broomfield",
    "sg:classifiers":[
        {
            "category":"Wholesale",
            "subcategory":"Machinery & Supplies",
            "type":"Manufacturing & Wholesale Goods"
        }
    ],
    "sg:phone":"+1 303 439 2600",
    "sg:postcode":"80020",
    "sg:province":"CO",
    "sg:tags":[
        "equipment",
        "industrial"
    ],
    "wof:name":"Munro Supply",
    "wof:placetype":"venue"
},
  "geometry": {"coordinates":[-105.054169,39.935589],"type":"Point"}
}