{
  "type": "Feature",
  "properties": {
    "iso:country":"US",
    "sg:address":"440 Wadsworth Blvd",
    "sg:city":"Denver",
    "sg:classifiers":[
        {
            "category":"Restaurant",
            "type":"Food & Drink"
        }
    ],
    "sg:menulink":"http://www.allmenus.com/co/northeast-jefferson/128783-subway/menu/",
    "sg:phone":"+1 303 237 4690",
    "sg:postcode":"80226",
    "sg:province":"CO",
    "sg:tags":[
        "american",
        "sandwich"
    ],
    "wof:name":"Subway",
    "wof:placetype":"venue"
},
  "geometry": {"coordinates":[-105.080316,39.721614],"type":"Point"}
}