{
  "type": "Feature",
  "properties": {
    "iso:country":"US",
    "sg:address":"2211 Stout Street",
    "sg:city":"Denver",
    "sg:classifiers":[
        {
            "category":"Personal",
            "subcategory":"Barber",
            "type":"Services"
        }
    ],
    "sg:phone":"+1 303 294 9111",
    "sg:postcode":"80205",
    "sg:province":"CO",
    "wof:name":"Roffler Mile High",
    "wof:placetype":"venue"
},
  "geometry": {"coordinates":[-104.985781,39.751623],"type":"Point"}
}