{
  "type": "Feature",
  "properties": {
    "iso:country":"US",
    "sg:address":"3647 S King St",
    "sg:city":"Denver",
    "sg:classifiers":[
        {
            "category":"Autos & Motor Vehicles",
            "subcategory":"Automobile Sales",
            "type":"Retail Goods"
        }
    ],
    "sg:phone":"+1 303 781 3233",
    "sg:postcode":"80236",
    "sg:province":"CO",
    "sg:tags":[
        "used"
    ],
    "wof:name":"Bagby Motors",
    "wof:placetype":"venue"
},
  "geometry": {"coordinates":[-105.033424,39.65148],"type":"Point"}
}