{
  "type": "Feature",
  "properties": {
    "addr:full":"8174 Co Rd 7 Wiggins CO 80654",
    "addr:housenumber":"8174",
    "addr:postcode":"80654",
    "addr:street":"Co Rd 7 Wiggins",
    "iso:country":"US",
    "sg:address":"8174 Co Rd 7",
    "sg:city":"Wiggins",
    "sg:classifiers":[
        {
            "category":"Building & Trades",
            "subcategory":"Construction",
            "type":"Services"
        }
    ],
    "sg:phone":"+1 970 483 5513",
    "sg:postcode":"80654",
    "sg:province":"CO",
    "sg:tags":[
        "contractor"
    ],
    "wof:name":"Skeets Tile & Marble",
    "wof:placetype":"venue"
},
  "geometry": {"coordinates":[-104.018376,40.117995],"type":"Point"}
}