{
  "type": "Feature",
  "properties": {
    "addr:full":"7875 Montane Dr Colorado Springs CO 80920",
    "addr:housenumber":"7875",
    "addr:postcode":"80920",
    "addr:street":"Montane Dr",
    "iso:country":"US",
    "sg:address":"7875 Montane Dr",
    "sg:city":"Colorado Springs",
    "sg:classifiers":[
        {
            "category":"Organizations",
            "subcategory":"Religious Organization",
            "type":"Services"
        }
    ],
    "sg:phone":"+1 719 522 0220",
    "sg:postcode":"80920",
    "sg:province":"CO",
    "sg:tags":[
        "church"
    ],
    "sg:website":"www.cowboychurches.org",
    "wof:name":"Colorado Springs Cowboy Church",
    "wof:placetype":"venue"
},
  "geometry": {"coordinates":[-104.75511899999999,38.943698],"type":"Point"}
}