{
  "type": "Feature",
  "properties": {
    "addr:full":"8972 W 81st Ln Arvada CO 80005",
    "addr:housenumber":"8972",
    "addr:postcode":"80005",
    "addr:street":"W 81St Ln",
    "iso:country":"US",
    "sg:address":"8972 W 81st Ln",
    "sg:city":"Arvada",
    "sg:classifiers":[
        {
            "category":"Banks & Credit Unions",
            "subcategory":"Bank",
            "type":"Services"
        }
    ],
    "sg:phone":"+1 303 423 3780",
    "sg:postcode":"80005",
    "sg:province":"CO",
    "sg:tags":[
        "loan",
        "real estate"
    ],
    "sg:website":"www.achoiceloan.com",
    "wof:name":"Choice Financial Resources Inc",
    "wof:placetype":"venue"
},
  "geometry": {"coordinates":[-105.098761,39.843885],"type":"Point"}
}