{
  "type": "Feature",
  "properties": {
    "iso:country":"US",
    "sg:address":"299 Webster Ave",
    "sg:city":"Burlington",
    "sg:classifiers":[
        {
            "category":"Professional",
            "subcategory":"Accounting & Tax Preparation",
            "type":"Services"
        }
    ],
    "sg:phone":"+1 719 346 5432",
    "sg:postcode":"80807",
    "sg:province":"CO",
    "sg:tags":[
        "accountant"
    ],
    "wof:name":"Northeast Agri Svc",
    "wof:placetype":"venue"
},
  "geometry": {"coordinates":[-102.253643,39.307303],"type":"Point"}
}