{
  "type": "Feature",
  "properties": {
    "addr:full":"5684 W 88th Ave Westminster CO 80031",
    "addr:housenumber":"5684",
    "addr:postcode":"80031",
    "addr:street":"W 88Th Ave",
    "iso:country":"US",
    "sg:address":"5684 W 88th Ave",
    "sg:city":"Westminster",
    "sg:classifiers":[
        {
            "category":"Shopping",
            "subcategory":"Clothing, Apparel, & Fashions",
            "type":"Retail Goods"
        }
    ],
    "sg:phone":"+1 303 430 5664",
    "sg:postcode":"80031",
    "sg:province":"CO",
    "sg:tags":[
        "maternity"
    ],
    "wof:name":"Motherhood Maternity",
    "wof:placetype":"venue"
},
  "geometry": {"coordinates":[-105.059164,39.856365],"type":"Point"}
}