{
  "type": "Feature",
  "properties": {
    "iso:country":"US",
    "sg:address":"2240 S Broadway",
    "sg:city":"Denver",
    "sg:classifiers":[
        {
            "category":"Building & Trades",
            "subcategory":"Construction",
            "type":"Services"
        }
    ],
    "sg:phone":"+1 303 722 7183",
    "sg:postcode":"80210",
    "sg:province":"CO",
    "sg:tags":[
        "air",
        "heating",
        "conditioning/hvac"
    ],
    "sg:website":"www.buildersheating.com/",
    "wof:name":"Builders Heating & Air Conditioning Company",
    "wof:placetype":"venue"
},
  "geometry": {"coordinates":[-104.987712,39.676145],"type":"Point"}
}