{
  "type": "Feature",
  "properties": {
    "iso:country":"US",
    "sg:address":"4225 Strasburg Rd",
    "sg:city":"Strasburg",
    "sg:classifiers":[
        {
            "category":"Wholesale",
            "subcategory":"Machinery & Supplies",
            "type":"Manufacturing & Wholesale Goods"
        }
    ],
    "sg:phone":"+1 303 622 4207",
    "sg:postcode":"80136",
    "sg:province":"CO",
    "sg:tags":[
        "farm",
        "equipment"
    ],
    "sg:website":"www.strasburgequipment.com",
    "wof:name":"Strasburg Equipment Co",
    "wof:placetype":"venue"
},
  "geometry": {"coordinates":[-104.322898,39.638517],"type":"Point"}
}