{
  "type": "Feature",
  "properties": {
    "iso:country":"US",
    "sg:address":"1300 S Willow Street Apt 8302",
    "sg:city":"Denver",
    "sg:classifiers":[
        {
            "category":"Real Estate",
            "subcategory":"Real Estate Operator",
            "type":"Services"
        }
    ],
    "sg:phone":"+1 720 744 9700",
    "sg:postcode":"80247",
    "sg:province":"CO",
    "sg:tags":[
        "apartment"
    ],
    "wof:name":"Devon Square",
    "wof:placetype":"venue"
},
  "geometry": {"coordinates":[-104.88817,39.692887],"type":"Point"}
}