{
  "type": "Feature",
  "properties": {
    "addr:full":"9380 E Aspen Hill Pl Lone Tree CO 80124",
    "addr:housenumber":"9380",
    "addr:postcode":"80124",
    "addr:street":"E Aspen Hill Pl",
    "iso:country":"US",
    "sg:address":"9380 E Aspen Hill Pl",
    "sg:city":"Lone Tree",
    "sg:classifiers":[
        {
            "category":"Professional",
            "subcategory":"Accounting & Tax Preparation",
            "type":"Services"
        }
    ],
    "sg:phone":"+1 303 220 2553",
    "sg:postcode":"80124",
    "sg:province":"CO",
    "sg:tags":[
        "accountant"
    ],
    "wof:name":"Carlton Hargett CPA",
    "wof:placetype":"venue"
},
  "geometry": {"coordinates":[-104.879734,39.549894],"type":"Point"}
}