{
  "type": "Feature",
  "properties": {
    "iso:country":"US",
    "sg:address":"12390 Richardson Ln",
    "sg:city":"Peyton",
    "sg:classifiers":[
        {
            "category":"Insurance",
            "subcategory":"Insurance Agent",
            "type":"Services"
        }
    ],
    "sg:phone":"+1 719 683 4919",
    "sg:postcode":"80831",
    "sg:province":"CO",
    "wof:name":"Springs Property Ins",
    "wof:placetype":"venue"
},
  "geometry": {"coordinates":[-104.595581,38.909584],"type":"Point"}
}