{
  "type": "Feature",
  "properties": {
    "addr:full":"2780 Landingview Ln Grand Junction CO 81506",
    "addr:housenumber":"2780",
    "addr:postcode":"81506",
    "addr:street":"Landingview Ln",
    "iso:country":"US",
    "sg:address":"2780 Landingview Ln",
    "sg:city":"Grand Junction",
    "sg:classifiers":[
        {
            "category":"Professional",
            "subcategory":"Engineering",
            "type":"Services"
        }
    ],
    "sg:phone":"+1 970 243 1800",
    "sg:postcode":"81506",
    "sg:province":"CO",
    "sg:tags":[
        "operator",
        "aviation",
        "fixed",
        "based"
    ],
    "wof:name":"Timberline Aviation LLC",
    "wof:placetype":"venue"
},
  "geometry": {"coordinates":[-108.535608,39.125885],"type":"Point"}
}