{
  "type": "Feature",
  "properties": {
    "addr:full":"100 Valley View Way Boulder CO 80304",
    "addr:housenumber":"100",
    "addr:postcode":"80304",
    "addr:street":"Valley View Way",
    "iso:country":"US",
    "sg:address":"100 Valley View Way",
    "sg:city":"Boulder",
    "sg:classifiers":[
        {
            "category":"Banks & Credit Unions",
            "subcategory":"Financial Services",
            "type":"Services"
        }
    ],
    "sg:phone":"+1 303 447 8330",
    "sg:postcode":"80304",
    "sg:province":"CO",
    "sg:tags":[
        "investor"
    ],
    "wof:name":"Gulf Coast Investment Partners",
    "wof:placetype":"venue"
},
  "geometry": {"coordinates":[-105.30391,40.055012],"type":"Point"}
}