{
  "type": "Feature",
  "properties": {
    "iso:country":"US",
    "sg:address":"546 Main Ave",
    "sg:city":"Durango",
    "sg:classifiers":[
        {
            "category":"Shopping",
            "subcategory":"Clothing, Apparel, & Fashions",
            "type":"Retail Goods"
        }
    ],
    "sg:phone":"+1 970 259 2005",
    "sg:postcode":"81301",
    "sg:province":"CO",
    "sg:tags":[
        "leather",
        "sheepskin",
        "specialty",
        "outerwear"
    ],
    "sg:website":"www.overland.com",
    "wof:name":"Overland Sheepskin Co",
    "wof:placetype":"venue"
},
  "geometry": {"coordinates":[-107.881844,37.269643],"type":"Point"}
}