{
  "type": "Feature",
  "properties": {
    "addr:full":"30 Colorado Ave Montrose CO 81401",
    "addr:housenumber":"30",
    "addr:postcode":"81401",
    "addr:street":"Colorado Ave",
    "iso:country":"US",
    "sg:address":"30 Colorado Ave",
    "sg:city":"Montrose",
    "sg:classifiers":[
        {
            "category":"Organizations",
            "subcategory":"Religious Organization",
            "type":"Services"
        }
    ],
    "sg:phone":"+1 970 249 4262",
    "sg:postcode":"81401",
    "sg:province":"CO",
    "sg:tags":[
        "church"
    ],
    "wof:name":"Gateway Pentecostal Church-God",
    "wof:placetype":"venue"
},
  "geometry": {"coordinates":[-107.873012,38.470122],"type":"Point"}
}