{
  "type": "Feature",
  "properties": {
    "iso:country":"US",
    "sg:address":"3004 W Colorado Ave",
    "sg:city":"Colorado Springs",
    "sg:classifiers":[
        {
            "category":"Food & Beverages",
            "subcategory":"Groceries & Convenience Stores",
            "type":"Retail Goods"
        }
    ],
    "sg:phone":"+1 719 635 0142",
    "sg:postcode":"80904",
    "sg:province":"CO",
    "sg:website":"www.7-eleven.com",
    "wof:name":"Seven Eleven Store",
    "wof:placetype":"venue"
},
  "geometry": {"coordinates":[-104.870242,38.852012],"type":"Point"}
}