{
  "type": "Feature",
  "properties": {
    "addr:full":"1625 Miner St Idaho Springs CO 80452",
    "addr:housenumber":"1625",
    "addr:postcode":"80452",
    "addr:street":"Miner St",
    "iso:country":"US",
    "sg:address":"1625 Miner St",
    "sg:city":"Idaho Springs",
    "sg:classifiers":[
        {
            "category":"Health Services",
            "subcategory":"Dentist",
            "type":"Services"
        }
    ],
    "sg:phone":"+1 303 567 4412",
    "sg:postcode":"80452",
    "sg:province":"CO",
    "sg:website":"www.drescherdental.com",
    "wof:name":"Drescher David DMD",
    "wof:placetype":"venue"
},
  "geometry": {"coordinates":[-105.515672,39.742024],"type":"Point"}
}