{
  "type": "Feature",
  "properties": {
    "iso:country":"US",
    "sg:address":"1549 Lefthand Dr",
    "sg:city":"Longmont",
    "sg:classifiers":[
        {
            "category":"Building & Trades",
            "subcategory":"Landscaping Services",
            "type":"Services"
        }
    ],
    "sg:phone":"+1 303 682 0456",
    "sg:postcode":"80501",
    "sg:province":"CO",
    "sg:tags":[
        "landscape",
        "contractor"
    ],
    "wof:name":"Rodriguez Landscaping",
    "wof:placetype":"venue"
},
  "geometry": {"coordinates":[-105.117875,40.139752],"type":"Point"}
}