{
  "type": "Feature",
  "properties": {
    "addr:full":"3824 Wright St Wheat Ridge CO 80033",
    "addr:housenumber":"3824",
    "addr:postcode":"80033",
    "addr:street":"Wright St",
    "iso:country":"US",
    "sg:address":"3824 Wright St",
    "sg:city":"Wheat Ridge",
    "sg:classifiers":[
        {
            "category":"Wholesale",
            "subcategory":"Drugs",
            "type":"Manufacturing & Wholesale Goods"
        }
    ],
    "sg:phone":"+1 303 431 2714",
    "sg:postcode":"80033",
    "sg:province":"CO",
    "wof:name":"Floyd Littlepage",
    "wof:placetype":"venue"
},
  "geometry": {"coordinates":[-105.13923800000001,39.76847],"type":"Point"}
}