{
  "type": "Feature",
  "properties": {
    "iso:country":"US",
    "sg:address":"12564 W 83rd Way",
    "sg:city":"Arvada",
    "sg:classifiers":[
        {
            "category":"Utilities",
            "subcategory":"Electric",
            "type":"Services"
        }
    ],
    "sg:phone":"+1 303 940 7331",
    "sg:postcode":"80005",
    "sg:province":"CO",
    "wof:name":"Hometown Connections",
    "wof:placetype":"venue"
},
  "geometry": {"coordinates":[-105.142349,39.848042],"type":"Point"}
}