{
  "type": "Feature",
  "properties": {
    "addr:full":"2530 E County Line Rd Littleton CO 80126",
    "addr:housenumber":"2530",
    "addr:postcode":"80126",
    "addr:street":"E County Line Rd",
    "iso:country":"US",
    "sg:address":"2530 E County Line Rd",
    "sg:city":"Littleton",
    "sg:classifiers":[
        {
            "category":"Bars & Pubs",
            "type":"Food & Drink"
        },
        {
            "category":"Shopping",
            "subcategory":"Party Supplies",
            "type":"Retail Goods"
        },
        {
            "category":"Sports & Exercise",
            "subcategory":"Bowling",
            "type":"Entertainment"
        }
    ],
    "sg:phone":"+1 303 779 5599",
    "sg:postcode":"80126",
    "sg:province":"CO",
    "sg:tags":[
        "children's",
        "planning"
    ],
    "sg:website":"http://www.amf.com",
    "wof:name":"AMF Littleton Lanes",
    "wof:placetype":"venue"
},
  "geometry": {"coordinates":[-104.95474,39.566119],"type":"Point"}
}