{
  "type": "Feature",
  "properties": {
    "addr:full":"509 N Main St Fountain CO 80817",
    "addr:housenumber":"509",
    "addr:postcode":"80817",
    "addr:street":"N Main St",
    "iso:country":"US",
    "sg:address":"509 N Main St",
    "sg:city":"Fountain",
    "sg:classifiers":[
        {
            "category":"Organizations",
            "subcategory":"Professional Association",
            "type":"Services"
        }
    ],
    "sg:phone":"+1 719 382 7290",
    "sg:postcode":"80817",
    "sg:province":"CO",
    "wof:name":"Masonic Af AM Temples",
    "wof:placetype":"venue"
},
  "geometry": {"coordinates":[-104.700772,38.686193],"type":"Point"}
}