{
  "type": "Feature",
  "properties": {
    "addr:full":"115 E Vermijo Ave Colorado Springs CO 80903",
    "addr:housenumber":"115",
    "addr:postcode":"80903",
    "addr:street":"E Vermijo Ave",
    "iso:country":"US",
    "sg:address":"115 E Vermijo Ave",
    "sg:city":"Colorado Springs",
    "sg:classifiers":[
        {
            "category":"Professional",
            "subcategory":"Business Services",
            "type":"Services"
        }
    ],
    "sg:phone":"+1 719 578 0331",
    "sg:postcode":"80903",
    "sg:province":"CO",
    "sg:tags":[
        "translator",
        "organization",
        "religious",
        "interpreter"
    ],
    "sg:website":"www.prontocom.com",
    "wof:name":"Prontocom",
    "wof:placetype":"venue"
},
  "geometry": {"coordinates":[-104.821877,38.829416],"type":"Point"}
}