{
  "type": "Feature",
  "properties": {
    "iso:country":"US",
    "sg:address":"5585 Erindale Dr",
    "sg:city":"Colorado Springs",
    "sg:classifiers":[
        {
            "category":"Insurance",
            "subcategory":"Insurance Agent",
            "type":"Services"
        }
    ],
    "sg:phone":"+1 719 226 0499",
    "sg:postcode":"80918",
    "sg:province":"CO",
    "wof:name":"Rainwater Insurance Agency",
    "wof:placetype":"venue"
},
  "geometry": {"coordinates":[-104.78541199999999,38.912495],"type":"Point"}
}