{
  "type": "Feature",
  "properties": {
    "addr:full":"91 Beaver Creek Pl Avon CO 81620",
    "addr:housenumber":"91",
    "addr:postcode":"81620",
    "addr:street":"Beaver Creek Pl",
    "iso:country":"US",
    "sg:address":"91 Beaver Creek Pl",
    "sg:city":"Avon",
    "sg:classifiers":[
        {
            "category":"Cinema",
            "subcategory":"Movie Rental",
            "type":"Entertainment"
        }
    ],
    "sg:phone":"+1 970 949 0400",
    "sg:postcode":"81620",
    "sg:province":"CO",
    "sg:tags":[
        "leasing",
        "video",
        "disc",
        "tape"
    ],
    "wof:name":"Box Office Video",
    "wof:placetype":"venue"
},
  "geometry": {"coordinates":[-106.519991,39.634113],"type":"Point"}
}