{
  "type": "Feature",
  "properties": {
    "iso:country":"US",
    "sg:address":"2433 Central Ave",
    "sg:city":"Canon City",
    "sg:classifiers":[
        {
            "category":"Autos & Motor Vehicles",
            "subcategory":"Automobile Sales",
            "type":"Retail Goods"
        }
    ],
    "sg:phone":"+1 719 275 6275",
    "sg:postcode":"81212",
    "sg:province":"CO",
    "sg:tags":[
        "car",
        "dealer"
    ],
    "wof:name":"Wells Motors",
    "wof:placetype":"venue"
},
  "geometry": {"coordinates":[-105.211524,38.459488],"type":"Point"}
}