{
  "type": "Feature",
  "properties": {
    "iso:country":"US",
    "sg:address":"671 Garrison St",
    "sg:city":"Denver",
    "sg:classifiers":[
        {
            "category":"Wholesale",
            "subcategory":"Groceries",
            "type":"Manufacturing & Wholesale Goods"
        }
    ],
    "sg:phone":"+1 303 202 2192",
    "sg:postcode":"80215",
    "sg:province":"CO",
    "wof:name":"Princeton International Inc",
    "wof:placetype":"venue"
},
  "geometry": {"coordinates":[-105.10031499999999,39.726454],"type":"Point"}
}