{
  "type": "Feature",
  "properties": {
    "addr:full":"2414 4th Ave Greeley CO 80631",
    "addr:housenumber":"2414",
    "addr:postcode":"80631",
    "addr:street":"4Th Ave",
    "iso:country":"US",
    "sg:address":"2414 4th Ave",
    "sg:city":"Greeley",
    "sg:classifiers":[
        {
            "category":"Professional",
            "subcategory":"Management & Consulting",
            "type":"Services"
        }
    ],
    "sg:phone":"+1 970 353 6200",
    "sg:postcode":"80631",
    "sg:province":"CO",
    "sg:tags":[
        "order"
    ],
    "wof:name":"Technipak LLC",
    "wof:placetype":"venue"
},
  "geometry": {"coordinates":[-104.684252,40.400969],"type":"Point"}
}