{
  "type": "Feature",
  "properties": {
    "iso:country":"US",
    "sg:address":"82 Co Rd 113",
    "sg:city":"Carbondale",
    "sg:classifiers":[
        {
            "category":"Retail",
            "subcategory":"Repair Shop",
            "type":"Services"
        }
    ],
    "sg:phone":"+1 970 945 0893",
    "sg:postcode":"81623",
    "sg:province":"CO",
    "sg:tags":[
        "welding"
    ],
    "wof:name":"Western Forge",
    "wof:placetype":"venue"
},
  "geometry": {"coordinates":[-107.261836,39.457413],"type":"Point"}
}