{
  "type": "Feature",
  "properties": {
    "iso:country":"US",
    "sg:address":"500 Edison St",
    "sg:city":"Brush",
    "sg:classifiers":[
        {
            "category":"Retail",
            "subcategory":"Auto Repair",
            "type":"Services"
        }
    ],
    "sg:phone":"+1 970 842 5818",
    "sg:postcode":"80723",
    "sg:province":"CO",
    "sg:tags":[
        "repairing",
        "automobile"
    ],
    "wof:name":"Brush Auto Repair",
    "wof:placetype":"venue"
},
  "geometry": {"coordinates":[-103.62527300000001,40.255274],"type":"Point"}
}