{
  "type": "Feature",
  "properties": {
    "iso:country":"US",
    "sg:address":"4830 Trailmark Loop",
    "sg:city":"Colorado Springs",
    "sg:classifiers":[
        {
            "category":"Professional",
            "subcategory":"Business Services",
            "type":"Services"
        }
    ],
    "sg:phone":"+1 719 380 0878",
    "sg:postcode":"80916",
    "sg:province":"CO",
    "sg:tags":[
        "drafting"
    ],
    "wof:name":"Cadventures",
    "wof:placetype":"venue"
},
  "geometry": {"coordinates":[-104.738463,38.819682],"type":"Point"}
}