{
  "type": "Feature",
  "properties": {
    "iso:country":"US",
    "sg:address":"1805 Kipling St",
    "sg:city":"Denver",
    "sg:classifiers":[
        {
            "category":"Real Estate",
            "subcategory":"Real Estate Agent",
            "type":"Services"
        }
    ],
    "sg:phone":"+1 303 432 2425",
    "sg:postcode":"80215",
    "sg:province":"CO",
    "sg:tags":[
        "appraiser"
    ],
    "wof:name":"Proficient Appraisals",
    "wof:placetype":"venue"
},
  "geometry": {"coordinates":[-105.109644,39.745429],"type":"Point"}
}