{
  "type": "Feature",
  "properties": {
    "iso:country":"US",
    "sg:address":"125 Wilcox Street",
    "sg:city":"Castle Rock",
    "sg:classifiers":[
        {
            "category":"Personal",
            "subcategory":"Tattoo Parlor",
            "type":"Services"
        }
    ],
    "sg:phone":"+1 720 733 2134",
    "sg:postcode":"80104",
    "sg:province":"CO",
    "wof:name":"Red Sky Tattoo",
    "wof:placetype":"venue"
},
  "geometry": {"coordinates":[-104.860134,39.370737],"type":"Point"}
}