{
  "type": "Feature",
  "properties": {
    "iso:country":"US",
    "sg:address":"28082 Co Rd 10.75",
    "sg:city":"Las Animas",
    "sg:classifiers":[
        {
            "category":"Real Estate",
            "subcategory":"Developer",
            "type":"Services"
        }
    ],
    "sg:phone":"+1 719 456 0617",
    "sg:postcode":"81054",
    "sg:province":"CO",
    "sg:tags":[
        "cemetery"
    ],
    "wof:name":"Las Animas Cemetery",
    "wof:placetype":"venue"
},
  "geometry": {"coordinates":[-103.220485,38.043095],"type":"Point"}
}