{
  "type": "Feature",
  "properties": {
    "addr:full":"1302 E 6th Avenue Denver CO 80218",
    "addr:housenumber":"1302",
    "addr:postcode":"80218",
    "addr:street":"E 6Th Avenue",
    "iso:country":"US",
    "sg:address":"1302 E 6th Avenue",
    "sg:city":"Denver",
    "sg:classifiers":[
        {
            "category":"Food & Beverages",
            "subcategory":"Liquor & Beverages",
            "type":"Retail Goods"
        }
    ],
    "sg:phone":"+1 303 744 6219",
    "sg:postcode":"80218",
    "sg:province":"CO",
    "sg:tags":[
        "beer",
        "spirit",
        "wine"
    ],
    "wof:name":"Joy Wine & Spirits",
    "wof:placetype":"venue"
},
  "geometry": {"coordinates":[-104.971338,39.725488],"type":"Point"}
}