{
  "type": "Feature",
  "properties": {
    "addr:full":"18581 E Hampden Ave Aurora CO 80013",
    "addr:housenumber":"18581",
    "addr:postcode":"80013",
    "addr:street":"E Hampden Ave",
    "iso:country":"US",
    "sg:address":"18581 E Hampden Ave",
    "sg:city":"Aurora",
    "sg:classifiers":[
        {
            "category":"Restaurant",
            "type":"Food & Drink"
        }
    ],
    "sg:phone":"+1 303 690 7738",
    "sg:postcode":"80013",
    "sg:province":"CO",
    "sg:tags":[
        "eating"
    ],
    "wof:name":"Royal Hilltop",
    "wof:placetype":"venue"
},
  "geometry": {"coordinates":[-104.768429,39.653088],"type":"Point"}
}