{
  "type": "Feature",
  "properties": {
    "addr:full":"4295 Kipling St Wheat Ridge CO 80033",
    "addr:housenumber":"4295",
    "addr:postcode":"80033",
    "addr:street":"Kipling St",
    "iso:country":"US",
    "sg:address":"4295 Kipling St",
    "sg:city":"Wheat Ridge",
    "sg:classifiers":[
        {
            "category":"Manufacturing",
            "subcategory":"Tools & Machinery",
            "type":"Manufacturing & Wholesale Goods"
        }
    ],
    "sg:phone":"+1 303 431 7973",
    "sg:postcode":"80033",
    "sg:province":"CO",
    "sg:tags":[
        "performance",
        "parts",
        "aftermarket"
    ],
    "wof:name":"Automotive Transm Specialist",
    "wof:placetype":"venue"
},
  "geometry": {"coordinates":[-105.109692,39.775683],"type":"Point"}
}