{
  "type": "Feature",
  "properties": {
    "iso:country":"US",
    "sg:address":"23976 Co Hwy 50",
    "sg:city":"Fraser",
    "sg:classifiers":[
        {
            "category":"Building & Trades",
            "subcategory":"Construction",
            "type":"Services"
        }
    ],
    "sg:phone":"+1 970 726 4440",
    "sg:postcode":"80482",
    "sg:province":"CO",
    "sg:tags":[
        "wallpaper"
    ],
    "wof:name":"Ready Rollers Painting Co",
    "wof:placetype":"venue"
},
  "geometry": {"coordinates":[-105.840201,39.948155],"type":"Point"}
}