{
  "type": "Feature",
  "properties": {
    "addr:full":"410 W Garden of the Gods Rd Colorado Springs CO 80907",
    "addr:housenumber":"410",
    "addr:postcode":"springs;80907",
    "addr:street":"W Garden Of The Gods Rd",
    "iso:country":"US",
    "sg:address":"410 W Garden of the Gods Rd",
    "sg:city":"Colorado Springs",
    "sg:classifiers":[
        {
            "category":"Autos & Motor Vehicles",
            "subcategory":"Automobile Sales",
            "type":"Retail Goods"
        }
    ],
    "sg:phone":"+1 719 548 8811",
    "sg:postcode":"80907",
    "sg:province":"CO",
    "sg:tags":[
        "car",
        "used",
        "rental",
        "passenger"
    ],
    "wof:name":"Garden of God Auto Sales",
    "wof:placetype":"venue"
},
  "geometry": {"coordinates":[-104.827949,38.896968],"type":"Point"}
}