{
  "type": "Feature",
  "properties": {
    "addr:full":"410 Cascadilla St Crested Butte CO 81224",
    "addr:housenumber":"410",
    "addr:postcode":"81224",
    "addr:street":"Cascadilla St",
    "iso:country":"US",
    "sg:address":"410 Cascadilla St",
    "sg:city":"Crested Butte",
    "sg:classifiers":[
        {
            "category":"Building & Trades",
            "subcategory":"Electrical",
            "type":"Services"
        }
    ],
    "sg:phone":"+1 970 349 6805",
    "sg:postcode":"81224",
    "sg:province":"CO",
    "sg:tags":[
        "electrical",
        "contractor"
    ],
    "wof:name":"Kuby Electrical Inc",
    "wof:placetype":"venue"
},
  "geometry": {"coordinates":[-106.88826299999999,38.81181],"type":"Point"}
}