{
  "type": "Feature",
  "properties": {
    "iso:country":"US",
    "sg:address":"411 Valley Rd",
    "sg:city":"Canon City",
    "sg:classifiers":[
        {
            "category":"Retail",
            "subcategory":"Auto Repair",
            "type":"Services"
        }
    ],
    "sg:phone":"+1 719 269 8839",
    "sg:postcode":"81212",
    "sg:province":"CO",
    "sg:tags":[
        "wrecker"
    ],
    "wof:name":"Ameri Tow LLC",
    "wof:placetype":"venue"
},
  "geometry": {"coordinates":[-105.248133,38.417448],"type":"Point"}
}