{
  "type": "Feature",
  "properties": {
    "iso:country":"US",
    "sg:address":"2121 S Oneida St",
    "sg:city":"Denver",
    "sg:classifiers":[
        {
            "category":"Health Services",
            "subcategory":"Health Practitioner",
            "type":"Services"
        }
    ],
    "sg:phone":"+1 303 759 2844",
    "sg:postcode":"80224",
    "sg:province":"CO",
    "sg:tags":[
        "psychologist"
    ],
    "wof:name":"Jennifer Bugg Psyd",
    "wof:placetype":"venue"
},
  "geometry": {"coordinates":[-104.908281,39.677731],"type":"Point"}
}