{
  "type": "Feature",
  "properties": {
    "addr:full":"1115 Grant St. #303 Denver CO 80203",
    "addr:housenumber":"1115",
    "addr:postcode":"80203",
    "addr:street":"Grant St. # 303",
    "iso:country":"US",
    "sg:address":"1115 Grant St. #303",
    "sg:city":"Denver",
    "sg:classifiers":[
        {
            "category":"Health Services",
            "subcategory":"Clinic",
            "type":"Services"
        }
    ],
    "sg:phone":"+1 303 681 7913",
    "sg:postcode":"80203",
    "sg:province":"CO",
    "sg:tags":[
        "counseling",
        "mental"
    ],
    "sg:website":"www.erinbrumleve.com",
    "wof:name":"Denver Art Therapy Counseling Co. , LLC",
    "wof:placetype":"venue"
},
  "geometry": {"coordinates":[-104.98399499999999,39.734148],"type":"Point"}
}