{
  "type": "Feature",
  "properties": {
    "iso:country":"US",
    "sg:address":"220 E Rogers Rd",
    "sg:city":"Longmont",
    "sg:classifiers":[
        {
            "category":"Shopping",
            "subcategory":"Pharmacy",
            "type":"Retail Goods"
        }
    ],
    "sg:phone":"+1 303 776 9589",
    "sg:postcode":"80501",
    "sg:province":"CO",
    "wof:name":"Associated Pharmacists",
    "wof:placetype":"venue"
},
  "geometry": {"coordinates":[-105.08689699999999,40.162339],"type":"Point"}
}