{
  "type": "Feature",
  "properties": {
    "addr:full":"122 W 4th St Wray CO 80758",
    "addr:housenumber":"122",
    "addr:postcode":"80758",
    "addr:street":"W 4Th St",
    "iso:country":"US",
    "sg:address":"122 W 4th St",
    "sg:city":"Wray",
    "sg:classifiers":[
        {
            "category":"Personal",
            "subcategory":"Barber",
            "type":"Services"
        }
    ],
    "sg:phone":"+1 970 332 0660",
    "sg:postcode":"80758",
    "sg:province":"CO",
    "wof:name":"Bob's Barber Shop",
    "wof:placetype":"venue"
},
  "geometry": {"coordinates":[-102.222509,40.077869],"type":"Point"}
}