{
  "type": "Feature",
  "properties": {
    "addr:full":"7050 N Academy Blvd Colorado Springs CO 80920",
    "addr:housenumber":"7050",
    "addr:postcode":"80920",
    "addr:street":"N Academy Blvd",
    "iso:country":"US",
    "sg:address":"7050 N Academy Blvd",
    "sg:city":"Colorado Springs",
    "sg:classifiers":[
        {
            "category":"Autos & Motor Vehicles",
            "subcategory":"Fuel & Gas Station",
            "type":"Retail Goods"
        }
    ],
    "sg:phone":"+1 719 599 9559",
    "sg:postcode":"80920",
    "sg:province":"CO",
    "sg:tags":[
        "grocery",
        "station",
        "gasoline"
    ],
    "wof:name":"Shell Oil Products U S",
    "wof:placetype":"venue"
},
  "geometry": {"coordinates":[-104.796587,38.93294],"type":"Point"}
}