{
  "type": "Feature",
  "properties": {
    "iso:country":"US",
    "sg:address":"703 Stagecoach Dr",
    "sg:city":"Canon City",
    "sg:classifiers":[
        {
            "category":"Professional",
            "subcategory":"Accounting & Tax Preparation",
            "type":"Services"
        }
    ],
    "sg:phone":"+1 719 276 0688",
    "sg:postcode":"81212",
    "sg:province":"CO",
    "sg:tags":[
        "return",
        "filing"
    ],
    "wof:name":"Abbott Accounting & Tax Svc",
    "wof:placetype":"venue"
},
  "geometry": {"coordinates":[-105.215065,38.45779],"type":"Point"}
}