{
  "type": "Feature",
  "properties": {
    "addr:full":"3161 Johnson Ln Erie CO 80516",
    "addr:housenumber":"3161",
    "addr:postcode":"80516",
    "addr:street":"Johnson Ln",
    "iso:country":"US",
    "sg:address":"3161 Johnson Ln",
    "sg:city":"Erie",
    "sg:classifiers":[
        {
            "category":"Building & Trades",
            "subcategory":"Landscaping Services",
            "type":"Services"
        }
    ],
    "sg:phone":"+1 303 412 6701",
    "sg:postcode":"80516",
    "sg:province":"CO",
    "sg:tags":[
        "landscape",
        "contractor"
    ],
    "wof:name":"Green Valley Landscape & Lawn",
    "wof:placetype":"venue"
},
  "geometry": {"coordinates":[-104.989864,40.011324],"type":"Point"}
}