{
  "type": "Feature",
  "properties": {
    "iso:country":"US",
    "sg:address":"3801 E Florida Ave Ste 400",
    "sg:city":"Denver",
    "sg:classifiers":[
        {
            "category":"Professional",
            "subcategory":"Lawyer & Legal Services",
            "type":"Services"
        }
    ],
    "sg:phone":"+1 303 395 9227",
    "sg:postcode":"80210",
    "sg:province":"CO",
    "sg:tags":[
        "attorney",
        "law",
        "bankruptcy"
    ],
    "sg:website":"http://www.afmlaw.net",
    "wof:name":"Andrew McKenna, Attorney At Law",
    "wof:placetype":"venue"
},
  "geometry": {"coordinates":[-104.943031,39.689301],"type":"Point"}
}