{
  "type": "Feature",
  "properties": {
    "addr:full":"3239 S Parker Rd Aurora CO 80014",
    "addr:housenumber":"3239",
    "addr:postcode":"80014",
    "addr:street":"S Parker Rd",
    "iso:country":"US",
    "sg:address":"3239 S Parker Rd",
    "sg:city":"Aurora",
    "sg:classifiers":[
        {
            "category":"Utilities",
            "subcategory":"Refuse",
            "type":"Services"
        }
    ],
    "sg:phone":"+1 303 503 7810",
    "sg:postcode":"80014",
    "sg:province":"CO",
    "sg:tags":[
        "system"
    ],
    "wof:name":"Environmental Renewbl/Recyclng",
    "wof:placetype":"venue"
},
  "geometry": {"coordinates":[-104.84930799999999,39.659253],"type":"Point"}
}