{
  "type": "Feature",
  "properties": {
    "iso:country":"US",
    "sg:address":"7233 W 116th Pl",
    "sg:city":"Broomfield",
    "sg:classifiers":[
        {
            "category":"Retail",
            "subcategory":"Auto Repair",
            "type":"Services"
        }
    ],
    "sg:phone":"+1 720 566 0521",
    "sg:postcode":"80020",
    "sg:province":"CO",
    "sg:tags":[
        "repairing",
        "automobile",
        "general"
    ],
    "wof:name":"Bimmer Haus Performance Group",
    "wof:placetype":"venue"
},
  "geometry": {"coordinates":[-105.077803,39.908875],"type":"Point"}
}