{
  "type": "Feature",
  "properties": {
    "addr:full":"1100 8th Ave Greeley CO 80631",
    "addr:housenumber":"1100",
    "addr:postcode":"80631",
    "addr:street":"8Th Ave",
    "iso:country":"US",
    "sg:address":"1100 8th Ave",
    "sg:city":"Greeley",
    "sg:classifiers":[
        {
            "category":"Cinema",
            "subcategory":"Movie Rental",
            "type":"Entertainment"
        }
    ],
    "sg:phone":"+1 970 352 9317",
    "sg:postcode":"80631",
    "sg:province":"CO",
    "sg:tags":[
        "leasing",
        "video",
        "disc",
        "tape"
    ],
    "wof:name":"Video Estelar",
    "wof:placetype":"venue"
},
  "geometry": {"coordinates":[-104.690876,40.419789],"type":"Point"}
}