{
  "type": "Feature",
  "properties": {
    "iso:country":"US",
    "sg:address":"800 Grant Street",
    "sg:city":"Denver",
    "sg:classifiers":[
        {
            "category":"Professional",
            "subcategory":"Accounting & Tax Preparation",
            "type":"Services"
        }
    ],
    "sg:phone":"+1 303 830 8109",
    "sg:postcode":"80203",
    "sg:province":"CO",
    "sg:tags":[
        "accountant"
    ],
    "wof:name":"The Taylor Company Certified Public Accountant",
    "wof:placetype":"venue"
},
  "geometry": {"coordinates":[-104.98359,39.729089],"type":"Point"}
}