{
  "type": "Feature",
  "properties": {
    "iso:country":"US",
    "sg:address":"10995 Birch Dr",
    "sg:city":"Denver",
    "sg:classifiers":[
        {
            "category":"Freight",
            "type":"Transportation"
        }
    ],
    "sg:phone":"+1 303 920 1933",
    "sg:postcode":"80233",
    "sg:province":"CO",
    "sg:tags":[
        "operator",
        "local",
        "trucking"
    ],
    "wof:name":"Rivera Trucking",
    "wof:placetype":"venue"
},
  "geometry": {"coordinates":[-104.93141799999999,39.895176],"type":"Point"}
}