{
  "type": "Feature",
  "properties": {
    "addr:full":"7375 W 88th Ave Broomfield CO 80021",
    "addr:housenumber":"7375",
    "addr:postcode":"80021",
    "addr:street":"W 88Th Ave",
    "iso:country":"US",
    "sg:address":"7375 W 88th Ave",
    "sg:city":"Broomfield",
    "sg:classifiers":[
        {
            "category":"Home & Garden",
            "subcategory":"Home Furnishings",
            "type":"Retail Goods"
        }
    ],
    "sg:phone":"+1 303 420 3414",
    "sg:postcode":"80021",
    "sg:province":"CO",
    "sg:tags":[
        "lamp",
        "shades"
    ],
    "wof:name":"Lamps Plus",
    "wof:placetype":"venue"
},
  "geometry": {"coordinates":[-105.074787,39.85662],"type":"Point"}
}