{
  "type": "Feature",
  "properties": {
    "addr:full":"16695 E Smoky Hill Rd Aurora CO 80015",
    "addr:housenumber":"16695",
    "addr:postcode":"80015",
    "addr:street":"E Smoky Hill Rd",
    "iso:country":"US",
    "sg:address":"16695 E Smoky Hill Rd",
    "sg:city":"Aurora",
    "sg:classifiers":[
        {
            "category":"Autos & Motor Vehicles",
            "subcategory":"Auto Supplies",
            "type":"Retail Goods"
        },
        {
            "category":"Retail",
            "subcategory":"Auto Repair",
            "type":"Services"
        }
    ],
    "sg:phone":"+1 303 766 9227",
    "sg:postcode":"80015",
    "sg:province":"CO",
    "sg:tags":[
        "automobile",
        "part",
        "truck"
    ],
    "sg:website":"http://clickserve.dartsearch.net/link/click?lid=43000000313867447&ds_s_kwgid=58000000006820725&ds_e_matchtype={MatchType}&ds_e_kwdid={OrderItemId}&ds_e_adid={AdId}&ds_url_v=2",
    "wof:name":"Smoky Hill Auto Service",
    "wof:placetype":"venue"
},
  "geometry": {"coordinates":[-104.792779,39.626618],"type":"Point"}
}