{
  "type": "Feature",
  "properties": {
    "iso:country":"US",
    "sg:address":"810 S Portland Ave",
    "sg:city":"Pueblo",
    "sg:classifiers":[
        {
            "category":"Wholesale",
            "subcategory":"Durable Goods & Equipment",
            "type":"Manufacturing & Wholesale Goods"
        }
    ],
    "sg:phone":"+1 719 543 1601",
    "sg:postcode":"81001",
    "sg:province":"CO",
    "sg:tags":[
        "professional"
    ],
    "wof:name":"National Interlock",
    "wof:placetype":"venue"
},
  "geometry": {"coordinates":[-104.580382,38.261386],"type":"Point"}
}