{
  "type": "Feature",
  "properties": {
    "addr:full":"4199 N Academy Blvd Colorado Springs CO 80918",
    "addr:housenumber":"4199",
    "addr:postcode":"80918",
    "addr:street":"N Academy Blvd",
    "iso:country":"US",
    "sg:address":"4199 N Academy Blvd",
    "sg:city":"Colorado Springs",
    "sg:classifiers":[
        {
            "category":"Government",
            "subcategory":"Office",
            "type":"Public Place"
        }
    ],
    "sg:phone":"+1 719 472 3100",
    "sg:postcode":"80918",
    "sg:province":"CO",
    "sg:tags":[
        "communications"
    ],
    "wof:name":"US Dept of the Air Force",
    "wof:placetype":"venue"
},
  "geometry": {"coordinates":[-104.75726,38.892621],"type":"Point"}
}