{
  "type": "Feature",
  "properties": {
    "addr:full":"3225 International Cir Colorado Springs CO 80910",
    "addr:housenumber":"3225",
    "addr:postcode":"80910",
    "addr:street":"International Cir",
    "iso:country":"US",
    "sg:address":"3225 International Cir",
    "sg:city":"Colorado Springs",
    "sg:classifiers":[
        {
            "category":"Personal",
            "type":"Services"
        }
    ],
    "sg:phone":"+1 719 520 5205",
    "sg:postcode":"80910",
    "sg:province":"CO",
    "sg:tags":[
        "electrolysis"
    ],
    "wof:name":"Laser Hair Removal Ctr LLC",
    "wof:placetype":"venue"
},
  "geometry": {"coordinates":[-104.79027499999999,38.828164],"type":"Point"}
}