{
  "type": "Feature",
  "properties": {
    "addr:full":"1271 S Downing St Denver CO 80210",
    "addr:housenumber":"1271",
    "addr:postcode":"80210",
    "addr:street":"S Downing St",
    "iso:country":"US",
    "sg:address":"1271 S Downing St",
    "sg:city":"Denver",
    "sg:classifiers":[
        {
            "category":"Arts & Performance",
            "subcategory":"Theater",
            "type":"Entertainment"
        }
    ],
    "sg:phone":"+1 303 722 2140",
    "sg:postcode":"80210",
    "sg:province":"CO",
    "sg:tags":[
        "musician"
    ],
    "wof:name":"Sure Thing Entertainment",
    "wof:placetype":"venue"
},
  "geometry": {"coordinates":[-104.97348700000001,39.694238],"type":"Point"}
}