{
  "type": "Feature",
  "properties": {
    "iso:country":"US",
    "sg:address":"3255 Adams St",
    "sg:city":"Denver",
    "sg:classifiers":[
        {
            "category":"Restaurant",
            "type":"Food & Drink"
        }
    ],
    "sg:phone":"+1 303 377 2338",
    "sg:postcode":"80205",
    "sg:province":"CO",
    "sg:tags":[
        "preparation",
        "dessert"
    ],
    "wof:name":"Absolutely Fabulous Sugar-Free",
    "wof:placetype":"venue"
},
  "geometry": {"coordinates":[-104.94879899999999,39.762511],"type":"Point"}
}