{
  "type": "Feature",
  "properties": {
    "iso:country":"US",
    "sg:address":"1300 S Parker Rd",
    "sg:city":"Denver",
    "sg:classifiers":[
        {
            "category":"Organizations",
            "subcategory":"Community Association",
            "type":"Services"
        }
    ],
    "sg:phone":"+1 303 696 9549",
    "sg:postcode":"80231",
    "sg:province":"CO",
    "wof:name":"Club Valencia Condo Assn",
    "wof:placetype":"venue"
},
  "geometry": {"coordinates":[-104.89178200000001,39.691179],"type":"Point"}
}