{
  "type": "Feature",
  "properties": {
    "addr:full":"901 W 8th Ave Denver CO 80204",
    "addr:housenumber":"901",
    "addr:postcode":"80204",
    "addr:street":"W 8Th Ave",
    "iso:country":"US",
    "sg:address":"901 W 8th Ave",
    "sg:city":"Denver",
    "sg:classifiers":[
        {
            "category":"Retail",
            "subcategory":"Auto Repair",
            "type":"Services"
        }
    ],
    "sg:phone":"+1 303 825 5915",
    "sg:postcode":"80204",
    "sg:province":"CO",
    "sg:tags":[
        "automotive"
    ],
    "wof:name":"Grease Monkey",
    "wof:placetype":"venue"
},
  "geometry": {"coordinates":[-105.000176,39.728923],"type":"Point"}
}