{
  "type": "Feature",
  "properties": {
    "iso:country":"US",
    "sg:address":"1434 Blake St",
    "sg:city":"Denver",
    "sg:classifiers":[
        {
            "category":"Bars & Pubs",
            "subcategory":"Sports Bar",
            "type":"Food & Drink"
        }
    ],
    "sg:phone":"+1 303 446 2222",
    "sg:postcode":"80202",
    "sg:province":"CO",
    "sg:website":"www.tsbdenver.com",
    "wof:name":"The SportsBook",
    "wof:placetype":"venue"
},
  "geometry": {"coordinates":[-105.000853,39.749138],"type":"Point"}
}