{
  "type": "Feature",
  "properties": {
    "iso:country":"US",
    "sg:address":"26773 US Hwy 6",
    "sg:city":"Wolcott",
    "sg:classifiers":[
        {
            "category":"Freight",
            "type":"Transportation"
        }
    ],
    "sg:phone":"+1 970 926 3723",
    "sg:postcode":"81620",
    "sg:province":"CO",
    "wof:name":"Colorado Dept Of Trnsprtn",
    "wof:placetype":"venue"
},
  "geometry": {"coordinates":[-106.517571,39.629434],"type":"Point"}
}