{
  "type": "Feature",
  "properties": {
    "addr:full":"907 3rd Ave Monte Vista CO 81144",
    "addr:housenumber":"907",
    "addr:postcode":"81144",
    "addr:street":"3Rd Ave",
    "iso:country":"US",
    "sg:address":"907 3rd Ave",
    "sg:city":"Monte Vista",
    "sg:classifiers":[
        {
            "category":"Building & Trades",
            "subcategory":"Construction",
            "type":"Services"
        }
    ],
    "sg:phone":"+1 719 852 3211",
    "sg:postcode":"81144",
    "sg:province":"CO",
    "sg:tags":[
        "excavating",
        "contractor"
    ],
    "wof:name":"T C Pipeline",
    "wof:placetype":"venue"
},
  "geometry": {"coordinates":[-106.14622300000001,37.577952],"type":"Point"}
}