{
  "type": "Feature",
  "properties": {
    "addr:full":"10755 NW Routt Way Broomfield CO 80021",
    "addr:housenumber":"10755",
    "addr:postcode":"80021",
    "addr:street":"Nw Routt Way",
    "iso:country":"US",
    "sg:address":"10755 NW Routt Way",
    "sg:city":"Broomfield",
    "sg:classifiers":[
        {
            "category":"Organizations",
            "subcategory":"Religious Organization",
            "type":"Services"
        }
    ],
    "sg:phone":"+1 303 469 4390",
    "sg:postcode":"80021",
    "sg:province":"CO",
    "wof:name":"Jericho Marriage Ministries",
    "wof:placetype":"venue"
},
  "geometry": {"coordinates":[-105.12803,39.891996],"type":"Point"}
}