{
  "type": "Feature",
  "properties": {
    "addr:full":"1226 Sinton Rd Evergreen CO 80439",
    "addr:housenumber":"1226",
    "addr:postcode":"80439",
    "addr:street":"Sinton Rd",
    "iso:country":"US",
    "sg:address":"1226 Sinton Rd",
    "sg:city":"Evergreen",
    "sg:classifiers":[
        {
            "category":"Real Estate",
            "subcategory":"Real Estate Agent",
            "type":"Services"
        }
    ],
    "sg:phone":"+1 303 674 3080",
    "sg:postcode":"80439",
    "sg:province":"CO",
    "sg:tags":[
        "inspection"
    ],
    "wof:name":"Blochinger Home Inspections",
    "wof:placetype":"venue"
},
  "geometry": {"coordinates":[-105.428618,39.673514],"type":"Point"}
}