{
  "type": "Feature",
  "properties": {
    "addr:full":"315 S Magnolia St Denver CO 80224",
    "addr:housenumber":"315",
    "addr:postcode":"80224",
    "addr:street":"S Magnolia St",
    "iso:country":"US",
    "sg:address":"315 S Magnolia St",
    "sg:city":"Denver",
    "sg:classifiers":[
        {
            "category":"Health Services",
            "subcategory":"Clinic",
            "type":"Services"
        }
    ],
    "sg:phone":"+1 303 333 1017",
    "sg:postcode":"80224",
    "sg:province":"CO",
    "wof:name":"Bikur Cholim of Denver Inc",
    "wof:placetype":"venue"
},
  "geometry": {"coordinates":[-104.911219,39.709985],"type":"Point"}
}