{
  "type": "Feature",
  "properties": {
    "iso:country":"US",
    "sg:address":"26689 Pleasant Park Rd",
    "sg:city":"Conifer",
    "sg:classifiers":[
        {
            "category":"Health Services",
            "subcategory":"Doctor",
            "type":"Services"
        }
    ],
    "sg:phone":"+1 303 838 7337",
    "sg:postcode":"80433",
    "sg:province":"CO",
    "sg:tags":[
        "physician",
        "surgeon"
    ],
    "wof:name":"Evergreen-Conifer Pediatrics",
    "wof:placetype":"venue"
},
  "geometry": {"coordinates":[-105.29154,39.518108],"type":"Point"}
}