{
  "type": "Feature",
  "properties": {
    "iso:country":"US",
    "sg:address":"3383 W Hayward Pl",
    "sg:city":"Denver",
    "sg:classifiers":[
        {
            "category":"Professional",
            "subcategory":"Management & Consulting",
            "type":"Services"
        }
    ],
    "sg:phone":"+1 303 433 1775",
    "sg:postcode":"80211",
    "sg:province":"CO",
    "sg:tags":[
        "consultant",
        "training"
    ],
    "wof:name":"Vitale Training & Consulting",
    "wof:placetype":"venue"
},
  "geometry": {"coordinates":[-105.030322,39.75949],"type":"Point"}
}