{
  "type": "Feature",
  "properties": {
    "addr:full":"179 N College Ave Fort Collins CO 80524",
    "addr:housenumber":"179",
    "addr:postcode":"80524",
    "addr:street":"N College Ave",
    "iso:country":"US",
    "sg:address":"179 N College Ave",
    "sg:city":"Fort Collins",
    "sg:classifiers":[
        {
            "category":"Personal",
            "subcategory":"Barber",
            "type":"Services"
        }
    ],
    "sg:phone":"+1 970 482 2291",
    "sg:postcode":"80524",
    "sg:province":"CO",
    "wof:name":"Mc Carty's Barber Shop",
    "wof:placetype":"venue"
},
  "geometry": {"coordinates":[-105.077093,40.588038],"type":"Point"}
}