{
  "type": "Feature",
  "properties": {
    "addr:full":"9900 E 104th Ave Henderson CO 80640",
    "addr:housenumber":"9900",
    "addr:postcode":"80640",
    "addr:street":"E 104Th Ave",
    "iso:country":"US",
    "sg:address":"9900 E 104th Ave",
    "sg:city":"Henderson",
    "sg:classifiers":[
        {
            "category":"Mining & Drilling",
            "type":"Manufacturing & Wholesale Goods"
        }
    ],
    "sg:phone":"+1 303 288 0990",
    "sg:postcode":"80640",
    "sg:province":"CO",
    "sg:tags":[
        "field"
    ],
    "wof:name":"Dowell A Division Schlumber",
    "wof:placetype":"venue"
},
  "geometry": {"coordinates":[-104.86954900000001,39.885227],"type":"Point"}
}