{
  "type": "Feature",
  "properties": {
    "iso:country":"US",
    "sg:address":"600 S Cherry St",
    "sg:city":"Denver",
    "sg:classifiers":[
        {
            "category":"Professional",
            "subcategory":"Accounting & Tax Preparation",
            "type":"Services"
        }
    ],
    "sg:phone":"+1 303 377 2555",
    "sg:postcode":"80246",
    "sg:province":"CO",
    "wof:name":"Dickinson Dekruif & Hess",
    "wof:placetype":"venue"
},
  "geometry": {"coordinates":[-104.93384399999999,39.704497],"type":"Point"}
}