{
  "type": "Feature",
  "properties": {
    "iso:country":"US",
    "sg:address":"531 Broadway",
    "sg:city":"Denver",
    "sg:classifiers":[
        {
            "category":"Building & Trades",
            "subcategory":"Construction",
            "type":"Services"
        }
    ],
    "sg:phone":"+1 303 446 2800",
    "sg:postcode":"80203",
    "sg:province":"CO",
    "sg:tags":[
        "house"
    ],
    "wof:name":"Action Home Buyers",
    "wof:placetype":"venue"
},
  "geometry": {"coordinates":[-104.987523,39.725179],"type":"Point"}
}