{
  "type": "Feature",
  "properties": {
    "addr:full":"12650 W 64th Ave Arvada CO 80004",
    "addr:housenumber":"12650",
    "addr:postcode":"80004",
    "addr:street":"W 64Th Ave",
    "iso:country":"US",
    "sg:address":"12650 W 64th Ave",
    "sg:city":"Arvada",
    "sg:classifiers":[
        {
            "category":"Shopping",
            "subcategory":"Gifts & Souvenirs",
            "type":"Retail Goods"
        }
    ],
    "sg:phone":"+1 303 981 8137",
    "sg:postcode":"80004",
    "sg:province":"CO",
    "wof:name":"Easy Street Gifts",
    "wof:placetype":"venue"
},
  "geometry": {"coordinates":[-105.138873,39.812561],"type":"Point"}
}