{
  "type": "Feature",
  "properties": {
    "iso:country":"US",
    "sg:address":"11295 W Coal Mine Dr",
    "sg:city":"Littleton",
    "sg:classifiers":[
        {
            "category":"Professional",
            "type":"Services"
        }
    ],
    "sg:phone":"+1 303 904 6484",
    "sg:postcode":"80127",
    "sg:province":"CO",
    "wof:name":"Rosemount Analytical",
    "wof:placetype":"venue"
},
  "geometry": {"coordinates":[-105.12453499999999,39.5999],"type":"Point"}
}