{
  "type": "Feature",
  "properties": {
    "addr:full":"5535 State Hwy 12 La Veta CO 81055",
    "addr:housenumber":"5535",
    "addr:postcode":"81055",
    "addr:street":"State Hwy 12",
    "iso:country":"US",
    "sg:address":"5535 State Hwy 12",
    "sg:city":"La Veta",
    "sg:classifiers":[
        {
            "category":"Shopping",
            "subcategory":"Gifts & Souvenirs",
            "type":"Retail Goods"
        }
    ],
    "sg:phone":"+1 719 742 5533",
    "sg:postcode":"81055",
    "sg:province":"CO",
    "wof:name":"Elk Valley Fly Shop Gifts",
    "wof:placetype":"venue"
},
  "geometry": {"coordinates":[-105.01468,37.499729],"type":"Point"}
}