{
  "type": "Feature",
  "properties": {
    "iso:country":"US",
    "sg:address":"135 Silver St",
    "sg:city":"Delta",
    "sg:classifiers":[
        {
            "category":"Building & Trades",
            "subcategory":"Construction",
            "type":"Services"
        }
    ],
    "sg:phone":"+1 970 874 8241",
    "sg:postcode":"81416",
    "sg:province":"CO",
    "sg:tags":[
        "floor",
        "laying",
        "contractor"
    ],
    "wof:name":"Dougs Flooring",
    "wof:placetype":"venue"
},
  "geometry": {"coordinates":[-108.07648399999999,38.745093],"type":"Point"}
}