{
  "type": "Feature",
  "properties": {
    "addr:full":"605 William Ave Colorado Springs CO 80906",
    "addr:housenumber":"605",
    "addr:postcode":"80906",
    "addr:street":"William Ave",
    "iso:country":"US",
    "sg:address":"605 William Ave",
    "sg:city":"Colorado Springs",
    "sg:classifiers":[
        {
            "category":"Freight",
            "type":"Transportation"
        }
    ],
    "sg:phone":"+1 719 633 0417",
    "sg:postcode":"80906",
    "sg:province":"CO",
    "sg:tags":[
        "courier"
    ],
    "wof:name":"Pal Messenger Service",
    "wof:placetype":"venue"
},
  "geometry": {"coordinates":[-104.814964,38.804909],"type":"Point"}
}