{
  "type": "Feature",
  "properties": {
    "iso:country":"US",
    "sg:address":"2515 Westen Rd",
    "sg:city":"Colorado Springs",
    "sg:classifiers":[
        {
            "category":"Retail",
            "subcategory":"Auto Repair",
            "type":"Services"
        }
    ],
    "sg:phone":"+1 719 392 5550",
    "sg:postcode":"80910",
    "sg:province":"CO",
    "sg:tags":[
        "repairing",
        "automobile"
    ],
    "wof:name":"American Automotive Inc",
    "wof:placetype":"venue"
},
  "geometry": {"coordinates":[-104.777939,38.795238],"type":"Point"}
}