{
  "type": "Feature",
  "properties": {
    "addr:full":"2680 18th Street Suite 100 Denver CO 80211",
    "addr:housenumber":"2680",
    "addr:postcode":"80211",
    "addr:street":"18Th Street Suite 100",
    "iso:country":"US",
    "sg:address":"2680 18th Street Suite 100",
    "sg:city":"Denver",
    "sg:classifiers":[
        {
            "category":"Real Estate",
            "subcategory":"Architect",
            "type":"Services"
        }
    ],
    "sg:phone":"+1 303 477 2770",
    "sg:postcode":"80211",
    "sg:province":"CO",
    "wof:name":"Mitchell Plus Associates",
    "wof:placetype":"venue"
},
  "geometry": {"coordinates":[-105.009319,39.761939],"type":"Point"}
}