{
  "type": "Feature",
  "properties": {
    "addr:full":"25 N 20th St Colorado Springs CO 80904",
    "addr:housenumber":"25",
    "addr:postcode":"80904",
    "addr:street":"N 20Th St",
    "iso:country":"US",
    "sg:address":"25 N 20th St",
    "sg:city":"Colorado Springs",
    "sg:classifiers":[
        {
            "category":"Organizations",
            "subcategory":"Non-profit Organization",
            "type":"Services"
        }
    ],
    "sg:phone":"+1 719 385 7930",
    "sg:postcode":"80904",
    "sg:province":"CO",
    "wof:name":"Billie Spielman Ctr",
    "wof:placetype":"venue"
},
  "geometry": {"coordinates":[-104.85396,38.843813],"type":"Point"}
}