{
  "type": "Feature",
  "properties": {
    "iso:country":"US",
    "sg:address":"8637 W 79th Pl",
    "sg:city":"Arvada",
    "sg:classifiers":[
        {
            "category":"Professional",
            "type":"Services"
        }
    ],
    "sg:phone":"+1 303 420 7812",
    "sg:postcode":"80005",
    "sg:province":"CO",
    "wof:name":"Headings Inc",
    "wof:placetype":"venue"
},
  "geometry": {"coordinates":[-105.09367399999999,39.84137],"type":"Point"}
}