{
  "type": "Feature",
  "properties": {
    "addr:full":"732 S Lemay Ave Fort Collins CO 80524",
    "addr:housenumber":"732",
    "addr:postcode":"80524",
    "addr:street":"S Lemay Ave",
    "iso:country":"US",
    "sg:address":"732 S Lemay Ave",
    "sg:city":"Fort Collins",
    "sg:classifiers":[
        {
            "category":"Restaurant",
            "type":"Food & Drink"
        }
    ],
    "sg:menulink":"http://www.allmenus.com/co/fort-collins/69475-dominos-pizza/menu/",
    "sg:phone":"+1 970 407 1073",
    "sg:postcode":"80524",
    "sg:province":"CO",
    "sg:tags":[
        "american",
        "wing",
        "pizza"
    ],
    "wof:name":"Domino's Pizza",
    "wof:placetype":"venue"
},
  "geometry": {"coordinates":[-105.05757,40.577252],"type":"Point"}
}