{
  "type": "Feature",
  "properties": {
    "iso:country":"US",
    "sg:address":"1221 S Pearl St",
    "sg:city":"Denver",
    "sg:classifiers":[
        {
            "category":"Building & Trades",
            "subcategory":"Construction",
            "type":"Services"
        }
    ],
    "sg:phone":"+1 303 777 1515",
    "sg:postcode":"80210",
    "sg:province":"CO",
    "sg:tags":[
        "contractor"
    ],
    "wof:name":"All About Saving Heat & Window",
    "wof:placetype":"venue"
},
  "geometry": {"coordinates":[-104.980493,39.693316],"type":"Point"}
}