{
  "type": "Feature",
  "properties": {
    "iso:country":"US",
    "sg:address":"9746 W 106th Ave",
    "sg:city":"Broomfield",
    "sg:classifiers":[
        {
            "category":"Banks & Credit Unions",
            "subcategory":"Bank",
            "type":"Services"
        }
    ],
    "sg:phone":"+1 303 942 9587",
    "sg:postcode":"80021",
    "sg:province":"CO",
    "sg:tags":[
        "financing"
    ],
    "wof:name":"Advanced Funding Svc",
    "wof:placetype":"venue"
},
  "geometry": {"coordinates":[-105.104737,39.890191],"type":"Point"}
}