{
  "type": "Feature",
  "properties": {
    "addr:full":"12465 Co Rd 2 Brighton CO 80603",
    "addr:housenumber":"12465",
    "addr:postcode":"80603",
    "addr:street":"Co Rd 2",
    "iso:country":"US",
    "sg:address":"12465 Co Rd 2",
    "sg:city":"Brighton",
    "sg:classifiers":[
        {
            "category":"Travel",
            "subcategory":"Hotels & Motels",
            "type":"Entertainment"
        }
    ],
    "sg:phone":"+1 303 659 1546",
    "sg:postcode":"80603",
    "sg:province":"CO",
    "wof:name":"Motel 85",
    "wof:placetype":"venue"
},
  "geometry": {"coordinates":[-104.82155,40.000484],"type":"Point"}
}