{
  "type": "Feature",
  "properties": {
    "addr:full":"805 Denargo Market Denver CO 80216",
    "addr:housenumber":"805",
    "addr:postcode":"80216",
    "addr:street":"Denargo",
    "iso:country":"US",
    "sg:address":"805 Denargo Market",
    "sg:city":"Denver",
    "sg:classifiers":[
        {
            "category":"Home & Garden",
            "subcategory":"Building Materials",
            "type":"Retail Goods"
        }
    ],
    "sg:phone":"+1 303 295 1078",
    "sg:postcode":"80216",
    "sg:province":"CO",
    "sg:tags":[
        "glass",
        "window",
        "plate"
    ],
    "wof:name":"Denver West Glass",
    "wof:placetype":"venue"
},
  "geometry": {"coordinates":[-104.99001800000001,39.763983],"type":"Point"}
}