{
  "type": "Feature",
  "properties": {
    "iso:country":"US",
    "sg:address":"7650 W Virginia Ave",
    "sg:city":"Denver",
    "sg:classifiers":[
        {
            "category":"Restaurant",
            "type":"Food & Drink"
        }
    ],
    "sg:menulink":"http://www.allmenus.com/co/northeast-jefferson/96000-souper-salad/menu/",
    "sg:phone":"+1 303 989 2202",
    "sg:postcode":"80226",
    "sg:province":"CO",
    "sg:tags":[
        "smoothy",
        "soup",
        "american",
        "salad",
        "juice"
    ],
    "wof:name":"Souper Salad",
    "wof:placetype":"venue"
},
  "geometry": {"coordinates":[-105.082346,39.706607],"type":"Point"}
}