{
  "type": "Feature",
  "properties": {
    "addr:full":"1303 Greene St Silverton CO 81433",
    "addr:housenumber":"1303",
    "addr:postcode":"81433",
    "addr:street":"Greene St",
    "iso:country":"US",
    "sg:address":"1303 Greene St",
    "sg:city":"Silverton",
    "sg:classifiers":[
        {
            "category":"Shopping",
            "subcategory":"Clothing, Apparel, & Fashions",
            "type":"Retail Goods"
        }
    ],
    "sg:phone":"+1 970 387 5853",
    "sg:postcode":"81433",
    "sg:province":"CO",
    "wof:name":"Hold Your Horses",
    "wof:placetype":"venue"
},
  "geometry": {"coordinates":[-107.66291,37.813343],"type":"Point"}
}