{
  "type": "Feature",
  "properties": {
    "addr:full":"1312 E Routt Ave Pueblo CO 81004",
    "addr:housenumber":"1312",
    "addr:postcode":"81004",
    "addr:street":"E Routt Ave",
    "iso:country":"US",
    "sg:address":"1312 E Routt Ave",
    "sg:city":"Pueblo",
    "sg:classifiers":[
        {
            "category":"Manufacturing",
            "subcategory":"Apparel",
            "type":"Manufacturing & Wholesale Goods"
        }
    ],
    "sg:phone":"+1 719 561 2727",
    "sg:postcode":"81004",
    "sg:province":"CO",
    "sg:tags":[
        "mfg"
    ],
    "wof:name":"Bra Man The Pueblo",
    "wof:placetype":"venue"
},
  "geometry": {"coordinates":[-104.616039,38.242646],"type":"Point"}
}