{
  "type": "Feature",
  "properties": {
    "addr:full":"451 Oak St Frederick CO 80530",
    "addr:housenumber":"451",
    "addr:postcode":"80530",
    "addr:street":"Oak St",
    "iso:country":"US",
    "sg:address":"451 Oak St",
    "sg:city":"Frederick",
    "sg:classifiers":[
        {
            "category":"Professional",
            "subcategory":"Accounting & Tax Preparation",
            "type":"Services"
        }
    ],
    "sg:phone":"+1 303 833 1083",
    "sg:postcode":"80530",
    "sg:province":"CO",
    "sg:tags":[
        "accountant"
    ],
    "wof:name":"Bachman & Co",
    "wof:placetype":"venue"
},
  "geometry": {"coordinates":[-104.93828999999999,40.099081],"type":"Point"}
}