{
  "type": "Feature",
  "properties": {
    "addr:full":"1855 Aeroplaza Dr Colorado Springs CO 80916",
    "addr:housenumber":"1855",
    "addr:postcode":"80916",
    "addr:street":"Aeroplaza Dr",
    "iso:country":"US",
    "sg:address":"1855 Aeroplaza Dr",
    "sg:city":"Colorado Springs",
    "sg:classifiers":[
        {
            "category":"Restaurant",
            "type":"Food & Drink"
        }
    ],
    "sg:phone":"+1 719 380 0356",
    "sg:postcode":"80916",
    "sg:province":"CO",
    "wof:name":"Maggie's Roadhouse",
    "wof:placetype":"venue"
},
  "geometry": {"coordinates":[-104.73744600000001,38.804108],"type":"Point"}
}