{
  "type": "Feature",
  "properties": {
    "iso:country":"US",
    "sg:address":"700 E 6th Ave",
    "sg:city":"Denver",
    "sg:classifiers":[
        {
            "category":"Building & Trades",
            "subcategory":"Locksmith",
            "type":"Services"
        }
    ],
    "sg:phone":"+1 303 395 2087",
    "sg:postcode":"80203",
    "sg:province":"CO",
    "sg:tags":[
        "key"
    ],
    "wof:name":"A Emergency Locksmith",
    "wof:placetype":"venue"
},
  "geometry": {"coordinates":[-104.978763,39.725493],"type":"Point"}
}