{
  "type": "Feature",
  "properties": {
    "iso:country":"US",
    "sg:address":"9344 Bauer Ct",
    "sg:city":"Lone Tree",
    "sg:classifiers":[
        {
            "category":"Banks & Credit Unions",
            "subcategory":"Investment Brokerage",
            "type":"Services"
        }
    ],
    "sg:phone":"+1 303 790 4009",
    "sg:postcode":"80124",
    "sg:province":"CO",
    "sg:tags":[
        "merger",
        "acquisition"
    ],
    "wof:name":"Dwyer Group Inc",
    "wof:placetype":"venue"
},
  "geometry": {"coordinates":[-104.892703,39.546118],"type":"Point"}
}