{
  "type": "Feature",
  "properties": {
    "addr:full":"303 6th Ave Ouray CO 81427",
    "addr:housenumber":"303",
    "addr:postcode":"81427",
    "addr:street":"6Th Ave",
    "iso:country":"US",
    "sg:address":"303 6th Ave",
    "sg:city":"Ouray",
    "sg:classifiers":[
        {
            "category":"Travel",
            "subcategory":"Hotels & Motels",
            "type":"Entertainment"
        }
    ],
    "sg:phone":"+1 970 325 0500",
    "sg:postcode":"81427",
    "sg:province":"CO",
    "sg:website":"www.ourayhotel.com",
    "wof:name":"Ouray Hotel",
    "wof:placetype":"venue"
},
  "geometry": {"coordinates":[-107.671476,38.022705],"type":"Point"}
}