{
  "type": "Feature",
  "properties": {
    "iso:country":"US",
    "sg:address":"13685 Halleluiah Trl",
    "sg:city":"Elbert",
    "sg:classifiers":[
        {
            "category":"Building & Trades",
            "subcategory":"Construction",
            "type":"Services"
        }
    ],
    "sg:phone":"+1 719 495 3030",
    "sg:postcode":"80106",
    "sg:province":"CO",
    "sg:tags":[
        "nonresidential"
    ],
    "wof:name":"Barn-TEC Inc",
    "wof:placetype":"venue"
},
  "geometry": {"coordinates":[-104.583698,39.018657],"type":"Point"}
}