{
  "type": "Feature",
  "properties": {
    "iso:country":"US",
    "sg:address":"98 Wadsworth Blvd",
    "sg:city":"Denver",
    "sg:classifiers":[
        {
            "category":"Shopping",
            "subcategory":"Clothing, Apparel, & Fashions",
            "type":"Retail Goods"
        }
    ],
    "sg:phone":"+1 303 202 1040",
    "sg:postcode":"80226",
    "sg:province":"CO",
    "sg:website":"www.rue21.com",
    "wof:name":"Rue 21",
    "wof:placetype":"venue"
},
  "geometry": {"coordinates":[-105.081413,39.718403],"type":"Point"}
}