{
  "type": "Feature",
  "properties": {
    "iso:country":"US",
    "sg:address":"1300 Monaco Pkwy",
    "sg:city":"Denver",
    "sg:classifiers":[
        {
            "category":"Building & Trades",
            "subcategory":"Construction",
            "type":"Services"
        }
    ],
    "sg:phone":"+1 303 316 8690",
    "sg:postcode":"80220",
    "sg:province":"CO",
    "sg:tags":[
        "contractor"
    ],
    "wof:name":"Sun Tube of Colorado",
    "wof:placetype":"venue"
},
  "geometry": {"coordinates":[-104.91243,39.73863],"type":"Point"}
}