{
  "type": "Feature",
  "properties": {
    "addr:full":"8374 S Yukon St Littleton CO 80128",
    "addr:housenumber":"8374",
    "addr:postcode":"80128",
    "addr:street":"S Yukon St",
    "iso:country":"US",
    "sg:address":"8374 S Yukon St",
    "sg:city":"Littleton",
    "sg:classifiers":[
        {
            "category":"Building & Trades",
            "subcategory":"Construction",
            "type":"Services"
        }
    ],
    "sg:phone":"+1 303 948 9459",
    "sg:postcode":"80128",
    "sg:province":"CO",
    "sg:tags":[
        "excavating",
        "contractor"
    ],
    "wof:name":"Hodapp's Backhoe & Utility Svc",
    "wof:placetype":"venue"
},
  "geometry": {"coordinates":[-105.08493900000001,39.563745],"type":"Point"}
}