{
  "type": "Feature",
  "properties": {
    "iso:country":"US",
    "sg:address":"146 Smokey Rock Rd",
    "sg:city":"Bailey",
    "sg:classifiers":[
        {
            "category":"Professional",
            "subcategory":"Advertising",
            "type":"Services"
        }
    ],
    "sg:phone":"+1 303 838 3511",
    "sg:postcode":"80421",
    "sg:province":"CO",
    "sg:tags":[
        "counselor"
    ],
    "wof:name":"Ayers Advertising & Marketing",
    "wof:placetype":"venue"
},
  "geometry": {"coordinates":[-105.529589,39.489074],"type":"Point"}
}