{
  "type": "Feature",
  "properties": {
    "iso:country":"US",
    "sg:address":"425 E Fillmore St",
    "sg:city":"Colorado Springs",
    "sg:classifiers":[
        {
            "category":"Professional",
            "subcategory":"Computer Services",
            "type":"Services"
        }
    ],
    "sg:phone":"+1 719 389 0368",
    "sg:postcode":"80907",
    "sg:province":"CO",
    "sg:tags":[
        "consultant",
        "designer",
        "datum",
        "system"
    ],
    "wof:name":"Litton Data Systems Div",
    "wof:placetype":"venue"
},
  "geometry": {"coordinates":[-104.81264400000001,38.874034],"type":"Point"}
}