{
  "type": "Feature",
  "properties": {
    "addr:full":"9220 Teddy Ln Lone Tree CO 80124",
    "addr:postcode":"9220;80124",
    "addr:street":"Teddy Ln",
    "iso:country":"US",
    "sg:address":"9220 Teddy Ln",
    "sg:city":"Lone Tree",
    "sg:classifiers":[
        {
            "category":"Professional",
            "subcategory":"Management & Consulting",
            "type":"Services"
        },
        {
            "category":"Education",
            "subcategory":"Special Training",
            "type":"Public Place"
        }
    ],
    "sg:phone":"+1 303 220 8326",
    "sg:postcode":"80124",
    "sg:province":"CO",
    "sg:tags":[
        "program"
    ],
    "sg:website":"www.teammarketinggroup.com",
    "wof:name":"Team Marketing Group Inc",
    "wof:placetype":"venue"
},
  "geometry": {"coordinates":[-104.880636,39.551692],"type":"Point"}
}