{
  "type": "Feature",
  "properties": {
    "iso:country":"US",
    "sg:address":"515 Ponderosa Vw",
    "sg:city":"Manitou Springs",
    "sg:classifiers":[
        {
            "category":"Building & Trades",
            "subcategory":"Construction",
            "type":"Services"
        }
    ],
    "sg:phone":"+1 719 685 5672",
    "sg:postcode":"80829",
    "sg:province":"CO",
    "sg:tags":[
        "house"
    ],
    "wof:name":"Dreamworks Cnstr Solutions",
    "wof:placetype":"venue"
},
  "geometry": {"coordinates":[-104.924111,38.81871],"type":"Point"}
}