{
  "type": "Feature",
  "properties": {
    "addr:full":"2475 River Rd Grand Junction CO 81505",
    "addr:housenumber":"2475",
    "addr:postcode":"81505",
    "addr:street":"River Rd",
    "iso:country":"US",
    "sg:address":"2475 River Rd",
    "sg:city":"Grand Junction",
    "sg:classifiers":[
        {
            "category":"Building & Trades",
            "subcategory":"Construction",
            "type":"Services"
        }
    ],
    "sg:phone":"+1 970 243 0072",
    "sg:postcode":"81505",
    "sg:province":"CO",
    "sg:tags":[
        "general",
        "contractor"
    ],
    "wof:name":"Lannie & Rund Gen Contr Inc",
    "wof:placetype":"venue"
},
  "geometry": {"coordinates":[-108.600499,39.086548],"type":"Point"}
}