{
  "type": "Feature",
  "properties": {
    "addr:full":"293 S Grant St Denver CO 80209",
    "addr:housenumber":"293",
    "addr:postcode":"80209",
    "addr:street":"S Grant St",
    "iso:country":"US",
    "sg:address":"293 S Grant St",
    "sg:city":"Denver",
    "sg:classifiers":[
        {
            "category":"Communications",
            "subcategory":"Film & Video Production",
            "type":"Services"
        }
    ],
    "sg:phone":"+1 303 715 1221",
    "sg:postcode":"80209",
    "sg:province":"CO",
    "sg:tags":[
        "services-commercial"
    ],
    "sg:website":"http://www.attentionmediagroup.com",
    "wof:name":"Horn E Toad Productions",
    "wof:placetype":"venue"
},
  "geometry": {"coordinates":[-104.984015,39.711241],"type":"Point"}
}