{
  "type": "Feature",
  "properties": {
    "iso:country":"US",
    "sg:address":"1 Cheyenne Blvd",
    "sg:city":"Colorado Springs",
    "sg:classifiers":[
        {
            "category":"Building & Trades",
            "subcategory":"Landscaping Services",
            "type":"Services"
        }
    ],
    "sg:phone":"+1 719 630 8645",
    "sg:postcode":"80906",
    "sg:province":"CO",
    "sg:tags":[
        "tree"
    ],
    "wof:name":"Vedanta Tree Svc",
    "wof:placetype":"venue"
},
  "geometry": {"coordinates":[-104.82871299999999,38.807994],"type":"Point"}
}