{
  "type": "Feature",
  "properties": {
    "iso:country":"US",
    "sg:address":"1041 Galapago St",
    "sg:city":"Denver",
    "sg:classifiers":[
        {
            "category":"Retail",
            "subcategory":"Veterinary Services",
            "type":"Services"
        },
        {
            "category":"Community Center",
            "type":"Public Place"
        }
    ],
    "sg:phone":"+1 303 595 3561",
    "sg:postcode":"80204",
    "sg:province":"CO",
    "sg:tags":[
        "medical",
        "veterinarian"
    ],
    "sg:website":"www.daccdenver.com/",
    "wof:name":"Downtown Animal Care Center",
    "wof:placetype":"venue"
},
  "geometry": {"coordinates":[-104.996628,39.732759],"type":"Point"}
}