{
  "type": "Feature",
  "properties": {
    "addr:full":"8330 E Quincy Ave Denver CO 80237",
    "addr:housenumber":"8330 e",
    "addr:postcode":"80237",
    "addr:street":"Quincy Ave",
    "iso:country":"US",
    "sg:address":"8330 E Quincy Ave",
    "sg:city":"Denver",
    "sg:classifiers":[
        {
            "category":"Professional",
            "type":"Services"
        }
    ],
    "sg:phone":"+1 303 316 7600",
    "sg:postcode":"80237",
    "sg:province":"CO",
    "wof:name":"Nixon Incorporated",
    "wof:placetype":"venue"
},
  "geometry": {"coordinates":[-104.89260899999999,39.638592],"type":"Point"}
}