{
  "type": "Feature",
  "properties": {
    "addr:full":"335 E 3rd St Rifle CO 81650",
    "addr:housenumber":"335",
    "addr:postcode":"81650",
    "addr:street":"E 3Rd St",
    "iso:country":"US",
    "sg:address":"335 E 3rd St",
    "sg:city":"Rifle",
    "sg:classifiers":[
        {
            "category":"Building & Trades",
            "subcategory":"Plumbing",
            "type":"Services"
        }
    ],
    "sg:phone":"+1 970 625 5351",
    "sg:postcode":"81650",
    "sg:province":"CO",
    "sg:tags":[
        "plumbing",
        "contractor"
    ],
    "wof:name":"Birchfield Plumbing",
    "wof:placetype":"venue"
},
  "geometry": {"coordinates":[-107.779939,39.531543],"type":"Point"}
}