{
  "type": "Feature",
  "properties": {
    "addr:full":"5622 S Delaware St Littleton CO 80120",
    "addr:housenumber":"5622",
    "addr:postcode":"80120",
    "addr:street":"S Delaware St",
    "iso:country":"US",
    "sg:address":"5622 S Delaware St",
    "sg:city":"Littleton",
    "sg:classifiers":[
        {
            "category":"Health Services",
            "subcategory":"Medical Lab",
            "type":"Services"
        }
    ],
    "sg:phone":"+1 303 798 6145",
    "sg:postcode":"80120",
    "sg:province":"CO",
    "sg:tags":[
        "laboratory"
    ],
    "wof:name":"Majestic Dental Designs",
    "wof:placetype":"venue"
},
  "geometry": {"coordinates":[-104.99315199999999,39.614929],"type":"Point"}
}