{
  "type": "Feature",
  "properties": {
    "addr:full":"2721 Stanford Rd Fort Collins CO 80525",
    "addr:housenumber":"2721",
    "addr:postcode":"80525",
    "addr:street":"Stanford Rd",
    "iso:country":"US",
    "sg:address":"2721 Stanford Rd",
    "sg:city":"Fort Collins",
    "sg:classifiers":[
        {
            "category":"Professional",
            "type":"Services"
        }
    ],
    "sg:phone":"+1 970 377 9926",
    "sg:postcode":"80525",
    "sg:province":"CO",
    "wof:name":"Sarah Peters",
    "wof:placetype":"venue"
},
  "geometry": {"coordinates":[-105.06946499999999,40.551389],"type":"Point"}
}