{
  "type": "Feature",
  "properties": {
    "iso:country":"US",
    "sg:address":"43651 E 38th Ave",
    "sg:city":"Bennett",
    "sg:phone":"+1 303 644 3435",
    "sg:postcode":"80102",
    "sg:province":"CO",
    "sg:tags":[
        "farm",
        "wheat"
    ],
    "wof:name":"Lowell Piland",
    "wof:placetype":"venue"
},
  "geometry": {"coordinates":[-104.47573,39.766891],"type":"Point"}
}