{
  "type": "Feature",
  "properties": {
    "iso:country":"US",
    "sg:address":"292 W Meadow Dr",
    "sg:city":"Vail",
    "sg:classifiers":[
        {
            "category":"Education",
            "subcategory":"Library",
            "type":"Public Place"
        }
    ],
    "sg:phone":"+1 970 479 2183",
    "sg:postcode":"81657",
    "sg:province":"CO",
    "sg:website":"www.vaillibrary.com",
    "wof:name":"Vail Town Library",
    "wof:placetype":"venue"
},
  "geometry": {"coordinates":[-106.379706,39.642513],"type":"Point"}
}