{
  "type": "Feature",
  "properties": {
    "addr:full":"1320 20th St Denver CO 80202",
    "addr:housenumber":"1320",
    "addr:postcode":"80202",
    "addr:street":"20Th St",
    "iso:country":"US",
    "sg:address":"1320 20th St",
    "sg:city":"Denver",
    "sg:classifiers":[
        {
            "category":"Restaurant",
            "type":"Food & Drink"
        }
    ],
    "sg:phone":"+1 303 297 8300",
    "sg:postcode":"80202",
    "sg:province":"CO",
    "sg:tags":[
        "sport",
        "bar"
    ],
    "sg:website":"www.giggling-grizzly.com",
    "wof:name":"Giggling Grizzly",
    "wof:placetype":"venue"
},
  "geometry": {"coordinates":[-104.99299600000001,39.752998],"type":"Point"}
}