{
  "type": "Feature",
  "properties": {
    "addr:full":"138 12th St SE Loveland CO 80537",
    "addr:housenumber":"138",
    "addr:postcode":"80537",
    "addr:street":"12Th St Se",
    "iso:country":"US",
    "sg:address":"138 12th St SE",
    "sg:city":"Loveland",
    "sg:classifiers":[
        {
            "category":"Professional",
            "type":"Services"
        }
    ],
    "sg:phone":"+1 970 663 3363",
    "sg:postcode":"80537",
    "sg:province":"CO",
    "sg:tags":[
        "art",
        "restoring"
    ],
    "wof:name":"Patrick Kipper Bronze Ptntn",
    "wof:placetype":"venue"
},
  "geometry": {"coordinates":[-105.076116,40.380069],"type":"Point"}
}