{
  "type": "Feature",
  "properties": {
    "iso:country":"US",
    "sg:address":"10000 Co Rd 92",
    "sg:city":"Lake George",
    "sg:phone":"+1 719 748 3288",
    "sg:postcode":"80827",
    "sg:province":"CO",
    "sg:tags":[
        "farm",
        "field",
        "crop"
    ],
    "wof:name":"Hubert Rodman",
    "wof:placetype":"venue"
},
  "geometry": {"coordinates":[-105.43197499999999,38.989803],"type":"Point"}
}