{
  "type": "Feature",
  "properties": {
    "iso:country":"US",
    "sg:address":"756 S Jason St #27",
    "sg:city":"Denver",
    "sg:classifiers":[
        {
            "category":"Building & Trades",
            "subcategory":"Construction",
            "type":"Services"
        }
    ],
    "sg:phone":"+1 303 282 4424",
    "sg:postcode":"80223",
    "sg:province":"CO",
    "sg:tags":[
        "contractor"
    ],
    "sg:website":"www.MGStoneLLC.com",
    "wof:name":"MG Stone LLC",
    "wof:placetype":"venue"
},
  "geometry": {"coordinates":[-104.99825199999999,39.702555],"type":"Point"}
}