{
  "type": "Feature",
  "properties": {
    "iso:country":"US",
    "sg:address":"740 Main St",
    "sg:city":"Silt",
    "sg:classifiers":[
        {
            "category":"Restaurant",
            "type":"Food & Drink"
        }
    ],
    "sg:phone":"+1 970 876 5372",
    "sg:postcode":"81652",
    "sg:province":"CO",
    "wof:name":"Miner's Claim Restaurant",
    "wof:placetype":"venue"
},
  "geometry": {"coordinates":[-107.65534599999999,39.547103],"type":"Point"}
}