{
  "type": "Feature",
  "properties": {
    "iso:country":"US",
    "sg:address":"6113 E Co Rd 36",
    "sg:city":"Fort Collins",
    "sg:classifiers":[
        {
            "category":"Farming",
            "subcategory":"Farm",
            "type":"Manufacturing & Wholesale Goods"
        }
    ],
    "sg:phone":"+1 970 221 4441",
    "sg:postcode":"80528",
    "sg:province":"CO",
    "wof:name":"Timnath Farms",
    "wof:placetype":"venue"
},
  "geometry": {"coordinates":[-104.958843,40.508625],"type":"Point"}
}