{
  "type": "Feature",
  "properties": {
    "iso:country":"US",
    "sg:address":"2510 S Zinnia Way",
    "sg:city":"Denver",
    "sg:classifiers":[
        {
            "category":"Banks & Credit Unions",
            "subcategory":"Financial Services",
            "type":"Services"
        }
    ],
    "sg:phone":"+1 303 986 9868",
    "sg:postcode":"80228",
    "sg:province":"CO",
    "sg:tags":[
        "company",
        "holding"
    ],
    "wof:name":"Ew Holdings LLC",
    "wof:placetype":"venue"
},
  "geometry": {"coordinates":[-105.14588999999999,39.670001],"type":"Point"}
}