{
  "type": "Feature",
  "properties": {
    "addr:full":"4001 E Arapahoe Rd Littleton CO 80122",
    "addr:housenumber":"4001",
    "addr:postcode":"80122",
    "addr:street":"E Arapahoe Rd",
    "iso:country":"US",
    "sg:address":"4001 E Arapahoe Rd",
    "sg:city":"Littleton",
    "sg:classifiers":[
        {
            "category":"Education",
            "subcategory":"School",
            "type":"Public Place"
        }
    ],
    "sg:phone":"+1 303 347 7900",
    "sg:postcode":"80122",
    "sg:province":"CO",
    "sg:tags":[
        "middle"
    ],
    "sg:website":"www.newton.littletonpublicschools.net",
    "wof:name":"Isaac Newton Middle School",
    "wof:placetype":"venue"
},
  "geometry": {"coordinates":[-104.939329,39.595045],"type":"Point"}
}