{
  "type": "Feature",
  "properties": {
    "iso:country":"US",
    "sg:address":"6011 W 44th Avenue",
    "sg:city":"Wheat Ridge",
    "sg:classifiers":[
        {
            "category":"Banks & Credit Unions",
            "subcategory":"Bank",
            "type":"Services"
        }
    ],
    "sg:phone":"+1 303 420 5124",
    "sg:postcode":"80033",
    "sg:province":"CO",
    "sg:website":"www.usbank.com",
    "wof:name":"U S Bank",
    "wof:placetype":"venue"
},
  "geometry": {"coordinates":[-105.063125,39.77649],"type":"Point"}
}