{
  "type": "Feature",
  "properties": {
    "iso:country":"US",
    "sg:address":"5754 N Academy Blvd",
    "sg:city":"Colorado Springs",
    "sg:classifiers":[
        {
            "category":"Retail",
            "subcategory":"Laundry & Dry Cleaning",
            "type":"Services"
        }
    ],
    "sg:phone":"+1 719 266 6761",
    "sg:postcode":"80918",
    "sg:province":"CO",
    "sg:tags":[
        "cleaners"
    ],
    "wof:name":"Blue Star Cleaners",
    "wof:placetype":"venue"
},
  "geometry": {"coordinates":[-104.787719,38.914164],"type":"Point"}
}