{
  "type": "Feature",
  "properties": {
    "iso:country":"US",
    "sg:address":"1965 Ski Time Square Dr",
    "sg:city":"Steamboat Spgs",
    "sg:classifiers":[
        {
            "category":"Restaurant",
            "type":"Food & Drink"
        }
    ],
    "sg:phone":"+1 970 879 6348",
    "sg:postcode":"80487",
    "sg:province":"CO",
    "wof:name":"Outlaws",
    "wof:placetype":"venue"
},
  "geometry": {"coordinates":[-106.803556,40.460101],"type":"Point"}
}