{
  "type": "Feature",
  "properties": {
    "addr:full":"4501 Chicago Creek Rd Idaho Springs CO 80452",
    "addr:housenumber":"4501",
    "addr:postcode":"80452",
    "addr:street":"Chicago Creek Rd",
    "iso:country":"US",
    "sg:address":"4501 Chicago Creek Rd",
    "sg:city":"Idaho Springs",
    "sg:classifiers":[
        {
            "category":"Building & Trades",
            "subcategory":"Construction",
            "type":"Services"
        }
    ],
    "sg:phone":"+1 303 567 4397",
    "sg:postcode":"80452",
    "sg:province":"CO",
    "sg:tags":[
        "gen",
        "contractor"
    ],
    "wof:name":"Alpine Craftsman Co Inc",
    "wof:placetype":"venue"
},
  "geometry": {"coordinates":[-105.587164,39.71126],"type":"Point"}
}