{
  "type": "Feature",
  "properties": {
    "addr:full":"7097 S Madison Way Centennial CO 80122",
    "addr:housenumber":"7097",
    "addr:postcode":"80122",
    "addr:street":"S Madison Way",
    "iso:country":"US",
    "sg:address":"7097 S Madison Way",
    "sg:city":"Centennial",
    "sg:classifiers":[
        {
            "category":"Building & Trades",
            "subcategory":"Construction",
            "type":"Services"
        }
    ],
    "sg:phone":"+1 303 771 2893",
    "sg:postcode":"80122",
    "sg:province":"CO",
    "sg:tags":[
        "contractor",
        "mason"
    ],
    "wof:name":"Stone Specialists Inc",
    "wof:placetype":"venue"
},
  "geometry": {"coordinates":[-104.949001,39.587689],"type":"Point"}
}