{
  "type": "Feature",
  "properties": {
    "addr:full":"2048 N Rd Fruita CO 81521",
    "addr:housenumber":"2048",
    "addr:postcode":"81521",
    "addr:street":"N Rd",
    "iso:country":"US",
    "sg:address":"2048 N Rd",
    "sg:city":"Fruita",
    "sg:classifiers":[
        {
            "category":"Building & Trades",
            "subcategory":"Construction",
            "type":"Services"
        }
    ],
    "sg:phone":"+1 970 858 3341",
    "sg:postcode":"81521",
    "sg:province":"CO",
    "sg:tags":[
        "house"
    ],
    "wof:name":"Pine Tree Construction",
    "wof:placetype":"venue"
},
  "geometry": {"coordinates":[-108.668469,39.207889],"type":"Point"}
}