{
  "type": "Feature",
  "properties": {
    "addr:full":"7344 N Academy Blvd Colorado Springs CO 80920",
    "addr:housenumber":"7344",
    "addr:postcode":"80920",
    "addr:street":"N Academy Blvd",
    "iso:country":"US",
    "sg:address":"7344 N Academy Blvd",
    "sg:city":"Colorado Springs",
    "sg:classifiers":[
        {
            "category":"Restaurant",
            "type":"Food & Drink"
        },
        {
            "category":"Bakery",
            "type":"Food & Drink"
        }
    ],
    "sg:menulink":"http://www.allmenus.com/co/colorado-springs/103182-panera-bread/menu/",
    "sg:phone":"+1 719 522 1100",
    "sg:postcode":"80920",
    "sg:province":"CO",
    "sg:tags":[
        "american",
        "sandwich",
        "bakery",
        "pastry"
    ],
    "wof:name":"Panera Bread",
    "wof:placetype":"venue"
},
  "geometry": {"coordinates":[-104.79851600000001,38.937792],"type":"Point"}
}