{
  "type": "Feature",
  "properties": {
    "iso:country":"US",
    "sg:address":"1027 N Weber St",
    "sg:city":"Colorado Springs",
    "sg:classifiers":[
        {
            "category":"Real Estate",
            "subcategory":"Real Estate Agent",
            "type":"Services"
        }
    ],
    "sg:phone":"+1 719 634 6490",
    "sg:postcode":"80903",
    "sg:province":"CO",
    "sg:tags":[
        "management"
    ],
    "wof:name":"Sunflower Management",
    "wof:placetype":"venue"
},
  "geometry": {"coordinates":[-104.81902700000001,38.847879],"type":"Point"}
}