{
  "type": "Feature",
  "properties": {
    "addr:full":"9736 E Bayou Gulch Rd Franktown CO 80134",
    "addr:housenumber":"9736",
    "addr:postcode":"80134",
    "addr:street":"E Bayou Gulch Rd",
    "iso:country":"US",
    "sg:address":"9736 E Bayou Gulch Rd",
    "sg:city":"Franktown",
    "sg:classifiers":[
        {
            "category":"Recreation",
            "type":"Entertainment"
        }
    ],
    "sg:phone":"+1 303 814 3536",
    "sg:postcode":"80134",
    "sg:province":"CO",
    "sg:tags":[
        "stable"
    ],
    "wof:name":"Helicon Show Stables",
    "wof:placetype":"venue"
},
  "geometry": {"coordinates":[-104.704825,39.414613],"type":"Point"}
}