{
  "type": "Feature",
  "properties": {
    "iso:country":"US",
    "sg:address":"3190 W 14th Avenue",
    "sg:city":"Denver",
    "sg:classifiers":[
        {
            "category":"Real Estate",
            "subcategory":"Real Estate Operator",
            "type":"Services"
        }
    ],
    "sg:phone":"+1 303 991 3941",
    "sg:postcode":"80204",
    "sg:province":"CO",
    "sg:tags":[
        "apartment"
    ],
    "wof:name":"Dorchester Apts",
    "wof:placetype":"venue"
},
  "geometry": {"coordinates":[-105.027002,39.73858],"type":"Point"}
}