{
  "type": "Feature",
  "properties": {
    "addr:full":"9635 S Maroon Cir Englewood CO 80112",
    "addr:housenumber":"9635",
    "addr:postcode":"80112",
    "addr:street":"S Maroon Cir",
    "iso:country":"US",
    "sg:address":"9635 S Maroon Cir",
    "sg:city":"Englewood",
    "sg:classifiers":[
        {
            "category":"Professional",
            "subcategory":"Computer Services",
            "type":"Services"
        }
    ],
    "sg:phone":"+1 303 446 9000",
    "sg:postcode":"80112",
    "sg:province":"CO",
    "sg:tags":[
        "software"
    ],
    "sg:website":"www.mincom.com",
    "wof:name":"Mincom USA Inc",
    "wof:placetype":"venue"
},
  "geometry": {"coordinates":[-104.86066099999999,39.542358],"type":"Point"}
}