{
  "type": "Feature",
  "properties": {
    "addr:full":"94 Arlian Rd Carbondale CO 81623",
    "addr:housenumber":"94",
    "addr:postcode":"81623",
    "addr:street":"Arlian Rd",
    "iso:country":"US",
    "sg:address":"94 Arlian Rd",
    "sg:city":"Carbondale",
    "sg:classifiers":[
        {
            "category":"Building & Trades",
            "subcategory":"Construction",
            "type":"Services"
        }
    ],
    "sg:phone":"+1 970 963 3309",
    "sg:postcode":"81623",
    "sg:province":"CO",
    "sg:tags":[
        "house"
    ],
    "wof:name":"Gaviota Graphics",
    "wof:placetype":"venue"
},
  "geometry": {"coordinates":[-107.115601,39.400488],"type":"Point"}
}