{
  "type": "Feature",
  "properties": {
    "iso:country":"US",
    "sg:address":"202 W North St",
    "sg:city":"Cortez",
    "sg:classifiers":[
        {
            "category":"Professional",
            "subcategory":"Lawyer & Legal Services",
            "type":"Services"
        }
    ],
    "sg:phone":"+1 970 565 2466",
    "sg:postcode":"81321",
    "sg:province":"CO",
    "sg:tags":[
        "attorney"
    ],
    "wof:name":"Diana Barber",
    "wof:placetype":"venue"
},
  "geometry": {"coordinates":[-108.589136,37.349728],"type":"Point"}
}