{
  "type": "Feature",
  "properties": {
    "addr:full":"1451 W Cedar Ave Denver CO 80223",
    "addr:housenumber":"1451",
    "addr:postcode":"80223",
    "addr:street":"W Cedar Ave",
    "iso:country":"US",
    "sg:address":"1451 W Cedar Ave",
    "sg:city":"Denver",
    "sg:classifiers":[
        {
            "category":"Building & Trades",
            "subcategory":"Electrical",
            "type":"Services"
        }
    ],
    "sg:phone":"+1 303 766 1977",
    "sg:postcode":"80223",
    "sg:province":"CO",
    "sg:tags":[
        "electrical",
        "contractor"
    ],
    "wof:name":"Sasco Electric Inc",
    "wof:placetype":"venue"
},
  "geometry": {"coordinates":[-105.00760699999999,39.713117],"type":"Point"}
}