{
  "type": "Feature",
  "properties": {
    "addr:full":"931 Crown Ct Fruita CO 81521",
    "addr:housenumber":"931",
    "addr:postcode":"81521",
    "addr:street":"Crown Ct",
    "iso:country":"US",
    "sg:address":"931 Crown Ct",
    "sg:city":"Fruita",
    "sg:classifiers":[
        {
            "category":"Building & Trades",
            "subcategory":"Plumbing",
            "type":"Services"
        }
    ],
    "sg:phone":"+1 970 858 4750",
    "sg:postcode":"81521",
    "sg:province":"CO",
    "sg:tags":[
        "contractor"
    ],
    "wof:name":"Reed Plumbing and Heating Inc",
    "wof:placetype":"venue"
},
  "geometry": {"coordinates":[-108.74434599999999,39.136094],"type":"Point"}
}