{
  "type": "Feature",
  "properties": {
    "addr:full":"1501 E Colfax Ave Denver CO 80218",
    "addr:housenumber":"1501",
    "addr:postcode":"80218",
    "addr:street":"E Colfax Ave",
    "iso:country":"US",
    "sg:address":"1501 E Colfax Ave",
    "sg:city":"Denver",
    "sg:classifiers":[
        {
            "category":"Restaurant",
            "type":"Food & Drink"
        }
    ],
    "sg:phone":"+1 303 623 4897",
    "sg:postcode":"80218",
    "sg:province":"CO",
    "sg:tags":[
        "pizza"
    ],
    "sg:website":"www.3guyspies.com",
    "wof:name":"3 Guys Pies",
    "wof:placetype":"venue"
},
  "geometry": {"coordinates":[-104.969489,39.740033],"type":"Point"}
}