{
  "type": "Feature",
  "properties": {
    "addr:full":"3805 Carson Ave Evans CO 80620",
    "addr:housenumber":"3805",
    "addr:postcode":"80620",
    "addr:street":"Carson Ave",
    "iso:country":"US",
    "sg:address":"3805 Carson Ave",
    "sg:city":"Evans",
    "sg:classifiers":[
        {
            "category":"Freight",
            "type":"Transportation"
        },
        {
            "category":"Shopping",
            "type":"Retail Goods"
        }
    ],
    "sg:phone":"+1 970 339 9905",
    "sg:postcode":"80620",
    "sg:province":"CO",
    "sg:tags":[
        "commercial",
        "storage",
        "merchandise"
    ],
    "wof:name":"Apex Storage & Warehouse LLC",
    "wof:placetype":"venue"
},
  "geometry": {"coordinates":[-104.699405,40.374342],"type":"Point"}
}