{
  "type": "Feature",
  "properties": {
    "iso:country":"US",
    "sg:address":"1305 Barlow Rd",
    "sg:city":"Fort Morgan",
    "sg:classifiers":[
        {
            "category":"Restaurant",
            "type":"Food & Drink"
        }
    ],
    "sg:menulink":"http://www.allmenus.com/co/fort-morgan/124106-quiznos-sub/menu/",
    "sg:phone":"+1 970 867 3955",
    "sg:postcode":"80701",
    "sg:province":"CO",
    "sg:tags":[
        "wrap",
        "american",
        "sandwich"
    ],
    "wof:name":"Quiznos Sub",
    "wof:placetype":"venue"
},
  "geometry": {"coordinates":[-103.772847,40.258704],"type":"Point"}
}