{
  "type": "Feature",
  "properties": {
    "addr:full":"239 Corby Pl Castle Rock CO 80108",
    "addr:housenumber":"239",
    "addr:postcode":"80108",
    "addr:street":"Corby Pl",
    "iso:country":"US",
    "sg:address":"239 Corby Pl",
    "sg:city":"Castle Rock",
    "sg:classifiers":[
        {
            "category":"Food & Beverages",
            "subcategory":"Meat & Fish",
            "type":"Retail Goods"
        }
    ],
    "sg:phone":"+1 720 733 1342",
    "sg:postcode":"80108",
    "sg:province":"CO",
    "wof:name":"Dave Fish",
    "wof:placetype":"venue"
},
  "geometry": {"coordinates":[-104.889821,39.466726],"type":"Point"}
}