{
  "type": "Feature",
  "properties": {
    "addr:full":"4211 S Natches Ct Englewood CO 80110",
    "addr:housenumber":"4211",
    "addr:postcode":"80110",
    "addr:street":"S Natches Ct",
    "iso:country":"US",
    "sg:address":"4211 S Natches Ct",
    "sg:city":"Englewood",
    "sg:classifiers":[
        {
            "category":"Autos & Motor Vehicles",
            "subcategory":"Automobile Sales",
            "type":"Retail Goods"
        }
    ],
    "sg:phone":"+1 303 761 1200",
    "sg:postcode":"80110",
    "sg:province":"CO",
    "sg:tags":[
        "car",
        "used",
        "dealer"
    ],
    "wof:name":"Rocky Mountain Auto Sport",
    "wof:placetype":"venue"
},
  "geometry": {"coordinates":[-105.008808,39.640335],"type":"Point"}
}