{
  "type": "Feature",
  "properties": {
    "addr:full":"3320 S Parker Rd Aurora CO 80014",
    "addr:housenumber":"3320",
    "addr:postcode":"80014",
    "addr:street":"S Parker Rd",
    "iso:country":"US",
    "sg:address":"3320 S Parker Rd",
    "sg:city":"Aurora",
    "sg:classifiers":[
        {
            "category":"Building & Trades",
            "subcategory":"Construction",
            "type":"Services"
        }
    ],
    "sg:phone":"+1 303 755 2077",
    "sg:postcode":"80014",
    "sg:province":"CO",
    "wof:name":"Transportation Colorado Dept",
    "wof:placetype":"venue"
},
  "geometry": {"coordinates":[-104.838396,39.657663],"type":"Point"}
}