{
  "type": "Feature",
  "properties": {
    "iso:country":"US",
    "sg:address":"240 Front St",
    "sg:city":"Placerville",
    "sg:classifiers":[
        {
            "category":"Food & Beverages",
            "subcategory":"Groceries & Convenience Stores",
            "type":"Retail Goods"
        }
    ],
    "sg:phone":"+1 970 728 3216",
    "sg:postcode":"81430",
    "sg:province":"CO",
    "sg:tags":[
        "grocer"
    ],
    "wof:name":"M & M Mercantile",
    "wof:placetype":"venue"
},
  "geometry": {"coordinates":[-108.053127,38.016569],"type":"Point"}
}