{
  "type": "Feature",
  "properties": {
    "iso:country":"US",
    "sg:address":"244 E Main St",
    "sg:city":"Cortez",
    "sg:classifiers":[
        {
            "category":"Autos & Motor Vehicles",
            "subcategory":"Fuel & Gas Station",
            "type":"Retail Goods"
        }
    ],
    "sg:phone":"+1 970 565 4844",
    "sg:postcode":"81321",
    "sg:province":"CO",
    "sg:tags":[
        "oil"
    ],
    "wof:name":"Texaco Amigo Mart & Xpress",
    "wof:placetype":"venue"
},
  "geometry": {"coordinates":[-108.58172999999999,37.348744],"type":"Point"}
}