{
  "type": "Feature",
  "properties": {
    "addr:full":"59 Cottonwood Rd Avon CO 81620",
    "addr:housenumber":"59",
    "addr:postcode":"81620",
    "addr:street":"Cottonwood Rd",
    "iso:country":"US",
    "sg:address":"59 Cottonwood Rd",
    "sg:city":"Avon",
    "sg:classifiers":[
        {
            "category":"Personal",
            "subcategory":"Beauty Salon",
            "type":"Services"
        }
    ],
    "sg:phone":"+1 970 748 9048",
    "sg:postcode":"81620",
    "sg:province":"CO",
    "sg:tags":[
        "manicuring"
    ],
    "wof:name":"Fingertips",
    "wof:placetype":"venue"
},
  "geometry": {"coordinates":[-106.487296,39.618456],"type":"Point"}
}