{
  "type": "Feature",
  "properties": {
    "iso:country":"US",
    "sg:address":"1255 Centaur Village Dr",
    "sg:city":"Lafayette",
    "sg:classifiers":[
        {
            "category":"Organizations",
            "subcategory":"Religious Organization",
            "type":"Services"
        }
    ],
    "sg:phone":"+1 303 665 5165",
    "sg:postcode":"80026",
    "sg:province":"CO",
    "sg:tags":[
        "church"
    ],
    "wof:name":"First United Methodist Church",
    "wof:placetype":"venue"
},
  "geometry": {"coordinates":[-105.107619,39.982583],"type":"Point"}
}