{
  "type": "Feature",
  "properties": {
    "iso:country":"US",
    "sg:address":"3122 W Clyde Pl",
    "sg:city":"Denver",
    "sg:classifiers":[
        {
            "category":"Restaurant",
            "type":"Food & Drink"
        }
    ],
    "sg:phone":"+1 303 477 3244",
    "sg:postcode":"80211",
    "sg:province":"CO",
    "sg:tags":[
        "eating"
    ],
    "wof:name":"Susanna Cucina Inc",
    "wof:placetype":"venue"
},
  "geometry": {"coordinates":[-105.029754,39.768263],"type":"Point"}
}