{
  "type": "Feature",
  "properties": {
    "addr:full":"10316 S Baneberry Pl Littleton CO 80129",
    "addr:housenumber":"10316",
    "addr:postcode":"80129",
    "addr:street":"S Baneberry Pl",
    "iso:country":"US",
    "sg:address":"10316 S Baneberry Pl",
    "sg:city":"Littleton",
    "sg:classifiers":[
        {
            "category":"Shopping",
            "subcategory":"Computers & Home Electronics",
            "type":"Retail Goods"
        }
    ],
    "sg:phone":"+1 303 683 7470",
    "sg:postcode":"80129",
    "sg:province":"CO",
    "sg:tags":[
        "software"
    ],
    "sg:website":"www.software-more.com",
    "wof:name":"Chadams Marketing Inc",
    "wof:placetype":"venue"
},
  "geometry": {"coordinates":[-105.023831,39.528851],"type":"Point"}
}