{
  "type": "Feature",
  "properties": {
    "iso:country":"US",
    "sg:address":"825 S Shields St",
    "sg:city":"Fort Collins",
    "sg:classifiers":[
        {
            "category":"Real Estate",
            "subcategory":"Real Estate Agent",
            "type":"Services"
        }
    ],
    "sg:phone":"+1 970 204 4490",
    "sg:postcode":"80521",
    "sg:province":"CO",
    "wof:name":"Schreiber Real Estate",
    "wof:placetype":"venue"
},
  "geometry": {"coordinates":[-105.09601600000001,40.574773],"type":"Point"}
}