{
  "type": "Feature",
  "properties": {
    "iso:country":"US",
    "sg:address":"19511 E Batavia Dr",
    "sg:city":"Aurora",
    "sg:classifiers":[
        {
            "category":"Building & Trades",
            "subcategory":"Construction",
            "type":"Services"
        }
    ],
    "sg:phone":"+1 303 367 9693",
    "sg:postcode":"80011",
    "sg:province":"CO",
    "sg:tags":[
        "house"
    ],
    "wof:name":"Massey Const Inc",
    "wof:placetype":"venue"
},
  "geometry": {"coordinates":[-104.756332,39.741905],"type":"Point"}
}