{
  "type": "Feature",
  "properties": {
    "addr:full":"10855 W 77th Ave Arvada CO 80005",
    "addr:housenumber":"10855",
    "addr:postcode":"80005",
    "addr:street":"W 77Th Ave",
    "iso:country":"US",
    "sg:address":"10855 W 77th Ave",
    "sg:city":"Arvada",
    "sg:classifiers":[
        {
            "category":"Manufacturing",
            "subcategory":"Aerospace",
            "type":"Manufacturing & Wholesale Goods"
        }
    ],
    "sg:phone":"+1 303 431 1625",
    "sg:postcode":"80005",
    "sg:province":"CO",
    "sg:tags":[
        "aircraft"
    ],
    "wof:name":"Teledyne Continental Motors",
    "wof:placetype":"venue"
},
  "geometry": {"coordinates":[-105.12125399999999,39.836636],"type":"Point"}
}