{
  "type": "Feature",
  "properties": {
    "addr:full":"5400 W 11th St Greeley CO 80634",
    "addr:housenumber":"5400",
    "addr:postcode":"80634",
    "addr:street":"W 11Th St",
    "iso:country":"US",
    "sg:address":"5400 W 11th St",
    "sg:city":"Greeley",
    "sg:classifiers":[
        {
            "category":"Real Estate",
            "subcategory":"Developer",
            "type":"Services"
        }
    ],
    "sg:phone":"+1 970 304 1392",
    "sg:postcode":"80634",
    "sg:province":"CO",
    "wof:name":"C L Vista Ventures",
    "wof:placetype":"venue"
},
  "geometry": {"coordinates":[-104.770669,40.419953],"type":"Point"}
}