{
  "type": "Feature",
  "properties": {
    "addr:full":"8990 York St Denver CO 80229",
    "addr:housenumber":"8990",
    "addr:postcode":"80229",
    "addr:street":"York St",
    "iso:country":"US",
    "sg:address":"8990 York St",
    "sg:city":"Denver",
    "sg:classifiers":[
        {
            "category":"Education",
            "subcategory":"School",
            "type":"Public Place"
        }
    ],
    "sg:phone":"+1 303 853 1200",
    "sg:postcode":"80229",
    "sg:province":"CO",
    "sg:tags":[
        "high"
    ],
    "sg:website":"www.mapletonpublicschools.com",
    "wof:name":"Skyview High School",
    "wof:placetype":"venue"
},
  "geometry": {"coordinates":[-104.95901499999999,39.85988],"type":"Point"}
}