{
  "type": "Feature",
  "properties": {
    "iso:country":"US",
    "sg:address":"357 Tamara Ln",
    "sg:city":"Bayfield",
    "sg:classifiers":[
        {
            "category":"Arts & Performance",
            "subcategory":"Theater",
            "type":"Entertainment"
        }
    ],
    "sg:phone":"+1 970 749 5422",
    "sg:postcode":"81122",
    "sg:province":"CO",
    "sg:tags":[
        "musician"
    ],
    "wof:name":"Mountain Rose Music",
    "wof:placetype":"venue"
},
  "geometry": {"coordinates":[-107.61592,37.277337],"type":"Point"}
}