{
  "type": "Feature",
  "properties": {
    "iso:country":"US",
    "sg:address":"3561 Stagecoach Rd N",
    "sg:city":"Longmont",
    "sg:classifiers":[
        {
            "category":"Banks & Credit Unions",
            "subcategory":"Bank",
            "type":"Services"
        }
    ],
    "sg:phone":"+1 720 494 5603",
    "sg:postcode":"80504",
    "sg:province":"CO",
    "sg:tags":[
        "loan",
        "real estate"
    ],
    "wof:name":"Countrywide Home Loans",
    "wof:placetype":"venue"
},
  "geometry": {"coordinates":[-104.986935,40.1596],"type":"Point"}
}