{
  "type": "Feature",
  "properties": {
    "addr:full":"13490 Co Rd 70 Hayden CO 81639",
    "addr:housenumber":"13490;70",
    "addr:postcode":"81639",
    "addr:street":"Co Rd",
    "iso:country":"US",
    "sg:address":"13490 Co Rd 70",
    "sg:city":"Hayden",
    "sg:classifiers":[
        {
            "category":"Farming",
            "subcategory":"Livestock Farm",
            "type":"Manufacturing & Wholesale Goods"
        }
    ],
    "sg:phone":"+1 970 276 4171",
    "sg:postcode":"81639",
    "sg:province":"CO",
    "sg:tags":[
        "ranch"
    ],
    "wof:name":"Wolf Mountain Ranch",
    "wof:placetype":"venue"
},
  "geometry": {"coordinates":[-107.171828,40.512501],"type":"Point"}
}