{
  "type": "Feature",
  "properties": {
    "iso:country":"US",
    "sg:address":"3055 Roslyn St Ste 120",
    "sg:city":"Denver",
    "sg:classifiers":[
        {
            "category":"Personal",
            "subcategory":"Massage",
            "type":"Services"
        },
        {
            "category":"Health Services",
            "subcategory":"Health Practitioner",
            "type":"Services"
        },
        {
            "category":"Health Services",
            "subcategory":"Chiropractor",
            "type":"Services"
        }
    ],
    "sg:phone":"+1 303 355 0363",
    "sg:postcode":"80238",
    "sg:province":"CO",
    "sg:tags":[
        "acupuncture"
    ],
    "sg:website":"www.nbihdenver.com",
    "wof:name":"Natural Balance Integrative Health",
    "wof:placetype":"venue"
},
  "geometry": {"coordinates":[-104.90039,39.76018],"type":"Point"}
}