{
  "type": "Feature",
  "properties": {
    "iso:country":"US",
    "sg:address":"504 Graceland Dr",
    "sg:city":"Carbondale",
    "sg:classifiers":[
        {
            "category":"Real Estate",
            "subcategory":"Real Estate Agent",
            "type":"Services"
        }
    ],
    "sg:phone":"+1 970 963 1569",
    "sg:postcode":"81623",
    "sg:province":"CO",
    "wof:name":"A E Management Inc",
    "wof:placetype":"venue"
},
  "geometry": {"coordinates":[-107.220373,39.394889],"type":"Point"}
}