{
  "type": "Feature",
  "properties": {
    "iso:country":"US",
    "sg:address":"18245 State Hwy 94",
    "sg:city":"Colorado Springs",
    "sg:classifiers":[
        {
            "category":"Manufacturing",
            "subcategory":"Signs",
            "type":"Manufacturing & Wholesale Goods"
        }
    ],
    "sg:phone":"+1 719 597 9994",
    "sg:postcode":"80930",
    "sg:province":"CO",
    "sg:website":"www.usoma.com",
    "wof:name":"Performance Graphics",
    "wof:placetype":"venue"
},
  "geometry": {"coordinates":[-104.47484799999999,38.838715],"type":"Point"}
}