{
  "type": "Feature",
  "properties": {
    "addr:full":"4340 E Kentucky Ave Denver CO 80246",
    "addr:housenumber":"4340",
    "addr:postcode":"80246",
    "addr:street":"E Kentucky Ave",
    "iso:country":"US",
    "sg:address":"4340 E Kentucky Ave",
    "sg:city":"Denver",
    "sg:classifiers":[
        {
            "category":"Arts & Performance",
            "subcategory":"Arts Center",
            "type":"Entertainment"
        }
    ],
    "sg:phone":"+1 303 757 8824",
    "sg:postcode":"80246",
    "sg:province":"CO",
    "sg:website":"www.alewistickets.com",
    "wof:name":"A Lewis Tickets",
    "wof:placetype":"venue"
},
  "geometry": {"coordinates":[-104.937234,39.699799],"type":"Point"}
}