{
  "type": "Feature",
  "properties": {
    "addr:full":"17300 Co Rd 33.7 Sterling CO 80751",
    "addr:housenumber":"17300",
    "addr:postcode":"80751",
    "addr:street":"Co Rd",
    "iso:country":"US",
    "sg:address":"17300 Co Rd 33.7",
    "sg:city":"Sterling",
    "sg:classifiers":[
        {
            "category":"Manufacturing",
            "subcategory":"Metals",
            "type":"Manufacturing & Wholesale Goods"
        },
        {
            "category":"Manufacturing",
            "subcategory":"Tools & Machinery",
            "type":"Manufacturing & Wholesale Goods"
        }
    ],
    "sg:phone":"+1 970 522 4300",
    "sg:postcode":"80751",
    "sg:province":"CO",
    "sg:tags":[
        "product",
        "fan",
        "fabricated",
        "mfg"
    ],
    "wof:name":"Delta H Systems Inc",
    "wof:placetype":"venue"
},
  "geometry": {"coordinates":[-103.263102,40.683039],"type":"Point"}
}