{
  "type": "Feature",
  "properties": {
    "addr:full":"7742 Cornwall Cir Boulder CO 80301",
    "addr:housenumber":"7742",
    "addr:postcode":"80301",
    "addr:street":"Cornwall Cir",
    "iso:country":"US",
    "sg:address":"7742 Cornwall Cir",
    "sg:city":"Boulder",
    "sg:classifiers":[
        {
            "category":"Building & Trades",
            "subcategory":"Construction",
            "type":"Services"
        }
    ],
    "sg:phone":"+1 303 530 1173",
    "sg:postcode":"80301",
    "sg:province":"CO",
    "sg:tags":[
        "house"
    ],
    "wof:name":"Davids Home Improvement",
    "wof:placetype":"venue"
},
  "geometry": {"coordinates":[-105.172729,40.064039],"type":"Point"}
}