{
  "type": "Feature",
  "properties": {
    "addr:full":"2862 Co Rd 16 Woodrow CO 80757",
    "addr:housenumber":"2862;16",
    "addr:postcode":"80757",
    "addr:street":"Co Rd",
    "iso:country":"US",
    "sg:address":"2862 Co Rd 16",
    "sg:city":"Woodrow",
    "sg:classifiers":[
        {
            "category":"Farming",
            "subcategory":"Farm",
            "type":"Manufacturing & Wholesale Goods"
        }
    ],
    "sg:phone":"+1 970 386 2216",
    "sg:postcode":"80757",
    "sg:province":"CO",
    "sg:tags":[
        "crop",
        "general"
    ],
    "wof:name":"Baker Farm",
    "wof:placetype":"venue"
},
  "geometry": {"coordinates":[-103.65076999999999,39.798516],"type":"Point"}
}