{
  "type": "Feature",
  "properties": {
    "addr:full":"222 E Midland Ave Woodland Park CO 80863",
    "addr:housenumber":"222",
    "addr:postcode":"80863",
    "addr:street":"E Midland Ave",
    "iso:country":"US",
    "sg:address":"222 E Midland Ave",
    "sg:city":"Woodland Park",
    "sg:classifiers":[
        {
            "category":"Museum",
            "type":"Entertainment"
        }
    ],
    "sg:phone":"+1 719 686 7512",
    "sg:postcode":"80863",
    "sg:province":"CO",
    "sg:website":"www.utepasshistoricalsociety.org",
    "wof:name":"Pikes Peak Museum",
    "wof:placetype":"venue"
},
  "geometry": {"coordinates":[-105.050284,38.994572],"type":"Point"}
}