{
  "type": "Feature",
  "properties": {
    "iso:country":"US",
    "sg:address":"1605 Main St",
    "sg:city":"Alamosa",
    "sg:classifiers":[
        {
            "category":"Restaurant",
            "type":"Food & Drink"
        }
    ],
    "sg:phone":"+1 719 589 9256",
    "sg:postcode":"81101",
    "sg:province":"CO",
    "wof:name":"Sonic Drive-In",
    "wof:placetype":"venue"
},
  "geometry": {"coordinates":[-105.88178000000001,37.469768],"type":"Point"}
}