{
  "type": "Feature",
  "properties": {
    "iso:country":"US",
    "sg:address":"15363 E Nassau Dr",
    "sg:city":"Aurora",
    "sg:classifiers":[
        {
            "category":"Building & Trades",
            "subcategory":"Plumbing",
            "type":"Services"
        }
    ],
    "sg:phone":"+1 720 641 3227",
    "sg:postcode":"80013",
    "sg:province":"CO",
    "sg:tags":[
        "contractor"
    ],
    "wof:name":"Midwest Air Conditioning & Htg",
    "wof:placetype":"venue"
},
  "geometry": {"coordinates":[-104.809299,39.644128],"type":"Point"}
}