{
  "type": "Feature",
  "properties": {
    "addr:full":"8256 State Hwy 135 Gunnison CO 81230",
    "addr:housenumber":"8256",
    "addr:postcode":"81230",
    "addr:street":"State Hwy 135",
    "iso:country":"US",
    "sg:address":"8256 State Hwy 135",
    "sg:city":"Gunnison",
    "sg:classifiers":[
        {
            "category":"Home & Garden",
            "subcategory":"Building Materials",
            "type":"Retail Goods"
        }
    ],
    "sg:phone":"+1 970 641 9296",
    "sg:postcode":"81230",
    "sg:province":"CO",
    "sg:tags":[
        "glass",
        "window",
        "plate"
    ],
    "wof:name":"Roper Glass",
    "wof:placetype":"venue"
},
  "geometry": {"coordinates":[-106.855814,38.655431],"type":"Point"}
}