{
  "type": "Feature",
  "properties": {
    "addr:full":"11001 W 120th Ave Broomfield CO 80021",
    "addr:housenumber":"11001",
    "addr:postcode":"80021",
    "addr:street":"W 120Th Ave",
    "iso:country":"US",
    "sg:address":"11001 W 120th Ave",
    "sg:city":"Broomfield",
    "sg:classifiers":[
        {
            "category":"Professional",
            "subcategory":"Management & Consulting",
            "type":"Services"
        }
    ],
    "sg:phone":"+1 303 474 2020",
    "sg:postcode":"80021",
    "sg:province":"CO",
    "sg:tags":[
        "supplier",
        "indirect"
    ],
    "wof:name":"Essentialink",
    "wof:placetype":"venue"
},
  "geometry": {"coordinates":[-105.123884,39.915327],"type":"Point"}
}