{
  "type": "Feature",
  "properties": {
    "iso:country":"US",
    "sg:address":"3117 28th St",
    "sg:city":"Boulder",
    "sg:classifiers":[
        {
            "category":"Restaurant",
            "type":"Food & Drink"
        }
    ],
    "sg:phone":"+1 303 442 7864",
    "sg:postcode":"80301",
    "sg:province":"CO",
    "sg:tags":[
        "eating"
    ],
    "wof:name":"Togos Eatery",
    "wof:placetype":"venue"
},
  "geometry": {"coordinates":[-105.25849599999999,40.030642],"type":"Point"}
}