{
  "type": "Feature",
  "properties": {
    "iso:country":"US",
    "sg:address":"2045 S Holly Street",
    "sg:city":"Denver",
    "sg:classifiers":[
        {
            "category":"Education",
            "subcategory":"Music School",
            "type":"Public Place"
        }
    ],
    "sg:phone":"+1 303 756 5777",
    "sg:postcode":"80222",
    "sg:province":"CO",
    "sg:tags":[
        "instrument",
        "teacher",
        "musical"
    ],
    "wof:name":"Rupps Drums",
    "wof:placetype":"venue"
},
  "geometry": {"coordinates":[-104.922135,39.679591],"type":"Point"}
}