{
  "type": "Feature",
  "properties": {
    "iso:country":"US",
    "sg:address":"4151 E County Line Rd",
    "sg:city":"Centennial",
    "sg:classifiers":[
        {
            "category":"Home & Garden",
            "subcategory":"Building Materials",
            "type":"Retail Goods"
        },
        {
            "category":"Building & Trades",
            "subcategory":"Construction",
            "type":"Services"
        }
    ],
    "sg:phone":"+1 303 721 9198",
    "sg:postcode":"80122",
    "sg:province":"CO",
    "sg:tags":[
        "tile",
        "ceramic",
        "dealer"
    ],
    "sg:website":"www.coloradotile.com",
    "wof:name":"Colorado Ceramic Tile Inc",
    "wof:placetype":"venue"
},
  "geometry": {"coordinates":[-104.936835,39.566116],"type":"Point"}
}