{
  "type": "Feature",
  "properties": {
    "iso:country":"US",
    "sg:address":"3126 Buttercup Ln",
    "sg:city":"Evergreen",
    "sg:classifiers":[
        {
            "category":"Professional",
            "type":"Services"
        }
    ],
    "sg:phone":"+1 303 674 5622",
    "sg:postcode":"80439",
    "sg:province":"CO",
    "wof:name":"Charles Campfield",
    "wof:placetype":"venue"
},
  "geometry": {"coordinates":[-105.30102599999999,39.659016],"type":"Point"}
}