{
  "type": "Feature",
  "properties": {
    "iso:country":"US",
    "sg:address":"615 Main St",
    "sg:city":"Westcliffe",
    "sg:classifiers":[
        {
            "category":"Professional",
            "subcategory":"Management & Consulting",
            "type":"Services"
        }
    ],
    "sg:phone":"+1 719 783 4699",
    "sg:postcode":"81252",
    "sg:province":"CO",
    "sg:tags":[
        "consultant",
        "business"
    ],
    "wof:name":"ROI Management Corp",
    "wof:placetype":"venue"
},
  "geometry": {"coordinates":[-105.46359699999999,38.135995],"type":"Point"}
}