{
  "type": "Feature",
  "properties": {
    "addr:full":"10642 E US Hwy 160 Alamosa CO 81101",
    "addr:housenumber":"10642",
    "addr:postcode":"81101",
    "addr:street":"E Us Hwy 160",
    "iso:country":"US",
    "sg:address":"10642 E US Hwy 160",
    "sg:city":"Alamosa",
    "sg:classifiers":[
        {
            "category":"Wholesale",
            "subcategory":"Farm Supplies",
            "type":"Manufacturing & Wholesale Goods"
        }
    ],
    "sg:phone":"+1 719 589 2942",
    "sg:postcode":"81101",
    "sg:province":"CO",
    "sg:tags":[
        "hay"
    ],
    "wof:name":"Paine Enterprises LLC",
    "wof:placetype":"venue"
},
  "geometry": {"coordinates":[-105.84563300000001,37.473249],"type":"Point"}
}