{
  "type": "Feature",
  "properties": {
    "iso:country":"US",
    "sg:address":"1930 S Havana St",
    "sg:city":"Aurora",
    "sg:classifiers":[
        {
            "category":"Cinema",
            "subcategory":"Movie Rental",
            "type":"Entertainment"
        }
    ],
    "sg:phone":"+1 303 337 1588",
    "sg:postcode":"80014",
    "sg:province":"CO",
    "sg:tags":[
        "leasing",
        "video",
        "disc",
        "tape"
    ],
    "wof:name":"Denver Video",
    "wof:placetype":"venue"
},
  "geometry": {"coordinates":[-104.865875,39.680761],"type":"Point"}
}