{
  "type": "Feature",
  "properties": {
    "addr:full":"630 Lipan St Denver CO 80204",
    "addr:housenumber":"630",
    "addr:postcode":"80204",
    "addr:street":"Lipan St",
    "iso:country":"US",
    "sg:address":"630 Lipan St",
    "sg:city":"Denver",
    "sg:classifiers":[
        {
            "category":"Professional",
            "subcategory":"Engineering",
            "type":"Services"
        },
        {
            "category":"Building & Trades",
            "subcategory":"Construction",
            "type":"Services"
        }
    ],
    "sg:phone":"+1 303 573 7100",
    "sg:postcode":"80204",
    "sg:province":"CO",
    "sg:tags":[
        "system",
        "specialty",
        "heating",
        "equipment",
        "contractor",
        "air conditioning"
    ],
    "sg:website":"http://www.jebco.com",
    "wof:name":"Jebco Heating & Air Conditioning",
    "wof:placetype":"venue"
},
  "geometry": {"coordinates":[-105.001617,39.725679],"type":"Point"}
}