{
  "type": "Feature",
  "properties": {
    "addr:full":"5818 S Skyline Dr Evergreen CO 80439",
    "addr:housenumber":"5818",
    "addr:postcode":"80439",
    "addr:street":"S Skyline Dr",
    "iso:country":"US",
    "sg:address":"5818 S Skyline Dr",
    "sg:city":"Evergreen",
    "sg:classifiers":[
        {
            "category":"Building & Trades",
            "subcategory":"Construction",
            "type":"Services"
        }
    ],
    "sg:phone":"+1 303 674 2767",
    "sg:postcode":"80439",
    "sg:province":"CO",
    "sg:tags":[
        "floor",
        "laying",
        "contractor"
    ],
    "wof:name":"MRM Custom Cabinetry Inc",
    "wof:placetype":"venue"
},
  "geometry": {"coordinates":[-105.310214,39.610502],"type":"Point"}
}