{
  "type": "Feature",
  "properties": {
    "addr:full":"4300 Co Rd 18 Longmont CO 80504",
    "addr:housenumber":"4300;18",
    "addr:postcode":"80504",
    "addr:street":"Co Rd",
    "iso:country":"US",
    "sg:address":"4300 Co Rd 18",
    "sg:city":"Longmont",
    "sg:classifiers":[
        {
            "category":"Manufacturing",
            "subcategory":"Motor Vehicles & Parts",
            "type":"Manufacturing & Wholesale Goods"
        }
    ],
    "sg:phone":"+1 720 494 1555",
    "sg:postcode":"80504",
    "sg:province":"CO",
    "sg:tags":[
        "automobile",
        "supply"
    ],
    "wof:name":"Delphi Automotive",
    "wof:placetype":"venue"
},
  "geometry": {"coordinates":[-104.974165,40.116826],"type":"Point"}
}