{
  "type": "Feature",
  "properties": {
    "addr:full":"18648 E Hampden Ave Aurora CO 80013",
    "addr:housenumber":"18648",
    "addr:postcode":"80013",
    "addr:street":"E Hampden Ave",
    "iso:country":"US",
    "sg:address":"18648 E Hampden Ave",
    "sg:city":"Aurora",
    "sg:classifiers":[
        {
            "category":"Restaurant",
            "type":"Food & Drink"
        }
    ],
    "sg:menulink":"http://www.allmenus.com/co/south-aurora/65303-cicis-pizza-buffet/menu/",
    "sg:phone":"+1 303 617 3222",
    "sg:postcode":"80013",
    "sg:province":"CO",
    "sg:tags":[
        "american",
        "pizza"
    ],
    "wof:name":"CiCi's Pizza Buffet",
    "wof:placetype":"venue"
},
  "geometry": {"coordinates":[-104.770533,39.652952],"type":"Point"}
}