{
  "type": "Feature",
  "properties": {
    "addr:full":"2520 14th Ave Greeley CO 80631",
    "addr:housenumber":"2520",
    "addr:postcode":"80631",
    "addr:street":"14Th Ave",
    "iso:country":"US",
    "sg:address":"2520 14th Ave",
    "sg:city":"Greeley",
    "sg:classifiers":[
        {
            "category":"Bars & Pubs",
            "type":"Food & Drink"
        }
    ],
    "sg:phone":"+1 970 356 7407",
    "sg:postcode":"80631",
    "sg:province":"CO",
    "wof:name":"Rick's Libations",
    "wof:placetype":"venue"
},
  "geometry": {"coordinates":[-104.700987,40.395417],"type":"Point"}
}