{
  "type": "Feature",
  "properties": {
    "iso:country":"US",
    "sg:address":"25019 E Plymouth Cir",
    "sg:city":"Aurora",
    "sg:classifiers":[
        {
            "category":"Banks & Credit Unions",
            "subcategory":"Bank",
            "type":"Services"
        }
    ],
    "sg:phone":"+1 303 873 1847",
    "sg:postcode":"80016",
    "sg:province":"CO",
    "sg:tags":[
        "mortgage",
        "loan",
        "broker",
        "real estate"
    ],
    "wof:name":"Thompson Mortgage & Associates",
    "wof:placetype":"venue"
},
  "geometry": {"coordinates":[-104.69606,39.59065],"type":"Point"}
}