{
  "type": "Feature",
  "properties": {
    "addr:full":"10200 Brush Creek Rd Eagle CO 81631",
    "addr:housenumber":"10200",
    "addr:postcode":"81631",
    "addr:street":"Brush Creek Rd",
    "iso:country":"US",
    "sg:address":"10200 Brush Creek Rd",
    "sg:city":"Eagle",
    "sg:classifiers":[
        {
            "category":"Travel",
            "subcategory":"Campground",
            "type":"Entertainment"
        }
    ],
    "sg:phone":"+1 970 328 2021",
    "sg:postcode":"81631",
    "sg:province":"CO",
    "sg:website":"www.parks.state.co.us",
    "wof:name":"Sylvan Lake State Park",
    "wof:placetype":"venue"
},
  "geometry": {"coordinates":[-106.762435,39.55244],"type":"Point"}
}