{
  "type": "Feature",
  "properties": {
    "iso:country":"US",
    "sg:address":"468 Tiara Rd",
    "sg:city":"Lake George",
    "sg:classifiers":[
        {
            "category":"Building & Trades",
            "subcategory":"Construction",
            "type":"Services"
        }
    ],
    "sg:phone":"+1 719 748 5295",
    "sg:postcode":"80827",
    "sg:province":"CO",
    "sg:tags":[
        "contractor"
    ],
    "wof:name":"Kelley Contracting LLC",
    "wof:placetype":"venue"
},
  "geometry": {"coordinates":[-105.51758,38.971412],"type":"Point"}
}