{
  "type": "Feature",
  "properties": {
    "iso:country":"US",
    "sg:address":"20695 E Lake Ave",
    "sg:city":"Centennial",
    "sg:classifiers":[
        {
            "category":"Banks & Credit Unions",
            "subcategory":"Bank",
            "type":"Services"
        }
    ],
    "sg:phone":"+1 303 680 3517",
    "sg:postcode":"80016",
    "sg:province":"CO",
    "sg:tags":[
        "loan",
        "real estate"
    ],
    "wof:name":"Experian Mortgage Svc",
    "wof:placetype":"venue"
},
  "geometry": {"coordinates":[-104.750854,39.607579],"type":"Point"}
}