{
  "type": "Feature",
  "properties": {
    "addr:full":"4910 Iris St Wheat Ridge CO 80033",
    "addr:housenumber":"4910",
    "addr:postcode":"80033",
    "addr:street":"Iris St",
    "iso:country":"US",
    "sg:address":"4910 Iris St",
    "sg:city":"Wheat Ridge",
    "sg:classifiers":[
        {
            "category":"Professional",
            "subcategory":"Management & Consulting",
            "type":"Services"
        }
    ],
    "sg:phone":"+1 303 463 6661",
    "sg:postcode":"80033",
    "sg:province":"CO",
    "sg:tags":[
        "consultant",
        "lighting"
    ],
    "wof:name":"White Lighting Design Inc",
    "wof:placetype":"venue"
},
  "geometry": {"coordinates":[-105.10611299999999,39.787591],"type":"Point"}
}