{
  "type": "Feature",
  "properties": {
    "addr:full":"400 N 11th St Rocky Ford CO 81067",
    "addr:housenumber":"400",
    "addr:postcode":"81067",
    "addr:street":"N 11Th St",
    "iso:country":"US",
    "sg:address":"400 N 11th St",
    "sg:city":"Rocky Ford",
    "sg:classifiers":[
        {
            "category":"Restaurant",
            "type":"Food & Drink"
        }
    ],
    "sg:phone":"+1 719 254 2451",
    "sg:postcode":"81067",
    "sg:province":"CO",
    "wof:name":"Fiesta Restaurant",
    "wof:placetype":"venue"
},
  "geometry": {"coordinates":[-103.71546600000001,38.054164],"type":"Point"}
}