{
  "type": "Feature",
  "properties": {
    "iso:country":"US",
    "sg:address":"1428 Leeds Ave",
    "sg:city":"Montrose",
    "sg:classifiers":[
        {
            "category":"Shopping",
            "type":"Retail Goods"
        }
    ],
    "sg:phone":"+1 970 240 4860",
    "sg:postcode":"81401",
    "sg:province":"CO",
    "sg:tags":[
        "merchandise"
    ],
    "wof:name":"Rushing Communications",
    "wof:placetype":"venue"
},
  "geometry": {"coordinates":[-107.85011900000001,38.469242],"type":"Point"}
}