{
  "type": "Feature",
  "properties": {
    "iso:country":"US",
    "sg:address":"3401 Humboldt St",
    "sg:city":"Denver",
    "sg:classifiers":[
        {
            "category":"Retail",
            "subcategory":"Auto Repair",
            "type":"Services"
        }
    ],
    "sg:phone":"+1 303 295 2491",
    "sg:postcode":"80205",
    "sg:province":"CO",
    "wof:name":"East Side Auto and Tire Repair",
    "wof:placetype":"venue"
},
  "geometry": {"coordinates":[-104.97,39.764787],"type":"Point"}
}