{
  "type": "Feature",
  "properties": {
    "addr:full":"850 E Harvard Ave Ste 505 Suite 500 Denver CO 80210",
    "addr:housenumber":"850",
    "addr:postcode":"80210",
    "addr:street":"E Harvard Ave Ste 505 Suite 500",
    "iso:country":"US",
    "sg:address":"850 E Harvard Ave Ste 505 Suite 500",
    "sg:city":"Denver",
    "sg:classifiers":[
        {
            "category":"Health Services",
            "subcategory":"Doctor",
            "type":"Services"
        }
    ],
    "sg:phone":"+1 303 744 1961",
    "sg:postcode":"80210",
    "sg:province":"CO",
    "sg:website":"www.entmds.com",
    "wof:name":"Associates of Otolaryngology PC",
    "wof:placetype":"venue"
},
  "geometry": {"coordinates":[-104.97781999999999,39.670389],"type":"Point"}
}