{
  "type": "Feature",
  "properties": {
    "iso:country":"US",
    "sg:address":"6395 S Clarkson St",
    "sg:city":"Centennial",
    "sg:classifiers":[
        {
            "category":"Organizations",
            "subcategory":"Religious Organization",
            "type":"Services"
        }
    ],
    "sg:phone":"+1 303 347 9706",
    "sg:postcode":"80121",
    "sg:province":"CO",
    "sg:tags":[
        "church"
    ],
    "sg:website":"www.fwcenter.org",
    "wof:name":"Family Worship Ctr",
    "wof:placetype":"venue"
},
  "geometry": {"coordinates":[-104.97887,39.60253],"type":"Point"}
}