{
  "type": "Feature",
  "properties": {
    "addr:full":"1232 Bergen Pkwy Evergreen CO 80439",
    "addr:housenumber":"1232",
    "addr:postcode":"80439",
    "addr:street":"Bergen Pkwy",
    "iso:country":"US",
    "sg:address":"1232 Bergen Pkwy",
    "sg:city":"Evergreen",
    "sg:classifiers":[
        {
            "category":"Home & Garden",
            "subcategory":"Building Materials",
            "type":"Retail Goods"
        }
    ],
    "sg:phone":"+1 303 674 3301",
    "sg:postcode":"80439",
    "sg:province":"CO",
    "sg:tags":[
        "lumber"
    ],
    "sg:website":"www.bmhc.com",
    "wof:name":"BMC West Building Materials",
    "wof:placetype":"venue"
},
  "geometry": {"coordinates":[-105.356745,39.692963],"type":"Point"}
}