{
  "type": "Feature",
  "properties": {
    "addr:full":"11512 Co Rd 31 Sterling CO 80751",
    "addr:housenumber":"11512;31",
    "addr:postcode":"80751",
    "addr:street":"Co Rd",
    "iso:country":"US",
    "sg:address":"11512 Co Rd 31",
    "sg:city":"Sterling",
    "sg:classifiers":[
        {
            "category":"Farming",
            "subcategory":"Livestock Farm",
            "type":"Manufacturing & Wholesale Goods"
        }
    ],
    "sg:phone":"+1 970 522 8006",
    "sg:postcode":"80751",
    "sg:province":"CO",
    "sg:tags":[
        "equine"
    ],
    "wof:name":"Tri Star Farms Inc",
    "wof:placetype":"venue"
},
  "geometry": {"coordinates":[-103.296902,40.602922],"type":"Point"}
}