{
  "type": "Feature",
  "properties": {
    "addr:full":"10 S Parkside Dr Colorado Springs CO 80910",
    "addr:housenumber":"10",
    "addr:postcode":"80910",
    "addr:street":"S Parkside Dr",
    "iso:country":"US",
    "sg:address":"10 S Parkside Dr",
    "sg:city":"Colorado Springs",
    "sg:classifiers":[
        {
            "category":"Organizations",
            "subcategory":"Religious Organization",
            "type":"Services"
        }
    ],
    "sg:phone":"+1 719 477 9300",
    "sg:postcode":"80910",
    "sg:province":"CO",
    "sg:tags":[
        "church"
    ],
    "sg:website":"www.vocos.org",
    "wof:name":"Victory Outreach",
    "wof:placetype":"venue"
},
  "geometry": {"coordinates":[-104.78472499999999,38.832108],"type":"Point"}
}