{
  "type": "Feature",
  "properties": {
    "addr:full":"6885 S Marshall St Littleton CO 80128",
    "addr:housenumber":"6885",
    "addr:postcode":"80128",
    "addr:street":"S Marshall St",
    "iso:country":"US",
    "sg:address":"6885 S Marshall St",
    "sg:city":"Littleton",
    "sg:classifiers":[
        {
            "category":"Professional",
            "subcategory":"Research",
            "type":"Services"
        }
    ],
    "sg:phone":"+1 303 948 7733",
    "sg:postcode":"80128",
    "sg:province":"CO",
    "sg:tags":[
        "environmental",
        "ecological"
    ],
    "wof:name":"American Enviormental Conslnt",
    "wof:placetype":"venue"
},
  "geometry": {"coordinates":[-105.06840699999999,39.591634],"type":"Point"}
}