{
  "type": "Feature",
  "properties": {
    "iso:country":"US",
    "sg:address":"1945 S Sheridan Boulevard Unit 101",
    "sg:city":"Denver",
    "sg:classifiers":[
        {
            "category":"Cinema",
            "subcategory":"Movie Rental",
            "type":"Entertainment"
        }
    ],
    "sg:phone":"+1 303 980 1900",
    "sg:postcode":"80227",
    "sg:province":"CO",
    "sg:tags":[
        "game",
        "video"
    ],
    "sg:website":"www.blockbuster.com",
    "wof:name":"Blockbuster Video",
    "wof:placetype":"venue"
},
  "geometry": {"coordinates":[-105.05327,39.681608],"type":"Point"}
}