{
  "type": "Feature",
  "properties": {
    "iso:country":"US",
    "sg:address":"5281 E 52nd Avenue",
    "sg:city":"Commerce City",
    "sg:classifiers":[
        {
            "category":"Food & Beverages",
            "subcategory":"Liquor & Beverages",
            "type":"Retail Goods"
        }
    ],
    "sg:phone":"+1 303 287 7966",
    "sg:postcode":"80022",
    "sg:province":"CO",
    "sg:tags":[
        "beer",
        "spirit",
        "wine"
    ],
    "wof:name":"Liquors Plus",
    "wof:placetype":"venue"
},
  "geometry": {"coordinates":[-104.925342,39.791178],"type":"Point"}
}