{
  "type": "Feature",
  "properties": {
    "iso:country":"US",
    "sg:address":"1460 S Federal Boulevard",
    "sg:city":"Denver",
    "sg:classifiers":[
        {
            "category":"Personal",
            "subcategory":"Nail Salon",
            "type":"Services"
        }
    ],
    "sg:phone":"+1 303 742 2184",
    "sg:postcode":"80219",
    "sg:province":"CO",
    "wof:name":"Lisa Nails",
    "wof:placetype":"venue"
},
  "geometry": {"coordinates":[-105.025161,39.690471],"type":"Point"}
}