{
  "type": "Feature",
  "properties": {
    "addr:full":"1321 Windjammer Cove Fort Collins CO 80524",
    "addr:housenumber":"1321",
    "addr:postcode":"80524",
    "addr:street":"Windjammer Cove",
    "iso:country":"US",
    "sg:address":"1321 Windjammer Cove",
    "sg:city":"Fort Collins",
    "sg:classifiers":[
        {
            "category":"Professional",
            "subcategory":"Advertising",
            "type":"Services"
        }
    ],
    "sg:phone":"+1 970 221 1691",
    "sg:postcode":"80524",
    "sg:province":"CO",
    "wof:name":"Discover Fort Collins Magazine",
    "wof:placetype":"venue"
},
  "geometry": {"coordinates":[-105.052289,40.607706],"type":"Point"}
}