{
  "type": "Feature",
  "properties": {
    "addr:full":"215 E Main St Cortez CO 81321",
    "addr:housenumber":"215",
    "addr:postcode":"81321",
    "addr:street":"E Main St",
    "iso:country":"US",
    "sg:address":"215 E Main St",
    "sg:city":"Cortez",
    "sg:classifiers":[
        {
            "category":"Shopping",
            "subcategory":"Music",
            "type":"Retail Goods"
        }
    ],
    "sg:phone":"+1 970 565 3795",
    "sg:postcode":"81321",
    "sg:province":"CO",
    "sg:tags":[
        "compact",
        "record",
        "disc",
        "tape"
    ],
    "wof:name":"Rocky Mountain One Stop",
    "wof:placetype":"venue"
},
  "geometry": {"coordinates":[-108.581214,37.348676],"type":"Point"}
}