{
  "type": "Feature",
  "properties": {
    "iso:country":"US",
    "sg:address":"722 Horizon Dr",
    "sg:city":"Grand Junction",
    "sg:classifiers":[
        {
            "category":"Restaurant",
            "type":"Food & Drink"
        }
    ],
    "sg:menulink":"http://www.allmenus.com/co/grand-junction/128845-subway/menu/",
    "sg:phone":"+1 970 241 6336",
    "sg:postcode":"81506",
    "sg:province":"CO",
    "sg:tags":[
        "american",
        "sandwich"
    ],
    "wof:name":"Subway",
    "wof:placetype":"venue"
},
  "geometry": {"coordinates":[-108.55962599999999,39.096664],"type":"Point"}
}