{
  "type": "Feature",
  "properties": {
    "iso:country":"US",
    "sg:address":"3442 Cody Ave",
    "sg:city":"Evans",
    "sg:classifiers":[
        {
            "category":"Building & Trades",
            "subcategory":"Construction",
            "type":"Services"
        }
    ],
    "sg:phone":"+1 970 506 1257",
    "sg:postcode":"80620",
    "sg:province":"CO",
    "sg:tags":[
        "carpentry",
        "contractor"
    ],
    "wof:name":"Cross Our Hearts Enterprise",
    "wof:placetype":"venue"
},
  "geometry": {"coordinates":[-104.7454,40.381678],"type":"Point"}
}