{
  "type": "Feature",
  "properties": {
    "addr:full":"8100 E Union Ave Denver CO 80237",
    "addr:housenumber":"8100",
    "addr:postcode":"80237",
    "addr:street":"E Union Ave",
    "iso:country":"US",
    "sg:address":"8100 E Union Ave",
    "sg:city":"Denver",
    "sg:classifiers":[
        {
            "category":"Restaurant",
            "type":"Food & Drink"
        }
    ],
    "sg:menulink":"http://www.allmenus.com/co/denver/101162-mccormick--schmicks/menu/",
    "sg:phone":"+1 720 200 9339",
    "sg:postcode":"80237",
    "sg:province":"CO",
    "sg:tags":[
        "seafood",
        "american"
    ],
    "wof:name":"McCormick & Schmick's",
    "wof:placetype":"venue"
},
  "geometry": {"coordinates":[-104.894226,39.62959],"type":"Point"}
}