{
  "type": "Feature",
  "properties": {
    "iso:country":"US",
    "sg:address":"2525 W 64th Ave",
    "sg:city":"Denver",
    "sg:classifiers":[
        {
            "category":"Building & Trades",
            "subcategory":"Landscaping Services",
            "type":"Services"
        }
    ],
    "sg:phone":"+1 303 657 2600",
    "sg:postcode":"80221",
    "sg:province":"CO",
    "sg:tags":[
        "landscape",
        "contractor"
    ],
    "sg:website":"www.bluelinelandscape.com",
    "wof:name":"Blueline Inc Landscape Contrs",
    "wof:placetype":"venue"
},
  "geometry": {"coordinates":[-105.014799,39.812878],"type":"Point"}
}