{
  "type": "Feature",
  "properties": {
    "addr:full":"2525 W 64th Ave Denver CO 80221",
    "addr:housenumber":"2525",
    "addr:postcode":"80221",
    "addr:street":"W 64Th Ave",
    "iso:country":"US",
    "sg:address":"2525 W 64th Ave",
    "sg:city":"Denver",
    "sg:classifiers":[
        {
            "category":"Building & Trades",
            "subcategory":"Landscaping Services",
            "type":"Services"
        }
    ],
    "sg:phone":"+1 303 657 2600",
    "sg:postcode":"80221",
    "sg:province":"CO",
    "sg:tags":[
        "landscape",
        "contractor"
    ],
    "sg:website":"www.bluelinelandscape.com",
    "wof:name":"Blueline Inc Landscape Contrs",
    "wof:placetype":"venue"
},
  "geometry": {"coordinates":[-105.014799,39.812878],"type":"Point"}
}