{
  "type": "Feature",
  "properties": {
    "addr:full":"1450 W Evans Ave Denver CO 80223",
    "addr:housenumber":"1450",
    "addr:postcode":"80223",
    "addr:street":"W Evans Ave",
    "iso:country":"US",
    "sg:address":"1450 W Evans Ave",
    "sg:city":"Denver",
    "sg:classifiers":[
        {
            "category":"Wholesale",
            "subcategory":"Groceries",
            "type":"Manufacturing & Wholesale Goods"
        }
    ],
    "sg:phone":"+1 303 922 9828",
    "sg:postcode":"80223",
    "sg:province":"CO",
    "sg:tags":[
        "general"
    ],
    "wof:name":"Vranicar Brokerage Co",
    "wof:placetype":"venue"
},
  "geometry": {"coordinates":[-105.00346,39.678465],"type":"Point"}
}