{
  "type": "Feature",
  "properties": {
    "addr:full":"23 Smuggler Grove Aspen CO 81611",
    "addr:housenumber":"23",
    "addr:postcode":"81611",
    "addr:street":"Smuggler Grove",
    "iso:country":"US",
    "sg:address":"23 Smuggler Grove",
    "sg:city":"Aspen",
    "sg:classifiers":[
        {
            "category":"Real Estate",
            "subcategory":"Real Estate Agent",
            "type":"Services"
        }
    ],
    "sg:phone":"+1 970 925 4583",
    "sg:postcode":"81611",
    "sg:province":"CO",
    "sg:tags":[
        "management"
    ],
    "wof:name":"Ute City Properties Inc",
    "wof:placetype":"venue"
},
  "geometry": {"coordinates":[-106.80859,39.188044],"type":"Point"}
}