{
  "type": "Feature",
  "properties": {
    "iso:country":"US",
    "sg:address":"22022 Chippewa Ln",
    "sg:city":"Golden",
    "sg:classifiers":[
        {
            "category":"Professional",
            "subcategory":"Management & Consulting",
            "type":"Services"
        }
    ],
    "sg:phone":"+1 303 526 5259",
    "sg:postcode":"80401",
    "sg:province":"CO",
    "sg:tags":[
        "consultant",
        "energy",
        "conservation"
    ],
    "sg:website":"www.enerquest.com",
    "wof:name":"Enerquest Systems",
    "wof:placetype":"venue"
},
  "geometry": {"coordinates":[-105.248301,39.701071],"type":"Point"}
}