{
  "type": "Feature",
  "properties": {
    "addr:full":"407 W 7th St Wray CO 80758",
    "addr:housenumber":"407",
    "addr:postcode":"80758",
    "addr:street":"W 7Th St",
    "iso:country":"US",
    "sg:address":"407 W 7th St",
    "sg:city":"Wray",
    "sg:classifiers":[
        {
            "category":"Government",
            "subcategory":"Post Office",
            "type":"Public Place"
        }
    ],
    "sg:phone":"+1 970 332 5819",
    "sg:postcode":"80758",
    "sg:province":"CO",
    "wof:name":"US Post Office",
    "wof:placetype":"venue"
},
  "geometry": {"coordinates":[-102.226209,40.075452],"type":"Point"}
}