{
  "type": "Feature",
  "properties": {
    "iso:country":"US",
    "sg:address":"385 Inverness Way S",
    "sg:city":"Englewood",
    "sg:classifiers":[
        {
            "category":"Insurance",
            "subcategory":"Insurance Agent",
            "type":"Services"
        }
    ],
    "sg:phone":"+1 303 792 0476",
    "sg:postcode":"80112",
    "sg:province":"CO",
    "wof:name":"Allstate Insurance",
    "wof:placetype":"venue"
},
  "geometry": {"coordinates":[-104.868165,39.564199],"type":"Point"}
}