{
  "type": "Feature",
  "properties": {
    "iso:country":"US",
    "sg:address":"1100 W 38th Ave",
    "sg:city":"Denver",
    "sg:classifiers":[
        {
            "category":"Building & Trades",
            "subcategory":"Construction",
            "type":"Services"
        }
    ],
    "sg:phone":"+1 720 904 8744",
    "sg:postcode":"80211",
    "sg:province":"CO",
    "sg:tags":[
        "painter"
    ],
    "sg:website":"www.cornerstonepainting.com",
    "wof:name":"Cornerstone Painting Contr",
    "wof:placetype":"venue"
},
  "geometry": {"coordinates":[-105.00058799999999,39.769286],"type":"Point"}
}