{
  "type": "Feature",
  "properties": {
    "iso:country":"US",
    "sg:address":"3400 Industrial Ln",
    "sg:city":"Broomfield",
    "sg:classifiers":[
        {
            "category":"Wholesale",
            "subcategory":"Sporting Goods",
            "type":"Manufacturing & Wholesale Goods"
        },
        {
            "category":"Home & Garden",
            "subcategory":"Furniture",
            "type":"Retail Goods"
        }
    ],
    "sg:phone":"+1 720 274 0951",
    "sg:postcode":"80020",
    "sg:province":"CO",
    "wof:name":"Rocky Mountain Pool Table Co",
    "wof:placetype":"venue"
},
  "geometry": {"coordinates":[-105.1135,39.927236],"type":"Point"}
}