{
  "type": "Feature",
  "properties": {
    "addr:full":"7344 Ln 6 N Mosca CO 81146",
    "addr:postcode":"7344;81146",
    "addr:street":"Ln 6 N Mosca",
    "iso:country":"US",
    "sg:address":"7344 Ln 6 N",
    "sg:city":"Mosca",
    "sg:classifiers":[
        {
            "category":"Farming",
            "subcategory":"Farm",
            "type":"Manufacturing & Wholesale Goods"
        }
    ],
    "sg:phone":"+1 719 378 2576",
    "sg:postcode":"81146",
    "sg:province":"CO",
    "sg:tags":[
        "crop",
        "general"
    ],
    "wof:name":"Jason Kirkpatrick Farms",
    "wof:placetype":"venue"
},
  "geometry": {"coordinates":[-105.915592,37.661936],"type":"Point"}
}