{
  "type": "Feature",
  "properties": {
    "addr:full":"401 Meadows Rd Durango CO 81301",
    "addr:housenumber":"401",
    "addr:postcode":"co 81301",
    "addr:street":"Meadows Rd",
    "iso:country":"US",
    "sg:address":"401 Meadows Rd",
    "sg:city":"Durango",
    "sg:classifiers":[
        {
            "category":"Home & Garden",
            "subcategory":"Household Appliances",
            "type":"Retail Goods"
        }
    ],
    "sg:phone":"+1 970 259 3998",
    "sg:postcode":"81301",
    "sg:province":"CO",
    "sg:tags":[
        "cleaners",
        "vacuum"
    ],
    "wof:name":"Absolute Hepa Vacuum Cleaners",
    "wof:placetype":"venue"
},
  "geometry": {"coordinates":[-107.730574,37.26863],"type":"Point"}
}