{
  "type": "Feature",
  "properties": {
    "iso:country":"US",
    "sg:address":"2727 E Geddes Ave",
    "sg:city":"Littleton",
    "sg:classifiers":[
        {
            "category":"Shopping",
            "subcategory":"Jewelry",
            "type":"Retail Goods"
        }
    ],
    "sg:phone":"+1 303 796 8020",
    "sg:postcode":"80122",
    "sg:province":"CO",
    "sg:tags":[
        "stone"
    ],
    "wof:name":"Tria Prima LLC",
    "wof:placetype":"venue"
},
  "geometry": {"coordinates":[-104.957927,39.585707],"type":"Point"}
}