{
  "type": "Feature",
  "properties": {
    "addr:full":"173 Buchanan Rd Aspen CO 81611",
    "addr:housenumber":"173",
    "addr:postcode":"81611",
    "addr:street":"Buchanan Rd",
    "iso:country":"US",
    "sg:address":"173 Buchanan Rd",
    "sg:city":"Aspen",
    "sg:classifiers":[
        {
            "category":"Building & Trades",
            "subcategory":"Construction",
            "type":"Services"
        }
    ],
    "sg:phone":"+1 970 925 2963",
    "sg:postcode":"81611",
    "sg:province":"CO",
    "sg:tags":[
        "general",
        "contractor"
    ],
    "wof:name":"D H Construction",
    "wof:placetype":"venue"
},
  "geometry": {"coordinates":[-106.85066,39.236077],"type":"Point"}
}