{
  "type": "Feature",
  "properties": {
    "addr:full":"501 Idaho Ave Ordway CO 81063",
    "addr:housenumber":"501",
    "addr:postcode":"81063",
    "addr:street":"Idaho Ave",
    "iso:country":"US",
    "sg:address":"501 Idaho Ave",
    "sg:city":"Ordway",
    "sg:classifiers":[
        {
            "category":"Real Estate",
            "subcategory":"Real Estate Operator",
            "type":"Services"
        }
    ],
    "sg:phone":"+1 719 267 4691",
    "sg:postcode":"81063",
    "sg:province":"CO",
    "sg:tags":[
        "apartment"
    ],
    "wof:name":"Country Manor Inc",
    "wof:placetype":"venue"
},
  "geometry": {"coordinates":[-103.754034,38.221635],"type":"Point"}
}