{
  "type": "Feature",
  "properties": {
    "addr:full":"625 Main St Walden CO 80480",
    "addr:housenumber":"625",
    "addr:postcode":"80480",
    "addr:street":"Main St",
    "iso:country":"US",
    "sg:address":"625 Main St",
    "sg:city":"Walden",
    "sg:classifiers":[
        {
            "category":"Travel",
            "subcategory":"Hotels & Motels",
            "type":"Entertainment"
        }
    ],
    "sg:phone":"+1 970 723 4271",
    "sg:postcode":"80480",
    "sg:province":"CO",
    "wof:name":"North Park Motel",
    "wof:placetype":"venue"
},
  "geometry": {"coordinates":[-106.28203499999999,40.727406],"type":"Point"}
}