{
  "type": "Feature",
  "properties": {
    "iso:country":"US",
    "sg:address":"5800 E Jewell Ave",
    "sg:city":"Denver",
    "sg:classifiers":[
        {
            "category":"Building & Trades",
            "subcategory":"Construction",
            "type":"Services"
        }
    ],
    "sg:phone":"+1 303 759 2762",
    "sg:postcode":"80224",
    "sg:province":"CO",
    "sg:tags":[
        "tile",
        "dealer"
    ],
    "sg:website":"www.capcotile.com",
    "wof:name":"Import Tile Outlet",
    "wof:placetype":"venue"
},
  "geometry": {"coordinates":[-104.91746500000001,39.682008],"type":"Point"}
}