{
  "type": "Feature",
  "properties": {
    "iso:country":"US",
    "sg:address":"5270 Fox Street",
    "sg:city":"Denver",
    "sg:classifiers":[
        {
            "category":"Winery",
            "type":"Food & Drink"
        },
        {
            "category":"Food & Beverages",
            "subcategory":"Liquor & Beverages",
            "type":"Retail Goods"
        },
        {
            "category":"Wholesale",
            "subcategory":"Wine & Distilled Alcoholic Beverages",
            "type":"Manufacturing & Wholesale Goods"
        }
    ],
    "sg:phone":"+1 303 292 1711",
    "sg:postcode":"80216",
    "sg:province":"CO",
    "sg:tags":[
        "liquors-wholesale",
        "beer",
        "broker",
        "store",
        "spirit"
    ],
    "sg:website":"http://www.southernwine.com",
    "wof:name":"Southern Wine & Spirits",
    "wof:placetype":"venue"
},
  "geometry": {"coordinates":[-104.994975,39.791203],"type":"Point"}
}