{
  "type": "Feature",
  "properties": {
    "iso:country":"US",
    "sg:address":"4637 S Mason St",
    "sg:city":"Fort Collins",
    "sg:classifiers":[
        {
            "category":"Home & Garden",
            "subcategory":"Building Materials",
            "type":"Retail Goods"
        }
    ],
    "sg:phone":"+1 970 226 0891",
    "sg:postcode":"80525",
    "sg:province":"CO",
    "wof:name":"Kwal-Howells Pnt Wallcovering",
    "wof:placetype":"venue"
},
  "geometry": {"coordinates":[-105.07767699999999,40.521612],"type":"Point"}
}