{
  "type": "Feature",
  "properties": {
    "iso:country":"US",
    "sg:address":"3445 Penrose Pl",
    "sg:city":"Boulder",
    "sg:classifiers":[
        {
            "category":"Banks & Credit Unions",
            "subcategory":"Bank",
            "type":"Services"
        }
    ],
    "sg:phone":"+1 303 444 1545",
    "sg:postcode":"80301",
    "sg:province":"CO",
    "sg:tags":[
        "mortgage",
        "loan",
        "broker",
        "real estate"
    ],
    "sg:website":"www.crowder.com",
    "wof:name":"Crowder Mortgage Corp",
    "wof:placetype":"venue"
},
  "geometry": {"coordinates":[-105.24777899999999,40.037235],"type":"Point"}
}