{
  "type": "Feature",
  "properties": {
    "iso:country":"US",
    "sg:address":"515 Kimbark St",
    "sg:city":"Longmont",
    "sg:classifiers":[
        {
            "category":"Real Estate",
            "subcategory":"Architect",
            "type":"Services"
        },
        {
            "category":"Professional",
            "subcategory":"Engineering",
            "type":"Services"
        }
    ],
    "sg:phone":"+1 303 772 2533",
    "sg:postcode":"80501",
    "sg:province":"CO",
    "wof:name":"Moore & Bishton Architects PC",
    "wof:placetype":"venue"
},
  "geometry": {"coordinates":[-105.10126700000001,40.168793],"type":"Point"}
}