{
  "type": "Feature",
  "properties": {
    "addr:full":"3000 E 1st Avenue Denver CO 80206",
    "addr:housenumber":"3000",
    "addr:postcode":"80206",
    "addr:street":"E 1St Avenue",
    "iso:country":"US",
    "sg:address":"3000 E 1st Avenue",
    "sg:city":"Denver",
    "sg:classifiers":[
        {
            "category":"Shopping",
            "subcategory":"Department Store",
            "type":"Retail Goods"
        },
        {
            "category":"Shopping",
            "subcategory":"Clothing, Apparel, & Fashions",
            "type":"Retail Goods"
        },
        {
            "category":"Shopping Center",
            "type":"Public Place"
        }
    ],
    "sg:phone":"+1 303 316 7201",
    "sg:postcode":"80206",
    "sg:province":"CO",
    "sg:tags":[
        "children's",
        "clothing"
    ],
    "sg:website":"www.childrensplace.com",
    "wof:name":"Children's Place",
    "wof:placetype":"venue"
},
  "geometry": {"coordinates":[-104.952189,39.718037],"type":"Point"}
}