{
  "type": "Feature",
  "properties": {
    "iso:country":"US",
    "sg:address":"315 Sunset Rd",
    "sg:city":"Colorado Springs",
    "sg:classifiers":[
        {
            "category":"Building & Trades",
            "subcategory":"Construction",
            "type":"Services"
        }
    ],
    "sg:phone":"+1 719 448 0464",
    "sg:postcode":"80909",
    "sg:province":"CO",
    "sg:tags":[
        "paving",
        "asphalt"
    ],
    "wof:name":"All Purpose Paving Inc",
    "wof:placetype":"venue"
},
  "geometry": {"coordinates":[-104.788724,38.838222],"type":"Point"}
}