{
  "type": "Feature",
  "properties": {
    "addr:full":"34925 US Hwy 6 Edwards CO 81632",
    "addr:postcode":"34925;81632",
    "addr:street":"Us Hwy 6 Edwards",
    "iso:country":"US",
    "sg:address":"34925 US Hwy 6",
    "sg:city":"Edwards",
    "sg:classifiers":[
        {
            "category":"Professional",
            "type":"Services"
        }
    ],
    "sg:phone":"+1 970 926 7110",
    "sg:postcode":"81632",
    "sg:province":"CO",
    "sg:tags":[
        "establishment"
    ],
    "wof:name":"Western Paytel",
    "wof:placetype":"venue"
},
  "geometry": {"coordinates":[-106.58386900000001,39.638892],"type":"Point"}
}