{
  "type": "Feature",
  "properties": {
    "addr:full":"4891 Independence St Wheat Ridge CO 80033",
    "addr:housenumber":"4891",
    "addr:postcode":"80033",
    "addr:street":"Independence St",
    "iso:country":"US",
    "sg:address":"4891 Independence St",
    "sg:city":"Wheat Ridge",
    "sg:classifiers":[
        {
            "category":"Manufacturing",
            "subcategory":"Printing",
            "type":"Manufacturing & Wholesale Goods"
        }
    ],
    "sg:phone":"+1 303 467 1776",
    "sg:postcode":"80033",
    "sg:province":"CO",
    "sg:tags":[
        "publisher"
    ],
    "sg:website":"www.compositesworld.com",
    "wof:name":"Ray Publishing Inc",
    "wof:placetype":"venue"
},
  "geometry": {"coordinates":[-105.104916,39.78439],"type":"Point"}
}