{
  "type": "Feature",
  "properties": {
    "iso:country":"US",
    "sg:address":"1002 Kipling St",
    "sg:city":"Lakewood",
    "sg:classifiers":[
        {
            "category":"Utilities",
            "subcategory":"Water",
            "type":"Services"
        }
    ],
    "sg:phone":"+1 303 233 2182",
    "sg:postcode":"80215",
    "sg:province":"CO",
    "sg:tags":[
        "company",
        "sewage"
    ],
    "wof:name":"High View Water District",
    "wof:placetype":"venue"
},
  "geometry": {"coordinates":[-105.109544,39.73466],"type":"Point"}
}