{
  "type": "Feature",
  "properties": {
    "iso:country":"US",
    "sg:address":"370 Interlocken Blvd",
    "sg:city":"Broomfield",
    "sg:classifiers":[
        {
            "category":"Professional",
            "subcategory":"Management & Consulting",
            "type":"Services"
        }
    ],
    "sg:phone":"+1 303 466 6363",
    "sg:postcode":"80021",
    "sg:province":"CO",
    "sg:tags":[
        "marketing",
        "program"
    ],
    "sg:website":"www.experian.com",
    "wof:name":"Experian",
    "wof:placetype":"venue"
},
  "geometry": {"coordinates":[-105.110991,39.921844],"type":"Point"}
}