{
  "type": "Feature",
  "properties": {
    "iso:country":"US",
    "sg:address":"1211 Eagle St",
    "sg:city":"Aurora",
    "sg:classifiers":[
        {
            "category":"Real Estate",
            "subcategory":"Real Estate Services",
            "type":"Services"
        },
        {
            "category":"Building & Trades",
            "subcategory":"Cleaning & Sanitation",
            "type":"Services"
        }
    ],
    "sg:phone":"+1 303 365 2056",
    "sg:postcode":"80011",
    "sg:province":"CO",
    "sg:tags":[
        "maintenance",
        "cleaners-interior"
    ],
    "wof:name":"Vans House Cleaning",
    "wof:placetype":"venue"
},
  "geometry": {"coordinates":[-104.81706699999999,39.740693],"type":"Point"}
}