{
  "type": "Feature",
  "properties": {
    "addr:full":"315 Delaware Dr Colorado Springs CO 80909",
    "addr:housenumber":"315",
    "addr:postcode":"80909",
    "addr:street":"Delaware Dr",
    "iso:country":"US",
    "sg:address":"315 Delaware Dr",
    "sg:city":"Colorado Springs",
    "sg:classifiers":[
        {
            "category":"Retail",
            "subcategory":"Repair Shop",
            "type":"Services"
        }
    ],
    "sg:phone":"+1 719 597 0399",
    "sg:postcode":"80909",
    "sg:province":"CO",
    "wof:name":"Roto-Rooter",
    "wof:placetype":"venue"
},
  "geometry": {"coordinates":[-104.76015200000001,38.8382],"type":"Point"}
}