{
  "type": "Feature",
  "properties": {
    "iso:country":"US",
    "sg:address":"2126 9th St",
    "sg:city":"Greeley",
    "sg:classifiers":[
        {
            "category":"Shopping",
            "subcategory":"Clothing, Apparel, & Fashions",
            "type":"Retail Goods"
        }
    ],
    "sg:phone":"+1 970 353 2229",
    "sg:postcode":"80631",
    "sg:province":"CO",
    "sg:tags":[
        "infant",
        "wear"
    ],
    "wof:name":"Baby Stuff",
    "wof:placetype":"venue"
},
  "geometry": {"coordinates":[-104.711274,40.424045],"type":"Point"}
}