{
  "type": "Feature",
  "properties": {
    "addr:full":"1721 W Uintah St Colorado Springs CO 80904",
    "addr:housenumber":"1721",
    "addr:postcode":"80904",
    "addr:street":"W Uintah St",
    "iso:country":"US",
    "sg:address":"1721 W Uintah St",
    "sg:city":"Colorado Springs",
    "sg:classifiers":[
        {
            "category":"Retail",
            "subcategory":"Veterinary Services",
            "type":"Services"
        }
    ],
    "sg:phone":"+1 719 632 0222",
    "sg:postcode":"80904",
    "sg:province":"CO",
    "sg:tags":[
        "clinic",
        "animal"
    ],
    "wof:name":"Eggleston Leroy E Dvm",
    "wof:placetype":"venue"
},
  "geometry": {"coordinates":[-104.848151,38.847847],"type":"Point"}
}