{
  "type": "Feature",
  "properties": {
    "iso:country":"US",
    "sg:address":"5647 Raleigh Circle",
    "sg:city":"Castle Rock",
    "sg:classifiers":[
        {
            "category":"Personal",
            "type":"Services"
        }
    ],
    "sg:phone":"+1 303 944 2994",
    "sg:postcode":"80104",
    "sg:province":"CO",
    "sg:tags":[
        "home"
    ],
    "sg:website":"www.relevantyellow.com/Heating-a...",
    "wof:name":"Air Right Heating And Air Conditioning",
    "wof:placetype":"venue"
},
  "geometry": {"coordinates":[-104.798077,39.364195],"type":"Point"}
}