{
  "type": "Feature",
  "properties": {
    "addr:full":"610 S Chelton Rd Colorado Springs CO 80910",
    "addr:housenumber":"610",
    "addr:postcode":"80910",
    "addr:street":"S Chelton Rd",
    "iso:country":"US",
    "sg:address":"610 S Chelton Rd",
    "sg:city":"Colorado Springs",
    "sg:classifiers":[
        {
            "category":"Restaurant",
            "type":"Food & Drink"
        }
    ],
    "sg:menulink":"http://www.allmenus.com/co/colorado-springs/4396-mulligans-at-valley-hi-golf-course/menu/",
    "sg:phone":"+1 719 385 6918",
    "sg:postcode":"80910",
    "sg:province":"CO",
    "sg:tags":[
        "american"
    ],
    "wof:name":"Mulligan's at Valley Hi Golf Course",
    "wof:placetype":"venue"
},
  "geometry": {"coordinates":[-104.76799800000001,38.821668],"type":"Point"}
}