{
  "type": "Feature",
  "properties": {
    "addr:full":"212 39th Ln Pueblo CO 81006",
    "addr:housenumber":"212",
    "addr:postcode":"81006",
    "addr:street":"39Th Ln",
    "iso:country":"US",
    "sg:address":"212 39th Ln",
    "sg:city":"Pueblo",
    "sg:classifiers":[
        {
            "category":"Building & Trades",
            "subcategory":"Construction",
            "type":"Services"
        }
    ],
    "sg:phone":"+1 719 948 2403",
    "sg:postcode":"81006",
    "sg:province":"CO",
    "sg:tags":[
        "roofing",
        "contractor"
    ],
    "wof:name":"Valley Roofing & Siding Inc",
    "wof:placetype":"venue"
},
  "geometry": {"coordinates":[-104.433902,38.272078],"type":"Point"}
}