{
  "type": "Feature",
  "properties": {
    "addr:full":"1300 E 17th Ave Denver CO 80218",
    "addr:housenumber":"1300",
    "addr:postcode":"80218",
    "addr:street":"E 17Th Ave",
    "iso:country":"US",
    "sg:address":"1300 E 17th Ave",
    "sg:city":"Denver",
    "sg:classifiers":[
        {
            "category":"Manufacturing",
            "subcategory":"Signs",
            "type":"Manufacturing & Wholesale Goods"
        }
    ],
    "sg:phone":"+1 303 832 3771",
    "sg:postcode":"80218",
    "sg:province":"CO",
    "sg:tags":[
        "specialty",
        "mfg"
    ],
    "sg:website":"www.rjcollins.com",
    "wof:name":"Collins Sign & Graphics Inc",
    "wof:placetype":"venue"
},
  "geometry": {"coordinates":[-104.96968,39.743237],"type":"Point"}
}