{
  "type": "Feature",
  "properties": {
    "addr:full":"2604 S Lima St Aurora CO 80014",
    "addr:housenumber":"2604",
    "addr:postcode":"80014",
    "addr:street":"S Lima St",
    "iso:country":"US",
    "sg:address":"2604 S Lima St",
    "sg:city":"Aurora",
    "sg:classifiers":[
        {
            "category":"Manufacturing",
            "subcategory":"Printing",
            "type":"Manufacturing & Wholesale Goods"
        }
    ],
    "sg:phone":"+1 720 535 7266",
    "sg:postcode":"80014",
    "sg:province":"CO",
    "sg:tags":[
        "publishing"
    ],
    "wof:name":"Dajazz Records",
    "wof:placetype":"venue"
},
  "geometry": {"coordinates":[-104.860677,39.668334],"type":"Point"}
}