{
  "type": "Feature",
  "properties": {
    "addr:full":"1413 Potter Dr Colorado Springs CO 80909",
    "addr:housenumber":"1413",
    "addr:postcode":"80909",
    "addr:street":"Potter Dr",
    "iso:country":"US",
    "sg:address":"1413 Potter Dr",
    "sg:city":"Colorado Springs",
    "sg:classifiers":[
        {
            "category":"Professional",
            "subcategory":"Advertising",
            "type":"Services"
        }
    ],
    "sg:phone":"+1 719 591 8271",
    "sg:postcode":"80909",
    "sg:province":"CO",
    "wof:name":"Consolidated Electrical Distr",
    "wof:placetype":"venue"
},
  "geometry": {"coordinates":[-104.752641,38.852714],"type":"Point"}
}