{
  "type": "Feature",
  "properties": {
    "iso:country":"US",
    "sg:address":"7400 W Grant Ranch Blvd",
    "sg:city":"Littleton",
    "sg:classifiers":[
        {
            "category":"Building & Trades",
            "subcategory":"Construction",
            "type":"Services"
        }
    ],
    "sg:phone":"+1 303 904 8821",
    "sg:postcode":"80123",
    "sg:province":"CO",
    "sg:tags":[
        "residential",
        "nonresidential"
    ],
    "wof:name":"Cromwell Construction Co",
    "wof:placetype":"venue"
},
  "geometry": {"coordinates":[-105.081228,39.618499],"type":"Point"}
}