{
  "type": "Feature",
  "properties": {
    "iso:country":"US",
    "sg:address":"1955 W 153rd Pl",
    "sg:city":"Broomfield",
    "sg:classifiers":[
        {
            "category":"Professional",
            "subcategory":"Testing Lab",
            "type":"Services"
        }
    ],
    "sg:phone":"+1 303 452 5717",
    "sg:postcode":"80023",
    "sg:province":"CO",
    "sg:tags":[
        "laboratory"
    ],
    "wof:name":"Components Reliability & Sfty",
    "wof:placetype":"venue"
},
  "geometry": {"coordinates":[-105.010628,39.975052],"type":"Point"}
}