{
  "type": "Feature",
  "properties": {
    "iso:country":"US",
    "sg:address":"919 N 7th Pl",
    "sg:city":"Johnstown",
    "sg:classifiers":[
        {
            "category":"Banks & Credit Unions",
            "subcategory":"Financial Services",
            "type":"Services"
        }
    ],
    "sg:phone":"+1 970 587 2111",
    "sg:postcode":"80534",
    "sg:province":"CO",
    "sg:tags":[
        "trust",
        "nonprofit",
        "management"
    ],
    "wof:name":"Randall Scott Rehn Foundation",
    "wof:placetype":"venue"
},
  "geometry": {"coordinates":[-104.917925,40.342452],"type":"Point"}
}