{
  "type": "Feature",
  "properties": {
    "addr:full":"718 Cheyenne Meadows Rd Colorado Springs CO 80906",
    "addr:housenumber":"718",
    "addr:postcode":"80906",
    "addr:street":"Cheyenne Meadows Rd",
    "iso:country":"US",
    "sg:address":"718 Cheyenne Meadows Rd",
    "sg:city":"Colorado Springs",
    "sg:classifiers":[
        {
            "category":"Banks & Credit Unions",
            "subcategory":"Bank",
            "type":"Services"
        }
    ],
    "sg:phone":"+1 719 540 3750",
    "sg:postcode":"80906",
    "sg:province":"CO",
    "sg:tags":[
        "loan"
    ],
    "wof:name":"Ace Cash Advance",
    "wof:placetype":"venue"
},
  "geometry": {"coordinates":[-104.81362300000001,38.776842],"type":"Point"}
}