{
  "type": "Feature",
  "properties": {
    "iso:country":"US",
    "sg:address":"4372 S Everett St",
    "sg:city":"Littleton",
    "sg:classifiers":[
        {
            "category":"Wholesale",
            "subcategory":"Machinery & Supplies",
            "type":"Manufacturing & Wholesale Goods"
        }
    ],
    "sg:phone":"+1 303 973 0140",
    "sg:postcode":"80123",
    "sg:province":"CO",
    "sg:tags":[
        "equipment",
        "establishment"
    ],
    "wof:name":"Meyer Supply Inc",
    "wof:placetype":"venue"
},
  "geometry": {"coordinates":[-105.097076,39.637932],"type":"Point"}
}