{
  "type": "Feature",
  "properties": {
    "iso:country":"US",
    "sg:address":"1310 17th St",
    "sg:city":"Denver",
    "sg:classifiers":[
        {
            "category":"Manufacturing",
            "subcategory":"Printing",
            "type":"Manufacturing & Wholesale Goods"
        }
    ],
    "sg:phone":"+1 303 534 5525",
    "sg:postcode":"80202",
    "sg:province":"CO",
    "sg:tags":[
        "commercial",
        "type",
        "duplicating",
        "offset"
    ],
    "sg:website":"www.anacondaprinting.com",
    "wof:name":"Anaconda Printing",
    "wof:placetype":"venue"
},
  "geometry": {"coordinates":[-104.99660799999999,39.750347],"type":"Point"}
}