{
  "type": "Feature",
  "properties": {
    "addr:full":"3109 N Cascade Ave Colorado Springs CO 80907",
    "addr:housenumber":"3109",
    "addr:postcode":"80907",
    "addr:street":"N Cascade Ave",
    "iso:country":"US",
    "sg:address":"3109 N Cascade Ave",
    "sg:city":"Colorado Springs",
    "sg:classifiers":[
        {
            "category":"Manufacturing",
            "subcategory":"Tools & Machinery",
            "type":"Manufacturing & Wholesale Goods"
        }
    ],
    "sg:phone":"+1 719 634 2259",
    "sg:postcode":"80907",
    "sg:province":"CO",
    "sg:tags":[
        "control",
        "measuring",
        "electrical",
        "mfg"
    ],
    "wof:name":"Srt",
    "wof:placetype":"venue"
},
  "geometry": {"coordinates":[-104.822607,38.875384],"type":"Point"}
}