{
  "type": "Feature",
  "properties": {
    "addr:full":"537 4th St Mead CO 80550",
    "addr:housenumber":"537",
    "addr:postcode":"80550",
    "addr:street":"4Th St Mead",
    "iso:country":"US",
    "sg:address":"537 4th St",
    "sg:city":"Mead",
    "sg:classifiers":[
        {
            "category":"Government",
            "subcategory":"Office",
            "type":"Public Place"
        }
    ],
    "sg:phone":"+1 970 535 4770",
    "sg:postcode":"80550",
    "sg:province":"CO",
    "sg:tags":[
        "village"
    ],
    "wof:name":"Maintenance Dept",
    "wof:placetype":"venue"
},
  "geometry": {"coordinates":[-104.90254299999999,40.474769],"type":"Point"}
}