{
  "type": "Feature",
  "properties": {
    "iso:country":"US",
    "sg:address":"4825 S Yank Way",
    "sg:city":"Morrison",
    "sg:classifiers":[
        {
            "category":"Manufacturing",
            "subcategory":"Glass & Minerals",
            "type":"Manufacturing & Wholesale Goods"
        }
    ],
    "sg:phone":"+1 303 979 8922",
    "sg:postcode":"80465",
    "sg:province":"CO",
    "sg:tags":[
        "tile",
        "ceramic",
        "mfg"
    ],
    "wof:name":"Chris Hordinski Co",
    "wof:placetype":"venue"
},
  "geometry": {"coordinates":[-105.143361,39.629245],"type":"Point"}
}