{
  "type": "Feature",
  "properties": {
    "addr:full":"6222 S Spotswood St Apt 1 Littleton CO 80120",
    "addr:housenumber":"6222;1",
    "addr:postcode":"80120",
    "addr:street":"S Spotswood St Apt",
    "iso:country":"US",
    "sg:address":"6222 S Spotswood St Apt 1",
    "sg:city":"Littleton",
    "sg:classifiers":[
        {
            "category":"Building & Trades",
            "subcategory":"Construction",
            "type":"Services"
        }
    ],
    "sg:phone":"+1 303 794 3415",
    "sg:postcode":"80120",
    "sg:province":"CO",
    "sg:tags":[
        "handyman"
    ],
    "wof:name":"Clif's Service And Repair",
    "wof:placetype":"venue"
},
  "geometry": {"coordinates":[-105.01158599999999,39.603836],"type":"Point"}
}