{
  "type": "Feature",
  "properties": {
    "iso:country":"US",
    "sg:address":"6766 W 97th Cir",
    "sg:city":"Broomfield",
    "sg:classifiers":[
        {
            "category":"Building & Trades",
            "subcategory":"Construction",
            "type":"Services"
        }
    ],
    "sg:phone":"+1 720 289 7634",
    "sg:postcode":"80021",
    "sg:province":"CO",
    "sg:tags":[
        "house"
    ],
    "wof:name":"Charles Henry Construction",
    "wof:placetype":"venue"
},
  "geometry": {"coordinates":[-105.073607,39.872976],"type":"Point"}
}