{
  "type": "Feature",
  "properties": {
    "addr:full":"4955 W 72nd Ave Westminster CO 80030",
    "addr:housenumber":"4955",
    "addr:postcode":"80030",
    "addr:street":"W 72Nd Ave",
    "iso:country":"US",
    "sg:address":"4955 W 72nd Ave",
    "sg:city":"Westminster",
    "sg:classifiers":[
        {
            "category":"Professional",
            "type":"Services"
        },
        {
            "category":"Shopping",
            "subcategory":"Musical Instruments",
            "type":"Retail Goods"
        }
    ],
    "sg:phone":"+1 303 430 0096",
    "sg:postcode":"80030",
    "sg:province":"CO",
    "sg:tags":[
        "music",
        "dealer"
    ],
    "wof:name":"Mundo Musical",
    "wof:placetype":"venue"
},
  "geometry": {"coordinates":[-105.048872,39.827362],"type":"Point"}
}