{
  "type": "Feature",
  "properties": {
    "addr:full":"450 Pratt St Longmont CO 80501",
    "addr:housenumber":"450",
    "addr:postcode":"80501",
    "addr:street":"Pratt St",
    "iso:country":"US",
    "sg:address":"450 Pratt St",
    "sg:city":"Longmont",
    "sg:classifiers":[
        {
            "category":"Organizations",
            "subcategory":"Religious Organization",
            "type":"Services"
        }
    ],
    "sg:phone":"+1 303 772 8124",
    "sg:postcode":"80501",
    "sg:province":"CO",
    "sg:tags":[
        "church"
    ],
    "sg:website":"www.boulderhome.com",
    "wof:name":"Church Of Christ Scientist",
    "wof:placetype":"venue"
},
  "geometry": {"coordinates":[-105.10677699999999,40.166535],"type":"Point"}
}