{
  "type": "Feature",
  "properties": {
    "iso:country":"US",
    "sg:address":"566 Nucla Way",
    "sg:city":"Aurora",
    "sg:classifiers":[
        {
            "category":"Freight",
            "type":"Transportation"
        },
        {
            "category":"Professional",
            "type":"Services"
        }
    ],
    "sg:phone":"+1 303 344 8641",
    "sg:postcode":"80011",
    "sg:province":"CO",
    "wof:name":"Elite Services",
    "wof:placetype":"venue"
},
  "geometry": {"coordinates":[-104.794099,39.724036],"type":"Point"}
}