{
  "type": "Feature",
  "properties": {
    "iso:country":"US",
    "sg:address":"2055 Ken Pratt Blvd",
    "sg:city":"Longmont",
    "sg:classifiers":[
        {
            "category":"Restaurant",
            "type":"Food & Drink"
        }
    ],
    "sg:menulink":"http://www.allmenus.com/co/longmont/280198-egg--i-restaurant/menu/",
    "sg:phone":"+1 303 485 9477",
    "sg:postcode":"80501",
    "sg:province":"CO",
    "sg:tags":[
        "american"
    ],
    "wof:name":"Egg & I Restaurant",
    "wof:placetype":"venue"
},
  "geometry": {"coordinates":[-105.12775499999999,40.143107],"type":"Point"}
}