{
  "type": "Feature",
  "properties": {
    "iso:country":"US",
    "sg:address":"6863 E 48th Ave",
    "sg:city":"Commerce City",
    "sg:classifiers":[
        {
            "category":"Retail",
            "subcategory":"Auto Repair",
            "type":"Services"
        }
    ],
    "sg:phone":"+1 303 762 8388",
    "sg:postcode":"80216",
    "sg:province":"CO",
    "sg:tags":[
        "body"
    ],
    "wof:name":"Corvette City",
    "wof:placetype":"venue"
},
  "geometry": {"coordinates":[-104.90824000000001,39.784119],"type":"Point"}
}