{
  "type": "Feature",
  "properties": {
    "addr:full":"1455 Coal Creek Dr Lafayette CO 80026",
    "addr:housenumber":"1455",
    "addr:postcode":"80026",
    "addr:street":"Coal Creek Dr",
    "iso:country":"US",
    "sg:address":"1455 Coal Creek Dr",
    "sg:city":"Lafayette",
    "sg:classifiers":[
        {
            "category":"Restaurant",
            "type":"Food & Drink"
        }
    ],
    "sg:phone":"+1 303 666 0912",
    "sg:postcode":"80026",
    "sg:province":"CO",
    "sg:tags":[
        "eating"
    ],
    "wof:name":"Pizza Hut",
    "wof:placetype":"venue"
},
  "geometry": {"coordinates":[-105.09646600000001,39.985504],"type":"Point"}
}