{
  "type": "Feature",
  "properties": {
    "addr:full":"14798 State Hwy 14 Sterling CO 80751",
    "addr:housenumber":"14798",
    "addr:postcode":"80751",
    "addr:street":"State Hwy 14",
    "iso:country":"US",
    "sg:address":"14798 State Hwy 14",
    "sg:city":"Sterling",
    "sg:classifiers":[
        {
            "category":"Retail",
            "subcategory":"Repair Shop",
            "type":"Services"
        }
    ],
    "sg:phone":"+1 970 526 2837",
    "sg:postcode":"80751",
    "sg:province":"CO",
    "sg:tags":[
        "welding"
    ],
    "wof:name":"Klinzmann Welding",
    "wof:placetype":"venue"
},
  "geometry": {"coordinates":[-103.29964,40.62384],"type":"Point"}
}