{
  "type": "Feature",
  "properties": {
    "addr:full":"8000 E Girard Ave Denver CO 80231",
    "addr:housenumber":"8000",
    "addr:postcode":"80231",
    "addr:street":"E Girard Ave",
    "iso:country":"US",
    "sg:address":"8000 E Girard Ave",
    "sg:city":"Denver",
    "sg:classifiers":[
        {
            "category":"Real Estate",
            "subcategory":"Real Estate Operator",
            "type":"Services"
        }
    ],
    "sg:phone":"+1 866 337 4902",
    "sg:postcode":"80231",
    "sg:province":"CO",
    "sg:tags":[
        "building",
        "apartment",
        "rental",
        "finder"
    ],
    "sg:website":"http://denver.citysearch.com/profile/external/1856614/denver_co/remington_place.html?publisher=yellowpages&reference_id=1&placement=ypwebsitemip",
    "wof:name":"Remington Place",
    "wof:placetype":"venue"
},
  "geometry": {"coordinates":[-104.89552999999999,39.654508],"type":"Point"}
}