{
  "type": "Feature",
  "properties": {
    "iso:country":"US",
    "sg:address":"6610 W 14th Ave",
    "sg:city":"Lakewood",
    "sg:classifiers":[
        {
            "category":"Organizations",
            "subcategory":"Community Association",
            "type":"Services"
        }
    ],
    "sg:phone":"+1 303 232 1700",
    "sg:postcode":"80214",
    "sg:province":"CO",
    "sg:tags":[
        "fraternal"
    ],
    "wof:name":"Sons Of Norway",
    "wof:placetype":"venue"
},
  "geometry": {"coordinates":[-105.070685,39.738418],"type":"Point"}
}