{
  "type": "Feature",
  "properties": {
    "addr:full":"4363 Tennyson St Denver CO 80212",
    "addr:housenumber":"4363",
    "addr:postcode":"80212",
    "addr:street":"Tennyson St",
    "iso:country":"US",
    "sg:address":"4363 Tennyson St",
    "sg:city":"Denver",
    "sg:classifiers":[
        {
            "category":"Social Services",
            "type":"Services"
        }
    ],
    "sg:phone":"+1 303 749 8678",
    "sg:postcode":"80212",
    "sg:province":"CO",
    "sg:tags":[
        "counselor",
        "marriage",
        "family"
    ],
    "wof:name":"Center For Comprehensive Human",
    "wof:placetype":"venue"
},
  "geometry": {"coordinates":[-105.04405300000001,39.776144],"type":"Point"}
}