{
  "type": "Feature",
  "properties": {
    "iso:country":"US",
    "sg:address":"6083 S Akron Way",
    "sg:city":"Greenwood Vlg",
    "sg:classifiers":[
        {
            "category":"Organizations",
            "subcategory":"Non-profit Organization",
            "type":"Services"
        }
    ],
    "sg:phone":"+1 303 779 6722",
    "sg:postcode":"80111",
    "sg:province":"CO",
    "sg:tags":[
        "breastfeeding",
        "information",
        "supply"
    ],
    "wof:name":"LA Leche Of Colorado",
    "wof:placetype":"venue"
},
  "geometry": {"coordinates":[-104.884569,39.606119],"type":"Point"}
}