{
  "type": "Feature",
  "properties": {
    "iso:country":"US",
    "sg:address":"264 Brian Ave",
    "sg:city":"Silverthorne",
    "sg:classifiers":[
        {
            "category":"Building & Trades",
            "subcategory":"Construction",
            "type":"Services"
        }
    ],
    "sg:phone":"+1 970 262 7340",
    "sg:postcode":"80498",
    "sg:province":"CO",
    "sg:tags":[
        "marking",
        "maintenance",
        "parking"
    ],
    "wof:name":"Silverthorne Public Works",
    "wof:placetype":"venue"
},
  "geometry": {"coordinates":[-106.075152,39.629027],"type":"Point"}
}