{
  "type": "Feature",
  "properties": {
    "addr:full":"15380 E Hampden Ave Aurora CO 80013",
    "addr:housenumber":"15380",
    "addr:postcode":"80013",
    "addr:street":"E Hampden Ave",
    "iso:country":"US",
    "sg:address":"15380 E Hampden Ave",
    "sg:city":"Aurora",
    "sg:classifiers":[
        {
            "category":"Food & Beverages",
            "subcategory":"Groceries & Convenience Stores",
            "type":"Retail Goods"
        }
    ],
    "sg:phone":"+1 303 693 1100",
    "sg:postcode":"80013",
    "sg:province":"CO",
    "wof:name":"Albertsons Grocery",
    "wof:placetype":"venue"
},
  "geometry": {"coordinates":[-104.80922200000001,39.653011],"type":"Point"}
}