{
  "type": "Feature",
  "properties": {
    "addr:full":"14600 Woodland Trl Nathrop CO 81236",
    "addr:housenumber":"14600",
    "addr:postcode":"81236",
    "addr:street":"Woodland Trl",
    "iso:country":"US",
    "sg:address":"14600 Woodland Trl",
    "sg:city":"Nathrop",
    "sg:classifiers":[
        {
            "category":"Building & Trades",
            "subcategory":"Construction",
            "type":"Services"
        }
    ],
    "sg:phone":"+1 719 539 3733",
    "sg:postcode":"81236",
    "sg:province":"CO",
    "sg:tags":[
        "painter"
    ],
    "wof:name":"Ninja Painting Co",
    "wof:placetype":"venue"
},
  "geometry": {"coordinates":[-106.13853,38.679297],"type":"Point"}
}