{
  "type": "Feature",
  "properties": {
    "iso:country":"US",
    "sg:address":"14 Inverness Dr E",
    "sg:city":"Englewood",
    "sg:classifiers":[
        {
            "category":"Professional",
            "subcategory":"Advertising",
            "type":"Services"
        }
    ],
    "sg:phone":"+1 303 799 6090",
    "sg:postcode":"80112",
    "sg:province":"CO",
    "sg:tags":[
        "mail"
    ],
    "sg:website":"www.newmethodmarketing.com",
    "wof:name":"New Method Marketing Inc",
    "wof:placetype":"venue"
},
  "geometry": {"coordinates":[-104.86219699999999,39.566915],"type":"Point"}
}