{
  "type": "Feature",
  "properties": {
    "addr:full":"4130 E 130th Pl Denver CO 80241",
    "addr:housenumber":"4130",
    "addr:postcode":"80241",
    "addr:street":"E 130Th Pl",
    "iso:country":"US",
    "sg:address":"4130 E 130th Pl",
    "sg:city":"Denver",
    "sg:classifiers":[
        {
            "category":"Real Estate",
            "subcategory":"Real Estate Agent",
            "type":"Services"
        }
    ],
    "sg:phone":"+1 303 451 7807",
    "sg:postcode":"80241",
    "sg:province":"CO",
    "wof:name":"Oasis Basis Intl Inc",
    "wof:placetype":"venue"
},
  "geometry": {"coordinates":[-104.937939,39.932476],"type":"Point"}
}