{
  "type": "Feature",
  "properties": {
    "addr:full":"222 N 3rd St Cheraw CO 81030",
    "addr:housenumber":"222",
    "addr:postcode":"81030",
    "addr:street":"N 3Rd St",
    "iso:country":"US",
    "sg:address":"222 N 3rd St",
    "sg:city":"Cheraw",
    "sg:classifiers":[
        {
            "category":"Freight",
            "type":"Transportation"
        }
    ],
    "sg:phone":"+1 719 853 6290",
    "sg:postcode":"81030",
    "sg:province":"CO",
    "sg:tags":[
        "dry",
        "bulk",
        "trucking"
    ],
    "wof:name":"Elam Trucking",
    "wof:placetype":"venue"
},
  "geometry": {"coordinates":[-103.51179500000001,38.108844],"type":"Point"}
}