{
  "type": "Feature",
  "properties": {
    "addr:full":"1811 S 6th St Lamar CO 81052",
    "addr:housenumber":"1811",
    "addr:postcode":"81052",
    "addr:street":"S 6Th St",
    "iso:country":"US",
    "sg:address":"1811 S 6th St",
    "sg:city":"Lamar",
    "sg:classifiers":[
        {
            "category":"Education",
            "subcategory":"School",
            "type":"Public Place"
        }
    ],
    "sg:phone":"+1 719 336 4523",
    "sg:postcode":"81052",
    "sg:province":"CO",
    "wof:name":"Lamar Sda School",
    "wof:placetype":"venue"
},
  "geometry": {"coordinates":[-102.621336,38.071131],"type":"Point"}
}