{
  "type": "Feature",
  "properties": {
    "iso:country":"US",
    "sg:address":"7510 Burgess Rd",
    "sg:city":"Colorado Springs",
    "sg:classifiers":[
        {
            "category":"Freight",
            "type":"Transportation"
        }
    ],
    "sg:phone":"+1 719 495 9752",
    "sg:postcode":"80908",
    "sg:province":"CO",
    "sg:tags":[
        "operator",
        "local",
        "trucking"
    ],
    "wof:name":"Lanckriet Trucking",
    "wof:placetype":"venue"
},
  "geometry": {"coordinates":[-104.687416,38.998368],"type":"Point"}
}