{
  "type": "Feature",
  "properties": {
    "addr:full":"1101 Colorado Blvd Denver CO 80206",
    "addr:housenumber":"1101",
    "addr:postcode":"80206",
    "addr:street":"Colorado Blvd",
    "iso:country":"US",
    "sg:address":"1101 Colorado Blvd",
    "sg:city":"Denver",
    "sg:classifiers":[
        {
            "category":"Professional",
            "type":"Services"
        }
    ],
    "sg:phone":"+1 303 333 8356",
    "sg:postcode":"80206",
    "sg:province":"CO",
    "wof:name":"CB 1101 LLC",
    "wof:placetype":"venue"
},
  "geometry": {"coordinates":[-104.940668,39.734688],"type":"Point"}
}