{
  "type": "Feature",
  "properties": {
    "addr:full":"15814 Co Rd 169 Matheson CO 80830",
    "addr:housenumber":"15814",
    "addr:postcode":"80830",
    "addr:street":"Co Rd 169 Matheson",
    "iso:country":"US",
    "sg:address":"15814 Co Rd 169",
    "sg:city":"Matheson",
    "sg:classifiers":[
        {
            "category":"Farming",
            "subcategory":"Livestock Farm",
            "type":"Manufacturing & Wholesale Goods"
        }
    ],
    "sg:phone":"+1 719 541 2797",
    "sg:postcode":"80830",
    "sg:province":"CO",
    "sg:tags":[
        "wheat",
        "cattle"
    ],
    "wof:name":"Scherrer Brothers",
    "wof:placetype":"venue"
},
  "geometry": {"coordinates":[-103.885166,39.090096],"type":"Point"}
}