{
  "type": "Feature",
  "properties": {
    "iso:country":"US",
    "sg:address":"1818 E Dale St",
    "sg:city":"Colorado Springs",
    "sg:classifiers":[
        {
            "category":"Organizations",
            "subcategory":"Religious Organization",
            "type":"Services"
        }
    ],
    "sg:phone":"+1 719 634 5787",
    "sg:postcode":"80909",
    "sg:province":"CO",
    "sg:tags":[
        "church"
    ],
    "wof:name":"Heritage Wesleyan Church",
    "wof:placetype":"venue"
},
  "geometry": {"coordinates":[-104.793735,38.843694],"type":"Point"}
}