{
  "type": "Feature",
  "properties": {
    "iso:country":"US",
    "sg:address":"4545 Laguna Pl",
    "sg:city":"Boulder",
    "sg:classifiers":[
        {
            "category":"Professional",
            "type":"Services"
        }
    ],
    "sg:phone":"+1 303 736 6847",
    "sg:postcode":"80303",
    "sg:province":"CO",
    "wof:name":"Spicer Mineral Corporation",
    "wof:placetype":"venue"
},
  "geometry": {"coordinates":[-105.238911,40.00004],"type":"Point"}
}