{
  "type": "Feature",
  "properties": {
    "iso:country":"US",
    "sg:address":"9633 N Surrey Rd",
    "sg:city":"Castle Rock",
    "sg:classifiers":[
        {
            "category":"Building & Trades",
            "subcategory":"Construction",
            "type":"Services"
        }
    ],
    "sg:phone":"+1 303 660 4858",
    "sg:postcode":"80108",
    "sg:province":"CO",
    "sg:tags":[
        "house"
    ],
    "wof:name":"Stephen Hinkley Builder",
    "wof:placetype":"venue"
},
  "geometry": {"coordinates":[-104.866955,39.517262],"type":"Point"}
}