{
  "type": "Feature",
  "properties": {
    "addr:full":"536 S Campbell Ave Holyoke CO 80734",
    "addr:housenumber":"536",
    "addr:postcode":"80734",
    "addr:street":"S Campbell Ave",
    "iso:country":"US",
    "sg:address":"536 S Campbell Ave",
    "sg:city":"Holyoke",
    "sg:classifiers":[
        {
            "category":"Professional",
            "type":"Services"
        }
    ],
    "sg:phone":"+1 970 854 2445",
    "sg:postcode":"80734",
    "sg:province":"CO",
    "wof:name":"Loren A Pfau",
    "wof:placetype":"venue"
},
  "geometry": {"coordinates":[-102.300878,40.581223],"type":"Point"}
}