{
  "type": "Feature",
  "properties": {
    "addr:full":"14853 E Hinsdale Ave Centennial CO 80112",
    "addr:housenumber":"14853",
    "addr:postcode":"80112",
    "addr:street":"E Hinsdale Ave",
    "iso:country":"US",
    "sg:address":"14853 E Hinsdale Ave",
    "sg:city":"Centennial",
    "sg:classifiers":[
        {
            "category":"Home & Garden",
            "subcategory":"Building Materials",
            "type":"Retail Goods"
        }
    ],
    "sg:phone":"+1 303 400 3466",
    "sg:postcode":"80112",
    "sg:province":"CO",
    "sg:tags":[
        "door"
    ],
    "sg:website":"www.baywatchdoors.com",
    "wof:name":"Baywatch Services",
    "wof:placetype":"venue"
},
  "geometry": {"coordinates":[-104.81679099999999,39.581486],"type":"Point"}
}