{
  "type": "Feature",
  "properties": {
    "iso:country":"US",
    "sg:address":"571 Zerex St",
    "sg:city":"Fraser",
    "sg:classifiers":[
        {
            "category":"Retail",
            "subcategory":"Repair Shop",
            "type":"Services"
        }
    ],
    "sg:phone":"+1 970 726 1350",
    "sg:postcode":"80442",
    "sg:province":"CO",
    "sg:tags":[
        "equipment",
        "skiing"
    ],
    "wof:name":"High Peaks Alpine Svc",
    "wof:placetype":"venue"
},
  "geometry": {"coordinates":[-105.81752899999999,39.949641],"type":"Point"}
}