{
  "type": "Feature",
  "properties": {
    "iso:country":"US",
    "sg:address":"9786 S Ashleigh Pl",
    "sg:city":"Littleton",
    "sg:classifiers":[
        {
            "category":"Shopping",
            "type":"Retail Goods"
        }
    ],
    "sg:phone":"+1 303 470 0940",
    "sg:postcode":"80126",
    "sg:province":"CO",
    "sg:tags":[
        "merchandise"
    ],
    "wof:name":"Multi Pure Drinking Water Sys",
    "wof:placetype":"venue"
},
  "geometry": {"coordinates":[-104.96659099999999,39.538109],"type":"Point"}
}