{
  "type": "Feature",
  "properties": {
    "iso:country":"US",
    "sg:address":"398 Lucerne Dr",
    "sg:city":"Lafayette",
    "sg:classifiers":[
        {
            "category":"Building & Trades",
            "subcategory":"Construction",
            "type":"Services"
        }
    ],
    "sg:phone":"+1 303 604 6333",
    "sg:postcode":"80026",
    "sg:province":"CO",
    "sg:tags":[
        "house"
    ],
    "wof:name":"Markel Homes Inc",
    "wof:placetype":"venue"
},
  "geometry": {"coordinates":[-105.088747,40.007144],"type":"Point"}
}