{
  "type": "Feature",
  "properties": {
    "addr:full":"7314 Valmont Rd Boulder CO 80301",
    "addr:housenumber":"7314",
    "addr:postcode":"80301",
    "addr:street":"Valmont Rd",
    "iso:country":"US",
    "sg:address":"7314 Valmont Rd",
    "sg:city":"Boulder",
    "sg:phone":"+1 303 444 1787",
    "sg:postcode":"80301",
    "sg:province":"CO",
    "sg:tags":[
        "gas"
    ],
    "wof:name":"Fred's Propane Svc",
    "wof:placetype":"venue"
},
  "geometry": {"coordinates":[-105.179455,40.033189],"type":"Point"}
}