{
  "type": "Feature",
  "properties": {
    "addr:full":"2150 Victor Pl Colorado Springs CO 80915",
    "addr:housenumber":"2150",
    "addr:postcode":"80915",
    "addr:street":"Victor Pl",
    "iso:country":"US",
    "sg:address":"2150 Victor Pl",
    "sg:city":"Colorado Springs",
    "sg:classifiers":[
        {
            "category":"Wholesale",
            "subcategory":"Beer",
            "type":"Manufacturing & Wholesale Goods"
        }
    ],
    "sg:phone":"+1 719 262 0649",
    "sg:postcode":"80915",
    "sg:province":"CO",
    "sg:tags":[
        "ale"
    ],
    "wof:name":"Western Distributing Co",
    "wof:placetype":"venue"
},
  "geometry": {"coordinates":[-104.720947,38.863401],"type":"Point"}
}