{
  "type": "Feature",
  "properties": {
    "addr:full":"3132 W Monmouth Ave Englewood CO 80110",
    "addr:housenumber":"3132",
    "addr:postcode":"80110",
    "addr:street":"W Monmouth Ave",
    "iso:country":"US",
    "sg:address":"3132 W Monmouth Ave",
    "sg:city":"Englewood",
    "sg:classifiers":[
        {
            "category":"Arts & Performance",
            "subcategory":"Theater",
            "type":"Entertainment"
        }
    ],
    "sg:phone":"+1 303 347 8510",
    "sg:postcode":"80110",
    "sg:province":"CO",
    "sg:tags":[
        "music"
    ],
    "wof:name":"Jeff Hildebrandt Entertainment",
    "wof:placetype":"venue"
},
  "geometry": {"coordinates":[-105.027824,39.626058],"type":"Point"}
}