{
  "type": "Feature",
  "properties": {
    "addr:full":"9244 S Hwy 83 Franktown CO 80116",
    "addr:housenumber":"9244",
    "addr:postcode":"80116",
    "addr:street":"S Hwy 83",
    "iso:country":"US",
    "sg:address":"9244 S Hwy 83",
    "sg:city":"Franktown",
    "sg:classifiers":[
        {
            "category":"Education",
            "subcategory":"School",
            "type":"Public Place"
        }
    ],
    "sg:phone":"+1 303 688 3211",
    "sg:postcode":"80116",
    "sg:province":"CO",
    "sg:website":"www.dcsdk12.org",
    "wof:name":"Cherry Valley Elementary Schl",
    "wof:placetype":"venue"
},
  "geometry": {"coordinates":[-104.699684,39.227908],"type":"Point"}
}