{
  "type": "Feature",
  "properties": {
    "addr:full":"2985 Co Rd K Rush CO 80833",
    "addr:housenumber":"2985",
    "addr:postcode":"80833",
    "addr:street":"Co Rd;Rush",
    "iso:country":"US",
    "sg:address":"2985 Co Rd K",
    "sg:city":"Rush",
    "sg:classifiers":[
        {
            "category":"Organizations",
            "subcategory":"Religious Organization",
            "type":"Services"
        }
    ],
    "sg:phone":"+1 719 478 5576",
    "sg:postcode":"80833",
    "sg:province":"CO",
    "sg:tags":[
        "church"
    ],
    "wof:name":"Kendrick Bible Church",
    "wof:placetype":"venue"
},
  "geometry": {"coordinates":[-104.015946,38.653178],"type":"Point"}
}