{
  "type": "Feature",
  "properties": {
    "iso:country":"US",
    "sg:address":"1229 Thompson St",
    "sg:city":"Limon",
    "sg:classifiers":[
        {
            "category":"Autos & Motor Vehicles",
            "subcategory":"Auto Supplies",
            "type":"Retail Goods"
        }
    ],
    "sg:phone":"+1 719 775 2093",
    "sg:postcode":"80828",
    "sg:province":"CO",
    "wof:name":"Limon Tire & Diesel",
    "wof:placetype":"venue"
},
  "geometry": {"coordinates":[-103.693252,39.254791],"type":"Point"}
}