{
  "type": "Feature",
  "properties": {
    "iso:country":"US",
    "sg:address":"6167 S Moline Ct",
    "sg:city":"Englewood",
    "sg:classifiers":[
        {
            "category":"Professional",
            "type":"Services"
        }
    ],
    "sg:phone":"+1 303 740 0567",
    "sg:postcode":"80111",
    "sg:province":"CO",
    "wof:name":"Lambros Gianos",
    "wof:placetype":"venue"
},
  "geometry": {"coordinates":[-104.855056,39.603666],"type":"Point"}
}