{
  "type": "Feature",
  "properties": {
    "iso:country":"US",
    "sg:address":"6202 E Pine Ln",
    "sg:city":"Parker",
    "sg:classifiers":[
        {
            "category":"Home & Garden",
            "subcategory":"Building Materials",
            "type":"Retail Goods"
        }
    ],
    "sg:phone":"+1 303 840 3322",
    "sg:postcode":"80138",
    "sg:province":"CO",
    "wof:name":"Sherwin-Williams",
    "wof:placetype":"venue"
},
  "geometry": {"coordinates":[-104.769516,39.544148],"type":"Point"}
}