{
  "type": "Feature",
  "properties": {
    "iso:country":"US",
    "sg:address":"2472 S Fenton Dr",
    "sg:city":"Denver",
    "sg:classifiers":[
        {
            "category":"Shopping",
            "subcategory":"Computers & Home Electronics",
            "type":"Retail Goods"
        }
    ],
    "sg:phone":"+1 303 985 9752",
    "sg:postcode":"80227",
    "sg:province":"CO",
    "wof:name":"Winped Pedigree",
    "wof:placetype":"venue"
},
  "geometry": {"coordinates":[-105.063585,39.672292],"type":"Point"}
}