{
  "type": "Feature",
  "properties": {
    "addr:full":"2020 W Barberry Pl Denver CO 80204",
    "addr:housenumber":"2020",
    "addr:postcode":"80204",
    "addr:street":"W Barberry Pl",
    "iso:country":"US",
    "sg:address":"2020 W Barberry Pl",
    "sg:city":"Denver",
    "sg:classifiers":[
        {
            "category":"Wholesale",
            "subcategory":"Electrical",
            "type":"Manufacturing & Wholesale Goods"
        },
        {
            "category":"Manufacturing",
            "subcategory":"Tools & Machinery",
            "type":"Manufacturing & Wholesale Goods"
        }
    ],
    "sg:phone":"+1 303 623 8658",
    "sg:postcode":"80204",
    "sg:province":"CO",
    "sg:tags":[
        "armature",
        "mfg",
        "electric",
        "motor",
        "rewinding"
    ],
    "sg:website":"www.wazeeelectric.com",
    "wof:name":"Wazee Electric Co Inc",
    "wof:placetype":"venue"
},
  "geometry": {"coordinates":[-105.01206500000001,39.730115],"type":"Point"}
}