{
  "type": "Feature",
  "properties": {
    "addr:full":"1715 Ivy Pl Colorado Springs CO 80906",
    "addr:housenumber":"1715",
    "addr:postcode":"80906",
    "addr:street":"Ivy Pl",
    "iso:country":"US",
    "sg:address":"1715 Ivy Pl",
    "sg:city":"Colorado Springs",
    "sg:classifiers":[
        {
            "category":"Manufacturing",
            "subcategory":"Metals",
            "type":"Manufacturing & Wholesale Goods"
        }
    ],
    "sg:phone":"+1 719 477 0860",
    "sg:postcode":"80906",
    "sg:province":"CO",
    "sg:tags":[
        "panel"
    ],
    "wof:name":"Eco Envi Inc",
    "wof:placetype":"venue"
},
  "geometry": {"coordinates":[-104.830156,38.807872],"type":"Point"}
}