{
  "type": "Feature",
  "properties": {
    "addr:full":"9100 East Panorama Drive Suite 250 Englewood CO 80112",
    "addr:housenumber":"9100",
    "addr:postcode":"80112",
    "addr:street":"East Panorama Drive Suite 250",
    "iso:country":"US",
    "sg:address":"9100 East Panorama Drive Suite 250",
    "sg:city":"Englewood",
    "sg:classifiers":[
        {
            "category":"Professional",
            "subcategory":"Computer Services",
            "type":"Services"
        }
    ],
    "sg:phone":"+1 877 658 4473",
    "sg:postcode":"80112",
    "sg:province":"CO",
    "sg:website":"http://www.ontargetjobs.com/",
    "wof:name":"onTargetjobs",
    "wof:placetype":"venue"
},
  "geometry": {"coordinates":[-104.883556,39.578201],"type":"Point"}
}