{
  "type": "Feature",
  "properties": {
    "addr:full":"512 W 2nd St Loveland CO 80537",
    "addr:housenumber":"512",
    "addr:postcode":"80537",
    "addr:street":"W 2Nd St",
    "iso:country":"US",
    "sg:address":"512 W 2nd St",
    "sg:city":"Loveland",
    "sg:classifiers":[
        {
            "category":"Building & Trades",
            "subcategory":"Construction",
            "type":"Services"
        }
    ],
    "sg:phone":"+1 970 667 5805",
    "sg:postcode":"80537",
    "sg:province":"CO",
    "sg:tags":[
        "windows",
        "siding",
        "contractor"
    ],
    "wof:name":"Siding Plus Windows",
    "wof:placetype":"venue"
},
  "geometry": {"coordinates":[-105.08503899999999,40.393578],"type":"Point"}
}