{
  "type": "Feature",
  "properties": {
    "addr:full":"853 E Ohio Ave Denver CO 80209",
    "addr:housenumber":"853",
    "addr:postcode":"80209",
    "addr:street":"E Ohio Ave",
    "iso:country":"US",
    "sg:address":"853 E Ohio Ave",
    "sg:city":"Denver",
    "sg:classifiers":[
        {
            "category":"Coffee & Tea",
            "type":"Food & Drink"
        },
        {
            "category":"Bakery",
            "type":"Food & Drink"
        }
    ],
    "sg:phone":"+1 720 542 9202",
    "sg:postcode":"80209",
    "sg:province":"CO",
    "sg:website":"www.washperk.com",
    "wof:name":"Wash Perk",
    "wof:placetype":"venue"
},
  "geometry": {"coordinates":[-104.977478,39.702054],"type":"Point"}
}