{
  "type": "Feature",
  "properties": {
    "addr:full":"3204 N Cascade Ave Colorado Springs CO 80907",
    "addr:housenumber":"3204",
    "addr:postcode":"80907",
    "addr:street":"N Cascade Ave",
    "iso:country":"US",
    "sg:address":"3204 N Cascade Ave",
    "sg:city":"Colorado Springs",
    "sg:classifiers":[
        {
            "category":"Mining & Drilling",
            "type":"Manufacturing & Wholesale Goods"
        }
    ],
    "sg:phone":"+1 719 237 8741",
    "sg:postcode":"80907",
    "sg:province":"CO",
    "sg:tags":[
        "stone",
        "dimension",
        "quarry"
    ],
    "wof:name":"Bullnose World Colorado Spr",
    "wof:placetype":"venue"
},
  "geometry": {"coordinates":[-104.822912,38.879204],"type":"Point"}
}