{
  "type": "Feature",
  "properties": {
    "iso:country":"US",
    "sg:address":"1215 19th St",
    "sg:city":"Golden",
    "sg:classifiers":[
        {
            "category":"Building & Trades",
            "subcategory":"Landscaping Services",
            "type":"Services"
        }
    ],
    "sg:phone":"+1 303 216 2100",
    "sg:postcode":"80401",
    "sg:province":"CO",
    "wof:name":"Golden Landscaping Nursery",
    "wof:placetype":"venue"
},
  "geometry": {"coordinates":[-105.219464,39.74776],"type":"Point"}
}