{
  "type": "Feature",
  "properties": {
    "iso:country":"US",
    "sg:address":"4020 Ridge Dr",
    "sg:city":"Pueblo",
    "sg:classifiers":[
        {
            "category":"Banks & Credit Unions",
            "subcategory":"Bank",
            "type":"Services"
        }
    ],
    "sg:phone":"+1 719 544 0840",
    "sg:postcode":"81008",
    "sg:province":"CO",
    "sg:tags":[
        "loan",
        "real estate"
    ],
    "wof:name":"VPM Funding-Pueblo",
    "wof:placetype":"venue"
},
  "geometry": {"coordinates":[-104.633004,38.311921],"type":"Point"}
}