{
  "type": "Feature",
  "properties": {
    "iso:country":"US",
    "sg:address":"5367 S Lewiston St",
    "sg:city":"Aurora",
    "sg:classifiers":[
        {
            "category":"Insurance",
            "subcategory":"Insurance Agent",
            "type":"Services"
        }
    ],
    "sg:phone":"+1 303 699 1346",
    "sg:postcode":"80015",
    "sg:province":"CO",
    "wof:name":"Qcs Insurance Solutions Inc",
    "wof:placetype":"venue"
},
  "geometry": {"coordinates":[-104.80225799999999,39.618371],"type":"Point"}
}