{
  "type": "Feature",
  "properties": {
    "addr:full":"7391 Village Square Dr Castle Rock CO 80104",
    "addr:housenumber":"7391",
    "addr:postcode":"80104",
    "addr:street":"Village Square Dr",
    "iso:country":"US",
    "sg:address":"7391 Village Square Dr",
    "sg:city":"Castle Rock",
    "sg:classifiers":[
        {
            "category":"Building & Trades",
            "subcategory":"Plumbing",
            "type":"Services"
        }
    ],
    "sg:phone":"+1 720 733 9950",
    "sg:postcode":"80104",
    "sg:province":"CO",
    "sg:tags":[
        "contractor"
    ],
    "wof:name":"Colorado Mechanical",
    "wof:placetype":"venue"
},
  "geometry": {"coordinates":[-104.87835099999999,39.470922],"type":"Point"}
}