{
  "type": "Feature",
  "properties": {
    "iso:country":"US",
    "sg:address":"407 S Broadway Ste 400",
    "sg:city":"Denver",
    "sg:classifiers":[
        {
            "category":"Shopping",
            "type":"Retail Goods"
        }
    ],
    "sg:phone":"+1 303 733 3965",
    "sg:postcode":"80209",
    "sg:province":"CO",
    "sg:website":"www.dollartree.com",
    "wof:name":"Dollar Tree, Inc",
    "wof:placetype":"venue"
},
  "geometry": {"coordinates":[-104.987607,39.709266],"type":"Point"}
}