{
  "type": "Feature",
  "properties": {
    "addr:full":"3393 Iris Ave Boulder CO 80301",
    "addr:housenumber":"3393",
    "addr:postcode":"80301",
    "addr:street":"Iris Ave",
    "iso:country":"US",
    "sg:address":"3393 Iris Ave",
    "sg:city":"Boulder",
    "sg:classifiers":[
        {
            "category":"Health Services",
            "subcategory":"Health Practitioner",
            "type":"Services"
        }
    ],
    "sg:phone":"+1 303 447 2872",
    "sg:postcode":"80301",
    "sg:province":"CO",
    "sg:tags":[
        "dental",
        "hygienist"
    ],
    "wof:name":"Danielle Woody",
    "wof:placetype":"venue"
},
  "geometry": {"coordinates":[-105.24929,40.036549],"type":"Point"}
}