{
  "type": "Feature",
  "properties": {
    "iso:country":"US",
    "sg:address":"10140 W Alamo Pl",
    "sg:city":"Littleton",
    "sg:classifiers":[
        {
            "category":"Wholesale",
            "subcategory":"Electrical",
            "type":"Manufacturing & Wholesale Goods"
        }
    ],
    "sg:phone":"+1 303 979 8829",
    "sg:postcode":"80127",
    "sg:province":"CO",
    "sg:tags":[
        "equipment",
        "parts",
        "electronic"
    ],
    "wof:name":"G E Harris Controls",
    "wof:placetype":"venue"
},
  "geometry": {"coordinates":[-105.11208499999999,39.614177],"type":"Point"}
}