{
  "type": "Feature",
  "properties": {
    "iso:country":"US",
    "sg:address":"1104 Francis St",
    "sg:city":"Longmont",
    "sg:classifiers":[
        {
            "category":"Organizations",
            "subcategory":"Religious Organization",
            "type":"Services"
        }
    ],
    "sg:phone":"+1 303 772 2459",
    "sg:postcode":"80501",
    "sg:province":"CO",
    "wof:name":"March For Jesus-Longmont",
    "wof:placetype":"venue"
},
  "geometry": {"coordinates":[-105.116479,40.179378],"type":"Point"}
}