{
  "type": "Feature",
  "properties": {
    "iso:country":"US",
    "sg:address":"5445 Dtc Pkwy",
    "sg:city":"Englewood",
    "sg:classifiers":[
        {
            "category":"Banks & Credit Unions",
            "subcategory":"Bank",
            "type":"Services"
        }
    ],
    "sg:phone":"+1 303 694 6280",
    "sg:postcode":"80111",
    "sg:province":"CO",
    "sg:tags":[
        "institution",
        "business"
    ],
    "wof:name":"MetLife AG Investments",
    "wof:placetype":"venue"
},
  "geometry": {"coordinates":[-104.896162,39.617378],"type":"Point"}
}