{
  "type": "Feature",
  "properties": {
    "addr:full":"2330 Coventry Ct Fort Collins CO 80526",
    "addr:housenumber":"2330",
    "addr:postcode":"80526",
    "addr:street":"Coventry Ct",
    "iso:country":"US",
    "sg:address":"2330 Coventry Ct",
    "sg:city":"Fort Collins",
    "sg:classifiers":[
        {
            "category":"Building & Trades",
            "subcategory":"Construction",
            "type":"Services"
        }
    ],
    "sg:phone":"+1 970 224 4771",
    "sg:postcode":"80526",
    "sg:province":"CO",
    "sg:tags":[
        "hanging",
        "contractor"
    ],
    "wof:name":"Peacock Painting Inc",
    "wof:placetype":"venue"
},
  "geometry": {"coordinates":[-105.119961,40.565743],"type":"Point"}
}