{
  "type": "Feature",
  "properties": {
    "addr:full":"4235 S College Ave Fort Collins CO 80525",
    "addr:housenumber":"4235",
    "addr:postcode":"80525",
    "addr:street":"S College Ave",
    "iso:country":"US",
    "sg:address":"4235 S College Ave",
    "sg:city":"Fort Collins",
    "sg:classifiers":[
        {
            "category":"Manufacturing",
            "subcategory":"Printing",
            "type":"Manufacturing & Wholesale Goods"
        }
    ],
    "sg:phone":"+1 970 267 9393",
    "sg:postcode":"80525",
    "sg:province":"CO",
    "sg:tags":[
        "lithographic",
        "commercial"
    ],
    "wof:name":"Instant Imprints Fort Colli",
    "wof:placetype":"venue"
},
  "geometry": {"coordinates":[-105.07714799999999,40.531779],"type":"Point"}
}