{
  "type": "Feature",
  "properties": {
    "iso:country":"US",
    "sg:address":"611 Water St",
    "sg:city":"Silver Plume",
    "sg:classifiers":[
        {
            "category":"Professional",
            "type":"Services"
        }
    ],
    "sg:phone":"+1 303 569 0155",
    "sg:postcode":"80476",
    "sg:province":"CO",
    "sg:tags":[
        "establishment"
    ],
    "wof:name":"Salem Minerals Inc",
    "wof:placetype":"venue"
},
  "geometry": {"coordinates":[-105.732794,39.695079],"type":"Point"}
}