{
  "type": "Feature",
  "properties": {
    "addr:full":"6300 E Yale Avenue Suite 126 Denver CO 80222",
    "addr:housenumber":"6300",
    "addr:postcode":"80222",
    "addr:street":"E Yale Avenue Suite 126",
    "iso:country":"US",
    "sg:address":"6300 E Yale Avenue Suite 126",
    "sg:city":"Denver",
    "sg:classifiers":[
        {
            "category":"Professional",
            "subcategory":"Accounting & Tax Preparation",
            "type":"Services"
        }
    ],
    "sg:phone":"+1 303 753 0290",
    "sg:postcode":"80222",
    "sg:province":"CO",
    "sg:tags":[
        "accountant"
    ],
    "wof:name":"Shawcross Howard CPA",
    "wof:placetype":"venue"
},
  "geometry": {"coordinates":[-104.91556199999999,39.667549],"type":"Point"}
}