{
  "type": "Feature",
  "properties": {
    "addr:full":"5155 Farmingdale Dr Colorado Springs CO 80917",
    "addr:housenumber":"5155",
    "addr:postcode":"80917",
    "addr:street":"Farmingdale Dr",
    "iso:country":"US",
    "sg:address":"5155 Farmingdale Dr",
    "sg:city":"Colorado Springs",
    "sg:classifiers":[
        {
            "category":"Building & Trades",
            "subcategory":"Landscaping Services",
            "type":"Services"
        }
    ],
    "sg:phone":"+1 719 573 8722",
    "sg:postcode":"80917",
    "sg:province":"CO",
    "wof:name":"Fertilawn Landscape",
    "wof:placetype":"venue"
},
  "geometry": {"coordinates":[-104.731712,38.904655],"type":"Point"}
}