{
  "type": "Feature",
  "properties": {
    "addr:full":"6401 E 72nd Ave Commerce City CO 80022",
    "addr:housenumber":"6401",
    "addr:postcode":"80022",
    "addr:street":"E 72Nd Ave",
    "iso:country":"US",
    "sg:address":"6401 E 72nd Ave",
    "sg:city":"Commerce City",
    "sg:classifiers":[
        {
            "category":"Banks & Credit Unions",
            "subcategory":"Investment Brokerage",
            "type":"Services"
        }
    ],
    "sg:phone":"+1 303 286 3550",
    "sg:postcode":"80022",
    "sg:province":"CO",
    "sg:tags":[
        "advisory"
    ],
    "wof:name":"S W Financial LLC",
    "wof:placetype":"venue"
},
  "geometry": {"coordinates":[-104.912667,39.827193],"type":"Point"}
}