{
  "type": "Feature",
  "properties": {
    "iso:country":"US",
    "sg:address":"2350 W Midway Blvd",
    "sg:city":"Broomfield",
    "sg:classifiers":[
        {
            "category":"Wholesale",
            "subcategory":"Machinery & Supplies",
            "type":"Manufacturing & Wholesale Goods"
        },
        {
            "category":"Building & Trades",
            "subcategory":"Equipment Rental",
            "type":"Services"
        }
    ],
    "sg:phone":"+1 303 777 9692",
    "sg:postcode":"80020",
    "sg:province":"CO",
    "sg:tags":[
        "chemical",
        "railroad",
        "blender",
        "toll"
    ],
    "wof:name":"R Mac Sales & Leasing LLC",
    "wof:placetype":"venue"
},
  "geometry": {"coordinates":[-105.096103,39.922596],"type":"Point"}
}