{
  "type": "Feature",
  "properties": {
    "addr:full":"366 Norfolk St Aurora CO 80011",
    "addr:housenumber":"366",
    "addr:postcode":"80011",
    "addr:street":"Norfolk St",
    "iso:country":"US",
    "sg:address":"366 Norfolk St",
    "sg:city":"Aurora",
    "sg:classifiers":[
        {
            "category":"Retail",
            "subcategory":"Auto Repair",
            "type":"Services"
        }
    ],
    "sg:phone":"+1 720 560 2435",
    "sg:postcode":"80011",
    "sg:province":"CO",
    "sg:tags":[
        "repairing",
        "automobile"
    ],
    "wof:name":"Subytech",
    "wof:placetype":"venue"
},
  "geometry": {"coordinates":[-104.797721,39.724871],"type":"Point"}
}