{
  "type": "Feature",
  "properties": {
    "iso:country":"US",
    "sg:address":"18468 E Berry Dr",
    "sg:city":"Centennial",
    "sg:classifiers":[
        {
            "category":"Banks & Credit Unions",
            "subcategory":"Financial Services",
            "type":"Services"
        }
    ],
    "sg:phone":"+1 303 690 2789",
    "sg:postcode":"80015",
    "sg:province":"CO",
    "sg:tags":[
        "company",
        "holding"
    ],
    "wof:name":"Cbj & R Enterprises",
    "wof:placetype":"venue"
},
  "geometry": {"coordinates":[-104.77296,39.615198],"type":"Point"}
}