{
  "type": "Feature",
  "properties": {
    "addr:full":"3836 E Long Ave Littleton CO 80122",
    "addr:housenumber":"3836",
    "addr:postcode":"80122",
    "addr:street":"E Long Ave",
    "iso:country":"US",
    "sg:address":"3836 E Long Ave",
    "sg:city":"Littleton",
    "sg:classifiers":[
        {
            "category":"Local Transit",
            "type":"Transportation"
        }
    ],
    "sg:phone":"+1 303 741 6930",
    "sg:postcode":"80122",
    "sg:province":"CO",
    "sg:tags":[
        "passenger"
    ],
    "wof:name":"American Limousine Cnnctn",
    "wof:placetype":"venue"
},
  "geometry": {"coordinates":[-104.94287,39.57475],"type":"Point"}
}