{
  "type": "Feature",
  "properties": {
    "addr:full":"1001 W 52nd Ave Denver CO 80221",
    "addr:housenumber":"1001",
    "addr:postcode":"80221",
    "addr:street":"W 52Nd Ave",
    "iso:country":"US",
    "sg:address":"1001 W 52nd Ave",
    "sg:city":"Denver",
    "sg:classifiers":[
        {
            "category":"Wholesale",
            "subcategory":"Construction Materials",
            "type":"Manufacturing & Wholesale Goods"
        }
    ],
    "sg:phone":"+1 303 477 0432",
    "sg:postcode":"80221",
    "sg:province":"CO",
    "sg:tags":[
        "concrete",
        "product"
    ],
    "wof:name":"Holcim Inc",
    "wof:placetype":"venue"
},
  "geometry": {"coordinates":[-105.004614,39.79096],"type":"Point"}
}