{
  "type": "Feature",
  "properties": {
    "addr:full":"2617 Broadway St Boulder CO 80304",
    "addr:housenumber":"2617",
    "addr:postcode":"80304",
    "addr:street":"Broadway St",
    "iso:country":"US",
    "sg:address":"2617 Broadway St",
    "sg:city":"Boulder",
    "sg:classifiers":[
        {
            "category":"Health Services",
            "subcategory":"Doctor",
            "type":"Services"
        }
    ],
    "sg:phone":"+1 303 449 6666",
    "sg:postcode":"80304",
    "sg:province":"CO",
    "sg:tags":[
        "physician",
        "surgeon"
    ],
    "wof:name":"Boulder Valley Plastic Surgery",
    "wof:placetype":"venue"
},
  "geometry": {"coordinates":[-105.282134,40.025344],"type":"Point"}
}