{
  "type": "Feature",
  "properties": {
    "addr:full":"62786 Niagara Rd Montrose CO 81401",
    "addr:housenumber":"62786",
    "addr:postcode":"81401",
    "addr:street":"Niagara Rd",
    "iso:country":"US",
    "sg:address":"62786 Niagara Rd",
    "sg:city":"Montrose",
    "sg:classifiers":[
        {
            "category":"Manufacturing",
            "subcategory":"Tools & Machinery",
            "type":"Manufacturing & Wholesale Goods"
        }
    ],
    "sg:phone":"+1 970 249 5155",
    "sg:postcode":"81401",
    "sg:province":"CO",
    "sg:tags":[
        "machine",
        "shop",
        "industrial",
        "mfg"
    ],
    "wof:name":"Centech Manufacturing Co Inc",
    "wof:placetype":"venue"
},
  "geometry": {"coordinates":[-107.918486,38.46749],"type":"Point"}
}