{
  "type": "Feature",
  "properties": {
    "addr:full":"263 S Forest St Denver CO 80246",
    "addr:housenumber":"263",
    "addr:postcode":"80246",
    "addr:street":"S Forest St",
    "iso:country":"US",
    "sg:address":"263 S Forest St",
    "sg:city":"Denver",
    "sg:classifiers":[
        {
            "category":"Real Estate",
            "subcategory":"Real Estate Agent",
            "type":"Services"
        }
    ],
    "sg:phone":"+1 303 322 5452",
    "sg:postcode":"80246",
    "sg:province":"CO",
    "sg:tags":[
        "trust",
        "investment"
    ],
    "wof:name":"Mrs Co",
    "wof:placetype":"venue"
},
  "geometry": {"coordinates":[-104.927052,39.712455],"type":"Point"}
}