{
  "type": "Feature",
  "properties": {
    "addr:full":"539 Co Rd 5 Fraser CO 80435",
    "addr:housenumber":"539",
    "addr:postcode":"80435",
    "addr:street":"Co Rd 5 Fraser",
    "iso:country":"US",
    "sg:address":"539 Co Rd 5",
    "sg:city":"Fraser",
    "sg:classifiers":[
        {
            "category":"Building & Trades",
            "subcategory":"Construction",
            "type":"Services"
        }
    ],
    "sg:phone":"+1 970 726 0416",
    "sg:postcode":"80435",
    "sg:province":"CO",
    "sg:tags":[
        "excavating",
        "contractor"
    ],
    "wof:name":"Pratt Excavation Co",
    "wof:placetype":"venue"
},
  "geometry": {"coordinates":[-105.935506,39.607804],"type":"Point"}
}