{
  "type": "Feature",
  "properties": {
    "iso:country":"US",
    "sg:address":"4378 Co Rd 12",
    "sg:city":"Meeker",
    "sg:classifiers":[
        {
            "category":"Professional",
            "subcategory":"Management & Consulting",
            "type":"Services"
        },
        {
            "category":"Travel",
            "subcategory":"Hotels & Motels",
            "type":"Entertainment"
        }
    ],
    "sg:phone":"+1 970 878 3595",
    "sg:postcode":"81641",
    "sg:province":"CO",
    "sg:tags":[
        "banking",
        "ranch",
        "guest"
    ],
    "wof:name":"Marvine Ranch LLC",
    "wof:placetype":"venue"
},
  "geometry": {"coordinates":[-107.45295400000001,40.026573],"type":"Point"}
}