{
  "type": "Feature",
  "properties": {
    "iso:country":"US",
    "sg:address":"7476 E 29th Ave Ste 13",
    "sg:city":"Denver",
    "sg:classifiers":[
        {
            "category":"Professional",
            "subcategory":"Employment Agencies",
            "type":"Services"
        }
    ],
    "sg:phone":"+1 303 909 3868",
    "sg:postcode":"80223",
    "sg:province":"CO",
    "sg:website":"www.tentiltwo.com",
    "wof:name":"10 Til 2",
    "wof:placetype":"venue"
},
  "geometry": {"coordinates":[-104.900565,39.757663],"type":"Point"}
}