{
  "type": "Feature",
  "properties": {
    "addr:full":"2315 Fairway Ln Greeley CO 80634",
    "addr:housenumber":"2315",
    "addr:postcode":"80634",
    "addr:street":"Fairway Ln",
    "iso:country":"US",
    "sg:address":"2315 Fairway Ln",
    "sg:city":"Greeley",
    "sg:classifiers":[
        {
            "category":"Professional",
            "subcategory":"Research",
            "type":"Services"
        }
    ],
    "sg:phone":"+1 970 330 9101",
    "sg:postcode":"80634",
    "sg:province":"CO",
    "sg:tags":[
        "market",
        "analysis"
    ],
    "sg:website":"www.focusgroupguru.com",
    "wof:name":"Cambridge Associates LTD",
    "wof:placetype":"venue"
},
  "geometry": {"coordinates":[-104.774608,40.4041],"type":"Point"}
}