{
  "type": "Feature",
  "properties": {
    "iso:country":"US",
    "sg:address":"2220 S Fraser St",
    "sg:city":"Aurora",
    "sg:classifiers":[
        {
            "category":"Professional",
            "subcategory":"Accounting & Tax Preparation",
            "type":"Services"
        }
    ],
    "sg:phone":"+1 303 337 6804",
    "sg:postcode":"80014",
    "sg:province":"CO",
    "sg:tags":[
        "accountant"
    ],
    "wof:name":"Marilyn R Burnside CPA",
    "wof:placetype":"venue"
},
  "geometry": {"coordinates":[-104.812192,39.675556],"type":"Point"}
}