{
  "type": "Feature",
  "properties": {
    "iso:country":"US",
    "sg:address":"2394 W 119th Ave",
    "sg:city":"Denver",
    "sg:classifiers":[
        {
            "category":"Travel",
            "subcategory":"Travel Agent",
            "type":"Entertainment"
        }
    ],
    "sg:phone":"+1 303 830 8928",
    "sg:postcode":"80234",
    "sg:province":"CO",
    "sg:tags":[
        "agency",
        "bureau"
    ],
    "wof:name":"Business & Leisure Travel Inc",
    "wof:placetype":"venue"
},
  "geometry": {"coordinates":[-105.013761,39.91337],"type":"Point"}
}