{
  "type": "Feature",
  "properties": {
    "iso:country":"US",
    "sg:address":"615 N Murray Blvd",
    "sg:city":"Colorado Springs",
    "sg:classifiers":[
        {
            "category":"Personal",
            "subcategory":"Shoe Repair & Shine",
            "type":"Services"
        }
    ],
    "sg:phone":"+1 719 596 8870",
    "sg:postcode":"80915",
    "sg:province":"CO",
    "sg:tags":[
        "repairing",
        "boot"
    ],
    "wof:name":"Murray Shoe Repair",
    "wof:placetype":"venue"
},
  "geometry": {"coordinates":[-104.74803199999999,38.841438],"type":"Point"}
}