{
  "type": "Feature",
  "properties": {
    "iso:country":"US",
    "sg:address":"1201 S Broadway",
    "sg:city":"Denver",
    "sg:classifiers":[
        {
            "category":"Food & Beverages",
            "subcategory":"Groceries & Convenience Stores",
            "type":"Retail Goods"
        }
    ],
    "sg:phone":"+1 303 715 9451",
    "sg:postcode":"80210",
    "sg:province":"CO",
    "wof:name":"Barn Store # 12",
    "wof:placetype":"venue"
},
  "geometry": {"coordinates":[-104.987638,39.694812],"type":"Point"}
}