{
  "type": "Feature",
  "properties": {
    "addr:full":"2601 Foothill Blvd Rock Springs CO 82901",
    "addr:housenumber":"2601",
    "addr:postcode":"82901",
    "addr:street":"Foothill Blvd",
    "iso:country":"US",
    "sg:address":"2601 Foothill Blvd",
    "sg:city":"Rock Springs",
    "sg:classifiers":[
        {
            "category":"Shopping",
            "subcategory":"Department Store",
            "type":"Retail Goods"
        }
    ],
    "sg:phone":"+1 307 362 1209",
    "sg:postcode":"82901",
    "sg:province":"CO",
    "sg:tags":[
        "shop"
    ],
    "wof:name":"Dollar Tree",
    "wof:placetype":"venue"
},
  "geometry": {"coordinates":[-109.25557000000001,41.58376],"type":"Point"}
}