{
  "type": "Feature",
  "properties": {
    "iso:country":"US",
    "sg:address":"4765 E 129th Ct",
    "sg:city":"Denver",
    "sg:classifiers":[
        {
            "category":"Shopping",
            "type":"Retail Goods"
        }
    ],
    "sg:phone":"+1 720 935 1035",
    "sg:postcode":"80241",
    "sg:province":"CO",
    "sg:tags":[
        "merchandise"
    ],
    "wof:name":"Kittycat Habitat",
    "wof:placetype":"venue"
},
  "geometry": {"coordinates":[-104.93209899999999,39.930331],"type":"Point"}
}