{
  "type": "Feature",
  "properties": {
    "iso:country":"US",
    "sg:address":"15231 E Colfax Ave",
    "sg:city":"Aurora",
    "sg:classifiers":[
        {
            "category":"Utilities",
            "subcategory":"Mobile Phone",
            "type":"Services"
        },
        {
            "category":"Coffee & Tea",
            "type":"Food & Drink"
        }
    ],
    "sg:phone":"+1 303 340 3403",
    "sg:postcode":"80011",
    "sg:province":"CO",
    "sg:tags":[
        "shop",
        "restaurant",
        "espresso",
        "hotspot",
        "wi-fi"
    ],
    "sg:website":"http://www.starbuckscoffee.com",
    "wof:name":"Starbucks Coffee",
    "wof:placetype":"venue"
},
  "geometry": {"coordinates":[-104.810993,39.74016],"type":"Point"}
}