{
  "type": "Feature",
  "properties": {
    "iso:country":"US",
    "sg:address":"2460 W 26th Ave",
    "sg:city":"Denver",
    "sg:classifiers":[
        {
            "category":"Professional",
            "subcategory":"Engineering",
            "type":"Services"
        }
    ],
    "sg:phone":"+1 303 433 1777",
    "sg:postcode":"80211",
    "sg:province":"CO",
    "sg:tags":[
        "engineer"
    ],
    "wof:name":"Carl Walker Inc",
    "wof:placetype":"venue"
},
  "geometry": {"coordinates":[-105.01681000000001,39.754737],"type":"Point"}
}