{
  "type": "Feature",
  "properties": {
    "iso:country":"US",
    "sg:address":"11111 E 53rd Ave",
    "sg:city":"Denver",
    "sg:classifiers":[
        {
            "category":"Wholesale",
            "subcategory":"Durable Goods & Equipment",
            "type":"Manufacturing & Wholesale Goods"
        }
    ],
    "sg:phone":"+1 303 722 5721",
    "sg:postcode":"80239",
    "sg:province":"CO",
    "sg:tags":[
        "representative",
        "manufacturer"
    ],
    "sg:website":"www.eleclines.com",
    "wof:name":"Electrical Lines Inc",
    "wof:placetype":"venue"
},
  "geometry": {"coordinates":[-104.860373,39.793192],"type":"Point"}
}