{
  "type": "Feature",
  "properties": {
    "iso:country":"US",
    "sg:address":"1006 S Main St",
    "sg:city":"Lamar",
    "sg:classifiers":[
        {
            "category":"Organizations",
            "subcategory":"Non-profit Organization",
            "type":"Services"
        }
    ],
    "sg:phone":"+1 719 336 2600",
    "sg:postcode":"81052",
    "sg:province":"CO",
    "sg:tags":[
        "information",
        "alcoholism",
        "treatment"
    ],
    "wof:name":"Se Colorado For Drug Free Comm",
    "wof:placetype":"venue"
},
  "geometry": {"coordinates":[-102.61864799999999,38.078938],"type":"Point"}
}