{
  "type": "Feature",
  "properties": {
    "iso:country":"US",
    "sg:address":"2255 W Berry Ave",
    "sg:city":"Littleton",
    "sg:classifiers":[
        {
            "category":"Government",
            "subcategory":"Office",
            "type":"Public Place"
        }
    ],
    "sg:phone":"+1 303 795 3772",
    "sg:postcode":"80120",
    "sg:province":"CO",
    "sg:tags":[
        "dept",
        "sewer"
    ],
    "wof:name":"Littleton Sewer Dept",
    "wof:placetype":"venue"
},
  "geometry": {"coordinates":[-105.014565,39.616959],"type":"Point"}
}