{
  "type": "Feature",
  "properties": {
    "iso:country":"US",
    "sg:address":"1899 Wynkoop St",
    "sg:city":"Denver",
    "sg:classifiers":[
        {
            "category":"Professional",
            "type":"Services"
        }
    ],
    "sg:phone":"+1 303 824 5600",
    "sg:postcode":"80202",
    "sg:province":"CO",
    "sg:tags":[
        "establishment"
    ],
    "wof:name":"Idea Integration",
    "wof:placetype":"venue"
},
  "geometry": {"coordinates":[-104.998481,39.753782],"type":"Point"}
}