{
  "type": "Feature",
  "properties": {
    "addr:full":"15 N River St Rico CO 81323",
    "addr:housenumber":"15",
    "addr:postcode":"81323",
    "addr:street":"N River St",
    "iso:country":"US",
    "sg:address":"15 N River St",
    "sg:city":"Rico",
    "sg:classifiers":[
        {
            "category":"Recreation",
            "type":"Entertainment"
        }
    ],
    "sg:phone":"+1 970 967 2635",
    "sg:postcode":"81323",
    "sg:province":"CO",
    "sg:tags":[
        "instruction",
        "yoga"
    ],
    "wof:name":"Deva Yoga",
    "wof:placetype":"venue"
},
  "geometry": {"coordinates":[-108.032304,37.694209],"type":"Point"}
}