{
  "type": "Feature",
  "properties": {
    "addr:full":"4001 Holly St Denver CO 80207",
    "addr:housenumber":"4001",
    "addr:postcode":"80207",
    "addr:street":"Holly St",
    "iso:country":"US",
    "sg:address":"4001 Holly St",
    "sg:city":"Denver",
    "sg:classifiers":[
        {
            "category":"Building & Trades",
            "subcategory":"Equipment Rental",
            "type":"Services"
        },
        {
            "category":"Professional",
            "subcategory":"Advertising",
            "type":"Services"
        }
    ],
    "sg:phone":"+1 303 322 1915",
    "sg:postcode":"80207",
    "sg:province":"CO",
    "sg:tags":[
        "crane",
        "outdoor"
    ],
    "wof:name":"C Behrend Corp",
    "wof:placetype":"venue"
},
  "geometry": {"coordinates":[-104.92238999999999,39.773162],"type":"Point"}
}