{
  "type": "Feature",
  "properties": {
    "iso:country":"US",
    "sg:address":"2195 N Hwy 83",
    "sg:city":"Franktown",
    "sg:classifiers":[
        {
            "category":"Banks & Credit Unions",
            "subcategory":"Bank",
            "type":"Services"
        }
    ],
    "sg:phone":"+1 303 805 5389",
    "sg:postcode":"80116",
    "sg:province":"CO",
    "wof:name":"Wells Fargo Bank",
    "wof:placetype":"venue"
},
  "geometry": {"coordinates":[-104.753378,39.392497],"type":"Point"}
}