{
  "type": "Feature",
  "properties": {
    "addr:full":"157 Adams St Monte Vista CO 81144",
    "addr:housenumber":"157",
    "addr:postcode":"81144",
    "addr:street":"Adams St",
    "iso:country":"US",
    "sg:address":"157 Adams St",
    "sg:city":"Monte Vista",
    "sg:classifiers":[
        {
            "category":"Shopping",
            "subcategory":"Computers & Home Electronics",
            "type":"Retail Goods"
        }
    ],
    "sg:phone":"+1 719 852 3512",
    "sg:postcode":"81144",
    "sg:province":"CO",
    "sg:tags":[
        "software"
    ],
    "wof:name":"Southern Colorado Cmpt Svcs",
    "wof:placetype":"venue"
},
  "geometry": {"coordinates":[-106.146789,37.579759],"type":"Point"}
}