{
  "type": "Feature",
  "properties": {
    "addr:full":"1728 Grove St Boulder CO 80302",
    "addr:housenumber":"1728",
    "addr:postcode":"80302",
    "addr:street":"Grove St",
    "iso:country":"US",
    "sg:address":"1728 Grove St",
    "sg:city":"Boulder",
    "sg:classifiers":[
        {
            "category":"Food & Beverages",
            "subcategory":"Specialty",
            "type":"Retail Goods"
        }
    ],
    "sg:phone":"+1 303 444 9448",
    "sg:postcode":"80302",
    "sg:province":"CO",
    "sg:tags":[
        "health",
        "diet"
    ],
    "wof:name":"Nature's Sunshine Products",
    "wof:placetype":"venue"
},
  "geometry": {"coordinates":[-105.271854,40.015336],"type":"Point"}
}