{
  "type": "Feature",
  "properties": {
    "iso:country":"US",
    "sg:address":"311 S Victoria Ave",
    "sg:city":"Pueblo",
    "sg:classifiers":[
        {
            "category":"Personal",
            "type":"Services"
        }
    ],
    "sg:phone":"+1 719 583 1976",
    "sg:postcode":"81003",
    "sg:province":"CO",
    "wof:name":"Tanned Banana Studio",
    "wof:placetype":"venue"
},
  "geometry": {"coordinates":[-104.61683499999999,38.263368],"type":"Point"}
}