{
  "type": "Feature",
  "properties": {
    "addr:full":"2625 Walnut St Denver CO 80205",
    "addr:housenumber":"2625",
    "addr:postcode":"80205",
    "addr:street":"Walnut St",
    "iso:country":"US",
    "sg:address":"2625 Walnut St",
    "sg:city":"Denver",
    "sg:classifiers":[
        {
            "category":"Real Estate",
            "subcategory":"Architect",
            "type":"Services"
        }
    ],
    "sg:phone":"+1 303 296 2122",
    "sg:postcode":"80205",
    "sg:province":"CO",
    "wof:name":"Harrier House Architectural",
    "wof:placetype":"venue"
},
  "geometry": {"coordinates":[-104.985343,39.759981],"type":"Point"}
}