{
  "type": "Feature",
  "properties": {
    "iso:country":"US",
    "sg:address":"750 W Hampden Ave",
    "sg:city":"Englewood",
    "sg:classifiers":[
        {
            "category":"Professional",
            "subcategory":"Computer Services",
            "type":"Services"
        }
    ],
    "sg:phone":"+1 303 783 8888",
    "sg:postcode":"80110",
    "sg:province":"CO",
    "sg:tags":[
        "datum",
        "solution",
        "business",
        "spatial"
    ],
    "wof:name":"Q C Data Inc",
    "wof:placetype":"venue"
},
  "geometry": {"coordinates":[-104.99656299999999,39.653135],"type":"Point"}
}