{
  "type": "Feature",
  "properties": {
    "iso:country":"US",
    "sg:address":"400 S 3rd St",
    "sg:city":"Montrose",
    "sg:phone":"+1 970 249 8707",
    "sg:postcode":"81401",
    "sg:province":"CO",
    "sg:tags":[
        "irrigation",
        "system"
    ],
    "wof:name":"Bostwick Park Wtr Conservancy",
    "wof:placetype":"venue"
},
  "geometry": {"coordinates":[-107.87307300000001,38.477913],"type":"Point"}
}