{
  "type": "Feature",
  "properties": {
    "iso:country":"US",
    "sg:address":"532 Stewart Ave",
    "sg:city":"De Beque",
    "sg:classifiers":[
        {
            "category":"Food & Beverages",
            "subcategory":"Meat & Fish",
            "type":"Retail Goods"
        }
    ],
    "sg:phone":"+1 970 283 8632",
    "sg:postcode":"81630",
    "sg:province":"CO",
    "wof:name":"Rustler Brand Meats",
    "wof:placetype":"venue"
},
  "geometry": {"coordinates":[-108.212506,39.334978],"type":"Point"}
}