{
  "type": "Feature",
  "properties": {
    "iso:country":"US",
    "sg:address":"2120 S College Ave",
    "sg:city":"Fort Collins",
    "sg:classifiers":[
        {
            "category":"Professional",
            "subcategory":"Computer Services",
            "type":"Services"
        }
    ],
    "sg:phone":"+1 970 266 4620",
    "sg:postcode":"80525",
    "sg:province":"CO",
    "sg:tags":[
        "security",
        "network"
    ],
    "wof:name":"Tactical Security Solutions",
    "wof:placetype":"venue"
},
  "geometry": {"coordinates":[-105.07687799999999,40.559634],"type":"Point"}
}