{
  "type": "Feature",
  "properties": {
    "addr:full":"511 W 18th St Pueblo CO 81003",
    "addr:housenumber":"511",
    "addr:postcode":"81003",
    "addr:street":"W 18Th St",
    "iso:country":"US",
    "sg:address":"511 W 18th St",
    "sg:city":"Pueblo",
    "sg:classifiers":[
        {
            "category":"Health Services",
            "subcategory":"Doctor",
            "type":"Services"
        }
    ],
    "sg:phone":"+1 719 584 4017",
    "sg:postcode":"81003",
    "sg:province":"CO",
    "sg:tags":[
        "physician",
        "surgeon"
    ],
    "wof:name":"Pueblo Anesthesists Assoc",
    "wof:placetype":"venue"
},
  "geometry": {"coordinates":[-104.614716,38.283578],"type":"Point"}
}