{
  "type": "Feature",
  "properties": {
    "addr:full":"9195 W Progress Pl Littleton CO 80123",
    "addr:housenumber":"9195",
    "addr:postcode":"80123",
    "addr:street":"W Progress Pl",
    "iso:country":"US",
    "sg:address":"9195 W Progress Pl",
    "sg:city":"Littleton",
    "sg:classifiers":[
        {
            "category":"Building & Trades",
            "subcategory":"Construction",
            "type":"Services"
        }
    ],
    "sg:phone":"+1 303 979 1241",
    "sg:postcode":"80123",
    "sg:province":"CO",
    "sg:tags":[
        "high",
        "home",
        "remodeling",
        "custom"
    ],
    "wof:name":"Bruin Ltd LLC",
    "wof:placetype":"venue"
},
  "geometry": {"coordinates":[-105.10123,39.621431],"type":"Point"}
}