{
  "type": "Feature",
  "properties": {
    "iso:country":"US",
    "sg:address":"5500 Central Ave",
    "sg:city":"Boulder",
    "sg:classifiers":[
        {
            "category":"Manufacturing",
            "subcategory":"Printing",
            "type":"Manufacturing & Wholesale Goods"
        }
    ],
    "sg:phone":"+1 303 444 3541",
    "sg:postcode":"80301",
    "sg:province":"CO",
    "sg:tags":[
        "publishes",
        "book"
    ],
    "sg:website":"www.westviewpress.com",
    "wof:name":"Westview Press",
    "wof:placetype":"venue"
},
  "geometry": {"coordinates":[-105.22284399999999,40.019724],"type":"Point"}
}