{
  "type": "Feature",
  "properties": {
    "iso:country":"US",
    "sg:address":"1250 S Inca Street",
    "sg:city":"Denver",
    "sg:classifiers":[
        {
            "category":"Retail",
            "subcategory":"Auto Repair",
            "type":"Services"
        }
    ],
    "sg:phone":"+1 303 698 2431",
    "sg:postcode":"80223",
    "sg:province":"CO",
    "wof:name":"Stu Ritter Mercedes-Benz Technician",
    "wof:placetype":"venue"
},
  "geometry": {"coordinates":[-104.998141,39.693972],"type":"Point"}
}