{
  "type": "Feature",
  "properties": {
    "iso:country":"US",
    "sg:address":"1005 N 12th St",
    "sg:city":"Grand Junction",
    "sg:classifiers":[
        {
            "category":"Organizations",
            "subcategory":"Non-profit Organization",
            "type":"Services"
        }
    ],
    "sg:phone":"+1 970 245 9649",
    "sg:postcode":"81501",
    "sg:province":"CO",
    "sg:tags":[
        "information",
        "alcoholism",
        "treatment"
    ],
    "wof:name":"Alcoholics Anonymous",
    "wof:placetype":"venue"
},
  "geometry": {"coordinates":[-108.552464,39.077349],"type":"Point"}
}