{
  "type": "Feature",
  "properties": {
    "iso:country":"US",
    "sg:address":"5484 White Pl",
    "sg:city":"Boulder",
    "sg:classifiers":[
        {
            "category":"Manufacturing",
            "subcategory":"Tools & Machinery",
            "type":"Manufacturing & Wholesale Goods"
        }
    ],
    "sg:phone":"+1 303 442 5083",
    "sg:postcode":"80303",
    "sg:province":"CO",
    "wof:name":"Analog Solutions",
    "wof:placetype":"venue"
},
  "geometry": {"coordinates":[-105.22554100000001,40.009482],"type":"Point"}
}