{
  "type": "Feature",
  "properties": {
    "iso:country":"US",
    "sg:address":"509 Main St",
    "sg:city":"Springfield",
    "sg:classifiers":[
        {
            "category":"Cinema",
            "subcategory":"Movie Rental",
            "type":"Entertainment"
        }
    ],
    "sg:phone":"+1 719 523 6300",
    "sg:postcode":"81073",
    "sg:province":"CO",
    "sg:tags":[
        "leasing",
        "video",
        "disc",
        "tape"
    ],
    "wof:name":"Movie Corral",
    "wof:placetype":"venue"
},
  "geometry": {"coordinates":[-102.61661700000001,37.409215],"type":"Point"}
}