{
  "type": "Feature",
  "properties": {
    "addr:full":"1222 Madison St Denver CO 80206",
    "addr:housenumber":"1222",
    "addr:postcode":"80206",
    "addr:street":"Madison St",
    "iso:country":"US",
    "sg:address":"1222 Madison St",
    "sg:city":"Denver",
    "sg:classifiers":[
        {
            "category":"Education",
            "subcategory":"Dance Studio",
            "type":"Public Place"
        }
    ],
    "sg:phone":"+1 303 905 9775",
    "sg:postcode":"80206",
    "sg:province":"CO",
    "sg:tags":[
        "instruction",
        "dancing"
    ],
    "wof:name":"Crescendo Dance",
    "wof:placetype":"venue"
},
  "geometry": {"coordinates":[-104.946101,39.736398],"type":"Point"}
}