{
  "type": "Feature",
  "properties": {
    "addr:full":"4175 Harlan St Wheat Ridge CO 80033",
    "addr:housenumber":"4175",
    "addr:postcode":"80033",
    "addr:street":"Harlan St",
    "iso:country":"US",
    "sg:address":"4175 Harlan St",
    "sg:city":"Wheat Ridge",
    "sg:classifiers":[
        {
            "category":"Building & Trades",
            "subcategory":"Construction",
            "type":"Services"
        },
        {
            "category":"Wholesale",
            "subcategory":"Home Furnishings",
            "type":"Manufacturing & Wholesale Goods"
        }
    ],
    "sg:phone":"+1 303 420 8116",
    "sg:postcode":"80033",
    "sg:province":"CO",
    "sg:tags":[
        "floor",
        "contractor",
        "laying",
        "rug",
        "carpet"
    ],
    "wof:name":"Amerifloor Inc",
    "wof:placetype":"venue"
},
  "geometry": {"coordinates":[-105.062696,39.773858],"type":"Point"}
}