{
  "type": "Feature",
  "properties": {
    "iso:country":"US",
    "sg:address":"128 N F St",
    "sg:city":"Salida",
    "sg:classifiers":[
        {
            "category":"Restaurant",
            "type":"Food & Drink"
        }
    ],
    "sg:phone":"+1 719 539 7919",
    "sg:postcode":"81201",
    "sg:province":"CO",
    "sg:tags":[
        "eating"
    ],
    "wof:name":"La Frontera",
    "wof:placetype":"venue"
},
  "geometry": {"coordinates":[-105.99160500000001,38.536521],"type":"Point"}
}