{
  "type": "Feature",
  "properties": {
    "addr:full":"13476 Elizabeth Way Denver CO 80241",
    "addr:housenumber":"13476",
    "addr:postcode":"80241",
    "addr:street":"Elizabeth Way",
    "iso:country":"US",
    "sg:address":"13476 Elizabeth Way",
    "sg:city":"Denver",
    "sg:classifiers":[
        {
            "category":"Insurance",
            "subcategory":"Insurance Agent",
            "type":"Services"
        }
    ],
    "sg:phone":"+1 303 450 1121",
    "sg:postcode":"80241",
    "sg:province":"CO",
    "wof:name":"Farmers Insurance Group",
    "wof:placetype":"venue"
},
  "geometry": {"coordinates":[-104.95404600000001,39.936813],"type":"Point"}
}