{
  "type": "Feature",
  "properties": {
    "iso:country":"US",
    "sg:address":"950 E 120th Ave",
    "sg:city":"Denver",
    "sg:classifiers":[
        {
            "category":"Restaurant",
            "type":"Food & Drink"
        }
    ],
    "sg:menulink":"http://www.allmenus.com/co/west-adams/206972-sonic/menu/",
    "sg:phone":"+1 303 457 3012",
    "sg:postcode":"80233",
    "sg:province":"CO",
    "sg:tags":[
        "burger",
        "american"
    ],
    "wof:name":"Sonic",
    "wof:placetype":"venue"
},
  "geometry": {"coordinates":[-104.97522499999999,39.913943],"type":"Point"}
}