{
  "type": "Feature",
  "properties": {
    "iso:country":"US",
    "sg:address":"1323 S Navajo St",
    "sg:city":"Denver",
    "sg:classifiers":[
        {
            "category":"Place Of Worship",
            "subcategory":"Church",
            "type":"Public Place"
        },
        {
            "category":"Place Of Worship",
            "type":"Public Place"
        },
        {
            "category":"Organizations",
            "subcategory":"Religious Organization",
            "type":"Services"
        }
    ],
    "sg:phone":"+1 303 595 9274",
    "sg:postcode":"80223",
    "sg:province":"CO",
    "sg:tags":[
        "churches-catholic-traditional",
        "churches-catholic"
    ],
    "wof:name":"Bread Of Life Cathedral Chu Rc",
    "wof:placetype":"venue"
},
  "geometry": {"coordinates":[-105.003893,39.693737],"type":"Point"}
}