{
  "type": "Feature",
  "properties": {
    "addr:full":"234 Light Hill Rd Snowmass CO 81654",
    "addr:housenumber":"234",
    "addr:postcode":"81654",
    "addr:street":"Light Hill Rd",
    "iso:country":"US",
    "sg:address":"234 Light Hill Rd",
    "sg:city":"Snowmass",
    "sg:classifiers":[
        {
            "category":"Real Estate",
            "subcategory":"Real Estate Agent",
            "type":"Services"
        }
    ],
    "sg:phone":"+1 970 927 4800",
    "sg:postcode":"81654",
    "sg:province":"CO",
    "wof:name":"Raczak Real Estate Company",
    "wof:placetype":"venue"
},
  "geometry": {"coordinates":[-106.99105,39.309323],"type":"Point"}
}