{
  "type": "Feature",
  "properties": {
    "addr:full":"618 Grand Ave Del Norte CO 81132",
    "addr:housenumber":"618",
    "addr:postcode":"norte;81132",
    "addr:street":"Grand Ave",
    "iso:country":"US",
    "sg:address":"618 Grand Ave",
    "sg:city":"Del Norte",
    "sg:classifiers":[
        {
            "category":"Personal",
            "subcategory":"Barber",
            "type":"Services"
        }
    ],
    "sg:phone":"+1 719 657 2717",
    "sg:postcode":"81132",
    "sg:province":"CO",
    "wof:name":"O M's Barber Shop",
    "wof:placetype":"venue"
},
  "geometry": {"coordinates":[-106.35441299999999,37.678934],"type":"Point"}
}