{
  "type": "Feature",
  "properties": {
    "addr:full":"700 S University Blvd Denver CO 80209",
    "addr:housenumber":"700",
    "addr:postcode":"80209",
    "addr:street":"S University Blvd",
    "iso:country":"US",
    "sg:address":"700 S University Blvd",
    "sg:city":"Denver",
    "sg:classifiers":[
        {
            "category":"Building & Trades",
            "subcategory":"Locksmith",
            "type":"Services"
        }
    ],
    "sg:phone":"+1 303 558 4455",
    "sg:postcode":"80209",
    "sg:province":"CO",
    "sg:tags":[
        "key"
    ],
    "wof:name":"A 24 Locksmith",
    "wof:placetype":"venue"
},
  "geometry": {"coordinates":[-104.95916200000001,39.703894],"type":"Point"}
}