{
  "type": "Feature",
  "properties": {
    "iso:country":"US",
    "sg:address":"621 E Grand Ave",
    "sg:city":"Fruita",
    "sg:classifiers":[
        {
            "category":"Building & Trades",
            "subcategory":"Plumbing",
            "type":"Services"
        }
    ],
    "sg:phone":"+1 970 858 8286",
    "sg:postcode":"81521",
    "sg:province":"CO",
    "sg:tags":[
        "conditioning",
        "air",
        "system",
        "contractor"
    ],
    "wof:name":"Air Flow Plumbing & Heating",
    "wof:placetype":"venue"
},
  "geometry": {"coordinates":[-108.727187,39.153558],"type":"Point"}
}