{
  "type": "Feature",
  "properties": {
    "iso:country":"US",
    "sg:address":"10841 S Crossroads Dr",
    "sg:city":"Parker",
    "sg:classifiers":[
        {
            "category":"Health Services",
            "subcategory":"Medical Lab",
            "type":"Services"
        }
    ],
    "sg:phone":"+1 303 840 0332",
    "sg:postcode":"80134",
    "sg:province":"CO",
    "sg:tags":[
        "laboratory"
    ],
    "wof:name":"Artistic Expressions Dental",
    "wof:placetype":"venue"
},
  "geometry": {"coordinates":[-104.76651099999999,39.520248],"type":"Point"}
}