{
  "type": "Feature",
  "properties": {
    "iso:country":"US",
    "sg:address":"302 M St",
    "sg:city":"Rock Springs",
    "sg:classifiers":[
        {
            "category":"Organizations",
            "subcategory":"Religious Organization",
            "type":"Services"
        }
    ],
    "sg:phone":"+1 307 362 2930",
    "sg:postcode":"82901",
    "sg:province":"CO",
    "sg:tags":[
        "church"
    ],
    "wof:name":"Holy Trinity Greek Orthodox",
    "wof:placetype":"venue"
},
  "geometry": {"coordinates":[-109.218681,41.5914],"type":"Point"}
}