{
  "type": "Feature",
  "properties": {
    "addr:full":"65429 Sunridge Ct Montrose CO 81401",
    "addr:housenumber":"65429",
    "addr:postcode":"81401",
    "addr:street":"Sunridge Ct",
    "iso:country":"US",
    "sg:address":"65429 Sunridge Ct",
    "sg:city":"Montrose",
    "sg:classifiers":[
        {
            "category":"Building & Trades",
            "subcategory":"Electrical",
            "type":"Services"
        }
    ],
    "sg:phone":"+1 970 252 8887",
    "sg:postcode":"81401",
    "sg:province":"CO",
    "sg:tags":[
        "electrical",
        "contractor"
    ],
    "wof:name":"Lefthand Electric Inc",
    "wof:placetype":"venue"
},
  "geometry": {"coordinates":[-107.863714,38.393845],"type":"Point"}
}