{
  "type": "Feature",
  "properties": {
    "iso:country":"US",
    "sg:address":"1821 E Harmony Rd",
    "sg:city":"Fort Collins",
    "sg:classifiers":[
        {
            "category":"Farming",
            "subcategory":"Dairy Farm",
            "type":"Manufacturing & Wholesale Goods"
        },
        {
            "category":"Ice Cream",
            "type":"Food & Drink"
        }
    ],
    "sg:menulink":"http://www.allmenus.com/co/fort-collins/184555-cold-stone-creamery/menu/",
    "sg:phone":"+1 970 204 1284",
    "sg:postcode":"80528",
    "sg:province":"CO",
    "sg:tags":[
        "smoothy",
        "juice",
        "american",
        "ice",
        "cream"
    ],
    "wof:name":"Cold Stone Creamery",
    "wof:placetype":"venue"
},
  "geometry": {"coordinates":[-105.04323100000001,40.523362],"type":"Point"}
}