{
  "type": "Feature",
  "properties": {
    "addr:full":"3120 Alkire St Golden CO 80401",
    "addr:housenumber":"3120",
    "addr:postcode":"80401",
    "addr:street":"Alkire St",
    "iso:country":"US",
    "sg:address":"3120 Alkire St",
    "sg:city":"Golden",
    "sg:classifiers":[
        {
            "category":"Building & Trades",
            "subcategory":"Construction",
            "type":"Services"
        }
    ],
    "sg:phone":"+1 303 278 2854",
    "sg:postcode":"80401",
    "sg:province":"CO",
    "sg:tags":[
        "contractor"
    ],
    "wof:name":"Peterson Roofing",
    "wof:placetype":"venue"
},
  "geometry": {"coordinates":[-105.147181,39.761519],"type":"Point"}
}