{
  "type": "Feature",
  "properties": {
    "iso:country":"US",
    "sg:address":"180 Glory View Dr",
    "sg:city":"Grand Junction",
    "sg:classifiers":[
        {
            "category":"Shopping",
            "type":"Retail Goods"
        }
    ],
    "sg:phone":"+1 970 242 3053",
    "sg:postcode":"81503",
    "sg:province":"CO",
    "sg:tags":[
        "merchandise"
    ],
    "wof:name":"Cellcomm",
    "wof:placetype":"venue"
},
  "geometry": {"coordinates":[-108.52684600000001,39.031454],"type":"Point"}
}