{
  "type": "Feature",
  "properties": {
    "addr:full":"1180 Sassafras Ln Broomfield CO 80020",
    "addr:housenumber":"1180",
    "addr:postcode":"80020",
    "addr:street":"Sassafras Ln",
    "iso:country":"US",
    "sg:address":"1180 Sassafras Ln",
    "sg:city":"Broomfield",
    "sg:classifiers":[
        {
            "category":"Banks & Credit Unions",
            "subcategory":"Financial Services",
            "type":"Services"
        }
    ],
    "sg:phone":"+1 303 466 3870",
    "sg:postcode":"80020",
    "sg:province":"CO",
    "sg:tags":[
        "investor"
    ],
    "wof:name":"Ctc Investments Corp",
    "wof:placetype":"venue"
},
  "geometry": {"coordinates":[-105.083564,39.931682],"type":"Point"}
}