{
  "type": "Feature",
  "properties": {
    "addr:full":"635 Flatiron Marketplace Dr Broomfield CO 80021",
    "addr:housenumber":"635",
    "addr:postcode":"80021",
    "addr:street":"Flatiron Marketplace Dr",
    "iso:country":"US",
    "sg:address":"635 Flatiron Marketplace Dr",
    "sg:city":"Broomfield",
    "sg:classifiers":[
        {
            "category":"Restaurant",
            "type":"Food & Drink"
        }
    ],
    "sg:phone":"+1 303 466 1683",
    "sg:postcode":"80021",
    "sg:province":"CO",
    "sg:tags":[
        "style",
        "mexican",
        "american",
        "family"
    ],
    "wof:name":"Wahoo's",
    "wof:placetype":"venue"
},
  "geometry": {"coordinates":[-105.12556499999999,39.929377],"type":"Point"}
}