{
  "type": "Feature",
  "properties": {
    "addr:full":"16839 W 15th Ave Golden CO 80401",
    "addr:housenumber":"16839",
    "addr:postcode":"80401",
    "addr:street":"W 15Th Ave",
    "iso:country":"US",
    "sg:address":"16839 W 15th Ave",
    "sg:city":"Golden",
    "sg:classifiers":[
        {
            "category":"Wholesale",
            "subcategory":"Sporting Goods",
            "type":"Manufacturing & Wholesale Goods"
        }
    ],
    "sg:phone":"+1 303 278 2780",
    "sg:postcode":"80401",
    "sg:province":"CO",
    "wof:name":"Accurate Golf LLC",
    "wof:placetype":"venue"
},
  "geometry": {"coordinates":[-105.18980500000001,39.740145],"type":"Point"}
}