{
  "type": "Feature",
  "properties": {
    "iso:country":"US",
    "sg:address":"1835 Steamboat Blvd",
    "sg:city":"Steamboat Spgs",
    "sg:classifiers":[
        {
            "category":"Recreation",
            "type":"Entertainment"
        }
    ],
    "sg:phone":"+1 970 879 1250",
    "sg:postcode":"80487",
    "sg:province":"CO",
    "sg:tags":[
        "equipment",
        "skiing"
    ],
    "sg:website":"www.christysports.com",
    "wof:name":"Christy Sports",
    "wof:placetype":"venue"
},
  "geometry": {"coordinates":[-106.81236699999999,40.46179],"type":"Point"}
}