{
  "type": "Feature",
  "properties": {
    "iso:country":"US",
    "sg:address":"535 Denver Ave",
    "sg:city":"Loveland",
    "sg:classifiers":[
        {
            "category":"Home & Garden",
            "subcategory":"Carpets & Floor Coverings",
            "type":"Retail Goods"
        }
    ],
    "sg:phone":"+1 970 667 5513",
    "sg:postcode":"80537",
    "sg:province":"CO",
    "sg:tags":[
        "dealer",
        "rug"
    ],
    "wof:name":"Mielke Brothers Floor Covering",
    "wof:placetype":"venue"
},
  "geometry": {"coordinates":[-105.04477900000001,40.396937],"type":"Point"}
}