{
  "type": "Feature",
  "properties": {
    "addr:full":"2448 F Rd Grand Junction CO 81505",
    "addr:housenumber":"2448",
    "addr:postcode":"81505",
    "addr:street":"F Rd",
    "iso:country":"US",
    "sg:address":"2448 F Rd",
    "sg:city":"Grand Junction",
    "sg:classifiers":[
        {
            "category":"Banks & Credit Unions",
            "subcategory":"Bank",
            "type":"Services"
        }
    ],
    "sg:phone":"+1 970 254 7503",
    "sg:postcode":"81505",
    "sg:province":"CO",
    "sg:tags":[
        "loan",
        "real estate"
    ],
    "wof:name":"Weststar Bank & Mortgage",
    "wof:placetype":"venue"
},
  "geometry": {"coordinates":[-108.602597,39.094794],"type":"Point"}
}