{
  "type": "Feature",
  "properties": {
    "addr:full":"1528 E Colfax Ave  Denver CO 80218",
    "addr:housenumber":"1528",
    "addr:postcode":"80218",
    "addr:street":"E Colfax Ave",
    "iso:country":"US",
    "sg:address":"1528 E Colfax Ave ",
    "sg:city":"Denver",
    "sg:classifiers":[
        {
            "category":"Restaurant",
            "type":"Food & Drink"
        }
    ],
    "sg:menulink":"http://www.allmenus.com/co/denver/293543-famous-pizza/menu/",
    "sg:phone":"+1 303 832 1200",
    "sg:postcode":"80218",
    "sg:province":"CO",
    "sg:tags":[
        "pizza"
    ],
    "wof:name":"FAMOUS PIZZA",
    "wof:placetype":"venue"
},
  "geometry": {"coordinates":[-104.96887700000001,39.739906],"type":"Point"}
}