{
  "type": "Feature",
  "properties": {
    "iso:country":"US",
    "sg:address":"620 Arrawanna St",
    "sg:city":"Colorado Springs",
    "sg:classifiers":[
        {
            "category":"Building & Trades",
            "subcategory":"Electrical",
            "type":"Services"
        }
    ],
    "sg:phone":"+1 719 667 1200",
    "sg:postcode":"80909",
    "sg:province":"CO",
    "sg:tags":[
        "electrical",
        "contractor"
    ],
    "wof:name":"C&D Electric Inc",
    "wof:placetype":"venue"
},
  "geometry": {"coordinates":[-104.771979,38.841973],"type":"Point"}
}