{
  "type": "Feature",
  "properties": {
    "iso:country":"US",
    "sg:address":"31459 Co Rd 23",
    "sg:city":"Greeley",
    "sg:classifiers":[
        {
            "category":"Building & Trades",
            "subcategory":"Landscaping Services",
            "type":"Services"
        }
    ],
    "sg:phone":"+1 970 674 0210",
    "sg:postcode":"80631",
    "sg:province":"CO",
    "sg:tags":[
        "lawn",
        "maintenance",
        "grounds"
    ],
    "wof:name":"D-Lawn Svc",
    "wof:placetype":"venue"
},
  "geometry": {"coordinates":[-104.851513,40.4548],"type":"Point"}
}