{
  "type": "Feature",
  "properties": {
    "iso:country":"US",
    "sg:address":"1710 W Eisenhower Blvd",
    "sg:city":"Loveland",
    "sg:classifiers":[
        {
            "category":"Shopping",
            "type":"Retail Goods"
        }
    ],
    "sg:phone":"+1 970 593 9254",
    "sg:postcode":"80537",
    "sg:province":"CO",
    "sg:tags":[
        "merchandise"
    ],
    "wof:name":"Aquatic Interiors",
    "wof:placetype":"venue"
},
  "geometry": {"coordinates":[-105.102947,40.407167],"type":"Point"}
}