{
  "type": "Feature",
  "properties": {
    "iso:country":"US",
    "sg:address":"8216 E Colfax Ave",
    "sg:city":"Denver",
    "sg:classifiers":[
        {
            "category":"Shopping",
            "subcategory":"Books",
            "type":"Retail Goods"
        }
    ],
    "sg:phone":"+1 303 320 9203",
    "sg:postcode":"80220",
    "sg:province":"CO",
    "sg:tags":[
        "bookstore"
    ],
    "wof:name":"Pleasures Adult Entertainment",
    "wof:placetype":"venue"
},
  "geometry": {"coordinates":[-104.892394,39.740088],"type":"Point"}
}