{
  "type": "Feature",
  "properties": {
    "iso:country":"US",
    "sg:address":"4094 E 131st Dr",
    "sg:city":"Denver",
    "sg:classifiers":[
        {
            "category":"Manufacturing",
            "subcategory":"Printing",
            "type":"Manufacturing & Wholesale Goods"
        }
    ],
    "sg:phone":"+1 303 920 1814",
    "sg:postcode":"80241",
    "sg:province":"CO",
    "sg:tags":[
        "publishing"
    ],
    "wof:name":"Promise Publishing Inc",
    "wof:placetype":"venue"
},
  "geometry": {"coordinates":[-104.938796,39.934884],"type":"Point"}
}