{
  "type": "Feature",
  "properties": {
    "addr:full":"5671 Tejon St Denver CO 80221",
    "addr:housenumber":"5671",
    "addr:postcode":"80221",
    "addr:street":"Tejon St",
    "iso:country":"US",
    "sg:address":"5671 Tejon St",
    "sg:city":"Denver",
    "sg:classifiers":[
        {
            "category":"Autos & Motor Vehicles",
            "subcategory":"Fuel & Gas Station",
            "type":"Retail Goods"
        }
    ],
    "sg:phone":"+1 303 455 1743",
    "sg:postcode":"80221",
    "sg:province":"CO",
    "sg:tags":[
        "convenience",
        "station",
        "store"
    ],
    "wof:name":"Rexoco Stores Ltd",
    "wof:placetype":"venue"
},
  "geometry": {"coordinates":[-105.01117000000001,39.799102],"type":"Point"}
}