{
  "type": "Feature",
  "properties": {
    "iso:country":"US",
    "sg:address":"1594 Walnut Dr",
    "sg:city":"Brighton",
    "sg:classifiers":[
        {
            "category":"Health Services",
            "subcategory":"Nursing And Care Facility",
            "type":"Services"
        }
    ],
    "sg:phone":"+1 303 659 8670",
    "sg:postcode":"80601",
    "sg:province":"CO",
    "sg:tags":[
        "skilled"
    ],
    "wof:name":"Glen At Brighton",
    "wof:placetype":"venue"
},
  "geometry": {"coordinates":[-104.802134,39.98865],"type":"Point"}
}