{
  "type": "Feature",
  "properties": {
    "addr:full":"530 Garfield Ave Loveland CO 80537",
    "addr:housenumber":"530",
    "addr:postcode":"80537",
    "addr:street":"Garfield Ave",
    "iso:country":"US",
    "sg:address":"530 Garfield Ave",
    "sg:city":"Loveland",
    "sg:classifiers":[
        {
            "category":"Home & Garden",
            "subcategory":"Garden Supply",
            "type":"Retail Goods"
        }
    ],
    "sg:phone":"+1 970 667 2932",
    "sg:postcode":"80537",
    "sg:province":"CO",
    "sg:tags":[
        "center",
        "equipment",
        "field",
        "seed",
        "greenhouse",
        "fertilizer"
    ],
    "wof:name":"Gateway Garden & Home Center",
    "wof:placetype":"venue"
},
  "geometry": {"coordinates":[-105.077843,40.397269],"type":"Point"}
}