{
  "type": "Feature",
  "properties": {
    "addr:full":"7825 Burgess Rd Colorado Springs CO 80908",
    "addr:housenumber":"7825",
    "addr:postcode":"80908",
    "addr:street":"Burgess Rd",
    "iso:country":"US",
    "sg:address":"7825 Burgess Rd",
    "sg:city":"Colorado Springs",
    "sg:classifiers":[
        {
            "category":"Retail",
            "subcategory":"Repair Shop",
            "type":"Services"
        }
    ],
    "sg:phone":"+1 719 495 2582",
    "sg:postcode":"80908",
    "sg:province":"CO",
    "sg:tags":[
        "furniture"
    ],
    "wof:name":"Furniture Medic",
    "wof:placetype":"venue"
},
  "geometry": {"coordinates":[-104.681487,38.998316],"type":"Point"}
}