{
  "type": "Feature",
  "properties": {
    "addr:full":"9400 E Iliff Ave Apt 414 Denver CO 80231",
    "addr:housenumber":"9400;414",
    "addr:postcode":"80231",
    "addr:street":"E Iliff Ave Apt",
    "iso:country":"US",
    "sg:address":"9400 E Iliff Ave Apt 414",
    "sg:city":"Denver",
    "sg:classifiers":[
        {
            "category":"Structure",
            "subcategory":"Office Building",
            "type":"Public Place"
        }
    ],
    "sg:phone":"+1 720 747 7652",
    "sg:postcode":"80231",
    "sg:province":"CO",
    "sg:tags":[
        "park"
    ],
    "wof:name":"Pdq Property Services",
    "wof:placetype":"venue"
},
  "geometry": {"coordinates":[-104.878868,39.674728],"type":"Point"}
}