{
  "type": "Feature",
  "properties": {
    "iso:country":"US",
    "sg:address":"3920 N Nevada Ave",
    "sg:city":"Colorado Springs",
    "sg:classifiers":[
        {
            "category":"Travel",
            "subcategory":"Hotels & Motels",
            "type":"Entertainment"
        }
    ],
    "sg:phone":"+1 719 598 4044",
    "sg:postcode":"80907",
    "sg:province":"CO",
    "wof:name":"Santa Fe Inn",
    "wof:placetype":"venue"
},
  "geometry": {"coordinates":[-104.819146,38.891447],"type":"Point"}
}