{
  "type": "Feature",
  "properties": {
    "iso:country":"US",
    "sg:address":"3205 W Floyd Ave",
    "sg:city":"Englewood",
    "sg:classifiers":[
        {
            "category":"Real Estate",
            "subcategory":"Real Estate Operator",
            "type":"Services"
        }
    ],
    "sg:phone":"+1 303 781 0952",
    "sg:postcode":"80236",
    "sg:province":"CO",
    "sg:tags":[
        "apartment",
        "complex"
    ],
    "sg:website":"www.foothillsapartments.com",
    "wof:name":"Foothills Apartments",
    "wof:placetype":"venue"
},
  "geometry": {"coordinates":[-105.02457200000001,39.656909],"type":"Point"}
}