{
  "type": "Feature",
  "properties": {
    "addr:full":"1460 S Cherokee St Denver CO 80223",
    "addr:housenumber":"1460",
    "addr:postcode":"80223",
    "addr:street":"S Cherokee St",
    "iso:country":"US",
    "sg:address":"1460 S Cherokee St",
    "sg:city":"Denver",
    "sg:classifiers":[
        {
            "category":"Restaurant",
            "type":"Food & Drink"
        }
    ],
    "sg:phone":"+1 303 534 7511",
    "sg:postcode":"80223",
    "sg:province":"CO",
    "sg:tags":[
        "cafeteria"
    ],
    "wof:name":"City & County-Denver Cafeteria",
    "wof:placetype":"venue"
},
  "geometry": {"coordinates":[-104.990959,39.690624],"type":"Point"}
}