{
  "type": "Feature",
  "properties": {
    "iso:country":"US",
    "sg:address":"1733 E Evans Avenue",
    "sg:city":"Denver",
    "sg:classifiers":[
        {
            "category":"Retail",
            "subcategory":"Laundry & Dry Cleaning",
            "type":"Services"
        }
    ],
    "sg:phone":"+1 303 871 8501",
    "sg:postcode":"80210",
    "sg:province":"CO",
    "wof:name":"Campus Cleaners",
    "wof:placetype":"venue"
},
  "geometry": {"coordinates":[-104.96672100000001,39.678597],"type":"Point"}
}