{
  "type": "Feature",
  "properties": {
    "addr:full":"6101 E 38th Ave Denver CO 80207",
    "addr:housenumber":"6101",
    "addr:postcode":"80207",
    "addr:street":"E 38Th Ave",
    "iso:country":"US",
    "sg:address":"6101 E 38th Ave",
    "sg:city":"Denver",
    "sg:classifiers":[
        {
            "category":"Health Services",
            "subcategory":"Clinic",
            "type":"Services"
        },
        {
            "category":"Health Services",
            "subcategory":"Nursing And Care Facility",
            "type":"Services"
        },
        {
            "category":"Health Services",
            "subcategory":"Hospital",
            "type":"Services"
        }
    ],
    "sg:phone":"+1 303 321 7127",
    "sg:postcode":"80207",
    "sg:province":"CO",
    "sg:tags":[
        "urgent",
        "medical",
        "emergency",
        "ambulance"
    ],
    "wof:name":"Evmars",
    "wof:placetype":"venue"
},
  "geometry": {"coordinates":[-104.917603,39.769249],"type":"Point"}
}