{
  "type": "Feature",
  "properties": {
    "iso:country":"US",
    "sg:address":"5632 W Geddes Pl",
    "sg:city":"Littleton",
    "sg:classifiers":[
        {
            "category":"Building & Trades",
            "subcategory":"Construction",
            "type":"Services"
        }
    ],
    "sg:phone":"+1 303 979 5412",
    "sg:postcode":"80128",
    "sg:province":"CO",
    "sg:tags":[
        "hanging",
        "contractor"
    ],
    "wof:name":"GM Decorating",
    "wof:placetype":"venue"
},
  "geometry": {"coordinates":[-105.060016,39.584822],"type":"Point"}
}