{
  "type": "Feature",
  "properties": {
    "iso:country":"US",
    "sg:address":"5325 E Colfax Ave",
    "sg:city":"Denver",
    "sg:classifiers":[
        {
            "category":"Food & Beverages",
            "subcategory":"Liquor & Beverages",
            "type":"Retail Goods"
        }
    ],
    "sg:phone":"+1 303 355 3134",
    "sg:postcode":"80220",
    "sg:province":"CO",
    "sg:tags":[
        "alcoholic"
    ],
    "wof:name":"Continental Liquor Co",
    "wof:placetype":"venue"
},
  "geometry": {"coordinates":[-104.924882,39.74022],"type":"Point"}
}