{
  "type": "Feature",
  "properties": {
    "iso:country":"US",
    "sg:address":"5000 W Colfax Ave",
    "sg:city":"Denver",
    "sg:classifiers":[
        {
            "category":"Autos & Motor Vehicles",
            "subcategory":"Automobile Sales",
            "type":"Retail Goods"
        }
    ],
    "sg:phone":"+1 303 623 3337",
    "sg:postcode":"80204",
    "sg:province":"CO",
    "sg:tags":[
        "used"
    ],
    "wof:name":"El Dorado Auto Sales",
    "wof:placetype":"venue"
},
  "geometry": {"coordinates":[-105.05207299999999,39.740356],"type":"Point"}
}