{
  "type": "Feature",
  "properties": {
    "addr:full":"1206 W Tomichi Ave Gunnison CO 81230",
    "addr:housenumber":"1206",
    "addr:postcode":"81230",
    "addr:street":"W Tomichi Ave",
    "iso:country":"US",
    "sg:address":"1206 W Tomichi Ave",
    "sg:city":"Gunnison",
    "sg:classifiers":[
        {
            "category":"Building & Trades",
            "subcategory":"Plumbing",
            "type":"Services"
        }
    ],
    "sg:phone":"+1 719 240 6469",
    "sg:postcode":"81230",
    "sg:province":"CO",
    "sg:tags":[
        "plumbing",
        "water",
        "heating"
    ],
    "wof:name":"Artesian Plumbing & Hydronics",
    "wof:placetype":"venue"
},
  "geometry": {"coordinates":[-106.941444,38.544222],"type":"Point"}
}