{
  "type": "Feature",
  "properties": {
    "addr:full":"1101 S Tennyson St Denver CO 80219",
    "addr:housenumber":"1101",
    "addr:postcode":"80219",
    "addr:street":"S Tennyson St",
    "iso:country":"US",
    "sg:address":"1101 S Tennyson St",
    "sg:city":"Denver",
    "sg:classifiers":[
        {
            "category":"Retail",
            "subcategory":"Repair Shop",
            "type":"Services"
        }
    ],
    "sg:phone":"+1 303 934 1376",
    "sg:postcode":"80219",
    "sg:province":"CO",
    "sg:tags":[
        "electrical"
    ],
    "wof:name":"Allens Appliances",
    "wof:placetype":"venue"
},
  "geometry": {"coordinates":[-105.04373,39.694942],"type":"Point"}
}