{
  "type": "Feature",
  "properties": {
    "addr:full":"1696 E Evans Ave Denver CO 80210",
    "addr:housenumber":"1696",
    "addr:postcode":"80210",
    "addr:street":"E Evans Ave",
    "iso:country":"US",
    "sg:address":"1696 E Evans Ave",
    "sg:city":"Denver",
    "sg:classifiers":[
        {
            "category":"Home & Garden",
            "subcategory":"Building Materials",
            "type":"Retail Goods"
        }
    ],
    "sg:phone":"+1 303 777 0182",
    "sg:postcode":"80210",
    "sg:province":"CO",
    "wof:name":"Home Clearance Center Inc",
    "wof:placetype":"venue"
},
  "geometry": {"coordinates":[-104.968676,39.678413],"type":"Point"}
}