{
  "type": "Feature",
  "properties": {
    "iso:country":"US",
    "sg:address":"53580 Co Rd 46",
    "sg:city":"Arriba",
    "sg:phone":"+1 719 768 3429",
    "sg:postcode":"80804",
    "sg:province":"CO",
    "sg:tags":[
        "farm",
        "wheat"
    ],
    "wof:name":"Jim Smithburg",
    "wof:placetype":"venue"
},
  "geometry": {"coordinates":[-103.21142,39.281664],"type":"Point"}
}