{
  "type": "Feature",
  "properties": {
    "iso:country":"US",
    "sg:address":"62919 Co Hwy 63",
    "sg:city":"Arriba",
    "sg:classifiers":[
        {
            "category":"Organizations",
            "subcategory":"Religious Organization",
            "type":"Services"
        }
    ],
    "sg:phone":"+1 719 768 3229",
    "sg:postcode":"80804",
    "sg:province":"CO",
    "sg:tags":[
        "clergy"
    ],
    "wof:name":"Bethel Church Parsonage",
    "wof:placetype":"venue"
},
  "geometry": {"coordinates":[-103.266817,39.404311],"type":"Point"}
}