{
  "type": "Feature",
  "properties": {
    "iso:country":"US",
    "sg:address":"29770 Denali Ln",
    "sg:city":"Evergreen",
    "sg:classifiers":[
        {
            "category":"Shopping",
            "type":"Retail Goods"
        }
    ],
    "sg:phone":"+1 303 670 8934",
    "sg:postcode":"80439",
    "sg:province":"CO",
    "sg:tags":[
        "merchandise"
    ],
    "wof:name":"Deborah Carlson",
    "wof:placetype":"venue"
},
  "geometry": {"coordinates":[-105.337988,39.674857],"type":"Point"}
}