{
  "type": "Feature",
  "properties": {
    "iso:country":"US",
    "sg:address":"943 Geneva St",
    "sg:city":"Aurora",
    "sg:classifiers":[
        {
            "category":"Building & Trades",
            "subcategory":"Construction",
            "type":"Services"
        }
    ],
    "sg:phone":"+1 303 340 3636",
    "sg:postcode":"80010",
    "sg:province":"CO",
    "sg:tags":[
        "siding",
        "contractor"
    ],
    "wof:name":"O'Neil Siding & Windows",
    "wof:placetype":"venue"
},
  "geometry": {"coordinates":[-104.868337,39.729732],"type":"Point"}
}