{
  "type": "Feature",
  "properties": {
    "iso:country":"US",
    "sg:address":"1200 Bannock St",
    "sg:city":"Denver",
    "sg:classifiers":[
        {
            "category":"Building & Trades",
            "subcategory":"Landscaping Services",
            "type":"Services"
        }
    ],
    "sg:phone":"+1 303 571 0053",
    "sg:postcode":"80204",
    "sg:province":"CO",
    "sg:tags":[
        "designer",
        "landscape"
    ],
    "sg:website":"www.civitasinc.com",
    "wof:name":"Civitas",
    "wof:placetype":"venue"
},
  "geometry": {"coordinates":[-104.99024300000001,39.736851],"type":"Point"}
}