{
  "type": "Feature",
  "properties": {
    "addr:full":"12512 Arapahoe Rd Lafayette CO 80026",
    "addr:housenumber":"12512",
    "addr:postcode":"80026",
    "addr:street":"Arapahoe Rd",
    "iso:country":"US",
    "sg:address":"12512 Arapahoe Rd",
    "sg:city":"Lafayette",
    "sg:classifiers":[
        {
            "category":"Building & Trades",
            "subcategory":"Plumbing",
            "type":"Services"
        }
    ],
    "sg:phone":"+1 303 665 2140",
    "sg:postcode":"80026",
    "sg:province":"CO",
    "sg:tags":[
        "contractor"
    ],
    "wof:name":"Powell Plumbing",
    "wof:placetype":"venue"
},
  "geometry": {"coordinates":[-105.058458,40.014699],"type":"Point"}
}