{
  "type": "Feature",
  "properties": {
    "iso:country":"US",
    "sg:address":"310 Park Ave",
    "sg:city":"Kremmling",
    "sg:classifiers":[
        {
            "category":"Restaurant",
            "type":"Food & Drink"
        }
    ],
    "sg:phone":"+1 970 724 9578",
    "sg:postcode":"80459",
    "sg:province":"CO",
    "wof:name":"Subway Sandwiches & Salads",
    "wof:placetype":"venue"
},
  "geometry": {"coordinates":[-106.39225999999999,40.058843],"type":"Point"}
}