{
  "type": "Feature",
  "properties": {
    "addr:full":"167 S Madison Ave Loveland CO 80537",
    "addr:housenumber":"167",
    "addr:postcode":"80537",
    "addr:street":"S Madison Ave",
    "iso:country":"US",
    "sg:address":"167 S Madison Ave",
    "sg:city":"Loveland",
    "sg:classifiers":[
        {
            "category":"Professional",
            "type":"Services"
        }
    ],
    "sg:phone":"+1 970 461 8265",
    "sg:postcode":"80537",
    "sg:province":"CO",
    "wof:name":"High Country",
    "wof:placetype":"venue"
},
  "geometry": {"coordinates":[-105.058966,40.390502],"type":"Point"}
}