{
  "type": "Feature",
  "properties": {
    "addr:full":"14560 Co Rd 30 Weston CO 81091",
    "addr:housenumber":"14560;30",
    "addr:postcode":"81091",
    "addr:street":"Co Rd",
    "iso:country":"US",
    "sg:address":"14560 Co Rd 30",
    "sg:city":"Weston",
    "sg:classifiers":[
        {
            "category":"Building & Trades",
            "subcategory":"Landscaping Services",
            "type":"Services"
        }
    ],
    "sg:phone":"+1 719 859 0574",
    "sg:postcode":"81091",
    "sg:province":"CO",
    "wof:name":"Western Rain Sprinkler Systems",
    "wof:placetype":"venue"
},
  "geometry": {"coordinates":[-104.803878,37.199675],"type":"Point"}
}