{
  "type": "Feature",
  "properties": {
    "addr:full":"301 E Grand Ave Mancos CO 81328",
    "addr:housenumber":"301",
    "addr:postcode":"81328",
    "addr:street":"E Grand Ave",
    "iso:country":"US",
    "sg:address":"301 E Grand Ave",
    "sg:city":"Mancos",
    "sg:classifiers":[
        {
            "category":"Education",
            "subcategory":"School",
            "type":"Public Place"
        }
    ],
    "sg:phone":"+1 970 533 7744",
    "sg:postcode":"81328",
    "sg:province":"CO",
    "sg:tags":[
        "elementary"
    ],
    "wof:name":"Mancos Elementary School",
    "wof:placetype":"venue"
},
  "geometry": {"coordinates":[-108.293086,37.345074],"type":"Point"}
}