{
  "type": "Feature",
  "properties": {
    "iso:country":"US",
    "sg:address":"360 Lincoln St",
    "sg:city":"Canon City",
    "sg:classifiers":[
        {
            "category":"Building & Trades",
            "subcategory":"Construction",
            "type":"Services"
        }
    ],
    "sg:phone":"+1 719 269 8479",
    "sg:postcode":"81212",
    "sg:province":"CO",
    "sg:tags":[
        "concrete",
        "contractor"
    ],
    "wof:name":"Handeland Concrete",
    "wof:placetype":"venue"
},
  "geometry": {"coordinates":[-105.18557699999999,38.437237],"type":"Point"}
}