{
  "type": "Feature",
  "properties": {
    "iso:country":"US",
    "sg:address":"11685 E 53rd Ave",
    "sg:city":"Denver",
    "sg:classifiers":[
        {
            "category":"Wholesale",
            "subcategory":"Electrical",
            "type":"Manufacturing & Wholesale Goods"
        }
    ],
    "sg:phone":"+1 303 307 1900",
    "sg:postcode":"80239",
    "sg:province":"CO",
    "sg:tags":[
        "generator"
    ],
    "wof:name":"General Compressed Air Inc",
    "wof:placetype":"venue"
},
  "geometry": {"coordinates":[-104.856641,39.793185],"type":"Point"}
}