{
  "type": "Feature",
  "properties": {
    "iso:country":"US",
    "sg:address":"1488 Co Rd 10 S",
    "sg:city":"Alamosa",
    "sg:classifiers":[
        {
            "category":"Wholesale",
            "subcategory":"Farm Supplies",
            "type":"Manufacturing & Wholesale Goods"
        }
    ],
    "sg:phone":"+1 719 589 4000",
    "sg:postcode":"81101",
    "sg:province":"CO",
    "sg:tags":[
        "livestock"
    ],
    "wof:name":"Wilbur Wiescamp Livestock",
    "wof:placetype":"venue"
},
  "geometry": {"coordinates":[-106.002713,37.429692],"type":"Point"}
}