{
  "type": "Feature",
  "properties": {
    "iso:country":"US",
    "sg:address":"2941 20th St",
    "sg:city":"Boulder",
    "sg:classifiers":[
        {
            "category":"Professional",
            "subcategory":"Management & Consulting",
            "type":"Services"
        }
    ],
    "sg:phone":"+1 303 443 8094",
    "sg:postcode":"80304",
    "sg:province":"CO",
    "sg:tags":[
        "consultant"
    ],
    "wof:name":"Land Stewardship Consulting",
    "wof:placetype":"venue"
},
  "geometry": {"coordinates":[-105.271693,40.028246],"type":"Point"}
}