{
  "type": "Feature",
  "properties": {
    "iso:country":"US",
    "sg:address":"1100 Nickel Dr",
    "sg:city":"Loveland",
    "sg:classifiers":[
        {
            "category":"Home & Garden",
            "subcategory":"Building Materials",
            "type":"Retail Goods"
        }
    ],
    "sg:phone":"+1 970 461 9406",
    "sg:postcode":"80537",
    "sg:province":"CO",
    "sg:website":"www.homedepot.com",
    "wof:name":"Home Depot",
    "wof:placetype":"venue"
},
  "geometry": {"coordinates":[-105.05999300000001,40.405646],"type":"Point"}
}