{
  "type": "Feature",
  "properties": {
    "addr:full":"22370 E Lake Ln Centennial CO 80015",
    "addr:housenumber":"22370",
    "addr:postcode":"80015",
    "addr:street":"E Lake Ln",
    "iso:country":"US",
    "sg:address":"22370 E Lake Ln",
    "sg:city":"Centennial",
    "sg:classifiers":[
        {
            "category":"Freight",
            "type":"Transportation"
        }
    ],
    "sg:phone":"+1 303 680 1563",
    "sg:postcode":"80015",
    "sg:province":"CO",
    "sg:tags":[
        "trucking"
    ],
    "wof:name":"Berest Trucking Inc",
    "wof:placetype":"venue"
},
  "geometry": {"coordinates":[-104.728987,39.607426],"type":"Point"}
}