{
  "type": "Feature",
  "properties": {
    "addr:full":"9575 N Motsenbocker Rd Parker CO 80134",
    "addr:housenumber":"9575",
    "addr:postcode":"80134",
    "addr:street":"N Motsenbocker Rd",
    "iso:country":"US",
    "sg:address":"9575 N Motsenbocker Rd",
    "sg:city":"Parker",
    "sg:classifiers":[
        {
            "category":"Freight",
            "type":"Transportation"
        }
    ],
    "sg:phone":"+1 303 905 6666",
    "sg:postcode":"80134",
    "sg:province":"CO",
    "sg:tags":[
        "recreational",
        "vehicle"
    ],
    "wof:name":"Outdoor Storage",
    "wof:placetype":"venue"
},
  "geometry": {"coordinates":[-104.778454,39.507289],"type":"Point"}
}