{
  "type": "Feature",
  "properties": {
    "iso:country":"US",
    "sg:address":"1082 Havana St",
    "sg:city":"Aurora",
    "sg:classifiers":[
        {
            "category":"Manufacturing",
            "subcategory":"Printing",
            "type":"Manufacturing & Wholesale Goods"
        }
    ],
    "sg:phone":"+1 303 364 4200",
    "sg:postcode":"80010",
    "sg:province":"CO",
    "sg:tags":[
        "printer"
    ],
    "wof:name":"Econocopy Printing Ctr",
    "wof:placetype":"venue"
},
  "geometry": {"coordinates":[-104.865792,39.73134],"type":"Point"}
}