{
  "type": "Feature",
  "properties": {
    "iso:country":"US",
    "sg:address":"7458 Taft St",
    "sg:city":"Arvada",
    "sg:classifiers":[
        {
            "category":"Real Estate",
            "subcategory":"Real Estate Operator",
            "type":"Services"
        }
    ],
    "sg:phone":"+1 303 423 8789",
    "sg:postcode":"80005",
    "sg:province":"CO",
    "sg:tags":[
        "building",
        "nonresidential"
    ],
    "wof:name":"Liberty Properties LLC",
    "wof:placetype":"venue"
},
  "geometry": {"coordinates":[-105.13261300000001,39.832386],"type":"Point"}
}