{
  "type": "Feature",
  "properties": {
    "iso:country":"US",
    "sg:address":"6694 State Hwy 2",
    "sg:city":"Commerce City",
    "sg:classifiers":[
        {
            "category":"Real Estate",
            "subcategory":"Developer",
            "type":"Services"
        }
    ],
    "sg:phone":"+1 303 288 1413",
    "sg:postcode":"80022",
    "sg:province":"CO",
    "sg:tags":[
        "mobile",
        "home"
    ],
    "wof:name":"Lincoln Motel & Mobile Home Pk",
    "wof:placetype":"venue"
},
  "geometry": {"coordinates":[-104.928004,39.816338],"type":"Point"}
}