{
  "type": "Feature",
  "properties": {
    "addr:full":"541 Lincoln Ave Louisville CO 80027",
    "addr:housenumber":"541",
    "addr:postcode":"80027",
    "addr:street":"Lincoln Ave",
    "iso:country":"US",
    "sg:address":"541 Lincoln Ave",
    "sg:city":"Louisville",
    "sg:classifiers":[
        {
            "category":"Communications",
            "type":"Services"
        }
    ],
    "sg:phone":"+1 303 926 6948",
    "sg:postcode":"80027",
    "sg:province":"CO",
    "sg:tags":[
        "communication"
    ],
    "wof:name":"Bob Walter Communications",
    "wof:placetype":"venue"
},
  "geometry": {"coordinates":[-105.136956,39.975837],"type":"Point"}
}