{
  "type": "Feature",
  "properties": {
    "addr:full":"2504 Alteza Pl Colorado Springs CO 80917",
    "addr:housenumber":"2504",
    "addr:postcode":"80917",
    "addr:street":"Alteza Pl",
    "iso:country":"US",
    "sg:address":"2504 Alteza Pl",
    "sg:city":"Colorado Springs",
    "sg:classifiers":[
        {
            "category":"Restaurant",
            "type":"Food & Drink"
        }
    ],
    "sg:phone":"+1 719 570 0040",
    "sg:postcode":"80917",
    "sg:province":"CO",
    "sg:tags":[
        "eating"
    ],
    "wof:name":"Java Express Rx Inc",
    "wof:placetype":"venue"
},
  "geometry": {"coordinates":[-104.732933,38.869021],"type":"Point"}
}