{
  "type": "Feature",
  "properties": {
    "addr:full":"2601 Sinton Rd Evergreen CO 80439",
    "addr:housenumber":"2601",
    "addr:postcode":"80439",
    "addr:street":"Sinton Rd",
    "iso:country":"US",
    "sg:address":"2601 Sinton Rd",
    "sg:city":"Evergreen",
    "sg:classifiers":[
        {
            "category":"Building & Trades",
            "subcategory":"Construction",
            "type":"Services"
        }
    ],
    "sg:phone":"+1 303 674 7761",
    "sg:postcode":"80439",
    "sg:province":"CO",
    "sg:tags":[
        "home",
        "improvement"
    ],
    "wof:name":"Cover All Repairs & Renovation",
    "wof:placetype":"venue"
},
  "geometry": {"coordinates":[-105.40327499999999,39.673055],"type":"Point"}
}