{
  "type": "Feature",
  "properties": {
    "iso:country":"US",
    "sg:address":"1714 Topaz Dr",
    "sg:city":"Loveland",
    "sg:classifiers":[
        {
            "category":"Shopping",
            "type":"Retail Goods"
        }
    ],
    "sg:phone":"+1 970 669 5536",
    "sg:postcode":"80537",
    "sg:province":"CO",
    "sg:tags":[
        "medical",
        "supply"
    ],
    "wof:name":"Loveland Medical Supply",
    "wof:placetype":"venue"
},
  "geometry": {"coordinates":[-105.051513,40.406596],"type":"Point"}
}