{
  "type": "Feature",
  "properties": {
    "addr:full":"2737 Mapleton Ave Boulder CO 80304",
    "addr:housenumber":"2737",
    "addr:postcode":"80304",
    "addr:street":"Mapleton Ave",
    "iso:country":"US",
    "sg:address":"2737 Mapleton Ave",
    "sg:city":"Boulder",
    "sg:classifiers":[
        {
            "category":"Real Estate",
            "subcategory":"Real Estate Agent",
            "type":"Services"
        }
    ],
    "sg:phone":"+1 303 442 0200",
    "sg:postcode":"80304",
    "sg:province":"CO",
    "sg:tags":[
        "building",
        "operator",
        "apartment"
    ],
    "wof:name":"Boardwalk Realty Inc",
    "wof:placetype":"venue"
},
  "geometry": {"coordinates":[-105.258729,40.025528],"type":"Point"}
}