{
  "type": "Feature",
  "properties": {
    "iso:country":"US",
    "sg:address":"2273 Stepping Stones Way",
    "sg:city":"Colorado Springs",
    "sg:classifiers":[
        {
            "category":"Building & Trades",
            "subcategory":"Construction",
            "type":"Services"
        }
    ],
    "sg:phone":"+1 719 636 1362",
    "sg:postcode":"80904",
    "sg:province":"CO",
    "sg:tags":[
        "home",
        "builder"
    ],
    "wof:name":"Harmony Homes",
    "wof:placetype":"venue"
},
  "geometry": {"coordinates":[-104.85383299999999,38.849605],"type":"Point"}
}