{
  "type": "Feature",
  "properties": {
    "iso:country":"US",
    "sg:address":"8811 E Hampden Ave",
    "sg:city":"Denver",
    "sg:classifiers":[
        {
            "category":"Building & Trades",
            "subcategory":"Construction",
            "type":"Services"
        }
    ],
    "sg:phone":"+1 303 696 1900",
    "sg:postcode":"80231",
    "sg:province":"CO",
    "sg:tags":[
        "management",
        "general",
        "contractor"
    ],
    "wof:name":"Schlegel Williams and Assoc",
    "wof:placetype":"venue"
},
  "geometry": {"coordinates":[-104.88503799999999,39.653143],"type":"Point"}
}