{
  "type": "Feature",
  "properties": {
    "addr:full":"2154 S Jason St Denver CO 80223",
    "addr:housenumber":"2154",
    "addr:postcode":"80223",
    "addr:street":"S Jason St",
    "iso:country":"US",
    "sg:address":"2154 S Jason St",
    "sg:city":"Denver",
    "sg:classifiers":[
        {
            "category":"Retail",
            "subcategory":"Repair Shop",
            "type":"Services"
        }
    ],
    "sg:phone":"+1 303 936 8036",
    "sg:postcode":"80223",
    "sg:province":"CO",
    "sg:tags":[
        "compressor"
    ],
    "wof:name":"Circle Service",
    "wof:placetype":"venue"
},
  "geometry": {"coordinates":[-104.999385,39.677674],"type":"Point"}
}