{
  "type": "Feature",
  "properties": {
    "iso:country":"US",
    "sg:address":"521 E Nichols Dr",
    "sg:city":"Littleton",
    "sg:classifiers":[
        {
            "category":"Real Estate",
            "subcategory":"Real Estate Agent",
            "type":"Services"
        }
    ],
    "sg:phone":"+1 303 797 2004",
    "sg:postcode":"80122",
    "sg:province":"CO",
    "wof:name":"Veljkovich Peter-Peter Realty",
    "wof:placetype":"venue"
},
  "geometry": {"coordinates":[-104.982463,39.569441],"type":"Point"}
}