{
  "type": "Feature",
  "properties": {
    "iso:country":"US",
    "sg:address":"6130 W 112th Pl",
    "sg:city":"Broomfield",
    "sg:classifiers":[
        {
            "category":"Professional",
            "type":"Services"
        }
    ],
    "sg:phone":"+1 303 469 3346",
    "sg:postcode":"80020",
    "sg:province":"CO",
    "wof:name":"Daniel M Lubben",
    "wof:placetype":"venue"
},
  "geometry": {"coordinates":[-105.0652,39.900317],"type":"Point"}
}