{
  "type": "Feature",
  "properties": {
    "addr:full":"949 Main Ave Durango CO 81301",
    "addr:housenumber":"949",
    "addr:postcode":"co 81301",
    "addr:street":"Main Ave",
    "iso:country":"US",
    "sg:address":"949 Main Ave",
    "sg:city":"Durango",
    "sg:classifiers":[
        {
            "category":"Organizations",
            "subcategory":"Membership Organization",
            "type":"Services"
        }
    ],
    "sg:phone":"+1 970 259 4621",
    "sg:postcode":"81301",
    "sg:province":"CO",
    "sg:tags":[
        "operator",
        "tour"
    ],
    "wof:name":"Ironhorse Bicycle Classic",
    "wof:placetype":"venue"
},
  "geometry": {"coordinates":[-107.880582,37.273966],"type":"Point"}
}