{
  "type": "Feature",
  "properties": {
    "addr:full":"518 Hwy 133 Carbondale CO 81623",
    "addr:housenumber":"518",
    "addr:postcode":"81623",
    "addr:street":"Hwy 133",
    "iso:country":"US",
    "sg:address":"518 Hwy 133",
    "sg:city":"Carbondale",
    "sg:classifiers":[
        {
            "category":"Personal",
            "subcategory":"Beauty Salon",
            "type":"Services"
        }
    ],
    "sg:phone":"+1 970 704 1800",
    "sg:postcode":"81623",
    "sg:province":"CO",
    "wof:name":"Arikikis Beauty Salon",
    "wof:placetype":"venue"
},
  "geometry": {"coordinates":[-107.22135299999999,39.408181],"type":"Point"}
}