{
  "type": "Feature",
  "properties": {
    "addr:full":"13321 E Iliff Ave Aurora CO 80014",
    "addr:housenumber":"13321",
    "addr:postcode":"80014",
    "addr:street":"E Iliff Ave",
    "iso:country":"US",
    "sg:address":"13321 E Iliff Ave",
    "sg:city":"Aurora",
    "sg:classifiers":[
        {
            "category":"Real Estate",
            "subcategory":"Real Estate Operator",
            "type":"Services"
        }
    ],
    "sg:phone":"+1 303 743 1400",
    "sg:postcode":"80014",
    "sg:province":"CO",
    "sg:tags":[
        "building",
        "apartment"
    ],
    "wof:name":"Country Club Villas LLC",
    "wof:placetype":"venue"
},
  "geometry": {"coordinates":[-104.83376199999999,39.675026],"type":"Point"}
}