{
  "type": "Feature",
  "properties": {
    "iso:country":"US",
    "sg:address":"9034 E Easter Pl",
    "sg:city":"Centennial",
    "sg:classifiers":[
        {
            "category":"Banks & Credit Unions",
            "subcategory":"Bank",
            "type":"Services"
        }
    ],
    "sg:phone":"+1 720 488 9192",
    "sg:postcode":"80112",
    "sg:province":"CO",
    "sg:tags":[
        "loan",
        "real estate"
    ],
    "wof:name":"Mike Conway",
    "wof:placetype":"venue"
},
  "geometry": {"coordinates":[-104.88425700000001,39.586873],"type":"Point"}
}