{
  "type": "Feature",
  "properties": {
    "addr:full":"909 Santa Fe Dr Denver CO 80204",
    "addr:housenumber":"909",
    "addr:postcode":"80204",
    "addr:street":"Santa Fe Dr",
    "iso:country":"US",
    "sg:address":"909 Santa Fe Dr",
    "sg:city":"Denver",
    "sg:classifiers":[
        {
            "category":"Organizations",
            "subcategory":"Non-profit Organization",
            "type":"Services"
        }
    ],
    "sg:phone":"+1 303 777 0797",
    "sg:postcode":"80204",
    "sg:province":"CO",
    "sg:tags":[
        "disability"
    ],
    "wof:name":"Very Special Arts Colorado",
    "wof:placetype":"venue"
},
  "geometry": {"coordinates":[-104.998722,39.731967],"type":"Point"}
}