{
  "type": "Feature",
  "properties": {
    "iso:country":"US",
    "sg:address":"2541 Platte Pl",
    "sg:city":"Colorado Springs",
    "sg:classifiers":[
        {
            "category":"Autos & Motor Vehicles",
            "subcategory":"Boat Sales",
            "type":"Retail Goods"
        }
    ],
    "sg:phone":"+1 719 471 9574",
    "sg:postcode":"80909",
    "sg:province":"CO",
    "sg:tags":[
        "dealer",
        "sales"
    ],
    "wof:name":"Acme Motorsports",
    "wof:placetype":"venue"
},
  "geometry": {"coordinates":[-104.779847,38.836667],"type":"Point"}
}