{
  "type": "Feature",
  "properties": {
    "addr:full":"7349 W Alaska Dr Lakewood CO 80226",
    "addr:housenumber":"7349",
    "addr:postcode":"80226",
    "addr:street":"W Alaska Dr",
    "iso:country":"US",
    "sg:address":"7349 W Alaska Dr",
    "sg:city":"Lakewood",
    "sg:classifiers":[
        {
            "category":"Shopping",
            "subcategory":"Department Store",
            "type":"Retail Goods"
        }
    ],
    "sg:phone":"+1 303 937 1400",
    "sg:postcode":"80226",
    "sg:province":"CO",
    "wof:name":"Sharper Image",
    "wof:placetype":"venue"
},
  "geometry": {"coordinates":[-105.079193,39.709284],"type":"Point"}
}