{
  "type": "Feature",
  "properties": {
    "iso:country":"US",
    "sg:address":"2 N Cascade Ave",
    "sg:city":"Colorado Springs",
    "sg:classifiers":[
        {
            "category":"Banks & Credit Unions",
            "subcategory":"Financial Services",
            "type":"Services"
        }
    ],
    "sg:phone":"+1 719 685 0600",
    "sg:postcode":"80903",
    "sg:province":"CO",
    "sg:tags":[
        "trust",
        "investment",
        "real estate"
    ],
    "wof:name":"Commonwealth",
    "wof:placetype":"venue"
},
  "geometry": {"coordinates":[-104.82514999999999,38.835369],"type":"Point"}
}