{
  "type": "Feature",
  "properties": {
    "addr:full":"2430 Broadway St Boulder CO 80304",
    "addr:housenumber":"2430",
    "addr:postcode":"80304",
    "addr:street":"Broadway St",
    "iso:country":"US",
    "sg:address":"2430 Broadway St",
    "sg:city":"Boulder",
    "sg:classifiers":[
        {
            "category":"Professional",
            "subcategory":"Accounting & Tax Preparation",
            "type":"Services"
        }
    ],
    "sg:phone":"+1 303 443 4034",
    "sg:postcode":"80304",
    "sg:province":"CO",
    "sg:tags":[
        "accountant"
    ],
    "wof:name":"Jane Evans Cornelius CPA",
    "wof:placetype":"venue"
},
  "geometry": {"coordinates":[-105.281592,40.022902],"type":"Point"}
}