{
  "type": "Feature",
  "properties": {
    "addr:full":"10620 W 12th Pl Denver CO 80215",
    "addr:housenumber":"10620",
    "addr:postcode":"80215",
    "addr:street":"W 12Th Pl",
    "iso:country":"US",
    "sg:address":"10620 W 12th Pl",
    "sg:city":"Denver",
    "sg:classifiers":[
        {
            "category":"Building & Trades",
            "subcategory":"Construction",
            "type":"Services"
        }
    ],
    "sg:phone":"+1 720 318 7365",
    "sg:postcode":"80215",
    "sg:province":"CO",
    "sg:tags":[
        "contractor"
    ],
    "wof:name":"Rocky Mountain Metal Roofing",
    "wof:placetype":"venue"
},
  "geometry": {"coordinates":[-105.118782,39.73581],"type":"Point"}
}