{
  "type": "Feature",
  "properties": {
    "iso:country":"US",
    "sg:address":"333 S Federal Blvd",
    "sg:city":"Denver",
    "sg:classifiers":[
        {
            "category":"Utilities",
            "subcategory":"Mobile Phone",
            "type":"Services"
        },
        {
            "category":"Shopping",
            "type":"Retail Goods"
        }
    ],
    "sg:phone":"+1 303 975 9286",
    "sg:postcode":"80219",
    "sg:province":"CO",
    "sg:tags":[
        "communication",
        "merchandise",
        "radiotelephone",
        "cellular",
        "telephone"
    ],
    "wof:name":"Millennium Trenz Inc",
    "wof:placetype":"venue"
},
  "geometry": {"coordinates":[-105.025166,39.709985],"type":"Point"}
}