{
  "type": "Feature",
  "properties": {
    "iso:country":"US",
    "sg:address":"4901 Nelson Rd",
    "sg:city":"Longmont",
    "sg:classifiers":[
        {
            "category":"Organizations",
            "subcategory":"Religious Organization",
            "type":"Services"
        }
    ],
    "sg:phone":"+1 303 485 5722",
    "sg:postcode":"80503",
    "sg:province":"CO",
    "sg:tags":[
        "church"
    ],
    "sg:website":"www.stvrainpc.com",
    "wof:name":"St Vrain Presbyterian Church",
    "wof:placetype":"venue"
},
  "geometry": {"coordinates":[-105.236532,40.153059],"type":"Point"}
}