{
  "type": "Feature",
  "properties": {
    "addr:full":"228 Garcia St Trinidad CO 81082",
    "addr:housenumber":"228",
    "addr:postcode":"81082",
    "addr:street":"Garcia St",
    "iso:country":"US",
    "sg:address":"228 Garcia St",
    "sg:city":"Trinidad",
    "sg:classifiers":[
        {
            "category":"Retail",
            "subcategory":"Repair Shop",
            "type":"Services"
        }
    ],
    "sg:phone":"+1 719 846 6211",
    "sg:postcode":"81082",
    "sg:province":"CO",
    "sg:tags":[
        "lock",
        "locksmith"
    ],
    "wof:name":"Patco Auto Lock-Out",
    "wof:placetype":"venue"
},
  "geometry": {"coordinates":[-104.50076300000001,37.142085],"type":"Point"}
}