{
  "type": "Feature",
  "properties": {
    "addr:full":"760 Gardenia St Golden CO 80401",
    "addr:housenumber":"760",
    "addr:postcode":"80401",
    "addr:street":"Gardenia St",
    "iso:country":"US",
    "sg:address":"760 Gardenia St",
    "sg:city":"Golden",
    "sg:classifiers":[
        {
            "category":"Government",
            "subcategory":"Fire Station",
            "type":"Public Place"
        }
    ],
    "sg:phone":"+1 303 278 9454",
    "sg:postcode":"80401",
    "sg:province":"CO",
    "sg:tags":[
        "protection",
        "engineer"
    ],
    "wof:name":"Advantage Fire Protection, Inc",
    "wof:placetype":"venue"
},
  "geometry": {"coordinates":[-105.161148,39.728767],"type":"Point"}
}