{
  "type": "Feature",
  "properties": {
    "iso:country":"US",
    "sg:address":"45000 Co Rd 38",
    "sg:city":"Otis",
    "sg:phone":"+1 970 848 2564",
    "sg:postcode":"80743",
    "sg:province":"CO",
    "sg:tags":[
        "farm",
        "corn"
    ],
    "wof:name":"Russell Zwirn",
    "wof:placetype":"venue"
},
  "geometry": {"coordinates":[-102.855966,40.119229],"type":"Point"}
}