{
  "type": "Feature",
  "properties": {
    "iso:country":"US",
    "sg:address":"2293 N Frontage Rd W",
    "sg:city":"Vail",
    "sg:classifiers":[
        {
            "category":"Autos & Motor Vehicles",
            "subcategory":"Fuel & Gas Station",
            "type":"Retail Goods"
        }
    ],
    "sg:phone":"+1 970 476 7399",
    "sg:postcode":"81657",
    "sg:province":"CO",
    "sg:tags":[
        "grocery",
        "station",
        "gasoline"
    ],
    "wof:name":"West Vail",
    "wof:placetype":"venue"
},
  "geometry": {"coordinates":[-106.421019,39.628396],"type":"Point"}
}