{
  "type": "Feature",
  "properties": {
    "iso:country":"US",
    "sg:address":"12695 E 39th Ave",
    "sg:city":"Denver",
    "sg:classifiers":[
        {
            "category":"Shopping",
            "subcategory":"Computers & Home Electronics",
            "type":"Retail Goods"
        }
    ],
    "sg:phone":"+1 720 374 0800",
    "sg:postcode":"80239",
    "sg:province":"CO",
    "sg:tags":[
        "equipment",
        "dealer"
    ],
    "wof:name":"Computer Group Inc",
    "wof:placetype":"venue"
},
  "geometry": {"coordinates":[-104.839094,39.771098],"type":"Point"}
}