{
  "type": "Feature",
  "properties": {
    "iso:country":"US",
    "sg:address":"2970 Washington St",
    "sg:city":"Boulder",
    "sg:classifiers":[
        {
            "category":"Professional",
            "subcategory":"Business Services",
            "type":"Services"
        }
    ],
    "sg:phone":"+1 303 449 9155",
    "sg:postcode":"80304",
    "sg:province":"CO",
    "wof:name":"Gettliffe Construction",
    "wof:placetype":"venue"
},
  "geometry": {"coordinates":[-105.27812400000001,40.029656],"type":"Point"}
}