{
  "type": "Feature",
  "properties": {
    "iso:country":"US",
    "sg:address":"19000 State Hwy 72",
    "sg:city":"Arvada",
    "sg:classifiers":[
        {
            "category":"Professional",
            "type":"Services"
        }
    ],
    "sg:phone":"+1 720 898 8200",
    "sg:postcode":"80007",
    "sg:province":"CO",
    "sg:tags":[
        "consultant",
        "geological"
    ],
    "sg:website":"www.gti-ticora.com",
    "wof:name":"Ticora Geosciences Inc",
    "wof:placetype":"venue"
},
  "geometry": {"coordinates":[-105.216832,39.863808],"type":"Point"}
}