{
  "type": "Feature",
  "properties": {
    "iso:country":"US",
    "sg:address":"16728 E Smoky Hill Rd",
    "sg:city":"Aurora",
    "sg:classifiers":[
        {
            "category":"Restaurant",
            "type":"Food & Drink"
        }
    ],
    "sg:phone":"+1 303 766 9343",
    "sg:postcode":"80015",
    "sg:province":"CO",
    "sg:tags":[
        "grill",
        "bar"
    ],
    "wof:name":"Goal Line Grill",
    "wof:placetype":"venue"
},
  "geometry": {"coordinates":[-104.794235,39.626954],"type":"Point"}
}