{
  "type": "Feature",
  "properties": {
    "addr:full":"6320 Dewsbury Dr Colorado Springs CO 80918",
    "addr:housenumber":"6320",
    "addr:postcode":"80918",
    "addr:street":"Dewsbury Dr",
    "iso:country":"US",
    "sg:address":"6320 Dewsbury Dr",
    "sg:city":"Colorado Springs",
    "sg:classifiers":[
        {
            "category":"Building & Trades",
            "subcategory":"Construction",
            "type":"Services"
        }
    ],
    "sg:phone":"+1 719 593 1254",
    "sg:postcode":"80918",
    "sg:province":"CO",
    "sg:tags":[
        "specializing",
        "int",
        "residential",
        "commercial",
        "contractor",
        "painter"
    ],
    "wof:name":"Ron Cornelius Painting Inc",
    "wof:placetype":"venue"
},
  "geometry": {"coordinates":[-104.809797,38.923381],"type":"Point"}
}