{
  "type": "Feature",
  "properties": {
    "iso:country":"US",
    "sg:address":"1838 Pine St",
    "sg:city":"Boulder",
    "sg:classifiers":[
        {
            "category":"Shopping",
            "subcategory":"Books",
            "type":"Retail Goods"
        }
    ],
    "sg:phone":"+1 303 444 1886",
    "sg:postcode":"80302",
    "sg:province":"CO",
    "wof:name":"Baksun Books",
    "wof:placetype":"venue"
},
  "geometry": {"coordinates":[-105.271869,40.021621],"type":"Point"}
}