{
  "type": "Feature",
  "properties": {
    "iso:country":"US",
    "sg:address":"102 W Ilex Ct",
    "sg:city":"Milliken",
    "sg:classifiers":[
        {
            "category":"Professional",
            "type":"Services"
        }
    ],
    "sg:phone":"+1 970 587 0818",
    "sg:postcode":"80543",
    "sg:province":"CO",
    "wof:name":"John Otero",
    "wof:placetype":"venue"
},
  "geometry": {"coordinates":[-104.86897399999999,40.324122],"type":"Point"}
}