{
  "type": "Feature",
  "properties": {
    "iso:country":"US",
    "sg:address":"342 7th Ave",
    "sg:city":"Ouray",
    "sg:classifiers":[
        {
            "category":"Professional",
            "subcategory":"Management & Consulting",
            "type":"Services"
        }
    ],
    "sg:phone":"+1 970 325 4600",
    "sg:postcode":"81427",
    "sg:province":"CO",
    "sg:tags":[
        "consultant",
        "mining"
    ],
    "wof:name":"Monadnock Mineral Svc",
    "wof:placetype":"venue"
},
  "geometry": {"coordinates":[-107.670903,38.023955],"type":"Point"}
}