{
  "type": "Feature",
  "properties": {
    "addr:full":"3200 N Chestnut St Colorado Springs CO 80907",
    "addr:housenumber":"3200",
    "addr:postcode":"80907",
    "addr:street":"N Chestnut St",
    "iso:country":"US",
    "sg:address":"3200 N Chestnut St",
    "sg:city":"Colorado Springs",
    "sg:classifiers":[
        {
            "category":"Government",
            "subcategory":"Office",
            "type":"Public Place"
        }
    ],
    "sg:phone":"+1 719 632 1567",
    "sg:postcode":"80907",
    "sg:province":"CO",
    "sg:tags":[
        "state",
        "security"
    ],
    "wof:name":"Colorado Army National Guard",
    "wof:placetype":"venue"
},
  "geometry": {"coordinates":[-104.836466,38.879557],"type":"Point"}
}