{
  "type": "Feature",
  "properties": {
    "iso:country":"US",
    "sg:address":"308 W Fillmore St",
    "sg:city":"Colorado Springs",
    "sg:classifiers":[
        {
            "category":"Retail",
            "subcategory":"Portrait Studio",
            "type":"Services"
        }
    ],
    "sg:phone":"+1 719 648 0274",
    "sg:postcode":"80907",
    "sg:province":"CO",
    "sg:tags":[
        "photographer"
    ],
    "wof:name":"Braggable Photos By Tami Bragg",
    "wof:placetype":"venue"
},
  "geometry": {"coordinates":[-104.827461,38.875164],"type":"Point"}
}