{
  "type": "Feature",
  "properties": {
    "iso:country":"US",
    "sg:address":"1222 E Evans Ave",
    "sg:city":"Pueblo",
    "sg:classifiers":[
        {
            "category":"Shopping",
            "subcategory":"Used Merchandise",
            "type":"Retail Goods"
        }
    ],
    "sg:phone":"+1 719 544 1837",
    "sg:postcode":"81004",
    "sg:province":"CO",
    "wof:name":"Pueblo Trader Pawn Shop",
    "wof:placetype":"venue"
},
  "geometry": {"coordinates":[-104.61485500000001,38.244542],"type":"Point"}
}