{
  "type": "Feature",
  "properties": {
    "iso:country":"US",
    "sg:address":"6224 E Progress Ln",
    "sg:city":"Parker",
    "sg:classifiers":[
        {
            "category":"Wholesale",
            "subcategory":"Apparel",
            "type":"Manufacturing & Wholesale Goods"
        },
        {
            "category":"Shopping",
            "subcategory":"Luggage & Leather Goods",
            "type":"Retail Goods"
        }
    ],
    "sg:phone":"+1 303 805 0362",
    "sg:postcode":"80134",
    "sg:province":"CO",
    "sg:tags":[
        "footwear"
    ],
    "wof:name":"Ruby Leather",
    "wof:placetype":"venue"
},
  "geometry": {"coordinates":[-104.769836,39.53196],"type":"Point"}
}