{
  "type": "Feature",
  "properties": {
    "addr:full":"7944 Logan St Denver CO 80229",
    "addr:housenumber":"7944",
    "addr:postcode":"80229",
    "addr:street":"Logan St",
    "iso:country":"US",
    "sg:address":"7944 Logan St",
    "sg:city":"Denver",
    "sg:classifiers":[
        {
            "category":"Building & Trades",
            "subcategory":"Plumbing",
            "type":"Services"
        }
    ],
    "sg:phone":"+1 720 490 6921",
    "sg:postcode":"80229",
    "sg:province":"CO",
    "sg:tags":[
        "contractor"
    ],
    "wof:name":"T J F Plumbing",
    "wof:placetype":"venue"
},
  "geometry": {"coordinates":[-104.98065699999999,39.839907],"type":"Point"}
}