{
  "type": "Feature",
  "properties": {
    "addr:full":"335 E 6th St Loveland CO 80537",
    "addr:housenumber":"335",
    "addr:postcode":"80537",
    "addr:street":"E 6Th St",
    "iso:country":"US",
    "sg:address":"335 E 6th St",
    "sg:city":"Loveland",
    "sg:classifiers":[
        {
            "category":"Freight",
            "type":"Transportation"
        }
    ],
    "sg:phone":"+1 970 667 4244",
    "sg:postcode":"80537",
    "sg:province":"CO",
    "sg:tags":[
        "operator",
        "local",
        "trucking"
    ],
    "wof:name":"Pro Moving Services",
    "wof:placetype":"venue"
},
  "geometry": {"coordinates":[-105.072197,40.39759],"type":"Point"}
}