{
  "type": "Feature",
  "properties": {
    "addr:full":"2517 Broadway St Boulder CO 80304",
    "addr:housenumber":"2517",
    "addr:postcode":"80304",
    "addr:street":"Broadway St",
    "iso:country":"US",
    "sg:address":"2517 Broadway St",
    "sg:city":"Boulder",
    "sg:classifiers":[
        {
            "category":"Manufacturing",
            "subcategory":"Printing",
            "type":"Manufacturing & Wholesale Goods"
        }
    ],
    "sg:phone":"+1 720 562 6185",
    "sg:postcode":"80304",
    "sg:province":"CO",
    "sg:tags":[
        "multimedia"
    ],
    "wof:name":"Havoc Interactive",
    "wof:placetype":"venue"
},
  "geometry": {"coordinates":[-105.282107,40.024253],"type":"Point"}
}