{
  "type": "Feature",
  "properties": {
    "addr:full":"7 S Wahsatch Ave Colorado Springs CO 80903",
    "addr:housenumber":"7",
    "addr:postcode":"80903",
    "addr:street":"S Wahsatch Ave",
    "iso:country":"US",
    "sg:address":"7 S Wahsatch Ave",
    "sg:city":"Colorado Springs",
    "sg:classifiers":[
        {
            "category":"Professional",
            "type":"Services"
        }
    ],
    "sg:phone":"+1 719 227 1656",
    "sg:postcode":"80903",
    "sg:province":"CO",
    "sg:tags":[
        "establishment"
    ],
    "wof:name":"Prodeloz Customs",
    "wof:placetype":"venue"
},
  "geometry": {"coordinates":[-104.81814300000001,38.83236],"type":"Point"}
}