{
  "type": "Feature",
  "properties": {
    "iso:country":"US",
    "sg:address":"1015 E 70th Ave",
    "sg:city":"Denver",
    "sg:classifiers":[
        {
            "category":"Local Transit",
            "type":"Transportation"
        }
    ],
    "sg:phone":"+1 303 289 3378",
    "sg:postcode":"80229",
    "sg:province":"CO",
    "sg:tags":[
        "passenger"
    ],
    "wof:name":"A Abcott Limousines",
    "wof:placetype":"venue"
},
  "geometry": {"coordinates":[-104.971684,39.825085],"type":"Point"}
}