{
  "type": "Feature",
  "properties": {
    "addr:full":"1348 Buffalo Grass Pl Elizabeth CO 80107",
    "addr:housenumber":"1348",
    "addr:postcode":"80107",
    "addr:street":"Buffalo Grass Pl",
    "iso:country":"US",
    "sg:address":"1348 Buffalo Grass Pl",
    "sg:city":"Elizabeth",
    "sg:classifiers":[
        {
            "category":"Building & Trades",
            "subcategory":"Construction",
            "type":"Services"
        }
    ],
    "sg:phone":"+1 303 646 1275",
    "sg:postcode":"80107",
    "sg:province":"CO",
    "sg:tags":[
        "residential"
    ],
    "wof:name":"Genuine Homes Corp",
    "wof:placetype":"venue"
},
  "geometry": {"coordinates":[-104.638447,39.417789],"type":"Point"}
}