{
  "type": "Feature",
  "properties": {
    "addr:full":"1401 19th St Denver CO 80202",
    "addr:housenumber":"1401",
    "addr:postcode":"80202",
    "addr:street":"19Th St",
    "iso:country":"US",
    "sg:address":"1401 19th St",
    "sg:city":"Denver",
    "sg:classifiers":[
        {
            "category":"Social Services",
            "subcategory":"Job Training",
            "type":"Services"
        }
    ],
    "sg:phone":"+1 303 295 0550",
    "sg:postcode":"80202",
    "sg:province":"CO",
    "sg:tags":[
        "career",
        "counseling",
        "vocational"
    ],
    "wof:name":"Denver Career College",
    "wof:placetype":"venue"
},
  "geometry": {"coordinates":[-104.995521,39.753344],"type":"Point"}
}