{
  "type": "Feature",
  "properties": {
    "iso:country":"US",
    "sg:address":"3701 E 91st Ave",
    "sg:city":"Denver",
    "sg:classifiers":[
        {
            "category":"Freight",
            "type":"Transportation"
        }
    ],
    "sg:phone":"+1 303 287 8106",
    "sg:postcode":"80229",
    "sg:province":"CO",
    "sg:tags":[
        "operator",
        "local",
        "trucking"
    ],
    "wof:name":"Chavez Trucking",
    "wof:placetype":"venue"
},
  "geometry": {"coordinates":[-104.941548,39.860626],"type":"Point"}
}