{
  "type": "Feature",
  "properties": {
    "addr:full":"1729 Alexander Cir Pueblo CO 81001",
    "addr:housenumber":"1729",
    "addr:postcode":"81001",
    "addr:street":"Alexander Cir",
    "iso:country":"US",
    "sg:address":"1729 Alexander Cir",
    "sg:city":"Pueblo",
    "sg:classifiers":[
        {
            "category":"Autos & Motor Vehicles",
            "subcategory":"Automobile Sales",
            "type":"Retail Goods"
        }
    ],
    "sg:phone":"+1 719 543 8281",
    "sg:postcode":"81001",
    "sg:province":"CO",
    "sg:tags":[
        "used"
    ],
    "wof:name":"Alpha Motor Sales Inc",
    "wof:placetype":"venue"
},
  "geometry": {"coordinates":[-104.58934600000001,38.293516],"type":"Point"}
}