{
  "type": "Feature",
  "properties": {
    "iso:country":"US",
    "sg:address":"1705 14th St",
    "sg:city":"Boulder",
    "sg:classifiers":[
        {
            "category":"Building & Trades",
            "subcategory":"Cleaning & Sanitation",
            "type":"Services"
        }
    ],
    "sg:phone":"+1 303 444 3378",
    "sg:postcode":"80302",
    "sg:province":"CO",
    "sg:tags":[
        "property",
        "maintenance"
    ],
    "wof:name":"Showhomes Of America",
    "wof:placetype":"venue"
},
  "geometry": {"coordinates":[-105.27637300000001,40.015487],"type":"Point"}
}