{
  "type": "Feature",
  "properties": {
    "addr:full":"729 Pershing St Craig CO 81625",
    "addr:housenumber":"729",
    "addr:postcode":"81625",
    "addr:street":"Pershing St",
    "iso:country":"US",
    "sg:address":"729 Pershing St",
    "sg:city":"Craig",
    "sg:classifiers":[
        {
            "category":"Building & Trades",
            "subcategory":"Plumbing",
            "type":"Services"
        }
    ],
    "sg:phone":"+1 970 824 7435",
    "sg:postcode":"81625",
    "sg:province":"CO",
    "sg:tags":[
        "contractor"
    ],
    "wof:name":"ARS Mechanical",
    "wof:placetype":"venue"
},
  "geometry": {"coordinates":[-107.554412,40.518735],"type":"Point"}
}