{
  "type": "Feature",
  "properties": {
    "iso:country":"US",
    "sg:address":"1000 E Hopkins Ave",
    "sg:city":"Aspen",
    "sg:classifiers":[
        {
            "category":"Building & Trades",
            "subcategory":"Construction",
            "type":"Services"
        }
    ],
    "sg:phone":"+1 970 925 1398",
    "sg:postcode":"81611",
    "sg:province":"CO",
    "sg:tags":[
        "painter"
    ],
    "wof:name":"Ajax Custom Painting",
    "wof:placetype":"venue"
},
  "geometry": {"coordinates":[-106.81245199999999,39.188402],"type":"Point"}
}