{
  "type": "Feature",
  "properties": {
    "iso:country":"US",
    "sg:address":"3375 Fox St",
    "sg:city":"Denver",
    "sg:classifiers":[
        {
            "category":"Park",
            "type":"Public Place"
        }
    ],
    "sg:phone":"+1 303 458 4856",
    "sg:postcode":"80216",
    "sg:province":"CO",
    "wof:name":"Denver Park District",
    "wof:placetype":"venue"
},
  "geometry": {"coordinates":[-104.994827,39.769994],"type":"Point"}
}