{
  "type": "Feature",
  "properties": {
    "iso:country":"US",
    "sg:address":"2900 S Forest St",
    "sg:city":"Denver",
    "sg:classifiers":[
        {
            "category":"Banks & Credit Unions",
            "subcategory":"Bank",
            "type":"Services"
        },
        {
            "category":"Shopping",
            "subcategory":"Used Merchandise",
            "type":"Retail Goods"
        }
    ],
    "sg:phone":"+1 303 757 3187",
    "sg:postcode":"80222",
    "sg:province":"CO",
    "sg:tags":[
        "resale",
        "shop",
        "second",
        "hand"
    ],
    "wof:name":"L M S Uniques",
    "wof:placetype":"venue"
},
  "geometry": {"coordinates":[-104.927656,39.665182],"type":"Point"}
}