{
  "type": "Feature",
  "properties": {
    "addr:full":"421 Brach Dr Grand Junction CO 81503",
    "addr:housenumber":"421",
    "addr:postcode":"81503",
    "addr:street":"Brach Dr",
    "iso:country":"US",
    "sg:address":"421 Brach Dr",
    "sg:city":"Grand Junction",
    "sg:classifiers":[
        {
            "category":"Restaurant",
            "type":"Food & Drink"
        }
    ],
    "sg:menulink":"http://www.allmenus.com/co/grand-junction/278141-dos-hombres/menu/",
    "sg:phone":"+1 970 242 8861",
    "sg:postcode":"81503",
    "sg:province":"CO",
    "sg:tags":[
        "mexican"
    ],
    "wof:name":"Dos Hombres",
    "wof:placetype":"venue"
},
  "geometry": {"coordinates":[-108.586152,39.064511],"type":"Point"}
}