{
  "type": "Feature",
  "properties": {
    "addr:full":"3230 23rd Ave Evans CO 80620",
    "addr:housenumber":"3230",
    "addr:postcode":"80620",
    "addr:street":"23Rd Ave",
    "iso:country":"US",
    "sg:address":"3230 23rd Ave",
    "sg:city":"Evans",
    "sg:classifiers":[
        {
            "category":"Restaurant",
            "type":"Food & Drink"
        }
    ],
    "sg:menulink":"http://www.allmenus.com/co/greeley/87174-little-caesars-pizza/menu/",
    "sg:phone":"+1 970 330 1131",
    "sg:postcode":"80620",
    "sg:province":"CO",
    "sg:tags":[
        "american",
        "pizza"
    ],
    "wof:name":"Little Caesar's Pizza",
    "wof:placetype":"venue"
},
  "geometry": {"coordinates":[-104.715053,40.383477],"type":"Point"}
}