{
  "type": "Feature",
  "properties": {
    "addr:full":"7367 W Grant Ranch Blvd Littleton CO 80123",
    "addr:housenumber":"7367",
    "addr:postcode":"80123",
    "addr:street":"W Grant Ranch Blvd",
    "iso:country":"US",
    "sg:address":"7367 W Grant Ranch Blvd",
    "sg:city":"Littleton",
    "sg:classifiers":[
        {
            "category":"Real Estate",
            "subcategory":"Developer",
            "type":"Services"
        }
    ],
    "sg:phone":"+1 303 978 0877",
    "sg:postcode":"80123",
    "sg:province":"CO",
    "wof:name":"Lundy Professional Development",
    "wof:placetype":"venue"
},
  "geometry": {"coordinates":[-105.081125,39.6185],"type":"Point"}
}