{
  "type": "Feature",
  "properties": {
    "addr:full":"6668 S Killarney Ct Aurora CO 80016",
    "addr:housenumber":"6668",
    "addr:postcode":"80016",
    "addr:street":"S Killarney Ct",
    "iso:country":"US",
    "sg:address":"6668 S Killarney Ct",
    "sg:city":"Aurora",
    "sg:classifiers":[
        {
            "category":"Building & Trades",
            "subcategory":"Plumbing",
            "type":"Services"
        }
    ],
    "sg:phone":"+1 303 699 2185",
    "sg:postcode":"80016",
    "sg:province":"CO",
    "sg:tags":[
        "contractor"
    ],
    "wof:name":"Fluid Flow Plumbing Inc",
    "wof:placetype":"venue"
},
  "geometry": {"coordinates":[-104.747035,39.596616],"type":"Point"}
}