{
  "type": "Feature",
  "properties": {
    "iso:country":"US",
    "sg:address":"2050 S Havana St",
    "sg:city":"Aurora",
    "sg:classifiers":[
        {
            "category":"Shopping",
            "subcategory":"Computers & Home Electronics",
            "type":"Retail Goods"
        }
    ],
    "sg:phone":"+1 303 755 5919",
    "sg:postcode":"80014",
    "sg:province":"CO",
    "wof:name":"Radio Shack",
    "wof:placetype":"venue"
},
  "geometry": {"coordinates":[-104.86588500000001,39.679316],"type":"Point"}
}