{
  "type": "Feature",
  "properties": {
    "addr:full":"1701 Wynkoop St Denver CO 80202",
    "addr:housenumber":"1701",
    "addr:postcode":"80202",
    "addr:street":"Wynkoop St",
    "iso:country":"US",
    "sg:address":"1701 Wynkoop St",
    "sg:city":"Denver",
    "sg:classifiers":[
        {
            "category":"Building & Trades",
            "subcategory":"Construction",
            "type":"Services"
        }
    ],
    "sg:phone":"+1 720 533 4800",
    "sg:postcode":"80202",
    "sg:province":"CO",
    "sg:tags":[
        "interior",
        "design"
    ],
    "wof:name":"Dwelling Interiors",
    "wof:placetype":"venue"
},
  "geometry": {"coordinates":[-104.999809,39.752948],"type":"Point"}
}