{
  "type": "Feature",
  "properties": {
    "addr:full":"2638 King St Denver CO 80211",
    "addr:housenumber":"2638",
    "addr:postcode":"80211",
    "addr:street":"King St",
    "iso:country":"US",
    "sg:address":"2638 King St",
    "sg:city":"Denver",
    "sg:classifiers":[
        {
            "category":"Banks & Credit Unions",
            "subcategory":"Financial Services",
            "type":"Services"
        }
    ],
    "sg:phone":"+1 303 458 1349",
    "sg:postcode":"80211",
    "sg:province":"CO",
    "sg:tags":[
        "company",
        "holding"
    ],
    "wof:name":"Ire Holdings Inc",
    "wof:placetype":"venue"
},
  "geometry": {"coordinates":[-105.033354,39.755958],"type":"Point"}
}