{
  "type": "Feature",
  "properties": {
    "iso:country":"US",
    "sg:address":"8316 Russet Ct",
    "sg:city":"Littleton",
    "sg:classifiers":[
        {
            "category":"Health Services",
            "subcategory":"Clinic",
            "type":"Services"
        }
    ],
    "sg:phone":"+1 720 488 1710",
    "sg:postcode":"80126",
    "sg:province":"CO",
    "sg:tags":[
        "wellness",
        "program"
    ],
    "wof:name":"Wellness Press",
    "wof:placetype":"venue"
},
  "geometry": {"coordinates":[-104.95480999999999,39.565384],"type":"Point"}
}