{
  "type": "Feature",
  "properties": {
    "addr:full":"1270 S Lipan Street Denver CO 80223",
    "addr:housenumber":"1270",
    "addr:postcode":"80223",
    "addr:street":"S Lipan Street",
    "iso:country":"US",
    "sg:address":"1270 S Lipan Street",
    "sg:city":"Denver",
    "sg:classifiers":[
        {
            "category":"Building & Trades",
            "subcategory":"Plumbing",
            "type":"Services"
        }
    ],
    "sg:phone":"+1 303 744 2188",
    "sg:postcode":"80223",
    "sg:province":"CO",
    "wof:name":"Environmental Control Systems",
    "wof:placetype":"venue"
},
  "geometry": {"coordinates":[-105.00156200000001,39.694473],"type":"Point"}
}