{
  "type": "Feature",
  "properties": {
    "addr:full":"10789 Moore St Broomfield CO 80021",
    "addr:housenumber":"10789",
    "addr:postcode":"80021",
    "addr:street":"Moore St",
    "iso:country":"US",
    "sg:address":"10789 Moore St",
    "sg:city":"Broomfield",
    "sg:classifiers":[
        {
            "category":"Building & Trades",
            "subcategory":"Plumbing",
            "type":"Services"
        }
    ],
    "sg:phone":"+1 303 460 1326",
    "sg:postcode":"80021",
    "sg:province":"CO",
    "sg:tags":[
        "contractor"
    ],
    "wof:name":"Broomfield Mechanical LLC",
    "wof:placetype":"venue"
},
  "geometry": {"coordinates":[-105.113243,39.891207],"type":"Point"}
}