{
  "type": "Feature",
  "properties": {
    "addr:full":"8859 Fox Dr Denver CO 80260",
    "addr:housenumber":"8859",
    "addr:postcode":"80260",
    "addr:street":"Fox Dr",
    "iso:country":"US",
    "sg:address":"8859 Fox Dr",
    "sg:city":"Denver",
    "sg:classifiers":[
        {
            "category":"Health Services",
            "subcategory":"Health Practitioner",
            "type":"Services"
        }
    ],
    "sg:phone":"+1 303 428 4646",
    "sg:postcode":"80260",
    "sg:province":"CO",
    "sg:tags":[
        "therapist",
        "physical"
    ],
    "wof:name":"Brookside Physical Therapy",
    "wof:placetype":"venue"
},
  "geometry": {"coordinates":[-104.994203,39.85737],"type":"Point"}
}