{
  "type": "Feature",
  "properties": {
    "addr:full":"116 Hummingbird Pl Berthoud CO 80513",
    "addr:housenumber":"116",
    "addr:postcode":"80513",
    "addr:street":"Hummingbird Pl",
    "iso:country":"US",
    "sg:address":"116 Hummingbird Pl",
    "sg:city":"Berthoud",
    "sg:classifiers":[
        {
            "category":"Farming",
            "subcategory":"Livestock Farm",
            "type":"Manufacturing & Wholesale Goods"
        }
    ],
    "sg:phone":"+1 970 532 4325",
    "sg:postcode":"80513",
    "sg:province":"CO",
    "sg:tags":[
        "equine"
    ],
    "wof:name":"Mark Zabel",
    "wof:placetype":"venue"
},
  "geometry": {"coordinates":[-105.084315,40.302164],"type":"Point"}
}