{
  "type": "Feature",
  "properties": {
    "addr:full":"300 S Downing St Denver CO 80209",
    "addr:housenumber":"300",
    "addr:postcode":"80209",
    "addr:street":"S Downing St",
    "iso:country":"US",
    "sg:address":"300 S Downing St",
    "sg:city":"Denver",
    "sg:classifiers":[
        {
            "category":"Building & Trades",
            "subcategory":"Locksmith",
            "type":"Services"
        }
    ],
    "sg:phone":"+1 303 578 3057",
    "sg:postcode":"80209",
    "sg:province":"CO",
    "sg:tags":[
        "key"
    ],
    "wof:name":"24 Hour Emergency Locksmith",
    "wof:placetype":"venue"
},
  "geometry": {"coordinates":[-104.973202,39.711108],"type":"Point"}
}