{
  "type": "Feature",
  "properties": {
    "addr:full":"95 S Wadsworth Blvd Denver CO 80226",
    "addr:housenumber":"95",
    "addr:postcode":"80226",
    "addr:street":"S Wadsworth Blvd",
    "iso:country":"US",
    "sg:address":"95 S Wadsworth Blvd",
    "sg:city":"Denver",
    "sg:classifiers":[
        {
            "category":"Building & Trades",
            "subcategory":"Plumbing",
            "type":"Services"
        }
    ],
    "sg:phone":"+1 303 302 1386",
    "sg:postcode":"80226",
    "sg:province":"CO",
    "sg:tags":[
        "contractor"
    ],
    "wof:name":"Aays Mechanical Inc",
    "wof:placetype":"venue"
},
  "geometry": {"coordinates":[-105.081546,39.716568],"type":"Point"}
}