{
  "type": "Feature",
  "properties": {
    "addr:full":"1718 Dublin Blvd Colorado Springs CO 80918",
    "addr:housenumber":"1718",
    "addr:postcode":"80918",
    "addr:street":"Dublin Blvd",
    "iso:country":"US",
    "sg:address":"1718 Dublin Blvd",
    "sg:city":"Colorado Springs",
    "sg:classifiers":[
        {
            "category":"Personal",
            "subcategory":"Beauty Salon",
            "type":"Services"
        }
    ],
    "sg:phone":"+1 719 590 9898",
    "sg:postcode":"80918",
    "sg:province":"CO",
    "wof:name":"Cost Cutters Family Hair Care",
    "wof:placetype":"venue"
},
  "geometry": {"coordinates":[-104.794067,38.925795],"type":"Point"}
}