{
  "type": "Feature",
  "properties": {
    "addr:full":"5226 Red Hawk Pkwy Brighton CO 80601",
    "addr:housenumber":"5226",
    "addr:postcode":"80601",
    "addr:street":"Red Hawk Pkwy",
    "iso:country":"US",
    "sg:address":"5226 Red Hawk Pkwy",
    "sg:city":"Brighton",
    "sg:classifiers":[
        {
            "category":"Wholesale",
            "subcategory":"Farm Supplies",
            "type":"Manufacturing & Wholesale Goods"
        }
    ],
    "sg:phone":"+1 303 419 7761",
    "sg:postcode":"80601",
    "sg:province":"CO",
    "wof:name":"Quality Hay",
    "wof:placetype":"venue"
},
  "geometry": {"coordinates":[-104.749172,39.98475],"type":"Point"}
}