{
  "type": "Feature",
  "properties": {
    "addr:full":"741 Corona St Denver CO 80218",
    "addr:housenumber":"741",
    "addr:postcode":"80218",
    "addr:street":"Corona St",
    "iso:country":"US",
    "sg:address":"741 Corona St",
    "sg:city":"Denver",
    "sg:classifiers":[
        {
            "category":"Farming",
            "subcategory":"Nursery",
            "type":"Manufacturing & Wholesale Goods"
        }
    ],
    "sg:phone":"+1 303 457 4000",
    "sg:postcode":"80218",
    "sg:province":"CO",
    "sg:tags":[
        "greenhouse"
    ],
    "wof:name":"Nexus Greenhouse",
    "wof:placetype":"venue"
},
  "geometry": {"coordinates":[-104.974158,39.728341],"type":"Point"}
}