{
  "type": "Feature",
  "properties": {
    "addr:full":"308 S 3rd St Sterling CO 80751",
    "addr:housenumber":"308",
    "addr:postcode":"80751",
    "addr:street":"S 3Rd St",
    "iso:country":"US",
    "sg:address":"308 S 3rd St",
    "sg:city":"Sterling",
    "sg:classifiers":[
        {
            "category":"Insurance",
            "subcategory":"Insurance Agent",
            "type":"Services"
        }
    ],
    "sg:phone":"+1 970 522 0505",
    "sg:postcode":"80751",
    "sg:province":"CO",
    "wof:name":"Able Agency",
    "wof:placetype":"venue"
},
  "geometry": {"coordinates":[-103.210201,40.621478],"type":"Point"}
}