{
  "type": "Feature",
  "properties": {
    "iso:country":"US",
    "sg:address":"1712 W Stuart St",
    "sg:city":"Fort Collins",
    "sg:classifiers":[
        {
            "category":"Building & Trades",
            "subcategory":"Construction",
            "type":"Services"
        }
    ],
    "sg:phone":"+1 970 495 1986",
    "sg:postcode":"80526",
    "sg:province":"CO",
    "sg:tags":[
        "concrete",
        "contractor"
    ],
    "wof:name":"Creative Concrete Coatings",
    "wof:placetype":"venue"
},
  "geometry": {"coordinates":[-105.108701,40.562125],"type":"Point"}
}