{
  "type": "Feature",
  "properties": {
    "iso:country":"US",
    "sg:address":"6750 S Lima St",
    "sg:city":"Englewood",
    "sg:classifiers":[
        {
            "category":"Shopping",
            "subcategory":"Computers & Home Electronics",
            "type":"Retail Goods"
        }
    ],
    "sg:phone":"+1 303 792 7372",
    "sg:postcode":"80112",
    "sg:province":"CO",
    "sg:tags":[
        "software"
    ],
    "wof:name":"Peachtree Support By Engrav",
    "wof:placetype":"venue"
},
  "geometry": {"coordinates":[-104.85744699999999,39.594939],"type":"Point"}
}