{
  "type": "Feature",
  "properties": {
    "addr:full":"2400 Agate Rd Boulder CO 80304",
    "addr:housenumber":"2400",
    "addr:postcode":"80304",
    "addr:street":"Agate Rd",
    "iso:country":"US",
    "sg:address":"2400 Agate Rd",
    "sg:city":"Boulder",
    "sg:classifiers":[
        {
            "category":"Real Estate",
            "subcategory":"Architect",
            "type":"Services"
        }
    ],
    "sg:phone":"+1 303 444 6498",
    "sg:postcode":"80304",
    "sg:province":"CO",
    "wof:name":"Rohde Design Inc",
    "wof:placetype":"venue"
},
  "geometry": {"coordinates":[-105.26329200000001,40.048351],"type":"Point"}
}