{
  "type": "Feature",
  "properties": {
    "iso:country":"US",
    "sg:address":"415 E Hyman Ave",
    "sg:city":"Aspen",
    "sg:classifiers":[
        {
            "category":"Real Estate",
            "subcategory":"Real Estate Agent",
            "type":"Services"
        }
    ],
    "sg:phone":"+1 970 618 3330",
    "sg:postcode":"81611",
    "sg:province":"CO",
    "sg:tags":[
        "investment"
    ],
    "wof:name":"Briscoe & Briscoe",
    "wof:placetype":"venue"
},
  "geometry": {"coordinates":[-106.819682,39.188987],"type":"Point"}
}