{
  "type": "Feature",
  "properties": {
    "addr:full":"200 N Townsend Ave Montrose CO 81401",
    "addr:housenumber":"200",
    "addr:postcode":"81401",
    "addr:street":"N Townsend Ave",
    "iso:country":"US",
    "sg:address":"200 N Townsend Ave",
    "sg:city":"Montrose",
    "sg:classifiers":[
        {
            "category":"Banks & Credit Unions",
            "subcategory":"Bank",
            "type":"Services"
        }
    ],
    "sg:phone":"+1 970 249 3408",
    "sg:postcode":"81401",
    "sg:province":"CO",
    "sg:tags":[
        "state",
        "commercial"
    ],
    "wof:name":"Montrosebank",
    "wof:placetype":"venue"
},
  "geometry": {"coordinates":[-107.88029400000001,38.481049],"type":"Point"}
}