{
  "type": "Feature",
  "properties": {
    "addr:full":"31141 Co Rd 44 Burlington CO 80807",
    "addr:housenumber":"31141;44",
    "addr:postcode":"80807",
    "addr:street":"Co Rd",
    "iso:country":"US",
    "sg:address":"31141 Co Rd 44",
    "sg:city":"Burlington",
    "sg:classifiers":[
        {
            "category":"Airport",
            "type":"Transportation"
        }
    ],
    "sg:phone":"+1 719 346 8529",
    "sg:postcode":"80807",
    "sg:province":"CO",
    "sg:tags":[
        "support",
        "airline"
    ],
    "wof:name":"Mangus Aviation",
    "wof:placetype":"venue"
},
  "geometry": {"coordinates":[-102.352502,39.463181],"type":"Point"}
}