{
  "type": "Feature",
  "properties": {
    "addr:full":"150 Front St Platteville CO 80651",
    "addr:housenumber":"150",
    "addr:postcode":"80651",
    "addr:street":"Front St",
    "iso:country":"US",
    "sg:address":"150 Front St",
    "sg:city":"Platteville",
    "sg:classifiers":[
        {
            "category":"Home & Garden",
            "subcategory":"Building Materials",
            "type":"Retail Goods"
        }
    ],
    "sg:phone":"+1 970 785 9255",
    "sg:postcode":"80651",
    "sg:province":"CO",
    "sg:tags":[
        "mixed",
        "concrete"
    ],
    "wof:name":"Platteville Ready Mix",
    "wof:placetype":"venue"
},
  "geometry": {"coordinates":[-104.81949299999999,40.218616],"type":"Point"}
}