{
  "type": "Feature",
  "properties": {
    "iso:country":"US",
    "sg:address":"3525 Co Rd 309A",
    "sg:city":"Ignacio",
    "sg:classifiers":[
        {
            "category":"Wholesale",
            "subcategory":"Sporting Goods",
            "type":"Manufacturing & Wholesale Goods"
        }
    ],
    "sg:phone":"+1 970 563 4664",
    "sg:postcode":"81137",
    "sg:province":"CO",
    "wof:name":"Horvat Billiards",
    "wof:placetype":"venue"
},
  "geometry": {"coordinates":[-107.749872,37.113962],"type":"Point"}
}