{
  "type": "Feature",
  "properties": {
    "iso:country":"US",
    "sg:address":"339 E Rainbow Blvd",
    "sg:city":"Salida",
    "sg:classifiers":[
        {
            "category":"Banks & Credit Unions",
            "subcategory":"Bank",
            "type":"Services"
        }
    ],
    "sg:phone":"+1 719 539 9799",
    "sg:postcode":"81201",
    "sg:province":"CO",
    "wof:name":"Community Banks Of The Rockies",
    "wof:placetype":"venue"
},
  "geometry": {"coordinates":[-105.99950800000001,38.524027],"type":"Point"}
}