{
  "type": "Feature",
  "properties": {
    "iso:country":"US",
    "sg:address":"501 Palmer St",
    "sg:city":"Delta",
    "sg:classifiers":[
        {
            "category":"Government",
            "subcategory":"Office",
            "type":"Public Place"
        }
    ],
    "sg:phone":"+1 970 874 2110",
    "sg:postcode":"81416",
    "sg:province":"CO",
    "sg:tags":[
        "county",
        "executive",
        "program"
    ],
    "wof:name":"Planning & Development",
    "wof:placetype":"venue"
},
  "geometry": {"coordinates":[-108.072152,38.740342],"type":"Point"}
}