{
  "type": "Feature",
  "properties": {
    "addr:full":"206 Primrose Ln Bayfield CO 81122",
    "addr:housenumber":"206",
    "addr:postcode":"81122",
    "addr:street":"Primrose Ln",
    "iso:country":"US",
    "sg:address":"206 Primrose Ln",
    "sg:city":"Bayfield",
    "sg:classifiers":[
        {
            "category":"Home & Garden",
            "subcategory":"Building Materials",
            "type":"Retail Goods"
        }
    ],
    "sg:phone":"+1 970 884 1191",
    "sg:postcode":"81122",
    "sg:province":"CO",
    "sg:tags":[
        "glass",
        "window",
        "plate"
    ],
    "wof:name":"American Precision Auto Glass",
    "wof:placetype":"venue"
},
  "geometry": {"coordinates":[-107.597437,37.253586],"type":"Point"}
}