{
  "type": "Feature",
  "properties": {
    "addr:full":"205 C St Rock Springs CO 82901",
    "addr:housenumber":"205",
    "addr:postcode":"82901",
    "addr:street":"C St",
    "iso:country":"US",
    "sg:address":"205 C St",
    "sg:city":"Rock Springs",
    "sg:classifiers":[
        {
            "category":"Professional",
            "subcategory":"Lawyer & Legal Services",
            "type":"Services"
        }
    ],
    "sg:phone":"+1 307 382 6600",
    "sg:postcode":"82901",
    "sg:province":"CO",
    "sg:tags":[
        "attorney"
    ],
    "wof:name":"Greenhalgh Beckwith Lemich",
    "wof:placetype":"venue"
},
  "geometry": {"coordinates":[-109.22045900000001,41.585651],"type":"Point"}
}