{
  "type": "Feature",
  "properties": {
    "iso:country":"US",
    "sg:address":"397 Bush St",
    "sg:city":"Brighton",
    "sg:classifiers":[
        {
            "category":"Building & Trades",
            "subcategory":"Cleaning & Sanitation",
            "type":"Services"
        }
    ],
    "sg:phone":"+1 303 637 0445",
    "sg:postcode":"80601",
    "sg:province":"CO",
    "wof:name":"Royal Treatment Cleaning & Mnt",
    "wof:placetype":"venue"
},
  "geometry": {"coordinates":[-104.819185,39.985322],"type":"Point"}
}