{
  "type": "Feature",
  "properties": {
    "iso:country":"US",
    "sg:address":"2327 E Boulder St",
    "sg:city":"Colorado Springs",
    "sg:classifiers":[
        {
            "category":"Retail",
            "subcategory":"Portrait Studio",
            "type":"Services"
        }
    ],
    "sg:phone":"+1 719 228 9256",
    "sg:postcode":"80909",
    "sg:province":"CO",
    "sg:tags":[
        "photographer"
    ],
    "wof:name":"Wedding Photography Ctr",
    "wof:placetype":"venue"
},
  "geometry": {"coordinates":[-104.78582,38.838292],"type":"Point"}
}