{
  "type": "Feature",
  "properties": {
    "iso:country":"US",
    "sg:address":"13030 Co Rd 501",
    "sg:city":"Bayfield",
    "sg:classifiers":[
        {
            "category":"Restaurant",
            "type":"Food & Drink"
        }
    ],
    "sg:phone":"+1 970 884 9458",
    "sg:postcode":"81122",
    "sg:province":"CO",
    "wof:name":"Vallecito Cafe",
    "wof:placetype":"venue"
},
  "geometry": {"coordinates":[-107.57999700000001,37.381758],"type":"Point"}
}