{
  "type": "Feature",
  "properties": {
    "addr:full":"4101 E Louisiana Ave Denver CO 80246",
    "addr:housenumber":"4101",
    "addr:postcode":"80246",
    "addr:street":"E Louisiana Ave",
    "iso:country":"US",
    "sg:address":"4101 E Louisiana Ave",
    "sg:city":"Denver",
    "sg:classifiers":[
        {
            "category":"Health Services",
            "subcategory":"Medical Lab",
            "type":"Services"
        }
    ],
    "sg:phone":"+1 303 759 5189",
    "sg:postcode":"80246",
    "sg:province":"CO",
    "sg:tags":[
        "laboratory"
    ],
    "wof:name":"Pan AM Affiliated Dental Lbrts",
    "wof:placetype":"venue"
},
  "geometry": {"coordinates":[-104.938363,39.693025],"type":"Point"}
}