{
  "type": "Feature",
  "properties": {
    "iso:country":"US",
    "sg:address":"755 Silver St",
    "sg:city":"Delta",
    "sg:classifiers":[
        {
            "category":"Building & Trades",
            "subcategory":"Electrical",
            "type":"Services"
        }
    ],
    "sg:phone":"+1 970 874 8676",
    "sg:postcode":"81416",
    "sg:province":"CO",
    "sg:tags":[
        "electrical",
        "contractor"
    ],
    "wof:name":"Colorado West Electric Inc",
    "wof:placetype":"venue"
},
  "geometry": {"coordinates":[-108.076352,38.737238],"type":"Point"}
}