{
  "type": "Feature",
  "properties": {
    "iso:country":"US",
    "sg:address":"1563 E Bridge St",
    "sg:city":"Brighton",
    "sg:classifiers":[
        {
            "category":"Insurance",
            "subcategory":"Insurance Agent",
            "type":"Services"
        }
    ],
    "sg:phone":"+1 303 659 3300",
    "sg:postcode":"80601",
    "sg:province":"CO",
    "wof:name":"Titan Insurance",
    "wof:placetype":"venue"
},
  "geometry": {"coordinates":[-104.801541,39.986868],"type":"Point"}
}