{
  "type": "Feature",
  "properties": {
    "addr:full":"7111 W Alameda Ave Denver CO 80226",
    "addr:housenumber":"7111",
    "addr:postcode":"80226",
    "addr:street":"W Alameda Ave",
    "iso:country":"US",
    "sg:address":"7111 W Alameda Ave",
    "sg:city":"Denver",
    "sg:classifiers":[
        {
            "category":"Real Estate",
            "subcategory":"Real Estate Agent",
            "type":"Services"
        }
    ],
    "sg:phone":"+1 303 237 8658",
    "sg:postcode":"80226",
    "sg:province":"CO",
    "sg:tags":[
        "property",
        "broker",
        "provides",
        "developer"
    ],
    "wof:name":"Bruce Katchen & Co",
    "wof:placetype":"venue"
},
  "geometry": {"coordinates":[-105.076531,39.711133],"type":"Point"}
}