{
  "type": "Feature",
  "properties": {
    "iso:country":"US",
    "sg:address":"206 Grand Ave",
    "sg:city":"Paonia",
    "sg:classifiers":[
        {
            "category":"Home & Garden",
            "subcategory":"Hardware",
            "type":"Retail Goods"
        }
    ],
    "sg:phone":"+1 970 527 3301",
    "sg:postcode":"81428",
    "sg:province":"CO",
    "wof:name":"Paonia Farm & Home Supply",
    "wof:placetype":"venue"
},
  "geometry": {"coordinates":[-107.59789000000001,38.868467],"type":"Point"}
}