{
  "type": "Feature",
  "properties": {
    "iso:country":"US",
    "sg:address":"1550 W Dry Creek Rd",
    "sg:city":"Littleton",
    "sg:classifiers":[
        {
            "category":"Autos & Motor Vehicles",
            "subcategory":"Fuel & Gas Station",
            "type":"Retail Goods"
        }
    ],
    "sg:phone":"+1 303 798 5596",
    "sg:postcode":"80120",
    "sg:province":"CO",
    "sg:tags":[
        "station",
        "gasoline"
    ],
    "wof:name":"Taylor Oil Properties",
    "wof:placetype":"venue"
},
  "geometry": {"coordinates":[-105.005715,39.57948],"type":"Point"}
}