{
  "type": "Feature",
  "properties": {
    "iso:country":"US",
    "sg:address":"4701 Peoria St",
    "sg:city":"Denver",
    "sg:classifiers":[
        {
            "category":"Shopping",
            "subcategory":"Shoes",
            "type":"Retail Goods"
        }
    ],
    "sg:phone":"+1 303 371 2747",
    "sg:postcode":"80239",
    "sg:province":"CO",
    "sg:tags":[
        "clothing"
    ],
    "wof:name":"Mr TS Sportswear",
    "wof:placetype":"venue"
},
  "geometry": {"coordinates":[-104.847022,39.783626],"type":"Point"}
}