{
  "type": "Feature",
  "properties": {
    "iso:country":"US",
    "sg:address":"705 Old State Rd",
    "sg:city":"Bailey",
    "sg:classifiers":[
        {
            "category":"Manufacturing",
            "subcategory":"Electronics",
            "type":"Manufacturing & Wholesale Goods"
        }
    ],
    "sg:phone":"+1 303 838 2374",
    "sg:postcode":"80421",
    "sg:province":"CO",
    "sg:tags":[
        "prerecorded",
        "instrument",
        "musical",
        "mfg"
    ],
    "wof:name":"Nuebel Music",
    "wof:placetype":"venue"
},
  "geometry": {"coordinates":[-105.471345,39.426002],"type":"Point"}
}