{
  "type": "Feature",
  "properties": {
    "addr:full":"2704 Freedom Rd Trinidad CO 81082",
    "addr:housenumber":"2704",
    "addr:postcode":"81082",
    "addr:street":"Freedom Rd",
    "iso:country":"US",
    "sg:address":"2704 Freedom Rd",
    "sg:city":"Trinidad",
    "sg:classifiers":[
        {
            "category":"Freight",
            "type":"Transportation"
        }
    ],
    "sg:phone":"+1 719 845 9000",
    "sg:postcode":"81082",
    "sg:province":"CO",
    "sg:tags":[
        "trucking"
    ],
    "wof:name":"RAC Transport",
    "wof:placetype":"venue"
},
  "geometry": {"coordinates":[-104.496624,37.193948],"type":"Point"}
}