{
  "type": "Feature",
  "properties": {
    "addr:full":"5861 E 61st Ave Commerce City CO 80022",
    "addr:housenumber":"5861",
    "addr:postcode":"80022",
    "addr:street":"E 61St Ave",
    "iso:country":"US",
    "sg:address":"5861 E 61st Ave",
    "sg:city":"Commerce City",
    "sg:classifiers":[
        {
            "category":"Communications",
            "subcategory":"Radio Station",
            "type":"Services"
        }
    ],
    "sg:phone":"+1 303 288 2861",
    "sg:postcode":"80022",
    "sg:province":"CO",
    "sg:tags":[
        "education",
        "optics"
    ],
    "wof:name":"Building Blocks Optics",
    "wof:placetype":"venue"
},
  "geometry": {"coordinates":[-104.917935,39.807151],"type":"Point"}
}