{
  "type": "Feature",
  "properties": {
    "addr:full":"6469 Lamar Pl Arvada CO 80003",
    "addr:housenumber":"6469",
    "addr:postcode":"80003",
    "addr:street":"Lamar Pl",
    "iso:country":"US",
    "sg:address":"6469 Lamar Pl",
    "sg:city":"Arvada",
    "sg:classifiers":[
        {
            "category":"Building & Trades",
            "subcategory":"Electrical",
            "type":"Services"
        },
        {
            "category":"Wholesale",
            "subcategory":"Electrical",
            "type":"Manufacturing & Wholesale Goods"
        }
    ],
    "sg:phone":"+1 303 422 7210",
    "sg:postcode":"80003",
    "sg:province":"CO",
    "sg:tags":[
        "control",
        "contractor"
    ],
    "wof:name":"Electrical Control Specialists",
    "wof:placetype":"venue"
},
  "geometry": {"coordinates":[-105.06828,39.813049],"type":"Point"}
}