{
  "type": "Feature",
  "properties": {
    "iso:country":"US",
    "sg:address":"1010 S Joliet St",
    "sg:city":"Aurora",
    "sg:classifiers":[
        {
            "category":"Organizations",
            "subcategory":"Non-profit Organization",
            "type":"Services"
        }
    ],
    "sg:phone":"+1 303 361 9895",
    "sg:postcode":"80012",
    "sg:province":"CO",
    "sg:tags":[
        "info",
        "addiction",
        "abuse",
        "treatment",
        "drug"
    ],
    "wof:name":"Peoria Treatment Ctr",
    "wof:placetype":"venue"
},
  "geometry": {"coordinates":[-104.861186,39.696756],"type":"Point"}
}