{
  "type": "Feature",
  "properties": {
    "iso:country":"US",
    "sg:address":"10595 E Empire Dr",
    "sg:city":"Franktown",
    "sg:classifiers":[
        {
            "category":"Shopping",
            "type":"Retail Goods"
        }
    ],
    "sg:phone":"+1 303 688 2737",
    "sg:postcode":"80116",
    "sg:province":"CO",
    "sg:tags":[
        "merchandise"
    ],
    "wof:name":"Golden Opportunities",
    "wof:placetype":"venue"
},
  "geometry": {"coordinates":[-104.688619,39.344496],"type":"Point"}
}