{
  "type": "Feature",
  "properties": {
    "addr:full":"9536 W Avalon Dr Littleton CO 80127",
    "addr:housenumber":"9536",
    "addr:postcode":"80127",
    "addr:street":"W Avalon Dr",
    "iso:country":"US",
    "sg:address":"9536 W Avalon Dr",
    "sg:city":"Littleton",
    "sg:classifiers":[
        {
            "category":"Building & Trades",
            "subcategory":"Construction",
            "type":"Services"
        }
    ],
    "sg:phone":"+1 303 933 7130",
    "sg:postcode":"80127",
    "sg:province":"CO",
    "sg:tags":[
        "floor",
        "laying",
        "contractor"
    ],
    "wof:name":"Nielsen Enterprise Inc",
    "wof:placetype":"venue"
},
  "geometry": {"coordinates":[-105.105582,39.545513],"type":"Point"}
}