{
  "type": "Feature",
  "properties": {
    "iso:country":"US",
    "sg:address":"4950 Nome St",
    "sg:city":"Denver",
    "sg:classifiers":[
        {
            "category":"Autos & Motor Vehicles",
            "subcategory":"Auto Supplies",
            "type":"Retail Goods"
        }
    ],
    "sg:phone":"+1 303 371 8700",
    "sg:postcode":"80239",
    "sg:province":"CO",
    "sg:tags":[
        "automobile",
        "stereo",
        "radio"
    ],
    "wof:name":"Dashworks",
    "wof:placetype":"venue"
},
  "geometry": {"coordinates":[-104.8526,39.789174],"type":"Point"}
}