{
  "type": "Feature",
  "properties": {
    "addr:full":"9 N 32nd St Colorado Springs CO 80904",
    "addr:housenumber":"9",
    "addr:postcode":"80904",
    "addr:street":"N 32Nd St",
    "iso:country":"US",
    "sg:address":"9 N 32nd St",
    "sg:city":"Colorado Springs",
    "sg:classifiers":[
        {
            "category":"Manufacturing",
            "subcategory":"Retail Goods",
            "type":"Manufacturing & Wholesale Goods"
        }
    ],
    "sg:phone":"+1 719 632 7193",
    "sg:postcode":"80904",
    "sg:province":"CO",
    "sg:tags":[
        "device",
        "operator",
        "product",
        "amusement",
        "mfg"
    ],
    "wof:name":"ENE Music Co",
    "wof:placetype":"venue"
},
  "geometry": {"coordinates":[-104.87421500000001,38.856694],"type":"Point"}
}