{
  "type": "Feature",
  "properties": {
    "iso:country":"US",
    "sg:address":"5201 E 58th Ave",
    "sg:city":"Commerce City",
    "sg:classifiers":[
        {
            "category":"Freight",
            "type":"Transportation"
        }
    ],
    "sg:phone":"+1 303 227 0427",
    "sg:postcode":"80022",
    "sg:province":"CO",
    "wof:name":"Roads West Transportation",
    "wof:placetype":"venue"
},
  "geometry": {"coordinates":[-104.927083,39.801926],"type":"Point"}
}