{
  "type": "Feature",
  "properties": {
    "addr:full":"119 Huron Ct Boulder CO 80303",
    "addr:housenumber":"119",
    "addr:postcode":"80303",
    "addr:street":"Huron Ct",
    "iso:country":"US",
    "sg:address":"119 Huron Ct",
    "sg:city":"Boulder",
    "sg:classifiers":[
        {
            "category":"Professional",
            "subcategory":"Computer Services",
            "type":"Services"
        }
    ],
    "sg:phone":"+1 303 499 5152",
    "sg:postcode":"80303",
    "sg:province":"CO",
    "sg:tags":[
        "repair"
    ],
    "wof:name":"Premier Computers",
    "wof:placetype":"venue"
},
  "geometry": {"coordinates":[-105.222742,39.987276],"type":"Point"}
}