{
  "type": "Feature",
  "properties": {
    "iso:country":"US",
    "sg:address":"2186 S Jackson St",
    "sg:city":"Denver",
    "sg:classifiers":[
        {
            "category":"Building & Trades",
            "subcategory":"Construction",
            "type":"Services"
        }
    ],
    "sg:phone":"+1 303 935 2663",
    "sg:postcode":"80210",
    "sg:province":"CO",
    "sg:tags":[
        "contractor"
    ],
    "wof:name":"Mc Stone & Tile",
    "wof:placetype":"venue"
},
  "geometry": {"coordinates":[-104.943647,39.676814],"type":"Point"}
}