{
  "type": "Feature",
  "properties": {
    "iso:country":"US",
    "sg:address":"300 S Dahlia St",
    "sg:city":"Denver",
    "sg:classifiers":[
        {
            "category":"Organizations",
            "subcategory":"Non-profit Organization",
            "type":"Services"
        }
    ],
    "sg:phone":"+1 303 321 3399",
    "sg:postcode":"80246",
    "sg:province":"CO",
    "sg:tags":[
        "fund",
        "counselor",
        "raising"
    ],
    "sg:website":"www.jewishcolorado.org",
    "wof:name":"Allied Jewish Federation Colo",
    "wof:placetype":"venue"
},
  "geometry": {"coordinates":[-104.93153,39.709088],"type":"Point"}
}