{
  "type": "Feature",
  "properties": {
    "addr:full":"7139 Pecos St Denver CO 80221",
    "addr:housenumber":"7139",
    "addr:postcode":"80221",
    "addr:street":"Pecos St",
    "iso:country":"US",
    "sg:address":"7139 Pecos St",
    "sg:city":"Denver",
    "sg:classifiers":[
        {
            "category":"Arena",
            "subcategory":"Indoor Arena",
            "type":"Entertainment"
        }
    ],
    "sg:phone":"+1 303 657 1851",
    "sg:postcode":"80221",
    "sg:province":"CO",
    "sg:tags":[
        "bingo",
        "hall"
    ],
    "wof:name":"Turn To Bingo",
    "wof:placetype":"venue"
},
  "geometry": {"coordinates":[-105.006157,39.826843],"type":"Point"}
}