{
  "type": "Feature",
  "properties": {
    "iso:country":"US",
    "sg:address":"9665 W Danzig Pl",
    "sg:city":"Littleton",
    "sg:classifiers":[
        {
            "category":"Banks & Credit Unions",
            "subcategory":"Bank",
            "type":"Services"
        }
    ],
    "sg:phone":"+1 303 972 1891",
    "sg:postcode":"80127",
    "sg:province":"CO",
    "sg:tags":[
        "loan",
        "real estate"
    ],
    "wof:name":"Western Financial Group",
    "wof:placetype":"venue"
},
  "geometry": {"coordinates":[-105.10719400000001,39.541315],"type":"Point"}
}