{
  "type": "Feature",
  "properties": {
    "addr:full":"1014 S Jason St Denver CO 80223",
    "addr:housenumber":"1014",
    "addr:postcode":"80223",
    "addr:street":"S Jason St",
    "iso:country":"US",
    "sg:address":"1014 S Jason St",
    "sg:city":"Denver",
    "sg:classifiers":[
        {
            "category":"Building & Trades",
            "subcategory":"Plumbing",
            "type":"Services"
        }
    ],
    "sg:phone":"+1 303 871 1908",
    "sg:postcode":"80223",
    "sg:province":"CO",
    "sg:tags":[
        "plumbing",
        "contractor"
    ],
    "wof:name":"A Reliable Plumbing Inc",
    "wof:placetype":"venue"
},
  "geometry": {"coordinates":[-104.999077,39.696846],"type":"Point"}
}