{
  "type": "Feature",
  "properties": {
    "iso:country":"US",
    "sg:address":"10 9th Ave",
    "sg:city":"Longmont",
    "sg:classifiers":[
        {
            "category":"Shopping",
            "subcategory":"Computers & Home Electronics",
            "type":"Retail Goods"
        }
    ],
    "sg:phone":"+1 303 678 1065",
    "sg:postcode":"80501",
    "sg:province":"CO",
    "wof:name":"American Satellite TV System",
    "wof:placetype":"venue"
},
  "geometry": {"coordinates":[-105.094669,40.174],"type":"Point"}
}