{
  "type": "Feature",
  "properties": {
    "iso:country":"US",
    "sg:address":"1734 W 6th St",
    "sg:city":"Las Animas",
    "sg:classifiers":[
        {
            "category":"Real Estate",
            "subcategory":"Real Estate Agent",
            "type":"Services"
        }
    ],
    "sg:phone":"+1 719 456 1144",
    "sg:postcode":"81054",
    "sg:province":"CO",
    "sg:tags":[
        "appraiser"
    ],
    "wof:name":"Bogner Appraisal Svc",
    "wof:placetype":"venue"
},
  "geometry": {"coordinates":[-103.239138,38.066523],"type":"Point"}
}