{
  "type": "Feature",
  "properties": {
    "iso:country":"US",
    "sg:address":"2630 Stoneridge Dr",
    "sg:city":"Colorado Springs",
    "sg:classifiers":[
        {
            "category":"Manufacturing",
            "subcategory":"Toys & Sporting Goods",
            "type":"Manufacturing & Wholesale Goods"
        }
    ],
    "sg:phone":"+1 719 327 2900",
    "sg:postcode":"80919",
    "sg:province":"CO",
    "sg:tags":[
        "mfg"
    ],
    "wof:name":"CHI Energy",
    "wof:placetype":"venue"
},
  "geometry": {"coordinates":[-104.874994,38.906687],"type":"Point"}
}