{
  "type": "Feature",
  "properties": {
    "iso:country":"US",
    "sg:address":"5250 N Nevada Ave",
    "sg:city":"Colorado Springs",
    "sg:classifiers":[
        {
            "category":"Professional",
            "type":"Services"
        }
    ],
    "sg:phone":"+1 719 260 8573",
    "sg:postcode":"80918",
    "sg:province":"CO",
    "sg:tags":[
        "establishment"
    ],
    "wof:name":"Redwood Toxology Inc",
    "wof:placetype":"venue"
},
  "geometry": {"coordinates":[-104.816939,38.905819],"type":"Point"}
}