{
  "type": "Feature",
  "properties": {
    "addr:full":"19643 E Girard Dr Aurora CO 80013",
    "addr:housenumber":"19643",
    "addr:postcode":"80013",
    "addr:street":"E Girard Dr",
    "iso:country":"US",
    "sg:address":"19643 E Girard Dr",
    "sg:city":"Aurora",
    "sg:classifiers":[
        {
            "category":"Building & Trades",
            "subcategory":"Landscaping Services",
            "type":"Services"
        }
    ],
    "sg:phone":"+1 303 690 6429",
    "sg:postcode":"80013",
    "sg:province":"CO",
    "sg:tags":[
        "landscape",
        "contractor"
    ],
    "wof:name":"J & K Landscaping Svc",
    "wof:placetype":"venue"
},
  "geometry": {"coordinates":[-104.757903,39.654241],"type":"Point"}
}