{
  "type": "Feature",
  "properties": {
    "iso:country":"US",
    "sg:address":"11854 S Breeze Grass Way",
    "sg:city":"Parker",
    "sg:classifiers":[
        {
            "category":"Internet Cafe",
            "subcategory":"None",
            "type":"Food & Drink"
        }
    ],
    "sg:phone":"+1 720 851 6528",
    "sg:postcode":"80134",
    "sg:province":"CO",
    "sg:tags":[
        "assigned",
        "heading"
    ],
    "wof:name":"Kelly Minerals",
    "wof:placetype":"venue"
},
  "geometry": {"coordinates":[-104.80541599999999,39.501038],"type":"Point"}
}