{
  "type": "Feature",
  "properties": {
    "iso:country":"US",
    "sg:address":"8801 Creekside Way",
    "sg:city":"Littleton",
    "sg:classifiers":[
        {
            "category":"Banks & Credit Unions",
            "subcategory":"Financial Services",
            "type":"Services"
        }
    ],
    "sg:phone":"+1 720 344 0658",
    "sg:postcode":"80129",
    "sg:province":"CO",
    "sg:tags":[
        "investor"
    ],
    "wof:name":"C & B Aircraft Investment",
    "wof:placetype":"venue"
},
  "geometry": {"coordinates":[-105.015123,39.552226],"type":"Point"}
}