{
  "type": "Feature",
  "properties": {
    "addr:full":"38334 US Hwy 24 Lake George CO 80827",
    "addr:postcode":"38334;80827",
    "addr:street":"Us Hwy 24",
    "iso:country":"US",
    "sg:address":"38334 US Hwy 24",
    "sg:city":"Lake George",
    "sg:classifiers":[
        {
            "category":"Professional",
            "type":"Services"
        },
        {
            "category":"Building & Trades",
            "subcategory":"Construction",
            "type":"Services"
        }
    ],
    "sg:phone":"+1 719 748 0159",
    "sg:postcode":"80827",
    "sg:province":"CO",
    "sg:tags":[
        "establishment",
        "contractor"
    ],
    "wof:name":"R A Waffensmith & Company Inc",
    "wof:placetype":"venue"
},
  "geometry": {"coordinates":[-105.35654700000001,38.979121],"type":"Point"}
}