{
  "type": "Feature",
  "properties": {
    "addr:full":"6794 S Yates Ct Littleton CO 80128",
    "addr:housenumber":"6794",
    "addr:postcode":"80128",
    "addr:street":"S Yates Ct",
    "iso:country":"US",
    "sg:address":"6794 S Yates Ct",
    "sg:city":"Littleton",
    "sg:classifiers":[
        {
            "category":"Farming",
            "subcategory":"Livestock Farm",
            "type":"Manufacturing & Wholesale Goods"
        }
    ],
    "sg:phone":"+1 303 972 5866",
    "sg:postcode":"80128",
    "sg:province":"CO",
    "sg:tags":[
        "animal",
        "general"
    ],
    "wof:name":"Blue Moon Ranches LLC",
    "wof:placetype":"venue"
},
  "geometry": {"coordinates":[-105.05093599999999,39.5938],"type":"Point"}
}