{
  "type": "Feature",
  "properties": {
    "addr:full":"165 2nd St SW Loveland CO 80537",
    "addr:housenumber":"165",
    "addr:postcode":"80537",
    "addr:street":"2Nd St Sw",
    "iso:country":"US",
    "sg:address":"165 2nd St SW",
    "sg:city":"Loveland",
    "sg:classifiers":[
        {
            "category":"Professional",
            "subcategory":"Engineering",
            "type":"Services"
        }
    ],
    "sg:phone":"+1 970 667 8010",
    "sg:postcode":"80537",
    "sg:province":"CO",
    "sg:tags":[
        "laboratory",
        "consulting",
        "testing",
        "surveying"
    ],
    "wof:name":"Cds Engineering Corporation",
    "wof:placetype":"venue"
},
  "geometry": {"coordinates":[-105.07747999999999,40.391834],"type":"Point"}
}