{
  "type": "Feature",
  "properties": {
    "addr:full":"193 Sweetwater Rd Gypsum CO 81637",
    "addr:housenumber":"193",
    "addr:postcode":"81637",
    "addr:street":"Sweetwater Rd",
    "iso:country":"US",
    "sg:address":"193 Sweetwater Rd",
    "sg:city":"Gypsum",
    "sg:classifiers":[
        {
            "category":"Professional",
            "type":"Services"
        }
    ],
    "sg:phone":"+1 970 524 1455",
    "sg:postcode":"81637",
    "sg:province":"CO",
    "sg:tags":[
        "establishment"
    ],
    "wof:name":"Sweetwater Perennials",
    "wof:placetype":"venue"
},
  "geometry": {"coordinates":[-107.05032300000001,39.726479],"type":"Point"}
}