{
  "type": "Feature",
  "properties": {
    "iso:country":"US",
    "sg:address":"5496 S Parker Rd",
    "sg:city":"Aurora",
    "sg:classifiers":[
        {
            "category":"Personal",
            "subcategory":"Beauty Salon",
            "type":"Services"
        }
    ],
    "sg:phone":"+1 303 680 7121",
    "sg:postcode":"80015",
    "sg:province":"CO",
    "sg:tags":[
        "hair",
        "stylist"
    ],
    "sg:website":"http://www.hairrx.net",
    "wof:name":"HairRx Salon",
    "wof:placetype":"venue"
},
  "geometry": {"coordinates":[-104.817095,39.615745],"type":"Point"}
}