{
  "type": "Feature",
  "properties": {
    "iso:country":"US",
    "sg:address":"8335 Feather Grass Ct",
    "sg:city":"Parker",
    "sg:classifiers":[
        {
            "category":"Building & Trades",
            "subcategory":"Construction",
            "type":"Services"
        }
    ],
    "sg:phone":"+1 720 323 1298",
    "sg:postcode":"80134",
    "sg:province":"CO",
    "sg:tags":[
        "resurfacing",
        "laying",
        "refinishing",
        "floor"
    ],
    "wof:name":"Barta Flooring",
    "wof:placetype":"venue"
},
  "geometry": {"coordinates":[-104.802132,39.565557],"type":"Point"}
}