{
  "type": "Feature",
  "properties": {
    "iso:country":"US",
    "sg:address":"3485 W 1st Ave",
    "sg:city":"Denver",
    "sg:classifiers":[
        {
            "category":"Professional",
            "type":"Services"
        }
    ],
    "sg:phone":"+1 303 936 1213",
    "sg:postcode":"80219",
    "sg:province":"CO",
    "sg:tags":[
        "establishment"
    ],
    "wof:name":"Arroma A Tile Inc",
    "wof:placetype":"venue"
},
  "geometry": {"coordinates":[-105.032972,39.718228],"type":"Point"}
}