{
  "type": "Feature",
  "properties": {
    "addr:full":"17960 E Dorado Dr Aurora CO 80015",
    "addr:housenumber":"17960",
    "addr:postcode":"80015",
    "addr:street":"E Dorado Dr",
    "iso:country":"US",
    "sg:address":"17960 E Dorado Dr",
    "sg:city":"Aurora",
    "sg:classifiers":[
        {
            "category":"Real Estate",
            "subcategory":"Real Estate Agent",
            "type":"Services"
        }
    ],
    "sg:phone":"+1 303 756 8300",
    "sg:postcode":"80015",
    "sg:province":"CO",
    "wof:name":"Claim Jumper Realty LLC",
    "wof:placetype":"venue"
},
  "geometry": {"coordinates":[-104.779827,39.612036],"type":"Point"}
}