{
  "type": "Feature",
  "properties": {
    "iso:country":"US",
    "sg:address":"591 N Murray Blvd",
    "sg:city":"Colorado Springs",
    "sg:classifiers":[
        {
            "category":"Retail",
            "subcategory":"Laundry & Dry Cleaning",
            "type":"Services"
        },
        {
            "category":"Shopping",
            "subcategory":"Clothing, Apparel, & Fashions",
            "type":"Retail Goods"
        }
    ],
    "sg:phone":"+1 719 591 9978",
    "sg:postcode":"80915",
    "sg:province":"CO",
    "sg:tags":[
        "alteration"
    ],
    "wof:name":"Linda's Tailoring",
    "wof:placetype":"venue"
},
  "geometry": {"coordinates":[-104.747958,38.841884],"type":"Point"}
}