{
  "type": "Feature",
  "properties": {
    "addr:full":"1747 Pearl Street Denver CO 80203",
    "addr:housenumber":"1747",
    "addr:postcode":"80203",
    "addr:street":"Pearl Street",
    "iso:country":"US",
    "sg:address":"1747 Pearl Street",
    "sg:city":"Denver",
    "sg:classifiers":[
        {
            "category":"Health Services",
            "subcategory":"Doctor",
            "type":"Services"
        }
    ],
    "sg:phone":"+1 303 894 0228",
    "sg:postcode":"80203",
    "sg:province":"CO",
    "wof:name":"Web MD",
    "wof:placetype":"venue"
},
  "geometry": {"coordinates":[-104.97992000000001,39.744029],"type":"Point"}
}