{
  "type": "Feature",
  "properties": {
    "iso:country":"US",
    "sg:address":"1540 Barber Dr",
    "sg:city":"Carbondale",
    "sg:classifiers":[
        {
            "category":"Professional",
            "subcategory":"Computer Services",
            "type":"Services"
        }
    ],
    "sg:phone":"+1 970 379 4554",
    "sg:postcode":"81623",
    "sg:province":"CO",
    "wof:name":"Ute City Ware",
    "wof:placetype":"venue"
},
  "geometry": {"coordinates":[-107.223176,39.398548],"type":"Point"}
}