{
  "type": "Feature",
  "properties": {
    "iso:country":"US",
    "sg:address":"2000 Coronado Pkwy N",
    "sg:city":"Thornton",
    "sg:classifiers":[
        {
            "category":"Retail",
            "subcategory":"Auto Rental",
            "type":"Services"
        }
    ],
    "sg:phone":"+1 303 439 2574",
    "sg:postcode":"80229",
    "sg:province":"CO",
    "sg:tags":[
        "renting",
        "truck",
        "leasing"
    ],
    "wof:name":"U-Haul Co",
    "wof:placetype":"venue"
},
  "geometry": {"coordinates":[-104.964735,39.842073],"type":"Point"}
}