{
  "type": "Feature",
  "properties": {
    "iso:country":"US",
    "sg:address":"401 3rd Ave",
    "sg:city":"Longmont",
    "sg:classifiers":[
        {
            "category":"Restaurant",
            "type":"Food & Drink"
        }
    ],
    "sg:phone":"+1 303 651 7256",
    "sg:postcode":"80501",
    "sg:province":"CO",
    "sg:tags":[
        "eating"
    ],
    "wof:name":"Fong Garden Restaurant",
    "wof:placetype":"venue"
},
  "geometry": {"coordinates":[-105.10118900000001,40.163934],"type":"Point"}
}