{
  "type": "Feature",
  "properties": {
    "iso:country":"US",
    "sg:address":"451 E 58th Ave",
    "sg:city":"Denver",
    "sg:classifiers":[
        {
            "category":"Wholesale",
            "subcategory":"Non-durable Goods",
            "type":"Manufacturing & Wholesale Goods"
        }
    ],
    "sg:phone":"+1 303 296 3288",
    "sg:postcode":"80216",
    "sg:province":"CO",
    "wof:name":"One Coast-Lee Too",
    "wof:placetype":"venue"
},
  "geometry": {"coordinates":[-104.97712900000001,39.80195],"type":"Point"}
}