{
  "type": "Feature",
  "properties": {
    "iso:country":"US",
    "sg:address":"6666 E Stapleton Drive S",
    "sg:city":"Denver",
    "sg:classifiers":[
        {
            "category":"Wholesale",
            "subcategory":"Computers",
            "type":"Manufacturing & Wholesale Goods"
        }
    ],
    "sg:phone":"+1 303 393 0027",
    "sg:postcode":"80216",
    "sg:province":"CO",
    "wof:name":"Copy Vend",
    "wof:placetype":"venue"
},
  "geometry": {"coordinates":[-104.91152700000001,39.777877],"type":"Point"}
}