{
  "type": "Feature",
  "properties": {
    "addr:full":"7308 S Alton Way Centennial CO 80112",
    "addr:housenumber":"7308",
    "addr:postcode":"80112",
    "addr:street":"S Alton Way",
    "iso:country":"US",
    "sg:address":"7308 S Alton Way",
    "sg:city":"Centennial",
    "sg:classifiers":[
        {
            "category":"Health Services",
            "subcategory":"Clinic",
            "type":"Services"
        }
    ],
    "sg:phone":"+1 303 770 5065",
    "sg:postcode":"80112",
    "sg:province":"CO",
    "sg:tags":[
        "home"
    ],
    "wof:name":"Westcare Infusion Svc",
    "wof:placetype":"venue"
},
  "geometry": {"coordinates":[-104.884477,39.582193],"type":"Point"}
}