{
  "type": "Feature",
  "properties": {
    "addr:full":"2250 E Jewell Avenue Denver CO 80210",
    "addr:housenumber":"2250",
    "addr:postcode":"80210",
    "addr:street":"E Jewell Avenue",
    "iso:country":"US",
    "sg:address":"2250 E Jewell Avenue",
    "sg:city":"Denver",
    "sg:classifiers":[
        {
            "category":"Education",
            "subcategory":"University",
            "type":"Public Place"
        }
    ],
    "sg:phone":"+1 303 871 2336",
    "sg:postcode":"80210",
    "sg:province":"CO",
    "sg:tags":[
        "college"
    ],
    "wof:name":"University of Denver",
    "wof:placetype":"venue"
},
  "geometry": {"coordinates":[-104.9606,39.682052],"type":"Point"}
}