{
  "type": "Feature",
  "properties": {
    "iso:country":"US",
    "sg:address":"10325 State Hwy 194",
    "sg:city":"Las Animas",
    "sg:classifiers":[
        {
            "category":"Farming",
            "subcategory":"Farm",
            "type":"Manufacturing & Wholesale Goods"
        }
    ],
    "sg:phone":"+1 719 456 2735",
    "sg:postcode":"81054",
    "sg:province":"CO",
    "sg:tags":[
        "crop",
        "general"
    ],
    "wof:name":"David Gardner",
    "wof:placetype":"venue"
},
  "geometry": {"coordinates":[-103.22845700000001,38.084885],"type":"Point"}
}