{
  "type": "Feature",
  "properties": {
    "iso:country":"US",
    "sg:address":"7061 S University Blvd",
    "sg:city":"Centennial",
    "sg:classifiers":[
        {
            "category":"Organizations",
            "subcategory":"Non-profit Organization",
            "type":"Services"
        },
        {
            "category":"Social Services",
            "type":"Services"
        }
    ],
    "sg:phone":"+1 303 694 9706",
    "sg:postcode":"80122",
    "sg:province":"CO",
    "sg:tags":[
        "disability"
    ],
    "wof:name":"Opportunity In Living",
    "wof:placetype":"venue"
},
  "geometry": {"coordinates":[-104.960273,39.590101],"type":"Point"}
}