{
  "type": "Feature",
  "properties": {
    "addr:full":"18883 E Hampden Ave Aurora CO 80013",
    "addr:housenumber":"18883",
    "addr:postcode":"80013",
    "addr:street":"E Hampden Ave",
    "iso:country":"US",
    "sg:address":"18883 E Hampden Ave",
    "sg:city":"Aurora",
    "sg:classifiers":[
        {
            "category":"Insurance",
            "subcategory":"Insurance Agent",
            "type":"Services"
        }
    ],
    "sg:phone":"+1 303 699 0540",
    "sg:postcode":"80013",
    "sg:province":"CO",
    "wof:name":"Allstate",
    "wof:placetype":"venue"
},
  "geometry": {"coordinates":[-104.770574,39.653105],"type":"Point"}
}