{
  "type": "Feature",
  "properties": {
    "iso:country":"US",
    "sg:address":"10217 Andee Way",
    "sg:city":"Littleton",
    "sg:classifiers":[
        {
            "category":"Manufacturing",
            "subcategory":"Printing",
            "type":"Manufacturing & Wholesale Goods"
        }
    ],
    "sg:phone":"+1 720 344 6606",
    "sg:postcode":"80130",
    "sg:province":"CO",
    "sg:tags":[
        "newspaper",
        "publishing"
    ],
    "wof:name":"E W Scripps Company",
    "wof:placetype":"venue"
},
  "geometry": {"coordinates":[-104.91378,39.530701],"type":"Point"}
}