{
  "type": "Feature",
  "properties": {
    "iso:country":"US",
    "sg:address":"406 Catalina Dr",
    "sg:city":"Colorado Springs",
    "sg:classifiers":[
        {
            "category":"Real Estate",
            "subcategory":"Real Estate Agent",
            "type":"Services"
        }
    ],
    "sg:phone":"+1 719 227 1172",
    "sg:postcode":"80906",
    "sg:province":"CO",
    "wof:name":"Theresa Bennett",
    "wof:placetype":"venue"
},
  "geometry": {"coordinates":[-104.79352799999999,38.778089],"type":"Point"}
}