{
  "type": "Feature",
  "properties": {
    "addr:full":"10456 Lipan St Denver CO 80234",
    "addr:housenumber":"10456",
    "addr:postcode":"80234",
    "addr:street":"Lipan St",
    "iso:country":"US",
    "sg:address":"10456 Lipan St",
    "sg:city":"Denver",
    "sg:classifiers":[
        {
            "category":"Wholesale",
            "subcategory":"Furniture",
            "type":"Manufacturing & Wholesale Goods"
        }
    ],
    "sg:phone":"+1 303 452 5377",
    "sg:postcode":"80234",
    "sg:province":"CO",
    "wof:name":"Robert Shurte & Associates",
    "wof:placetype":"venue"
},
  "geometry": {"coordinates":[-105.001135,39.887323],"type":"Point"}
}