{
  "type": "Feature",
  "properties": {
    "iso:country":"US",
    "sg:address":"515 N Erie Ave",
    "sg:city":"Pueblo",
    "sg:classifiers":[
        {
            "category":"Retail",
            "subcategory":"Laundry & Dry Cleaning",
            "type":"Services"
        }
    ],
    "sg:phone":"+1 719 778 0931",
    "sg:postcode":"81001",
    "sg:province":"CO",
    "wof:name":"Lady Fair Coin Laundries",
    "wof:placetype":"venue"
},
  "geometry": {"coordinates":[-104.599867,38.271899],"type":"Point"}
}