{
  "type": "Feature",
  "properties": {
    "addr:full":"31491 Shadow Mountain Dr Conifer CO 80433",
    "addr:housenumber":"31491",
    "addr:postcode":"80433",
    "addr:street":"Shadow Mountain Dr",
    "iso:country":"US",
    "sg:address":"31491 Shadow Mountain Dr",
    "sg:city":"Conifer",
    "sg:classifiers":[
        {
            "category":"Building & Trades",
            "subcategory":"Construction",
            "type":"Services"
        }
    ],
    "sg:phone":"+1 303 674 4669",
    "sg:postcode":"80433",
    "sg:province":"CO",
    "sg:tags":[
        "contractor"
    ],
    "wof:name":"Tile Artisan",
    "wof:placetype":"venue"
},
  "geometry": {"coordinates":[-105.357484,39.540102],"type":"Point"}
}