{
  "type": "Feature",
  "properties": {
    "addr:full":"8478 S Castaway Dr Fort Collins CO 80528",
    "addr:housenumber":"8478",
    "addr:postcode":"80528",
    "addr:street":"S Castaway Dr",
    "iso:country":"US",
    "sg:address":"8478 S Castaway Dr",
    "sg:city":"Fort Collins",
    "sg:classifiers":[
        {
            "category":"Shopping",
            "type":"Retail Goods"
        }
    ],
    "sg:phone":"+1 970 204 1114",
    "sg:postcode":"80528",
    "sg:province":"CO",
    "sg:tags":[
        "cosmetic",
        "perfume"
    ],
    "wof:name":"Mary Kay",
    "wof:placetype":"venue"
},
  "geometry": {"coordinates":[-104.981376,40.465629],"type":"Point"}
}