{
  "type": "Feature",
  "properties": {
    "addr:full":"1800 S 120th St Lafayette CO 80026",
    "addr:housenumber":"1800",
    "addr:postcode":"80026",
    "addr:street":"S 120Th St",
    "iso:country":"US",
    "sg:address":"1800 S 120th St",
    "sg:city":"Lafayette",
    "sg:classifiers":[
        {
            "category":"Professional",
            "subcategory":"Advertising",
            "type":"Services"
        }
    ],
    "sg:phone":"+1 303 604 2092",
    "sg:postcode":"80026",
    "sg:province":"CO",
    "sg:tags":[
        "guide"
    ],
    "wof:name":"Downs-Kingston Publishing Inc",
    "wof:placetype":"venue"
},
  "geometry": {"coordinates":[-105.07193700000001,39.957938],"type":"Point"}
}