{
  "type": "Feature",
  "properties": {
    "iso:country":"US",
    "sg:address":"5500 E Yale Ave",
    "sg:city":"Denver",
    "sg:classifiers":[
        {
            "category":"Professional",
            "subcategory":"Lawyer & Legal Services",
            "type":"Services"
        }
    ],
    "sg:phone":"+1 303 504 4737",
    "sg:postcode":"80222",
    "sg:province":"CO",
    "sg:tags":[
        "personal",
        "injury"
    ],
    "wof:name":"Peters James J",
    "wof:placetype":"venue"
},
  "geometry": {"coordinates":[-104.922997,39.667702],"type":"Point"}
}