{
  "type": "Feature",
  "properties": {
    "iso:country":"US",
    "sg:address":"17745 E Dorado Dr",
    "sg:city":"Aurora",
    "sg:classifiers":[
        {
            "category":"Restaurant",
            "type":"Food & Drink"
        }
    ],
    "sg:phone":"+1 303 617 0575",
    "sg:postcode":"80015",
    "sg:province":"CO",
    "sg:tags":[
        "eating"
    ],
    "wof:name":"Maj Pizza Inc",
    "wof:placetype":"venue"
},
  "geometry": {"coordinates":[-104.783804,39.61234],"type":"Point"}
}