{
  "type": "Feature",
  "properties": {
    "addr:full":"205 Elm St Julesburg CO 80737",
    "addr:housenumber":"205",
    "addr:postcode":"80737",
    "addr:street":"Elm St",
    "iso:country":"US",
    "sg:address":"205 Elm St",
    "sg:city":"Julesburg",
    "sg:classifiers":[
        {
            "category":"Insurance",
            "subcategory":"Insurance Agent",
            "type":"Services"
        }
    ],
    "sg:phone":"+1 970 474 2601",
    "sg:postcode":"80737",
    "sg:province":"CO",
    "wof:name":"Kansas City Life Insurance Co",
    "wof:placetype":"venue"
},
  "geometry": {"coordinates":[-102.262449,40.988345],"type":"Point"}
}