{
  "type": "Feature",
  "properties": {
    "addr:full":"5565 E Yale Ave Denver CO 80222",
    "addr:housenumber":"5565",
    "addr:postcode":"80222",
    "addr:street":"E Yale Ave",
    "iso:country":"US",
    "sg:address":"5565 E Yale Ave",
    "sg:city":"Denver",
    "sg:classifiers":[
        {
            "category":"Real Estate",
            "subcategory":"Real Estate Operator",
            "type":"Services"
        }
    ],
    "sg:phone":"+1 303 691 0263",
    "sg:postcode":"80222",
    "sg:province":"CO",
    "sg:tags":[
        "building",
        "apartment"
    ],
    "wof:name":"Koclanes Investments",
    "wof:placetype":"venue"
},
  "geometry": {"coordinates":[-104.92224899999999,39.667504],"type":"Point"}
}