{
  "type": "Feature",
  "properties": {
    "addr:full":"1615 Downing St Denver CO 80218",
    "addr:housenumber":"1615",
    "addr:postcode":"80218",
    "addr:street":"Downing St",
    "iso:country":"US",
    "sg:address":"1615 Downing St",
    "sg:city":"Denver",
    "sg:classifiers":[
        {
            "category":"Building & Trades",
            "subcategory":"Locksmith",
            "type":"Services"
        }
    ],
    "sg:phone":"+1 866 373 0323",
    "sg:postcode":"80218",
    "sg:province":"CO",
    "sg:tags":[
        "key"
    ],
    "wof:name":"24 Hour Locksmith Service",
    "wof:placetype":"venue"
},
  "geometry": {"coordinates":[-104.97358199999999,39.741881],"type":"Point"}
}