{
  "type": "Feature",
  "properties": {
    "iso:country":"US",
    "sg:address":"3055 Quail Wood Ct",
    "sg:city":"Grand Junction",
    "sg:classifiers":[
        {
            "category":"Manufacturing",
            "subcategory":"Metals",
            "type":"Manufacturing & Wholesale Goods"
        }
    ],
    "sg:phone":"+1 970 523 1059",
    "sg:postcode":"81504",
    "sg:province":"CO",
    "sg:tags":[
        "shop",
        "sheet"
    ],
    "wof:name":"McHones Metal",
    "wof:placetype":"venue"
},
  "geometry": {"coordinates":[-108.486419,39.068145],"type":"Point"}
}