{
  "type": "Feature",
  "properties": {
    "iso:country":"US",
    "sg:address":"276 Eagle Dr",
    "sg:city":"Golden",
    "sg:classifiers":[
        {
            "category":"Banks & Credit Unions",
            "subcategory":"Investment Brokerage",
            "type":"Services"
        }
    ],
    "sg:phone":"+1 303 279 6503",
    "sg:postcode":"80403",
    "sg:province":"CO",
    "sg:tags":[
        "security"
    ],
    "wof:name":"Edward Jones 29629",
    "wof:placetype":"venue"
},
  "geometry": {"coordinates":[-105.234617,39.762554],"type":"Point"}
}