{
  "type": "Feature",
  "properties": {
    "iso:country":"US",
    "sg:address":"330 Field Ave",
    "sg:city":"Canon City",
    "sg:classifiers":[
        {
            "category":"Professional",
            "type":"Services"
        }
    ],
    "sg:phone":"+1 719 269 8213",
    "sg:postcode":"81212",
    "sg:province":"CO",
    "sg:tags":[
        "establishment"
    ],
    "wof:name":"Fontecchio Brothers",
    "wof:placetype":"venue"
},
  "geometry": {"coordinates":[-105.208608,38.450317],"type":"Point"}
}