{
  "type": "Feature",
  "properties": {
    "iso:country":"US",
    "sg:address":"1895 Co Rd 28",
    "sg:city":"Sedgwick",
    "sg:classifiers":[
        {
            "category":"Retail",
            "subcategory":"Veterinary Services",
            "type":"Services"
        }
    ],
    "sg:phone":"+1 970 463 8844",
    "sg:postcode":"80749",
    "sg:province":"CO",
    "wof:name":"D H Parker DVM",
    "wof:placetype":"venue"
},
  "geometry": {"coordinates":[-102.616148,40.939318],"type":"Point"}
}