{
  "type": "Feature",
  "properties": {
    "iso:country":"US",
    "sg:address":"1409 Gemini Cir",
    "sg:city":"Fruita",
    "sg:classifiers":[
        {
            "category":"Professional",
            "type":"Services"
        }
    ],
    "sg:phone":"+1 970 858 1251",
    "sg:postcode":"81521",
    "sg:province":"CO",
    "wof:name":"Helen L Carbone Etal",
    "wof:placetype":"venue"
},
  "geometry": {"coordinates":[-108.713313,39.164753],"type":"Point"}
}