{
  "type": "Feature",
  "properties": {
    "iso:country":"US",
    "sg:address":"6645 S Quemoy Cir",
    "sg:city":"Aurora",
    "sg:classifiers":[
        {
            "category":"Shopping",
            "subcategory":"Beauty & Cosmetics",
            "type":"Retail Goods"
        }
    ],
    "sg:phone":"+1 303 766 9515",
    "sg:postcode":"80016",
    "sg:province":"CO",
    "sg:tags":[
        "merchandise"
    ],
    "wof:name":"Mary Kay Cosmetics",
    "wof:placetype":"venue"
},
  "geometry": {"coordinates":[-104.734672,39.596786],"type":"Point"}
}