{
  "type": "Feature",
  "properties": {
    "iso:country":"US",
    "sg:address":"6311 W Brittany Pl",
    "sg:city":"Littleton",
    "sg:classifiers":[
        {
            "category":"Professional",
            "subcategory":"Business Services",
            "type":"Services"
        }
    ],
    "sg:phone":"+1 303 795 7616",
    "sg:postcode":"80123",
    "sg:province":"CO",
    "sg:tags":[
        "embroidery"
    ],
    "wof:name":"Columbine Copper & Embroidery",
    "wof:placetype":"venue"
},
  "geometry": {"coordinates":[-105.06877299999999,39.608779],"type":"Point"}
}