{
  "type": "Feature",
  "properties": {
    "addr:full":"11102 W Cooper Dr Littleton CO 80127",
    "addr:housenumber":"11102",
    "addr:postcode":"80127",
    "addr:street":"W Cooper Dr",
    "iso:country":"US",
    "sg:address":"11102 W Cooper Dr",
    "sg:city":"Littleton",
    "sg:classifiers":[
        {
            "category":"Shopping",
            "type":"Retail Goods"
        }
    ],
    "sg:phone":"+1 303 933 8426",
    "sg:postcode":"80127",
    "sg:province":"CO",
    "sg:tags":[
        "merchandise"
    ],
    "wof:name":"Web Stores Unlimited LLC",
    "wof:placetype":"venue"
},
  "geometry": {"coordinates":[-105.127438,39.59878],"type":"Point"}
}