{
  "type": "Feature",
  "properties": {
    "iso:country":"US",
    "sg:address":"5900 Federal Blvd",
    "sg:city":"Denver",
    "sg:classifiers":[
        {
            "category":"Shopping",
            "subcategory":"Used Merchandise",
            "type":"Retail Goods"
        }
    ],
    "sg:phone":"+1 303 480 3556",
    "sg:postcode":"80221",
    "sg:province":"CO",
    "sg:tags":[
        "shop",
        "thrift"
    ],
    "wof:name":"Goodwill Vehicle Donation",
    "wof:placetype":"venue"
},
  "geometry": {"coordinates":[-105.025204,39.803832],"type":"Point"}
}