{
  "type": "Feature",
  "properties": {
    "addr:full":"3782 Ponderosa Dr Evans CO 80620",
    "addr:housenumber":"3782",
    "addr:postcode":"80620",
    "addr:street":"Ponderosa Dr",
    "iso:country":"US",
    "sg:address":"3782 Ponderosa Dr",
    "sg:city":"Evans",
    "sg:classifiers":[
        {
            "category":"Real Estate",
            "subcategory":"Real Estate Operator",
            "type":"Services"
        }
    ],
    "sg:phone":"+1 970 352 7888",
    "sg:postcode":"80620",
    "sg:province":"CO",
    "sg:tags":[
        "condominium"
    ],
    "wof:name":"Fox Crossing Condominiums",
    "wof:placetype":"venue"
},
  "geometry": {"coordinates":[-104.74099,40.379357],"type":"Point"}
}