{
  "type": "Feature",
  "properties": {
    "iso:country":"US",
    "sg:address":"2160 S Broadway",
    "sg:city":"Denver",
    "sg:classifiers":[
        {
            "category":"Food & Beverages",
            "subcategory":"Groceries & Convenience Stores",
            "type":"Retail Goods"
        }
    ],
    "sg:phone":"+1 303 722 9430",
    "sg:postcode":"80210",
    "sg:province":"CO",
    "sg:website":"www.7-eleven.com",
    "wof:name":"Seven-Eleven Stores",
    "wof:placetype":"venue"
},
  "geometry": {"coordinates":[-104.98771,39.678063],"type":"Point"}
}