{
  "type": "Feature",
  "properties": {
    "iso:country":"US",
    "sg:address":"335 17th St",
    "sg:city":"Denver",
    "sg:classifiers":[
        {
            "category":"Shopping",
            "subcategory":"Florist",
            "type":"Retail Goods"
        }
    ],
    "sg:phone":"+1 303 292 3893",
    "sg:postcode":"80202",
    "sg:province":"CO",
    "wof:name":"Brown Palace Hotel Flower Shop",
    "wof:placetype":"venue"
},
  "geometry": {"coordinates":[-104.98800199999999,39.743898],"type":"Point"}
}