{
  "type": "Feature",
  "properties": {
    "iso:country":"US",
    "sg:address":"806 Yates St",
    "sg:city":"Denver",
    "sg:classifiers":[
        {
            "category":"Building & Trades",
            "subcategory":"Construction",
            "type":"Services"
        }
    ],
    "sg:phone":"+1 303 893 0486",
    "sg:postcode":"80204",
    "sg:province":"CO",
    "sg:tags":[
        "contractor"
    ],
    "wof:name":"Rafael C Contractor Stucco",
    "wof:placetype":"venue"
},
  "geometry": {"coordinates":[-105.050962,39.731171],"type":"Point"}
}