{
  "type": "Feature",
  "properties": {
    "iso:country":"US",
    "sg:address":"1720 S Bellaire St",
    "sg:city":"Denver",
    "sg:classifiers":[
        {
            "category":"Professional",
            "subcategory":"Lawyer & Legal Services",
            "type":"Services"
        }
    ],
    "sg:phone":"+1 303 300 1002",
    "sg:postcode":"80222",
    "sg:province":"CO",
    "sg:tags":[
        "firm",
        "attorney",
        "law"
    ],
    "wof:name":"Sutherland Tarler Laugesen P C",
    "wof:placetype":"venue"
},
  "geometry": {"coordinates":[-104.93725000000001,39.685283],"type":"Point"}
}