{
  "type": "Feature",
  "properties": {
    "addr:full":"8853 S Maplewood Dr Littleton CO 80126",
    "addr:housenumber":"8853",
    "addr:postcode":"80126",
    "addr:street":"S Maplewood Dr",
    "iso:country":"US",
    "sg:address":"8853 S Maplewood Dr",
    "sg:city":"Littleton",
    "sg:classifiers":[
        {
            "category":"Banks & Credit Unions",
            "subcategory":"Financial Services",
            "type":"Services"
        }
    ],
    "sg:phone":"+1 303 470 6679",
    "sg:postcode":"80126",
    "sg:province":"CO",
    "sg:tags":[
        "company",
        "holding"
    ],
    "wof:name":"M H Holdings",
    "wof:placetype":"venue"
},
  "geometry": {"coordinates":[-104.96654700000001,39.559331],"type":"Point"}
}