{
  "type": "Feature",
  "properties": {
    "addr:full":"105 1st St Fort Lupton CO 80621",
    "addr:housenumber":"105",
    "addr:postcode":"80621",
    "addr:street":"1St St",
    "iso:country":"US",
    "sg:address":"105 1st St",
    "sg:city":"Fort Lupton",
    "sg:classifiers":[
        {
            "category":"Food & Beverages",
            "subcategory":"Groceries & Convenience Stores",
            "type":"Retail Goods"
        }
    ],
    "sg:phone":"+1 303 857 4988",
    "sg:postcode":"80621",
    "sg:province":"CO",
    "sg:tags":[
        "station",
        "gas"
    ],
    "wof:name":"U Pump It",
    "wof:placetype":"venue"
},
  "geometry": {"coordinates":[-104.81831200000001,40.080217],"type":"Point"}
}