{
  "type": "Feature",
  "properties": {
    "addr:full":"5662 S Lansing Ct Englewood CO 80111",
    "addr:housenumber":"5662",
    "addr:postcode":"80111",
    "addr:street":"S Lansing Ct",
    "iso:country":"US",
    "sg:address":"5662 S Lansing Ct",
    "sg:city":"Englewood",
    "sg:classifiers":[
        {
            "category":"Professional",
            "type":"Services"
        }
    ],
    "sg:phone":"+1 303 694 4991",
    "sg:postcode":"80111",
    "sg:province":"CO",
    "wof:name":"Rush Bell",
    "wof:placetype":"venue"
},
  "geometry": {"coordinates":[-104.85671000000001,39.613777],"type":"Point"}
}