{
  "type": "Feature",
  "properties": {
    "iso:country":"US",
    "sg:address":"4881 Washington St",
    "sg:city":"Denver",
    "sg:classifiers":[
        {
            "category":"Manufacturing",
            "subcategory":"Tools & Machinery",
            "type":"Manufacturing & Wholesale Goods"
        }
    ],
    "sg:phone":"+1 303 292 4889",
    "sg:postcode":"80216",
    "sg:province":"CO",
    "sg:tags":[
        "machine",
        "shop"
    ],
    "wof:name":"H & E Inc Machine Shop",
    "wof:placetype":"venue"
},
  "geometry": {"coordinates":[-104.978375,39.784831],"type":"Point"}
}