{
  "type": "Feature",
  "properties": {
    "iso:country":"US",
    "sg:address":"1915 S Bryant St",
    "sg:city":"Denver",
    "sg:classifiers":[
        {
            "category":"Real Estate",
            "subcategory":"Real Estate Agent",
            "type":"Services"
        }
    ],
    "sg:phone":"+1 303 934 1415",
    "sg:postcode":"80219",
    "sg:province":"CO",
    "wof:name":"Coastal Divide Properties",
    "wof:placetype":"venue"
},
  "geometry": {"coordinates":[-105.018091,39.680796],"type":"Point"}
}