{
  "type": "Feature",
  "properties": {
    "iso:country":"US",
    "sg:address":"5121 Zang St",
    "sg:city":"Arvada",
    "sg:classifiers":[
        {
            "category":"Retail",
            "subcategory":"Portrait Studio",
            "type":"Services"
        }
    ],
    "sg:phone":"+1 303 422 0572",
    "sg:postcode":"80002",
    "sg:province":"CO",
    "sg:tags":[
        "photographer"
    ],
    "wof:name":"Le Baron Photography",
    "wof:placetype":"venue"
},
  "geometry": {"coordinates":[-105.1451,39.79047],"type":"Point"}
}