{
  "type": "Feature",
  "properties": {
    "addr:full":"6964 S Pontiac Ct Centennial CO 80112",
    "addr:housenumber":"6964",
    "addr:postcode":"80112",
    "addr:street":"S Pontiac Ct",
    "iso:country":"US",
    "sg:address":"6964 S Pontiac Ct",
    "sg:city":"Centennial",
    "sg:classifiers":[
        {
            "category":"Autos & Motor Vehicles",
            "subcategory":"Auto Supplies",
            "type":"Retail Goods"
        }
    ],
    "sg:phone":"+1 303 771 2705",
    "sg:postcode":"80112",
    "sg:province":"CO",
    "sg:tags":[
        "automobile",
        "accessory"
    ],
    "sg:website":"www.autoexpressions.com",
    "wof:name":"Rocky Mountain Aftermarket LTD",
    "wof:placetype":"venue"
},
  "geometry": {"coordinates":[-104.90668599999999,39.589892],"type":"Point"}
}