{
  "type": "Feature",
  "properties": {
    "iso:country":"US",
    "sg:address":"2 Kalamath St",
    "sg:city":"Denver",
    "sg:classifiers":[
        {
            "category":"Food & Beverages",
            "subcategory":"Candy",
            "type":"Retail Goods"
        }
    ],
    "sg:phone":"+1 303 733 7311",
    "sg:postcode":"80223",
    "sg:province":"CO",
    "sg:tags":[
        "nut"
    ],
    "wof:name":"Going Nuts",
    "wof:placetype":"venue"
},
  "geometry": {"coordinates":[-105.000186,39.718401],"type":"Point"}
}