{
  "type": "Feature",
  "properties": {
    "addr:full":"1847 S Nevada Ave Colorado Springs CO 80906",
    "addr:housenumber":"1847",
    "addr:postcode":"80906",
    "addr:street":"S Nevada Ave",
    "iso:country":"US",
    "sg:address":"1847 S Nevada Ave",
    "sg:city":"Colorado Springs",
    "sg:classifiers":[
        {
            "category":"Professional",
            "type":"Services"
        }
    ],
    "sg:phone":"+1 719 538 5761",
    "sg:postcode":"80906",
    "sg:province":"CO",
    "sg:tags":[
        "establishment"
    ],
    "wof:name":"Optometrist",
    "wof:placetype":"venue"
},
  "geometry": {"coordinates":[-104.822193,38.806753],"type":"Point"}
}