{
  "type": "Feature",
  "properties": {
    "addr:full":"1555 E Bridge St Brighton CO 80601",
    "addr:housenumber":"1555",
    "addr:postcode":"80601",
    "addr:street":"E Bridge St",
    "iso:country":"US",
    "sg:address":"1555 E Bridge St",
    "sg:city":"Brighton",
    "sg:classifiers":[
        {
            "category":"Home & Garden",
            "subcategory":"Building Materials",
            "type":"Retail Goods"
        }
    ],
    "sg:phone":"+1 303 654 1699",
    "sg:postcode":"80601",
    "sg:province":"CO",
    "sg:tags":[
        "paint",
        "covering"
    ],
    "wof:name":"Sherwin-Williams Paints",
    "wof:placetype":"venue"
},
  "geometry": {"coordinates":[-104.801508,39.986867],"type":"Point"}
}