{
  "type": "Feature",
  "properties": {
    "addr:full":"611 San Juan St Pagosa Springs CO 81147",
    "addr:housenumber":"611",
    "addr:postcode":"81147",
    "addr:street":"San Juan St",
    "iso:country":"US",
    "sg:address":"611 San Juan St",
    "sg:city":"Pagosa Springs",
    "sg:classifiers":[
        {
            "category":"Shopping",
            "subcategory":"Gifts & Souvenirs",
            "type":"Retail Goods"
        }
    ],
    "sg:phone":"+1 970 264 5825",
    "sg:postcode":"81147",
    "sg:province":"CO",
    "sg:tags":[
        "shop"
    ],
    "wof:name":"Rainbow Gifts",
    "wof:placetype":"venue"
},
  "geometry": {"coordinates":[-107.01571300000001,37.266281],"type":"Point"}
}