{
  "type": "Feature",
  "properties": {
    "addr:full":"4865 Riverbend Rd Boulder CO 80301",
    "addr:housenumber":"4865",
    "addr:postcode":"80301",
    "addr:street":"Riverbend Rd",
    "iso:country":"US",
    "sg:address":"4865 Riverbend Rd",
    "sg:city":"Boulder",
    "sg:classifiers":[
        {
            "category":"Shopping",
            "subcategory":"Bicycles & Sporting Goods",
            "type":"Retail Goods"
        }
    ],
    "sg:phone":"+1 303 998 1531",
    "sg:postcode":"80301",
    "sg:province":"CO",
    "sg:tags":[
        "equipment",
        "exercise"
    ],
    "sg:website":"www.peakpilates.com",
    "wof:name":"Peak Body Systems",
    "wof:placetype":"venue"
},
  "geometry": {"coordinates":[-105.233566,40.015602],"type":"Point"}
}