{
  "type": "Feature",
  "properties": {
    "addr:full":"861 Odin Dr Silt CO 81652",
    "addr:housenumber":"861",
    "addr:postcode":"81652",
    "addr:street":"Odin Dr",
    "iso:country":"US",
    "sg:address":"861 Odin Dr",
    "sg:city":"Silt",
    "sg:classifiers":[
        {
            "category":"Manufacturing",
            "subcategory":"Watercraft",
            "type":"Manufacturing & Wholesale Goods"
        }
    ],
    "sg:phone":"+1 970 876 2221",
    "sg:postcode":"81652",
    "sg:province":"CO",
    "sg:tags":[
        "repair"
    ],
    "wof:name":"Hy TEC Marine Props LLC",
    "wof:placetype":"venue"
},
  "geometry": {"coordinates":[-107.67367400000001,39.587809],"type":"Point"}
}