{
  "type": "Feature",
  "properties": {
    "iso:country":"US",
    "sg:address":"1560 Dewar Dr",
    "sg:city":"Rock Springs",
    "sg:classifiers":[
        {
            "category":"Retail",
            "subcategory":"Auto Repair",
            "type":"Services"
        }
    ],
    "sg:phone":"+1 307 382 5511",
    "sg:postcode":"82901",
    "sg:province":"CO",
    "sg:tags":[
        "repairing",
        "automobile"
    ],
    "wof:name":"Rezko Auto & Truck Ctr Inc",
    "wof:placetype":"venue"
},
  "geometry": {"coordinates":[-109.245481,41.574598],"type":"Point"}
}