{
  "type": "Feature",
  "properties": {
    "addr:full":"287 US Hwy 287 Lafayette CO 80026",
    "addr:housenumber":"287",
    "addr:postcode":"80026",
    "addr:street":"Us Hwy 287",
    "iso:country":"US",
    "sg:address":"287 US Hwy 287",
    "sg:city":"Lafayette",
    "sg:classifiers":[
        {
            "category":"Shopping",
            "subcategory":"Bicycles & Sporting Goods",
            "type":"Retail Goods"
        }
    ],
    "sg:phone":"+1 303 665 4540",
    "sg:postcode":"80026",
    "sg:province":"CO",
    "sg:tags":[
        "equipment",
        "hockey"
    ],
    "wof:name":"Proskate",
    "wof:placetype":"venue"
},
  "geometry": {"coordinates":[-105.092662,40.000304],"type":"Point"}
}