{
  "type": "Feature",
  "properties": {
    "addr:full":"905 Bromefield Dr Fountain CO 80817",
    "addr:housenumber":"905",
    "addr:postcode":"80817",
    "addr:street":"Bromefield Dr",
    "iso:country":"US",
    "sg:address":"905 Bromefield Dr",
    "sg:city":"Fountain",
    "sg:classifiers":[
        {
            "category":"Building & Trades",
            "subcategory":"Plumbing",
            "type":"Services"
        }
    ],
    "sg:phone":"+1 719 491 3308",
    "sg:postcode":"80817",
    "sg:province":"CO",
    "sg:tags":[
        "heating",
        "contractor"
    ],
    "wof:name":"Claude's Heating & Air Cond",
    "wof:placetype":"venue"
},
  "geometry": {"coordinates":[-104.67469,38.666809],"type":"Point"}
}