{
  "type": "Feature",
  "properties": {
    "addr:full":"11405 State Hwy 2 Brighton CO 80603",
    "addr:housenumber":"11405",
    "addr:postcode":"80603",
    "addr:street":"State Hwy 2",
    "iso:country":"US",
    "sg:address":"11405 State Hwy 2",
    "sg:city":"Brighton",
    "sg:classifiers":[
        {
            "category":"Freight",
            "type":"Transportation"
        }
    ],
    "sg:phone":"+1 303 288 6091",
    "sg:postcode":"80603",
    "sg:province":"CO",
    "sg:tags":[
        "trucking"
    ],
    "wof:name":"R & K Trucking",
    "wof:placetype":"venue"
},
  "geometry": {"coordinates":[-104.826956,39.902129],"type":"Point"}
}