{
  "type": "Feature",
  "properties": {
    "iso:country":"US",
    "sg:address":"4785 Elati St",
    "sg:city":"Denver",
    "sg:classifiers":[
        {
            "category":"Shopping",
            "type":"Retail Goods"
        },
        {
            "category":"Wholesale",
            "subcategory":"Sporting Goods",
            "type":"Manufacturing & Wholesale Goods"
        }
    ],
    "sg:phone":"+1 303 297 8098",
    "sg:postcode":"80216",
    "sg:province":"CO",
    "sg:tags":[
        "spa",
        "hot",
        "tub"
    ],
    "wof:name":"Colorado Custom Spas",
    "wof:placetype":"venue"
},
  "geometry": {"coordinates":[-104.99271299999999,39.782645],"type":"Point"}
}