{
  "type": "Feature",
  "properties": {
    "iso:country":"US",
    "sg:address":"805 Opal Way",
    "sg:city":"Broomfield",
    "sg:classifiers":[
        {
            "category":"Building & Trades",
            "subcategory":"Construction",
            "type":"Services"
        }
    ],
    "sg:phone":"+1 303 466 4529",
    "sg:postcode":"80020",
    "sg:province":"CO",
    "sg:tags":[
        "house"
    ],
    "wof:name":"Jpj Construction",
    "wof:placetype":"venue"
},
  "geometry": {"coordinates":[-105.087918,39.926996],"type":"Point"}
}