{
  "type": "Feature",
  "properties": {
    "addr:full":"410 San Juan Ave Alamosa CO 81101",
    "addr:housenumber":"410",
    "addr:postcode":"81101",
    "addr:street":"San Juan Ave",
    "iso:country":"US",
    "sg:address":"410 San Juan Ave",
    "sg:city":"Alamosa",
    "sg:classifiers":[
        {
            "category":"Professional",
            "subcategory":"Lawyer & Legal Services",
            "type":"Services"
        }
    ],
    "sg:phone":"+1 719 589 6676",
    "sg:postcode":"81101",
    "sg:province":"CO",
    "sg:tags":[
        "attorney"
    ],
    "wof:name":"Motz Pearson Rogers",
    "wof:placetype":"venue"
},
  "geometry": {"coordinates":[-105.867075,37.469167],"type":"Point"}
}