{
  "type": "Feature",
  "properties": {
    "iso:country":"US",
    "sg:address":"205 E Main St",
    "sg:city":"Montrose",
    "sg:classifiers":[
        {
            "category":"Professional",
            "subcategory":"Accounting & Tax Preparation",
            "type":"Services"
        }
    ],
    "sg:phone":"+1 970 249 1628",
    "sg:postcode":"81401",
    "sg:province":"CO",
    "sg:tags":[
        "accountant"
    ],
    "wof:name":"Mc Guire & Assoc Inc",
    "wof:placetype":"venue"
},
  "geometry": {"coordinates":[-107.877802,38.478772],"type":"Point"}
}