{
  "type": "Feature",
  "properties": {
    "iso:country":"US",
    "sg:address":"2550 Stover St",
    "sg:city":"Fort Collins",
    "sg:classifiers":[
        {
            "category":"Retail",
            "subcategory":"Veterinary Services",
            "type":"Services"
        }
    ],
    "sg:phone":"+1 970 416 9101",
    "sg:postcode":"80525",
    "sg:province":"CO",
    "wof:name":"Douglas Leidholt Dvm",
    "wof:placetype":"venue"
},
  "geometry": {"coordinates":[-105.06743899999999,40.552682],"type":"Point"}
}