{
  "type": "Feature",
  "properties": {
    "iso:country":"US",
    "sg:address":"4733 Lipan St",
    "sg:city":"Denver",
    "sg:classifiers":[
        {
            "category":"Wholesale",
            "subcategory":"Machinery & Supplies",
            "type":"Manufacturing & Wholesale Goods"
        }
    ],
    "sg:phone":"+1 303 433 5330",
    "sg:postcode":"80211",
    "sg:province":"CO",
    "sg:tags":[
        "equipment",
        "janitorial"
    ],
    "wof:name":"Commercial Sanitary Labs",
    "wof:placetype":"venue"
},
  "geometry": {"coordinates":[-105.001761,39.782616],"type":"Point"}
}