{
  "type": "Feature",
  "properties": {
    "iso:country":"US",
    "sg:address":"14135 E 42nd Ave",
    "sg:city":"Denver",
    "sg:classifiers":[
        {
            "category":"Utilities",
            "subcategory":"Refuse",
            "type":"Services"
        },
        {
            "category":"Shopping",
            "subcategory":"Computers & Home Electronics",
            "type":"Retail Goods"
        }
    ],
    "sg:phone":"+1 303 660 2000",
    "sg:postcode":"80239",
    "sg:province":"CO",
    "sg:tags":[
        "system"
    ],
    "wof:name":"Luminous Electronics Recycling",
    "wof:placetype":"venue"
},
  "geometry": {"coordinates":[-104.842411,39.774324],"type":"Point"}
}