{
  "type": "Feature",
  "properties": {
    "iso:country":"US",
    "sg:address":"830 E Fillmore St",
    "sg:city":"Colorado Springs",
    "sg:classifiers":[
        {
            "category":"Shopping",
            "type":"Retail Goods"
        }
    ],
    "sg:phone":"+1 719 641 8477",
    "sg:postcode":"80907",
    "sg:province":"CO",
    "sg:tags":[
        "merchandise"
    ],
    "wof:name":"Radio Shoppe",
    "wof:placetype":"venue"
},
  "geometry": {"coordinates":[-104.810013,38.874149],"type":"Point"}
}