{
  "type": "Feature",
  "properties": {
    "iso:country":"US",
    "sg:address":"7108 S Alton Way",
    "sg:city":"Englewood",
    "sg:classifiers":[
        {
            "category":"Professional",
            "subcategory":"Art Services",
            "type":"Services"
        }
    ],
    "sg:phone":"+1 303 488 6220",
    "sg:postcode":"80112",
    "sg:province":"CO",
    "sg:tags":[
        "arts",
        "graphic",
        "design",
        "related",
        "typesetting"
    ],
    "wof:name":"Desktop Concepts Inc",
    "wof:placetype":"venue"
},
  "geometry": {"coordinates":[-104.88272499999999,39.584135],"type":"Point"}
}