{
  "type": "Feature",
  "properties": {
    "addr:full":"60 S 8th St Carbondale CO 81623",
    "addr:housenumber":"60",
    "addr:postcode":"81623",
    "addr:street":"S 8Th St",
    "iso:country":"US",
    "sg:address":"60 S 8th St",
    "sg:city":"Carbondale",
    "sg:classifiers":[
        {
            "category":"Health Services",
            "subcategory":"Doctor",
            "type":"Services"
        }
    ],
    "sg:phone":"+1 970 963 8984",
    "sg:postcode":"81623",
    "sg:province":"CO",
    "sg:tags":[
        "dentist"
    ],
    "wof:name":"John M Traul & Assoc",
    "wof:placetype":"venue"
},
  "geometry": {"coordinates":[-107.215476,39.400154],"type":"Point"}
}