{
  "type": "Feature",
  "properties": {
    "addr:full":"76 Sheppard Dr Durango CO 81303",
    "addr:housenumber":"76",
    "addr:postcode":"co 81303",
    "addr:street":"Sheppard Dr",
    "iso:country":"US",
    "sg:address":"76 Sheppard Dr",
    "sg:city":"Durango",
    "sg:classifiers":[
        {
            "category":"Wholesale",
            "subcategory":"Hardware",
            "type":"Manufacturing & Wholesale Goods"
        }
    ],
    "sg:phone":"+1 970 259 5005",
    "sg:postcode":"81303",
    "sg:province":"CO",
    "sg:tags":[
        "plumbing",
        "equipment",
        "heating"
    ],
    "wof:name":"Ferguson Enterprises Inc",
    "wof:placetype":"venue"
},
  "geometry": {"coordinates":[-107.873771,37.236571],"type":"Point"}
}