{
  "type": "Feature",
  "properties": {
    "addr:full":"1124 W Elizabeth St Fort Collins CO 80521",
    "addr:housenumber":"1124",
    "addr:postcode":"80521",
    "addr:street":"W Elizabeth St",
    "iso:country":"US",
    "sg:address":"1124 W Elizabeth St",
    "sg:city":"Fort Collins",
    "sg:classifiers":[
        {
            "category":"Education",
            "subcategory":"Special Training",
            "type":"Public Place"
        }
    ],
    "sg:phone":"+1 970 484 5229",
    "sg:postcode":"80521",
    "sg:province":"CO",
    "sg:tags":[
        "instruction",
        "driving"
    ],
    "wof:name":"Choice Drivers Education",
    "wof:placetype":"venue"
},
  "geometry": {"coordinates":[-105.100418,40.574636],"type":"Point"}
}