{
  "type": "Feature",
  "properties": {
    "iso:country":"US",
    "sg:address":"1850 S Acoma St",
    "sg:city":"Denver",
    "sg:classifiers":[
        {
            "category":"Retail",
            "subcategory":"Laundry & Dry Cleaning",
            "type":"Services"
        }
    ],
    "sg:phone":"+1 303 722 4661",
    "sg:postcode":"80223",
    "sg:province":"CO",
    "sg:tags":[
        "linen",
        "supply"
    ],
    "sg:website":"www.alsco.com",
    "wof:name":"Alsco Inc",
    "wof:placetype":"venue"
},
  "geometry": {"coordinates":[-104.98871,39.683069],"type":"Point"}
}