{
  "type": "Feature",
  "properties": {
    "iso:country":"US",
    "sg:address":"6588 S Niagara Ct",
    "sg:city":"Englewood",
    "sg:classifiers":[
        {
            "category":"Banks & Credit Unions",
            "subcategory":"Financial Services",
            "type":"Services"
        }
    ],
    "sg:phone":"+1 303 290 8683",
    "sg:postcode":"80111",
    "sg:province":"CO",
    "sg:tags":[
        "investment",
        "closed"
    ],
    "wof:name":"Niagara Investments Co LLC",
    "wof:placetype":"venue"
},
  "geometry": {"coordinates":[-104.910304,39.598424],"type":"Point"}
}