{
  "type": "Feature",
  "properties": {
    "addr:full":"633 17th St Suite 3000 Denver CO 80202",
    "addr:housenumber":"633",
    "addr:postcode":"80202",
    "addr:street":"17Th St Suite 3000",
    "iso:country":"US",
    "sg:address":"633 17th St Suite 3000",
    "sg:city":"Denver",
    "sg:classifiers":[
        {
            "category":"Professional",
            "subcategory":"Lawyer & Legal Services",
            "type":"Services"
        }
    ],
    "sg:phone":"+1 303 297 2900",
    "sg:postcode":"80202",
    "sg:province":"CO",
    "sg:tags":[
        "litigation",
        "tort",
        "attorney"
    ],
    "wof:name":"Robinson Kelly K",
    "wof:placetype":"venue"
},
  "geometry": {"coordinates":[-104.990381,39.745659],"type":"Point"}
}