{
  "type": "Feature",
  "properties": {
    "iso:country":"US",
    "sg:address":"1645 Bear Mountain Dr",
    "sg:city":"Boulder",
    "sg:classifiers":[
        {
            "category":"Real Estate",
            "subcategory":"Developer",
            "type":"Services"
        }
    ],
    "sg:phone":"+1 303 499 2689",
    "sg:postcode":"80305",
    "sg:province":"CO",
    "wof:name":"Boulder Niagara Properties LLC",
    "wof:placetype":"venue"
},
  "geometry": {"coordinates":[-105.265488,39.972826],"type":"Point"}
}