{
  "type": "Feature",
  "properties": {
    "iso:country":"US",
    "sg:address":"1825 Hood Ave",
    "sg:city":"Pueblo",
    "sg:classifiers":[
        {
            "category":"Banks & Credit Unions",
            "subcategory":"Bank",
            "type":"Services"
        }
    ],
    "sg:phone":"+1 719 542 5773",
    "sg:postcode":"81003",
    "sg:province":"CO",
    "sg:tags":[
        "federal"
    ],
    "wof:name":"Pueblo Horizons Federal Cr Un",
    "wof:placetype":"venue"
},
  "geometry": {"coordinates":[-104.630769,38.28419],"type":"Point"}
}