{
  "type": "Feature",
  "properties": {
    "iso:country":"US",
    "sg:address":"370 17th St Ste 3800",
    "sg:city":"Denver",
    "sg:classifiers":[
        {
            "category":"Real Estate",
            "subcategory":"Real Estate Services",
            "type":"Services"
        }
    ],
    "sg:phone":"+1 303 595 7000",
    "sg:postcode":"80202",
    "sg:province":"CO",
    "wof:name":"Brookfield Properties",
    "wof:placetype":"venue"
},
  "geometry": {"coordinates":[-104.98817200000001,39.7438],"type":"Point"}
}