{
  "type": "Feature",
  "properties": {
    "addr:full":"14095 E Exposition Ave Aurora CO 80012",
    "addr:housenumber":"14095",
    "addr:postcode":"80012",
    "addr:street":"E Exposition Ave",
    "iso:country":"US",
    "sg:address":"14095 E Exposition Ave",
    "sg:city":"Aurora",
    "sg:classifiers":[
        {
            "category":"Autos & Motor Vehicles",
            "subcategory":"Auto Supplies",
            "type":"Retail Goods"
        }
    ],
    "sg:phone":"+1 303 341 6516",
    "sg:postcode":"80012",
    "sg:province":"CO",
    "sg:tags":[
        "automobile",
        "parts"
    ],
    "wof:name":"Carquest Auto Parts",
    "wof:placetype":"venue"
},
  "geometry": {"coordinates":[-104.82732900000001,39.703963],"type":"Point"}
}