{
  "type": "Feature",
  "properties": {
    "addr:full":"1245 Humboldt St Denver CO 80218",
    "addr:housenumber":"1245",
    "addr:postcode":"80218",
    "addr:street":"Humboldt St",
    "iso:country":"US",
    "sg:address":"1245 Humboldt St",
    "sg:city":"Denver",
    "sg:classifiers":[
        {
            "category":"Shopping",
            "subcategory":"Books",
            "type":"Retail Goods"
        }
    ],
    "sg:phone":"+1 720 855 3093",
    "sg:postcode":"80218",
    "sg:province":"CO",
    "wof:name":"Mean Jeanines Book Shop",
    "wof:placetype":"venue"
},
  "geometry": {"coordinates":[-104.969594,39.736108],"type":"Point"}
}