{
  "type": "Feature",
  "properties": {
    "iso:country":"US",
    "sg:address":"2004 Cooper Ave",
    "sg:city":"Colorado Springs",
    "sg:classifiers":[
        {
            "category":"Building & Trades",
            "subcategory":"Electrical",
            "type":"Services"
        }
    ],
    "sg:phone":"+1 719 442 0652",
    "sg:postcode":"80907",
    "sg:province":"CO",
    "sg:tags":[
        "electrical",
        "contractor"
    ],
    "wof:name":"Ballard Communications",
    "wof:placetype":"venue"
},
  "geometry": {"coordinates":[-104.835036,38.863012],"type":"Point"}
}