{
  "type": "Feature",
  "properties": {
    "addr:full":"5870 S Long Ln Greenwood Vlg CO 80121",
    "addr:housenumber":"5870",
    "addr:postcode":"co 80121",
    "addr:street":"S Long Ln",
    "iso:country":"US",
    "sg:address":"5870 S Long Ln",
    "sg:city":"Greenwood Vlg",
    "sg:classifiers":[
        {
            "category":"Real Estate",
            "subcategory":"Architect",
            "type":"Services"
        }
    ],
    "sg:phone":"+1 303 773 2504",
    "sg:postcode":"80121",
    "sg:province":"CO",
    "wof:name":"Coffey Associates",
    "wof:placetype":"venue"
},
  "geometry": {"coordinates":[-104.956085,39.610089],"type":"Point"}
}