{
  "type": "Feature",
  "properties": {
    "addr:full":"1360 Gillaspie Dr Boulder CO 80305",
    "addr:housenumber":"1360",
    "addr:postcode":"80305",
    "addr:street":"Gillaspie Dr",
    "iso:country":"US",
    "sg:address":"1360 Gillaspie Dr",
    "sg:city":"Boulder",
    "sg:classifiers":[
        {
            "category":"Recreation",
            "type":"Entertainment"
        }
    ],
    "sg:phone":"+1 303 441 3448",
    "sg:postcode":"80305",
    "sg:province":"CO",
    "sg:tags":[
        "executive"
    ],
    "wof:name":"South Boulder Recreation Ctr",
    "wof:placetype":"venue"
},
  "geometry": {"coordinates":[-105.249661,39.974943],"type":"Point"}
}