{
  "type": "Feature",
  "properties": {
    "iso:country":"US",
    "sg:address":"195 Gandy Ave",
    "sg:city":"Keenesburg",
    "sg:classifiers":[
        {
            "category":"Social Services",
            "subcategory":"Adult Care",
            "type":"Services"
        }
    ],
    "sg:phone":"+1 303 732 4424",
    "sg:postcode":"80643",
    "sg:province":"CO",
    "sg:tags":[
        "home",
        "residential"
    ],
    "wof:name":"Gray Cara Alternative Facility",
    "wof:placetype":"venue"
},
  "geometry": {"coordinates":[-104.51755900000001,40.108132],"type":"Point"}
}