{
  "type": "Feature",
  "properties": {
    "iso:country":"US",
    "sg:address":"1050 17th Street Suite 800",
    "sg:city":"Denver",
    "sg:classifiers":[
        {
            "category":"Professional",
            "subcategory":"Computer Services",
            "type":"Services"
        }
    ],
    "sg:phone":"+1 866 777 2673",
    "sg:postcode":"80265",
    "sg:province":"CO",
    "sg:website":"http://www.coresite.com/",
    "wof:name":"Coresite",
    "wof:placetype":"venue"
},
  "geometry": {"coordinates":[-104.994139,39.748402],"type":"Point"}
}