{
  "type": "Feature",
  "properties": {
    "iso:country":"US",
    "sg:address":"209 Ten Mile Cir",
    "sg:city":"Copper Mountain",
    "sg:classifiers":[
        {
            "category":"Travel",
            "subcategory":"Hotels & Motels",
            "type":"Entertainment"
        },
        {
            "category":"Recreation",
            "type":"Entertainment"
        }
    ],
    "sg:phone":"+1 970 968 2882",
    "sg:postcode":"80443",
    "sg:province":"CO",
    "sg:tags":[
        "equipment",
        "skiing",
        "resort"
    ],
    "wof:name":"Copper Mountain Resort",
    "wof:placetype":"venue"
},
  "geometry": {"coordinates":[-106.153531,39.500834],"type":"Point"}
}