{
  "type": "Feature",
  "properties": {
    "iso:country":"US",
    "sg:address":"12165 Sheridan Blvd",
    "sg:city":"Broomfield",
    "sg:classifiers":[
        {
            "category":"Food & Beverages",
            "subcategory":"Liquor & Beverages",
            "type":"Retail Goods"
        }
    ],
    "sg:phone":"+1 303 466 3208",
    "sg:postcode":"80020",
    "sg:province":"CO",
    "wof:name":"Roundup Liquors",
    "wof:placetype":"venue"
},
  "geometry": {"coordinates":[-105.05302500000001,39.914765],"type":"Point"}
}