{
  "type": "Feature",
  "properties": {
    "iso:country":"US",
    "sg:address":"1456 Dallas St",
    "sg:city":"Aurora",
    "sg:classifiers":[
        {
            "category":"Professional",
            "subcategory":"Printing & Photocopies",
            "type":"Services"
        }
    ],
    "sg:phone":"+1 303 366 4411",
    "sg:postcode":"80010",
    "sg:province":"CO",
    "sg:tags":[
        "services-commercial"
    ],
    "wof:name":"Thermo Graphtek",
    "wof:placetype":"venue"
},
  "geometry": {"coordinates":[-104.876406,39.739284],"type":"Point"}
}