{
  "type": "Feature",
  "properties": {
    "addr:full":"6185 Iverson Ct Colorado Springs CO 80922",
    "addr:housenumber":"6185",
    "addr:postcode":"80922",
    "addr:street":"Iverson Ct",
    "iso:country":"US",
    "sg:address":"6185 Iverson Ct",
    "sg:city":"Colorado Springs",
    "sg:classifiers":[
        {
            "category":"Building & Trades",
            "subcategory":"Construction",
            "type":"Services"
        }
    ],
    "sg:phone":"+1 719 651 7935",
    "sg:postcode":"80922",
    "sg:province":"CO",
    "sg:tags":[
        "builder",
        "deck"
    ],
    "wof:name":"Barkley Custom Decks",
    "wof:placetype":"venue"
},
  "geometry": {"coordinates":[-104.706895,38.903307],"type":"Point"}
}