{
  "type": "Feature",
  "properties": {
    "iso:country":"US",
    "sg:address":"4461 S Wright Ct",
    "sg:city":"Morrison",
    "sg:classifiers":[
        {
            "category":"Building & Trades",
            "subcategory":"Construction",
            "type":"Services"
        }
    ],
    "sg:phone":"+1 720 922 9476",
    "sg:postcode":"80465",
    "sg:province":"CO",
    "sg:tags":[
        "contractor"
    ],
    "wof:name":"All Brothers Roofing",
    "wof:placetype":"venue"
},
  "geometry": {"coordinates":[-105.140113,39.63639],"type":"Point"}
}