{
  "type": "Feature",
  "properties": {
    "addr:full":"15225 Co Rd 21 Platteville CO 80651",
    "addr:housenumber":"15225;21",
    "addr:postcode":"80651",
    "addr:street":"Co Rd",
    "iso:country":"US",
    "sg:address":"15225 Co Rd 21",
    "sg:city":"Platteville",
    "sg:phone":"+1 970 785 2510",
    "sg:postcode":"80651",
    "sg:province":"CO",
    "sg:tags":[
        "farm",
        "corn",
        "irish",
        "soybean"
    ],
    "wof:name":"Rose Lee Rusch",
    "wof:placetype":"venue"
},
  "geometry": {"coordinates":[-104.86755100000001,40.213058],"type":"Point"}
}