{
  "type": "Feature",
  "properties": {
    "iso:country":"US",
    "sg:address":"15200 E 132nd Ave",
    "sg:city":"Brighton",
    "sg:classifiers":[
        {
            "category":"Building & Trades",
            "subcategory":"Construction",
            "type":"Services"
        }
    ],
    "sg:phone":"+1 303 655 0585",
    "sg:postcode":"80601",
    "sg:province":"CO",
    "sg:tags":[
        "contractor"
    ],
    "wof:name":"Dkr Drywall Services Inc",
    "wof:placetype":"venue"
},
  "geometry": {"coordinates":[-104.796176,39.935988],"type":"Point"}
}