{
  "type": "Feature",
  "properties": {
    "addr:full":"2166 Ridgetrail Dr Castle Rock CO 80104",
    "addr:housenumber":"2166",
    "addr:postcode":"80104",
    "addr:street":"Ridgetrail Dr",
    "iso:country":"US",
    "sg:address":"2166 Ridgetrail Dr",
    "sg:city":"Castle Rock",
    "sg:classifiers":[
        {
            "category":"Building & Trades",
            "subcategory":"Locksmith",
            "type":"Services"
        }
    ],
    "sg:phone":"+1 866 270 1888",
    "sg:postcode":"80104",
    "sg:province":"CO",
    "sg:tags":[
        "key"
    ],
    "wof:name":"Always Available Emergency Locksmith",
    "wof:placetype":"venue"
},
  "geometry": {"coordinates":[-104.839832,39.3816],"type":"Point"}
}