{
  "type": "Feature",
  "properties": {
    "iso:country":"US",
    "sg:address":"125 Sawyer Dr",
    "sg:city":"Durango",
    "sg:classifiers":[
        {
            "category":"Insurance",
            "subcategory":"Insurance Agent",
            "type":"Services"
        }
    ],
    "sg:phone":"+1 970 247 9500",
    "sg:postcode":"81303",
    "sg:province":"CO",
    "wof:name":"Lau Financial Management",
    "wof:placetype":"venue"
},
  "geometry": {"coordinates":[-107.87299,37.242334],"type":"Point"}
}