{
  "type": "Feature",
  "properties": {
    "addr:full":"101 East Ave Rifle CO 81650",
    "addr:housenumber":"101",
    "addr:postcode":"81650",
    "addr:street":"East Ave",
    "iso:country":"US",
    "sg:address":"101 East Ave",
    "sg:city":"Rifle",
    "sg:classifiers":[
        {
            "category":"Retail",
            "subcategory":"Repair Shop",
            "type":"Services"
        }
    ],
    "sg:phone":"+1 970 625 0938",
    "sg:postcode":"81650",
    "sg:province":"CO",
    "sg:tags":[
        "appliance"
    ],
    "wof:name":"Mark's Home Appliance Repairs",
    "wof:placetype":"venue"
},
  "geometry": {"coordinates":[-107.781964,39.530165],"type":"Point"}
}