{
  "type": "Feature",
  "properties": {
    "iso:country":"US",
    "sg:address":"615 Nichols Blvd",
    "sg:city":"Colorado Springs",
    "sg:classifiers":[
        {
            "category":"Building & Trades",
            "subcategory":"Equipment Rental",
            "type":"Services"
        }
    ],
    "sg:phone":"+1 719 630 8500",
    "sg:postcode":"80907",
    "sg:province":"CO",
    "sg:tags":[
        "crane"
    ],
    "sg:website":"www.rmscranes.com",
    "wof:name":"Rocky Mountain Structures",
    "wof:placetype":"venue"
},
  "geometry": {"coordinates":[-104.811983,38.882153],"type":"Point"}
}