{
  "type": "Feature",
  "properties": {
    "addr:full":"10414 Independence St Broomfield CO 80021",
    "addr:housenumber":"10414",
    "addr:postcode":"80021",
    "addr:street":"Independence St",
    "iso:country":"US",
    "sg:address":"10414 Independence St",
    "sg:city":"Broomfield",
    "sg:classifiers":[
        {
            "category":"Building & Trades",
            "subcategory":"Electrical",
            "type":"Services"
        }
    ],
    "sg:phone":"+1 303 460 1070",
    "sg:postcode":"80021",
    "sg:province":"CO",
    "sg:tags":[
        "electrical",
        "contractor"
    ],
    "sg:website":"www.mdwelectric.com",
    "wof:name":"MDW Electric Inc",
    "wof:placetype":"venue"
},
  "geometry": {"coordinates":[-105.10573100000001,39.886912],"type":"Point"}
}