{
  "type": "Feature",
  "properties": {
    "iso:country":"US",
    "sg:address":"118 Main St",
    "sg:city":"Sterling",
    "sg:classifiers":[
        {
            "category":"Social Services",
            "type":"Services"
        }
    ],
    "sg:phone":"+1 970 521 0922",
    "sg:postcode":"80751",
    "sg:province":"CO",
    "sg:tags":[
        "counselor",
        "marriage",
        "family"
    ],
    "wof:name":"Community Counseling Svc",
    "wof:placetype":"venue"
},
  "geometry": {"coordinates":[-103.207189,40.623378],"type":"Point"}
}