{
  "type": "Feature",
  "properties": {
    "iso:country":"US",
    "sg:address":"1859 S Pearl St",
    "sg:city":"Denver",
    "sg:classifiers":[
        {
            "category":"Food & Beverages",
            "subcategory":"Supermarket",
            "type":"Retail Goods"
        }
    ],
    "sg:phone":"+1 720 524 3750",
    "sg:postcode":"80210",
    "sg:province":"CO",
    "sg:tags":[
        "super",
        "store"
    ],
    "wof:name":"Momo Foods",
    "wof:placetype":"venue"
},
  "geometry": {"coordinates":[-104.98049,39.682917],"type":"Point"}
}