{
  "type": "Feature",
  "properties": {
    "iso:country":"US",
    "sg:address":"3880 S Elkhart St",
    "sg:city":"Aurora",
    "sg:classifiers":[
        {
            "category":"Professional",
            "subcategory":"Computer Services",
            "type":"Services"
        }
    ],
    "sg:phone":"+1 303 699 8043",
    "sg:postcode":"80014",
    "sg:province":"CO",
    "sg:tags":[
        "prepackaged",
        "software"
    ],
    "wof:name":"Information Software Support",
    "wof:placetype":"venue"
},
  "geometry": {"coordinates":[-104.815476,39.647627],"type":"Point"}
}