{
  "type": "Feature",
  "properties": {
    "addr:full":"3605 S Bannock St Englewood CO 80110",
    "addr:housenumber":"3605",
    "addr:postcode":"80110",
    "addr:street":"S Bannock St",
    "iso:country":"US",
    "sg:address":"3605 S Bannock St",
    "sg:city":"Englewood",
    "sg:classifiers":[
        {
            "category":"Professional",
            "subcategory":"Accounting & Tax Preparation",
            "type":"Services"
        }
    ],
    "sg:phone":"+1 303 783 0400",
    "sg:postcode":"80110",
    "sg:province":"CO",
    "sg:tags":[
        "accountant"
    ],
    "wof:name":"Comprehensive Business Sltns",
    "wof:placetype":"venue"
},
  "geometry": {"coordinates":[-104.99015900000001,39.649477],"type":"Point"}
}