{
  "type": "Feature",
  "properties": {
    "iso:country":"US",
    "sg:address":"6371 S Yellowstone Way",
    "sg:city":"Aurora",
    "sg:classifiers":[
        {
            "category":"Building & Trades",
            "subcategory":"Landscaping Services",
            "type":"Services"
        }
    ],
    "sg:phone":"+1 303 690 3339",
    "sg:postcode":"80016",
    "sg:province":"CO",
    "sg:tags":[
        "installation",
        "sprinkler"
    ],
    "wof:name":"All Amrican Sprnklr Ldscpg Inc",
    "wof:placetype":"venue"
},
  "geometry": {"coordinates":[-104.718576,39.600883],"type":"Point"}
}