{
  "type": "Feature",
  "properties": {
    "addr:full":"2475 Wadsworth Boulevard Lakewood CO 80214",
    "addr:housenumber":"2475",
    "addr:postcode":"80214",
    "addr:street":"Wadsworth Boulevard",
    "iso:country":"US",
    "sg:address":"2475 Wadsworth Boulevard",
    "sg:city":"Lakewood",
    "sg:classifiers":[
        {
            "category":"Health Services",
            "subcategory":"Dentist",
            "type":"Services"
        }
    ],
    "sg:phone":"+1 303 233 1335",
    "sg:postcode":"80214",
    "sg:province":"CO",
    "wof:name":"Rocky Mountain Dental Group",
    "wof:placetype":"venue"
},
  "geometry": {"coordinates":[-105.08144799999999,39.753772],"type":"Point"}
}