{
  "type": "Feature",
  "properties": {
    "addr:full":"4197 Hwy 50 Whitewater CO 81527",
    "addr:housenumber":"4197",
    "addr:postcode":"81527",
    "addr:street":"Hwy 50",
    "iso:country":"US",
    "sg:address":"4197 Hwy 50",
    "sg:city":"Whitewater",
    "sg:classifiers":[
        {
            "category":"Building & Trades",
            "subcategory":"Plumbing",
            "type":"Services"
        }
    ],
    "sg:phone":"+1 970 245 4844",
    "sg:postcode":"81527",
    "sg:province":"CO",
    "sg:tags":[
        "contractor"
    ],
    "wof:name":"Xtreme Plumbing Service & Repr",
    "wof:placetype":"venue"
},
  "geometry": {"coordinates":[-108.440268,38.980414],"type":"Point"}
}