{
  "type": "Feature",
  "properties": {
    "addr:full":"2114 E Pikes Peak Ave Colorado Springs CO 80909",
    "addr:housenumber":"2114",
    "addr:postcode":"80909",
    "addr:street":"E Pikes Peak Ave",
    "iso:country":"US",
    "sg:address":"2114 E Pikes Peak Ave",
    "sg:city":"Colorado Springs",
    "sg:classifiers":[
        {
            "category":"Insurance",
            "subcategory":"Insurance Agent",
            "type":"Services"
        }
    ],
    "sg:phone":"+1 719 597 0001",
    "sg:postcode":"80909",
    "sg:province":"CO",
    "wof:name":"Terry Walker Brokerage",
    "wof:placetype":"venue"
},
  "geometry": {"coordinates":[-104.790183,38.832898],"type":"Point"}
}