{
  "type": "Feature",
  "properties": {
    "addr:full":"673 Pear Dr Fruita CO 81521",
    "addr:housenumber":"673",
    "addr:postcode":"fruita;81521",
    "addr:street":"Pear Dr",
    "iso:country":"US",
    "sg:address":"673 Pear Dr",
    "sg:city":"Fruita",
    "sg:classifiers":[
        {
            "category":"Building & Trades",
            "subcategory":"Construction",
            "type":"Services"
        }
    ],
    "sg:phone":"+1 970 858 7098",
    "sg:postcode":"81521",
    "sg:province":"CO",
    "sg:tags":[
        "excavation",
        "contractor"
    ],
    "wof:name":"Kodiak Skidsteer Service",
    "wof:placetype":"venue"
},
  "geometry": {"coordinates":[-108.73150800000001,39.16944],"type":"Point"}
}