{
  "type": "Feature",
  "properties": {
    "iso:country":"US",
    "sg:address":"7475 W 5th Ave",
    "sg:city":"Lakewood",
    "sg:classifiers":[
        {
            "category":"Professional",
            "subcategory":"Accounting & Tax Preparation",
            "type":"Services"
        }
    ],
    "sg:phone":"+1 303 237 2700",
    "sg:postcode":"80226",
    "sg:province":"CO",
    "sg:tags":[
        "return",
        "filing"
    ],
    "wof:name":"Empire Bookkeeping Inc",
    "wof:placetype":"venue"
},
  "geometry": {"coordinates":[-105.079176,39.723937],"type":"Point"}
}