{
  "type": "Feature",
  "properties": {
    "iso:country":"US",
    "sg:address":"1025 E 12th Ave",
    "sg:city":"Denver",
    "sg:classifiers":[
        {
            "category":"Utilities",
            "subcategory":"Telephone",
            "type":"Services"
        }
    ],
    "sg:phone":"+1 303 860 7902",
    "sg:postcode":"80218",
    "sg:province":"CO",
    "sg:tags":[
        "company"
    ],
    "wof:name":"Eschelon Telecom",
    "wof:placetype":"venue"
},
  "geometry": {"coordinates":[-104.97438699999999,39.73523],"type":"Point"}
}