{
  "type": "Feature",
  "properties": {
    "iso:country":"US",
    "sg:address":"1783 N Frontage Rd W",
    "sg:city":"Vail",
    "sg:classifiers":[
        {
            "category":"Travel",
            "subcategory":"Hotels & Motels",
            "type":"Entertainment"
        }
    ],
    "sg:phone":"+1 970 476 5451",
    "sg:postcode":"81657",
    "sg:province":"CO",
    "sg:website":"www.roostlodge.com",
    "wof:name":"Roost Lodge",
    "wof:placetype":"venue"
},
  "geometry": {"coordinates":[-106.409914,39.635069],"type":"Point"}
}