{
  "type": "Feature",
  "properties": {
    "addr:full":"1415 N College Ave Fort Collins CO 80524",
    "addr:housenumber":"1415",
    "addr:postcode":"80524",
    "addr:street":"N College Ave",
    "iso:country":"US",
    "sg:address":"1415 N College Ave",
    "sg:city":"Fort Collins",
    "sg:classifiers":[
        {
            "category":"Shopping",
            "subcategory":"Tobacco",
            "type":"Retail Goods"
        }
    ],
    "sg:phone":"+1 970 530 0367",
    "sg:postcode":"80524",
    "sg:province":"CO",
    "sg:tags":[
        "cigarette",
        "product",
        "cigar",
        "dealer"
    ],
    "wof:name":"Cigarettes 4 Less",
    "wof:placetype":"venue"
},
  "geometry": {"coordinates":[-105.076623,40.606559],"type":"Point"}
}