{
  "type": "Feature",
  "properties": {
    "addr:full":"7354 Washington St Denver CO 80229",
    "addr:housenumber":"7354",
    "addr:postcode":"80229",
    "addr:street":"Washington St",
    "iso:country":"US",
    "sg:address":"7354 Washington St",
    "sg:city":"Denver",
    "sg:classifiers":[
        {
            "category":"Real Estate",
            "subcategory":"Developer",
            "type":"Services"
        },
        {
            "category":"Real Estate",
            "subcategory":"Real Estate Agent",
            "type":"Services"
        }
    ],
    "sg:phone":"+1 303 288 4201",
    "sg:postcode":"80229",
    "sg:province":"CO",
    "wof:name":"Center Land Co Inc",
    "wof:placetype":"venue"
},
  "geometry": {"coordinates":[-104.977839,39.829889],"type":"Point"}
}