{
  "type": "Feature",
  "properties": {
    "iso:country":"US",
    "sg:address":"9200 W Cross Dr",
    "sg:city":"Littleton",
    "sg:classifiers":[
        {
            "category":"Shopping",
            "subcategory":"Computers & Home Electronics",
            "type":"Retail Goods"
        }
    ],
    "sg:phone":"+1 303 933 6160",
    "sg:postcode":"80123",
    "sg:province":"CO",
    "sg:tags":[
        "software"
    ],
    "wof:name":"Abra Human Rsrcs & Pyrll Sftwr",
    "wof:placetype":"venue"
},
  "geometry": {"coordinates":[-105.102478,39.611596],"type":"Point"}
}