{
  "type": "Feature",
  "properties": {
    "iso:country":"US",
    "sg:address":"117 White Pine Dr",
    "sg:city":"Alamosa",
    "sg:classifiers":[
        {
            "category":"Mining & Drilling",
            "type":"Manufacturing & Wholesale Goods"
        }
    ],
    "sg:phone":"+1 719 589 5103",
    "sg:postcode":"81101",
    "sg:province":"CO",
    "sg:tags":[
        "stone",
        "crushed"
    ],
    "wof:name":"Southway Cnstr Co Inc Alamosa",
    "wof:placetype":"venue"
},
  "geometry": {"coordinates":[-105.849879,37.473409],"type":"Point"}
}