{
  "type": "Feature",
  "properties": {
    "addr:full":"2399 Co Rd 134 Hesperus CO 81326",
    "addr:housenumber":"2399",
    "addr:postcode":"81326",
    "addr:street":"Co Rd 134 Hesperus",
    "iso:country":"US",
    "sg:address":"2399 Co Rd 134",
    "sg:city":"Hesperus",
    "sg:classifiers":[
        {
            "category":"Building & Trades",
            "subcategory":"Construction",
            "type":"Services"
        }
    ],
    "sg:phone":"+1 970 588 3833",
    "sg:postcode":"81326",
    "sg:province":"CO",
    "sg:tags":[
        "contractor"
    ],
    "wof:name":"Dry Side Builders",
    "wof:placetype":"venue"
},
  "geometry": {"coordinates":[-108.13547699999999,37.074365],"type":"Point"}
}