{
  "type": "Feature",
  "properties": {
    "iso:country":"US",
    "sg:address":"1612 Pennsylvania Street",
    "sg:city":"Denver",
    "sg:classifiers":[
        {
            "category":"Banks & Credit Unions",
            "subcategory":"Atm",
            "type":"Services"
        }
    ],
    "sg:phone":"+1 303 860 1700",
    "sg:postcode":"80203",
    "sg:province":"CO",
    "sg:tags":[
        "bankruptcy"
    ],
    "wof:name":"Law Offices of Todd J Hall PC",
    "wof:placetype":"venue"
},
  "geometry": {"coordinates":[-104.981099,39.741858],"type":"Point"}
}