{
  "type": "Feature",
  "properties": {
    "iso:country":"US",
    "sg:address":"2050 E County Line Rd",
    "sg:city":"Littleton",
    "sg:classifiers":[
        {
            "category":"Shopping",
            "subcategory":"Clothing, Apparel, & Fashions",
            "type":"Retail Goods"
        }
    ],
    "sg:phone":"+1 303 347 8533",
    "sg:postcode":"80126",
    "sg:province":"CO",
    "sg:tags":[
        "furnishing"
    ],
    "sg:website":"www.menswearhouse.com",
    "wof:name":"Men's Wearhouse",
    "wof:placetype":"venue"
},
  "geometry": {"coordinates":[-104.96914200000001,39.565999],"type":"Point"}
}