{
  "type": "Feature",
  "properties": {
    "addr:full":"104 Orchard Ave Grand Junction CO 81501",
    "addr:housenumber":"104",
    "addr:postcode":"81501",
    "addr:street":"Orchard Ave",
    "iso:country":"US",
    "sg:address":"104 Orchard Ave",
    "sg:city":"Grand Junction",
    "sg:classifiers":[
        {
            "category":"Insurance",
            "subcategory":"Insurance Agent",
            "type":"Services"
        }
    ],
    "sg:phone":"+1 970 243 6472",
    "sg:postcode":"81501",
    "sg:province":"CO",
    "wof:name":"Rick Hudak Agency",
    "wof:placetype":"venue"
},
  "geometry": {"coordinates":[-108.568079,39.084696],"type":"Point"}
}