{
  "type": "Feature",
  "properties": {
    "iso:country":"US",
    "sg:address":"9197 W 6th Ave",
    "sg:city":"Denver",
    "sg:classifiers":[
        {
            "category":"Manufacturing",
            "subcategory":"Apparel",
            "type":"Manufacturing & Wholesale Goods"
        },
        {
            "category":"Shopping",
            "subcategory":"Clothing, Apparel, & Fashions",
            "type":"Retail Goods"
        }
    ],
    "sg:phone":"+1 303 674 3139",
    "sg:postcode":"80215",
    "sg:province":"CO",
    "sg:tags":[
        "infant",
        "wear",
        "mfg"
    ],
    "wof:name":"Garb Inc",
    "wof:placetype":"venue"
},
  "geometry": {"coordinates":[-105.09704600000001,39.725691],"type":"Point"}
}