{
  "type": "Feature",
  "properties": {
    "addr:full":"5330 Fox St Denver CO 80216",
    "addr:housenumber":"5330",
    "addr:postcode":"80216",
    "addr:street":"Fox St",
    "iso:country":"US",
    "sg:address":"5330 Fox St",
    "sg:city":"Denver",
    "sg:classifiers":[
        {
            "category":"Wholesale",
            "subcategory":"Jewelry",
            "type":"Manufacturing & Wholesale Goods"
        }
    ],
    "sg:phone":"+1 303 292 3090",
    "sg:postcode":"80216",
    "sg:province":"CO",
    "sg:tags":[
        "indian"
    ],
    "sg:website":"www.navajomfg.com",
    "wof:name":"Navajo Manufacturing Co",
    "wof:placetype":"venue"
},
  "geometry": {"coordinates":[-104.994896,39.791457],"type":"Point"}
}