{
  "type": "Feature",
  "properties": {
    "addr:full":"12835 E Arapahoe Rd Centennial CO 80112",
    "addr:housenumber":"12835",
    "addr:postcode":"80112",
    "addr:street":"E Arapahoe Rd",
    "iso:country":"US",
    "sg:address":"12835 E Arapahoe Rd",
    "sg:city":"Centennial",
    "sg:classifiers":[
        {
            "category":"Professional",
            "type":"Services"
        },
        {
            "category":"Professional",
            "subcategory":"Computer Services",
            "type":"Services"
        }
    ],
    "sg:phone":"+1 303 708 9033",
    "sg:postcode":"80112",
    "sg:province":"CO",
    "sg:tags":[
        "development",
        "establishment",
        "software"
    ],
    "sg:website":"www.federationweb.com",
    "wof:name":"Federation Web Inc",
    "wof:placetype":"venue"
},
  "geometry": {"coordinates":[-104.83904200000001,39.59512],"type":"Point"}
}