{
  "type": "Feature",
  "properties": {
    "addr:full":"211 Violet St Golden CO 80401",
    "addr:housenumber":"211",
    "addr:postcode":"80401",
    "addr:street":"Violet St",
    "iso:country":"US",
    "sg:address":"211 Violet St",
    "sg:city":"Golden",
    "sg:classifiers":[
        {
            "category":"Wholesale",
            "subcategory":"Medical Equipment & Supplies",
            "type":"Manufacturing & Wholesale Goods"
        },
        {
            "category":"Shopping",
            "subcategory":"Clothing, Apparel, & Fashions",
            "type":"Retail Goods"
        }
    ],
    "sg:phone":"+1 303 894 9748",
    "sg:postcode":"80401",
    "sg:province":"CO",
    "sg:tags":[
        "device",
        "shoes-orthopedic",
        "orthopedic",
        "appliance",
        "prosthetic"
    ],
    "wof:name":"Durbin And Associates",
    "wof:placetype":"venue"
},
  "geometry": {"coordinates":[-105.19689200000001,39.719195],"type":"Point"}
}