{
  "type": "Feature",
  "properties": {
    "iso:country":"US",
    "sg:address":"6157 N Academy Blvd",
    "sg:city":"Colorado Springs",
    "sg:classifiers":[
        {
            "category":"Retail",
            "subcategory":"Auto Repair",
            "type":"Services"
        }
    ],
    "sg:phone":"+1 719 598 4544",
    "sg:postcode":"80918",
    "sg:province":"CO",
    "sg:tags":[
        "transmission"
    ],
    "wof:name":"Best Western Transmission",
    "wof:placetype":"venue"
},
  "geometry": {"coordinates":[-104.792249,38.921734],"type":"Point"}
}