{
  "type": "Feature",
  "properties": {
    "iso:country":"US",
    "sg:address":"2100 W Littleton Blvd # 50",
    "sg:city":"Littleton",
    "sg:classifiers":[
        {
            "category":"Building & Trades",
            "subcategory":"Construction",
            "type":"Services"
        }
    ],
    "sg:phone":"+1 303 385 1290",
    "sg:postcode":"80120",
    "sg:province":"CO",
    "sg:tags":[
        "system",
        "specialty",
        "heating",
        "contractor",
        "air conditioning"
    ],
    "sg:website":"http://www.e-cbsinc.com",
    "wof:name":"Urquhart Consulting, Inc.",
    "wof:placetype":"venue"
},
  "geometry": {"coordinates":[-105.012038,39.613251],"type":"Point"}
}