{
  "type": "Feature",
  "properties": {
    "iso:country":"US",
    "sg:address":"921 E Main St",
    "sg:city":"Florence",
    "sg:classifiers":[
        {
            "category":"Restaurant",
            "type":"Food & Drink"
        }
    ],
    "sg:menulink":"http://www.allmenus.com/co/florence/128893-subway/menu/",
    "sg:phone":"+1 719 784 0338",
    "sg:postcode":"81226",
    "sg:province":"CO",
    "sg:tags":[
        "american",
        "sandwich"
    ],
    "wof:name":"Subway",
    "wof:placetype":"venue"
},
  "geometry": {"coordinates":[-105.10334899999999,38.387357],"type":"Point"}
}