{
  "type": "Feature",
  "properties": {
    "addr:full":"1307 Bannock St Denver CO 80204",
    "addr:housenumber":"1307",
    "addr:postcode":"80204",
    "addr:street":"Bannock St",
    "iso:country":"US",
    "sg:address":"1307 Bannock St",
    "sg:city":"Denver",
    "sg:classifiers":[
        {
            "category":"Shopping",
            "type":"Retail Goods"
        }
    ],
    "sg:phone":"+1 303 534 0996",
    "sg:postcode":"80204",
    "sg:province":"CO",
    "sg:tags":[
        "art",
        "gallery",
        "dealer"
    ],
    "wof:name":"Emil Nelson Gallery",
    "wof:placetype":"venue"
},
  "geometry": {"coordinates":[-104.990315,39.73835],"type":"Point"}
}