{
  "type": "Feature",
  "properties": {
    "addr:full":"1372 Main St Carbondale CO 81623",
    "addr:housenumber":"1372",
    "addr:postcode":"81623",
    "addr:street":"Main St",
    "iso:country":"US",
    "sg:address":"1372 Main St",
    "sg:city":"Carbondale",
    "sg:classifiers":[
        {
            "category":"Real Estate",
            "subcategory":"Real Estate Agent",
            "type":"Services"
        }
    ],
    "sg:phone":"+1 970 963 1480",
    "sg:postcode":"81623",
    "sg:province":"CO",
    "sg:tags":[
        "appraiser"
    ],
    "wof:name":"High Country Appraisal Assoc",
    "wof:placetype":"venue"
},
  "geometry": {"coordinates":[-107.221878,39.401019],"type":"Point"}
}