{
  "type": "Feature",
  "properties": {
    "addr:full":"10135 W Idaho Pl Lakewood CO 80232",
    "addr:housenumber":"10135",
    "addr:postcode":"80232",
    "addr:street":"W Idaho Pl",
    "iso:country":"US",
    "sg:address":"10135 W Idaho Pl",
    "sg:city":"Lakewood",
    "sg:classifiers":[
        {
            "category":"Wholesale",
            "subcategory":"Machinery & Supplies",
            "type":"Manufacturing & Wholesale Goods"
        }
    ],
    "sg:phone":"+1 303 200 4798",
    "sg:postcode":"80232",
    "sg:province":"CO",
    "sg:tags":[
        "fire",
        "department",
        "equipment"
    ],
    "wof:name":"Respirator Tru-Fit Svc Inc",
    "wof:placetype":"venue"
},
  "geometry": {"coordinates":[-105.11133,39.689765],"type":"Point"}
}