{
  "type": "Feature",
  "properties": {
    "iso:country":"US",
    "sg:address":"329 E Colfax Ave",
    "sg:city":"Denver",
    "sg:classifiers":[
        {
            "category":"Building & Trades",
            "subcategory":"Locksmith",
            "type":"Services"
        }
    ],
    "sg:phone":"+1 303 218 7272",
    "sg:postcode":"80203",
    "sg:province":"CO",
    "sg:tags":[
        "key"
    ],
    "wof:name":"Locksmith Express",
    "wof:placetype":"venue"
},
  "geometry": {"coordinates":[-104.983193,39.740197],"type":"Point"}
}