{
  "type": "Feature",
  "properties": {
    "iso:country":"US",
    "sg:address":"1115 49th Ave",
    "sg:city":"Greeley",
    "sg:classifiers":[
        {
            "category":"Building & Trades",
            "subcategory":"Plumbing",
            "type":"Services"
        }
    ],
    "sg:phone":"+1 970 336 6437",
    "sg:postcode":"80634",
    "sg:province":"CO",
    "sg:tags":[
        "plumbing",
        "contractor"
    ],
    "wof:name":"Jantz Plumbing & Heating",
    "wof:placetype":"venue"
},
  "geometry": {"coordinates":[-104.761725,40.419028],"type":"Point"}
}