{
  "type": "Feature",
  "properties": {
    "iso:country":"US",
    "sg:address":"2720 S Academy Blvd",
    "sg:city":"Colorado Springs",
    "sg:classifiers":[
        {
            "category":"Restaurant",
            "type":"Food & Drink"
        }
    ],
    "sg:phone":"+1 719 392 2277",
    "sg:postcode":"80916",
    "sg:province":"CO",
    "sg:tags":[
        "eating"
    ],
    "wof:name":"El Super Taco",
    "wof:placetype":"venue"
},
  "geometry": {"coordinates":[-104.757653,38.795772],"type":"Point"}
}