{
  "type": "Feature",
  "properties": {
    "addr:full":"2680 S Tejon St Englewood CO 80110",
    "addr:housenumber":"2680",
    "addr:postcode":"80110",
    "addr:street":"S Tejon St",
    "iso:country":"US",
    "sg:address":"2680 S Tejon St",
    "sg:city":"Englewood",
    "sg:classifiers":[
        {
            "category":"Home & Garden",
            "subcategory":"Carpets & Floor Coverings",
            "type":"Retail Goods"
        }
    ],
    "sg:phone":"+1 303 936 4040",
    "sg:postcode":"80110",
    "sg:province":"CO",
    "wof:name":"Walters Flooring Inc",
    "wof:placetype":"venue"
},
  "geometry": {"coordinates":[-105.010998,39.668334],"type":"Point"}
}