{
  "type": "Feature",
  "properties": {
    "addr:full":"264 Union Blvd Denver CO 80228",
    "addr:housenumber":"264",
    "addr:postcode":"80228",
    "addr:street":"Union Blvd",
    "iso:country":"US",
    "sg:address":"264 Union Blvd",
    "sg:city":"Denver",
    "sg:classifiers":[
        {
            "category":"Restaurant",
            "type":"Food & Drink"
        }
    ],
    "sg:menulink":"http://www.allmenus.com/co/northeast-jefferson/25728-red-lobster/menu/",
    "sg:phone":"+1 303 987 3789",
    "sg:postcode":"80228",
    "sg:province":"CO",
    "sg:tags":[
        "seafood",
        "american"
    ],
    "wof:name":"Red Lobster",
    "wof:placetype":"venue"
},
  "geometry": {"coordinates":[-105.131677,39.719746],"type":"Point"}
}