{
  "type": "Feature",
  "properties": {
    "iso:country":"US",
    "sg:address":"32 10th St",
    "sg:city":"Steamboat Spgs",
    "sg:classifiers":[
        {
            "category":"Utilities",
            "subcategory":"Electric",
            "type":"Services"
        }
    ],
    "sg:phone":"+1 970 879 1160",
    "sg:postcode":"80487",
    "sg:province":"CO",
    "sg:tags":[
        "company"
    ],
    "sg:website":"www.yvea.com",
    "wof:name":"Yampa Valley Electric Assn Inc",
    "wof:placetype":"venue"
},
  "geometry": {"coordinates":[-106.836912,40.487113],"type":"Point"}
}