{
  "type": "Feature",
  "properties": {
    "addr:full":"438 W Main St Montrose CO 81401",
    "addr:housenumber":"438",
    "addr:postcode":"81401",
    "addr:street":"W Main St",
    "iso:country":"US",
    "sg:address":"438 W Main St",
    "sg:city":"Montrose",
    "sg:classifiers":[
        {
            "category":"Shopping",
            "subcategory":"Beauty & Cosmetics",
            "type":"Retail Goods"
        }
    ],
    "sg:phone":"+1 970 249 4856",
    "sg:postcode":"81401",
    "sg:province":"CO",
    "wof:name":"Merle Norman Cosmetics",
    "wof:placetype":"venue"
},
  "geometry": {"coordinates":[-107.885541,38.475151],"type":"Point"}
}