{
  "type": "Feature",
  "properties": {
    "addr:full":"117 S Sunset St Longmont CO 80501",
    "addr:housenumber":"117",
    "addr:postcode":"80501",
    "addr:street":"S Sunset St",
    "iso:country":"US",
    "sg:address":"117 S Sunset St",
    "sg:city":"Longmont",
    "sg:classifiers":[
        {
            "category":"Professional",
            "subcategory":"Business Services",
            "type":"Services"
        }
    ],
    "sg:phone":"+1 303 485 0116",
    "sg:postcode":"80501",
    "sg:province":"CO",
    "sg:tags":[
        "embroidery"
    ],
    "wof:name":"Stitchables",
    "wof:placetype":"venue"
},
  "geometry": {"coordinates":[-105.121438,40.157463],"type":"Point"}
}