{
  "type": "Feature",
  "properties": {
    "iso:country":"US",
    "sg:address":"4667 Decatur Street",
    "sg:city":"Denver",
    "sg:classifiers":[
        {
            "category":"Building & Trades",
            "subcategory":"Locksmith",
            "type":"Services"
        }
    ],
    "sg:phone":"+1 303 242 3152",
    "sg:postcode":"80211",
    "sg:province":"CO",
    "sg:tags":[
        "key"
    ],
    "wof:name":"MacFarlane Bros 24 Hr Emerg Locksmith",
    "wof:placetype":"venue"
},
  "geometry": {"coordinates":[-105.021777,39.781402],"type":"Point"}
}