{
  "type": "Feature",
  "properties": {
    "iso:country":"US",
    "sg:address":"4740 Flintridge Dr",
    "sg:city":"Colorado Springs",
    "sg:classifiers":[
        {
            "category":"Wholesale",
            "subcategory":"Electrical",
            "type":"Manufacturing & Wholesale Goods"
        }
    ],
    "sg:phone":"+1 719 266 0050",
    "sg:postcode":"80918",
    "sg:province":"CO",
    "sg:tags":[
        "lighting",
        "fixture"
    ],
    "wof:name":"M H Lighting Assoc Inc",
    "wof:placetype":"venue"
},
  "geometry": {"coordinates":[-104.76854899999999,38.900664],"type":"Point"}
}