{
  "type": "Feature",
  "properties": {
    "iso:country":"US",
    "sg:address":"9200 Cherry Creek South D",
    "sg:city":"Denver",
    "sg:classifiers":[
        {
            "category":"Banks & Credit Unions",
            "subcategory":"Investment Brokerage",
            "type":"Services"
        }
    ],
    "sg:phone":"+1 303 369 6699",
    "sg:postcode":"80231",
    "sg:province":"CO",
    "sg:tags":[
        "investing"
    ],
    "wof:name":"Williams Ceuleers",
    "wof:placetype":"venue"
},
  "geometry": {"coordinates":[-104.88189199999999,39.665205],"type":"Point"}
}