{
  "type": "Feature",
  "properties": {
    "iso:country":"US",
    "sg:address":"11757 W Ken Caryl Ave",
    "sg:city":"Littleton",
    "sg:classifiers":[
        {
            "category":"Food & Beverages",
            "subcategory":"Liquor & Beverages",
            "type":"Retail Goods"
        }
    ],
    "sg:phone":"+1 303 979 7837",
    "sg:postcode":"80127",
    "sg:province":"CO",
    "wof:name":"L & L Liquor",
    "wof:placetype":"venue"
},
  "geometry": {"coordinates":[-105.13040100000001,39.580801],"type":"Point"}
}