{
  "type": "Feature",
  "properties": {
    "addr:full":"7906 Clarkson Ct Denver CO 80229",
    "addr:housenumber":"7906",
    "addr:postcode":"80229",
    "addr:street":"Clarkson Ct",
    "iso:country":"US",
    "sg:address":"7906 Clarkson Ct",
    "sg:city":"Denver",
    "sg:classifiers":[
        {
            "category":"Building & Trades",
            "subcategory":"Construction",
            "type":"Services"
        }
    ],
    "sg:phone":"+1 303 288 7429",
    "sg:postcode":"80229",
    "sg:province":"CO",
    "sg:tags":[
        "contractor"
    ],
    "wof:name":"Jose Menendez Tile",
    "wof:placetype":"venue"
},
  "geometry": {"coordinates":[-104.97695899999999,39.84019],"type":"Point"}
}