{
  "type": "Feature",
  "properties": {
    "iso:country":"US",
    "sg:address":"2863 North Ave",
    "sg:city":"Grand Junction",
    "sg:classifiers":[
        {
            "category":"Manufacturing",
            "subcategory":"Printing",
            "type":"Manufacturing & Wholesale Goods"
        }
    ],
    "sg:phone":"+1 970 245 9395",
    "sg:postcode":"81501",
    "sg:province":"CO",
    "sg:tags":[
        "periodical"
    ],
    "wof:name":"Newcomers Magazine",
    "wof:placetype":"venue"
},
  "geometry": {"coordinates":[-108.52292799999999,39.077282],"type":"Point"}
}