{
  "type": "Feature",
  "properties": {
    "addr:full":"2761 W Oxford Ave Englewood CO 80110",
    "addr:housenumber":"2761",
    "addr:postcode":"80110",
    "addr:street":"W Oxford Ave",
    "iso:country":"US",
    "sg:address":"2761 W Oxford Ave",
    "sg:city":"Englewood",
    "sg:classifiers":[
        {
            "category":"Wholesale",
            "subcategory":"Hardware",
            "type":"Manufacturing & Wholesale Goods"
        }
    ],
    "sg:phone":"+1 303 781 9559",
    "sg:postcode":"80110",
    "sg:province":"CO",
    "sg:tags":[
        "system",
        "equipment",
        "heating",
        "representative",
        "mfg"
    ],
    "wof:name":"Hydronic Sales Inc",
    "wof:placetype":"venue"
},
  "geometry": {"coordinates":[-105.020954,39.642398],"type":"Point"}
}