{
  "type": "Feature",
  "properties": {
    "addr:full":"12350 E Colfax Ave Aurora CO 80011",
    "addr:housenumber":"12350",
    "addr:postcode":"80011",
    "addr:street":"E Colfax Ave",
    "iso:country":"US",
    "sg:address":"12350 E Colfax Ave",
    "sg:city":"Aurora",
    "sg:classifiers":[
        {
            "category":"Social Services",
            "type":"Services"
        }
    ],
    "sg:phone":"+1 303 344 4824",
    "sg:postcode":"80011",
    "sg:province":"CO",
    "sg:tags":[
        "youth",
        "organization",
        "center"
    ],
    "wof:name":"Denver Area Youth For Christ",
    "wof:placetype":"venue"
},
  "geometry": {"coordinates":[-104.84178199999999,39.740383],"type":"Point"}
}