{
  "type": "Feature",
  "properties": {
    "iso:country":"US",
    "sg:address":"305 Willow St",
    "sg:city":"Del Norte",
    "sg:classifiers":[
        {
            "category":"Building & Trades",
            "subcategory":"Construction",
            "type":"Services"
        }
    ],
    "sg:phone":"+1 719 657 2140",
    "sg:postcode":"81132",
    "sg:province":"CO",
    "sg:tags":[
        "residential"
    ],
    "wof:name":"Samy A Construction",
    "wof:placetype":"venue"
},
  "geometry": {"coordinates":[-106.359847,37.681483],"type":"Point"}
}