{
  "type": "Feature",
  "properties": {
    "iso:country":"US",
    "sg:address":"1475 Jasmine Street",
    "sg:city":"Denver",
    "sg:classifiers":[
        {
            "category":"Retail",
            "subcategory":"Auto Repair",
            "type":"Services"
        }
    ],
    "sg:phone":"+1 303 322 3777",
    "sg:postcode":"80220",
    "sg:province":"CO",
    "wof:name":"Emick's Auto Service",
    "wof:placetype":"venue"
},
  "geometry": {"coordinates":[-104.918516,39.739997],"type":"Point"}
}