{
  "type": "Feature",
  "properties": {
    "iso:country":"US",
    "sg:address":"2155 Midpoint Dr",
    "sg:city":"Fort Collins",
    "sg:classifiers":[
        {
            "category":"Wholesale",
            "subcategory":"Machinery & Supplies",
            "type":"Manufacturing & Wholesale Goods"
        }
    ],
    "sg:phone":"+1 970 226 5888",
    "sg:postcode":"80525",
    "sg:province":"CO",
    "sg:tags":[
        "dry wall",
        "contractor"
    ],
    "sg:website":"www.gypsumproducts.com",
    "wof:name":"Gypsum Products Inc",
    "wof:placetype":"venue"
},
  "geometry": {"coordinates":[-105.038245,40.565635],"type":"Point"}
}