{
  "type": "Feature",
  "properties": {
    "addr:full":"390 Main Ave Akron CO 80720",
    "addr:housenumber":"390",
    "addr:postcode":"80720",
    "addr:street":"Main Ave",
    "iso:country":"US",
    "sg:address":"390 Main Ave",
    "sg:city":"Akron",
    "sg:classifiers":[
        {
            "category":"Professional",
            "subcategory":"Lawyer & Legal Services",
            "type":"Services"
        }
    ],
    "sg:phone":"+1 970 345 6630",
    "sg:postcode":"80720",
    "sg:province":"CO",
    "sg:tags":[
        "attorney"
    ],
    "wof:name":"Kevin L Hoyer",
    "wof:placetype":"venue"
},
  "geometry": {"coordinates":[-103.212749,40.161233],"type":"Point"}
}