{
  "type": "Feature",
  "properties": {
    "iso:country":"US",
    "sg:address":"900 Castleton Road Suite 210",
    "sg:city":"Castle Rock",
    "sg:classifiers":[
        {
            "category":"Professional",
            "subcategory":"Lawyer & Legal Services",
            "type":"Services"
        }
    ],
    "sg:phone":"+1 303 660 9056",
    "sg:postcode":"80109",
    "sg:province":"CO",
    "wof:name":"Law Office of Lori Crystal L L C",
    "wof:placetype":"venue"
},
  "geometry": {"coordinates":[-104.868712,39.409522],"type":"Point"}
}