{
  "type": "Feature",
  "properties": {
    "iso:country":"US",
    "sg:address":"9320 State Hwy 78",
    "sg:city":"Beulah",
    "sg:classifiers":[
        {
            "category":"Travel",
            "subcategory":"Hotels & Motels",
            "type":"Entertainment"
        }
    ],
    "sg:phone":"+1 719 485 7467",
    "sg:postcode":"81023",
    "sg:province":"CO",
    "wof:name":"Hotel Shopping Network",
    "wof:placetype":"venue"
},
  "geometry": {"coordinates":[-105.008652,38.015558],"type":"Point"}
}