{
  "type": "Feature",
  "properties": {
    "iso:country":"US",
    "sg:address":"3159 State Hwy 89",
    "sg:city":"Holly",
    "sg:classifiers":[
        {
            "category":"Wholesale",
            "subcategory":"Farm Supplies",
            "type":"Manufacturing & Wholesale Goods"
        }
    ],
    "sg:phone":"+1 719 537 6728",
    "sg:postcode":"81047",
    "sg:province":"CO",
    "sg:tags":[
        "bean"
    ],
    "wof:name":"Buckeye",
    "wof:placetype":"venue"
},
  "geometry": {"coordinates":[-102.128483,37.673132],"type":"Point"}
}