{
  "type": "Feature",
  "properties": {
    "iso:country":"US",
    "sg:address":"1500 W Littleton Blvd",
    "sg:city":"Littleton",
    "sg:classifiers":[
        {
            "category":"Banks & Credit Unions",
            "subcategory":"Bank",
            "type":"Services"
        }
    ],
    "sg:phone":"+1 303 347 1479",
    "sg:postcode":"80120",
    "sg:province":"CO",
    "sg:tags":[
        "loan"
    ],
    "wof:name":"Advance America",
    "wof:placetype":"venue"
},
  "geometry": {"coordinates":[-105.006828,39.613248],"type":"Point"}
}