{
  "type": "Feature",
  "properties": {
    "addr:full":"1420 Washington Ave Golden CO 80401",
    "addr:housenumber":"1420",
    "addr:postcode":"80401",
    "addr:street":"Washington Ave",
    "iso:country":"US",
    "sg:address":"1420 Washington Ave",
    "sg:city":"Golden",
    "sg:classifiers":[
        {
            "category":"Real Estate",
            "subcategory":"Architect",
            "type":"Services"
        }
    ],
    "sg:phone":"+1 303 271 0977",
    "sg:postcode":"80401",
    "sg:province":"CO",
    "sg:website":"www.ewersarchitecture.com",
    "wof:name":"Ewers Architecture",
    "wof:placetype":"venue"
},
  "geometry": {"coordinates":[-105.219255,39.753063],"type":"Point"}
}