{
  "type": "Feature",
  "properties": {
    "iso:country":"US",
    "sg:address":"1629 57th Ave",
    "sg:city":"Greeley",
    "sg:classifiers":[
        {
            "category":"Shopping",
            "type":"Retail Goods"
        },
        {
            "category":"Retail",
            "subcategory":"Animal Services",
            "type":"Services"
        }
    ],
    "sg:phone":"+1 970 381 9677",
    "sg:postcode":"80634",
    "sg:province":"CO",
    "sg:tags":[
        "pet",
        "boarding",
        "merchandise",
        "sitting"
    ],
    "wof:name":"Pets Best Friend",
    "wof:placetype":"venue"
},
  "geometry": {"coordinates":[-104.772791,40.412507],"type":"Point"}
}