{
  "type": "Feature",
  "properties": {
    "iso:country":"US",
    "sg:address":"22 N Uncompahgre Ave",
    "sg:city":"Montrose",
    "sg:classifiers":[
        {
            "category":"Personal",
            "subcategory":"Beauty Salon",
            "type":"Services"
        }
    ],
    "sg:phone":"+1 970 240 3421",
    "sg:postcode":"81401",
    "sg:province":"CO",
    "wof:name":"Stylz",
    "wof:placetype":"venue"
},
  "geometry": {"coordinates":[-107.876243,38.48086],"type":"Point"}
}