{
  "type": "Feature",
  "properties": {
    "addr:full":"11757 W Ken Caryl Ave Littleton CO 80127",
    "addr:housenumber":"11757",
    "addr:postcode":"80127",
    "addr:street":"W Ken Caryl Ave",
    "iso:country":"US",
    "sg:address":"11757 W Ken Caryl Ave",
    "sg:city":"Littleton",
    "sg:classifiers":[
        {
            "category":"Home & Garden",
            "subcategory":"Home Furnishings",
            "type":"Retail Goods"
        }
    ],
    "sg:phone":"+1 303 973 1235",
    "sg:postcode":"80127",
    "sg:province":"CO",
    "sg:tags":[
        "window",
        "covering"
    ],
    "sg:website":"www.theblindspot.biz",
    "wof:name":"Blind Spot",
    "wof:placetype":"venue"
},
  "geometry": {"coordinates":[-105.13040100000001,39.580801],"type":"Point"}
}