{
  "type": "Feature",
  "properties": {
    "iso:country":"US",
    "sg:address":"511 N Main St",
    "sg:city":"Pueblo",
    "sg:classifiers":[
        {
            "category":"Banks & Credit Unions",
            "subcategory":"Investment Brokerage",
            "type":"Services"
        }
    ],
    "sg:phone":"+1 719 544 8611",
    "sg:postcode":"81003",
    "sg:province":"CO",
    "sg:tags":[
        "firm",
        "brokerage",
        "stock",
        "bond"
    ],
    "sg:website":"www.wachoviasec.com",
    "wof:name":"Wachovia Securities LLC",
    "wof:placetype":"venue"
},
  "geometry": {"coordinates":[-104.60869,38.272404],"type":"Point"}
}