{
  "type": "Feature",
  "properties": {
    "addr:full":"1336 Northridge Ct Boulder CO 80304",
    "addr:housenumber":"1336",
    "addr:postcode":"80304",
    "addr:street":"Northridge Ct",
    "iso:country":"US",
    "sg:address":"1336 Northridge Ct",
    "sg:city":"Boulder",
    "sg:classifiers":[
        {
            "category":"Professional",
            "subcategory":"Business Services",
            "type":"Services"
        }
    ],
    "sg:phone":"+1 303 444 0181",
    "sg:postcode":"80304",
    "sg:province":"CO",
    "sg:tags":[
        "arbitration"
    ],
    "wof:name":"Tom Smith Divorce Mediation",
    "wof:placetype":"venue"
},
  "geometry": {"coordinates":[-105.28059,40.044475],"type":"Point"}
}