{
  "type": "Feature",
  "properties": {
    "iso:country":"US",
    "sg:address":"3680 Twisted Oak Cir",
    "sg:city":"Colorado Springs",
    "sg:classifiers":[
        {
            "category":"Professional",
            "subcategory":"Management & Consulting",
            "type":"Services"
        }
    ],
    "sg:phone":"+1 719 685 3200",
    "sg:postcode":"80904",
    "sg:province":"CO",
    "sg:tags":[
        "consultant",
        "business"
    ],
    "wof:name":"Symmetrics Marketing Corp",
    "wof:placetype":"venue"
},
  "geometry": {"coordinates":[-104.89892500000001,38.882722],"type":"Point"}
}