{
  "type": "Feature",
  "properties": {
    "iso:country":"US",
    "sg:address":"8015 W Alameda Avenue Suite 150",
    "sg:city":"Lakewood",
    "sg:classifiers":[
        {
            "category":"Health Services",
            "subcategory":"Clinic",
            "type":"Services"
        },
        {
            "category":"Personal",
            "subcategory":"Hair Removal",
            "type":"Services"
        },
        {
            "category":"Personal",
            "subcategory":"Skin Care",
            "type":"Services"
        }
    ],
    "sg:phone":"+1 303 202 0927",
    "sg:postcode":"80226",
    "sg:province":"CO",
    "sg:tags":[
        "spa",
        "medical",
        "laser"
    ],
    "sg:website":"www.lakewoodlaser.com",
    "wof:name":"Lakewood Laser & Skin Renewal",
    "wof:placetype":"venue"
},
  "geometry": {"coordinates":[-105.086293,39.711118],"type":"Point"}
}