{
  "type": "Feature",
  "properties": {
    "iso:country":"US",
    "sg:address":"4877 Co Rd X",
    "sg:city":"Lamar",
    "sg:classifiers":[
        {
            "category":"Farming",
            "subcategory":"Livestock Farm",
            "type":"Manufacturing & Wholesale Goods"
        }
    ],
    "sg:phone":"+1 719 336 0800",
    "sg:postcode":"81052",
    "sg:province":"CO",
    "sg:tags":[
        "hog"
    ],
    "wof:name":"Colorado Pork",
    "wof:placetype":"venue"
},
  "geometry": {"coordinates":[-102.669729,37.939897],"type":"Point"}
}