{
  "type": "Feature",
  "properties": {
    "addr:full":"3300 S Tamarac Dr Denver CO 80231",
    "addr:housenumber":"3300",
    "addr:postcode":"80231",
    "addr:street":"S Tamarac Dr",
    "iso:country":"US",
    "sg:address":"3300 S Tamarac Dr",
    "sg:city":"Denver",
    "sg:classifiers":[
        {
            "category":"Manufacturing",
            "subcategory":"Retail Goods",
            "type":"Manufacturing & Wholesale Goods"
        }
    ],
    "sg:phone":"+1 303 671 2770",
    "sg:postcode":"80231",
    "sg:province":"CO",
    "sg:tags":[
        "product",
        "mfg"
    ],
    "wof:name":"Brensen Industries",
    "wof:placetype":"venue"
},
  "geometry": {"coordinates":[-104.898667,39.654281],"type":"Point"}
}