{
  "type": "Feature",
  "properties": {
    "iso:country":"US",
    "sg:address":"616 Prospect Ave",
    "sg:city":"La Junta",
    "sg:classifiers":[
        {
            "category":"Banks & Credit Unions",
            "subcategory":"Bank",
            "type":"Services"
        }
    ],
    "sg:phone":"+1 719 384 1977",
    "sg:postcode":"81050",
    "sg:province":"CO",
    "sg:tags":[
        "institution",
        "business"
    ],
    "wof:name":"Smart Check",
    "wof:placetype":"venue"
},
  "geometry": {"coordinates":[-103.525785,37.981929],"type":"Point"}
}