{
  "type": "Feature",
  "properties": {
    "iso:country":"US",
    "sg:address":"2300 S Marion St",
    "sg:city":"Denver",
    "sg:classifiers":[
        {
            "category":"Organizations",
            "subcategory":"Religious Organization",
            "type":"Services"
        }
    ],
    "sg:phone":"+1 303 722 8622",
    "sg:postcode":"80210",
    "sg:province":"CO",
    "sg:tags":[
        "church"
    ],
    "wof:name":"South Denver Church Of God",
    "wof:placetype":"venue"
},
  "geometry": {"coordinates":[-104.97228699999999,39.673104],"type":"Point"}
}