{
  "type": "Feature",
  "properties": {
    "addr:full":"5273 E Mineral Ln Centennial CO 80122",
    "addr:housenumber":"5273",
    "addr:postcode":"80122",
    "addr:street":"E Mineral Ln",
    "iso:country":"US",
    "sg:address":"5273 E Mineral Ln",
    "sg:city":"Centennial",
    "sg:classifiers":[
        {
            "category":"Home & Garden",
            "subcategory":"Garden Supply",
            "type":"Retail Goods"
        },
        {
            "category":"Shopping",
            "subcategory":"Party Supplies",
            "type":"Retail Goods"
        },
        {
            "category":"Shopping",
            "subcategory":"Florist",
            "type":"Retail Goods"
        }
    ],
    "sg:phone":"+1 866 990 8415",
    "sg:postcode":"80122",
    "sg:province":"CO",
    "sg:tags":[
        "plant",
        "wedding"
    ],
    "sg:website":"http://www.cherryknollsfloral.com",
    "wof:name":"Cherry Knolls Floral",
    "wof:placetype":"venue"
},
  "geometry": {"coordinates":[-104.926158,39.57357],"type":"Point"}
}