{
  "type": "Feature",
  "properties": {
    "iso:country":"US",
    "sg:address":"23574 US Hwy 287",
    "sg:city":"Springfield",
    "sg:classifiers":[
        {
            "category":"Farming",
            "subcategory":"Livestock Farm",
            "type":"Manufacturing & Wholesale Goods"
        }
    ],
    "sg:phone":"+1 719 523 6704",
    "sg:postcode":"81073",
    "sg:province":"CO",
    "sg:tags":[
        "real",
        "beef",
        "lessor",
        "cattle",
        "property",
        "feedlot"
    ],
    "wof:name":"Higgins Ranch Partnership",
    "wof:placetype":"venue"
},
  "geometry": {"coordinates":[-102.615459,37.325659],"type":"Point"}
}