{
  "type": "Feature",
  "properties": {
    "addr:full":"222 Detroit St Denver CO 80206",
    "addr:housenumber":"222",
    "addr:postcode":"80206",
    "addr:street":"Detroit St",
    "iso:country":"US",
    "sg:address":"222 Detroit St",
    "sg:city":"Denver",
    "sg:classifiers":[
        {
            "category":"Wholesale",
            "subcategory":"Office Equipment",
            "type":"Manufacturing & Wholesale Goods"
        },
        {
            "category":"Home & Garden",
            "subcategory":"Home Furnishings",
            "type":"Retail Goods"
        },
        {
            "category":"Home & Garden",
            "subcategory":"Furniture",
            "type":"Retail Goods"
        }
    ],
    "sg:phone":"+1 303 322 6462",
    "sg:postcode":"80206",
    "sg:province":"CO",
    "sg:tags":[
        "equipment-wholesale",
        "furniture-children's",
        "decor",
        "store",
        "manufacturer"
    ],
    "sg:website":"www.roomandboard.com",
    "wof:name":"Room & Board",
    "wof:placetype":"venue"
},
  "geometry": {"coordinates":[-104.9543,39.71984],"type":"Point"}
}