{
  "type": "Feature",
  "properties": {
    "addr:full":"602 2nd St Paonia CO 81428",
    "addr:housenumber":"602",
    "addr:postcode":"81428",
    "addr:street":"2Nd St",
    "iso:country":"US",
    "sg:address":"602 2nd St",
    "sg:city":"Paonia",
    "sg:classifiers":[
        {
            "category":"Professional",
            "subcategory":"Business Services",
            "type":"Services"
        }
    ],
    "sg:phone":"+1 970 527 5327",
    "sg:postcode":"81428",
    "sg:province":"CO",
    "sg:tags":[
        "interior",
        "consultant",
        "design",
        "decorator"
    ],
    "wof:name":"Sheppard/Hill Designs",
    "wof:placetype":"venue"
},
  "geometry": {"coordinates":[-107.59310600000001,38.867011],"type":"Point"}
}