{
  "type": "Feature",
  "properties": {
    "addr:full":"3141 S Broadway Englewood CO 80113",
    "addr:housenumber":"3141",
    "addr:postcode":"80113",
    "addr:street":"S Broadway",
    "iso:country":"US",
    "sg:address":"3141 S Broadway",
    "sg:city":"Englewood",
    "sg:classifiers":[
        {
            "category":"Home & Garden",
            "subcategory":"Building Materials",
            "type":"Retail Goods"
        }
    ],
    "sg:phone":"+1 303 770 9717",
    "sg:postcode":"80113",
    "sg:province":"CO",
    "sg:tags":[
        "windows"
    ],
    "wof:name":"Signal Home Improvements",
    "wof:placetype":"venue"
},
  "geometry": {"coordinates":[-104.987664,39.659379],"type":"Point"}
}