{
  "type": "Feature",
  "properties": {
    "iso:country":"US",
    "sg:address":"772 Whalers Way",
    "sg:city":"Fort Collins",
    "sg:classifiers":[
        {
            "category":"Professional",
            "subcategory":"Engineering",
            "type":"Services"
        }
    ],
    "sg:phone":"+1 970 377 2086",
    "sg:postcode":"80525",
    "sg:province":"CO",
    "sg:tags":[
        "engineer"
    ],
    "wof:name":"AVI Engineers",
    "wof:placetype":"venue"
},
  "geometry": {"coordinates":[-105.064702,40.52562],"type":"Point"}
}