{
  "type": "Feature",
  "properties": {
    "iso:country":"US",
    "sg:address":"5136 E Tuscany Ct",
    "sg:city":"Littleton",
    "sg:classifiers":[
        {
            "category":"Restaurant",
            "type":"Food & Drink"
        }
    ],
    "sg:phone":"+1 303 346 5175",
    "sg:postcode":"80130",
    "sg:province":"CO",
    "sg:tags":[
        "eating"
    ],
    "wof:name":"TW Telecomputer",
    "wof:placetype":"venue"
},
  "geometry": {"coordinates":[-104.929351,39.554785],"type":"Point"}
}