{
  "type": "Feature",
  "properties": {
    "addr:full":"5 S Fox St Denver CO 80223",
    "addr:housenumber":"5",
    "addr:postcode":"80223",
    "addr:street":"S Fox St",
    "iso:country":"US",
    "sg:address":"5 S Fox St",
    "sg:city":"Denver",
    "sg:classifiers":[
        {
            "category":"Building & Trades",
            "subcategory":"Landscaping Services",
            "type":"Services"
        }
    ],
    "sg:phone":"+1 303 765 4700",
    "sg:postcode":"80223",
    "sg:province":"CO",
    "sg:tags":[
        "landscape"
    ],
    "wof:name":"Thornton McHel-Landscape Desgr",
    "wof:placetype":"venue"
},
  "geometry": {"coordinates":[-104.995244,39.714877],"type":"Point"}
}