{
  "type": "Feature",
  "properties": {
    "iso:country":"US",
    "sg:address":"612 N Tejon St",
    "sg:city":"Colorado Springs",
    "sg:classifiers":[
        {
            "category":"Professional",
            "subcategory":"Business Services",
            "type":"Services"
        }
    ],
    "sg:phone":"+1 719 635 3533",
    "sg:postcode":"80903",
    "sg:province":"CO",
    "sg:tags":[
        "interior",
        "consultant",
        "design",
        "decorator"
    ],
    "wof:name":"Braley Design Assoc",
    "wof:placetype":"venue"
},
  "geometry": {"coordinates":[-104.822968,38.84378],"type":"Point"}
}