{
  "type": "Feature",
  "properties": {
    "iso:country":"US",
    "sg:address":"11450 Huron St",
    "sg:city":"Northglenn",
    "sg:classifiers":[
        {
            "category":"Autos & Motor Vehicles",
            "subcategory":"Auto Supplies",
            "type":"Retail Goods"
        }
    ],
    "sg:phone":"+1 303 452 4543",
    "sg:postcode":"80234",
    "sg:province":"CO",
    "sg:tags":[
        "equipment",
        "air",
        "conditioning",
        "automobile"
    ],
    "wof:name":"Maxair",
    "wof:placetype":"venue"
},
  "geometry": {"coordinates":[-104.99656,39.906453],"type":"Point"}
}