{
  "type": "Feature",
  "properties": {
    "addr:full":"5844 S Datura St Littleton CO 80120",
    "addr:housenumber":"5844",
    "addr:postcode":"80120",
    "addr:street":"S Datura St",
    "iso:country":"US",
    "sg:address":"5844 S Datura St",
    "sg:city":"Littleton",
    "sg:classifiers":[
        {
            "category":"Social Services",
            "type":"Services"
        }
    ],
    "sg:phone":"+1 303 798 7642",
    "sg:postcode":"80120",
    "sg:province":"CO",
    "sg:tags":[
        "organization",
        "welfare"
    ],
    "wof:name":"Meals On Wheels",
    "wof:placetype":"venue"
},
  "geometry": {"coordinates":[-105.004363,39.612247],"type":"Point"}
}