{
  "type": "Feature",
  "properties": {
    "iso:country":"US",
    "sg:address":"82 S Broadway",
    "sg:city":"Denver",
    "sg:classifiers":[
        {
            "category":"Arts & Performance",
            "subcategory":"Art Gallery",
            "type":"Entertainment"
        }
    ],
    "sg:phone":"+1 303 993 4474",
    "sg:postcode":"80223",
    "sg:province":"CO",
    "wof:name":"Illiterate Media Gallery",
    "wof:placetype":"venue"
},
  "geometry": {"coordinates":[-104.98751799999999,39.715009],"type":"Point"}
}