{
  "type": "Feature",
  "properties": {
    "addr:full":"1727 Greeley Mall Greeley CO 80631",
    "addr:housenumber":"1727",
    "addr:postcode":"80631",
    "addr:street":"Greeley Mall",
    "iso:country":"US",
    "sg:address":"1727 Greeley Mall",
    "sg:city":"Greeley",
    "sg:classifiers":[
        {
            "category":"Shopping",
            "subcategory":"Bicycles & Sporting Goods",
            "type":"Retail Goods"
        }
    ],
    "sg:phone":"+1 970 351 0386",
    "sg:postcode":"80631",
    "sg:province":"CO",
    "sg:website":"www.gartsports.com",
    "wof:name":"Gart Sports",
    "wof:placetype":"venue"
},
  "geometry": {"coordinates":[-104.709671,40.388576],"type":"Point"}
}