{
  "type": "Feature",
  "properties": {
    "iso:country":"US",
    "sg:address":"6875 S Broadway",
    "sg:city":"Centennial",
    "sg:classifiers":[
        {
            "category":"Restaurant",
            "type":"Food & Drink"
        }
    ],
    "sg:phone":"+1 303 795 0686",
    "sg:postcode":"80122",
    "sg:province":"CO",
    "sg:tags":[
        "drinking",
        "eating"
    ],
    "sg:website":"www.stuartandersons.com",
    "wof:name":"Stuart Anderson's Black Angus",
    "wof:placetype":"venue"
},
  "geometry": {"coordinates":[-104.988349,39.592722],"type":"Point"}
}