{
  "type": "Feature",
  "properties": {
    "addr:full":"90 Wildernest Ct Silverthorne CO 80498",
    "addr:housenumber":"90",
    "addr:postcode":"80498",
    "addr:street":"Wildernest Ct",
    "iso:country":"US",
    "sg:address":"90 Wildernest Ct",
    "sg:city":"Silverthorne",
    "sg:classifiers":[
        {
            "category":"Real Estate",
            "subcategory":"Real Estate Agent",
            "type":"Services"
        }
    ],
    "sg:phone":"+1 970 262 9499",
    "sg:postcode":"80498",
    "sg:province":"CO",
    "wof:name":"Century 21",
    "wof:placetype":"venue"
},
  "geometry": {"coordinates":[-106.09216600000001,39.615671],"type":"Point"}
}