{
  "type": "Feature",
  "properties": {
    "iso:country":"US",
    "sg:address":"19357 Co Rd 8",
    "sg:city":"Hudson",
    "sg:classifiers":[
        {
            "category":"Recreation",
            "type":"Entertainment"
        }
    ],
    "sg:phone":"+1 303 536 9524",
    "sg:postcode":"80642",
    "sg:province":"CO",
    "sg:tags":[
        "stable"
    ],
    "wof:name":"Yarbrough Stables",
    "wof:placetype":"venue"
},
  "geometry": {"coordinates":[-104.69171900000001,40.044315],"type":"Point"}
}