{
  "type": "Feature",
  "properties": {
    "addr:full":"21 W 2nd St La Junta CO 81050",
    "addr:housenumber":"21",
    "addr:postcode":"81050",
    "addr:street":"W 2Nd St",
    "iso:country":"US",
    "sg:address":"21 W 2nd St",
    "sg:city":"La Junta",
    "sg:classifiers":[
        {
            "category":"Banks & Credit Unions",
            "subcategory":"Investment Brokerage",
            "type":"Services"
        }
    ],
    "sg:phone":"+1 719 384 5478",
    "sg:postcode":"81050",
    "sg:province":"CO",
    "sg:tags":[
        "stock",
        "bond"
    ],
    "wof:name":"Edward Jones Co",
    "wof:placetype":"venue"
},
  "geometry": {"coordinates":[-103.54425999999999,37.987028],"type":"Point"}
}