{
  "type": "Feature",
  "properties": {
    "addr:full":"864 Iris Ave Boulder CO 80304",
    "addr:housenumber":"864",
    "addr:postcode":"80304",
    "addr:street":"Iris Ave",
    "iso:country":"US",
    "sg:address":"864 Iris Ave",
    "sg:city":"Boulder",
    "sg:classifiers":[
        {
            "category":"Professional",
            "type":"Services"
        }
    ],
    "sg:phone":"+1 303 440 3352",
    "sg:postcode":"80304",
    "sg:province":"CO",
    "wof:name":"Colorado Derivatives LLC",
    "wof:placetype":"venue"
},
  "geometry": {"coordinates":[-105.28980300000001,40.03586],"type":"Point"}
}