{
  "type": "Feature",
  "properties": {
    "iso:country":"US",
    "sg:address":"1430 Nelson Rd",
    "sg:city":"Longmont",
    "sg:classifiers":[
        {
            "category":"Wholesale",
            "subcategory":"Machinery & Supplies",
            "type":"Manufacturing & Wholesale Goods"
        },
        {
            "category":"Freight",
            "type":"Transportation"
        }
    ],
    "sg:phone":"+1 303 485 2498",
    "sg:postcode":"80501",
    "sg:province":"CO",
    "sg:tags":[
        "glass",
        "bottle",
        "plastic"
    ],
    "wof:name":"Pacific Coast Container Inc",
    "wof:placetype":"venue"
},
  "geometry": {"coordinates":[-105.116259,40.152382],"type":"Point"}
}