{
  "type": "Feature",
  "properties": {
    "iso:country":"US",
    "sg:address":"1245 Palmer Ave",
    "sg:city":"Pueblo",
    "sg:classifiers":[
        {
            "category":"Organizations",
            "subcategory":"Non-profit Organization",
            "type":"Services"
        }
    ],
    "sg:phone":"+1 719 546 0904",
    "sg:postcode":"81004",
    "sg:province":"CO",
    "sg:tags":[
        "information",
        "alcoholism",
        "treatment"
    ],
    "wof:name":"Awareness Institute",
    "wof:placetype":"venue"
},
  "geometry": {"coordinates":[-104.630039,38.244513],"type":"Point"}
}