{
  "type": "Feature",
  "properties": {
    "addr:full":"4005 N Valley Dr Longmont CO 80504",
    "addr:housenumber":"4005",
    "addr:postcode":"80504",
    "addr:street":"N Valley Dr",
    "iso:country":"US",
    "sg:address":"4005 N Valley Dr",
    "sg:city":"Longmont",
    "sg:classifiers":[
        {
            "category":"Utilities",
            "subcategory":"Telephone",
            "type":"Services"
        }
    ],
    "sg:phone":"+1 970 535 0725",
    "sg:postcode":"80504",
    "sg:province":"CO",
    "sg:tags":[
        "communications"
    ],
    "wof:name":"Phonesmart",
    "wof:placetype":"venue"
},
  "geometry": {"coordinates":[-104.97889600000001,40.207189],"type":"Point"}
}