{
  "type": "Feature",
  "properties": {
    "addr:full":"18063 E Gunnison Pl Aurora CO 80017",
    "addr:housenumber":"18063",
    "addr:postcode":"80017",
    "addr:street":"E Gunnison Pl",
    "iso:country":"US",
    "sg:address":"18063 E Gunnison Pl",
    "sg:city":"Aurora",
    "sg:classifiers":[
        {
            "category":"Wholesale",
            "subcategory":"Electrical",
            "type":"Manufacturing & Wholesale Goods"
        }
    ],
    "sg:phone":"+1 303 369 1814",
    "sg:postcode":"80017",
    "sg:province":"CO",
    "sg:tags":[
        "high",
        "fidelity",
        "stereophonic"
    ],
    "wof:name":"Audio Magic Inc",
    "wof:placetype":"venue"
},
  "geometry": {"coordinates":[-104.776628,39.687409],"type":"Point"}
}