{
  "type": "Feature",
  "properties": {
    "addr:full":"7251 Beech Ct Arvada CO 80005",
    "addr:housenumber":"7251",
    "addr:postcode":"80005",
    "addr:street":"Beech Ct",
    "iso:country":"US",
    "sg:address":"7251 Beech Ct",
    "sg:city":"Arvada",
    "sg:classifiers":[
        {
            "category":"Real Estate",
            "subcategory":"Real Estate Operator",
            "type":"Services"
        }
    ],
    "sg:phone":"+1 303 761 8770",
    "sg:postcode":"80005",
    "sg:province":"CO",
    "sg:tags":[
        "building",
        "property",
        "lessor",
        "maintenance"
    ],
    "wof:name":"Jammco LLC",
    "wof:placetype":"venue"
},
  "geometry": {"coordinates":[-105.150826,39.829536],"type":"Point"}
}