{
  "type": "Feature",
  "properties": {
    "addr:full":"1901 L Rd Fruita CO 81521",
    "addr:housenumber":"1901",
    "addr:postcode":"81521",
    "addr:street":"L Rd",
    "iso:country":"US",
    "sg:address":"1901 L Rd",
    "sg:city":"Fruita",
    "sg:phone":"+1 970 858 0820",
    "sg:postcode":"81521",
    "sg:province":"CO",
    "sg:tags":[
        "equipment",
        "commercial"
    ],
    "wof:name":"Desert Equipment Inc",
    "wof:placetype":"venue"
},
  "geometry": {"coordinates":[-108.682536,39.178879],"type":"Point"}
}