{
  "type": "Feature",
  "properties": {
    "addr:full":"14500 W Colfax Ave Untfc11 Lakewood CO 80401",
    "addr:housenumber":"14500",
    "addr:postcode":"80401",
    "addr:street":"W Colfax Ave",
    "iso:country":"US",
    "sg:address":"14500 W Colfax Ave Untfc11",
    "sg:city":"Lakewood",
    "sg:classifiers":[
        {
            "category":"Food & Beverages",
            "subcategory":"Groceries & Convenience Stores",
            "type":"Retail Goods"
        }
    ],
    "sg:phone":"+1 303 215 7100",
    "sg:postcode":"80401",
    "sg:province":"CO",
    "sg:tags":[
        "pretzel"
    ],
    "wof:name":"S Wetzel Pretzels",
    "wof:placetype":"venue"
},
  "geometry": {"coordinates":[-105.159637,39.73481],"type":"Point"}
}