{
  "type": "Feature",
  "properties": {
    "iso:country":"US",
    "sg:address":"321 Court St",
    "sg:city":"Pueblo",
    "sg:classifiers":[
        {
            "category":"Personal",
            "subcategory":"Tanning Parlor",
            "type":"Services"
        }
    ],
    "sg:phone":"+1 719 545 2799",
    "sg:postcode":"81003",
    "sg:province":"CO",
    "sg:tags":[
        "salon"
    ],
    "wof:name":"Braun & Braun Tanning Salon",
    "wof:placetype":"venue"
},
  "geometry": {"coordinates":[-104.610148,38.269969],"type":"Point"}
}