{
  "type": "Feature",
  "properties": {
    "addr:full":"2761 E 124th Cir Thornton CO 80241",
    "addr:housenumber":"2761",
    "addr:postcode":"80241",
    "addr:street":"E 124Th Cir",
    "iso:country":"US",
    "sg:address":"2761 E 124th Cir",
    "sg:city":"Thornton",
    "sg:classifiers":[
        {
            "category":"Shopping",
            "type":"Retail Goods"
        }
    ],
    "sg:phone":"+1 303 451 7525",
    "sg:postcode":"80241",
    "sg:province":"CO",
    "sg:tags":[
        "equipment",
        "pool",
        "swimming"
    ],
    "wof:name":"Supply Connection",
    "wof:placetype":"venue"
},
  "geometry": {"coordinates":[-104.95340400000001,39.923189],"type":"Point"}
}