{
  "type": "Feature",
  "properties": {
    "iso:country":"US",
    "sg:address":"103 Sheppard Dr",
    "sg:city":"Durango",
    "sg:classifiers":[
        {
            "category":"Professional",
            "type":"Services"
        }
    ],
    "sg:phone":"+1 970 247 5021",
    "sg:postcode":"81303",
    "sg:province":"CO",
    "sg:tags":[
        "establishment"
    ],
    "wof:name":"Aardex Corp",
    "wof:placetype":"venue"
},
  "geometry": {"coordinates":[-107.873445,37.236287],"type":"Point"}
}