{
  "type": "Feature",
  "properties": {
    "iso:country":"US",
    "sg:address":"650 Bryant St",
    "sg:city":"Denver",
    "sg:classifiers":[
        {
            "category":"Building & Trades",
            "subcategory":"Construction",
            "type":"Services"
        }
    ],
    "sg:phone":"+1 303 900 5986",
    "sg:postcode":"80204",
    "sg:province":"CO",
    "sg:tags":[
        "system",
        "specialty",
        "heating",
        "ventilating",
        "contractor",
        "air conditioning"
    ],
    "sg:website":"http://www.qualitywestservices.com",
    "wof:name":"Quality West Heating & Cooling",
    "wof:placetype":"venue"
},
  "geometry": {"coordinates":[-105.018681,39.726619],"type":"Point"}
}