{
  "type": "Feature",
  "properties": {
    "iso:country":"US",
    "sg:address":"9140 Wadsworth Pkwy",
    "sg:city":"Broomfield",
    "sg:classifiers":[
        {
            "category":"Personal",
            "subcategory":"Beauty Salon",
            "type":"Services"
        },
        {
            "category":"Personal",
            "subcategory":"Day Spa",
            "type":"Services"
        }
    ],
    "sg:phone":"+1 303 423 2442",
    "sg:postcode":"80021",
    "sg:province":"CO",
    "wof:name":"Body & Sole Salon",
    "wof:placetype":"venue"
},
  "geometry": {"coordinates":[-105.08269300000001,39.862042],"type":"Point"}
}