{
  "type": "Feature",
  "properties": {
    "addr:full":"24059 US Hwy 40 Golden CO 80401",
    "addr:postcode":"24059;co 80401",
    "addr:street":"Us Hwy 40",
    "iso:country":"US",
    "sg:address":"24059 US Hwy 40",
    "sg:city":"Golden",
    "sg:classifiers":[
        {
            "category":"Retail",
            "subcategory":"Veterinary Services",
            "type":"Services"
        }
    ],
    "sg:phone":"+1 303 526 2652",
    "sg:postcode":"80401",
    "sg:province":"CO",
    "sg:tags":[
        "veterinarian"
    ],
    "wof:name":"Canyon Animal Hospital",
    "wof:placetype":"venue"
},
  "geometry": {"coordinates":[-105.270641,39.711555],"type":"Point"}
}