{
  "type": "Feature",
  "properties": {
    "iso:country":"US",
    "sg:address":"7585 S Anvil Horn",
    "sg:city":"Littleton",
    "sg:classifiers":[
        {
            "category":"Wholesale",
            "subcategory":"Durable Goods & Equipment",
            "type":"Manufacturing & Wholesale Goods"
        }
    ],
    "sg:phone":"+1 303 933 4717",
    "sg:postcode":"80127",
    "sg:province":"CO",
    "wof:name":"T & L Filing",
    "wof:placetype":"venue"
},
  "geometry": {"coordinates":[-105.127889,39.579978],"type":"Point"}
}