{
  "type": "Feature",
  "properties": {
    "iso:country":"US",
    "sg:address":"2111 Mountain View Ave",
    "sg:city":"Longmont",
    "sg:classifiers":[
        {
            "category":"Organizations",
            "subcategory":"Religious Organization",
            "type":"Services"
        }
    ],
    "sg:phone":"+1 303 776 7066",
    "sg:postcode":"80501",
    "sg:province":"CO",
    "sg:tags":[
        "church"
    ],
    "sg:website":"www.longmontnazarene.org",
    "wof:name":"Longmont Community Nazarene",
    "wof:placetype":"venue"
},
  "geometry": {"coordinates":[-105.12850899999999,40.181254],"type":"Point"}
}