{
  "type": "Feature",
  "properties": {
    "addr:full":"580 Lakewood Ct Windsor CO 80550",
    "addr:housenumber":"580",
    "addr:postcode":"80550",
    "addr:street":"Lakewood Ct",
    "iso:country":"US",
    "sg:address":"580 Lakewood Ct",
    "sg:city":"Windsor",
    "sg:classifiers":[
        {
            "category":"Banks & Credit Unions",
            "subcategory":"Financial Services",
            "type":"Services"
        }
    ],
    "sg:phone":"+1 970 686 1139",
    "sg:postcode":"80550",
    "sg:province":"CO",
    "sg:tags":[
        "investor"
    ],
    "wof:name":"McCallum Investments LLC",
    "wof:placetype":"venue"
},
  "geometry": {"coordinates":[-104.930334,40.473008],"type":"Point"}
}