{
  "type": "Feature",
  "properties": {
    "iso:country":"US",
    "sg:address":"2600 S Lincoln Ave",
    "sg:city":"Loveland",
    "sg:classifiers":[
        {
            "category":"Freight",
            "type":"Transportation"
        }
    ],
    "sg:phone":"+1 970 663 2988",
    "sg:postcode":"80537",
    "sg:province":"CO",
    "sg:tags":[
        "commercial",
        "storage"
    ],
    "sg:website":"www.abcselfstorage.com",
    "wof:name":"ABC Self Storage",
    "wof:placetype":"venue"
},
  "geometry": {"coordinates":[-105.073297,40.366921],"type":"Point"}
}