{
  "type": "Feature",
  "properties": {
    "addr:full":"5775 Flatiron Pkwy Boulder CO 80301",
    "addr:housenumber":"5775",
    "addr:postcode":"80301",
    "addr:street":"Flatiron Pkwy",
    "iso:country":"US",
    "sg:address":"5775 Flatiron Pkwy",
    "sg:city":"Boulder",
    "sg:classifiers":[
        {
            "category":"Professional",
            "subcategory":"Computer Services",
            "type":"Services"
        }
    ],
    "sg:phone":"+1 303 444 3758",
    "sg:postcode":"80301",
    "sg:province":"CO",
    "sg:tags":[
        "developer"
    ],
    "wof:name":"Ps Technology",
    "wof:placetype":"venue"
},
  "geometry": {"coordinates":[-105.220647,40.02286],"type":"Point"}
}