{
  "type": "Feature",
  "properties": {
    "iso:country":"US",
    "sg:address":"3201 S Zuni St",
    "sg:city":"Englewood",
    "sg:classifiers":[
        {
            "category":"Manufacturing",
            "subcategory":"Tools & Machinery",
            "type":"Manufacturing & Wholesale Goods"
        }
    ],
    "sg:phone":"+1 303 806 0451",
    "sg:postcode":"80110",
    "sg:province":"CO",
    "sg:tags":[
        "machine",
        "shop",
        "mold"
    ],
    "wof:name":"High Plains Tool & Mold",
    "wof:placetype":"venue"
},
  "geometry": {"coordinates":[-105.015829,39.656976],"type":"Point"}
}