{
  "type": "Feature",
  "properties": {
    "iso:country":"US",
    "sg:address":"2116 Sand Dollar Cir",
    "sg:city":"Longmont",
    "sg:classifiers":[
        {
            "category":"Building & Trades",
            "subcategory":"Electrical",
            "type":"Services"
        }
    ],
    "sg:phone":"+1 303 651 6269",
    "sg:postcode":"80503",
    "sg:province":"CO",
    "sg:tags":[
        "electrical",
        "contractor"
    ],
    "wof:name":"Stewart Electric",
    "wof:placetype":"venue"
},
  "geometry": {"coordinates":[-105.142077,40.19757],"type":"Point"}
}