{
  "type": "Feature",
  "properties": {
    "addr:full":"17301 W Colfax Ave Golden CO 80401",
    "addr:housenumber":"17301",
    "addr:postcode":"80401",
    "addr:street":"W Colfax Ave",
    "iso:country":"US",
    "sg:address":"17301 W Colfax Ave",
    "sg:city":"Golden",
    "sg:classifiers":[
        {
            "category":"Home & Garden",
            "subcategory":"Building Materials",
            "type":"Retail Goods"
        }
    ],
    "sg:phone":"+1 303 287 5700",
    "sg:postcode":"80401",
    "sg:province":"CO",
    "sg:tags":[
        "windows"
    ],
    "sg:website":"www.eaglewindow.com",
    "wof:name":"Eagle Window Of Colorado",
    "wof:placetype":"venue"
},
  "geometry": {"coordinates":[-105.196716,39.721979],"type":"Point"}
}