{
  "type": "Feature",
  "properties": {
    "iso:country":"US",
    "sg:address":"4785 Tejon St",
    "sg:city":"Denver",
    "sg:classifiers":[
        {
            "category":"Banks & Credit Unions",
            "subcategory":"Bank",
            "type":"Services"
        }
    ],
    "sg:phone":"+1 303 433 9601",
    "sg:postcode":"80211",
    "sg:province":"CO",
    "sg:tags":[
        "loan",
        "real estate"
    ],
    "wof:name":"International Business Finance",
    "wof:placetype":"venue"
},
  "geometry": {"coordinates":[-105.01121500000001,39.782753],"type":"Point"}
}