{
  "type": "Feature",
  "properties": {
    "iso:country":"US",
    "sg:address":"1085 Sherman St",
    "sg:city":"Denver",
    "sg:classifiers":[
        {
            "category":"Professional",
            "type":"Services"
        }
    ],
    "sg:phone":"+1 303 863 1785",
    "sg:postcode":"80203",
    "sg:province":"CO",
    "sg:tags":[
        "establishment"
    ],
    "wof:name":"Brown Adlen Co",
    "wof:placetype":"venue"
},
  "geometry": {"coordinates":[-104.984928,39.732301],"type":"Point"}
}