{
  "type": "Feature",
  "properties": {
    "iso:country":"US",
    "sg:address":"1042 S Peoria St",
    "sg:city":"Aurora",
    "sg:classifiers":[
        {
            "category":"Restaurant",
            "type":"Food & Drink"
        }
    ],
    "sg:phone":"+1 303 363 6737",
    "sg:postcode":"80012",
    "sg:province":"CO",
    "sg:tags":[
        "eating"
    ],
    "wof:name":"Palm Tree Restaurant & Lounge",
    "wof:placetype":"venue"
},
  "geometry": {"coordinates":[-104.847083,39.697792],"type":"Point"}
}