{
  "type": "Feature",
  "properties": {
    "iso:country":"US",
    "sg:address":"3200 W 71st Ave",
    "sg:city":"Westminster",
    "sg:classifiers":[
        {
            "category":"Building & Trades",
            "subcategory":"Construction",
            "type":"Services"
        }
    ],
    "sg:phone":"+1 303 428 2490",
    "sg:postcode":"80030",
    "sg:province":"CO",
    "sg:tags":[
        "contractor"
    ],
    "wof:name":"Horizon Restoration",
    "wof:placetype":"venue"
},
  "geometry": {"coordinates":[-105.03049,39.824567],"type":"Point"}
}