{
  "type": "Feature",
  "properties": {
    "addr:full":"27037 Co Rd 28 Wray CO 80758",
    "addr:housenumber":"27037;28",
    "addr:postcode":"80758",
    "addr:street":"Co Rd",
    "iso:country":"US",
    "sg:address":"27037 Co Rd 28",
    "sg:city":"Wray",
    "sg:phone":"+1 970 332 5248",
    "sg:postcode":"80758",
    "sg:province":"CO",
    "sg:tags":[
        "farm",
        "wheat",
        "corn",
        "grain",
        "cash"
    ],
    "wof:name":"Welp Farms Inc",
    "wof:placetype":"venue"
},
  "geometry": {"coordinates":[-102.298269,39.977329],"type":"Point"}
}