{
  "type": "Feature",
  "properties": {
    "iso:country":"US",
    "sg:address":"6255 W Quincy Ave",
    "sg:city":"Denver",
    "sg:classifiers":[
        {
            "category":"Shopping",
            "subcategory":"Bicycles & Sporting Goods",
            "type":"Retail Goods"
        }
    ],
    "sg:phone":"+1 303 985 1559",
    "sg:postcode":"80236",
    "sg:province":"CO",
    "sg:tags":[
        "equipment",
        "golf"
    ],
    "wof:name":"Golf Shop",
    "wof:placetype":"venue"
},
  "geometry": {"coordinates":[-105.060057,39.638752],"type":"Point"}
}