{
  "type": "Feature",
  "properties": {
    "addr:full":"3270 W Alameda Ave Denver CO 80219",
    "addr:housenumber":"3270",
    "addr:postcode":"80219",
    "addr:street":"W Alameda Ave",
    "iso:country":"US",
    "sg:address":"3270 W Alameda Ave",
    "sg:city":"Denver",
    "sg:classifiers":[
        {
            "category":"Retail",
            "subcategory":"Repair Shop",
            "type":"Services"
        }
    ],
    "sg:phone":"+1 303 972 4270",
    "sg:postcode":"80219",
    "sg:province":"CO",
    "sg:tags":[
        "appliance"
    ],
    "sg:website":"www.dnmech.com",
    "wof:name":"Day & Night Mechanical Inc",
    "wof:placetype":"venue"
},
  "geometry": {"coordinates":[-105.02924299999999,39.711077],"type":"Point"}
}