{
  "type": "Feature",
  "properties": {
    "addr:full":"8547 E Arapahoe Rd Englewood CO 80112",
    "addr:housenumber":"8547",
    "addr:postcode":"80112",
    "addr:street":"E Arapahoe Rd",
    "iso:country":"US",
    "sg:address":"8547 E Arapahoe Rd",
    "sg:city":"Englewood",
    "sg:classifiers":[
        {
            "category":"Restaurant",
            "type":"Food & Drink"
        }
    ],
    "sg:phone":"+1 303 779 3685",
    "sg:postcode":"80112",
    "sg:province":"CO",
    "sg:tags":[
        "eating"
    ],
    "wof:name":"Steak Escape",
    "wof:placetype":"venue"
},
  "geometry": {"coordinates":[-104.89237300000001,39.595112],"type":"Point"}
}