{
  "type": "Feature",
  "properties": {
    "addr:full":"5150 W 120th Ave Broomfield CO 80020",
    "addr:housenumber":"5150",
    "addr:postcode":"80020",
    "addr:street":"W 120Th Ave",
    "iso:country":"US",
    "sg:address":"5150 W 120th Ave",
    "sg:city":"Broomfield",
    "sg:classifiers":[
        {
            "category":"Food & Beverages",
            "subcategory":"Groceries & Convenience Stores",
            "type":"Retail Goods"
        }
    ],
    "sg:phone":"+1 303 404 3460",
    "sg:postcode":"80020",
    "sg:province":"CO",
    "sg:tags":[
        "grocer"
    ],
    "wof:name":"Albertsons",
    "wof:placetype":"venue"
},
  "geometry": {"coordinates":[-105.04644,39.914059],"type":"Point"}
}