{
  "type": "Feature",
  "properties": {
    "iso:country":"US",
    "sg:address":"2510 E Arapahoe Rd",
    "sg:city":"Centennial",
    "sg:classifiers":[
        {
            "category":"Professional",
            "subcategory":"Accounting & Tax Preparation",
            "type":"Services"
        }
    ],
    "sg:phone":"+1 303 781 0100",
    "sg:postcode":"80122",
    "sg:province":"CO",
    "sg:tags":[
        "return",
        "filing"
    ],
    "wof:name":"Brewer Accounting Inc",
    "wof:placetype":"venue"
},
  "geometry": {"coordinates":[-104.95932000000001,39.595074],"type":"Point"}
}