{
  "type": "Feature",
  "properties": {
    "iso:country":"US",
    "sg:address":"333 Perry St Ste 309",
    "sg:city":"Castle Rock",
    "sg:classifiers":[
        {
            "category":"Professional",
            "subcategory":"Advertising",
            "type":"Services"
        },
        {
            "category":"Communications",
            "subcategory":"Newspaper",
            "type":"Services"
        },
        {
            "category":"Communications",
            "type":"Services"
        }
    ],
    "sg:phone":"+1 303 660 8222",
    "sg:postcode":"80104",
    "sg:province":"CO",
    "sg:tags":[
        "marketing",
        "design",
        "web"
    ],
    "wof:name":"Savant Marketing Solutions",
    "wof:placetype":"venue"
},
  "geometry": {"coordinates":[-104.858691,39.372922],"type":"Point"}
}