{
  "type": "Feature",
  "properties": {
    "iso:country":"US",
    "sg:address":"300 Main St",
    "sg:city":"Grand Junction",
    "sg:classifiers":[
        {
            "category":"Professional",
            "subcategory":"Lawyer & Legal Services",
            "type":"Services"
        }
    ],
    "sg:phone":"+1 970 248 0984",
    "sg:postcode":"81501",
    "sg:province":"CO",
    "sg:tags":[
        "attorney"
    ],
    "wof:name":"Mark S Rubinstein",
    "wof:placetype":"venue"
},
  "geometry": {"coordinates":[-108.566135,39.067373],"type":"Point"}
}