{
  "type": "Feature",
  "properties": {
    "addr:full":"9950 W 80th Ave Arvada CO 80005",
    "addr:housenumber":"9950",
    "addr:postcode":"80005",
    "addr:street":"W 80Th Ave",
    "iso:country":"US",
    "sg:address":"9950 W 80th Ave",
    "sg:city":"Arvada",
    "sg:classifiers":[
        {
            "category":"Shopping",
            "subcategory":"Pharmacy",
            "type":"Retail Goods"
        }
    ],
    "sg:phone":"+1 303 422 4862",
    "sg:postcode":"80005",
    "sg:province":"CO",
    "sg:tags":[
        "drug",
        "store"
    ],
    "sg:website":"www.lindyspharmacy.com",
    "wof:name":"Lindy's Pharmacy",
    "wof:placetype":"venue"
},
  "geometry": {"coordinates":[-105.10897300000001,39.841856],"type":"Point"}
}