{
  "type": "Feature",
  "properties": {
    "iso:country":"US",
    "sg:address":"2155 Meadowlark Pl",
    "sg:city":"Longmont",
    "sg:classifiers":[
        {
            "category":"Building & Trades",
            "subcategory":"Construction",
            "type":"Services"
        }
    ],
    "sg:phone":"+1 303 478 5029",
    "sg:postcode":"80504",
    "sg:province":"CO",
    "sg:tags":[
        "reclamation",
        "mined",
        "gravel",
        "pit"
    ],
    "wof:name":"Claystone Construction",
    "wof:placetype":"venue"
},
  "geometry": {"coordinates":[-105.014661,40.164847],"type":"Point"}
}