{
  "type": "Feature",
  "properties": {
    "iso:country":"US",
    "sg:address":"5300 Dtc Pkwy",
    "sg:city":"Englewood",
    "sg:classifiers":[
        {
            "category":"Building & Trades",
            "subcategory":"Construction",
            "type":"Services"
        }
    ],
    "sg:phone":"+1 303 220 5600",
    "sg:postcode":"80111",
    "sg:province":"CO",
    "sg:tags":[
        "home",
        "general",
        "family",
        "contractor"
    ],
    "wof:name":"Adare Homes LLC",
    "wof:placetype":"venue"
},
  "geometry": {"coordinates":[-104.896175,39.617709],"type":"Point"}
}