{
  "type": "Feature",
  "properties": {
    "iso:country":"US",
    "sg:address":"3010 E 6th Avenue",
    "sg:city":"Denver",
    "sg:classifiers":[
        {
            "category":"Professional",
            "subcategory":"Lawyer & Legal Services",
            "type":"Services"
        }
    ],
    "sg:phone":"+1 303 573 7777",
    "sg:postcode":"80206",
    "sg:province":"CO",
    "wof:name":"Marlin William C Atty",
    "wof:placetype":"venue"
},
  "geometry": {"coordinates":[-104.951885,39.725493],"type":"Point"}
}