{
  "type": "Feature",
  "properties": {
    "addr:full":"9330 Monaco St Henderson CO 80640",
    "addr:housenumber":"9330",
    "addr:postcode":"80640",
    "addr:street":"Monaco St",
    "iso:country":"US",
    "sg:address":"9330 Monaco St",
    "sg:city":"Henderson",
    "sg:classifiers":[
        {
            "category":"Building & Trades",
            "subcategory":"Construction",
            "type":"Services"
        }
    ],
    "sg:phone":"+1 303 227 9009",
    "sg:postcode":"80640",
    "sg:province":"CO",
    "sg:tags":[
        "hanging",
        "contractor"
    ],
    "wof:name":"INX Painting",
    "wof:placetype":"venue"
},
  "geometry": {"coordinates":[-104.91242699999999,39.864204],"type":"Point"}
}