{
  "type": "Feature",
  "properties": {
    "addr:full":"4320 W Colfax Ave Denver CO 80204",
    "addr:housenumber":"4320",
    "addr:postcode":"80204",
    "addr:street":"W Colfax Ave",
    "iso:country":"US",
    "sg:address":"4320 W Colfax Ave",
    "sg:city":"Denver",
    "sg:classifiers":[
        {
            "category":"Banks & Credit Unions",
            "subcategory":"Bank",
            "type":"Services"
        }
    ],
    "sg:phone":"+1 303 893 8888",
    "sg:postcode":"80204",
    "sg:province":"CO",
    "sg:tags":[
        "cashing",
        "loan",
        "check"
    ],
    "sg:website":"http://www.pcloansco.com",
    "wof:name":"Emergency Cash",
    "wof:placetype":"venue"
},
  "geometry": {"coordinates":[-105.04308399999999,39.740349],"type":"Point"}
}