{
  "type": "Feature",
  "properties": {
    "addr:full":"4380 S Syracuse St Denver CO 80237",
    "addr:housenumber":"4380",
    "addr:postcode":"80237",
    "addr:street":"S Syracuse St",
    "iso:country":"US",
    "sg:address":"4380 S Syracuse St",
    "sg:city":"Denver",
    "sg:classifiers":[
        {
            "category":"Manufacturing",
            "subcategory":"Printing",
            "type":"Manufacturing & Wholesale Goods"
        }
    ],
    "sg:phone":"+1 303 694 2920",
    "sg:postcode":"80237",
    "sg:province":"CO",
    "sg:tags":[
        "printer"
    ],
    "wof:name":"Sir Speedy Printing Ctr",
    "wof:placetype":"venue"
},
  "geometry": {"coordinates":[-104.89922300000001,39.636915],"type":"Point"}
}