{
  "type": "Feature",
  "properties": {
    "iso:country":"US",
    "sg:address":"9145 E Kenyon Ave",
    "sg:city":"Denver",
    "sg:classifiers":[
        {
            "category":"Building & Trades",
            "subcategory":"Construction",
            "type":"Services"
        }
    ],
    "sg:phone":"+1 303 220 0040",
    "sg:postcode":"80237",
    "sg:province":"CO",
    "sg:tags":[
        "house",
        "family",
        "general"
    ],
    "wof:name":"Alpert CM Inc",
    "wof:placetype":"venue"
},
  "geometry": {"coordinates":[-104.88133000000001,39.649682],"type":"Point"}
}