{
  "type": "Feature",
  "properties": {
    "iso:country":"US",
    "sg:address":"851 E Hwy 224",
    "sg:city":"Denver",
    "sg:classifiers":[
        {
            "category":"Retail",
            "subcategory":"Auto Repair",
            "type":"Services"
        }
    ],
    "sg:phone":"+1 303 286 7201",
    "sg:postcode":"80229",
    "sg:province":"CO",
    "sg:tags":[
        "transmission"
    ],
    "wof:name":"Tramsmission Repair",
    "wof:placetype":"venue"
},
  "geometry": {"coordinates":[-104.97122400000001,39.82529],"type":"Point"}
}