{
  "type": "Feature",
  "properties": {
    "iso:country":"US",
    "sg:address":"501 W 1st St",
    "sg:city":"Glenwood Springs",
    "sg:classifiers":[
        {
            "category":"Travel",
            "subcategory":"Hotels & Motels",
            "type":"Entertainment"
        }
    ],
    "sg:phone":"+1 970 928 7800",
    "sg:postcode":"81601",
    "sg:province":"CO",
    "wof:name":"Holiday Inn Express Glenwd Spg",
    "wof:placetype":"venue"
},
  "geometry": {"coordinates":[-107.330107,39.552967],"type":"Point"}
}