{
  "type": "Feature",
  "properties": {
    "addr:full":"2966 W Long Dr Littleton CO 80120",
    "addr:housenumber":"2966",
    "addr:postcode":"80120",
    "addr:street":"W Long Dr",
    "iso:country":"US",
    "sg:address":"2966 W Long Dr",
    "sg:city":"Littleton",
    "sg:classifiers":[
        {
            "category":"Professional",
            "type":"Services"
        }
    ],
    "sg:phone":"+1 303 794 0024",
    "sg:postcode":"80120",
    "sg:province":"CO",
    "wof:name":"Bower Inc",
    "wof:placetype":"venue"
},
  "geometry": {"coordinates":[-105.023336,39.577277],"type":"Point"}
}