{
  "type": "Feature",
  "properties": {
    "addr:full":"951 20th St Ste 44432 Denver CO 80202",
    "addr:housenumber":"951",
    "addr:postcode":"44432;80202",
    "addr:street":"20Th St Ste",
    "iso:country":"US",
    "sg:address":"951 20th St Ste 44432",
    "sg:city":"Denver",
    "sg:classifiers":[
        {
            "category":"Autos & Motor Vehicles",
            "subcategory":"Automobile Sales",
            "type":"Retail Goods"
        },
        {
            "category":"Airline",
            "type":"Transportation"
        }
    ],
    "sg:phone":"+1 303 470 3867",
    "sg:postcode":"80202",
    "sg:province":"CO",
    "sg:tags":[
        "shuttle",
        "airport",
        "limo"
    ],
    "sg:website":"www.denvercrownlimo.com",
    "wof:name":"Crown Denver limo",
    "wof:placetype":"venue"
},
  "geometry": {"coordinates":[-104.989535,39.75062],"type":"Point"}
}