{
  "type": "Feature",
  "properties": {
    "iso:country":"US",
    "sg:address":"1189 Graves Ave",
    "sg:city":"Estes Park",
    "sg:classifiers":[
        {
            "category":"Real Estate",
            "subcategory":"Real Estate Agent",
            "type":"Services"
        }
    ],
    "sg:phone":"+1 970 586 6322",
    "sg:postcode":"80517",
    "sg:province":"CO",
    "wof:name":"Jane B Cornell",
    "wof:placetype":"venue"
},
  "geometry": {"coordinates":[-105.503286,40.369156],"type":"Point"}
}