{
  "type": "Feature",
  "properties": {
    "iso:country":"US",
    "sg:address":"1050 17th St",
    "sg:city":"Denver",
    "sg:classifiers":[
        {
            "category":"Banks & Credit Unions",
            "subcategory":"Investment Brokerage",
            "type":"Services"
        }
    ],
    "sg:phone":"+1 303 571 0419",
    "sg:postcode":"80202",
    "sg:province":"CO",
    "sg:tags":[
        "security"
    ],
    "wof:name":"J P Morgan Invest LLC",
    "wof:placetype":"venue"
},
  "geometry": {"coordinates":[-104.994139,39.748402],"type":"Point"}
}