{
  "type": "Feature",
  "properties": {
    "iso:country":"US",
    "sg:address":"8611 W Star Cir",
    "sg:city":"Littleton",
    "sg:classifiers":[
        {
            "category":"Building & Trades",
            "subcategory":"Landscaping Services",
            "type":"Services"
        }
    ],
    "sg:phone":"+1 303 994 9725",
    "sg:postcode":"80128",
    "sg:province":"CO",
    "sg:tags":[
        "synthetic",
        "turf",
        "distributor",
        "designer"
    ],
    "wof:name":"Faux Grow",
    "wof:placetype":"venue"
},
  "geometry": {"coordinates":[-105.095404,39.560607],"type":"Point"}
}