{
  "type": "Feature",
  "properties": {
    "iso:country":"US",
    "sg:address":"110 Rd C",
    "sg:city":"Winter Park",
    "sg:classifiers":[
        {
            "category":"Building & Trades",
            "subcategory":"Construction",
            "type":"Services"
        }
    ],
    "sg:phone":"+1 970 726 4482",
    "sg:postcode":"80470",
    "sg:province":"CO",
    "sg:tags":[
        "general",
        "contractor"
    ],
    "wof:name":"Jimmy Leonard",
    "wof:placetype":"venue"
},
  "geometry": {"coordinates":[-105.441266,39.509428],"type":"Point"}
}