{
  "type": "Feature",
  "properties": {
    "iso:country":"US",
    "sg:address":"2495 Uravan St",
    "sg:city":"Aurora",
    "sg:classifiers":[
        {
            "category":"Wholesale",
            "subcategory":"Metals & Minerals",
            "type":"Manufacturing & Wholesale Goods"
        }
    ],
    "sg:phone":"+1 303 371 2200",
    "sg:postcode":"80011",
    "sg:province":"CO",
    "sg:tags":[
        "steel",
        "carbon",
        "product",
        "distributes"
    ],
    "sg:website":"www.brown-strauss.com",
    "wof:name":"Brown-Strauss Steel",
    "wof:placetype":"venue"
},
  "geometry": {"coordinates":[-104.779579,39.75329],"type":"Point"}
}