{
  "type": "Feature",
  "properties": {
    "addr:full":"10866 E Orchard Pl Englewood CO 80111",
    "addr:housenumber":"10866",
    "addr:postcode":"80111",
    "addr:street":"E Orchard Pl",
    "iso:country":"US",
    "sg:address":"10866 E Orchard Pl",
    "sg:city":"Englewood",
    "sg:classifiers":[
        {
            "category":"Banks & Credit Unions",
            "subcategory":"Bank",
            "type":"Services"
        }
    ],
    "sg:phone":"+1 720 529 8382",
    "sg:postcode":"80111",
    "sg:province":"CO",
    "sg:tags":[
        "broker",
        "mortgage"
    ],
    "wof:name":"Mortgage Specialists & Referra",
    "wof:placetype":"venue"
},
  "geometry": {"coordinates":[-104.86264799999999,39.608583],"type":"Point"}
}