{
  "type": "Feature",
  "properties": {
    "iso:country":"US",
    "sg:address":"19000 E Chaffee Pl",
    "sg:city":"Denver",
    "sg:classifiers":[
        {
            "category":"Wholesale",
            "subcategory":"Vending Machines",
            "type":"Manufacturing & Wholesale Goods"
        }
    ],
    "sg:phone":"+1 303 601 6475",
    "sg:postcode":"80249",
    "sg:province":"CO",
    "sg:tags":[
        "operator"
    ],
    "wof:name":"Greens Vending",
    "wof:placetype":"venue"
},
  "geometry": {"coordinates":[-104.765123,39.7786],"type":"Point"}
}