{
  "type": "Feature",
  "properties": {
    "addr:full":"6923 S Buffalo St Littleton CO 80120",
    "addr:housenumber":"6923",
    "addr:postcode":"80120",
    "addr:street":"S Buffalo St",
    "iso:country":"US",
    "sg:address":"6923 S Buffalo St",
    "sg:city":"Littleton",
    "sg:classifiers":[
        {
            "category":"Building & Trades",
            "subcategory":"Construction",
            "type":"Services"
        }
    ],
    "sg:phone":"+1 303 703 4952",
    "sg:postcode":"80120",
    "sg:province":"CO",
    "sg:tags":[
        "contractor"
    ],
    "wof:name":"Super Natural Wood Care",
    "wof:placetype":"venue"
},
  "geometry": {"coordinates":[-104.994677,39.592331],"type":"Point"}
}