{
  "type": "Feature",
  "properties": {
    "addr:full":"3753 Norwood Dr Littleton CO 80125",
    "addr:housenumber":"3753",
    "addr:postcode":"80125",
    "addr:street":"Norwood Dr",
    "iso:country":"US",
    "sg:address":"3753 Norwood Dr",
    "sg:city":"Littleton",
    "sg:classifiers":[
        {
            "category":"Retail",
            "subcategory":"Auto Repair",
            "type":"Services"
        }
    ],
    "sg:phone":"+1 303 470 0286",
    "sg:postcode":"80125",
    "sg:province":"CO",
    "sg:tags":[
        "part",
        "tires-wholesale",
        "manufacturer"
    ],
    "sg:website":"http://www.coopertire.com/html/",
    "wof:name":"All American 4 X 4",
    "wof:placetype":"venue"
},
  "geometry": {"coordinates":[-105.03777599999999,39.555378],"type":"Point"}
}