{
  "type": "Feature",
  "properties": {
    "addr:full":"1860 N Ridge Ln Estes Park CO 80517",
    "addr:housenumber":"1860",
    "addr:postcode":"80517",
    "addr:street":"N Ridge Ln",
    "iso:country":"US",
    "sg:address":"1860 N Ridge Ln",
    "sg:city":"Estes Park",
    "sg:classifiers":[
        {
            "category":"Social Services",
            "type":"Services"
        }
    ],
    "sg:phone":"+1 970 586 0710",
    "sg:postcode":"80517",
    "sg:province":"CO",
    "sg:tags":[
        "counselor",
        "marriage",
        "family"
    ],
    "wof:name":"Ronald P Dutton",
    "wof:placetype":"venue"
},
  "geometry": {"coordinates":[-105.490484,40.386327],"type":"Point"}
}