{
  "type": "Feature",
  "properties": {
    "addr:full":"2725 W 10th St Greeley CO 80634",
    "addr:housenumber":"2725",
    "addr:postcode":"80634",
    "addr:street":"W 10Th St",
    "iso:country":"US",
    "sg:address":"2725 W 10th St",
    "sg:city":"Greeley",
    "sg:classifiers":[
        {
            "category":"Restaurant",
            "type":"Food & Drink"
        }
    ],
    "sg:phone":"+1 970 356 8400",
    "sg:postcode":"80634",
    "sg:province":"CO",
    "sg:tags":[
        "greek"
    ],
    "wof:name":"Paragon Family Restaurant",
    "wof:placetype":"venue"
},
  "geometry": {"coordinates":[-104.725176,40.422961],"type":"Point"}
}