{
  "type": "Feature",
  "properties": {
    "addr:full":"2180 S Leyden St Denver CO 80222",
    "addr:housenumber":"2180",
    "addr:postcode":"80222",
    "addr:street":"S Leyden St",
    "iso:country":"US",
    "sg:address":"2180 S Leyden St",
    "sg:city":"Denver",
    "sg:classifiers":[
        {
            "category":"Health Services",
            "subcategory":"Doctor",
            "type":"Services"
        }
    ],
    "sg:phone":"+1 303 512 0888",
    "sg:postcode":"80222",
    "sg:province":"CO",
    "sg:tags":[
        "medical",
        "lab"
    ],
    "wof:name":"Unipath",
    "wof:placetype":"venue"
},
  "geometry": {"coordinates":[-104.915886,39.677099],"type":"Point"}
}