{
  "type": "Feature",
  "properties": {
    "addr:full":"3733 Cherry Creek North Dr Denver CO 80209",
    "addr:housenumber":"3733",
    "addr:postcode":"80209",
    "addr:street":"Cherry Creek North Dr",
    "iso:country":"US",
    "sg:address":"3733 Cherry Creek North Dr",
    "sg:city":"Denver",
    "sg:classifiers":[
        {
            "category":"Education",
            "subcategory":"College",
            "type":"Public Place"
        }
    ],
    "sg:phone":"+1 303 331 6430",
    "sg:postcode":"80209",
    "sg:province":"CO",
    "sg:tags":[
        "academic",
        "school"
    ],
    "wof:name":"University Of Chicago Press",
    "wof:placetype":"venue"
},
  "geometry": {"coordinates":[-104.942099,39.707544],"type":"Point"}
}