{
  "type": "Feature",
  "properties": {
    "iso:country":"US",
    "sg:address":"7575 E Arkansas Ave",
    "sg:city":"Denver",
    "sg:classifiers":[
        {
            "category":"Real Estate",
            "subcategory":"Real Estate Operator",
            "type":"Services"
        }
    ],
    "sg:phone":"+1 303 696 1060",
    "sg:postcode":"80231",
    "sg:province":"CO",
    "sg:tags":[
        "building",
        "apartment"
    ],
    "wof:name":"Torrey Pines",
    "wof:placetype":"venue"
},
  "geometry": {"coordinates":[-104.90122,39.691628],"type":"Point"}
}