{
  "type": "Feature",
  "properties": {
    "iso:country":"US",
    "sg:address":"19627 E Fair Dr",
    "sg:city":"Aurora",
    "sg:classifiers":[
        {
            "category":"Wholesale",
            "subcategory":"Jewelry",
            "type":"Manufacturing & Wholesale Goods"
        }
    ],
    "sg:phone":"+1 303 693 7767",
    "sg:postcode":"80016",
    "sg:province":"CO",
    "sg:tags":[
        "stone"
    ],
    "wof:name":"Trinity Precious Metals",
    "wof:placetype":"venue"
},
  "geometry": {"coordinates":[-104.75791700000001,39.60481],"type":"Point"}
}