{
  "type": "Feature",
  "properties": {
    "addr:full":"312 Aabc Aspen CO 81611",
    "addr:housenumber":"312",
    "addr:postcode":"81611",
    "addr:street":"Aabc Aspen",
    "iso:country":"US",
    "sg:address":"312 Aabc",
    "sg:city":"Aspen",
    "sg:classifiers":[
        {
            "category":"Shopping",
            "subcategory":"Computers & Home Electronics",
            "type":"Retail Goods"
        }
    ],
    "sg:phone":"+1 970 925 5515",
    "sg:postcode":"81611",
    "sg:province":"CO",
    "sg:tags":[
        "audio"
    ],
    "wof:name":"Artistic Sound Inc",
    "wof:placetype":"venue"
},
  "geometry": {"coordinates":[-106.86111,39.218229],"type":"Point"}
}