{
  "type": "Feature",
  "properties": {
    "iso:country":"US",
    "sg:address":"3834 Tennyson Street",
    "sg:city":"Denver",
    "sg:classifiers":[
        {
            "category":"Bars & Pubs",
            "subcategory":"Dive Bar",
            "type":"Food & Drink"
        }
    ],
    "sg:phone":"+1 877 471 2794",
    "sg:postcode":"80212",
    "sg:province":"CO",
    "wof:name":"Berkeley Inn",
    "wof:placetype":"venue"
},
  "geometry": {"coordinates":[-105.043705,39.770123],"type":"Point"}
}