{
  "type": "Feature",
  "properties": {
    "iso:country":"US",
    "sg:address":"3150 Slocum Rd",
    "sg:city":"Peyton",
    "sg:classifiers":[
        {
            "category":"Building & Trades",
            "subcategory":"Construction",
            "type":"Services"
        }
    ],
    "sg:phone":"+1 719 683 2749",
    "sg:postcode":"80831",
    "sg:province":"CO",
    "sg:tags":[
        "contractor"
    ],
    "wof:name":"Falcon Glass",
    "wof:placetype":"venue"
},
  "geometry": {"coordinates":[-104.5168,38.881918],"type":"Point"}
}