{
  "type": "Feature",
  "properties": {
    "iso:country":"US",
    "sg:address":"12252 W Chenango Dr",
    "sg:city":"Morrison",
    "sg:classifiers":[
        {
            "category":"Food & Beverages",
            "subcategory":"Specialty",
            "type":"Retail Goods"
        }
    ],
    "sg:phone":"+1 303 979 8094",
    "sg:postcode":"80465",
    "sg:province":"CO",
    "wof:name":"Shaklee Products",
    "wof:placetype":"venue"
},
  "geometry": {"coordinates":[-105.13628,39.626463],"type":"Point"}
}