{
  "type": "Feature",
  "properties": {
    "addr:full":"13994 Turnberry Ct Broomfield CO 80023",
    "addr:housenumber":"13994",
    "addr:postcode":"80023",
    "addr:street":"Turnberry Ct",
    "iso:country":"US",
    "sg:address":"13994 Turnberry Ct",
    "sg:city":"Broomfield",
    "sg:classifiers":[
        {
            "category":"Real Estate",
            "subcategory":"Architect",
            "type":"Services"
        }
    ],
    "sg:phone":"+1 303 465 2983",
    "sg:postcode":"80023",
    "sg:province":"CO",
    "wof:name":"Ennis Associates",
    "wof:placetype":"venue"
},
  "geometry": {"coordinates":[-105.039384,39.950575],"type":"Point"}
}