{
  "type": "Feature",
  "properties": {
    "addr:full":"3010 N Nevada Ave Colorado Springs CO 80907",
    "addr:housenumber":"3010",
    "addr:postcode":"80907",
    "addr:street":"N Nevada Ave",
    "iso:country":"US",
    "sg:address":"3010 N Nevada Ave",
    "sg:city":"Colorado Springs",
    "sg:classifiers":[
        {
            "category":"Cinema",
            "subcategory":"Movie Rental",
            "type":"Entertainment"
        }
    ],
    "sg:phone":"+1 719 473 2223",
    "sg:postcode":"80907",
    "sg:province":"CO",
    "sg:tags":[
        "leasing",
        "video",
        "disc",
        "tape"
    ],
    "wof:name":"Blockbuster Video",
    "wof:placetype":"venue"
},
  "geometry": {"coordinates":[-104.81945,38.875072],"type":"Point"}
}