{
  "type": "Feature",
  "properties": {
    "addr:full":"7005 N Carefree Cir Colorado Springs CO 80922",
    "addr:housenumber":"7005",
    "addr:postcode":"80922",
    "addr:street":"N Carefree Cir",
    "iso:country":"US",
    "sg:address":"7005 N Carefree Cir",
    "sg:city":"Colorado Springs",
    "sg:classifiers":[
        {
            "category":"Education",
            "subcategory":"School",
            "type":"Public Place"
        }
    ],
    "sg:phone":"+1 719 572 0924",
    "sg:postcode":"80922",
    "sg:province":"CO",
    "sg:website":"www.d49.org",
    "wof:name":"Sand Creek High School",
    "wof:placetype":"venue"
},
  "geometry": {"coordinates":[-104.701494,38.886713],"type":"Point"}
}