{
  "type": "Feature",
  "properties": {
    "addr:full":"2441 Bella Pago Dr Grand Junction CO 81503",
    "addr:housenumber":"2441",
    "addr:postcode":"81503",
    "addr:street":"Bella Pago Dr",
    "iso:country":"US",
    "sg:address":"2441 Bella Pago Dr",
    "sg:city":"Grand Junction",
    "sg:classifiers":[
        {
            "category":"Building & Trades",
            "subcategory":"Construction",
            "type":"Services"
        }
    ],
    "sg:phone":"+1 970 243 1985",
    "sg:postcode":"81503",
    "sg:province":"CO",
    "sg:tags":[
        "house",
        "builder",
        "home"
    ],
    "wof:name":"Austin Augusta Design & Cnstr",
    "wof:placetype":"venue"
},
  "geometry": {"coordinates":[-108.602268,39.05778],"type":"Point"}
}