{
  "type": "Feature",
  "properties": {
    "addr:full":"5316 W 24th St Greeley CO 80634",
    "addr:housenumber":"5316",
    "addr:postcode":"80634",
    "addr:street":"W 24Th St",
    "iso:country":"US",
    "sg:address":"5316 W 24th St",
    "sg:city":"Greeley",
    "sg:classifiers":[
        {
            "category":"Professional",
            "type":"Services"
        }
    ],
    "sg:phone":"+1 970 339 3475",
    "sg:postcode":"80634",
    "sg:province":"CO",
    "sg:tags":[
        "geophysical"
    ],
    "wof:name":"Marshall Geophysical",
    "wof:placetype":"venue"
},
  "geometry": {"coordinates":[-104.766897,40.399921],"type":"Point"}
}