{
  "type": "Feature",
  "properties": {
    "iso:country":"US",
    "sg:address":"1050 S Pierce St",
    "sg:city":"Denver",
    "sg:classifiers":[
        {
            "category":"Shopping",
            "subcategory":"Jewelry",
            "type":"Retail Goods"
        },
        {
            "category":"Wholesale",
            "subcategory":"Jewelry",
            "type":"Manufacturing & Wholesale Goods"
        }
    ],
    "sg:phone":"+1 303 935 9879",
    "sg:postcode":"80226",
    "sg:province":"CO",
    "sg:tags":[
        "stone",
        "jeweler"
    ],
    "wof:name":"Rexford's",
    "wof:placetype":"venue"
},
  "geometry": {"coordinates":[-105.072073,39.697495],"type":"Point"}
}