{
  "type": "Feature",
  "properties": {
    "iso:country":"US",
    "sg:address":"216 Pennsylvania Ave",
    "sg:city":"Woodland Park",
    "sg:classifiers":[
        {
            "category":"Manufacturing",
            "subcategory":"Wood Products",
            "type":"Manufacturing & Wholesale Goods"
        }
    ],
    "sg:phone":"+1 719 686 9883",
    "sg:postcode":"80863",
    "sg:province":"CO",
    "sg:tags":[
        "mfg"
    ],
    "wof:name":"Foxy Woodz",
    "wof:placetype":"venue"
},
  "geometry": {"coordinates":[-105.08725200000001,38.963673],"type":"Point"}
}