{
  "type": "Feature",
  "properties": {
    "iso:country":"US",
    "sg:address":"882 Laurel Ave",
    "sg:city":"Boulder",
    "sg:classifiers":[
        {
            "category":"Building & Trades",
            "subcategory":"Construction",
            "type":"Services"
        }
    ],
    "sg:phone":"+1 303 494 4447",
    "sg:postcode":"80303",
    "sg:province":"CO",
    "sg:tags":[
        "house"
    ],
    "wof:name":"BF Improvements Inc",
    "wof:placetype":"venue"
},
  "geometry": {"coordinates":[-105.227091,40.001209],"type":"Point"}
}