{
  "type": "Feature",
  "properties": {
    "iso:country":"US",
    "sg:address":"1699 S Colorado Blvd",
    "sg:city":"Denver",
    "sg:classifiers":[
        {
            "category":"Government",
            "subcategory":"Office",
            "type":"Public Place"
        }
    ],
    "sg:phone":"+1 720 904 2174",
    "sg:postcode":"80222",
    "sg:province":"CO",
    "sg:tags":[
        "armed",
        "force",
        "recruiting"
    ],
    "wof:name":"US Army Recruiting",
    "wof:placetype":"venue"
},
  "geometry": {"coordinates":[-104.940651,39.687492],"type":"Point"}
}