{
  "type": "Feature",
  "properties": {
    "addr:full":"5096 S Crystal Ct Aurora CO 80015",
    "addr:housenumber":"5096",
    "addr:postcode":"80015",
    "addr:street":"S Crystal Ct",
    "iso:country":"US",
    "sg:address":"5096 S Crystal Ct",
    "sg:city":"Aurora",
    "sg:classifiers":[
        {
            "category":"Shopping",
            "subcategory":"Stationery & Office Supplies",
            "type":"Retail Goods"
        }
    ],
    "sg:phone":"+1 720 886 9600",
    "sg:postcode":"80015",
    "sg:province":"CO",
    "sg:tags":[
        "rubber",
        "stamp",
        "plastic"
    ],
    "wof:name":"Aurora Artistic Imprints LTD",
    "wof:placetype":"venue"
},
  "geometry": {"coordinates":[-104.820859,39.62504],"type":"Point"}
}