{
  "type": "Feature",
  "properties": {
    "iso:country":"US",
    "sg:address":"37723 US Hwy 24",
    "sg:city":"Avon",
    "sg:classifiers":[
        {
            "category":"Real Estate",
            "subcategory":"Real Estate Operator",
            "type":"Services"
        }
    ],
    "sg:phone":"+1 970 949 1119",
    "sg:postcode":"81620",
    "sg:province":"CO",
    "sg:tags":[
        "apartment"
    ],
    "wof:name":"River Edge Apartments",
    "wof:placetype":"venue"
},
  "geometry": {"coordinates":[-106.523135,39.631209],"type":"Point"}
}