{
  "type": "Feature",
  "properties": {
    "iso:country":"US",
    "sg:address":"651 Chambers Rd",
    "sg:city":"Aurora",
    "sg:classifiers":[
        {
            "category":"Social Services",
            "type":"Services"
        }
    ],
    "sg:phone":"+1 303 340 0598",
    "sg:postcode":"80011",
    "sg:province":"CO",
    "sg:tags":[
        "counselor",
        "marriage",
        "family"
    ],
    "wof:name":"Life Skills Intl",
    "wof:placetype":"venue"
},
  "geometry": {"coordinates":[-104.810166,39.727599],"type":"Point"}
}