{
  "type": "Feature",
  "properties": {
    "iso:country":"US",
    "sg:address":"34333 Co Rd 37",
    "sg:city":"Eaton",
    "sg:phone":"+1 970 454 3153",
    "sg:postcode":"80615",
    "sg:province":"CO",
    "sg:tags":[
        "farm",
        "grain",
        "cash"
    ],
    "wof:name":"Fagerberg Produce",
    "wof:placetype":"venue"
},
  "geometry": {"coordinates":[-104.71593300000001,40.505284],"type":"Point"}
}