{
  "type": "Feature",
  "properties": {
    "addr:full":"12650 W 64th Ave Arvada CO 80004",
    "addr:housenumber":"12650",
    "addr:postcode":"80004",
    "addr:street":"W 64Th Ave",
    "iso:country":"US",
    "sg:address":"12650 W 64th Ave",
    "sg:city":"Arvada",
    "sg:classifiers":[
        {
            "category":"Freight",
            "type":"Transportation"
        }
    ],
    "sg:phone":"+1 303 940 8775",
    "sg:postcode":"80004",
    "sg:province":"CO",
    "sg:tags":[
        "a",
        "center",
        "business",
        "operates",
        "as",
        "retail",
        "mailing"
    ],
    "wof:name":"UPS Stores The",
    "wof:placetype":"venue"
},
  "geometry": {"coordinates":[-105.138873,39.812561],"type":"Point"}
}