{
  "type": "Feature",
  "properties": {
    "addr:full":"232 Broadway St Eagle CO 81631",
    "addr:housenumber":"232",
    "addr:postcode":"81631",
    "addr:street":"Broadway St",
    "iso:country":"US",
    "sg:address":"232 Broadway St",
    "sg:city":"Eagle",
    "sg:classifiers":[
        {
            "category":"Health Services",
            "subcategory":"Doctor",
            "type":"Services"
        }
    ],
    "sg:phone":"+1 970 328 1650",
    "sg:postcode":"81631",
    "sg:province":"CO",
    "sg:tags":[
        "clinic"
    ],
    "sg:website":"www.vvmc.com",
    "wof:name":"Medical Center Of Eagle",
    "wof:placetype":"venue"
},
  "geometry": {"coordinates":[-106.827775,39.654907],"type":"Point"}
}