{
  "type": "Feature",
  "properties": {
    "addr:full":"3001 Grand Ave Glenwood Springs CO 81601",
    "addr:housenumber":"3001",
    "addr:postcode":"81601",
    "addr:street":"Grand Ave",
    "iso:country":"US",
    "sg:address":"3001 Grand Ave",
    "sg:city":"Glenwood Springs",
    "sg:classifiers":[
        {
            "category":"Autos & Motor Vehicles",
            "subcategory":"Motorcycle Sales",
            "type":"Retail Goods"
        }
    ],
    "sg:phone":"+1 970 945 6301",
    "sg:postcode":"81601",
    "sg:province":"CO",
    "sg:tags":[
        "scooter"
    ],
    "sg:website":"www.sportlandcolorado.com",
    "wof:name":"Sportland",
    "wof:placetype":"venue"
},
  "geometry": {"coordinates":[-107.324181,39.521382],"type":"Point"}
}