{
  "type": "Feature",
  "properties": {
    "addr:full":"2634 W 9th Ave Denver CO 80204",
    "addr:housenumber":"2634",
    "addr:postcode":"80204",
    "addr:street":"W 9Th Ave",
    "iso:country":"US",
    "sg:address":"2634 W 9th Ave",
    "sg:city":"Denver",
    "sg:classifiers":[
        {
            "category":"Utilities",
            "subcategory":"Cable",
            "type":"Services"
        }
    ],
    "sg:phone":"+1 303 629 0999",
    "sg:postcode":"80204",
    "sg:province":"CO",
    "sg:tags":[
        "satellite",
        "carrier"
    ],
    "sg:website":"www.wavelengthsatellite.com",
    "wof:name":"Wavelength Commercial",
    "wof:placetype":"venue"
},
  "geometry": {"coordinates":[-105.02141,39.731125],"type":"Point"}
}