{
  "type": "Feature",
  "properties": {
    "addr:full":"2221 Hagerman St Colorado Springs CO 80904",
    "addr:postcode":"2221;80904",
    "addr:street":"Hagerman St",
    "iso:country":"US",
    "sg:address":"2221 Hagerman St",
    "sg:city":"Colorado Springs",
    "sg:classifiers":[
        {
            "category":"Recreation",
            "type":"Entertainment"
        }
    ],
    "sg:phone":"+1 719 634 5207",
    "sg:postcode":"80904",
    "sg:province":"CO",
    "sg:tags":[
        "guide"
    ],
    "wof:name":"Glens Cove Inc",
    "wof:placetype":"venue"
},
  "geometry": {"coordinates":[-104.86427999999999,38.840089],"type":"Point"}
}