{
  "type": "Feature",
  "properties": {
    "iso:country":"US",
    "sg:address":"8744 W Union Ave",
    "sg:city":"Denver",
    "sg:classifiers":[
        {
            "category":"Professional",
            "subcategory":"Engineering",
            "type":"Services"
        },
        {
            "category":"Restaurant",
            "type":"Food & Drink"
        }
    ],
    "sg:phone":"+1 303 972 1960",
    "sg:postcode":"80123",
    "sg:province":"CO",
    "sg:tags":[
        "eating",
        "engineer"
    ],
    "wof:name":"Sub Terra Inc",
    "wof:placetype":"venue"
},
  "geometry": {"coordinates":[-105.095792,39.631758],"type":"Point"}
}