{
  "type": "Feature",
  "properties": {
    "addr:full":"1220 Ravenwood Rd Boulder CO 80303",
    "addr:housenumber":"1220",
    "addr:postcode":"80303",
    "addr:street":"Ravenwood Rd",
    "iso:country":"US",
    "sg:address":"1220 Ravenwood Rd",
    "sg:city":"Boulder",
    "sg:classifiers":[
        {
            "category":"Health Services",
            "subcategory":"Medical Lab",
            "type":"Services"
        }
    ],
    "sg:phone":"+1 303 499 1473",
    "sg:postcode":"80303",
    "sg:province":"CO",
    "sg:tags":[
        "detection",
        "equipment",
        "drug"
    ],
    "sg:website":"www.precisioncompliance.com",
    "wof:name":"Precision Compliance Inc",
    "wof:placetype":"venue"
},
  "geometry": {"coordinates":[-105.198277,40.009777],"type":"Point"}
}