{
  "type": "Feature",
  "properties": {
    "iso:country":"US",
    "sg:address":"221 E Main St",
    "sg:city":"Aspen",
    "sg:classifiers":[
        {
            "category":"Shopping",
            "subcategory":"Books",
            "type":"Retail Goods"
        }
    ],
    "sg:phone":"+1 970 925 5336",
    "sg:postcode":"81611",
    "sg:province":"CO",
    "sg:tags":[
        "dealer"
    ],
    "sg:website":"www.explorebooksellers.com",
    "wof:name":"Explore Booksellers",
    "wof:placetype":"venue"
},
  "geometry": {"coordinates":[-106.82136199999999,39.191037],"type":"Point"}
}