{
  "type": "Feature",
  "properties": {
    "iso:country":"US",
    "sg:address":"8555 W Belleview Ave",
    "sg:city":"Littleton",
    "sg:classifiers":[
        {
            "category":"Restaurant",
            "type":"Food & Drink"
        }
    ],
    "sg:menulink":"http://www.allmenus.com/co/denver/81071-papa-johns-pizza/menu/",
    "sg:phone":"+1 303 932 8200",
    "sg:postcode":"80123",
    "sg:province":"CO",
    "sg:tags":[
        "american",
        "pizza"
    ],
    "wof:name":"Papa John's Pizza",
    "wof:placetype":"venue"
},
  "geometry": {"coordinates":[-105.092372,39.62574],"type":"Point"}
}