{
  "type": "Feature",
  "properties": {
    "iso:country":"US",
    "sg:address":"11624 del Mar Pkwy",
    "sg:city":"Aurora",
    "sg:classifiers":[
        {
            "category":"Manufacturing",
            "subcategory":"Metals",
            "type":"Manufacturing & Wholesale Goods"
        },
        {
            "category":"Wholesale",
            "subcategory":"Vending Machines",
            "type":"Manufacturing & Wholesale Goods"
        }
    ],
    "sg:phone":"+1 303 537 5985",
    "sg:postcode":"80010",
    "sg:province":"CO",
    "sg:tags":[
        "precision",
        "grinding"
    ],
    "wof:name":"Robert Shouse Stump Grinding",
    "wof:placetype":"venue"
},
  "geometry": {"coordinates":[-104.854911,39.727288],"type":"Point"}
}