{
  "type": "Feature",
  "properties": {
    "addr:full":"801 S Public Rd Lafayette CO 80026",
    "addr:housenumber":"801",
    "addr:postcode":"80026",
    "addr:street":"S Public Rd",
    "iso:country":"US",
    "sg:address":"801 S Public Rd",
    "sg:city":"Lafayette",
    "sg:classifiers":[
        {
            "category":"Health Services",
            "subcategory":"Optometrist",
            "type":"Services"
        }
    ],
    "sg:phone":"+1 303 665 3200",
    "sg:postcode":"80026",
    "sg:province":"CO",
    "wof:name":"Cleve E Armstrong OD",
    "wof:placetype":"venue"
},
  "geometry": {"coordinates":[-105.09056099999999,39.992119],"type":"Point"}
}