{
  "type": "Feature",
  "properties": {
    "iso:country":"US",
    "sg:address":"2730 S Jay St",
    "sg:city":"Denver",
    "sg:classifiers":[
        {
            "category":"Food & Beverages",
            "subcategory":"Candy",
            "type":"Retail Goods"
        }
    ],
    "sg:phone":"+1 303 780 0696",
    "sg:postcode":"80227",
    "sg:province":"CO",
    "sg:tags":[
        "popcorn"
    ],
    "wof:name":"Tubbys Carmel Corn",
    "wof:placetype":"venue"
},
  "geometry": {"coordinates":[-105.06396599999999,39.665629],"type":"Point"}
}