{
  "type": "Feature",
  "properties": {
    "iso:country":"US",
    "sg:address":"1662 Cherry St",
    "sg:city":"Denver",
    "sg:classifiers":[
        {
            "category":"Shopping",
            "subcategory":"Clothing, Apparel, & Fashions",
            "type":"Retail Goods"
        }
    ],
    "sg:phone":"+1 303 355 2040",
    "sg:postcode":"80220",
    "sg:province":"CO",
    "wof:name":"Tailor Group",
    "wof:placetype":"venue"
},
  "geometry": {"coordinates":[-104.933717,39.743313],"type":"Point"}
}