{
  "type": "Feature",
  "properties": {
    "iso:country":"US",
    "sg:address":"1421 Fox Canyon Lane",
    "sg:city":"Castle Rock",
    "sg:classifiers":[
        {
            "category":"Building & Trades",
            "subcategory":"Construction",
            "type":"Services"
        }
    ],
    "sg:phone":"+1 303 688 6031",
    "sg:postcode":"80104",
    "sg:province":"CO",
    "sg:tags":[
        "contractor"
    ],
    "wof:name":"Klein Builders",
    "wof:placetype":"venue"
},
  "geometry": {"coordinates":[-104.847681,39.380318],"type":"Point"}
}