{
  "type": "Feature",
  "properties": {
    "addr:full":"153 Washington St Monument CO 80132",
    "addr:housenumber":"153",
    "addr:postcode":"80132",
    "addr:street":"Washington St",
    "iso:country":"US",
    "sg:address":"153 Washington St",
    "sg:city":"Monument",
    "sg:classifiers":[
        {
            "category":"Social Services",
            "type":"Services"
        }
    ],
    "sg:phone":"+1 719 488 0402",
    "sg:postcode":"80132",
    "sg:province":"CO",
    "sg:tags":[
        "counselor",
        "marriage",
        "family"
    ],
    "wof:name":"Linda Mc Kay",
    "wof:placetype":"venue"
},
  "geometry": {"coordinates":[-104.872658,39.090637],"type":"Point"}
}