{
  "type": "Feature",
  "properties": {
    "iso:country":"US",
    "sg:address":"7852 Whitney Ct",
    "sg:city":"Fort Collins",
    "sg:classifiers":[
        {
            "category":"Food & Beverages",
            "subcategory":"Specialty",
            "type":"Retail Goods"
        }
    ],
    "sg:phone":"+1 970 278 0411",
    "sg:postcode":"80525",
    "sg:province":"CO",
    "sg:tags":[
        "vitamin"
    ],
    "wof:name":"Ron Stern",
    "wof:placetype":"venue"
},
  "geometry": {"coordinates":[-105.071668,40.475616],"type":"Point"}
}