{
  "type": "Feature",
  "properties": {
    "iso:country":"US",
    "sg:address":"2454 Patterson Rd",
    "sg:city":"Grand Junction",
    "sg:classifiers":[
        {
            "category":"Professional",
            "subcategory":"Lawyer & Legal Services",
            "type":"Services"
        }
    ],
    "sg:phone":"+1 970 242 3311",
    "sg:postcode":"81505",
    "sg:province":"CO",
    "sg:tags":[
        "attorney"
    ],
    "wof:name":"Coleman Williams & Wilson",
    "wof:placetype":"venue"
},
  "geometry": {"coordinates":[-108.596563,39.09195],"type":"Point"}
}