{
  "type": "Feature",
  "properties": {
    "iso:country":"US",
    "sg:address":"6850 E 45th St",
    "sg:city":"Loveland",
    "sg:classifiers":[
        {
            "category":"Freight",
            "type":"Transportation"
        }
    ],
    "sg:phone":"+1 970 593 9640",
    "sg:postcode":"80538",
    "sg:province":"CO",
    "sg:tags":[
        "1",
        "carrier",
        "class",
        "motor"
    ],
    "wof:name":"ABF",
    "wof:placetype":"venue"
},
  "geometry": {"coordinates":[-104.974011,40.439212],"type":"Point"}
}