{
  "type": "Feature",
  "properties": {
    "iso:country":"US",
    "sg:address":"665 Briggs St",
    "sg:city":"Erie",
    "sg:classifiers":[
        {
            "category":"Organizations",
            "subcategory":"Religious Organization",
            "type":"Services"
        }
    ],
    "sg:phone":"+1 303 828 3800",
    "sg:postcode":"80516",
    "sg:province":"CO",
    "sg:tags":[
        "church"
    ],
    "wof:name":"Mountain Ridge Community Chr",
    "wof:placetype":"venue"
},
  "geometry": {"coordinates":[-105.047359,40.051092],"type":"Point"}
}