{
  "type": "Feature",
  "properties": {
    "iso:country":"US",
    "sg:address":"5434 E Nichols Pl",
    "sg:city":"Littleton",
    "sg:classifiers":[
        {
            "category":"Real Estate",
            "subcategory":"Real Estate Operator",
            "type":"Services"
        }
    ],
    "sg:phone":"+1 303 740 8630",
    "sg:postcode":"80122",
    "sg:province":"CO",
    "sg:tags":[
        "building",
        "nonresidential"
    ],
    "wof:name":"Tiber Properties LLC",
    "wof:placetype":"venue"
},
  "geometry": {"coordinates":[-104.924725,39.570137],"type":"Point"}
}