{
  "type": "Feature",
  "properties": {
    "iso:country":"US",
    "sg:address":"625 W 4th St",
    "sg:city":"Pueblo",
    "sg:classifiers":[
        {
            "category":"Recreation",
            "type":"Entertainment"
        }
    ],
    "sg:phone":"+1 719 543 5557",
    "sg:postcode":"81004",
    "sg:province":"CO",
    "sg:tags":[
        "bingo",
        "game"
    ],
    "wof:name":"Bingo Casino",
    "wof:placetype":"venue"
},
  "geometry": {"coordinates":[-104.616105,38.270579],"type":"Point"}
}