{
  "type": "Feature",
  "properties": {
    "iso:country":"US",
    "sg:address":"3865 Cherry Creek North D",
    "sg:city":"Denver",
    "sg:classifiers":[
        {
            "category":"Health Services",
            "subcategory":"Doctor",
            "type":"Services"
        }
    ],
    "sg:phone":"+1 303 394 2888",
    "sg:postcode":"80209",
    "sg:province":"CO",
    "wof:name":"Kerstein Howard M D",
    "wof:placetype":"venue"
},
  "geometry": {"coordinates":[-104.942046,39.707436],"type":"Point"}
}