{
  "type": "Feature",
  "properties": {
    "addr:full":"2538 Kittredge Dr Loveland CO 80538",
    "addr:housenumber":"2538",
    "addr:postcode":"80538",
    "addr:street":"Kittredge Dr",
    "iso:country":"US",
    "sg:address":"2538 Kittredge Dr",
    "sg:city":"Loveland",
    "sg:classifiers":[
        {
            "category":"Retail",
            "subcategory":"Animal Services",
            "type":"Services"
        }
    ],
    "sg:phone":"+1 970 667 9286",
    "sg:postcode":"80538",
    "sg:province":"CO",
    "sg:tags":[
        "specialty"
    ],
    "wof:name":"Shear Heaven Pet Grooming",
    "wof:placetype":"venue"
},
  "geometry": {"coordinates":[-105.11366700000001,40.416663],"type":"Point"}
}