{
  "type": "Feature",
  "properties": {
    "iso:country":"US",
    "sg:address":"2150 Centre Ave",
    "sg:city":"Fort Collins",
    "sg:classifiers":[
        {
            "category":"Professional",
            "subcategory":"Research",
            "type":"Services"
        }
    ],
    "sg:phone":"+1 970 295 5908",
    "sg:postcode":"80526",
    "sg:province":"CO",
    "sg:tags":[
        "commercial",
        "physical"
    ],
    "wof:name":"U S D A Agricultural Res Svcs",
    "wof:placetype":"venue"
},
  "geometry": {"coordinates":[-105.088185,40.556986],"type":"Point"}
}