{
  "type": "Feature",
  "properties": {
    "addr:full":"11596 W Colfax Ave Lakewood CO 80215",
    "addr:housenumber":"11596",
    "addr:postcode":"80215",
    "addr:street":"W Colfax Ave",
    "iso:country":"US",
    "sg:address":"11596 W Colfax Ave",
    "sg:city":"Lakewood",
    "sg:classifiers":[
        {
            "category":"Professional",
            "subcategory":"Computer Services",
            "type":"Services"
        }
    ],
    "sg:phone":"+1 303 374 3277",
    "sg:postcode":"80215",
    "sg:province":"CO",
    "sg:tags":[
        "internet"
    ],
    "sg:website":"www.liquidatorsonthenet.com",
    "wof:name":"LIQUIDATORSONTHENET.COM",
    "wof:placetype":"venue"
},
  "geometry": {"coordinates":[-105.127341,39.740092],"type":"Point"}
}