{
  "type": "Feature",
  "properties": {
    "addr:full":"19128 E Oxford Dr Aurora CO 80013",
    "addr:housenumber":"19128",
    "addr:postcode":"80013",
    "addr:street":"E Oxford Dr",
    "iso:country":"US",
    "sg:address":"19128 E Oxford Dr",
    "sg:city":"Aurora",
    "sg:classifiers":[
        {
            "category":"Building & Trades",
            "subcategory":"Construction",
            "type":"Services"
        }
    ],
    "sg:phone":"+1 303 942 0622",
    "sg:postcode":"80013",
    "sg:province":"CO",
    "sg:tags":[
        "installation",
        "flooring",
        "floor",
        "vinyl",
        "tile",
        "carpet"
    ],
    "wof:name":"J B Floormaster",
    "wof:placetype":"venue"
},
  "geometry": {"coordinates":[-104.766409,39.641759],"type":"Point"}
}