{
  "type": "Feature",
  "properties": {
    "iso:country":"US",
    "sg:address":"501 Wazee St",
    "sg:city":"Denver",
    "sg:classifiers":[
        {
            "category":"Professional",
            "subcategory":"Computer Services",
            "type":"Services"
        }
    ],
    "sg:phone":"+1 303 446 5360",
    "sg:postcode":"80204",
    "sg:province":"CO",
    "sg:tags":[
        "internet"
    ],
    "wof:name":"Viawest",
    "wof:placetype":"venue"
},
  "geometry": {"coordinates":[-105.01113700000001,39.745186],"type":"Point"}
}