{
  "type": "Feature",
  "properties": {
    "iso:country":"US",
    "sg:address":"447 Main St",
    "sg:city":"Lyons",
    "sg:classifiers":[
        {
            "category":"Manufacturing",
            "subcategory":"Tools & Machinery",
            "type":"Manufacturing & Wholesale Goods"
        }
    ],
    "sg:phone":"+1 303 823 6330",
    "sg:postcode":"80540",
    "sg:province":"CO",
    "sg:tags":[
        "physician",
        "surgeon"
    ],
    "sg:website":"www.productsgroup.com",
    "wof:name":"Products Group Intl",
    "wof:placetype":"venue"
},
  "geometry": {"coordinates":[-105.27091900000001,40.224598],"type":"Point"}
}