{
  "type": "Feature",
  "properties": {
    "iso:country":"US",
    "sg:address":"724 Sue St",
    "sg:city":"Lafayette",
    "sg:classifiers":[
        {
            "category":"Retail",
            "subcategory":"Repair Shop",
            "type":"Services"
        }
    ],
    "sg:phone":"+1 303 665 9619",
    "sg:postcode":"80026",
    "sg:province":"CO",
    "sg:tags":[
        "equipment",
        "electrical"
    ],
    "wof:name":"M&K Systems",
    "wof:placetype":"venue"
},
  "geometry": {"coordinates":[-105.07925,39.996787],"type":"Point"}
}