{
  "type": "Feature",
  "properties": {
    "addr:full":"1508 Co Rd 21 Brighton CO 80603",
    "addr:housenumber":"1508;21",
    "addr:postcode":"80603",
    "addr:street":"Co Rd",
    "iso:country":"US",
    "sg:address":"1508 Co Rd 21",
    "sg:city":"Brighton",
    "sg:classifiers":[
        {
            "category":"Manufacturing",
            "subcategory":"Electronics",
            "type":"Manufacturing & Wholesale Goods"
        }
    ],
    "sg:phone":"+1 303 654 1992",
    "sg:postcode":"80603",
    "sg:province":"CO",
    "sg:tags":[
        "apparatus",
        "mfg"
    ],
    "wof:name":"Freephone International",
    "wof:placetype":"venue"
},
  "geometry": {"coordinates":[-104.867194,40.022303],"type":"Point"}
}