{
  "type": "Feature",
  "properties": {
    "iso:country":"US",
    "sg:address":"11028 Co Rd 3",
    "sg:city":"Kirk",
    "sg:classifiers":[
        {
            "category":"Government",
            "subcategory":"Post Office",
            "type":"Public Place"
        }
    ],
    "sg:phone":"+1 970 362 4394",
    "sg:postcode":"80824",
    "sg:province":"CO",
    "wof:name":"US Post Office",
    "wof:placetype":"venue"
},
  "geometry": {"coordinates":[-102.591843,39.612628],"type":"Point"}
}