{
  "type": "Feature",
  "properties": {
    "iso:country":"US",
    "sg:address":"4240 E Co Rd 66",
    "sg:city":"Wellington",
    "sg:classifiers":[
        {
            "category":"Social Services",
            "subcategory":"Job Training",
            "type":"Services"
        }
    ],
    "sg:phone":"+1 970 568 9803",
    "sg:postcode":"80549",
    "sg:province":"CO",
    "sg:tags":[
        "rehabilitation"
    ],
    "sg:website":"www.denverrescuemission.org",
    "wof:name":"Harvest Farm",
    "wof:placetype":"venue"
},
  "geometry": {"coordinates":[-104.998937,40.72621],"type":"Point"}
}