{
  "type": "Feature",
  "properties": {
    "iso:country":"US",
    "sg:address":"612 Alpine Dr",
    "sg:city":"Boulder",
    "sg:classifiers":[
        {
            "category":"Building & Trades",
            "subcategory":"Construction",
            "type":"Services"
        }
    ],
    "sg:phone":"+1 303 444 8811",
    "sg:postcode":"80304",
    "sg:province":"CO",
    "sg:tags":[
        "general",
        "contractor"
    ],
    "wof:name":"Big Horn Builders",
    "wof:placetype":"venue"
},
  "geometry": {"coordinates":[-105.286841,40.025445],"type":"Point"}
}