{
  "type": "Feature",
  "properties": {
    "iso:country":"US",
    "sg:address":"330 Acoma St",
    "sg:city":"Denver",
    "sg:classifiers":[
        {
            "category":"Professional",
            "type":"Services"
        }
    ],
    "sg:phone":"+1 303 744 7696",
    "sg:postcode":"80223",
    "sg:province":"CO",
    "sg:tags":[
        "establishment"
    ],
    "sg:website":"www.kuzos.com",
    "wof:name":"Kuzos",
    "wof:placetype":"venue"
},
  "geometry": {"coordinates":[-104.989103,39.72205],"type":"Point"}
}