{
  "type": "Feature",
  "properties": {
    "addr:full":"209 Leta Dr Colorado Springs CO 80911",
    "addr:housenumber":"209",
    "addr:postcode":"80911",
    "addr:street":"Leta Dr",
    "iso:country":"US",
    "sg:address":"209 Leta Dr",
    "sg:city":"Colorado Springs",
    "sg:classifiers":[
        {
            "category":"Education",
            "subcategory":"School",
            "type":"Public Place"
        }
    ],
    "sg:phone":"+1 719 391 3375",
    "sg:postcode":"80911",
    "sg:province":"CO",
    "wof:name":"North Elementary School",
    "wof:placetype":"venue"
},
  "geometry": {"coordinates":[-104.745366,38.762029],"type":"Point"}
}