{
  "type": "Feature",
  "properties": {
    "addr:full":"16215 Jones Rd Peyton CO 80831",
    "addr:housenumber":"16215",
    "addr:postcode":"80831",
    "addr:street":"Jones Rd",
    "iso:country":"US",
    "sg:address":"16215 Jones Rd",
    "sg:city":"Peyton",
    "sg:classifiers":[
        {
            "category":"Building & Trades",
            "subcategory":"Construction",
            "type":"Services"
        }
    ],
    "sg:phone":"+1 719 683 4758",
    "sg:postcode":"80831",
    "sg:province":"CO",
    "sg:tags":[
        "hanging",
        "contractor"
    ],
    "wof:name":"Enterprise Painting Inc",
    "wof:placetype":"venue"
},
  "geometry": {"coordinates":[-104.533891,38.896298],"type":"Point"}
}