{
  "type": "Feature",
  "properties": {
    "iso:country":"US",
    "sg:address":"5660 Greenwood Plaza Blvd",
    "sg:city":"Englewood",
    "sg:classifiers":[
        {
            "category":"Building & Trades",
            "subcategory":"Construction",
            "type":"Services"
        }
    ],
    "sg:phone":"+1 303 484 5114",
    "sg:postcode":"80111",
    "sg:province":"CO",
    "sg:tags":[
        "house"
    ],
    "wof:name":"Mark Renn",
    "wof:placetype":"venue"
},
  "geometry": {"coordinates":[-104.89876,39.614087],"type":"Point"}
}