{
  "type": "Feature",
  "properties": {
    "addr:full":"309 Aabc Aspen CO 81611",
    "addr:housenumber":"309",
    "addr:postcode":"81611",
    "addr:street":"Aabc Aspen",
    "iso:country":"US",
    "sg:address":"309 Aabc",
    "sg:city":"Aspen",
    "sg:classifiers":[
        {
            "category":"Professional",
            "subcategory":"Business Services",
            "type":"Services"
        }
    ],
    "sg:phone":"+1 970 925 4310",
    "sg:postcode":"81611",
    "sg:province":"CO",
    "sg:tags":[
        "interior",
        "consultant",
        "design",
        "decorator"
    ],
    "wof:name":"Inner Design",
    "wof:placetype":"venue"
},
  "geometry": {"coordinates":[-106.860367,39.218649],"type":"Point"}
}