{
  "type": "Feature",
  "properties": {
    "iso:country":"US",
    "sg:address":"221 Federal Blvd",
    "sg:city":"Denver",
    "sg:classifiers":[
        {
            "category":"Restaurant",
            "type":"Food & Drink"
        }
    ],
    "sg:phone":"+1 303 922 9119",
    "sg:postcode":"80219",
    "sg:province":"CO",
    "sg:tags":[
        "mexican",
        "eating"
    ],
    "wof:name":"La Gota De Miel",
    "wof:placetype":"venue"
},
  "geometry": {"coordinates":[-105.025002,39.720402],"type":"Point"}
}