{
  "type": "Feature",
  "properties": {
    "iso:country":"US",
    "sg:address":"4910 Old Farm Cir W",
    "sg:city":"Colorado Springs",
    "sg:classifiers":[
        {
            "category":"Real Estate",
            "subcategory":"Real Estate Agent",
            "type":"Services"
        }
    ],
    "sg:phone":"+1 719 550 1515",
    "sg:postcode":"80917",
    "sg:province":"CO",
    "sg:website":"www.kenneyandcompany.net",
    "wof:name":"Kenney & Co",
    "wof:placetype":"venue"
},
  "geometry": {"coordinates":[-104.73594300000001,38.903428],"type":"Point"}
}