{
  "type": "Feature",
  "properties": {
    "addr:full":"4500 E 9th Ave Ste 510S Denver CO 80220",
    "addr:housenumber":"4500",
    "addr:postcode":"80220",
    "addr:street":"E 9Th Ave Ste 510S",
    "iso:country":"US",
    "sg:address":"4500 E 9th Ave Ste 510S",
    "sg:city":"Denver",
    "sg:classifiers":[
        {
            "category":"Health Services",
            "subcategory":"Doctor",
            "type":"Services"
        }
    ],
    "sg:phone":"+1 303 333 6556",
    "sg:postcode":"80220",
    "sg:province":"CO",
    "sg:tags":[
        "podiatrist"
    ],
    "wof:name":"Eugene Rosenthall, DPM",
    "wof:placetype":"venue"
},
  "geometry": {"coordinates":[-104.93517,39.731027],"type":"Point"}
}