{
  "type": "Feature",
  "properties": {
    "addr:full":"570 Evans St Steamboat Spgs CO 80487",
    "addr:housenumber":"570",
    "addr:postcode":"80487",
    "addr:street":"Evans St Steamboat Spgs",
    "iso:country":"US",
    "sg:address":"570 Evans St",
    "sg:city":"Steamboat Spgs",
    "sg:classifiers":[
        {
            "category":"Shopping",
            "type":"Retail Goods"
        }
    ],
    "sg:phone":"+1 970 879 8658",
    "sg:postcode":"80487",
    "sg:province":"CO",
    "sg:tags":[
        "art",
        "gallery",
        "dealer"
    ],
    "wof:name":"Georgia A Taylor Artist",
    "wof:placetype":"venue"
},
  "geometry": {"coordinates":[-106.84682599999999,40.488609],"type":"Point"}
}