{
  "type": "Feature",
  "properties": {
    "addr:full":"1774 W Wesley Ave Englewood CO 80110",
    "addr:housenumber":"1774",
    "addr:postcode":"80110",
    "addr:street":"W Wesley Ave",
    "iso:country":"US",
    "sg:address":"1774 W Wesley Ave",
    "sg:city":"Englewood",
    "sg:classifiers":[
        {
            "category":"Wholesale",
            "subcategory":"Auto Parts",
            "type":"Manufacturing & Wholesale Goods"
        }
    ],
    "sg:phone":"+1 303 935 6666",
    "sg:postcode":"80110",
    "sg:province":"CO",
    "sg:tags":[
        "automotive",
        "accessory"
    ],
    "sg:website":"www.midstatesinc.com",
    "wof:name":"Midstates Distributing",
    "wof:placetype":"venue"
},
  "geometry": {"coordinates":[-105.007384,39.673107],"type":"Point"}
}