{
  "type": "Feature",
  "properties": {
    "addr:full":"4575 S Knox Ct Englewood CO 80110",
    "addr:housenumber":"4575",
    "addr:postcode":"80110",
    "addr:street":"S Knox Ct",
    "iso:country":"US",
    "sg:address":"4575 S Knox Ct",
    "sg:city":"Englewood",
    "sg:classifiers":[
        {
            "category":"Building & Trades",
            "subcategory":"Electrical",
            "type":"Services"
        }
    ],
    "sg:phone":"+1 303 847 0297",
    "sg:postcode":"80110",
    "sg:province":"CO",
    "sg:tags":[
        "industrial",
        "electrician",
        "contractors-commercial",
        "electric"
    ],
    "sg:website":"http://www.currentelectricservice.com",
    "wof:name":"Current Electric Service Inc",
    "wof:placetype":"venue"
},
  "geometry": {"coordinates":[-105.032383,39.634262],"type":"Point"}
}