{
  "type": "Feature",
  "properties": {
    "iso:country":"US",
    "sg:address":"45199 Co Rd 36",
    "sg:city":"Fleming",
    "sg:classifiers":[
        {
            "category":"Local Transit",
            "type":"Transportation"
        }
    ],
    "sg:phone":"+1 970 774 3280",
    "sg:postcode":"80731",
    "sg:province":"CO",
    "sg:tags":[
        "passenger"
    ],
    "wof:name":"High Plins Rgnal Ems Crdinator",
    "wof:placetype":"venue"
},
  "geometry": {"coordinates":[-102.71885399999999,40.685817],"type":"Point"}
}