{
  "type": "Feature",
  "properties": {
    "iso:country":"US",
    "sg:address":"850 Englewood Pkwy",
    "sg:city":"Englewood",
    "sg:classifiers":[
        {
            "category":"Health Services",
            "subcategory":"Doctor",
            "type":"Services"
        }
    ],
    "sg:phone":"+1 303 789 0004",
    "sg:postcode":"80110",
    "sg:province":"CO",
    "sg:tags":[
        "physician",
        "surgeon"
    ],
    "wof:name":"Denver Open MRI",
    "wof:placetype":"venue"
},
  "geometry": {"coordinates":[-104.99722300000001,39.654811],"type":"Point"}
}