{
  "type": "Feature",
  "properties": {
    "iso:country":"US",
    "sg:address":"3250 W Oxford Ave",
    "sg:city":"Denver",
    "sg:classifiers":[
        {
            "category":"Food & Beverages",
            "subcategory":"Groceries & Convenience Stores",
            "type":"Retail Goods"
        }
    ],
    "sg:phone":"+1 303 503 4154",
    "sg:postcode":"80236",
    "sg:province":"CO",
    "sg:tags":[
        "product"
    ],
    "wof:name":"Beehive Foods & Vending",
    "wof:placetype":"venue"
},
  "geometry": {"coordinates":[-105.02955300000001,39.642178],"type":"Point"}
}