{
  "type": "Feature",
  "properties": {
    "iso:country":"US",
    "sg:address":"2048 S Pontiac Way",
    "sg:city":"Denver",
    "sg:classifiers":[
        {
            "category":"Personal",
            "type":"Services"
        }
    ],
    "sg:phone":"+1 303 512 0200",
    "sg:postcode":"80224",
    "sg:province":"CO",
    "sg:tags":[
        "therapist",
        "massage"
    ],
    "wof:name":"King's Health Spa",
    "wof:placetype":"venue"
},
  "geometry": {"coordinates":[-104.90760400000001,39.679848],"type":"Point"}
}