{
  "type": "Feature",
  "properties": {
    "addr:full":"203 E Oak St Lamar CO 81052",
    "addr:housenumber":"203",
    "addr:postcode":"81052",
    "addr:street":"E Oak St",
    "iso:country":"US",
    "sg:address":"203 E Oak St",
    "sg:city":"Lamar",
    "sg:classifiers":[
        {
            "category":"Professional",
            "subcategory":"Accounting & Tax Preparation",
            "type":"Services"
        }
    ],
    "sg:phone":"+1 719 336 7428",
    "sg:postcode":"81052",
    "sg:province":"CO",
    "sg:tags":[
        "accountant"
    ],
    "wof:name":"Farmer & Co",
    "wof:placetype":"venue"
},
  "geometry": {"coordinates":[-102.616389,38.086257],"type":"Point"}
}