{
  "type": "Feature",
  "properties": {
    "iso:country":"US",
    "sg:address":"4050 Nonchalant Cir S",
    "sg:city":"Colorado Springs",
    "sg:classifiers":[
        {
            "category":"Education",
            "subcategory":"School",
            "type":"Public Place"
        }
    ],
    "sg:phone":"+1 719 597 3675",
    "sg:postcode":"80917",
    "sg:province":"CO",
    "sg:tags":[
        "christian"
    ],
    "wof:name":"Evangelical Christian Academy",
    "wof:placetype":"venue"
},
  "geometry": {"coordinates":[-104.752114,38.879889],"type":"Point"}
}