{
  "type": "Feature",
  "properties": {
    "iso:country":"US",
    "sg:address":"2692 Highway 50",
    "sg:city":"Grand Junction",
    "sg:classifiers":[
        {
            "category":"Restaurant",
            "type":"Food & Drink"
        }
    ],
    "sg:menulink":"http://www.allmenus.com/co/grand-junction/128915-subway/menu/",
    "sg:phone":"+1 970 242 3892",
    "sg:postcode":"81503",
    "sg:province":"CO",
    "sg:tags":[
        "american",
        "sandwich"
    ],
    "wof:name":"Subway",
    "wof:placetype":"venue"
},
  "geometry": {"coordinates":[-108.554046,39.043858],"type":"Point"}
}