{
  "type": "Feature",
  "properties": {
    "iso:country":"US",
    "sg:address":"2828 Walker Field Dr",
    "sg:city":"Grand Junction",
    "sg:classifiers":[
        {
            "category":"Restaurant",
            "type":"Food & Drink"
        }
    ],
    "sg:phone":"+1 970 241 1042",
    "sg:postcode":"81506",
    "sg:province":"CO",
    "wof:name":"Mesa Cafe",
    "wof:placetype":"venue"
},
  "geometry": {"coordinates":[-108.525474,39.120682],"type":"Point"}
}