{
  "type": "Feature",
  "properties": {
    "addr:full":"323 Muddy Rd Westcliffe CO 81252",
    "addr:housenumber":"323",
    "addr:postcode":"81252",
    "addr:street":"Muddy Rd",
    "iso:country":"US",
    "sg:address":"323 Muddy Rd",
    "sg:city":"Westcliffe",
    "sg:classifiers":[
        {
            "category":"Shopping",
            "type":"Retail Goods"
        }
    ],
    "sg:phone":"+1 719 783 2166",
    "sg:postcode":"81252",
    "sg:province":"CO",
    "sg:tags":[
        "art",
        "gallery",
        "dealer"
    ],
    "sg:website":"www.brookwoodgallery.com",
    "wof:name":"Brookwood Gallery",
    "wof:placetype":"venue"
},
  "geometry": {"coordinates":[-105.515309,38.117641],"type":"Point"}
}