{
  "type": "Feature",
  "properties": {
    "addr:full":"10980 Larry Dr Denver CO 80233",
    "addr:housenumber":"10980",
    "addr:postcode":"80233",
    "addr:street":"Larry Dr",
    "iso:country":"US",
    "sg:address":"10980 Larry Dr",
    "sg:city":"Denver",
    "sg:classifiers":[
        {
            "category":"Restaurant",
            "type":"Food & Drink"
        }
    ],
    "sg:phone":"+1 303 566 3268",
    "sg:postcode":"80233",
    "sg:province":"CO",
    "sg:tags":[
        "eating"
    ],
    "wof:name":"CC Ice Cream Inc",
    "wof:placetype":"venue"
},
  "geometry": {"coordinates":[-104.970039,39.89567],"type":"Point"}
}