{
  "type": "Feature",
  "properties": {
    "addr:full":"3925 Half Turn Pl Colorado Springs CO 80917",
    "addr:housenumber":"3925",
    "addr:postcode":"80917",
    "addr:street":"Half Turn Pl",
    "iso:country":"US",
    "sg:address":"3925 Half Turn Pl",
    "sg:city":"Colorado Springs",
    "sg:classifiers":[
        {
            "category":"Building & Trades",
            "subcategory":"Construction",
            "type":"Services"
        }
    ],
    "sg:phone":"+1 719 597 2508",
    "sg:postcode":"80917",
    "sg:province":"CO",
    "sg:tags":[
        "house"
    ],
    "wof:name":"Thomas Finish & Remodel",
    "wof:placetype":"venue"
},
  "geometry": {"coordinates":[-104.751706,38.888364],"type":"Point"}
}