{
  "type": "Feature",
  "properties": {
    "iso:country":"US",
    "sg:address":"177 E 1st St",
    "sg:city":"Delta",
    "sg:classifiers":[
        {
            "category":"Home & Garden",
            "subcategory":"Carpets & Floor Coverings",
            "type":"Retail Goods"
        }
    ],
    "sg:phone":"+1 970 874 4457",
    "sg:postcode":"81416",
    "sg:province":"CO",
    "sg:tags":[
        "installation",
        "flooring"
    ],
    "wof:name":"Nichols House Of Carpet",
    "wof:placetype":"venue"
},
  "geometry": {"coordinates":[-108.06906600000001,38.745673],"type":"Point"}
}