{
  "type": "Feature",
  "properties": {
    "addr:full":"550 Holly St Hudson CO 80642",
    "addr:housenumber":"550",
    "addr:postcode":"80642",
    "addr:street":"Holly St",
    "iso:country":"US",
    "sg:address":"550 Holly St",
    "sg:city":"Hudson",
    "sg:classifiers":[
        {
            "category":"Building & Trades",
            "subcategory":"Construction",
            "type":"Services"
        }
    ],
    "sg:phone":"+1 303 536 4035",
    "sg:postcode":"80642",
    "sg:province":"CO",
    "sg:tags":[
        "concrete",
        "contractor"
    ],
    "wof:name":"TW Concrete",
    "wof:placetype":"venue"
},
  "geometry": {"coordinates":[-104.632471,40.067548],"type":"Point"}
}