{
  "type": "Feature",
  "properties": {
    "addr:full":"3100 Hollywood Dr Pueblo CO 81005",
    "addr:housenumber":"3100",
    "addr:postcode":"81005",
    "addr:street":"Hollywood Dr",
    "iso:country":"US",
    "sg:address":"3100 Hollywood Dr",
    "sg:city":"Pueblo",
    "sg:classifiers":[
        {
            "category":"Education",
            "subcategory":"School",
            "type":"Public Place"
        }
    ],
    "sg:phone":"+1 719 549 7600",
    "sg:postcode":"81005",
    "sg:province":"CO",
    "wof:name":"South Park Elementary School",
    "wof:placetype":"venue"
},
  "geometry": {"coordinates":[-104.65440599999999,38.216057],"type":"Point"}
}