{
  "type": "Feature",
  "properties": {
    "iso:country":"US",
    "sg:address":"250 S Grand Mesa Dr",
    "sg:city":"Cedaredge",
    "sg:classifiers":[
        {
            "category":"Shopping",
            "subcategory":"Gifts & Souvenirs",
            "type":"Retail Goods"
        }
    ],
    "sg:phone":"+1 970 856 7664",
    "sg:postcode":"81413",
    "sg:province":"CO",
    "sg:tags":[
        "shop"
    ],
    "wof:name":"Apple Tree Hollow",
    "wof:placetype":"venue"
},
  "geometry": {"coordinates":[-107.92451199999999,38.898896],"type":"Point"}
}