{
  "type": "Feature",
  "properties": {
    "addr:full":"1171 W Dillon Rd Louisville CO 80027",
    "addr:housenumber":"1171",
    "addr:postcode":"80027",
    "addr:street":"W Dillon Rd",
    "iso:country":"US",
    "sg:address":"1171 W Dillon Rd",
    "sg:city":"Louisville",
    "sg:classifiers":[
        {
            "category":"Freight",
            "type":"Transportation"
        }
    ],
    "sg:phone":"+1 303 664 0401",
    "sg:postcode":"80027",
    "sg:province":"CO",
    "sg:tags":[
        "operator",
        "local",
        "trucking"
    ],
    "wof:name":"Huffy Service First Inc",
    "wof:placetype":"venue"
},
  "geometry": {"coordinates":[-105.163309,39.961105],"type":"Point"}
}