{
  "type": "Feature",
  "properties": {
    "iso:country":"US",
    "sg:address":"2925 S College Ave",
    "sg:city":"Fort Collins",
    "sg:classifiers":[
        {
            "category":"Real Estate",
            "subcategory":"Real Estate Agent",
            "type":"Services"
        }
    ],
    "sg:phone":"+1 970 225 1843",
    "sg:postcode":"80525",
    "sg:province":"CO",
    "sg:tags":[
        "agency",
        "rental"
    ],
    "wof:name":"Budget Ft Collins Co Rental",
    "wof:placetype":"venue"
},
  "geometry": {"coordinates":[-105.077125,40.548291],"type":"Point"}
}