{
  "type": "Feature",
  "properties": {
    "addr:full":"1210 S Parker Rd Denver CO 80231",
    "addr:housenumber":"1210",
    "addr:postcode":"80231",
    "addr:street":"S Parker Rd",
    "iso:country":"US",
    "sg:address":"1210 S Parker Rd",
    "sg:city":"Denver",
    "sg:classifiers":[
        {
            "category":"Banks & Credit Unions",
            "subcategory":"Bank",
            "type":"Services"
        }
    ],
    "sg:phone":"+1 303 751 0290",
    "sg:postcode":"80231",
    "sg:province":"CO",
    "sg:tags":[
        "loan",
        "real estate"
    ],
    "wof:name":"Financial Connection Group",
    "wof:placetype":"venue"
},
  "geometry": {"coordinates":[-104.896824,39.696091],"type":"Point"}
}