{
  "type": "Feature",
  "properties": {
    "addr:full":"9595 Pecos St Denver CO 80260",
    "addr:housenumber":"9595",
    "addr:postcode":"80260",
    "addr:street":"Pecos St",
    "iso:country":"US",
    "sg:address":"9595 Pecos St",
    "sg:city":"Denver",
    "sg:classifiers":[
        {
            "category":"Freight",
            "type":"Transportation"
        }
    ],
    "sg:phone":"+1 303 255 1508",
    "sg:postcode":"80260",
    "sg:province":"CO",
    "sg:tags":[
        "operator",
        "local",
        "trucking"
    ],
    "wof:name":"G&G Ramirez Trucking LLC",
    "wof:placetype":"venue"
},
  "geometry": {"coordinates":[-105.005707,39.870543],"type":"Point"}
}