{
  "type": "Feature",
  "properties": {
    "addr:full":"220 N Oak St Telluride CO 81435",
    "addr:housenumber":"220",
    "addr:postcode":"81435",
    "addr:street":"N Oak St",
    "iso:country":"US",
    "sg:address":"220 N Oak St",
    "sg:city":"Telluride",
    "sg:classifiers":[
        {
            "category":"Building & Trades",
            "subcategory":"Construction",
            "type":"Services"
        }
    ],
    "sg:phone":"+1 970 728 3746",
    "sg:postcode":"81435",
    "sg:province":"CO",
    "sg:tags":[
        "general",
        "contractor"
    ],
    "wof:name":"Mc Carthy Construction",
    "wof:placetype":"venue"
},
  "geometry": {"coordinates":[-107.812089,37.939109],"type":"Point"}
}