{
  "type": "Feature",
  "properties": {
    "addr:full":"309 US Hwy 287 Lafayette CO 80026",
    "addr:housenumber":"309",
    "addr:postcode":"80026",
    "addr:street":"Us Hwy 287",
    "iso:country":"US",
    "sg:address":"309 US Hwy 287",
    "sg:city":"Lafayette",
    "sg:classifiers":[
        {
            "category":"Shopping",
            "subcategory":"Pharmacy",
            "type":"Retail Goods"
        }
    ],
    "sg:phone":"+1 720 890 7038",
    "sg:postcode":"80026",
    "sg:province":"CO",
    "wof:name":"Walgreens",
    "wof:placetype":"venue"
},
  "geometry": {"coordinates":[-105.09410200000001,40.000304],"type":"Point"}
}