{
  "type": "Feature",
  "properties": {
    "iso:country":"US",
    "sg:address":"1578 S Broadway",
    "sg:city":"Denver",
    "sg:classifiers":[
        {
            "category":"Building & Trades",
            "subcategory":"Locksmith",
            "type":"Services"
        }
    ],
    "sg:phone":"+1 303 562 2084",
    "sg:postcode":"80210",
    "sg:province":"CO",
    "sg:tags":[
        "key"
    ],
    "wof:name":"Ac ABC Express Locksmith 24 7",
    "wof:placetype":"venue"
},
  "geometry": {"coordinates":[-104.987356,39.687943],"type":"Point"}
}