{
  "type": "Feature",
  "properties": {
    "addr:full":"53299 Co Rd 104 Grover CO 80729",
    "addr:housenumber":"53299;104",
    "addr:postcode":"80729",
    "addr:street":"Co Rd",
    "iso:country":"US",
    "sg:address":"53299 Co Rd 104",
    "sg:city":"Grover",
    "sg:classifiers":[
        {
            "category":"Farming",
            "subcategory":"Livestock Farm",
            "type":"Manufacturing & Wholesale Goods"
        }
    ],
    "sg:phone":"+1 970 656 3618",
    "sg:postcode":"80729",
    "sg:province":"CO",
    "sg:tags":[
        "wheat",
        "beef",
        "feedlot",
        "cattle"
    ],
    "wof:name":"Enderson Ranch",
    "wof:placetype":"venue"
},
  "geometry": {"coordinates":[-104.03068500000001,40.743343],"type":"Point"}
}