{
  "type": "Feature",
  "properties": {
    "iso:country":"US",
    "sg:address":"213 1st St",
    "sg:city":"Ault",
    "sg:classifiers":[
        {
            "category":"Shopping",
            "subcategory":"Used Merchandise",
            "type":"Retail Goods"
        }
    ],
    "sg:phone":"+1 970 834 2291",
    "sg:postcode":"80610",
    "sg:province":"CO",
    "sg:tags":[
        "antique"
    ],
    "wof:name":"J R's Antiques & Etc",
    "wof:placetype":"venue"
},
  "geometry": {"coordinates":[-104.732519,40.582322],"type":"Point"}
}