{
  "type": "Feature",
  "properties": {
    "iso:country":"US",
    "sg:address":"1966 S Hwy 83",
    "sg:city":"Franktown",
    "sg:classifiers":[
        {
            "category":"Building & Trades",
            "subcategory":"Construction",
            "type":"Services"
        }
    ],
    "sg:phone":"+1 303 660 3505",
    "sg:postcode":"80116",
    "sg:province":"CO",
    "sg:tags":[
        "utility",
        "contractor"
    ],
    "wof:name":"Western Utility Supply Inc",
    "wof:placetype":"venue"
},
  "geometry": {"coordinates":[-104.734059,39.333642],"type":"Point"}
}