{
  "type": "Feature",
  "properties": {
    "addr:full":"1083 Mockingbird St Brighton CO 80601",
    "addr:housenumber":"1083",
    "addr:postcode":"80601",
    "addr:street":"Mockingbird St",
    "iso:country":"US",
    "sg:address":"1083 Mockingbird St",
    "sg:city":"Brighton",
    "sg:classifiers":[
        {
            "category":"Professional",
            "type":"Services"
        }
    ],
    "sg:phone":"+1 303 655 1965",
    "sg:postcode":"80601",
    "sg:province":"CO",
    "wof:name":"Maureen Gaylord MBA",
    "wof:placetype":"venue"
},
  "geometry": {"coordinates":[-104.833941,39.969807],"type":"Point"}
}