{
  "type": "Feature",
  "properties": {
    "addr:full":"3045 S Parker Rd Aurora CO 80014",
    "addr:housenumber":"3045",
    "addr:postcode":"80014",
    "addr:street":"S Parker Rd",
    "iso:country":"US",
    "sg:address":"3045 S Parker Rd",
    "sg:city":"Aurora",
    "sg:classifiers":[
        {
            "category":"Travel",
            "subcategory":"Travel Agent",
            "type":"Entertainment"
        }
    ],
    "sg:phone":"+1 303 751 7095",
    "sg:postcode":"80014",
    "sg:province":"CO",
    "sg:tags":[
        "agency",
        "bureau"
    ],
    "wof:name":"Five Star Travel Assn",
    "wof:placetype":"venue"
},
  "geometry": {"coordinates":[-104.857353,39.662495],"type":"Point"}
}