{
  "type": "Feature",
  "properties": {
    "addr:full":"65782 Lincoln Rd Montrose CO 81401",
    "addr:housenumber":"65782",
    "addr:postcode":"81401",
    "addr:street":"Lincoln Rd",
    "iso:country":"US",
    "sg:address":"65782 Lincoln Rd",
    "sg:city":"Montrose",
    "sg:classifiers":[
        {
            "category":"Home & Garden",
            "subcategory":"Carpets & Floor Coverings",
            "type":"Retail Goods"
        }
    ],
    "sg:phone":"+1 970 240 1938",
    "sg:postcode":"81401",
    "sg:province":"CO",
    "sg:tags":[
        "dealer",
        "rug"
    ],
    "wof:name":"Willis Carpet Svc",
    "wof:placetype":"venue"
},
  "geometry": {"coordinates":[-107.857823,38.507069],"type":"Point"}
}