{
  "type": "Feature",
  "properties": {
    "iso:country":"US",
    "sg:address":"56825 I- 70",
    "sg:city":"Strasburg",
    "sg:classifiers":[
        {
            "category":"Autos & Motor Vehicles",
            "subcategory":"Automobile Sales",
            "type":"Retail Goods"
        }
    ],
    "sg:phone":"+1 303 622 6137",
    "sg:postcode":"80136",
    "sg:province":"CO",
    "sg:tags":[
        "glass",
        "used",
        "replacement"
    ],
    "wof:name":"Rollin Stone Auto Sales LLC",
    "wof:placetype":"venue"
},
  "geometry": {"coordinates":[-104.32337,39.734296],"type":"Point"}
}