{
  "type": "Feature",
  "properties": {
    "addr:full":"330 Park Dr Glenwood Springs CO 81601",
    "addr:housenumber":"330",
    "addr:postcode":"81601",
    "addr:street":"Park Dr",
    "iso:country":"US",
    "sg:address":"330 Park Dr",
    "sg:city":"Glenwood Springs",
    "sg:classifiers":[
        {
            "category":"Building & Trades",
            "subcategory":"Cleaning & Sanitation",
            "type":"Services"
        }
    ],
    "sg:phone":"+1 970 945 4462",
    "sg:postcode":"81601",
    "sg:province":"CO",
    "sg:tags":[
        "maintenance"
    ],
    "wof:name":"Ballinger Cleaning Service",
    "wof:placetype":"venue"
},
  "geometry": {"coordinates":[-107.328717,39.535009],"type":"Point"}
}