{
  "type": "Feature",
  "properties": {
    "iso:country":"US",
    "sg:address":"1021 Cottonwood St",
    "sg:city":"Broomfield",
    "sg:classifiers":[
        {
            "category":"Professional",
            "type":"Services"
        }
    ],
    "sg:phone":"+1 303 466 2659",
    "sg:postcode":"80020",
    "sg:province":"CO",
    "wof:name":"Future 5000 LLC",
    "wof:placetype":"venue"
},
  "geometry": {"coordinates":[-105.057005,39.932177],"type":"Point"}
}