{
  "type": "Feature",
  "properties": {
    "addr:full":"34600 Co Rd 31 Greeley CO 80631",
    "addr:housenumber":"34600;31",
    "addr:postcode":"80631",
    "addr:street":"Co Rd",
    "iso:country":"US",
    "sg:address":"34600 Co Rd 31",
    "sg:city":"Greeley",
    "sg:classifiers":[
        {
            "category":"Farming",
            "subcategory":"Dairy Farm",
            "type":"Manufacturing & Wholesale Goods"
        }
    ],
    "sg:phone":"+1 970 454 3630",
    "sg:postcode":"80631",
    "sg:province":"CO",
    "wof:name":"Hard-Ley Holsteins",
    "wof:placetype":"venue"
},
  "geometry": {"coordinates":[-104.773391,40.508965],"type":"Point"}
}