{
  "type": "Feature",
  "properties": {
    "iso:country":"US",
    "sg:address":"2024 35th Ave",
    "sg:city":"Greeley",
    "sg:classifiers":[
        {
            "category":"Food & Beverages",
            "subcategory":"Liquor & Beverages",
            "type":"Retail Goods"
        }
    ],
    "sg:phone":"+1 970 330 8466",
    "sg:postcode":"80634",
    "sg:province":"CO",
    "sg:tags":[
        "alcoholic"
    ],
    "wof:name":"Westlake Wine & Spirits Inc",
    "wof:placetype":"venue"
},
  "geometry": {"coordinates":[-104.73494100000001,40.403687],"type":"Point"}
}