{
  "type": "Feature",
  "properties": {
    "addr:full":"774 Co Rd 110 Glenwood Springs CO 81601",
    "addr:housenumber":"774;110",
    "addr:postcode":"81601",
    "addr:street":"Co Rd",
    "iso:country":"US",
    "sg:address":"774 Co Rd 110",
    "sg:city":"Glenwood Springs",
    "sg:classifiers":[
        {
            "category":"Mining & Drilling",
            "type":"Manufacturing & Wholesale Goods"
        }
    ],
    "sg:phone":"+1 970 945 8849",
    "sg:postcode":"81601",
    "sg:province":"CO",
    "sg:tags":[
        "well"
    ],
    "wof:name":"Shelton Drilling",
    "wof:placetype":"venue"
},
  "geometry": {"coordinates":[-107.259725,39.462491],"type":"Point"}
}