{
  "type": "Feature",
  "properties": {
    "iso:country":"US",
    "sg:address":"1402 W Eisenhower Blvd",
    "sg:city":"Loveland",
    "sg:classifiers":[
        {
            "category":"Real Estate",
            "subcategory":"Real Estate Agent",
            "type":"Services"
        }
    ],
    "sg:phone":"+1 970 669 9696",
    "sg:postcode":"80537",
    "sg:province":"CO",
    "wof:name":"First Choice Realtors",
    "wof:placetype":"venue"
},
  "geometry": {"coordinates":[-105.096917,40.407121],"type":"Point"}
}