{
  "type": "Feature",
  "properties": {
    "iso:country":"US",
    "sg:address":"3659 Austin Bluffs Pkwy",
    "sg:city":"Colorado Springs",
    "sg:classifiers":[
        {
            "category":"Wholesale",
            "subcategory":"Machinery & Supplies",
            "type":"Manufacturing & Wholesale Goods"
        }
    ],
    "sg:phone":"+1 719 260 7767",
    "sg:postcode":"80918",
    "sg:province":"CO",
    "sg:tags":[
        "equipment",
        "industrial",
        "radiotelephone",
        "communication"
    ],
    "wof:name":"Advantage Wireless",
    "wof:placetype":"venue"
},
  "geometry": {"coordinates":[-104.760104,38.890758],"type":"Point"}
}