{
  "type": "Feature",
  "properties": {
    "iso:country":"US",
    "sg:address":"1438 N Hancock Ave",
    "sg:city":"Colorado Springs",
    "sg:classifiers":[
        {
            "category":"Social Services",
            "type":"Services"
        }
    ],
    "sg:phone":"+1 719 634 4115",
    "sg:postcode":"80903",
    "sg:province":"CO",
    "sg:tags":[
        "senior",
        "citizen"
    ],
    "wof:name":"Rebuilding Together",
    "wof:placetype":"venue"
},
  "geometry": {"coordinates":[-104.80261299999999,38.853587],"type":"Point"}
}