{
  "type": "Feature",
  "properties": {
    "iso:country":"US",
    "sg:address":"4545 E 9th Avenue Suite 300",
    "sg:city":"Denver",
    "sg:classifiers":[
        {
            "category":"Health Services",
            "subcategory":"Doctor",
            "type":"Services"
        }
    ],
    "sg:phone":"+1 303 321 0700",
    "sg:postcode":"80220",
    "sg:province":"CO",
    "wof:name":"Neurological Consultants",
    "wof:placetype":"venue"
},
  "geometry": {"coordinates":[-104.93464299999999,39.731072],"type":"Point"}
}