{
  "type": "Feature",
  "properties": {
    "addr:full":"4949 Broadway St Boulder CO 80304",
    "addr:housenumber":"4949",
    "addr:postcode":"80304",
    "addr:street":"Broadway St",
    "iso:country":"US",
    "sg:address":"4949 Broadway St",
    "sg:city":"Boulder",
    "sg:classifiers":[
        {
            "category":"Wholesale",
            "subcategory":"Non-durable Goods",
            "type":"Manufacturing & Wholesale Goods"
        }
    ],
    "sg:phone":"+1 303 448 1942",
    "sg:postcode":"80304",
    "sg:province":"CO",
    "sg:tags":[
        "pet",
        "supply"
    ],
    "sg:website":"www.rockymountaink9.com",
    "wof:name":"Rocky Mtn Canine Accessories",
    "wof:placetype":"venue"
},
  "geometry": {"coordinates":[-105.282003,40.064728],"type":"Point"}
}