{
  "type": "Feature",
  "properties": {
    "addr:full":"262 W Danbury Ct Grand Junction CO 81503",
    "addr:housenumber":"262",
    "addr:postcode":"81503",
    "addr:street":"W Danbury Ct",
    "iso:country":"US",
    "sg:address":"262 W Danbury Ct",
    "sg:city":"Grand Junction",
    "sg:classifiers":[
        {
            "category":"Building & Trades",
            "subcategory":"Construction",
            "type":"Services"
        }
    ],
    "sg:phone":"+1 970 245 7840",
    "sg:postcode":"81503",
    "sg:province":"CO",
    "sg:tags":[
        "contractor"
    ],
    "wof:name":"Hughes Bathtub Refinishin",
    "wof:placetype":"venue"
},
  "geometry": {"coordinates":[-108.532771,39.04198],"type":"Point"}
}