{
  "type": "Feature",
  "properties": {
    "addr:full":"10377 Santa Fe Trl Trinidad CO 81082",
    "addr:housenumber":"10377",
    "addr:postcode":"81082",
    "addr:street":"Santa Fe Trl",
    "iso:country":"US",
    "sg:address":"10377 Santa Fe Trl",
    "sg:city":"Trinidad",
    "sg:classifiers":[
        {
            "category":"Organizations",
            "subcategory":"Religious Organization",
            "type":"Services"
        }
    ],
    "sg:phone":"+1 719 846 6018",
    "sg:postcode":"81082",
    "sg:province":"CO",
    "sg:tags":[
        "church"
    ],
    "wof:name":"First Southern Baptist Church",
    "wof:placetype":"venue"
},
  "geometry": {"coordinates":[-104.51711400000001,37.140014],"type":"Point"}
}