{
  "type": "Feature",
  "properties": {
    "iso:country":"US",
    "sg:address":"1330 Zuni Street",
    "sg:city":"Denver",
    "sg:classifiers":[
        {
            "category":"Health Services",
            "subcategory":"Doctor",
            "type":"Services"
        }
    ],
    "sg:phone":"+1 303 436 9177",
    "sg:postcode":"80204",
    "sg:province":"CO",
    "sg:tags":[
        "orthopedist"
    ],
    "wof:name":"Zimmer Frey",
    "wof:placetype":"venue"
},
  "geometry": {"coordinates":[-105.015915,39.737398],"type":"Point"}
}