{
  "type": "Feature",
  "properties": {
    "iso:country":"US",
    "sg:address":"154 W Mountain Ave",
    "sg:city":"Fort Collins",
    "sg:classifiers":[
        {
            "category":"Manufacturing",
            "subcategory":"Printing",
            "type":"Manufacturing & Wholesale Goods"
        }
    ],
    "sg:phone":"+1 970 221 5444",
    "sg:postcode":"80524",
    "sg:province":"CO",
    "sg:tags":[
        "commercial"
    ],
    "wof:name":"Kwik Kopy Printing",
    "wof:placetype":"venue"
},
  "geometry": {"coordinates":[-105.078721,40.58711],"type":"Point"}
}