{
  "type": "Feature",
  "properties": {
    "addr:full":"6425 W 52nd Ave Arvada CO 80002",
    "addr:housenumber":"6425",
    "addr:postcode":"80002",
    "addr:street":"W 52Nd Ave",
    "iso:country":"US",
    "sg:address":"6425 W 52nd Ave",
    "sg:city":"Arvada",
    "sg:classifiers":[
        {
            "category":"Local Transit",
            "type":"Transportation"
        }
    ],
    "sg:phone":"+1 303 432 0100",
    "sg:postcode":"80002",
    "sg:province":"CO",
    "sg:tags":[
        "passenger",
        "ambulance"
    ],
    "wof:name":"Pridemark Paramedic Services",
    "wof:placetype":"venue"
},
  "geometry": {"coordinates":[-105.06856500000001,39.791171],"type":"Point"}
}