{
  "type": "Feature",
  "properties": {
    "addr:full":"2124 Broadway St Boulder CO 80304",
    "addr:housenumber":"2124",
    "addr:postcode":"80304",
    "addr:street":"Broadway St",
    "iso:country":"US",
    "sg:address":"2124 Broadway St",
    "sg:city":"Boulder",
    "sg:classifiers":[
        {
            "category":"Shopping",
            "subcategory":"Computers & Home Electronics",
            "type":"Retail Goods"
        }
    ],
    "sg:phone":"+1 303 449 1974",
    "sg:postcode":"80304",
    "sg:province":"CO",
    "sg:tags":[
        "consulting"
    ],
    "wof:name":"I Q Computer",
    "wof:placetype":"venue"
},
  "geometry": {"coordinates":[-105.280534,40.019682],"type":"Point"}
}