{
  "type": "Feature",
  "properties": {
    "addr:full":"213 Smokey St Fort Collins CO 80525",
    "addr:housenumber":"213",
    "addr:postcode":"80525",
    "addr:street":"Smokey St",
    "iso:country":"US",
    "sg:address":"213 Smokey St",
    "sg:city":"Fort Collins",
    "sg:classifiers":[
        {
            "category":"Building & Trades",
            "subcategory":"Construction",
            "type":"Services"
        }
    ],
    "sg:phone":"+1 970 206 1110",
    "sg:postcode":"80525",
    "sg:province":"CO",
    "sg:tags":[
        "concrete",
        "contractor"
    ],
    "wof:name":"Sipes Concrete Construction",
    "wof:placetype":"venue"
},
  "geometry": {"coordinates":[-105.07536399999999,40.506437],"type":"Point"}
}