{
  "type": "Feature",
  "properties": {
    "iso:country":"US",
    "sg:address":"17800 E 32nd Ave",
    "sg:city":"Aurora",
    "sg:classifiers":[
        {
            "category":"Manufacturing",
            "subcategory":"Tools & Machinery",
            "type":"Manufacturing & Wholesale Goods"
        }
    ],
    "sg:phone":"+1 303 340 5641",
    "sg:postcode":"80011",
    "sg:province":"CO",
    "sg:tags":[
        "x",
        "mfg"
    ],
    "wof:name":"Philips Med Systems Cleveland",
    "wof:placetype":"venue"
},
  "geometry": {"coordinates":[-104.78026,39.759428],"type":"Point"}
}