{
  "type": "Feature",
  "properties": {
    "iso:country":"US",
    "sg:address":"10 Rupert St",
    "sg:city":"Monte Vista",
    "sg:classifiers":[
        {
            "category":"Personal",
            "type":"Services"
        }
    ],
    "sg:phone":"+1 719 852 4400",
    "sg:postcode":"81144",
    "sg:province":"CO",
    "sg:tags":[
        "therapist",
        "massage"
    ],
    "wof:name":"Healing Hands Therapeutic Msge",
    "wof:placetype":"venue"
},
  "geometry": {"coordinates":[-106.16136,37.583335],"type":"Point"}
}