{
  "type": "Feature",
  "properties": {
    "iso:country":"US",
    "sg:address":"120 1st St",
    "sg:city":"Fort Lupton",
    "sg:classifiers":[
        {
            "category":"Health Services",
            "subcategory":"Hospital",
            "type":"Services"
        }
    ],
    "sg:phone":"+1 303 857 2723",
    "sg:postcode":"80621",
    "sg:province":"CO",
    "sg:tags":[
        "mental"
    ],
    "wof:name":"North Range Behavioral Health",
    "wof:placetype":"venue"
},
  "geometry": {"coordinates":[-104.818217,40.080144],"type":"Point"}
}