{
  "type": "Feature",
  "properties": {
    "addr:full":"1542 Deanna Ct Loveland CO 80537",
    "addr:housenumber":"1542",
    "addr:postcode":"80537",
    "addr:street":"Deanna Ct",
    "iso:country":"US",
    "sg:address":"1542 Deanna Ct",
    "sg:city":"Loveland",
    "sg:classifiers":[
        {
            "category":"Home & Garden",
            "subcategory":"Carpets & Floor Coverings",
            "type":"Retail Goods"
        }
    ],
    "sg:phone":"+1 970 278 1255",
    "sg:postcode":"80537",
    "sg:province":"CO",
    "wof:name":"Ralphs Floor Coverings",
    "wof:placetype":"venue"
},
  "geometry": {"coordinates":[-105.09204800000001,40.377104],"type":"Point"}
}