{
  "type": "Feature",
  "properties": {
    "addr:full":"3400 W 16th St Greeley CO 80634",
    "addr:housenumber":"3400",
    "addr:postcode":"80634",
    "addr:street":"W 16Th St",
    "iso:country":"US",
    "sg:address":"3400 W 16th St",
    "sg:city":"Greeley",
    "sg:classifiers":[
        {
            "category":"Professional",
            "type":"Services"
        }
    ],
    "sg:phone":"+1 970 346 5140",
    "sg:postcode":"80634",
    "sg:province":"CO",
    "sg:tags":[
        "establishment"
    ],
    "wof:name":"Total Convenience Inc",
    "wof:placetype":"venue"
},
  "geometry": {"coordinates":[-104.733412,40.414691],"type":"Point"}
}