{
  "type": "Feature",
  "properties": {
    "iso:country":"US",
    "sg:address":"3799 E 60th Ave",
    "sg:city":"Commerce City",
    "sg:classifiers":[
        {
            "category":"Building & Trades",
            "subcategory":"Locksmith",
            "type":"Services"
        }
    ],
    "sg:phone":"+1 303 323 0056",
    "sg:postcode":"80022",
    "sg:province":"CO",
    "sg:tags":[
        "key"
    ],
    "wof:name":"23 7 A Locksmith",
    "wof:placetype":"venue"
},
  "geometry": {"coordinates":[-104.942872,39.804989],"type":"Point"}
}