{
  "type": "Feature",
  "properties": {
    "iso:country":"US",
    "sg:address":"200 E Colfax Ave Ste 140",
    "sg:city":"Denver",
    "sg:classifiers":[
        {
            "category":"Government",
            "subcategory":"Office",
            "type":"Public Place"
        }
    ],
    "sg:phone":"+1 303 866 2757",
    "sg:postcode":"80203",
    "sg:province":"CO",
    "sg:tags":[
        "township",
        "government-city",
        "village"
    ],
    "sg:website":"http://www.greatcopayback.net",
    "wof:name":"Investment Division",
    "wof:placetype":"venue"
},
  "geometry": {"coordinates":[-104.98484000000001,39.740059],"type":"Point"}
}