{
  "type": "Feature",
  "properties": {
    "iso:country":"US",
    "sg:address":"5924 S Kipling St",
    "sg:city":"Littleton",
    "sg:classifiers":[
        {
            "category":"Personal",
            "subcategory":"Beauty Salon",
            "type":"Services"
        }
    ],
    "sg:phone":"+1 303 933 7836",
    "sg:postcode":"80127",
    "sg:province":"CO",
    "sg:tags":[
        "manicuring"
    ],
    "wof:name":"Kay Kare Nails",
    "wof:placetype":"venue"
},
  "geometry": {"coordinates":[-105.109915,39.606588],"type":"Point"}
}