{
  "type": "Feature",
  "properties": {
    "addr:full":"703 Illinois St Golden CO 80401",
    "addr:housenumber":"703",
    "addr:postcode":"80401",
    "addr:street":"Illinois St",
    "iso:country":"US",
    "sg:address":"703 Illinois St",
    "sg:city":"Golden",
    "sg:classifiers":[
        {
            "category":"Shopping",
            "subcategory":"Florist",
            "type":"Retail Goods"
        }
    ],
    "sg:phone":"+1 303 384 9594",
    "sg:postcode":"80401",
    "sg:province":"CO",
    "wof:name":"Kettys Flowers",
    "wof:placetype":"venue"
},
  "geometry": {"coordinates":[-105.22841699999999,39.757784],"type":"Point"}
}