{
  "type": "Feature",
  "properties": {
    "addr:full":"503 Pawnee Dr Sterling CO 80751",
    "addr:housenumber":"503",
    "addr:postcode":"80751",
    "addr:street":"Pawnee Dr",
    "iso:country":"US",
    "sg:address":"503 Pawnee Dr",
    "sg:city":"Sterling",
    "sg:classifiers":[
        {
            "category":"Insurance",
            "subcategory":"Insurance Agent",
            "type":"Services"
        }
    ],
    "sg:phone":"+1 970 522 2827",
    "sg:postcode":"80751",
    "sg:province":"CO",
    "wof:name":"Hospitality Insurance Services",
    "wof:placetype":"venue"
},
  "geometry": {"coordinates":[-103.251632,40.610874],"type":"Point"}
}