{
  "type": "Feature",
  "properties": {
    "iso:country":"US",
    "sg:address":"1318 S Havana St",
    "sg:city":"Aurora",
    "sg:classifiers":[
        {
            "category":"Shopping",
            "subcategory":"Clothing, Apparel, & Fashions",
            "type":"Retail Goods"
        }
    ],
    "sg:phone":"+1 303 695 8302",
    "sg:postcode":"80012",
    "sg:province":"CO",
    "sg:website":"www.gorave.com",
    "wof:name":"Rave",
    "wof:placetype":"venue"
},
  "geometry": {"coordinates":[-104.865887,39.695307],"type":"Point"}
}