{
  "type": "Feature",
  "properties": {
    "iso:country":"US",
    "sg:address":"930 S Prospect St",
    "sg:city":"Colorado Springs",
    "sg:classifiers":[
        {
            "category":"Organizations",
            "subcategory":"Religious Organization",
            "type":"Services"
        }
    ],
    "sg:phone":"+1 719 632 0721",
    "sg:postcode":"80903",
    "sg:province":"CO",
    "wof:name":"Progrssive Chrch God In Christ",
    "wof:placetype":"venue"
},
  "geometry": {"coordinates":[-104.81089299999999,38.820467],"type":"Point"}
}