{
  "type": "Feature",
  "properties": {
    "iso:country":"US",
    "sg:address":"250 Palomino Trl",
    "sg:city":"Ridgway",
    "sg:classifiers":[
        {
            "category":"Bars & Pubs",
            "type":"Food & Drink"
        }
    ],
    "sg:phone":"+1 970 626 3884",
    "sg:postcode":"81432",
    "sg:province":"CO",
    "wof:name":"Wild Horse Saloon",
    "wof:placetype":"venue"
},
  "geometry": {"coordinates":[-107.747698,38.151921],"type":"Point"}
}