{
  "type": "Feature",
  "properties": {
    "addr:full":"269 Evergreen Rd Woodland Park CO 80863",
    "addr:housenumber":"269",
    "addr:postcode":"80863",
    "addr:street":"Evergreen Rd",
    "iso:country":"US",
    "sg:address":"269 Evergreen Rd",
    "sg:city":"Woodland Park",
    "sg:classifiers":[
        {
            "category":"Building & Trades",
            "subcategory":"Construction",
            "type":"Services"
        }
    ],
    "sg:phone":"+1 719 686 1359",
    "sg:postcode":"80863",
    "sg:province":"CO",
    "sg:tags":[
        "water",
        "well",
        "drilling"
    ],
    "wof:name":"Front Range Inspections",
    "wof:placetype":"venue"
},
  "geometry": {"coordinates":[-105.117642,38.990162],"type":"Point"}
}