{
  "type": "Feature",
  "properties": {
    "iso:country":"US",
    "sg:address":"5760 Ward Rd",
    "sg:city":"Arvada",
    "sg:classifiers":[
        {
            "category":"Retail",
            "subcategory":"Car Wash",
            "type":"Services"
        }
    ],
    "sg:phone":"+1 303 467 0505",
    "sg:postcode":"80002",
    "sg:province":"CO",
    "sg:tags":[
        "operated",
        "polishing",
        "washing"
    ],
    "wof:name":"Pump House Carwash",
    "wof:placetype":"venue"
},
  "geometry": {"coordinates":[-105.137843,39.800495],"type":"Point"}
}