{
  "type": "Feature",
  "properties": {
    "iso:country":"US",
    "sg:address":"6285 Lehman Dr",
    "sg:city":"Colorado Springs",
    "sg:classifiers":[
        {
            "category":"Building & Trades",
            "subcategory":"Construction",
            "type":"Services"
        }
    ],
    "sg:phone":"+1 719 534 9253",
    "sg:postcode":"80918",
    "sg:province":"CO",
    "sg:tags":[
        "sing",
        "carpentry",
        "contractor"
    ],
    "wof:name":"Westech Framing",
    "wof:placetype":"venue"
},
  "geometry": {"coordinates":[-104.78827,38.921741],"type":"Point"}
}