{
  "type": "Feature",
  "properties": {
    "iso:country":"US",
    "sg:address":"4080 W Floyd Ave",
    "sg:city":"Denver",
    "sg:classifiers":[
        {
            "category":"Retail",
            "subcategory":"Repair Shop",
            "type":"Services"
        }
    ],
    "sg:phone":"+1 303 936 6417",
    "sg:postcode":"80236",
    "sg:province":"CO",
    "sg:tags":[
        "appliance"
    ],
    "wof:name":"Allstar Refinishing",
    "wof:placetype":"venue"
},
  "geometry": {"coordinates":[-105.039975,39.65736],"type":"Point"}
}