{
  "type": "Feature",
  "properties": {
    "addr:full":"1200 Larimer St Denver CO 80202",
    "addr:housenumber":"1200",
    "addr:postcode":"80202",
    "addr:street":"Larimer St",
    "iso:country":"US",
    "sg:address":"1200 Larimer St",
    "sg:city":"Denver",
    "sg:classifiers":[
        {
            "category":"Education",
            "subcategory":"College",
            "type":"Public Place"
        }
    ],
    "sg:phone":"+1 303 556 5600",
    "sg:postcode":"80202",
    "sg:province":"CO",
    "sg:tags":[
        "academic",
        "school"
    ],
    "wof:name":"University Of Colorado-Denver",
    "wof:placetype":"venue"
},
  "geometry": {"coordinates":[-105.00142099999999,39.74641],"type":"Point"}
}