{
  "type": "Feature",
  "properties": {
    "addr:full":"9900 I- 76 Svc Rd Henderson CO 80640",
    "addr:housenumber":"9900;76",
    "addr:postcode":"80640",
    "addr:street":"I;Rd",
    "iso:country":"US",
    "sg:address":"9900 I- 76 Svc Rd",
    "sg:city":"Henderson",
    "sg:classifiers":[
        {
            "category":"Freight",
            "type":"Transportation"
        }
    ],
    "sg:phone":"+1 303 287 0273",
    "sg:postcode":"80640",
    "sg:province":"CO",
    "sg:tags":[
        "hauler",
        "contract"
    ],
    "wof:name":"Allied Systems Ltd LLP",
    "wof:placetype":"venue"
},
  "geometry": {"coordinates":[-104.89918900000001,39.872295],"type":"Point"}
}