{
  "type": "Feature",
  "properties": {
    "addr:full":"180 E Bridge St Brighton CO 80601",
    "addr:housenumber":"180",
    "addr:postcode":"80601",
    "addr:street":"E Bridge St",
    "iso:country":"US",
    "sg:address":"180 E Bridge St",
    "sg:city":"Brighton",
    "sg:classifiers":[
        {
            "category":"Professional",
            "subcategory":"Business Services",
            "type":"Services"
        }
    ],
    "sg:phone":"+1 303 637 9020",
    "sg:postcode":"80601",
    "sg:province":"CO",
    "sg:tags":[
        "interior",
        "consultant",
        "design",
        "decorator"
    ],
    "wof:name":"Unique Interiors",
    "wof:placetype":"venue"
},
  "geometry": {"coordinates":[-104.8203,39.98674],"type":"Point"}
}