{
  "type": "Feature",
  "properties": {
    "addr:full":"246 Main St Delta CO 81416",
    "addr:housenumber":"246",
    "addr:postcode":"81416",
    "addr:street":"Main St",
    "iso:country":"US",
    "sg:address":"246 Main St",
    "sg:city":"Delta",
    "sg:classifiers":[
        {
            "category":"Utilities",
            "subcategory":"Mobile Phone",
            "type":"Services"
        },
        {
            "category":"Shopping",
            "subcategory":"Computers & Home Electronics",
            "type":"Retail Goods"
        }
    ],
    "sg:phone":"+1 970 874 1551",
    "sg:postcode":"81416",
    "sg:province":"CO",
    "sg:tags":[
        "satellite",
        "antenna",
        "sales",
        "telephone",
        "cellular",
        "dish"
    ],
    "wof:name":"All American Satellite Service",
    "wof:placetype":"venue"
},
  "geometry": {"coordinates":[-108.07070899999999,38.743669],"type":"Point"}
}