{
  "type": "Feature",
  "properties": {
    "addr:full":"6455 Divide Dr Salida CO 81201",
    "addr:housenumber":"6455",
    "addr:postcode":"81201",
    "addr:street":"Divide Dr",
    "iso:country":"US",
    "sg:address":"6455 Divide Dr",
    "sg:city":"Salida",
    "sg:classifiers":[
        {
            "category":"Professional",
            "type":"Services"
        }
    ],
    "sg:phone":"+1 719 539 9258",
    "sg:postcode":"81201",
    "sg:province":"CO",
    "wof:name":"Townsend Co",
    "wof:placetype":"venue"
},
  "geometry": {"coordinates":[-105.99912,38.508332],"type":"Point"}
}