{
  "type": "Feature",
  "properties": {
    "addr:full":"10347 Heathcliff Ln Parker CO 80134",
    "addr:housenumber":"10347",
    "addr:postcode":"80134",
    "addr:street":"Heathcliff Ln",
    "iso:country":"US",
    "sg:address":"10347 Heathcliff Ln",
    "sg:city":"Parker",
    "sg:classifiers":[
        {
            "category":"Professional",
            "subcategory":"Business Services",
            "type":"Services"
        }
    ],
    "sg:phone":"+1 303 840 1976",
    "sg:postcode":"80134",
    "sg:province":"CO",
    "sg:tags":[
        "notary",
        "public"
    ],
    "wof:name":"Nina M Beinhorn Notary Public",
    "wof:placetype":"venue"
},
  "geometry": {"coordinates":[-104.790841,39.528439],"type":"Point"}
}