{
  "type": "Feature",
  "properties": {
    "iso:country":"US",
    "sg:address":"1532 E Mulberry St",
    "sg:city":"Fort Collins",
    "sg:classifiers":[
        {
            "category":"Insurance",
            "subcategory":"Insurance Agent",
            "type":"Services"
        }
    ],
    "sg:phone":"+1 970 495 9937",
    "sg:postcode":"80524",
    "sg:province":"CO",
    "wof:name":"Tom Pilkington Financial Svc",
    "wof:placetype":"venue"
},
  "geometry": {"coordinates":[-105.04711399999999,40.581224],"type":"Point"}
}