{
  "type": "Feature",
  "properties": {
    "addr:full":"2040 W 104th Ave Denver CO 80234",
    "addr:housenumber":"2040",
    "addr:postcode":"80234",
    "addr:street":"W 104Th Ave",
    "iso:country":"US",
    "sg:address":"2040 W 104th Ave",
    "sg:city":"Denver",
    "sg:classifiers":[
        {
            "category":"Autos & Motor Vehicles",
            "subcategory":"Automobile Sales",
            "type":"Retail Goods"
        }
    ],
    "sg:phone":"+1 303 500 5642",
    "sg:postcode":"80234",
    "sg:province":"CO",
    "sg:tags":[
        "dealers-used",
        "car",
        "cars-wholesale",
        "new"
    ],
    "sg:website":"http://www.skylinemitsubishi.com",
    "wof:name":"Skyline Mitsubishi",
    "wof:placetype":"venue"
},
  "geometry": {"coordinates":[-105.012654,39.885109],"type":"Point"}
}