{
  "type": "Feature",
  "properties": {
    "addr:full":"2250 S Federal Blvd Denver CO 80219",
    "addr:housenumber":"2250",
    "addr:postcode":"80219",
    "addr:street":"S Federal Blvd",
    "iso:country":"US",
    "sg:address":"2250 S Federal Blvd",
    "sg:city":"Denver",
    "sg:classifiers":[
        {
            "category":"Building & Trades",
            "subcategory":"Locksmith",
            "type":"Services"
        }
    ],
    "sg:phone":"+1 866 531 5198",
    "sg:postcode":"80219",
    "sg:province":"CO",
    "sg:tags":[
        "key"
    ],
    "wof:name":"Locksmith Service",
    "wof:placetype":"venue"
},
  "geometry": {"coordinates":[-105.024867,39.675977],"type":"Point"}
}