{
  "type": "Feature",
  "properties": {
    "iso:country":"US",
    "sg:address":"905 S Summit View Dr",
    "sg:city":"Fort Collins",
    "sg:classifiers":[
        {
            "category":"Health Services",
            "subcategory":"Clinic",
            "type":"Services"
        }
    ],
    "sg:phone":"+1 970 498 0207",
    "sg:postcode":"80524",
    "sg:province":"CO",
    "sg:tags":[
        "holistic",
        "practitioner"
    ],
    "wof:name":"Energetic Wellness",
    "wof:placetype":"venue"
},
  "geometry": {"coordinates":[-105.01866200000001,40.572304],"type":"Point"}
}