{
  "type": "Feature",
  "properties": {
    "addr:full":"1220 11th Ave Greeley CO 80631",
    "addr:housenumber":"1220",
    "addr:postcode":"80631",
    "addr:street":"11Th Ave",
    "iso:country":"US",
    "sg:address":"1220 11th Ave",
    "sg:city":"Greeley",
    "sg:classifiers":[
        {
            "category":"Education",
            "subcategory":"Special Training",
            "type":"Public Place"
        }
    ],
    "sg:phone":"+1 970 352 3235",
    "sg:postcode":"80631",
    "sg:province":"CO",
    "sg:tags":[
        "center"
    ],
    "wof:name":"Educational Opportunity Ctr",
    "wof:placetype":"venue"
},
  "geometry": {"coordinates":[-104.69621100000001,40.419418],"type":"Point"}
}