{
  "type": "Feature",
  "properties": {
    "iso:country":"US",
    "sg:address":"1380 Lawrence St",
    "sg:city":"Denver",
    "sg:classifiers":[
        {
            "category":"Banks & Credit Unions",
            "subcategory":"Bank",
            "type":"Services"
        }
    ],
    "sg:phone":"+1 303 595 9898",
    "sg:postcode":"80204",
    "sg:province":"CO",
    "wof:name":"Matrix Advisory Services",
    "wof:placetype":"venue"
},
  "geometry": {"coordinates":[-104.99900100000001,39.746498],"type":"Point"}
}