{
  "type": "Feature",
  "properties": {
    "addr:full":"5574 Harlan St Arvada CO 80002",
    "addr:housenumber":"5574",
    "addr:postcode":"80002",
    "addr:street":"Harlan St",
    "iso:country":"US",
    "sg:address":"5574 Harlan St",
    "sg:city":"Arvada",
    "sg:classifiers":[
        {
            "category":"Professional",
            "subcategory":"Engineering",
            "type":"Services"
        }
    ],
    "sg:phone":"+1 303 421 6454",
    "sg:postcode":"80002",
    "sg:province":"CO",
    "sg:tags":[
        "industrial",
        "machinery",
        "mfg"
    ],
    "wof:name":"Fagerstone Donald",
    "wof:placetype":"venue"
},
  "geometry": {"coordinates":[-105.06250199999999,39.797908],"type":"Point"}
}