{
  "type": "Feature",
  "properties": {
    "addr:full":"1691 Newport St Denver CO 80220",
    "addr:housenumber":"1691",
    "addr:postcode":"80220",
    "addr:street":"Newport St",
    "iso:country":"US",
    "sg:address":"1691 Newport St",
    "sg:city":"Denver",
    "sg:classifiers":[
        {
            "category":"Home & Garden",
            "subcategory":"Furniture",
            "type":"Retail Goods"
        }
    ],
    "sg:phone":"+1 303 321 3323",
    "sg:postcode":"80220",
    "sg:province":"CO",
    "wof:name":"Wilderness Furniture Inc",
    "wof:placetype":"venue"
},
  "geometry": {"coordinates":[-104.90944399999999,39.74279],"type":"Point"}
}