{
  "type": "Feature",
  "properties": {
    "iso:country":"US",
    "sg:address":"1550 W 88th Ave",
    "sg:city":"Denver",
    "sg:classifiers":[
        {
            "category":"Food & Beverages",
            "subcategory":"Groceries & Convenience Stores",
            "type":"Retail Goods"
        }
    ],
    "sg:phone":"+1 303 428 1262",
    "sg:postcode":"80260",
    "sg:province":"CO",
    "sg:tags":[
        "station",
        "gas"
    ],
    "wof:name":"Gas Mart Inc",
    "wof:placetype":"venue"
},
  "geometry": {"coordinates":[-105.00586800000001,39.856099],"type":"Point"}
}