{
  "type": "Feature",
  "properties": {
    "iso:country":"US",
    "sg:address":"130 Ski Hill Rd",
    "sg:city":"Dillon",
    "sg:classifiers":[
        {
            "category":"Banks & Credit Unions",
            "subcategory":"Bank",
            "type":"Services"
        }
    ],
    "sg:phone":"+1 970 468 1300",
    "sg:postcode":"80424",
    "sg:province":"CO",
    "sg:tags":[
        "loan",
        "real estate"
    ],
    "wof:name":"Weststar Mortgage",
    "wof:placetype":"venue"
},
  "geometry": {"coordinates":[-106.046955,39.482301],"type":"Point"}
}