{
  "type": "Feature",
  "properties": {
    "iso:country":"US",
    "sg:address":"3701 S College Ave",
    "sg:city":"Fort Collins",
    "sg:classifiers":[
        {
            "category":"Autos & Motor Vehicles",
            "subcategory":"Automobile Sales",
            "type":"Retail Goods"
        }
    ],
    "sg:phone":"+1 970 267 5072",
    "sg:postcode":"80525",
    "sg:province":"CO",
    "sg:tags":[
        "car",
        "dealer"
    ],
    "sg:website":"www.lithia.com",
    "wof:name":"Lithia Hyundai Of Fort Collins",
    "wof:placetype":"venue"
},
  "geometry": {"coordinates":[-105.07719299999999,40.536686],"type":"Point"}
}