{
  "type": "Feature",
  "properties": {
    "iso:country":"US",
    "sg:address":"7754 S Jackson Cir",
    "sg:city":"Centennial",
    "sg:classifiers":[
        {
            "category":"Shopping",
            "subcategory":"Gifts & Souvenirs",
            "type":"Retail Goods"
        }
    ],
    "sg:phone":"+1 303 770 2461",
    "sg:postcode":"80122",
    "sg:province":"CO",
    "sg:tags":[
        "basket",
        "parcel"
    ],
    "sg:website":"www.basketsbymaggie.com",
    "wof:name":"Beautiful Baskets By Maggie",
    "wof:placetype":"venue"
},
  "geometry": {"coordinates":[-104.946707,39.575294],"type":"Point"}
}