{
  "type": "Feature",
  "properties": {
    "addr:full":"2510 S Meade St Denver CO 80219",
    "addr:housenumber":"2510",
    "addr:postcode":"80219",
    "addr:street":"S Meade St",
    "iso:country":"US",
    "sg:address":"2510 S Meade St",
    "sg:city":"Denver",
    "sg:classifiers":[
        {
            "category":"Building & Trades",
            "subcategory":"Construction",
            "type":"Services"
        }
    ],
    "sg:phone":"+1 303 936 9944",
    "sg:postcode":"80219",
    "sg:province":"CO",
    "sg:tags":[
        "floor",
        "laying",
        "contractor"
    ],
    "wof:name":"First Class Flooring",
    "wof:placetype":"venue"
},
  "geometry": {"coordinates":[-105.03582,39.670526],"type":"Point"}
}