{
  "type": "Feature",
  "properties": {
    "addr:full":"1130 Navajo Pl Berthoud CO 80513",
    "addr:housenumber":"1130",
    "addr:postcode":"80513",
    "addr:street":"Navajo Pl",
    "iso:country":"US",
    "sg:address":"1130 Navajo Pl",
    "sg:city":"Berthoud",
    "sg:classifiers":[
        {
            "category":"Professional",
            "subcategory":"Engineering",
            "type":"Services"
        }
    ],
    "sg:phone":"+1 970 532 2109",
    "sg:postcode":"80513",
    "sg:province":"CO",
    "sg:tags":[
        "water",
        "treatment",
        "engineer"
    ],
    "wof:name":"Sterkel Operations",
    "wof:placetype":"venue"
},
  "geometry": {"coordinates":[-105.090965,40.29921],"type":"Point"}
}