{
  "type": "Feature",
  "properties": {
    "iso:country":"US",
    "sg:address":"1308 Oldfield St",
    "sg:city":"Castle Rock",
    "sg:classifiers":[
        {
            "category":"Building & Trades",
            "subcategory":"Electrical",
            "type":"Services"
        }
    ],
    "sg:phone":"+1 303 688 6638",
    "sg:postcode":"80104",
    "sg:province":"CO",
    "sg:tags":[
        "electrical",
        "electric",
        "contractor"
    ],
    "wof:name":"4 Way Electric",
    "wof:placetype":"venue"
},
  "geometry": {"coordinates":[-104.800526,39.358545],"type":"Point"}
}