{
  "type": "Feature",
  "properties": {
    "iso:country":"US",
    "sg:address":"2504 Zeppelin Rd",
    "sg:city":"Colorado Springs",
    "sg:classifiers":[
        {
            "category":"Manufacturing",
            "subcategory":"Metals",
            "type":"Manufacturing & Wholesale Goods"
        }
    ],
    "sg:phone":"+1 719 380 8009",
    "sg:postcode":"80916",
    "sg:province":"CO",
    "sg:tags":[
        "coating",
        "painting",
        "powder"
    ],
    "wof:name":"Compass Industrial Coating Inc",
    "wof:placetype":"venue"
},
  "geometry": {"coordinates":[-104.727465,38.795621],"type":"Point"}
}