{
  "type": "Feature",
  "properties": {
    "addr:full":"7051 Holly St Commerce City CO 80022",
    "addr:housenumber":"7051",
    "addr:postcode":"80022",
    "addr:street":"Holly St",
    "iso:country":"US",
    "sg:address":"7051 Holly St",
    "sg:city":"Commerce City",
    "sg:classifiers":[
        {
            "category":"Shopping",
            "subcategory":"Hobbies, Toys, & Games",
            "type":"Retail Goods"
        }
    ],
    "sg:phone":"+1 303 288 4507",
    "sg:postcode":"80022",
    "sg:province":"CO",
    "wof:name":"Tri-Chem Liquid Embroidery",
    "wof:placetype":"venue"
},
  "geometry": {"coordinates":[-104.922224,39.824584],"type":"Point"}
}