{
  "type": "Feature",
  "properties": {
    "iso:country":"US",
    "sg:address":"1515 7th Ave",
    "sg:city":"Greeley",
    "sg:classifiers":[
        {
            "category":"Real Estate",
            "subcategory":"Real Estate Operator",
            "type":"Services"
        }
    ],
    "sg:phone":"+1 970 356 6759",
    "sg:postcode":"80631",
    "sg:province":"CO",
    "sg:tags":[
        "apartment"
    ],
    "wof:name":"Ivanhoe Apartments",
    "wof:placetype":"venue"
},
  "geometry": {"coordinates":[-104.68914599999999,40.413737],"type":"Point"}
}