{
  "type": "Feature",
  "properties": {
    "iso:country":"US",
    "sg:address":"6254 Red Canyon Dr",
    "sg:city":"Littleton",
    "sg:classifiers":[
        {
            "category":"Local Transit",
            "type":"Transportation"
        }
    ],
    "sg:phone":"+1 303 471 5653",
    "sg:postcode":"80130",
    "sg:province":"CO",
    "sg:tags":[
        "passenger"
    ],
    "wof:name":"Premier Limousine Inc",
    "wof:placetype":"venue"
},
  "geometry": {"coordinates":[-104.912769,39.556632],"type":"Point"}
}