{
  "type": "Feature",
  "properties": {
    "addr:full":"2975 Walnut St Denver CO 80205",
    "addr:housenumber":"2975",
    "addr:postcode":"80205",
    "addr:street":"Walnut St",
    "iso:country":"US",
    "sg:address":"2975 Walnut St",
    "sg:city":"Denver",
    "sg:classifiers":[
        {
            "category":"Manufacturing",
            "subcategory":"Printing",
            "type":"Manufacturing & Wholesale Goods"
        }
    ],
    "sg:phone":"+1 303 691 0273",
    "sg:postcode":"80205",
    "sg:province":"CO",
    "sg:tags":[
        "publisher"
    ],
    "wof:name":"Mc Leod USA Yellow Book",
    "wof:placetype":"venue"
},
  "geometry": {"coordinates":[-104.98219899999999,39.762311],"type":"Point"}
}