{
  "type": "Feature",
  "properties": {
    "addr:full":"6560 Quarter Circle Rd Colorado Springs CO 80922",
    "addr:housenumber":"6560",
    "addr:postcode":"80922",
    "addr:street":"Quarter Circle Rd",
    "iso:country":"US",
    "sg:address":"6560 Quarter Circle Rd",
    "sg:city":"Colorado Springs",
    "sg:classifiers":[
        {
            "category":"Professional",
            "type":"Services"
        }
    ],
    "sg:phone":"+1 719 574 2329",
    "sg:postcode":"80922",
    "sg:province":"CO",
    "wof:name":"Kelly L Coan",
    "wof:placetype":"venue"
},
  "geometry": {"coordinates":[-104.705061,38.878167],"type":"Point"}
}