{
  "type": "Feature",
  "properties": {
    "addr:full":"3874 S Fraser St Aurora CO 80014",
    "addr:housenumber":"3874",
    "addr:postcode":"80014",
    "addr:street":"S Fraser St",
    "iso:country":"US",
    "sg:address":"3874 S Fraser St",
    "sg:city":"Aurora",
    "sg:classifiers":[
        {
            "category":"Building & Trades",
            "subcategory":"Construction",
            "type":"Services"
        }
    ],
    "sg:phone":"+1 303 680 2112",
    "sg:postcode":"80014",
    "sg:province":"CO",
    "sg:tags":[
        "floor",
        "laying",
        "contractor"
    ],
    "wof:name":"Karapitian Vadim",
    "wof:placetype":"venue"
},
  "geometry": {"coordinates":[-104.81092099999999,39.646773],"type":"Point"}
}