{
  "type": "Feature",
  "properties": {
    "iso:country":"US",
    "sg:address":"11725 Rd 27.3",
    "sg:city":"Dolores",
    "sg:classifiers":[
        {
            "category":"Food & Beverages",
            "subcategory":"Specialty",
            "type":"Retail Goods"
        }
    ],
    "sg:phone":"+1 970 799 0192",
    "sg:postcode":"81323",
    "sg:province":"CO",
    "sg:tags":[
        "tea",
        "coffee"
    ],
    "wof:name":"Magpie Coffeehouse",
    "wof:placetype":"venue"
},
  "geometry": {"coordinates":[-108.547763,37.38182],"type":"Point"}
}