{
  "type": "Feature",
  "properties": {
    "iso:country":"US",
    "sg:address":"8700 Santa Fe Dr",
    "sg:city":"Littleton",
    "sg:classifiers":[
        {
            "category":"Professional",
            "subcategory":"Business Services",
            "type":"Services"
        }
    ],
    "sg:phone":"+1 303 470 0776",
    "sg:postcode":"80125",
    "sg:province":"CO",
    "sg:tags":[
        "inspection"
    ],
    "wof:name":"Highlands Ranch Inspection",
    "wof:placetype":"venue"
},
  "geometry": {"coordinates":[-105.001242,39.49306],"type":"Point"}
}