{
  "type": "Feature",
  "properties": {
    "addr:full":"15975 W 5th Ave Golden CO 80401",
    "addr:housenumber":"15975",
    "addr:postcode":"80401",
    "addr:street":"W 5Th Ave",
    "iso:country":"US",
    "sg:address":"15975 W 5th Ave",
    "sg:city":"Golden",
    "sg:classifiers":[
        {
            "category":"Manufacturing",
            "subcategory":"Metals",
            "type":"Manufacturing & Wholesale Goods"
        }
    ],
    "sg:phone":"+1 303 278 4423",
    "sg:postcode":"80401",
    "sg:province":"CO",
    "wof:name":"Foothills Powder Coating Inc",
    "wof:placetype":"venue"
},
  "geometry": {"coordinates":[-105.179557,39.723202],"type":"Point"}
}