{
  "type": "Feature",
  "properties": {
    "iso:country":"US",
    "sg:address":"6225 W 48th Ave Unit 203",
    "sg:city":"Wheat Ridge",
    "sg:classifiers":[
        {
            "category":"Building & Trades",
            "subcategory":"Construction",
            "type":"Services"
        }
    ],
    "sg:phone":"+1 303 239 6597",
    "sg:postcode":"80033",
    "sg:province":"CO",
    "sg:tags":[
        "painter"
    ],
    "wof:name":"Custom Painting & Remodeling Inc",
    "wof:placetype":"venue"
},
  "geometry": {"coordinates":[-105.066099,39.785004],"type":"Point"}
}