{
  "type": "Feature",
  "properties": {
    "iso:country":"US",
    "sg:address":"1220 Devereux Rd",
    "sg:city":"Glenwood Springs",
    "sg:classifiers":[
        {
            "category":"Wholesale",
            "subcategory":"Groceries",
            "type":"Manufacturing & Wholesale Goods"
        }
    ],
    "sg:phone":"+1 970 945 2434",
    "sg:postcode":"81601",
    "sg:province":"CO",
    "sg:tags":[
        "juice",
        "fruit"
    ],
    "wof:name":"Coca-Cola Swire Pacific",
    "wof:placetype":"venue"
},
  "geometry": {"coordinates":[-107.33827700000001,39.555603],"type":"Point"}
}