{
  "type": "Feature",
  "properties": {
    "addr:full":"1433 17th St Denver CO 80202",
    "addr:housenumber":"1433",
    "addr:postcode":"80202",
    "addr:street":"17Th St",
    "iso:country":"US",
    "sg:address":"1433 17th St",
    "sg:city":"Denver",
    "sg:classifiers":[
        {
            "category":"Mining & Drilling",
            "type":"Manufacturing & Wholesale Goods"
        }
    ],
    "sg:phone":"+1 303 292 2442",
    "sg:postcode":"80202",
    "sg:province":"CO",
    "sg:tags":[
        "development",
        "gas",
        "oil",
        "exploration"
    ],
    "wof:name":"Freedom Energy",
    "wof:placetype":"venue"
},
  "geometry": {"coordinates":[-104.997651,39.751312],"type":"Point"}
}