{
  "type": "Feature",
  "properties": {
    "iso:country":"US",
    "sg:address":"755 S Perry Street",
    "sg:city":"Castle Rock",
    "sg:classifiers":[
        {
            "category":"Health Services",
            "subcategory":"Doctor",
            "type":"Services"
        }
    ],
    "sg:phone":"+1 303 814 1082",
    "sg:postcode":"80104",
    "sg:province":"CO",
    "wof:name":"O'rourke Jeannie DPM PC",
    "wof:placetype":"venue"
},
  "geometry": {"coordinates":[-104.861607,39.363459],"type":"Point"}
}