{
  "type": "Feature",
  "properties": {
    "iso:country":"US",
    "sg:address":"6300 S Syracuse Way",
    "sg:city":"Englewood",
    "sg:classifiers":[
        {
            "category":"Manufacturing",
            "subcategory":"Chemicals & Compounds",
            "type":"Manufacturing & Wholesale Goods"
        }
    ],
    "sg:phone":"+1 303 488 0084",
    "sg:postcode":"80111",
    "sg:province":"CO",
    "sg:tags":[
        "preparation",
        "pharmaceutical",
        "mfg"
    ],
    "wof:name":"Bristol-Myers Squibb",
    "wof:placetype":"venue"
},
  "geometry": {"coordinates":[-104.899496,39.599795],"type":"Point"}
}