{
  "type": "Feature",
  "properties": {
    "addr:full":"2616 Sedona Hills Ct Loveland CO 80537",
    "addr:housenumber":"2616",
    "addr:postcode":"80537",
    "addr:street":"Sedona Hills Ct",
    "iso:country":"US",
    "sg:address":"2616 Sedona Hills Ct",
    "sg:city":"Loveland",
    "sg:classifiers":[
        {
            "category":"Professional",
            "subcategory":"Art Services",
            "type":"Services"
        }
    ],
    "sg:phone":"+1 970 461 5864",
    "sg:postcode":"80537",
    "sg:province":"CO",
    "sg:tags":[
        "photographer"
    ],
    "wof:name":"Rod Walker Photography",
    "wof:placetype":"venue"
},
  "geometry": {"coordinates":[-105.197495,40.365735],"type":"Point"}
}