{
  "type": "Feature",
  "properties": {
    "addr:full":"1018 Whispering Oak Dr Castle Rock CO 80104",
    "addr:housenumber":"1018",
    "addr:postcode":"80104",
    "addr:street":"Whispering Oak Dr",
    "iso:country":"US",
    "sg:address":"1018 Whispering Oak Dr",
    "sg:city":"Castle Rock",
    "sg:classifiers":[
        {
            "category":"Manufacturing",
            "subcategory":"Apparel",
            "type":"Manufacturing & Wholesale Goods"
        }
    ],
    "sg:phone":"+1 303 688 0475",
    "sg:postcode":"80104",
    "sg:province":"CO",
    "sg:tags":[
        "commercial",
        "embroidery",
        "custom"
    ],
    "wof:name":"F W Embroidery",
    "wof:placetype":"venue"
},
  "geometry": {"coordinates":[-104.851882,39.390418],"type":"Point"}
}