{
  "type": "Feature",
  "properties": {
    "addr:full":"363 W 2nd St Wray CO 80758",
    "addr:housenumber":"363",
    "addr:postcode":"80758",
    "addr:street":"W 2Nd St",
    "iso:country":"US",
    "sg:address":"363 W 2nd St",
    "sg:city":"Wray",
    "sg:classifiers":[
        {
            "category":"Banks & Credit Unions",
            "subcategory":"Bank",
            "type":"Services"
        }
    ],
    "sg:phone":"+1 970 332 4111",
    "sg:postcode":"80758",
    "sg:province":"CO",
    "sg:website":"www.wraystatebank.com",
    "wof:name":"WRAY State Bank",
    "wof:placetype":"venue"
},
  "geometry": {"coordinates":[-102.22393700000001,40.079976],"type":"Point"}
}