{
  "type": "Feature",
  "properties": {
    "iso:country":"US",
    "sg:address":"7730 State Hwy 7",
    "sg:city":"Estes Park",
    "sg:classifiers":[
        {
            "category":"Shopping",
            "subcategory":"Used Merchandise",
            "type":"Retail Goods"
        }
    ],
    "sg:phone":"+1 970 586 2095",
    "sg:postcode":"80517",
    "sg:province":"CO",
    "sg:tags":[
        "antique"
    ],
    "wof:name":"Mountain Windfall Antiques",
    "wof:placetype":"venue"
},
  "geometry": {"coordinates":[-105.539974,40.268096],"type":"Point"}
}