{
  "type": "Feature",
  "properties": {
    "iso:country":"US",
    "sg:address":"924 Elkton Dr",
    "sg:city":"Colorado Springs",
    "sg:classifiers":[
        {
            "category":"Wholesale",
            "subcategory":"Electrical",
            "type":"Manufacturing & Wholesale Goods"
        }
    ],
    "sg:phone":"+1 719 388 4635",
    "sg:postcode":"80907",
    "sg:province":"CO",
    "sg:tags":[
        "electronic"
    ],
    "wof:name":"ADT Security Systems",
    "wof:placetype":"venue"
},
  "geometry": {"coordinates":[-104.844579,38.896866],"type":"Point"}
}