{
  "type": "Feature",
  "properties": {
    "addr:full":"1801 Lefthand Cir Longmont CO 80501",
    "addr:housenumber":"1801",
    "addr:postcode":"80501",
    "addr:street":"Lefthand Cir",
    "iso:country":"US",
    "sg:address":"1801 Lefthand Cir",
    "sg:city":"Longmont",
    "sg:classifiers":[
        {
            "category":"Sports & Exercise",
            "subcategory":"Gym",
            "type":"Entertainment"
        }
    ],
    "sg:phone":"+1 303 774 8888",
    "sg:postcode":"80501",
    "sg:province":"CO",
    "sg:tags":[
        "club",
        "health",
        "studio",
        "gymnasium"
    ],
    "wof:name":"Longmont Athletic Club",
    "wof:placetype":"venue"
},
  "geometry": {"coordinates":[-105.124709,40.140183],"type":"Point"}
}