{
  "type": "Feature",
  "properties": {
    "iso:country":"US",
    "sg:address":"1040 S Gaylord Street Suite 100",
    "sg:city":"Denver",
    "sg:classifiers":[
        {
            "category":"Health Services",
            "subcategory":"Chiropractor",
            "type":"Services"
        }
    ],
    "sg:phone":"+1 303 698 2225",
    "sg:postcode":"80209",
    "sg:province":"CO",
    "wof:name":"Chiropractique Etc",
    "wof:placetype":"venue"
},
  "geometry": {"coordinates":[-104.961556,39.697685],"type":"Point"}
}