{
  "type": "Feature",
  "properties": {
    "addr:full":"18730 E Hampden Ave Aurora CO 80013",
    "addr:housenumber":"18730",
    "addr:postcode":"80013",
    "addr:street":"E Hampden Ave",
    "iso:country":"US",
    "sg:address":"18730 E Hampden Ave",
    "sg:city":"Aurora",
    "sg:classifiers":[
        {
            "category":"Coffee & Tea",
            "type":"Food & Drink"
        }
    ],
    "sg:menulink":"http://www.allmenus.com/co/south-aurora/118143-starbucks-coffee/menu/",
    "sg:phone":"+1 720 876 2244",
    "sg:postcode":"80013",
    "sg:province":"CO",
    "sg:tags":[
        "american"
    ],
    "wof:name":"Starbucks Coffee",
    "wof:placetype":"venue"
},
  "geometry": {"coordinates":[-104.769751,39.651565],"type":"Point"}
}