{
  "type": "Feature",
  "properties": {
    "iso:country":"US",
    "sg:address":"18888 E Saratoga Cir",
    "sg:city":"Aurora",
    "sg:classifiers":[
        {
            "category":"Freight",
            "type":"Transportation"
        }
    ],
    "sg:phone":"+1 303 617 1313",
    "sg:postcode":"80015",
    "sg:province":"CO",
    "sg:tags":[
        "operator",
        "local",
        "trucking"
    ],
    "wof:name":"Merry Estimates",
    "wof:placetype":"venue"
},
  "geometry": {"coordinates":[-104.76904500000001,39.62834],"type":"Point"}
}