{
  "type": "Feature",
  "properties": {
    "iso:country":"US",
    "sg:address":"11423 Washington St",
    "sg:city":"Denver",
    "sg:classifiers":[
        {
            "category":"Food & Beverages",
            "subcategory":"Liquor & Beverages",
            "type":"Retail Goods"
        }
    ],
    "sg:phone":"+1 303 451 5265",
    "sg:postcode":"80233",
    "sg:province":"CO",
    "sg:tags":[
        "alcoholic"
    ],
    "wof:name":"D L Discount Liquors",
    "wof:placetype":"venue"
},
  "geometry": {"coordinates":[-104.977863,39.904537],"type":"Point"}
}