{
  "type": "Feature",
  "properties": {
    "addr:full":"32 N 7th Ave Brighton CO 80601",
    "addr:housenumber":"32",
    "addr:postcode":"80601",
    "addr:street":"N 7Th Ave",
    "iso:country":"US",
    "sg:address":"32 N 7th Ave",
    "sg:city":"Brighton",
    "sg:classifiers":[
        {
            "category":"Retail",
            "subcategory":"Repair Shop",
            "type":"Services"
        }
    ],
    "sg:phone":"+1 303 659 0806",
    "sg:postcode":"80601",
    "sg:province":"CO",
    "sg:tags":[
        "plumbing",
        "drain",
        "cleaning",
        "sewer"
    ],
    "wof:name":"Adams County Sewer Svc",
    "wof:placetype":"venue"
},
  "geometry": {"coordinates":[-104.814009,39.987139],"type":"Point"}
}