{
  "type": "Feature",
  "properties": {
    "addr:full":"777 Steamboat Blvd Steamboat Spgs CO 80487",
    "addr:housenumber":"777",
    "addr:postcode":"80487",
    "addr:street":"Steamboat Blvd;Spgs",
    "iso:country":"US",
    "sg:address":"777 Steamboat Blvd",
    "sg:city":"Steamboat Spgs",
    "sg:classifiers":[
        {
            "category":"Autos & Motor Vehicles",
            "subcategory":"Auto Supplies",
            "type":"Retail Goods"
        }
    ],
    "sg:phone":"+1 970 879 1881",
    "sg:postcode":"80487",
    "sg:province":"CO",
    "sg:tags":[
        "four",
        "wheel",
        "drive",
        "accessory"
    ],
    "wof:name":"Ultimate Jeep",
    "wof:placetype":"venue"
},
  "geometry": {"coordinates":[-106.78883399999999,40.474404],"type":"Point"}
}