{
  "type": "Feature",
  "properties": {
    "iso:country":"US",
    "sg:address":"1805 Westmoreland Rd",
    "sg:city":"Colorado Springs",
    "sg:classifiers":[
        {
            "category":"Banks & Credit Unions",
            "subcategory":"Financial Services",
            "type":"Services"
        }
    ],
    "sg:phone":"+1 719 265 8825",
    "sg:postcode":"80907",
    "sg:province":"CO",
    "sg:tags":[
        "investor"
    ],
    "wof:name":"Harmony Investments",
    "wof:placetype":"venue"
},
  "geometry": {"coordinates":[-104.792681,38.886444],"type":"Point"}
}