{
  "type": "Feature",
  "properties": {
    "addr:full":"15325 State Hwy 14 Sterling CO 80751",
    "addr:housenumber":"15325",
    "addr:postcode":"80751",
    "addr:street":"State Hwy 14",
    "iso:country":"US",
    "sg:address":"15325 State Hwy 14",
    "sg:city":"Sterling",
    "sg:classifiers":[
        {
            "category":"Building & Trades",
            "subcategory":"Electrical",
            "type":"Services"
        }
    ],
    "sg:phone":"+1 970 522 1734",
    "sg:postcode":"80751",
    "sg:province":"CO",
    "sg:tags":[
        "electrical",
        "electric",
        "contractor"
    ],
    "wof:name":"Sterling Electrical Services",
    "wof:placetype":"venue"
},
  "geometry": {"coordinates":[-103.29409099999999,40.623908],"type":"Point"}
}