{
  "type": "Feature",
  "properties": {
    "iso:country":"US",
    "sg:address":"142 6th St",
    "sg:city":"Frederick",
    "sg:classifiers":[
        {
            "category":"Shopping",
            "subcategory":"Bicycles & Sporting Goods",
            "type":"Retail Goods"
        }
    ],
    "sg:phone":"+1 303 833 4160",
    "sg:postcode":"80530",
    "sg:province":"CO",
    "wof:name":"Shalom Bikes",
    "wof:placetype":"venue"
},
  "geometry": {"coordinates":[-104.940855,40.097681],"type":"Point"}
}