{
  "type": "Feature",
  "properties": {
    "addr:full":"200 S Hwy 13 Craig CO 81625",
    "addr:housenumber":"200",
    "addr:postcode":"81625",
    "addr:street":"S Hwy 13",
    "iso:country":"US",
    "sg:address":"200 S Hwy 13",
    "sg:city":"Craig",
    "sg:classifiers":[
        {
            "category":"Travel",
            "subcategory":"Hotels & Motels",
            "type":"Entertainment"
        }
    ],
    "sg:phone":"+1 970 824 3471",
    "sg:postcode":"81625",
    "sg:province":"CO",
    "sg:website":"www.super8.com",
    "wof:name":"Super 8 Motel",
    "wof:placetype":"venue"
},
  "geometry": {"coordinates":[-107.79880300000001,40.229496],"type":"Point"}
}