{
  "type": "Feature",
  "properties": {
    "addr:full":"2046 Market Denver CO 80205",
    "addr:housenumber":"2046",
    "addr:postcode":"80205",
    "iso:country":"US",
    "sg:address":"2046 Market",
    "sg:city":"Denver",
    "sg:classifiers":[
        {
            "category":"Ice Cream",
            "type":"Food & Drink"
        }
    ],
    "sg:postcode":"80205",
    "sg:province":"CO",
    "sg:tags":[
        "frozen",
        "yogurt"
    ],
    "wof:name":"Sorbeteria",
    "wof:placetype":"venue"
},
  "geometry": {"coordinates":[-104.992862,39.754069],"type":"Point"}
}