{
  "type": "Feature",
  "properties": {
    "iso:country":"US",
    "sg:address":"2025 E 4th Avenue",
    "sg:city":"Denver",
    "sg:classifiers":[
        {
            "category":"Shopping",
            "subcategory":"Clothing, Apparel, & Fashions",
            "type":"Retail Goods"
        }
    ],
    "sg:phone":"+1 303 399 6607",
    "sg:postcode":"80206",
    "sg:province":"CO",
    "sg:tags":[
        "clothing",
        "women's"
    ],
    "wof:name":"Union Handbags",
    "wof:placetype":"venue"
},
  "geometry": {"coordinates":[-104.962896,39.722658],"type":"Point"}
}