{
  "type": "Feature",
  "properties": {
    "iso:country":"US",
    "sg:address":"56 Park Ave",
    "sg:city":"Manitou Springs",
    "sg:classifiers":[
        {
            "category":"Food & Beverages",
            "subcategory":"Specialty",
            "type":"Retail Goods"
        }
    ],
    "sg:phone":"+1 719 685 5434",
    "sg:postcode":"80829",
    "sg:province":"CO",
    "sg:tags":[
        "health",
        "market"
    ],
    "wof:name":"Manitou Natural Foods",
    "wof:placetype":"venue"
},
  "geometry": {"coordinates":[-104.91999800000001,38.8605],"type":"Point"}
}