{
  "type": "Feature",
  "properties": {
    "addr:full":"7533 S Gartner Rd Evergreen CO 80439",
    "addr:housenumber":"7533",
    "addr:postcode":"80439",
    "addr:street":"S Gartner Rd",
    "iso:country":"US",
    "sg:address":"7533 S Gartner Rd",
    "sg:city":"Evergreen",
    "sg:classifiers":[
        {
            "category":"Real Estate",
            "subcategory":"Surveying",
            "type":"Services"
        }
    ],
    "sg:phone":"+1 303 670 8604",
    "sg:postcode":"80439",
    "sg:province":"CO",
    "sg:tags":[
        "surveyor"
    ],
    "wof:name":"Guffey Survey Consultants",
    "wof:placetype":"venue"
},
  "geometry": {"coordinates":[-105.283187,39.580554],"type":"Point"}
}