{
  "type": "Feature",
  "properties": {
    "iso:country":"US",
    "sg:address":"474 State Hwy 71",
    "sg:city":"Limon",
    "sg:classifiers":[
        {
            "category":"Retail",
            "subcategory":"Auto Repair",
            "type":"Services"
        }
    ],
    "sg:phone":"+1 719 775 9087",
    "sg:postcode":"80828",
    "sg:province":"CO",
    "sg:tags":[
        "repairing",
        "automobile"
    ],
    "wof:name":"Tri County Automotive",
    "wof:placetype":"venue"
},
  "geometry": {"coordinates":[-103.67729199999999,39.264592],"type":"Point"}
}