{
  "type": "Feature",
  "properties": {
    "iso:country":"US",
    "sg:address":"2428 Grove St",
    "sg:city":"Denver",
    "sg:classifiers":[
        {
            "category":"Professional",
            "type":"Services"
        }
    ],
    "sg:phone":"+1 303 433 4799",
    "sg:postcode":"80211",
    "sg:province":"CO",
    "wof:name":"Robert S Quicke",
    "wof:placetype":"venue"
},
  "geometry": {"coordinates":[-105.02675000000001,39.753277],"type":"Point"}
}