{
  "type": "Feature",
  "properties": {
    "addr:full":"8360 Auburn Ln Westminster CO 80031",
    "addr:housenumber":"8360",
    "addr:postcode":"80031",
    "addr:street":"Auburn Ln",
    "iso:country":"US",
    "sg:address":"8360 Auburn Ln",
    "sg:city":"Westminster",
    "sg:classifiers":[
        {
            "category":"Retail",
            "subcategory":"Repair Shop",
            "type":"Services"
        }
    ],
    "sg:phone":"+1 303 429 7462",
    "sg:postcode":"80031",
    "sg:province":"CO",
    "sg:tags":[
        "appliance"
    ],
    "wof:name":"Appliance Doctor",
    "wof:placetype":"venue"
},
  "geometry": {"coordinates":[-105.040633,39.845446],"type":"Point"}
}