{
  "type": "Feature",
  "properties": {
    "iso:country":"US",
    "sg:address":"3870 Gypsum Creek Rd",
    "sg:city":"Gypsum",
    "sg:classifiers":[
        {
            "category":"Building & Trades",
            "subcategory":"Construction",
            "type":"Services"
        }
    ],
    "sg:phone":"+1 970 524 9585",
    "sg:postcode":"81637",
    "sg:province":"CO",
    "sg:tags":[
        "contractor"
    ],
    "wof:name":"Cornerstone Masonry",
    "wof:placetype":"venue"
},
  "geometry": {"coordinates":[-106.951678,39.56512],"type":"Point"}
}