{
  "type": "Feature",
  "properties": {
    "addr:full":"4221 Brighton Boulevard Denver CO 80216",
    "addr:housenumber":"4221",
    "addr:postcode":"80216",
    "addr:street":"Brighton Boulevard",
    "iso:country":"US",
    "sg:address":"4221 Brighton Boulevard",
    "sg:city":"Denver",
    "sg:classifiers":[
        {
            "category":"Building & Trades",
            "subcategory":"Plumbing",
            "type":"Services"
        },
        {
            "category":"Wholesale",
            "subcategory":"Construction Materials",
            "type":"Manufacturing & Wholesale Goods"
        },
        {
            "category":"Wholesale",
            "subcategory":"Home Furnishings",
            "type":"Manufacturing & Wholesale Goods"
        }
    ],
    "sg:phone":"+1 303 293 8012",
    "sg:postcode":"80216",
    "sg:province":"CO",
    "sg:tags":[
        "supply",
        "fixture",
        "heating",
        "systems-wholesale",
        "equipment",
        "part",
        "fixtures",
        "supplies-wholesale",
        "manufacturer"
    ],
    "wof:name":"Performance Sales",
    "wof:placetype":"venue"
},
  "geometry": {"coordinates":[-104.971135,39.776328],"type":"Point"}
}