{
  "type": "Feature",
  "properties": {
    "iso:country":"US",
    "sg:address":"1866 Vine Street",
    "sg:city":"Denver",
    "sg:classifiers":[
        {
            "category":"Professional",
            "subcategory":"Lawyer & Legal Services",
            "type":"Services"
        }
    ],
    "sg:phone":"+1 303 398 4000",
    "sg:postcode":"80206",
    "sg:province":"CO",
    "wof:name":"Bryant Elizabeth A PC",
    "wof:placetype":"venue"
},
  "geometry": {"coordinates":[-104.962063,39.746203],"type":"Point"}
}