{
  "type": "Feature",
  "properties": {
    "addr:full":"2520 Aviation Way Colorado Springs CO 80916",
    "addr:housenumber":"2520",
    "addr:postcode":"80916",
    "addr:street":"Aviation Way",
    "iso:country":"US",
    "sg:address":"2520 Aviation Way",
    "sg:city":"Colorado Springs",
    "sg:classifiers":[
        {
            "category":"Airport",
            "type":"Transportation"
        }
    ],
    "sg:phone":"+1 719 573 7638",
    "sg:postcode":"80916",
    "sg:province":"CO",
    "sg:tags":[
        "freight",
        "arrange"
    ],
    "wof:name":"U P S Sup Chain Solutions Inc",
    "wof:placetype":"venue"
},
  "geometry": {"coordinates":[-104.72367199999999,38.795414],"type":"Point"}
}