{
  "type": "Feature",
  "properties": {
    "addr:full":"5000 Moline St Denver CO 80239",
    "addr:housenumber":"5000",
    "addr:postcode":"80239",
    "addr:street":"Moline St",
    "iso:country":"US",
    "sg:address":"5000 Moline St",
    "sg:city":"Denver",
    "sg:classifiers":[
        {
            "category":"Wholesale",
            "subcategory":"Books, Periodicals, & Newspapers",
            "type":"Manufacturing & Wholesale Goods"
        }
    ],
    "sg:phone":"+1 303 371 1833",
    "sg:postcode":"80239",
    "sg:province":"CO",
    "sg:tags":[
        "magazine"
    ],
    "sg:website":"www.andersonnews.com",
    "wof:name":"Anderson News Co",
    "wof:placetype":"venue"
},
  "geometry": {"coordinates":[-104.854797,39.789644],"type":"Point"}
}