{
  "type": "Feature",
  "properties": {
    "iso:country":"US",
    "sg:address":"1544 Race Street",
    "sg:city":"Denver",
    "sg:classifiers":[
        {
            "category":"Professional",
            "subcategory":"Lawyer & Legal Services",
            "type":"Services"
        }
    ],
    "sg:phone":"+1 303 393 1101",
    "sg:postcode":"80206",
    "sg:province":"CO",
    "wof:name":"Ward Thomas Attorney At Law",
    "wof:placetype":"venue"
},
  "geometry": {"coordinates":[-104.9633,39.74069],"type":"Point"}
}