{
  "type": "Feature",
  "properties": {
    "iso:country":"US",
    "sg:address":"177 N College Ave",
    "sg:city":"Fort Collins",
    "sg:classifiers":[
        {
            "category":"Shopping",
            "subcategory":"News",
            "type":"Retail Goods"
        }
    ],
    "sg:phone":"+1 970 482 9853",
    "sg:postcode":"80524",
    "sg:province":"CO",
    "sg:tags":[
        "magazine"
    ],
    "wof:name":"Al's Newstand",
    "wof:placetype":"venue"
},
  "geometry": {"coordinates":[-105.077093,40.58807],"type":"Point"}
}