{
  "type": "Feature",
  "properties": {
    "addr:full":"12025 Pecos St Denver CO 80234",
    "addr:housenumber":"12025",
    "addr:postcode":"80234",
    "addr:street":"Pecos St",
    "iso:country":"US",
    "sg:address":"12025 Pecos St",
    "sg:city":"Denver",
    "sg:classifiers":[
        {
            "category":"Professional",
            "type":"Services"
        }
    ],
    "sg:phone":"+1 303 451 8228",
    "sg:postcode":"80234",
    "sg:province":"CO",
    "wof:name":"Senor GS",
    "wof:placetype":"venue"
},
  "geometry": {"coordinates":[-105.006185,39.914493],"type":"Point"}
}