{
  "type": "Feature",
  "properties": {
    "iso:country":"US",
    "sg:address":"21 Deer Blvd",
    "sg:city":"Avon",
    "sg:classifiers":[
        {
            "category":"Building & Trades",
            "subcategory":"Electrical",
            "type":"Services"
        }
    ],
    "sg:phone":"+1 970 845 0188",
    "sg:postcode":"81620",
    "sg:province":"CO",
    "sg:tags":[
        "electric",
        "contractor"
    ],
    "wof:name":"A-Phase ELECTRIC LLC",
    "wof:placetype":"venue"
},
  "geometry": {"coordinates":[-106.490449,39.622291],"type":"Point"}
}