{
  "type": "Feature",
  "properties": {
    "iso:country":"US",
    "sg:address":"4430 Arapahoe Ave",
    "sg:city":"Boulder",
    "sg:classifiers":[
        {
            "category":"Banks & Credit Unions",
            "subcategory":"Bank",
            "type":"Services"
        }
    ],
    "sg:phone":"+1 303 417 1601",
    "sg:postcode":"80303",
    "sg:province":"CO",
    "sg:tags":[
        "financing"
    ],
    "wof:name":"Morgenthaler Ventures",
    "wof:placetype":"venue"
},
  "geometry": {"coordinates":[-105.244851,40.014499],"type":"Point"}
}