{
  "type": "Feature",
  "properties": {
    "iso:country":"US",
    "sg:address":"1831 Lefthand Cir",
    "sg:city":"Longmont",
    "sg:classifiers":[
        {
            "category":"Professional",
            "subcategory":"Computer Services",
            "type":"Services"
        }
    ],
    "sg:phone":"+1 303 651 1177",
    "sg:postcode":"80501",
    "sg:province":"CO",
    "wof:name":"Technology Integration Group",
    "wof:placetype":"venue"
},
  "geometry": {"coordinates":[-105.124724,40.141841],"type":"Point"}
}