{
  "type": "Feature",
  "properties": {
    "iso:country":"US",
    "sg:address":"2269 Commercial Blvd",
    "sg:city":"Colorado Springs",
    "sg:classifiers":[
        {
            "category":"Building & Trades",
            "subcategory":"Construction",
            "type":"Services"
        }
    ],
    "sg:phone":"+1 719 540 5299",
    "sg:postcode":"80906",
    "sg:province":"CO",
    "sg:tags":[
        "excavating",
        "contractor"
    ],
    "wof:name":"Steve Firebaugh Excavating",
    "wof:placetype":"venue"
},
  "geometry": {"coordinates":[-104.800574,38.803183],"type":"Point"}
}