{
  "type": "Feature",
  "properties": {
    "iso:country":"US",
    "sg:address":"34343 Co Rd Pp",
    "sg:city":"Wiley",
    "sg:phone":"+1 719 829 4747",
    "sg:postcode":"81092",
    "sg:province":"CO",
    "sg:tags":[
        "farm",
        "field",
        "corn",
        "wheat",
        "crop"
    ],
    "wof:name":"RR Farms",
    "wof:placetype":"venue"
},
  "geometry": {"coordinates":[-102.768799,38.172197],"type":"Point"}
}