{
  "type": "Feature",
  "properties": {
    "iso:country":"US",
    "sg:address":"617 22nd St",
    "sg:city":"Denver",
    "sg:classifiers":[
        {
            "category":"Food & Beverages",
            "subcategory":"Groceries & Convenience Stores",
            "type":"Retail Goods"
        }
    ],
    "sg:phone":"+1 303 825 4133",
    "sg:postcode":"80205",
    "sg:province":"CO",
    "sg:tags":[
        "alcoholic"
    ],
    "wof:name":"Lemon Sisters Market",
    "wof:placetype":"venue"
},
  "geometry": {"coordinates":[-104.98476100000001,39.750731],"type":"Point"}
}