{
  "type": "Feature",
  "properties": {
    "iso:country":"US",
    "sg:address":"1240 E 5th Ave",
    "sg:city":"Longmont",
    "sg:classifiers":[
        {
            "category":"Restaurant",
            "type":"Food & Drink"
        }
    ],
    "sg:phone":"+1 303 772 6288",
    "sg:postcode":"80501",
    "sg:province":"CO",
    "sg:tags":[
        "eating"
    ],
    "wof:name":"La Mariposa Mexican Restaurant",
    "wof:placetype":"venue"
},
  "geometry": {"coordinates":[-105.070165,40.167094],"type":"Point"}
}