{
  "type": "Feature",
  "properties": {
    "iso:country":"US",
    "sg:address":"2805 N Prospect St",
    "sg:city":"Colorado Springs",
    "sg:classifiers":[
        {
            "category":"Professional",
            "type":"Services"
        }
    ],
    "sg:phone":"+1 719 473 8844",
    "sg:postcode":"80907",
    "sg:province":"CO",
    "sg:tags":[
        "establishment"
    ],
    "wof:name":"Cogitic Corp",
    "wof:placetype":"venue"
},
  "geometry": {"coordinates":[-104.811238,38.871054],"type":"Point"}
}