{
  "type": "Feature",
  "properties": {
    "addr:full":"1709 W Elizabeth St Fort Collins CO 80521",
    "addr:housenumber":"1709",
    "addr:postcode":"80521",
    "addr:street":"W Elizabeth St",
    "iso:country":"US",
    "sg:address":"1709 W Elizabeth St",
    "sg:city":"Fort Collins",
    "sg:classifiers":[
        {
            "category":"Organizations",
            "subcategory":"Religious Organization",
            "type":"Services"
        }
    ],
    "sg:phone":"+1 970 482 7214",
    "sg:postcode":"80521",
    "sg:province":"CO",
    "sg:tags":[
        "church"
    ],
    "wof:name":"Westminster Presbyterian Chr",
    "wof:placetype":"venue"
},
  "geometry": {"coordinates":[-105.10978799999999,40.574594],"type":"Point"}
}