{
  "type": "Feature",
  "properties": {
    "iso:country":"US",
    "sg:address":"6360 E 58th Ave",
    "sg:city":"Commerce City",
    "sg:classifiers":[
        {
            "category":"Food & Beverages",
            "subcategory":"Bakery",
            "type":"Retail Goods"
        },
        {
            "category":"Restaurant",
            "type":"Food & Drink"
        }
    ],
    "sg:phone":"+1 303 288 9115",
    "sg:postcode":"80022",
    "sg:province":"CO",
    "sg:tags":[
        "company",
        "bread"
    ],
    "wof:name":"Panera Bread",
    "wof:placetype":"venue"
},
  "geometry": {"coordinates":[-104.919077,39.801821],"type":"Point"}
}