{
  "type": "Feature",
  "properties": {
    "iso:country":"US",
    "sg:address":"345 S Lincoln Ave",
    "sg:city":"Steamboat Spgs",
    "sg:classifiers":[
        {
            "category":"Health Services",
            "subcategory":"Health Practitioner",
            "type":"Services"
        }
    ],
    "sg:phone":"+1 970 870 3484",
    "sg:postcode":"80487",
    "sg:province":"CO",
    "sg:tags":[
        "therapist",
        "physical"
    ],
    "wof:name":"Forever Fit Of Steamboat Spg",
    "wof:placetype":"venue"
},
  "geometry": {"coordinates":[-106.826517,40.477931],"type":"Point"}
}