{
  "type": "Feature",
  "properties": {
    "iso:country":"US",
    "sg:address":"2049 S Federal Boulevard",
    "sg:city":"Denver",
    "sg:classifiers":[
        {
            "category":"Restaurant",
            "type":"Food & Drink"
        }
    ],
    "sg:phone":"+1 303 936 3544",
    "sg:postcode":"80219",
    "sg:province":"CO",
    "wof:name":"Rico Pollo # 1",
    "wof:placetype":"venue"
},
  "geometry": {"coordinates":[-105.024862,39.679476],"type":"Point"}
}