{
  "type": "Feature",
  "properties": {
    "iso:country":"US",
    "sg:address":"1015 W Garden of the Gods Rd",
    "sg:city":"Colorado Springs",
    "sg:classifiers":[
        {
            "category":"Banks & Credit Unions",
            "subcategory":"Bank",
            "type":"Services"
        }
    ],
    "sg:phone":"+1 719 219 3592",
    "sg:postcode":"80907",
    "sg:province":"CO",
    "sg:tags":[
        "cashing",
        "check"
    ],
    "wof:name":"Checkmate Payday Loans",
    "wof:placetype":"venue"
},
  "geometry": {"coordinates":[-104.84360100000001,38.8966],"type":"Point"}
}