{
  "type": "Feature",
  "properties": {
    "addr:full":"2746 W Greens Dr Littleton CO 80123",
    "addr:housenumber":"2746",
    "addr:postcode":"80123",
    "addr:street":"W Greens Dr",
    "iso:country":"US",
    "sg:address":"2746 W Greens Dr",
    "sg:city":"Littleton",
    "sg:classifiers":[
        {
            "category":"Freight",
            "type":"Transportation"
        }
    ],
    "sg:phone":"+1 303 748 0460",
    "sg:postcode":"80123",
    "sg:province":"CO",
    "sg:tags":[
        "special"
    ],
    "wof:name":"Arapahoe Storage Inc",
    "wof:placetype":"venue"
},
  "geometry": {"coordinates":[-105.01955599999999,39.620464],"type":"Point"}
}