{
  "type": "Feature",
  "properties": {
    "addr:full":"3785 Kipling St Wheat Ridge CO 80033",
    "addr:housenumber":"3785",
    "addr:postcode":"80033",
    "addr:street":"Kipling St",
    "iso:country":"US",
    "sg:address":"3785 Kipling St",
    "sg:city":"Wheat Ridge",
    "sg:classifiers":[
        {
            "category":"Banks & Credit Unions",
            "subcategory":"Investment Brokerage",
            "type":"Services"
        }
    ],
    "sg:phone":"+1 303 940 1155",
    "sg:postcode":"80033",
    "sg:province":"CO",
    "sg:tags":[
        "advisory",
        "financial"
    ],
    "wof:name":"Dean Financial Corp",
    "wof:placetype":"venue"
},
  "geometry": {"coordinates":[-105.10973,39.765843],"type":"Point"}
}