{
  "type": "Feature",
  "properties": {
    "addr:full":"3215 S Broadway Englewood CO 80113",
    "addr:housenumber":"3215",
    "addr:postcode":"80113",
    "addr:street":"S Broadway",
    "iso:country":"US",
    "sg:address":"3215 S Broadway",
    "sg:city":"Englewood",
    "sg:classifiers":[
        {
            "category":"Autos & Motor Vehicles",
            "subcategory":"Automobile Sales",
            "type":"Retail Goods"
        }
    ],
    "sg:phone":"+1 303 788 0870",
    "sg:postcode":"80113",
    "sg:province":"CO",
    "sg:tags":[
        "car",
        "dealer"
    ],
    "wof:name":"Johnny's Auto Sales Inc",
    "wof:placetype":"venue"
},
  "geometry": {"coordinates":[-104.98766500000001,39.656701],"type":"Point"}
}