{
  "type": "Feature",
  "properties": {
    "addr:full":"3 Bandera Ct Pueblo CO 81005",
    "addr:housenumber":"3",
    "addr:postcode":"81005",
    "addr:street":"Bandera Ct",
    "iso:country":"US",
    "sg:address":"3 Bandera Ct",
    "sg:city":"Pueblo",
    "sg:classifiers":[
        {
            "category":"Professional",
            "subcategory":"Management & Consulting",
            "type":"Services"
        }
    ],
    "sg:phone":"+1 719 560 0556",
    "sg:postcode":"81005",
    "sg:province":"CO",
    "sg:tags":[
        "consultant",
        "business"
    ],
    "wof:name":"Marjorie A Smith Consulting",
    "wof:placetype":"venue"
},
  "geometry": {"coordinates":[-104.67806299999999,38.215589],"type":"Point"}
}