{
  "type": "Feature",
  "properties": {
    "addr:full":"11875 County Line Rd Elbert CO 80106",
    "addr:housenumber":"11875",
    "addr:postcode":"80106",
    "addr:street":"County Line Rd",
    "iso:country":"US",
    "sg:address":"11875 County Line Rd",
    "sg:city":"Elbert",
    "sg:classifiers":[
        {
            "category":"Farming",
            "subcategory":"Livestock Farm",
            "type":"Manufacturing & Wholesale Goods"
        }
    ],
    "sg:phone":"+1 719 495 2532",
    "sg:postcode":"80106",
    "sg:province":"CO",
    "sg:tags":[
        "feedlot",
        "field",
        "crop",
        "beef",
        "cattle"
    ],
    "wof:name":"Welty John",
    "wof:placetype":"venue"
},
  "geometry": {"coordinates":[-104.602603,39.129419],"type":"Point"}
}