{
  "type": "Feature",
  "properties": {
    "addr:full":"1908 Sage Dr Golden CO 80401",
    "addr:housenumber":"1908",
    "addr:postcode":"80401",
    "addr:street":"Sage Dr",
    "iso:country":"US",
    "sg:address":"1908 Sage Dr",
    "sg:city":"Golden",
    "sg:classifiers":[
        {
            "category":"Professional",
            "type":"Services"
        }
    ],
    "sg:phone":"+1 303 273 3950",
    "sg:postcode":"80401",
    "sg:province":"CO",
    "wof:name":"Mathew Jibson",
    "wof:placetype":"venue"
},
  "geometry": {"coordinates":[-105.22930100000001,39.744092],"type":"Point"}
}