{
  "type": "Feature",
  "properties": {
    "addr:full":"381 Main St Longmont CO 80501",
    "addr:housenumber":"381",
    "addr:postcode":"80501",
    "addr:street":"Main St",
    "iso:country":"US",
    "sg:address":"381 Main St",
    "sg:city":"Longmont",
    "sg:classifiers":[
        {
            "category":"Shopping",
            "type":"Retail Goods"
        }
    ],
    "sg:phone":"+1 303 774 9661",
    "sg:postcode":"80501",
    "sg:province":"CO",
    "sg:tags":[
        "department",
        "merchandise",
        "store"
    ],
    "wof:name":"Boulder Cnty C C Cins Cllctble",
    "wof:placetype":"venue"
},
  "geometry": {"coordinates":[-105.10259000000001,40.164267],"type":"Point"}
}