{
  "type": "Feature",
  "properties": {
    "iso:country":"US",
    "sg:address":"9700 W 8th Ave",
    "sg:city":"Lakewood",
    "sg:classifiers":[
        {
            "category":"Education",
            "subcategory":"School",
            "type":"Public Place"
        }
    ],
    "sg:phone":"+1 303 982 7096",
    "sg:postcode":"80215",
    "sg:province":"CO",
    "sg:website":"www.lhstiger.com",
    "wof:name":"Lakewood Senior High School",
    "wof:placetype":"venue"
},
  "geometry": {"coordinates":[-105.10494199999999,39.729265],"type":"Point"}
}