{
  "type": "Feature",
  "properties": {
    "addr:full":"409 Phelps St Sterling CO 80751",
    "addr:housenumber":"409",
    "addr:postcode":"80751",
    "addr:street":"Phelps St",
    "iso:country":"US",
    "sg:address":"409 Phelps St",
    "sg:city":"Sterling",
    "sg:classifiers":[
        {
            "category":"Professional",
            "type":"Services"
        },
        {
            "category":"Professional",
            "subcategory":"Computer Services",
            "type":"Services"
        }
    ],
    "sg:phone":"+1 970 522 7660",
    "sg:postcode":"80751",
    "sg:province":"CO",
    "wof:name":"Paul D Beintema",
    "wof:placetype":"venue"
},
  "geometry": {"coordinates":[-103.218159,40.622383],"type":"Point"}
}