{
  "type": "Feature",
  "properties": {
    "iso:country":"US",
    "sg:address":"3898 S Broadway",
    "sg:city":"Englewood",
    "sg:classifiers":[
        {
            "category":"Retail",
            "subcategory":"Auto Repair",
            "type":"Services"
        }
    ],
    "sg:phone":"+1 303 806 8634",
    "sg:postcode":"80113",
    "sg:province":"CO",
    "sg:tags":[
        "muffler",
        "exhaust",
        "system"
    ],
    "wof:name":"A A Performance Muffler & Brks",
    "wof:placetype":"venue"
},
  "geometry": {"coordinates":[-104.987708,39.647631],"type":"Point"}
}