{
  "type": "Feature",
  "properties": {
    "addr:full":"1490 S Pearl St Denver CO 80210",
    "addr:housenumber":"1490",
    "addr:postcode":"80210",
    "addr:street":"S Pearl St",
    "iso:country":"US",
    "sg:address":"1490 S Pearl St",
    "sg:city":"Denver",
    "sg:classifiers":[
        {
            "category":"Banks & Credit Unions",
            "subcategory":"Investment Brokerage",
            "type":"Services"
        }
    ],
    "sg:phone":"+1 303 744 8899",
    "sg:postcode":"80210",
    "sg:province":"CO",
    "sg:tags":[
        "consultant",
        "planning",
        "financial"
    ],
    "sg:website":"www.sindrich.com",
    "wof:name":"Sindrich & Assoc Inc",
    "wof:placetype":"venue"
},
  "geometry": {"coordinates":[-104.98036399999999,39.691018],"type":"Point"}
}