{
  "type": "Feature",
  "properties": {
    "addr:full":"103 Rose Ln Montrose CO 81401",
    "addr:housenumber":"103",
    "addr:postcode":"81401",
    "addr:street":"Rose Ln",
    "iso:country":"US",
    "sg:address":"103 Rose Ln",
    "sg:city":"Montrose",
    "sg:classifiers":[
        {
            "category":"Restaurant",
            "type":"Food & Drink"
        }
    ],
    "sg:phone":"+1 970 249 1961",
    "sg:postcode":"81401",
    "sg:province":"CO",
    "sg:tags":[
        "drinking",
        "eating"
    ],
    "wof:name":"Backwoods Inn",
    "wof:placetype":"venue"
},
  "geometry": {"coordinates":[-107.858991,38.486101],"type":"Point"}
}