{
  "type": "Feature",
  "properties": {
    "iso:country":"US",
    "sg:address":"3900 Nome St",
    "sg:city":"Denver",
    "sg:classifiers":[
        {
            "category":"Home & Garden",
            "subcategory":"Building Materials",
            "type":"Retail Goods"
        }
    ],
    "sg:phone":"+1 303 373 0651",
    "sg:postcode":"80239",
    "sg:province":"CO",
    "sg:tags":[
        "insulation",
        "heat"
    ],
    "sg:website":"www.ejbartells.com",
    "wof:name":"E J Bartells Co",
    "wof:placetype":"venue"
},
  "geometry": {"coordinates":[-104.851642,39.769835],"type":"Point"}
}