{
  "type": "Feature",
  "properties": {
    "addr:full":"41 Co Rd 27 Brighton CO 80603",
    "addr:housenumber":"41;27",
    "addr:postcode":"80603",
    "addr:street":"Co Rd",
    "iso:country":"US",
    "sg:address":"41 Co Rd 27",
    "sg:city":"Brighton",
    "sg:classifiers":[
        {
            "category":"Restaurant",
            "type":"Food & Drink"
        }
    ],
    "sg:phone":"+1 303 654 0532",
    "sg:postcode":"80603",
    "sg:province":"CO",
    "sg:tags":[
        "eating"
    ],
    "wof:name":"Big Daddy's",
    "wof:placetype":"venue"
},
  "geometry": {"coordinates":[-104.81665700000001,40.001006],"type":"Point"}
}