{
  "type": "Feature",
  "properties": {
    "addr:full":"10789 Bradford Rd Littleton CO 80127",
    "addr:housenumber":"10789",
    "addr:postcode":"80127",
    "addr:street":"Bradford Rd",
    "iso:country":"US",
    "sg:address":"10789 Bradford Rd",
    "sg:city":"Littleton",
    "sg:classifiers":[
        {
            "category":"Arena",
            "subcategory":"Sports Club",
            "type":"Entertainment"
        }
    ],
    "sg:phone":"+1 303 948 1510",
    "sg:postcode":"80127",
    "sg:province":"CO",
    "sg:tags":[
        "manager",
        "recruiter",
        "promoter"
    ],
    "sg:website":"www.prostaronline.com",
    "wof:name":"Pro Star",
    "wof:placetype":"venue"
},
  "geometry": {"coordinates":[-105.119742,39.568831],"type":"Point"}
}