{
  "type": "Feature",
  "properties": {
    "iso:country":"US",
    "sg:address":"810 12th St",
    "sg:city":"Greeley",
    "sg:classifiers":[
        {
            "category":"Social Services",
            "type":"Services"
        }
    ],
    "sg:phone":"+1 970 301 2286",
    "sg:postcode":"80631",
    "sg:province":"CO",
    "sg:tags":[
        "counselor",
        "marriage",
        "family"
    ],
    "wof:name":"Pamela Morrow",
    "wof:placetype":"venue"
},
  "geometry": {"coordinates":[-104.692526,40.419719],"type":"Point"}
}