{
  "type": "Feature",
  "properties": {
    "addr:full":"510 W Colfax Ave Denver CO 80204",
    "addr:housenumber":"510",
    "addr:postcode":"80204",
    "addr:street":"W Colfax Ave",
    "iso:country":"US",
    "sg:address":"510 W Colfax Ave",
    "sg:city":"Denver",
    "sg:classifiers":[
        {
            "category":"Retail",
            "subcategory":"Auto Repair",
            "type":"Services"
        }
    ],
    "sg:phone":"+1 303 825 1960",
    "sg:postcode":"80204",
    "sg:province":"CO",
    "sg:tags":[
        "body",
        "automobile",
        "painting"
    ],
    "wof:name":"A & K Auto Works Inc",
    "wof:placetype":"venue"
},
  "geometry": {"coordinates":[-104.99518,39.740069],"type":"Point"}
}