{
  "type": "Feature",
  "properties": {
    "addr:full":"2121 S Hudson St Denver CO 80222",
    "addr:housenumber":"2121",
    "addr:postcode":"80222",
    "addr:street":"S Hudson St",
    "iso:country":"US",
    "sg:address":"2121 S Hudson St",
    "sg:city":"Denver",
    "sg:classifiers":[
        {
            "category":"Building & Trades",
            "subcategory":"Electrical",
            "type":"Services"
        }
    ],
    "sg:phone":"+1 303 520 4000",
    "sg:postcode":"80222",
    "sg:province":"CO",
    "sg:tags":[
        "electrical",
        "contractor"
    ],
    "wof:name":"Nuno Electric LLC",
    "wof:placetype":"venue"
},
  "geometry": {"coordinates":[-104.923503,39.677018],"type":"Point"}
}