{
  "type": "Feature",
  "properties": {
    "iso:country":"US",
    "sg:address":"5777 E Evans Ave",
    "sg:city":"Denver",
    "sg:classifiers":[
        {
            "category":"Building & Trades",
            "subcategory":"Locksmith",
            "type":"Services"
        }
    ],
    "sg:phone":"+1 866 718 8993",
    "sg:postcode":"80222",
    "sg:province":"CO",
    "sg:tags":[
        "key"
    ],
    "wof:name":"Always Affective Available Emergency Locksmith",
    "wof:placetype":"venue"
},
  "geometry": {"coordinates":[-104.920143,39.678587],"type":"Point"}
}