{
  "type": "Feature",
  "properties": {
    "iso:country":"US",
    "sg:address":"1212 Mariposa St",
    "sg:city":"Denver",
    "sg:classifiers":[
        {
            "category":"Professional",
            "subcategory":"Employment Agencies",
            "type":"Services"
        }
    ],
    "sg:phone":"+1 720 946 2901",
    "sg:postcode":"80204",
    "sg:province":"CO",
    "wof:name":"Senior Community Service Employment Program",
    "wof:placetype":"venue"
},
  "geometry": {"coordinates":[-105.027,39.731899],"type":"Point"}
}