{
  "type": "Feature",
  "properties": {
    "addr:full":"5440 Roslyn St Denver CO 80216",
    "addr:housenumber":"5440",
    "addr:postcode":"80216",
    "addr:street":"Roslyn St",
    "iso:country":"US",
    "sg:address":"5440 Roslyn St",
    "sg:city":"Denver",
    "sg:classifiers":[
        {
            "category":"Government",
            "subcategory":"Office",
            "type":"Public Place"
        }
    ],
    "sg:phone":"+1 720 865 3900",
    "sg:postcode":"80216",
    "sg:province":"CO",
    "sg:tags":[
        "marking",
        "general",
        "maintenance",
        "parking"
    ],
    "wof:name":"Denver Public Works Dept",
    "wof:placetype":"venue"
},
  "geometry": {"coordinates":[-104.90145,39.795821],"type":"Point"}
}