{
  "type": "Feature",
  "properties": {
    "iso:country":"US",
    "sg:address":"7595 W Florida Ave",
    "sg:city":"Denver",
    "sg:classifiers":[
        {
            "category":"Shopping",
            "subcategory":"Hobbies, Toys, & Games",
            "type":"Retail Goods"
        },
        {
            "category":"Shopping",
            "subcategory":"Jewelry",
            "type":"Retail Goods"
        }
    ],
    "sg:phone":"+1 303 985 5559",
    "sg:postcode":"80232",
    "sg:province":"CO",
    "sg:tags":[
        "shop",
        "repair",
        "industrial",
        "rock"
    ],
    "wof:name":"Red & Green Minerals Inc",
    "wof:placetype":"venue"
},
  "geometry": {"coordinates":[-105.081152,39.689526],"type":"Point"}
}