{
  "type": "Feature",
  "properties": {
    "iso:country":"US",
    "sg:address":"1638 S Clarkson St",
    "sg:city":"Denver",
    "sg:classifiers":[
        {
            "category":"Insurance",
            "subcategory":"Insurance Agent",
            "type":"Services"
        }
    ],
    "sg:phone":"+1 303 777 2551",
    "sg:postcode":"80210",
    "sg:province":"CO",
    "wof:name":"Garden Street Financial Group",
    "wof:placetype":"venue"
},
  "geometry": {"coordinates":[-104.978033,39.68647],"type":"Point"}
}