{
  "type": "Feature",
  "properties": {
    "iso:country":"US",
    "sg:address":"12053 Comeapart Rd",
    "sg:city":"Peyton",
    "sg:classifiers":[
        {
            "category":"Professional",
            "subcategory":"Management & Consulting",
            "type":"Services"
        }
    ],
    "sg:phone":"+1 719 548 9507",
    "sg:postcode":"80831",
    "sg:province":"CO",
    "sg:tags":[
        "counselor",
        "public",
        "relations"
    ],
    "wof:name":"Bliss Communications",
    "wof:placetype":"venue"
},
  "geometry": {"coordinates":[-104.603066,38.94687],"type":"Point"}
}