{
  "type": "Feature",
  "properties": {
    "addr:full":"1560 Autopista Mall Lp Colorado Springs CO 80920",
    "addr:postcode":"1560;80920",
    "addr:street":"Autopista Mall",
    "iso:country":"US",
    "sg:address":"1560 Autopista Mall Lp",
    "sg:city":"Colorado Springs",
    "sg:classifiers":[
        {
            "category":"Autos & Motor Vehicles",
            "subcategory":"Automobile Sales",
            "type":"Retail Goods"
        }
    ],
    "sg:phone":"+1 719 867 6800",
    "sg:postcode":"80920",
    "sg:province":"CO",
    "sg:tags":[
        "car",
        "dealer"
    ],
    "wof:name":"Phil Long KIA",
    "wof:placetype":"venue"
},
  "geometry": {"coordinates":[-104.797725,38.953558],"type":"Point"}
}