{
  "type": "Feature",
  "properties": {
    "addr:full":"10686 N Co Rd 100 Center CO 81125",
    "addr:housenumber":"10686;100",
    "addr:postcode":"81125",
    "addr:street":"N Co Rd",
    "iso:country":"US",
    "sg:address":"10686 N Co Rd 100",
    "sg:city":"Center",
    "sg:classifiers":[
        {
            "category":"Farming",
            "subcategory":"Farm",
            "type":"Manufacturing & Wholesale Goods"
        }
    ],
    "sg:phone":"+1 719 754 2700",
    "sg:postcode":"81125",
    "sg:province":"CO",
    "sg:tags":[
        "primarily",
        "gen",
        "crop"
    ],
    "wof:name":"Entz Farms Shop",
    "wof:placetype":"venue"
},
  "geometry": {"coordinates":[-106.03858,37.730951],"type":"Point"}
}