{
  "type": "Feature",
  "properties": {
    "addr:full":"2300 Cavanaugh Rd Watkins CO 80137",
    "addr:housenumber":"2300",
    "addr:postcode":"80137",
    "addr:street":"Cavanaugh Rd",
    "iso:country":"US",
    "sg:address":"2300 Cavanaugh Rd",
    "sg:city":"Watkins",
    "sg:classifiers":[
        {
            "category":"Utilities",
            "subcategory":"Fuel Oil & Lpg",
            "type":"Services"
        }
    ],
    "sg:phone":"+1 303 644 5939",
    "sg:postcode":"80137",
    "sg:province":"CO",
    "sg:tags":[
        "firewood"
    ],
    "wof:name":"Jonesy's Woodyard",
    "wof:placetype":"venue"
},
  "geometry": {"coordinates":[-104.545793,39.753246],"type":"Point"}
}