{
  "type": "Feature",
  "properties": {
    "addr:full":"1360 2nd Street Rd Eaton CO 80615",
    "addr:housenumber":"1360",
    "addr:postcode":"80615",
    "addr:street":"2Nd Street Rd",
    "iso:country":"US",
    "sg:address":"1360 2nd Street Rd",
    "sg:city":"Eaton",
    "sg:classifiers":[
        {
            "category":"Farming",
            "subcategory":"Farm",
            "type":"Manufacturing & Wholesale Goods"
        }
    ],
    "sg:phone":"+1 970 454 2915",
    "sg:postcode":"80615",
    "sg:province":"CO",
    "sg:tags":[
        "crop",
        "general"
    ],
    "wof:name":"Brown Farms",
    "wof:placetype":"venue"
},
  "geometry": {"coordinates":[-104.728272,40.527904],"type":"Point"}
}