{
  "type": "Feature",
  "properties": {
    "addr:full":"2852 W Bowles Ave Littleton CO 80120",
    "addr:housenumber":"2852",
    "addr:postcode":"80120",
    "addr:street":"W Bowles Ave",
    "iso:country":"US",
    "sg:address":"2852 W Bowles Ave",
    "sg:city":"Littleton",
    "sg:classifiers":[
        {
            "category":"Restaurant",
            "type":"Food & Drink"
        }
    ],
    "sg:phone":"+1 303 738 9692",
    "sg:postcode":"80120",
    "sg:province":"CO",
    "wof:name":"Kahuna's Bar & Grill",
    "wof:placetype":"venue"
},
  "geometry": {"coordinates":[-105.024079,39.613126],"type":"Point"}
}