{
  "type": "Feature",
  "properties": {
    "addr:full":"242 Tall Spruce Cir Brighton CO 80601",
    "addr:housenumber":"242",
    "addr:postcode":"80601",
    "addr:street":"Tall Spruce Cir",
    "iso:country":"US",
    "sg:address":"242 Tall Spruce Cir",
    "sg:city":"Brighton",
    "sg:classifiers":[
        {
            "category":"Building & Trades",
            "subcategory":"Construction",
            "type":"Services"
        }
    ],
    "sg:phone":"+1 720 685 9682",
    "sg:postcode":"80601",
    "sg:province":"CO",
    "sg:tags":[
        "home",
        "builder"
    ],
    "sg:website":"www.beazer.com",
    "wof:name":"Beazer Homes",
    "wof:placetype":"venue"
},
  "geometry": {"coordinates":[-104.74368200000001,39.990829],"type":"Point"}
}