{
  "type": "Feature",
  "properties": {
    "iso:country":"US",
    "sg:address":"5725 Wells Fargo Dr",
    "sg:city":"Colorado Springs",
    "sg:classifiers":[
        {
            "category":"Wholesale",
            "subcategory":"Vending Machines",
            "type":"Manufacturing & Wholesale Goods"
        }
    ],
    "sg:phone":"+1 719 260 8298",
    "sg:postcode":"80918",
    "sg:province":"CO",
    "sg:tags":[
        "operator"
    ],
    "wof:name":"Gumballs Etc",
    "wof:placetype":"venue"
},
  "geometry": {"coordinates":[-104.74178000000001,38.915769],"type":"Point"}
}