{
  "type": "Feature",
  "properties": {
    "addr:full":"111 E 2nd St Leadville CO 80461",
    "addr:housenumber":"111",
    "addr:postcode":"80461",
    "addr:street":"E 2Nd St",
    "iso:country":"US",
    "sg:address":"111 E 2nd St",
    "sg:city":"Leadville",
    "sg:classifiers":[
        {
            "category":"Building & Trades",
            "subcategory":"Plumbing",
            "type":"Services"
        }
    ],
    "sg:phone":"+1 719 486 1167",
    "sg:postcode":"80461",
    "sg:province":"CO",
    "sg:tags":[
        "plumbing",
        "contractor"
    ],
    "wof:name":"State Street Enterprises",
    "wof:placetype":"venue"
},
  "geometry": {"coordinates":[-106.289546,39.245506],"type":"Point"}
}