{
  "type": "Feature",
  "properties": {
    "addr:full":"809 N Cascade Ave Colorado Springs CO 80903",
    "addr:housenumber":"809",
    "addr:postcode":"80903",
    "addr:street":"N Cascade Ave",
    "iso:country":"US",
    "sg:address":"809 N Cascade Ave",
    "sg:city":"Colorado Springs",
    "sg:classifiers":[
        {
            "category":"Professional",
            "subcategory":"Printing & Photocopies",
            "type":"Services"
        }
    ],
    "sg:phone":"+1 719 635 7111",
    "sg:postcode":"80903",
    "sg:province":"CO",
    "sg:tags":[
        "photocopying",
        "reporting"
    ],
    "wof:name":"Office Helpr Amrcn Secretarial",
    "wof:placetype":"venue"
},
  "geometry": {"coordinates":[-104.82446400000001,38.846457],"type":"Point"}
}