{
  "type": "Feature",
  "properties": {
    "iso:country":"US",
    "sg:address":"18407 E Crestridge Dr",
    "sg:city":"Aurora",
    "sg:classifiers":[
        {
            "category":"Professional",
            "type":"Services"
        }
    ],
    "sg:phone":"+1 303 617 1578",
    "sg:postcode":"80015",
    "sg:province":"CO",
    "wof:name":"GS Originals",
    "wof:placetype":"venue"
},
  "geometry": {"coordinates":[-104.77499899999999,39.61706],"type":"Point"}
}