{
  "type": "Feature",
  "properties": {
    "iso:country":"US",
    "sg:address":"2378 S Downing St",
    "sg:city":"Denver",
    "sg:classifiers":[
        {
            "category":"Shopping",
            "subcategory":"Clothing, Apparel, & Fashions",
            "type":"Retail Goods"
        }
    ],
    "sg:phone":"+1 303 744 7179",
    "sg:postcode":"80210",
    "sg:province":"CO",
    "sg:tags":[
        "wig",
        "toupee",
        "hairpiece",
        "w"
    ],
    "wof:name":"Linda's Boutique",
    "wof:placetype":"venue"
},
  "geometry": {"coordinates":[-104.973372,39.674528],"type":"Point"}
}