{
  "type": "Feature",
  "properties": {
    "iso:country":"US",
    "sg:address":"1915 Pearl St",
    "sg:city":"Boulder",
    "sg:classifiers":[
        {
            "category":"Shopping",
            "subcategory":"Florist",
            "type":"Retail Goods"
        }
    ],
    "sg:phone":"+1 303 381 1480",
    "sg:postcode":"80302",
    "sg:province":"CO",
    "wof:name":"Hw Home",
    "wof:placetype":"venue"
},
  "geometry": {"coordinates":[-105.269643,40.020016],"type":"Point"}
}