{
  "type": "Feature",
  "properties": {
    "addr:full":"9449 S Barnes Ave Conifer CO 80433",
    "addr:housenumber":"9449",
    "addr:postcode":"80433",
    "addr:street":"S Barnes Ave",
    "iso:country":"US",
    "sg:address":"9449 S Barnes Ave",
    "sg:city":"Conifer",
    "sg:classifiers":[
        {
            "category":"Education",
            "subcategory":"School",
            "type":"Public Place"
        }
    ],
    "sg:phone":"+1 303 982 3056",
    "sg:postcode":"80433",
    "sg:province":"CO",
    "wof:name":"West Jefferson Middle School",
    "wof:placetype":"venue"
},
  "geometry": {"coordinates":[-105.301874,39.544326],"type":"Point"}
}