{
  "type": "Feature",
  "properties": {
    "iso:country":"US",
    "sg:address":"321 Hy-Vu Dr",
    "sg:city":"Evergreen",
    "sg:classifiers":[
        {
            "category":"Banks & Credit Unions",
            "subcategory":"Financial Services",
            "type":"Services"
        }
    ],
    "sg:phone":"+1 303 674 2482",
    "sg:postcode":"80439",
    "sg:province":"CO",
    "sg:tags":[
        "investor"
    ],
    "wof:name":"Gw Capital Corp",
    "wof:placetype":"venue"
},
  "geometry": {"coordinates":[-105.41565300000001,39.713861],"type":"Point"}
}