{
  "type": "Feature",
  "properties": {
    "iso:country":"US",
    "sg:address":"12550 Palomino Dr",
    "sg:city":"Calhan",
    "sg:classifiers":[
        {
            "category":"Shopping",
            "subcategory":"Crafts & Fabrics",
            "type":"Retail Goods"
        }
    ],
    "sg:phone":"+1 719 347 0216",
    "sg:postcode":"80808",
    "sg:province":"CO",
    "sg:tags":[
        "sewing"
    ],
    "wof:name":"Mark C Yarns",
    "wof:placetype":"venue"
},
  "geometry": {"coordinates":[-104.378692,39.014072],"type":"Point"}
}