{
  "type": "Feature",
  "properties": {
    "addr:full":"700 Longs Peak Ave Longmont CO 80501",
    "addr:housenumber":"700",
    "addr:postcode":"80501",
    "addr:street":"Longs Peak Ave",
    "iso:country":"US",
    "sg:address":"700 Longs Peak Ave",
    "sg:city":"Longmont",
    "sg:classifiers":[
        {
            "category":"Building & Trades",
            "subcategory":"Construction",
            "type":"Services"
        }
    ],
    "sg:phone":"+1 303 776 3210",
    "sg:postcode":"80501",
    "sg:province":"CO",
    "sg:tags":[
        "company"
    ],
    "wof:name":"Golden Triangle Construction",
    "wof:placetype":"venue"
},
  "geometry": {"coordinates":[-105.105155,40.170671],"type":"Point"}
}