{
  "type": "Feature",
  "properties": {
    "iso:country":"US",
    "sg:address":"2412 W Saint Vrain St",
    "sg:city":"Colorado Springs",
    "sg:classifiers":[
        {
            "category":"Retail",
            "subcategory":"Repair Shop",
            "type":"Services"
        }
    ],
    "sg:phone":"+1 719 473 7749",
    "sg:postcode":"80904",
    "sg:province":"CO",
    "sg:tags":[
        "lighting",
        "fixture"
    ],
    "wof:name":"Riter & Riter",
    "wof:placetype":"venue"
},
  "geometry": {"coordinates":[-104.85833599999999,38.851247],"type":"Point"}
}