{
  "type": "Feature",
  "properties": {
    "addr:full":"107 Cheesman St Erie CO 80516",
    "addr:housenumber":"107",
    "addr:postcode":"80516",
    "addr:street":"Cheesman St",
    "iso:country":"US",
    "sg:address":"107 Cheesman St",
    "sg:city":"Erie",
    "sg:classifiers":[
        {
            "category":"Autos & Motor Vehicles",
            "subcategory":"Automobile Sales",
            "type":"Retail Goods"
        }
    ],
    "sg:phone":"+1 303 828 4558",
    "sg:postcode":"80516",
    "sg:province":"CO",
    "sg:tags":[
        "equipment",
        "aircraft",
        "parts",
        "supply"
    ],
    "wof:name":"Pacific Aeromotive Corp",
    "wof:placetype":"venue"
},
  "geometry": {"coordinates":[-105.04612899999999,40.051622],"type":"Point"}
}