{
  "type": "Feature",
  "properties": {
    "addr:full":"1510 Hilltop Dr Loveland CO 80537",
    "addr:housenumber":"1510",
    "addr:postcode":"80537",
    "addr:street":"Hilltop Dr",
    "iso:country":"US",
    "sg:address":"1510 Hilltop Dr",
    "sg:city":"Loveland",
    "sg:classifiers":[
        {
            "category":"Personal",
            "subcategory":"Beauty Salon",
            "type":"Services"
        }
    ],
    "sg:phone":"+1 970 663 3639",
    "sg:postcode":"80537",
    "sg:province":"CO",
    "wof:name":"Karspeck Hair Design",
    "wof:placetype":"venue"
},
  "geometry": {"coordinates":[-105.10067100000001,40.403413],"type":"Point"}
}