{
  "type": "Feature",
  "properties": {
    "iso:country":"US",
    "sg:address":"7851 S Elati St",
    "sg:city":"Littleton",
    "sg:classifiers":[
        {
            "category":"Health Services",
            "subcategory":"Doctor",
            "type":"Services"
        }
    ],
    "sg:phone":"+1 720 497 6170",
    "sg:postcode":"80120",
    "sg:province":"CO",
    "sg:tags":[
        "physician",
        "surgeon"
    ],
    "sg:website":"www.panoramaortho.com",
    "wof:name":"Panorama Orthopedics",
    "wof:placetype":"venue"
},
  "geometry": {"coordinates":[-104.99777400000001,39.574232],"type":"Point"}
}