{
  "type": "Feature",
  "properties": {
    "addr:full":"2201 Hagerman St Colorado Springs CO 80904",
    "addr:housenumber":"2201",
    "addr:postcode":"80904",
    "addr:street":"Hagerman St",
    "iso:country":"US",
    "sg:address":"2201 Hagerman St",
    "sg:city":"Colorado Springs",
    "sg:classifiers":[
        {
            "category":"Professional",
            "type":"Services"
        }
    ],
    "sg:phone":"+1 719 632 3277",
    "sg:postcode":"80904",
    "sg:province":"CO",
    "sg:tags":[
        "establishment"
    ],
    "wof:name":"Jamie's English Connection",
    "wof:placetype":"venue"
},
  "geometry": {"coordinates":[-104.864569,38.840303],"type":"Point"}
}