{
  "type": "Feature",
  "properties": {
    "iso:country":"US",
    "sg:address":"8917 Cloverleaf Cir",
    "sg:city":"Parker",
    "sg:classifiers":[
        {
            "category":"Wholesale",
            "subcategory":"Hardware",
            "type":"Manufacturing & Wholesale Goods"
        }
    ],
    "sg:phone":"+1 303 400 8875",
    "sg:postcode":"80134",
    "sg:province":"CO",
    "sg:tags":[
        "industrial",
        "filtration",
        "commercial",
        "system",
        "broker",
        "water"
    ],
    "wof:name":"Conscious Consulting",
    "wof:placetype":"venue"
},
  "geometry": {"coordinates":[-104.794411,39.555594],"type":"Point"}
}