{
  "type": "Feature",
  "properties": {
    "addr:full":"1317 Fuller Rd Colorado Springs CO 80920",
    "addr:housenumber":"1317",
    "addr:postcode":"80920",
    "addr:street":"Fuller Rd",
    "iso:country":"US",
    "sg:address":"1317 Fuller Rd",
    "sg:city":"Colorado Springs",
    "sg:classifiers":[
        {
            "category":"Retail",
            "subcategory":"Laundry & Dry Cleaning",
            "type":"Services"
        }
    ],
    "sg:phone":"+1 719 548 8757",
    "sg:postcode":"80920",
    "sg:province":"CO",
    "sg:tags":[
        "cleaners",
        "rug",
        "carpet"
    ],
    "wof:name":"MAJIC Carpet MD",
    "wof:placetype":"venue"
},
  "geometry": {"coordinates":[-104.80177500000001,38.939469],"type":"Point"}
}