{
  "type": "Feature",
  "properties": {
    "iso:country":"US",
    "sg:address":"6251 S Iola Ct",
    "sg:city":"Englewood",
    "sg:classifiers":[
        {
            "category":"Real Estate",
            "subcategory":"Real Estate Agent",
            "type":"Services"
        }
    ],
    "sg:phone":"+1 303 946 0725",
    "sg:postcode":"80111",
    "sg:province":"CO",
    "wof:name":"Masterpiece Realty",
    "wof:placetype":"venue"
},
  "geometry": {"coordinates":[-104.86588500000001,39.601856],"type":"Point"}
}