{
  "type": "Feature",
  "properties": {
    "iso:country":"US",
    "sg:address":"1 S Walnut St",
    "sg:city":"Colorado Springs",
    "sg:classifiers":[
        {
            "category":"Organizations",
            "subcategory":"Religious Organization",
            "type":"Services"
        }
    ],
    "sg:phone":"+1 719 635 4865",
    "sg:postcode":"80905",
    "sg:province":"CO",
    "sg:tags":[
        "church"
    ],
    "wof:name":"Emmanuel Baptist Church",
    "wof:placetype":"venue"
},
  "geometry": {"coordinates":[-104.834337,38.832744],"type":"Point"}
}