{
  "type": "Feature",
  "properties": {
    "addr:full":"2310 Executive Cir Colorado Springs CO 80906",
    "addr:housenumber":"2310",
    "addr:postcode":"80906",
    "addr:street":"Executive Cir",
    "iso:country":"US",
    "sg:address":"2310 Executive Cir",
    "sg:city":"Colorado Springs",
    "sg:classifiers":[
        {
            "category":"Recreation",
            "type":"Entertainment"
        }
    ],
    "sg:phone":"+1 719 226 2255",
    "sg:postcode":"80906",
    "sg:province":"CO",
    "sg:tags":[
        "range",
        "baseball",
        "batting"
    ],
    "sg:website":"www.playatthebullpen.com",
    "wof:name":"Play At The Bullpen",
    "wof:placetype":"venue"
},
  "geometry": {"coordinates":[-104.785912,38.790441],"type":"Point"}
}