{
  "type": "Feature",
  "properties": {
    "iso:country":"US",
    "sg:address":"3945 Rosemere St",
    "sg:city":"Colorado Springs",
    "sg:classifiers":[
        {
            "category":"Professional",
            "type":"Services"
        }
    ],
    "sg:phone":"+1 719 576 1136",
    "sg:postcode":"80906",
    "sg:province":"CO",
    "wof:name":"Ruben Montijo",
    "wof:placetype":"venue"
},
  "geometry": {"coordinates":[-104.80165100000001,38.774497],"type":"Point"}
}