{
  "type": "Feature",
  "properties": {
    "iso:country":"US",
    "sg:address":"1445 S Argonne Cir",
    "sg:city":"Aurora",
    "sg:classifiers":[
        {
            "category":"Local Transit",
            "type":"Transportation"
        }
    ],
    "sg:phone":"+1 303 745 2140",
    "sg:postcode":"80017",
    "sg:province":"CO",
    "sg:tags":[
        "passenger",
        "bus"
    ],
    "wof:name":"Classic Charters",
    "wof:placetype":"venue"
},
  "geometry": {"coordinates":[-104.77072800000001,39.688745],"type":"Point"}
}