{
  "type": "Feature",
  "properties": {
    "iso:country":"US",
    "sg:address":"990 Hartford Dr",
    "sg:city":"Boulder",
    "sg:classifiers":[
        {
            "category":"Food & Beverages",
            "subcategory":"Specialty",
            "type":"Retail Goods"
        }
    ],
    "sg:phone":"+1 303 786 9117",
    "sg:postcode":"80305",
    "sg:province":"CO",
    "sg:tags":[
        "vitamin"
    ],
    "wof:name":"Coach Industries Inc USA",
    "wof:placetype":"venue"
},
  "geometry": {"coordinates":[-105.255726,39.979714],"type":"Point"}
}