{
  "type": "Feature",
  "properties": {
    "iso:country":"US",
    "sg:address":"330 Mountain View Dr",
    "sg:city":"Berthoud",
    "sg:classifiers":[
        {
            "category":"Shopping",
            "subcategory":"Pharmacy",
            "type":"Retail Goods"
        }
    ],
    "sg:phone":"+1 970 532 2034",
    "sg:postcode":"80513",
    "sg:province":"CO",
    "wof:name":"Berthoud Drug",
    "wof:placetype":"venue"
},
  "geometry": {"coordinates":[-104.987065,40.339717],"type":"Point"}
}