{
  "type": "Feature",
  "properties": {
    "addr:full":"4431 Maroon Cir Broomfield CO 80023",
    "addr:housenumber":"4431",
    "addr:postcode":"80023",
    "addr:street":"Maroon Cir",
    "iso:country":"US",
    "sg:address":"4431 Maroon Cir",
    "sg:city":"Broomfield",
    "sg:classifiers":[
        {
            "category":"Restaurant",
            "type":"Food & Drink"
        }
    ],
    "sg:phone":"+1 303 523 9719",
    "sg:postcode":"80023",
    "sg:province":"CO",
    "sg:tags":[
        "pizza"
    ],
    "wof:name":"Blackjack Pizza Dba",
    "wof:placetype":"venue"
},
  "geometry": {"coordinates":[-105.044923,39.943722],"type":"Point"}
}