{
  "type": "Feature",
  "properties": {
    "iso:country":"US",
    "sg:address":"304 Landmark Dr",
    "sg:city":"Fort Morgan",
    "sg:classifiers":[
        {
            "category":"Real Estate",
            "subcategory":"Developer",
            "type":"Services"
        }
    ],
    "sg:phone":"+1 970 867 6207",
    "sg:postcode":"80701",
    "sg:province":"CO",
    "sg:tags":[
        "mobile",
        "home"
    ],
    "wof:name":"Landmark South Mobile Cmnty",
    "wof:placetype":"venue"
},
  "geometry": {"coordinates":[-103.80217399999999,40.243579],"type":"Point"}
}