{
  "type": "Feature",
  "properties": {
    "iso:country":"US",
    "sg:address":"1625 S University Blvd",
    "sg:city":"Denver",
    "sg:classifiers":[
        {
            "category":"Government",
            "subcategory":"Police Station",
            "type":"Public Place"
        }
    ],
    "sg:phone":"+1 303 698 3333",
    "sg:postcode":"80210",
    "sg:province":"CO",
    "sg:tags":[
        "protection"
    ],
    "wof:name":"Police Dept",
    "wof:placetype":"venue"
},
  "geometry": {"coordinates":[-104.959501,39.686796],"type":"Point"}
}