{
  "type": "Feature",
  "properties": {
    "iso:country":"US",
    "sg:address":"833 E Agate Ave",
    "sg:city":"Granby",
    "sg:classifiers":[
        {
            "category":"Professional",
            "subcategory":"Computer Services",
            "type":"Services"
        }
    ],
    "sg:phone":"+1 970 887 2205",
    "sg:postcode":"80446",
    "sg:province":"CO",
    "sg:tags":[
        "internet"
    ],
    "wof:name":"Thin Air Technology",
    "wof:placetype":"venue"
},
  "geometry": {"coordinates":[-105.929199,40.0847],"type":"Point"}
}