{
  "type": "Feature",
  "properties": {
    "iso:country":"US",
    "sg:address":"1017 S Santa Fe Ave",
    "sg:city":"Pueblo",
    "sg:classifiers":[
        {
            "category":"Building & Trades",
            "subcategory":"Landscaping Services",
            "type":"Services"
        }
    ],
    "sg:phone":"+1 719 543 7910",
    "sg:postcode":"81006",
    "sg:province":"CO",
    "sg:tags":[
        "horticultural",
        "spraying"
    ],
    "wof:name":"Chem-Way Lawn Care",
    "wof:placetype":"venue"
},
  "geometry": {"coordinates":[-104.6067,38.248774],"type":"Point"}
}