{
  "type": "Feature",
  "properties": {
    "iso:country":"US",
    "sg:address":"121 S Tejon St",
    "sg:city":"Colorado Springs",
    "sg:classifiers":[
        {
            "category":"Professional",
            "subcategory":"Lawyer & Legal Services",
            "type":"Services"
        }
    ],
    "sg:phone":"+1 719 475 2014",
    "sg:postcode":"80903",
    "sg:province":"CO",
    "sg:tags":[
        "attorney"
    ],
    "sg:website":"www.rmjblaw.com",
    "wof:name":"Retherford Mullen Johnson",
    "wof:placetype":"venue"
},
  "geometry": {"coordinates":[-104.823548,38.831818],"type":"Point"}
}