{
  "type": "Feature",
  "properties": {
    "addr:full":"2230 Southgate Rd Colorado Springs CO 80906",
    "addr:housenumber":"2230",
    "addr:postcode":"80906",
    "addr:street":"Southgate Rd",
    "iso:country":"US",
    "sg:address":"2230 Southgate Rd",
    "sg:city":"Colorado Springs",
    "sg:classifiers":[
        {
            "category":"Restaurant",
            "type":"Food & Drink"
        }
    ],
    "sg:menulink":"http://www.allmenus.com/co/colorado-springs/8531-red-robin/menu/",
    "sg:phone":"+1 719 447 8810",
    "sg:postcode":"80906",
    "sg:province":"CO",
    "sg:tags":[
        "american"
    ],
    "wof:name":"Red Robin",
    "wof:placetype":"venue"
},
  "geometry": {"coordinates":[-104.817469,38.79853],"type":"Point"}
}