{
  "type": "Feature",
  "properties": {
    "iso:country":"US",
    "sg:address":"11990 Grant St",
    "sg:city":"Northglenn",
    "sg:classifiers":[
        {
            "category":"Building & Trades",
            "subcategory":"Construction",
            "type":"Services"
        }
    ],
    "sg:phone":"+1 303 920 8444",
    "sg:postcode":"80233",
    "sg:province":"CO",
    "sg:tags":[
        "home",
        "builder"
    ],
    "wof:name":"Suburban Homes Inc",
    "wof:placetype":"venue"
},
  "geometry": {"coordinates":[-104.981416,39.911398],"type":"Point"}
}