{
  "type": "Feature",
  "properties": {
    "addr:full":"2902 W 19th St Greeley CO 80634",
    "addr:housenumber":"2902",
    "addr:postcode":"80634",
    "addr:street":"W 19Th St",
    "iso:country":"US",
    "sg:address":"2902 W 19th St",
    "sg:city":"Greeley",
    "sg:classifiers":[
        {
            "category":"Food & Beverages",
            "subcategory":"Specialty",
            "type":"Retail Goods"
        }
    ],
    "sg:phone":"+1 970 304 1927",
    "sg:postcode":"80634",
    "sg:province":"CO",
    "wof:name":"Morgans Nutrition Consulting",
    "wof:placetype":"venue"
},
  "geometry": {"coordinates":[-104.730177,40.410121],"type":"Point"}
}