{
  "type": "Feature",
  "properties": {
    "iso:country":"US",
    "sg:address":"5789 Co Rd 173",
    "sg:city":"Matheson",
    "sg:phone":"+1 719 541 2943",
    "sg:postcode":"80832",
    "sg:province":"CO",
    "sg:tags":[
        "farm",
        "grain",
        "cash"
    ],
    "wof:name":"Craig A Vermillion",
    "wof:placetype":"venue"
},
  "geometry": {"coordinates":[-103.86854599999999,38.940811],"type":"Point"}
}