{
  "type": "Feature",
  "properties": {
    "addr:full":"310 W Uintah St Colorado Springs CO 80905",
    "addr:housenumber":"310",
    "addr:postcode":"80905",
    "addr:street":"W Uintah St",
    "iso:country":"US",
    "sg:address":"310 W Uintah St",
    "sg:city":"Colorado Springs",
    "sg:classifiers":[
        {
            "category":"Food & Beverages",
            "subcategory":"Groceries & Convenience Stores",
            "type":"Retail Goods"
        }
    ],
    "sg:phone":"+1 719 635 0253",
    "sg:postcode":"80905",
    "sg:province":"CO",
    "wof:name":"7-Eleven",
    "wof:placetype":"venue"
},
  "geometry": {"coordinates":[-104.83080200000001,38.850944],"type":"Point"}
}