{
  "type": "Feature",
  "properties": {
    "addr:full":"3820 E Pikes Peak Ave Colorado Springs CO 80909",
    "addr:housenumber":"3820",
    "addr:postcode":"80909",
    "addr:street":"E Pikes Peak Ave",
    "iso:country":"US",
    "sg:address":"3820 E Pikes Peak Ave",
    "sg:city":"Colorado Springs",
    "sg:classifiers":[
        {
            "category":"Retail",
            "subcategory":"Auto Repair",
            "type":"Services"
        }
    ],
    "sg:phone":"+1 719 597 8791",
    "sg:postcode":"80909",
    "sg:province":"CO",
    "sg:tags":[
        "general",
        "supply"
    ],
    "wof:name":"AGC Enterprises Inc",
    "wof:placetype":"venue"
},
  "geometry": {"coordinates":[-104.75603099999999,38.832009],"type":"Point"}
}