{
  "type": "Feature",
  "properties": {
    "iso:country":"US",
    "sg:address":"2001 S Platte River Drive",
    "sg:city":"Denver",
    "sg:classifiers":[
        {
            "category":"Communications",
            "subcategory":"Newspaper",
            "type":"Services"
        }
    ],
    "sg:phone":"+1 303 936 0303",
    "sg:postcode":"80223",
    "sg:province":"CO",
    "sg:tags":[
        "print",
        "medium"
    ],
    "wof:name":"Publication Printers Corporation",
    "wof:placetype":"venue"
},
  "geometry": {"coordinates":[-104.999284,39.680134],"type":"Point"}
}