{
  "type": "Feature",
  "properties": {
    "addr:full":"111 W Sopris Creek Rd Basalt CO 81621",
    "addr:housenumber":"111",
    "addr:postcode":"81621",
    "addr:street":"W Sopris Creek Rd",
    "iso:country":"US",
    "sg:address":"111 W Sopris Creek Rd",
    "sg:city":"Basalt",
    "sg:classifiers":[
        {
            "category":"Farming",
            "subcategory":"Livestock Farm",
            "type":"Manufacturing & Wholesale Goods"
        }
    ],
    "sg:phone":"+1 970 927 3500",
    "sg:postcode":"81621",
    "sg:province":"CO",
    "sg:tags":[
        "beef",
        "feedlot",
        "cattle"
    ],
    "wof:name":"William Fender",
    "wof:placetype":"venue"
},
  "geometry": {"coordinates":[-107.06114599999999,39.350682],"type":"Point"}
}