{
  "type": "Feature",
  "properties": {
    "iso:country":"US",
    "sg:address":"2710 E 147th Ave",
    "sg:city":"Brighton",
    "sg:classifiers":[
        {
            "category":"Wholesale",
            "subcategory":"Non-durable Goods",
            "type":"Manufacturing & Wholesale Goods"
        }
    ],
    "sg:phone":"+1 303 280 8801",
    "sg:postcode":"80602",
    "sg:province":"CO",
    "wof:name":"F&M Trading Company",
    "wof:placetype":"venue"
},
  "geometry": {"coordinates":[-104.95606600000001,39.961744],"type":"Point"}
}