{
  "type": "Feature",
  "properties": {
    "iso:country":"US",
    "sg:address":"760 S Colorado Boulevard",
    "sg:city":"Denver",
    "sg:classifiers":[
        {
            "category":"Personal",
            "subcategory":"Beauty Salon",
            "type":"Services"
        },
        {
            "category":"Personal",
            "subcategory":"Hair Removal",
            "type":"Services"
        }
    ],
    "sg:phone":"+1 303 757 7157",
    "sg:postcode":"80246",
    "sg:province":"CO",
    "sg:website":"www.salonphoenixco.com",
    "wof:name":"Salon Phoenix",
    "wof:placetype":"venue"
},
  "geometry": {"coordinates":[-104.94058800000001,39.702742],"type":"Point"}
}