{
  "type": "Feature",
  "properties": {
    "addr:full":"1735 W 48th Ave Denver CO 80221",
    "addr:housenumber":"1735",
    "addr:postcode":"80221",
    "addr:street":"W 48Th Ave",
    "iso:country":"US",
    "sg:address":"1735 W 48th Ave",
    "sg:city":"Denver",
    "sg:classifiers":[
        {
            "category":"Shopping",
            "subcategory":"Clothing, Apparel, & Fashions",
            "type":"Retail Goods"
        }
    ],
    "sg:phone":"+1 303 455 7000",
    "sg:postcode":"80221",
    "sg:province":"CO",
    "sg:tags":[
        "uniform"
    ],
    "wof:name":"Neve's Uniforms Inc",
    "wof:placetype":"venue"
},
  "geometry": {"coordinates":[-105.007143,39.783915],"type":"Point"}
}