{
  "type": "Feature",
  "properties": {
    "addr:full":"940 Main Ave Durango CO 81301",
    "addr:housenumber":"940",
    "addr:postcode":"co 81301",
    "addr:street":"Main Ave",
    "iso:country":"US",
    "sg:address":"940 Main Ave",
    "sg:city":"Durango",
    "sg:classifiers":[
        {
            "category":"Banks & Credit Unions",
            "subcategory":"Investment Brokerage",
            "type":"Services"
        }
    ],
    "sg:phone":"+1 970 259 0937",
    "sg:postcode":"81301",
    "sg:province":"CO",
    "sg:tags":[
        "stock",
        "bond"
    ],
    "sg:website":"www.morganstanley.com",
    "wof:name":"Morgan Stanley",
    "wof:placetype":"venue"
},
  "geometry": {"coordinates":[-107.880413,37.274012],"type":"Point"}
}