{
  "type": "Feature",
  "properties": {
    "iso:country":"US",
    "sg:address":"101 Main St",
    "sg:city":"Frisco",
    "sg:classifiers":[
        {
            "category":"Wholesale",
            "subcategory":"Office Equipment",
            "type":"Manufacturing & Wholesale Goods"
        }
    ],
    "sg:phone":"+1 970 668 8111",
    "sg:postcode":"80443",
    "sg:province":"CO",
    "sg:tags":[
        "machine",
        "duplicating",
        "copying"
    ],
    "wof:name":"Konica Minolta Bus Solutions",
    "wof:placetype":"venue"
},
  "geometry": {"coordinates":[-106.095164,39.576302],"type":"Point"}
}