{
  "type": "Feature",
  "properties": {
    "iso:country":"US",
    "sg:address":"7293 S Harrison Way",
    "sg:city":"Centennial",
    "sg:classifiers":[
        {
            "category":"Shopping",
            "type":"Retail Goods"
        }
    ],
    "sg:phone":"+1 303 713 9328",
    "sg:postcode":"80122",
    "sg:province":"CO",
    "sg:tags":[
        "art",
        "gallery",
        "dealer"
    ],
    "wof:name":"Groves Studio",
    "wof:placetype":"venue"
},
  "geometry": {"coordinates":[-104.942365,39.58441],"type":"Point"}
}