{
  "type": "Feature",
  "properties": {
    "addr:full":"628 Mountain Peak Rd Tabernash CO 80478",
    "addr:housenumber":"628",
    "addr:postcode":"80478",
    "addr:street":"Mountain Peak Rd",
    "iso:country":"US",
    "sg:address":"628 Mountain Peak Rd",
    "sg:city":"Tabernash",
    "sg:classifiers":[
        {
            "category":"Building & Trades",
            "subcategory":"Construction",
            "type":"Services"
        }
    ],
    "sg:phone":"+1 970 887 1614",
    "sg:postcode":"80478",
    "sg:province":"CO",
    "sg:tags":[
        "home",
        "builder"
    ],
    "wof:name":"Wilson Mountain Designs LLC",
    "wof:placetype":"venue"
},
  "geometry": {"coordinates":[-105.87620699999999,39.987418],"type":"Point"}
}