{
  "type": "Feature",
  "properties": {
    "addr:full":"17733 Cottonwood Dr Parker CO 80134",
    "addr:housenumber":"17733",
    "addr:postcode":"80134",
    "addr:street":"Cottonwood Dr",
    "iso:country":"US",
    "sg:address":"17733 Cottonwood Dr",
    "sg:city":"Parker",
    "sg:classifiers":[
        {
            "category":"Health Services",
            "subcategory":"Podiatrist",
            "type":"Services"
        }
    ],
    "sg:phone":"+1 303 617 6465",
    "sg:postcode":"80134",
    "sg:province":"CO",
    "wof:name":"Total Foot & Ankle Clinic",
    "wof:placetype":"venue"
},
  "geometry": {"coordinates":[-104.78150599999999,39.557983],"type":"Point"}
}