{
  "type": "Feature",
  "properties": {
    "iso:country":"US",
    "sg:address":"2606 W 11th St",
    "sg:city":"Pueblo",
    "sg:classifiers":[
        {
            "category":"Building & Trades",
            "subcategory":"Electrical",
            "type":"Services"
        }
    ],
    "sg:phone":"+1 719 545 3191",
    "sg:postcode":"81003",
    "sg:province":"CO",
    "sg:tags":[
        "electric",
        "contractor"
    ],
    "wof:name":"In Phase Electric Inc",
    "wof:placetype":"venue"
},
  "geometry": {"coordinates":[-104.651178,38.277012],"type":"Point"}
}