{
  "type": "Feature",
  "properties": {
    "iso:country":"US",
    "sg:address":"726 Lincoln St.",
    "sg:city":"Denver",
    "sg:classifiers":[
        {
            "category":"Food & Beverages",
            "subcategory":"Bakery",
            "type":"Retail Goods"
        }
    ],
    "sg:phone":"+1 303 861 1693",
    "sg:postcode":"80203",
    "sg:province":"CO",
    "sg:tags":[
        "sandwich"
    ],
    "sg:website":"www.lennys.com",
    "wof:name":"Lenny's",
    "wof:placetype":"venue"
},
  "geometry": {"coordinates":[-104.986153,39.72794],"type":"Point"}
}