{
  "type": "Feature",
  "properties": {
    "iso:country":"US",
    "sg:address":"969 E 133rd Ave",
    "sg:city":"Denver",
    "sg:classifiers":[
        {
            "category":"Building & Trades",
            "subcategory":"Construction",
            "type":"Services"
        }
    ],
    "sg:phone":"+1 303 452 3032",
    "sg:postcode":"80241",
    "sg:province":"CO",
    "sg:tags":[
        "painter"
    ],
    "wof:name":"Picture Perfect Painting",
    "wof:placetype":"venue"
},
  "geometry": {"coordinates":[-104.974778,39.938448],"type":"Point"}
}