{
  "type": "Feature",
  "properties": {
    "addr:full":"402 Valley Rd Canon City CO 81212",
    "addr:housenumber":"402",
    "addr:postcode":"81212",
    "addr:street":"Valley Rd",
    "iso:country":"US",
    "sg:address":"402 Valley Rd",
    "sg:city":"Canon City",
    "sg:classifiers":[
        {
            "category":"Wholesale",
            "subcategory":"Office Equipment",
            "type":"Manufacturing & Wholesale Goods"
        }
    ],
    "sg:phone":"+1 719 269 7123",
    "sg:postcode":"81212",
    "sg:province":"CO",
    "sg:tags":[
        "machine",
        "duplicating",
        "copying"
    ],
    "wof:name":"Canon Trailer Supply",
    "wof:placetype":"venue"
},
  "geometry": {"coordinates":[-105.248482,38.417296],"type":"Point"}
}