{
  "type": "Feature",
  "properties": {
    "iso:country":"US",
    "sg:address":"420 Yampa Ave",
    "sg:city":"Craig",
    "sg:classifiers":[
        {
            "category":"Restaurant",
            "type":"Food & Drink"
        }
    ],
    "sg:phone":"+1 970 824 9946",
    "sg:postcode":"81625",
    "sg:province":"CO",
    "sg:tags":[
        "lounge"
    ],
    "wof:name":"Mathers Bar",
    "wof:placetype":"venue"
},
  "geometry": {"coordinates":[-107.547341,40.513868],"type":"Point"}
}