{
  "type": "Feature",
  "properties": {
    "iso:country":"US",
    "sg:address":"9734 E Villasur Ct",
    "sg:city":"Parker",
    "sg:classifiers":[
        {
            "category":"Shopping",
            "subcategory":"Gifts & Souvenirs",
            "type":"Retail Goods"
        }
    ],
    "sg:phone":"+1 303 912 5044",
    "sg:postcode":"80134",
    "sg:province":"CO",
    "sg:tags":[
        "announcement",
        "invitation"
    ],
    "wof:name":"Invitation Wise",
    "wof:placetype":"venue"
},
  "geometry": {"coordinates":[-104.705074,39.452232],"type":"Point"}
}