{
  "type": "Feature",
  "properties": {
    "iso:country":"US",
    "sg:address":"201 S Fairview St",
    "sg:city":"Woodland Park",
    "sg:classifiers":[
        {
            "category":"Professional",
            "subcategory":"Business Services",
            "type":"Services"
        }
    ],
    "sg:phone":"+1 719 686 1334",
    "sg:postcode":"80863",
    "sg:province":"CO",
    "sg:tags":[
        "information",
        "bureau",
        "convention"
    ],
    "sg:website":"www.rmdrc.com",
    "wof:name":"Rocky Mountain Dinosaur",
    "wof:placetype":"venue"
},
  "geometry": {"coordinates":[-105.05167,38.99444],"type":"Point"}
}