{
  "type": "Feature",
  "properties": {
    "iso:country":"US",
    "sg:address":"1037 Oak Way",
    "sg:city":"Rock Springs",
    "sg:classifiers":[
        {
            "category":"Real Estate",
            "subcategory":"Real Estate Agent",
            "type":"Services"
        }
    ],
    "sg:phone":"+1 307 362 8054",
    "sg:postcode":"82901",
    "sg:province":"CO",
    "wof:name":"Jh Real Estate Lc",
    "wof:placetype":"venue"
},
  "geometry": {"coordinates":[-109.22567100000001,41.619998],"type":"Point"}
}