{
  "type": "Feature",
  "properties": {
    "iso:country":"US",
    "sg:address":"12295 Oracle Blvd Suite 200",
    "sg:city":"Colorado Springs ",
    "sg:classifiers":[
        {
            "category":"Professional",
            "subcategory":"Management & Consulting",
            "type":"Services"
        }
    ],
    "sg:phone":"+1 719 573 0084",
    "sg:postcode":"80921",
    "sg:province":"CO",
    "sg:tags":[
        "web-design",
        "web-development",
        "web-hosting",
        "inbound-marketing",
        "seo",
        "internet-marketing",
        "online-marketing",
        "web2-0",
        "social-media",
        "email-marketing"
    ],
    "sg:website":"http://www.hightouchweb.com",
    "wof:name":"HighTouch",
    "wof:placetype":"venue"
},
  "geometry": {"coordinates":[-104.816177,39.010107],"type":"Point"}
}