{
  "type": "Feature",
  "properties": {
    "iso:country":"US",
    "sg:address":"304 S 8th St",
    "sg:city":"Colorado Springs",
    "sg:classifiers":[
        {
            "category":"Organizations",
            "subcategory":"Non-profit Organization",
            "type":"Services"
        }
    ],
    "sg:phone":"+1 719 578 5433",
    "sg:postcode":"80905",
    "sg:province":"CO",
    "sg:tags":[
        "information",
        "alcoholism",
        "treatment"
    ],
    "wof:name":"Addiction Recovery Systems",
    "wof:placetype":"venue"
},
  "geometry": {"coordinates":[-104.840636,38.831177],"type":"Point"}
}