{
  "type": "Feature",
  "properties": {
    "addr:full":"290 Doc Susie Ave Fraser CO 80442",
    "addr:housenumber":"290",
    "addr:postcode":"80442",
    "addr:street":"Doc Susie Ave",
    "iso:country":"US",
    "sg:address":"290 Doc Susie Ave",
    "sg:city":"Fraser",
    "sg:classifiers":[
        {
            "category":"Building & Trades",
            "subcategory":"Construction",
            "type":"Services"
        }
    ],
    "sg:phone":"+1 970 726 4344",
    "sg:postcode":"80442",
    "sg:province":"CO",
    "sg:tags":[
        "excavating",
        "contractor"
    ],
    "wof:name":"J & L Contractors",
    "wof:placetype":"venue"
},
  "geometry": {"coordinates":[-105.81544599999999,39.948254],"type":"Point"}
}