{
  "type": "Feature",
  "properties": {
    "addr:full":"6635 Greenwood Plaza Blvd Greenwood Vlg CO 80111",
    "addr:housenumber":"6635",
    "addr:postcode":"co 80111",
    "addr:street":"Greenwood Plaza Blvd",
    "iso:country":"US",
    "sg:address":"6635 Greenwood Plaza Blvd",
    "sg:city":"Greenwood Vlg",
    "sg:classifiers":[
        {
            "category":"Insurance",
            "subcategory":"Insurance Agent",
            "type":"Services"
        }
    ],
    "sg:phone":"+1 303 790 1779",
    "sg:postcode":"80111",
    "sg:province":"CO",
    "wof:name":"Miok L Fowler Insurance",
    "wof:placetype":"venue"
},
  "geometry": {"coordinates":[-104.89453399999999,39.59718],"type":"Point"}
}