{
  "type": "Feature",
  "properties": {
    "addr:full":"66 Michael Way Durango CO 81301",
    "addr:housenumber":"66",
    "addr:postcode":"co 81301",
    "addr:street":"Michael Way",
    "iso:country":"US",
    "sg:address":"66 Michael Way",
    "sg:city":"Durango",
    "sg:classifiers":[
        {
            "category":"Utilities",
            "subcategory":"Water",
            "type":"Services"
        }
    ],
    "sg:phone":"+1 970 259 3946",
    "sg:postcode":"81301",
    "sg:province":"CO",
    "sg:tags":[
        "company",
        "sewage"
    ],
    "wof:name":"Durango Metro District",
    "wof:placetype":"venue"
},
  "geometry": {"coordinates":[-107.981403,37.267154],"type":"Point"}
}