{
  "type": "Feature",
  "properties": {
    "addr:full":"10699 Melody Dr Denver CO 80234",
    "addr:housenumber":"10699",
    "addr:postcode":"80234",
    "addr:street":"Melody Dr",
    "iso:country":"US",
    "sg:address":"10699 Melody Dr",
    "sg:city":"Denver",
    "sg:classifiers":[
        {
            "category":"Insurance",
            "subcategory":"Insurance Agent",
            "type":"Services"
        }
    ],
    "sg:phone":"+1 303 255 0515",
    "sg:postcode":"80234",
    "sg:province":"CO",
    "wof:name":"Todd W Coleman Agency America",
    "wof:placetype":"venue"
},
  "geometry": {"coordinates":[-104.993335,39.889933],"type":"Point"}
}