{
  "type": "Feature",
  "properties": {
    "addr:full":"1940 W Mississippi Ave Denver CO 80223",
    "addr:housenumber":"1940",
    "addr:postcode":"80223",
    "addr:street":"W Mississippi Ave",
    "iso:country":"US",
    "sg:address":"1940 W Mississippi Ave",
    "sg:city":"Denver",
    "sg:classifiers":[
        {
            "category":"Professional",
            "subcategory":"Lawyer & Legal Services",
            "type":"Services"
        }
    ],
    "sg:phone":"+1 303 922 3711",
    "sg:postcode":"80223",
    "sg:province":"CO",
    "sg:tags":[
        "attorney"
    ],
    "wof:name":"Joe C Medina",
    "wof:placetype":"venue"
},
  "geometry": {"coordinates":[-105.01088300000001,39.696663],"type":"Point"}
}