{
  "type": "Feature",
  "properties": {
    "iso:country":"US",
    "sg:address":"3300 S Parker Rd",
    "sg:city":"Aurora",
    "sg:classifiers":[
        {
            "category":"Communications",
            "type":"Services"
        }
    ],
    "sg:phone":"+1 303 595 0888",
    "sg:postcode":"80014",
    "sg:province":"CO",
    "sg:tags":[
        "communication"
    ],
    "wof:name":"Iis",
    "wof:placetype":"venue"
},
  "geometry": {"coordinates":[-104.837855,39.657415],"type":"Point"}
}