{
  "type": "Feature",
  "properties": {
    "addr:full":"6686 State Hwy 392 Windsor CO 80550",
    "addr:housenumber":"6686",
    "addr:postcode":"80550",
    "addr:street":"State Hwy 392",
    "iso:country":"US",
    "sg:address":"6686 State Hwy 392",
    "sg:city":"Windsor",
    "sg:classifiers":[
        {
            "category":"Farming",
            "subcategory":"Farm",
            "type":"Manufacturing & Wholesale Goods"
        }
    ],
    "sg:phone":"+1 970 686 9781",
    "sg:postcode":"80550",
    "sg:province":"CO",
    "sg:tags":[
        "crop",
        "general"
    ],
    "wof:name":"Jerry Roth",
    "wof:placetype":"venue"
},
  "geometry": {"coordinates":[-104.933093,40.47932],"type":"Point"}
}