{
  "type": "Feature",
  "properties": {
    "iso:country":"US",
    "sg:address":"7592 State Hwy 2",
    "sg:city":"Commerce City",
    "sg:classifiers":[
        {
            "category":"Restaurant",
            "type":"Food & Drink"
        }
    ],
    "sg:phone":"+1 303 288 2288",
    "sg:postcode":"80022",
    "sg:province":"CO",
    "sg:tags":[
        "eating"
    ],
    "wof:name":"Rice Bowl Chinese Cafe",
    "wof:placetype":"venue"
},
  "geometry": {"coordinates":[-104.90608899999999,39.835216],"type":"Point"}
}