{
  "type": "Feature",
  "properties": {
    "iso:country":"US",
    "sg:address":"2750 Glenwood Dr",
    "sg:city":"Boulder",
    "sg:classifiers":[
        {
            "category":"Personal",
            "subcategory":"Beauty Salon",
            "type":"Services"
        }
    ],
    "sg:phone":"+1 303 440 1085",
    "sg:postcode":"80301",
    "sg:province":"CO",
    "wof:name":"Zumo Hair Studio",
    "wof:placetype":"venue"
},
  "geometry": {"coordinates":[-105.25851,40.032746],"type":"Point"}
}