{
  "type": "Feature",
  "properties": {
    "addr:full":"2090 Whiteriver Ave Rifle CO 81650",
    "addr:housenumber":"2090",
    "addr:postcode":"81650",
    "addr:street":"Whiteriver Ave",
    "iso:country":"US",
    "sg:address":"2090 Whiteriver Ave",
    "sg:city":"Rifle",
    "sg:classifiers":[
        {
            "category":"Bars & Pubs",
            "type":"Food & Drink"
        }
    ],
    "sg:phone":"+1 970 618 3621",
    "sg:postcode":"81650",
    "sg:province":"CO",
    "sg:tags":[
        "drinking"
    ],
    "wof:name":"El Bandedo",
    "wof:placetype":"venue"
},
  "geometry": {"coordinates":[-107.781025,39.54675],"type":"Point"}
}