{
  "type": "Feature",
  "properties": {
    "addr:full":"489 Excelsior Rd Silver Cliff CO 81252",
    "addr:housenumber":"489",
    "addr:postcode":"81252",
    "addr:street":"Excelsior Rd",
    "iso:country":"US",
    "sg:address":"489 Excelsior Rd",
    "sg:city":"Silver Cliff",
    "sg:classifiers":[
        {
            "category":"Retail",
            "subcategory":"Portrait Studio",
            "type":"Services"
        }
    ],
    "sg:phone":"+1 719 783 9746",
    "sg:postcode":"81252",
    "sg:province":"CO",
    "sg:tags":[
        "photography"
    ],
    "wof:name":"Gillette Bill Photography",
    "wof:placetype":"venue"
},
  "geometry": {"coordinates":[-105.362202,38.14412],"type":"Point"}
}