{
  "type": "Feature",
  "properties": {
    "iso:country":"US",
    "sg:address":"8565 S Poplar Way",
    "sg:city":"Highlands Ranch",
    "sg:classifiers":[
        {
            "category":"Organizations",
            "subcategory":"Religious Organization",
            "type":"Services"
        }
    ],
    "sg:phone":"+1 303 933 3331",
    "sg:postcode":"80130",
    "sg:province":"CO",
    "wof:name":"Marriage Ministries Intl",
    "wof:placetype":"venue"
},
  "geometry": {"coordinates":[-104.90709099999999,39.56153],"type":"Point"}
}