{
  "type": "Feature",
  "properties": {
    "iso:country":"US",
    "sg:address":"2201 Lawrence St",
    "sg:city":"Denver",
    "sg:classifiers":[
        {
            "category":"Professional",
            "subcategory":"Art Services",
            "type":"Services"
        }
    ],
    "sg:phone":"+1 303 297 9373",
    "sg:postcode":"80205",
    "sg:province":"CO",
    "sg:tags":[
        "photographer"
    ],
    "wof:name":"Dan Knudson Photography",
    "wof:placetype":"venue"
},
  "geometry": {"coordinates":[-104.9881,39.755075],"type":"Point"}
}