{
  "type": "Feature",
  "properties": {
    "addr:full":"119 Welch Ave Berthoud CO 80513",
    "addr:housenumber":"119",
    "addr:postcode":"80513",
    "addr:street":"Welch Ave",
    "iso:country":"US",
    "sg:address":"119 Welch Ave",
    "sg:city":"Berthoud",
    "sg:classifiers":[
        {
            "category":"Retail",
            "subcategory":"Animal Services",
            "type":"Services"
        }
    ],
    "sg:phone":"+1 970 481 0813",
    "sg:postcode":"80513",
    "sg:province":"CO",
    "sg:tags":[
        "pet",
        "boarding",
        "sitting"
    ],
    "wof:name":"A-1 Critter Sitters",
    "wof:placetype":"venue"
},
  "geometry": {"coordinates":[-105.074482,40.30415],"type":"Point"}
}