{
  "type": "Feature",
  "properties": {
    "addr:full":"7061 S University Blvd Centennial CO 80122",
    "addr:housenumber":"7061",
    "addr:postcode":"80122",
    "addr:street":"S University Blvd",
    "iso:country":"US",
    "sg:address":"7061 S University Blvd",
    "sg:city":"Centennial",
    "sg:classifiers":[
        {
            "category":"Professional",
            "subcategory":"Accounting & Tax Preparation",
            "type":"Services"
        }
    ],
    "sg:phone":"+1 303 797 1070",
    "sg:postcode":"80122",
    "sg:province":"CO",
    "sg:tags":[
        "return",
        "filing"
    ],
    "wof:name":"Taxtime Inc",
    "wof:placetype":"venue"
},
  "geometry": {"coordinates":[-104.960273,39.590101],"type":"Point"}
}