{
  "type": "Feature",
  "properties": {
    "iso:country":"US",
    "sg:address":"3705 Grant Ave",
    "sg:city":"Loveland",
    "sg:classifiers":[
        {
            "category":"Real Estate",
            "subcategory":"Real Estate Services",
            "type":"Services"
        }
    ],
    "sg:phone":"+1 970 663 3628",
    "sg:postcode":"80538",
    "sg:province":"CO",
    "sg:tags":[
        "company",
        "title"
    ],
    "wof:name":"Land Title Guarantee Co",
    "wof:placetype":"venue"
},
  "geometry": {"coordinates":[-105.079311,40.43055],"type":"Point"}
}