{
  "type": "Feature",
  "properties": {
    "iso:country":"US",
    "sg:address":"10 W Beaver Creek Blvd",
    "sg:city":"Avon",
    "sg:classifiers":[
        {
            "category":"Professional",
            "subcategory":"Lawyer & Legal Services",
            "type":"Services"
        }
    ],
    "sg:phone":"+1 970 748 9100",
    "sg:postcode":"81620",
    "sg:province":"CO",
    "sg:tags":[
        "attorney"
    ],
    "wof:name":"Mountain Immigration Law Ofc",
    "wof:placetype":"venue"
},
  "geometry": {"coordinates":[-106.522536,39.635295],"type":"Point"}
}