{
  "type": "Feature",
  "properties": {
    "addr:full":"13986 W Bowles Ave Littleton CO 80127",
    "addr:housenumber":"13986",
    "addr:postcode":"80127",
    "addr:street":"W Bowles Ave",
    "iso:country":"US",
    "sg:address":"13986 W Bowles Ave",
    "sg:city":"Littleton",
    "sg:classifiers":[
        {
            "category":"Professional",
            "type":"Services"
        }
    ],
    "sg:phone":"+1 303 904 4815",
    "sg:postcode":"80127",
    "sg:province":"CO",
    "wof:name":"Rs Pot",
    "wof:placetype":"venue"
},
  "geometry": {"coordinates":[-105.155783,39.609615],"type":"Point"}
}