{
  "type": "Feature",
  "properties": {
    "iso:country":"US",
    "sg:address":"1722 14th St",
    "sg:city":"Boulder",
    "sg:classifiers":[
        {
            "category":"Shopping",
            "subcategory":"Computers & Home Electronics",
            "type":"Retail Goods"
        }
    ],
    "sg:phone":"+1 303 443 9175",
    "sg:postcode":"80304",
    "sg:province":"CO",
    "wof:name":"Source One",
    "wof:placetype":"venue"
},
  "geometry": {"coordinates":[-105.27637300000001,40.015487],"type":"Point"}
}