{
  "type": "Feature",
  "properties": {
    "iso:country":"US",
    "sg:address":"114 Glade Park Rd",
    "sg:city":"Grand Junction",
    "sg:classifiers":[
        {
            "category":"Building & Trades",
            "subcategory":"Construction",
            "type":"Services"
        }
    ],
    "sg:phone":"+1 970 255 9499",
    "sg:postcode":"81503",
    "sg:province":"CO",
    "sg:tags":[
        "house"
    ],
    "wof:name":"El Construction",
    "wof:placetype":"venue"
},
  "geometry": {"coordinates":[-108.59043699999999,39.059538],"type":"Point"}
}