{
  "type": "Feature",
  "properties": {
    "addr:full":"3301 Milwaukee Street Denver CO 80205",
    "addr:housenumber":"3301",
    "addr:postcode":"80205",
    "addr:street":"Milwaukee Street",
    "iso:country":"US",
    "sg:address":"3301 Milwaukee Street",
    "sg:city":"Denver",
    "sg:classifiers":[
        {
            "category":"Place Of Worship",
            "subcategory":"Church",
            "type":"Public Place"
        },
        {
            "category":"Place Of Worship",
            "type":"Public Place"
        },
        {
            "category":"Organizations",
            "subcategory":"Religious Organization",
            "type":"Services"
        }
    ],
    "sg:phone":"+1 303 321 2744",
    "sg:postcode":"80205",
    "sg:province":"CO",
    "sg:tags":[
        "churches-interdenominational",
        "churches-various",
        "denomination"
    ],
    "sg:website":"http://www.spottswoodamezion.org",
    "wof:name":"Spottswood A M E Zion Church",
    "wof:placetype":"venue"
},
  "geometry": {"coordinates":[-104.952546,39.763465],"type":"Point"}
}