{
  "type": "Feature",
  "properties": {
    "addr:full":"10559 W 44th Ave Wheat Ridge CO 80033",
    "addr:housenumber":"10559",
    "addr:postcode":"80033",
    "addr:street":"W 44Th Ave",
    "iso:country":"US",
    "sg:address":"10559 W 44th Ave",
    "sg:city":"Wheat Ridge",
    "sg:classifiers":[
        {
            "category":"Insurance",
            "subcategory":"Insurance Agent",
            "type":"Services"
        }
    ],
    "sg:phone":"+1 303 425 3210",
    "sg:postcode":"80033",
    "sg:province":"CO",
    "wof:name":"Brooke Financial of Rockies",
    "wof:placetype":"venue"
},
  "geometry": {"coordinates":[-105.116348,39.778258],"type":"Point"}
}