{
  "type": "Feature",
  "properties": {
    "iso:country":"US",
    "sg:address":"6430 S Fiddlers Green Cir",
    "sg:city":"Englewood",
    "sg:classifiers":[
        {
            "category":"Insurance",
            "subcategory":"Health Insurance",
            "type":"Services"
        }
    ],
    "sg:phone":"+1 303 793 2500",
    "sg:postcode":"80111",
    "sg:province":"CO",
    "sg:tags":[
        "plan"
    ],
    "wof:name":"Aetna",
    "wof:placetype":"venue"
},
  "geometry": {"coordinates":[-104.89140500000001,39.598911],"type":"Point"}
}