{
  "type": "Feature",
  "properties": {
    "iso:country":"US",
    "sg:address":"806 E Goddard Ave",
    "sg:city":"Trinidad",
    "sg:classifiers":[
        {
            "category":"Food & Beverages",
            "subcategory":"Candy",
            "type":"Retail Goods"
        }
    ],
    "sg:phone":"+1 719 846 8304",
    "sg:postcode":"81082",
    "sg:province":"CO",
    "sg:tags":[
        "lubricant",
        "convenience",
        "gas",
        "store"
    ],
    "wof:name":"Convenience Plus",
    "wof:placetype":"venue"
},
  "geometry": {"coordinates":[-104.499882,37.184178],"type":"Point"}
}