{
  "type": "Feature",
  "properties": {
    "iso:country":"US",
    "sg:address":"2600 Canton Ct",
    "sg:city":"Fort Collins",
    "sg:classifiers":[
        {
            "category":"Manufacturing",
            "subcategory":"Printing",
            "type":"Manufacturing & Wholesale Goods"
        }
    ],
    "sg:phone":"+1 970 221 2522",
    "sg:postcode":"80525",
    "sg:province":"CO",
    "sg:tags":[
        "printer"
    ],
    "wof:name":"Printing Station",
    "wof:placetype":"venue"
},
  "geometry": {"coordinates":[-105.027376,40.561795],"type":"Point"}
}