{
  "type": "Feature",
  "properties": {
    "addr:full":"6128 Habitat Dr Boulder CO 80301",
    "addr:housenumber":"6128",
    "addr:postcode":"80301",
    "addr:street":"Habitat Dr",
    "iso:country":"US",
    "sg:address":"6128 Habitat Dr",
    "sg:city":"Boulder",
    "sg:classifiers":[
        {
            "category":"Wholesale",
            "subcategory":"Medical Equipment & Supplies",
            "type":"Manufacturing & Wholesale Goods"
        }
    ],
    "sg:phone":"+1 303 516 1618",
    "sg:postcode":"80301",
    "sg:province":"CO",
    "wof:name":"Baxter Healthcare Corporation",
    "wof:placetype":"venue"
},
  "geometry": {"coordinates":[-105.209417,40.060852],"type":"Point"}
}