{
  "type": "Feature",
  "properties": {
    "iso:country":"US",
    "sg:address":"1631 Emerson St",
    "sg:city":"Denver",
    "sg:classifiers":[
        {
            "category":"Banks & Credit Unions",
            "subcategory":"Financial Services",
            "type":"Services"
        }
    ],
    "sg:phone":"+1 303 814 0344",
    "sg:postcode":"80218",
    "sg:province":"CO",
    "sg:tags":[
        "investor"
    ],
    "wof:name":"G & G Connections",
    "wof:placetype":"venue"
},
  "geometry": {"coordinates":[-104.97623,39.742767],"type":"Point"}
}