{
  "type": "Feature",
  "properties": {
    "iso:country":"US",
    "sg:address":"710 11th St",
    "sg:city":"Greeley",
    "sg:classifiers":[
        {
            "category":"Banks & Credit Unions",
            "subcategory":"Investment Brokerage",
            "type":"Services"
        }
    ],
    "sg:phone":"+1 303 659 1264",
    "sg:postcode":"80631",
    "sg:province":"CO",
    "sg:tags":[
        "security"
    ],
    "wof:name":"Prudential",
    "wof:placetype":"venue"
},
  "geometry": {"coordinates":[-104.690724,40.421088],"type":"Point"}
}