{
  "type": "Feature",
  "properties": {
    "iso:country":"US",
    "sg:address":"7701 E 1st Ave Unit D",
    "sg:city":"Denver",
    "sg:classifiers":[
        {
            "category":"Health Services",
            "subcategory":"Doctor",
            "type":"Services"
        }
    ],
    "sg:phone":"+1 303 261 3825",
    "sg:postcode":"80230",
    "sg:province":"CO",
    "wof:name":"Western OB Gyn Associates",
    "wof:placetype":"venue"
},
  "geometry": {"coordinates":[-104.894566,39.722326],"type":"Point"}
}