{
  "type": "Feature",
  "properties": {
    "addr:full":"2440 S Raritan St Englewood CO 80110",
    "addr:housenumber":"2440",
    "addr:postcode":"80110",
    "addr:street":"S Raritan St",
    "iso:country":"US",
    "sg:address":"2440 S Raritan St",
    "sg:city":"Englewood",
    "sg:classifiers":[
        {
            "category":"Wholesale",
            "subcategory":"Auto Parts",
            "type":"Manufacturing & Wholesale Goods"
        }
    ],
    "sg:phone":"+1 303 937 3500",
    "sg:postcode":"80110",
    "sg:province":"CO",
    "sg:tags":[
        "used"
    ],
    "wof:name":"Media Auto Inc",
    "wof:placetype":"venue"
},
  "geometry": {"coordinates":[-105.008613,39.673036],"type":"Point"}
}