{
  "type": "Feature",
  "properties": {
    "addr:full":"1633 Babcock Ln Colorado Springs CO 80915",
    "addr:housenumber":"1633",
    "addr:postcode":"80915",
    "addr:street":"Babcock Ln",
    "iso:country":"US",
    "sg:address":"1633 Babcock Ln",
    "sg:city":"Colorado Springs",
    "sg:classifiers":[
        {
            "category":"Insurance",
            "subcategory":"Insurance Agent",
            "type":"Services"
        }
    ],
    "sg:phone":"+1 719 596 2320",
    "sg:postcode":"80915",
    "sg:province":"CO",
    "wof:name":"American Home Life Insurance",
    "wof:placetype":"venue"
},
  "geometry": {"coordinates":[-104.73002700000001,38.856618],"type":"Point"}
}