{
  "type": "Feature",
  "properties": {
    "iso:country":"US",
    "sg:address":"16830 Northgate Dr Ste 110",
    "sg:city":"Parker",
    "sg:classifiers":[
        {
            "category":"Health Services",
            "subcategory":"Dentist",
            "type":"Services"
        }
    ],
    "sg:phone":"+1 720 897 6785",
    "sg:postcode":"80134",
    "sg:province":"CO",
    "sg:tags":[
        "implant",
        "dentistry",
        "dentists-cosmetic",
        "dentists-implantology"
    ],
    "sg:website":"http://www.cherilnealddspc.com",
    "wof:name":"Neal Cheri L DDS PC",
    "wof:placetype":"venue"
},
  "geometry": {"coordinates":[-104.79479000000001,39.539758],"type":"Point"}
}