{
  "type": "Feature",
  "properties": {
    "addr:full":"1850 Lisbon Dr Parker CO 80138",
    "addr:housenumber":"1850",
    "addr:postcode":"80138",
    "addr:street":"Lisbon Dr",
    "iso:country":"US",
    "sg:address":"1850 Lisbon Dr",
    "sg:city":"Parker",
    "sg:classifiers":[
        {
            "category":"Building & Trades",
            "subcategory":"Construction",
            "type":"Services"
        }
    ],
    "sg:phone":"+1 720 851 9131",
    "sg:postcode":"80138",
    "sg:province":"CO",
    "sg:tags":[
        "house"
    ],
    "wof:name":"Rnf Construction Inc",
    "wof:placetype":"venue"
},
  "geometry": {"coordinates":[-104.626693,39.467486],"type":"Point"}
}