{
  "type": "Feature",
  "properties": {
    "addr:full":"1121 Scott Ave Estes Park CO 80517",
    "addr:housenumber":"1121",
    "addr:postcode":"80517",
    "addr:street":"Scott Ave",
    "iso:country":"US",
    "sg:address":"1121 Scott Ave",
    "sg:city":"Estes Park",
    "sg:classifiers":[
        {
            "category":"Professional",
            "type":"Services"
        }
    ],
    "sg:phone":"+1 970 586 6594",
    "sg:postcode":"80517",
    "sg:province":"CO",
    "wof:name":"Iris LLC",
    "wof:placetype":"venue"
},
  "geometry": {"coordinates":[-105.504649,40.348989],"type":"Point"}
}