{
  "type": "Feature",
  "properties": {
    "iso:country":"US",
    "sg:address":"9185 E Kenyon Ave",
    "sg:city":"Denver",
    "sg:classifiers":[
        {
            "category":"Banks & Credit Unions",
            "subcategory":"Investment Brokerage",
            "type":"Services"
        }
    ],
    "sg:phone":"+1 303 770 3030",
    "sg:postcode":"80237",
    "sg:province":"CO",
    "sg:tags":[
        "advisory",
        "financial"
    ],
    "wof:name":"Value Financial Advisors",
    "wof:placetype":"venue"
},
  "geometry": {"coordinates":[-104.881773,39.649634],"type":"Point"}
}