{
  "type": "Feature",
  "properties": {
    "addr:full":"9716 Stoneglen Dr Colorado Springs CO 80920",
    "addr:housenumber":"9716",
    "addr:postcode":"80920",
    "addr:street":"Stoneglen Dr",
    "iso:country":"US",
    "sg:address":"9716 Stoneglen Dr",
    "sg:city":"Colorado Springs",
    "sg:classifiers":[
        {
            "category":"Shopping",
            "subcategory":"Computers & Home Electronics",
            "type":"Retail Goods"
        }
    ],
    "sg:phone":"+1 719 260 1236",
    "sg:postcode":"80920",
    "sg:province":"CO",
    "sg:tags":[
        "publishing"
    ],
    "wof:name":"I Design Etc",
    "wof:placetype":"venue"
},
  "geometry": {"coordinates":[-104.76230099999999,38.967621],"type":"Point"}
}