{
  "type": "Feature",
  "properties": {
    "addr:full":"56400 E Co Rd 6 Strasburg CO 80136",
    "addr:housenumber":"56400",
    "addr:postcode":"80136",
    "addr:street":"E Co Rd 6",
    "iso:country":"US",
    "sg:address":"56400 E Co Rd 6",
    "sg:city":"Strasburg",
    "sg:classifiers":[
        {
            "category":"Insurance",
            "subcategory":"Insurance Agent",
            "type":"Services"
        }
    ],
    "sg:phone":"+1 303 622 6595",
    "sg:postcode":"80136",
    "sg:province":"CO",
    "wof:name":"Mc Cart & Assoc",
    "wof:placetype":"venue"
},
  "geometry": {"coordinates":[-104.33399799999999,39.724081],"type":"Point"}
}