{
  "type": "Feature",
  "properties": {
    "addr:full":"3330 N Elizabeth St Pueblo CO 81008",
    "addr:housenumber":"3330",
    "addr:postcode":"81008",
    "addr:street":"N Elizabeth St",
    "iso:country":"US",
    "sg:address":"3330 N Elizabeth St",
    "sg:city":"Pueblo",
    "sg:classifiers":[
        {
            "category":"Banks & Credit Unions",
            "subcategory":"Bank",
            "type":"Services"
        }
    ],
    "sg:phone":"+1 719 542 8559",
    "sg:postcode":"81008",
    "sg:province":"CO",
    "sg:website":"www.usbank.com",
    "wof:name":"US Bank",
    "wof:placetype":"venue"
},
  "geometry": {"coordinates":[-104.61566000000001,38.307157],"type":"Point"}
}