{
  "type": "Feature",
  "properties": {
    "addr:full":"275 Brookside Ct Boulder CO 80302",
    "addr:housenumber":"275",
    "addr:postcode":"80302",
    "addr:street":"Brookside Ct",
    "iso:country":"US",
    "sg:address":"275 Brookside Ct",
    "sg:city":"Boulder",
    "sg:classifiers":[
        {
            "category":"Manufacturing",
            "subcategory":"Toys & Sporting Goods",
            "type":"Manufacturing & Wholesale Goods"
        }
    ],
    "sg:phone":"+1 303 415 1100",
    "sg:postcode":"80302",
    "sg:province":"CO",
    "sg:tags":[
        "mfg"
    ],
    "wof:name":"Kbe Flyfishing",
    "wof:placetype":"venue"
},
  "geometry": {"coordinates":[-105.292879,40.018766],"type":"Point"}
}