{
  "type": "Feature",
  "properties": {
    "addr:full":"2345 E Platte Ave Colorado Springs CO 80909",
    "addr:housenumber":"2345",
    "addr:postcode":"80909",
    "addr:street":"E Platte Ave",
    "iso:country":"US",
    "sg:address":"2345 E Platte Ave",
    "sg:city":"Colorado Springs",
    "sg:classifiers":[
        {
            "category":"Restaurant",
            "type":"Food & Drink"
        }
    ],
    "sg:menulink":"http://www.allmenus.com/co/colorado-springs/128632-subway/menu/",
    "sg:phone":"+1 719 630 0637",
    "sg:postcode":"80909",
    "sg:province":"CO",
    "sg:tags":[
        "american",
        "sandwich"
    ],
    "wof:name":"Subway",
    "wof:placetype":"venue"
},
  "geometry": {"coordinates":[-104.784572,38.837092],"type":"Point"}
}