{
  "type": "Feature",
  "properties": {
    "iso:country":"US",
    "sg:address":"482 Adams Ave",
    "sg:city":"Akron",
    "sg:classifiers":[
        {
            "category":"Health Services",
            "subcategory":"Doctor",
            "type":"Services"
        }
    ],
    "sg:phone":"+1 970 345 2262",
    "sg:postcode":"80720",
    "sg:province":"CO",
    "sg:tags":[
        "clinic"
    ],
    "wof:name":"Washington County Clinic",
    "wof:placetype":"venue"
},
  "geometry": {"coordinates":[-103.214161,40.162344],"type":"Point"}
}