{
  "type": "Feature",
  "properties": {
    "iso:country":"US",
    "sg:address":"7000 S Yosemite St",
    "sg:city":"Englewood",
    "sg:classifiers":[
        {
            "category":"Professional",
            "type":"Services"
        }
    ],
    "sg:phone":"+1 720 200 2745",
    "sg:postcode":"80112",
    "sg:province":"CO",
    "wof:name":"Horizon Title & Settlement",
    "wof:placetype":"venue"
},
  "geometry": {"coordinates":[-104.88538800000001,39.589807],"type":"Point"}
}