{
  "type": "Feature",
  "properties": {
    "iso:country":"US",
    "sg:address":"8055 W Bowles Ave",
    "sg:city":"Littleton",
    "sg:classifiers":[
        {
            "category":"Food & Beverages",
            "subcategory":"Liquor & Beverages",
            "type":"Retail Goods"
        }
    ],
    "sg:phone":"+1 303 399 2123",
    "sg:postcode":"80123",
    "sg:province":"CO",
    "wof:name":"Arrow Liquormart",
    "wof:placetype":"venue"
},
  "geometry": {"coordinates":[-105.088719,39.609797],"type":"Point"}
}