{
  "type": "Feature",
  "properties": {
    "addr:full":"9987 Wadsworth Pkwy Broomfield CO 80021",
    "addr:housenumber":"9987",
    "addr:postcode":"80021",
    "addr:street":"Wadsworth Pkwy",
    "iso:country":"US",
    "sg:address":"9987 Wadsworth Pkwy",
    "sg:city":"Broomfield",
    "sg:classifiers":[
        {
            "category":"Restaurant",
            "type":"Food & Drink"
        }
    ],
    "sg:phone":"+1 303 456 1428",
    "sg:postcode":"80021",
    "sg:province":"CO",
    "wof:name":"Subway Sandwiches & Salads",
    "wof:placetype":"venue"
},
  "geometry": {"coordinates":[-105.095491,39.877257],"type":"Point"}
}