{
  "type": "Feature",
  "properties": {
    "addr:full":"393 Lima St Aurora CO 80010",
    "addr:housenumber":"393",
    "addr:postcode":"80010",
    "addr:street":"Lima St",
    "iso:country":"US",
    "sg:address":"393 Lima St",
    "sg:city":"Aurora",
    "sg:classifiers":[
        {
            "category":"Professional",
            "subcategory":"Advertising",
            "type":"Services"
        }
    ],
    "sg:phone":"+1 303 361 9177",
    "sg:postcode":"80010",
    "sg:province":"CO",
    "sg:tags":[
        "counselor"
    ],
    "wof:name":"Van Dyke Agency",
    "wof:placetype":"venue"
},
  "geometry": {"coordinates":[-104.858931,39.720266],"type":"Point"}
}