{
  "type": "Feature",
  "properties": {
    "iso:country":"US",
    "sg:address":"202 E Cheyenne Mountain Blvd",
    "sg:city":"Colorado Springs",
    "sg:classifiers":[
        {
            "category":"Real Estate",
            "subcategory":"Developer",
            "type":"Services"
        }
    ],
    "sg:phone":"+1 719 471 2135",
    "sg:postcode":"80906",
    "sg:province":"CO",
    "wof:name":"Cog Land End & Development Co",
    "wof:placetype":"venue"
},
  "geometry": {"coordinates":[-104.82323,38.789341],"type":"Point"}
}