{
  "type": "Feature",
  "properties": {
    "iso:country":"US",
    "sg:address":"350 Grape St",
    "sg:city":"Denver",
    "sg:classifiers":[
        {
            "category":"Professional",
            "subcategory":"Employment Agencies",
            "type":"Services"
        }
    ],
    "sg:phone":"+1 720 536 5609",
    "sg:postcode":"80220",
    "sg:province":"CO",
    "wof:name":"Beville International",
    "wof:placetype":"venue"
},
  "geometry": {"coordinates":[-104.924737,39.722161],"type":"Point"}
}