{
  "type": "Feature",
  "properties": {
    "addr:full":"1931 Lilly Dr Denver CO 80229",
    "addr:housenumber":"1931",
    "addr:postcode":"80229",
    "addr:street":"Lilly Dr",
    "iso:country":"US",
    "sg:address":"1931 Lilly Dr",
    "sg:city":"Denver",
    "sg:classifiers":[
        {
            "category":"Building & Trades",
            "subcategory":"Electrical",
            "type":"Services"
        }
    ],
    "sg:phone":"+1 303 356 4293",
    "sg:postcode":"80229",
    "sg:province":"CO",
    "sg:tags":[
        "installation"
    ],
    "wof:name":"RKL Installations",
    "wof:placetype":"venue"
},
  "geometry": {"coordinates":[-104.962818,39.859437],"type":"Point"}
}