{
  "type": "Feature",
  "properties": {
    "addr:full":"2475 Broadway St Boulder CO 80304",
    "addr:housenumber":"2475",
    "addr:postcode":"80304",
    "addr:street":"Broadway St",
    "iso:country":"US",
    "sg:address":"2475 Broadway St",
    "sg:city":"Boulder",
    "sg:classifiers":[
        {
            "category":"Professional",
            "subcategory":"Research",
            "type":"Services"
        }
    ],
    "sg:phone":"+1 303 442 8222",
    "sg:postcode":"80304",
    "sg:province":"CO",
    "sg:tags":[
        "environmental",
        "ecological"
    ],
    "sg:website":"www.lnt.org",
    "wof:name":"Leave No Trace",
    "wof:placetype":"venue"
},
  "geometry": {"coordinates":[-105.28162500000001,40.022409],"type":"Point"}
}