{
  "type": "Feature",
  "properties": {
    "iso:country":"US",
    "sg:address":"5999 Pecos St",
    "sg:city":"Denver",
    "sg:classifiers":[
        {
            "category":"Personal",
            "type":"Services"
        }
    ],
    "sg:phone":"+1 720 253 0341",
    "sg:postcode":"80221",
    "sg:province":"CO",
    "sg:tags":[
        "mover"
    ],
    "sg:website":"http://www.cannonballmovers.net",
    "wof:name":"Cannonball Movers",
    "wof:placetype":"venue"
},
  "geometry": {"coordinates":[-105.006333,39.80613],"type":"Point"}
}