{
  "type": "Feature",
  "properties": {
    "iso:country":"US",
    "sg:address":"1750 15th St",
    "sg:city":"Boulder",
    "sg:classifiers":[
        {
            "category":"Food & Beverages",
            "subcategory":"Liquor & Beverages",
            "type":"Retail Goods"
        }
    ],
    "sg:phone":"+1 303 449 3374",
    "sg:postcode":"80302",
    "sg:province":"CO",
    "sg:website":"www.liquormart.com",
    "wof:name":"Liquor Mart",
    "wof:placetype":"venue"
},
  "geometry": {"coordinates":[-105.27533699999999,40.016631],"type":"Point"}
}