{
  "type": "Feature",
  "properties": {
    "iso:country":"US",
    "sg:address":"514 Wilcox St",
    "sg:city":"Castle Rock",
    "sg:classifiers":[
        {
            "category":"Professional",
            "subcategory":"Lawyer & Legal Services",
            "type":"Services"
        }
    ],
    "sg:phone":"+1 720 733 9037",
    "sg:postcode":"80104",
    "sg:province":"CO",
    "sg:tags":[
        "attorney"
    ],
    "wof:name":"James H Porter PC",
    "wof:placetype":"venue"
},
  "geometry": {"coordinates":[-104.859927,39.375249],"type":"Point"}
}