{
  "type": "Feature",
  "properties": {
    "iso:country":"US",
    "sg:address":"605 W 2nd St",
    "sg:city":"Salida",
    "sg:classifiers":[
        {
            "category":"Personal",
            "type":"Services"
        }
    ],
    "sg:phone":"+1 719 207 0500",
    "sg:postcode":"81201",
    "sg:province":"CO",
    "sg:tags":[
        "therapist",
        "massage"
    ],
    "wof:name":"Andreas Hands Of Healing",
    "wof:placetype":"venue"
},
  "geometry": {"coordinates":[-105.997546,38.539512],"type":"Point"}
}