{
  "type": "Feature",
  "properties": {
    "addr:full":"1701 Santa Fe Trl Trinidad CO 81082",
    "addr:housenumber":"1701",
    "addr:postcode":"81082",
    "addr:street":"Santa Fe Trl",
    "iso:country":"US",
    "sg:address":"1701 Santa Fe Trl",
    "sg:city":"Trinidad",
    "sg:classifiers":[
        {
            "category":"Travel",
            "subcategory":"Campground",
            "type":"Entertainment"
        }
    ],
    "sg:phone":"+1 719 846 3303",
    "sg:postcode":"81082",
    "sg:province":"CO",
    "sg:tags":[
        "recreational",
        "parks",
        "vehicle"
    ],
    "wof:name":"Cawthon Park",
    "wof:placetype":"venue"
},
  "geometry": {"coordinates":[-104.51181,37.15529],"type":"Point"}
}