{
  "type": "Feature",
  "properties": {
    "addr:full":"4522 E Colfax Avenue Denver CO 80220",
    "addr:housenumber":"4522",
    "addr:postcode":"80220",
    "addr:street":"E Colfax Avenue",
    "iso:country":"US",
    "sg:address":"4522 E Colfax Avenue",
    "sg:city":"Denver",
    "sg:classifiers":[
        {
            "category":"Personal",
            "subcategory":"Nail Salon",
            "type":"Services"
        }
    ],
    "sg:phone":"+1 303 388 5662",
    "sg:postcode":"80220",
    "sg:province":"CO",
    "wof:name":"Tammy Nails",
    "wof:placetype":"venue"
},
  "geometry": {"coordinates":[-104.934836,39.739971],"type":"Point"}
}