{
  "type": "Feature",
  "properties": {
    "addr:full":"12671 Meadow Bridge Way Parker CO 80134",
    "addr:housenumber":"12671",
    "addr:postcode":"80134",
    "addr:street":"Meadow Bridge Way",
    "iso:country":"US",
    "sg:address":"12671 Meadow Bridge Way",
    "sg:city":"Parker",
    "sg:classifiers":[
        {
            "category":"Retail",
            "subcategory":"Auto Repair",
            "type":"Services"
        }
    ],
    "sg:phone":"+1 720 851 0997",
    "sg:postcode":"80134",
    "sg:province":"CO",
    "sg:tags":[
        "equipment",
        "industrial",
        "automotive"
    ],
    "wof:name":"L&W Towing",
    "wof:placetype":"venue"
},
  "geometry": {"coordinates":[-104.762941,39.495818],"type":"Point"}
}