{
  "type": "Feature",
  "properties": {
    "iso:country":"US",
    "sg:address":"1332 S Broadway",
    "sg:city":"Denver",
    "sg:classifiers":[
        {
            "category":"Education",
            "subcategory":"Music School",
            "type":"Public Place"
        }
    ],
    "sg:phone":"+1 303 777 2636",
    "sg:postcode":"80210",
    "sg:province":"CO",
    "sg:tags":[
        "instrument",
        "teacher",
        "musical"
    ],
    "wof:name":"Onofrio Piano Company",
    "wof:placetype":"venue"
},
  "geometry": {"coordinates":[-104.987623,39.692342],"type":"Point"}
}