{
  "type": "Feature",
  "properties": {
    "iso:country":"US",
    "sg:address":"1288 S Peak View Dr",
    "sg:city":"Castle Rock",
    "sg:classifiers":[
        {
            "category":"Manufacturing",
            "subcategory":"Electronics",
            "type":"Manufacturing & Wholesale Goods"
        }
    ],
    "sg:phone":"+1 303 663 5299",
    "sg:postcode":"80109",
    "sg:province":"CO",
    "sg:tags":[
        "satellite",
        "inst"
    ],
    "wof:name":"Central Cable Corp",
    "wof:placetype":"venue"
},
  "geometry": {"coordinates":[-104.90790200000001,39.338258],"type":"Point"}
}