{
  "type": "Feature",
  "properties": {
    "addr:full":"10295 Quail St Broomfield CO 80021",
    "addr:housenumber":"10295",
    "addr:postcode":"80021",
    "addr:street":"Quail St",
    "iso:country":"US",
    "sg:address":"10295 Quail St",
    "sg:city":"Broomfield",
    "sg:classifiers":[
        {
            "category":"Building & Trades",
            "subcategory":"Landscaping Services",
            "type":"Services"
        }
    ],
    "sg:phone":"+1 303 469 3576",
    "sg:postcode":"80021",
    "sg:province":"CO",
    "sg:tags":[
        "landscape"
    ],
    "wof:name":"Grass Plus Icemans Plowing",
    "wof:placetype":"venue"
},
  "geometry": {"coordinates":[-105.12498100000001,39.881947],"type":"Point"}
}