{
  "type": "Feature",
  "properties": {
    "iso:country":"US",
    "sg:address":"11825 Co Rd 67.3",
    "sg:city":"Trinidad",
    "sg:classifiers":[
        {
            "category":"Professional",
            "subcategory":"Management & Consulting",
            "type":"Services"
        }
    ],
    "sg:phone":"+1 719 846 4975",
    "sg:postcode":"81082",
    "sg:province":"CO",
    "sg:tags":[
        "fuel"
    ],
    "wof:name":"Peak Project Mgmt",
    "wof:placetype":"venue"
},
  "geometry": {"coordinates":[-104.540335,37.159199],"type":"Point"}
}