{
  "type": "Feature",
  "properties": {
    "iso:country":"US",
    "sg:address":"4700 S College Ave",
    "sg:city":"Fort Collins",
    "sg:classifiers":[
        {
            "category":"Professional",
            "subcategory":"Computer Services",
            "type":"Services"
        }
    ],
    "sg:phone":"+1 970 416 8506",
    "sg:postcode":"80525",
    "sg:province":"CO",
    "sg:tags":[
        "internet"
    ],
    "wof:name":"Northern Colorado Internet",
    "wof:placetype":"venue"
},
  "geometry": {"coordinates":[-105.077135,40.520793],"type":"Point"}
}