{
  "type": "Feature",
  "properties": {
    "iso:country":"US",
    "sg:address":"5612 Newland Way",
    "sg:city":"Arvada",
    "sg:classifiers":[
        {
            "category":"Building & Trades",
            "subcategory":"Plumbing",
            "type":"Services"
        }
    ],
    "sg:phone":"+1 303 422 5621",
    "sg:postcode":"80002",
    "sg:province":"CO",
    "sg:tags":[
        "air",
        "heating",
        "conditioning",
        "contractor"
    ],
    "wof:name":"Arts Heating Service Inc",
    "wof:placetype":"venue"
},
  "geometry": {"coordinates":[-105.070004,39.797154],"type":"Point"}
}