{
  "type": "Feature",
  "properties": {
    "iso:country":"US",
    "sg:address":"5160 Milwaukee Street",
    "sg:city":"Denver",
    "sg:classifiers":[
        {
            "category":"Food & Beverages",
            "subcategory":"Candy",
            "type":"Retail Goods"
        }
    ],
    "sg:phone":"+1 303 455 1016",
    "sg:postcode":"80216",
    "sg:province":"CO",
    "sg:tags":[
        "store"
    ],
    "wof:name":"Dulceria La Estrella",
    "wof:placetype":"venue"
},
  "geometry": {"coordinates":[-104.952088,39.790793],"type":"Point"}
}