{
  "type": "Feature",
  "properties": {
    "iso:country":"US",
    "sg:address":"14854 E Hinsdale Ave",
    "sg:city":"Centennial",
    "sg:classifiers":[
        {
            "category":"Local Transit",
            "type":"Transportation"
        }
    ],
    "sg:phone":"+1 303 870 4700",
    "sg:postcode":"80112",
    "sg:province":"CO",
    "sg:tags":[
        "ambulance"
    ],
    "sg:website":"www.actioncare.com",
    "wof:name":"Action Care Ambulance Inc",
    "wof:placetype":"venue"
},
  "geometry": {"coordinates":[-104.81681,39.581336],"type":"Point"}
}