{
  "type": "Feature",
  "properties": {
    "addr:full":"2150 S Monaco Pkwy Denver CO 80222",
    "addr:housenumber":"2150",
    "addr:postcode":"80222",
    "addr:street":"S Monaco Pkwy",
    "iso:country":"US",
    "sg:address":"2150 S Monaco Pkwy",
    "sg:city":"Denver",
    "sg:classifiers":[
        {
            "category":"Autos & Motor Vehicles",
            "subcategory":"Auto Supplies",
            "type":"Retail Goods"
        },
        {
            "category":"Retail",
            "subcategory":"Auto Repair",
            "type":"Services"
        }
    ],
    "sg:phone":"+1 303 928 4795",
    "sg:postcode":"80222",
    "sg:province":"CO",
    "sg:tags":[
        "oil",
        "tire",
        "automobile",
        "accessory",
        "lube",
        "part",
        "supplies-used",
        "brake",
        "rebuilt"
    ],
    "sg:website":"http://www.sears.com/shc/s/v_10153_12605_Automotive?adCell=AH",
    "wof:name":"Sears Auto Center",
    "wof:placetype":"venue"
},
  "geometry": {"coordinates":[-104.91275899999999,39.677204],"type":"Point"}
}