{
  "type": "Feature",
  "properties": {
    "addr:full":"3939 Tennyson St Denver CO 80212",
    "addr:housenumber":"3939",
    "addr:postcode":"80212",
    "addr:street":"Tennyson St",
    "iso:country":"US",
    "sg:address":"3939 Tennyson St",
    "sg:city":"Denver",
    "sg:classifiers":[
        {
            "category":"Shopping",
            "subcategory":"Clothing, Apparel, & Fashions",
            "type":"Retail Goods"
        }
    ],
    "sg:phone":"+1 303 433 0742",
    "sg:postcode":"80212",
    "sg:province":"CO",
    "wof:name":"Silviana Lamoure",
    "wof:placetype":"venue"
},
  "geometry": {"coordinates":[-105.04407999999999,39.772952],"type":"Point"}
}