{
  "type": "Feature",
  "properties": {
    "iso:country":"US",
    "sg:address":"479 S White Tail Dr",
    "sg:city":"Franktown",
    "sg:classifiers":[
        {
            "category":"Manufacturing",
            "subcategory":"Building Materials",
            "type":"Manufacturing & Wholesale Goods"
        },
        {
            "category":"Building & Trades",
            "subcategory":"Construction",
            "type":"Services"
        }
    ],
    "sg:phone":"+1 303 688 8881",
    "sg:postcode":"80116",
    "sg:province":"CO",
    "sg:tags":[
        "builder",
        "stair",
        "mfg"
    ],
    "wof:name":"Denver Stair Company",
    "wof:placetype":"venue"
},
  "geometry": {"coordinates":[-104.69540499999999,39.363892],"type":"Point"}
}