{
  "type": "Feature",
  "properties": {
    "iso:country":"US",
    "sg:address":"20 Vail Rd",
    "sg:city":"Vail",
    "sg:classifiers":[
        {
            "category":"Restaurant",
            "type":"Food & Drink"
        }
    ],
    "sg:menulink":"http://www.allmenus.com/co/minturn-red-cliff/268172-swiss-chalet---vail/menu/",
    "sg:phone":"+1 970 479 5462",
    "sg:postcode":"81657",
    "sg:province":"CO",
    "wof:name":"Swiss Chalet - Vail",
    "wof:placetype":"venue"
},
  "geometry": {"coordinates":[-106.378221,39.641699],"type":"Point"}
}