{
  "type": "Feature",
  "properties": {
    "iso:country":"US",
    "sg:address":"11539 E Grant Rd",
    "sg:city":"Franktown",
    "sg:classifiers":[
        {
            "category":"Manufacturing",
            "subcategory":"Wood Products",
            "type":"Manufacturing & Wholesale Goods"
        }
    ],
    "sg:phone":"+1 303 517 3102",
    "sg:postcode":"80116",
    "sg:province":"CO",
    "sg:tags":[
        "mfg"
    ],
    "wof:name":"Bird Man",
    "wof:placetype":"venue"
},
  "geometry": {"coordinates":[-104.671616,39.391094],"type":"Point"}
}