{
  "type": "Feature",
  "properties": {
    "iso:country":"US",
    "sg:address":"350 W Spaulding St",
    "sg:city":"Lafayette",
    "sg:classifiers":[
        {
            "category":"Building & Trades",
            "subcategory":"Construction",
            "type":"Services"
        }
    ],
    "sg:phone":"+1 303 665 1842",
    "sg:postcode":"80026",
    "sg:province":"CO",
    "sg:tags":[
        "contractor"
    ],
    "wof:name":"Hanson S Excavating & Fencing",
    "wof:placetype":"venue"
},
  "geometry": {"coordinates":[-105.094453,39.990542],"type":"Point"}
}