{
  "type": "Feature",
  "properties": {
    "iso:country":"US",
    "sg:address":"3900 York Street",
    "sg:city":"Denver",
    "sg:classifiers":[
        {
            "category":"Retail",
            "subcategory":"Auto Repair",
            "type":"Services"
        }
    ],
    "sg:phone":"+1 303 675 0102",
    "sg:postcode":"80205",
    "sg:province":"CO",
    "wof:name":"Mijares Automotive",
    "wof:placetype":"venue"
},
  "geometry": {"coordinates":[-104.959581,39.771437],"type":"Point"}
}