{
  "type": "Feature",
  "properties": {
    "iso:country":"US",
    "sg:address":"1245 Hole Cir",
    "sg:city":"Colorado Springs",
    "sg:classifiers":[
        {
            "category":"Real Estate",
            "subcategory":"Real Estate Agent",
            "type":"Services"
        }
    ],
    "sg:phone":"+1 719 591 8030",
    "sg:postcode":"80915",
    "sg:province":"CO",
    "wof:name":"Ron Welch Realty Co",
    "wof:placetype":"venue"
},
  "geometry": {"coordinates":[-104.723066,38.849577],"type":"Point"}
}