{
  "type": "Feature",
  "properties": {
    "iso:country":"US",
    "sg:address":"1329 Main St",
    "sg:city":"Reliance",
    "sg:classifiers":[
        {
            "category":"Education",
            "subcategory":"Library",
            "type":"Public Place"
        }
    ],
    "sg:phone":"+1 307 352 6670",
    "sg:postcode":"82943",
    "sg:province":"CO",
    "wof:name":"Reliance Library",
    "wof:placetype":"venue"
},
  "geometry": {"coordinates":[-109.19423500000001,41.670191],"type":"Point"}
}