{
  "type": "Feature",
  "properties": {
    "addr:full":"330 N Lincoln Ave Loveland CO 80537",
    "addr:housenumber":"330",
    "addr:postcode":"80537",
    "addr:street":"N Lincoln Ave",
    "iso:country":"US",
    "sg:address":"330 N Lincoln Ave",
    "sg:city":"Loveland",
    "sg:classifiers":[
        {
            "category":"Bars & Pubs",
            "type":"Food & Drink"
        }
    ],
    "sg:phone":"+1 970 667 1400",
    "sg:postcode":"80537",
    "sg:province":"CO",
    "sg:tags":[
        "lounge",
        "cocktail"
    ],
    "wof:name":"Cove Tavern",
    "wof:placetype":"venue"
},
  "geometry": {"coordinates":[-105.073134,40.395121],"type":"Point"}
}