{
  "type": "Feature",
  "properties": {
    "addr:full":"3736 Norwood Dr Littleton CO 80125",
    "addr:housenumber":"3736",
    "addr:postcode":"80125",
    "addr:street":"Norwood Dr",
    "iso:country":"US",
    "sg:address":"3736 Norwood Dr",
    "sg:city":"Littleton",
    "sg:classifiers":[
        {
            "category":"Autos & Motor Vehicles",
            "subcategory":"Motorcycle Sales",
            "type":"Retail Goods"
        }
    ],
    "sg:phone":"+1 303 814 1709",
    "sg:postcode":"80125",
    "sg:province":"CO",
    "wof:name":"Black Widow Cams",
    "wof:placetype":"venue"
},
  "geometry": {"coordinates":[-105.037283,39.555324],"type":"Point"}
}