{
  "type": "Feature",
  "properties": {
    "iso:country":"US",
    "sg:address":"35895 Co Rd 18",
    "sg:city":"Roggen",
    "sg:classifiers":[
        {
            "category":"Farming",
            "subcategory":"Livestock Farm",
            "type":"Manufacturing & Wholesale Goods"
        },
        {
            "category":"Wholesale",
            "subcategory":"Farm Supplies",
            "type":"Manufacturing & Wholesale Goods"
        }
    ],
    "sg:phone":"+1 303 849 5200",
    "sg:postcode":"80652",
    "sg:province":"CO",
    "sg:tags":[
        "feed",
        "feedlot",
        "beef",
        "cattle"
    ],
    "wof:name":"Fox Hill Feeders LLC",
    "wof:placetype":"venue"
},
  "geometry": {"coordinates":[-104.37947699999999,40.116633],"type":"Point"}
}