{
  "type": "Feature",
  "properties": {
    "iso:country":"US",
    "sg:address":"2350 E 120th Ave",
    "sg:city":"Denver",
    "sg:classifiers":[
        {
            "category":"Autos & Motor Vehicles",
            "subcategory":"Fuel & Gas Station",
            "type":"Retail Goods"
        }
    ],
    "sg:phone":"+1 303 252 9574",
    "sg:postcode":"80233",
    "sg:province":"CO",
    "sg:tags":[
        "station",
        "store",
        "oil"
    ],
    "wof:name":"Conoco",
    "wof:placetype":"venue"
},
  "geometry": {"coordinates":[-104.958181,39.913732],"type":"Point"}
}