{
  "type": "Feature",
  "properties": {
    "addr:full":"4251 Creek Dr Broomfield CO 80023",
    "addr:housenumber":"4251",
    "addr:postcode":"80023",
    "addr:street":"Creek Dr",
    "iso:country":"US",
    "sg:address":"4251 Creek Dr",
    "sg:city":"Broomfield",
    "sg:classifiers":[
        {
            "category":"Freight",
            "type":"Transportation"
        }
    ],
    "sg:phone":"+1 303 469 3430",
    "sg:postcode":"80023",
    "sg:province":"CO",
    "wof:name":"Jacobs Transport Inc",
    "wof:placetype":"venue"
},
  "geometry": {"coordinates":[-105.04136200000001,39.945992],"type":"Point"}
}