{
  "type": "Feature",
  "properties": {
    "iso:country":"US",
    "sg:address":"10317 Echo Cir",
    "sg:city":"Longmont",
    "sg:classifiers":[
        {
            "category":"Wholesale",
            "subcategory":"Electrical",
            "type":"Manufacturing & Wholesale Goods"
        }
    ],
    "sg:phone":"+1 303 298 0522",
    "sg:postcode":"80504",
    "sg:province":"CO",
    "sg:tags":[
        "equipment"
    ],
    "wof:name":"Industrial Battery Service",
    "wof:placetype":"venue"
},
  "geometry": {"coordinates":[-104.931693,40.148955],"type":"Point"}
}