{
  "type": "Feature",
  "properties": {
    "addr:full":"10075 Westmoor Drive Suite 200 Westminster CO 80021",
    "addr:housenumber":"10075",
    "addr:postcode":"80021",
    "addr:street":"Westmoor Drive Suite 200",
    "iso:country":"US",
    "sg:address":"10075 Westmoor Drive Suite 200",
    "sg:city":"Westminster",
    "sg:classifiers":[
        {
            "category":"Professional",
            "subcategory":"Advertising",
            "type":"Services"
        }
    ],
    "sg:phone":"+1 303 327 1600",
    "sg:postcode":"80021",
    "sg:province":"CO",
    "sg:website":"http://datalogix.com/",
    "wof:name":"Datalogix",
    "wof:placetype":"venue"
},
  "geometry": {"coordinates":[-105.12183,39.898544],"type":"Point"}
}