{
  "type": "Feature",
  "properties": {
    "addr:full":"5328 Tennyson Street Denver CO 80212",
    "addr:housenumber":"5328",
    "addr:postcode":"80212",
    "addr:street":"Tennyson Street",
    "iso:country":"US",
    "sg:address":"5328 Tennyson Street",
    "sg:city":"Denver",
    "sg:classifiers":[
        {
            "category":"Professional",
            "subcategory":"Computer Services",
            "type":"Services"
        }
    ],
    "sg:phone":"+1 303 455 3701",
    "sg:postcode":"80212",
    "sg:province":"CO",
    "sg:tags":[
        "repair"
    ],
    "wof:name":"Keppley & Son",
    "wof:placetype":"venue"
},
  "geometry": {"coordinates":[-105.043734,39.793996],"type":"Point"}
}