{
  "type": "Feature",
  "properties": {
    "iso:country":"US",
    "sg:address":"8755 E Orchard Rd",
    "sg:city":"Englewood",
    "sg:classifiers":[
        {
            "category":"Wholesale",
            "subcategory":"Durable Goods & Equipment",
            "type":"Manufacturing & Wholesale Goods"
        }
    ],
    "sg:phone":"+1 303 790 4700",
    "sg:postcode":"80111",
    "sg:province":"CO",
    "sg:tags":[
        "supplier",
        "financial",
        "system"
    ],
    "wof:name":"C R I Financial Systems Inc",
    "wof:placetype":"venue"
},
  "geometry": {"coordinates":[-104.887888,39.609695],"type":"Point"}
}