{
  "type": "Feature",
  "properties": {
    "iso:country":"US",
    "sg:address":"9625 E Arapahoe Rd",
    "sg:city":"Greenwood Vlg",
    "sg:classifiers":[
        {
            "category":"Building & Trades",
            "subcategory":"Equipment Rental",
            "type":"Services"
        }
    ],
    "sg:phone":"+1 303 649 9767",
    "sg:postcode":"80112",
    "sg:province":"CO",
    "sg:tags":[
        "carpet",
        "cleaning",
        "rug"
    ],
    "wof:name":"A-Academy Carpet Cleaning",
    "wof:placetype":"venue"
},
  "geometry": {"coordinates":[-104.87741200000001,39.595109],"type":"Point"}
}