{
  "type": "Feature",
  "properties": {
    "addr:full":"5650 S Windermere St Littleton CO 80120",
    "addr:housenumber":"5650",
    "addr:postcode":"80120",
    "addr:street":"S Windermere St",
    "iso:country":"US",
    "sg:address":"5650 S Windermere St",
    "sg:city":"Littleton",
    "sg:classifiers":[
        {
            "category":"Manufacturing",
            "subcategory":"Tools & Machinery",
            "type":"Manufacturing & Wholesale Goods"
        }
    ],
    "sg:phone":"+1 303 795 6455",
    "sg:postcode":"80120",
    "sg:province":"CO",
    "sg:tags":[
        "magnifying",
        "glasses"
    ],
    "wof:name":"Beyond Sight",
    "wof:placetype":"venue"
},
  "geometry": {"coordinates":[-105.006747,39.614198],"type":"Point"}
}