{
  "type": "Feature",
  "properties": {
    "addr:full":"56062 US Hwy 285 Shawnee CO 80475",
    "addr:postcode":"56062;80475",
    "addr:street":"Us Hwy 285",
    "iso:country":"US",
    "sg:address":"56062 US Hwy 285",
    "sg:city":"Shawnee",
    "sg:classifiers":[
        {
            "category":"Government",
            "subcategory":"Post Office",
            "type":"Public Place"
        }
    ],
    "sg:phone":"+1 303 838 9512",
    "sg:postcode":"80475",
    "sg:province":"CO",
    "wof:name":"US Post Office",
    "wof:placetype":"venue"
},
  "geometry": {"coordinates":[-105.555305,39.422236],"type":"Point"}
}