{
  "type": "Feature",
  "properties": {
    "iso:country":"US",
    "sg:address":"8000 E Belleview Ave",
    "sg:city":"Englewood",
    "sg:classifiers":[
        {
            "category":"Restaurant",
            "type":"Food & Drink"
        }
    ],
    "sg:menulink":"http://www.allmenus.com/co/southwest-arapahoe/5308-il-fornaio/menu/",
    "sg:phone":"+1 303 221 8400",
    "sg:postcode":"80111",
    "sg:province":"CO",
    "sg:tags":[
        "italian"
    ],
    "wof:name":"Il Fornaio",
    "wof:placetype":"venue"
},
  "geometry": {"coordinates":[-104.89601999999999,39.62371],"type":"Point"}
}