{
  "type": "Feature",
  "properties": {
    "addr:full":"619 S College Ave Fort Collins CO 80524",
    "addr:housenumber":"619",
    "addr:postcode":"80524",
    "addr:street":"S College Ave",
    "iso:country":"US",
    "sg:address":"619 S College Ave",
    "sg:city":"Fort Collins",
    "sg:classifiers":[
        {
            "category":"Shopping",
            "subcategory":"Books",
            "type":"Retail Goods"
        },
        {
            "category":"Shopping",
            "subcategory":"Clothing, Apparel, & Fashions",
            "type":"Retail Goods"
        }
    ],
    "sg:phone":"+1 970 472 0224",
    "sg:postcode":"80524",
    "sg:province":"CO",
    "sg:tags":[
        "organization",
        "religious",
        "dealer"
    ],
    "sg:website":"www.star-knowledge.net",
    "wof:name":"Earth Star Creations",
    "wof:placetype":"venue"
},
  "geometry": {"coordinates":[-105.077157,40.578463],"type":"Point"}
}