{
  "type": "Feature",
  "properties": {
    "addr:full":"18290 Bent Oak Ln Monument CO 80132",
    "addr:housenumber":"18290",
    "addr:postcode":"80132",
    "addr:street":"Bent Oak Ln",
    "iso:country":"US",
    "sg:address":"18290 Bent Oak Ln",
    "sg:city":"Monument",
    "sg:classifiers":[
        {
            "category":"Airport",
            "type":"Transportation"
        }
    ],
    "sg:phone":"+1 719 488 3869",
    "sg:postcode":"80132",
    "sg:province":"CO",
    "sg:tags":[
        "help",
        "supply"
    ],
    "wof:name":"Aviation Training Resource",
    "wof:placetype":"venue"
},
  "geometry": {"coordinates":[-104.837999,39.097151],"type":"Point"}
}