{
  "type": "Feature",
  "properties": {
    "addr:full":"357 D Ave Limon CO 80828",
    "addr:housenumber":"357",
    "addr:postcode":"80828",
    "addr:street":"D Ave",
    "iso:country":"US",
    "sg:address":"357 D Ave",
    "sg:city":"Limon",
    "sg:classifiers":[
        {
            "category":"Professional",
            "subcategory":"Accounting & Tax Preparation",
            "type":"Services"
        }
    ],
    "sg:phone":"+1 719 775 2610",
    "sg:postcode":"80828",
    "sg:province":"CO",
    "sg:tags":[
        "accountant"
    ],
    "wof:name":"Errol Hertneky Inc",
    "wof:placetype":"venue"
},
  "geometry": {"coordinates":[-103.686622,39.263845],"type":"Point"}
}