{
  "type": "Feature",
  "properties": {
    "iso:country":"US",
    "sg:address":"371 Brian Ave",
    "sg:city":"Silverthorne",
    "sg:classifiers":[
        {
            "category":"Home & Garden",
            "subcategory":"Furniture",
            "type":"Retail Goods"
        }
    ],
    "sg:phone":"+1 970 468 7566",
    "sg:postcode":"80498",
    "sg:province":"CO",
    "wof:name":"Re Fine Furniture Store",
    "wof:placetype":"venue"
},
  "geometry": {"coordinates":[-106.075317,39.629149],"type":"Point"}
}