{
  "type": "Feature",
  "properties": {
    "addr:full":"2197 US Hwy 160 Pagosa Springs CO 81147",
    "addr:housenumber":"2197",
    "addr:postcode":"81147",
    "addr:street":"Us Hwy 160",
    "iso:country":"US",
    "sg:address":"2197 US Hwy 160",
    "sg:city":"Pagosa Springs",
    "sg:classifiers":[
        {
            "category":"Retail",
            "subcategory":"Veterinary Services",
            "type":"Services"
        }
    ],
    "sg:phone":"+1 970 264 2629",
    "sg:postcode":"81147",
    "sg:province":"CO",
    "sg:tags":[
        "veterinarian"
    ],
    "wof:name":"San Juan Veterinary Clinic",
    "wof:placetype":"venue"
},
  "geometry": {"coordinates":[-107.04908399999999,37.268697],"type":"Point"}
}