{
  "type": "Feature",
  "properties": {
    "addr:full":"104 W 1st St Trinidad CO 81082",
    "addr:housenumber":"104",
    "addr:postcode":"81082",
    "addr:street":"W 1St St",
    "iso:country":"US",
    "sg:address":"104 W 1st St",
    "sg:city":"Trinidad",
    "sg:classifiers":[
        {
            "category":"Social Services",
            "type":"Services"
        }
    ],
    "sg:phone":"+1 719 846 3252",
    "sg:postcode":"81082",
    "sg:province":"CO",
    "sg:tags":[
        "organization",
        "welfare"
    ],
    "wof:name":"Salvation Army Trinidad Unit",
    "wof:placetype":"venue"
},
  "geometry": {"coordinates":[-104.50527099999999,37.167793],"type":"Point"}
}