{
  "type": "Feature",
  "properties": {
    "addr:full":"46465 Black Spruce Ln Parker CO 80138",
    "addr:housenumber":"46465",
    "addr:postcode":"80138",
    "addr:street":"Black Spruce Ln",
    "iso:country":"US",
    "sg:address":"46465 Black Spruce Ln",
    "sg:city":"Parker",
    "sg:classifiers":[
        {
            "category":"Professional",
            "type":"Services"
        }
    ],
    "sg:phone":"+1 303 841 8647",
    "sg:postcode":"80138",
    "sg:province":"CO",
    "sg:tags":[
        "establishment"
    ],
    "wof:name":"Colorado Courseware",
    "wof:placetype":"venue"
},
  "geometry": {"coordinates":[-104.651533,39.539793],"type":"Point"}
}