{
  "type": "Feature",
  "properties": {
    "addr:full":"501 S Cherry Street Denver CO 80246",
    "addr:housenumber":"501",
    "addr:postcode":"80246",
    "addr:street":"S Cherry Street",
    "iso:country":"US",
    "sg:address":"501 S Cherry Street",
    "sg:city":"Denver",
    "sg:classifiers":[
        {
            "category":"Building & Trades",
            "subcategory":"Construction",
            "type":"Services"
        },
        {
            "category":"Real Estate",
            "subcategory":"Architect",
            "type":"Services"
        }
    ],
    "sg:phone":"+1 303 399 9100",
    "sg:postcode":"80246",
    "sg:province":"CO",
    "sg:tags":[
        "interior",
        "design"
    ],
    "wof:name":"W E Kieding Interior Architects",
    "wof:placetype":"venue"
},
  "geometry": {"coordinates":[-104.933384,39.707406],"type":"Point"}
}