{
  "type": "Feature",
  "properties": {
    "iso:country":"US",
    "sg:address":"111 S Ranney St",
    "sg:city":"Craig",
    "sg:classifiers":[
        {
            "category":"Utilities",
            "subcategory":"Water",
            "type":"Services"
        }
    ],
    "sg:phone":"+1 970 824 6340",
    "sg:postcode":"81625",
    "sg:province":"CO",
    "sg:tags":[
        "supply"
    ],
    "wof:name":"Craig City Water Plant",
    "wof:placetype":"venue"
},
  "geometry": {"coordinates":[-107.55291099999999,40.499978],"type":"Point"}
}