{
  "type": "Feature",
  "properties": {
    "iso:country":"US",
    "sg:address":"12440 Mount Baldy Dr",
    "sg:city":"Colorado Springs",
    "sg:classifiers":[
        {
            "category":"Building & Trades",
            "subcategory":"Construction",
            "type":"Services"
        }
    ],
    "sg:phone":"+1 719 661 1339",
    "sg:postcode":"80921",
    "sg:province":"CO",
    "sg:tags":[
        "stucco",
        "contractor"
    ],
    "wof:name":"Triple C Construction Inc",
    "wof:placetype":"venue"
},
  "geometry": {"coordinates":[-104.796359,39.009876],"type":"Point"}
}