{
  "type": "Feature",
  "properties": {
    "addr:full":"2033 E Colfax Ave Denver CO 80206",
    "addr:housenumber":"2033",
    "addr:postcode":"80206",
    "addr:street":"E Colfax Ave",
    "iso:country":"US",
    "sg:address":"2033 E Colfax Ave",
    "sg:city":"Denver",
    "sg:classifiers":[
        {
            "category":"Recreation",
            "type":"Entertainment"
        }
    ],
    "sg:phone":"+1 303 355 2258",
    "sg:postcode":"80206",
    "sg:province":"CO",
    "sg:tags":[
        "martial art",
        "instruction"
    ],
    "sg:website":"www.ussd.com",
    "wof:name":"United Studios of Self Defense",
    "wof:placetype":"venue"
},
  "geometry": {"coordinates":[-104.96199799999999,39.740101],"type":"Point"}
}