{
  "type": "Feature",
  "properties": {
    "iso:country":"US",
    "sg:address":"7310 Space Village Ave",
    "sg:city":"Colorado Springs",
    "sg:classifiers":[
        {
            "category":"Freight",
            "type":"Transportation"
        }
    ],
    "sg:phone":"+1 719 573 9900",
    "sg:postcode":"80929",
    "sg:province":"CO",
    "sg:tags":[
        "vehicle",
        "recreational",
        "general"
    ],
    "wof:name":"A Better R V Storage",
    "wof:placetype":"venue"
},
  "geometry": {"coordinates":[-104.691633,38.839016],"type":"Point"}
}