{
  "type": "Feature",
  "properties": {
    "addr:full":"11175 E Mississippi Ave Aurora CO 80012",
    "addr:housenumber":"11175",
    "addr:postcode":"80012",
    "addr:street":"E Mississippi Ave",
    "iso:country":"US",
    "sg:address":"11175 E Mississippi Ave",
    "sg:city":"Aurora",
    "sg:classifiers":[
        {
            "category":"Health Services",
            "subcategory":"Health Practitioner",
            "type":"Services"
        }
    ],
    "sg:phone":"+1 720 858 8306",
    "sg:postcode":"80012",
    "sg:province":"CO",
    "sg:tags":[
        "therapist",
        "physical"
    ],
    "wof:name":"Quality Care Medical Ctr",
    "wof:placetype":"venue"
},
  "geometry": {"coordinates":[-104.857975,39.696654],"type":"Point"}
}