{
  "type": "Feature",
  "properties": {
    "iso:country":"US",
    "sg:address":"623 E 18th St",
    "sg:city":"Greeley",
    "sg:classifiers":[
        {
            "category":"Food & Beverages",
            "subcategory":"Fruits & Vegetables",
            "type":"Retail Goods"
        }
    ],
    "sg:phone":"+1 970 352 2787",
    "sg:postcode":"80631",
    "sg:province":"CO",
    "sg:tags":[
        "produce"
    ],
    "wof:name":"Hungenberg Produce Co",
    "wof:placetype":"venue"
},
  "geometry": {"coordinates":[-104.674339,40.410151],"type":"Point"}
}