{
  "type": "Feature",
  "properties": {
    "addr:full":"1317 Edith Ln Colorado Springs CO 80909",
    "addr:housenumber":"1317",
    "addr:postcode":"80909",
    "addr:street":"Edith Ln",
    "iso:country":"US",
    "sg:address":"1317 Edith Ln",
    "sg:city":"Colorado Springs",
    "sg:classifiers":[
        {
            "category":"Building & Trades",
            "subcategory":"Construction",
            "type":"Services"
        }
    ],
    "sg:phone":"+1 719 630 7962",
    "sg:postcode":"80909",
    "sg:province":"CO",
    "sg:tags":[
        "contractor"
    ],
    "wof:name":"JB Drywall Inc",
    "wof:placetype":"venue"
},
  "geometry": {"coordinates":[-104.772313,38.852901],"type":"Point"}
}