{
  "type": "Feature",
  "properties": {
    "addr:full":"2709 W 38th Avenue Denver CO 80211",
    "addr:housenumber":"2709",
    "addr:postcode":"80211",
    "addr:street":"W 38Th Avenue",
    "iso:country":"US",
    "sg:address":"2709 W 38th Avenue",
    "sg:city":"Denver",
    "sg:classifiers":[
        {
            "category":"Shopping",
            "subcategory":"Florist",
            "type":"Retail Goods"
        }
    ],
    "sg:phone":"+1 303 477 7229",
    "sg:postcode":"80211",
    "sg:province":"CO",
    "wof:name":"Diz's Daisys Flower Shop",
    "wof:placetype":"venue"
},
  "geometry": {"coordinates":[-105.020833,39.769166],"type":"Point"}
}