{
  "type": "Feature",
  "properties": {
    "addr:full":"6731 S Gilpin Cir W Littleton CO 80122",
    "addr:housenumber":"6731",
    "addr:postcode":"80122",
    "addr:street":"S Gilpin Cir W",
    "iso:country":"US",
    "sg:address":"6731 S Gilpin Cir W",
    "sg:city":"Littleton",
    "sg:classifiers":[
        {
            "category":"Shopping",
            "type":"Retail Goods"
        }
    ],
    "sg:phone":"+1 303 795 3275",
    "sg:postcode":"80122",
    "sg:province":"CO",
    "sg:tags":[
        "cosmetic",
        "perfume"
    ],
    "wof:name":"Avon Independent Rep",
    "wof:placetype":"venue"
},
  "geometry": {"coordinates":[-104.969014,39.592689],"type":"Point"}
}