{
  "type": "Feature",
  "properties": {
    "iso:country":"US",
    "sg:address":"3560 E Orchard Rd",
    "sg:city":"Littleton",
    "sg:classifiers":[
        {
            "category":"Banks & Credit Unions",
            "subcategory":"Bank",
            "type":"Services"
        }
    ],
    "sg:phone":"+1 303 947 5124",
    "sg:postcode":"80121",
    "sg:province":"CO",
    "sg:tags":[
        "broker",
        "mortgage"
    ],
    "wof:name":"Platinum Lending",
    "wof:placetype":"venue"
},
  "geometry": {"coordinates":[-104.94425200000001,39.607749],"type":"Point"}
}