{
  "type": "Feature",
  "properties": {
    "iso:country":"US",
    "sg:address":"3000 E 1st Ave",
    "sg:city":"Denver",
    "sg:classifiers":[
        {
            "category":"Shopping",
            "subcategory":"Clothing, Apparel, & Fashions",
            "type":"Retail Goods"
        }
    ],
    "sg:phone":"+1 303 393 2902",
    "sg:postcode":"80206",
    "sg:province":"CO",
    "sg:tags":[
        "accessory",
        "clothing",
        "women's"
    ],
    "wof:name":"Cali & Mo",
    "wof:placetype":"venue"
},
  "geometry": {"coordinates":[-104.953288,39.717893],"type":"Point"}
}