{
  "type": "Feature",
  "properties": {
    "addr:full":"4127 Genoa St Denver CO 80249",
    "addr:housenumber":"4127",
    "addr:postcode":"80249",
    "addr:street":"Genoa St",
    "iso:country":"US",
    "sg:address":"4127 Genoa St",
    "sg:city":"Denver",
    "sg:classifiers":[
        {
            "category":"Retail",
            "subcategory":"Auto Repair",
            "type":"Services"
        }
    ],
    "sg:phone":"+1 303 574 0808",
    "sg:postcode":"80249",
    "sg:province":"CO",
    "sg:tags":[
        "road"
    ],
    "wof:name":"Tlc Flatmaster",
    "wof:placetype":"venue"
},
  "geometry": {"coordinates":[-104.756362,39.773075],"type":"Point"}
}