{
  "type": "Feature",
  "properties": {
    "iso:country":"US",
    "sg:address":"4606 Asbury Dr",
    "sg:city":"Castle Rock",
    "sg:classifiers":[
        {
            "category":"Mining & Drilling",
            "type":"Manufacturing & Wholesale Goods"
        }
    ],
    "sg:phone":"+1 720 733 0573",
    "sg:postcode":"80104",
    "sg:province":"CO",
    "sg:tags":[
        "company"
    ],
    "wof:name":"Newmont Mining",
    "wof:placetype":"venue"
},
  "geometry": {"coordinates":[-104.814013,39.374781],"type":"Point"}
}