{
  "type": "Feature",
  "properties": {
    "addr:full":"236 W 3rd St Eagle CO 81631",
    "addr:housenumber":"236",
    "addr:postcode":"81631",
    "addr:street":"W 3Rd St",
    "iso:country":"US",
    "sg:address":"236 W 3rd St",
    "sg:city":"Eagle",
    "sg:classifiers":[
        {
            "category":"Government",
            "subcategory":"Office",
            "type":"Public Place"
        }
    ],
    "sg:phone":"+1 970 328 6988",
    "sg:postcode":"81631",
    "sg:province":"CO",
    "sg:tags":[
        "federal"
    ],
    "wof:name":"Natural Resources Conservation",
    "wof:placetype":"venue"
},
  "geometry": {"coordinates":[-106.829263,39.654143],"type":"Point"}
}