{
  "type": "Feature",
  "properties": {
    "iso:country":"US",
    "sg:address":"380 Lashley St",
    "sg:city":"Longmont",
    "sg:classifiers":[
        {
            "category":"Organizations",
            "subcategory":"Non-profit Organization",
            "type":"Services"
        },
        {
            "category":"Health Services",
            "subcategory":"Clinic",
            "type":"Services"
        }
    ],
    "sg:phone":"+1 303 485 0023",
    "sg:postcode":"80501",
    "sg:province":"CO",
    "sg:tags":[
        "disability"
    ],
    "wof:name":"A Better Life Experience L L P",
    "wof:placetype":"venue"
},
  "geometry": {"coordinates":[-105.0881,40.16447],"type":"Point"}
}