{
  "type": "Feature",
  "properties": {
    "iso:country":"US",
    "sg:address":"7225 S Xanthia St",
    "sg:city":"Englewood",
    "sg:classifiers":[
        {
            "category":"Shopping",
            "subcategory":"Bicycles & Sporting Goods",
            "type":"Retail Goods"
        }
    ],
    "sg:phone":"+1 303 741 2085",
    "sg:postcode":"80112",
    "sg:province":"CO",
    "wof:name":"Fnshng TCH FN Arts Crfts",
    "wof:placetype":"venue"
},
  "geometry": {"coordinates":[-104.888976,39.585581],"type":"Point"}
}