{
  "type": "Feature",
  "properties": {
    "addr:full":"10251 E Powers Ave Englewood CO 80111",
    "addr:housenumber":"10251",
    "addr:postcode":"80111",
    "addr:street":"E Powers Ave",
    "iso:country":"US",
    "sg:address":"10251 E Powers Ave",
    "sg:city":"Englewood",
    "sg:classifiers":[
        {
            "category":"Professional",
            "type":"Services"
        }
    ],
    "sg:phone":"+1 303 741 4206",
    "sg:postcode":"80111",
    "sg:province":"CO",
    "wof:name":"Beda Intense LLC",
    "wof:placetype":"venue"
},
  "geometry": {"coordinates":[-104.870667,39.615701],"type":"Point"}
}