{
  "type": "Feature",
  "properties": {
    "addr:full":"1660 Wynkoop St Ste 925 Denver CO 80202",
    "addr:housenumber":"1660",
    "addr:postcode":"80202",
    "addr:street":"Wynkoop St Ste 925",
    "iso:country":"US",
    "sg:address":"1660 Wynkoop St Ste 925",
    "sg:city":"Denver",
    "sg:classifiers":[
        {
            "category":"Real Estate",
            "subcategory":"Architect",
            "type":"Services"
        }
    ],
    "sg:phone":"+1 303 832 2887",
    "sg:postcode":"80202",
    "sg:province":"CO",
    "wof:name":"Marasco Associates",
    "wof:placetype":"venue"
},
  "geometry": {"coordinates":[-105.00014,39.752117],"type":"Point"}
}