{
  "type": "Feature",
  "properties": {
    "addr:full":"64 el Jebel Rd Carbondale CO 81623",
    "addr:housenumber":"64",
    "addr:postcode":"81623",
    "addr:street":"El Jebel Rd",
    "iso:country":"US",
    "sg:address":"64 el Jebel Rd",
    "sg:city":"Carbondale",
    "sg:classifiers":[
        {
            "category":"Wholesale",
            "subcategory":"Auto Parts",
            "type":"Manufacturing & Wholesale Goods"
        }
    ],
    "sg:phone":"+1 970 963 0440",
    "sg:postcode":"81623",
    "sg:province":"CO",
    "wof:name":"El Jebel NAPA",
    "wof:placetype":"venue"
},
  "geometry": {"coordinates":[-107.090414,39.393411],"type":"Point"}
}