{
  "type": "Feature",
  "properties": {
    "iso:country":"US",
    "sg:address":"2500 47th St",
    "sg:city":"Boulder",
    "sg:classifiers":[
        {
            "category":"Wholesale",
            "subcategory":"Groceries",
            "type":"Manufacturing & Wholesale Goods"
        }
    ],
    "sg:phone":"+1 303 449 4674",
    "sg:postcode":"80301",
    "sg:province":"CO",
    "wof:name":"Hopi Bread Co",
    "wof:placetype":"venue"
},
  "geometry": {"coordinates":[-105.244128,40.025688],"type":"Point"}
}