{
  "type": "Feature",
  "properties": {
    "addr:full":"806 Garden Ln Lamar CO 81052",
    "addr:housenumber":"806",
    "addr:postcode":"81052",
    "addr:street":"Garden Ln",
    "iso:country":"US",
    "sg:address":"806 Garden Ln",
    "sg:city":"Lamar",
    "sg:classifiers":[
        {
            "category":"Building & Trades",
            "subcategory":"Construction",
            "type":"Services"
        }
    ],
    "sg:phone":"+1 719 336 9098",
    "sg:postcode":"81052",
    "sg:province":"CO",
    "sg:tags":[
        "excavating",
        "contractor"
    ],
    "wof:name":"Emick Excavating",
    "wof:placetype":"venue"
},
  "geometry": {"coordinates":[-102.628469,38.077023],"type":"Point"}
}