{
  "type": "Feature",
  "properties": {
    "iso:country":"US",
    "sg:address":"2000 S Colorado Blvd",
    "sg:city":"Denver",
    "sg:classifiers":[
        {
            "category":"Professional",
            "type":"Services"
        }
    ],
    "sg:phone":"+1 303 756 9096",
    "sg:postcode":"80222",
    "sg:province":"CO",
    "sg:tags":[
        "establishment"
    ],
    "wof:name":"Galloway Group",
    "wof:placetype":"venue"
},
  "geometry": {"coordinates":[-104.94068300000001,39.680097],"type":"Point"}
}