{
  "type": "Feature",
  "properties": {
    "addr:full":"2531 S Shields St Fort Collins CO 80526",
    "addr:housenumber":"2531",
    "addr:postcode":"80526",
    "addr:street":"S Shields St",
    "iso:country":"US",
    "sg:address":"2531 S Shields St",
    "sg:city":"Fort Collins",
    "sg:classifiers":[
        {
            "category":"Wholesale",
            "subcategory":"Office Equipment",
            "type":"Manufacturing & Wholesale Goods"
        }
    ],
    "sg:phone":"+1 970 482 8830",
    "sg:postcode":"80526",
    "sg:province":"CO",
    "sg:tags":[
        "machine",
        "duplicating",
        "copying"
    ],
    "sg:website":"www.ikon.com",
    "wof:name":"Ikon Office Solutions Inc",
    "wof:placetype":"venue"
},
  "geometry": {"coordinates":[-105.09617299999999,40.554745],"type":"Point"}
}