{
  "type": "Feature",
  "properties": {
    "addr:full":"624 Hwy 105 Monument CO 80132",
    "addr:housenumber":"624",
    "addr:postcode":"80132",
    "addr:street":"Hwy 105",
    "iso:country":"US",
    "sg:address":"624 Hwy 105",
    "sg:city":"Monument",
    "sg:classifiers":[
        {
            "category":"Restaurant",
            "type":"Food & Drink"
        }
    ],
    "sg:phone":"+1 719 488 1187",
    "sg:postcode":"80132",
    "sg:province":"CO",
    "sg:tags":[
        "eating"
    ],
    "wof:name":"Starbucks",
    "wof:placetype":"venue"
},
  "geometry": {"coordinates":[-104.83710600000001,39.093035],"type":"Point"}
}