{
  "type": "Feature",
  "properties": {
    "iso:country":"US",
    "sg:address":"29703 State Hwy 97",
    "sg:city":"Nucla",
    "sg:classifiers":[
        {
            "category":"Freight",
            "type":"Transportation"
        }
    ],
    "sg:phone":"+1 970 864 7662",
    "sg:postcode":"81424",
    "sg:province":"CO",
    "sg:tags":[
        "trucking"
    ],
    "wof:name":"Sutherland Brothers Inc",
    "wof:placetype":"venue"
},
  "geometry": {"coordinates":[-108.54599,38.257909],"type":"Point"}
}