{
  "type": "Feature",
  "properties": {
    "iso:country":"US",
    "sg:address":"1133 Patterson Rd",
    "sg:city":"Grand Junction",
    "sg:classifiers":[
        {
            "category":"Personal",
            "subcategory":"Beauty Salon",
            "type":"Services"
        }
    ],
    "sg:phone":"+1 970 241 1212",
    "sg:postcode":"81506",
    "sg:province":"CO",
    "sg:tags":[
        "shop"
    ],
    "wof:name":"Creative Hair Lines",
    "wof:placetype":"venue"
},
  "geometry": {"coordinates":[-108.552353,39.091854],"type":"Point"}
}