{
  "type": "Feature",
  "properties": {
    "addr:full":"215 31st St Boulder CO 80305",
    "addr:housenumber":"215",
    "addr:postcode":"80305",
    "addr:street":"31St St",
    "iso:country":"US",
    "sg:address":"215 31st St",
    "sg:city":"Boulder",
    "sg:classifiers":[
        {
            "category":"Professional",
            "subcategory":"Management & Consulting",
            "type":"Services"
        }
    ],
    "sg:phone":"+1 303 543 9290",
    "sg:postcode":"80305",
    "sg:province":"CO",
    "sg:tags":[
        "consultant",
        "business"
    ],
    "wof:name":"Light WORX Technology Cnsltng",
    "wof:placetype":"venue"
},
  "geometry": {"coordinates":[-105.25516399999999,39.997107],"type":"Point"}
}