{
  "type": "Feature",
  "properties": {
    "addr:full":"709 Palmer St Salida CO 81201",
    "addr:housenumber":"709",
    "addr:postcode":"81201",
    "addr:street":"Palmer St",
    "iso:country":"US",
    "sg:address":"709 Palmer St",
    "sg:city":"Salida",
    "sg:classifiers":[
        {
            "category":"Shopping",
            "subcategory":"Computers & Home Electronics",
            "type":"Retail Goods"
        }
    ],
    "sg:phone":"+1 719 539 9584",
    "sg:postcode":"81201",
    "sg:province":"CO",
    "sg:tags":[
        "software"
    ],
    "wof:name":"Brass Tacks Computer Svc",
    "wof:placetype":"venue"
},
  "geometry": {"coordinates":[-105.98972999999999,38.52484],"type":"Point"}
}