{
  "type": "Feature",
  "properties": {
    "iso:country":"US",
    "sg:address":"1975 Sheridan Blvd",
    "sg:city":"Edgewater",
    "sg:classifiers":[
        {
            "category":"Sports & Exercise",
            "subcategory":"Gym",
            "type":"Entertainment"
        }
    ],
    "sg:phone":"+1 303 233 2209",
    "sg:postcode":"80214",
    "sg:province":"CO",
    "sg:tags":[
        "club",
        "health",
        "studio",
        "gymnasium"
    ],
    "wof:name":"Jazzercise At Sloan's Lake",
    "wof:placetype":"venue"
},
  "geometry": {"coordinates":[-105.053291,39.745941],"type":"Point"}
}