{
  "type": "Feature",
  "properties": {
    "iso:country":"US",
    "sg:address":"2860 N Speer Boulevard",
    "sg:city":"Denver",
    "sg:classifiers":[
        {
            "category":"Social Services",
            "subcategory":"Child Care",
            "type":"Services"
        },
        {
            "category":"Education",
            "subcategory":"Preschool",
            "type":"Public Place"
        },
        {
            "category":"Education",
            "subcategory":"School",
            "type":"Public Place"
        }
    ],
    "sg:phone":"+1 303 477 3848",
    "sg:postcode":"80211",
    "sg:province":"CO",
    "sg:tags":[
        "elementary",
        "day"
    ],
    "sg:website":"www.creativebeginnings.org",
    "wof:name":"Creative Beginnings",
    "wof:placetype":"venue"
},
  "geometry": {"coordinates":[-105.020235,39.758062],"type":"Point"}
}