{
  "type": "Feature",
  "properties": {
    "addr:full":"19362 E Tufts Cir Aurora CO 80015",
    "addr:housenumber":"19362",
    "addr:postcode":"80015",
    "addr:street":"E Tufts Cir",
    "iso:country":"US",
    "sg:address":"19362 E Tufts Cir",
    "sg:city":"Aurora",
    "sg:classifiers":[
        {
            "category":"Wholesale",
            "subcategory":"Electrical",
            "type":"Manufacturing & Wholesale Goods"
        }
    ],
    "sg:phone":"+1 303 690 2036",
    "sg:postcode":"80015",
    "sg:province":"CO",
    "wof:name":"Bosnia Intl Co Ltd",
    "wof:placetype":"venue"
},
  "geometry": {"coordinates":[-104.76199800000001,39.63377],"type":"Point"}
}