{
  "type": "Feature",
  "properties": {
    "iso:country":"US",
    "sg:address":"3823 E 120th Ave",
    "sg:city":"Denver",
    "sg:classifiers":[
        {
            "category":"Shopping",
            "subcategory":"Pets & Pet Supplies",
            "type":"Retail Goods"
        }
    ],
    "sg:phone":"+1 303 452 2050",
    "sg:postcode":"80233",
    "sg:province":"CO",
    "sg:tags":[
        "store"
    ],
    "wof:name":"Pet Ranch",
    "wof:placetype":"venue"
},
  "geometry": {"coordinates":[-104.94266,39.913925],"type":"Point"}
}