{
  "type": "Feature",
  "properties": {
    "addr:full":"9964 W Canyon Ave Littleton CO 80127",
    "addr:housenumber":"9964",
    "addr:postcode":"80127",
    "addr:street":"W Canyon Ave",
    "iso:country":"US",
    "sg:address":"9964 W Canyon Ave",
    "sg:city":"Littleton",
    "sg:classifiers":[
        {
            "category":"Retail",
            "subcategory":"Repair Shop",
            "type":"Services"
        }
    ],
    "sg:phone":"+1 303 904 4455",
    "sg:postcode":"80127",
    "sg:province":"CO",
    "sg:tags":[
        "antique",
        "restoring"
    ],
    "wof:name":"All Things Wood",
    "wof:placetype":"venue"
},
  "geometry": {"coordinates":[-105.109162,39.575291],"type":"Point"}
}