{
  "type": "Feature",
  "properties": {
    "addr:full":"1677 W Evans Ave Denver CO 80223",
    "addr:housenumber":"1677",
    "addr:postcode":"80223",
    "addr:street":"W Evans Ave",
    "iso:country":"US",
    "sg:address":"1677 W Evans Ave",
    "sg:city":"Denver",
    "sg:classifiers":[
        {
            "category":"Autos & Motor Vehicles",
            "subcategory":"Fuel & Gas Station",
            "type":"Retail Goods"
        }
    ],
    "sg:phone":"+1 303 935 3336",
    "sg:postcode":"80223",
    "sg:province":"CO",
    "sg:tags":[
        "oil"
    ],
    "wof:name":"Number 1 Auto Recycling & Rpr",
    "wof:placetype":"venue"
},
  "geometry": {"coordinates":[-105.007892,39.678687],"type":"Point"}
}