{
  "type": "Feature",
  "properties": {
    "iso:country":"US",
    "sg:address":"3050 S Vrain St",
    "sg:city":"Denver",
    "sg:classifiers":[
        {
            "category":"Education",
            "subcategory":"School",
            "type":"Public Place"
        }
    ],
    "sg:phone":"+1 303 936 3413",
    "sg:postcode":"80236",
    "sg:province":"CO",
    "sg:website":"www.dpsk12.org",
    "wof:name":"Sabin Elementary School",
    "wof:placetype":"venue"
},
  "geometry": {"coordinates":[-105.04667999999999,39.659164],"type":"Point"}
}