{
  "type": "Feature",
  "properties": {
    "addr:full":"3229 Dillon Dr Pueblo CO 81008",
    "addr:housenumber":"3229",
    "addr:postcode":"81008",
    "addr:street":"Dillon Dr",
    "iso:country":"US",
    "sg:address":"3229 Dillon Dr",
    "sg:city":"Pueblo",
    "sg:classifiers":[
        {
            "category":"Personal",
            "subcategory":"Beauty Salon",
            "type":"Services"
        }
    ],
    "sg:phone":"+1 719 545 4334",
    "sg:postcode":"81008",
    "sg:province":"CO",
    "sg:tags":[
        "shop"
    ],
    "wof:name":"Mastercuts",
    "wof:placetype":"venue"
},
  "geometry": {"coordinates":[-104.606567,38.303055],"type":"Point"}
}