{
  "type": "Feature",
  "properties": {
    "iso:country":"US",
    "sg:address":"9960 Santa Fe Trl",
    "sg:city":"Trinidad",
    "sg:classifiers":[
        {
            "category":"Food & Beverages",
            "subcategory":"Groceries & Convenience Stores",
            "type":"Retail Goods"
        }
    ],
    "sg:phone":"+1 719 846 7076",
    "sg:postcode":"81082",
    "sg:province":"CO",
    "wof:name":"Trinidad Fuel Stop",
    "wof:placetype":"venue"
},
  "geometry": {"coordinates":[-104.520872,37.131751],"type":"Point"}
}