{
  "type": "Feature",
  "properties": {
    "iso:country":"US",
    "sg:address":"1275 Eagle Dr",
    "sg:city":"Loveland",
    "sg:classifiers":[
        {
            "category":"Banks & Credit Unions",
            "subcategory":"Bank",
            "type":"Services"
        }
    ],
    "sg:phone":"+1 970 461 0115",
    "sg:postcode":"80537",
    "sg:province":"CO",
    "wof:name":"US Bank",
    "wof:placetype":"venue"
},
  "geometry": {"coordinates":[-105.09802000000001,40.380727],"type":"Point"}
}