{
  "type": "Feature",
  "properties": {
    "addr:full":"16832 E Hialeah Ave Aurora CO 80015",
    "addr:housenumber":"16832",
    "addr:postcode":"80015",
    "addr:street":"E Hialeah Ave",
    "iso:country":"US",
    "sg:address":"16832 E Hialeah Ave",
    "sg:city":"Aurora",
    "sg:classifiers":[
        {
            "category":"Utilities",
            "subcategory":"Telephone",
            "type":"Services"
        }
    ],
    "sg:phone":"+1 303 693 7633",
    "sg:postcode":"80015",
    "sg:province":"CO",
    "sg:tags":[
        "communications"
    ],
    "wof:name":"NRG Communications LLC",
    "wof:placetype":"venue"
},
  "geometry": {"coordinates":[-104.793655,39.621702],"type":"Point"}
}