{
  "type": "Feature",
  "properties": {
    "addr:full":"5262 S Xenophon Ct Littleton CO 80127",
    "addr:housenumber":"5262",
    "addr:postcode":"80127",
    "addr:street":"S Xenophon Ct",
    "iso:country":"US",
    "sg:address":"5262 S Xenophon Ct",
    "sg:city":"Littleton",
    "sg:classifiers":[
        {
            "category":"Building & Trades",
            "subcategory":"Plumbing",
            "type":"Services"
        }
    ],
    "sg:phone":"+1 303 978 1405",
    "sg:postcode":"80127",
    "sg:province":"CO",
    "sg:tags":[
        "contractor",
        "general",
        "mechanical"
    ],
    "wof:name":"Westland Construction Inc",
    "wof:placetype":"venue"
},
  "geometry": {"coordinates":[-105.141999,39.621344],"type":"Point"}
}