{
  "type": "Feature",
  "properties": {
    "iso:country":"US",
    "sg:address":"802 16th St",
    "sg:city":"Greeley",
    "sg:classifiers":[
        {
            "category":"Wholesale",
            "subcategory":"Medical Equipment & Supplies",
            "type":"Manufacturing & Wholesale Goods"
        }
    ],
    "sg:phone":"+1 970 356 1506",
    "sg:postcode":"80631",
    "sg:province":"CO",
    "wof:name":"Lincare Inc",
    "wof:placetype":"venue"
},
  "geometry": {"coordinates":[-104.692367,40.413686],"type":"Point"}
}