{
  "type": "Feature",
  "properties": {
    "addr:full":"96 Co Rd 452 Grand Lake CO 80446",
    "addr:housenumber":"96",
    "addr:postcode":"80446",
    "addr:street":"Co Rd 452",
    "iso:country":"US",
    "sg:address":"96 Co Rd 452",
    "sg:city":"Grand Lake",
    "sg:classifiers":[
        {
            "category":"Professional",
            "type":"Services"
        }
    ],
    "sg:phone":"+1 970 627 0338",
    "sg:postcode":"80446",
    "sg:province":"CO",
    "sg:tags":[
        "establishment"
    ],
    "wof:name":"Eden Recor",
    "wof:placetype":"venue"
},
  "geometry": {"coordinates":[-105.887193,40.210031],"type":"Point"}
}