{
  "type": "Feature",
  "properties": {
    "addr:full":"5423 W 88th Ave Westminster CO 80031",
    "addr:housenumber":"5423",
    "addr:postcode":"80031",
    "addr:street":"W 88Th Ave",
    "iso:country":"US",
    "sg:address":"5423 W 88th Ave",
    "sg:city":"Westminster",
    "sg:classifiers":[
        {
            "category":"Shopping",
            "subcategory":"Jewelry",
            "type":"Retail Goods"
        }
    ],
    "sg:phone":"+1 303 428 9486",
    "sg:postcode":"80031",
    "sg:province":"CO",
    "wof:name":"Odyssey",
    "wof:placetype":"venue"
},
  "geometry": {"coordinates":[-105.061818,39.856565],"type":"Point"}
}