{
  "type": "Feature",
  "properties": {
    "addr:full":"20600 E Berry Dr Centennial CO 80015",
    "addr:housenumber":"20600",
    "addr:postcode":"80015",
    "addr:street":"E Berry Dr",
    "iso:country":"US",
    "sg:address":"20600 E Berry Dr",
    "sg:city":"Centennial",
    "sg:classifiers":[
        {
            "category":"Organizations",
            "subcategory":"Professional Association",
            "type":"Services"
        }
    ],
    "sg:phone":"+1 303 680 0753",
    "sg:postcode":"80015",
    "sg:province":"CO",
    "wof:name":"Park View Community",
    "wof:placetype":"venue"
},
  "geometry": {"coordinates":[-104.747326,39.614481],"type":"Point"}
}