{
  "type": "Feature",
  "properties": {
    "addr:full":"3419 W Eisenhower Blvd Loveland CO 80537",
    "addr:housenumber":"3419",
    "addr:postcode":"80537",
    "addr:street":"W Eisenhower Blvd",
    "iso:country":"US",
    "sg:address":"3419 W Eisenhower Blvd",
    "sg:city":"Loveland",
    "sg:classifiers":[
        {
            "category":"Building & Trades",
            "subcategory":"Construction",
            "type":"Services"
        }
    ],
    "sg:phone":"+1 970 663 0089",
    "sg:postcode":"80537",
    "sg:province":"CO",
    "sg:tags":[
        "general",
        "contractor"
    ],
    "wof:name":"Gerrard Construction Inc",
    "wof:placetype":"venue"
},
  "geometry": {"coordinates":[-105.12610599999999,40.407295],"type":"Point"}
}