{
  "type": "Feature",
  "properties": {
    "addr:full":"1965 W 38th Ave Denver CO 80211",
    "addr:housenumber":"1965",
    "addr:postcode":"80211",
    "addr:street":"W 38Th Ave",
    "iso:country":"US",
    "sg:address":"1965 W 38th Ave",
    "sg:city":"Denver",
    "sg:classifiers":[
        {
            "category":"Banks & Credit Unions",
            "subcategory":"Bank",
            "type":"Services"
        }
    ],
    "sg:phone":"+1 303 477 0051",
    "sg:postcode":"80211",
    "sg:province":"CO",
    "sg:tags":[
        "cashing",
        "agency",
        "check"
    ],
    "wof:name":"ACE Cash Express",
    "wof:placetype":"venue"
},
  "geometry": {"coordinates":[-105.010334,39.769361],"type":"Point"}
}