{
  "type": "Feature",
  "properties": {
    "addr:full":"4965 Co Rd 42 Yuma CO 80759",
    "addr:housenumber":"4965;42",
    "addr:postcode":"80759",
    "addr:street":"Co Rd",
    "iso:country":"US",
    "sg:address":"4965 Co Rd 42",
    "sg:city":"Yuma",
    "sg:phone":"+1 970 848 2707",
    "sg:postcode":"80759",
    "sg:province":"CO",
    "sg:tags":[
        "farm",
        "real",
        "property",
        "wheat",
        "lessor"
    ],
    "wof:name":"Keith Lillich",
    "wof:placetype":"venue"
},
  "geometry": {"coordinates":[-102.721085,40.176203],"type":"Point"}
}