{
  "type": "Feature",
  "properties": {
    "iso:country":"US",
    "sg:address":"3773 Cherry Creek Dr S",
    "sg:city":"Denver",
    "sg:classifiers":[
        {
            "category":"Banks & Credit Unions",
            "subcategory":"Investment Brokerage",
            "type":"Services"
        }
    ],
    "sg:phone":"+1 303 336 4000",
    "sg:postcode":"80209",
    "sg:province":"CO",
    "sg:tags":[
        "funds",
        "manager",
        "mutual"
    ],
    "wof:name":"Janus Capital Management LLC",
    "wof:placetype":"venue"
},
  "geometry": {"coordinates":[-104.945391,39.709221],"type":"Point"}
}