{
  "type": "Feature",
  "properties": {
    "addr:full":"3202 Cramer Ave Evans CO 80620",
    "addr:housenumber":"3202",
    "addr:postcode":"80620",
    "addr:street":"Cramer Ave",
    "iso:country":"US",
    "sg:address":"3202 Cramer Ave",
    "sg:city":"Evans",
    "sg:classifiers":[
        {
            "category":"Freight",
            "type":"Transportation"
        }
    ],
    "sg:phone":"+1 970 330 3638",
    "sg:postcode":"80620",
    "sg:province":"CO",
    "sg:tags":[
        "operator",
        "trucking"
    ],
    "wof:name":"Cherokee Feather Enterprises",
    "wof:placetype":"venue"
},
  "geometry": {"coordinates":[-104.711293,40.383036],"type":"Point"}
}