{
  "type": "Feature",
  "properties": {
    "iso:country":"US",
    "sg:address":"28031 Bonanza Dr",
    "sg:city":"Evergreen",
    "sg:classifiers":[
        {
            "category":"Banks & Credit Unions",
            "subcategory":"Bank",
            "type":"Services"
        }
    ],
    "sg:phone":"+1 303 670 5660",
    "sg:postcode":"80439",
    "sg:province":"CO",
    "sg:tags":[
        "loan",
        "real estate"
    ],
    "wof:name":"Aspen Funding",
    "wof:placetype":"venue"
},
  "geometry": {"coordinates":[-105.319226,39.553536],"type":"Point"}
}