{
  "type": "Feature",
  "properties": {
    "iso:country":"US",
    "sg:address":"630 E 4th Ave",
    "sg:city":"Durango",
    "sg:classifiers":[
        {
            "category":"Professional",
            "subcategory":"Detective & Security Services",
            "type":"Services"
        }
    ],
    "sg:phone":"+1 970 259 0626",
    "sg:postcode":"81301",
    "sg:province":"CO",
    "sg:tags":[
        "guard",
        "patrol"
    ],
    "wof:name":"Southwest Investigation Inc",
    "wof:placetype":"venue"
},
  "geometry": {"coordinates":[-107.877259,37.270003],"type":"Point"}
}