{
  "type": "Feature",
  "properties": {
    "addr:full":"598 S Spaulding Ave Pueblo West CO 81007",
    "addr:housenumber":"598",
    "addr:postcode":"81007",
    "addr:street":"S Spaulding Ave",
    "iso:country":"US",
    "sg:address":"598 S Spaulding Ave",
    "sg:city":"Pueblo West",
    "sg:classifiers":[
        {
            "category":"Education",
            "subcategory":"Special Training",
            "type":"Public Place"
        }
    ],
    "sg:phone":"+1 719 547 9795",
    "sg:postcode":"81007",
    "sg:province":"CO",
    "sg:tags":[
        "aircraft",
        "school"
    ],
    "wof:name":"Summit Helicopter Svc",
    "wof:placetype":"venue"
},
  "geometry": {"coordinates":[-104.77087299999999,38.31818],"type":"Point"}
}