{
  "type": "Feature",
  "properties": {
    "iso:country":"US",
    "sg:address":"2020 Wadsworth Blvd 18B",
    "sg:city":"Lakewood",
    "sg:classifiers":[
        {
            "category":"Health Services",
            "subcategory":"Doctor",
            "type":"Services"
        },
        {
            "category":"Health Services",
            "subcategory":"Clinic",
            "type":"Services"
        }
    ],
    "sg:phone":"+1 303 231 9700",
    "sg:postcode":"80214",
    "sg:province":"CO",
    "sg:tags":[
        "physician",
        "surgeon",
        "osteopathic"
    ],
    "wof:name":"David Leon Md",
    "wof:placetype":"venue"
},
  "geometry": {"coordinates":[-105.08140299999999,39.74778],"type":"Point"}
}