{
  "type": "Feature",
  "properties": {
    "iso:country":"US",
    "sg:address":"1052 S Gaylord St",
    "sg:city":"Denver",
    "sg:classifiers":[
        {
            "category":"Restaurant",
            "type":"Food & Drink"
        }
    ],
    "sg:phone":"+1 303 722 7456",
    "sg:postcode":"80209",
    "sg:province":"CO",
    "sg:tags":[
        "seafood"
    ],
    "sg:website":"www.maxgillandgrill.com",
    "wof:name":"Max Gill and Grill",
    "wof:placetype":"venue"
},
  "geometry": {"coordinates":[-104.961736,39.697444],"type":"Point"}
}