{
  "type": "Feature",
  "properties": {
    "iso:country":"US",
    "sg:address":"385 Anglers Dr",
    "sg:city":"Steamboat Spgs",
    "sg:classifiers":[
        {
            "category":"Shopping",
            "subcategory":"Crafts & Fabrics",
            "type":"Retail Goods"
        }
    ],
    "sg:phone":"+1 970 871 9888",
    "sg:postcode":"80487",
    "sg:province":"CO",
    "sg:tags":[
        "shop"
    ],
    "wof:name":"Piece By Piece Quilting & Home",
    "wof:placetype":"venue"
},
  "geometry": {"coordinates":[-106.82221199999999,40.46695],"type":"Point"}
}