{
  "type": "Feature",
  "properties": {
    "iso:country":"US",
    "sg:address":"1051 S Memphis St",
    "sg:city":"Aurora",
    "sg:classifiers":[
        {
            "category":"Shopping",
            "subcategory":"Catalog Store",
            "type":"Retail Goods"
        }
    ],
    "sg:phone":"+1 303 755 0442",
    "sg:postcode":"80017",
    "sg:province":"CO",
    "sg:tags":[
        "house",
        "mail"
    ],
    "wof:name":"CDK Enterprises Inc",
    "wof:placetype":"venue"
},
  "geometry": {"coordinates":[-104.798329,39.697536],"type":"Point"}
}