{
  "type": "Feature",
  "properties": {
    "iso:country":"US",
    "sg:address":"5727 Webster St",
    "sg:city":"Arvada",
    "sg:classifiers":[
        {
            "category":"Professional",
            "type":"Services"
        }
    ],
    "sg:phone":"+1 303 420 9947",
    "sg:postcode":"80002",
    "sg:province":"CO",
    "sg:tags":[
        "establishment"
    ],
    "wof:name":"Historic Olde Town Arvada",
    "wof:placetype":"venue"
},
  "geometry": {"coordinates":[-105.08014900000001,39.800604],"type":"Point"}
}