{
  "type": "Feature",
  "properties": {
    "addr:full":"9765 Tomahawk Trl Colorado Springs CO 80908",
    "addr:housenumber":"9765",
    "addr:postcode":"80908",
    "addr:street":"Tomahawk Trl",
    "iso:country":"US",
    "sg:address":"9765 Tomahawk Trl",
    "sg:city":"Colorado Springs",
    "sg:classifiers":[
        {
            "category":"Professional",
            "type":"Services"
        }
    ],
    "sg:phone":"+1 719 495 6297",
    "sg:postcode":"80908",
    "sg:province":"CO",
    "sg:tags":[
        "establishment"
    ],
    "wof:name":"Camerden & Camerden",
    "wof:placetype":"venue"
},
  "geometry": {"coordinates":[-104.64824900000001,38.974412],"type":"Point"}
}