{
  "type": "Feature",
  "properties": {
    "iso:country":"US",
    "sg:address":"1037 Lincoln St",
    "sg:city":"Denver",
    "sg:classifiers":[
        {
            "category":"Building & Trades",
            "subcategory":"Locksmith",
            "type":"Services"
        }
    ],
    "sg:phone":"+1 866 313 5850",
    "sg:postcode":"80203",
    "sg:province":"CO",
    "sg:tags":[
        "key"
    ],
    "wof:name":"24 Emergency Locksmith",
    "wof:placetype":"venue"
},
  "geometry": {"coordinates":[-104.98629200000001,39.73271],"type":"Point"}
}