{
  "type": "Feature",
  "properties": {
    "iso:country":"US",
    "sg:address":"467 Florida Acres Dr",
    "sg:city":"Durango",
    "sg:classifiers":[
        {
            "category":"Building & Trades",
            "subcategory":"Construction",
            "type":"Services"
        }
    ],
    "sg:phone":"+1 970 385 0707",
    "sg:postcode":"81303",
    "sg:province":"CO",
    "sg:tags":[
        "contractor"
    ],
    "wof:name":"Animas Kitchen & Bath",
    "wof:placetype":"venue"
},
  "geometry": {"coordinates":[-107.78908699999999,37.229289],"type":"Point"}
}