{
  "type": "Feature",
  "properties": {
    "iso:country":"US",
    "sg:address":"1468 Pearl St",
    "sg:city":"Boulder",
    "sg:classifiers":[
        {
            "category":"Restaurant",
            "type":"Food & Drink"
        }
    ],
    "sg:menulink":"http://www.allmenus.com/co/boulder/128500-subway/menu/",
    "sg:phone":"+1 720 565 6123",
    "sg:postcode":"80302",
    "sg:province":"CO",
    "sg:tags":[
        "american",
        "sandwich"
    ],
    "wof:name":"Subway",
    "wof:placetype":"venue"
},
  "geometry": {"coordinates":[-105.276224,40.018673],"type":"Point"}
}