{
  "type": "Feature",
  "properties": {
    "addr:full":"4915 Washington Street Denver CO 80216",
    "addr:housenumber":"4915",
    "addr:postcode":"80216",
    "addr:street":"Washington Street",
    "iso:country":"US",
    "sg:address":"4915 Washington Street",
    "sg:city":"Denver",
    "sg:classifiers":[
        {
            "category":"Food & Beverages",
            "subcategory":"Liquor & Beverages",
            "type":"Retail Goods"
        }
    ],
    "sg:phone":"+1 303 297 1399",
    "sg:postcode":"80216",
    "sg:province":"CO",
    "sg:tags":[
        "beer",
        "spirit",
        "wine"
    ],
    "wof:name":"Globe Liquors",
    "wof:placetype":"venue"
},
  "geometry": {"coordinates":[-104.978324,39.785786],"type":"Point"}
}