{
  "type": "Feature",
  "properties": {
    "addr:full":"205 S Main St Longmont CO 80501",
    "addr:housenumber":"205",
    "addr:postcode":"80501",
    "addr:street":"S Main St",
    "iso:country":"US",
    "sg:address":"205 S Main St",
    "sg:city":"Longmont",
    "sg:classifiers":[
        {
            "category":"Health Services",
            "subcategory":"Doctor",
            "type":"Services"
        }
    ],
    "sg:phone":"+1 303 532 2190",
    "sg:postcode":"80501",
    "sg:province":"CO",
    "sg:tags":[
        "physician",
        "surgeon"
    ],
    "wof:name":"Rocky Mountain Family Practice",
    "wof:placetype":"venue"
},
  "geometry": {"coordinates":[-105.102627,40.153778],"type":"Point"}
}