{
  "type": "Feature",
  "properties": {
    "iso:country":"US",
    "sg:address":"1735 York St",
    "sg:city":"Denver",
    "sg:classifiers":[
        {
            "category":"Social Services",
            "type":"Services"
        }
    ],
    "sg:phone":"+1 303 355 6414",
    "sg:postcode":"80206",
    "sg:province":"CO",
    "sg:tags":[
        "worker"
    ],
    "wof:name":"Julie Vanryswyk Msw",
    "wof:placetype":"venue"
},
  "geometry": {"coordinates":[-104.95983099999999,39.743712],"type":"Point"}
}