{
  "type": "Feature",
  "properties": {
    "iso:country":"US",
    "sg:address":"42145 Ridge Rd",
    "sg:city":"Parker",
    "sg:classifiers":[
        {
            "category":"Building & Trades",
            "subcategory":"Construction",
            "type":"Services"
        }
    ],
    "sg:phone":"+1 303 841 6242",
    "sg:postcode":"80105",
    "sg:province":"CO",
    "sg:tags":[
        "residential"
    ],
    "wof:name":"Rodney Stein Construction",
    "wof:placetype":"venue"
},
  "geometry": {"coordinates":[-104.20846899999999,39.490873],"type":"Point"}
}