{
  "type": "Feature",
  "properties": {
    "iso:country":"US",
    "sg:address":"3220 Co Rd 100",
    "sg:city":"Carbondale",
    "sg:classifiers":[
        {
            "category":"Building & Trades",
            "subcategory":"Construction",
            "type":"Services"
        }
    ],
    "sg:phone":"+1 970 704 0208",
    "sg:postcode":"81623",
    "sg:province":"CO",
    "sg:tags":[
        "general",
        "contractor"
    ],
    "wof:name":"Construction Fenton",
    "wof:placetype":"venue"
},
  "geometry": {"coordinates":[-107.15241899999999,39.407148],"type":"Point"}
}