{
  "type": "Feature",
  "properties": {
    "addr:full":"3195 Airport Rd Colorado Springs CO 80910",
    "addr:housenumber":"3195",
    "addr:postcode":"80910",
    "addr:street":"Airport Rd",
    "iso:country":"US",
    "sg:address":"3195 Airport Rd",
    "sg:city":"Colorado Springs",
    "sg:classifiers":[
        {
            "category":"Organizations",
            "subcategory":"Religious Organization",
            "type":"Services"
        }
    ],
    "sg:phone":"+1 719 473 7365",
    "sg:postcode":"80910",
    "sg:province":"CO",
    "sg:tags":[
        "church"
    ],
    "sg:website":"www.salembaptistcoloradosprings.org",
    "wof:name":"Salem Baptist Church Inc",
    "wof:placetype":"venue"
},
  "geometry": {"coordinates":[-104.77023800000001,38.825277],"type":"Point"}
}