{
  "type": "Feature",
  "properties": {
    "iso:country":"US",
    "sg:address":"5200 N Taft Hill Rd",
    "sg:city":"Fort Collins",
    "sg:classifiers":[
        {
            "category":"Farming",
            "subcategory":"Livestock Farm",
            "type":"Manufacturing & Wholesale Goods"
        }
    ],
    "sg:phone":"+1 970 407 9410",
    "sg:postcode":"80524",
    "sg:province":"CO",
    "sg:tags":[
        "beef",
        "feedlot",
        "cattle"
    ],
    "wof:name":"Mountain View Feeders",
    "wof:placetype":"venue"
},
  "geometry": {"coordinates":[-105.113384,40.661847],"type":"Point"}
}