{
  "type": "Feature",
  "properties": {
    "iso:country":"US",
    "sg:address":"14485 E Evans Ave",
    "sg:city":"Aurora",
    "sg:classifiers":[
        {
            "category":"Shopping",
            "subcategory":"Computers & Home Electronics",
            "type":"Retail Goods"
        }
    ],
    "sg:phone":"+1 303 283 1474",
    "sg:postcode":"80014",
    "sg:province":"CO",
    "sg:tags":[
        "software"
    ],
    "wof:name":"Computers In Ministry",
    "wof:placetype":"venue"
},
  "geometry": {"coordinates":[-104.820666,39.67916],"type":"Point"}
}