{
  "type": "Feature",
  "properties": {
    "addr:full":"18101 E 160th Ave Brighton CO 80601",
    "addr:housenumber":"18101",
    "addr:postcode":"80601",
    "addr:street":"E 160Th Ave",
    "iso:country":"US",
    "sg:address":"18101 E 160th Ave",
    "sg:city":"Brighton",
    "sg:classifiers":[
        {
            "category":"Retail",
            "subcategory":"Repair Shop",
            "type":"Services"
        }
    ],
    "sg:phone":"+1 303 659 2330",
    "sg:postcode":"80601",
    "sg:province":"CO",
    "sg:tags":[
        "scooter",
        "motorcycle",
        "motor"
    ],
    "wof:name":"JAM Racing",
    "wof:placetype":"venue"
},
  "geometry": {"coordinates":[-104.776194,39.986872],"type":"Point"}
}