{
  "type": "Feature",
  "properties": {
    "addr:full":"1099 S Gaylord St Denver CO 80209",
    "addr:housenumber":"1099",
    "addr:postcode":"80209",
    "addr:street":"S Gaylord St",
    "iso:country":"US",
    "sg:address":"1099 S Gaylord St",
    "sg:city":"Denver",
    "sg:classifiers":[
        {
            "category":"Shopping",
            "subcategory":"Clothing, Apparel, & Fashions",
            "type":"Retail Goods"
        }
    ],
    "sg:phone":"+1 303 777 0516",
    "sg:postcode":"80209",
    "sg:province":"CO",
    "wof:name":"Iris Fields",
    "wof:placetype":"venue"
},
  "geometry": {"coordinates":[-104.96173,39.698398],"type":"Point"}
}