{
  "type": "Feature",
  "properties": {
    "iso:country":"US",
    "sg:address":"508 Patty Dr",
    "sg:city":"Evergreen",
    "sg:classifiers":[
        {
            "category":"Professional",
            "subcategory":"Lawyer & Legal Services",
            "type":"Services"
        }
    ],
    "sg:phone":"+1 303 679 0995",
    "sg:postcode":"80439",
    "sg:province":"CO",
    "sg:tags":[
        "research"
    ],
    "sg:website":"www.courtroomperformance.com",
    "wof:name":"Courtroom Performance Inc",
    "wof:placetype":"venue"
},
  "geometry": {"coordinates":[-105.410032,39.64038],"type":"Point"}
}