{
  "type": "Feature",
  "properties": {
    "iso:country":"US",
    "sg:address":"308 Main St",
    "sg:city":"Wray",
    "sg:classifiers":[
        {
            "category":"Shopping",
            "subcategory":"Clothing, Apparel, & Fashions",
            "type":"Retail Goods"
        }
    ],
    "sg:phone":"+1 970 332 5845",
    "sg:postcode":"80758",
    "sg:province":"CO",
    "wof:name":"Rustic Rose",
    "wof:placetype":"venue"
},
  "geometry": {"coordinates":[-102.222003,40.078848],"type":"Point"}
}