{
  "type": "Feature",
  "properties": {
    "iso:country":"US",
    "sg:address":"225 W 12th St",
    "sg:city":"Leadville",
    "sg:classifiers":[
        {
            "category":"Building & Trades",
            "subcategory":"Construction",
            "type":"Services"
        }
    ],
    "sg:phone":"+1 719 486 3630",
    "sg:postcode":"80461",
    "sg:province":"CO",
    "sg:tags":[
        "house"
    ],
    "wof:name":"Todd Renovations",
    "wof:placetype":"venue"
},
  "geometry": {"coordinates":[-106.29618000000001,39.252916],"type":"Point"}
}