{
  "type": "Feature",
  "properties": {
    "iso:country":"US",
    "sg:address":"210 Seminole Dr",
    "sg:city":"Boulder",
    "sg:classifiers":[
        {
            "category":"Building & Trades",
            "subcategory":"Construction",
            "type":"Services"
        }
    ],
    "sg:phone":"+1 303 499 5115",
    "sg:postcode":"80303",
    "sg:province":"CO",
    "sg:tags":[
        "house"
    ],
    "wof:name":"Larry Hicks",
    "wof:placetype":"venue"
},
  "geometry": {"coordinates":[-105.230766,39.992824],"type":"Point"}
}