{
  "type": "Feature",
  "properties": {
    "iso:country":"US",
    "sg:address":"188 Rose Ln",
    "sg:city":"Montrose",
    "sg:classifiers":[
        {
            "category":"Organizations",
            "subcategory":"Community Association",
            "type":"Services"
        }
    ],
    "sg:phone":"+1 970 249 3943",
    "sg:postcode":"81401",
    "sg:province":"CO",
    "sg:tags":[
        "fraternal"
    ],
    "wof:name":"Masonic Lodge",
    "wof:placetype":"venue"
},
  "geometry": {"coordinates":[-107.85914,38.485382],"type":"Point"}
}