{
  "type": "Feature",
  "properties": {
    "iso:country":"US",
    "sg:address":"2223 E 128th Ave",
    "sg:city":"Denver",
    "sg:classifiers":[
        {
            "category":"Building & Trades",
            "subcategory":"Construction",
            "type":"Services"
        }
    ],
    "sg:phone":"+1 720 929 9124",
    "sg:postcode":"80241",
    "sg:province":"CO",
    "sg:tags":[
        "house"
    ],
    "wof:name":"Brittany Builders Sales Office",
    "wof:placetype":"venue"
},
  "geometry": {"coordinates":[-104.959085,39.928477],"type":"Point"}
}