{
  "type": "Feature",
  "properties": {
    "iso:country":"US",
    "sg:address":"451 E 58th Ave",
    "sg:city":"Denver",
    "sg:classifiers":[
        {
            "category":"Wholesale",
            "subcategory":"Apparel",
            "type":"Manufacturing & Wholesale Goods"
        }
    ],
    "sg:phone":"+1 303 292 3800",
    "sg:postcode":"80216",
    "sg:province":"CO",
    "wof:name":"Martin & Martin & Assoc",
    "wof:placetype":"venue"
},
  "geometry": {"coordinates":[-104.97712900000001,39.80195],"type":"Point"}
}