{
  "type": "Feature",
  "properties": {
    "iso:country":"US",
    "sg:address":"1591 Frank St",
    "sg:city":"Burlington",
    "sg:classifiers":[
        {
            "category":"Home & Garden",
            "subcategory":"Mobile Homes",
            "type":"Retail Goods"
        }
    ],
    "sg:phone":"+1 719 346 7715",
    "sg:postcode":"80807",
    "sg:province":"CO",
    "wof:name":"Colorado Comfort Homes LLC",
    "wof:placetype":"venue"
},
  "geometry": {"coordinates":[-102.26967500000001,39.299602],"type":"Point"}
}