{
  "type": "Feature",
  "properties": {
    "iso:country":"US",
    "sg:address":"519 16th St",
    "sg:city":"Denver",
    "sg:classifiers":[
        {
            "category":"Bars & Pubs",
            "type":"Food & Drink"
        },
        {
            "category":"Restaurant",
            "type":"Food & Drink"
        }
    ],
    "sg:phone":"+1 303 893 2000",
    "sg:postcode":"80202",
    "sg:province":"CO",
    "sg:website":"www.paramountcafe.com",
    "wof:name":"Paramount Cafe",
    "wof:placetype":"venue"
},
  "geometry": {"coordinates":[-104.990579,39.743992],"type":"Point"}
}