{
  "type": "Feature",
  "properties": {
    "addr:full":"905 Yuma St Colorado Springs CO 80909",
    "addr:housenumber":"905",
    "addr:postcode":"80909",
    "addr:street":"Yuma St",
    "iso:country":"US",
    "sg:address":"905 Yuma St",
    "sg:city":"Colorado Springs",
    "sg:classifiers":[
        {
            "category":"Building & Trades",
            "subcategory":"Plumbing",
            "type":"Services"
        }
    ],
    "sg:phone":"+1 719 473 8545",
    "sg:postcode":"80909",
    "sg:province":"CO",
    "sg:tags":[
        "plumbing",
        "heating",
        "contractor"
    ],
    "wof:name":"Jolly Plumbing & Heating Inc",
    "wof:placetype":"venue"
},
  "geometry": {"coordinates":[-104.778076,38.843468],"type":"Point"}
}