{
  "type": "Feature",
  "properties": {
    "addr:full":"59 S 1st Ave Brighton CO 80601",
    "addr:housenumber":"59",
    "addr:postcode":"80601",
    "addr:street":"S 1St Ave",
    "iso:country":"US",
    "sg:address":"59 S 1st Ave",
    "sg:city":"Brighton",
    "sg:classifiers":[
        {
            "category":"Shopping",
            "subcategory":"Bicycles & Sporting Goods",
            "type":"Retail Goods"
        }
    ],
    "sg:phone":"+1 303 659 3286",
    "sg:postcode":"80601",
    "sg:province":"CO",
    "wof:name":"Bait-N-Bullet Shop",
    "wof:placetype":"venue"
},
  "geometry": {"coordinates":[-104.822401,39.985871],"type":"Point"}
}