{
  "type": "Feature",
  "properties": {
    "iso:country":"US",
    "sg:address":"1708 Rolling Gate Rd",
    "sg:city":"Fort Collins",
    "sg:classifiers":[
        {
            "category":"Building & Trades",
            "subcategory":"Construction",
            "type":"Services"
        }
    ],
    "sg:phone":"+1 970 577 0675",
    "sg:postcode":"80526",
    "sg:province":"CO",
    "sg:tags":[
        "nonresidential"
    ],
    "wof:name":"Moenning & Assoc Inc",
    "wof:placetype":"venue"
},
  "geometry": {"coordinates":[-105.10724999999999,40.52796],"type":"Point"}
}