{
  "type": "Feature",
  "properties": {
    "iso:country":"US",
    "sg:address":"1590 Little Raven St",
    "sg:city":"Denver",
    "sg:classifiers":[
        {
            "category":"Food & Beverages",
            "subcategory":"Liquor & Beverages",
            "type":"Retail Goods"
        }
    ],
    "sg:phone":"+1 303 573 9463",
    "sg:postcode":"80202",
    "sg:province":"CO",
    "sg:tags":[
        "beer",
        "spirit",
        "wine"
    ],
    "sg:website":"www.littleravenvineyards.com",
    "wof:name":"Little Raven Vineyards",
    "wof:placetype":"venue"
},
  "geometry": {"coordinates":[-105.004997,39.754902],"type":"Point"}
}