{
  "type": "Feature",
  "properties": {
    "iso:country":"US",
    "sg:address":"3470 S Sherman St",
    "sg:city":"Englewood",
    "sg:classifiers":[
        {
            "category":"Real Estate",
            "subcategory":"Real Estate Agent",
            "type":"Services"
        }
    ],
    "sg:phone":"+1 303 761 3531",
    "sg:postcode":"80113",
    "sg:province":"CO",
    "wof:name":"Flanagan Lamee Real Estate LLC",
    "wof:placetype":"venue"
},
  "geometry": {"coordinates":[-104.985168,39.654471],"type":"Point"}
}