{
  "type": "Feature",
  "properties": {
    "addr:full":"452 W Morning Glory Dr Pueblo West CO 81007",
    "addr:housenumber":"452",
    "addr:postcode":"81007",
    "addr:street":"W Morning Glory Dr",
    "iso:country":"US",
    "sg:address":"452 W Morning Glory Dr",
    "sg:city":"Pueblo West",
    "sg:classifiers":[
        {
            "category":"Building & Trades",
            "subcategory":"Construction",
            "type":"Services"
        }
    ],
    "sg:phone":"+1 719 547 9442",
    "sg:postcode":"81007",
    "sg:province":"CO",
    "sg:tags":[
        "general",
        "contractor"
    ],
    "wof:name":"Y Construction Inc",
    "wof:placetype":"venue"
},
  "geometry": {"coordinates":[-104.761483,38.307526],"type":"Point"}
}