{
  "type": "Feature",
  "properties": {
    "iso:country":"US",
    "sg:address":"905 N College Ave",
    "sg:city":"Fort Collins",
    "sg:classifiers":[
        {
            "category":"Social Services",
            "type":"Services"
        }
    ],
    "sg:phone":"+1 970 472 9630",
    "sg:postcode":"80524",
    "sg:province":"CO",
    "sg:tags":[
        "senior",
        "citizen"
    ],
    "wof:name":"Volunteers Of America",
    "wof:placetype":"venue"
},
  "geometry": {"coordinates":[-105.076722,40.599869],"type":"Point"}
}