{
  "type": "Feature",
  "properties": {
    "addr:full":"1300 E Main St Montrose CO 81401",
    "addr:housenumber":"1300",
    "addr:postcode":"81401",
    "addr:street":"E Main St",
    "iso:country":"US",
    "sg:address":"1300 E Main St",
    "sg:city":"Montrose",
    "sg:classifiers":[
        {
            "category":"Shopping",
            "subcategory":"Jewelry",
            "type":"Retail Goods"
        }
    ],
    "sg:phone":"+1 970 249 4663",
    "sg:postcode":"81401",
    "sg:province":"CO",
    "sg:tags":[
        "jeweler"
    ],
    "wof:name":"Thurder Moon Turquoise Shop",
    "wof:placetype":"venue"
},
  "geometry": {"coordinates":[-107.867057,38.486094],"type":"Point"}
}