{
  "type": "Feature",
  "properties": {
    "addr:full":"628 S Hahns Peak Ave Pueblo CO 81007",
    "addr:housenumber":"628",
    "addr:postcode":"81007",
    "addr:street":"S Hahns Peak Ave",
    "iso:country":"US",
    "sg:address":"628 S Hahns Peak Ave",
    "sg:city":"Pueblo",
    "sg:classifiers":[
        {
            "category":"Building & Trades",
            "subcategory":"Construction",
            "type":"Services"
        }
    ],
    "sg:phone":"+1 719 584 3465",
    "sg:postcode":"81007",
    "sg:province":"CO",
    "sg:tags":[
        "general",
        "electrical",
        "contractor"
    ],
    "wof:name":"Royal T Construction",
    "wof:placetype":"venue"
},
  "geometry": {"coordinates":[-104.76227799999999,38.314696],"type":"Point"}
}