{
  "type": "Feature",
  "properties": {
    "iso:country":"US",
    "sg:address":"11545 W 102nd Ave",
    "sg:city":"Broomfield",
    "sg:classifiers":[
        {
            "category":"Professional",
            "type":"Services"
        }
    ],
    "sg:phone":"+1 303 465 5853",
    "sg:postcode":"80021",
    "sg:province":"CO",
    "sg:tags":[
        "establishment"
    ],
    "wof:name":"Bacon & Bacon",
    "wof:placetype":"venue"
},
  "geometry": {"coordinates":[-105.12768,39.880768],"type":"Point"}
}