{
  "type": "Feature",
  "properties": {
    "addr:full":"124 E Coal Creek Dr Superior CO 80027",
    "addr:housenumber":"124",
    "addr:postcode":"80027",
    "addr:street":"E Coal Creek Dr",
    "iso:country":"US",
    "sg:address":"124 E Coal Creek Dr",
    "sg:city":"Superior",
    "sg:classifiers":[
        {
            "category":"Government",
            "subcategory":"Office",
            "type":"Public Place"
        }
    ],
    "sg:phone":"+1 720 304 6797",
    "sg:postcode":"80027",
    "sg:province":"CO",
    "sg:tags":[
        "govt",
        "city"
    ],
    "wof:name":"Utilities & Public Works",
    "wof:placetype":"venue"
},
  "geometry": {"coordinates":[-105.166601,39.953974],"type":"Point"}
}