{
  "type": "Feature",
  "properties": {
    "addr:full":"747 Sheridan Blvd Denver CO 80214",
    "addr:housenumber":"747",
    "addr:postcode":"80214",
    "addr:street":"Sheridan Blvd",
    "iso:country":"US",
    "sg:address":"747 Sheridan Blvd",
    "sg:city":"Denver",
    "sg:classifiers":[
        {
            "category":"Wholesale",
            "subcategory":"Chemicals & Plastics",
            "type":"Manufacturing & Wholesale Goods"
        }
    ],
    "sg:phone":"+1 303 458 7474",
    "sg:postcode":"80214",
    "sg:province":"CO",
    "wof:name":"Med Mart Pacific Pulmonary",
    "wof:placetype":"venue"
},
  "geometry": {"coordinates":[-105.05332799999999,39.727398],"type":"Point"}
}