{
  "type": "Feature",
  "properties": {
    "iso:country":"US",
    "sg:address":"4744 Forest St",
    "sg:city":"Denver",
    "sg:classifiers":[
        {
            "category":"Personal",
            "type":"Services"
        }
    ],
    "sg:phone":"+1 303 322 3203",
    "sg:postcode":"80216",
    "sg:province":"CO",
    "sg:tags":[
        "mover"
    ],
    "wof:name":"1-800-Pack-Rat",
    "wof:placetype":"venue"
},
  "geometry": {"coordinates":[-104.926795,39.78231],"type":"Point"}
}