{
  "type": "Feature",
  "properties": {
    "iso:country":"US",
    "sg:address":"490 G Ave",
    "sg:city":"Limon",
    "sg:classifiers":[
        {
            "category":"Retail",
            "subcategory":"Portrait Studio",
            "type":"Services"
        }
    ],
    "sg:phone":"+1 719 775 2791",
    "sg:postcode":"80828",
    "sg:province":"CO",
    "sg:tags":[
        "photographer"
    ],
    "wof:name":"Schieffelin Photography",
    "wof:placetype":"venue"
},
  "geometry": {"coordinates":[-103.69054800000001,39.264683],"type":"Point"}
}