{
  "type": "Feature",
  "properties": {
    "iso:country":"US",
    "sg:address":"7145 S Vine Cir W",
    "sg:city":"Littleton",
    "sg:classifiers":[
        {
            "category":"Professional",
            "type":"Services"
        }
    ],
    "sg:phone":"+1 303 794 3081",
    "sg:postcode":"80122",
    "sg:province":"CO",
    "wof:name":"Tab It Inc",
    "wof:placetype":"venue"
},
  "geometry": {"coordinates":[-104.96504899999999,39.588251],"type":"Point"}
}