{
  "type": "Feature",
  "properties": {
    "iso:country":"US",
    "sg:address":"4221 W Eisenhower Blvd",
    "sg:city":"Loveland",
    "sg:classifiers":[
        {
            "category":"Freight",
            "type":"Transportation"
        }
    ],
    "sg:phone":"+1 970 635 0709",
    "sg:postcode":"80537",
    "sg:province":"CO",
    "sg:tags":[
        "operator",
        "local",
        "trucking"
    ],
    "wof:name":"R&M Hauling",
    "wof:placetype":"venue"
},
  "geometry": {"coordinates":[-105.136894,40.40742],"type":"Point"}
}