{
  "type": "Feature",
  "properties": {
    "addr:full":"2034 Snow Bowl Plz Steamboat Spgs CO 80487",
    "addr:housenumber":"2034",
    "addr:postcode":"80487",
    "addr:street":"Snow Bowl Plz;Spgs",
    "iso:country":"US",
    "sg:address":"2034 Snow Bowl Plz",
    "sg:city":"Steamboat Spgs",
    "sg:classifiers":[
        {
            "category":"Building & Trades",
            "subcategory":"Construction",
            "type":"Services"
        }
    ],
    "sg:phone":"+1 970 879 7529",
    "sg:postcode":"80487",
    "sg:province":"CO",
    "sg:tags":[
        "general",
        "contractor"
    ],
    "sg:website":"www.fox-construction.com",
    "wof:name":"Fox Construction Inc",
    "wof:placetype":"venue"
},
  "geometry": {"coordinates":[-106.870312,40.503221],"type":"Point"}
}