{
  "type": "Feature",
  "properties": {
    "addr:full":"7032 S Franklin St Centennial CO 80122",
    "addr:housenumber":"7032",
    "addr:postcode":"80122",
    "addr:street":"S Franklin St",
    "iso:country":"US",
    "sg:address":"7032 S Franklin St",
    "sg:city":"Centennial",
    "sg:classifiers":[
        {
            "category":"Social Services",
            "subcategory":"Adult Care",
            "type":"Services"
        }
    ],
    "sg:phone":"+1 303 797 3151",
    "sg:postcode":"80122",
    "sg:province":"CO",
    "sg:tags":[
        "home",
        "residential"
    ],
    "sg:website":"www.lifequalityhomesofdenver.com",
    "wof:name":"Life Quality Homes Of Denver",
    "wof:placetype":"venue"
},
  "geometry": {"coordinates":[-104.968013,39.588927],"type":"Point"}
}