{
  "type": "Feature",
  "properties": {
    "iso:country":"US",
    "sg:address":"333 W Colorado Ave",
    "sg:city":"Telluride",
    "sg:classifiers":[
        {
            "category":"Government",
            "subcategory":"Office",
            "type":"Public Place"
        }
    ],
    "sg:phone":"+1 970 728 4289",
    "sg:postcode":"81435",
    "sg:province":"CO",
    "wof:name":"San Miguel County Nursing Svc",
    "wof:placetype":"venue"
},
  "geometry": {"coordinates":[-107.813419,37.937911],"type":"Point"}
}