{
  "type": "Feature",
  "properties": {
    "iso:country":"US",
    "sg:address":"818 Carson Ave",
    "sg:city":"La Junta",
    "sg:classifiers":[
        {
            "category":"Wholesale",
            "subcategory":"Durable Goods & Equipment",
            "type":"Manufacturing & Wholesale Goods"
        }
    ],
    "sg:phone":"+1 719 384 4245",
    "sg:postcode":"81050",
    "sg:province":"CO",
    "sg:tags":[
        "sell",
        "firewood"
    ],
    "wof:name":"Rj Firewood Inc",
    "wof:placetype":"venue"
},
  "geometry": {"coordinates":[-103.5484,37.980696],"type":"Point"}
}