{
  "type": "Feature",
  "properties": {
    "iso:country":"US",
    "sg:address":"505 Bendemeer Dr",
    "sg:city":"Evergreen",
    "sg:classifiers":[
        {
            "category":"Home & Garden",
            "subcategory":"Building Materials",
            "type":"Retail Goods"
        }
    ],
    "sg:phone":"+1 303 670 1445",
    "sg:postcode":"80439",
    "sg:province":"CO",
    "sg:tags":[
        "door"
    ],
    "sg:website":"www.handcarveddoors.com",
    "wof:name":"Laughing Sun Hand Carvings",
    "wof:placetype":"venue"
},
  "geometry": {"coordinates":[-105.42257499999999,39.632686],"type":"Point"}
}