{
  "type": "Feature",
  "properties": {
    "iso:country":"US",
    "sg:address":"1300 S Abilene St",
    "sg:city":"Aurora",
    "sg:classifiers":[
        {
            "category":"Home & Garden",
            "subcategory":"Carpets & Floor Coverings",
            "type":"Retail Goods"
        }
    ],
    "sg:phone":"+1 303 369 8809",
    "sg:postcode":"80012",
    "sg:province":"CO",
    "sg:tags":[
        "dealer",
        "rug"
    ],
    "wof:name":"Carpet Mill Outlet Store",
    "wof:placetype":"venue"
},
  "geometry": {"coordinates":[-104.828239,39.693562],"type":"Point"}
}