{
  "type": "Feature",
  "properties": {
    "addr:full":"601 E Agate Ave Granby CO 80446",
    "addr:housenumber":"601",
    "addr:postcode":"80446",
    "addr:street":"E Agate Ave",
    "iso:country":"US",
    "sg:address":"601 E Agate Ave",
    "sg:city":"Granby",
    "sg:classifiers":[
        {
            "category":"Building & Trades",
            "subcategory":"Construction",
            "type":"Services"
        }
    ],
    "sg:phone":"+1 970 887 0358",
    "sg:postcode":"80446",
    "sg:province":"CO",
    "sg:tags":[
        "tile",
        "dealer"
    ],
    "wof:name":"American Tile Works Inc",
    "wof:placetype":"venue"
},
  "geometry": {"coordinates":[-105.93155,40.08487],"type":"Point"}
}