{
  "type": "Feature",
  "properties": {
    "addr:full":"30065 Co Rd 7 Idalia CO 80735",
    "addr:housenumber":"30065",
    "addr:postcode":"80735",
    "addr:street":"Co Rd 7 Idalia",
    "iso:country":"US",
    "sg:address":"30065 Co Rd 7",
    "sg:city":"Idalia",
    "sg:classifiers":[
        {
            "category":"Manufacturing",
            "subcategory":"Tools & Machinery",
            "type":"Manufacturing & Wholesale Goods"
        },
        {
            "category":"Mining & Drilling",
            "type":"Manufacturing & Wholesale Goods"
        }
    ],
    "sg:phone":"+1 970 354 7336",
    "sg:postcode":"80735",
    "sg:province":"CO",
    "sg:tags":[
        "development",
        "oil",
        "mfg",
        "industry",
        "gas",
        "exploration"
    ],
    "wof:name":"Bitter Creek Pipelines LLC",
    "wof:placetype":"venue"
},
  "geometry": {"coordinates":[-102.215913,39.673951],"type":"Point"}
}