{
  "type": "Feature",
  "properties": {
    "iso:country":"US",
    "sg:address":"37115 Broadway Ave",
    "sg:city":"Matheson",
    "sg:classifiers":[
        {
            "category":"Building & Trades",
            "subcategory":"Construction",
            "type":"Services"
        }
    ],
    "sg:phone":"+1 719 541 2196",
    "sg:postcode":"80830",
    "sg:province":"CO",
    "sg:tags":[
        "general",
        "contractor"
    ],
    "wof:name":"T P Home Improvements",
    "wof:placetype":"venue"
},
  "geometry": {"coordinates":[-103.974577,39.172098],"type":"Point"}
}