{
  "type": "Feature",
  "properties": {
    "addr:full":"620 E Main St Montrose CO 81401",
    "addr:housenumber":"620",
    "addr:postcode":"81401",
    "addr:street":"E Main St",
    "iso:country":"US",
    "sg:address":"620 E Main St",
    "sg:city":"Montrose",
    "sg:classifiers":[
        {
            "category":"Banks & Credit Unions",
            "subcategory":"Bank",
            "type":"Services"
        }
    ],
    "sg:phone":"+1 970 249 1500",
    "sg:postcode":"81401",
    "sg:province":"CO",
    "sg:tags":[
        "personal",
        "financing",
        "short",
        "institution",
        "business"
    ],
    "wof:name":"Citi Financial",
    "wof:placetype":"venue"
},
  "geometry": {"coordinates":[-107.873678,38.481456],"type":"Point"}
}