{
  "type": "Feature",
  "properties": {
    "iso:country":"US",
    "sg:address":"1625 Co Rd 111",
    "sg:city":"Carbondale",
    "sg:classifiers":[
        {
            "category":"Retail",
            "subcategory":"Animal Services",
            "type":"Services"
        }
    ],
    "sg:phone":"+1 970 963 1337",
    "sg:postcode":"81623",
    "sg:province":"CO",
    "sg:tags":[
        "specialty"
    ],
    "wof:name":"McIntyre Ranch",
    "wof:placetype":"venue"
},
  "geometry": {"coordinates":[-107.19286200000001,39.368835],"type":"Point"}
}