{
  "type": "Feature",
  "properties": {
    "addr:full":"1695 Wadsworth Blvd Lakewood CO 80214",
    "addr:housenumber":"1695",
    "addr:postcode":"80214",
    "addr:street":"Wadsworth Blvd",
    "iso:country":"US",
    "sg:address":"1695 Wadsworth Blvd",
    "sg:city":"Lakewood",
    "sg:classifiers":[
        {
            "category":"Retail",
            "subcategory":"Self-service Laundry",
            "type":"Services"
        }
    ],
    "sg:phone":"+1 303 232 7670",
    "sg:postcode":"80214",
    "sg:province":"CO",
    "wof:name":"Lakewood Laundromat",
    "wof:placetype":"venue"
},
  "geometry": {"coordinates":[-105.081423,39.742598],"type":"Point"}
}