{
  "type": "Feature",
  "properties": {
    "iso:country":"US",
    "sg:address":"215 Main St",
    "sg:city":"Silver Cliff",
    "sg:classifiers":[
        {
            "category":"Autos & Motor Vehicles",
            "subcategory":"Auto Supplies",
            "type":"Retail Goods"
        }
    ],
    "sg:phone":"+1 719 783 3281",
    "sg:postcode":"81252",
    "sg:province":"CO",
    "sg:tags":[
        "tire"
    ],
    "wof:name":"Western Tires Inc",
    "wof:placetype":"venue"
},
  "geometry": {"coordinates":[-105.468478,38.136109],"type":"Point"}
}