{
  "type": "Feature",
  "properties": {
    "addr:full":"2300 Krameria St Denver CO 80207",
    "addr:housenumber":"2300",
    "addr:postcode":"80207",
    "addr:street":"Krameria St",
    "iso:country":"US",
    "sg:address":"2300 Krameria St",
    "sg:city":"Denver",
    "sg:classifiers":[
        {
            "category":"Wholesale",
            "subcategory":"Jewelry",
            "type":"Manufacturing & Wholesale Goods"
        }
    ],
    "sg:phone":"+1 303 316 7570",
    "sg:postcode":"80207",
    "sg:province":"CO",
    "sg:tags":[
        "over",
        "retail",
        "art",
        "african"
    ],
    "wof:name":"Africa Direct",
    "wof:placetype":"venue"
},
  "geometry": {"coordinates":[-104.916335,39.752885],"type":"Point"}
}