{
  "type": "Feature",
  "properties": {
    "addr:full":"11475 Salem Ct Peyton CO 80831",
    "addr:housenumber":"11475",
    "addr:postcode":"80831",
    "addr:street":"Salem Ct",
    "iso:country":"US",
    "sg:address":"11475 Salem Ct",
    "sg:city":"Peyton",
    "sg:classifiers":[
        {
            "category":"Building & Trades",
            "subcategory":"Construction",
            "type":"Services"
        },
        {
            "category":"Wholesale",
            "subcategory":"Chemicals & Plastics",
            "type":"Manufacturing & Wholesale Goods"
        }
    ],
    "sg:phone":"+1 719 495 8850",
    "sg:postcode":"80831",
    "sg:province":"CO",
    "sg:tags":[
        "plastering",
        "product",
        "for",
        "coping",
        "spa",
        "tiling",
        "pool",
        "swimming"
    ],
    "wof:name":"S C C Pool & Spa",
    "wof:placetype":"venue"
},
  "geometry": {"coordinates":[-104.612916,38.971875],"type":"Point"}
}