{
  "type": "Feature",
  "properties": {
    "addr:full":"2580 Hwy 6 and 50 Grand Junction CO 81501",
    "addr:housenumber":"2580",
    "addr:postcode":"81501",
    "addr:street":"Hwy 6 And 50",
    "iso:country":"US",
    "sg:address":"2580 Hwy 6 and 50",
    "sg:city":"Grand Junction",
    "sg:classifiers":[
        {
            "category":"Home & Garden",
            "subcategory":"Furniture",
            "type":"Retail Goods"
        }
    ],
    "sg:phone":"+1 970 263 4433",
    "sg:postcode":"81501",
    "sg:province":"CO",
    "sg:website":"www.blackcarriagefurniture.com",
    "wof:name":"Black Carriage Furniture Inc",
    "wof:placetype":"venue"
},
  "geometry": {"coordinates":[-108.57090599999999,39.070319],"type":"Point"}
}