{
  "type": "Feature",
  "properties": {
    "iso:country":"US",
    "sg:address":"421 Co Rd 804",
    "sg:city":"Fraser",
    "sg:classifiers":[
        {
            "category":"Retail",
            "subcategory":"Auto Repair",
            "type":"Services"
        }
    ],
    "sg:phone":"+1 970 726 5841",
    "sg:postcode":"80442",
    "sg:province":"CO",
    "sg:tags":[
        "transmission"
    ],
    "wof:name":"Hilly's Hooker Svc",
    "wof:placetype":"venue"
},
  "geometry": {"coordinates":[-105.806432,39.944597],"type":"Point"}
}