{
  "type": "Feature",
  "properties": {
    "iso:country":"US",
    "sg:address":"3575 S Sherman St",
    "sg:city":"Englewood",
    "sg:classifiers":[
        {
            "category":"Insurance",
            "subcategory":"Hazard Insurance",
            "type":"Services"
        }
    ],
    "sg:phone":"+1 303 670 9600",
    "sg:postcode":"80113",
    "sg:province":"CO",
    "sg:tags":[
        "fidelity",
        "bond"
    ],
    "wof:name":"Rocky Mountain Surety",
    "wof:placetype":"venue"
},
  "geometry": {"coordinates":[-104.98532299999999,39.652723],"type":"Point"}
}