{
  "type": "Feature",
  "properties": {
    "addr:full":"13696 E. Alameda Avenue, #A Aurora CO 80012",
    "addr:housenumber":"13696",
    "addr:postcode":"80012",
    "addr:street":"E. Alameda Avenue # A",
    "iso:country":"US",
    "sg:address":"13696 E. Alameda Avenue, #A",
    "sg:city":"Aurora",
    "sg:classifiers":[
        {
            "category":"Professional",
            "subcategory":"Employment Agencies",
            "type":"Services"
        }
    ],
    "sg:phone":"+1 303 361 6894",
    "sg:postcode":"80012",
    "sg:province":"CO",
    "sg:tags":[
        "consultant",
        "opportunity",
        "screening",
        "resume"
    ],
    "sg:website":"http://denver.expresspros.com/?utm_source=yellowpages&utm_content=1022&utm_campaign=localmaps",
    "wof:name":"Express Employment Professionals - Staffing",
    "wof:placetype":"venue"
},
  "geometry": {"coordinates":[-104.828389,39.711102],"type":"Point"}
}