{
  "type": "Feature",
  "properties": {
    "iso:country":"US",
    "sg:address":"5640 Jarman St",
    "sg:city":"Colorado Springs",
    "sg:classifiers":[
        {
            "category":"Manufacturing",
            "subcategory":"Toys & Sporting Goods",
            "type":"Manufacturing & Wholesale Goods"
        }
    ],
    "sg:phone":"+1 719 538 9576",
    "sg:postcode":"80906",
    "sg:province":"CO",
    "sg:tags":[
        "durable",
        "merchandise",
        "mfg"
    ],
    "wof:name":"Brown Bear Enterprises",
    "wof:placetype":"venue"
},
  "geometry": {"coordinates":[-104.83934499999999,38.753907],"type":"Point"}
}