{
  "type": "Feature",
  "properties": {
    "iso:country":"US",
    "sg:address":"7125 W 88th Ave",
    "sg:city":"Broomfield",
    "sg:classifiers":[
        {
            "category":"Home & Garden",
            "subcategory":"Building Materials",
            "type":"Retail Goods"
        }
    ],
    "sg:phone":"+1 303 420 2498",
    "sg:postcode":"80021",
    "sg:province":"CO",
    "sg:website":"www.homedepot.com",
    "wof:name":"Home Depot",
    "wof:placetype":"venue"
},
  "geometry": {"coordinates":[-105.075603,39.856603],"type":"Point"}
}