{
  "type": "Feature",
  "properties": {
    "addr:full":"565 E 70th Ave Denver CO 80229",
    "addr:housenumber":"565",
    "addr:postcode":"80229",
    "addr:street":"E 70Th Ave",
    "iso:country":"US",
    "sg:address":"565 E 70th Ave",
    "sg:city":"Denver",
    "sg:classifiers":[
        {
            "category":"Shopping",
            "type":"Retail Goods"
        }
    ],
    "sg:phone":"+1 303 280 3087",
    "sg:postcode":"80229",
    "sg:province":"CO",
    "sg:tags":[
        "pet",
        "food",
        "supply"
    ],
    "wof:name":"Canine Automotive Restraint",
    "wof:placetype":"venue"
},
  "geometry": {"coordinates":[-104.98010499999999,39.82383],"type":"Point"}
}