{
  "type": "Feature",
  "properties": {
    "iso:country":"US",
    "sg:address":"1445 Market St",
    "sg:city":"Denver",
    "sg:classifiers":[
        {
            "category":"Restaurant",
            "type":"Food & Drink"
        }
    ],
    "sg:menulink":"http://www.allmenus.com/co/denver/14319-ruths-chris-steak-house/menu/",
    "sg:phone":"+1 303 446 2233",
    "sg:postcode":"80202",
    "sg:province":"CO",
    "sg:tags":[
        "american",
        "steakhouse"
    ],
    "wof:name":"Ruth's Chris Steak House",
    "wof:placetype":"venue"
},
  "geometry": {"coordinates":[-105.000114,39.748929],"type":"Point"}
}