{
  "type": "Feature",
  "properties": {
    "addr:full":"1840 Prospector Dr Leadville CO 80461",
    "addr:housenumber":"1840",
    "addr:postcode":"80461",
    "addr:street":"Prospector Dr",
    "iso:country":"US",
    "sg:address":"1840 Prospector Dr",
    "sg:city":"Leadville",
    "sg:classifiers":[
        {
            "category":"Professional",
            "subcategory":"Accounting & Tax Preparation",
            "type":"Services"
        }
    ],
    "sg:phone":"+1 970 389 4121",
    "sg:postcode":"80461",
    "sg:province":"CO",
    "sg:tags":[
        "billing"
    ],
    "wof:name":"Prospector Billing Svc",
    "wof:placetype":"venue"
},
  "geometry": {"coordinates":[-106.32273499999999,39.260426],"type":"Point"}
}