{
  "type": "Feature",
  "properties": {
    "addr:full":"1916 Sheldon Ave Colorado Springs CO 80904",
    "addr:housenumber":"1916",
    "addr:postcode":"80904",
    "addr:street":"Sheldon Ave",
    "iso:country":"US",
    "sg:address":"1916 Sheldon Ave",
    "sg:city":"Colorado Springs",
    "sg:classifiers":[
        {
            "category":"Home & Garden",
            "subcategory":"Garden Supply",
            "type":"Retail Goods"
        }
    ],
    "sg:phone":"+1 719 632 7779",
    "sg:postcode":"80904",
    "sg:province":"CO",
    "sg:tags":[
        "landscaping",
        "equipment"
    ],
    "wof:name":"Environmental Supply Inc",
    "wof:placetype":"venue"
},
  "geometry": {"coordinates":[-104.856843,38.840945],"type":"Point"}
}