{
  "type": "Feature",
  "properties": {
    "addr:full":"1562 Wildflower Pl Brighton CO 80601",
    "addr:housenumber":"1562",
    "addr:postcode":"80601",
    "addr:street":"Wildflower Pl",
    "iso:country":"US",
    "sg:address":"1562 Wildflower Pl",
    "sg:city":"Brighton",
    "sg:classifiers":[
        {
            "category":"Professional",
            "subcategory":"Research",
            "type":"Services"
        }
    ],
    "sg:phone":"+1 303 659 6183",
    "sg:postcode":"80601",
    "sg:province":"CO",
    "sg:tags":[
        "market",
        "analysis"
    ],
    "wof:name":"Present Futures Group",
    "wof:placetype":"venue"
},
  "geometry": {"coordinates":[-104.806516,39.963966],"type":"Point"}
}