{
  "type": "Feature",
  "properties": {
    "iso:country":"US",
    "sg:address":"335 I St",
    "sg:city":"Rock Springs",
    "sg:classifiers":[
        {
            "category":"Real Estate",
            "subcategory":"Real Estate Agent",
            "type":"Services"
        }
    ],
    "sg:phone":"+1 307 362 4400",
    "sg:postcode":"82901",
    "sg:province":"CO",
    "wof:name":"M & H Properties",
    "wof:placetype":"venue"
},
  "geometry": {"coordinates":[-109.210863,41.586983],"type":"Point"}
}