{
  "type": "Feature",
  "properties": {
    "iso:country":"US",
    "sg:address":"4725 S Monaco St",
    "sg:city":"Denver",
    "sg:classifiers":[
        {
            "category":"Health Services",
            "subcategory":"Health Practitioner",
            "type":"Services"
        }
    ],
    "sg:phone":"+1 303 796 9645",
    "sg:postcode":"80237",
    "sg:province":"CO",
    "sg:tags":[
        "physician"
    ],
    "wof:name":"Sylvia Flesner & Assocs",
    "wof:placetype":"venue"
},
  "geometry": {"coordinates":[-104.911332,39.628077],"type":"Point"}
}