{
  "type": "Feature",
  "properties": {
    "iso:country":"US",
    "sg:address":"1101 13th St",
    "sg:city":"Denver",
    "sg:classifiers":[
        {
            "category":"Arts & Performance",
            "subcategory":"Arts Center",
            "type":"Entertainment"
        },
        {
            "category":"Education",
            "subcategory":"School",
            "type":"Public Place"
        }
    ],
    "sg:phone":"+1 303 446 4892",
    "sg:postcode":"80204",
    "sg:province":"CO",
    "sg:tags":[
        "performing"
    ],
    "sg:website":"www.denvercenter.org",
    "wof:name":"Denver Center Theatre Academy",
    "wof:placetype":"venue"
},
  "geometry": {"coordinates":[-104.99849,39.744611],"type":"Point"}
}