{
  "type": "Feature",
  "properties": {
    "addr:full":"205 Camden Pl Boulder CO 80302",
    "addr:housenumber":"205",
    "addr:postcode":"80302",
    "addr:street":"Camden Pl",
    "iso:country":"US",
    "sg:address":"205 Camden Pl",
    "sg:city":"Boulder",
    "sg:classifiers":[
        {
            "category":"Professional",
            "subcategory":"Management & Consulting",
            "type":"Services"
        }
    ],
    "sg:phone":"+1 303 447 3566",
    "sg:postcode":"80302",
    "sg:province":"CO",
    "sg:tags":[
        "consultant",
        "lighting"
    ],
    "sg:website":"www.hpild.com",
    "wof:name":"Hefferan Partnership Inc",
    "wof:placetype":"venue"
},
  "geometry": {"coordinates":[-105.268433,39.996192],"type":"Point"}
}