{
  "type": "Feature",
  "properties": {
    "iso:country":"US",
    "sg:address":"1395 S Broadway",
    "sg:city":"Denver",
    "sg:classifiers":[
        {
            "category":"Autos & Motor Vehicles",
            "subcategory":"Automobile Sales",
            "type":"Retail Goods"
        }
    ],
    "sg:phone":"+1 303 778 1335",
    "sg:postcode":"80210",
    "sg:province":"CO",
    "sg:tags":[
        "car",
        "used",
        "dealer"
    ],
    "wof:name":"Davidson's Auto Sales",
    "wof:placetype":"venue"
},
  "geometry": {"coordinates":[-104.987544,39.692942],"type":"Point"}
}