{
  "type": "Feature",
  "properties": {
    "addr:full":"1775 Sherman St Ste 2870 Denver CO 80203",
    "addr:housenumber":"1775",
    "addr:postcode":"80203",
    "addr:street":"Sherman St Ste 2870",
    "iso:country":"US",
    "sg:address":"1775 Sherman St Ste 2870",
    "sg:city":"Denver",
    "sg:classifiers":[
        {
            "category":"Autos & Motor Vehicles",
            "subcategory":"Auto Supplies",
            "type":"Retail Goods"
        }
    ],
    "sg:phone":"+1 303 861 1974",
    "sg:postcode":"80203",
    "sg:province":"CO",
    "sg:tags":[
        "lube",
        "oil"
    ],
    "wof:name":"Marks T Keith Oil",
    "wof:placetype":"venue"
},
  "geometry": {"coordinates":[-104.984863,39.744465],"type":"Point"}
}