{
  "type": "Feature",
  "properties": {
    "iso:country":"US",
    "sg:address":"631 E Main St",
    "sg:city":"Cortez",
    "sg:classifiers":[
        {
            "category":"Real Estate",
            "subcategory":"Real Estate Services",
            "type":"Services"
        }
    ],
    "sg:phone":"+1 970 564 9770",
    "sg:postcode":"81321",
    "sg:province":"CO",
    "sg:tags":[
        "company",
        "title"
    ],
    "wof:name":"Colorado Land Title Co",
    "wof:placetype":"venue"
},
  "geometry": {"coordinates":[-108.575163,37.348702],"type":"Point"}
}