{
  "type": "Feature",
  "properties": {
    "iso:country":"US",
    "sg:address":"3720 Calhan Hwy",
    "sg:city":"Calhan",
    "sg:classifiers":[
        {
            "category":"Farming",
            "subcategory":"Livestock Farm",
            "type":"Manufacturing & Wholesale Goods"
        }
    ],
    "sg:phone":"+1 719 478 2781",
    "sg:postcode":"80808",
    "sg:province":"CO",
    "sg:tags":[
        "animal",
        "general"
    ],
    "wof:name":"Mountain Vista Ranch",
    "wof:placetype":"venue"
},
  "geometry": {"coordinates":[-104.259333,38.883101],"type":"Point"}
}