{
  "type": "Feature",
  "properties": {
    "iso:country":"US",
    "sg:address":"3470 S Sherman St",
    "sg:city":"Englewood",
    "sg:classifiers":[
        {
            "category":"Professional",
            "subcategory":"Lawyer & Legal Services",
            "type":"Services"
        }
    ],
    "sg:phone":"+1 303 789 2899",
    "sg:postcode":"80113",
    "sg:province":"CO",
    "sg:tags":[
        "attorney"
    ],
    "wof:name":"Palmer Goertzel & Assoc PC",
    "wof:placetype":"venue"
},
  "geometry": {"coordinates":[-104.985168,39.654471],"type":"Point"}
}