{
  "type": "Feature",
  "properties": {
    "addr:full":"3240 Tackhouse Rd Peyton CO 80831",
    "addr:postcode":"3240;80831",
    "addr:street":"Tackhouse Rd",
    "iso:country":"US",
    "sg:address":"3240 Tackhouse Rd",
    "sg:city":"Peyton",
    "sg:classifiers":[
        {
            "category":"Home & Garden",
            "subcategory":"Hardware",
            "type":"Retail Goods"
        }
    ],
    "sg:phone":"+1 719 337 8105",
    "sg:postcode":"80831",
    "sg:province":"CO",
    "sg:tags":[
        "tool",
        "used"
    ],
    "wof:name":"Richies's Tools",
    "wof:placetype":"venue"
},
  "geometry": {"coordinates":[-104.586598,38.879358],"type":"Point"}
}