{
  "type": "Feature",
  "properties": {
    "iso:country":"US",
    "sg:address":"15700 E Jamison Dr",
    "sg:city":"Englewood",
    "sg:classifiers":[
        {
            "category":"Building & Trades",
            "subcategory":"Construction",
            "type":"Services"
        }
    ],
    "sg:phone":"+1 303 766 2709",
    "sg:postcode":"80112",
    "sg:province":"CO",
    "sg:tags":[
        "home",
        "builder"
    ],
    "wof:name":"Savannah Construction",
    "wof:placetype":"venue"
},
  "geometry": {"coordinates":[-104.80665999999999,39.578784],"type":"Point"}
}