{
  "type": "Feature",
  "properties": {
    "iso:country":"US",
    "sg:address":"5150 N Union Blvd",
    "sg:city":"Colorado Springs",
    "sg:classifiers":[
        {
            "category":"Insurance",
            "subcategory":"Insurance Agent",
            "type":"Services"
        }
    ],
    "sg:phone":"+1 719 590 8696",
    "sg:postcode":"80918",
    "sg:province":"CO",
    "wof:name":"David Morriss",
    "wof:placetype":"venue"
},
  "geometry": {"coordinates":[-104.775144,38.905046],"type":"Point"}
}