{
  "type": "Feature",
  "properties": {
    "iso:country":"US",
    "sg:address":"14960 Tiboria Loop",
    "sg:city":"Peyton",
    "sg:classifiers":[
        {
            "category":"Real Estate",
            "subcategory":"Real Estate Agent",
            "type":"Services"
        }
    ],
    "sg:phone":"+1 719 749 0266",
    "sg:postcode":"80831",
    "sg:province":"CO",
    "wof:name":"Solutions & Results",
    "wof:placetype":"venue"
},
  "geometry": {"coordinates":[-104.51798100000001,39.043648],"type":"Point"}
}