{
  "type": "Feature",
  "properties": {
    "addr:full":"271 Hwy 105 Monument CO 80132",
    "addr:housenumber":"271",
    "addr:postcode":"80132",
    "addr:street":"Hwy 105",
    "iso:country":"US",
    "sg:address":"271 Hwy 105",
    "sg:city":"Monument",
    "sg:classifiers":[
        {
            "category":"Restaurant",
            "type":"Food & Drink"
        }
    ],
    "sg:phone":"+1 719 481 3404",
    "sg:postcode":"80132",
    "sg:province":"CO",
    "sg:tags":[
        "eating"
    ],
    "wof:name":"Monument Sub Shoppe & Deli",
    "wof:placetype":"venue"
},
  "geometry": {"coordinates":[-104.83208399999999,39.092812],"type":"Point"}
}