{
  "type": "Feature",
  "properties": {
    "addr:full":"835 Elk St Rock Springs CO 82901",
    "addr:housenumber":"835",
    "addr:postcode":"82901",
    "addr:street":"Elk St",
    "iso:country":"US",
    "sg:address":"835 Elk St",
    "sg:city":"Rock Springs",
    "sg:classifiers":[
        {
            "category":"Building & Trades",
            "subcategory":"Construction",
            "type":"Services"
        }
    ],
    "sg:phone":"+1 307 362 3302",
    "sg:postcode":"82901",
    "sg:province":"CO",
    "sg:tags":[
        "concrete",
        "contractor"
    ],
    "wof:name":"Chavez Concrete",
    "wof:placetype":"venue"
},
  "geometry": {"coordinates":[-109.227942,41.595189],"type":"Point"}
}