{
  "type": "Feature",
  "properties": {
    "iso:country":"US",
    "sg:address":"1414 N Academy Blvd",
    "sg:city":"Colorado Springs",
    "sg:classifiers":[
        {
            "category":"Wholesale",
            "subcategory":"Jewelry",
            "type":"Manufacturing & Wholesale Goods"
        }
    ],
    "sg:phone":"+1 719 491 7143",
    "sg:postcode":"80909",
    "sg:province":"CO",
    "sg:tags":[
        "stone"
    ],
    "wof:name":"Glitz Gems",
    "wof:placetype":"venue"
},
  "geometry": {"coordinates":[-104.756411,38.853611],"type":"Point"}
}