{
  "type": "Feature",
  "properties": {
    "addr:full":"2323 S Troy St Aurora CO 80014",
    "addr:housenumber":"2323",
    "addr:postcode":"80014",
    "addr:street":"S Troy St",
    "iso:country":"US",
    "sg:address":"2323 S Troy St",
    "sg:city":"Aurora",
    "sg:classifiers":[
        {
            "category":"Professional",
            "subcategory":"Management & Consulting",
            "type":"Services"
        }
    ],
    "sg:phone":"+1 303 340 8228",
    "sg:postcode":"80014",
    "sg:province":"CO",
    "sg:tags":[
        "communications",
        "consultant"
    ],
    "sg:website":"www.technologyplus.com",
    "wof:name":"Technology Plus Inc",
    "wof:placetype":"venue"
},
  "geometry": {"coordinates":[-104.839353,39.674703],"type":"Point"}
}