{
  "type": "Feature",
  "properties": {
    "addr:full":"606 Mountain View Ave Longmont CO 80501",
    "addr:housenumber":"606",
    "addr:postcode":"80501",
    "addr:street":"Mountain View Ave",
    "iso:country":"US",
    "sg:address":"606 Mountain View Ave",
    "sg:city":"Longmont",
    "sg:classifiers":[
        {
            "category":"Banks & Credit Unions",
            "subcategory":"Bank",
            "type":"Services"
        }
    ],
    "sg:phone":"+1 303 678 5777",
    "sg:postcode":"80501",
    "sg:province":"CO",
    "sg:tags":[
        "switching",
        "for"
    ],
    "wof:name":"NYCE Corporation",
    "wof:placetype":"venue"
},
  "geometry": {"coordinates":[-105.102419,40.181334],"type":"Point"}
}