{
  "type": "Feature",
  "properties": {
    "iso:country":"US",
    "sg:address":"22667 E Ida Ave",
    "sg:city":"Aurora",
    "sg:classifiers":[
        {
            "category":"Building & Trades",
            "subcategory":"Construction",
            "type":"Services"
        }
    ],
    "sg:phone":"+1 720 231 2144",
    "sg:postcode":"80015",
    "sg:province":"CO",
    "sg:tags":[
        "hanging",
        "contractor"
    ],
    "wof:name":"Rainbow Painting",
    "wof:placetype":"venue"
},
  "geometry": {"coordinates":[-104.723607,39.610385],"type":"Point"}
}