{
  "type": "Feature",
  "properties": {
    "addr:full":"619 Pueblo Ave Simla CO 80835",
    "addr:housenumber":"619",
    "addr:postcode":"80835",
    "addr:street":"Pueblo Ave",
    "iso:country":"US",
    "sg:address":"619 Pueblo Ave",
    "sg:city":"Simla",
    "sg:classifiers":[
        {
            "category":"Education",
            "subcategory":"School",
            "type":"Public Place"
        }
    ],
    "sg:phone":"+1 719 541 2291",
    "sg:postcode":"80835",
    "sg:province":"CO",
    "wof:name":"Big Sandy School",
    "wof:placetype":"venue"
},
  "geometry": {"coordinates":[-104.08225400000001,39.138905],"type":"Point"}
}