{
  "type": "Feature",
  "properties": {
    "addr:full":"5135 Ward Rd Wheat Ridge CO 80033",
    "addr:housenumber":"5135",
    "addr:postcode":"80033",
    "addr:street":"Ward Rd",
    "iso:country":"US",
    "sg:address":"5135 Ward Rd",
    "sg:city":"Wheat Ridge",
    "sg:classifiers":[
        {
            "category":"Building & Trades",
            "subcategory":"Construction",
            "type":"Services"
        }
    ],
    "sg:phone":"+1 303 423 6834",
    "sg:postcode":"80033",
    "sg:province":"CO",
    "sg:tags":[
        "heavy",
        "contractor"
    ],
    "wof:name":"D & B Drlg & Engrg Contracto",
    "wof:placetype":"venue"
},
  "geometry": {"coordinates":[-105.138052,39.787071],"type":"Point"}
}