{
  "type": "Feature",
  "properties": {
    "iso:country":"US",
    "sg:address":"18495 Co Rd 39",
    "sg:city":"Walsh",
    "sg:classifiers":[
        {
            "category":"Farming",
            "subcategory":"Livestock Farm",
            "type":"Manufacturing & Wholesale Goods"
        }
    ],
    "sg:phone":"+1 719 787 2030",
    "sg:postcode":"81090",
    "sg:province":"CO",
    "sg:tags":[
        "animal",
        "general"
    ],
    "wof:name":"J C Rivale",
    "wof:placetype":"venue"
},
  "geometry": {"coordinates":[-102.368089,37.258423],"type":"Point"}
}