{
  "type": "Feature",
  "properties": {
    "addr:full":"1434 Champa St Denver CO 80202",
    "addr:housenumber":"1434",
    "addr:postcode":"80202",
    "addr:street":"Champa St",
    "iso:country":"US",
    "sg:address":"1434 Champa St",
    "sg:city":"Denver",
    "sg:classifiers":[
        {
            "category":"Home & Garden",
            "subcategory":"Furniture",
            "type":"Retail Goods"
        }
    ],
    "sg:phone":"+1 303 534 7291",
    "sg:postcode":"80202",
    "sg:province":"CO",
    "sg:website":"www.davisandshaw.com",
    "wof:name":"Davis & Shaw Furniture Co Inc",
    "wof:placetype":"venue"
},
  "geometry": {"coordinates":[-104.99547200000001,39.745216],"type":"Point"}
}