{
  "type": "Feature",
  "properties": {
    "addr:full":"3345 Quail St Wheat Ridge CO 80033",
    "addr:housenumber":"3345",
    "addr:postcode":"80033",
    "addr:street":"Quail St",
    "iso:country":"US",
    "sg:address":"3345 Quail St",
    "sg:city":"Wheat Ridge",
    "sg:classifiers":[
        {
            "category":"Wholesale",
            "subcategory":"Toys & Hobbies",
            "type":"Manufacturing & Wholesale Goods"
        }
    ],
    "sg:phone":"+1 303 232 2080",
    "sg:postcode":"80033",
    "sg:province":"CO",
    "sg:tags":[
        "wholesaler"
    ],
    "wof:name":"Saving Places Bookmarks",
    "wof:placetype":"venue"
},
  "geometry": {"coordinates":[-105.123734,39.766381],"type":"Point"}
}