{
  "type": "Feature",
  "properties": {
    "iso:country":"US",
    "sg:address":"11410 Owl Pl",
    "sg:city":"Peyton",
    "sg:classifiers":[
        {
            "category":"Professional",
            "type":"Services"
        }
    ],
    "sg:phone":"+1 719 630 3321",
    "sg:postcode":"80831",
    "sg:province":"CO",
    "sg:tags":[
        "writer"
    ],
    "wof:name":"Hypocrisy Unlimited",
    "wof:placetype":"venue"
},
  "geometry": {"coordinates":[-104.61601,38.946273],"type":"Point"}
}