{
  "type": "Feature",
  "properties": {
    "addr:full":"2052 W 2nd St Rifle CO 81650",
    "addr:housenumber":"2052",
    "addr:postcode":"81650",
    "addr:street":"W 2Nd St",
    "iso:country":"US",
    "sg:address":"2052 W 2nd St",
    "sg:city":"Rifle",
    "sg:classifiers":[
        {
            "category":"Building & Trades",
            "subcategory":"Construction",
            "type":"Services"
        }
    ],
    "sg:phone":"+1 970 625 1484",
    "sg:postcode":"81650",
    "sg:province":"CO",
    "sg:tags":[
        "excavation",
        "contractor"
    ],
    "wof:name":"Runyan Sand & Gravel",
    "wof:placetype":"venue"
},
  "geometry": {"coordinates":[-107.807204,39.529878],"type":"Point"}
}