{
  "type": "Feature",
  "properties": {
    "addr:full":"9404 Co Rd 201 Limon CO 80828",
    "addr:housenumber":"9404;201",
    "addr:postcode":"limon;80828",
    "addr:street":"Co Rd",
    "iso:country":"US",
    "sg:address":"9404 Co Rd 201",
    "sg:city":"Limon",
    "sg:classifiers":[
        {
            "category":"Farming",
            "subcategory":"Livestock Farm",
            "type":"Manufacturing & Wholesale Goods"
        }
    ],
    "sg:phone":"+1 719 775 2539",
    "sg:postcode":"80828",
    "sg:province":"CO",
    "sg:tags":[
        "feedlot",
        "grain",
        "cash",
        "beef",
        "cattle"
    ],
    "wof:name":"Burton Hass",
    "wof:placetype":"venue"
},
  "geometry": {"coordinates":[-103.739842,39.003257],"type":"Point"}
}