{
  "type": "Feature",
  "properties": {
    "iso:country":"US",
    "sg:address":"2680 Jarett Dr",
    "sg:city":"Mead",
    "sg:classifiers":[
        {
            "category":"Building & Trades",
            "subcategory":"Plumbing",
            "type":"Services"
        }
    ],
    "sg:phone":"+1 303 772 4019",
    "sg:postcode":"80542",
    "sg:province":"CO",
    "sg:tags":[
        "septic"
    ],
    "wof:name":"Sullivan Septic",
    "wof:placetype":"venue"
},
  "geometry": {"coordinates":[-105.00564799999999,40.240984],"type":"Point"}
}