{
  "type": "Feature",
  "properties": {
    "addr:full":"320 S Lipan St Denver CO 80223",
    "addr:housenumber":"320",
    "addr:postcode":"80223",
    "addr:street":"S Lipan St",
    "iso:country":"US",
    "sg:address":"320 S Lipan St",
    "sg:city":"Denver",
    "sg:classifiers":[
        {
            "category":"Wholesale",
            "subcategory":"Stationery",
            "type":"Manufacturing & Wholesale Goods"
        }
    ],
    "sg:phone":"+1 720 570 5400",
    "sg:postcode":"80223",
    "sg:province":"CO",
    "sg:tags":[
        "product",
        "commercial"
    ],
    "wof:name":"Eon Office Products",
    "wof:placetype":"venue"
},
  "geometry": {"coordinates":[-105.00144400000001,39.710633],"type":"Point"}
}