{
  "type": "Feature",
  "properties": {
    "iso:country":"US",
    "sg:address":"5743 W 118th Cir",
    "sg:city":"Broomfield",
    "sg:classifiers":[
        {
            "category":"Building & Trades",
            "subcategory":"Plumbing",
            "type":"Services"
        }
    ],
    "sg:phone":"+1 303 404 3071",
    "sg:postcode":"80020",
    "sg:province":"CO",
    "sg:tags":[
        "heating",
        "contractor"
    ],
    "wof:name":"Preferred Heating & Air Cond",
    "wof:placetype":"venue"
},
  "geometry": {"coordinates":[-105.060631,39.911101],"type":"Point"}
}