{
  "type": "Feature",
  "properties": {
    "iso:country":"US",
    "sg:address":"1202 Bergen Pkwy",
    "sg:city":"Evergreen",
    "sg:classifiers":[
        {
            "category":"Insurance",
            "subcategory":"Insurance Agent",
            "type":"Services"
        }
    ],
    "sg:phone":"+1 303 670 2779",
    "sg:postcode":"80439",
    "sg:province":"CO",
    "wof:name":"AFLAC",
    "wof:placetype":"venue"
},
  "geometry": {"coordinates":[-105.35616899999999,39.693788],"type":"Point"}
}