{
  "type": "Feature",
  "properties": {
    "addr:full":"1229 Lake Plaza Dr Colorado Springs CO 80906",
    "addr:housenumber":"1229",
    "addr:postcode":"80906",
    "addr:street":"Lake Plaza Dr",
    "iso:country":"US",
    "sg:address":"1229 Lake Plaza Dr",
    "sg:city":"Colorado Springs",
    "sg:classifiers":[
        {
            "category":"Banks & Credit Unions",
            "subcategory":"Investment Brokerage",
            "type":"Services"
        }
    ],
    "sg:phone":"+1 719 579 6802",
    "sg:postcode":"80906",
    "sg:province":"CO",
    "sg:tags":[
        "stock",
        "bond"
    ],
    "wof:name":"Raymond James Financial Svc",
    "wof:placetype":"venue"
},
  "geometry": {"coordinates":[-104.805801,38.793352],"type":"Point"}
}