{
  "type": "Feature",
  "properties": {
    "addr:full":"3500 N Nevada Ave Colorado Springs CO 80907",
    "addr:housenumber":"3500",
    "addr:postcode":"80907",
    "addr:street":"N Nevada Ave",
    "iso:country":"US",
    "sg:address":"3500 N Nevada Ave",
    "sg:city":"Colorado Springs",
    "sg:classifiers":[
        {
            "category":"Insurance",
            "subcategory":"Hazard Insurance",
            "type":"Services"
        },
        {
            "category":"Insurance",
            "subcategory":"Insurance Agent",
            "type":"Services"
        }
    ],
    "sg:phone":"+1 719 630 2000",
    "sg:postcode":"80907",
    "sg:province":"CO",
    "sg:website":"www.farmersinsurance.com",
    "wof:name":"Farmers Insurance Group",
    "wof:placetype":"venue"
},
  "geometry": {"coordinates":[-104.81868,38.882695],"type":"Point"}
}