{
  "type": "Feature",
  "properties": {
    "iso:country":"US",
    "sg:address":"7500 E Arapahoe Rd",
    "sg:city":"Centennial",
    "sg:classifiers":[
        {
            "category":"Insurance",
            "subcategory":"Insurance Agent",
            "type":"Services"
        }
    ],
    "sg:phone":"+1 720 493 4493",
    "sg:postcode":"80112",
    "sg:province":"CO",
    "wof:name":"Susan Decarlo-Steele Agency",
    "wof:placetype":"venue"
},
  "geometry": {"coordinates":[-104.900227,39.594955],"type":"Point"}
}