{
  "type": "Feature",
  "properties": {
    "addr:full":"316 Evans St Lyons CO 80540",
    "addr:housenumber":"316",
    "addr:postcode":"80540",
    "addr:street":"Evans St",
    "iso:country":"US",
    "sg:address":"316 Evans St",
    "sg:city":"Lyons",
    "sg:classifiers":[
        {
            "category":"Retail",
            "subcategory":"Auto Repair",
            "type":"Services"
        }
    ],
    "sg:phone":"+1 303 823 6770",
    "sg:postcode":"80540",
    "sg:province":"CO",
    "sg:tags":[
        "road"
    ],
    "wof:name":"George's Towing",
    "wof:placetype":"venue"
},
  "geometry": {"coordinates":[-105.26960200000001,40.222699],"type":"Point"}
}