{
  "type": "Feature",
  "properties": {
    "addr:full":"9499 Sheridan Blvd Westminster CO 80031",
    "addr:housenumber":"9499",
    "addr:postcode":"80031",
    "addr:street":"Sheridan Blvd",
    "iso:country":"US",
    "sg:address":"9499 Sheridan Blvd",
    "sg:city":"Westminster",
    "sg:classifiers":[
        {
            "category":"Shopping",
            "subcategory":"Department Store",
            "type":"Retail Goods"
        }
    ],
    "sg:phone":"+1 303 427 4882",
    "sg:postcode":"80031",
    "sg:province":"CO",
    "sg:tags":[
        "discount"
    ],
    "wof:name":"Wal-Mart",
    "wof:placetype":"venue"
},
  "geometry": {"coordinates":[-105.05323300000001,39.86884],"type":"Point"}
}