{
  "type": "Feature",
  "properties": {
    "addr:full":"6503 Thompson Dr Fort Collins CO 80526",
    "addr:housenumber":"6503",
    "addr:postcode":"80526",
    "addr:street":"Thompson Dr",
    "iso:country":"US",
    "sg:address":"6503 Thompson Dr",
    "sg:city":"Fort Collins",
    "sg:classifiers":[
        {
            "category":"Wholesale",
            "subcategory":"Durable Goods & Equipment",
            "type":"Manufacturing & Wholesale Goods"
        }
    ],
    "sg:phone":"+1 970 207 1568",
    "sg:postcode":"80526",
    "sg:province":"CO",
    "wof:name":"United Plaster Supply LLC",
    "wof:placetype":"venue"
},
  "geometry": {"coordinates":[-105.102238,40.496861],"type":"Point"}
}