{
  "type": "Feature",
  "properties": {
    "iso:country":"US",
    "sg:address":"808 E Mulberry St",
    "sg:city":"Fort Collins",
    "sg:classifiers":[
        {
            "category":"Retail",
            "subcategory":"Auto Repair",
            "type":"Services"
        }
    ],
    "sg:phone":"+1 970 482 8355",
    "sg:postcode":"80524",
    "sg:province":"CO",
    "sg:tags":[
        "body",
        "automobile",
        "painting"
    ],
    "wof:name":"Advance Body Tek",
    "wof:placetype":"venue"
},
  "geometry": {"coordinates":[-105.063362,40.58157],"type":"Point"}
}