{
  "type": "Feature",
  "properties": {
    "addr:full":"600 Main Ave Durango CO 81301",
    "addr:housenumber":"600",
    "addr:postcode":"co 81301",
    "addr:street":"Main Ave",
    "iso:country":"US",
    "sg:address":"600 Main Ave",
    "sg:city":"Durango",
    "sg:classifiers":[
        {
            "category":"Shopping",
            "type":"Retail Goods"
        }
    ],
    "sg:phone":"+1 970 385 8568",
    "sg:postcode":"81301",
    "sg:province":"CO",
    "sg:tags":[
        "art",
        "gallery",
        "dealer"
    ],
    "wof:name":"Aspen Moon Gallery",
    "wof:placetype":"venue"
},
  "geometry": {"coordinates":[-107.88142499999999,37.271243],"type":"Point"}
}