{
  "type": "Feature",
  "properties": {
    "addr:full":"8101 E Prentice Ave Englewood CO 80111",
    "addr:housenumber":"8101",
    "addr:postcode":"80111",
    "addr:street":"E Prentice Ave",
    "iso:country":"US",
    "sg:address":"8101 E Prentice Ave",
    "sg:city":"Englewood",
    "sg:classifiers":[
        {
            "category":"Professional",
            "subcategory":"Computer Services",
            "type":"Services"
        }
    ],
    "sg:phone":"+1 720 256 4300",
    "sg:postcode":"80111",
    "sg:province":"CO",
    "sg:tags":[
        "design",
        "integration",
        "software"
    ],
    "wof:name":"Fujitsu Consulting",
    "wof:placetype":"venue"
},
  "geometry": {"coordinates":[-104.891942,39.620234],"type":"Point"}
}