{
  "type": "Feature",
  "properties": {
    "iso:country":"US",
    "sg:address":"1206 Luther St",
    "sg:city":"Eads",
    "sg:classifiers":[
        {
            "category":"Government",
            "subcategory":"Office",
            "type":"Public Place"
        }
    ],
    "sg:phone":"+1 719 438 5782",
    "sg:postcode":"81036",
    "sg:province":"CO",
    "sg:tags":[
        "county",
        "program",
        "health"
    ],
    "wof:name":"Kiowa County Health Nurse",
    "wof:placetype":"venue"
},
  "geometry": {"coordinates":[-102.78445600000001,38.480937],"type":"Point"}
}