{
  "type": "Feature",
  "properties": {
    "addr:full":"601 16th St Greeley CO 80631",
    "addr:housenumber":"601",
    "addr:postcode":"80631",
    "addr:street":"16Th St",
    "iso:country":"US",
    "sg:address":"601 16th St",
    "sg:city":"Greeley",
    "sg:classifiers":[
        {
            "category":"Building & Trades",
            "subcategory":"Construction",
            "type":"Services"
        }
    ],
    "sg:phone":"+1 970 392 9212",
    "sg:postcode":"80631",
    "sg:province":"CO",
    "sg:tags":[
        "carpenter"
    ],
    "wof:name":"Friebus Construction",
    "wof:placetype":"venue"
},
  "geometry": {"coordinates":[-104.68914599999999,40.413737],"type":"Point"}
}