{
  "type": "Feature",
  "properties": {
    "addr:full":"1523 Market St Denver CO 80202",
    "addr:housenumber":"1523",
    "addr:postcode":"80202",
    "addr:street":"Market St",
    "iso:country":"US",
    "sg:address":"1523 Market St",
    "sg:city":"Denver",
    "sg:classifiers":[
        {
            "category":"Building & Trades",
            "subcategory":"Locksmith",
            "type":"Services"
        }
    ],
    "sg:phone":"+1 303 557 6522",
    "sg:postcode":"80202",
    "sg:province":"CO",
    "sg:tags":[
        "key"
    ],
    "wof:name":"Akc 24 7 Locksmith Service Inc",
    "wof:placetype":"venue"
},
  "geometry": {"coordinates":[-104.999354,39.749256],"type":"Point"}
}