{
  "type": "Feature",
  "properties": {
    "addr:full":"3855 S Alicia Pkwy Aurora CO 80013",
    "addr:housenumber":"3855",
    "addr:postcode":"80013",
    "addr:street":"S Alicia Pkwy",
    "iso:country":"US",
    "sg:address":"3855 S Alicia Pkwy",
    "sg:city":"Aurora",
    "sg:classifiers":[
        {
            "category":"Education",
            "subcategory":"School",
            "type":"Public Place"
        }
    ],
    "sg:phone":"+1 720 886 8000",
    "sg:postcode":"80013",
    "sg:province":"CO",
    "sg:tags":[
        "elementary"
    ],
    "sg:website":"www.missionpossible.org",
    "wof:name":"Mission Viejo Elementary Schl",
    "wof:placetype":"venue"
},
  "geometry": {"coordinates":[-104.804059,39.647289],"type":"Point"}
}