{
  "type": "Feature",
  "properties": {
    "addr:full":"7361 Utica St Westminster CO 80030",
    "addr:housenumber":"7361",
    "addr:postcode":"80030",
    "addr:street":"Utica St",
    "iso:country":"US",
    "sg:address":"7361 Utica St",
    "sg:city":"Westminster",
    "sg:classifiers":[
        {
            "category":"Organizations",
            "subcategory":"Religious Organization",
            "type":"Services"
        }
    ],
    "sg:phone":"+1 303 650 6359",
    "sg:postcode":"80030",
    "sg:province":"CO",
    "sg:tags":[
        "church"
    ],
    "wof:name":"Church For Better Living",
    "wof:placetype":"venue"
},
  "geometry": {"coordinates":[-105.045529,39.829882],"type":"Point"}
}