{
  "type": "Feature",
  "properties": {
    "iso:country":"US",
    "sg:address":"288 Clayton Street",
    "sg:city":"Denver",
    "sg:classifiers":[
        {
            "category":"Personal",
            "subcategory":"Nail Salon",
            "type":"Services"
        }
    ],
    "sg:phone":"+1 303 321 7655",
    "sg:postcode":"80206",
    "sg:province":"CO",
    "wof:name":"Nail Affairs of Cherry Creek",
    "wof:placetype":"venue"
},
  "geometry": {"coordinates":[-104.955789,39.720706],"type":"Point"}
}