{
  "type": "Feature",
  "properties": {
    "addr:full":"546 Clover Ln Boulder CO 80303",
    "addr:housenumber":"546",
    "addr:postcode":"80303",
    "addr:street":"Clover Ln",
    "iso:country":"US",
    "sg:address":"546 Clover Ln",
    "sg:city":"Boulder",
    "sg:classifiers":[
        {
            "category":"Building & Trades",
            "subcategory":"Plumbing",
            "type":"Services"
        }
    ],
    "sg:phone":"+1 303 494 0608",
    "sg:postcode":"80303",
    "sg:province":"CO",
    "sg:tags":[
        "plumbing",
        "contractor"
    ],
    "wof:name":"Ritter Plumbing & Heating Inc",
    "wof:placetype":"venue"
},
  "geometry": {"coordinates":[-105.181123,39.998543],"type":"Point"}
}