{
  "type": "Feature",
  "properties": {
    "iso:country":"US",
    "sg:address":"9308 W Plymouth Ave",
    "sg:city":"Littleton",
    "sg:classifiers":[
        {
            "category":"Building & Trades",
            "subcategory":"Construction",
            "type":"Services"
        }
    ],
    "sg:phone":"+1 303 948 5507",
    "sg:postcode":"80128",
    "sg:province":"CO",
    "sg:tags":[
        "home",
        "builder"
    ],
    "wof:name":"Genesis Homes",
    "wof:placetype":"venue"
},
  "geometry": {"coordinates":[-105.104253,39.590998],"type":"Point"}
}