{
  "type": "Feature",
  "properties": {
    "addr:full":"1323 Santa Fe Dr Pueblo CO 81006",
    "addr:housenumber":"1323",
    "addr:postcode":"81006",
    "addr:street":"Santa Fe Dr",
    "iso:country":"US",
    "sg:address":"1323 Santa Fe Dr",
    "sg:city":"Pueblo",
    "sg:classifiers":[
        {
            "category":"Real Estate",
            "subcategory":"Real Estate Agent",
            "type":"Services"
        }
    ],
    "sg:phone":"+1 719 542 7312",
    "sg:postcode":"81006",
    "sg:province":"CO",
    "wof:name":"Vigil & Assoc Inc",
    "wof:placetype":"venue"
},
  "geometry": {"coordinates":[-104.58418,38.245752],"type":"Point"}
}