{
  "type": "Feature",
  "properties": {
    "iso:country":"US",
    "sg:address":"635 W Corona Ave",
    "sg:city":"Pueblo",
    "sg:classifiers":[
        {
            "category":"Insurance",
            "subcategory":"Insurance Agent",
            "type":"Services"
        }
    ],
    "sg:phone":"+1 719 545 0535",
    "sg:postcode":"81004",
    "sg:province":"CO",
    "wof:name":"Medina Insurance Co",
    "wof:placetype":"venue"
},
  "geometry": {"coordinates":[-104.62548099999999,38.265533],"type":"Point"}
}