{
  "type": "Feature",
  "properties": {
    "addr:full":"5775 S Andes St Aurora CO 80015",
    "addr:housenumber":"5775",
    "addr:postcode":"80015",
    "addr:street":"S Andes St",
    "iso:country":"US",
    "sg:address":"5775 S Andes St",
    "sg:city":"Aurora",
    "sg:classifiers":[
        {
            "category":"Restaurant",
            "type":"Food & Drink"
        },
        {
            "category":"Ice Cream",
            "type":"Food & Drink"
        }
    ],
    "sg:phone":"+1 720 949 0022",
    "sg:postcode":"80015",
    "sg:province":"CO",
    "sg:tags":[
        "frozen",
        "dessert"
    ],
    "wof:name":"Dip N Delights",
    "wof:placetype":"venue"
},
  "geometry": {"coordinates":[-104.77217899999999,39.61272],"type":"Point"}
}