{
  "type": "Feature",
  "properties": {
    "addr:full":"1160 Grand Ave Del Norte CO 81132",
    "addr:housenumber":"1160",
    "addr:postcode":"norte;81132",
    "addr:street":"Grand Ave",
    "iso:country":"US",
    "sg:address":"1160 Grand Ave",
    "sg:city":"Del Norte",
    "sg:classifiers":[
        {
            "category":"Travel",
            "subcategory":"Hotels & Motels",
            "type":"Entertainment"
        }
    ],
    "sg:phone":"+1 719 657 3332",
    "sg:postcode":"81132",
    "sg:province":"CO",
    "sg:website":"www.el-rancho-motel.com",
    "wof:name":"El Rancho Motel",
    "wof:placetype":"venue"
},
  "geometry": {"coordinates":[-106.347168,37.678317],"type":"Point"}
}