{
  "type": "Feature",
  "properties": {
    "addr:full":"302 Hanson Ranch Rd Vail CO 81657",
    "addr:housenumber":"302",
    "addr:postcode":"81657",
    "addr:street":"Hanson Ranch Rd",
    "iso:country":"US",
    "sg:address":"302 Hanson Ranch Rd",
    "sg:city":"Vail",
    "sg:classifiers":[
        {
            "category":"Banks & Credit Unions",
            "subcategory":"Bank",
            "type":"Services"
        }
    ],
    "sg:phone":"+1 970 476 2905",
    "sg:postcode":"81657",
    "sg:province":"CO",
    "sg:tags":[
        "national",
        "commercial"
    ],
    "wof:name":"Weststar Bank",
    "wof:placetype":"venue"
},
  "geometry": {"coordinates":[-106.372818,39.640122],"type":"Point"}
}