{
  "type": "Feature",
  "properties": {
    "iso:country":"US",
    "sg:address":"7148 N Academy Blvd",
    "sg:city":"Colorado Springs",
    "sg:classifiers":[
        {
            "category":"Restaurant",
            "type":"Food & Drink"
        }
    ],
    "sg:menulink":"http://www.allmenus.com/co/colorado-springs/39971-pei-wei/menu/",
    "sg:phone":"+1 719 260 9922",
    "sg:postcode":"80920",
    "sg:province":"CO",
    "sg:tags":[
        "chinese",
        "vietnamese",
        "japanese",
        "asian",
        "korean",
        "thai"
    ],
    "wof:name":"Pei Wei",
    "wof:placetype":"venue"
},
  "geometry": {"coordinates":[-104.797679,38.935342],"type":"Point"}
}