{
  "type": "Feature",
  "properties": {
    "iso:country":"US",
    "sg:address":"645 Kayenta Ct",
    "sg:city":"Grand Junction",
    "sg:classifiers":[
        {
            "category":"Real Estate",
            "subcategory":"Real Estate Operator",
            "type":"Services"
        }
    ],
    "sg:phone":"+1 970 257 9112",
    "sg:postcode":"81503",
    "sg:province":"CO",
    "sg:tags":[
        "building",
        "nonresidential"
    ],
    "wof:name":"Cafarelli Properties LLC",
    "wof:placetype":"venue"
},
  "geometry": {"coordinates":[-108.696521,39.098286],"type":"Point"}
}