{
  "type": "Feature",
  "properties": {
    "addr:full":"500 E 84th Ave Denver CO 80229",
    "addr:housenumber":"500",
    "addr:postcode":"80229",
    "addr:street":"E 84Th Ave",
    "iso:country":"US",
    "sg:address":"500 E 84th Ave",
    "sg:city":"Denver",
    "sg:classifiers":[
        {
            "category":"Shopping",
            "subcategory":"Clothing, Apparel, & Fashions",
            "type":"Retail Goods"
        }
    ],
    "sg:phone":"+1 303 289 1929",
    "sg:postcode":"80229",
    "sg:province":"CO",
    "sg:tags":[
        "t"
    ],
    "wof:name":"Valley Roundup",
    "wof:placetype":"venue"
},
  "geometry": {"coordinates":[-104.981127,39.848867],"type":"Point"}
}