{
  "type": "Feature",
  "properties": {
    "iso:country":"US",
    "sg:address":"4340 E Kentucky Ave",
    "sg:city":"Denver",
    "sg:classifiers":[
        {
            "category":"Building & Trades",
            "subcategory":"Construction",
            "type":"Services"
        }
    ],
    "sg:phone":"+1 303 504 9364",
    "sg:postcode":"80246",
    "sg:province":"CO",
    "sg:tags":[
        "woodworker"
    ],
    "wof:name":"Farhad's",
    "wof:placetype":"venue"
},
  "geometry": {"coordinates":[-104.939211,39.700119],"type":"Point"}
}