{
  "type": "Feature",
  "properties": {
    "addr:full":"1660 Lincoln St Denver CO 80264",
    "addr:housenumber":"1660",
    "addr:postcode":"80264",
    "addr:street":"Lincoln St",
    "iso:country":"US",
    "sg:address":"1660 Lincoln St",
    "sg:city":"Denver",
    "sg:classifiers":[
        {
            "category":"Professional",
            "subcategory":"Lawyer & Legal Services",
            "type":"Services"
        }
    ],
    "sg:phone":"+1 303 813 9808",
    "sg:postcode":"80264",
    "sg:province":"CO",
    "wof:name":"Wiebe Peter Atty",
    "wof:placetype":"venue"
},
  "geometry": {"coordinates":[-104.986,39.742401],"type":"Point"}
}