{
  "type": "Feature",
  "properties": {
    "iso:country":"US",
    "sg:address":"305 McCaslin Blvd",
    "sg:city":"Louisville",
    "sg:classifiers":[
        {
            "category":"Retail",
            "subcategory":"Laundry & Dry Cleaning",
            "type":"Services"
        }
    ],
    "sg:phone":"+1 303 926 9120",
    "sg:postcode":"80027",
    "sg:province":"CO",
    "sg:tags":[
        "cleaners"
    ],
    "wof:name":"Continental Cleaners",
    "wof:placetype":"venue"
},
  "geometry": {"coordinates":[-105.164267,39.947444],"type":"Point"}
}