{
  "type": "Feature",
  "properties": {
    "iso:country":"US",
    "sg:address":"1950 W Littleton Blvd",
    "sg:city":"Littleton",
    "sg:classifiers":[
        {
            "category":"Social Services",
            "type":"Services"
        }
    ],
    "sg:phone":"+1 303 794 9216",
    "sg:postcode":"80120",
    "sg:province":"CO",
    "wof:name":"Littleton Community Center",
    "wof:placetype":"venue"
},
  "geometry": {"coordinates":[-105.01103500000001,39.613182],"type":"Point"}
}