{
  "type": "Feature",
  "properties": {
    "addr:full":"2912 N Hancock Ave Colorado Springs CO 80907",
    "addr:housenumber":"2912",
    "addr:postcode":"80907",
    "addr:street":"N Hancock Ave",
    "iso:country":"US",
    "sg:address":"2912 N Hancock Ave",
    "sg:city":"Colorado Springs",
    "sg:classifiers":[
        {
            "category":"Shopping",
            "subcategory":"Gifts & Souvenirs",
            "type":"Retail Goods"
        }
    ],
    "sg:phone":"+1 719 473 7376",
    "sg:postcode":"80907",
    "sg:province":"CO",
    "wof:name":"Etc Evas Trasured Collectibles",
    "wof:placetype":"venue"
},
  "geometry": {"coordinates":[-104.8035,38.872855],"type":"Point"}
}