{
  "type": "Feature",
  "properties": {
    "iso:country":"US",
    "sg:address":"5303 Maggie Ln",
    "sg:city":"Evergreen",
    "sg:classifiers":[
        {
            "category":"Wholesale",
            "subcategory":"Durable Goods & Equipment",
            "type":"Manufacturing & Wholesale Goods"
        }
    ],
    "sg:phone":"+1 303 674 6005",
    "sg:postcode":"80439",
    "sg:province":"CO",
    "sg:tags":[
        "representative",
        "manufacturer"
    ],
    "wof:name":"JLE & Assoc",
    "wof:placetype":"venue"
},
  "geometry": {"coordinates":[-105.3432,39.616154],"type":"Point"}
}