{
  "type": "Feature",
  "properties": {
    "iso:country":"US",
    "sg:address":"1306 Main St",
    "sg:city":"Alamosa",
    "sg:classifiers":[
        {
            "category":"Shopping",
            "subcategory":"Hobbies, Toys, & Games",
            "type":"Retail Goods"
        }
    ],
    "sg:phone":"+1 719 589 2053",
    "sg:postcode":"81101",
    "sg:province":"CO",
    "wof:name":"A Crafters Dream",
    "wof:placetype":"venue"
},
  "geometry": {"coordinates":[-105.877173,37.468099],"type":"Point"}
}