{
  "type": "Feature",
  "properties": {
    "iso:country":"US",
    "sg:address":"11205 Raritan St",
    "sg:city":"Denver",
    "sg:classifiers":[
        {
            "category":"Insurance",
            "subcategory":"Insurance Agent",
            "type":"Services"
        }
    ],
    "sg:phone":"+1 303 469 4869",
    "sg:postcode":"80234",
    "sg:province":"CO",
    "wof:name":"Allen & Assoc Insurance Agency",
    "wof:placetype":"venue"
},
  "geometry": {"coordinates":[-105.009603,39.899804],"type":"Point"}
}