{
  "type": "Feature",
  "properties": {
    "addr:full":"5555 Wagon Master Dr Colorado Springs CO 80917",
    "addr:housenumber":"5555",
    "addr:postcode":"80917",
    "addr:street":"Wagon Master Dr",
    "iso:country":"US",
    "sg:address":"5555 Wagon Master Dr",
    "sg:city":"Colorado Springs",
    "sg:classifiers":[
        {
            "category":"Professional",
            "subcategory":"Accounting & Tax Preparation",
            "type":"Services"
        }
    ],
    "sg:phone":"+1 719 233 3872",
    "sg:postcode":"80917",
    "sg:province":"CO",
    "sg:tags":[
        "bookkeeping",
        "general"
    ],
    "wof:name":"Flocks & Herds Accounting Svc",
    "wof:placetype":"venue"
},
  "geometry": {"coordinates":[-104.72704299999999,38.88782],"type":"Point"}
}