{
  "type": "Feature",
  "properties": {
    "addr:full":"720 E Rainbow Blvd Salida CO 81201",
    "addr:housenumber":"720",
    "addr:postcode":"81201",
    "addr:street":"E Rainbow Blvd",
    "iso:country":"US",
    "sg:address":"720 E Rainbow Blvd",
    "sg:city":"Salida",
    "sg:classifiers":[
        {
            "category":"Restaurant",
            "type":"Food & Drink"
        }
    ],
    "sg:phone":"+1 719 539 3594",
    "sg:postcode":"81201",
    "sg:province":"CO",
    "wof:name":"Windmill Restaurant",
    "wof:placetype":"venue"
},
  "geometry": {"coordinates":[-105.994514,38.524158],"type":"Point"}
}