{
  "type": "Feature",
  "properties": {
    "iso:country":"US",
    "sg:address":"557 Burbank St",
    "sg:city":"Broomfield",
    "sg:classifiers":[
        {
            "category":"Manufacturing",
            "subcategory":"Tools & Machinery",
            "type":"Manufacturing & Wholesale Goods"
        }
    ],
    "sg:phone":"+1 303 465 4800",
    "sg:postcode":"80020",
    "sg:province":"CO",
    "sg:tags":[
        "control",
        "mfg",
        "system",
        "fluid",
        "metering",
        "pump",
        "design"
    ],
    "wof:name":"Encynova International Inc",
    "wof:placetype":"venue"
},
  "geometry": {"coordinates":[-105.095439,39.923479],"type":"Point"}
}