{
  "type": "Feature",
  "properties": {
    "addr:full":"240 E 5th St Center CO 81125",
    "addr:housenumber":"240",
    "addr:postcode":"81125",
    "addr:street":"E 5Th St",
    "iso:country":"US",
    "sg:address":"240 E 5th St",
    "sg:city":"Center",
    "sg:classifiers":[
        {
            "category":"Organizations",
            "subcategory":"Religious Organization",
            "type":"Services"
        }
    ],
    "sg:phone":"+1 719 754 3904",
    "sg:postcode":"81125",
    "sg:province":"CO",
    "sg:tags":[
        "church"
    ],
    "wof:name":"Harvest Fellowship",
    "wof:placetype":"venue"
},
  "geometry": {"coordinates":[-106.110502,37.751235],"type":"Point"}
}