{
  "type": "Feature",
  "properties": {
    "addr:full":"1875 York St Denver CO 80206",
    "addr:housenumber":"1875",
    "addr:postcode":"80206",
    "addr:street":"York St",
    "iso:country":"US",
    "sg:address":"1875 York St",
    "sg:city":"Denver",
    "sg:classifiers":[
        {
            "category":"Restaurant",
            "type":"Food & Drink"
        }
    ],
    "sg:phone":"+1 303 399 7320",
    "sg:postcode":"80206",
    "sg:province":"CO",
    "wof:name":"Le Peep Restaurants",
    "wof:placetype":"venue"
},
  "geometry": {"coordinates":[-104.960616,39.68204],"type":"Point"}
}