{
  "type": "Feature",
  "properties": {
    "iso:country":"US",
    "sg:address":"3 S Newton St",
    "sg:city":"Denver",
    "sg:classifiers":[
        {
            "category":"Communications",
            "subcategory":"Film & Video Production",
            "type":"Services"
        }
    ],
    "sg:phone":"+1 303 936 8995",
    "sg:postcode":"80219",
    "sg:province":"CO",
    "sg:tags":[
        "taping"
    ],
    "wof:name":"Zelo Productions",
    "wof:placetype":"venue"
},
  "geometry": {"coordinates":[-105.037373,39.714998],"type":"Point"}
}