{
  "type": "Feature",
  "properties": {
    "iso:country":"US",
    "sg:address":"1556 Florence St",
    "sg:city":"Aurora",
    "sg:classifiers":[
        {
            "category":"Wholesale",
            "subcategory":"Toys & Hobbies",
            "type":"Manufacturing & Wholesale Goods"
        }
    ],
    "sg:phone":"+1 303 364 3031",
    "sg:postcode":"80010",
    "sg:province":"CO",
    "sg:tags":[
        "craft",
        "art",
        "supply"
    ],
    "wof:name":"K & S Tole & Craft Supply Inc",
    "wof:placetype":"venue"
},
  "geometry": {"coordinates":[-104.871661,39.740964],"type":"Point"}
}