{
  "type": "Feature",
  "properties": {
    "iso:country":"US",
    "sg:address":"435 E Main St",
    "sg:city":"Montrose",
    "sg:classifiers":[
        {
            "category":"Shopping",
            "subcategory":"Used Merchandise",
            "type":"Retail Goods"
        }
    ],
    "sg:phone":"+1 970 252 3648",
    "sg:postcode":"81401",
    "sg:province":"CO",
    "wof:name":"Heirlooms For Hospice",
    "wof:placetype":"venue"
},
  "geometry": {"coordinates":[-107.875995,38.479997],"type":"Point"}
}