{
  "type": "Feature",
  "properties": {
    "iso:country":"US",
    "sg:address":"6500 E Stapleton Dr S",
    "sg:city":"Denver",
    "sg:classifiers":[
        {
            "category":"Building & Trades",
            "subcategory":"Locksmith",
            "type":"Services"
        }
    ],
    "sg:phone":"+1 720 438 7583",
    "sg:postcode":"80216",
    "sg:province":"CO",
    "sg:tags":[
        "key"
    ],
    "wof:name":"Locksmith Around the Clock Denver",
    "wof:placetype":"venue"
},
  "geometry": {"coordinates":[-104.91287,39.777863],"type":"Point"}
}