{
  "type": "Feature",
  "properties": {
    "iso:country":"US",
    "sg:address":"1225 Claremont Ave",
    "sg:city":"Pueblo",
    "sg:classifiers":[
        {
            "category":"Building & Trades",
            "subcategory":"Landscaping Services",
            "type":"Services"
        }
    ],
    "sg:phone":"+1 719 545 8225",
    "sg:postcode":"81004",
    "sg:province":"CO",
    "sg:tags":[
        "lawn",
        "maintenance",
        "grounds"
    ],
    "wof:name":"CCMS",
    "wof:placetype":"venue"
},
  "geometry": {"coordinates":[-104.628894,38.244583],"type":"Point"}
}