{
  "type": "Feature",
  "properties": {
    "addr:full":"3828 S Jasmine St Denver CO 80237",
    "addr:housenumber":"3828",
    "addr:postcode":"80237",
    "addr:street":"S Jasmine St",
    "iso:country":"US",
    "sg:address":"3828 S Jasmine St",
    "sg:city":"Denver",
    "sg:classifiers":[
        {
            "category":"Home & Garden",
            "subcategory":"Home Furnishings",
            "type":"Retail Goods"
        }
    ],
    "sg:phone":"+1 303 692 8515",
    "sg:postcode":"80237",
    "sg:province":"CO",
    "wof:name":"Ron Kehler Window Covering",
    "wof:placetype":"venue"
},
  "geometry": {"coordinates":[-104.91690800000001,39.646606],"type":"Point"}
}