{
  "type": "Feature",
  "properties": {
    "addr:full":"6660 Delmonico Dr Colorado Springs CO 80919",
    "addr:postcode":"6660;80919",
    "addr:street":"Delmonico Dr",
    "iso:country":"US",
    "sg:address":"6660 Delmonico Dr",
    "sg:city":"Colorado Springs",
    "sg:classifiers":[
        {
            "category":"Professional",
            "subcategory":"Detective & Security Services",
            "type":"Services"
        }
    ],
    "sg:phone":"+1 719 531 6666",
    "sg:postcode":"80919",
    "sg:province":"CO",
    "sg:tags":[
        "investigator"
    ],
    "wof:name":"Carlson Co LLC",
    "wof:placetype":"venue"
},
  "geometry": {"coordinates":[-104.831495,38.929815],"type":"Point"}
}