{
  "type": "Feature",
  "properties": {
    "addr:full":"4435 Co Rd 113 Carbondale CO 81623",
    "addr:housenumber":"4435",
    "addr:postcode":"81623",
    "addr:street":"Co Rd 113",
    "iso:country":"US",
    "sg:address":"4435 Co Rd 113",
    "sg:city":"Carbondale",
    "sg:classifiers":[
        {
            "category":"Real Estate",
            "subcategory":"Real Estate Agent",
            "type":"Services"
        }
    ],
    "sg:phone":"+1 970 928 7107",
    "sg:postcode":"81623",
    "sg:province":"CO",
    "sg:tags":[
        "property",
        "management"
    ],
    "wof:name":"Ros Realty",
    "wof:placetype":"venue"
},
  "geometry": {"coordinates":[-107.202242,39.460251],"type":"Point"}
}