{
  "type": "Feature",
  "properties": {
    "iso:country":"US",
    "sg:address":"218 Quarter Horse Rd",
    "sg:city":"Jefferson",
    "sg:classifiers":[
        {
            "category":"Wholesale",
            "subcategory":"Construction Materials",
            "type":"Manufacturing & Wholesale Goods"
        }
    ],
    "sg:phone":"+1 719 836 1843",
    "sg:postcode":"80456",
    "sg:province":"CO",
    "wof:name":"South Park Glass",
    "wof:placetype":"venue"
},
  "geometry": {"coordinates":[-105.75349300000001,39.263136],"type":"Point"}
}