{
  "type": "Feature",
  "properties": {
    "iso:country":"US",
    "sg:address":"2620 S Parker Rd",
    "sg:city":"Aurora",
    "sg:classifiers":[
        {
            "category":"Autos & Motor Vehicles",
            "subcategory":"Automobile Sales",
            "type":"Retail Goods"
        }
    ],
    "sg:phone":"+1 303 755 2886",
    "sg:postcode":"80014",
    "sg:province":"CO",
    "sg:tags":[
        "car",
        "dealer"
    ],
    "wof:name":"Apex Autos",
    "wof:placetype":"venue"
},
  "geometry": {"coordinates":[-104.864259,39.669608],"type":"Point"}
}