{
  "type": "Feature",
  "properties": {
    "addr:full":"6474 S Quebec St Centennial CO 80111",
    "addr:housenumber":"6474",
    "addr:postcode":"80111",
    "addr:street":"S Quebec St",
    "iso:country":"US",
    "sg:address":"6474 S Quebec St",
    "sg:city":"Centennial",
    "sg:classifiers":[
        {
            "category":"Banks & Credit Unions",
            "subcategory":"Bank",
            "type":"Services"
        }
    ],
    "sg:phone":"+1 303 694 0155",
    "sg:postcode":"80111",
    "sg:province":"CO",
    "sg:tags":[
        "other",
        "plan",
        "card"
    ],
    "wof:name":"National State Bank Card Inc",
    "wof:placetype":"venue"
},
  "geometry": {"coordinates":[-104.904077,39.599494],"type":"Point"}
}