{
  "type": "Feature",
  "properties": {
    "addr:full":"9201 Adams St Denver CO 80229",
    "addr:housenumber":"9201",
    "addr:postcode":"80229",
    "addr:street":"Adams St",
    "iso:country":"US",
    "sg:address":"9201 Adams St",
    "sg:city":"Denver",
    "sg:classifiers":[
        {
            "category":"Professional",
            "type":"Services"
        }
    ],
    "sg:phone":"+1 303 455 3135",
    "sg:postcode":"80229",
    "sg:province":"CO",
    "sg:tags":[
        "establishment"
    ],
    "wof:name":"Karamat Bhatti",
    "wof:placetype":"venue"
},
  "geometry": {"coordinates":[-104.94734699999999,39.864667],"type":"Point"}
}