{
  "type": "Feature",
  "properties": {
    "addr:full":"28 Red Lily Pl Evergreen CO 80439",
    "addr:housenumber":"28",
    "addr:postcode":"80439",
    "addr:street":"Red Lily Pl",
    "iso:country":"US",
    "sg:address":"28 Red Lily Pl",
    "sg:city":"Evergreen",
    "sg:classifiers":[
        {
            "category":"Building & Trades",
            "subcategory":"Construction",
            "type":"Services"
        }
    ],
    "sg:phone":"+1 303 674 4103",
    "sg:postcode":"80439",
    "sg:province":"CO",
    "sg:tags":[
        "equipment",
        "installation"
    ],
    "wof:name":"Alternative Energy Source Inc",
    "wof:placetype":"venue"
},
  "geometry": {"coordinates":[-105.398554,39.632127],"type":"Point"}
}