{
  "type": "Feature",
  "properties": {
    "addr:full":"110 W 6th St Walsenburg CO 81089",
    "addr:housenumber":"110",
    "addr:postcode":"81089",
    "addr:street":"W 6Th St",
    "iso:country":"US",
    "sg:address":"110 W 6th St",
    "sg:city":"Walsenburg",
    "sg:classifiers":[
        {
            "category":"Bars & Pubs",
            "type":"Food & Drink"
        }
    ],
    "sg:phone":"+1 719 738 9968",
    "sg:postcode":"81089",
    "sg:province":"CO",
    "sg:tags":[
        "drinking"
    ],
    "wof:name":"Starlite Inn",
    "wof:placetype":"venue"
},
  "geometry": {"coordinates":[-104.78100999999999,37.623675],"type":"Point"}
}