{
  "type": "Feature",
  "properties": {
    "addr:full":"2190 E Iliff Avenue Denver CO 80210",
    "addr:housenumber":"2190",
    "addr:postcode":"80210",
    "addr:street":"E Iliff Avenue",
    "iso:country":"US",
    "sg:address":"2190 E Iliff Avenue",
    "sg:city":"Denver",
    "sg:classifiers":[
        {
            "category":"Education",
            "subcategory":"University",
            "type":"Public Place"
        }
    ],
    "sg:phone":"+1 303 871 3661",
    "sg:postcode":"80210",
    "sg:province":"CO",
    "sg:tags":[
        "college"
    ],
    "wof:name":"University of Denver",
    "wof:placetype":"venue"
},
  "geometry": {"coordinates":[-104.96176,39.674735],"type":"Point"}
}