{
  "type": "Feature",
  "properties": {
    "iso:country":"US",
    "sg:address":"13922 Meadowbrook Dr",
    "sg:city":"Broomfield",
    "sg:classifiers":[
        {
            "category":"Professional",
            "type":"Services"
        }
    ],
    "sg:phone":"+1 720 887 4808",
    "sg:postcode":"80020",
    "sg:province":"CO",
    "wof:name":"Tran Trinh",
    "wof:placetype":"venue"
},
  "geometry": {"coordinates":[-105.053641,39.947403],"type":"Point"}
}