{
  "type": "Feature",
  "properties": {
    "addr:full":"2268 S Broadway Denver CO 80223",
    "addr:housenumber":"2268",
    "addr:postcode":"80223",
    "addr:street":"S Broadway",
    "iso:country":"US",
    "sg:address":"2268 S Broadway",
    "sg:city":"Denver",
    "sg:classifiers":[
        {
            "category":"Personal",
            "type":"Services"
        },
        {
            "category":"Retail",
            "subcategory":"Laundry & Dry Cleaning",
            "type":"Services"
        },
        {
            "category":"Shopping",
            "subcategory":"Bridal",
            "type":"Retail Goods"
        }
    ],
    "sg:phone":"+1 303 909 2409",
    "sg:postcode":"80223",
    "sg:province":"CO",
    "sg:tags":[
        "sewing",
        "alteration"
    ],
    "sg:website":"www.totalapparelcare.com/",
    "wof:name":"A B Cleaners",
    "wof:placetype":"venue"
},
  "geometry": {"coordinates":[-104.987557,39.675285],"type":"Point"}
}