{
  "type": "Feature",
  "properties": {
    "addr:full":"9357 Flower St Broomfield CO 80021",
    "addr:housenumber":"9357",
    "addr:postcode":"80021",
    "addr:street":"Flower St",
    "iso:country":"US",
    "sg:address":"9357 Flower St",
    "sg:city":"Broomfield",
    "sg:classifiers":[
        {
            "category":"Building & Trades",
            "subcategory":"Plumbing",
            "type":"Services"
        }
    ],
    "sg:phone":"+1 303 412 1609",
    "sg:postcode":"80021",
    "sg:province":"CO",
    "sg:tags":[
        "contractor"
    ],
    "wof:name":"Half Pipe Plumbing LLC",
    "wof:placetype":"venue"
},
  "geometry": {"coordinates":[-105.09898800000001,39.865842],"type":"Point"}
}