{
  "type": "Feature",
  "properties": {
    "addr:full":"1865 Yeager Dr Longmont CO 80501",
    "addr:housenumber":"1865",
    "addr:postcode":"80501",
    "addr:street":"Yeager Dr",
    "iso:country":"US",
    "sg:address":"1865 Yeager Dr",
    "sg:city":"Longmont",
    "sg:classifiers":[
        {
            "category":"Professional",
            "type":"Services"
        }
    ],
    "sg:phone":"+1 303 651 3132",
    "sg:postcode":"80501",
    "sg:province":"CO",
    "wof:name":"Chem Care",
    "wof:placetype":"venue"
},
  "geometry": {"coordinates":[-105.105979,40.191265],"type":"Point"}
}