{
  "type": "Feature",
  "properties": {
    "addr:full":"5398 Co Rd 154 Glenwood Springs CO 81601",
    "addr:housenumber":"5398;154",
    "addr:postcode":"81601",
    "addr:street":"Co Rd",
    "iso:country":"US",
    "sg:address":"5398 Co Rd 154",
    "sg:city":"Glenwood Springs",
    "sg:classifiers":[
        {
            "category":"Building & Trades",
            "subcategory":"Plumbing",
            "type":"Services"
        }
    ],
    "sg:phone":"+1 970 945 8595",
    "sg:postcode":"81601",
    "sg:province":"CO",
    "sg:tags":[
        "conditioning",
        "air",
        "system",
        "contractor"
    ],
    "wof:name":"Corrigan's Refrigeration & Air",
    "wof:placetype":"venue"
},
  "geometry": {"coordinates":[-107.272164,39.474165],"type":"Point"}
}