{
  "type": "Feature",
  "properties": {
    "iso:country":"US",
    "sg:address":"1050 Walnut St",
    "sg:city":"Boulder",
    "sg:classifiers":[
        {
            "category":"Government",
            "subcategory":"Police Station",
            "type":"Public Place"
        }
    ],
    "sg:phone":"+1 303 443 4900",
    "sg:postcode":"80302",
    "sg:province":"CO",
    "sg:tags":[
        "federal",
        "investigation"
    ],
    "wof:name":"FBI",
    "wof:placetype":"venue"
},
  "geometry": {"coordinates":[-105.281329,40.016422],"type":"Point"}
}