{
  "type": "Feature",
  "properties": {
    "addr:full":"3398 S Broadway Englewood CO 80113",
    "addr:housenumber":"3398",
    "addr:postcode":"80113",
    "addr:street":"S Broadway",
    "iso:country":"US",
    "sg:address":"3398 S Broadway",
    "sg:city":"Englewood",
    "sg:classifiers":[
        {
            "category":"Shopping",
            "subcategory":"Books",
            "type":"Retail Goods"
        },
        {
            "category":"Shopping",
            "type":"Retail Goods"
        }
    ],
    "sg:phone":"+1 303 762 8385",
    "sg:postcode":"80113",
    "sg:province":"CO",
    "sg:tags":[
        "bookstore",
        "bible",
        "religious",
        "store"
    ],
    "sg:website":"http://www.catholicstore.com",
    "wof:name":"Catholic Store",
    "wof:placetype":"venue"
},
  "geometry": {"coordinates":[-104.987617,39.654949],"type":"Point"}
}