{
  "type": "Feature",
  "properties": {
    "addr:full":"4104 Outlook Blvd Pueblo CO 81008",
    "addr:housenumber":"4104",
    "addr:postcode":"81008",
    "addr:street":"Outlook Blvd",
    "iso:country":"US",
    "sg:address":"4104 Outlook Blvd",
    "sg:city":"Pueblo",
    "sg:classifiers":[
        {
            "category":"Shopping",
            "subcategory":"Florist",
            "type":"Retail Goods"
        }
    ],
    "sg:phone":"+1 719 542 5408",
    "sg:postcode":"81008",
    "sg:province":"CO",
    "sg:tags":[
        "work",
        "art",
        "flower",
        "gift"
    ],
    "wof:name":"PS I Love You",
    "wof:placetype":"venue"
},
  "geometry": {"coordinates":[-104.626942,38.313805],"type":"Point"}
}