{
  "type": "Feature",
  "properties": {
    "iso:country":"US",
    "sg:address":"340 Oswego Ct",
    "sg:city":"Aurora",
    "sg:classifiers":[
        {
            "category":"Manufacturing",
            "subcategory":"Tools & Machinery",
            "type":"Manufacturing & Wholesale Goods"
        }
    ],
    "sg:phone":"+1 303 366 2898",
    "sg:postcode":"80010",
    "sg:province":"CO",
    "sg:tags":[
        "dental",
        "mfg"
    ],
    "wof:name":"Denpro Company",
    "wof:placetype":"venue"
},
  "geometry": {"coordinates":[-104.851795,39.720071],"type":"Point"}
}