{
  "type": "Feature",
  "properties": {
    "addr:full":"1206 Lincoln Ave Steamboat Spgs CO 80487",
    "addr:housenumber":"1206",
    "addr:postcode":"80487",
    "addr:street":"Lincoln Ave;Spgs",
    "iso:country":"US",
    "sg:address":"1206 Lincoln Ave",
    "sg:city":"Steamboat Spgs",
    "sg:classifiers":[
        {
            "category":"Wholesale",
            "subcategory":"Electrical",
            "type":"Manufacturing & Wholesale Goods"
        }
    ],
    "sg:phone":"+1 970 879 5281",
    "sg:postcode":"80487",
    "sg:province":"CO",
    "sg:tags":[
        "alarm",
        "burglar",
        "system"
    ],
    "wof:name":"Western Security Systems Inc",
    "wof:placetype":"venue"
},
  "geometry": {"coordinates":[-106.839303,40.488975],"type":"Point"}
}