{
  "type": "Feature",
  "properties": {
    "iso:country":"US",
    "sg:address":"400 E 4th St",
    "sg:city":"Pueblo",
    "sg:classifiers":[
        {
            "category":"Professional",
            "subcategory":"Credit Reporting & Collection",
            "type":"Services"
        }
    ],
    "sg:phone":"+1 719 545 2547",
    "sg:postcode":"81001",
    "sg:province":"CO",
    "sg:tags":[
        "agency"
    ],
    "wof:name":"Advantage Network Systems",
    "wof:placetype":"venue"
},
  "geometry": {"coordinates":[-104.602476,38.270679],"type":"Point"}
}