{
  "type": "Feature",
  "properties": {
    "addr:full":"9620 Trotter Cir Colorado Springs CO 80908",
    "addr:housenumber":"9620",
    "addr:postcode":"80908",
    "addr:street":"Trotter Cir",
    "iso:country":"US",
    "sg:address":"9620 Trotter Cir",
    "sg:city":"Colorado Springs",
    "sg:classifiers":[
        {
            "category":"Insurance",
            "subcategory":"Insurance Agent",
            "type":"Services"
        }
    ],
    "sg:phone":"+1 719 494 1234",
    "sg:postcode":"80908",
    "sg:province":"CO",
    "wof:name":"Farmers Insurance",
    "wof:placetype":"venue"
},
  "geometry": {"coordinates":[-104.64817600000001,39.090064],"type":"Point"}
}