{
  "type": "Feature",
  "properties": {
    "addr:full":"8941 Harlan St Westminster CO 80031",
    "addr:housenumber":"8941",
    "addr:postcode":"80031",
    "addr:street":"Harlan St",
    "iso:country":"US",
    "sg:address":"8941 Harlan St",
    "sg:city":"Westminster",
    "sg:classifiers":[
        {
            "category":"Professional",
            "subcategory":"Employment Agencies",
            "type":"Services"
        }
    ],
    "sg:phone":"+1 303 425 6646",
    "sg:postcode":"80031",
    "sg:province":"CO",
    "sg:tags":[
        "help",
        "contractor"
    ],
    "sg:website":"www.corestaff.com",
    "wof:name":"Corestaff",
    "wof:placetype":"venue"
},
  "geometry": {"coordinates":[-105.06397800000001,39.860434],"type":"Point"}
}