{
  "type": "Feature",
  "properties": {
    "iso:country":"US",
    "sg:address":"201 W Asbury Ave",
    "sg:city":"Denver",
    "sg:classifiers":[
        {
            "category":"Building & Trades",
            "subcategory":"Locksmith",
            "type":"Services"
        }
    ],
    "sg:phone":"+1 303 390 0384",
    "sg:postcode":"80223",
    "sg:province":"CO",
    "sg:tags":[
        "key"
    ],
    "wof:name":"Emergency A 24 Locksmith",
    "wof:placetype":"venue"
},
  "geometry": {"coordinates":[-104.989958,39.680457],"type":"Point"}
}