{
  "type": "Feature",
  "properties": {
    "iso:country":"US",
    "sg:address":"6504 Wadsworth Bypass",
    "sg:city":"Arvada",
    "sg:classifiers":[
        {
            "category":"Restaurant",
            "type":"Food & Drink"
        }
    ],
    "sg:phone":"+1 303 467 1002",
    "sg:postcode":"80003",
    "sg:province":"CO",
    "sg:tags":[
        "traditional",
        "american"
    ],
    "wof:name":"George's Cafe",
    "wof:placetype":"venue"
},
  "geometry": {"coordinates":[-105.080948,39.814106],"type":"Point"}
}