{
  "type": "Feature",
  "properties": {
    "iso:country":"US",
    "sg:address":"2400 Industrial Ln",
    "sg:city":"Broomfield",
    "sg:classifiers":[
        {
            "category":"Manufacturing",
            "subcategory":"Tools & Machinery",
            "type":"Manufacturing & Wholesale Goods"
        }
    ],
    "sg:phone":"+1 303 465 3922",
    "sg:postcode":"80020",
    "sg:province":"CO",
    "sg:tags":[
        "machine",
        "shop",
        "die"
    ],
    "wof:name":"Stacy Machine & Tooling Inc",
    "wof:placetype":"venue"
},
  "geometry": {"coordinates":[-105.09627999999999,39.920646],"type":"Point"}
}