{
  "type": "Feature",
  "properties": {
    "iso:country":"US",
    "sg:address":"701 E Main St",
    "sg:city":"Montrose",
    "sg:classifiers":[
        {
            "category":"Personal",
            "subcategory":"Barber",
            "type":"Services"
        }
    ],
    "sg:phone":"+1 970 240 3057",
    "sg:postcode":"81401",
    "sg:province":"CO",
    "wof:name":"Carla's Clip Joint",
    "wof:placetype":"venue"
},
  "geometry": {"coordinates":[-107.87244699999999,38.482402],"type":"Point"}
}