{
  "type": "Feature",
  "properties": {
    "iso:country":"US",
    "sg:address":"7208 S Tucson Way",
    "sg:city":"Centennial",
    "sg:classifiers":[
        {
            "category":"Professional",
            "subcategory":"Computer Services",
            "type":"Services"
        }
    ],
    "sg:phone":"+1 303 858 1650",
    "sg:postcode":"80112",
    "sg:province":"CO",
    "sg:tags":[
        "consultant",
        "designer"
    ],
    "sg:website":"www.dcmi.com",
    "wof:name":"DCMI",
    "wof:placetype":"venue"
},
  "geometry": {"coordinates":[-104.835566,39.586689],"type":"Point"}
}