{
  "type": "Feature",
  "properties": {
    "addr:full":"340 Lakewood Dr Durango CO 81301",
    "addr:housenumber":"340",
    "addr:postcode":"co 81301",
    "addr:street":"Lakewood Dr",
    "iso:country":"US",
    "sg:address":"340 Lakewood Dr",
    "sg:city":"Durango",
    "sg:classifiers":[
        {
            "category":"Manufacturing",
            "subcategory":"Printing",
            "type":"Manufacturing & Wholesale Goods"
        }
    ],
    "sg:phone":"+1 970 259 4616",
    "sg:postcode":"81301",
    "sg:province":"CO",
    "sg:tags":[
        "wheel",
        "publishing",
        "drive",
        "four",
        "book",
        "guide"
    ],
    "wof:name":"Backcountry Travelers",
    "wof:placetype":"venue"
},
  "geometry": {"coordinates":[-107.822885,37.565473],"type":"Point"}
}