{
  "type": "Feature",
  "properties": {
    "iso:country":"US",
    "sg:address":"4450 Arapahoe Ave",
    "sg:city":"Boulder",
    "sg:classifiers":[
        {
            "category":"Banks & Credit Unions",
            "subcategory":"Bank",
            "type":"Services"
        }
    ],
    "sg:phone":"+1 303 546 7956",
    "sg:postcode":"80303",
    "sg:province":"CO",
    "sg:tags":[
        "mortgage",
        "loan",
        "broker",
        "real estate"
    ],
    "wof:name":"Core One Mortgage LLC",
    "wof:placetype":"venue"
},
  "geometry": {"coordinates":[-105.244851,40.014499],"type":"Point"}
}