{
  "type": "Feature",
  "properties": {
    "iso:country":"US",
    "sg:address":"429 N College Ave",
    "sg:city":"Fort Collins",
    "sg:classifiers":[
        {
            "category":"Government",
            "subcategory":"Office",
            "type":"Public Place"
        }
    ],
    "sg:phone":"+1 970 221 5324",
    "sg:postcode":"80524",
    "sg:province":"CO",
    "sg:tags":[
        "state",
        "program",
        "health"
    ],
    "wof:name":"Health Dept Air Info",
    "wof:placetype":"venue"
},
  "geometry": {"coordinates":[-105.076801,40.592742],"type":"Point"}
}