{
  "type": "Feature",
  "properties": {
    "iso:country":"US",
    "sg:address":"4918 E Colfax Ave",
    "sg:city":"Denver",
    "sg:classifiers":[
        {
            "category":"Wholesale",
            "subcategory":"Medical Equipment & Supplies",
            "type":"Manufacturing & Wholesale Goods"
        }
    ],
    "sg:phone":"+1 720 941 8487",
    "sg:postcode":"80220",
    "sg:province":"CO",
    "sg:tags":[
        "physician",
        "surgeon"
    ],
    "wof:name":"Alliance Medical Supply LLC",
    "wof:placetype":"venue"
},
  "geometry": {"coordinates":[-104.929993,39.740059],"type":"Point"}
}