{
  "type": "Feature",
  "properties": {
    "addr:full":"4237 Hammock Dr S Colorado Springs CO 80917",
    "addr:housenumber":"4237",
    "addr:postcode":"80917",
    "addr:street":"Hammock Dr S",
    "iso:country":"US",
    "sg:address":"4237 Hammock Dr S",
    "sg:city":"Colorado Springs",
    "sg:classifiers":[
        {
            "category":"Wholesale",
            "subcategory":"Construction Materials",
            "type":"Manufacturing & Wholesale Goods"
        }
    ],
    "sg:phone":"+1 719 596 2690",
    "sg:postcode":"80917",
    "sg:province":"CO",
    "sg:tags":[
        "well",
        "window",
        "cover"
    ],
    "wof:name":"Colorado Custom Welding",
    "wof:placetype":"venue"
},
  "geometry": {"coordinates":[-104.748058,38.882928],"type":"Point"}
}