{
  "type": "Feature",
  "properties": {
    "iso:country":"US",
    "sg:address":"235 S Franceville Coal Mine Rd",
    "sg:city":"Colorado Springs",
    "sg:classifiers":[
        {
            "category":"Freight",
            "type":"Transportation"
        }
    ],
    "sg:phone":"+1 719 683 5100",
    "sg:postcode":"80929",
    "sg:province":"CO",
    "sg:tags":[
        "hauling",
        "trucking"
    ],
    "wof:name":"K W Transportation Svc Inc",
    "wof:placetype":"venue"
},
  "geometry": {"coordinates":[-104.590603,38.826918],"type":"Point"}
}