{
  "type": "Feature",
  "properties": {
    "addr:full":"7411 Decatur St Westminster CO 80030",
    "addr:housenumber":"7411",
    "addr:postcode":"80030",
    "addr:street":"Decatur St",
    "iso:country":"US",
    "sg:address":"7411 Decatur St",
    "sg:city":"Westminster",
    "sg:classifiers":[
        {
            "category":"Wholesale",
            "subcategory":"Hardware",
            "type":"Manufacturing & Wholesale Goods"
        },
        {
            "category":"Building & Trades",
            "subcategory":"Landscaping Services",
            "type":"Services"
        }
    ],
    "sg:phone":"+1 303 668 0340",
    "sg:postcode":"80030",
    "sg:province":"CO",
    "sg:tags":[
        "plumbing",
        "landscape",
        "contractor"
    ],
    "wof:name":"Mountain View Landscaping Inc",
    "wof:placetype":"venue"
},
  "geometry": {"coordinates":[-105.022739,39.833306],"type":"Point"}
}