{
  "type": "Feature",
  "properties": {
    "iso:country":"US",
    "sg:address":"6622 Cheyenne Ct",
    "sg:city":"Longmont",
    "sg:classifiers":[
        {
            "category":"Banks & Credit Unions",
            "subcategory":"Financial Services",
            "type":"Services"
        }
    ],
    "sg:phone":"+1 303 444 1877",
    "sg:postcode":"80503",
    "sg:province":"CO",
    "sg:tags":[
        "annuity",
        "insurance"
    ],
    "wof:name":"Hein Financial Svc",
    "wof:placetype":"venue"
},
  "geometry": {"coordinates":[-105.142996,40.095775],"type":"Point"}
}