{
  "type": "Feature",
  "properties": {
    "iso:country":"US",
    "sg:address":"3300 Arapahoe Ave",
    "sg:city":"Boulder",
    "sg:classifiers":[
        {
            "category":"Professional",
            "subcategory":"Lawyer & Legal Services",
            "type":"Services"
        }
    ],
    "sg:phone":"+1 303 443 6253",
    "sg:postcode":"80303",
    "sg:province":"CO",
    "sg:tags":[
        "attorney"
    ],
    "wof:name":"William J Henninger",
    "wof:placetype":"venue"
},
  "geometry": {"coordinates":[-105.246664,40.014516],"type":"Point"}
}