{
  "type": "Feature",
  "properties": {
    "iso:country":"US",
    "sg:address":"1560 Broadway",
    "sg:city":"Denver",
    "sg:classifiers":[
        {
            "category":"Professional",
            "subcategory":"Lawyer & Legal Services",
            "type":"Services"
        }
    ],
    "sg:phone":"+1 303 831 1099",
    "sg:postcode":"80202",
    "sg:province":"CO",
    "wof:name":"Bruno Colin Jewel & Lowe PC",
    "wof:placetype":"venue"
},
  "geometry": {"coordinates":[-104.987405,39.740993],"type":"Point"}
}