{
  "type": "Feature",
  "properties": {
    "addr:full":"350 S Paddock St Elizabeth CO 80107",
    "addr:housenumber":"350",
    "addr:postcode":"80107",
    "addr:street":"S Paddock St",
    "iso:country":"US",
    "sg:address":"350 S Paddock St",
    "sg:city":"Elizabeth",
    "sg:classifiers":[
        {
            "category":"Shopping",
            "subcategory":"Musical Instruments",
            "type":"Retail Goods"
        }
    ],
    "sg:phone":"+1 303 646 3768",
    "sg:postcode":"80107",
    "sg:province":"CO",
    "wof:name":"Music Workshop",
    "wof:placetype":"venue"
},
  "geometry": {"coordinates":[-104.603201,39.359131],"type":"Point"}
}