{
  "type": "Feature",
  "properties": {
    "iso:country":"US",
    "sg:address":"720 S Colorado Blvd",
    "sg:city":"Denver",
    "sg:classifiers":[
        {
            "category":"Banks & Credit Unions",
            "subcategory":"Investment Brokerage",
            "type":"Services"
        }
    ],
    "sg:phone":"+1 303 393 2357",
    "sg:postcode":"80246",
    "sg:province":"CO",
    "sg:tags":[
        "advisory"
    ],
    "wof:name":"Matthew B Miller CLU Cfp",
    "wof:placetype":"venue"
},
  "geometry": {"coordinates":[-104.940635,39.70351],"type":"Point"}
}