{
  "type": "Feature",
  "properties": {
    "addr:full":"1142 S Abilene St Aurora CO 80012",
    "addr:housenumber":"1142",
    "addr:postcode":"80012",
    "addr:street":"S Abilene St",
    "iso:country":"US",
    "sg:address":"1142 S Abilene St",
    "sg:city":"Aurora",
    "sg:classifiers":[
        {
            "category":"Personal",
            "subcategory":"Tanning Parlor",
            "type":"Services"
        }
    ],
    "sg:phone":"+1 303 755 7567",
    "sg:postcode":"80012",
    "sg:province":"CO",
    "sg:tags":[
        "salon"
    ],
    "wof:name":"Executive Tans",
    "wof:placetype":"venue"
},
  "geometry": {"coordinates":[-104.826663,39.695773],"type":"Point"}
}