{
  "type": "Feature",
  "properties": {
    "addr:full":"4128 Austin Bluffs Pkwy Colorado Springs CO 80918",
    "addr:housenumber":"4128",
    "addr:postcode":"80918",
    "addr:street":"Austin Bluffs Pkwy",
    "iso:country":"US",
    "sg:address":"4128 Austin Bluffs Pkwy",
    "sg:city":"Colorado Springs",
    "sg:classifiers":[
        {
            "category":"Restaurant",
            "type":"Food & Drink"
        }
    ],
    "sg:phone":"+1 719 528 6565",
    "sg:postcode":"80918",
    "sg:province":"CO",
    "sg:tags":[
        "shop",
        "submarine",
        "sandwich"
    ],
    "wof:name":"S S Subs",
    "wof:placetype":"venue"
},
  "geometry": {"coordinates":[-104.753795,38.89209],"type":"Point"}
}