{
  "type": "Feature",
  "properties": {
    "addr:full":"2945 E Las Vegas St Colorado Springs CO 80906",
    "addr:housenumber":"2945",
    "addr:postcode":"80906",
    "addr:street":"E Las Vegas St",
    "iso:country":"US",
    "sg:address":"2945 E Las Vegas St",
    "sg:city":"Colorado Springs",
    "sg:classifiers":[
        {
            "category":"Professional",
            "type":"Services"
        }
    ],
    "sg:phone":"+1 719 390 1303",
    "sg:postcode":"80906",
    "sg:province":"CO",
    "sg:tags":[
        "establishment"
    ],
    "wof:name":"Community Alternative Of El",
    "wof:placetype":"venue"
},
  "geometry": {"coordinates":[-104.772457,38.778758],"type":"Point"}
}