{
  "type": "Feature",
  "properties": {
    "iso:country":"US",
    "sg:address":"1075 S Yukon St",
    "sg:city":"Lakewood",
    "sg:classifiers":[
        {
            "category":"Real Estate",
            "subcategory":"Real Estate Agent",
            "type":"Services"
        }
    ],
    "sg:phone":"+1 303 595 9555",
    "sg:postcode":"80226",
    "sg:province":"CO",
    "sg:tags":[
        "investment"
    ],
    "sg:website":"www.rocproperties.com",
    "wof:name":"ROC Properties",
    "wof:placetype":"venue"
},
  "geometry": {"coordinates":[-105.08277099999999,39.699726],"type":"Point"}
}