{
  "type": "Feature",
  "properties": {
    "addr:full":"2160 Southgate Rd Colorado Springs CO 80906",
    "addr:housenumber":"2160",
    "addr:postcode":"80906",
    "addr:street":"Southgate Rd",
    "iso:country":"US",
    "sg:address":"2160 Southgate Rd",
    "sg:city":"Colorado Springs",
    "sg:classifiers":[
        {
            "category":"Shopping",
            "type":"Retail Goods"
        }
    ],
    "sg:phone":"+1 719 447 0622",
    "sg:postcode":"80906",
    "sg:province":"CO",
    "sg:tags":[
        "merchandise"
    ],
    "wof:name":"Petsmart",
    "wof:placetype":"venue"
},
  "geometry": {"coordinates":[-104.817491,38.801546],"type":"Point"}
}