{
  "type": "Feature",
  "properties": {
    "addr:full":"1690 S Abilene St Aurora CO 80012",
    "addr:housenumber":"1690",
    "addr:postcode":"80012",
    "addr:street":"S Abilene St",
    "iso:country":"US",
    "sg:address":"1690 S Abilene St",
    "sg:city":"Aurora",
    "sg:classifiers":[
        {
            "category":"Manufacturing",
            "subcategory":"Metals",
            "type":"Manufacturing & Wholesale Goods"
        }
    ],
    "sg:phone":"+1 303 367 5955",
    "sg:postcode":"80012",
    "sg:province":"CO",
    "sg:tags":[
        "industrial",
        "valve",
        "mfg"
    ],
    "wof:name":"Vapor Trail",
    "wof:placetype":"venue"
},
  "geometry": {"coordinates":[-104.82819000000001,39.685585],"type":"Point"}
}