{
  "type": "Feature",
  "properties": {
    "iso:country":"US",
    "sg:address":"5500 S Simms St",
    "sg:city":"Littleton",
    "sg:classifiers":[
        {
            "category":"Food & Beverages",
            "subcategory":"Groceries & Convenience Stores",
            "type":"Retail Goods"
        }
    ],
    "sg:phone":"+1 303 904 9027",
    "sg:postcode":"80127",
    "sg:province":"CO",
    "wof:name":"Pump Shop & Save",
    "wof:placetype":"venue"
},
  "geometry": {"coordinates":[-105.128642,39.615122],"type":"Point"}
}