{
  "type": "Feature",
  "properties": {
    "iso:country":"US",
    "sg:address":"2037 N Surrey Ct",
    "sg:city":"Grand Junction",
    "sg:classifiers":[
        {
            "category":"Communications",
            "type":"Services"
        }
    ],
    "sg:phone":"+1 970 257 0871",
    "sg:postcode":"81503",
    "sg:province":"CO",
    "wof:name":"Fortson Communications Inc",
    "wof:placetype":"venue"
},
  "geometry": {"coordinates":[-108.67001500000001,39.098595],"type":"Point"}
}