{
  "type": "Feature",
  "properties": {
    "iso:country":"US",
    "sg:address":"18885 E Colfax Ave",
    "sg:city":"Aurora",
    "sg:classifiers":[
        {
            "category":"Shopping",
            "subcategory":"Shoes",
            "type":"Retail Goods"
        },
        {
            "category":"Shopping",
            "subcategory":"Clothing, Apparel, & Fashions",
            "type":"Retail Goods"
        }
    ],
    "sg:phone":"+1 303 343 0318",
    "sg:postcode":"80011",
    "sg:province":"CO",
    "sg:tags":[
        "tack",
        "boot",
        "wear",
        "western",
        "saddle"
    ],
    "wof:name":"Lancaster's Western Wear",
    "wof:placetype":"venue"
},
  "geometry": {"coordinates":[-104.773107,39.740327],"type":"Point"}
}