{
  "type": "Feature",
  "properties": {
    "addr:full":"704 Main St San Luis CO 81152",
    "addr:housenumber":"704",
    "addr:postcode":"81152",
    "addr:street":"Main St",
    "iso:country":"US",
    "sg:address":"704 Main St",
    "sg:city":"San Luis",
    "sg:classifiers":[
        {
            "category":"Autos & Motor Vehicles",
            "subcategory":"Fuel & Gas Station",
            "type":"Retail Goods"
        }
    ],
    "sg:phone":"+1 719 672 3840",
    "sg:postcode":"81152",
    "sg:province":"CO",
    "sg:tags":[
        "oil"
    ],
    "wof:name":"Central Oil Co",
    "wof:placetype":"venue"
},
  "geometry": {"coordinates":[-105.425186,37.204152],"type":"Point"}
}