{
  "type": "Feature",
  "properties": {
    "addr:full":"3842 Co Rd 21 Fort Lupton CO 80621",
    "addr:housenumber":"3842;21",
    "addr:postcode":"80621",
    "addr:street":"Co Rd;Fort Lupton",
    "iso:country":"US",
    "sg:address":"3842 Co Rd 21",
    "sg:city":"Fort Lupton",
    "sg:classifiers":[
        {
            "category":"Manufacturing",
            "subcategory":"Tools & Machinery",
            "type":"Manufacturing & Wholesale Goods"
        }
    ],
    "sg:phone":"+1 303 659 2759",
    "sg:postcode":"80621",
    "sg:province":"CO",
    "sg:tags":[
        "machine",
        "shop"
    ],
    "wof:name":"General Machine",
    "wof:placetype":"venue"
},
  "geometry": {"coordinates":[-104.867259,40.056489],"type":"Point"}
}