{
  "type": "Feature",
  "properties": {
    "iso:country":"US",
    "sg:address":"315 Co Rd 338",
    "sg:city":"Ignacio",
    "sg:classifiers":[
        {
            "category":"Farming",
            "subcategory":"Livestock Farm",
            "type":"Manufacturing & Wholesale Goods"
        }
    ],
    "sg:phone":"+1 970 259 6061",
    "sg:postcode":"81137",
    "sg:province":"CO",
    "sg:tags":[
        "beef",
        "feedlot",
        "cattle"
    ],
    "wof:name":"McCaw Ranch",
    "wof:placetype":"venue"
},
  "geometry": {"coordinates":[-107.737351,37.17821],"type":"Point"}
}