{
  "type": "Feature",
  "properties": {
    "iso:country":"US",
    "sg:address":"1115 11th St",
    "sg:city":"Greeley",
    "sg:classifiers":[
        {
            "category":"Building & Trades",
            "subcategory":"Construction",
            "type":"Services"
        }
    ],
    "sg:phone":"+1 970 346 0066",
    "sg:postcode":"80631",
    "sg:province":"CO",
    "sg:tags":[
        "dry wall",
        "contractor"
    ],
    "wof:name":"AAA Drywall Co",
    "wof:placetype":"venue"
},
  "geometry": {"coordinates":[-104.69786499999999,40.421282],"type":"Point"}
}