{
  "type": "Feature",
  "properties": {
    "iso:country":"US",
    "sg:address":"45 Sopris Ave",
    "sg:city":"Carbondale",
    "sg:classifiers":[
        {
            "category":"Building & Trades",
            "subcategory":"Construction",
            "type":"Services"
        }
    ],
    "sg:phone":"+1 970 963 6673",
    "sg:postcode":"81623",
    "sg:province":"CO",
    "sg:tags":[
        "hanging",
        "contractor"
    ],
    "wof:name":"Tim Adams Painting Inc",
    "wof:placetype":"venue"
},
  "geometry": {"coordinates":[-107.20678100000001,39.39807],"type":"Point"}
}