{
  "type": "Feature",
  "properties": {
    "addr:full":"1709 W Harmony Rd Fort Collins CO 80526",
    "addr:housenumber":"1709",
    "addr:postcode":"80526",
    "addr:street":"W Harmony Rd",
    "iso:country":"US",
    "sg:address":"1709 W Harmony Rd",
    "sg:city":"Fort Collins",
    "sg:classifiers":[
        {
            "category":"Retail",
            "subcategory":"Car Wash",
            "type":"Services"
        }
    ],
    "sg:phone":"+1 970 377 2466",
    "sg:postcode":"80526",
    "sg:province":"CO",
    "sg:tags":[
        "polishing",
        "washing"
    ],
    "wof:name":"Schrader Oil Co/Car Washes",
    "wof:placetype":"venue"
},
  "geometry": {"coordinates":[-105.105858,40.523505],"type":"Point"}
}