{
  "type": "Feature",
  "properties": {
    "iso:country":"US",
    "sg:address":"8821 Harlan St",
    "sg:city":"Westminster",
    "sg:classifiers":[
        {
            "category":"Professional",
            "subcategory":"Business Services",
            "type":"Services"
        }
    ],
    "sg:phone":"+1 303 650 4131",
    "sg:postcode":"80031",
    "sg:province":"CO",
    "wof:name":"Custom Apparel By Mr KS",
    "wof:placetype":"venue"
},
  "geometry": {"coordinates":[-105.063497,39.856585],"type":"Point"}
}