{
  "type": "Feature",
  "properties": {
    "addr:full":"9921 US Hwy 34 Grand Lake CO 80447",
    "addr:housenumber":"9921",
    "addr:postcode":"80447",
    "addr:street":"Us Hwy 34",
    "iso:country":"US",
    "sg:address":"9921 US Hwy 34",
    "sg:city":"Grand Lake",
    "sg:classifiers":[
        {
            "category":"Real Estate",
            "subcategory":"Real Estate Agent",
            "type":"Services"
        }
    ],
    "sg:phone":"+1 970 627 8125",
    "sg:postcode":"80447",
    "sg:province":"CO",
    "sg:tags":[
        "property",
        "sales"
    ],
    "wof:name":"Soda Springs Ranch",
    "wof:placetype":"venue"
},
  "geometry": {"coordinates":[-105.879104,40.192977],"type":"Point"}
}