{
  "type": "Feature",
  "properties": {
    "addr:full":"2900 Worthington Ave Fort Collins CO 80526",
    "addr:housenumber":"2900",
    "addr:postcode":"80526",
    "addr:street":"Worthington Ave",
    "iso:country":"US",
    "sg:address":"2900 Worthington Ave",
    "sg:city":"Fort Collins",
    "sg:classifiers":[
        {
            "category":"Building & Trades",
            "subcategory":"Landscaping Services",
            "type":"Services"
        }
    ],
    "sg:phone":"+1 970 204 4822",
    "sg:postcode":"80526",
    "sg:province":"CO",
    "sg:tags":[
        "designer",
        "landscape"
    ],
    "wof:name":"Urban Ecology Studio Inc",
    "wof:placetype":"venue"
},
  "geometry": {"coordinates":[-105.09126500000001,40.546154],"type":"Point"}
}