{
  "type": "Feature",
  "properties": {
    "iso:country":"US",
    "sg:address":"20840 Co Rd 2",
    "sg:city":"Canon City",
    "sg:classifiers":[
        {
            "category":"Utilities",
            "subcategory":"Fuel Oil & Lpg",
            "type":"Services"
        }
    ],
    "sg:phone":"+1 719 276 1691",
    "sg:postcode":"81212",
    "sg:province":"CO",
    "sg:tags":[
        "dealer"
    ],
    "wof:name":"Firewood Guy",
    "wof:placetype":"venue"
},
  "geometry": {"coordinates":[-105.55502799999999,38.612863],"type":"Point"}
}