{
  "type": "Feature",
  "properties": {
    "iso:country":"US",
    "sg:address":"9692 E Arapahoe Rd",
    "sg:city":"Greenwood Vlg",
    "sg:classifiers":[
        {
            "category":"Real Estate",
            "subcategory":"Real Estate Agent",
            "type":"Services"
        }
    ],
    "sg:phone":"+1 303 791 2688",
    "sg:postcode":"80112",
    "sg:province":"CO",
    "sg:tags":[
        "management"
    ],
    "wof:name":"Power Apartment Leasing & Mrkt",
    "wof:placetype":"venue"
},
  "geometry": {"coordinates":[-104.878063,39.594964],"type":"Point"}
}