{
  "type": "Feature",
  "properties": {
    "addr:full":"7168 S Glencoe Cir Centennial CO 80122",
    "addr:housenumber":"7168",
    "addr:postcode":"80122",
    "addr:street":"S Glencoe Cir",
    "iso:country":"US",
    "sg:address":"7168 S Glencoe Cir",
    "sg:city":"Centennial",
    "sg:classifiers":[
        {
            "category":"Shopping",
            "type":"Retail Goods"
        }
    ],
    "sg:phone":"+1 303 770 0041",
    "sg:postcode":"80122",
    "sg:province":"CO",
    "sg:tags":[
        "cosmetic",
        "perfume"
    ],
    "wof:name":"Mary Kay Cosmetics",
    "wof:placetype":"venue"
},
  "geometry": {"coordinates":[-104.927307,39.586729],"type":"Point"}
}