{
  "type": "Feature",
  "properties": {
    "addr:full":"502 Haven Dr Fort Collins CO 80526",
    "addr:housenumber":"502",
    "addr:postcode":"80526",
    "addr:street":"Haven Dr",
    "iso:country":"US",
    "sg:address":"502 Haven Dr",
    "sg:city":"Fort Collins",
    "sg:classifiers":[
        {
            "category":"Building & Trades",
            "subcategory":"Construction",
            "type":"Services"
        }
    ],
    "sg:phone":"+1 970 420 4666",
    "sg:postcode":"80526",
    "sg:province":"CO",
    "sg:tags":[
        "painter"
    ],
    "wof:name":"Shade Brothers Painting",
    "wof:placetype":"venue"
},
  "geometry": {"coordinates":[-105.086203,40.536533],"type":"Point"}
}