{
  "type": "Feature",
  "properties": {
    "iso:country":"US",
    "sg:address":"2360 Cherry St",
    "sg:city":"Denver",
    "sg:classifiers":[
        {
            "category":"Professional",
            "subcategory":"Engineering",
            "type":"Services"
        }
    ],
    "sg:phone":"+1 303 388 7138",
    "sg:postcode":"80207",
    "sg:province":"CO",
    "sg:tags":[
        "consultant",
        "energy",
        "conservation"
    ],
    "wof:name":"Entegrity Wind Systems",
    "wof:placetype":"venue"
},
  "geometry": {"coordinates":[-104.933935,39.751586],"type":"Point"}
}