{
  "type": "Feature",
  "properties": {
    "iso:country":"US",
    "sg:address":"1740 Platte St",
    "sg:city":"Denver",
    "sg:classifiers":[
        {
            "category":"Building & Trades",
            "subcategory":"Landscaping Services",
            "type":"Services"
        }
    ],
    "sg:phone":"+1 303 433 7100",
    "sg:postcode":"80202",
    "sg:province":"CO",
    "sg:tags":[
        "urban",
        "planning",
        "design",
        "architecture",
        "campus",
        "landscape"
    ],
    "wof:name":"Insitedesign",
    "wof:placetype":"venue"
},
  "geometry": {"coordinates":[-105.005554,39.759211],"type":"Point"}
}