{
  "type": "Feature",
  "properties": {
    "addr:full":"8731 Grand Cypress Ln Littleton CO 80124",
    "addr:housenumber":"8731",
    "addr:postcode":"80124",
    "addr:street":"Grand Cypress Ln",
    "iso:country":"US",
    "sg:address":"8731 Grand Cypress Ln",
    "sg:city":"Littleton",
    "sg:classifiers":[
        {
            "category":"Restaurant",
            "type":"Food & Drink"
        }
    ],
    "sg:phone":"+1 303 708 0776",
    "sg:postcode":"80124",
    "sg:province":"CO",
    "sg:tags":[
        "eating"
    ],
    "wof:name":"Kitchen Angels",
    "wof:placetype":"venue"
},
  "geometry": {"coordinates":[-104.88749900000001,39.543729],"type":"Point"}
}