{
  "type": "Feature",
  "properties": {
    "iso:country":"US",
    "sg:address":"445 N Ellicott Hwy",
    "sg:city":"Calhan",
    "sg:classifiers":[
        {
            "category":"Banks & Credit Unions",
            "subcategory":"Bank",
            "type":"Services"
        }
    ],
    "sg:phone":"+1 719 683 3999",
    "sg:postcode":"80808",
    "sg:province":"CO",
    "wof:name":"Farmers State Bank",
    "wof:placetype":"venue"
},
  "geometry": {"coordinates":[-104.387058,38.837717],"type":"Point"}
}