{
  "type": "Feature",
  "properties": {
    "iso:country":"US",
    "sg:address":"615 S Federal Blvd",
    "sg:city":"Denver",
    "sg:classifiers":[
        {
            "category":"Social Services",
            "type":"Services"
        }
    ],
    "sg:phone":"+1 303 935 9994",
    "sg:postcode":"80219",
    "sg:province":"CO",
    "sg:tags":[
        "organization",
        "welfare"
    ],
    "wof:name":"Vietnamese Elderly Assoc Of Co",
    "wof:placetype":"venue"
},
  "geometry": {"coordinates":[-105.02517400000001,39.705215],"type":"Point"}
}