{
  "type": "Feature",
  "properties": {
    "iso:country":"US",
    "sg:address":"2452 F Rd",
    "sg:city":"Grand Junction",
    "sg:classifiers":[
        {
            "category":"Real Estate",
            "subcategory":"Real Estate Services",
            "type":"Services"
        }
    ],
    "sg:phone":"+1 970 256 0071",
    "sg:postcode":"81505",
    "sg:province":"CO",
    "sg:tags":[
        "company",
        "title"
    ],
    "wof:name":"Security Title Guaranty Co",
    "wof:placetype":"venue"
},
  "geometry": {"coordinates":[-108.596082,39.091951],"type":"Point"}
}