{
  "type": "Feature",
  "properties": {
    "addr:full":"1226 Leeds Ave Montrose CO 81401",
    "addr:housenumber":"1226",
    "addr:postcode":"81401",
    "addr:street":"Leeds Ave",
    "iso:country":"US",
    "sg:address":"1226 Leeds Ave",
    "sg:city":"Montrose",
    "sg:classifiers":[
        {
            "category":"Shopping",
            "subcategory":"Gifts & Souvenirs",
            "type":"Retail Goods"
        }
    ],
    "sg:phone":"+1 970 249 7199",
    "sg:postcode":"81401",
    "sg:province":"CO",
    "wof:name":"Kemmco",
    "wof:placetype":"venue"
},
  "geometry": {"coordinates":[-107.849174,38.471038],"type":"Point"}
}