{
  "type": "Feature",
  "properties": {
    "iso:country":"US",
    "sg:address":"2255 E 18th Ave",
    "sg:city":"Denver",
    "sg:classifiers":[
        {
            "category":"Professional",
            "subcategory":"Research",
            "type":"Services"
        }
    ],
    "sg:phone":"+1 303 322 1220",
    "sg:postcode":"80206",
    "sg:province":"CO",
    "sg:tags":[
        "market",
        "analysis"
    ],
    "wof:name":"Nvision Research",
    "wof:placetype":"venue"
},
  "geometry": {"coordinates":[-104.960357,39.744873],"type":"Point"}
}