{
  "type": "Feature",
  "properties": {
    "addr:full":"321 S Nevada Ave Colorado Springs CO 80903",
    "addr:housenumber":"321",
    "addr:postcode":"80903",
    "addr:street":"S Nevada Ave",
    "iso:country":"US",
    "sg:address":"321 S Nevada Ave",
    "sg:city":"Colorado Springs",
    "sg:classifiers":[
        {
            "category":"Professional",
            "subcategory":"Employment Agencies",
            "type":"Services"
        }
    ],
    "sg:phone":"+1 719 473 5531",
    "sg:postcode":"80903",
    "sg:province":"CO",
    "sg:tags":[
        "help",
        "contractor"
    ],
    "wof:name":"Tandem Staffing For Industry",
    "wof:placetype":"venue"
},
  "geometry": {"coordinates":[-104.821771,38.828444],"type":"Point"}
}