{
  "type": "Feature",
  "properties": {
    "iso:country":"US",
    "sg:address":"255 E Ave",
    "sg:city":"Limon",
    "sg:classifiers":[
        {
            "category":"Personal",
            "subcategory":"Beauty Salon",
            "type":"Services"
        }
    ],
    "sg:phone":"+1 719 775 9334",
    "sg:postcode":"80828",
    "sg:province":"CO",
    "wof:name":"Shear Sensations",
    "wof:placetype":"venue"
},
  "geometry": {"coordinates":[-103.687923,39.262913],"type":"Point"}
}