{
  "type": "Feature",
  "properties": {
    "iso:country":"US",
    "sg:address":"13405 Co Rd X",
    "sg:city":"Seibert",
    "sg:classifiers":[
        {
            "category":"Farming",
            "subcategory":"Livestock Farm",
            "type":"Manufacturing & Wholesale Goods"
        }
    ],
    "sg:phone":"+1 970 664 2449",
    "sg:postcode":"80834",
    "sg:province":"CO",
    "sg:tags":[
        "beef",
        "feedlot",
        "cattle"
    ],
    "wof:name":"Dykstra Ranch Inc",
    "wof:placetype":"venue"
},
  "geometry": {"coordinates":[-102.88494300000001,39.330274],"type":"Point"}
}