{
  "type": "Feature",
  "properties": {
    "addr:full":"1501 W 13th Ave Denver CO 80204",
    "addr:housenumber":"1501",
    "addr:postcode":"80204",
    "addr:street":"W 13Th Ave",
    "iso:country":"US",
    "sg:address":"1501 W 13th Ave",
    "sg:city":"Denver",
    "sg:classifiers":[
        {
            "category":"Building & Trades",
            "subcategory":"Locksmith",
            "type":"Services"
        }
    ],
    "sg:phone":"+1 303 323 0156",
    "sg:postcode":"80204",
    "sg:province":"CO",
    "sg:tags":[
        "key"
    ],
    "wof:name":"Locks A A A Locksmith",
    "wof:placetype":"venue"
},
  "geometry": {"coordinates":[-105.00633999999999,39.737037],"type":"Point"}
}