{
  "type": "Feature",
  "properties": {
    "addr:full":"125 E 30th St Rifle CO 81650",
    "addr:housenumber":"125",
    "addr:postcode":"81650",
    "addr:street":"E 30Th St",
    "iso:country":"US",
    "sg:address":"125 E 30th St",
    "sg:city":"Rifle",
    "sg:classifiers":[
        {
            "category":"Retail",
            "subcategory":"Auto Rental",
            "type":"Services"
        }
    ],
    "sg:phone":"+1 970 625 3259",
    "sg:postcode":"81650",
    "sg:province":"CO",
    "sg:tags":[
        "renting",
        "truck",
        "leasing"
    ],
    "wof:name":"U-Haul Co",
    "wof:placetype":"venue"
},
  "geometry": {"coordinates":[-107.774866,39.556336],"type":"Point"}
}