{
  "type": "Feature",
  "properties": {
    "iso:country":"US",
    "sg:address":"69 Mission Dr",
    "sg:city":"Pueblo West",
    "sg:classifiers":[
        {
            "category":"Building & Trades",
            "subcategory":"Construction",
            "type":"Services"
        }
    ],
    "sg:phone":"+1 719 647 3029",
    "sg:postcode":"81007",
    "sg:province":"CO",
    "sg:tags":[
        "general",
        "contractor"
    ],
    "wof:name":"Printz TL Constructors",
    "wof:placetype":"venue"
},
  "geometry": {"coordinates":[-104.708215,38.330704],"type":"Point"}
}