{
  "type": "Feature",
  "properties": {
    "addr:full":"7800 E Dorado Pl Englewood CO 80111",
    "addr:housenumber":"7800",
    "addr:postcode":"80111",
    "addr:street":"E Dorado Pl",
    "iso:country":"US",
    "sg:address":"7800 E Dorado Pl",
    "sg:city":"Englewood",
    "sg:classifiers":[
        {
            "category":"Education",
            "subcategory":"Vocational School",
            "type":"Public Place"
        }
    ],
    "sg:phone":"+1 720 346 1710",
    "sg:postcode":"80111",
    "sg:province":"CO",
    "sg:tags":[
        "training",
        "computer",
        "software"
    ],
    "wof:name":"Ameriteach UCI Inc",
    "wof:placetype":"venue"
},
  "geometry": {"coordinates":[-104.896682,39.611481],"type":"Point"}
}