{
  "type": "Feature",
  "properties": {
    "addr:full":"474 E Bridge St Hotchkiss CO 81419",
    "addr:housenumber":"474",
    "addr:postcode":"81419",
    "addr:street":"E Bridge St",
    "iso:country":"US",
    "sg:address":"474 E Bridge St",
    "sg:city":"Hotchkiss",
    "sg:classifiers":[
        {
            "category":"Autos & Motor Vehicles",
            "subcategory":"Fuel & Gas Station",
            "type":"Retail Goods"
        },
        {
            "category":"Retail",
            "subcategory":"Auto Repair",
            "type":"Services"
        }
    ],
    "sg:phone":"+1 970 872 2137",
    "sg:postcode":"81419",
    "sg:province":"CO",
    "sg:tags":[
        "station",
        "oil",
        "gasoline",
        "general"
    ],
    "wof:name":"North Fork Standard Inc",
    "wof:placetype":"venue"
},
  "geometry": {"coordinates":[-107.71495899999999,38.798976],"type":"Point"}
}