{
  "type": "Feature",
  "properties": {
    "addr:full":"2209 9th Ave Greeley CO 80631",
    "addr:housenumber":"2209",
    "addr:postcode":"80631",
    "addr:street":"9Th Ave",
    "iso:country":"US",
    "sg:address":"2209 9th Ave",
    "sg:city":"Greeley",
    "sg:classifiers":[
        {
            "category":"Professional",
            "subcategory":"Business Services",
            "type":"Services"
        }
    ],
    "sg:phone":"+1 970 353 3184",
    "sg:postcode":"80631",
    "sg:province":"CO",
    "sg:tags":[
        "embroidery"
    ],
    "wof:name":"Lee's Sewing Ctr & Repair",
    "wof:placetype":"venue"
},
  "geometry": {"coordinates":[-104.692967,40.401285],"type":"Point"}
}