{
  "type": "Feature",
  "properties": {
    "iso:country":"US",
    "sg:address":"4040 Clearview Frontage Rd",
    "sg:city":"Colorado Springs",
    "sg:classifiers":[
        {
            "category":"Utilities",
            "subcategory":"Refuse",
            "type":"Services"
        }
    ],
    "sg:phone":"+1 719 390 5097",
    "sg:postcode":"80911",
    "sg:province":"CO",
    "sg:tags":[
        "disposal",
        "rubbish",
        "collection"
    ],
    "wof:name":"Wsi",
    "wof:placetype":"venue"
},
  "geometry": {"coordinates":[-104.739176,38.774301],"type":"Point"}
}