{
  "type": "Feature",
  "properties": {
    "addr:full":"911 S Hazel Ct Denver CO 80219",
    "addr:housenumber":"911",
    "addr:postcode":"80219",
    "addr:street":"S Hazel Ct",
    "iso:country":"US",
    "sg:address":"911 S Hazel Ct",
    "sg:city":"Denver",
    "sg:classifiers":[
        {
            "category":"Education",
            "subcategory":"School",
            "type":"Public Place"
        }
    ],
    "sg:phone":"+1 720 424 0000",
    "sg:postcode":"80219",
    "sg:province":"CO",
    "sg:tags":[
        "high",
        "middle",
        "elementary"
    ],
    "wof:name":"Kepner Junior High School",
    "wof:placetype":"venue"
},
  "geometry": {"coordinates":[-105.02800000000001,39.700001],"type":"Point"}
}