{
  "type": "Feature",
  "properties": {
    "iso:country":"US",
    "sg:address":"11881 E 33rd Ave",
    "sg:city":"Aurora",
    "sg:classifiers":[
        {
            "category":"Wholesale",
            "subcategory":"Chemicals & Plastics",
            "type":"Manufacturing & Wholesale Goods"
        }
    ],
    "sg:phone":"+1 303 344 8824",
    "sg:postcode":"80010",
    "sg:province":"CO",
    "sg:tags":[
        "floor",
        "treatment",
        "compound"
    ],
    "wof:name":"Superior Floor Equipment",
    "wof:placetype":"venue"
},
  "geometry": {"coordinates":[-104.84804200000001,39.763941],"type":"Point"}
}