{
  "type": "Feature",
  "properties": {
    "iso:country":"US",
    "sg:address":"10496 E Colfax Ave",
    "sg:city":"Aurora",
    "sg:classifiers":[
        {
            "category":"Professional",
            "type":"Services"
        },
        {
            "category":"Restaurant",
            "type":"Food & Drink"
        },
        {
            "category":"Fast Food",
            "type":"Food & Drink"
        }
    ],
    "sg:phone":"+1 720 975 2000",
    "sg:postcode":"80010",
    "sg:province":"CO",
    "sg:tags":[
        "delivery",
        "take",
        "pizza"
    ],
    "sg:website":"http://www.mypizzapizza.com",
    "wof:name":"Little Caesars",
    "wof:placetype":"venue"
},
  "geometry": {"coordinates":[-104.865852,39.7401],"type":"Point"}
}