{
  "type": "Feature",
  "properties": {
    "iso:country":"US",
    "sg:address":"7450 Woodstock St",
    "sg:city":"Colorado Springs",
    "sg:classifiers":[
        {
            "category":"Shopping",
            "subcategory":"Computers & Home Electronics",
            "type":"Retail Goods"
        }
    ],
    "sg:phone":"+1 719 391 8674",
    "sg:postcode":"80911",
    "sg:province":"CO",
    "wof:name":"Millenium Computers",
    "wof:placetype":"venue"
},
  "geometry": {"coordinates":[-104.69000800000001,38.728332],"type":"Point"}
}