{
  "type": "Feature",
  "properties": {
    "iso:country":"US",
    "sg:address":"309 Marmot Cir",
    "sg:city":"Lafayette",
    "sg:classifiers":[
        {
            "category":"Real Estate",
            "subcategory":"Real Estate Agent",
            "type":"Services"
        }
    ],
    "sg:phone":"+1 303 664 0952",
    "sg:postcode":"80026",
    "sg:province":"CO",
    "wof:name":"Trek Enterprises LLC",
    "wof:placetype":"venue"
},
  "geometry": {"coordinates":[-105.096283,39.970402],"type":"Point"}
}