{
  "type": "Feature",
  "properties": {
    "addr:full":"50771 State Hwy 71 Limon CO 80828",
    "addr:housenumber":"50771",
    "addr:postcode":"80828",
    "addr:street":"State Hwy 71",
    "iso:country":"US",
    "sg:address":"50771 State Hwy 71",
    "sg:city":"Limon",
    "sg:classifiers":[
        {
            "category":"Recreation",
            "type":"Entertainment"
        }
    ],
    "sg:phone":"+1 719 775 9461",
    "sg:postcode":"80828",
    "sg:province":"CO",
    "sg:tags":[
        "course",
        "golf"
    ],
    "wof:name":"Tamarack Golf Club",
    "wof:placetype":"venue"
},
  "geometry": {"coordinates":[-103.69594600000001,39.240876],"type":"Point"}
}