{
  "type": "Feature",
  "properties": {
    "addr:full":"4955 E 74th Ave Commerce City CO 80022",
    "addr:housenumber":"4955",
    "addr:postcode":"80022",
    "addr:street":"E 74Th Ave",
    "iso:country":"US",
    "sg:address":"4955 E 74th Ave",
    "sg:city":"Commerce City",
    "sg:classifiers":[
        {
            "category":"Government",
            "subcategory":"Office",
            "type":"Public Place"
        }
    ],
    "sg:phone":"+1 303 853 7000",
    "sg:postcode":"80022",
    "sg:province":"CO",
    "sg:tags":[
        "general"
    ],
    "wof:name":"County of Adams",
    "wof:placetype":"venue"
},
  "geometry": {"coordinates":[-104.92805799999999,39.830947],"type":"Point"}
}