{
  "type": "Feature",
  "properties": {
    "addr:full":"950 Co Rd 245 New Castle CO 81647",
    "addr:housenumber":"950;245",
    "addr:postcode":"81647",
    "addr:street":"Co Rd",
    "iso:country":"US",
    "sg:address":"950 Co Rd 245",
    "sg:city":"New Castle",
    "sg:classifiers":[
        {
            "category":"Building & Trades",
            "subcategory":"Construction",
            "type":"Services"
        }
    ],
    "sg:phone":"+1 970 984 2083",
    "sg:postcode":"81647",
    "sg:province":"CO",
    "sg:tags":[
        "concrete",
        "contractor"
    ],
    "wof:name":"Davis Construction",
    "wof:placetype":"venue"
},
  "geometry": {"coordinates":[-107.556513,39.591431],"type":"Point"}
}