{
  "type": "Feature",
  "properties": {
    "addr:full":"626 Main St Walsenburg CO 81089",
    "addr:housenumber":"626",
    "addr:postcode":"81089",
    "addr:street":"Main St",
    "iso:country":"US",
    "sg:address":"626 Main St",
    "sg:city":"Walsenburg",
    "sg:classifiers":[
        {
            "category":"Shopping",
            "subcategory":"Computers & Home Electronics",
            "type":"Retail Goods"
        }
    ],
    "sg:phone":"+1 719 738 3688",
    "sg:postcode":"81089",
    "sg:province":"CO",
    "wof:name":"Vintage Electronics & Sales",
    "wof:placetype":"venue"
},
  "geometry": {"coordinates":[-104.780659,37.623444],"type":"Point"}
}