{
  "type": "Feature",
  "properties": {
    "iso:country":"US",
    "sg:address":"1700 Lincoln St",
    "sg:city":"Denver",
    "sg:classifiers":[
        {
            "category":"Government",
            "subcategory":"Office",
            "type":"Public Place"
        }
    ],
    "sg:phone":"+1 303 866 0543",
    "sg:postcode":"80203",
    "sg:province":"CO",
    "sg:tags":[
        "international",
        "affairs"
    ],
    "wof:name":"Royal Norwegian Consulate",
    "wof:placetype":"venue"
},
  "geometry": {"coordinates":[-104.98611699999999,39.744889],"type":"Point"}
}