{
  "type": "Feature",
  "properties": {
    "iso:country":"US",
    "sg:address":"810 3rd St",
    "sg:city":"Windsor",
    "sg:classifiers":[
        {
            "category":"Education",
            "subcategory":"School",
            "type":"Public Place"
        }
    ],
    "sg:phone":"+1 970 686 8324",
    "sg:postcode":"80550",
    "sg:province":"CO",
    "wof:name":"Flow Center School",
    "wof:placetype":"venue"
},
  "geometry": {"coordinates":[-104.90085000000001,40.471965],"type":"Point"}
}