{
  "type": "Feature",
  "properties": {
    "iso:country":"US",
    "sg:address":"1260 Linden Ave",
    "sg:city":"Boulder",
    "sg:classifiers":[
        {
            "category":"Shopping",
            "subcategory":"Computers & Home Electronics",
            "type":"Retail Goods"
        }
    ],
    "sg:phone":"+1 303 449 1440",
    "sg:postcode":"80304",
    "sg:province":"CO",
    "wof:name":"Modern Audio Consultants",
    "wof:placetype":"venue"
},
  "geometry": {"coordinates":[-105.28134900000001,40.04098],"type":"Point"}
}