{
  "type": "Feature",
  "properties": {
    "addr:full":"2620 S Copper Psge Steamboat Springs CO 80487",
    "addr:housenumber":"2620",
    "addr:postcode":"80487",
    "addr:street":"S Copper Psge",
    "iso:country":"US",
    "sg:address":"2620 S Copper Psge",
    "sg:city":"Steamboat Springs",
    "sg:classifiers":[
        {
            "category":"Shopping",
            "subcategory":"Bicycles & Sporting Goods",
            "type":"Retail Goods"
        }
    ],
    "sg:phone":"+1 970 879 1023",
    "sg:postcode":"80487",
    "sg:province":"CO",
    "wof:name":"Elk River Archery",
    "wof:placetype":"venue"
},
  "geometry": {"coordinates":[-106.856264,40.510899],"type":"Point"}
}