{
  "type": "Feature",
  "properties": {
    "iso:country":"US",
    "sg:address":"909 York St",
    "sg:city":"Denver",
    "sg:classifiers":[
        {
            "category":"Education",
            "subcategory":"Library",
            "type":"Public Place"
        }
    ],
    "sg:phone":"+1 720 865 3570",
    "sg:postcode":"80206",
    "sg:province":"CO",
    "wof:name":"Helen Fowler Library",
    "wof:placetype":"venue"
},
  "geometry": {"coordinates":[-104.960217,39.730506],"type":"Point"}
}