{
  "type": "Feature",
  "properties": {
    "iso:country":"US",
    "sg:address":"1525 E Evans Ave",
    "sg:city":"Pueblo",
    "sg:classifiers":[
        {
            "category":"Restaurant",
            "type":"Food & Drink"
        }
    ],
    "sg:phone":"+1 719 564 0095",
    "sg:postcode":"81004",
    "sg:province":"CO",
    "sg:tags":[
        "eating"
    ],
    "wof:name":"Pasta Cottage",
    "wof:placetype":"venue"
},
  "geometry": {"coordinates":[-104.615022,38.239318],"type":"Point"}
}