{
  "type": "Feature",
  "properties": {
    "addr:full":"905 Nolte Dr W Colorado Springs CO 80916",
    "addr:housenumber":"905",
    "addr:postcode":"80916",
    "addr:street":"Nolte Dr W",
    "iso:country":"US",
    "sg:address":"905 Nolte Dr W",
    "sg:city":"Colorado Springs",
    "sg:classifiers":[
        {
            "category":"Real Estate",
            "subcategory":"Real Estate Agent",
            "type":"Services"
        },
        {
            "category":"Professional",
            "subcategory":"Business Services",
            "type":"Services"
        }
    ],
    "sg:phone":"+1 719 574 7781",
    "sg:postcode":"80916",
    "sg:province":"CO",
    "sg:tags":[
        "appraiser"
    ],
    "wof:name":"Acts 238 Appraisal Service",
    "wof:placetype":"venue"
},
  "geometry": {"coordinates":[-104.73687200000001,38.819073],"type":"Point"}
}