{
  "type": "Feature",
  "properties": {
    "iso:country":"US",
    "sg:address":"9090 Ridgeline Blvd",
    "sg:city":"Littleton",
    "sg:classifiers":[
        {
            "category":"Real Estate",
            "subcategory":"Real Estate Services",
            "type":"Services"
        }
    ],
    "sg:phone":"+1 303 339 4322",
    "sg:postcode":"80129",
    "sg:province":"CO",
    "sg:tags":[
        "company",
        "title"
    ],
    "wof:name":"Vista Title",
    "wof:placetype":"venue"
},
  "geometry": {"coordinates":[-104.996407,39.551182],"type":"Point"}
}