{
  "type": "Feature",
  "properties": {
    "iso:country":"US",
    "sg:address":"740 Lipan St",
    "sg:city":"Denver",
    "sg:classifiers":[
        {
            "category":"Building & Trades",
            "subcategory":"Electrical",
            "type":"Services"
        }
    ],
    "sg:phone":"+1 303 892 8852",
    "sg:postcode":"80204",
    "sg:province":"CO",
    "sg:tags":[
        "electrical",
        "contractor"
    ],
    "wof:name":"Connelly Electric Co",
    "wof:placetype":"venue"
},
  "geometry": {"coordinates":[-105.001516,39.72826],"type":"Point"}
}