{
  "type": "Feature",
  "properties": {
    "iso:country":"US",
    "sg:address":"4661 Brighton Blvd",
    "sg:city":"Denver",
    "sg:classifiers":[
        {
            "category":"Wholesale",
            "subcategory":"Auto Parts",
            "type":"Manufacturing & Wholesale Goods"
        }
    ],
    "sg:phone":"+1 303 296 8644",
    "sg:postcode":"80216",
    "sg:province":"CO",
    "sg:tags":[
        "automobile",
        "supply"
    ],
    "wof:name":"Auto & Truck Parts Wholesale",
    "wof:placetype":"venue"
},
  "geometry": {"coordinates":[-104.96673199999999,39.780764],"type":"Point"}
}