{
  "type": "Feature",
  "properties": {
    "iso:country":"US",
    "sg:address":"1613 Pelican Lake Pt",
    "sg:city":"Windsor",
    "sg:classifiers":[
        {
            "category":"Professional",
            "subcategory":"Lawyer & Legal Services",
            "type":"Services"
        }
    ],
    "sg:phone":"+1 970 686 6618",
    "sg:postcode":"80550",
    "sg:province":"CO",
    "wof:name":"Hagen Jo Anne Esq",
    "wof:placetype":"venue"
},
  "geometry": {"coordinates":[-104.89865500000001,40.455763],"type":"Point"}
}