{
  "type": "Feature",
  "properties": {
    "addr:full":"3205 S Winona Ct Denver CO 80236",
    "addr:housenumber":"3205",
    "addr:postcode":"80236",
    "addr:street":"S Winona Ct",
    "iso:country":"US",
    "sg:address":"3205 S Winona Ct",
    "sg:city":"Denver",
    "sg:classifiers":[
        {
            "category":"Professional",
            "type":"Services"
        }
    ],
    "sg:phone":"+1 303 722 7075",
    "sg:postcode":"80236",
    "sg:province":"CO",
    "wof:name":"Francisco Sanchez",
    "wof:placetype":"venue"
},
  "geometry": {"coordinates":[-105.04649999999999,39.65694],"type":"Point"}
}