{
  "type": "Feature",
  "properties": {
    "addr:full":"854 S Medea Way Denver CO 80209",
    "addr:housenumber":"854",
    "addr:postcode":"80209",
    "addr:street":"S Medea Way",
    "iso:country":"US",
    "sg:address":"854 S Medea Way",
    "sg:city":"Denver",
    "sg:classifiers":[
        {
            "category":"Building & Trades",
            "subcategory":"Plumbing",
            "type":"Services"
        }
    ],
    "sg:phone":"+1 303 733 5279",
    "sg:postcode":"80209",
    "sg:province":"CO",
    "sg:tags":[
        "contractor"
    ],
    "wof:name":"Cahill Sprinkler Service",
    "wof:placetype":"venue"
},
  "geometry": {"coordinates":[-104.952788,39.701373],"type":"Point"}
}