{
  "type": "Feature",
  "properties": {
    "addr:full":"676 Independence Valley Dr Grand Junction CO 81503",
    "addr:housenumber":"676",
    "addr:postcode":"81503",
    "addr:street":"Independence Valley Dr",
    "iso:country":"US",
    "sg:address":"676 Independence Valley Dr",
    "sg:city":"Grand Junction",
    "sg:classifiers":[
        {
            "category":"Wholesale",
            "subcategory":"Apparel",
            "type":"Manufacturing & Wholesale Goods"
        }
    ],
    "sg:phone":"+1 970 626 5057",
    "sg:postcode":"81503",
    "sg:province":"CO",
    "sg:tags":[
        "mfg",
        "printed",
        "representative"
    ],
    "wof:name":"Morningstar Design Group Inc",
    "wof:placetype":"venue"
},
  "geometry": {"coordinates":[-108.67458499999999,39.104782],"type":"Point"}
}