{
  "type": "Feature",
  "properties": {
    "addr:full":"1535 E Evans Ave Denver CO 80210",
    "addr:housenumber":"1535",
    "addr:postcode":"80210",
    "addr:street":"E Evans Ave",
    "iso:country":"US",
    "sg:address":"1535 E Evans Ave",
    "sg:city":"Denver",
    "sg:classifiers":[
        {
            "category":"Restaurant",
            "type":"Food & Drink"
        }
    ],
    "sg:phone":"+1 303 733 4292",
    "sg:postcode":"80210",
    "sg:province":"CO",
    "sg:tags":[
        "mexican"
    ],
    "sg:website":"www.carlsjr.com",
    "wof:name":"Carl's Jr",
    "wof:placetype":"venue"
},
  "geometry": {"coordinates":[-104.96951300000001,39.678634],"type":"Point"}
}