{
  "type": "Feature",
  "properties": {
    "addr:full":"2420 Ski Trail Ln Steamboat Springs CO 80487",
    "addr:postcode":"2420;80487",
    "addr:street":"Ski Trail Ln",
    "iso:country":"US",
    "sg:address":"2420 Ski Trail Ln",
    "sg:city":"Steamboat Springs",
    "sg:classifiers":[
        {
            "category":"Restaurant",
            "type":"Food & Drink"
        }
    ],
    "sg:phone":"+1 970 879 5710",
    "sg:postcode":"80487",
    "sg:province":"CO",
    "sg:tags":[
        "eating"
    ],
    "wof:name":"A Catered Affair",
    "wof:placetype":"venue"
},
  "geometry": {"coordinates":[-106.798564,40.457714],"type":"Point"}
}