{
  "type": "Feature",
  "properties": {
    "iso:country":"US",
    "sg:address":"4615 Sandstone Rd",
    "sg:city":"Monument",
    "sg:classifiers":[
        {
            "category":"Building & Trades",
            "subcategory":"Construction",
            "type":"Services"
        }
    ],
    "sg:phone":"+1 719 481 6778",
    "sg:postcode":"80132",
    "sg:province":"CO",
    "sg:tags":[
        "contractor"
    ],
    "wof:name":"Clifford Properties",
    "wof:placetype":"venue"
},
  "geometry": {"coordinates":[-104.911405,39.096178],"type":"Point"}
}