{
  "type": "Feature",
  "properties": {
    "iso:country":"US",
    "sg:address":"2440 Arapahoe Ave",
    "sg:city":"Boulder",
    "sg:classifiers":[
        {
            "category":"Shopping",
            "subcategory":"Crafts & Fabrics",
            "type":"Retail Goods"
        }
    ],
    "sg:phone":"+1 303 444 1954",
    "sg:postcode":"80302",
    "sg:province":"CO",
    "sg:tags":[
        "sewing"
    ],
    "sg:website":"www.joann.com",
    "wof:name":"Jo-Ann Fabrics & Crafts",
    "wof:placetype":"venue"
},
  "geometry": {"coordinates":[-105.258876,40.014478],"type":"Point"}
}