{
  "type": "Feature",
  "properties": {
    "iso:country":"US",
    "sg:address":"450 S Galena St",
    "sg:city":"Aspen",
    "sg:classifiers":[
        {
            "category":"Shopping",
            "subcategory":"Books",
            "type":"Retail Goods"
        }
    ],
    "sg:phone":"+1 970 544 3398",
    "sg:postcode":"81611",
    "sg:province":"CO",
    "sg:tags":[
        "dealer"
    ],
    "wof:name":"Books For Life Foundation",
    "wof:placetype":"venue"
},
  "geometry": {"coordinates":[-106.818986,39.187435],"type":"Point"}
}