{
  "type": "Feature",
  "properties": {
    "iso:country":"US",
    "sg:address":"2614 E 13th Ave",
    "sg:city":"Denver",
    "sg:classifiers":[
        {
            "category":"Health Services",
            "subcategory":"Chiropractor",
            "type":"Services"
        }
    ],
    "sg:phone":"+1 303 322 0188",
    "sg:postcode":"80206",
    "sg:province":"CO",
    "sg:website":"www.congressparkchiropracticwell...",
    "wof:name":"Congress Park Chiropractic Wellness Center",
    "wof:placetype":"venue"
},
  "geometry": {"coordinates":[-104.955803,39.736612],"type":"Point"}
}