{
  "type": "Feature",
  "properties": {
    "addr:full":"2643 17th Street Denver CO 80211",
    "addr:housenumber":"2643",
    "addr:postcode":"80211",
    "addr:street":"17Th Street",
    "iso:country":"US",
    "sg:address":"2643 17th Street",
    "sg:city":"Denver",
    "sg:classifiers":[
        {
            "category":"Home & Garden",
            "subcategory":"Furniture",
            "type":"Retail Goods"
        }
    ],
    "sg:phone":"+1 303 433 2501",
    "sg:postcode":"80211",
    "sg:province":"CO",
    "sg:tags":[
        "store"
    ],
    "wof:name":"Leever Builders Supply",
    "wof:placetype":"venue"
},
  "geometry": {"coordinates":[-105.00988099999999,39.760522],"type":"Point"}
}