{
  "type": "Feature",
  "properties": {
    "iso:country":"US",
    "sg:address":"901 Bannock St",
    "sg:city":"Denver",
    "sg:classifiers":[
        {
            "category":"Education",
            "subcategory":"School",
            "type":"Public Place"
        }
    ],
    "sg:phone":"+1 303 575 6690",
    "sg:postcode":"80204",
    "sg:province":"CO",
    "sg:tags":[
        "urban",
        "for",
        "community"
    ],
    "wof:name":"Ps1",
    "wof:placetype":"venue"
},
  "geometry": {"coordinates":[-104.990257,39.732051],"type":"Point"}
}