{
  "type": "Feature",
  "properties": {
    "addr:full":"630 Kimbark St Longmont CO 80501",
    "addr:housenumber":"630",
    "addr:postcode":"80501",
    "addr:street":"Kimbark St",
    "iso:country":"US",
    "sg:address":"630 Kimbark St",
    "sg:city":"Longmont",
    "sg:classifiers":[
        {
            "category":"Health Services",
            "subcategory":"Health Practitioner",
            "type":"Services"
        }
    ],
    "sg:phone":"+1 303 772 4450",
    "sg:postcode":"80501",
    "sg:province":"CO",
    "sg:tags":[
        "psychologist"
    ],
    "wof:name":"Family Therapy & Mediation",
    "wof:placetype":"venue"
},
  "geometry": {"coordinates":[-105.101096,40.170174],"type":"Point"}
}