{
  "type": "Feature",
  "properties": {
    "iso:country":"US",
    "sg:address":"2380 Deer Trail Creek Dr",
    "sg:city":"Brighton",
    "sg:classifiers":[
        {
            "category":"Manufacturing",
            "subcategory":"Signs",
            "type":"Manufacturing & Wholesale Goods"
        }
    ],
    "sg:phone":"+1 303 853 0000",
    "sg:postcode":"80601",
    "sg:province":"CO",
    "wof:name":"Looney For Logos",
    "wof:placetype":"venue"
},
  "geometry": {"coordinates":[-104.79277999999999,39.974539],"type":"Point"}
}