{
  "type": "Feature",
  "properties": {
    "iso:country":"US",
    "sg:address":"14730 Co Rd 39",
    "sg:city":"Sterling",
    "sg:classifiers":[
        {
            "category":"Mining & Drilling",
            "type":"Manufacturing & Wholesale Goods"
        }
    ],
    "sg:phone":"+1 970 522 2533",
    "sg:postcode":"80751",
    "sg:province":"CO",
    "sg:tags":[
        "field",
        "oil"
    ],
    "wof:name":"Baney Well Svc",
    "wof:placetype":"venue"
},
  "geometry": {"coordinates":[-103.221379,40.652022],"type":"Point"}
}