{
  "type": "Feature",
  "properties": {
    "iso:country":"US",
    "sg:address":"231 S Victoria Ave",
    "sg:city":"Pueblo",
    "sg:classifiers":[
        {
            "category":"Real Estate",
            "subcategory":"Real Estate Agent",
            "type":"Services"
        }
    ],
    "sg:phone":"+1 719 543 2080",
    "sg:postcode":"81003",
    "sg:province":"CO",
    "wof:name":"Carlsson Real Estate Inc",
    "wof:placetype":"venue"
},
  "geometry": {"coordinates":[-104.615441,38.264475],"type":"Point"}
}