{
  "type": "Feature",
  "properties": {
    "iso:country":"US",
    "sg:address":"9168 W Jewell Ave",
    "sg:city":"Lakewood",
    "sg:classifiers":[
        {
            "category":"Restaurant",
            "type":"Food & Drink"
        }
    ],
    "sg:phone":"+1 303 985 8711",
    "sg:postcode":"80232",
    "sg:province":"CO",
    "wof:name":"Garramone's Pizza & Italian",
    "wof:placetype":"venue"
},
  "geometry": {"coordinates":[-105.096977,39.682109],"type":"Point"}
}