{
  "type": "Feature",
  "properties": {
    "addr:full":"2707 E Bromley Ln Brighton CO 80602",
    "addr:housenumber":"2707",
    "addr:postcode":"80602",
    "addr:street":"E Bromley Ln",
    "iso:country":"US",
    "sg:address":"2707 E Bromley Ln",
    "sg:city":"Brighton",
    "sg:classifiers":[
        {
            "category":"Banks & Credit Unions",
            "subcategory":"Bank",
            "type":"Services"
        }
    ],
    "sg:phone":"+1 303 637 9797",
    "sg:postcode":"80602",
    "sg:province":"CO",
    "wof:name":"Guaranty Bank & Trust",
    "wof:placetype":"venue"
},
  "geometry": {"coordinates":[-104.789095,39.972339],"type":"Point"}
}