{
  "type": "Feature",
  "properties": {
    "addr:full":"4888 Pearl East Cir # 108 Boulder CO 80301",
    "addr:housenumber":"4888",
    "addr:postcode":"80301",
    "addr:street":"Pearl East Cir # 108",
    "iso:country":"US",
    "sg:address":"4888 Pearl East Cir # 108",
    "sg:city":"Boulder",
    "sg:classifiers":[
        {
            "category":"Professional",
            "subcategory":"Engineering",
            "type":"Services"
        },
        {
            "category":"Professional",
            "subcategory":"Management & Consulting",
            "type":"Services"
        }
    ],
    "sg:phone":"+1 303 443 3282",
    "sg:postcode":"80301",
    "sg:province":"CO",
    "sg:tags":[
        "consultant",
        "energy",
        "engineer",
        "ecological",
        "environmental"
    ],
    "sg:website":"http://www.walshenv.com",
    "wof:name":"Walsh Environmental",
    "wof:placetype":"venue"
},
  "geometry": {"coordinates":[-105.238501,40.021149],"type":"Point"}
}