{
  "type": "Feature",
  "properties": {
    "addr:full":"2755 Grass Mesa Rd Rifle CO 81650",
    "addr:housenumber":"2755",
    "addr:postcode":"81650",
    "addr:street":"Grass Mesa Rd",
    "iso:country":"US",
    "sg:address":"2755 Grass Mesa Rd",
    "sg:city":"Rifle",
    "sg:classifiers":[
        {
            "category":"Farming",
            "subcategory":"Livestock Farm",
            "type":"Manufacturing & Wholesale Goods"
        }
    ],
    "sg:phone":"+1 970 625 2433",
    "sg:postcode":"81650",
    "sg:province":"CO",
    "sg:tags":[
        "animal",
        "general"
    ],
    "wof:name":"Mountain Angel Ranch LLC",
    "wof:placetype":"venue"
},
  "geometry": {"coordinates":[-107.76621400000001,39.496105],"type":"Point"}
}