{
  "type": "Feature",
  "properties": {
    "iso:country":"US",
    "sg:address":"904 Diana St",
    "sg:city":"Fort Morgan",
    "sg:classifiers":[
        {
            "category":"Freight",
            "type":"Transportation"
        }
    ],
    "sg:phone":"+1 970 867 4600",
    "sg:postcode":"80701",
    "sg:province":"CO",
    "wof:name":"Calvin Secrist Transportation",
    "wof:placetype":"venue"
},
  "geometry": {"coordinates":[-103.788352,40.259225],"type":"Point"}
}