{
  "type": "Feature",
  "properties": {
    "addr:full":"120 S Union Ave Pueblo CO 81003",
    "addr:housenumber":"120",
    "addr:postcode":"81003",
    "addr:street":"S Union Ave",
    "iso:country":"US",
    "sg:address":"120 S Union Ave",
    "sg:city":"Pueblo",
    "sg:classifiers":[
        {
            "category":"Shopping",
            "subcategory":"Used Merchandise",
            "type":"Retail Goods"
        }
    ],
    "sg:phone":"+1 719 546 1886",
    "sg:postcode":"81003",
    "sg:province":"CO",
    "sg:tags":[
        "antique"
    ],
    "wof:name":"Aladdin's Fine Treasures",
    "wof:placetype":"venue"
},
  "geometry": {"coordinates":[-104.613393,38.264476],"type":"Point"}
}