{
  "type": "Feature",
  "properties": {
    "iso:country":"US",
    "sg:address":"9584 W Powers Cir",
    "sg:city":"Littleton",
    "sg:classifiers":[
        {
            "category":"Real Estate",
            "subcategory":"Real Estate Agent",
            "type":"Services"
        }
    ],
    "sg:phone":"+1 303 979 0945",
    "sg:postcode":"80123",
    "sg:province":"CO",
    "sg:tags":[
        "relocation"
    ],
    "wof:name":"Hewitt Associates",
    "wof:placetype":"venue"
},
  "geometry": {"coordinates":[-105.10493700000001,39.615016],"type":"Point"}
}