{
  "type": "Feature",
  "properties": {
    "addr:full":"6751 S Brook Forest Dr Evergreen CO 80439",
    "addr:housenumber":"6751",
    "addr:postcode":"80439",
    "addr:street":"S Brook Forest Dr",
    "iso:country":"US",
    "sg:address":"6751 S Brook Forest Dr",
    "sg:city":"Evergreen",
    "sg:classifiers":[
        {
            "category":"Manufacturing",
            "subcategory":"Printing",
            "type":"Manufacturing & Wholesale Goods"
        }
    ],
    "sg:phone":"+1 303 670 4947",
    "sg:postcode":"80439",
    "sg:province":"CO",
    "sg:tags":[
        "periodical"
    ],
    "wof:name":"Breeze N Bye",
    "wof:placetype":"venue"
},
  "geometry": {"coordinates":[-105.385426,39.588058],"type":"Point"}
}