{
  "type": "Feature",
  "properties": {
    "addr:full":"2845 Ore Mill Rd Ste 2 Colorado Springs CO 80904",
    "addr:housenumber":"2845",
    "addr:postcode":"80904",
    "addr:street":"Ore Mill Rd Ste 2",
    "iso:country":"US",
    "sg:address":"2845 Ore Mill Rd Ste 2",
    "sg:city":"Colorado Springs",
    "sg:classifiers":[
        {
            "category":"Shopping",
            "subcategory":"Bicycles & Sporting Goods",
            "type":"Retail Goods"
        },
        {
            "category":"Sports & Exercise",
            "subcategory":"Bicycle Rental",
            "type":"Entertainment"
        }
    ],
    "sg:phone":"+1 719 473 8300",
    "sg:postcode":"80904",
    "sg:province":"CO",
    "sg:tags":[
        "bike"
    ],
    "wof:name":"Rocky Mountain High Wheels",
    "wof:placetype":"venue"
},
  "geometry": {"coordinates":[-104.87032000000001,38.848408],"type":"Point"}
}