{
  "type": "Feature",
  "properties": {
    "iso:country":"US",
    "sg:address":"6454 E 72nd Pl",
    "sg:city":"Commerce City",
    "sg:classifiers":[
        {
            "category":"Banks & Credit Unions",
            "subcategory":"Bank",
            "type":"Services"
        }
    ],
    "sg:phone":"+1 303 227 9611",
    "sg:postcode":"80022",
    "sg:province":"CO",
    "sg:tags":[
        "cashing",
        "check"
    ],
    "wof:name":"1029 Check Cashing",
    "wof:placetype":"venue"
},
  "geometry": {"coordinates":[-104.91221,39.828179],"type":"Point"}
}