{
  "type": "Feature",
  "properties": {
    "addr:full":"3945 W Monmouth Ave Littleton CO 80123",
    "addr:housenumber":"3945",
    "addr:postcode":"80123",
    "addr:street":"W Monmouth Ave",
    "iso:country":"US",
    "sg:address":"3945 W Monmouth Ave",
    "sg:city":"Littleton",
    "sg:classifiers":[
        {
            "category":"Wholesale",
            "subcategory":"Machinery & Supplies",
            "type":"Manufacturing & Wholesale Goods"
        }
    ],
    "sg:phone":"+1 303 730 7467",
    "sg:postcode":"80123",
    "sg:province":"CO",
    "sg:tags":[
        "equipment",
        "industrial"
    ],
    "wof:name":"Innovative Energy Technologies",
    "wof:placetype":"venue"
},
  "geometry": {"coordinates":[-105.039337,39.627765],"type":"Point"}
}