{
  "type": "Feature",
  "properties": {
    "iso:country":"US",
    "sg:address":"1280 Centaur Village Dr",
    "sg:city":"Lafayette",
    "sg:classifiers":[
        {
            "category":"Health Services",
            "subcategory":"Chiropractor",
            "type":"Services"
        }
    ],
    "sg:phone":"+1 303 926 6706",
    "sg:postcode":"80026",
    "sg:province":"CO",
    "wof:name":"Stephens Family Chiropractic",
    "wof:placetype":"venue"
},
  "geometry": {"coordinates":[-105.10774000000001,39.981804],"type":"Point"}
}