{
  "type": "Feature",
  "properties": {
    "addr:full":"8104 N Academy Blvd Colorado Springs CO 80920",
    "addr:housenumber":"8104",
    "addr:postcode":"80920",
    "addr:street":"N Academy Blvd",
    "iso:country":"US",
    "sg:address":"8104 N Academy Blvd",
    "sg:city":"Colorado Springs",
    "sg:classifiers":[
        {
            "category":"Retail",
            "subcategory":"Auto Repair",
            "type":"Services"
        }
    ],
    "sg:phone":"+1 719 594 4788",
    "sg:postcode":"80920",
    "sg:province":"CO",
    "sg:tags":[
        "sp"
    ],
    "wof:name":"Midas Muffler",
    "wof:placetype":"venue"
},
  "geometry": {"coordinates":[-104.804247,38.949035],"type":"Point"}
}