{
  "type": "Feature",
  "properties": {
    "addr:full":"1009 W Colorado Ave Colorado Springs CO 80904",
    "addr:housenumber":"1009",
    "addr:postcode":"80904",
    "addr:street":"W Colorado Ave",
    "iso:country":"US",
    "sg:address":"1009 W Colorado Ave",
    "sg:city":"Colorado Springs",
    "sg:classifiers":[
        {
            "category":"Real Estate",
            "subcategory":"Real Estate Agent",
            "type":"Services"
        }
    ],
    "sg:phone":"+1 719 634 2664",
    "sg:postcode":"80904",
    "sg:province":"CO",
    "sg:tags":[
        "appraiser"
    ],
    "wof:name":"Capital Appraisal Co",
    "wof:placetype":"venue"
},
  "geometry": {"coordinates":[-104.84178300000001,38.834936],"type":"Point"}
}