{
  "type": "Feature",
  "properties": {
    "addr:full":"1310 Manford Ave Estes Park CO 80517",
    "addr:housenumber":"1310",
    "addr:postcode":"80517",
    "addr:street":"Manford Ave",
    "iso:country":"US",
    "sg:address":"1310 Manford Ave",
    "sg:city":"Estes Park",
    "sg:classifiers":[
        {
            "category":"Real Estate",
            "subcategory":"Real Estate Operator",
            "type":"Services"
        }
    ],
    "sg:phone":"+1 970 577 1539",
    "sg:postcode":"80517",
    "sg:province":"CO",
    "sg:tags":[
        "apartment"
    ],
    "wof:name":"Lone Tree Village",
    "wof:placetype":"venue"
},
  "geometry": {"coordinates":[-105.501604,40.371024],"type":"Point"}
}