{
  "type": "Feature",
  "properties": {
    "addr:full":"529 Arrawanna St Colorado Springs CO 80909",
    "addr:housenumber":"529",
    "addr:postcode":"80909",
    "addr:street":"Arrawanna St",
    "iso:country":"US",
    "sg:address":"529 Arrawanna St",
    "sg:city":"Colorado Springs",
    "sg:classifiers":[
        {
            "category":"Professional",
            "type":"Services"
        }
    ],
    "sg:phone":"+1 719 634 7278",
    "sg:postcode":"80909",
    "sg:province":"CO",
    "wof:name":"Undercar Plus Inc",
    "wof:placetype":"venue"
},
  "geometry": {"coordinates":[-104.77184,38.839042],"type":"Point"}
}