{
  "type": "Feature",
  "properties": {
    "addr:full":"228 E St Salida CO 81201",
    "addr:housenumber":"228",
    "addr:postcode":"81201",
    "addr:street":"E St",
    "iso:country":"US",
    "sg:address":"228 E St",
    "sg:city":"Salida",
    "sg:classifiers":[
        {
            "category":"Building & Trades",
            "subcategory":"Plumbing",
            "type":"Services"
        }
    ],
    "sg:phone":"+1 719 539 5257",
    "sg:postcode":"81201",
    "sg:province":"CO",
    "sg:tags":[
        "contractor"
    ],
    "wof:name":"Shelby Hill Dipl AC",
    "wof:placetype":"venue"
},
  "geometry": {"coordinates":[-105.99180699999999,38.534596],"type":"Point"}
}