{
  "type": "Feature",
  "properties": {
    "addr:full":"140 Sheridan Blvd Denver CO 80226",
    "addr:housenumber":"140",
    "addr:postcode":"80226",
    "addr:street":"Sheridan Blvd",
    "iso:country":"US",
    "sg:address":"140 Sheridan Blvd",
    "sg:city":"Denver",
    "sg:classifiers":[
        {
            "category":"Organizations",
            "subcategory":"Labor Organization",
            "type":"Services"
        }
    ],
    "sg:phone":"+1 303 433 2100",
    "sg:postcode":"80226",
    "sg:province":"CO",
    "wof:name":"Colorado AFL-CIO",
    "wof:placetype":"venue"
},
  "geometry": {"coordinates":[-105.053196,39.720327],"type":"Point"}
}