{
  "type": "Feature",
  "properties": {
    "addr:full":"320 W B St Pueblo CO 81003",
    "addr:housenumber":"320",
    "addr:postcode":"81003",
    "addr:street":"W B St",
    "iso:country":"US",
    "sg:address":"320 W B St",
    "sg:city":"Pueblo",
    "sg:classifiers":[
        {
            "category":"Government",
            "subcategory":"Police Station",
            "type":"Public Place"
        }
    ],
    "sg:phone":"+1 719 583 6250",
    "sg:postcode":"81003",
    "sg:province":"CO",
    "sg:tags":[
        "sheriff"
    ],
    "wof:name":"Pueblo County Sheriff Dispatch",
    "wof:placetype":"venue"
},
  "geometry": {"coordinates":[-104.617957,38.263923],"type":"Point"}
}