{
  "type": "Feature",
  "properties": {
    "addr:full":"1405 Heidi Ln Colorado Springs CO 80907",
    "addr:housenumber":"1405",
    "addr:postcode":"80907",
    "addr:street":"Heidi Ln",
    "iso:country":"US",
    "sg:address":"1405 Heidi Ln",
    "sg:city":"Colorado Springs",
    "sg:classifiers":[
        {
            "category":"Professional",
            "subcategory":"Business Services",
            "type":"Services"
        }
    ],
    "sg:phone":"+1 719 459 0481",
    "sg:postcode":"80907",
    "sg:province":"CO",
    "sg:tags":[
        "appraiser"
    ],
    "wof:name":"Pixley Appraisal",
    "wof:placetype":"venue"
},
  "geometry": {"coordinates":[-104.854782,38.890673],"type":"Point"}
}