{
  "type": "Feature",
  "properties": {
    "iso:country":"US",
    "sg:address":"1551 Larimer St",
    "sg:city":"Denver",
    "sg:classifiers":[
        {
            "category":"Banks & Credit Unions",
            "subcategory":"Investment Brokerage",
            "type":"Services"
        }
    ],
    "sg:phone":"+1 303 607 9440",
    "sg:postcode":"80202",
    "sg:province":"CO",
    "sg:tags":[
        "consultant",
        "planning",
        "financial"
    ],
    "wof:name":"Peggy C Houser",
    "wof:placetype":"venue"
},
  "geometry": {"coordinates":[-104.998012,39.74879],"type":"Point"}
}