{
  "type": "Feature",
  "properties": {
    "iso:country":"US",
    "sg:address":"865 Greene St",
    "sg:city":"Silverton",
    "sg:classifiers":[
        {
            "category":"Food & Beverages",
            "subcategory":"Liquor & Beverages",
            "type":"Retail Goods"
        }
    ],
    "sg:phone":"+1 970 387 5491",
    "sg:postcode":"81433",
    "sg:province":"CO",
    "wof:name":"Silverton Liquors",
    "wof:placetype":"venue"
},
  "geometry": {"coordinates":[-107.667225,37.808602],"type":"Point"}
}