{
  "type": "Feature",
  "properties": {
    "iso:country":"US",
    "sg:address":"1202 Adams Dr",
    "sg:city":"Colorado Springs",
    "sg:classifiers":[
        {
            "category":"Building & Trades",
            "subcategory":"Cleaning & Sanitation",
            "type":"Services"
        }
    ],
    "sg:phone":"+1 719 635 5128",
    "sg:postcode":"80904",
    "sg:province":"CO",
    "sg:tags":[
        "property",
        "maintenance"
    ],
    "wof:name":"Parkridge Property Svc",
    "wof:placetype":"venue"
},
  "geometry": {"coordinates":[-104.87145599999999,38.866894],"type":"Point"}
}