{
  "type": "Feature",
  "properties": {
    "iso:country":"US",
    "sg:address":"3912 O Neal Ave",
    "sg:city":"Pueblo",
    "sg:classifiers":[
        {
            "category":"Education",
            "subcategory":"School",
            "type":"Public Place"
        }
    ],
    "sg:phone":"+1 719 561 9120",
    "sg:postcode":"81005",
    "sg:province":"CO",
    "wof:name":"Day Star Christian School",
    "wof:placetype":"venue"
},
  "geometry": {"coordinates":[-104.80338399999999,37.952197],"type":"Point"}
}