{
  "type": "Feature",
  "properties": {
    "addr:full":"5516 W 4th Ave Denver CO 80226",
    "addr:housenumber":"5516",
    "addr:postcode":"80226",
    "addr:street":"W 4Th Ave",
    "iso:country":"US",
    "sg:address":"5516 W 4th Ave",
    "sg:city":"Denver",
    "sg:classifiers":[
        {
            "category":"Building & Trades",
            "subcategory":"Construction",
            "type":"Services"
        }
    ],
    "sg:phone":"+1 303 462 2362",
    "sg:postcode":"80226",
    "sg:province":"CO",
    "sg:tags":[
        "hanging",
        "contractor"
    ],
    "wof:name":"Moses & Guman Painting",
    "wof:placetype":"venue"
},
  "geometry": {"coordinates":[-105.057672,39.723037],"type":"Point"}
}