{
  "type": "Feature",
  "properties": {
    "iso:country":"US",
    "sg:address":"25797 Conifer Rd",
    "sg:city":"Conifer",
    "sg:classifiers":[
        {
            "category":"Shopping",
            "subcategory":"Shoes",
            "type":"Retail Goods"
        }
    ],
    "sg:phone":"+1 303 816 7327",
    "sg:postcode":"80433",
    "sg:province":"CO",
    "wof:name":"Wise Feet Shoes",
    "wof:placetype":"venue"
},
  "geometry": {"coordinates":[-105.29364200000001,39.543013],"type":"Point"}
}