{
  "type": "Feature",
  "properties": {
    "addr:full":"201 E Colfax Ave Denver CO 80203",
    "addr:housenumber":"201",
    "addr:postcode":"80203",
    "addr:street":"E Colfax Ave",
    "iso:country":"US",
    "sg:address":"201 E Colfax Ave",
    "sg:city":"Denver",
    "sg:classifiers":[
        {
            "category":"Government",
            "subcategory":"Office",
            "type":"Public Place"
        }
    ],
    "sg:phone":"+1 303 866 5649",
    "sg:postcode":"80203",
    "sg:province":"CO",
    "sg:tags":[
        "state",
        "treasury"
    ],
    "wof:name":"Treasury Colorado Department",
    "wof:placetype":"venue"
},
  "geometry": {"coordinates":[-104.98358399999999,39.740044],"type":"Point"}
}