{
  "type": "Feature",
  "properties": {
    "iso:country":"US",
    "sg:address":"9820 Palmer Ln",
    "sg:city":"Denver",
    "sg:classifiers":[
        {
            "category":"Professional",
            "subcategory":"Computer Services",
            "type":"Services"
        }
    ],
    "sg:phone":"+1 303 457 0960",
    "sg:postcode":"80260",
    "sg:province":"CO",
    "sg:tags":[
        "development",
        "software"
    ],
    "wof:name":"Second Wave",
    "wof:placetype":"venue"
},
  "geometry": {"coordinates":[-104.99799,39.873503],"type":"Point"}
}