{
  "type": "Feature",
  "properties": {
    "addr:full":"1454 W Spotted Owl Way Littleton CO 80129",
    "addr:housenumber":"1454",
    "addr:postcode":"80129",
    "addr:street":"W Spotted Owl Way",
    "iso:country":"US",
    "sg:address":"1454 W Spotted Owl Way",
    "sg:city":"Littleton",
    "sg:classifiers":[
        {
            "category":"Professional",
            "type":"Services"
        }
    ],
    "sg:phone":"+1 303 470 0237",
    "sg:postcode":"80129",
    "sg:province":"CO",
    "wof:name":"Jonathen Hoehn",
    "wof:placetype":"venue"
},
  "geometry": {"coordinates":[-105.00578299999999,39.531414],"type":"Point"}
}