{
  "type": "Feature",
  "properties": {
    "addr:full":"6825 E Tennessee Ave Denver CO 80224",
    "addr:housenumber":"6825",
    "addr:postcode":"80224",
    "addr:street":"E Tennessee Ave",
    "iso:country":"US",
    "sg:address":"6825 E Tennessee Ave",
    "sg:city":"Denver",
    "sg:classifiers":[
        {
            "category":"Insurance",
            "subcategory":"Health Insurance",
            "type":"Services"
        }
    ],
    "sg:phone":"+1 303 399 1212",
    "sg:postcode":"80224",
    "sg:province":"CO",
    "sg:tags":[
        "network",
        "preferred",
        "provider"
    ],
    "wof:name":"National Ear Care Plan",
    "wof:placetype":"venue"
},
  "geometry": {"coordinates":[-104.909449,39.698508],"type":"Point"}
}