{
  "type": "Feature",
  "properties": {
    "iso:country":"US",
    "sg:address":"48000 E 38th Ave",
    "sg:city":"Bennett",
    "sg:classifiers":[
        {
            "category":"Manufacturing",
            "subcategory":"Metals",
            "type":"Manufacturing & Wholesale Goods"
        }
    ],
    "sg:phone":"+1 303 644 4781",
    "sg:postcode":"80102",
    "sg:province":"CO",
    "sg:tags":[
        "steel"
    ],
    "sg:website":"www.cpminc.com",
    "wof:name":"CPM Inc",
    "wof:placetype":"venue"
},
  "geometry": {"coordinates":[-104.424915,39.76727],"type":"Point"}
}