{
  "type": "Feature",
  "properties": {
    "addr:full":"300 E Olive St Lamar CO 81052",
    "addr:housenumber":"300",
    "addr:postcode":"81052",
    "addr:street":"E Olive St",
    "iso:country":"US",
    "sg:address":"300 E Olive St",
    "sg:city":"Lamar",
    "sg:classifiers":[
        {
            "category":"Autos & Motor Vehicles",
            "subcategory":"Automobile Sales",
            "type":"Retail Goods"
        }
    ],
    "sg:phone":"+1 719 336 2459",
    "sg:postcode":"81052",
    "sg:province":"CO",
    "sg:tags":[
        "used"
    ],
    "wof:name":"Silvey Auto Sales",
    "wof:placetype":"venue"
},
  "geometry": {"coordinates":[-102.6152,38.088364],"type":"Point"}
}