{
  "type": "Feature",
  "properties": {
    "iso:country":"US",
    "sg:address":"1505 E Burlington Ave",
    "sg:city":"Fort Morgan",
    "sg:classifiers":[
        {
            "category":"Retail",
            "subcategory":"Repair Shop",
            "type":"Services"
        }
    ],
    "sg:phone":"+1 970 867 9479",
    "sg:postcode":"80701",
    "sg:province":"CO",
    "wof:name":"Packer Refrigeration",
    "wof:placetype":"venue"
},
  "geometry": {"coordinates":[-103.77846700000001,40.246862],"type":"Point"}
}