{
  "type": "Feature",
  "properties": {
    "addr:full":"771 E 3rd St Center CO 81125",
    "addr:housenumber":"771",
    "addr:postcode":"81125",
    "addr:street":"E 3Rd St",
    "iso:country":"US",
    "sg:address":"771 E 3rd St",
    "sg:city":"Center",
    "sg:classifiers":[
        {
            "category":"Wholesale",
            "subcategory":"Farm Supplies",
            "type":"Manufacturing & Wholesale Goods"
        }
    ],
    "sg:phone":"+1 719 754 3453",
    "sg:postcode":"81125",
    "sg:province":"CO",
    "sg:tags":[
        "chemical",
        "agricultural"
    ],
    "wof:name":"Stone's Farm Supply",
    "wof:placetype":"venue"
},
  "geometry": {"coordinates":[-106.10386,37.753481],"type":"Point"}
}