{
  "type": "Feature",
  "properties": {
    "iso:country":"US",
    "sg:address":"1136 S Colorado Boulevard",
    "sg:city":"Denver",
    "sg:classifiers":[
        {
            "category":"Restaurant",
            "type":"Food & Drink"
        }
    ],
    "sg:phone":"+1 303 758 8050",
    "sg:postcode":"80246",
    "sg:province":"CO",
    "sg:tags":[
        "pizza"
    ],
    "wof:name":"Domino's Pizza",
    "wof:placetype":"venue"
},
  "geometry": {"coordinates":[-104.94068,39.695944],"type":"Point"}
}