{
  "type": "Feature",
  "properties": {
    "iso:country":"US",
    "sg:address":"3655 Lutheran Pkwy",
    "sg:city":"Wheat Ridge",
    "sg:classifiers":[
        {
            "category":"Health Services",
            "subcategory":"Podiatrist",
            "type":"Services"
        }
    ],
    "sg:phone":"+1 303 422 6043",
    "sg:postcode":"80033",
    "sg:province":"CO",
    "wof:name":"Allied Foot & Ankle Clinic",
    "wof:placetype":"venue"
},
  "geometry": {"coordinates":[-105.088785,39.76795],"type":"Point"}
}