{
  "type": "Feature",
  "properties": {
    "addr:full":"557 Beverly Ln Grand Junction CO 81504",
    "addr:housenumber":"557",
    "addr:postcode":"81504",
    "addr:street":"Beverly Ln",
    "iso:country":"US",
    "sg:address":"557 Beverly Ln",
    "sg:city":"Grand Junction",
    "sg:classifiers":[
        {
            "category":"Retail",
            "subcategory":"Repair Shop",
            "type":"Services"
        }
    ],
    "sg:phone":"+1 970 434 7564",
    "sg:postcode":"81504",
    "sg:province":"CO",
    "sg:tags":[
        "upholsterer",
        "furniture"
    ],
    "wof:name":"John's Custom",
    "wof:placetype":"venue"
},
  "geometry": {"coordinates":[-108.46592200000001,39.086216],"type":"Point"}
}