{
  "type": "Feature",
  "properties": {
    "iso:country":"US",
    "sg:address":"5800 E Evans Avenue",
    "sg:city":"Denver",
    "sg:classifiers":[
        {
            "category":"Health Services",
            "subcategory":"Doctor",
            "type":"Services"
        }
    ],
    "sg:phone":"+1 303 759 8145",
    "sg:postcode":"80222",
    "sg:province":"CO",
    "wof:name":"Alford William MD",
    "wof:placetype":"venue"
},
  "geometry": {"coordinates":[-104.92053799999999,39.678429],"type":"Point"}
}