{
  "type": "Feature",
  "properties": {
    "addr:full":"Roslyn and E 29th Ave Denver CO 80238",
    "addr:postcode":"80238",
    "addr:street":"29Th Ave",
    "iso:country":"US",
    "sg:address":"Roslyn and E 29th Ave",
    "sg:city":"Denver",
    "sg:classifiers":[
        {
            "category":"Shopping",
            "type":"Retail Goods"
        }
    ],
    "sg:postcode":"80238",
    "sg:province":"CO",
    "wof:name":"Sweet William's Market",
    "wof:placetype":"venue"
},
  "geometry": {"coordinates":[-104.90049399999999,39.75766],"type":"Point"}
}