{
  "type": "Feature",
  "properties": {
    "addr:full":"3975 York St Denver CO 80205",
    "addr:housenumber":"3975",
    "addr:postcode":"80205",
    "addr:street":"York St",
    "iso:country":"US",
    "sg:address":"3975 York St",
    "sg:city":"Denver",
    "sg:classifiers":[
        {
            "category":"Retail",
            "subcategory":"Auto Repair",
            "type":"Services"
        }
    ],
    "sg:phone":"+1 303 308 1205",
    "sg:postcode":"80205",
    "sg:province":"CO",
    "sg:tags":[
        "repairing",
        "automobile"
    ],
    "wof:name":"Castiron LTD",
    "wof:placetype":"venue"
},
  "geometry": {"coordinates":[-104.95980900000001,39.771638],"type":"Point"}
}