{
  "type": "Feature",
  "properties": {
    "addr:full":"19107 E Berry Dr Aurora CO 80015",
    "addr:housenumber":"19107",
    "addr:postcode":"80015",
    "addr:street":"E Berry Dr",
    "iso:country":"US",
    "sg:address":"19107 E Berry Dr",
    "sg:city":"Aurora",
    "sg:classifiers":[
        {
            "category":"Shopping",
            "type":"Retail Goods"
        }
    ],
    "sg:phone":"+1 303 766 2525",
    "sg:postcode":"80015",
    "sg:province":"CO",
    "sg:tags":[
        "communication",
        "radiotelephone",
        "merchandise"
    ],
    "wof:name":"Buzzz Communications Inc",
    "wof:placetype":"venue"
},
  "geometry": {"coordinates":[-104.76532899999999,39.613656],"type":"Point"}
}