{
  "type": "Feature",
  "properties": {
    "addr:full":"6261 S Potomac Way Centennial CO 80111",
    "addr:housenumber":"6261",
    "addr:postcode":"80111",
    "addr:street":"S Potomac Way",
    "iso:country":"US",
    "sg:address":"6261 S Potomac Way",
    "sg:city":"Centennial",
    "sg:classifiers":[
        {
            "category":"Professional",
            "subcategory":"Advertising",
            "type":"Services"
        }
    ],
    "sg:phone":"+1 303 309 6000",
    "sg:postcode":"80111",
    "sg:province":"CO",
    "wof:name":"Advertising Creations Inc",
    "wof:placetype":"venue"
},
  "geometry": {"coordinates":[-104.83098,39.603105],"type":"Point"}
}