{
  "type": "Feature",
  "properties": {
    "addr:full":"3927 W 32nd Ave Denver CO 80212",
    "addr:housenumber":"3927",
    "addr:postcode":"80212",
    "addr:street":"W 32Nd Ave",
    "iso:country":"US",
    "sg:address":"3927 W 32nd Ave",
    "sg:city":"Denver",
    "sg:classifiers":[
        {
            "category":"Cafe",
            "type":"Food & Drink"
        },
        {
            "category":"Restaurant",
            "type":"Food & Drink"
        }
    ],
    "sg:menulink":"http://www.allmenus.com/co/denver/267821-highlands-garden-cafe/menu/",
    "sg:phone":"+1 303 458 5920",
    "sg:postcode":"80212",
    "sg:province":"CO",
    "wof:name":"Highland's Garden Cafe",
    "wof:placetype":"venue"
},
  "geometry": {"coordinates":[-105.03881699999999,39.762397],"type":"Point"}
}