{
  "type": "Feature",
  "properties": {
    "addr:full":"10465 Melody Dr Northglenn CO 80234",
    "addr:housenumber":"10465",
    "addr:postcode":"80234",
    "addr:street":"Melody Dr",
    "iso:country":"US",
    "sg:address":"10465 Melody Dr",
    "sg:city":"Northglenn",
    "sg:classifiers":[
        {
            "category":"Wholesale",
            "subcategory":"Durable Goods & Equipment",
            "type":"Manufacturing & Wholesale Goods"
        }
    ],
    "sg:phone":"+1 303 280 5777",
    "sg:postcode":"80234",
    "sg:province":"CO",
    "sg:tags":[
        "importer"
    ],
    "wof:name":"G T Ind Products LLC",
    "wof:placetype":"venue"
},
  "geometry": {"coordinates":[-104.99333900000001,39.886936],"type":"Point"}
}