{
  "type": "Feature",
  "properties": {
    "iso:country":"US",
    "sg:address":"11089 E Mississippi Ave",
    "sg:city":"Aurora",
    "sg:classifiers":[
        {
            "category":"Shopping",
            "type":"Retail Goods"
        }
    ],
    "sg:phone":"+1 303 344 1744",
    "sg:postcode":"80012",
    "sg:province":"CO",
    "sg:tags":[
        "aids",
        "hearing"
    ],
    "wof:name":"Affordable Hearing Aids",
    "wof:placetype":"venue"
},
  "geometry": {"coordinates":[-104.859572,39.696649],"type":"Point"}
}