{
  "type": "Feature",
  "properties": {
    "addr:full":"2 W Las Vegas St Colorado Springs CO 80903",
    "addr:housenumber":"2",
    "addr:postcode":"80903",
    "addr:street":"W Las Vegas St",
    "iso:country":"US",
    "sg:address":"2 W Las Vegas St",
    "sg:city":"Colorado Springs",
    "sg:classifiers":[
        {
            "category":"Retail",
            "subcategory":"Auto Repair",
            "type":"Services"
        }
    ],
    "sg:phone":"+1 719 635 7449",
    "sg:postcode":"80903",
    "sg:province":"CO",
    "sg:tags":[
        "body",
        "automobile",
        "painting"
    ],
    "wof:name":"MGM Repair Ctr",
    "wof:placetype":"venue"
},
  "geometry": {"coordinates":[-104.829527,38.818571],"type":"Point"}
}