{
  "type": "Feature",
  "properties": {
    "addr:full":"1933 Tower Rd Aurora CO 80011",
    "addr:housenumber":"1933",
    "addr:postcode":"80011",
    "addr:street":"Tower Rd",
    "iso:country":"US",
    "sg:address":"1933 Tower Rd",
    "sg:city":"Aurora",
    "sg:classifiers":[
        {
            "category":"Restaurant",
            "type":"Food & Drink"
        }
    ],
    "sg:phone":"+1 303 361 0387",
    "sg:postcode":"80011",
    "sg:province":"CO",
    "sg:tags":[
        "retail",
        "eating",
        "direct",
        "sales"
    ],
    "wof:name":"Phoenix Services Inc",
    "wof:placetype":"venue"
},
  "geometry": {"coordinates":[-104.77249500000001,39.747319],"type":"Point"}
}