{
  "type": "Feature",
  "properties": {
    "iso:country":"US",
    "sg:address":"3223 Arapahoe Ave",
    "sg:city":"Boulder",
    "sg:classifiers":[
        {
            "category":"Insurance",
            "subcategory":"Insurance Agent",
            "type":"Services"
        }
    ],
    "sg:phone":"+1 303 442 1877",
    "sg:postcode":"80303",
    "sg:province":"CO",
    "wof:name":"Kent Wilson CLU",
    "wof:placetype":"venue"
},
  "geometry": {"coordinates":[-105.252143,40.014787],"type":"Point"}
}