{
  "type": "Feature",
  "properties": {
    "iso:country":"US",
    "sg:address":"2139 Chuckwagon Rd",
    "sg:city":"Colorado Springs",
    "sg:classifiers":[
        {
            "category":"Professional",
            "subcategory":"Business Services",
            "type":"Services"
        }
    ],
    "sg:phone":"+1 719 636 8978",
    "sg:postcode":"80919",
    "sg:province":"CO",
    "sg:tags":[
        "interior",
        "consultant",
        "design",
        "decorator"
    ],
    "wof:name":"Interiors By Joni Bader",
    "wof:placetype":"venue"
},
  "geometry": {"coordinates":[-104.872006,38.916496],"type":"Point"}
}