{
  "type": "Feature",
  "properties": {
    "addr:full":"806 S 5th St Rocky Ford CO 81067",
    "addr:housenumber":"806",
    "addr:postcode":"81067",
    "addr:street":"S 5Th St",
    "iso:country":"US",
    "sg:address":"806 S 5th St",
    "sg:city":"Rocky Ford",
    "sg:classifiers":[
        {
            "category":"Shopping",
            "subcategory":"Hobbies, Toys, & Games",
            "type":"Retail Goods"
        }
    ],
    "sg:phone":"+1 719 254 3100",
    "sg:postcode":"81067",
    "sg:province":"CO",
    "wof:name":"Woodpecker Creations",
    "wof:placetype":"venue"
},
  "geometry": {"coordinates":[-103.72811,38.047741],"type":"Point"}
}