{
  "type": "Feature",
  "properties": {
    "iso:country":"US",
    "sg:address":"3931 Tennyson St",
    "sg:city":"Denver",
    "sg:classifiers":[
        {
            "category":"Shopping",
            "subcategory":"Jewelry",
            "type":"Retail Goods"
        }
    ],
    "sg:phone":"+1 303 433 0954",
    "sg:postcode":"80212",
    "sg:province":"CO",
    "wof:name":"Jesus Jewelry Shop",
    "wof:placetype":"venue"
},
  "geometry": {"coordinates":[-105.04409699999999,39.771267],"type":"Point"}
}