{
  "type": "Feature",
  "properties": {
    "iso:country":"US",
    "sg:address":"1196 Diamond Cir",
    "sg:city":"Lafayette",
    "sg:classifiers":[
        {
            "category":"Home & Garden",
            "subcategory":"Furniture",
            "type":"Retail Goods"
        }
    ],
    "sg:phone":"+1 303 604 0177",
    "sg:postcode":"80026",
    "sg:province":"CO",
    "sg:tags":[
        "equipment",
        "kitchen",
        "cabinet"
    ],
    "wof:name":"R Chase Design Inc",
    "wof:placetype":"venue"
},
  "geometry": {"coordinates":[-105.104722,40.003767],"type":"Point"}
}