{
  "type": "Feature",
  "properties": {
    "addr:full":"7070 W Alameda Ave Denver CO 80226",
    "addr:housenumber":"7070",
    "addr:postcode":"80226",
    "addr:street":"W Alameda Ave",
    "iso:country":"US",
    "sg:address":"7070 W Alameda Ave",
    "sg:city":"Denver",
    "sg:classifiers":[
        {
            "category":"Banks & Credit Unions",
            "subcategory":"Bank",
            "type":"Services"
        }
    ],
    "sg:phone":"+1 303 869 4380",
    "sg:postcode":"80226",
    "sg:province":"CO",
    "sg:tags":[
        "federal",
        "savings",
        "institution"
    ],
    "wof:name":"TCF Bank",
    "wof:placetype":"venue"
},
  "geometry": {"coordinates":[-105.074777,39.710992],"type":"Point"}
}