{
  "type": "Feature",
  "properties": {
    "iso:country":"US",
    "sg:address":"225 Co Rd 23",
    "sg:city":"Ouray",
    "sg:classifiers":[
        {
            "category":"Travel",
            "subcategory":"Campground",
            "type":"Entertainment"
        }
    ],
    "sg:phone":"+1 970 325 4736",
    "sg:postcode":"81427",
    "sg:province":"CO",
    "sg:tags":[
        "store",
        "general"
    ],
    "wof:name":"Ouray KOA Campground",
    "wof:placetype":"venue"
},
  "geometry": {"coordinates":[-107.703323,38.080454],"type":"Point"}
}