{
  "type": "Feature",
  "properties": {
    "iso:country":"US",
    "sg:address":"132 W 5th Ave",
    "sg:city":"Springfield",
    "sg:classifiers":[
        {
            "category":"Personal",
            "subcategory":"Beauty Salon",
            "type":"Services"
        }
    ],
    "sg:phone":"+1 719 523 4171",
    "sg:postcode":"81073",
    "sg:province":"CO",
    "wof:name":"Carol's Curls",
    "wof:placetype":"venue"
},
  "geometry": {"coordinates":[-102.617536,37.409233],"type":"Point"}
}