{
  "type": "Feature",
  "properties": {
    "addr:full":"2233 S Jackson St Denver CO 80210",
    "addr:housenumber":"2233",
    "addr:postcode":"80210",
    "addr:street":"S Jackson St",
    "iso:country":"US",
    "sg:address":"2233 S Jackson St",
    "sg:city":"Denver",
    "sg:classifiers":[
        {
            "category":"Communications",
            "type":"Services"
        }
    ],
    "sg:phone":"+1 303 757 0721",
    "sg:postcode":"80210",
    "sg:province":"CO",
    "sg:tags":[
        "communication"
    ],
    "wof:name":"Ghs Communications",
    "wof:placetype":"venue"
},
  "geometry": {"coordinates":[-104.94380099999999,39.675958],"type":"Point"}
}