{
  "type": "Feature",
  "properties": {
    "iso:country":"US",
    "sg:address":"2472 Wildcat Trl",
    "sg:city":"Crested Butte",
    "sg:classifiers":[
        {
            "category":"Professional",
            "subcategory":"Business Services",
            "type":"Services"
        }
    ],
    "sg:phone":"+1 970 349 2425",
    "sg:postcode":"81434",
    "sg:province":"CO",
    "sg:tags":[
        "recording",
        "studio"
    ],
    "wof:name":"Half Moon Studio & Yoga Schl",
    "wof:placetype":"venue"
},
  "geometry": {"coordinates":[-107.007381,38.866134],"type":"Point"}
}