{
  "type": "Feature",
  "properties": {
    "iso:country":"US",
    "sg:address":"6475 Balsam St",
    "sg:city":"Arvada",
    "sg:classifiers":[
        {
            "category":"Wholesale",
            "subcategory":"Electrical",
            "type":"Manufacturing & Wholesale Goods"
        }
    ],
    "sg:phone":"+1 303 423 5256",
    "sg:postcode":"80004",
    "sg:province":"CO",
    "sg:tags":[
        "equipment",
        "lighting",
        "system"
    ],
    "wof:name":"Renaissance Dome Lighting",
    "wof:placetype":"venue"
},
  "geometry": {"coordinates":[-105.088134,39.815275],"type":"Point"}
}