{
  "type": "Feature",
  "properties": {
    "addr:full":"6651 S Krameria Way Englewood CO 80111",
    "addr:housenumber":"6651",
    "addr:postcode":"80111",
    "addr:street":"S Krameria Way",
    "iso:country":"US",
    "sg:address":"6651 S Krameria Way",
    "sg:city":"Englewood",
    "sg:classifiers":[
        {
            "category":"Recreation",
            "type":"Entertainment"
        }
    ],
    "sg:phone":"+1 303 770 0333",
    "sg:postcode":"80111",
    "sg:province":"CO",
    "sg:tags":[
        "pool",
        "swimming"
    ],
    "wof:name":"Holly Pool",
    "wof:placetype":"venue"
},
  "geometry": {"coordinates":[-104.916184,39.59617],"type":"Point"}
}