{
  "type": "Feature",
  "properties": {
    "addr:full":"125 E Main St Cortez CO 81321",
    "addr:housenumber":"125",
    "addr:postcode":"81321",
    "addr:street":"E Main St",
    "iso:country":"US",
    "sg:address":"125 E Main St",
    "sg:city":"Cortez",
    "sg:classifiers":[
        {
            "category":"Bars & Pubs",
            "type":"Food & Drink"
        }
    ],
    "sg:phone":"+1 970 565 4093",
    "sg:postcode":"81321",
    "sg:province":"CO",
    "sg:tags":[
        "drinking",
        "eating"
    ],
    "wof:name":"Franciscas Restaurant",
    "wof:placetype":"venue"
},
  "geometry": {"coordinates":[-108.58352499999999,37.348572],"type":"Point"}
}