{
  "type": "Feature",
  "properties": {
    "iso:country":"US",
    "sg:address":"1521 N 25th Avenue Ct",
    "sg:city":"Greeley",
    "sg:classifiers":[
        {
            "category":"Organizations",
            "subcategory":"Religious Organization",
            "type":"Services"
        }
    ],
    "sg:phone":"+1 970 356 2367",
    "sg:postcode":"80631",
    "sg:province":"CO",
    "sg:tags":[
        "church"
    ],
    "wof:name":"Temple Bethel Church",
    "wof:placetype":"venue"
},
  "geometry": {"coordinates":[-104.72194399999999,40.450928],"type":"Point"}
}