{
  "type": "Feature",
  "properties": {
    "iso:country":"US",
    "sg:address":"2230 S Grape St",
    "sg:city":"Denver",
    "sg:classifiers":[
        {
            "category":"Building & Trades",
            "subcategory":"Locksmith",
            "type":"Services"
        }
    ],
    "sg:phone":"+1 303 476 2791",
    "sg:postcode":"80222",
    "sg:province":"CO",
    "sg:tags":[
        "key"
    ],
    "wof:name":"AA 24 7 Emergency Locksmith Service",
    "wof:placetype":"venue"
},
  "geometry": {"coordinates":[-104.925107,39.675985],"type":"Point"}
}