{
  "type": "Feature",
  "properties": {
    "addr:full":"17770 W 58th Dr Golden CO 80403",
    "addr:housenumber":"17770",
    "addr:postcode":"80403",
    "addr:street":"W 58Th Dr",
    "iso:country":"US",
    "sg:address":"17770 W 58th Dr",
    "sg:city":"Golden",
    "sg:classifiers":[
        {
            "category":"Mining & Drilling",
            "type":"Manufacturing & Wholesale Goods"
        }
    ],
    "sg:phone":"+1 303 278 0221",
    "sg:postcode":"80403",
    "sg:province":"CO",
    "sg:tags":[
        "exploration"
    ],
    "wof:name":"Lion Creek Resources LLC",
    "wof:placetype":"venue"
},
  "geometry": {"coordinates":[-105.197501,39.803007],"type":"Point"}
}