{
  "type": "Feature",
  "properties": {
    "addr:full":"756 Chipeta Ave Grand Junction CO 81501",
    "addr:housenumber":"756",
    "addr:postcode":"81501",
    "addr:street":"Chipeta Ave",
    "iso:country":"US",
    "sg:address":"756 Chipeta Ave",
    "sg:city":"Grand Junction",
    "sg:classifiers":[
        {
            "category":"Retail",
            "subcategory":"Repair Shop",
            "type":"Services"
        }
    ],
    "sg:phone":"+1 970 243 6226",
    "sg:postcode":"81501",
    "sg:province":"CO",
    "sg:tags":[
        "picture",
        "made",
        "frame",
        "custom",
        "framing",
        "ready",
        "po"
    ],
    "wof:name":"Picture This",
    "wof:placetype":"venue"
},
  "geometry": {"coordinates":[-108.56025,39.072432],"type":"Point"}
}