{
  "type": "Feature",
  "properties": {
    "iso:country":"US",
    "sg:address":"546 Main St",
    "sg:city":"Grand Junction",
    "sg:classifiers":[
        {
            "category":"Personal",
            "type":"Services"
        }
    ],
    "sg:phone":"+1 970 256 9180",
    "sg:postcode":"81501",
    "sg:province":"CO",
    "sg:tags":[
        "hair",
        "replacement"
    ],
    "wof:name":"Main St Medical Group",
    "wof:placetype":"venue"
},
  "geometry": {"coordinates":[-108.563585,39.067411],"type":"Point"}
}