{
  "type": "Feature",
  "properties": {
    "iso:country":"US",
    "sg:address":"520 Park Cir",
    "sg:city":"Basalt",
    "sg:classifiers":[
        {
            "category":"Professional",
            "type":"Services"
        }
    ],
    "sg:phone":"+1 970 927 9028",
    "sg:postcode":"81621",
    "sg:province":"CO",
    "wof:name":"Sno Away Unlimited Inc",
    "wof:placetype":"venue"
},
  "geometry": {"coordinates":[-107.026023,39.367169],"type":"Point"}
}