{
  "type": "Feature",
  "properties": {
    "addr:full":"3030 Marion St Denver CO 80205",
    "addr:housenumber":"3030",
    "addr:postcode":"80205",
    "addr:street":"Marion St",
    "iso:country":"US",
    "sg:address":"3030 Marion St",
    "sg:city":"Denver",
    "sg:classifiers":[
        {
            "category":"Freight",
            "type":"Transportation"
        }
    ],
    "sg:phone":"+1 303 342 3424",
    "sg:postcode":"80205",
    "sg:province":"CO",
    "sg:tags":[
        "shuttle",
        "passenger"
    ],
    "wof:name":"Denver Express Shuttle",
    "wof:placetype":"venue"
},
  "geometry": {"coordinates":[-104.972044,39.760365],"type":"Point"}
}