{
  "type": "Feature",
  "properties": {
    "addr:full":"13042 Co Rd 76 Eaton CO 80615",
    "addr:housenumber":"13042;76",
    "addr:postcode":"80615",
    "addr:street":"Co Rd;Eaton",
    "iso:country":"US",
    "sg:address":"13042 Co Rd 76",
    "sg:city":"Eaton",
    "sg:classifiers":[
        {
            "category":"Building & Trades",
            "subcategory":"Construction",
            "type":"Services"
        }
    ],
    "sg:phone":"+1 970 454 0853",
    "sg:postcode":"80615",
    "sg:province":"CO",
    "sg:tags":[
        "siding",
        "contractor"
    ],
    "wof:name":"Side By Side LLC",
    "wof:placetype":"venue"
},
  "geometry": {"coordinates":[-104.804822,40.538215],"type":"Point"}
}