{
  "type": "Feature",
  "properties": {
    "iso:country":"US",
    "sg:address":"4301 State Hwy 66",
    "sg:city":"Longmont",
    "sg:classifiers":[
        {
            "category":"Food & Beverages",
            "subcategory":"Groceries & Convenience Stores",
            "type":"Retail Goods"
        }
    ],
    "sg:phone":"+1 970 535 4606",
    "sg:postcode":"80504",
    "sg:province":"CO",
    "wof:name":"Shell",
    "wof:placetype":"venue"
},
  "geometry": {"coordinates":[-104.972769,40.204431],"type":"Point"}
}