{
  "type": "Feature",
  "properties": {
    "addr:full":"9644 Adelaide Cir Littleton CO 80130",
    "addr:housenumber":"9644",
    "addr:postcode":"80130",
    "addr:street":"Adelaide Cir",
    "iso:country":"US",
    "sg:address":"9644 Adelaide Cir",
    "sg:city":"Littleton",
    "sg:classifiers":[
        {
            "category":"Professional",
            "type":"Services"
        }
    ],
    "sg:phone":"+1 303 346 0639",
    "sg:postcode":"80130",
    "sg:province":"CO",
    "wof:name":"Hubert B Yosif",
    "wof:placetype":"venue"
},
  "geometry": {"coordinates":[-104.932778,39.539463],"type":"Point"}
}