{
  "type": "Feature",
  "properties": {
    "iso:country":"US",
    "sg:address":"1127 Eagle Way",
    "sg:city":"Lyons",
    "sg:classifiers":[
        {
            "category":"Shopping",
            "type":"Retail Goods"
        }
    ],
    "sg:phone":"+1 303 823 5913",
    "sg:postcode":"80540",
    "sg:province":"CO",
    "sg:tags":[
        "merchandise"
    ],
    "wof:name":"Canyon Lights World Art Slides",
    "wof:placetype":"venue"
},
  "geometry": {"coordinates":[-105.25738699999999,40.285246],"type":"Point"}
}