{
  "type": "Feature",
  "properties": {
    "iso:country":"US",
    "sg:address":"3715 Kechter Rd",
    "sg:city":"Fort Collins",
    "sg:classifiers":[
        {
            "category":"Education",
            "subcategory":"School",
            "type":"Public Place"
        }
    ],
    "sg:phone":"+1 970 494 5100",
    "sg:postcode":"80528",
    "sg:province":"CO",
    "wof:name":"Zach Elementary School",
    "wof:placetype":"venue"
},
  "geometry": {"coordinates":[-105.004705,40.508712],"type":"Point"}
}