{
  "type": "Feature",
  "properties": {
    "addr:full":"312 W 1st St Parachute CO 81635",
    "addr:housenumber":"312",
    "addr:postcode":"81635",
    "addr:street":"W 1St St",
    "iso:country":"US",
    "sg:address":"312 W 1st St",
    "sg:city":"Parachute",
    "sg:classifiers":[
        {
            "category":"Autos & Motor Vehicles",
            "subcategory":"Fuel & Gas Station",
            "type":"Retail Goods"
        }
    ],
    "sg:phone":"+1 970 285 9077",
    "sg:postcode":"81635",
    "sg:province":"CO",
    "sg:tags":[
        "oil"
    ],
    "wof:name":"Parachute Lube & Svc",
    "wof:placetype":"venue"
},
  "geometry": {"coordinates":[-108.054648,39.449896],"type":"Point"}
}