{
  "type": "Feature",
  "properties": {
    "iso:country":"US",
    "sg:address":"555 Alter St",
    "sg:city":"Broomfield",
    "sg:classifiers":[
        {
            "category":"Recreation",
            "type":"Entertainment"
        }
    ],
    "sg:phone":"+1 303 410 9937",
    "sg:postcode":"80020",
    "sg:province":"CO",
    "sg:tags":[
        "range",
        "baseball",
        "batting"
    ],
    "wof:name":"Sports Alley",
    "wof:placetype":"venue"
},
  "geometry": {"coordinates":[-105.09201400000001,39.924733],"type":"Point"}
}