{
  "type": "Feature",
  "properties": {
    "addr:full":"288 W 13th Ave Springfield CO 81073",
    "addr:housenumber":"288",
    "addr:postcode":"81073",
    "addr:street":"W 13Th Ave",
    "iso:country":"US",
    "sg:address":"288 W 13th Ave",
    "sg:city":"Springfield",
    "sg:classifiers":[
        {
            "category":"Wholesale",
            "subcategory":"Farm Supplies",
            "type":"Manufacturing & Wholesale Goods"
        }
    ],
    "sg:phone":"+1 719 523 6281",
    "sg:postcode":"81073",
    "sg:province":"CO",
    "sg:tags":[
        "feed"
    ],
    "wof:name":"Tempel Grain Elevator",
    "wof:placetype":"venue"
},
  "geometry": {"coordinates":[-102.61821999999999,37.400413],"type":"Point"}
}