{
  "type": "Feature",
  "properties": {
    "iso:country":"US",
    "sg:address":"96 Mountain View Ave",
    "sg:city":"Grand Lake",
    "sg:classifiers":[
        {
            "category":"Real Estate",
            "subcategory":"Real Estate Agent",
            "type":"Services"
        }
    ],
    "sg:phone":"+1 970 887 2577",
    "sg:postcode":"80447",
    "sg:province":"CO",
    "wof:name":"Elk Horn Realty Inc",
    "wof:placetype":"venue"
},
  "geometry": {"coordinates":[-105.94314799999999,40.010946],"type":"Point"}
}