{
  "type": "Feature",
  "properties": {
    "addr:full":"1449 Cape Cod Cir Fort Collins CO 80525",
    "addr:housenumber":"1449",
    "addr:postcode":"80525",
    "addr:street":"Cape Cod Cir",
    "iso:country":"US",
    "sg:address":"1449 Cape Cod Cir",
    "sg:city":"Fort Collins",
    "sg:classifiers":[
        {
            "category":"Professional",
            "subcategory":"Management & Consulting",
            "type":"Services"
        }
    ],
    "sg:phone":"+1 970 223 8993",
    "sg:postcode":"80525",
    "sg:province":"CO",
    "sg:tags":[
        "business"
    ],
    "wof:name":"Educational Development Co",
    "wof:placetype":"venue"
},
  "geometry": {"coordinates":[-105.051022,40.526871],"type":"Point"}
}