{
  "type": "Feature",
  "properties": {
    "addr:full":"3724 N Co Rd 13 Fort Collins CO 80524",
    "addr:housenumber":"3724;13",
    "addr:postcode":"80524",
    "addr:street":"N Co Rd",
    "iso:country":"US",
    "sg:address":"3724 N Co Rd 13",
    "sg:city":"Fort Collins",
    "sg:classifiers":[
        {
            "category":"Recreation",
            "type":"Entertainment"
        }
    ],
    "sg:phone":"+1 970 224 2501",
    "sg:postcode":"80524",
    "sg:province":"CO",
    "sg:tags":[
        "stable"
    ],
    "wof:name":"Buckeye Ranch",
    "wof:placetype":"venue"
},
  "geometry": {"coordinates":[-105.057005,40.640269],"type":"Point"}
}