{
  "type": "Feature",
  "properties": {
    "addr:full":"1451 24th St Denver CO 80205",
    "addr:housenumber":"1451",
    "addr:postcode":"80205",
    "addr:street":"24Th St",
    "iso:country":"US",
    "sg:address":"1451 24th St",
    "sg:city":"Denver",
    "sg:classifiers":[
        {
            "category":"Utilities",
            "subcategory":"Telephone",
            "type":"Services"
        },
        {
            "category":"Communications",
            "type":"Services"
        }
    ],
    "sg:phone":"+1 303 296 3415",
    "sg:postcode":"80205",
    "sg:province":"CO",
    "sg:tags":[
        "communication",
        "telecommunication"
    ],
    "wof:name":"Ev Communications LLC",
    "wof:placetype":"venue"
},
  "geometry": {"coordinates":[-104.989109,39.757802],"type":"Point"}
}