{
  "type": "Feature",
  "properties": {
    "iso:country":"US",
    "sg:address":"1260 E 1st Ave",
    "sg:city":"Broomfield",
    "sg:classifiers":[
        {
            "category":"Cinema",
            "subcategory":"Movie Rental",
            "type":"Entertainment"
        }
    ],
    "sg:phone":"+1 303 464 7100",
    "sg:postcode":"80020",
    "sg:province":"CO",
    "sg:tags":[
        "video",
        "tape"
    ],
    "sg:website":"www.hollywoodvideo.com",
    "wof:name":"Hollywood Video",
    "wof:placetype":"venue"
},
  "geometry": {"coordinates":[-105.05448699999999,39.915265],"type":"Point"}
}