{
  "type": "Feature",
  "properties": {
    "iso:country":"US",
    "sg:address":"7853 E Arapahoe Ct",
    "sg:city":"Centennial",
    "sg:classifiers":[
        {
            "category":"Shopping",
            "subcategory":"Computers & Home Electronics",
            "type":"Retail Goods"
        }
    ],
    "sg:phone":"+1 303 220 8780",
    "sg:postcode":"80112",
    "sg:province":"CO",
    "sg:tags":[
        "software"
    ],
    "sg:website":"www.mainstay.com",
    "wof:name":"Mainstay Software Corp",
    "wof:placetype":"venue"
},
  "geometry": {"coordinates":[-104.89548499999999,39.594657],"type":"Point"}
}