{
  "type": "Feature",
  "properties": {
    "iso:country":"US",
    "sg:address":"7260 Broadway St",
    "sg:city":"Denver",
    "sg:classifiers":[
        {
            "category":"Restaurant",
            "type":"Food & Drink"
        }
    ],
    "sg:phone":"+1 303 426 6360",
    "sg:postcode":"80221",
    "sg:province":"CO",
    "sg:tags":[
        "eating"
    ],
    "wof:name":"Subway",
    "wof:placetype":"venue"
},
  "geometry": {"coordinates":[-104.987662,39.828729],"type":"Point"}
}