{
  "type": "Feature",
  "properties": {
    "addr:full":"14832 E Kansas Pl Aurora CO 80012",
    "addr:housenumber":"14832",
    "addr:postcode":"80012",
    "addr:street":"E Kansas Pl",
    "iso:country":"US",
    "sg:address":"14832 E Kansas Pl",
    "sg:city":"Aurora",
    "sg:classifiers":[
        {
            "category":"Shopping",
            "subcategory":"Hobbies, Toys, & Games",
            "type":"Retail Goods"
        }
    ],
    "sg:phone":"+1 303 751 5965",
    "sg:postcode":"80012",
    "sg:province":"CO",
    "sg:tags":[
        "basket"
    ],
    "wof:name":"Basket Boutique",
    "wof:placetype":"venue"
},
  "geometry": {"coordinates":[-104.814758,39.696191],"type":"Point"}
}