{
  "type": "Feature",
  "properties": {
    "addr:full":"7208 S Cody Way Littleton CO 80128",
    "addr:housenumber":"7208",
    "addr:postcode":"80128",
    "addr:street":"S Cody Way",
    "iso:country":"US",
    "sg:address":"7208 S Cody Way",
    "sg:city":"Littleton",
    "sg:classifiers":[
        {
            "category":"Building & Trades",
            "subcategory":"Construction",
            "type":"Services"
        }
    ],
    "sg:phone":"+1 720 981 0607",
    "sg:postcode":"80128",
    "sg:province":"CO",
    "sg:tags":[
        "contractor"
    ],
    "wof:name":"Tile It All",
    "wof:placetype":"venue"
},
  "geometry": {"coordinates":[-105.093198,39.587365],"type":"Point"}
}