{
  "type": "Feature",
  "properties": {
    "addr:full":"601 16th St Golden CO 80401",
    "addr:housenumber":"601",
    "addr:postcode":"80401",
    "addr:street":"16Th St",
    "iso:country":"US",
    "sg:address":"601 16th St",
    "sg:city":"Golden",
    "sg:classifiers":[
        {
            "category":"Personal",
            "subcategory":"Beauty Salon",
            "type":"Services"
        }
    ],
    "sg:phone":"+1 303 277 0817",
    "sg:postcode":"80401",
    "sg:province":"CO",
    "sg:tags":[
        "unisex",
        "hair"
    ],
    "sg:website":"www.greatclips.com",
    "wof:name":"Great Clips",
    "wof:placetype":"venue"
},
  "geometry": {"coordinates":[-105.217207,39.752714],"type":"Point"}
}