{
  "type": "Feature",
  "properties": {
    "iso:country":"US",
    "sg:address":"410 W Main St",
    "sg:city":"Buena Vista",
    "sg:classifiers":[
        {
            "category":"Government",
            "subcategory":"Office",
            "type":"Public Place"
        }
    ],
    "sg:phone":"+1 719 395 8493",
    "sg:postcode":"81236",
    "sg:province":"CO",
    "sg:tags":[
        "executive"
    ],
    "wof:name":"Public Health",
    "wof:placetype":"venue"
},
  "geometry": {"coordinates":[-106.135836,38.840933],"type":"Point"}
}