{
  "type": "Feature",
  "properties": {
    "iso:country":"US",
    "sg:address":"250 Hooks Ln",
    "sg:city":"Basalt",
    "sg:classifiers":[
        {
            "category":"Building & Trades",
            "subcategory":"Construction",
            "type":"Services"
        }
    ],
    "sg:phone":"+1 970 927 4989",
    "sg:postcode":"81621",
    "sg:province":"CO",
    "sg:tags":[
        "hanging",
        "contractor"
    ],
    "wof:name":"Klees Painting Inc",
    "wof:placetype":"venue"
},
  "geometry": {"coordinates":[-107.08524,39.37019],"type":"Point"}
}