{
  "type": "Feature",
  "properties": {
    "iso:country":"US",
    "sg:address":"719 Winters Ave",
    "sg:city":"Grand Junction",
    "sg:classifiers":[
        {
            "category":"Freight",
            "type":"Transportation"
        }
    ],
    "sg:phone":"+1 970 245 8685",
    "sg:postcode":"81501",
    "sg:province":"CO",
    "sg:tags":[
        "general"
    ],
    "wof:name":"Stix Inc",
    "wof:placetype":"venue"
},
  "geometry": {"coordinates":[-108.559635,39.058314],"type":"Point"}
}