{
  "type": "Feature",
  "properties": {
    "iso:country":"US",
    "sg:address":"2222 E 74th Ave",
    "sg:city":"Denver",
    "sg:classifiers":[
        {
            "category":"Home & Garden",
            "subcategory":"Carpets & Floor Coverings",
            "type":"Retail Goods"
        }
    ],
    "sg:phone":"+1 303 288 2211",
    "sg:postcode":"80229",
    "sg:province":"CO",
    "wof:name":"First Choice Enterprises Inc",
    "wof:placetype":"venue"
},
  "geometry": {"coordinates":[-104.96184700000001,39.830818],"type":"Point"}
}