{
  "type": "Feature",
  "properties": {
    "iso:country":"US",
    "sg:address":"3525 Auntie Stone St",
    "sg:city":"Fort Collins",
    "sg:classifiers":[
        {
            "category":"Restaurant",
            "type":"Food & Drink"
        }
    ],
    "sg:phone":"+1 970 229 5728",
    "sg:postcode":"80526",
    "sg:province":"CO",
    "sg:tags":[
        "eating"
    ],
    "wof:name":"Chips West Inc",
    "wof:placetype":"venue"
},
  "geometry": {"coordinates":[-105.11964500000001,40.53863],"type":"Point"}
}