{
  "type": "Feature",
  "properties": {
    "iso:country":"US",
    "sg:address":"3609 Austin Bluffs Pkwy",
    "sg:city":"Colorado Springs",
    "sg:classifiers":[
        {
            "category":"Food & Beverages",
            "subcategory":"Bakery",
            "type":"Retail Goods"
        }
    ],
    "sg:phone":"+1 719 536 0979",
    "sg:postcode":"80918",
    "sg:province":"CO",
    "sg:tags":[
        "baker"
    ],
    "wof:name":"Old Heidelberg Pastry Shop",
    "wof:placetype":"venue"
},
  "geometry": {"coordinates":[-104.759652,38.890773],"type":"Point"}
}