{
  "type": "Feature",
  "properties": {
    "iso:country":"US",
    "sg:address":"4490 E Virginia Ave",
    "sg:city":"Denver",
    "sg:classifiers":[
        {
            "category":"Building & Trades",
            "subcategory":"Construction",
            "type":"Services"
        }
    ],
    "sg:phone":"+1 303 394 4892",
    "sg:postcode":"80246",
    "sg:province":"CO",
    "sg:tags":[
        "general",
        "commercial",
        "contractor"
    ],
    "sg:website":"www.gammaconst.com",
    "wof:name":"Gamma Construction Company",
    "wof:placetype":"venue"
},
  "geometry": {"coordinates":[-104.934324,39.707356],"type":"Point"}
}