{
  "type": "Feature",
  "properties": {
    "addr:full":"2755 Dagny Way Lafayette CO 80026",
    "addr:housenumber":"2755",
    "addr:postcode":"80026",
    "addr:street":"Dagny Way",
    "iso:country":"US",
    "sg:address":"2755 Dagny Way",
    "sg:city":"Lafayette",
    "sg:classifiers":[
        {
            "category":"Autos & Motor Vehicles",
            "subcategory":"Automobile Sales",
            "type":"Retail Goods"
        },
        {
            "category":"Autos & Motor Vehicles",
            "subcategory":"Fuel & Gas Station",
            "type":"Retail Goods"
        },
        {
            "category":"Autos & Motor Vehicles",
            "subcategory":"Auto Supplies",
            "type":"Retail Goods"
        },
        {
            "category":"Retail",
            "subcategory":"Auto Repair",
            "type":"Services"
        }
    ],
    "sg:phone":"+1 720 319 8936",
    "sg:postcode":"80026",
    "sg:province":"CO",
    "sg:tags":[
        "wheel",
        "exhaust",
        "oil",
        "muffler",
        "balancing",
        "wheels-aligning",
        "servicing-automotive",
        "system",
        "accessory",
        "equipment",
        "lube",
        "electrical",
        "axle",
        "equipment-service",
        "alignment-frame",
        "brake",
        "inspection",
        "air conditioning"
    ],
    "sg:website":"http://www.tomtracker.com/redirect.cfm?bID=4837&hID=111353",
    "wof:name":"Meineke Car Care Center",
    "wof:placetype":"venue"
},
  "geometry": {"coordinates":[-105.13307399999999,40.013019],"type":"Point"}
}