{
  "type": "Feature",
  "properties": {
    "iso:country":"US",
    "sg:address":"2905 S Devinney Ct",
    "sg:city":"Denver",
    "sg:classifiers":[
        {
            "category":"Building & Trades",
            "subcategory":"Landscaping Services",
            "type":"Services"
        }
    ],
    "sg:phone":"+1 720 359 8231",
    "sg:postcode":"80228",
    "sg:province":"CO",
    "wof:name":"Flowerscaping By Phyllis",
    "wof:placetype":"venue"
},
  "geometry": {"coordinates":[-105.151914,39.665917],"type":"Point"}
}