{
  "type": "Feature",
  "properties": {
    "addr:full":"13157 E Dakota Ave Aurora CO 80012",
    "addr:housenumber":"13157",
    "addr:postcode":"80012",
    "addr:street":"E Dakota Ave",
    "iso:country":"US",
    "sg:address":"13157 E Dakota Ave",
    "sg:city":"Aurora",
    "sg:classifiers":[
        {
            "category":"Wholesale",
            "subcategory":"Home Furnishings",
            "type":"Manufacturing & Wholesale Goods"
        }
    ],
    "sg:phone":"+1 303 364 8805",
    "sg:postcode":"80012",
    "sg:province":"CO",
    "wof:name":"Vpa International Inc",
    "wof:placetype":"venue"
},
  "geometry": {"coordinates":[-104.83705999999999,39.7087],"type":"Point"}
}