{
  "type": "Feature",
  "properties": {
    "iso:country":"US",
    "sg:address":"2321 W 27th St",
    "sg:city":"Greeley",
    "sg:classifiers":[
        {
            "category":"Personal",
            "type":"Services"
        }
    ],
    "sg:phone":"+1 970 330 2513",
    "sg:postcode":"80634",
    "sg:province":"CO",
    "wof:name":"Lisas Club Tan",
    "wof:placetype":"venue"
},
  "geometry": {"coordinates":[-104.717907,40.393613],"type":"Point"}
}