{
  "type": "Feature",
  "properties": {
    "iso:country":"US",
    "sg:address":"710 10th St",
    "sg:city":"Golden",
    "sg:classifiers":[
        {
            "category":"Recreation",
            "type":"Entertainment"
        }
    ],
    "sg:phone":"+1 303 279 3080",
    "sg:postcode":"80401",
    "sg:province":"CO",
    "sg:tags":[
        "amusement"
    ],
    "sg:website":"www.cmc.org",
    "wof:name":"Colorado Mountain Club",
    "wof:placetype":"venue"
},
  "geometry": {"coordinates":[-105.223298,39.75765],"type":"Point"}
}