{
  "type": "Feature",
  "properties": {
    "addr:full":"1008 Elm Ave Canon City CO 81212",
    "addr:housenumber":"1008",
    "addr:postcode":"81212",
    "addr:street":"Elm Ave",
    "iso:country":"US",
    "sg:address":"1008 Elm Ave",
    "sg:city":"Canon City",
    "sg:classifiers":[
        {
            "category":"Real Estate",
            "subcategory":"Developer",
            "type":"Services"
        }
    ],
    "sg:phone":"+1 719 275 5725",
    "sg:postcode":"81212",
    "sg:province":"CO",
    "sg:tags":[
        "cemetery"
    ],
    "wof:name":"Canon City Government",
    "wof:placetype":"venue"
},
  "geometry": {"coordinates":[-105.228069,38.424953],"type":"Point"}
}