{
  "type": "Feature",
  "properties": {
    "addr:full":"8200 W Colfax Ave Lakewood CO 80214",
    "addr:housenumber":"8200",
    "addr:postcode":"80214",
    "addr:street":"W Colfax Ave",
    "iso:country":"US",
    "sg:address":"8200 W Colfax Ave",
    "sg:city":"Lakewood",
    "sg:classifiers":[
        {
            "category":"Wholesale",
            "subcategory":"Electrical",
            "type":"Manufacturing & Wholesale Goods"
        }
    ],
    "sg:phone":"+1 303 232 4004",
    "sg:postcode":"80214",
    "sg:province":"CO",
    "sg:tags":[
        "electric",
        "motor"
    ],
    "wof:name":"R D Motors",
    "wof:placetype":"venue"
},
  "geometry": {"coordinates":[-105.089602,39.740262],"type":"Point"}
}