{
  "type": "Feature",
  "properties": {
    "iso:country":"US",
    "sg:address":"3535 Cherry Creek Dr N",
    "sg:city":"Denver",
    "sg:classifiers":[
        {
            "category":"Real Estate",
            "subcategory":"Real Estate Agent",
            "type":"Services"
        }
    ],
    "sg:phone":"+1 303 893 1105",
    "sg:postcode":"80209",
    "sg:province":"CO",
    "sg:tags":[
        "property",
        "management"
    ],
    "wof:name":"Cherry Creek Medical Building",
    "wof:placetype":"venue"
},
  "geometry": {"coordinates":[-104.94553500000001,39.710378],"type":"Point"}
}