{
  "type": "Feature",
  "properties": {
    "iso:country":"US",
    "sg:address":"3145 W Alameda Avenue",
    "sg:city":"Denver",
    "sg:classifiers":[
        {
            "category":"Personal",
            "subcategory":"Beauty Salon",
            "type":"Services"
        }
    ],
    "sg:phone":"+1 303 935 1442",
    "sg:postcode":"80219",
    "sg:province":"CO",
    "sg:tags":[
        "hair"
    ],
    "wof:name":"Cambio De Imagen",
    "wof:placetype":"venue"
},
  "geometry": {"coordinates":[-105.027154,39.711127],"type":"Point"}
}