{
  "type": "Feature",
  "properties": {
    "addr:full":"3130 Downhill Dr Colorado Springs CO 80918",
    "addr:postcode":"3130;80918",
    "addr:street":"Downhill Dr",
    "iso:country":"US",
    "sg:address":"3130 Downhill Dr",
    "sg:city":"Colorado Springs",
    "sg:classifiers":[
        {
            "category":"Building & Trades",
            "subcategory":"Construction",
            "type":"Services"
        }
    ],
    "sg:phone":"+1 719 590 8621",
    "sg:postcode":"80918",
    "sg:province":"CO",
    "sg:tags":[
        "tile",
        "installation"
    ],
    "wof:name":"Spectrum Tile",
    "wof:placetype":"venue"
},
  "geometry": {"coordinates":[-104.767785,38.921753],"type":"Point"}
}