{
  "type": "Feature",
  "properties": {
    "addr:full":"2624 Oro Blanco Dr Colorado Springs CO 80917",
    "addr:housenumber":"2624",
    "addr:postcode":"80917",
    "addr:street":"Oro Blanco Dr",
    "iso:country":"US",
    "sg:address":"2624 Oro Blanco Dr",
    "sg:city":"Colorado Springs",
    "sg:classifiers":[
        {
            "category":"Insurance",
            "subcategory":"Insurance Agent",
            "type":"Services"
        }
    ],
    "sg:phone":"+1 719 572 5516",
    "sg:postcode":"80917",
    "sg:province":"CO",
    "wof:name":"Lawson Insurance",
    "wof:placetype":"venue"
},
  "geometry": {"coordinates":[-104.735733,38.869695],"type":"Point"}
}