{
  "type": "Feature",
  "properties": {
    "iso:country":"US",
    "sg:address":"1076 Westview Dr",
    "sg:city":"Boulder",
    "sg:classifiers":[
        {
            "category":"Real Estate",
            "subcategory":"Real Estate Agent",
            "type":"Services"
        }
    ],
    "sg:phone":"+1 303 499 3731",
    "sg:postcode":"80303",
    "sg:province":"CO",
    "wof:name":"Deer Creek Management Inc",
    "wof:placetype":"venue"
},
  "geometry": {"coordinates":[-105.20169799999999,40.00349],"type":"Point"}
}