{
  "type": "Feature",
  "properties": {
    "addr:full":"286 Bridge St Vail CO 81657",
    "addr:housenumber":"286",
    "addr:postcode":"81657",
    "addr:street":"Bridge St",
    "iso:country":"US",
    "sg:address":"286 Bridge St",
    "sg:city":"Vail",
    "sg:classifiers":[
        {
            "category":"Shopping",
            "subcategory":"Jewelry",
            "type":"Retail Goods"
        }
    ],
    "sg:phone":"+1 970 476 4082",
    "sg:postcode":"81657",
    "sg:province":"CO",
    "sg:tags":[
        "jeweler"
    ],
    "sg:website":"www.thegoldenbear.com",
    "wof:name":"Golden Bear",
    "wof:placetype":"venue"
},
  "geometry": {"coordinates":[-106.373591,39.640586],"type":"Point"}
}