{
  "type": "Feature",
  "properties": {
    "addr:full":"6465 Good Fortune Rd Peyton CO 80831",
    "addr:housenumber":"6465",
    "addr:postcode":"80831",
    "addr:street":"Good Fortune Rd",
    "iso:country":"US",
    "sg:address":"6465 Good Fortune Rd",
    "sg:city":"Peyton",
    "sg:classifiers":[
        {
            "category":"Shopping",
            "subcategory":"Crafts & Fabrics",
            "type":"Retail Goods"
        }
    ],
    "sg:phone":"+1 719 683 4646",
    "sg:postcode":"80831",
    "sg:province":"CO",
    "sg:tags":[
        "personal",
        "sewing"
    ],
    "wof:name":"Dream Catcher Quilting Inc",
    "wof:placetype":"venue"
},
  "geometry": {"coordinates":[-104.56864,38.924473],"type":"Point"}
}