{
  "type": "Feature",
  "properties": {
    "addr:full":"201 Colorado Ave Pueblo CO 81004",
    "addr:housenumber":"201",
    "addr:postcode":"81004",
    "addr:street":"Colorado Ave",
    "iso:country":"US",
    "sg:address":"201 Colorado Ave",
    "sg:city":"Pueblo",
    "sg:classifiers":[
        {
            "category":"Retail",
            "subcategory":"Auto Repair",
            "type":"Services"
        }
    ],
    "sg:phone":"+1 719 543 6252",
    "sg:postcode":"81004",
    "sg:province":"CO",
    "sg:tags":[
        "repairing",
        "automobile"
    ],
    "wof:name":"Mesa Garage",
    "wof:placetype":"venue"
},
  "geometry": {"coordinates":[-104.623766,38.257719],"type":"Point"}
}