{
  "type": "Feature",
  "properties": {
    "addr:full":"Denver Convention Center 700 Fourteenth Street Denver CO 80202",
    "addr:housenumber":"700",
    "addr:postcode":"80202",
    "addr:street":"Fourteenth Street",
    "iso:country":"US",
    "sg:address":"Denver Convention Center 700 Fourteenth Street",
    "sg:city":"Denver",
    "sg:classifiers":[
        {
            "category":"Restaurant",
            "type":"Food & Drink"
        }
    ],
    "sg:phone":"+1 781 890 3234",
    "sg:postcode":"80202",
    "sg:province":"CO",
    "sg:tags":[
        "flavor",
        "local"
    ],
    "sg:website":"www.bewisports.com",
    "wof:name":"Colorado Ski and Snowboard Expo",
    "wof:placetype":"venue"
},
  "geometry": {"coordinates":[-104.99628,39.742192],"type":"Point"}
}