{
  "type": "Feature",
  "properties": {
    "addr:full":"2121 Wadsworth Blvd Denver CO 80214",
    "addr:housenumber":"2121",
    "addr:postcode":"80214",
    "addr:street":"Wadsworth Blvd",
    "iso:country":"US",
    "sg:address":"2121 Wadsworth Blvd",
    "sg:city":"Denver",
    "sg:classifiers":[
        {
            "category":"Social Services",
            "subcategory":"Adult Care",
            "type":"Services"
        }
    ],
    "sg:phone":"+1 303 233 2121",
    "sg:postcode":"80214",
    "sg:province":"CO",
    "sg:tags":[
        "independent",
        "living",
        "residential",
        "assisted",
        "home",
        "senior"
    ],
    "wof:name":"Homestead At Lakewood",
    "wof:placetype":"venue"
},
  "geometry": {"coordinates":[-105.081486,39.749305],"type":"Point"}
}