{
  "type": "Feature",
  "properties": {
    "addr:full":"11101 S Parker Rd Parker CO 80134",
    "addr:housenumber":"11101",
    "addr:postcode":"80134",
    "addr:street":"S Parker Rd",
    "iso:country":"US",
    "sg:address":"11101 S Parker Rd",
    "sg:city":"Parker",
    "sg:classifiers":[
        {
            "category":"Banks & Credit Unions",
            "subcategory":"Bank",
            "type":"Services"
        }
    ],
    "sg:phone":"+1 720 851 6424",
    "sg:postcode":"80134",
    "sg:province":"CO",
    "sg:tags":[
        "federal",
        "savings",
        "institution"
    ],
    "wof:name":"Liberty Savings Bank",
    "wof:placetype":"venue"
},
  "geometry": {"coordinates":[-104.766068,39.523842],"type":"Point"}
}