{
  "type": "Feature",
  "properties": {
    "iso:country":"US",
    "sg:address":"1929 Stout St",
    "sg:city":"Denver",
    "sg:classifiers":[
        {
            "category":"Professional",
            "subcategory":"Secretarial Services",
            "type":"Services"
        }
    ],
    "sg:phone":"+1 303 628 7877",
    "sg:postcode":"80202",
    "sg:province":"CO",
    "sg:tags":[
        "convention",
        "court",
        "reporter"
    ],
    "wof:name":"Theresa Lindblom",
    "wof:placetype":"venue"
},
  "geometry": {"coordinates":[-104.988602,39.74937],"type":"Point"}
}