{
  "type": "Feature",
  "properties": {
    "iso:country":"US",
    "sg:address":"15641 Co Rd G",
    "sg:city":"Ordway",
    "sg:classifiers":[
        {
            "category":"Farming",
            "subcategory":"Livestock Farm",
            "type":"Manufacturing & Wholesale Goods"
        }
    ],
    "sg:phone":"+1 719 267 3201",
    "sg:postcode":"81063",
    "sg:province":"CO",
    "wof:name":"Riemenschneider Brothers",
    "wof:placetype":"venue"
},
  "geometry": {"coordinates":[-103.795986,38.214362],"type":"Point"}
}