{
  "type": "Feature",
  "properties": {
    "addr:full":"1197 25th Ln Pueblo CO 81006",
    "addr:housenumber":"1197",
    "addr:postcode":"81006",
    "addr:street":"25Th Ln",
    "iso:country":"US",
    "sg:address":"1197 25th Ln",
    "sg:city":"Pueblo",
    "sg:classifiers":[
        {
            "category":"Building & Trades",
            "subcategory":"Construction",
            "type":"Services"
        }
    ],
    "sg:phone":"+1 719 544 4144",
    "sg:postcode":"81006",
    "sg:province":"CO",
    "sg:tags":[
        "house"
    ],
    "wof:name":"Foundation Installers Inc",
    "wof:placetype":"venue"
},
  "geometry": {"coordinates":[-104.542995,38.242841],"type":"Point"}
}