{
  "type": "Feature",
  "properties": {
    "addr:full":"119 Dayspring Pl Pagosa Springs CO 81147",
    "addr:housenumber":"119",
    "addr:postcode":"81147",
    "addr:street":"Dayspring Pl",
    "iso:country":"US",
    "sg:address":"119 Dayspring Pl",
    "sg:city":"Pagosa Springs",
    "sg:classifiers":[
        {
            "category":"Building & Trades",
            "subcategory":"Construction",
            "type":"Services"
        }
    ],
    "sg:phone":"+1 970 731 1291",
    "sg:postcode":"81147",
    "sg:province":"CO",
    "sg:tags":[
        "carpenter"
    ],
    "wof:name":"Specialty Plus Carpentry",
    "wof:placetype":"venue"
},
  "geometry": {"coordinates":[-107.083888,37.283292],"type":"Point"}
}