{
  "type": "Feature",
  "properties": {
    "iso:country":"US",
    "sg:address":"4935 N 30th St",
    "sg:city":"Colorado Springs",
    "sg:classifiers":[
        {
            "category":"Farming",
            "subcategory":"Farm & Veterinary Services",
            "type":"Manufacturing & Wholesale Goods"
        }
    ],
    "sg:phone":"+1 719 630 3200",
    "sg:postcode":"80919",
    "sg:province":"CO",
    "sg:tags":[
        "breeder",
        "breeding",
        "swine",
        "livestock",
        "stock"
    ],
    "sg:website":"www.newsham.com",
    "wof:name":"Newsham Genetics  Lc",
    "wof:placetype":"venue"
},
  "geometry": {"coordinates":[-104.86740899999999,38.902103],"type":"Point"}
}