{
  "type": "Feature",
  "properties": {
    "addr:full":"31166 US Hwy 50 La Junta CO 81050",
    "addr:housenumber":"31166",
    "addr:postcode":"81050",
    "addr:street":"Us Hwy 50",
    "iso:country":"US",
    "sg:address":"31166 US Hwy 50",
    "sg:city":"La Junta",
    "sg:classifiers":[
        {
            "category":"Freight",
            "type":"Transportation"
        }
    ],
    "sg:phone":"+1 719 384 9693",
    "sg:postcode":"81050",
    "sg:province":"CO",
    "sg:tags":[
        "livestock",
        "hauling"
    ],
    "wof:name":"Chester Bay Trucking",
    "wof:placetype":"venue"
},
  "geometry": {"coordinates":[-103.503902,37.989022],"type":"Point"}
}