{
  "type": "Feature",
  "properties": {
    "addr:full":"1322 Cavan St Boulder CO 80303",
    "addr:housenumber":"1322",
    "addr:postcode":"80303",
    "addr:street":"Cavan St",
    "iso:country":"US",
    "sg:address":"1322 Cavan St",
    "sg:city":"Boulder",
    "sg:classifiers":[
        {
            "category":"Building & Trades",
            "subcategory":"Construction",
            "type":"Services"
        }
    ],
    "sg:phone":"+1 303 666 6939",
    "sg:postcode":"80303",
    "sg:province":"CO",
    "sg:tags":[
        "contractor"
    ],
    "wof:name":"Persona Construction",
    "wof:placetype":"venue"
},
  "geometry": {"coordinates":[-105.13636700000001,40.010754],"type":"Point"}
}