{
  "type": "Feature",
  "properties": {
    "iso:country":"US",
    "sg:address":"10338 Co Rd 137",
    "sg:city":"Simla",
    "sg:classifiers":[
        {
            "category":"Farming",
            "subcategory":"Livestock Farm",
            "type":"Manufacturing & Wholesale Goods"
        }
    ],
    "sg:phone":"+1 719 541 2218",
    "sg:postcode":"80835",
    "sg:province":"CO",
    "sg:tags":[
        "beef",
        "feedlot",
        "cattle"
    ],
    "wof:name":"Donald Hendricks",
    "wof:placetype":"venue"
},
  "geometry": {"coordinates":[-104.034025,39.027767],"type":"Point"}
}