{
  "type": "Feature",
  "properties": {
    "addr:full":"3520 Cleveland Ave Wellington CO 80549",
    "addr:housenumber":"3520",
    "addr:postcode":"80549",
    "addr:street":"Cleveland Ave",
    "iso:country":"US",
    "sg:address":"3520 Cleveland Ave",
    "sg:city":"Wellington",
    "sg:classifiers":[
        {
            "category":"Food & Beverages",
            "subcategory":"Specialty",
            "type":"Retail Goods"
        }
    ],
    "sg:phone":"+1 970 266 0391",
    "sg:postcode":"80549",
    "sg:province":"CO",
    "sg:tags":[
        "water",
        "bulk",
        "company"
    ],
    "wof:name":"Wildwood Water",
    "wof:placetype":"venue"
},
  "geometry": {"coordinates":[-105.010882,40.703982],"type":"Point"}
}