{
  "type": "Feature",
  "properties": {
    "addr:full":"302 W Montezuma Ave Cortez CO 81321",
    "addr:housenumber":"302",
    "addr:postcode":"81321",
    "addr:street":"W Montezuma Ave",
    "iso:country":"US",
    "sg:address":"302 W Montezuma Ave",
    "sg:city":"Cortez",
    "sg:classifiers":[
        {
            "category":"Health Services",
            "subcategory":"Doctor",
            "type":"Services"
        }
    ],
    "sg:phone":"+1 970 565 3612",
    "sg:postcode":"81321",
    "sg:province":"CO",
    "sg:tags":[
        "dentist"
    ],
    "wof:name":"John A Vestal DDS PC",
    "wof:placetype":"venue"
},
  "geometry": {"coordinates":[-108.590857,37.35087],"type":"Point"}
}