{
  "type": "Feature",
  "properties": {
    "iso:country":"US",
    "sg:address":"14452 Co Rd 501",
    "sg:city":"Bayfield",
    "sg:classifiers":[
        {
            "category":"Travel",
            "subcategory":"Hotels & Motels",
            "type":"Entertainment"
        }
    ],
    "sg:phone":"+1 970 884 2517",
    "sg:postcode":"81122",
    "sg:province":"CO",
    "sg:tags":[
        "chalet",
        "rental",
        "cabin"
    ],
    "sg:website":"www.durangoresortonlake.com",
    "wof:name":"Durango Resort On Vallecito Lk",
    "wof:placetype":"venue"
},
  "geometry": {"coordinates":[-107.566742,37.394755],"type":"Point"}
}