{
  "type": "Feature",
  "properties": {
    "iso:country":"US",
    "sg:address":"400 Jurassic Ct",
    "sg:city":"Fruita",
    "sg:classifiers":[
        {
            "category":"Travel",
            "subcategory":"Hotels & Motels",
            "type":"Entertainment"
        }
    ],
    "sg:phone":"+1 970 858 1333",
    "sg:postcode":"81521",
    "sg:province":"CO",
    "sg:tags":[
        "operation"
    ],
    "wof:name":"Colorado Inn and Suites",
    "wof:placetype":"venue"
},
  "geometry": {"coordinates":[-108.73959000000001,39.151969],"type":"Point"}
}