{
  "type": "Feature",
  "properties": {
    "iso:country":"US",
    "sg:address":"1940 Cheyenne Blvd",
    "sg:city":"Colorado Springs",
    "sg:classifiers":[
        {
            "category":"Wholesale",
            "subcategory":"Groceries",
            "type":"Manufacturing & Wholesale Goods"
        }
    ],
    "sg:phone":"+1 719 632 2223",
    "sg:postcode":"80906",
    "sg:province":"CO",
    "wof:name":"D & Z Distributing",
    "wof:placetype":"venue"
},
  "geometry": {"coordinates":[-104.862269,38.790841],"type":"Point"}
}