{
  "type": "Feature",
  "properties": {
    "iso:country":"US",
    "sg:address":"1800 W 85th Ave",
    "sg:city":"Denver",
    "sg:classifiers":[
        {
            "category":"Real Estate",
            "subcategory":"Real Estate Operator",
            "type":"Services"
        }
    ],
    "sg:phone":"+1 303 650 6200",
    "sg:postcode":"80260",
    "sg:province":"CO",
    "sg:tags":[
        "building",
        "apartment"
    ],
    "wof:name":"Hyland Park Centre Apartments",
    "wof:placetype":"venue"
},
  "geometry": {"coordinates":[-105.00771899999999,39.851342],"type":"Point"}
}