{
  "type": "Feature",
  "properties": {
    "iso:country":"US",
    "sg:address":"8446 Nelson Ct",
    "sg:city":"Arvada",
    "sg:classifiers":[
        {
            "category":"Real Estate",
            "subcategory":"Real Estate Agent",
            "type":"Services"
        }
    ],
    "sg:phone":"+1 303 467 7769",
    "sg:postcode":"80005",
    "sg:province":"CO",
    "sg:tags":[
        "appraiser"
    ],
    "wof:name":"Kamin Co II",
    "wof:placetype":"venue"
},
  "geometry": {"coordinates":[-105.11817600000001,39.850123],"type":"Point"}
}