{
  "type": "Feature",
  "properties": {
    "iso:country":"US",
    "sg:address":"5900 E 1st Ave",
    "sg:city":"Denver",
    "sg:classifiers":[
        {
            "category":"Real Estate",
            "subcategory":"Real Estate Agent",
            "type":"Services"
        }
    ],
    "sg:phone":"+1 303 322 6292",
    "sg:postcode":"80220",
    "sg:province":"CO",
    "wof:name":"Ivy Court Condominiums Assn",
    "wof:placetype":"venue"
},
  "geometry": {"coordinates":[-104.91783100000001,39.717824],"type":"Point"}
}