{
  "type": "Feature",
  "properties": {
    "addr:full":"1420 S Holly Street Denver CO 80222",
    "addr:housenumber":"1420",
    "addr:postcode":"80222",
    "addr:street":"S Holly Street",
    "iso:country":"US",
    "sg:address":"1420 S Holly Street",
    "sg:city":"Denver",
    "sg:classifiers":[
        {
            "category":"Organizations",
            "subcategory":"Religious Organization",
            "type":"Services"
        }
    ],
    "sg:phone":"+1 303 756 5042",
    "sg:postcode":"80222",
    "sg:province":"CO",
    "wof:name":"Calvary Presbyterian Church",
    "wof:placetype":"venue"
},
  "geometry": {"coordinates":[-104.92245800000001,39.690303],"type":"Point"}
}