{
  "type": "Feature",
  "properties": {
    "iso:country":"US",
    "sg:address":"1420 S Holly Street",
    "sg:city":"Denver",
    "sg:classifiers":[
        {
            "category":"Organizations",
            "subcategory":"Religious Organization",
            "type":"Services"
        }
    ],
    "sg:phone":"+1 303 756 5042",
    "sg:postcode":"80222",
    "sg:province":"CO",
    "wof:name":"Calvary Presbyterian Church",
    "wof:placetype":"venue"
},
  "geometry": {"coordinates":[-104.922458,39.690303],"type":"Point"}
}