{
  "type": "Feature",
  "properties": {
    "addr:full":"4055 N Academy Blvd Colorado Springs CO 80918",
    "addr:housenumber":"4055",
    "addr:postcode":"80918",
    "addr:street":"N Academy Blvd",
    "iso:country":"US",
    "sg:address":"4055 N Academy Blvd",
    "sg:city":"Colorado Springs",
    "sg:classifiers":[
        {
            "category":"Retail",
            "subcategory":"Auto Repair",
            "type":"Services"
        }
    ],
    "sg:phone":"+1 719 593 1277",
    "sg:postcode":"80918",
    "sg:province":"CO",
    "sg:tags":[
        "installs",
        "muffler",
        "absorber",
        "shock",
        "brakes"
    ],
    "wof:name":"Midas Muffler",
    "wof:placetype":"venue"
},
  "geometry": {"coordinates":[-104.75699,38.889699],"type":"Point"}
}