{
  "type": "Feature",
  "properties": {
    "iso:country":"US",
    "sg:address":"2692 Hwy 50",
    "sg:city":"Grand Junction",
    "sg:classifiers":[
        {
            "category":"Banks & Credit Unions",
            "subcategory":"Bank",
            "type":"Services"
        }
    ],
    "sg:phone":"+1 970 243 0111",
    "sg:postcode":"81503",
    "sg:province":"CO",
    "sg:tags":[
        "loan",
        "real estate"
    ],
    "wof:name":"Epic Mortgage",
    "wof:placetype":"venue"
},
  "geometry": {"coordinates":[-108.55273,39.043237],"type":"Point"}
}