{
  "type": "Feature",
  "properties": {
    "iso:country":"US",
    "sg:address":"1115 Bowen Cir",
    "sg:city":"Longmont",
    "sg:classifiers":[
        {
            "category":"Retail",
            "subcategory":"Auto Repair",
            "type":"Services"
        }
    ],
    "sg:phone":"+1 303 776 6469",
    "sg:postcode":"80501",
    "sg:province":"CO",
    "sg:tags":[
        "automobile",
        "testing",
        "emission"
    ],
    "wof:name":"Al's Front Range Diesel Emssns",
    "wof:placetype":"venue"
},
  "geometry": {"coordinates":[-105.114181,40.157734],"type":"Point"}
}