{
  "type": "Feature",
  "properties": {
    "iso:country":"US",
    "sg:address":"607 Corona St",
    "sg:city":"Denver",
    "sg:classifiers":[
        {
            "category":"Wholesale",
            "subcategory":"Photographic Equipment",
            "type":"Manufacturing & Wholesale Goods"
        }
    ],
    "sg:phone":"+1 303 233 5148",
    "sg:postcode":"80218",
    "sg:province":"CO",
    "sg:tags":[
        "supply"
    ],
    "wof:name":"Imagequest Corp",
    "wof:placetype":"venue"
},
  "geometry": {"coordinates":[-104.97415700000001,39.727176],"type":"Point"}
}