{
  "type": "Feature",
  "properties": {
    "iso:country":"US",
    "sg:address":"4967 Perry St",
    "sg:city":"Denver",
    "sg:classifiers":[
        {
            "category":"Professional",
            "type":"Services"
        }
    ],
    "sg:phone":"+1 303 477 2910",
    "sg:postcode":"80212",
    "sg:province":"CO",
    "wof:name":"Terry L Schlaak",
    "wof:placetype":"venue"
},
  "geometry": {"coordinates":[-105.039332,39.786219],"type":"Point"}
}