{
  "type": "Feature",
  "properties": {
    "iso:country":"US",
    "sg:address":"4752 S Cedar Rd",
    "sg:city":"Evergreen",
    "sg:classifiers":[
        {
            "category":"Real Estate",
            "subcategory":"Real Estate Agent",
            "type":"Services"
        }
    ],
    "sg:phone":"+1 303 670 3882",
    "sg:postcode":"80439",
    "sg:province":"CO",
    "sg:tags":[
        "appraiser"
    ],
    "sg:website":"www.coloradohomes-4u.com",
    "wof:name":"Foothills Appraisals Svc",
    "wof:placetype":"venue"
},
  "geometry": {"coordinates":[-105.32519000000001,39.629729],"type":"Point"}
}