{
  "type": "Feature",
  "properties": {
    "iso:country":"US",
    "sg:address":"1106 S Main St",
    "sg:city":"Lamar",
    "sg:classifiers":[
        {
            "category":"Restaurant",
            "type":"Food & Drink"
        }
    ],
    "sg:menulink":"http://www.allmenus.com/co/lamar/189459-kfc---kentucky-fried-chicken/menu/",
    "sg:phone":"+1 719 336 7781",
    "sg:postcode":"81052",
    "sg:province":"CO",
    "sg:tags":[
        "american",
        "chicken"
    ],
    "wof:name":"KFC - Kentucky Fried Chicken",
    "wof:placetype":"venue"
},
  "geometry": {"coordinates":[-102.61854,38.078778],"type":"Point"}
}