{
  "type": "Feature",
  "properties": {
    "iso:country":"US",
    "sg:address":"1401 E 69th Ave",
    "sg:city":"Denver",
    "sg:classifiers":[
        {
            "category":"Building & Trades",
            "subcategory":"Construction",
            "type":"Services"
        }
    ],
    "sg:phone":"+1 303 288 3300",
    "sg:postcode":"80229",
    "sg:province":"CO",
    "sg:tags":[
        "dry wall",
        "contractor"
    ],
    "sg:website":"www.e-kco.com",
    "wof:name":"E & K Of Denver-Great Northern",
    "wof:placetype":"venue"
},
  "geometry": {"coordinates":[-104.966182,39.821805],"type":"Point"}
}