{
  "type": "Feature",
  "properties": {
    "iso:country":"US",
    "sg:address":"3106 S Parker Rd",
    "sg:city":"Aurora",
    "sg:classifiers":[
        {
            "category":"Professional",
            "subcategory":"Business Services",
            "type":"Services"
        }
    ],
    "sg:phone":"+1 303 337 5900",
    "sg:postcode":"80014",
    "sg:province":"CO",
    "wof:name":"Anything Liquidated",
    "wof:placetype":"venue"
},
  "geometry": {"coordinates":[-104.85533700000001,39.660745],"type":"Point"}
}