{
  "type": "Feature",
  "properties": {
    "iso:country":"US",
    "sg:address":"317 63rd Ave",
    "sg:city":"Greeley",
    "sg:classifiers":[
        {
            "category":"Recreation",
            "type":"Entertainment"
        }
    ],
    "sg:phone":"+1 970 352 4692",
    "sg:postcode":"80634",
    "sg:province":"CO",
    "sg:tags":[
        "club",
        "membership"
    ],
    "wof:name":"Club Nebula Inc",
    "wof:placetype":"venue"
},
  "geometry": {"coordinates":[-104.780777,40.430651],"type":"Point"}
}