{
  "type": "Feature",
  "properties": {
    "iso:country":"US",
    "sg:address":"16911 E Amherst Dr",
    "sg:city":"Aurora",
    "sg:classifiers":[
        {
            "category":"Retail",
            "subcategory":"Repair Shop",
            "type":"Services"
        }
    ],
    "sg:phone":"+1 303 690 3967",
    "sg:postcode":"80013",
    "sg:province":"CO",
    "sg:tags":[
        "related"
    ],
    "wof:name":"Rocking M Corp",
    "wof:placetype":"venue"
},
  "geometry": {"coordinates":[-104.790395,39.663952],"type":"Point"}
}