{
  "type": "Feature",
  "properties": {
    "addr:full":"619 W Columbia Ave Telluride CO 81435",
    "addr:housenumber":"619",
    "addr:postcode":"81435",
    "addr:street":"W Columbia Ave",
    "iso:country":"US",
    "sg:address":"619 W Columbia Ave",
    "sg:city":"Telluride",
    "sg:classifiers":[
        {
            "category":"Professional",
            "subcategory":"Advertising",
            "type":"Services"
        }
    ],
    "sg:phone":"+1 970 728 1835",
    "sg:postcode":"81435",
    "sg:province":"CO",
    "sg:tags":[
        "counselor"
    ],
    "wof:name":"SJS Design Marketing",
    "wof:placetype":"venue"
},
  "geometry": {"coordinates":[-107.816644,37.939496],"type":"Point"}
}