{
  "type": "Feature",
  "properties": {
    "addr:full":"412 Elk Ave Crested Butte CO 81224",
    "addr:housenumber":"412",
    "addr:postcode":"81224",
    "addr:street":"Elk Ave",
    "iso:country":"US",
    "sg:address":"412 Elk Ave",
    "sg:city":"Crested Butte",
    "sg:classifiers":[
        {
            "category":"Food & Beverages",
            "subcategory":"Specialty",
            "type":"Retail Goods"
        }
    ],
    "sg:phone":"+1 970 349 1449",
    "sg:postcode":"81224",
    "sg:province":"CO",
    "sg:tags":[
        "water",
        "bulk",
        "company"
    ],
    "wof:name":"Stewart Water Information",
    "wof:placetype":"venue"
},
  "geometry": {"coordinates":[-106.98401200000001,38.869687],"type":"Point"}
}