{
  "type": "Feature",
  "properties": {
    "iso:country":"US",
    "sg:address":"1550 S Steele Street",
    "sg:city":"Denver",
    "sg:classifiers":[
        {
            "category":"Education",
            "subcategory":"School",
            "type":"Public Place"
        }
    ],
    "sg:phone":"+1 303 744 2726",
    "sg:postcode":"80210",
    "sg:province":"CO",
    "sg:tags":[
        "high",
        "middle",
        "elementary"
    ],
    "wof:name":"Cory Elementary School",
    "wof:placetype":"venue"
},
  "geometry": {"coordinates":[-104.950171,39.688715],"type":"Point"}
}