{
  "type": "Feature",
  "properties": {
    "addr:full":"2227 N Nevada Ave Colorado Springs CO 80907",
    "addr:housenumber":"2227",
    "addr:postcode":"80907",
    "addr:street":"N Nevada Ave",
    "iso:country":"US",
    "sg:address":"2227 N Nevada Ave",
    "sg:city":"Colorado Springs",
    "sg:classifiers":[
        {
            "category":"Building & Trades",
            "subcategory":"Construction",
            "type":"Services"
        }
    ],
    "sg:phone":"+1 719 442 0417",
    "sg:postcode":"80907",
    "sg:province":"CO",
    "sg:tags":[
        "house"
    ],
    "wof:name":"Corona Homes",
    "wof:placetype":"venue"
},
  "geometry": {"coordinates":[-104.819858,38.865214],"type":"Point"}
}