{
  "type": "Feature",
  "properties": {
    "iso:country":"US",
    "sg:address":"7251 W Alaska Drive",
    "sg:city":"Lakewood",
    "sg:classifiers":[
        {
            "category":"Shopping",
            "subcategory":"Clothing, Apparel, & Fashions",
            "type":"Retail Goods"
        }
    ],
    "sg:phone":"+1 303 742 8721",
    "sg:postcode":"80226",
    "sg:province":"CO",
    "sg:tags":[
        "accessory",
        "clothing",
        "women's"
    ],
    "sg:website":"www.aeropostale.com",
    "wof:name":"Aeropostale #632",
    "wof:placetype":"venue"
},
  "geometry": {"coordinates":[-105.075999,39.709197],"type":"Point"}
}