{
  "type": "Feature",
  "properties": {
    "addr:full":"3519 Richmond Dr Fort Collins CO 80526",
    "addr:housenumber":"3519",
    "addr:postcode":"80526",
    "addr:street":"Richmond Dr",
    "iso:country":"US",
    "sg:address":"3519 Richmond Dr",
    "sg:city":"Fort Collins",
    "sg:classifiers":[
        {
            "category":"Health Services",
            "subcategory":"Health Practitioner",
            "type":"Services"
        }
    ],
    "sg:phone":"+1 970 482 7515",
    "sg:postcode":"80526",
    "sg:province":"CO",
    "sg:tags":[
        "therapist",
        "physical"
    ],
    "wof:name":"Healthsouth Rehabilitation Ctr",
    "wof:placetype":"venue"
},
  "geometry": {"coordinates":[-105.09863300000001,40.538332],"type":"Point"}
}