{
  "type": "Feature",
  "properties": {
    "iso:country":"US",
    "sg:address":"544 Saw Mill Rd",
    "sg:city":"Durango",
    "sg:classifiers":[
        {
            "category":"Manufacturing",
            "subcategory":"Metals",
            "type":"Manufacturing & Wholesale Goods"
        }
    ],
    "sg:phone":"+1 970 382 0393",
    "sg:postcode":"81303",
    "sg:province":"CO",
    "sg:tags":[
        "steel"
    ],
    "wof:name":"USA Steel",
    "wof:placetype":"venue"
},
  "geometry": {"coordinates":[-107.733175,37.271681],"type":"Point"}
}