{
  "type": "Feature",
  "properties": {
    "iso:country":"US",
    "sg:address":"2448 Irving St",
    "sg:city":"Denver",
    "sg:classifiers":[
        {
            "category":"Shopping",
            "subcategory":"Clothing, Apparel, & Fashions",
            "type":"Retail Goods"
        }
    ],
    "sg:phone":"+1 303 458 6430",
    "sg:postcode":"80211",
    "sg:province":"CO",
    "wof:name":"Mista Uh Nons Distribution",
    "wof:placetype":"venue"
},
  "geometry": {"coordinates":[-105.029892,39.753034],"type":"Point"}
}