{
  "type": "Feature",
  "properties": {
    "iso:country":"US",
    "sg:address":"9380 Federal Blvd",
    "sg:city":"Denver",
    "sg:classifiers":[
        {
            "category":"Food & Beverages",
            "subcategory":"Liquor & Beverages",
            "type":"Retail Goods"
        }
    ],
    "sg:phone":"+1 303 426 8500",
    "sg:postcode":"80260",
    "sg:province":"CO",
    "sg:tags":[
        "store"
    ],
    "wof:name":"Sam's Warehouse Liquors",
    "wof:placetype":"venue"
},
  "geometry": {"coordinates":[-105.025008,39.863492],"type":"Point"}
}