{
  "type": "Feature",
  "properties": {
    "addr:full":"2230 Kingston St Aurora CO 80010",
    "addr:housenumber":"2230",
    "addr:postcode":"80010",
    "addr:street":"Kingston St",
    "iso:country":"US",
    "sg:address":"2230 Kingston St",
    "sg:city":"Aurora",
    "sg:classifiers":[
        {
            "category":"Freight",
            "type":"Transportation"
        }
    ],
    "sg:phone":"+1 303 364 7965",
    "sg:postcode":"80010",
    "sg:province":"CO",
    "sg:tags":[
        "operator",
        "local",
        "trucking"
    ],
    "wof:name":"Rolling Rock Trucking Co",
    "wof:placetype":"venue"
},
  "geometry": {"coordinates":[-104.85866300000001,39.750536],"type":"Point"}
}