{
  "type": "Feature",
  "properties": {
    "addr:full":"2525 S. Downing St. Denver CO 80202",
    "addr:housenumber":"2525",
    "addr:postcode":"80202",
    "addr:street":"S. Downing St.",
    "iso:country":"US",
    "sg:address":"2525 S. Downing St.",
    "sg:city":"Denver",
    "sg:classifiers":[
        {
            "category":"Health Services",
            "subcategory":"Hospital",
            "type":"Services"
        }
    ],
    "sg:phone":"+1 303 722 3933",
    "sg:postcode":"80202",
    "sg:province":"CO",
    "sg:website":"www.centuraaskanurse.org",
    "wof:name":"Centura Health-Avista Adventist Hospital",
    "wof:placetype":"venue"
},
  "geometry": {"coordinates":[-104.974773,39.670117],"type":"Point"}
}