{
  "type": "Feature",
  "properties": {
    "iso:country":"US",
    "sg:address":"11189 N Donley Dr",
    "sg:city":"Parker",
    "sg:classifiers":[
        {
            "category":"Building & Trades",
            "subcategory":"Construction",
            "type":"Services"
        }
    ],
    "sg:phone":"+1 303 841 4341",
    "sg:postcode":"80138",
    "sg:province":"CO",
    "sg:tags":[
        "builder",
        "deck"
    ],
    "wof:name":"Preferred Construction Co",
    "wof:placetype":"venue"
},
  "geometry": {"coordinates":[-104.763711,39.525474],"type":"Point"}
}