{
  "type": "Feature",
  "properties": {
    "addr:full":"6850 Jay Rd Boulder CO 80301",
    "addr:housenumber":"6850",
    "addr:postcode":"80301",
    "addr:street":"Jay Rd",
    "iso:country":"US",
    "sg:address":"6850 Jay Rd",
    "sg:city":"Boulder",
    "sg:classifiers":[
        {
            "category":"Professional",
            "type":"Services"
        }
    ],
    "sg:phone":"+1 303 530 4611",
    "sg:postcode":"80301",
    "sg:province":"CO",
    "wof:name":"Walker Queeda",
    "wof:placetype":"venue"
},
  "geometry": {"coordinates":[-105.197776,40.0509],"type":"Point"}
}