{
  "type": "Feature",
  "properties": {
    "addr:full":"1795 Airport Rd Breckenridge CO 80424",
    "addr:housenumber":"1795",
    "addr:postcode":"80424",
    "addr:street":"Airport Rd",
    "iso:country":"US",
    "sg:address":"1795 Airport Rd",
    "sg:city":"Breckenridge",
    "sg:classifiers":[
        {
            "category":"Travel",
            "subcategory":"Hotels & Motels",
            "type":"Entertainment"
        }
    ],
    "sg:phone":"+1 970 453 5520",
    "sg:postcode":"80424",
    "sg:province":"CO",
    "sg:tags":[
        "resort"
    ],
    "wof:name":"Resort Quest",
    "wof:placetype":"venue"
},
  "geometry": {"coordinates":[-106.051675,39.508012],"type":"Point"}
}