{
  "type": "Feature",
  "properties": {
    "addr:full":"2808 11th Ave Evans CO 80620",
    "addr:housenumber":"2808",
    "addr:postcode":"80620",
    "addr:street":"11Th Ave",
    "iso:country":"US",
    "sg:address":"2808 11th Ave",
    "sg:city":"Evans",
    "sg:classifiers":[
        {
            "category":"Food & Beverages",
            "subcategory":"Liquor & Beverages",
            "type":"Retail Goods"
        }
    ],
    "sg:phone":"+1 970 352 2327",
    "sg:postcode":"80620",
    "sg:province":"CO",
    "sg:tags":[
        "alcoholic"
    ],
    "wof:name":"University Liquors Of Evans",
    "wof:placetype":"venue"
},
  "geometry": {"coordinates":[-104.696832,40.390899],"type":"Point"}
}