{
  "type": "Feature",
  "properties": {
    "addr:full":"16315 Tucson St Brighton CO 80601",
    "addr:housenumber":"16315",
    "addr:postcode":"80601",
    "addr:street":"Tucson St",
    "iso:country":"US",
    "sg:address":"16315 Tucson St",
    "sg:city":"Brighton",
    "sg:classifiers":[
        {
            "category":"Farming",
            "subcategory":"Nursery",
            "type":"Manufacturing & Wholesale Goods"
        }
    ],
    "sg:phone":"+1 303 659 2454",
    "sg:postcode":"80601",
    "sg:province":"CO",
    "sg:tags":[
        "greenhouse"
    ],
    "wof:name":"Horiuchi Brothers Greenhouse",
    "wof:placetype":"venue"
},
  "geometry": {"coordinates":[-104.837425,39.991675],"type":"Point"}
}