{
  "type": "Feature",
  "properties": {
    "iso:country":"US",
    "sg:address":"123 S Main St",
    "sg:city":"Fowler",
    "sg:classifiers":[
        {
            "category":"Government",
            "subcategory":"Post Office",
            "type":"Public Place"
        }
    ],
    "sg:phone":"+1 719 263 5260",
    "sg:postcode":"81039",
    "sg:province":"CO",
    "sg:tags":[
        "postal",
        "us"
    ],
    "wof:name":"Fowler Post Office",
    "wof:placetype":"venue"
},
  "geometry": {"coordinates":[-104.023421,38.131533],"type":"Point"}
}