{
  "type": "Feature",
  "properties": {
    "addr:full":"542 N 11th Ave Greeley CO 80631",
    "addr:housenumber":"542",
    "addr:postcode":"80631",
    "addr:street":"N 11Th Ave",
    "iso:country":"US",
    "sg:address":"542 N 11th Ave",
    "sg:city":"Greeley",
    "sg:classifiers":[
        {
            "category":"Real Estate",
            "subcategory":"Developer",
            "type":"Services"
        }
    ],
    "sg:phone":"+1 970 353 3691",
    "sg:postcode":"80631",
    "sg:province":"CO",
    "sg:tags":[
        "mobile",
        "home"
    ],
    "wof:name":"River Park Mobile Park",
    "wof:placetype":"venue"
},
  "geometry": {"coordinates":[-104.696558,40.443651],"type":"Point"}
}