{
  "type": "Feature",
  "properties": {
    "addr:full":"610 Barbed Wire Ignacio CO 81137",
    "addr:housenumber":"610",
    "addr:postcode":"81137",
    "addr:street":"Barbed;Ignacio",
    "iso:country":"US",
    "sg:address":"610 Barbed Wire",
    "sg:city":"Ignacio",
    "sg:classifiers":[
        {
            "category":"Food & Beverages",
            "subcategory":"Specialty",
            "type":"Retail Goods"
        }
    ],
    "sg:phone":"+1 970 883 3088",
    "sg:postcode":"81137",
    "sg:province":"CO",
    "wof:name":"Herb Lady Gardens",
    "wof:placetype":"venue"
},
  "geometry": {"coordinates":[-107.514777,37.050614],"type":"Point"}
}