{
  "type": "Feature",
  "properties": {
    "iso:country":"US",
    "sg:address":"420 Harrison Ave",
    "sg:city":"Leadville",
    "sg:classifiers":[
        {
            "category":"Professional",
            "type":"Services"
        }
    ],
    "sg:phone":"+1 719 486 1033",
    "sg:postcode":"80461",
    "sg:province":"CO",
    "sg:tags":[
        "establishment"
    ],
    "wof:name":"Q B Assoc",
    "wof:placetype":"venue"
},
  "geometry": {"coordinates":[-106.291336,39.247406],"type":"Point"}
}