{
  "type": "Feature",
  "properties": {
    "addr:full":"7140 N Academy Blvd Colorado Springs CO 80920",
    "addr:housenumber":"7140",
    "addr:postcode":"80920",
    "addr:street":"N Academy Blvd",
    "iso:country":"US",
    "sg:address":"7140 N Academy Blvd",
    "sg:city":"Colorado Springs",
    "sg:classifiers":[
        {
            "category":"Restaurant",
            "type":"Food & Drink"
        }
    ],
    "sg:menulink":"http://www.allmenus.com/co/colorado-springs/247255-qdoba-mexican-grill/menu/",
    "sg:phone":"+1 719 533 0046",
    "sg:postcode":"80920",
    "sg:province":"CO",
    "sg:tags":[
        "mexican"
    ],
    "wof:name":"Qdoba Mexican Grill",
    "wof:placetype":"venue"
},
  "geometry": {"coordinates":[-104.798633,38.936085],"type":"Point"}
}