{
  "type": "Feature",
  "properties": {
    "addr:full":"2180 E 68th Ave Denver CO 80229",
    "addr:housenumber":"2180",
    "addr:postcode":"80229",
    "addr:street":"E 68Th Ave",
    "iso:country":"US",
    "sg:address":"2180 E 68th Ave",
    "sg:city":"Denver",
    "sg:classifiers":[
        {
            "category":"Wholesale",
            "subcategory":"Electrical",
            "type":"Manufacturing & Wholesale Goods"
        }
    ],
    "sg:phone":"+1 303 425 6300",
    "sg:postcode":"80229",
    "sg:province":"CO",
    "sg:tags":[
        "equipment",
        "electronic"
    ],
    "wof:name":"Wwwtimebussystemscom",
    "wof:placetype":"venue"
},
  "geometry": {"coordinates":[-104.960157,39.819863],"type":"Point"}
}