{
  "type": "Feature",
  "properties": {
    "iso:country":"US",
    "sg:address":"120 N Dayton Ave",
    "sg:city":"Pueblo",
    "sg:classifiers":[
        {
            "category":"Building & Trades",
            "subcategory":"Construction",
            "type":"Services"
        }
    ],
    "sg:phone":"+1 719 544 6391",
    "sg:postcode":"81003",
    "sg:province":"CO",
    "sg:tags":[
        "general",
        "contractor"
    ],
    "wof:name":"Bassett Construction Co",
    "wof:placetype":"venue"
},
  "geometry": {"coordinates":[-104.601457,38.268692],"type":"Point"}
}