{
  "type": "Feature",
  "properties": {
    "iso:country":"US",
    "sg:address":"4695 S Broadway",
    "sg:city":"Englewood",
    "sg:classifiers":[
        {
            "category":"Autos & Motor Vehicles",
            "subcategory":"Fuel & Gas Station",
            "type":"Retail Goods"
        }
    ],
    "sg:phone":"+1 303 806 9905",
    "sg:postcode":"80113",
    "sg:province":"CO",
    "sg:tags":[
        "oil"
    ],
    "wof:name":"Bradley Petroleum Inc",
    "wof:placetype":"venue"
},
  "geometry": {"coordinates":[-104.987981,39.633048],"type":"Point"}
}