{
  "type": "Feature",
  "properties": {
    "iso:country":"US",
    "sg:address":"11742 E Jewell Pl",
    "sg:city":"Aurora",
    "sg:classifiers":[
        {
            "category":"Wholesale",
            "subcategory":"Electrical",
            "type":"Manufacturing & Wholesale Goods"
        },
        {
            "category":"Wholesale",
            "subcategory":"Durable Goods & Equipment",
            "type":"Manufacturing & Wholesale Goods"
        }
    ],
    "sg:phone":"+1 303 751 7220",
    "sg:postcode":"80012",
    "sg:province":"CO",
    "sg:tags":[
        "electronic",
        "representative",
        "manufacturer"
    ],
    "wof:name":"Scowcroft & Associates",
    "wof:placetype":"venue"
},
  "geometry": {"coordinates":[-104.85127,39.682726],"type":"Point"}
}