{
  "type": "Feature",
  "properties": {
    "iso:country":"US",
    "sg:address":"6633 W 66th Ave",
    "sg:city":"Arvada",
    "sg:classifiers":[
        {
            "category":"Retail",
            "subcategory":"Laundry & Dry Cleaning",
            "type":"Services"
        },
        {
            "category":"Building & Trades",
            "subcategory":"Cleaning & Sanitation",
            "type":"Services"
        }
    ],
    "sg:phone":"+1 303 456 5407",
    "sg:postcode":"80003",
    "sg:province":"CO",
    "sg:tags":[
        "cleaner",
        "house"
    ],
    "wof:name":"Scott's Landscaping",
    "wof:placetype":"venue"
},
  "geometry": {"coordinates":[-105.06952,39.816452],"type":"Point"}
}