{
  "type": "Feature",
  "properties": {
    "addr:full":"8607 W 54th Pl Arvada CO 80002",
    "addr:housenumber":"8607",
    "addr:postcode":"80002",
    "addr:street":"W 54Th Pl",
    "iso:country":"US",
    "sg:address":"8607 W 54th Pl",
    "sg:city":"Arvada",
    "sg:classifiers":[
        {
            "category":"Building & Trades",
            "subcategory":"Construction",
            "type":"Services"
        }
    ],
    "sg:phone":"+1 303 424 2271",
    "sg:postcode":"80002",
    "sg:province":"CO",
    "sg:tags":[
        "painter"
    ],
    "wof:name":"TLAA & Co",
    "wof:placetype":"venue"
},
  "geometry": {"coordinates":[-105.095063,39.794975],"type":"Point"}
}