{
  "type": "Feature",
  "properties": {
    "addr:full":"59 Golden Eagle Ln Littleton CO 80127",
    "addr:housenumber":"59",
    "addr:postcode":"80127",
    "addr:street":"Golden Eagle Ln",
    "iso:country":"US",
    "sg:address":"59 Golden Eagle Ln",
    "sg:city":"Littleton",
    "sg:classifiers":[
        {
            "category":"Mining & Drilling",
            "type":"Manufacturing & Wholesale Goods"
        }
    ],
    "sg:phone":"+1 303 694 6038",
    "sg:postcode":"80127",
    "sg:province":"CO",
    "sg:tags":[
        "exploration"
    ],
    "wof:name":"Clyde E Thompson",
    "wof:placetype":"venue"
},
  "geometry": {"coordinates":[-105.176762,39.594138],"type":"Point"}
}