{
  "type": "Feature",
  "properties": {
    "iso:country":"US",
    "sg:address":"120 Coleridge Ave",
    "sg:city":"Colorado Springs",
    "sg:classifiers":[
        {
            "category":"Real Estate",
            "subcategory":"Real Estate Operator",
            "type":"Services"
        }
    ],
    "sg:phone":"+1 719 597 0753",
    "sg:postcode":"80909",
    "sg:province":"CO",
    "sg:tags":[
        "condominium"
    ],
    "sg:website":"www.esperanzavillage.com",
    "wof:name":"Esperanza Village Condo Sales",
    "wof:placetype":"venue"
},
  "geometry": {"coordinates":[-104.751993,38.835271],"type":"Point"}
}