{
  "type": "Feature",
  "properties": {
    "addr:full":"7510 S Homesteader Dr Morrison CO 80465",
    "addr:housenumber":"7510",
    "addr:postcode":"80465",
    "addr:street":"S Homesteader Dr",
    "iso:country":"US",
    "sg:address":"7510 S Homesteader Dr",
    "sg:city":"Morrison",
    "sg:classifiers":[
        {
            "category":"Professional",
            "subcategory":"Management & Consulting",
            "type":"Services"
        }
    ],
    "sg:phone":"+1 303 697 7798",
    "sg:postcode":"80465",
    "sg:province":"CO",
    "sg:tags":[
        "consultant",
        "business"
    ],
    "wof:name":"K R Consulting",
    "wof:placetype":"venue"
},
  "geometry": {"coordinates":[-105.24575900000001,39.579452],"type":"Point"}
}