{
  "type": "Feature",
  "properties": {
    "iso:country":"US",
    "sg:address":"113 N Gold Flake Ter",
    "sg:city":"Breckenridge",
    "sg:classifiers":[
        {
            "category":"Professional",
            "type":"Services"
        }
    ],
    "sg:phone":"+1 970 453 1328",
    "sg:postcode":"80424",
    "sg:province":"CO",
    "sg:tags":[
        "establishment"
    ],
    "wof:name":"Altila Corp",
    "wof:placetype":"venue"
},
  "geometry": {"coordinates":[-106.040193,39.485354],"type":"Point"}
}