{
  "type": "Feature",
  "properties": {
    "addr:full":"545 Cottonwood Ave Las Animas CO 81054",
    "addr:housenumber":"545",
    "addr:postcode":"81054",
    "addr:street":"Cottonwood Ave Las",
    "iso:country":"US",
    "sg:address":"545 Cottonwood Ave",
    "sg:city":"Las Animas",
    "sg:classifiers":[
        {
            "category":"Building & Trades",
            "subcategory":"Construction",
            "type":"Services"
        }
    ],
    "sg:phone":"+1 719 456 1510",
    "sg:postcode":"81054",
    "sg:province":"CO",
    "sg:tags":[
        "marking",
        "maintenance",
        "parking"
    ],
    "wof:name":"Public Works Shop",
    "wof:placetype":"venue"
},
  "geometry": {"coordinates":[-103.23327999999999,38.067219],"type":"Point"}
}