{
  "type": "Feature",
  "properties": {
    "addr:full":"26800 Wild Flower Trl Evergreen CO 80439",
    "addr:housenumber":"26800",
    "addr:postcode":"80439",
    "addr:street":"Wild Flower Trl",
    "iso:country":"US",
    "sg:address":"26800 Wild Flower Trl",
    "sg:city":"Evergreen",
    "sg:classifiers":[
        {
            "category":"Professional",
            "type":"Services"
        }
    ],
    "sg:phone":"+1 303 679 4439",
    "sg:postcode":"80439",
    "sg:province":"CO",
    "wof:name":"Thomas J Wajcik",
    "wof:placetype":"venue"
},
  "geometry": {"coordinates":[-105.30088000000001,39.628551],"type":"Point"}
}