{
  "type": "Feature",
  "properties": {
    "iso:country":"US",
    "sg:address":"6510 S US Hwy 85-87",
    "sg:city":"Fountain",
    "sg:classifiers":[
        {
            "category":"Personal",
            "subcategory":"Beauty Salon",
            "type":"Services"
        }
    ],
    "sg:phone":"+1 719 392 4578",
    "sg:postcode":"80817",
    "sg:province":"CO",
    "sg:tags":[
        "manicuring"
    ],
    "wof:name":"Regal Nails",
    "wof:placetype":"venue"
},
  "geometry": {"coordinates":[-104.731516,38.737436],"type":"Point"}
}