{
  "type": "Feature",
  "properties": {
    "iso:country":"US",
    "sg:address":"126 S Taft Ave",
    "sg:city":"Loveland",
    "sg:classifiers":[
        {
            "category":"Autos & Motor Vehicles",
            "subcategory":"Fuel & Gas Station",
            "type":"Retail Goods"
        }
    ],
    "sg:phone":"+1 970 663 7261",
    "sg:postcode":"80537",
    "sg:province":"CO",
    "sg:tags":[
        "oil"
    ],
    "wof:name":"Diamond Shamrock Refining Co",
    "wof:placetype":"venue"
},
  "geometry": {"coordinates":[-105.096785,40.392303],"type":"Point"}
}