{
  "type": "Feature",
  "properties": {
    "addr:full":"28628 Aspen Dr Conifer CO 80433",
    "addr:housenumber":"28628",
    "addr:postcode":"80433",
    "addr:street":"Aspen Dr",
    "iso:country":"US",
    "sg:address":"28628 Aspen Dr",
    "sg:city":"Conifer",
    "sg:classifiers":[
        {
            "category":"Real Estate",
            "subcategory":"Real Estate Agent",
            "type":"Services"
        }
    ],
    "sg:phone":"+1 303 816 9356",
    "sg:postcode":"80433",
    "sg:province":"CO",
    "sg:tags":[
        "management"
    ],
    "wof:name":"A-1 Mountain Property Mgmt",
    "wof:placetype":"venue"
},
  "geometry": {"coordinates":[-105.328318,39.497087],"type":"Point"}
}