{
  "type": "Feature",
  "properties": {
    "iso:country":"US",
    "sg:address":"2663 S Howell St",
    "sg:city":"Lakewood",
    "sg:classifiers":[
        {
            "category":"Banks & Credit Unions",
            "subcategory":"Bank",
            "type":"Services"
        }
    ],
    "sg:phone":"+1 303 987 8881",
    "sg:postcode":"80228",
    "sg:province":"CO",
    "sg:tags":[
        "loan",
        "real estate"
    ],
    "wof:name":"All Credit Mortgage Experts",
    "wof:placetype":"venue"
},
  "geometry": {"coordinates":[-105.165162,39.668254],"type":"Point"}
}