{
  "type": "Feature",
  "properties": {
    "addr:full":"6425 W 60th Ave Arvada CO 80003",
    "addr:housenumber":"6425",
    "addr:postcode":"80003",
    "addr:street":"W 60Th Ave",
    "iso:country":"US",
    "sg:address":"6425 W 60th Ave",
    "sg:city":"Arvada",
    "sg:classifiers":[
        {
            "category":"Building & Trades",
            "subcategory":"Construction",
            "type":"Services"
        }
    ],
    "sg:phone":"+1 303 424 2812",
    "sg:postcode":"80003",
    "sg:province":"CO",
    "sg:tags":[
        "contractor"
    ],
    "wof:name":"Al's Maintenance & Repair Co",
    "wof:placetype":"venue"
},
  "geometry": {"coordinates":[-105.068502,39.805852],"type":"Point"}
}