{
  "type": "Feature",
  "properties": {
    "addr:full":"307 Comanche St Kiowa CO 80117",
    "addr:housenumber":"307",
    "addr:postcode":"80117",
    "addr:street":"Comanche St",
    "iso:country":"US",
    "sg:address":"307 Comanche St",
    "sg:city":"Kiowa",
    "sg:classifiers":[
        {
            "category":"Food & Beverages",
            "subcategory":"Groceries & Convenience Stores",
            "type":"Retail Goods"
        }
    ],
    "sg:phone":"+1 303 621 2757",
    "sg:postcode":"80117",
    "sg:province":"CO",
    "sg:tags":[
        "business"
    ],
    "wof:name":"UPS Stores The",
    "wof:placetype":"venue"
},
  "geometry": {"coordinates":[-104.466042,39.346663],"type":"Point"}
}