{
  "type": "Feature",
  "properties": {
    "addr:full":"6725 N Taft Hill Rd Fort Collins CO 80524",
    "addr:housenumber":"6725",
    "addr:postcode":"80524",
    "addr:street":"N Taft Hill Rd",
    "iso:country":"US",
    "sg:address":"6725 N Taft Hill Rd",
    "sg:city":"Fort Collins",
    "sg:classifiers":[
        {
            "category":"Farming",
            "subcategory":"Dairy Farm",
            "type":"Manufacturing & Wholesale Goods"
        }
    ],
    "sg:phone":"+1 970 224 2591",
    "sg:postcode":"80524",
    "sg:province":"CO",
    "wof:name":"Sas Dairy",
    "wof:placetype":"venue"
},
  "geometry": {"coordinates":[-105.113221,40.674763],"type":"Point"}
}