{
  "type": "Feature",
  "properties": {
    "addr:full":"72 Co Rd 451 Breckenridge CO 80424",
    "addr:housenumber":"72;451",
    "addr:postcode":"80424",
    "addr:street":"Co Rd",
    "iso:country":"US",
    "sg:address":"72 Co Rd 451",
    "sg:city":"Breckenridge",
    "sg:classifiers":[
        {
            "category":"Government",
            "subcategory":"Office",
            "type":"Public Place"
        }
    ],
    "sg:phone":"+1 970 547 0545",
    "sg:postcode":"80424",
    "sg:province":"CO",
    "sg:tags":[
        "village"
    ],
    "wof:name":"Town Of Blue River Clerks",
    "wof:placetype":"venue"
},
  "geometry": {"coordinates":[-106.036965,39.4909],"type":"Point"}
}