{
  "type": "Feature",
  "properties": {
    "iso:country":"US",
    "sg:address":"6165 S Forest Ct",
    "sg:city":"Littleton",
    "sg:classifiers":[
        {
            "category":"Real Estate",
            "subcategory":"Real Estate Agent",
            "type":"Services"
        }
    ],
    "sg:phone":"+1 303 773 1973",
    "sg:postcode":"80121",
    "sg:province":"CO",
    "wof:name":"BT Springs Resorts LLC",
    "wof:placetype":"venue"
},
  "geometry": {"coordinates":[-104.926073,39.604681],"type":"Point"}
}