{
  "type": "Feature",
  "properties": {
    "addr:full":"199 S Main St Longmont CO 80501",
    "addr:housenumber":"199",
    "addr:postcode":"80501",
    "addr:street":"S Main St",
    "iso:country":"US",
    "sg:address":"199 S Main St",
    "sg:city":"Longmont",
    "sg:classifiers":[
        {
            "category":"Restaurant",
            "type":"Food & Drink"
        }
    ],
    "sg:menulink":"http://www.allmenus.com/co/longmont/280205-las-palmeras/menu/",
    "sg:phone":"+1 303 848 0103",
    "sg:postcode":"80501",
    "sg:province":"CO",
    "sg:tags":[
        "mexican"
    ],
    "wof:name":"Las Palmeras",
    "wof:placetype":"venue"
},
  "geometry": {"coordinates":[-105.10297300000001,40.155275],"type":"Point"}
}