{
  "type": "Feature",
  "properties": {
    "iso:country":"US",
    "sg:address":"2785 N Speer Blvd",
    "sg:city":"Denver",
    "sg:classifiers":[
        {
            "category":"Building & Trades",
            "subcategory":"Construction",
            "type":"Services"
        }
    ],
    "sg:phone":"+1 303 458 5955",
    "sg:postcode":"80211",
    "sg:province":"CO",
    "sg:tags":[
        "contractor"
    ],
    "wof:name":"Acero Builders Inc",
    "wof:placetype":"venue"
},
  "geometry": {"coordinates":[-105.01903,39.757363],"type":"Point"}
}