{
  "type": "Feature",
  "properties": {
    "addr:full":"125 W 3rd St Wray CO 80758",
    "addr:housenumber":"125",
    "addr:postcode":"80758",
    "addr:street":"W 3Rd St",
    "iso:country":"US",
    "sg:address":"125 W 3rd St",
    "sg:city":"Wray",
    "sg:classifiers":[
        {
            "category":"Autos & Motor Vehicles",
            "subcategory":"Auto Supplies",
            "type":"Retail Goods"
        }
    ],
    "sg:phone":"+1 970 332 4865",
    "sg:postcode":"80758",
    "sg:province":"CO",
    "sg:tags":[
        "parts"
    ],
    "wof:name":"Car Quest Auto Parts",
    "wof:placetype":"venue"
},
  "geometry": {"coordinates":[-102.222499,40.079],"type":"Point"}
}