{
  "type": "Feature",
  "properties": {
    "addr:full":"4610 Austin Bluffs Pkwy Colorado Springs CO 80918",
    "addr:housenumber":"4610",
    "addr:postcode":"80918",
    "addr:street":"Austin Bluffs Pkwy",
    "iso:country":"US",
    "sg:address":"4610 Austin Bluffs Pkwy",
    "sg:city":"Colorado Springs",
    "sg:classifiers":[
        {
            "category":"Retail",
            "subcategory":"Auto Repair",
            "type":"Services"
        }
    ],
    "sg:phone":"+1 719 598 1535",
    "sg:postcode":"80918",
    "sg:province":"CO",
    "sg:tags":[
        "machine",
        "automobile",
        "shop"
    ],
    "wof:name":"Geddes Auto Machine",
    "wof:placetype":"venue"
},
  "geometry": {"coordinates":[-104.745088,38.899352],"type":"Point"}
}