{
  "type": "Feature",
  "properties": {
    "addr:full":"324 Main St Fort Morgan CO 80701",
    "addr:housenumber":"324",
    "addr:postcode":"80701",
    "addr:street":"Main St",
    "iso:country":"US",
    "sg:address":"324 Main St",
    "sg:city":"Fort Morgan",
    "sg:classifiers":[
        {
            "category":"Building & Trades",
            "subcategory":"Equipment Rental",
            "type":"Services"
        }
    ],
    "sg:phone":"+1 970 867 1000",
    "sg:postcode":"80701",
    "sg:province":"CO",
    "wof:name":"H Class Inc",
    "wof:placetype":"venue"
},
  "geometry": {"coordinates":[-103.80141999999999,40.250898],"type":"Point"}
}