{
  "type": "Feature",
  "properties": {
    "iso:country":"US",
    "sg:address":"542 S Belford Ave",
    "sg:city":"Holyoke",
    "sg:classifiers":[
        {
            "category":"Freight",
            "type":"Transportation"
        }
    ],
    "sg:phone":"+1 970 854 2726",
    "sg:postcode":"80734",
    "sg:province":"CO",
    "sg:tags":[
        "operator",
        "local",
        "trucking"
    ],
    "wof:name":"Randy Boyd Trucking",
    "wof:placetype":"venue"
},
  "geometry": {"coordinates":[-102.305072,40.581154],"type":"Point"}
}