{
  "type": "Feature",
  "properties": {
    "iso:country":"US",
    "sg:address":"13775 Garrett Rd",
    "sg:city":"Peyton",
    "sg:classifiers":[
        {
            "category":"Professional",
            "type":"Services"
        }
    ],
    "sg:phone":"+1 719 683 2933",
    "sg:postcode":"80831",
    "sg:province":"CO",
    "wof:name":"Sullivan",
    "wof:placetype":"venue"
},
  "geometry": {"coordinates":[-104.57013999999999,38.910812],"type":"Point"}
}