{
  "type": "Feature",
  "properties": {
    "addr:full":"127 Meadow Dr Fort Collins CO 80524",
    "addr:housenumber":"127",
    "addr:postcode":"80524",
    "addr:street":"Meadow Dr",
    "iso:country":"US",
    "sg:address":"127 Meadow Dr",
    "sg:city":"Fort Collins",
    "sg:classifiers":[
        {
            "category":"Building & Trades",
            "subcategory":"Construction",
            "type":"Services"
        }
    ],
    "sg:phone":"+1 970 221 3471",
    "sg:postcode":"80524",
    "sg:province":"CO",
    "wof:name":"Wind Hover",
    "wof:placetype":"venue"
},
  "geometry": {"coordinates":[-105.08658800000001,40.62292],"type":"Point"}
}