{
  "type": "Feature",
  "properties": {
    "addr:full":"3455 Ringsby Ct Denver CO 80216",
    "addr:housenumber":"3455",
    "addr:postcode":"80216",
    "addr:street":"Ringsby Ct",
    "iso:country":"US",
    "sg:address":"3455 Ringsby Ct",
    "sg:city":"Denver",
    "sg:classifiers":[
        {
            "category":"Real Estate",
            "subcategory":"Real Estate Agent",
            "type":"Services"
        }
    ],
    "sg:phone":"+1 303 573 0781",
    "sg:postcode":"80216",
    "sg:province":"CO",
    "wof:name":"Zeppelin Development",
    "wof:placetype":"venue"
},
  "geometry": {"coordinates":[-104.981516,39.772031],"type":"Point"}
}