{
  "type": "Feature",
  "properties": {
    "addr:full":"235 Thames Dr Colorado Springs CO 80906",
    "addr:housenumber":"235",
    "addr:postcode":"80906",
    "addr:street":"Thames Dr",
    "iso:country":"US",
    "sg:address":"235 Thames Dr",
    "sg:city":"Colorado Springs",
    "sg:classifiers":[
        {
            "category":"Insurance",
            "subcategory":"Insurance Agent",
            "type":"Services"
        }
    ],
    "sg:phone":"+1 719 540 8049",
    "sg:postcode":"80906",
    "sg:province":"CO",
    "sg:tags":[
        "housing",
        "inspection"
    ],
    "wof:name":"Cwis LLC",
    "wof:placetype":"venue"
},
  "geometry": {"coordinates":[-104.827079,38.764311],"type":"Point"}
}