{
  "type": "Feature",
  "properties": {
    "iso:country":"US",
    "sg:address":"2313 S Dawson Way",
    "sg:city":"Aurora",
    "sg:classifiers":[
        {
            "category":"Shopping",
            "subcategory":"Used Merchandise",
            "type":"Retail Goods"
        }
    ],
    "sg:phone":"+1 303 752 4499",
    "sg:postcode":"80014",
    "sg:province":"CO",
    "sg:tags":[
        "book",
        "rare",
        "dealer"
    ],
    "wof:name":"Book Rack",
    "wof:placetype":"venue"
},
  "geometry": {"coordinates":[-104.815562,39.674321],"type":"Point"}
}