{
  "type": "Feature",
  "properties": {
    "iso:country":"US",
    "sg:address":"40880 Madrid Dr",
    "sg:city":"Elizabeth",
    "sg:classifiers":[
        {
            "category":"Retail",
            "subcategory":"Auto Repair",
            "type":"Services"
        }
    ],
    "sg:phone":"+1 303 841 7201",
    "sg:postcode":"80107",
    "sg:province":"CO",
    "sg:tags":[
        "automobile",
        "restoration",
        "classic"
    ],
    "wof:name":"Painted Dreams",
    "wof:placetype":"venue"
},
  "geometry": {"coordinates":[-104.648217,39.46165],"type":"Point"}
}