{
  "type": "Feature",
  "properties": {
    "addr:full":"1000 S Wadsworth Blvd Lakewood CO 80226",
    "addr:housenumber":"1000",
    "addr:postcode":"80226",
    "addr:street":"S Wadsworth Blvd",
    "iso:country":"US",
    "sg:address":"1000 S Wadsworth Blvd",
    "sg:city":"Lakewood",
    "sg:classifiers":[
        {
            "category":"Banks & Credit Unions",
            "subcategory":"Bank",
            "type":"Services"
        }
    ],
    "sg:phone":"+1 303 935 0643",
    "sg:postcode":"80226",
    "sg:province":"CO",
    "sg:tags":[
        "cashing",
        "check"
    ],
    "wof:name":"Payday Now Loans",
    "wof:placetype":"venue"
},
  "geometry": {"coordinates":[-105.08150500000001,39.696624],"type":"Point"}
}