{
  "type": "Feature",
  "properties": {
    "addr:full":"Adventist Community Services 5045 1st Ave Denver CO 80219",
    "addr:housenumber":"5045",
    "addr:postcode":"80219",
    "addr:street":"1St Ave",
    "iso:country":"US",
    "sg:address":"Adventist Community Services 5045 1st Ave",
    "sg:city":"Denver",
    "sg:classifiers":[
        {
            "category":"Shopping",
            "subcategory":"Used Merchandise",
            "type":"Retail Goods"
        }
    ],
    "sg:phone":"+1 303 935 7389",
    "sg:postcode":"80219",
    "sg:province":"CO",
    "sg:tags":[
        "vintage",
        "consignment"
    ],
    "sg:website":"www.acslift.org",
    "wof:name":"ACS Community LIFT Thrift Store",
    "wof:placetype":"venue"
},
  "geometry": {"coordinates":[-105.05113299999999,39.718212],"type":"Point"}
}