{
  "type": "Feature",
  "properties": {
    "iso:country":"US",
    "sg:address":"PO Box 630830",
    "sg:city":"Littleton",
    "sg:classifiers":[
        {
            "category":"Professional",
            "subcategory":"Advertising",
            "type":"Services"
        }
    ],
    "sg:postcode":"80163",
    "sg:province":"CO",
    "sg:tags":[
        "airline",
        "airport",
        "aerospace",
        "aviation"
    ],
    "sg:website":"http://www.avjobs.com",
    "wof:name":"Avjobs",
    "wof:placetype":"venue"
},
  "geometry": {"coordinates":[-104.994708,39.347863],"type":"Point"}
}