{
  "type": "Feature",
  "properties": {
    "iso:country":"US",
    "sg:address":"2820 Foothill Blvd",
    "sg:city":"Rock Springs",
    "sg:classifiers":[
        {
            "category":"Banks & Credit Unions",
            "subcategory":"Investment Brokerage",
            "type":"Services"
        }
    ],
    "sg:phone":"+1 307 382 7990",
    "sg:postcode":"82901",
    "sg:province":"CO",
    "sg:tags":[
        "security",
        "business"
    ],
    "wof:name":"Smith Barney",
    "wof:placetype":"venue"
},
  "geometry": {"coordinates":[-109.252056,41.585858],"type":"Point"}
}