{
  "type": "Feature",
  "properties": {
    "iso:country":"US",
    "sg:address":"2401 W 27th St",
    "sg:city":"Greeley",
    "sg:classifiers":[
        {
            "category":"Shopping",
            "subcategory":"Used Merchandise",
            "type":"Retail Goods"
        }
    ],
    "sg:phone":"+1 970 330 7082",
    "sg:postcode":"80634",
    "sg:province":"CO",
    "sg:tags":[
        "second",
        "store",
        "hand"
    ],
    "wof:name":"ARC Thrift Shop",
    "wof:placetype":"venue"
},
  "geometry": {"coordinates":[-104.71660199999999,40.393623],"type":"Point"}
}