{
  "type": "Feature",
  "properties": {
    "addr:full":"1725 W Berkeley Pl Denver CO 80221",
    "addr:housenumber":"1725",
    "addr:postcode":"80221",
    "addr:street":"W Berkeley Pl",
    "iso:country":"US",
    "sg:address":"1725 W Berkeley Pl",
    "sg:city":"Denver",
    "sg:classifiers":[
        {
            "category":"Wholesale",
            "subcategory":"Construction Materials",
            "type":"Manufacturing & Wholesale Goods"
        }
    ],
    "sg:phone":"+1 303 430 5886",
    "sg:postcode":"80221",
    "sg:province":"CO",
    "wof:name":"Davids Tile",
    "wof:placetype":"venue"
},
  "geometry": {"coordinates":[-105.00716,39.79036],"type":"Point"}
}