{
  "type": "Feature",
  "properties": {
    "addr:full":"301 Sheridan Blvd Denver CO 80226",
    "addr:housenumber":"301",
    "addr:postcode":"80226",
    "addr:street":"Sheridan Blvd",
    "iso:country":"US",
    "sg:address":"301 Sheridan Blvd",
    "sg:city":"Denver",
    "sg:classifiers":[
        {
            "category":"Building & Trades",
            "subcategory":"Construction",
            "type":"Services"
        }
    ],
    "sg:phone":"+1 303 761 0423",
    "sg:postcode":"80226",
    "sg:province":"CO",
    "sg:tags":[
        "downspout",
        "gutter",
        "contractor"
    ],
    "wof:name":"Sutton Insulating and Gutters",
    "wof:placetype":"venue"
},
  "geometry": {"coordinates":[-105.053189,39.722561],"type":"Point"}
}