{
  "type": "Feature",
  "properties": {
    "iso:country":"US",
    "sg:address":"413 W Main St",
    "sg:city":"Buena Vista",
    "sg:classifiers":[
        {
            "category":"Personal",
            "subcategory":"Beauty Salon",
            "type":"Services"
        }
    ],
    "sg:phone":"+1 719 395 6446",
    "sg:postcode":"81236",
    "sg:province":"CO",
    "wof:name":"Double Header",
    "wof:placetype":"venue"
},
  "geometry": {"coordinates":[-106.135806,38.840784],"type":"Point"}
}