{
  "type": "Feature",
  "properties": {
    "addr:full":"6475 Huron St Denver CO 80221",
    "addr:housenumber":"6475",
    "addr:postcode":"80221",
    "addr:street":"Huron St",
    "iso:country":"US",
    "sg:address":"6475 Huron St",
    "sg:city":"Denver",
    "sg:classifiers":[
        {
            "category":"Freight",
            "type":"Transportation"
        }
    ],
    "sg:phone":"+1 303 487 8668",
    "sg:postcode":"80221",
    "sg:province":"CO",
    "sg:tags":[
        "hauling",
        "trucking"
    ],
    "wof:name":"Calabrese Trucking Inc",
    "wof:placetype":"venue"
},
  "geometry": {"coordinates":[-104.996889,39.813967],"type":"Point"}
}