{
  "type": "Feature",
  "properties": {
    "iso:country":"US",
    "sg:address":"3250 Oakland St",
    "sg:city":"Aurora",
    "sg:classifiers":[
        {
            "category":"Wholesale",
            "subcategory":"Machinery & Supplies",
            "type":"Manufacturing & Wholesale Goods"
        },
        {
            "category":"Wholesale",
            "subcategory":"Non-durable Goods",
            "type":"Manufacturing & Wholesale Goods"
        }
    ],
    "sg:phone":"+1 303 778 1204",
    "sg:postcode":"80010",
    "sg:province":"CO",
    "sg:tags":[
        "rope",
        "industrial"
    ],
    "wof:name":"Continental Western Corp",
    "wof:placetype":"venue"
},
  "geometry": {"coordinates":[-104.850825,39.760281],"type":"Point"}
}