{
  "type": "Feature",
  "properties": {
    "addr:full":"6509 S Yukon St Littleton CO 80123",
    "addr:housenumber":"6509",
    "addr:postcode":"80123",
    "addr:street":"S Yukon St",
    "iso:country":"US",
    "sg:address":"6509 S Yukon St",
    "sg:city":"Littleton",
    "sg:classifiers":[
        {
            "category":"Banks & Credit Unions",
            "subcategory":"Bank",
            "type":"Services"
        }
    ],
    "sg:phone":"+1 303 948 9370",
    "sg:postcode":"80123",
    "sg:province":"CO",
    "sg:tags":[
        "loan",
        "real estate"
    ],
    "wof:name":"Advantage Mortgage Svc",
    "wof:placetype":"venue"
},
  "geometry": {"coordinates":[-105.08118899999999,39.598831],"type":"Point"}
}