{
  "type": "Feature",
  "properties": {
    "addr:full":"4195 S Cimarron Way Denver CO 80014",
    "addr:housenumber":"4195",
    "addr:postcode":"80014",
    "addr:street":"S Cimarron Way",
    "iso:country":"US",
    "sg:address":"4195 S Cimarron Way",
    "sg:city":"Denver",
    "sg:classifiers":[
        {
            "category":"Shopping",
            "subcategory":"Gifts & Souvenirs",
            "type":"Retail Goods"
        }
    ],
    "sg:phone":"+1 303 593 2052",
    "sg:postcode":"80014",
    "sg:province":"CO",
    "sg:tags":[
        "basket",
        "parcel"
    ],
    "wof:name":"Basket Wrap",
    "wof:placetype":"venue"
},
  "geometry": {"coordinates":[-104.82213299999999,39.640315],"type":"Point"}
}