{
  "type": "Feature",
  "properties": {
    "iso:country":"US",
    "sg:address":"786 Co Rd 116",
    "sg:city":"Glenwood Springs",
    "sg:classifiers":[
        {
            "category":"Airport",
            "type":"Transportation"
        }
    ],
    "sg:phone":"+1 970 945 2909",
    "sg:postcode":"81601",
    "sg:province":"CO",
    "sg:tags":[
        "nonscheduled",
        "air"
    ],
    "wof:name":"Premier Aviation Inc",
    "wof:placetype":"venue"
},
  "geometry": {"coordinates":[-107.31222099999999,39.505979],"type":"Point"}
}