{
  "type": "Feature",
  "properties": {
    "iso:country":"US",
    "sg:address":"1080 Kalamath St",
    "sg:city":"Denver",
    "sg:classifiers":[
        {
            "category":"Professional",
            "subcategory":"Lawyer & Legal Services",
            "type":"Services"
        }
    ],
    "sg:phone":"+1 303 302 2737",
    "sg:postcode":"80204",
    "sg:province":"CO",
    "sg:tags":[
        "attorney"
    ],
    "wof:name":"Dan Cross",
    "wof:placetype":"venue"
},
  "geometry": {"coordinates":[-105.000083,39.732382],"type":"Point"}
}