{
  "type": "Feature",
  "properties": {
    "addr:full":"3301 30th St Boulder CO 80301",
    "addr:housenumber":"3301",
    "addr:postcode":"80301",
    "addr:street":"30Th St",
    "iso:country":"US",
    "sg:address":"3301 30th St",
    "sg:city":"Boulder",
    "sg:classifiers":[
        {
            "category":"Real Estate",
            "subcategory":"Real Estate Agent",
            "type":"Services"
        }
    ],
    "sg:phone":"+1 303 442 7355",
    "sg:postcode":"80301",
    "sg:province":"CO",
    "wof:name":"Help-U-Sell Real Estate",
    "wof:placetype":"venue"
},
  "geometry": {"coordinates":[-105.253691,40.033744],"type":"Point"}
}