{
  "type": "Feature",
  "properties": {
    "addr:full":"12441 W 49th Ave Wheat Ridge CO 80033",
    "addr:housenumber":"12441",
    "addr:postcode":"80033",
    "addr:street":"W 49Th Ave",
    "iso:country":"US",
    "sg:address":"12441 W 49th Ave",
    "sg:city":"Wheat Ridge",
    "sg:classifiers":[
        {
            "category":"Professional",
            "subcategory":"Advertising",
            "type":"Services"
        }
    ],
    "sg:phone":"+1 303 422 5002",
    "sg:postcode":"80033",
    "sg:province":"CO",
    "sg:tags":[
        "mail",
        "direct"
    ],
    "wof:name":"Marketing Source",
    "wof:placetype":"venue"
},
  "geometry": {"coordinates":[-105.14159600000001,39.78611],"type":"Point"}
}