{
  "type": "Feature",
  "properties": {
    "iso:country":"US",
    "sg:address":"15010 Jessie Dr",
    "sg:city":"Colorado Springs",
    "sg:classifiers":[
        {
            "category":"Building & Trades",
            "subcategory":"Construction",
            "type":"Services"
        }
    ],
    "sg:phone":"+1 719 481 8600",
    "sg:postcode":"80921",
    "sg:province":"CO",
    "wof:name":"B L Kunkle Inc",
    "wof:placetype":"venue"
},
  "geometry": {"coordinates":[-104.82937699999999,39.051782],"type":"Point"}
}