{
  "type": "Feature",
  "properties": {
    "iso:country":"US",
    "sg:address":"7443 E Iliff Ave",
    "sg:city":"Denver",
    "sg:classifiers":[
        {
            "category":"Professional",
            "type":"Services"
        }
    ],
    "sg:phone":"+1 303 695 5065",
    "sg:postcode":"80231",
    "sg:province":"CO",
    "wof:name":"Cambios Colorado",
    "wof:placetype":"venue"
},
  "geometry": {"coordinates":[-104.901579,39.675194],"type":"Point"}
}