{
  "type": "Feature",
  "properties": {
    "iso:country":"US",
    "sg:address":"2589 49th St",
    "sg:city":"Evans",
    "sg:classifiers":[
        {
            "category":"Wholesale",
            "subcategory":"Auto Parts",
            "type":"Manufacturing & Wholesale Goods"
        }
    ],
    "sg:phone":"+1 970 339 3275",
    "sg:postcode":"80620",
    "sg:province":"CO",
    "sg:tags":[
        "automobile",
        "rebuilt"
    ],
    "wof:name":"A To Z Auto Salvage",
    "wof:placetype":"venue"
},
  "geometry": {"coordinates":[-104.71793599999999,40.363083],"type":"Point"}
}