{
  "type": "Feature",
  "properties": {
    "addr:full":"4390 Stove Prairie Rd Bellvue CO 80512",
    "addr:postcode":"4390;80512",
    "addr:street":"Prairie Rd",
    "iso:country":"US",
    "sg:address":"4390 Stove Prairie Rd",
    "sg:city":"Bellvue",
    "sg:classifiers":[
        {
            "category":"Manufacturing",
            "subcategory":"Building Materials",
            "type":"Manufacturing & Wholesale Goods"
        }
    ],
    "sg:phone":"+1 970 493 4755",
    "sg:postcode":"80512",
    "sg:province":"CO",
    "sg:tags":[
        "mfg",
        "household",
        "appliance",
        "cabinet",
        "wood",
        "kitchen"
    ],
    "sg:website":"www.stoveprairie.com",
    "wof:name":"Stove Prairie Woodworks",
    "wof:placetype":"venue"
},
  "geometry": {"coordinates":[-105.36545099999999,40.631909],"type":"Point"}
}