{
  "type": "Feature",
  "properties": {
    "iso:country":"US",
    "sg:address":"3623 E 89th Ave",
    "sg:city":"Denver",
    "sg:classifiers":[
        {
            "category":"Home & Garden",
            "subcategory":"Furniture",
            "type":"Retail Goods"
        }
    ],
    "sg:phone":"+1 303 289 4100",
    "sg:postcode":"80229",
    "sg:province":"CO",
    "sg:tags":[
        "household"
    ],
    "wof:name":"American Furniture Whse Co",
    "wof:placetype":"venue"
},
  "geometry": {"coordinates":[-104.943234,39.857983],"type":"Point"}
}