{
  "type": "Feature",
  "properties": {
    "iso:country":"US",
    "sg:address":"6291 Co Rd 318",
    "sg:city":"Ignacio",
    "sg:classifiers":[
        {
            "category":"Building & Trades",
            "subcategory":"Construction",
            "type":"Services"
        }
    ],
    "sg:phone":"+1 970 563 4680",
    "sg:postcode":"81137",
    "sg:province":"CO",
    "sg:tags":[
        "contractor"
    ],
    "wof:name":"Bos Best Masonry",
    "wof:placetype":"venue"
},
  "geometry": {"coordinates":[-107.688846,37.096932],"type":"Point"}
}