{
  "type": "Feature",
  "properties": {
    "iso:country":"US",
    "sg:address":"1575 E 4th Ave",
    "sg:city":"Denver",
    "sg:classifiers":[
        {
            "category":"Food & Beverages",
            "subcategory":"Groceries & Convenience Stores",
            "type":"Retail Goods"
        }
    ],
    "sg:phone":"+1 303 427 9176",
    "sg:postcode":"80218",
    "sg:province":"CO",
    "sg:tags":[
        "pharmacy"
    ],
    "wof:name":"King Soopers 34",
    "wof:placetype":"venue"
},
  "geometry": {"coordinates":[-104.96899999999999,39.722034],"type":"Point"}
}