{
  "type": "Feature",
  "properties": {
    "addr:full":"1525 E 30th Ave Denver CO 80205",
    "addr:housenumber":"1525",
    "addr:postcode":"80205",
    "addr:street":"E 30Th Ave",
    "iso:country":"US",
    "sg:address":"1525 E 30th Ave",
    "sg:city":"Denver",
    "sg:classifiers":[
        {
            "category":"Social Services",
            "subcategory":"Child Care",
            "type":"Services"
        }
    ],
    "sg:phone":"+1 303 292 0277",
    "sg:postcode":"80205",
    "sg:province":"CO",
    "wof:name":"Skills Preschool & Daycare Hm",
    "wof:placetype":"venue"
},
  "geometry": {"coordinates":[-104.968706,39.759568],"type":"Point"}
}