{
  "type": "Feature",
  "properties": {
    "iso:country":"US",
    "sg:address":"2547 Welton Street",
    "sg:city":"Denver",
    "sg:classifiers":[
        {
            "category":"Arts & Performance",
            "subcategory":"Art Gallery",
            "type":"Entertainment"
        }
    ],
    "sg:phone":"+1 303 382 1337",
    "sg:postcode":"80205",
    "sg:province":"CO",
    "wof:name":"Neat Stuff At Black Market",
    "wof:placetype":"venue"
},
  "geometry": {"coordinates":[-104.979958,39.753485],"type":"Point"}
}