{
  "type": "Feature",
  "properties": {
    "addr:full":"2119 W Northern Ave Pueblo CO 81004",
    "addr:housenumber":"2119",
    "addr:postcode":"81004",
    "addr:street":"W Northern Ave",
    "iso:country":"US",
    "sg:address":"2119 W Northern Ave",
    "sg:city":"Pueblo",
    "sg:classifiers":[
        {
            "category":"Personal",
            "subcategory":"Beauty Salon",
            "type":"Services"
        }
    ],
    "sg:phone":"+1 719 561 0073",
    "sg:postcode":"81004",
    "sg:province":"CO",
    "wof:name":"Mr Karl's Styling Salon",
    "wof:placetype":"venue"
},
  "geometry": {"coordinates":[-104.63617000000001,38.244159],"type":"Point"}
}