{
  "type": "Feature",
  "properties": {
    "addr:full":"2883 Bergen Hill Dr Evergreen CO 80439",
    "addr:housenumber":"2883",
    "addr:postcode":"80439",
    "addr:street":"Bergen Hill Dr",
    "iso:country":"US",
    "sg:address":"2883 Bergen Hill Dr",
    "sg:city":"Evergreen",
    "sg:classifiers":[
        {
            "category":"Manufacturing",
            "subcategory":"Metals",
            "type":"Manufacturing & Wholesale Goods"
        }
    ],
    "sg:phone":"+1 303 670 9809",
    "sg:postcode":"80439",
    "sg:province":"CO",
    "sg:tags":[
        "engraver"
    ],
    "wof:name":"Evergreen Engraving",
    "wof:placetype":"venue"
},
  "geometry": {"coordinates":[-105.347979,39.662442],"type":"Point"}
}