{
  "type": "Feature",
  "properties": {
    "addr:full":"3401 Worwick Dr Fort Collins CO 80525",
    "addr:housenumber":"3401",
    "addr:postcode":"80525",
    "addr:street":"Worwick Dr",
    "iso:country":"US",
    "sg:address":"3401 Worwick Dr",
    "sg:city":"Fort Collins",
    "sg:classifiers":[
        {
            "category":"Building & Trades",
            "subcategory":"Construction",
            "type":"Services"
        }
    ],
    "sg:phone":"+1 970 226 5913",
    "sg:postcode":"80525",
    "sg:province":"CO",
    "sg:tags":[
        "house"
    ],
    "wof:name":"Wilkens Home Improvement",
    "wof:placetype":"venue"
},
  "geometry": {"coordinates":[-105.06307200000001,40.538698],"type":"Point"}
}