{
  "type": "Feature",
  "properties": {
    "addr:full":"3333 S Wadsworth Blvd Denver CO 80227",
    "addr:housenumber":"3333",
    "addr:postcode":"80227",
    "addr:street":"S Wadsworth Blvd",
    "iso:country":"US",
    "sg:address":"3333 S Wadsworth Blvd",
    "sg:city":"Denver",
    "sg:classifiers":[
        {
            "category":"Wholesale",
            "subcategory":"Groceries",
            "type":"Manufacturing & Wholesale Goods"
        }
    ],
    "sg:phone":"+1 303 986 6240",
    "sg:postcode":"80227",
    "sg:province":"CO",
    "sg:tags":[
        "bakery",
        "retail"
    ],
    "wof:name":"Granny Scotts Gourmet Pie Shop",
    "wof:placetype":"venue"
},
  "geometry": {"coordinates":[-105.081413,39.65379],"type":"Point"}
}