{
  "type": "Feature",
  "properties": {
    "iso:country":"US",
    "sg:address":"3819 Inca St",
    "sg:city":"Denver",
    "sg:classifiers":[
        {
            "category":"Manufacturing",
            "subcategory":"Metals",
            "type":"Manufacturing & Wholesale Goods"
        }
    ],
    "sg:phone":"+1 303 455 9353",
    "sg:postcode":"80211",
    "sg:province":"CO",
    "sg:tags":[
        "tool"
    ],
    "sg:website":"www.releeco.com",
    "wof:name":"R E Lee Co",
    "wof:placetype":"venue"
},
  "geometry": {"coordinates":[-104.998273,39.770293],"type":"Point"}
}