{
  "type": "Feature",
  "properties": {
    "addr:full":"5251 Youngfield Way Arvada CO 80002",
    "addr:housenumber":"5251",
    "addr:postcode":"80002",
    "addr:street":"Youngfield Way",
    "iso:country":"US",
    "sg:address":"5251 Youngfield Way",
    "sg:city":"Arvada",
    "sg:classifiers":[
        {
            "category":"Wholesale",
            "subcategory":"Durable Goods & Equipment",
            "type":"Manufacturing & Wholesale Goods"
        }
    ],
    "sg:phone":"+1 303 456 4651",
    "sg:postcode":"80002",
    "sg:province":"CO",
    "wof:name":"Abbey Battle Wholesalers",
    "wof:placetype":"venue"
},
  "geometry": {"coordinates":[-105.14361,39.791524],"type":"Point"}
}