{
  "type": "Feature",
  "properties": {
    "addr:full":"1102 Walz Ave Glenwood Springs CO 81601",
    "addr:housenumber":"1102",
    "addr:postcode":"81601",
    "addr:street":"Walz Ave",
    "iso:country":"US",
    "sg:address":"1102 Walz Ave",
    "sg:city":"Glenwood Springs",
    "sg:classifiers":[
        {
            "category":"Real Estate",
            "subcategory":"Architect",
            "type":"Services"
        }
    ],
    "sg:phone":"+1 970 945 5882",
    "sg:postcode":"81601",
    "sg:province":"CO",
    "wof:name":"Sustainable Design",
    "wof:placetype":"venue"
},
  "geometry": {"coordinates":[-107.333676,39.543416],"type":"Point"}
}