{
  "type": "Feature",
  "properties": {
    "iso:country":"US",
    "sg:address":"3773 Cherry Creek North Dr",
    "sg:city":"Denver",
    "sg:classifiers":[
        {
            "category":"Insurance",
            "subcategory":"Insurance Agent",
            "type":"Services"
        }
    ],
    "sg:phone":"+1 303 331 3401",
    "sg:postcode":"80209",
    "sg:province":"CO",
    "wof:name":"HILL Galleries",
    "wof:placetype":"venue"
},
  "geometry": {"coordinates":[-104.942498,39.707777],"type":"Point"}
}