{
  "type": "Feature",
  "properties": {
    "addr:full":"5299 Dtc Blvd Greenwood Vlg CO 80111",
    "addr:housenumber":"5299",
    "addr:postcode":"co 80111",
    "addr:street":"Dtc Blvd",
    "iso:country":"US",
    "sg:address":"5299 Dtc Blvd",
    "sg:city":"Greenwood Vlg",
    "sg:classifiers":[
        {
            "category":"Insurance",
            "subcategory":"Insurance Agent",
            "type":"Services"
        }
    ],
    "sg:phone":"+1 303 771 5021",
    "sg:postcode":"80111",
    "sg:province":"CO",
    "wof:name":"American Family Insurance",
    "wof:placetype":"venue"
},
  "geometry": {"coordinates":[-104.88981699999999,39.620999],"type":"Point"}
}