{
  "type": "Feature",
  "properties": {
    "iso:country":"US",
    "sg:address":"2528 S College Ave",
    "sg:city":"Fort Collins",
    "sg:classifiers":[
        {
            "category":"Insurance",
            "subcategory":"Hazard Insurance",
            "type":"Services"
        }
    ],
    "sg:phone":"+1 970 484 4546",
    "sg:postcode":"80525",
    "sg:province":"CO",
    "sg:tags":[
        "carrier",
        "surety"
    ],
    "wof:name":"Bruce Associates",
    "wof:placetype":"venue"
},
  "geometry": {"coordinates":[-105.076919,40.554907],"type":"Point"}
}