{
  "type": "Feature",
  "properties": {
    "iso:country":"US",
    "sg:address":"4570 Ivy St Ste B-400",
    "sg:city":"Denver",
    "sg:classifiers":[
        {
            "category":"Shopping",
            "subcategory":"Pharmacy",
            "type":"Retail Goods"
        }
    ],
    "sg:phone":"+1 303 455 9490",
    "sg:postcode":"80216",
    "sg:province":"CO",
    "sg:tags":[
        "drugstore"
    ],
    "wof:name":"Central Admixture Pharmacy Services",
    "wof:placetype":"venue"
},
  "geometry": {"coordinates":[-104.92005,39.778664],"type":"Point"}
}