{
  "type": "Feature",
  "properties": {
    "addr:full":"3250 Van Teylingen Dr Colorado Springs CO 80917",
    "addr:housenumber":"3250",
    "addr:postcode":"80917",
    "addr:street":"Van Teylingen Dr",
    "iso:country":"US",
    "sg:address":"3250 Van Teylingen Dr",
    "sg:city":"Colorado Springs",
    "sg:classifiers":[
        {
            "category":"Freight",
            "type":"Transportation"
        }
    ],
    "sg:phone":"+1 719 573 5467",
    "sg:postcode":"80917",
    "sg:province":"CO",
    "wof:name":"Secure Assisted Transport",
    "wof:placetype":"venue"
},
  "geometry": {"coordinates":[-104.761335,38.877566],"type":"Point"}
}