{
  "type": "Feature",
  "properties": {
    "addr:full":"3200 S Wadsworth Blvd Lakewood CO 80227",
    "addr:housenumber":"3200",
    "addr:postcode":"80227",
    "addr:street":"S Wadsworth Blvd",
    "iso:country":"US",
    "sg:address":"3200 S Wadsworth Blvd",
    "sg:city":"Lakewood",
    "sg:classifiers":[
        {
            "category":"Health Services",
            "subcategory":"Doctor",
            "type":"Services"
        }
    ],
    "sg:phone":"+1 303 716 8546",
    "sg:postcode":"80227",
    "sg:province":"CO",
    "sg:tags":[
        "dentist"
    ],
    "wof:name":"Comfort Dental",
    "wof:placetype":"venue"
},
  "geometry": {"coordinates":[-105.08134099999999,39.655798],"type":"Point"}
}