{
  "type": "Feature",
  "properties": {
    "addr:full":"2232 S Colorado Boulevard Denver CO 80222",
    "addr:housenumber":"2232",
    "addr:postcode":"80222",
    "addr:street":"S Colorado Boulevard",
    "iso:country":"US",
    "sg:address":"2232 S Colorado Boulevard",
    "sg:city":"Denver",
    "sg:classifiers":[
        {
            "category":"Personal",
            "subcategory":"Beauty Salon",
            "type":"Services"
        }
    ],
    "sg:phone":"+1 303 782 5690",
    "sg:postcode":"80222",
    "sg:province":"CO",
    "sg:tags":[
        "hair"
    ],
    "wof:name":"Fancy Shears",
    "wof:placetype":"venue"
},
  "geometry": {"coordinates":[-104.94076099999999,39.676129],"type":"Point"}
}