{
  "type": "Feature",
  "properties": {
    "iso:country":"US",
    "sg:address":"1005 W Stuart St",
    "sg:city":"Fort Collins",
    "sg:classifiers":[
        {
            "category":"Retail",
            "subcategory":"Laundry & Dry Cleaning",
            "type":"Services"
        }
    ],
    "sg:phone":"+1 970 482 9661",
    "sg:postcode":"80526",
    "sg:province":"CO",
    "sg:tags":[
        "cleaners"
    ],
    "wof:name":"Palumbo Dry Cleaners",
    "wof:placetype":"venue"
},
  "geometry": {"coordinates":[-105.09719200000001,40.56354],"type":"Point"}
}