{
  "type": "Feature",
  "properties": {
    "iso:country":"US",
    "sg:address":"5750 W 10th St",
    "sg:city":"Greeley",
    "sg:classifiers":[
        {
            "category":"Food & Beverages",
            "subcategory":"Liquor & Beverages",
            "type":"Retail Goods"
        }
    ],
    "sg:phone":"+1 970 356 1233",
    "sg:postcode":"80634",
    "sg:province":"CO",
    "sg:tags":[
        "alcoholic"
    ],
    "wof:name":"McRey LLC",
    "wof:placetype":"venue"
},
  "geometry": {"coordinates":[-104.773997,40.421222],"type":"Point"}
}