{
  "type": "Feature",
  "properties": {
    "addr:full":"215 E Foothills Pkwy Fort Collins CO 80525",
    "addr:housenumber":"215",
    "addr:postcode":"80525",
    "addr:street":"E Foothills Pkwy",
    "iso:country":"US",
    "sg:address":"215 E Foothills Pkwy",
    "sg:city":"Fort Collins",
    "sg:classifiers":[
        {
            "category":"Food & Beverages",
            "subcategory":"Specialty",
            "type":"Retail Goods"
        },
        {
            "category":"Restaurant",
            "type":"Food & Drink"
        }
    ],
    "sg:phone":"+1 970 223 0300",
    "sg:postcode":"80525",
    "sg:province":"CO",
    "sg:tags":[
        "tea",
        "coffee",
        "eating"
    ],
    "wof:name":"Colorado Coffee Exchange",
    "wof:placetype":"venue"
},
  "geometry": {"coordinates":[-105.07463300000001,40.543772],"type":"Point"}
}