{
  "type": "Feature",
  "properties": {
    "addr:full":"1580 Pine Grove Rd Steamboat Spgs CO 80487",
    "addr:housenumber":"1580",
    "addr:postcode":"80487",
    "addr:street":"Pine Grove Rd Steamboat Spgs",
    "iso:country":"US",
    "sg:address":"1580 Pine Grove Rd",
    "sg:city":"Steamboat Spgs",
    "sg:classifiers":[
        {
            "category":"Manufacturing",
            "subcategory":"Tools & Machinery",
            "type":"Manufacturing & Wholesale Goods"
        }
    ],
    "sg:phone":"+1 970 879 4355",
    "sg:postcode":"80487",
    "sg:province":"CO",
    "sg:tags":[
        "forming",
        "metal"
    ],
    "wof:name":"Hampden Industries LTD",
    "wof:placetype":"venue"
},
  "geometry": {"coordinates":[-106.821913,40.464769],"type":"Point"}
}