{
  "type": "Feature",
  "properties": {
    "addr:full":"4836 S College Ave Fort Collins CO 80525",
    "addr:housenumber":"4836",
    "addr:postcode":"80525",
    "addr:street":"S College Ave",
    "iso:country":"US",
    "sg:address":"4836 S College Ave",
    "sg:city":"Fort Collins",
    "sg:classifiers":[
        {
            "category":"Utilities",
            "type":"Services"
        }
    ],
    "sg:phone":"+1 970 494 1610",
    "sg:postcode":"80525",
    "sg:province":"CO",
    "sg:tags":[
        "water",
        "waste",
        "treatment"
    ],
    "wof:name":"Alberts Water & Wastewater Svc",
    "wof:placetype":"venue"
},
  "geometry": {"coordinates":[-105.077067,40.520708],"type":"Point"}
}