{
  "type": "Feature",
  "properties": {
    "iso:country":"US",
    "sg:address":"1500 W Thornton Pkwy",
    "sg:city":"Denver",
    "sg:classifiers":[
        {
            "category":"Building & Trades",
            "subcategory":"Plumbing",
            "type":"Services"
        }
    ],
    "sg:phone":"+1 303 428 1498",
    "sg:postcode":"80260",
    "sg:province":"CO",
    "sg:tags":[
        "conditioning",
        "air",
        "system",
        "contractor"
    ],
    "wof:name":"CMS Air Conditioning",
    "wof:placetype":"venue"
},
  "geometry": {"coordinates":[-105.00599699999999,39.863489],"type":"Point"}
}