{
  "type": "Feature",
  "properties": {
    "addr:full":"6312 S Fiddlers Green Cir Englewood CO 80111",
    "addr:housenumber":"6312",
    "addr:postcode":"80111",
    "addr:street":"S Fiddlers Green Cir",
    "iso:country":"US",
    "sg:address":"6312 S Fiddlers Green Cir",
    "sg:city":"Englewood",
    "sg:classifiers":[
        {
            "category":"Insurance",
            "subcategory":"Life Insurance",
            "type":"Services"
        }
    ],
    "sg:phone":"+1 303 689 0700",
    "sg:postcode":"80111",
    "sg:province":"CO",
    "sg:tags":[
        "mutual"
    ],
    "wof:name":"Mutual of Omaha",
    "wof:placetype":"venue"
},
  "geometry": {"coordinates":[-104.890475,39.60152],"type":"Point"}
}