{
  "type": "Feature",
  "properties": {
    "iso:country":"US",
    "sg:address":"353 D Ave",
    "sg:city":"Limon",
    "sg:classifiers":[
        {
            "category":"Professional",
            "subcategory":"Accounting & Tax Preparation",
            "type":"Services"
        }
    ],
    "sg:phone":"+1 719 775 9890",
    "sg:postcode":"80828",
    "sg:province":"CO",
    "sg:tags":[
        "accountant"
    ],
    "wof:name":"Hiner-Felzien Tax Preparation",
    "wof:placetype":"venue"
},
  "geometry": {"coordinates":[-103.686622,39.263876],"type":"Point"}
}