{
  "type": "Feature",
  "properties": {
    "iso:country":"US",
    "sg:address":"8201 S I- 25",
    "sg:city":"Pueblo",
    "sg:classifiers":[
        {
            "category":"Manufacturing",
            "subcategory":"Lumber",
            "type":"Manufacturing & Wholesale Goods"
        }
    ],
    "sg:phone":"+1 719 676 6120",
    "sg:postcode":"81082",
    "sg:province":"CO",
    "sg:tags":[
        "forestry"
    ],
    "wof:name":"Timberline Tree Seed",
    "wof:placetype":"venue"
},
  "geometry": {"coordinates":[-104.524372,37.104287],"type":"Point"}
}