{
  "type": "Feature",
  "properties": {
    "iso:country":"US",
    "sg:address":"10730 E Bethany Dr",
    "sg:city":"Aurora",
    "sg:classifiers":[
        {
            "category":"Professional",
            "subcategory":"Management & Consulting",
            "type":"Services"
        }
    ],
    "sg:phone":"+1 303 752 8144",
    "sg:postcode":"80014",
    "sg:province":"CO",
    "sg:tags":[
        "consultant",
        "business"
    ],
    "wof:name":"Enterprise Systems Consulting",
    "wof:placetype":"venue"
},
  "geometry": {"coordinates":[-104.864328,39.66263],"type":"Point"}
}