{
  "type": "Feature",
  "properties": {
    "iso:country":"US",
    "sg:address":"295 E 29th St",
    "sg:city":"Loveland",
    "sg:classifiers":[
        {
            "category":"Professional",
            "type":"Services"
        }
    ],
    "sg:phone":"+1 970 278 1538",
    "sg:postcode":"80538",
    "sg:province":"CO",
    "wof:name":"Ten Foundation",
    "wof:placetype":"venue"
},
  "geometry": {"coordinates":[-105.073303,40.421799],"type":"Point"}
}