{
  "type": "Feature",
  "properties": {
    "addr:full":"465 Old Wagon Rd Woodland Park CO 80863",
    "addr:housenumber":"465",
    "addr:postcode":"80863",
    "addr:street":"Old Wagon Rd",
    "iso:country":"US",
    "sg:address":"465 Old Wagon Rd",
    "sg:city":"Woodland Park",
    "sg:classifiers":[
        {
            "category":"Wholesale",
            "subcategory":"Vending Machines",
            "type":"Manufacturing & Wholesale Goods"
        }
    ],
    "sg:phone":"+1 719 495 2405",
    "sg:postcode":"80863",
    "sg:province":"CO",
    "sg:tags":[
        "operated",
        "phonograph"
    ],
    "wof:name":"Classic Jukebox & Game Co",
    "wof:placetype":"venue"
},
  "geometry": {"coordinates":[-105.05048499999999,38.979801],"type":"Point"}
}