{
  "type": "Feature",
  "properties": {
    "iso:country":"US",
    "sg:address":"1822 Skyway Dr",
    "sg:city":"Longmont",
    "sg:classifiers":[
        {
            "category":"Building & Trades",
            "subcategory":"Plumbing",
            "type":"Services"
        }
    ],
    "sg:phone":"+1 720 494 0899",
    "sg:postcode":"80504",
    "sg:province":"CO",
    "sg:tags":[
        "plumbing",
        "contractor"
    ],
    "wof:name":"Noah Plumbing & Heating",
    "wof:placetype":"venue"
},
  "geometry": {"coordinates":[-105.021286,40.158084],"type":"Point"}
}