{
  "type": "Feature",
  "properties": {
    "iso:country":"US",
    "sg:address":"155 N Co Rd 157",
    "sg:city":"Strasburg",
    "sg:classifiers":[
        {
            "category":"Professional",
            "subcategory":"Management & Consulting",
            "type":"Services"
        }
    ],
    "sg:phone":"+1 303 622 9588",
    "sg:postcode":"80136",
    "sg:province":"CO",
    "sg:tags":[
        "retail",
        "direct",
        "sales"
    ],
    "wof:name":"Doyle Lord Promotions",
    "wof:placetype":"venue"
},
  "geometry": {"coordinates":[-104.321753,39.711668],"type":"Point"}
}