{
  "type": "Feature",
  "properties": {
    "addr:full":"690 Pennsylvania St Denver CO 80203",
    "addr:housenumber":"690",
    "addr:postcode":"80203",
    "addr:street":"Pennsylvania St",
    "iso:country":"US",
    "sg:address":"690 Pennsylvania St",
    "sg:city":"Denver",
    "sg:classifiers":[
        {
            "category":"Health Services",
            "subcategory":"Clinic",
            "type":"Services"
        }
    ],
    "sg:phone":"+1 303 861 2543",
    "sg:postcode":"80203",
    "sg:province":"CO",
    "wof:name":"Poli Health Inc",
    "wof:placetype":"venue"
},
  "geometry": {"coordinates":[-104.98105700000001,39.725768],"type":"Point"}
}