{
  "type": "Feature",
  "properties": {
    "iso:country":"US",
    "sg:address":"267 E 29th St",
    "sg:city":"Loveland",
    "sg:classifiers":[
        {
            "category":"Professional",
            "type":"Services"
        }
    ],
    "sg:phone":"+1 970 622 9448",
    "sg:postcode":"80538",
    "sg:province":"CO",
    "wof:name":"Propaq",
    "wof:placetype":"venue"
},
  "geometry": {"coordinates":[-105.073673,40.421786],"type":"Point"}
}