{
  "type": "Feature",
  "properties": {
    "addr:full":"3801 Tennyson St Denver CO 80238",
    "addr:housenumber":"3801",
    "addr:postcode":"80238",
    "addr:street":"Tennyson St",
    "iso:country":"US",
    "sg:address":"3801 Tennyson St",
    "sg:city":"Denver",
    "sg:classifiers":[
        {
            "category":"Restaurant",
            "type":"Food & Drink"
        }
    ],
    "sg:phone":"+1 303 433 4005",
    "sg:postcode":"80238",
    "sg:province":"CO",
    "sg:tags":[
        "diner"
    ],
    "wof:name":"Javier & C Diner",
    "wof:placetype":"venue"
},
  "geometry": {"coordinates":[-105.04402899999999,39.769485],"type":"Point"}
}