{
  "type": "Feature",
  "properties": {
    "iso:country":"US",
    "sg:address":"1652 Franklin St",
    "sg:city":"Denver",
    "sg:classifiers":[
        {
            "category":"Health Services",
            "subcategory":"Doctor",
            "type":"Services"
        }
    ],
    "sg:phone":"+1 303 321 7965",
    "sg:postcode":"80218",
    "sg:province":"CO",
    "sg:tags":[
        "clinic",
        "medical"
    ],
    "wof:name":"People of Colr Cnsrt Agnstaids",
    "wof:placetype":"venue"
},
  "geometry": {"coordinates":[-104.968372,39.742387],"type":"Point"}
}