{
  "type": "Feature",
  "properties": {
    "addr:full":"9335 Ralston Rd Arvada CO 80002",
    "addr:housenumber":"9335",
    "addr:postcode":"80002",
    "addr:street":"Ralston Rd",
    "iso:country":"US",
    "sg:address":"9335 Ralston Rd",
    "sg:city":"Arvada",
    "sg:classifiers":[
        {
            "category":"Professional",
            "subcategory":"Accounting & Tax Preparation",
            "type":"Services"
        }
    ],
    "sg:phone":"+1 720 898 4600",
    "sg:postcode":"80002",
    "sg:province":"CO",
    "sg:tags":[
        "return",
        "filing"
    ],
    "wof:name":"Jackson Hewitt Tax Svc",
    "wof:placetype":"venue"
},
  "geometry": {"coordinates":[-105.101445,39.802128],"type":"Point"}
}