{
  "type": "Feature",
  "properties": {
    "iso:country":"US",
    "sg:address":"105 Village Ln",
    "sg:city":"Snowmass Village",
    "sg:classifiers":[
        {
            "category":"Building & Trades",
            "subcategory":"Construction",
            "type":"Services"
        }
    ],
    "sg:phone":"+1 970 923 6224",
    "sg:postcode":"81623",
    "sg:province":"CO",
    "sg:tags":[
        "contractor"
    ],
    "wof:name":"Timbermill Building",
    "wof:placetype":"venue"
},
  "geometry": {"coordinates":[-107.222572,39.400375],"type":"Point"}
}