{
  "type": "Feature",
  "properties": {
    "iso:country":"US",
    "sg:address":"2960 Hwy 394",
    "sg:city":"Craig",
    "sg:classifiers":[
        {
            "category":"Retail",
            "subcategory":"Repair Shop",
            "type":"Services"
        }
    ],
    "sg:phone":"+1 970 824 4087",
    "sg:postcode":"81625",
    "sg:province":"CO",
    "sg:tags":[
        "welding"
    ],
    "wof:name":"Western Welding & Fabrication",
    "wof:placetype":"venue"
},
  "geometry": {"coordinates":[-107.525164,40.492225],"type":"Point"}
}