{
  "type": "Feature",
  "properties": {
    "iso:country":"US",
    "sg:address":"135 W Colorado Ave",
    "sg:city":"Telluride",
    "sg:classifiers":[
        {
            "category":"Health Services",
            "subcategory":"Doctor",
            "type":"Services"
        }
    ],
    "sg:phone":"+1 970 728 6654",
    "sg:postcode":"81435",
    "sg:province":"CO",
    "sg:tags":[
        "physician",
        "surgeon"
    ],
    "wof:name":"Telluride Family Practice",
    "wof:placetype":"venue"
},
  "geometry": {"coordinates":[-107.81157399999999,37.93746],"type":"Point"}
}