{
  "type": "Feature",
  "properties": {
    "iso:country":"US",
    "sg:address":"234 Lead King Dr",
    "sg:city":"Castle Rock",
    "sg:classifiers":[
        {
            "category":"Banks & Credit Unions",
            "subcategory":"Investment Brokerage",
            "type":"Services"
        }
    ],
    "sg:phone":"+1 303 660 0333",
    "sg:postcode":"80108",
    "sg:province":"CO",
    "wof:name":"Livingston Investments",
    "wof:placetype":"venue"
},
  "geometry": {"coordinates":[-104.911252,39.446737],"type":"Point"}
}