{
  "type": "Feature",
  "properties": {
    "addr:full":"78786 US-40 Winter Park CO 80482",
    "addr:housenumber":"78786",
    "addr:postcode":"80482",
    "addr:street":"Us-40",
    "iso:country":"US",
    "sg:address":"78786 US-40",
    "sg:city":"Winter Park",
    "sg:classifiers":[
        {
            "category":"Restaurant",
            "type":"Food & Drink"
        }
    ],
    "sg:menulink":"http://www.allmenus.com/co/granby/276580-gasthaus-eichler-restaurant/menu/",
    "sg:phone":"+1 970 726 5133",
    "sg:postcode":"80482",
    "sg:province":"CO",
    "sg:tags":[
        "mediterranean"
    ],
    "wof:name":"Gasthaus Eichler Restaurant",
    "wof:placetype":"venue"
},
  "geometry": {"coordinates":[-105.785538,39.92018],"type":"Point"}
}