{
  "type": "Feature",
  "properties": {
    "iso:country":"US",
    "sg:address":"207 Rocky Cliff Trl",
    "sg:city":"Franktown",
    "sg:classifiers":[
        {
            "category":"Professional",
            "subcategory":"Business Services",
            "type":"Services"
        }
    ],
    "sg:phone":"+1 303 660 5015",
    "sg:postcode":"80116",
    "sg:province":"CO",
    "wof:name":"Brnd",
    "wof:placetype":"venue"
},
  "geometry": {"coordinates":[-104.670261,39.366278],"type":"Point"}
}