{
  "type": "Feature",
  "properties": {
    "iso:country":"US",
    "sg:address":"1130 W 127th Ct",
    "sg:city":"Denver",
    "sg:classifiers":[
        {
            "category":"Manufacturing",
            "subcategory":"Toys & Sporting Goods",
            "type":"Manufacturing & Wholesale Goods"
        }
    ],
    "sg:phone":"+1 303 460 0257",
    "sg:postcode":"80234",
    "sg:province":"CO",
    "sg:tags":[
        "mfg"
    ],
    "wof:name":"Photon Golf Inc",
    "wof:placetype":"venue"
},
  "geometry": {"coordinates":[-104.999245,39.927032],"type":"Point"}
}