{
  "type": "Feature",
  "properties": {
    "addr:full":"3816 S Taft Hill Rd Fort Collins CO 80526",
    "addr:housenumber":"3816",
    "addr:postcode":"80526",
    "addr:street":"S Taft Hill Rd",
    "iso:country":"US",
    "sg:address":"3816 S Taft Hill Rd",
    "sg:city":"Fort Collins",
    "sg:classifiers":[
        {
            "category":"Building & Trades",
            "subcategory":"Construction",
            "type":"Services"
        }
    ],
    "sg:phone":"+1 970 226 3666",
    "sg:postcode":"80526",
    "sg:province":"CO",
    "sg:tags":[
        "welding",
        "contractor"
    ],
    "wof:name":"Alliance Welding & Machine",
    "wof:placetype":"venue"
},
  "geometry": {"coordinates":[-105.115064,40.534961],"type":"Point"}
}