{
  "type": "Feature",
  "properties": {
    "iso:country":"US",
    "sg:address":"716 Walsen Ave",
    "sg:city":"Walsenburg",
    "sg:classifiers":[
        {
            "category":"Travel",
            "subcategory":"Hotels & Motels",
            "type":"Entertainment"
        }
    ],
    "sg:phone":"+1 719 738 3705",
    "sg:postcode":"81089",
    "sg:province":"CO",
    "wof:name":"Moon Glow Inn",
    "wof:placetype":"venue"
},
  "geometry": {"coordinates":[-104.789169,37.634971],"type":"Point"}
}