{
  "type": "Feature",
  "properties": {
    "addr:full":"9545 E Hidden Hill Ln Littleton CO 80124",
    "addr:housenumber":"9545",
    "addr:postcode":"80124",
    "addr:street":"E Hidden Hill Ln",
    "iso:country":"US",
    "sg:address":"9545 E Hidden Hill Ln",
    "sg:city":"Littleton",
    "sg:classifiers":[
        {
            "category":"Autos & Motor Vehicles",
            "subcategory":"Automobile Sales",
            "type":"Retail Goods"
        }
    ],
    "sg:phone":"+1 303 858 1976",
    "sg:postcode":"80124",
    "sg:province":"CO",
    "sg:tags":[
        "used"
    ],
    "wof:name":"Hyde Park Auto Brokers",
    "wof:placetype":"venue"
},
  "geometry": {"coordinates":[-104.878603,39.547575],"type":"Point"}
}