{
  "type": "Feature",
  "properties": {
    "addr:full":"2363 Fairplay St Aurora CO 80011",
    "addr:housenumber":"2363",
    "addr:postcode":"80011",
    "addr:street":"Fairplay St",
    "iso:country":"US",
    "sg:address":"2363 Fairplay St",
    "sg:city":"Aurora",
    "sg:classifiers":[
        {
            "category":"Building & Trades",
            "subcategory":"Construction",
            "type":"Services"
        }
    ],
    "sg:phone":"+1 303 364 2756",
    "sg:postcode":"80011",
    "sg:province":"CO",
    "sg:tags":[
        "home",
        "builder"
    ],
    "wof:name":"Anita's Western Framing Inc",
    "wof:placetype":"venue"
},
  "geometry": {"coordinates":[-104.813451,39.751521],"type":"Point"}
}