{
  "type": "Feature",
  "properties": {
    "addr:full":"8 W Dry Creek Cir Littleton CO 80120",
    "addr:housenumber":"8",
    "addr:postcode":"80120",
    "addr:street":"Dry Creek Cir",
    "iso:country":"US",
    "sg:address":"8 W Dry Creek Cir",
    "sg:city":"Littleton",
    "sg:classifiers":[
        {
            "category":"Banks & Credit Unions",
            "subcategory":"Investment Brokerage",
            "type":"Services"
        }
    ],
    "sg:phone":"+1 720 283 2260",
    "sg:postcode":"80120",
    "sg:province":"CO",
    "sg:tags":[
        "security"
    ],
    "wof:name":"Edward Jones Co",
    "wof:placetype":"venue"
},
  "geometry": {"coordinates":[-104.98969700000001,39.581929],"type":"Point"}
}