{
  "type": "Feature",
  "properties": {
    "iso:country":"US",
    "sg:address":"1900 Grant St Ste 820",
    "sg:city":"Denver",
    "sg:classifiers":[
        {
            "category":"Professional",
            "subcategory":"Lawyer & Legal Services",
            "type":"Services"
        }
    ],
    "sg:phone":"+1 303 837 9000",
    "sg:postcode":"80203",
    "sg:province":"CO",
    "wof:name":"Thompson Julia T Atty",
    "wof:placetype":"venue"
},
  "geometry": {"coordinates":[-104.982002,39.732899],"type":"Point"}
}