{
  "type": "Feature",
  "properties": {
    "addr:full":"1160 Rowena St Denver CO 80229",
    "addr:housenumber":"1160",
    "addr:postcode":"80229",
    "addr:street":"Rowena St",
    "iso:country":"US",
    "sg:address":"1160 Rowena St",
    "sg:city":"Denver",
    "sg:classifiers":[
        {
            "category":"Restaurant",
            "type":"Food & Drink"
        }
    ],
    "sg:phone":"+1 303 320 1553",
    "sg:postcode":"80229",
    "sg:province":"CO",
    "sg:tags":[
        "eating"
    ],
    "wof:name":"Subway",
    "wof:placetype":"venue"
},
  "geometry": {"coordinates":[-104.968632,39.869378],"type":"Point"}
}