{
  "type": "Feature",
  "properties": {
    "iso:country":"US",
    "sg:address":"707 S Main St",
    "sg:city":"Yuma",
    "sg:classifiers":[
        {
            "category":"Building & Trades",
            "subcategory":"Construction",
            "type":"Services"
        }
    ],
    "sg:phone":"+1 970 848 3342",
    "sg:postcode":"80759",
    "sg:province":"CO",
    "sg:tags":[
        "insulation",
        "heat",
        "contractor"
    ],
    "wof:name":"Hillman Insulation & Urethane",
    "wof:placetype":"venue"
},
  "geometry": {"coordinates":[-102.723769,40.119344],"type":"Point"}
}