{
  "type": "Feature",
  "properties": {
    "iso:country":"US",
    "sg:address":"125 Blue Grouse Ln",
    "sg:city":"Silverthorne",
    "sg:classifiers":[
        {
            "category":"Banks & Credit Unions",
            "subcategory":"Bank",
            "type":"Services"
        }
    ],
    "sg:phone":"+1 970 513 9944",
    "sg:postcode":"80498",
    "sg:province":"CO",
    "sg:tags":[
        "loan",
        "real estate"
    ],
    "wof:name":"Mortgage Works Inc",
    "wof:placetype":"venue"
},
  "geometry": {"coordinates":[-106.081847,39.653514],"type":"Point"}
}