{
  "type": "Feature",
  "properties": {
    "iso:country":"US",
    "sg:address":"1050 Walnut St",
    "sg:city":"Windsor",
    "sg:classifiers":[
        {
            "category":"Manufacturing",
            "subcategory":"Printing",
            "type":"Manufacturing & Wholesale Goods"
        }
    ],
    "sg:phone":"+1 970 686 0174",
    "sg:postcode":"80550",
    "sg:province":"CO",
    "sg:tags":[
        "me",
        "commercial",
        "design"
    ],
    "wof:name":"Huston Graphics & Printing",
    "wof:placetype":"venue"
},
  "geometry": {"coordinates":[-104.915404,40.475719],"type":"Point"}
}