{
  "type": "Feature",
  "properties": {
    "addr:full":"55084 Co Rd L Yuma CO 80759",
    "addr:housenumber":"55084",
    "addr:postcode":"80759",
    "addr:street":"Co Rd",
    "iso:country":"US",
    "sg:address":"55084 Co Rd L",
    "sg:city":"Yuma",
    "sg:classifiers":[
        {
            "category":"Farming",
            "subcategory":"Livestock Farm",
            "type":"Manufacturing & Wholesale Goods"
        }
    ],
    "sg:phone":"+1 970 848 2705",
    "sg:postcode":"80759",
    "sg:province":"CO",
    "sg:tags":[
        "hog",
        "or",
        "feedlot"
    ],
    "wof:name":"Kenton Farms",
    "wof:placetype":"venue"
},
  "geometry": {"coordinates":[-102.62639,40.365906],"type":"Point"}
}