{
  "type": "Feature",
  "properties": {
    "iso:country":"US",
    "sg:address":"705 E Simpson St",
    "sg:city":"Lafayette",
    "sg:classifiers":[
        {
            "category":"Building & Trades",
            "subcategory":"Construction",
            "type":"Services"
        }
    ],
    "sg:phone":"+1 303 666 0236",
    "sg:postcode":"80026",
    "sg:province":"CO",
    "sg:tags":[
        "dry wall",
        "contractor"
    ],
    "wof:name":"Johns Drywall Svc",
    "wof:placetype":"venue"
},
  "geometry": {"coordinates":[-105.07975500000001,39.998308],"type":"Point"}
}