{
  "type": "Feature",
  "properties": {
    "iso:country":"US",
    "sg:address":"3342 Ponderosa Dr",
    "sg:city":"Ridgway",
    "sg:classifiers":[
        {
            "category":"Building & Trades",
            "subcategory":"Construction",
            "type":"Services"
        }
    ],
    "sg:phone":"+1 970 626 3852",
    "sg:postcode":"81432",
    "sg:province":"CO",
    "sg:tags":[
        "hanging",
        "contractor"
    ],
    "wof:name":"Kirby Painting & Bldg Contg",
    "wof:placetype":"venue"
},
  "geometry": {"coordinates":[-107.76765,38.203079],"type":"Point"}
}