{
  "type": "Feature",
  "properties": {
    "addr:full":"20 Emmons Rd Crested Butte CO 81225",
    "addr:housenumber":"20",
    "addr:postcode":"81225",
    "addr:street":"Emmons Rd",
    "iso:country":"US",
    "sg:address":"20 Emmons Rd",
    "sg:city":"Crested Butte",
    "sg:classifiers":[
        {
            "category":"Real Estate",
            "subcategory":"Real Estate Agent",
            "type":"Services"
        }
    ],
    "sg:phone":"+1 970 349 6692",
    "sg:postcode":"81225",
    "sg:province":"CO",
    "wof:name":"Prudential Becky Hamlin Realty",
    "wof:placetype":"venue"
},
  "geometry": {"coordinates":[-106.967113,38.902162],"type":"Point"}
}