{
  "type": "Feature",
  "properties": {
    "iso:country":"US",
    "sg:address":"825 Garner St",
    "sg:city":"Colorado Springs",
    "sg:classifiers":[
        {
            "category":"Retail",
            "subcategory":"Auto Repair",
            "type":"Services"
        }
    ],
    "sg:phone":"+1 719 520 9943",
    "sg:postcode":"80905",
    "sg:province":"CO",
    "sg:tags":[
        "glass",
        "coating",
        "tinting"
    ],
    "wof:name":"Colorado Springs Windowtint",
    "wof:placetype":"venue"
},
  "geometry": {"coordinates":[-104.840954,38.829144],"type":"Point"}
}