{
  "type": "Feature",
  "properties": {
    "iso:country":"US",
    "sg:address":"4275 S Broadway",
    "sg:city":"Englewood",
    "sg:classifiers":[
        {
            "category":"Organizations",
            "subcategory":"Religious Organization",
            "type":"Services"
        }
    ],
    "sg:phone":"+1 303 761 5005",
    "sg:postcode":"80113",
    "sg:province":"CO",
    "sg:tags":[
        "counseling"
    ],
    "sg:website":"www.shepherdinggrace.org",
    "wof:name":"Cupbearers Inc",
    "wof:placetype":"venue"
},
  "geometry": {"coordinates":[-104.987882,39.639919],"type":"Point"}
}