{
  "type": "Feature",
  "properties": {
    "iso:country":"US",
    "sg:address":"9546 Saint Paul St",
    "sg:city":"Thornton",
    "sg:classifiers":[
        {
            "category":"Retail",
            "subcategory":"Car Wash",
            "type":"Services"
        }
    ],
    "sg:phone":"+1 303 853 0960",
    "sg:postcode":"80229",
    "sg:province":"CO",
    "sg:tags":[
        "automobile",
        "detail",
        "clean"
    ],
    "wof:name":"Denver's Finest Auto Detailing",
    "wof:placetype":"venue"
},
  "geometry": {"coordinates":[-104.951663,39.870316],"type":"Point"}
}