{
  "type": "Feature",
  "properties": {
    "addr:full":"1109 Oak Park Dr Fort Collins CO 80525",
    "addr:housenumber":"1109",
    "addr:postcode":"80525",
    "addr:street":"Oak Park Dr",
    "iso:country":"US",
    "sg:address":"1109 Oak Park Dr",
    "sg:city":"Fort Collins",
    "sg:classifiers":[
        {
            "category":"Local Transit",
            "type":"Transportation"
        },
        {
            "category":"Insurance",
            "subcategory":"Insurance Agent",
            "type":"Services"
        }
    ],
    "sg:phone":"+1 970 223 1804",
    "sg:postcode":"80525",
    "sg:province":"CO",
    "sg:tags":[
        "limousine"
    ],
    "wof:name":"Front Range Insurance Group",
    "wof:placetype":"venue"
},
  "geometry": {"coordinates":[-105.05423,40.519874],"type":"Point"}
}