{
  "type": "Feature",
  "properties": {
    "iso:country":"US",
    "sg:address":"360 Interlocken Blvd",
    "sg:city":"Broomfield",
    "sg:classifiers":[
        {
            "category":"Social Services",
            "subcategory":"Adult Care",
            "type":"Services"
        }
    ],
    "sg:phone":"+1 303 871 8201",
    "sg:postcode":"80021",
    "sg:province":"CO",
    "sg:tags":[
        "foster"
    ],
    "wof:name":"Casey Family Program",
    "wof:placetype":"venue"
},
  "geometry": {"coordinates":[-105.11139900000001,39.922088],"type":"Point"}
}