{
  "type": "Feature",
  "properties": {
    "iso:country":"US",
    "sg:address":"5232 W Geddes Pl",
    "sg:city":"Littleton",
    "sg:classifiers":[
        {
            "category":"Building & Trades",
            "subcategory":"Construction",
            "type":"Services"
        }
    ],
    "sg:phone":"+1 303 523 7434",
    "sg:postcode":"80128",
    "sg:province":"CO",
    "sg:tags":[
        "general",
        "contractor"
    ],
    "wof:name":"Cragar Construction",
    "wof:placetype":"venue"
},
  "geometry": {"coordinates":[-105.056549,39.582979],"type":"Point"}
}