{
  "type": "Feature",
  "properties": {
    "iso:country":"US",
    "sg:address":"225 E Goddard Ave",
    "sg:city":"Trinidad",
    "sg:classifiers":[
        {
            "category":"Building & Trades",
            "subcategory":"Construction",
            "type":"Services"
        }
    ],
    "sg:phone":"+1 719 680 1714",
    "sg:postcode":"81082",
    "sg:province":"CO",
    "sg:tags":[
        "restoration",
        "cleaning",
        "patio",
        "deck"
    ],
    "wof:name":"Power Wash Pros",
    "wof:placetype":"venue"
},
  "geometry": {"coordinates":[-104.50735299999999,37.184369],"type":"Point"}
}