{
  "type": "Feature",
  "properties": {
    "iso:country":"US",
    "sg:address":"5003 Fossil Blvd",
    "sg:city":"Fort Collins",
    "sg:classifiers":[
        {
            "category":"Wholesale",
            "subcategory":"Hardware",
            "type":"Manufacturing & Wholesale Goods"
        }
    ],
    "sg:phone":"+1 970 204 1450",
    "sg:postcode":"80525",
    "sg:province":"CO",
    "sg:tags":[
        "plumbing",
        "fixture",
        "supply"
    ],
    "wof:name":"George T Sanders Company",
    "wof:placetype":"venue"
},
  "geometry": {"coordinates":[-105.079752,40.517715],"type":"Point"}
}