{
  "type": "Feature",
  "properties": {
    "iso:country":"US",
    "sg:address":"1090 S Wadsworth Blvd",
    "sg:city":"Denver",
    "sg:classifiers":[
        {
            "category":"Utilities",
            "subcategory":"Mobile Phone",
            "type":"Services"
        },
        {
            "category":"Shopping",
            "type":"Retail Goods"
        }
    ],
    "sg:phone":"+1 303 937 0430",
    "sg:postcode":"80226",
    "sg:province":"CO",
    "sg:tags":[
        "pager",
        "telephone",
        "cellular"
    ],
    "wof:name":"Wizard Communications Inc",
    "wof:placetype":"venue"
},
  "geometry": {"coordinates":[-105.081433,39.69842],"type":"Point"}
}