{
  "type": "Feature",
  "properties": {
    "iso:country":"US",
    "sg:address":"2102 9th St",
    "sg:city":"Greeley",
    "sg:classifiers":[
        {
            "category":"Autos & Motor Vehicles",
            "subcategory":"Auto Supplies",
            "type":"Retail Goods"
        }
    ],
    "sg:phone":"+1 970 351 8603",
    "sg:postcode":"80631",
    "sg:province":"CO",
    "sg:tags":[
        "four",
        "wheel",
        "drive",
        "accessory"
    ],
    "wof:name":"CRP Truck Accessories",
    "wof:placetype":"venue"
},
  "geometry": {"coordinates":[-104.712794,40.424059],"type":"Point"}
}