{
  "type": "Feature",
  "properties": {
    "iso:country":"US",
    "sg:address":"6722 E 47th Ave Dr",
    "sg:city":"Denver",
    "sg:classifiers":[
        {
            "category":"Communications",
            "type":"Services"
        }
    ],
    "sg:phone":"+1 303 227 0700",
    "sg:postcode":"80216",
    "sg:province":"CO",
    "sg:tags":[
        "medium",
        "mass"
    ],
    "sg:website":"www.rockymountainmail.justgoodbu...",
    "wof:name":"Rocky Mountain Mail Services",
    "wof:placetype":"venue"
},
  "geometry": {"coordinates":[-104.909339,39.782404],"type":"Point"}
}