{
  "type": "Feature",
  "properties": {
    "iso:country":"US",
    "sg:address":"4766 Sutton St",
    "sg:city":"Castle Rock",
    "sg:classifiers":[
        {
            "category":"Professional",
            "subcategory":"Accounting & Tax Preparation",
            "type":"Services"
        }
    ],
    "sg:phone":"+1 720 733 1011",
    "sg:postcode":"80104",
    "sg:province":"CO",
    "sg:tags":[
        "payroll"
    ],
    "wof:name":"Payroll Benefits & Solutions",
    "wof:placetype":"venue"
},
  "geometry": {"coordinates":[-104.812496,39.366073],"type":"Point"}
}