{
  "type": "Feature",
  "properties": {
    "addr:full":"770 Meadowdale Ln Canon City CO 81212",
    "addr:housenumber":"770",
    "addr:postcode":"81212",
    "addr:street":"Meadowdale Ln",
    "iso:country":"US",
    "sg:address":"770 Meadowdale Ln",
    "sg:city":"Canon City",
    "sg:classifiers":[
        {
            "category":"Home & Garden",
            "subcategory":"Furniture",
            "type":"Retail Goods"
        }
    ],
    "sg:phone":"+1 719 276 0754",
    "sg:postcode":"81212",
    "sg:province":"CO",
    "wof:name":"Davis Designs",
    "wof:placetype":"venue"
},
  "geometry": {"coordinates":[-105.381208,38.477676],"type":"Point"}
}