{
  "type": "Feature",
  "properties": {
    "iso:country":"US",
    "sg:address":"319 S Meldrum St",
    "sg:city":"Fort Collins",
    "sg:classifiers":[
        {
            "category":"Banks & Credit Unions",
            "subcategory":"Bank",
            "type":"Services"
        }
    ],
    "sg:phone":"+1 970 221 1261",
    "sg:postcode":"80521",
    "sg:province":"CO",
    "sg:website":"www.norlarco.com",
    "wof:name":"Cuna Mutual-Cumis Inc Society",
    "wof:placetype":"venue"
},
  "geometry": {"coordinates":[-105.08259200000001,40.583129],"type":"Point"}
}