{
  "type": "Feature",
  "properties": {
    "iso:country":"US",
    "sg:address":"227 Oak Ave",
    "sg:city":"Paonia",
    "sg:classifiers":[
        {
            "category":"Wholesale",
            "subcategory":"Machinery & Supplies",
            "type":"Manufacturing & Wholesale Goods"
        },
        {
            "category":"Wholesale",
            "subcategory":"Farm Supplies",
            "type":"Manufacturing & Wholesale Goods"
        }
    ],
    "sg:phone":"+1 970 527 3987",
    "sg:postcode":"81428",
    "sg:province":"CO",
    "sg:tags":[
        "equipment",
        "trade",
        "livestock",
        "contractor"
    ],
    "wof:name":"Elk & Bison Co",
    "wof:placetype":"venue"
},
  "geometry": {"coordinates":[-107.590746,38.867383],"type":"Point"}
}