{
  "type": "Feature",
  "properties": {
    "addr:full":"2275 E Arapahoe Rd Centennial CO 80122",
    "addr:housenumber":"2275",
    "addr:postcode":"80122",
    "addr:street":"E Arapahoe Rd",
    "iso:country":"US",
    "sg:address":"2275 E Arapahoe Rd",
    "sg:city":"Centennial",
    "sg:classifiers":[
        {
            "category":"Insurance",
            "subcategory":"Insurance Agent",
            "type":"Services"
        }
    ],
    "sg:phone":"+1 303 795 5874",
    "sg:postcode":"80122",
    "sg:province":"CO",
    "wof:name":"Chris Maupin",
    "wof:placetype":"venue"
},
  "geometry": {"coordinates":[-104.96159,39.595249],"type":"Point"}
}