{
  "type": "Feature",
  "properties": {
    "iso:country":"US",
    "sg:address":"4525 Broadway St",
    "sg:city":"Boulder",
    "sg:classifiers":[
        {
            "category":"Retail",
            "subcategory":"Animal Services",
            "type":"Services"
        }
    ],
    "sg:phone":"+1 303 443 7297",
    "sg:postcode":"80304",
    "sg:province":"CO",
    "wof:name":"Paws & Claws Too Inc",
    "wof:placetype":"venue"
},
  "geometry": {"coordinates":[-105.28220399999999,40.057952],"type":"Point"}
}