{
  "type": "Feature",
  "properties": {
    "addr:full":"46500 Co Rd 4 Roggen CO 80652",
    "addr:housenumber":"46500",
    "addr:postcode":"80652",
    "addr:street":"Co Rd 4 Roggen",
    "iso:country":"US",
    "sg:address":"46500 Co Rd 4",
    "sg:city":"Roggen",
    "sg:classifiers":[
        {
            "category":"Farming",
            "subcategory":"Farm",
            "type":"Manufacturing & Wholesale Goods"
        }
    ],
    "sg:phone":"+1 303 849 5343",
    "sg:postcode":"80652",
    "sg:province":"CO",
    "sg:tags":[
        "crop",
        "general"
    ],
    "wof:name":"INA Farms",
    "wof:placetype":"venue"
},
  "geometry": {"coordinates":[-104.176479,40.015081],"type":"Point"}
}