{
  "type": "Feature",
  "properties": {
    "addr:full":"10452 Washington Way Denver CO 80233",
    "addr:housenumber":"10452",
    "addr:postcode":"80233",
    "addr:street":"Washington Way",
    "iso:country":"US",
    "sg:address":"10452 Washington Way",
    "sg:city":"Denver",
    "sg:classifiers":[
        {
            "category":"Building & Trades",
            "subcategory":"Electrical",
            "type":"Services"
        }
    ],
    "sg:phone":"+1 303 453 0469",
    "sg:postcode":"80233",
    "sg:province":"CO",
    "sg:tags":[
        "electrical",
        "contractor"
    ],
    "wof:name":"Amerimax Electric",
    "wof:placetype":"venue"
},
  "geometry": {"coordinates":[-104.979816,39.887791],"type":"Point"}
}