{
  "type": "Feature",
  "properties": {
    "addr:full":"791 Stone Creek Dr Avon CO 81620",
    "addr:housenumber":"791",
    "addr:postcode":"81620",
    "addr:street":"Stone Creek Dr",
    "iso:country":"US",
    "sg:address":"791 Stone Creek Dr",
    "sg:city":"Avon",
    "sg:classifiers":[
        {
            "category":"Manufacturing",
            "subcategory":"Tools & Machinery",
            "type":"Manufacturing & Wholesale Goods"
        }
    ],
    "sg:phone":"+1 970 949 1882",
    "sg:postcode":"81620",
    "sg:province":"CO",
    "sg:tags":[
        "equipment",
        "electric"
    ],
    "wof:name":"Starboard Electric-Sabina",
    "wof:placetype":"venue"
},
  "geometry": {"coordinates":[-106.49491,39.622452],"type":"Point"}
}