{
  "type": "Feature",
  "properties": {
    "iso:country":"US",
    "sg:address":"2370 S Kalamath St",
    "sg:city":"Denver",
    "sg:classifiers":[
        {
            "category":"Manufacturing",
            "subcategory":"Apparel",
            "type":"Manufacturing & Wholesale Goods"
        }
    ],
    "sg:phone":"+1 303 922 7130",
    "sg:postcode":"80223",
    "sg:province":"CO",
    "sg:tags":[
        "manufacture",
        "curtain",
        "drapery"
    ],
    "wof:name":"Precision Draperies Inc",
    "wof:placetype":"venue"
},
  "geometry": {"coordinates":[-105.000539,39.674341],"type":"Point"}
}