{
  "type": "Feature",
  "properties": {
    "iso:country":"US",
    "sg:address":"2409 Abeyta Ct",
    "sg:city":"Loveland",
    "sg:classifiers":[
        {
            "category":"Professional",
            "type":"Services"
        }
    ],
    "sg:phone":"+1 970 667 3829",
    "sg:postcode":"80538",
    "sg:province":"CO",
    "wof:name":"Jeremy Bloom Inc",
    "wof:placetype":"venue"
},
  "geometry": {"coordinates":[-105.097992,40.415003],"type":"Point"}
}