{
  "type": "Feature",
  "properties": {
    "addr:full":"3 Industrial Park Johnstown CO 80534",
    "addr:housenumber":"3",
    "addr:postcode":"80534",
    "addr:street":"Industrial Park",
    "iso:country":"US",
    "sg:address":"3 Industrial Park",
    "sg:city":"Johnstown",
    "sg:classifiers":[
        {
            "category":"Manufacturing",
            "subcategory":"Rubber & Plastics",
            "type":"Manufacturing & Wholesale Goods"
        }
    ],
    "sg:phone":"+1 970 587 2746",
    "sg:postcode":"80534",
    "sg:province":"CO",
    "wof:name":"Mountain States Plastics Inc",
    "wof:placetype":"venue"
},
  "geometry": {"coordinates":[-104.904101,40.336051],"type":"Point"}
}