{
  "type": "Feature",
  "properties": {
    "iso:country":"US",
    "sg:address":"999 Jasmine St",
    "sg:city":"Denver",
    "sg:classifiers":[
        {
            "category":"Building & Trades",
            "subcategory":"Locksmith",
            "type":"Services"
        }
    ],
    "sg:phone":"+1 303 242 3179",
    "sg:postcode":"80220",
    "sg:province":"CO",
    "sg:tags":[
        "key"
    ],
    "wof:name":"Ronaldo's Emergency Locksmith 1 Hr Service",
    "wof:placetype":"venue"
},
  "geometry": {"coordinates":[-104.918538,39.73167],"type":"Point"}
}