{
  "type": "Feature",
  "properties": {
    "addr:full":"6427 Co Rd 44 Fort Collins CO 80524",
    "addr:housenumber":"6427;44",
    "addr:postcode":"80524",
    "addr:street":"Co Rd",
    "iso:country":"US",
    "sg:address":"6427 Co Rd 44",
    "sg:city":"Fort Collins",
    "sg:classifiers":[
        {
            "category":"Retail",
            "subcategory":"Veterinary Services",
            "type":"Services"
        }
    ],
    "sg:phone":"+1 970 472 1268",
    "sg:postcode":"80524",
    "sg:province":"CO",
    "wof:name":"Stacie Wells Dvm",
    "wof:placetype":"venue"
},
  "geometry": {"coordinates":[-104.95707400000001,40.566292],"type":"Point"}
}