{
  "type": "Feature",
  "properties": {
    "addr:full":"3618 E Euclid Ave Littleton CO 80121",
    "addr:housenumber":"3618",
    "addr:postcode":"80121",
    "addr:street":"E Euclid Ave",
    "iso:country":"US",
    "sg:address":"3618 E Euclid Ave",
    "sg:city":"Littleton",
    "sg:classifiers":[
        {
            "category":"Autos & Motor Vehicles",
            "subcategory":"Motorcycle Sales",
            "type":"Retail Goods"
        }
    ],
    "sg:phone":"+1 303 689 9000",
    "sg:postcode":"80121",
    "sg:province":"CO",
    "wof:name":"Andover Cycles Sons",
    "wof:placetype":"venue"
},
  "geometry": {"coordinates":[-104.946112,39.595891],"type":"Point"}
}