{
  "type": "Feature",
  "properties": {
    "addr:full":"332 3rd St Kersey CO 80644",
    "addr:housenumber":"332",
    "addr:postcode":"80644",
    "addr:street":"3Rd St",
    "iso:country":"US",
    "sg:address":"332 3rd St",
    "sg:city":"Kersey",
    "sg:classifiers":[
        {
            "category":"Government",
            "subcategory":"Office",
            "type":"Public Place"
        }
    ],
    "sg:phone":"+1 970 353 1681",
    "sg:postcode":"80644",
    "sg:province":"CO",
    "sg:tags":[
        "city"
    ],
    "wof:name":"Kersey Town Clerk",
    "wof:placetype":"venue"
},
  "geometry": {"coordinates":[-104.56194499999999,40.387531],"type":"Point"}
}