{
  "type": "Feature",
  "properties": {
    "iso:country":"US",
    "sg:address":"1553 Platte St.",
    "sg:city":"Denver",
    "sg:classifiers":[
        {
            "category":"Professional",
            "subcategory":"Computer Services",
            "type":"Services"
        }
    ],
    "sg:phone":"+1 888 979 6769",
    "sg:postcode":"80202",
    "sg:province":"CO",
    "sg:tags":[
        "online-learning",
        "e-learning",
        "online-education",
        "virtual-education",
        "virtual-learning",
        "online-learning-platform"
    ],
    "sg:website":"http://sympoz.com",
    "wof:name":"Sympoz",
    "wof:placetype":"venue"
},
  "geometry": {"coordinates":[-105.00868699999999,39.75695],"type":"Point"}
}