{
  "type": "Feature",
  "properties": {
    "addr:full":"240 5th St Greeley CO 80631",
    "addr:housenumber":"240",
    "addr:postcode":"80631",
    "addr:street":"5Th St",
    "iso:country":"US",
    "sg:address":"240 5th St",
    "sg:city":"Greeley",
    "sg:classifiers":[
        {
            "category":"Wholesale",
            "subcategory":"Machinery & Supplies",
            "type":"Manufacturing & Wholesale Goods"
        }
    ],
    "sg:phone":"+1 970 356 3666",
    "sg:postcode":"80631",
    "sg:province":"CO",
    "sg:tags":[
        "farm",
        "equipment"
    ],
    "sg:website":"www.bi-statemachinery.com",
    "wof:name":"Bi-State Machinery Co",
    "wof:placetype":"venue"
},
  "geometry": {"coordinates":[-104.679389,40.428661],"type":"Point"}
}