{
  "type": "Feature",
  "properties": {
    "iso:country":"US",
    "sg:address":"4775 Barnes Rd",
    "sg:city":"Colorado Springs",
    "sg:classifiers":[
        {
            "category":"Insurance",
            "subcategory":"Insurance Agent",
            "type":"Services"
        }
    ],
    "sg:phone":"+1 719 597 5100",
    "sg:postcode":"80917",
    "sg:province":"CO",
    "wof:name":"State Farm Insurance",
    "wof:placetype":"venue"
},
  "geometry": {"coordinates":[-104.740095,38.896923],"type":"Point"}
}