{
  "type": "Feature",
  "properties": {
    "iso:country":"US",
    "sg:address":"36118 Hwy 133",
    "sg:city":"Hotchkiss",
    "sg:classifiers":[
        {
            "category":"Professional",
            "type":"Services"
        }
    ],
    "sg:phone":"+1 970 527 6335",
    "sg:postcode":"81419",
    "sg:province":"CO",
    "wof:name":"Ronald D Geisler",
    "wof:placetype":"venue"
},
  "geometry": {"coordinates":[-107.688762,38.822408],"type":"Point"}
}