{
  "type": "Feature",
  "properties": {
    "iso:country":"US",
    "sg:address":"13310 W Coal Mine Ave",
    "sg:city":"Littleton",
    "sg:classifiers":[
        {
            "category":"Real Estate",
            "subcategory":"Real Estate Operator",
            "type":"Services"
        }
    ],
    "sg:phone":"+1 303 723 5100",
    "sg:postcode":"80127",
    "sg:province":"CO",
    "sg:tags":[
        "apartment"
    ],
    "wof:name":"Archstone-Smith",
    "wof:placetype":"venue"
},
  "geometry": {"coordinates":[-105.14585099999999,39.600112],"type":"Point"}
}