{
  "type": "Feature",
  "properties": {
    "addr:full":"1817 Summernight Ter Colorado Springs CO 80909",
    "addr:housenumber":"1817",
    "addr:postcode":"80909",
    "addr:street":"Summernight Ter",
    "iso:country":"US",
    "sg:address":"1817 Summernight Ter",
    "sg:city":"Colorado Springs",
    "sg:classifiers":[
        {
            "category":"Home & Garden",
            "subcategory":"Building Materials",
            "type":"Retail Goods"
        }
    ],
    "sg:phone":"+1 719 574 7333",
    "sg:postcode":"80909",
    "sg:province":"CO",
    "wof:name":"Angel Fire Glass Co",
    "wof:placetype":"venue"
},
  "geometry": {"coordinates":[-104.751783,38.860192],"type":"Point"}
}