{
  "type": "Feature",
  "properties": {
    "addr:full":"1701 Howard Ave Rifle CO 81650",
    "addr:housenumber":"1701",
    "addr:postcode":"81650",
    "addr:street":"Howard Ave",
    "iso:country":"US",
    "sg:address":"1701 Howard Ave",
    "sg:city":"Rifle",
    "sg:classifiers":[
        {
            "category":"Freight",
            "type":"Transportation"
        }
    ],
    "sg:phone":"+1 970 625 9238",
    "sg:postcode":"81650",
    "sg:province":"CO",
    "sg:tags":[
        "special"
    ],
    "wof:name":"Winchester West Mini-Storage",
    "wof:placetype":"venue"
},
  "geometry": {"coordinates":[-107.78574500000001,39.546203],"type":"Point"}
}