{
  "type": "Feature",
  "properties": {
    "addr:full":"2135 Broadway St Colorado Springs CO 80904",
    "addr:housenumber":"2135",
    "addr:postcode":"80904",
    "addr:street":"Broadway St",
    "iso:country":"US",
    "sg:address":"2135 Broadway St",
    "sg:city":"Colorado Springs",
    "sg:classifiers":[
        {
            "category":"Freight",
            "type":"Transportation"
        }
    ],
    "sg:phone":"+1 719 447 0754",
    "sg:postcode":"80904",
    "sg:province":"CO",
    "sg:tags":[
        "general"
    ],
    "wof:name":"Garden of The Gods Visitor Ctr",
    "wof:placetype":"venue"
},
  "geometry": {"coordinates":[-104.861509,38.837237],"type":"Point"}
}