{
  "type": "Feature",
  "properties": {
    "addr:full":"805 N Murray Blvd Colorado Springs CO 80915",
    "addr:housenumber":"805",
    "addr:postcode":"80915",
    "addr:street":"N Murray Blvd",
    "iso:country":"US",
    "sg:address":"805 N Murray Blvd",
    "sg:city":"Colorado Springs",
    "sg:classifiers":[
        {
            "category":"Banks & Credit Unions",
            "subcategory":"Bank",
            "type":"Services"
        }
    ],
    "sg:phone":"+1 719 574 1100",
    "sg:postcode":"80915",
    "sg:province":"CO",
    "sg:website":"www.entfederal.com",
    "wof:name":"ENT Federal Credit Union",
    "wof:placetype":"venue"
},
  "geometry": {"coordinates":[-104.747972,38.844065],"type":"Point"}
}