{
  "type": "Feature",
  "properties": {
    "iso:country":"US",
    "sg:address":"1984 K Rd",
    "sg:city":"Fruita",
    "sg:classifiers":[
        {
            "category":"Professional",
            "subcategory":"Management & Consulting",
            "type":"Services"
        }
    ],
    "sg:phone":"+1 970 858 7871",
    "sg:postcode":"81521",
    "sg:province":"CO",
    "sg:tags":[
        "counselor",
        "public",
        "relations"
    ],
    "wof:name":"Diversions Public Relations",
    "wof:placetype":"venue"
},
  "geometry": {"coordinates":[-108.68320799999999,39.164339],"type":"Point"}
}