{
  "type": "Feature",
  "properties": {
    "iso:country":"US",
    "sg:address":"2434 Arapahoe Ave",
    "sg:city":"Boulder",
    "sg:classifiers":[
        {
            "category":"Health Services",
            "subcategory":"Clinic",
            "type":"Services"
        }
    ],
    "sg:phone":"+1 303 447 1040",
    "sg:postcode":"80302",
    "sg:province":"CO",
    "sg:tags":[
        "parenthood",
        "planned"
    ],
    "wof:name":"Planned Parenthood",
    "wof:placetype":"venue"
},
  "geometry": {"coordinates":[-105.258825,40.014478],"type":"Point"}
}