{
  "type": "Feature",
  "properties": {
    "addr:full":"370 17th St Denver CO 80202",
    "addr:housenumber":"370",
    "addr:postcode":"80202",
    "addr:street":"17Th St",
    "iso:country":"US",
    "sg:address":"370 17th St",
    "sg:city":"Denver",
    "sg:classifiers":[
        {
            "category":"Professional",
            "subcategory":"Lawyer & Legal Services",
            "type":"Services"
        }
    ],
    "sg:phone":"+1 303 628 1504",
    "sg:postcode":"80202",
    "sg:province":"CO",
    "wof:name":"Scott W Doyle",
    "wof:placetype":"venue"
},
  "geometry": {"coordinates":[-104.987827,39.743516],"type":"Point"}
}