{
  "type": "Feature",
  "properties": {
    "addr:full":"2293 S Peoria St Aurora CO 80014",
    "addr:housenumber":"2293",
    "addr:postcode":"80014",
    "addr:street":"S Peoria St",
    "iso:country":"US",
    "sg:address":"2293 S Peoria St",
    "sg:city":"Aurora",
    "sg:classifiers":[
        {
            "category":"Retail",
            "subcategory":"Laundry & Dry Cleaning",
            "type":"Services"
        },
        {
            "category":"Personal",
            "subcategory":"Shoe Repair & Shine",
            "type":"Services"
        }
    ],
    "sg:phone":"+1 303 671 8244",
    "sg:postcode":"80014",
    "sg:province":"CO",
    "sg:tags":[
        "cleaners",
        "parlor"
    ],
    "wof:name":"Kim's Cleaner & Shoe Repair",
    "wof:placetype":"venue"
},
  "geometry": {"coordinates":[-104.84718700000001,39.676485],"type":"Point"}
}