{
  "type": "Feature",
  "properties": {
    "addr:full":"1281 E 120th Ave Denver CO 80233",
    "addr:housenumber":"1281",
    "addr:postcode":"80233",
    "addr:street":"E 120Th Ave",
    "iso:country":"US",
    "sg:address":"1281 E 120th Ave",
    "sg:city":"Denver",
    "sg:classifiers":[
        {
            "category":"Personal",
            "subcategory":"Beauty Salon",
            "type":"Services"
        }
    ],
    "sg:phone":"+1 303 453 1199",
    "sg:postcode":"80233",
    "sg:province":"CO",
    "wof:name":"HCX Hair Color Xperts",
    "wof:placetype":"venue"
},
  "geometry": {"coordinates":[-104.967939,39.91392],"type":"Point"}
}