{
  "type": "Feature",
  "properties": {
    "iso:country":"US",
    "sg:address":"5485 Conestoga Ct",
    "sg:city":"Boulder",
    "sg:classifiers":[
        {
            "category":"Professional",
            "subcategory":"Engineering",
            "type":"Services"
        }
    ],
    "sg:phone":"+1 303 415 1112",
    "sg:postcode":"80301",
    "sg:province":"CO",
    "sg:tags":[
        "consulting"
    ],
    "wof:name":"Electronic Product Design Inc",
    "wof:placetype":"venue"
},
  "geometry": {"coordinates":[-105.227672,40.016457],"type":"Point"}
}