{
  "type": "Feature",
  "properties": {
    "addr:full":"1745 Main St Longmont CO 80501",
    "addr:housenumber":"1745",
    "addr:postcode":"80501",
    "addr:street":"Main St",
    "iso:country":"US",
    "sg:address":"1745 Main St",
    "sg:city":"Longmont",
    "sg:classifiers":[
        {
            "category":"Professional",
            "subcategory":"Accounting & Tax Preparation",
            "type":"Services"
        }
    ],
    "sg:phone":"+1 303 776 7521",
    "sg:postcode":"80501",
    "sg:province":"CO",
    "sg:tags":[
        "return",
        "filing"
    ],
    "wof:name":"H & R Block Tax Svc",
    "wof:placetype":"venue"
},
  "geometry": {"coordinates":[-105.10234800000001,40.19219],"type":"Point"}
}