{
  "type": "Feature",
  "properties": {
    "iso:country":"US",
    "sg:address":"1380 W 100th Ave",
    "sg:city":"Denver",
    "sg:classifiers":[
        {
            "category":"Wholesale",
            "subcategory":"Machinery & Supplies",
            "type":"Manufacturing & Wholesale Goods"
        }
    ],
    "sg:phone":"+1 303 451 5534",
    "sg:postcode":"80260",
    "sg:province":"CO",
    "sg:tags":[
        "wholesaler",
        "equipment",
        "safety"
    ],
    "wof:name":"Mountain Industrial Sales",
    "wof:placetype":"venue"
},
  "geometry": {"coordinates":[-105.00409999999999,39.878531],"type":"Point"}
}