{
  "type": "Feature",
  "properties": {
    "addr:full":"3602 S Quintero St Aurora CO 80013",
    "addr:housenumber":"3602",
    "addr:postcode":"80013",
    "addr:street":"S Quintero St",
    "iso:country":"US",
    "sg:address":"3602 S Quintero St",
    "sg:city":"Aurora",
    "sg:classifiers":[
        {
            "category":"Building & Trades",
            "subcategory":"Cleaning & Sanitation",
            "type":"Services"
        }
    ],
    "sg:phone":"+1 303 986 8123",
    "sg:postcode":"80013",
    "sg:province":"CO",
    "sg:tags":[
        "janitor"
    ],
    "wof:name":"Jet Cleaning Svc",
    "wof:placetype":"venue"
},
  "geometry": {"coordinates":[-104.787499,39.651058],"type":"Point"}
}