{
  "type": "Feature",
  "properties": {
    "iso:country":"US",
    "sg:address":"104 S 1st St",
    "sg:city":"Montrose",
    "sg:classifiers":[
        {
            "category":"Banks & Credit Unions",
            "subcategory":"Investment Brokerage",
            "type":"Services"
        }
    ],
    "sg:phone":"+1 970 240 0369",
    "sg:postcode":"81401",
    "sg:province":"CO",
    "sg:tags":[
        "security"
    ],
    "wof:name":"Financial West Group",
    "wof:placetype":"venue"
},
  "geometry": {"coordinates":[-107.87795800000001,38.477104],"type":"Point"}
}