{
  "type": "Feature",
  "properties": {
    "iso:country":"US",
    "sg:address":"932 Walnut St",
    "sg:city":"Louisville",
    "sg:classifiers":[
        {
            "category":"Real Estate",
            "subcategory":"Real Estate Agent",
            "type":"Services"
        }
    ],
    "sg:phone":"+1 303 665 3000",
    "sg:postcode":"80027",
    "sg:province":"CO",
    "wof:name":"Richardson & Associates Realty",
    "wof:placetype":"venue"
},
  "geometry": {"coordinates":[-105.131125,39.978639],"type":"Point"}
}