{
  "type": "Feature",
  "properties": {
    "iso:country":"US",
    "sg:address":"3110 Poe Pl",
    "sg:city":"Colorado Springs",
    "sg:classifiers":[
        {
            "category":"Freight",
            "type":"Transportation"
        }
    ],
    "sg:phone":"+1 719 661 7354",
    "sg:postcode":"80910",
    "sg:province":"CO",
    "sg:tags":[
        "mover"
    ],
    "wof:name":"Helping Hands Moving",
    "wof:placetype":"venue"
},
  "geometry": {"coordinates":[-104.75167999999999,38.826367],"type":"Point"}
}