{
  "type": "Feature",
  "properties": {
    "iso:country":"US",
    "sg:address":"7585 W Arkansas Ave Ste B",
    "sg:city":"Lakewood",
    "sg:classifiers":[
        {
            "category":"Health Services",
            "subcategory":"Chiropractor",
            "type":"Services"
        }
    ],
    "sg:phone":"+1 303 984 9570",
    "sg:postcode":"80232",
    "sg:province":"CO",
    "wof:name":"Weiser Chiropractic Center",
    "wof:placetype":"venue"
},
  "geometry": {"coordinates":[-105.08200100000001,39.691502],"type":"Point"}
}