{
  "type": "Feature",
  "properties": {
    "iso:country":"US",
    "sg:address":"361 Woodstock Ln",
    "sg:city":"Castle Rock",
    "sg:classifiers":[
        {
            "category":"Wholesale",
            "subcategory":"Apparel",
            "type":"Manufacturing & Wholesale Goods"
        }
    ],
    "sg:phone":"+1 303 663 7353",
    "sg:postcode":"80108",
    "sg:province":"CO",
    "sg:tags":[
        "outerwear"
    ],
    "wof:name":"Belfe USA",
    "wof:placetype":"venue"
},
  "geometry": {"coordinates":[-104.891515,39.474634],"type":"Point"}
}