{
  "type": "Feature",
  "properties": {
    "addr:full":"8442 Urban Ct Arvada CO 80005",
    "addr:housenumber":"8442",
    "addr:postcode":"80005",
    "addr:street":"Urban Ct",
    "iso:country":"US",
    "sg:address":"8442 Urban Ct",
    "sg:city":"Arvada",
    "sg:classifiers":[
        {
            "category":"Professional",
            "type":"Services"
        }
    ],
    "sg:phone":"+1 303 424 3158",
    "sg:postcode":"80005",
    "sg:province":"CO",
    "wof:name":"Envision Project Support LLC",
    "wof:placetype":"venue"
},
  "geometry": {"coordinates":[-105.13751499999999,39.850814],"type":"Point"}
}