{
  "type": "Feature",
  "properties": {
    "iso:country":"US",
    "sg:address":"2705 Lafayette St",
    "sg:city":"Denver",
    "sg:classifiers":[
        {
            "category":"Real Estate",
            "subcategory":"Real Estate Agent",
            "type":"Services"
        }
    ],
    "sg:phone":"+1 303 295 3815",
    "sg:postcode":"80205",
    "sg:province":"CO",
    "wof:name":"Palmer Real Estate",
    "wof:placetype":"venue"
},
  "geometry": {"coordinates":[-104.970974,39.756929],"type":"Point"}
}