{
  "type": "Feature",
  "properties": {
    "iso:country":"US",
    "sg:address":"3703 Windsor Ave",
    "sg:city":"Colorado Springs",
    "sg:classifiers":[
        {
            "category":"Real Estate",
            "subcategory":"Real Estate Agent",
            "type":"Services"
        }
    ],
    "sg:phone":"+1 719 633 8387",
    "sg:postcode":"80907",
    "sg:province":"CO",
    "wof:name":"Veterans Properties Of America",
    "wof:placetype":"venue"
},
  "geometry": {"coordinates":[-104.79498700000001,38.885872],"type":"Point"}
}