{
  "type": "Feature",
  "properties": {
    "iso:country":"US",
    "sg:address":"1549 E Bridge St",
    "sg:city":"Brighton",
    "sg:classifiers":[
        {
            "category":"Retail",
            "subcategory":"Laundry & Dry Cleaning",
            "type":"Services"
        }
    ],
    "sg:phone":"+1 303 659 1663",
    "sg:postcode":"80601",
    "sg:province":"CO",
    "sg:tags":[
        "drycleaning",
        "plant"
    ],
    "wof:name":"High Country Cleaners",
    "wof:placetype":"venue"
},
  "geometry": {"coordinates":[-104.801484,39.986867],"type":"Point"}
}