{
  "type": "Feature",
  "properties": {
    "iso:country":"US",
    "sg:address":"3551 Steele St",
    "sg:city":"Denver",
    "sg:classifiers":[
        {
            "category":"Organizations",
            "subcategory":"Religious Organization",
            "type":"Services"
        }
    ],
    "sg:phone":"+1 303 893 0536",
    "sg:postcode":"80205",
    "sg:province":"CO",
    "sg:tags":[
        "church"
    ],
    "wof:name":"Lincoln St Baptist Church",
    "wof:placetype":"venue"
},
  "geometry": {"coordinates":[-104.949986,39.766295],"type":"Point"}
}