{
  "type": "Feature",
  "properties": {
    "iso:country":"US",
    "sg:address":"2171 S Trenton Way",
    "sg:city":"Denver",
    "sg:classifiers":[
        {
            "category":"Home & Garden",
            "subcategory":"Carpets & Floor Coverings",
            "type":"Retail Goods"
        }
    ],
    "sg:phone":"+1 303 871 8377",
    "sg:postcode":"80231",
    "sg:province":"CO",
    "sg:tags":[
        "flooring"
    ],
    "sg:website":"www.hardwoodfloorsdenver.com/",
    "wof:name":"Van Camp's Quality Hardwood Floors",
    "wof:placetype":"venue"
},
  "geometry": {"coordinates":[-104.896806,39.675865],"type":"Point"}
}