{
  "type": "Feature",
  "properties": {
    "iso:country":"US",
    "sg:address":"3127 Teal Ct",
    "sg:city":"Grand Junction",
    "sg:classifiers":[
        {
            "category":"Building & Trades",
            "subcategory":"Construction",
            "type":"Services"
        }
    ],
    "sg:phone":"+1 970 523 6060",
    "sg:postcode":"81504",
    "sg:province":"CO",
    "sg:tags":[
        "boring",
        "drilling",
        "contractor"
    ],
    "wof:name":"Cimarron Drilling Inc",
    "wof:placetype":"venue"
},
  "geometry": {"coordinates":[-108.472629,39.063242],"type":"Point"}
}