{
  "type": "Feature",
  "properties": {
    "iso:country":"US",
    "sg:address":"3096 S Zenobia St",
    "sg:city":"Denver",
    "sg:classifiers":[
        {
            "category":"Professional",
            "subcategory":"Business Services",
            "type":"Services"
        }
    ],
    "sg:phone":"+1 303 937 0352",
    "sg:postcode":"80236",
    "sg:province":"CO",
    "sg:tags":[
        "telemarketing"
    ],
    "wof:name":"Contact Ink",
    "wof:placetype":"venue"
},
  "geometry": {"coordinates":[-105.05098099999999,39.659729],"type":"Point"}
}