{
  "type": "Feature",
  "properties": {
    "iso:country":"US",
    "sg:address":"3279 Dillon Dr",
    "sg:city":"Pueblo",
    "sg:classifiers":[
        {
            "category":"Shopping",
            "subcategory":"Optical Goods",
            "type":"Retail Goods"
        }
    ],
    "sg:phone":"+1 719 544 9600",
    "sg:postcode":"81008",
    "sg:province":"CO",
    "wof:name":"Lenscrafters 567",
    "wof:placetype":"venue"
},
  "geometry": {"coordinates":[-104.60657,38.303745],"type":"Point"}
}