{
  "type": "Feature",
  "properties": {
    "iso:country":"US",
    "sg:address":"6660 S Broadway",
    "sg:city":"Centennial",
    "sg:classifiers":[
        {
            "category":"Health Services",
            "subcategory":"Doctor",
            "type":"Services"
        }
    ],
    "sg:phone":"+1 303 794 2381",
    "sg:postcode":"80121",
    "sg:province":"CO",
    "sg:tags":[
        "clinic"
    ],
    "wof:name":"Littleton Dental",
    "wof:placetype":"venue"
},
  "geometry": {"coordinates":[-104.988193,39.596222],"type":"Point"}
}