{
  "type": "Feature",
  "properties": {
    "addr:full":"330 Meeker St Delta CO 81416",
    "addr:housenumber":"330",
    "addr:postcode":"81416",
    "addr:street":"Meeker St",
    "iso:country":"US",
    "sg:address":"330 Meeker St",
    "sg:city":"Delta",
    "sg:classifiers":[
        {
            "category":"Shopping",
            "subcategory":"Bicycles & Sporting Goods",
            "type":"Retail Goods"
        }
    ],
    "sg:phone":"+1 970 874 1563",
    "sg:postcode":"81416",
    "sg:province":"CO",
    "wof:name":"K CS Cycles",
    "wof:placetype":"venue"
},
  "geometry": {"coordinates":[-108.069408,38.742583],"type":"Point"}
}