{
  "type": "Feature",
  "properties": {
    "addr:full":"1720 S Bellaire Street Denver CO 80222",
    "addr:housenumber":"1720",
    "addr:postcode":"80222",
    "addr:street":"S Bellaire Street",
    "iso:country":"US",
    "sg:address":"1720 S Bellaire Street",
    "sg:city":"Denver",
    "sg:classifiers":[
        {
            "category":"Professional",
            "subcategory":"Accounting & Tax Preparation",
            "type":"Services"
        }
    ],
    "sg:phone":"+1 303 504 4560",
    "sg:postcode":"80222",
    "sg:province":"CO",
    "sg:tags":[
        "accountant"
    ],
    "wof:name":"Walberg Bradley A CPA",
    "wof:placetype":"venue"
},
  "geometry": {"coordinates":[-104.937243,39.685403],"type":"Point"}
}