{
  "type": "Feature",
  "properties": {
    "addr:full":"3188 D Rd Grand Junction CO 81504",
    "addr:housenumber":"3188",
    "addr:postcode":"81504",
    "addr:street":"D Rd",
    "iso:country":"US",
    "sg:address":"3188 D Rd",
    "sg:city":"Grand Junction",
    "sg:classifiers":[
        {
            "category":"Education",
            "subcategory":"School",
            "type":"Public Place"
        }
    ],
    "sg:phone":"+1 970 434 7387",
    "sg:postcode":"81504",
    "sg:province":"CO",
    "wof:name":"Chatfield Elementary School",
    "wof:placetype":"venue"
},
  "geometry": {"coordinates":[-108.460908,39.062874],"type":"Point"}
}