{
  "type": "Feature",
  "properties": {
    "addr:full":"10180 W 23rd Ave Denver CO 80215",
    "addr:housenumber":"10180",
    "addr:postcode":"80215",
    "addr:street":"W 23Rd Ave",
    "iso:country":"US",
    "sg:address":"10180 W 23rd Ave",
    "sg:city":"Denver",
    "sg:classifiers":[
        {
            "category":"Professional",
            "type":"Services"
        }
    ],
    "sg:phone":"+1 303 237 7134",
    "sg:postcode":"80215",
    "sg:province":"CO",
    "wof:name":"James Boardman",
    "wof:placetype":"venue"
},
  "geometry": {"coordinates":[-105.110219,39.750667],"type":"Point"}
}