{
  "type": "Feature",
  "properties": {
    "addr:full":"303 N Wisconsin St Gunnison CO 81230",
    "addr:housenumber":"303",
    "addr:postcode":"81230",
    "addr:street":"N Wisconsin St",
    "iso:country":"US",
    "sg:address":"303 N Wisconsin St",
    "sg:city":"Gunnison",
    "sg:classifiers":[
        {
            "category":"Social Services",
            "type":"Services"
        }
    ],
    "sg:phone":"+1 970 641 0268",
    "sg:postcode":"81230",
    "sg:province":"CO",
    "sg:tags":[
        "youth",
        "organization",
        "center"
    ],
    "wof:name":"St Peter's Youth",
    "wof:placetype":"venue"
},
  "geometry": {"coordinates":[-106.928273,38.547712],"type":"Point"}
}