{
  "type": "Feature",
  "properties": {
    "addr:full":"14231 W Colfax Ave Golden CO 80401",
    "addr:housenumber":"14231",
    "addr:postcode":"80401",
    "addr:street":"W Colfax Ave",
    "iso:country":"US",
    "sg:address":"14231 W Colfax Ave",
    "sg:city":"Golden",
    "sg:classifiers":[
        {
            "category":"Restaurant",
            "type":"Food & Drink"
        }
    ],
    "sg:menulink":"http://www.allmenus.com/co/northeast-jefferson/98184-qdoba/menu/",
    "sg:phone":"+1 303 273 0200",
    "sg:postcode":"80401",
    "sg:province":"CO",
    "sg:tags":[
        "mexican"
    ],
    "wof:name":"Qdoba",
    "wof:placetype":"venue"
},
  "geometry": {"coordinates":[-105.161627,39.736435],"type":"Point"}
}