{
  "type": "Feature",
  "properties": {
    "iso:country":"US",
    "sg:address":"5445 Dtc Pkwy",
    "sg:city":"Englewood",
    "sg:classifiers":[
        {
            "category":"Shopping",
            "subcategory":"Computers & Home Electronics",
            "type":"Retail Goods"
        }
    ],
    "sg:phone":"+1 303 486 6910",
    "sg:postcode":"80111",
    "sg:province":"CO",
    "wof:name":"Woodward Wealth Managment",
    "wof:placetype":"venue"
},
  "geometry": {"coordinates":[-104.896162,39.617378],"type":"Point"}
}