{
  "type": "Feature",
  "properties": {
    "addr:full":"151 Moenkopi Dr Durango CO 81301",
    "addr:housenumber":"151",
    "addr:postcode":"co 81301",
    "addr:street":"Moenkopi Dr",
    "iso:country":"US",
    "sg:address":"151 Moenkopi Dr",
    "sg:city":"Durango",
    "sg:classifiers":[
        {
            "category":"Building & Trades",
            "subcategory":"Construction",
            "type":"Services"
        }
    ],
    "sg:phone":"+1 970 385 7925",
    "sg:postcode":"81301",
    "sg:province":"CO",
    "sg:tags":[
        "siding",
        "contractor"
    ],
    "wof:name":"Winter Hawk Siding & Constr",
    "wof:placetype":"venue"
},
  "geometry": {"coordinates":[-107.847086,37.303367],"type":"Point"}
}