{
  "type": "Feature",
  "properties": {
    "iso:country":"US",
    "sg:address":"465 Main St",
    "sg:city":"Delta",
    "sg:classifiers":[
        {
            "category":"Personal",
            "type":"Services"
        }
    ],
    "sg:phone":"+1 970 874 2939",
    "sg:postcode":"81416",
    "sg:province":"CO",
    "sg:tags":[
        "therapist",
        "massage"
    ],
    "wof:name":"Sunflower Room-Therapeutic",
    "wof:placetype":"venue"
},
  "geometry": {"coordinates":[-108.070942,38.741216],"type":"Point"}
}