{
  "type": "Feature",
  "properties": {
    "addr:full":"7030 S Yosemite St Centennial CO 80112",
    "addr:housenumber":"7030",
    "addr:postcode":"80112",
    "addr:street":"S Yosemite St",
    "iso:country":"US",
    "sg:address":"7030 S Yosemite St",
    "sg:city":"Centennial",
    "sg:classifiers":[
        {
            "category":"Health Services",
            "subcategory":"Chiropractor",
            "type":"Services"
        }
    ],
    "sg:phone":"+1 303 267 4568",
    "sg:postcode":"80112",
    "sg:province":"CO",
    "sg:website":"www.clinixusa.com",
    "wof:name":"Healthcare Specialists",
    "wof:placetype":"venue"
},
  "geometry": {"coordinates":[-104.88539400000001,39.589327],"type":"Point"}
}