{
  "type": "Feature",
  "properties": {
    "iso:country":"US",
    "sg:address":"533 E Hopkins Ave",
    "sg:city":"Aspen",
    "sg:classifiers":[
        {
            "category":"Manufacturing",
            "subcategory":"Chemicals & Compounds",
            "type":"Manufacturing & Wholesale Goods"
        }
    ],
    "sg:phone":"+1 970 544 3375",
    "sg:postcode":"81611",
    "sg:province":"CO",
    "sg:tags":[
        "preparation",
        "toilet",
        "mfg"
    ],
    "wof:name":"Daughter Earth",
    "wof:placetype":"venue"
},
  "geometry": {"coordinates":[-106.818,39.189461],"type":"Point"}
}