{
  "type": "Feature",
  "properties": {
    "iso:country":"US",
    "sg:address":"1727 Pearl St",
    "sg:city":"Boulder",
    "sg:classifiers":[
        {
            "category":"Shopping",
            "subcategory":"Hobbies, Toys, & Games",
            "type":"Retail Goods"
        }
    ],
    "sg:phone":"+1 303 442 9998",
    "sg:postcode":"80302",
    "sg:province":"CO",
    "sg:tags":[
        "craft",
        "supply"
    ],
    "wof:name":"Yeti Arts & Crafts",
    "wof:placetype":"venue"
},
  "geometry": {"coordinates":[-105.272396,40.01951],"type":"Point"}
}