{
  "type": "Feature",
  "properties": {
    "iso:country":"US",
    "sg:address":"16609 Columbine Ln",
    "sg:city":"Cedaredge",
    "sg:classifiers":[
        {
            "category":"Manufacturing",
            "subcategory":"Metals",
            "type":"Manufacturing & Wholesale Goods"
        }
    ],
    "sg:phone":"+1 970 856 8000",
    "sg:postcode":"81413",
    "sg:province":"CO",
    "wof:name":"Artists Faux Hire Inc",
    "wof:placetype":"venue"
},
  "geometry": {"coordinates":[-107.965687,38.895942],"type":"Point"}
}