{
  "type": "Feature",
  "properties": {
    "iso:country":"US",
    "sg:address":"1777 S Harrison Street",
    "sg:city":"Denver",
    "sg:classifiers":[
        {
            "category":"Health Services",
            "subcategory":"Doctor",
            "type":"Services"
        }
    ],
    "sg:phone":"+1 303 758 5650",
    "sg:postcode":"80210",
    "sg:province":"CO",
    "wof:name":"Thomason Hubert H MD",
    "wof:placetype":"venue"
},
  "geometry": {"coordinates":[-104.94180900000001,39.684914],"type":"Point"}
}