{
  "type": "Feature",
  "properties": {
    "addr:full":"861 Co Rd 403 Breckenridge CO 80424",
    "addr:housenumber":"861;403",
    "addr:postcode":"80424",
    "addr:street":"Co Rd",
    "iso:country":"US",
    "sg:address":"861 Co Rd 403",
    "sg:city":"Breckenridge",
    "sg:classifiers":[
        {
            "category":"Building & Trades",
            "subcategory":"Electrical",
            "type":"Services"
        }
    ],
    "sg:phone":"+1 970 453 0726",
    "sg:postcode":"80424",
    "sg:province":"CO",
    "sg:tags":[
        "electrical",
        "electric",
        "contractor"
    ],
    "wof:name":"F D Taylor Electrical Cnstr Co",
    "wof:placetype":"venue"
},
  "geometry": {"coordinates":[-106.045579,39.514345],"type":"Point"}
}