{
  "type": "Feature",
  "properties": {
    "iso:country":"US",
    "sg:address":"229 Manitou Ave",
    "sg:city":"Manitou Springs",
    "sg:classifiers":[
        {
            "category":"Travel",
            "subcategory":"Hotels & Motels",
            "type":"Entertainment"
        }
    ],
    "sg:phone":"+1 719 685 5898",
    "sg:postcode":"80829",
    "sg:province":"CO",
    "sg:website":"www.super8.com",
    "wof:name":"Super 8 Motel",
    "wof:placetype":"venue"
},
  "geometry": {"coordinates":[-104.896004,38.857601],"type":"Point"}
}