{
  "type": "Feature",
  "properties": {
    "iso:country":"US",
    "sg:address":"2185 E 116th Dr",
    "sg:city":"Northglenn",
    "sg:classifiers":[
        {
            "category":"Retail",
            "subcategory":"Repair Shop",
            "type":"Services"
        }
    ],
    "sg:phone":"+1 303 255 7202",
    "sg:postcode":"80233",
    "sg:province":"CO",
    "sg:tags":[
        "plumbing",
        "drain",
        "cleaning",
        "sewer"
    ],
    "wof:name":"Power Rooter Inc",
    "wof:placetype":"venue"
},
  "geometry": {"coordinates":[-104.96029900000001,39.907787],"type":"Point"}
}