{
  "type": "Feature",
  "properties": {
    "iso:country":"US",
    "sg:address":"2620 S Parker Rd",
    "sg:city":"Aurora",
    "sg:classifiers":[
        {
            "category":"Professional",
            "subcategory":"Accounting & Tax Preparation",
            "type":"Services"
        }
    ],
    "sg:phone":"+1 303 302 1256",
    "sg:postcode":"80014",
    "sg:province":"CO",
    "sg:tags":[
        "billing"
    ],
    "wof:name":"Professional Health Alliance",
    "wof:placetype":"venue"
},
  "geometry": {"coordinates":[-104.864259,39.669608],"type":"Point"}
}