{
  "type": "Feature",
  "properties": {
    "addr:full":"1715 N Weber St Colorado Springs CO 80907",
    "addr:housenumber":"1715",
    "addr:postcode":"80907",
    "addr:street":"N Weber St",
    "iso:country":"US",
    "sg:address":"1715 N Weber St",
    "sg:city":"Colorado Springs",
    "sg:classifiers":[
        {
            "category":"Health Services",
            "subcategory":"Doctor",
            "type":"Services"
        }
    ],
    "sg:phone":"+1 719 577 4200",
    "sg:postcode":"80907",
    "sg:province":"CO",
    "sg:tags":[
        "physician",
        "surgeon"
    ],
    "wof:name":"Kids Are Great Pediatrics",
    "wof:placetype":"venue"
},
  "geometry": {"coordinates":[-104.818465,38.858852],"type":"Point"}
}