{
  "type": "Feature",
  "properties": {
    "iso:country":"US",
    "sg:address":"402 Oak Ave",
    "sg:city":"Eaton",
    "sg:classifiers":[
        {
            "category":"Cinema",
            "subcategory":"Movie Rental",
            "type":"Entertainment"
        }
    ],
    "sg:phone":"+1 970 454 3308",
    "sg:postcode":"80615",
    "sg:province":"CO",
    "sg:tags":[
        "leasing",
        "video",
        "disc",
        "tape"
    ],
    "wof:name":"Video Bisz",
    "wof:placetype":"venue"
},
  "geometry": {"coordinates":[-104.711947,40.530148],"type":"Point"}
}