{
  "type": "Feature",
  "properties": {
    "addr:full":"1215 E Hampden Ave Englewood CO 80113",
    "addr:housenumber":"1215",
    "addr:postcode":"80113",
    "addr:street":"E Hampden Ave",
    "iso:country":"US",
    "sg:address":"1215 E Hampden Ave",
    "sg:city":"Englewood",
    "sg:classifiers":[
        {
            "category":"Food & Beverages",
            "subcategory":"Liquor & Beverages",
            "type":"Retail Goods"
        }
    ],
    "sg:phone":"+1 303 789 2804",
    "sg:postcode":"80113",
    "sg:province":"CO",
    "wof:name":"Old Town Liquors",
    "wof:placetype":"venue"
},
  "geometry": {"coordinates":[-104.972469,39.653197],"type":"Point"}
}