{
  "type": "Feature",
  "properties": {
    "iso:country":"US",
    "sg:address":"11111 W 6th Ave",
    "sg:city":"Denver",
    "sg:classifiers":[
        {
            "category":"Home & Garden",
            "subcategory":"Hardware",
            "type":"Retail Goods"
        },
        {
            "category":"Wholesale",
            "subcategory":"Hardware",
            "type":"Manufacturing & Wholesale Goods"
        }
    ],
    "sg:phone":"+1 303 237 7779",
    "sg:postcode":"80215",
    "sg:province":"CO",
    "sg:tags":[
        "tool"
    ],
    "wof:name":"Tool King",
    "wof:placetype":"venue"
},
  "geometry": {"coordinates":[-105.122896,39.72594],"type":"Point"}
}