{
  "type": "Feature",
  "properties": {
    "iso:country":"US",
    "sg:address":"350 Kimbark St",
    "sg:city":"Longmont",
    "sg:classifiers":[
        {
            "category":"Government",
            "subcategory":"Office",
            "type":"Public Place"
        }
    ],
    "sg:phone":"+1 303 651 8695",
    "sg:postcode":"80501",
    "sg:province":"CO",
    "sg:tags":[
        "village"
    ],
    "wof:name":"Longmont Code Enforcement",
    "wof:placetype":"venue"
},
  "geometry": {"coordinates":[-105.101113,40.164814],"type":"Point"}
}