{
  "type": "Feature",
  "properties": {
    "addr:full":"2910 N Powers Blvd Colorado Springs CO 80922",
    "addr:housenumber":"2910",
    "addr:postcode":"80922",
    "addr:street":"N Powers Blvd",
    "iso:country":"US",
    "sg:address":"2910 N Powers Blvd",
    "sg:city":"Colorado Springs",
    "sg:classifiers":[
        {
            "category":"Professional",
            "subcategory":"Business Services",
            "type":"Services"
        },
        {
            "category":"Professional",
            "subcategory":"Advertising",
            "type":"Services"
        }
    ],
    "sg:phone":"+1 719 572 8018",
    "sg:postcode":"80922",
    "sg:province":"CO",
    "sg:tags":[
        "mailing",
        "shipping"
    ],
    "wof:name":"UPS Stores",
    "wof:placetype":"venue"
},
  "geometry": {"coordinates":[-104.719921,38.87476],"type":"Point"}
}