{
  "type": "Feature",
  "properties": {
    "iso:country":"US",
    "sg:address":"603 W Platte Ave",
    "sg:city":"Fort Morgan",
    "sg:classifiers":[
        {
            "category":"Food & Beverages",
            "subcategory":"Groceries & Convenience Stores",
            "type":"Retail Goods"
        }
    ],
    "sg:phone":"+1 970 867 3728",
    "sg:postcode":"80701",
    "sg:province":"CO",
    "wof:name":"7-Eleven",
    "wof:placetype":"venue"
},
  "geometry": {"coordinates":[-103.81009299999999,40.254091],"type":"Point"}
}