{
  "type": "Feature",
  "properties": {
    "addr:full":"833 S Gay St Longmont CO 80501",
    "addr:housenumber":"833",
    "addr:postcode":"80501",
    "addr:street":"S Gay St",
    "iso:country":"US",
    "sg:address":"833 S Gay St",
    "sg:city":"Longmont",
    "sg:classifiers":[
        {
            "category":"Banks & Credit Unions",
            "subcategory":"Bank",
            "type":"Services"
        }
    ],
    "sg:phone":"+1 303 772 9469",
    "sg:postcode":"80501",
    "sg:province":"CO",
    "sg:tags":[
        "mortgage"
    ],
    "wof:name":"Matson Mortgage Inc",
    "wof:placetype":"venue"
},
  "geometry": {"coordinates":[-105.11014400000001,40.15052],"type":"Point"}
}