{
  "type": "Feature",
  "properties": {
    "addr:full":"1820 W Asbury Ave Denver CO 80223",
    "addr:housenumber":"1820",
    "addr:postcode":"80223",
    "addr:street":"W Asbury Ave",
    "iso:country":"US",
    "sg:address":"1820 W Asbury Ave",
    "sg:city":"Denver",
    "sg:classifiers":[
        {
            "category":"Home & Garden",
            "subcategory":"Carpets & Floor Coverings",
            "type":"Retail Goods"
        }
    ],
    "sg:phone":"+1 303 975 7441",
    "sg:postcode":"80223",
    "sg:province":"CO",
    "wof:name":"Cardiel Carpet Service",
    "wof:placetype":"venue"
},
  "geometry": {"coordinates":[-105.01084899999999,39.680439],"type":"Point"}
}