{
  "type": "Feature",
  "properties": {
    "iso:country":"US",
    "sg:address":"4592 Prestige Pt",
    "sg:city":"Colorado Springs",
    "sg:classifiers":[
        {
            "category":"Building & Trades",
            "subcategory":"Construction",
            "type":"Services"
        }
    ],
    "sg:phone":"+1 719 579 9193",
    "sg:postcode":"80906",
    "sg:province":"CO",
    "sg:tags":[
        "contractor"
    ],
    "wof:name":"Pinnacle Mountain Builders",
    "wof:placetype":"venue"
},
  "geometry": {"coordinates":[-104.809183,38.767831],"type":"Point"}
}