{
  "type": "Feature",
  "properties": {
    "iso:country":"US",
    "sg:address":"10200 E Girard Ave",
    "sg:city":"Denver",
    "sg:classifiers":[
        {
            "category":"Health Services",
            "subcategory":"Doctor",
            "type":"Services"
        }
    ],
    "sg:phone":"+1 303 745 1430",
    "sg:postcode":"80231",
    "sg:province":"CO",
    "sg:tags":[
        "dentist"
    ],
    "wof:name":"Jason L Heiken DDS",
    "wof:placetype":"venue"
},
  "geometry": {"coordinates":[-104.869829,39.655146],"type":"Point"}
}