{
  "type": "Feature",
  "properties": {
    "iso:country":"US",
    "sg:address":"1247 Santa Fe Dr",
    "sg:city":"Denver",
    "sg:classifiers":[
        {
            "category":"Arts & Performance",
            "subcategory":"Art Gallery",
            "type":"Entertainment"
        }
    ],
    "sg:phone":"+1 303 209 0944",
    "sg:postcode":"80204",
    "sg:province":"CO",
    "sg:website":"www.gristudios.com/ditto",
    "wof:name":"Ditto Gallery @ GRI",
    "wof:placetype":"venue"
},
  "geometry": {"coordinates":[-104.99907,39.736118],"type":"Point"}
}