{
  "type": "Feature",
  "properties": {
    "addr:full":"15420 E 13th Ave Aurora CO 80011",
    "addr:housenumber":"15420",
    "addr:postcode":"80011",
    "addr:street":"E 13Th Ave",
    "iso:country":"US",
    "sg:address":"15420 E 13th Ave",
    "sg:city":"Aurora",
    "sg:classifiers":[
        {
            "category":"Professional",
            "type":"Services"
        }
    ],
    "sg:phone":"+1 303 995 3083",
    "sg:postcode":"80011",
    "sg:province":"CO",
    "wof:name":"Teresia Trotter",
    "wof:placetype":"venue"
},
  "geometry": {"coordinates":[-104.809517,39.735596],"type":"Point"}
}