{
  "type": "Feature",
  "properties": {
    "iso:country":"US",
    "sg:address":"228 N Cascade Ave",
    "sg:city":"Colorado Springs",
    "sg:classifiers":[
        {
            "category":"Social Services",
            "type":"Services"
        }
    ],
    "sg:phone":"+1 719 866 6535",
    "sg:postcode":"80903",
    "sg:province":"CO",
    "sg:tags":[
        "organization",
        "welfare"
    ],
    "sg:website":"www.ccharitiescs.org",
    "wof:name":"Catholic Charities",
    "wof:placetype":"venue"
},
  "geometry": {"coordinates":[-104.82508900000001,38.837947],"type":"Point"}
}