{
  "type": "Feature",
  "properties": {
    "iso:country":"US",
    "sg:address":"13655 W 30th Pl",
    "sg:city":"Golden",
    "sg:classifiers":[
        {
            "category":"Professional",
            "type":"Services"
        }
    ],
    "sg:phone":"+1 303 278 7448",
    "sg:postcode":"80401",
    "sg:province":"CO",
    "wof:name":"Stan Watkins Inc",
    "wof:placetype":"venue"
},
  "geometry": {"coordinates":[-105.153689,39.759987],"type":"Point"}
}