{
  "type": "Feature",
  "properties": {
    "iso:country":"US",
    "sg:address":"7302 Bondurant Rd",
    "sg:city":"Pueblo",
    "sg:classifiers":[
        {
            "category":"Freight",
            "type":"Transportation"
        }
    ],
    "sg:phone":"+1 719 676 2025",
    "sg:postcode":"81004",
    "sg:province":"CO",
    "sg:tags":[
        "company",
        "trucking"
    ],
    "wof:name":"4 L Trucking",
    "wof:placetype":"venue"
},
  "geometry": {"coordinates":[-104.872567,37.974789],"type":"Point"}
}