{
  "type": "Feature",
  "properties": {
    "addr:full":"331 H St Salida CO 81201",
    "addr:housenumber":"331",
    "addr:postcode":"81201",
    "addr:street":"H St",
    "iso:country":"US",
    "sg:address":"331 H St",
    "sg:city":"Salida",
    "sg:classifiers":[
        {
            "category":"Manufacturing",
            "subcategory":"Retail Goods",
            "type":"Manufacturing & Wholesale Goods"
        }
    ],
    "sg:phone":"+1 719 539 3534",
    "sg:postcode":"81201",
    "sg:province":"CO",
    "sg:tags":[
        "manufacturer"
    ],
    "sg:website":"www.techtoolmfg.com",
    "wof:name":"Tech-Tool Mfg",
    "wof:placetype":"venue"
},
  "geometry": {"coordinates":[-105.995701,38.53559],"type":"Point"}
}