{
  "type": "Feature",
  "properties": {
    "addr:full":"2612 Dumire Ct Fort Collins CO 80526",
    "addr:postcode":"2612;80526",
    "addr:street":"Dumire Ct",
    "iso:country":"US",
    "sg:address":"2612 Dumire Ct",
    "sg:city":"Fort Collins",
    "sg:classifiers":[
        {
            "category":"Building & Trades",
            "subcategory":"Equipment Rental",
            "type":"Services"
        }
    ],
    "sg:phone":"+1 970 206 4558",
    "sg:postcode":"80526",
    "sg:province":"CO",
    "sg:tags":[
        "party",
        "supply"
    ],
    "wof:name":"Better Birthdays",
    "wof:placetype":"venue"
},
  "geometry": {"coordinates":[-105.127375,40.551985],"type":"Point"}
}