{
  "type": "Feature",
  "properties": {
    "addr:full":"3195 S Dexter St Denver CO 80222",
    "addr:housenumber":"3195",
    "addr:postcode":"80222",
    "addr:street":"S Dexter St",
    "iso:country":"US",
    "sg:address":"3195 S Dexter St",
    "sg:city":"Denver",
    "sg:classifiers":[
        {
            "category":"Manufacturing",
            "subcategory":"Tools & Machinery",
            "type":"Manufacturing & Wholesale Goods"
        }
    ],
    "sg:phone":"+1 303 757 1622",
    "sg:postcode":"80222",
    "sg:province":"CO",
    "sg:tags":[
        "industrial",
        "mfg"
    ],
    "wof:name":"Machine Concepts Inc",
    "wof:placetype":"venue"
},
  "geometry": {"coordinates":[-104.932896,39.658726],"type":"Point"}
}