{
  "type": "Feature",
  "properties": {
    "iso:country":"US",
    "sg:address":"7803 N Foothills Hwy",
    "sg:city":"Boulder",
    "sg:classifiers":[
        {
            "category":"Building & Trades",
            "subcategory":"Construction",
            "type":"Services"
        }
    ],
    "sg:phone":"+1 303 444 2196",
    "sg:postcode":"80302",
    "sg:province":"CO",
    "sg:tags":[
        "general",
        "contractor"
    ],
    "wof:name":"Mahorski Construction",
    "wof:placetype":"venue"
},
  "geometry": {"coordinates":[-105.282366,40.11616],"type":"Point"}
}