{
  "type": "Feature",
  "properties": {
    "iso:country":"US",
    "sg:address":"101 Madison St",
    "sg:city":"Denver",
    "sg:classifiers":[
        {
            "category":"Restaurant",
            "type":"Food & Drink"
        }
    ],
    "sg:phone":"+1 303 355 1688",
    "sg:postcode":"80206",
    "sg:province":"CO",
    "sg:tags":[
        "chinese"
    ],
    "sg:website":"www.101asianfusion.com",
    "wof:name":"101 Asian Fusion",
    "wof:placetype":"venue"
},
  "geometry": {"coordinates":[-104.946521,39.717981],"type":"Point"}
}