{
  "type": "Feature",
  "properties": {
    "addr:full":"23768 Co Rd 66 Greeley CO 80631",
    "addr:housenumber":"23768;66",
    "addr:postcode":"80631",
    "addr:street":"Co Rd",
    "iso:country":"US",
    "sg:address":"23768 Co Rd 66",
    "sg:city":"Greeley",
    "sg:classifiers":[
        {
            "category":"Food & Beverages",
            "subcategory":"Meat & Fish",
            "type":"Retail Goods"
        }
    ],
    "sg:phone":"+1 970 356 3942",
    "sg:postcode":"80631",
    "sg:province":"CO",
    "wof:name":"Five O Meats LLC",
    "wof:placetype":"venue"
},
  "geometry": {"coordinates":[-104.606533,40.464058],"type":"Point"}
}