{
  "type": "Feature",
  "properties": {
    "addr:full":"10967 Melody Dr Northglenn CO 80234",
    "addr:housenumber":"10967",
    "addr:postcode":"80234",
    "addr:street":"Melody Dr",
    "iso:country":"US",
    "sg:address":"10967 Melody Dr",
    "sg:city":"Northglenn",
    "sg:classifiers":[
        {
            "category":"Freight",
            "type":"Transportation"
        }
    ],
    "sg:phone":"+1 303 254 8555",
    "sg:postcode":"80234",
    "sg:province":"CO",
    "sg:tags":[
        "shipping",
        "agent"
    ],
    "wof:name":"Mail Master",
    "wof:placetype":"venue"
},
  "geometry": {"coordinates":[-104.991888,39.893859],"type":"Point"}
}