{
  "type": "Feature",
  "properties": {
    "addr:full":"120 S Broadway Denver CO 80209",
    "addr:housenumber":"120",
    "addr:postcode":"80209",
    "addr:street":"S Broadway",
    "iso:country":"US",
    "sg:address":"120 S Broadway",
    "sg:city":"Denver",
    "sg:classifiers":[
        {
            "category":"Shopping",
            "subcategory":"Clothing, Apparel, & Fashions",
            "type":"Retail Goods"
        },
        {
            "category":"Personal",
            "subcategory":"Tattoo Parlor",
            "type":"Services"
        },
        {
            "category":"Personal",
            "subcategory":"Piercing",
            "type":"Services"
        }
    ],
    "sg:phone":"+1 720 366 6925",
    "sg:postcode":"80209",
    "sg:province":"CO",
    "sg:tags":[
        "body"
    ],
    "sg:website":"http://denver.citysearch.com/profile/external/603903162/denver_co/certified_customs.html?publisher=yellowpages&reference_id=1&placement=ypwebsitemip",
    "wof:name":"Certified Customs",
    "wof:placetype":"venue"
},
  "geometry": {"coordinates":[-104.98750699999999,39.714248],"type":"Point"}
}