{
  "type": "Feature",
  "properties": {
    "addr:full":"4543 S Akron St Englewood CO 80111",
    "addr:housenumber":"4543",
    "addr:postcode":"80111",
    "addr:street":"S Akron St",
    "iso:country":"US",
    "sg:address":"4543 S Akron St",
    "sg:city":"Englewood",
    "sg:classifiers":[
        {
            "category":"Manufacturing",
            "subcategory":"Retail Goods",
            "type":"Manufacturing & Wholesale Goods"
        }
    ],
    "sg:phone":"+1 303 779 0479",
    "sg:postcode":"80111",
    "sg:province":"CO",
    "sg:tags":[
        "lead",
        "mfg"
    ],
    "wof:name":"Dirty Hands Ceramics",
    "wof:placetype":"venue"
},
  "geometry": {"coordinates":[-104.88415999999999,39.634326],"type":"Point"}
}