{
  "type": "Feature",
  "properties": {
    "addr:full":"3557 Wazee St Denver CO 80216",
    "addr:housenumber":"3557",
    "addr:postcode":"80216",
    "addr:street":"Wazee St",
    "iso:country":"US",
    "sg:address":"3557 Wazee St",
    "sg:city":"Denver",
    "sg:classifiers":[
        {
            "category":"Wholesale",
            "subcategory":"Machinery & Supplies",
            "type":"Manufacturing & Wholesale Goods"
        }
    ],
    "sg:phone":"+1 303 297 0401",
    "sg:postcode":"80216",
    "sg:province":"CO",
    "sg:tags":[
        "dry wall",
        "contractor"
    ],
    "wof:name":"Colorado Drywall Supply LLC",
    "wof:placetype":"venue"
},
  "geometry": {"coordinates":[-104.976544,39.769442],"type":"Point"}
}