{
  "type": "Feature",
  "properties": {
    "addr:full":"1611 W 84th Ave Denver CO 80260",
    "addr:housenumber":"1611",
    "addr:postcode":"80260",
    "addr:street":"W 84Th Ave",
    "iso:country":"US",
    "sg:address":"1611 W 84th Ave",
    "sg:city":"Denver",
    "sg:classifiers":[
        {
            "category":"Cinema",
            "subcategory":"Movie Rental",
            "type":"Entertainment"
        }
    ],
    "sg:phone":"+1 303 426 4705",
    "sg:postcode":"80260",
    "sg:province":"CO",
    "sg:tags":[
        "leasing",
        "video",
        "disc",
        "tape"
    ],
    "sg:website":"www.hollywoodvideo.com",
    "wof:name":"Hollywood Video",
    "wof:placetype":"venue"
},
  "geometry": {"coordinates":[-105.00609900000001,39.849053],"type":"Point"}
}