{
  "type": "Feature",
  "properties": {
    "iso:country":"US",
    "sg:address":"4514 W 34th Ave",
    "sg:city":"Denver",
    "sg:classifiers":[
        {
            "category":"Building & Trades",
            "subcategory":"Construction",
            "type":"Services"
        }
    ],
    "sg:phone":"+1 303 455 0724",
    "sg:postcode":"80212",
    "sg:province":"CO",
    "sg:tags":[
        "floor",
        "laying",
        "contractor"
    ],
    "wof:name":"Step Up Flooring Inc",
    "wof:placetype":"venue"
},
  "geometry": {"coordinates":[-105.04663499999999,39.764741],"type":"Point"}
}