{
  "type": "Feature",
  "properties": {
    "iso:country":"US",
    "sg:address":"451 Oak St",
    "sg:city":"Frederick",
    "sg:classifiers":[
        {
            "category":"Professional",
            "subcategory":"Accounting & Tax Preparation",
            "type":"Services"
        }
    ],
    "sg:phone":"+1 303 833 1490",
    "sg:postcode":"80530",
    "sg:province":"CO",
    "sg:tags":[
        "billing"
    ],
    "wof:name":"Priority Medical Billing Svc",
    "wof:placetype":"venue"
},
  "geometry": {"coordinates":[-104.93828999999999,40.099081],"type":"Point"}
}