{
  "type": "Feature",
  "properties": {
    "iso:country":"US",
    "sg:address":"33109 Inverness Dr",
    "sg:city":"Evergreen",
    "sg:classifiers":[
        {
            "category":"Professional",
            "subcategory":"Computer Services",
            "type":"Services"
        }
    ],
    "sg:phone":"+1 303 674 3587",
    "sg:postcode":"80439",
    "sg:province":"CO",
    "sg:tags":[
        "related"
    ],
    "wof:name":"Over 40 Consultants L L C",
    "wof:placetype":"venue"
},
  "geometry": {"coordinates":[-105.346259,39.666298],"type":"Point"}
}