{
  "type": "Feature",
  "properties": {
    "iso:country":"US",
    "sg:address":"4 Doane Pl",
    "sg:city":"Pueblo",
    "sg:classifiers":[
        {
            "category":"Freight",
            "type":"Transportation"
        }
    ],
    "sg:phone":"+1 719 948 0081",
    "sg:postcode":"81001",
    "sg:province":"CO",
    "sg:tags":[
        "trucking"
    ],
    "sg:website":"www.swift.com",
    "wof:name":"Swift Transportation Co",
    "wof:placetype":"venue"
},
  "geometry": {"coordinates":[-104.474896,38.278686],"type":"Point"}
}