{
  "type": "Feature",
  "properties": {
    "addr:full":"7800 S Elati St Littleton CO 80120",
    "addr:housenumber":"7800",
    "addr:postcode":"80120",
    "addr:street":"S Elati St",
    "iso:country":"US",
    "sg:address":"7800 S Elati St",
    "sg:city":"Littleton",
    "sg:classifiers":[
        {
            "category":"Personal",
            "type":"Services"
        }
    ],
    "sg:phone":"+1 303 797 0206",
    "sg:postcode":"80120",
    "sg:province":"CO",
    "sg:tags":[
        "electrolysis"
    ],
    "wof:name":"Electrology & Laser Lab South",
    "wof:placetype":"venue"
},
  "geometry": {"coordinates":[-104.99739599999999,39.575756],"type":"Point"}
}