{
  "type": "Feature",
  "properties": {
    "addr:full":"6313 E Laguna Cir Littleton CO 80130",
    "addr:housenumber":"6313",
    "addr:postcode":"80130",
    "addr:street":"E Laguna Cir",
    "iso:country":"US",
    "sg:address":"6313 E Laguna Cir",
    "sg:city":"Littleton",
    "sg:classifiers":[
        {
            "category":"Insurance",
            "subcategory":"Insurance Agent",
            "type":"Services"
        }
    ],
    "sg:phone":"+1 303 471 0317",
    "sg:postcode":"80130",
    "sg:province":"CO",
    "wof:name":"Denver Division Insurance",
    "wof:placetype":"venue"
},
  "geometry": {"coordinates":[-104.917239,39.552713],"type":"Point"}
}