{
  "type": "Feature",
  "properties": {
    "iso:country":"US",
    "sg:address":"540 Main St",
    "sg:city":"Delta",
    "sg:classifiers":[
        {
            "category":"Social Services",
            "type":"Services"
        }
    ],
    "sg:phone":"+1 970 874 8744",
    "sg:postcode":"81416",
    "sg:province":"CO",
    "sg:tags":[
        "counselor",
        "marriage",
        "family"
    ],
    "wof:name":"Montrose Hospital",
    "wof:placetype":"venue"
},
  "geometry": {"coordinates":[-108.070652,38.73983],"type":"Point"}
}