{
  "type": "Feature",
  "properties": {
    "iso:country":"US",
    "sg:address":"595 S Broadway",
    "sg:city":"Denver",
    "sg:classifiers":[
        {
            "category":"Building & Trades",
            "subcategory":"Construction",
            "type":"Services"
        },
        {
            "category":"Real Estate",
            "subcategory":"Architect",
            "type":"Services"
        }
    ],
    "sg:phone":"+1 303 763 0424",
    "sg:postcode":"80209",
    "sg:province":"CO",
    "sg:tags":[
        "interior",
        "design"
    ],
    "sg:website":"feliciamoon.com",
    "wof:name":"Felicia Moon Interior Design & Home Staging",
    "wof:placetype":"venue"
},
  "geometry": {"coordinates":[-104.99083400000001,39.706575],"type":"Point"}
}