{
  "type": "Feature",
  "properties": {
    "iso:country":"US",
    "sg:address":"607 S Broadway St",
    "sg:city":"Boulder",
    "sg:classifiers":[
        {
            "category":"Personal",
            "subcategory":"Tanning Parlor",
            "type":"Services"
        }
    ],
    "sg:phone":"+1 303 494 8833",
    "sg:postcode":"80305",
    "sg:province":"CO",
    "sg:tags":[
        "salon"
    ],
    "wof:name":"Executive Tans",
    "wof:placetype":"venue"
},
  "geometry": {"coordinates":[-105.243117,39.977805],"type":"Point"}
}