{
  "type": "Feature",
  "properties": {
    "addr:full":"4541 Dixon Dr Westminster CO 80031",
    "addr:housenumber":"4541",
    "addr:postcode":"80031",
    "addr:street":"Dixon Dr",
    "iso:country":"US",
    "sg:address":"4541 Dixon Dr",
    "sg:city":"Westminster",
    "sg:classifiers":[
        {
            "category":"Education",
            "subcategory":"Special Training",
            "type":"Public Place"
        }
    ],
    "sg:phone":"+1 303 466 3520",
    "sg:postcode":"80031",
    "sg:province":"CO",
    "sg:tags":[
        "reading",
        "instruction",
        "improvement"
    ],
    "wof:name":"Colorado Institute Of Reading",
    "wof:placetype":"venue"
},
  "geometry": {"coordinates":[-105.047588,39.853472],"type":"Point"}
}