{
  "type": "Feature",
  "properties": {
    "iso:country":"US",
    "sg:address":"30 Rd C",
    "sg:city":"Grand Lake",
    "sg:classifiers":[
        {
            "category":"Insurance",
            "subcategory":"Insurance Agent",
            "type":"Services"
        }
    ],
    "sg:phone":"+1 970 627 8822",
    "sg:postcode":"80470",
    "sg:province":"CO",
    "wof:name":"Bankers Life & Casualty Co",
    "wof:placetype":"venue"
},
  "geometry": {"coordinates":[-105.442307,39.509996],"type":"Point"}
}