{
  "type": "Feature",
  "properties": {
    "addr:full":"500 Parachute Ave Parachute CO 81635",
    "addr:housenumber":"500",
    "addr:postcode":"81635",
    "addr:street":"Parachute Ave",
    "iso:country":"US",
    "sg:address":"500 Parachute Ave",
    "sg:city":"Parachute",
    "sg:classifiers":[
        {
            "category":"Social Services",
            "subcategory":"Adult Care",
            "type":"Services"
        }
    ],
    "sg:phone":"+1 970 285 9690",
    "sg:postcode":"81635",
    "sg:province":"CO",
    "sg:tags":[
        "home"
    ],
    "wof:name":"Valley Senior Housing",
    "wof:placetype":"venue"
},
  "geometry": {"coordinates":[-108.057793,39.455408],"type":"Point"}
}