{
  "type": "Feature",
  "properties": {
    "addr:full":"2001 Jamaica St Aurora CO 80010",
    "addr:housenumber":"2001",
    "addr:postcode":"80010",
    "addr:street":"Jamaica St",
    "iso:country":"US",
    "sg:address":"2001 Jamaica St",
    "sg:city":"Aurora",
    "sg:classifiers":[
        {
            "category":"Organizations",
            "subcategory":"Religious Organization",
            "type":"Services"
        }
    ],
    "sg:phone":"+1 303 360 9728",
    "sg:postcode":"80010",
    "sg:province":"CO",
    "sg:tags":[
        "church"
    ],
    "wof:name":"New Nation Cogic",
    "wof:placetype":"venue"
},
  "geometry": {"coordinates":[-104.86226000000001,39.749282],"type":"Point"}
}