{
  "type": "Feature",
  "properties": {
    "iso:country":"US",
    "sg:address":"6308 E 72nd Ave",
    "sg:city":"Commerce City",
    "sg:classifiers":[
        {
            "category":"Personal",
            "subcategory":"Tattoo Parlor",
            "type":"Services"
        }
    ],
    "sg:phone":"+1 303 288 3441",
    "sg:postcode":"80022",
    "sg:province":"CO",
    "sg:tags":[
        "tattooing"
    ],
    "wof:name":"My Daily Routine Tattoos",
    "wof:placetype":"venue"
},
  "geometry": {"coordinates":[-104.91381699999999,39.827125],"type":"Point"}
}