{
  "type": "Feature",
  "properties": {
    "iso:country":"US",
    "sg:address":"5203 E 56th Ave",
    "sg:city":"Commerce City",
    "sg:classifiers":[
        {
            "category":"Professional",
            "type":"Services"
        }
    ],
    "sg:phone":"+1 303 287 0374",
    "sg:postcode":"80022",
    "sg:province":"CO",
    "sg:tags":[
        "establishment"
    ],
    "wof:name":"H M Rattle Co",
    "wof:placetype":"venue"
},
  "geometry": {"coordinates":[-104.924858,39.798395],"type":"Point"}
}