{
  "type": "Feature",
  "properties": {
    "iso:country":"US",
    "sg:address":"11178 W 59th Pl",
    "sg:city":"Arvada",
    "sg:classifiers":[
        {
            "category":"Professional",
            "type":"Services"
        }
    ],
    "sg:phone":"+1 303 422 2498",
    "sg:postcode":"80004",
    "sg:province":"CO",
    "wof:name":"Silver Peak Foundation",
    "wof:placetype":"venue"
},
  "geometry": {"coordinates":[-105.123187,39.805084],"type":"Point"}
}