{
  "type": "Feature",
  "properties": {
    "iso:country":"US",
    "sg:address":"2180 S Leyden St",
    "sg:city":"Denver",
    "sg:classifiers":[
        {
            "category":"Professional",
            "type":"Services"
        }
    ],
    "sg:phone":"+1 303 691 1725",
    "sg:postcode":"80222",
    "sg:province":"CO",
    "sg:tags":[
        "establishment"
    ],
    "wof:name":"Lauren Corp",
    "wof:placetype":"venue"
},
  "geometry": {"coordinates":[-104.915886,39.677099],"type":"Point"}
}