{
  "type": "Feature",
  "properties": {
    "addr:full":"11 Willow Dr La Jara CO 81140",
    "addr:housenumber":"11",
    "addr:postcode":"81140",
    "addr:street":"Willow Dr",
    "iso:country":"US",
    "sg:address":"11 Willow Dr",
    "sg:city":"La Jara",
    "sg:classifiers":[
        {
            "category":"Freight",
            "type":"Transportation"
        }
    ],
    "sg:phone":"+1 719 274 3281",
    "sg:postcode":"81140",
    "sg:province":"CO",
    "sg:tags":[
        "operator",
        "local",
        "trucking"
    ],
    "wof:name":"Malouff Trucking",
    "wof:placetype":"venue"
},
  "geometry": {"coordinates":[-105.95766999999999,37.27071],"type":"Point"}
}