{
  "type": "Feature",
  "properties": {
    "addr:full":"6090 Crestbrook Dr Morrison CO 80465",
    "addr:housenumber":"6090",
    "addr:postcode":"80465",
    "addr:street":"Crestbrook Dr",
    "iso:country":"US",
    "sg:address":"6090 Crestbrook Dr",
    "sg:city":"Morrison",
    "sg:classifiers":[
        {
            "category":"Professional",
            "type":"Services"
        }
    ],
    "sg:phone":"+1 303 697 8589",
    "sg:postcode":"80465",
    "sg:province":"CO",
    "wof:name":"B Trautman Designs",
    "wof:placetype":"venue"
},
  "geometry": {"coordinates":[-105.167193,39.61004],"type":"Point"}
}