{
  "type": "Feature",
  "properties": {
    "addr:full":"1575 S Pearl Street Denver CO 80210",
    "addr:housenumber":"1575",
    "addr:postcode":"80210",
    "addr:street":"S Pearl Street",
    "iso:country":"US",
    "sg:address":"1575 S Pearl Street",
    "sg:city":"Denver",
    "sg:classifiers":[
        {
            "category":"Wholesale",
            "subcategory":"Stationery",
            "type":"Manufacturing & Wholesale Goods"
        }
    ],
    "sg:phone":"+1 303 777 1481",
    "sg:postcode":"80210",
    "sg:province":"CO",
    "sg:tags":[
        "card"
    ],
    "wof:name":"Paper Talk",
    "wof:placetype":"venue"
},
  "geometry": {"coordinates":[-104.98027399999999,39.687928],"type":"Point"}
}