{
  "type": "Feature",
  "properties": {
    "iso:country":"US",
    "sg:address":"2344 S Platte River Rd",
    "sg:city":"Sedalia",
    "sg:phone":"+1 303 647 1000",
    "sg:postcode":"80135",
    "sg:province":"CO",
    "sg:tags":[
        "product",
        "petroleum"
    ],
    "wof:name":"Mountain Propane",
    "wof:placetype":"venue"
},
  "geometry": {"coordinates":[-105.183477,39.328726],"type":"Point"}
}