{
  "type": "Feature",
  "properties": {
    "iso:country":"US",
    "sg:address":"28120 Co Rd Y",
    "sg:city":"La Junta",
    "sg:classifiers":[
        {
            "category":"Farming",
            "subcategory":"Livestock Farm",
            "type":"Manufacturing & Wholesale Goods"
        }
    ],
    "sg:phone":"+1 719 384 7109",
    "sg:postcode":"81050",
    "sg:province":"CO",
    "sg:tags":[
        "beef",
        "feedlot",
        "cattle"
    ],
    "wof:name":"Tenner Ranch",
    "wof:placetype":"venue"
},
  "geometry": {"coordinates":[-103.56262700000001,37.953305],"type":"Point"}
}