{
  "type": "Feature",
  "properties": {
    "addr:full":"3415 N Elizabeth St Pueblo CO 81008",
    "addr:housenumber":"3415",
    "addr:postcode":"81008",
    "addr:street":"N Elizabeth St",
    "iso:country":"US",
    "sg:address":"3415 N Elizabeth St",
    "sg:city":"Pueblo",
    "sg:classifiers":[
        {
            "category":"Utilities",
            "subcategory":"Mobile Phone",
            "type":"Services"
        }
    ],
    "sg:phone":"+1 719 545 5700",
    "sg:postcode":"81008",
    "sg:province":"CO",
    "sg:tags":[
        "communication",
        "radiotelephone"
    ],
    "wof:name":"Red DOT Wireless",
    "wof:placetype":"venue"
},
  "geometry": {"coordinates":[-104.616046,38.307744],"type":"Point"}
}