{
  "type": "Feature",
  "properties": {
    "iso:country":"US",
    "sg:address":"2010 Birdie Dr",
    "sg:city":"Milliken",
    "sg:classifiers":[
        {
            "category":"Building & Trades",
            "subcategory":"Electrical",
            "type":"Services"
        }
    ],
    "sg:phone":"+1 970 587 8863",
    "sg:postcode":"80543",
    "sg:province":"CO",
    "sg:tags":[
        "electrical",
        "electric",
        "contractor"
    ],
    "wof:name":"Peacock Electric Inc",
    "wof:placetype":"venue"
},
  "geometry": {"coordinates":[-104.870559,40.350655],"type":"Point"}
}