{
  "type": "Feature",
  "properties": {
    "iso:country":"US",
    "sg:address":"406 Grand Ave",
    "sg:city":"Grand Lake",
    "sg:classifiers":[
        {
            "category":"Building & Trades",
            "subcategory":"Construction",
            "type":"Services"
        }
    ],
    "sg:phone":"+1 970 627 3525",
    "sg:postcode":"80447",
    "sg:province":"CO",
    "sg:tags":[
        "house"
    ],
    "wof:name":"C & Z Builders Inc",
    "wof:placetype":"venue"
},
  "geometry": {"coordinates":[-105.831304,40.253648],"type":"Point"}
}