{
  "type": "Feature",
  "properties": {
    "iso:country":"US",
    "sg:address":"206 Colorado Pl",
    "sg:city":"Sterling",
    "sg:classifiers":[
        {
            "category":"Social Services",
            "type":"Services"
        }
    ],
    "sg:phone":"+1 970 521 0971",
    "sg:postcode":"80751",
    "sg:province":"CO",
    "sg:tags":[
        "youth",
        "organization",
        "center"
    ],
    "wof:name":"Boy Scouts Of America",
    "wof:placetype":"venue"
},
  "geometry": {"coordinates":[-103.196941,40.642844],"type":"Point"}
}