{
  "type": "Feature",
  "properties": {
    "iso:country":"US",
    "sg:address":"1007 Pearl St",
    "sg:city":"Boulder",
    "sg:classifiers":[
        {
            "category":"Professional",
            "type":"Services"
        },
        {
            "category":"Mining & Drilling",
            "type":"Manufacturing & Wholesale Goods"
        }
    ],
    "sg:phone":"+1 303 444 5100",
    "sg:postcode":"80302",
    "sg:province":"CO",
    "sg:tags":[
        "consultant",
        "geologist",
        "geological",
        "field"
    ],
    "wof:name":"Applied Geoscience Inc",
    "wof:placetype":"venue"
},
  "geometry": {"coordinates":[-105.281384,40.017676],"type":"Point"}
}