{
  "type": "Feature",
  "properties": {
    "iso:country":"US",
    "sg:address":"3230 S Glen Ave",
    "sg:city":"Glenwood Springs",
    "sg:classifiers":[
        {
            "category":"Banks & Credit Unions",
            "subcategory":"Bank",
            "type":"Services"
        }
    ],
    "sg:phone":"+1 970 947 0199",
    "sg:postcode":"81601",
    "sg:province":"CO",
    "wof:name":"Wells Fargo Bank",
    "wof:placetype":"venue"
},
  "geometry": {"coordinates":[-107.31877,39.517645],"type":"Point"}
}