{
  "type": "Feature",
  "properties": {
    "iso:country":"US",
    "sg:address":"871 Co Rd 501",
    "sg:city":"Bayfield",
    "sg:classifiers":[
        {
            "category":"Restaurant",
            "type":"Food & Drink"
        }
    ],
    "sg:phone":"+1 970 884 1119",
    "sg:postcode":"81122",
    "sg:province":"CO",
    "wof:name":"Martha T's",
    "wof:placetype":"venue"
},
  "geometry": {"coordinates":[-107.601705,37.243073],"type":"Point"}
}