{
  "type": "Feature",
  "properties": {
    "addr:full":"1545 Redwood Ave Boulder CO 80304",
    "addr:housenumber":"1545",
    "addr:postcode":"80304",
    "addr:street":"Redwood Ave",
    "iso:country":"US",
    "sg:address":"1545 Redwood Ave",
    "sg:city":"Boulder",
    "sg:classifiers":[
        {
            "category":"Building & Trades",
            "subcategory":"Landscaping Services",
            "type":"Services"
        }
    ],
    "sg:phone":"+1 303 443 0284",
    "sg:postcode":"80304",
    "sg:province":"CO",
    "wof:name":"Matrix Gardens Landscaping",
    "wof:placetype":"venue"
},
  "geometry": {"coordinates":[-105.276448,40.048861],"type":"Point"}
}