{
  "type": "Feature",
  "properties": {
    "iso:country":"US",
    "sg:address":"5172 Valmont Rd",
    "sg:city":"Boulder",
    "sg:classifiers":[
        {
            "category":"Building & Trades",
            "subcategory":"Construction",
            "type":"Services"
        }
    ],
    "sg:phone":"+1 303 442 6501",
    "sg:postcode":"80301",
    "sg:province":"CO",
    "sg:tags":[
        "roofing",
        "contractor"
    ],
    "wof:name":"Cote",
    "wof:placetype":"venue"
},
  "geometry": {"coordinates":[-105.23081999999999,40.029153],"type":"Point"}
}