{
  "type": "Feature",
  "properties": {
    "addr:full":"26649 Pleasant Park Rd Conifer CO 80433",
    "addr:housenumber":"26649",
    "addr:postcode":"80433",
    "addr:street":"Pleasant Park Rd",
    "iso:country":"US",
    "sg:address":"26649 Pleasant Park Rd",
    "sg:city":"Conifer",
    "sg:classifiers":[
        {
            "category":"Building & Trades",
            "subcategory":"Equipment Rental",
            "type":"Services"
        }
    ],
    "sg:phone":"+1 303 838 7233",
    "sg:postcode":"80433",
    "sg:province":"CO",
    "sg:tags":[
        "party",
        "tool",
        "supply"
    ],
    "wof:name":"285 Rent-A-Tool",
    "wof:placetype":"venue"
},
  "geometry": {"coordinates":[-105.292311,39.51823],"type":"Point"}
}