{
  "type": "Feature",
  "properties": {
    "addr:full":"7315 S Webster St Littleton CO 80128",
    "addr:housenumber":"7315",
    "addr:postcode":"80128",
    "addr:street":"S Webster St",
    "iso:country":"US",
    "sg:address":"7315 S Webster St",
    "sg:city":"Littleton",
    "sg:classifiers":[
        {
            "category":"Wholesale",
            "subcategory":"Stationery",
            "type":"Manufacturing & Wholesale Goods"
        }
    ],
    "sg:phone":"+1 303 904 8507",
    "sg:postcode":"80128",
    "sg:province":"CO",
    "sg:tags":[
        "business",
        "form",
        "system"
    ],
    "wof:name":"Proform Business Systems",
    "wof:placetype":"venue"
},
  "geometry": {"coordinates":[-105.082657,39.585439],"type":"Point"}
}