{
  "type": "Feature",
  "properties": {
    "iso:country":"US",
    "sg:address":"1930 S Havana St",
    "sg:city":"Aurora",
    "sg:classifiers":[
        {
            "category":"Restaurant",
            "type":"Food & Drink"
        }
    ],
    "sg:phone":"+1 303 755 2211",
    "sg:postcode":"80014",
    "sg:province":"CO",
    "sg:tags":[
        "eating"
    ],
    "wof:name":"Whispers",
    "wof:placetype":"venue"
},
  "geometry": {"coordinates":[-104.865875,39.680761],"type":"Point"}
}