{
  "type": "Feature",
  "properties": {
    "addr:full":"26 S Tejon St Colorado Springs CO 80903",
    "addr:housenumber":"26",
    "addr:postcode":"80903",
    "addr:street":"S Tejon St",
    "iso:country":"US",
    "sg:address":"26 S Tejon St",
    "sg:city":"Colorado Springs",
    "sg:classifiers":[
        {
            "category":"Shopping",
            "type":"Retail Goods"
        }
    ],
    "sg:phone":"+1 719 632 2028",
    "sg:postcode":"80903",
    "sg:province":"CO",
    "sg:tags":[
        "equipment",
        "wine",
        "supply"
    ],
    "wof:name":"Colorado Cellar Consulting",
    "wof:placetype":"venue"
},
  "geometry": {"coordinates":[-104.82363100000001,38.832792],"type":"Point"}
}