{
  "type": "Feature",
  "properties": {
    "iso:country":"US",
    "sg:address":"457 E Wonderview Ave",
    "sg:city":"Estes Park",
    "sg:classifiers":[
        {
            "category":"Real Estate",
            "subcategory":"Real Estate Agent",
            "type":"Services"
        }
    ],
    "sg:phone":"+1 970 586 3838",
    "sg:postcode":"80517",
    "sg:province":"CO",
    "sg:website":"www.prudentialcolorado.com",
    "wof:name":"Prudential Team Realty",
    "wof:placetype":"venue"
},
  "geometry": {"coordinates":[-105.517268,40.378552],"type":"Point"}
}