{
  "type": "Feature",
  "properties": {
    "addr:full":"347 Main St Delta CO 81416",
    "addr:housenumber":"347",
    "addr:postcode":"81416",
    "addr:street":"Main St",
    "iso:country":"US",
    "sg:address":"347 Main St",
    "sg:city":"Delta",
    "sg:classifiers":[
        {
            "category":"Shopping",
            "type":"Retail Goods"
        }
    ],
    "sg:phone":"+1 970 874 8305",
    "sg:postcode":"81416",
    "sg:province":"CO",
    "sg:tags":[
        "merchandise"
    ],
    "wof:name":"Finishing Touch",
    "wof:placetype":"venue"
},
  "geometry": {"coordinates":[-108.070959,38.742281],"type":"Point"}
}