{
  "type": "Feature",
  "properties": {
    "addr:full":"1767 S Dearborn Way Aurora CO 80012",
    "addr:housenumber":"1767",
    "addr:postcode":"80012",
    "addr:street":"S Dearborn Way",
    "iso:country":"US",
    "sg:address":"1767 S Dearborn Way",
    "sg:city":"Aurora",
    "sg:classifiers":[
        {
            "category":"Building & Trades",
            "subcategory":"Construction",
            "type":"Services"
        }
    ],
    "sg:phone":"+1 303 369 5129",
    "sg:postcode":"80012",
    "sg:province":"CO",
    "sg:tags":[
        "house"
    ],
    "wof:name":"Ms Construction",
    "wof:placetype":"venue"
},
  "geometry": {"coordinates":[-104.817168,39.684925],"type":"Point"}
}