{
  "type": "Feature",
  "properties": {
    "addr:full":"1020 Bonforte Blvd Pueblo CO 81001",
    "addr:housenumber":"1020",
    "addr:postcode":"81001",
    "addr:street":"Bonforte Blvd",
    "iso:country":"US",
    "sg:address":"1020 Bonforte Blvd",
    "sg:city":"Pueblo",
    "sg:classifiers":[
        {
            "category":"Wholesale",
            "subcategory":"Farm Supplies",
            "type":"Manufacturing & Wholesale Goods"
        }
    ],
    "sg:phone":"+1 719 543 8149",
    "sg:postcode":"81001",
    "sg:province":"CO",
    "sg:website":"www.bigronline.com",
    "wof:name":"Big R Of Pueblo Inc",
    "wof:placetype":"venue"
},
  "geometry": {"coordinates":[-104.594319,38.290213],"type":"Point"}
}