{
  "type": "Feature",
  "properties": {
    "iso:country":"US",
    "sg:address":"577 N Westgate Dr",
    "sg:city":"Grand Junction",
    "sg:classifiers":[
        {
            "category":"Building & Trades",
            "subcategory":"Landscaping Services",
            "type":"Services"
        }
    ],
    "sg:phone":"+1 970 243 1229",
    "sg:postcode":"81505",
    "sg:province":"CO",
    "wof:name":"W D Yards Inc",
    "wof:placetype":"venue"
},
  "geometry": {"coordinates":[-108.58666599999999,39.089336],"type":"Point"}
}