{
  "type": "Feature",
  "properties": {
    "iso:country":"US",
    "sg:address":"444 S 2nd St",
    "sg:city":"La Salle",
    "sg:classifiers":[
        {
            "category":"Professional",
            "subcategory":"Engineering",
            "type":"Services"
        }
    ],
    "sg:phone":"+1 970 284 9240",
    "sg:postcode":"80645",
    "sg:province":"CO",
    "sg:tags":[
        "general",
        "contractor"
    ],
    "wof:name":"Total Engineering Svc",
    "wof:placetype":"venue"
},
  "geometry": {"coordinates":[-104.707041,40.346605],"type":"Point"}
}