{
  "type": "Feature",
  "properties": {
    "addr:full":"5909 E Caley Dr Centennial CO 80111",
    "addr:housenumber":"5909",
    "addr:postcode":"80111",
    "addr:street":"E Caley Dr",
    "iso:country":"US",
    "sg:address":"5909 E Caley Dr",
    "sg:city":"Centennial",
    "sg:classifiers":[
        {
            "category":"Manufacturing",
            "subcategory":"Printing",
            "type":"Manufacturing & Wholesale Goods"
        }
    ],
    "sg:phone":"+1 303 771 1091",
    "sg:postcode":"80111",
    "sg:province":"CO",
    "sg:tags":[
        "publisher"
    ],
    "wof:name":"Akkad Press",
    "wof:placetype":"venue"
},
  "geometry": {"coordinates":[-104.921216,39.601038],"type":"Point"}
}