{
  "type": "Feature",
  "properties": {
    "iso:country":"US",
    "sg:address":"11450 Melody Dr",
    "sg:city":"Denver",
    "sg:classifiers":[
        {
            "category":"Real Estate",
            "subcategory":"Real Estate Operator",
            "type":"Services"
        }
    ],
    "sg:phone":"+1 303 280 5888",
    "sg:postcode":"80234",
    "sg:province":"CO",
    "sg:tags":[
        "building",
        "apartment"
    ],
    "wof:name":"Village At North Hills",
    "wof:placetype":"venue"
},
  "geometry": {"coordinates":[-104.994891,39.90519],"type":"Point"}
}