{
  "type": "Feature",
  "properties": {
    "iso:country":"US",
    "sg:address":"451 S Holly St",
    "sg:city":"Denver",
    "sg:classifiers":[
        {
            "category":"Building & Trades",
            "subcategory":"Locksmith",
            "type":"Services"
        }
    ],
    "sg:phone":"+1 303 801 0078",
    "sg:postcode":"80246",
    "sg:province":"CO",
    "sg:tags":[
        "key"
    ],
    "wof:name":"AAA 15 Minutes Colorado Locksmith",
    "wof:placetype":"venue"
},
  "geometry": {"coordinates":[-104.922436,39.708273],"type":"Point"}
}