{
  "type": "Feature",
  "properties": {
    "addr:full":"29309 Industrial Way Evergreen CO 80439",
    "addr:housenumber":"29309",
    "addr:postcode":"80439",
    "addr:street":"Industrial Way",
    "iso:country":"US",
    "sg:address":"29309 Industrial Way",
    "sg:city":"Evergreen",
    "sg:classifiers":[
        {
            "category":"Freight",
            "type":"Transportation"
        }
    ],
    "sg:phone":"+1 303 679 1415",
    "sg:postcode":"80439",
    "sg:province":"CO",
    "sg:tags":[
        "commercial",
        "storage"
    ],
    "wof:name":"A Storage Place",
    "wof:placetype":"venue"
},
  "geometry": {"coordinates":[-105.33336300000001,39.697499],"type":"Point"}
}