{
  "type": "Feature",
  "properties": {
    "iso:country":"US",
    "sg:address":"7476 E 29th Avenue",
    "sg:city":"Denver",
    "sg:classifiers":[
        {
            "category":"Real Estate",
            "subcategory":"Real Estate Services",
            "type":"Services"
        }
    ],
    "sg:phone":"+1 303 316 3333",
    "sg:postcode":"80238",
    "sg:province":"CO",
    "sg:tags":[
        "home",
        "inspector"
    ],
    "wof:name":"Crisp Inspections & Property Management",
    "wof:placetype":"venue"
},
  "geometry": {"coordinates":[-104.901124,39.757878],"type":"Point"}
}