{
  "type": "Feature",
  "properties": {
    "iso:country":"US",
    "sg:address":"811 Evergreen Pkwy",
    "sg:city":"Evergreen",
    "sg:classifiers":[
        {
            "category":"Professional",
            "type":"Services"
        }
    ],
    "sg:phone":"+1 303 526 2417",
    "sg:postcode":"80439",
    "sg:province":"CO",
    "sg:tags":[
        "establishment"
    ],
    "wof:name":"Alpine Rescue Team Inc",
    "wof:placetype":"venue"
},
  "geometry": {"coordinates":[-105.33696500000001,39.698456],"type":"Point"}
}