{
  "type": "Feature",
  "properties": {
    "iso:country":"US",
    "sg:address":"1341 Co Rd 309A",
    "sg:city":"Ignacio",
    "sg:classifiers":[
        {
            "category":"Insurance",
            "subcategory":"Insurance Agent",
            "type":"Services"
        }
    ],
    "sg:phone":"+1 970 247 9113",
    "sg:postcode":"81137",
    "sg:province":"CO",
    "wof:name":"Phyllis Haley Agency",
    "wof:placetype":"venue"
},
  "geometry": {"coordinates":[-107.744893,37.152827],"type":"Point"}
}