{
  "type": "Feature",
  "properties": {
    "addr:full":"7456 S Simms St Littleton CO 80127",
    "addr:housenumber":"7456",
    "addr:postcode":"80127",
    "addr:street":"S Simms St",
    "iso:country":"US",
    "sg:address":"7456 S Simms St",
    "sg:city":"Littleton",
    "sg:classifiers":[
        {
            "category":"Food & Beverages",
            "subcategory":"Fruits & Vegetables",
            "type":"Retail Goods"
        }
    ],
    "sg:phone":"+1 303 904 9343",
    "sg:postcode":"80127",
    "sg:province":"CO",
    "sg:tags":[
        "juice"
    ],
    "wof:name":"Jamba Juice",
    "wof:placetype":"venue"
},
  "geometry": {"coordinates":[-105.12889,39.580938],"type":"Point"}
}