{
  "type": "Feature",
  "properties": {
    "iso:country":"US",
    "sg:address":"1905 Linden Dr",
    "sg:city":"Boulder",
    "sg:classifiers":[
        {
            "category":"Government",
            "subcategory":"Fire Station",
            "type":"Public Place"
        }
    ],
    "sg:phone":"+1 303 440 0235",
    "sg:postcode":"80304",
    "sg:province":"CO",
    "sg:tags":[
        "a",
        "specifically",
        "as",
        "protection",
        "provides",
        "volunteer"
    ],
    "sg:website":"www.bouldermountainfire.org",
    "wof:name":"Boulder Mountain Fire Auth",
    "wof:placetype":"venue"
},
  "geometry": {"coordinates":[-105.309653,40.050315],"type":"Point"}
}