{
  "type": "Feature",
  "properties": {
    "iso:country":"US",
    "sg:address":"2121 Stratford Dr",
    "sg:city":"Montrose",
    "sg:classifiers":[
        {
            "category":"Building & Trades",
            "subcategory":"Construction",
            "type":"Services"
        }
    ],
    "sg:phone":"+1 970 249 9337",
    "sg:postcode":"81401",
    "sg:province":"CO",
    "sg:tags":[
        "general",
        "contractor"
    ],
    "wof:name":"Jackman Construction",
    "wof:placetype":"venue"
},
  "geometry": {"coordinates":[-107.855125,38.471367],"type":"Point"}
}