{
  "type": "Feature",
  "properties": {
    "addr:full":"1016 Coffman St Longmont CO 80501",
    "addr:housenumber":"1016",
    "addr:postcode":"80501",
    "addr:street":"Coffman St",
    "iso:country":"US",
    "sg:address":"1016 Coffman St",
    "sg:city":"Longmont",
    "sg:classifiers":[
        {
            "category":"Wholesale",
            "subcategory":"Hardware",
            "type":"Manufacturing & Wholesale Goods"
        }
    ],
    "sg:phone":"+1 303 776 9934",
    "sg:postcode":"80501",
    "sg:province":"CO",
    "wof:name":"Murphey Heating and AC",
    "wof:placetype":"venue"
},
  "geometry": {"coordinates":[-105.10365899999999,40.177337],"type":"Point"}
}