{
  "type": "Feature",
  "properties": {
    "iso:country":"US",
    "sg:address":"13176 E Linvale Pl",
    "sg:city":"Aurora",
    "sg:classifiers":[
        {
            "category":"Professional",
            "subcategory":"Management & Consulting",
            "type":"Services"
        }
    ],
    "sg:phone":"+1 303 755 4900",
    "sg:postcode":"80014",
    "sg:province":"CO",
    "sg:tags":[
        "counselor",
        "public",
        "relations"
    ],
    "wof:name":"Peifer Communications Inc",
    "wof:placetype":"venue"
},
  "geometry": {"coordinates":[-104.838525,39.666788],"type":"Point"}
}