{
  "type": "Feature",
  "properties": {
    "iso:country":"US",
    "sg:address":"721 Harrison Ave",
    "sg:city":"Leadville",
    "sg:classifiers":[
        {
            "category":"Organizations",
            "subcategory":"Community Association",
            "type":"Services"
        }
    ],
    "sg:phone":"+1 719 486 2352",
    "sg:postcode":"80461",
    "sg:province":"CO",
    "sg:tags":[
        "club"
    ],
    "wof:name":"Independent Order-Odd Fellows",
    "wof:placetype":"venue"
},
  "geometry": {"coordinates":[-106.292526,39.250228],"type":"Point"}
}