{
  "type": "Feature",
  "properties": {
    "iso:country":"US",
    "sg:address":"161 Denargo Market",
    "sg:city":"Denver",
    "sg:classifiers":[
        {
            "category":"Banks & Credit Unions",
            "subcategory":"Financial Services",
            "type":"Services"
        }
    ],
    "sg:phone":"+1 303 297 1902",
    "sg:postcode":"80216",
    "sg:province":"CO",
    "sg:tags":[
        "franchising"
    ],
    "wof:name":"Spicy Pickle Franchise",
    "wof:placetype":"venue"
},
  "geometry": {"coordinates":[-104.990021,39.763184],"type":"Point"}
}