{
  "type": "Feature",
  "properties": {
    "addr:full":"11269 Irma Dr Denver CO 80233",
    "addr:housenumber":"11269",
    "addr:postcode":"80233",
    "addr:street":"Irma Dr",
    "iso:country":"US",
    "sg:address":"11269 Irma Dr",
    "sg:city":"Denver",
    "sg:classifiers":[
        {
            "category":"Manufacturing",
            "subcategory":"Printing",
            "type":"Manufacturing & Wholesale Goods"
        }
    ],
    "sg:phone":"+1 303 457 4805",
    "sg:postcode":"80233",
    "sg:province":"CO",
    "sg:tags":[
        "lithographic",
        "commercial"
    ],
    "wof:name":"Pontious Printing",
    "wof:placetype":"venue"
},
  "geometry": {"coordinates":[-104.966393,39.900321],"type":"Point"}
}