{
  "type": "Feature",
  "properties": {
    "iso:country":"US",
    "sg:address":"3960 Sinton Rd",
    "sg:city":"Colorado Springs",
    "sg:classifiers":[
        {
            "category":"Home & Garden",
            "subcategory":"Hardware",
            "type":"Retail Goods"
        }
    ],
    "sg:phone":"+1 719 520 3372",
    "sg:postcode":"80907",
    "sg:province":"CO",
    "sg:tags":[
        "tool",
        "used"
    ],
    "wof:name":"Tool Wise",
    "wof:placetype":"venue"
},
  "geometry": {"coordinates":[-104.833429,38.887562],"type":"Point"}
}