{
  "type": "Feature",
  "properties": {
    "addr:full":"29320 Co Rd 361 Buena Vista CO 81211",
    "addr:postcode":"29320;81211",
    "addr:street":"Co Rd 361",
    "iso:country":"US",
    "sg:address":"29320 Co Rd 361",
    "sg:city":"Buena Vista",
    "sg:classifiers":[
        {
            "category":"Real Estate",
            "subcategory":"Real Estate Operator",
            "type":"Services"
        }
    ],
    "sg:phone":"+1 719 395 8011",
    "sg:postcode":"81211",
    "sg:province":"CO",
    "sg:tags":[
        "mobile",
        "home",
        "community"
    ],
    "wof:name":"Sleeping Indian Mobile Park",
    "wof:placetype":"venue"
},
  "geometry": {"coordinates":[-106.174481,38.843666],"type":"Point"}
}