{
  "type": "Feature",
  "properties": {
    "addr:full":"2508 Weslo Ave Grand Junction CO 81505",
    "addr:housenumber":"2508",
    "addr:postcode":"81505",
    "addr:street":"Weslo Ave",
    "iso:country":"US",
    "sg:address":"2508 Weslo Ave",
    "sg:city":"Grand Junction",
    "sg:classifiers":[
        {
            "category":"Home & Garden",
            "subcategory":"Furniture",
            "type":"Retail Goods"
        }
    ],
    "sg:phone":"+1 970 241 4655",
    "sg:postcode":"81505",
    "sg:province":"CO",
    "sg:tags":[
        "cabinet"
    ],
    "wof:name":"Advance Cabinet & Carpentry",
    "wof:placetype":"venue"
},
  "geometry": {"coordinates":[-108.586772,39.088753],"type":"Point"}
}