{
  "type": "Feature",
  "properties": {
    "addr:full":"5600 W Dartmouth Ave Ste 108 Denver CO 80227",
    "addr:housenumber":"5600",
    "addr:postcode":"80227",
    "addr:street":"W Dartmouth Ave Ste 108",
    "iso:country":"US",
    "sg:address":"5600 W Dartmouth Ave Ste 108",
    "sg:city":"Denver",
    "sg:classifiers":[
        {
            "category":"Retail",
            "subcategory":"Laundry & Dry Cleaning",
            "type":"Services"
        }
    ],
    "sg:phone":"+1 303 985 2433",
    "sg:postcode":"80227",
    "sg:province":"CO",
    "sg:tags":[
        "cleaner",
        "commercial"
    ],
    "wof:name":"Apple Cleaners",
    "wof:placetype":"venue"
},
  "geometry": {"coordinates":[-105.055573,39.655899],"type":"Point"}
}