{
  "type": "Feature",
  "properties": {
    "addr:full":"1336 E 17th Ave Denver CO 80218",
    "addr:housenumber":"1336",
    "addr:postcode":"80218",
    "addr:street":"E 17Th Ave",
    "iso:country":"US",
    "sg:address":"1336 E 17th Ave",
    "sg:city":"Denver",
    "sg:classifiers":[
        {
            "category":"Building & Trades",
            "subcategory":"Locksmith",
            "type":"Services"
        }
    ],
    "sg:phone":"+1 303 218 7350",
    "sg:postcode":"80218",
    "sg:province":"CO",
    "sg:tags":[
        "key"
    ],
    "wof:name":"Locksmith Emergency",
    "wof:placetype":"venue"
},
  "geometry": {"coordinates":[-104.97045,39.743089],"type":"Point"}
}