{
  "type": "Feature",
  "properties": {
    "addr:full":"5797 Quebec St Commerce City CO 80022",
    "addr:housenumber":"5797",
    "addr:postcode":"80022",
    "addr:street":"Quebec St",
    "iso:country":"US",
    "sg:address":"5797 Quebec St",
    "sg:city":"Commerce City",
    "sg:classifiers":[
        {
            "category":"Bars & Pubs",
            "type":"Food & Drink"
        },
        {
            "category":"Restaurant",
            "type":"Food & Drink"
        }
    ],
    "sg:phone":"+1 303 288 8390",
    "sg:postcode":"80022",
    "sg:province":"CO",
    "sg:tags":[
        "traditional",
        "american"
    ],
    "sg:website":"www.myspace.com/shiftersbarandgrill",
    "wof:name":"Shifters",
    "wof:placetype":"venue"
},
  "geometry": {"coordinates":[-104.903977,39.801768],"type":"Point"}
}