{
  "type": "Feature",
  "properties": {
    "addr:full":"3511 Wedgewood Dr Pueblo CO 81005",
    "addr:housenumber":"3511",
    "addr:postcode":"81005",
    "addr:street":"Wedgewood Dr",
    "iso:country":"US",
    "sg:address":"3511 Wedgewood Dr",
    "sg:city":"Pueblo",
    "sg:classifiers":[
        {
            "category":"Freight",
            "type":"Transportation"
        }
    ],
    "sg:phone":"+1 719 566 1404",
    "sg:postcode":"81005",
    "sg:province":"CO",
    "sg:tags":[
        "operator",
        "local",
        "trucking"
    ],
    "wof:name":"Hollis ML Trucking",
    "wof:placetype":"venue"
},
  "geometry": {"coordinates":[-104.64950399999999,38.242056],"type":"Point"}
}