{
  "type": "Feature",
  "properties": {
    "iso:country":"US",
    "sg:address":"1345 28th Street Frontage Rd",
    "sg:city":"Boulder",
    "sg:classifiers":[
        {
            "category":"Restaurant",
            "type":"Food & Drink"
        }
    ],
    "sg:phone":"+1 303 443 3850",
    "sg:postcode":"80302",
    "sg:province":"CO",
    "sg:tags":[
        "eating"
    ],
    "wof:name":"Thyme On The Creek",
    "wof:placetype":"venue"
},
  "geometry": {"coordinates":[-105.258365,40.011032],"type":"Point"}
}