{
  "type": "Feature",
  "properties": {
    "addr:full":"2429 N Union Blvd Colorado Springs CO 80909",
    "addr:housenumber":"2429",
    "addr:postcode":"80909",
    "addr:street":"N Union Blvd",
    "iso:country":"US",
    "sg:address":"2429 N Union Blvd",
    "sg:city":"Colorado Springs",
    "sg:classifiers":[
        {
            "category":"Professional",
            "type":"Services"
        }
    ],
    "sg:phone":"+1 719 635 4500",
    "sg:postcode":"80909",
    "sg:province":"CO",
    "wof:name":"Stephen Song",
    "wof:placetype":"venue"
},
  "geometry": {"coordinates":[-104.794068,38.867248],"type":"Point"}
}