{
  "type": "Feature",
  "properties": {
    "addr:full":"840 Oak St Salida CO 81201",
    "addr:housenumber":"840",
    "addr:postcode":"81201",
    "addr:street":"Oak St",
    "iso:country":"US",
    "sg:address":"840 Oak St",
    "sg:city":"Salida",
    "sg:classifiers":[
        {
            "category":"Real Estate",
            "subcategory":"Real Estate Agent",
            "type":"Services"
        }
    ],
    "sg:phone":"+1 719 539 6616",
    "sg:postcode":"81201",
    "sg:province":"CO",
    "wof:name":"Century 21",
    "wof:placetype":"venue"
},
  "geometry": {"coordinates":[-105.984686,38.524065],"type":"Point"}
}