{
  "type": "Feature",
  "properties": {
    "addr:full":"12469 Mariposa Ct Denver CO 80234",
    "addr:housenumber":"12469",
    "addr:postcode":"80234",
    "addr:street":"Mariposa Ct",
    "iso:country":"US",
    "sg:address":"12469 Mariposa Ct",
    "sg:city":"Denver",
    "sg:classifiers":[
        {
            "category":"Manufacturing",
            "subcategory":"Food",
            "type":"Manufacturing & Wholesale Goods"
        }
    ],
    "sg:phone":"+1 303 450 7127",
    "sg:postcode":"80234",
    "sg:province":"CO",
    "sg:tags":[
        "liquor",
        "mfg"
    ],
    "wof:name":"Jim Beam Brands Company",
    "wof:placetype":"venue"
},
  "geometry": {"coordinates":[-105.00335099999999,39.924255],"type":"Point"}
}