{
  "type": "Feature",
  "properties": {
    "iso:country":"US",
    "sg:address":"160 2nd St",
    "sg:city":"Clifton",
    "sg:classifiers":[
        {
            "category":"Retail",
            "subcategory":"Self-service Laundry",
            "type":"Services"
        }
    ],
    "sg:phone":"+1 970 434 9733",
    "sg:postcode":"81520",
    "sg:province":"CO",
    "wof:name":"Wash Up Doc Laundromat",
    "wof:placetype":"venue"
},
  "geometry": {"coordinates":[-108.44940699999999,39.088671],"type":"Point"}
}