{
  "type": "Feature",
  "properties": {
    "iso:country":"US",
    "sg:address":"5165 Independence Rd",
    "sg:city":"Boulder",
    "sg:classifiers":[
        {
            "category":"Building & Trades",
            "subcategory":"Construction",
            "type":"Services"
        }
    ],
    "sg:phone":"+1 303 530 2696",
    "sg:postcode":"80301",
    "sg:province":"CO",
    "sg:tags":[
        "excavation",
        "contractor"
    ],
    "wof:name":"Juhls Excavating",
    "wof:placetype":"venue"
},
  "geometry": {"coordinates":[-105.23474299999999,40.04022],"type":"Point"}
}