{
  "type": "Feature",
  "properties": {
    "iso:country":"US",
    "sg:address":"2000 Ski Time Square Dr",
    "sg:city":"Steamboat Spgs",
    "sg:classifiers":[
        {
            "category":"Shopping",
            "subcategory":"Bicycles & Sporting Goods",
            "type":"Retail Goods"
        }
    ],
    "sg:phone":"+1 970 879 1100",
    "sg:postcode":"80487",
    "sg:province":"CO",
    "sg:tags":[
        "snowboard"
    ],
    "wof:name":"Max Snowboard Rentals",
    "wof:placetype":"venue"
},
  "geometry": {"coordinates":[-106.801365,40.46055],"type":"Point"}
}