{
  "type": "Feature",
  "properties": {
    "addr:full":"13401 W 43rd Dr Golden CO 80403",
    "addr:housenumber":"13401",
    "addr:postcode":"80403",
    "addr:street":"W 43Rd Dr",
    "iso:country":"US",
    "sg:address":"13401 W 43rd Dr",
    "sg:city":"Golden",
    "sg:classifiers":[
        {
            "category":"Shopping",
            "type":"Retail Goods"
        }
    ],
    "sg:phone":"+1 303 216 2883",
    "sg:postcode":"80403",
    "sg:province":"CO",
    "sg:tags":[
        "pet",
        "shop"
    ],
    "wof:name":"Best Pet Co",
    "wof:placetype":"venue"
},
  "geometry": {"coordinates":[-105.148348,39.776768],"type":"Point"}
}