{
  "type": "Feature",
  "properties": {
    "iso:country":"US",
    "sg:address":"431 S Camp Rd",
    "sg:city":"Grand Junction",
    "sg:classifiers":[
        {
            "category":"Building & Trades",
            "subcategory":"Construction",
            "type":"Services"
        }
    ],
    "sg:phone":"+1 970 254 8777",
    "sg:postcode":"81503",
    "sg:province":"CO",
    "sg:tags":[
        "general",
        "contractor"
    ],
    "wof:name":"Jolly Construction Inc",
    "wof:placetype":"venue"
},
  "geometry": {"coordinates":[-108.64481499999999,39.072576],"type":"Point"}
}