{
  "type": "Feature",
  "properties": {
    "addr:full":"401 E 7th St Walsenburg CO 81089",
    "addr:housenumber":"401",
    "addr:postcode":"81089",
    "addr:street":"E 7Th St",
    "iso:country":"US",
    "sg:address":"401 E 7th St",
    "sg:city":"Walsenburg",
    "sg:classifiers":[
        {
            "category":"Wholesale",
            "subcategory":"Stationery",
            "type":"Manufacturing & Wholesale Goods"
        }
    ],
    "sg:phone":"+1 719 738 1364",
    "sg:postcode":"81089",
    "sg:province":"CO",
    "sg:tags":[
        "bag"
    ],
    "wof:name":"Ocana Julian Paul",
    "wof:placetype":"venue"
},
  "geometry": {"coordinates":[-104.773518,37.625046],"type":"Point"}
}