{
  "type": "Feature",
  "properties": {
    "iso:country":"US",
    "sg:address":"455 Rio Grande Pl",
    "sg:city":"Aspen",
    "sg:classifiers":[
        {
            "category":"Organizations",
            "subcategory":"Religious Organization",
            "type":"Services"
        }
    ],
    "sg:phone":"+1 970 704 1828",
    "sg:postcode":"81611",
    "sg:province":"CO",
    "sg:tags":[
        "church"
    ],
    "wof:name":"Aspen Christian World Outreach",
    "wof:placetype":"venue"
},
  "geometry": {"coordinates":[-106.81785600000001,39.191658],"type":"Point"}
}