{
  "type": "Feature",
  "properties": {
    "addr:full":"58 Broadway Denver CO 80203",
    "addr:housenumber":"58",
    "addr:postcode":"80203",
    "addr:street":"Broadway",
    "iso:country":"US",
    "sg:address":"58 Broadway",
    "sg:city":"Denver",
    "sg:classifiers":[
        {
            "category":"Bars & Pubs",
            "type":"Food & Drink"
        }
    ],
    "sg:phone":"+1 303 722 8489",
    "sg:postcode":"80203",
    "sg:province":"CO",
    "sg:tags":[
        "nightlife"
    ],
    "wof:name":"Barrys On Broadway",
    "wof:placetype":"venue"
},
  "geometry": {"coordinates":[-104.987112,39.717722],"type":"Point"}
}