{
  "type": "Feature",
  "properties": {
    "addr:full":"14133 W Exposition Dr Denver CO 80228",
    "addr:housenumber":"14133",
    "addr:postcode":"80228",
    "addr:street":"W Exposition Dr",
    "iso:country":"US",
    "sg:address":"14133 W Exposition Dr",
    "sg:city":"Denver",
    "sg:classifiers":[
        {
            "category":"Shopping",
            "type":"Retail Goods"
        }
    ],
    "sg:phone":"+1 303 985 3974",
    "sg:postcode":"80228",
    "sg:province":"CO",
    "sg:tags":[
        "art",
        "gallery",
        "merchandise",
        "dealer"
    ],
    "wof:name":"Duquette Art Studio",
    "wof:placetype":"venue"
},
  "geometry": {"coordinates":[-105.15757600000001,39.704631],"type":"Point"}
}