{
  "type": "Feature",
  "properties": {
    "addr:full":"609 Hillcrest Dr Basalt CO 81621",
    "addr:housenumber":"609",
    "addr:postcode":"81621",
    "addr:street":"Hillcrest Dr",
    "iso:country":"US",
    "sg:address":"609 Hillcrest Dr",
    "sg:city":"Basalt",
    "sg:classifiers":[
        {
            "category":"Real Estate",
            "subcategory":"Real Estate Agent",
            "type":"Services"
        }
    ],
    "sg:phone":"+1 970 927 1223",
    "sg:postcode":"81621",
    "sg:province":"CO",
    "wof:name":"Aspen Highlands Townhome Seven",
    "wof:placetype":"venue"
},
  "geometry": {"coordinates":[-107.066734,39.371059],"type":"Point"}
}