{
  "type": "Feature",
  "properties": {
    "iso:country":"US",
    "sg:address":"6581 S Otis Way",
    "sg:city":"Littleton",
    "sg:classifiers":[
        {
            "category":"Autos & Motor Vehicles",
            "subcategory":"Fuel & Gas Station",
            "type":"Retail Goods"
        }
    ],
    "sg:phone":"+1 720 981 8107",
    "sg:postcode":"80123",
    "sg:province":"CO",
    "sg:tags":[
        "convenience",
        "gasoline",
        "store"
    ],
    "wof:name":"Conoco",
    "wof:placetype":"venue"
},
  "geometry": {"coordinates":[-105.071496,39.597635],"type":"Point"}
}