{
  "type": "Feature",
  "properties": {
    "addr:full":"13488 W 74th Pl Arvada CO 80005",
    "addr:housenumber":"13488",
    "addr:postcode":"80005",
    "addr:street":"W 74Th Pl",
    "iso:country":"US",
    "sg:address":"13488 W 74th Pl",
    "sg:city":"Arvada",
    "sg:classifiers":[
        {
            "category":"Professional",
            "type":"Services"
        }
    ],
    "sg:phone":"+1 303 403 4125",
    "sg:postcode":"80005",
    "sg:province":"CO",
    "sg:tags":[
        "technical",
        "writing"
    ],
    "wof:name":"Mitchell International",
    "wof:placetype":"venue"
},
  "geometry": {"coordinates":[-105.15264500000001,39.831447],"type":"Point"}
}