{
  "type": "Feature",
  "properties": {
    "addr:full":"2270 Teller St Lakewood CO 80214",
    "addr:housenumber":"2270",
    "addr:postcode":"80214",
    "addr:street":"Teller St",
    "iso:country":"US",
    "sg:address":"2270 Teller St",
    "sg:city":"Lakewood",
    "sg:classifiers":[
        {
            "category":"Communications",
            "subcategory":"Film & Video Production",
            "type":"Services"
        }
    ],
    "sg:phone":"+1 303 274 1144",
    "sg:postcode":"80214",
    "sg:province":"CO",
    "sg:tags":[
        "audio"
    ],
    "sg:website":"www.tittyclub.com",
    "wof:name":"Rare Moment",
    "wof:placetype":"venue"
},
  "geometry": {"coordinates":[-105.07662000000001,39.749177],"type":"Point"}
}