{
  "type": "Feature",
  "properties": {
    "addr:full":"203 S Main St Rocky Ford CO 81067",
    "addr:housenumber":"203",
    "addr:postcode":"81067",
    "addr:street":"S Main St",
    "iso:country":"US",
    "sg:address":"203 S Main St",
    "sg:city":"Rocky Ford",
    "sg:classifiers":[
        {
            "category":"Government",
            "subcategory":"Office",
            "type":"Public Place"
        }
    ],
    "sg:phone":"+1 719 254 7414",
    "sg:postcode":"81067",
    "sg:province":"CO",
    "sg:tags":[
        "city"
    ],
    "wof:name":"Rocky Ford City Hall",
    "wof:placetype":"venue"
},
  "geometry": {"coordinates":[-103.72021599999999,38.052325],"type":"Point"}
}