{
  "type": "Feature",
  "properties": {
    "addr:full":"7802 W Ottawa Pl Littleton CO 80128",
    "addr:housenumber":"7802",
    "addr:postcode":"80128",
    "addr:street":"W Ottawa Pl",
    "iso:country":"US",
    "sg:address":"7802 W Ottawa Pl",
    "sg:city":"Littleton",
    "sg:classifiers":[
        {
            "category":"Manufacturing",
            "subcategory":"Electronics",
            "type":"Manufacturing & Wholesale Goods"
        }
    ],
    "sg:phone":"+1 303 979 5271",
    "sg:postcode":"80128",
    "sg:province":"CO",
    "sg:tags":[
        "apparatus",
        "mfg"
    ],
    "sg:website":"www.plantronics.com",
    "wof:name":"Plantronics Inc",
    "wof:placetype":"venue"
},
  "geometry": {"coordinates":[-105.086929,39.592043],"type":"Point"}
}