{
  "type": "Feature",
  "properties": {
    "iso:country":"US",
    "sg:address":"70 N 4th Ave",
    "sg:city":"Brighton",
    "sg:classifiers":[
        {
            "category":"Insurance",
            "subcategory":"Insurance Agent",
            "type":"Services"
        }
    ],
    "sg:phone":"+1 303 659 0190",
    "sg:postcode":"80601",
    "sg:province":"CO",
    "wof:name":"American Family Insurance",
    "wof:placetype":"venue"
},
  "geometry": {"coordinates":[-104.818073,39.988247],"type":"Point"}
}