{
  "type": "Feature",
  "properties": {
    "iso:country":"US",
    "sg:address":"4320 N Freeway Rd",
    "sg:city":"Pueblo",
    "sg:classifiers":[
        {
            "category":"Home & Garden",
            "subcategory":"Household Appliances",
            "type":"Retail Goods"
        }
    ],
    "sg:phone":"+1 719 543 5400",
    "sg:postcode":"81008",
    "sg:province":"CO",
    "wof:name":"Circuit City",
    "wof:placetype":"venue"
},
  "geometry": {"coordinates":[-104.614806,38.314569],"type":"Point"}
}