{
  "type": "Feature",
  "properties": {
    "iso:country":"US",
    "sg:address":"9927 Phillips Rd",
    "sg:city":"Lafayette",
    "sg:classifiers":[
        {
            "category":"Professional",
            "subcategory":"Computer Services",
            "type":"Services"
        }
    ],
    "sg:phone":"+1 303 666 4330",
    "sg:postcode":"80026",
    "sg:province":"CO",
    "sg:tags":[
        "development",
        "software"
    ],
    "wof:name":"Sophsys Inc",
    "wof:placetype":"venue"
},
  "geometry": {"coordinates":[-105.11557999999999,40.061583],"type":"Point"}
}