{
  "type": "Feature",
  "properties": {
    "addr:full":"429 S Nevada Ave Colorado Springs CO 80903",
    "addr:housenumber":"429",
    "addr:postcode":"80903",
    "addr:street":"S Nevada Ave",
    "iso:country":"US",
    "sg:address":"429 S Nevada Ave",
    "sg:city":"Colorado Springs",
    "sg:classifiers":[
        {
            "category":"Autos & Motor Vehicles",
            "subcategory":"Automobile Sales",
            "type":"Retail Goods"
        }
    ],
    "sg:phone":"+1 719 633 4815",
    "sg:postcode":"80903",
    "sg:province":"CO",
    "sg:tags":[
        "car",
        "dealer"
    ],
    "wof:name":"Landmark Motors",
    "wof:placetype":"venue"
},
  "geometry": {"coordinates":[-104.82184599999999,38.827198],"type":"Point"}
}