{
  "type": "Feature",
  "properties": {
    "addr:full":"358 S Teller St Denver CO 80226",
    "addr:housenumber":"358",
    "addr:postcode":"80226",
    "addr:street":"S Teller St",
    "iso:country":"US",
    "sg:address":"358 S Teller St",
    "sg:city":"Denver",
    "sg:classifiers":[
        {
            "category":"Personal",
            "subcategory":"Massage",
            "type":"Services"
        },
        {
            "category":"Personal",
            "subcategory":"Hair Removal",
            "type":"Services"
        },
        {
            "category":"Personal",
            "subcategory":"Barber",
            "type":"Services"
        }
    ],
    "sg:phone":"+1 303 934 5700",
    "sg:postcode":"80226",
    "sg:province":"CO",
    "sg:website":"www.shearproductions.com",
    "wof:name":"Shear Productions",
    "wof:placetype":"venue"
},
  "geometry": {"coordinates":[-105.076882,39.709967],"type":"Point"}
}