{
  "type": "Feature",
  "properties": {
    "iso:country":"US",
    "sg:address":"503 Mallard Dr",
    "sg:city":"Windsor",
    "sg:classifiers":[
        {
            "category":"Manufacturing",
            "subcategory":"Lumber",
            "type":"Manufacturing & Wholesale Goods"
        }
    ],
    "sg:phone":"+1 970 218 0918",
    "sg:postcode":"80550",
    "sg:province":"CO",
    "sg:tags":[
        "wildfire",
        "hazard"
    ],
    "wof:name":"Rocky Mtn Wldfire Prvntion LLP",
    "wof:placetype":"venue"
},
  "geometry": {"coordinates":[-104.852547,40.519927],"type":"Point"}
}