{
  "type": "Feature",
  "properties": {
    "iso:country":"US",
    "sg:address":"1645 Briargate Blvd",
    "sg:city":"Colorado Springs",
    "sg:classifiers":[
        {
            "category":"Shopping",
            "type":"Retail Goods"
        }
    ],
    "sg:phone":"+1 719 262 0589",
    "sg:postcode":"80920",
    "sg:province":"CO",
    "sg:tags":[
        "merchandise"
    ],
    "wof:name":"White House Stores",
    "wof:placetype":"venue"
},
  "geometry": {"coordinates":[-104.79772800000001,38.945206],"type":"Point"}
}