{
  "type": "Feature",
  "properties": {
    "addr:full":"557 Burbank St Broomfield CO 80020",
    "addr:housenumber":"557",
    "addr:postcode":"80020",
    "addr:street":"Burbank St",
    "iso:country":"US",
    "sg:address":"557 Burbank St",
    "sg:city":"Broomfield",
    "sg:phone":"+1 303 469 5266",
    "sg:postcode":"80020",
    "sg:province":"CO",
    "sg:tags":[
        "partition"
    ],
    "wof:name":"Simpson & Simpson Sales & Svc",
    "wof:placetype":"venue"
},
  "geometry": {"coordinates":[-105.095439,39.923479],"type":"Point"}
}