{
  "type": "Feature",
  "properties": {
    "iso:country":"US",
    "sg:address":"2007 Capulin Dr",
    "sg:city":"Colorado Springs",
    "sg:classifiers":[
        {
            "category":"Building & Trades",
            "subcategory":"Cleaning & Sanitation",
            "type":"Services"
        }
    ],
    "sg:phone":"+1 719 475 2872",
    "sg:postcode":"80910",
    "sg:province":"CO",
    "sg:tags":[
        "janitor"
    ],
    "wof:name":"Absolute Quality Janitorial",
    "wof:placetype":"venue"
},
  "geometry": {"coordinates":[-104.770415,38.803468],"type":"Point"}
}