{
  "type": "Feature",
  "properties": {
    "addr:full":"618 W Tomichi Ave Gunnison CO 81230",
    "addr:housenumber":"618",
    "addr:postcode":"81230",
    "addr:street":"W Tomichi Ave",
    "iso:country":"US",
    "sg:address":"618 W Tomichi Ave",
    "sg:city":"Gunnison",
    "sg:classifiers":[
        {
            "category":"Shopping",
            "type":"Retail Goods"
        }
    ],
    "sg:phone":"+1 970 642 1200",
    "sg:postcode":"81230",
    "sg:province":"CO",
    "sg:tags":[
        "merchandise"
    ],
    "wof:name":"Year Round Gar Sls & Pet Str",
    "wof:placetype":"venue"
},
  "geometry": {"coordinates":[-106.934183,38.544486],"type":"Point"}
}