{
  "type": "Feature",
  "properties": {
    "iso:country":"US",
    "sg:address":"640 W Tennessee Ave C",
    "sg:city":"Denver",
    "sg:classifiers":[
        {
            "category":"Building & Trades",
            "subcategory":"Construction",
            "type":"Services"
        }
    ],
    "sg:phone":"+1 303 778 8771",
    "sg:postcode":"80223",
    "sg:province":"CO",
    "sg:tags":[
        "plastering",
        "contractor"
    ],
    "wof:name":"Shamrock Plastering Company",
    "wof:placetype":"venue"
},
  "geometry": {"coordinates":[-104.994944,39.698502],"type":"Point"}
}