{
  "type": "Feature",
  "properties": {
    "addr:full":"7409 S Steele Cir Littleton CO 80122",
    "addr:housenumber":"7409",
    "addr:postcode":"80122",
    "addr:street":"S Steele Cir",
    "iso:country":"US",
    "sg:address":"7409 S Steele Cir",
    "sg:city":"Littleton",
    "sg:classifiers":[
        {
            "category":"Shopping",
            "subcategory":"Catalog Store",
            "type":"Retail Goods"
        }
    ],
    "sg:phone":"+1 303 220 1084",
    "sg:postcode":"80122",
    "sg:province":"CO",
    "sg:tags":[
        "mail",
        "merchandise",
        "house"
    ],
    "wof:name":"Pattys Paintings Collectibles",
    "wof:placetype":"venue"
},
  "geometry": {"coordinates":[-104.95112399999999,39.582534],"type":"Point"}
}