{
  "type": "Feature",
  "properties": {
    "iso:country":"US",
    "sg:address":"1492 Carr St",
    "sg:city":"Lakewood",
    "sg:classifiers":[
        {
            "category":"Personal",
            "subcategory":"Barber",
            "type":"Services"
        }
    ],
    "sg:phone":"+1 303 238 1397",
    "sg:postcode":"80214",
    "sg:province":"CO",
    "wof:name":"Sebring Hair Design-Lakewood",
    "wof:placetype":"venue"
},
  "geometry": {"coordinates":[-105.090684,39.738533],"type":"Point"}
}