{
  "type": "Feature",
  "properties": {
    "addr:full":"2950 S Jamaica Ct Aurora CO 80014",
    "addr:housenumber":"2950",
    "addr:postcode":"80014",
    "addr:street":"S Jamaica Ct",
    "iso:country":"US",
    "sg:address":"2950 S Jamaica Ct",
    "sg:city":"Aurora",
    "sg:classifiers":[
        {
            "category":"Manufacturing",
            "subcategory":"Tools & Machinery",
            "type":"Manufacturing & Wholesale Goods"
        }
    ],
    "sg:phone":"+1 303 755 0112",
    "sg:postcode":"80014",
    "sg:province":"CO",
    "sg:tags":[
        "surgical",
        "mfg"
    ],
    "wof:name":"AMD",
    "wof:placetype":"venue"
},
  "geometry": {"coordinates":[-104.86224,39.661018],"type":"Point"}
}