{
  "type": "Feature",
  "properties": {
    "iso:country":"US",
    "sg:address":"2741 Mapleton Ave",
    "sg:city":"Boulder",
    "sg:classifiers":[
        {
            "category":"Banks & Credit Unions",
            "subcategory":"Bank",
            "type":"Services"
        }
    ],
    "sg:phone":"+1 303 546 0004",
    "sg:postcode":"80304",
    "sg:province":"CO",
    "sg:tags":[
        "broker",
        "mortgage"
    ],
    "wof:name":"Spiritmoney Mortgage Services",
    "wof:placetype":"venue"
},
  "geometry": {"coordinates":[-105.258897,40.025515],"type":"Point"}
}