{
  "type": "Feature",
  "properties": {
    "iso:country":"US",
    "sg:address":"2303 E Dartmouth Avenue",
    "sg:city":"Englewood",
    "sg:classifiers":[
        {
            "category":"Professional",
            "subcategory":"Lawyer & Legal Services",
            "type":"Services"
        }
    ],
    "sg:phone":"+1 303 504 0055",
    "sg:postcode":"80113",
    "sg:province":"CO",
    "wof:name":"Von Gunten Law",
    "wof:placetype":"venue"
},
  "geometry": {"coordinates":[-104.96112100000001,39.660462],"type":"Point"}
}