{
  "type": "Feature",
  "properties": {
    "iso:country":"US",
    "sg:address":"100 Stagecoach Cir",
    "sg:city":"Carbondale",
    "sg:classifiers":[
        {
            "category":"Professional",
            "subcategory":"Art Services",
            "type":"Services"
        }
    ],
    "sg:phone":"+1 970 963 0893",
    "sg:postcode":"81623",
    "sg:province":"CO",
    "sg:tags":[
        "photographer"
    ],
    "wof:name":"Jim Noelker Photography",
    "wof:placetype":"venue"
},
  "geometry": {"coordinates":[-107.172562,39.408982],"type":"Point"}
}