{
  "type": "Feature",
  "properties": {
    "addr:full":"8585 W 14th Ave Lakewood CO 80215",
    "addr:housenumber":"8585",
    "addr:postcode":"80215",
    "addr:street":"W 14Th Ave",
    "iso:country":"US",
    "sg:address":"8585 W 14th Ave",
    "sg:city":"Lakewood",
    "sg:classifiers":[
        {
            "category":"Government",
            "subcategory":"Office",
            "type":"Public Place"
        }
    ],
    "sg:phone":"+1 303 234 5540",
    "sg:postcode":"80215",
    "sg:province":"CO",
    "sg:tags":[
        "federal",
        "human"
    ],
    "wof:name":"US Social Security Adm",
    "wof:placetype":"venue"
},
  "geometry": {"coordinates":[-105.094618,39.738506],"type":"Point"}
}