{
  "type": "Feature",
  "properties": {
    "iso:country":"US",
    "sg:address":"9499 Washington St",
    "sg:city":"Thornton",
    "sg:classifiers":[
        {
            "category":"Recreation",
            "subcategory":"Amusement Park",
            "type":"Entertainment"
        }
    ],
    "sg:phone":"+1 303 487 7351",
    "sg:postcode":"80229",
    "sg:province":"CO",
    "wof:name":"X-Treme Fun",
    "wof:placetype":"venue"
},
  "geometry": {"coordinates":[-104.977981,39.864389],"type":"Point"}
}