{
  "type": "Feature",
  "properties": {
    "addr:full":"3050 Austin Bluffs Pkwy Colorado Springs CO 80918",
    "addr:housenumber":"3050",
    "addr:postcode":"80918",
    "addr:street":"Austin Bluffs Pkwy",
    "iso:country":"US",
    "sg:address":"3050 Austin Bluffs Pkwy",
    "sg:city":"Colorado Springs",
    "sg:classifiers":[
        {
            "category":"Professional",
            "subcategory":"Management & Consulting",
            "type":"Services"
        }
    ],
    "sg:phone":"+1 719 594 9518",
    "sg:postcode":"80918",
    "sg:province":"CO",
    "sg:tags":[
        "retail",
        "direct",
        "sales"
    ],
    "wof:name":"Val-Pak of Southern Colorado",
    "wof:placetype":"venue"
},
  "geometry": {"coordinates":[-104.767286,38.890524],"type":"Point"}
}