{
  "type": "Feature",
  "properties": {
    "addr:full":"13022 Steele Ct Denver CO 80241",
    "addr:housenumber":"13022",
    "addr:postcode":"80241",
    "addr:street":"Steele Ct",
    "iso:country":"US",
    "sg:address":"13022 Steele Ct",
    "sg:city":"Denver",
    "sg:classifiers":[
        {
            "category":"Building & Trades",
            "subcategory":"Landscaping Services",
            "type":"Services"
        }
    ],
    "sg:phone":"+1 303 457 0139",
    "sg:postcode":"80241",
    "sg:province":"CO",
    "sg:tags":[
        "landscape",
        "contractor"
    ],
    "wof:name":"Accurate Landscaping",
    "wof:placetype":"venue"
},
  "geometry": {"coordinates":[-104.9481,39.93117],"type":"Point"}
}