{
  "type": "Feature",
  "properties": {
    "iso:country":"US",
    "sg:address":"16442 State Hwy 136",
    "sg:city":"La Jara",
    "sg:classifiers":[
        {
            "category":"Retail",
            "subcategory":"Veterinary Services",
            "type":"Services"
        }
    ],
    "sg:phone":"+1 719 274 5752",
    "sg:postcode":"81140",
    "sg:province":"CO",
    "sg:tags":[
        "veterinarian"
    ],
    "wof:name":"Haynie Animal Clinic",
    "wof:placetype":"venue"
},
  "geometry": {"coordinates":[-105.95507000000001,37.268818],"type":"Point"}
}