{
  "type": "Feature",
  "properties": {
    "iso:country":"US",
    "sg:address":"1567 US Hwy 160",
    "sg:city":"Monte Vista",
    "sg:classifiers":[
        {
            "category":"Wholesale",
            "subcategory":"Machinery & Supplies",
            "type":"Manufacturing & Wholesale Goods"
        }
    ],
    "sg:phone":"+1 719 852 5174",
    "sg:postcode":"81144",
    "sg:province":"CO",
    "sg:tags":[
        "pump"
    ],
    "wof:name":"Irrigation Engineering",
    "wof:placetype":"venue"
},
  "geometry": {"coordinates":[-106.182187,37.582067],"type":"Point"}
}