{
  "type": "Feature",
  "properties": {
    "iso:country":"US",
    "sg:address":"3816 S Lincoln St",
    "sg:city":"Englewood",
    "sg:classifiers":[
        {
            "category":"Manufacturing",
            "subcategory":"Printing",
            "type":"Manufacturing & Wholesale Goods"
        }
    ],
    "sg:phone":"+1 303 789 3833",
    "sg:postcode":"80113",
    "sg:province":"CO",
    "sg:tags":[
        "publishing",
        "typesetting"
    ],
    "wof:name":"Noteable Impressions",
    "wof:placetype":"venue"
},
  "geometry": {"coordinates":[-104.98641600000001,39.646112],"type":"Point"}
}