{
  "type": "Feature",
  "properties": {
    "iso:country":"US",
    "sg:address":"12340 W Alameda Pkwy",
    "sg:city":"Denver",
    "sg:classifiers":[
        {
            "category":"Professional",
            "type":"Services"
        },
        {
            "category":"Real Estate",
            "subcategory":"Real Estate Agent",
            "type":"Services"
        }
    ],
    "sg:phone":"+1 303 987 9000",
    "sg:postcode":"80228",
    "sg:province":"CO",
    "sg:tags":[
        "commercial",
        "space"
    ],
    "wof:name":"Apple Pie Properties III LLC",
    "wof:placetype":"venue"
},
  "geometry": {"coordinates":[-105.138863,39.703686],"type":"Point"}
}