{
  "type": "Feature",
  "properties": {
    "iso:country":"US",
    "sg:address":"6909 E Fremont Ave",
    "sg:city":"Centennial",
    "sg:classifiers":[
        {
            "category":"Professional",
            "subcategory":"Accounting & Tax Preparation",
            "type":"Services"
        }
    ],
    "sg:phone":"+1 303 843 9900",
    "sg:postcode":"80112",
    "sg:province":"CO",
    "sg:tags":[
        "accountant"
    ],
    "wof:name":"Les Bates & Assoc Inc",
    "wof:placetype":"venue"
},
  "geometry": {"coordinates":[-104.90856599999999,39.585999],"type":"Point"}
}