{
  "type": "Feature",
  "properties": {
    "iso:country":"US",
    "sg:address":"6821 Jordan Dr",
    "sg:city":"Denver",
    "sg:classifiers":[
        {
            "category":"Building & Trades",
            "subcategory":"Construction",
            "type":"Services"
        }
    ],
    "sg:phone":"+1 303 412 5899",
    "sg:postcode":"80221",
    "sg:province":"CO",
    "sg:tags":[
        "contractor"
    ],
    "wof:name":"Garcia Drywall",
    "wof:placetype":"venue"
},
  "geometry": {"coordinates":[-105.01512200000001,39.820205],"type":"Point"}
}