{
  "type": "Feature",
  "properties": {
    "iso:country":"US",
    "sg:address":"163 E 10th St",
    "sg:city":"Durango",
    "sg:classifiers":[
        {
            "category":"Building & Trades",
            "subcategory":"Plumbing",
            "type":"Services"
        }
    ],
    "sg:phone":"+1 970 247 1040",
    "sg:postcode":"81301",
    "sg:province":"CO",
    "sg:tags":[
        "plumbing",
        "contractor"
    ],
    "wof:name":"Roto-Rooter Plumbing & Drain",
    "wof:placetype":"venue"
},
  "geometry": {"coordinates":[-107.87952799999999,37.274362],"type":"Point"}
}