{
  "type": "Feature",
  "properties": {
    "iso:country":"US",
    "sg:address":"18 Co Rd 77",
    "sg:city":"Jefferson",
    "sg:classifiers":[
        {
            "category":"Banks & Credit Unions",
            "subcategory":"Bank",
            "type":"Services"
        }
    ],
    "sg:phone":"+1 719 836 2901",
    "sg:postcode":"80456",
    "sg:province":"CO",
    "sg:tags":[
        "loan",
        "real estate"
    ],
    "wof:name":"South Park Mortgage",
    "wof:placetype":"venue"
},
  "geometry": {"coordinates":[-105.78645,39.36109],"type":"Point"}
}