{
  "type": "Feature",
  "properties": {
    "iso:country":"US",
    "sg:address":"7529 S Turkey Creek Rd",
    "sg:city":"Morrison",
    "sg:classifiers":[
        {
            "category":"Restaurant",
            "type":"Food & Drink"
        }
    ],
    "sg:phone":"+1 303 697 1731",
    "sg:postcode":"80465",
    "sg:province":"CO",
    "sg:tags":[
        "eating"
    ],
    "wof:name":"Steves Barbecue LLC",
    "wof:placetype":"venue"
},
  "geometry": {"coordinates":[-105.217375,39.576443],"type":"Point"}
}