{
  "type": "Feature",
  "properties": {
    "iso:country":"US",
    "sg:address":"9700 W 51st Pl",
    "sg:city":"Arvada",
    "sg:classifiers":[
        {
            "category":"Real Estate",
            "subcategory":"Real Estate Operator",
            "type":"Services"
        }
    ],
    "sg:phone":"+1 303 421 2962",
    "sg:postcode":"80002",
    "sg:province":"CO",
    "sg:tags":[
        "apartment",
        "complex"
    ],
    "wof:name":"Mesa Verde Apartment Homes",
    "wof:placetype":"venue"
},
  "geometry": {"coordinates":[-105.106775,39.790283],"type":"Point"}
}