{
  "type": "Feature",
  "properties": {
    "iso:country":"US",
    "sg:address":"1100 Washington St",
    "sg:city":"Denver",
    "sg:classifiers":[
        {
            "category":"Building & Trades",
            "subcategory":"Cleaning & Sanitation",
            "type":"Services"
        }
    ],
    "sg:phone":"+1 303 860 1403",
    "sg:postcode":"80203",
    "sg:province":"CO",
    "sg:tags":[
        "home"
    ],
    "wof:name":"A A A Hauling",
    "wof:placetype":"venue"
},
  "geometry": {"coordinates":[-104.978996,39.733898],"type":"Point"}
}