{
  "type": "Feature",
  "properties": {
    "iso:country":"US",
    "sg:address":"5455 W 38th Ave",
    "sg:city":"Wheat Ridge",
    "sg:classifiers":[
        {
            "category":"Shopping",
            "subcategory":"Mobile Phones",
            "type":"Retail Goods"
        }
    ],
    "sg:phone":"+1 303 474 4436",
    "sg:postcode":"80212",
    "sg:province":"CO",
    "wof:name":"Tic Talk Wireless",
    "wof:placetype":"venue"
},
  "geometry": {"coordinates":[-105.056148,39.769447],"type":"Point"}
}