{
  "type": "Feature",
  "properties": {
    "addr:full":"5455 W 38th Ave Wheat Ridge CO 80212",
    "addr:housenumber":"5455",
    "addr:postcode":"80212",
    "addr:street":"W 38Th Ave",
    "iso:country":"US",
    "sg:address":"5455 W 38th Ave",
    "sg:city":"Wheat Ridge",
    "sg:classifiers":[
        {
            "category":"Shopping",
            "subcategory":"Mobile Phones",
            "type":"Retail Goods"
        }
    ],
    "sg:phone":"+1 303 474 4436",
    "sg:postcode":"80212",
    "sg:province":"CO",
    "wof:name":"Tic Talk Wireless",
    "wof:placetype":"venue"
},
  "geometry": {"coordinates":[-105.05614799999999,39.769447],"type":"Point"}
}