{
  "type": "Feature",
  "properties": {
    "addr:full":"2525 W Evans Ave Denver CO 80219",
    "addr:housenumber":"2525",
    "addr:postcode":"80219",
    "addr:street":"W Evans Ave",
    "iso:country":"US",
    "sg:address":"2525 W Evans Ave",
    "sg:city":"Denver",
    "sg:classifiers":[
        {
            "category":"Wholesale",
            "subcategory":"Machinery & Supplies",
            "type":"Manufacturing & Wholesale Goods"
        },
        {
            "category":"Manufacturing",
            "subcategory":"Tools & Machinery",
            "type":"Manufacturing & Wholesale Goods"
        }
    ],
    "sg:phone":"+1 303 922 7344",
    "sg:postcode":"80219",
    "sg:province":"CO",
    "sg:tags":[
        "packaging",
        "industrial",
        "mfg"
    ],
    "sg:website":"www.zygotinc.com",
    "wof:name":"Zygote Automation Inc",
    "wof:placetype":"venue"
},
  "geometry": {"coordinates":[-105.016795,39.678754],"type":"Point"}
}