{
  "type": "Feature",
  "properties": {
    "addr:full":"719 Walnut St Boulder CO 80302",
    "addr:housenumber":"719",
    "addr:postcode":"80302",
    "addr:street":"Walnut St",
    "iso:country":"US",
    "sg:address":"719 Walnut St",
    "sg:city":"Boulder",
    "sg:classifiers":[
        {
            "category":"Manufacturing",
            "subcategory":"Textiles",
            "type":"Manufacturing & Wholesale Goods"
        },
        {
            "category":"Shopping",
            "type":"Retail Goods"
        }
    ],
    "sg:phone":"+1 303 443 3287",
    "sg:postcode":"80302",
    "sg:province":"CO",
    "sg:tags":[
        "hat",
        "ice"
    ],
    "wof:name":"Ice Box Knitting LLC",
    "wof:placetype":"venue"
},
  "geometry": {"coordinates":[-105.28509,40.015826],"type":"Point"}
}