{
  "type": "Feature",
  "properties": {
    "iso:country":"US",
    "sg:address":"27050 US Hwy 24",
    "sg:city":"Calhan",
    "sg:classifiers":[
        {
            "category":"Shopping",
            "subcategory":"Gifts & Souvenirs",
            "type":"Retail Goods"
        }
    ],
    "sg:phone":"+1 719 347 2916",
    "sg:postcode":"80808",
    "sg:province":"CO",
    "wof:name":"Jeans Junk",
    "wof:placetype":"venue"
},
  "geometry": {"coordinates":[-104.321924,39.026774],"type":"Point"}
}