{
  "type": "Feature",
  "properties": {
    "iso:country":"US",
    "sg:address":"12750 State Hwy 94",
    "sg:city":"Colorado Springs",
    "sg:classifiers":[
        {
            "category":"Wholesale",
            "subcategory":"Auto Parts",
            "type":"Manufacturing & Wholesale Goods"
        }
    ],
    "sg:phone":"+1 719 683 5608",
    "sg:postcode":"80929",
    "sg:province":"CO",
    "sg:tags":[
        "automobile",
        "rebuilt"
    ],
    "wof:name":"American Import Auto",
    "wof:placetype":"venue"
},
  "geometry": {"coordinates":[-104.596079,38.838716],"type":"Point"}
}