{
  "type": "Feature",
  "properties": {
    "addr:full":"7220 Locust St Commerce City CO 80022",
    "addr:housenumber":"7220",
    "addr:postcode":"80022",
    "addr:street":"Locust St",
    "iso:country":"US",
    "sg:address":"7220 Locust St",
    "sg:city":"Commerce City",
    "sg:classifiers":[
        {
            "category":"Retail",
            "subcategory":"Laundry & Dry Cleaning",
            "type":"Services"
        }
    ],
    "sg:phone":"+1 303 288 2465",
    "sg:postcode":"80022",
    "sg:province":"CO",
    "sg:tags":[
        "drycleaning",
        "plant"
    ],
    "wof:name":"Derby Cleaners",
    "wof:placetype":"venue"
},
  "geometry": {"coordinates":[-104.913297,39.827809],"type":"Point"}
}