{
  "type": "Feature",
  "properties": {
    "iso:country":"US",
    "sg:address":"1447 W 101st Pl",
    "sg:city":"Northglenn",
    "sg:classifiers":[
        {
            "category":"Banks & Credit Unions",
            "subcategory":"Bank",
            "type":"Services"
        }
    ],
    "sg:phone":"+1 303 252 0188",
    "sg:postcode":"80260",
    "sg:province":"CO",
    "sg:tags":[
        "loan",
        "real estate"
    ],
    "wof:name":"Tlc Mortgage Solutions",
    "wof:placetype":"venue"
},
  "geometry": {"coordinates":[-105.002591,39.880777],"type":"Point"}
}