{
  "type": "Feature",
  "properties": {
    "iso:country":"US",
    "sg:address":"18230 Appaloosa Rd",
    "sg:city":"Monument",
    "sg:classifiers":[
        {
            "category":"Real Estate",
            "subcategory":"Real Estate Operator",
            "type":"Services"
        }
    ],
    "sg:phone":"+1 719 637 1804",
    "sg:postcode":"80132",
    "sg:province":"CO",
    "sg:tags":[
        "building",
        "nonresidential"
    ],
    "wof:name":"Hancock Carwash",
    "wof:placetype":"venue"
},
  "geometry": {"coordinates":[-104.781542,39.096162],"type":"Point"}
}