{
  "type": "Feature",
  "properties": {
    "iso:country":"US",
    "sg:address":"4395 Pierson St",
    "sg:city":"Wheat Ridge",
    "sg:classifiers":[
        {
            "category":"Building & Trades",
            "subcategory":"Electrical",
            "type":"Services"
        }
    ],
    "sg:phone":"+1 303 422 1642",
    "sg:postcode":"80033",
    "sg:province":"CO",
    "sg:tags":[
        "electric",
        "contractor"
    ],
    "wof:name":"Nite Lites Intl Inc",
    "wof:placetype":"venue"
},
  "geometry": {"coordinates":[-105.122225,39.776605],"type":"Point"}
}