{
  "type": "Feature",
  "properties": {
    "addr:full":"2334 Broadway St Boulder CO 80304",
    "addr:housenumber":"2334",
    "addr:postcode":"80304",
    "addr:street":"Broadway St",
    "iso:country":"US",
    "sg:address":"2334 Broadway St",
    "sg:city":"Boulder",
    "sg:classifiers":[
        {
            "category":"Organizations",
            "subcategory":"Membership Organization",
            "type":"Services"
        }
    ],
    "sg:phone":"+1 720 565 8289",
    "sg:postcode":"80304",
    "sg:province":"CO",
    "wof:name":"Colorado Conservation Trust",
    "wof:placetype":"venue"
},
  "geometry": {"coordinates":[-105.28111699999999,40.021376],"type":"Point"}
}