{
  "type": "Feature",
  "properties": {
    "iso:country":"US",
    "sg:address":"275 Waneka Pkwy",
    "sg:city":"Lafayette",
    "sg:classifiers":[
        {
            "category":"Restaurant",
            "type":"Food & Drink"
        }
    ],
    "sg:phone":"+1 720 890 4763",
    "sg:postcode":"80026",
    "sg:province":"CO",
    "sg:tags":[
        "eating"
    ],
    "wof:name":"Chef By Request",
    "wof:placetype":"venue"
},
  "geometry": {"coordinates":[-105.092826,39.989392],"type":"Point"}
}