{
  "type": "Feature",
  "properties": {
    "addr:full":"2535 Zenobia St Denver CO 80212",
    "addr:postcode":"2535;80212",
    "addr:street":"Zenobia St",
    "iso:country":"US",
    "sg:address":"2535 Zenobia St",
    "sg:city":"Denver",
    "sg:classifiers":[
        {
            "category":"Social Services",
            "subcategory":"Retirement Home",
            "type":"Services"
        }
    ],
    "sg:phone":"+1 303 795 0784",
    "sg:postcode":"80212",
    "sg:province":"CO",
    "sg:website":"assistedlivingdenverco.com/#cid=...",
    "wof:name":"Golden Orchard Assisted Living",
    "wof:placetype":"venue"
},
  "geometry": {"coordinates":[-105.052127,39.754607],"type":"Point"}
}