{
  "type": "Feature",
  "properties": {
    "iso:country":"US",
    "sg:address":"1102 Pearl St",
    "sg:city":"Boulder",
    "sg:classifiers":[
        {
            "category":"Restaurant",
            "type":"Food & Drink"
        }
    ],
    "sg:menulink":"http://www.allmenus.com/co/boulder/39064-old-chicago/menu/",
    "sg:phone":"+1 303 443 5031",
    "sg:postcode":"80302",
    "sg:province":"CO",
    "sg:tags":[
        "american",
        "pizza"
    ],
    "wof:name":"Old Chicago",
    "wof:placetype":"venue"
},
  "geometry": {"coordinates":[-105.281166,40.017646],"type":"Point"}
}