{
  "type": "Feature",
  "properties": {
    "iso:country":"US",
    "sg:address":"2111 W Iliff Ave",
    "sg:city":"Englewood",
    "sg:classifiers":[
        {
            "category":"Professional",
            "subcategory":"Management & Consulting",
            "type":"Services"
        }
    ],
    "sg:phone":"+1 303 934 6869",
    "sg:postcode":"80110",
    "sg:province":"CO",
    "wof:name":"Alpha Management Inc",
    "wof:placetype":"venue"
},
  "geometry": {"coordinates":[-105.01236299999999,39.675081],"type":"Point"}
}