{
  "type": "Feature",
  "properties": {
    "iso:country":"US",
    "sg:address":"3098 S Gilpin St",
    "sg:city":"Denver",
    "sg:classifiers":[
        {
            "category":"Professional",
            "subcategory":"Employment Agencies",
            "type":"Services"
        }
    ],
    "sg:phone":"+1 303 757 4103",
    "sg:postcode":"80210",
    "sg:province":"CO",
    "sg:tags":[
        "opportunity"
    ],
    "sg:website":"http://www.giftservicesinc.com",
    "wof:name":"What Should You Be Doing",
    "wof:placetype":"venue"
},
  "geometry": {"coordinates":[-104.967918,39.660412],"type":"Point"}
}