{
  "type": "Feature",
  "properties": {
    "iso:country":"US",
    "sg:address":"916 State Hwy 115",
    "sg:city":"Penrose",
    "sg:classifiers":[
        {
            "category":"Food & Beverages",
            "subcategory":"Groceries & Convenience Stores",
            "type":"Retail Goods"
        }
    ],
    "sg:phone":"+1 719 372 3200",
    "sg:postcode":"81240",
    "sg:province":"CO",
    "wof:name":"KWIK Stop",
    "wof:placetype":"venue"
},
  "geometry": {"coordinates":[-105.001966,38.46278],"type":"Point"}
}