{
  "type": "Feature",
  "properties": {
    "addr:full":"580 Alloo Gobi Durango CO 81303",
    "addr:housenumber":"580",
    "addr:postcode":"co 81303",
    "addr:street":"Alloo Gobi",
    "iso:country":"US",
    "sg:address":"580 Alloo Gobi",
    "sg:city":"Durango",
    "sg:classifiers":[
        {
            "category":"Manufacturing",
            "subcategory":"Building Materials",
            "type":"Manufacturing & Wholesale Goods"
        }
    ],
    "sg:phone":"+1 970 385 0154",
    "sg:postcode":"81303",
    "sg:province":"CO",
    "sg:tags":[
        "mfg"
    ],
    "wof:name":"Dave Grattan Woodworking",
    "wof:placetype":"venue"
},
  "geometry": {"coordinates":[-107.814335,37.174888],"type":"Point"}
}