{
  "type": "Feature",
  "properties": {
    "iso:country":"US",
    "sg:address":"7381 S Delaware St",
    "sg:city":"Littleton",
    "sg:classifiers":[
        {
            "category":"Building & Trades",
            "subcategory":"Electrical",
            "type":"Services"
        }
    ],
    "sg:phone":"+1 303 794 0803",
    "sg:postcode":"80120",
    "sg:province":"CO",
    "sg:tags":[
        "electric",
        "contractor"
    ],
    "wof:name":"High Line Electric LLC",
    "wof:placetype":"venue"
},
  "geometry": {"coordinates":[-104.99342799999999,39.586124],"type":"Point"}
}