{
  "type": "Feature",
  "properties": {
    "iso:country":"US",
    "sg:address":"1370 Pennsylvania St",
    "sg:city":"Denver",
    "sg:classifiers":[
        {
            "category":"Professional",
            "subcategory":"Management & Consulting",
            "type":"Services"
        }
    ],
    "sg:phone":"+1 303 863 7777",
    "sg:postcode":"80203",
    "sg:province":"CO",
    "sg:tags":[
        "consultant",
        "political"
    ],
    "wof:name":"Mendez Steadman & Assoc",
    "wof:placetype":"venue"
},
  "geometry": {"coordinates":[-104.981015,39.737324],"type":"Point"}
}