{
  "type": "Feature",
  "properties": {
    "iso:country":"US",
    "sg:address":"5650 Greenwood Plaza Blvd",
    "sg:city":"Englewood",
    "sg:classifiers":[
        {
            "category":"Banks & Credit Unions",
            "subcategory":"Bank",
            "type":"Services"
        }
    ],
    "sg:phone":"+1 303 721 6306",
    "sg:postcode":"80111",
    "sg:province":"CO",
    "sg:tags":[
        "loan",
        "mortgage",
        "real estate"
    ],
    "wof:name":"Troy Mortgage Corp Inc",
    "wof:placetype":"venue"
},
  "geometry": {"coordinates":[-104.89751099999999,39.612059],"type":"Point"}
}