{
  "type": "Feature",
  "properties": {
    "iso:country":"US",
    "sg:address":"15107 US Hwy 287",
    "sg:city":"Springfield",
    "sg:phone":"+1 719 523 6775",
    "sg:postcode":"81073",
    "sg:province":"CO",
    "sg:tags":[
        "farm",
        "wheat",
        "grain",
        "cash"
    ],
    "wof:name":"Self Farms",
    "wof:placetype":"venue"
},
  "geometry": {"coordinates":[-102.615443,37.214633],"type":"Point"}
}