{
  "type": "Feature",
  "properties": {
    "iso:country":"US",
    "sg:address":"4860 Broadway",
    "sg:city":"Denver",
    "sg:classifiers":[
        {
            "category":"Manufacturing",
            "subcategory":"Food",
            "type":"Manufacturing & Wholesale Goods"
        }
    ],
    "sg:phone":"+1 303 382 1805",
    "sg:postcode":"80216",
    "sg:province":"CO",
    "sg:tags":[
        "mix",
        "cocktail",
        "mfg"
    ],
    "sg:website":"www.freshies.com",
    "wof:name":"Freshies Food Corp",
    "wof:placetype":"venue"
},
  "geometry": {"coordinates":[-104.987515,39.784641],"type":"Point"}
}