{
  "type": "Feature",
  "properties": {
    "addr:full":"2032 W Cucharras St Colorado Springs CO 80904",
    "addr:housenumber":"2032",
    "addr:postcode":"80904",
    "addr:street":"W Cucharras St",
    "iso:country":"US",
    "sg:address":"2032 W Cucharras St",
    "sg:city":"Colorado Springs",
    "sg:classifiers":[
        {
            "category":"Travel",
            "subcategory":"Hotels & Motels",
            "type":"Entertainment"
        }
    ],
    "sg:phone":"+1 719 630 8366",
    "sg:postcode":"80904",
    "sg:province":"CO",
    "wof:name":"Old Colorado City Motel",
    "wof:placetype":"venue"
},
  "geometry": {"coordinates":[-104.856906,38.842564],"type":"Point"}
}