{
  "type": "Feature",
  "properties": {
    "iso:country":"US",
    "sg:address":"1500 E 128th Ave",
    "sg:city":"Thornton",
    "sg:classifiers":[
        {
            "category":"Food & Beverages",
            "subcategory":"Specialty",
            "type":"Retail Goods"
        }
    ],
    "sg:phone":"+1 303 474 2300",
    "sg:postcode":"80241",
    "sg:province":"CO",
    "sg:tags":[
        "vitamin"
    ],
    "wof:name":"Healthsmart Vitamins",
    "wof:placetype":"venue"
},
  "geometry": {"coordinates":[-104.970242,39.928424],"type":"Point"}
}