{
  "type": "Feature",
  "properties": {
    "addr:full":"2261 Blake St Denver CO 80205",
    "addr:housenumber":"2261",
    "addr:postcode":"80205",
    "addr:street":"Blake St",
    "iso:country":"US",
    "sg:address":"2261 Blake St",
    "sg:city":"Denver",
    "sg:classifiers":[
        {
            "category":"Professional",
            "subcategory":"Computer Services",
            "type":"Services"
        }
    ],
    "sg:phone":"+1 303 244 9999",
    "sg:postcode":"80205",
    "sg:province":"CO",
    "sg:tags":[
        "consultant",
        "designer"
    ],
    "wof:name":"GRT Consulting Inc Computers",
    "wof:placetype":"venue"
},
  "geometry": {"coordinates":[-104.99138499999999,39.756579],"type":"Point"}
}