{
  "type": "Feature",
  "properties": {
    "iso:country":"US",
    "sg:address":"204 Park Ave",
    "sg:city":"Basalt",
    "sg:classifiers":[
        {
            "category":"Building & Trades",
            "subcategory":"Cleaning & Sanitation",
            "type":"Services"
        }
    ],
    "sg:phone":"+1 970 704 1953",
    "sg:postcode":"81621",
    "sg:province":"CO",
    "sg:tags":[
        "household",
        "appliance",
        "maintenance"
    ],
    "wof:name":"Kips Kleaning",
    "wof:placetype":"venue"
},
  "geometry": {"coordinates":[-107.08201200000001,39.374873],"type":"Point"}
}