{
  "type": "Feature",
  "properties": {
    "addr:full":"4669 Dudley St Wheat Ridge CO 80033",
    "addr:housenumber":"4669",
    "addr:postcode":"80033",
    "addr:street":"Dudley St",
    "iso:country":"US",
    "sg:address":"4669 Dudley St",
    "sg:city":"Wheat Ridge",
    "sg:classifiers":[
        {
            "category":"Professional",
            "subcategory":"Management & Consulting",
            "type":"Services"
        }
    ],
    "sg:phone":"+1 303 420 9794",
    "sg:postcode":"80033",
    "sg:province":"CO",
    "sg:tags":[
        "home",
        "demonstration"
    ],
    "wof:name":"Watkins Products Independent",
    "wof:placetype":"venue"
},
  "geometry": {"coordinates":[-105.09417999999999,39.782205],"type":"Point"}
}