{
  "type": "Feature",
  "properties": {
    "iso:country":"US",
    "sg:address":"201 Laporte Ave",
    "sg:city":"Fort Collins",
    "sg:classifiers":[
        {
            "category":"Government",
            "subcategory":"Court House",
            "type":"Public Place"
        }
    ],
    "sg:phone":"+1 970 498 6100",
    "sg:postcode":"80521",
    "sg:province":"CO",
    "sg:tags":[
        "state"
    ],
    "wof:name":"8th Judicial District Court",
    "wof:placetype":"venue"
},
  "geometry": {"coordinates":[-105.07956299999999,40.588893],"type":"Point"}
}