{
  "type": "Feature",
  "properties": {
    "iso:country":"US",
    "sg:address":"494 Sheridan Blvd. Suite C100",
    "sg:city":"Denver",
    "sg:classifiers":[
        {
            "category":"Personal",
            "subcategory":"Massage",
            "type":"Services"
        }
    ],
    "sg:phone":"+1 303 594 2386",
    "sg:postcode":"80226",
    "sg:province":"CO",
    "wof:name":"Brenda's Massage Therapy LLC",
    "wof:placetype":"venue"
},
  "geometry": {"coordinates":[-105.05284399999999,39.723629],"type":"Point"}
}