{
  "type": "Feature",
  "properties": {
    "addr:full":"8 Foothill Ash Littleton CO 80127",
    "addr:housenumber":"8",
    "addr:postcode":"80127",
    "addr:street":"Foothill Ash",
    "iso:country":"US",
    "sg:address":"8 Foothill Ash",
    "sg:city":"Littleton",
    "sg:classifiers":[
        {
            "category":"Professional",
            "subcategory":"Accounting & Tax Preparation",
            "type":"Services"
        }
    ],
    "sg:phone":"+1 303 972 1354",
    "sg:postcode":"80127",
    "sg:province":"CO",
    "sg:tags":[
        "billing"
    ],
    "wof:name":"Red Rock Billing Management",
    "wof:placetype":"venue"
},
  "geometry": {"coordinates":[-105.158433,39.569475],"type":"Point"}
}