{
  "type": "Feature",
  "properties": {
    "iso:country":"US",
    "sg:address":"2717 Cherly St",
    "sg:city":"Fort Collins",
    "sg:classifiers":[
        {
            "category":"Home & Garden",
            "subcategory":"Home Furnishings",
            "type":"Retail Goods"
        }
    ],
    "sg:phone":"+1 970 419 0100",
    "sg:postcode":"80524",
    "sg:province":"CO",
    "sg:tags":[
        "venetian",
        "blind"
    ],
    "wof:name":"Majestic Blinds Cleaning & Rpr",
    "wof:placetype":"venue"
},
  "geometry": {"coordinates":[-105.027038,40.576259],"type":"Point"}
}