{
  "type": "Feature",
  "properties": {
    "addr:full":"12565 Co Rd 2 Brighton CO 80602",
    "addr:housenumber":"12565",
    "addr:postcode":"80602",
    "addr:street":"Co Rd 2",
    "iso:country":"US",
    "sg:address":"12565 Co Rd 2",
    "sg:city":"Brighton",
    "sg:classifiers":[
        {
            "category":"Home & Garden",
            "subcategory":"Building Materials",
            "type":"Retail Goods"
        }
    ],
    "sg:phone":"+1 303 637 0934",
    "sg:postcode":"80602",
    "sg:province":"CO",
    "sg:tags":[
        "windows"
    ],
    "sg:website":"www.vinylreplacementwindow.com",
    "wof:name":"Security Door & Window Store",
    "wof:placetype":"venue"
},
  "geometry": {"coordinates":[-104.838953,40.000403],"type":"Point"}
}