{
  "type": "Feature",
  "properties": {
    "addr:full":"12526 W Texas Pl Denver CO 80228",
    "addr:housenumber":"12526",
    "addr:postcode":"80228",
    "addr:street":"W Texas Pl",
    "iso:country":"US",
    "sg:address":"12526 W Texas Pl",
    "sg:city":"Denver",
    "sg:classifiers":[
        {
            "category":"Banks & Credit Unions",
            "subcategory":"Investment Brokerage",
            "type":"Services"
        }
    ],
    "sg:phone":"+1 303 985 2194",
    "sg:postcode":"80228",
    "sg:province":"CO",
    "sg:tags":[
        "advisory"
    ],
    "wof:name":"Chosen Path Financial Services",
    "wof:placetype":"venue"
},
  "geometry": {"coordinates":[-105.140146,39.696153],"type":"Point"}
}