{
  "type": "Feature",
  "properties": {
    "addr:full":"2359 W Main St Littleton CO 80120",
    "addr:housenumber":"2359",
    "addr:postcode":"80120",
    "addr:street":"W Main St",
    "iso:country":"US",
    "sg:address":"2359 W Main St",
    "sg:city":"Littleton",
    "sg:classifiers":[
        {
            "category":"Home & Garden",
            "subcategory":"Furniture",
            "type":"Retail Goods"
        }
    ],
    "sg:phone":"+1 303 794 3468",
    "sg:postcode":"80120",
    "sg:province":"CO",
    "sg:tags":[
        "finished",
        "unfinished"
    ],
    "wof:name":"Homewood Unfinished Furniture",
    "wof:placetype":"venue"
},
  "geometry": {"coordinates":[-105.015676,39.613798],"type":"Point"}
}