{
  "type": "Feature",
  "properties": {
    "iso:country":"US",
    "sg:address":"1221 S Prairie Ave",
    "sg:city":"Pueblo",
    "sg:classifiers":[
        {
            "category":"Banks & Credit Unions",
            "subcategory":"Bank",
            "type":"Services"
        }
    ],
    "sg:phone":"+1 719 561 9030",
    "sg:postcode":"81005",
    "sg:province":"CO",
    "sg:website":"www.wellsfargo.com",
    "wof:name":"Wells Fargo Bank",
    "wof:placetype":"venue"
},
  "geometry": {"coordinates":[-104.64386,38.244406],"type":"Point"}
}