{
  "type": "Feature",
  "properties": {
    "iso:country":"US",
    "sg:address":"12410 W Cedar Dr",
    "sg:city":"Lakewood",
    "sg:classifiers":[
        {
            "category":"Professional",
            "type":"Services"
        }
    ],
    "sg:phone":"+1 303 989 5135",
    "sg:postcode":"80228",
    "sg:province":"CO",
    "sg:tags":[
        "establishment"
    ],
    "wof:name":"Denver Die Mold Inc",
    "wof:placetype":"venue"
},
  "geometry": {"coordinates":[-105.14313199999999,39.712149],"type":"Point"}
}