{
  "type": "Feature",
  "properties": {
    "iso:country":"US",
    "sg:address":"2640 S Raritan St",
    "sg:city":"Englewood",
    "sg:classifiers":[
        {
            "category":"Professional",
            "subcategory":"Research",
            "type":"Services"
        },
        {
            "category":"Manufacturing",
            "subcategory":"Tools & Machinery",
            "type":"Manufacturing & Wholesale Goods"
        }
    ],
    "sg:phone":"+1 303 922 7773",
    "sg:postcode":"80110",
    "sg:province":"CO",
    "sg:tags":[
        "mfg",
        "pro",
        "system",
        "automation",
        "equipment",
        "physical"
    ],
    "wof:name":"Omnitech Robotics Intl",
    "wof:placetype":"venue"
},
  "geometry": {"coordinates":[-105.00860900000001,39.670711],"type":"Point"}
}