{
  "type": "Feature",
  "properties": {
    "addr:full":"7106 E Briarwood Dr Centennial CO 80112",
    "addr:housenumber":"7106",
    "addr:postcode":"80112",
    "addr:street":"E Briarwood Dr",
    "iso:country":"US",
    "sg:address":"7106 E Briarwood Dr",
    "sg:city":"Centennial",
    "sg:classifiers":[
        {
            "category":"Professional",
            "subcategory":"Business Services",
            "type":"Services"
        }
    ],
    "sg:phone":"+1 303 779 9819",
    "sg:postcode":"80112",
    "sg:province":"CO",
    "sg:tags":[
        "inventory"
    ],
    "wof:name":"United Retail Inventory Svc",
    "wof:placetype":"venue"
},
  "geometry": {"coordinates":[-104.905474,39.591809],"type":"Point"}
}