{
  "type": "Feature",
  "properties": {
    "iso:country":"US",
    "sg:address":"10870 Carol Ln",
    "sg:city":"Denver",
    "sg:classifiers":[
        {
            "category":"Freight",
            "type":"Transportation"
        }
    ],
    "sg:phone":"+1 303 255 4888",
    "sg:postcode":"80233",
    "sg:province":"CO",
    "wof:name":"Trujillo Transport Inc",
    "wof:placetype":"venue"
},
  "geometry": {"coordinates":[-104.981059,39.892802],"type":"Point"}
}