{
  "type": "Feature",
  "properties": {
    "iso:country":"US",
    "sg:address":"2201 Kipling St",
    "sg:city":"Lakewood",
    "sg:classifiers":[
        {
            "category":"Insurance",
            "subcategory":"Insurance Agent",
            "type":"Services"
        }
    ],
    "sg:phone":"+1 303 233 2288",
    "sg:postcode":"80215",
    "sg:province":"CO",
    "wof:name":"Robert W Walter Agency",
    "wof:placetype":"venue"
},
  "geometry": {"coordinates":[-105.109651,39.749634],"type":"Point"}
}