{
  "type": "Feature",
  "properties": {
    "iso:country":"US",
    "sg:address":"9235 Eastman Park Dr",
    "sg:city":"Windsor",
    "sg:classifiers":[
        {
            "category":"Restaurant",
            "type":"Food & Drink"
        }
    ],
    "sg:phone":"+1 970 686 5202",
    "sg:postcode":"80550",
    "sg:province":"CO",
    "wof:name":"Lecato's Steak Seafood",
    "wof:placetype":"venue"
},
  "geometry": {"coordinates":[-104.884736,40.465231],"type":"Point"}
}