{
  "type": "Feature",
  "properties": {
    "iso:country":"US",
    "sg:address":"6999 S Jordan Rd",
    "sg:city":"Centennial",
    "sg:classifiers":[
        {
            "category":"Freight",
            "type":"Transportation"
        }
    ],
    "sg:phone":"+1 303 690 7865",
    "sg:postcode":"80112",
    "sg:province":"CO",
    "sg:tags":[
        "mover"
    ],
    "wof:name":"United Van Lines",
    "wof:placetype":"venue"
},
  "geometry": {"coordinates":[-104.818344,39.590363],"type":"Point"}
}