{
  "type": "Feature",
  "properties": {
    "addr:full":"3131 State Hwy 7 Estes Park CO 80517",
    "addr:housenumber":"3131",
    "addr:postcode":"80517",
    "addr:street":"State Hwy 7",
    "iso:country":"US",
    "sg:address":"3131 State Hwy 7",
    "sg:city":"Estes Park",
    "sg:classifiers":[
        {
            "category":"Real Estate",
            "subcategory":"Real Estate Operator",
            "type":"Services"
        }
    ],
    "sg:phone":"+1 970 586 9396",
    "sg:postcode":"80517",
    "sg:province":"CO",
    "sg:tags":[
        "mobile",
        "home",
        "site"
    ],
    "wof:name":"Ramshorn Mountain Estates Land",
    "wof:placetype":"venue"
},
  "geometry": {"coordinates":[-105.525847,40.331123],"type":"Point"}
}