{
  "type": "Feature",
  "properties": {
    "addr:full":"200 W Agate Ave Granby CO 80446",
    "addr:housenumber":"200",
    "addr:postcode":"80446",
    "addr:street":"W Agate Ave",
    "iso:country":"US",
    "sg:address":"200 W Agate Ave",
    "sg:city":"Granby",
    "sg:classifiers":[
        {
            "category":"Insurance",
            "subcategory":"Insurance Agent",
            "type":"Services"
        }
    ],
    "sg:phone":"+1 970 887 9770",
    "sg:postcode":"80446",
    "sg:province":"CO",
    "wof:name":"Sean M Dee Agency/American Fam",
    "wof:placetype":"venue"
},
  "geometry": {"coordinates":[-105.94324899999999,40.085754],"type":"Point"}
}