{
  "type": "Feature",
  "properties": {
    "iso:country":"US",
    "sg:address":"10037 Chelmsford Ter",
    "sg:city":"Parker",
    "sg:classifiers":[
        {
            "category":"Shopping",
            "type":"Retail Goods"
        }
    ],
    "sg:phone":"+1 303 840 9932",
    "sg:postcode":"80134",
    "sg:province":"CO",
    "sg:tags":[
        "equipment",
        "telephone",
        "supply"
    ],
    "wof:name":"Lucent Technologies",
    "wof:placetype":"venue"
},
  "geometry": {"coordinates":[-104.805825,39.533311],"type":"Point"}
}