{
  "type": "Feature",
  "properties": {
    "addr:full":"205 E Foothills Pkwy Fort Collins CO 80525",
    "addr:housenumber":"205",
    "addr:postcode":"80525",
    "addr:street":"E Foothills Pkwy",
    "iso:country":"US",
    "sg:address":"205 E Foothills Pkwy",
    "sg:city":"Fort Collins",
    "sg:classifiers":[
        {
            "category":"Professional",
            "subcategory":"Accounting & Tax Preparation",
            "type":"Services"
        }
    ],
    "sg:phone":"+1 970 229 1278",
    "sg:postcode":"80525",
    "sg:province":"CO",
    "sg:tags":[
        "return",
        "filing"
    ],
    "wof:name":"H & R Block Tax Svc",
    "wof:placetype":"venue"
},
  "geometry": {"coordinates":[-105.074563,40.543842],"type":"Point"}
}