{
  "type": "Feature",
  "properties": {
    "iso:country":"US",
    "sg:address":"1750 S Estrella Ave",
    "sg:city":"Loveland",
    "sg:classifiers":[
        {
            "category":"Personal",
            "type":"Services"
        }
    ],
    "sg:phone":"+1 970 222 3061",
    "sg:postcode":"80537",
    "sg:province":"CO",
    "sg:tags":[
        "therapist",
        "massage"
    ],
    "wof:name":"Canine Caring Therapeutic",
    "wof:placetype":"venue"
},
  "geometry": {"coordinates":[-105.10945599999999,40.376484],"type":"Point"}
}