{
  "type": "Feature",
  "properties": {
    "iso:country":"US",
    "sg:address":"260 S Locust St",
    "sg:city":"Denver",
    "sg:classifiers":[
        {
            "category":"Restaurant",
            "type":"Food & Drink"
        }
    ],
    "sg:phone":"+1 303 370 6740",
    "sg:postcode":"80224",
    "sg:province":"CO",
    "sg:tags":[
        "eating"
    ],
    "wof:name":"Canteen Catering LLC",
    "wof:placetype":"venue"
},
  "geometry": {"coordinates":[-104.914114,39.712442],"type":"Point"}
}