{
  "type": "Feature",
  "properties": {
    "iso:country":"US",
    "sg:address":"5903 Pennsylvania Ave",
    "sg:city":"Beulah",
    "sg:classifiers":[
        {
            "category":"Organizations",
            "subcategory":"Religious Organization",
            "type":"Services"
        }
    ],
    "sg:phone":"+1 719 485 3405",
    "sg:postcode":"81023",
    "sg:province":"CO",
    "sg:tags":[
        "church"
    ],
    "wof:name":"Beulah United Methodist Church",
    "wof:placetype":"venue"
},
  "geometry": {"coordinates":[-104.989175,38.069686],"type":"Point"}
}