{
  "type": "Feature",
  "properties": {
    "iso:country":"US",
    "sg:address":"5265 S Rio Grande St",
    "sg:city":"Littleton",
    "sg:classifiers":[
        {
            "category":"Shopping",
            "type":"Retail Goods"
        }
    ],
    "sg:phone":"+1 303 794 9800",
    "sg:postcode":"80120",
    "sg:province":"CO",
    "sg:tags":[
        "plastic"
    ],
    "wof:name":"Regal Plastics Corporate Ofc",
    "wof:placetype":"venue"
},
  "geometry": {"coordinates":[-105.011713,39.622033],"type":"Point"}
}