{
  "type": "Feature",
  "properties": {
    "addr:full":"3709 N Nevada Ave Colorado Springs CO 80907",
    "addr:housenumber":"3709",
    "addr:postcode":"80907",
    "addr:street":"N Nevada Ave",
    "iso:country":"US",
    "sg:address":"3709 N Nevada Ave",
    "sg:city":"Colorado Springs",
    "sg:classifiers":[
        {
            "category":"Utilities",
            "subcategory":"Fuel Oil & Lpg",
            "type":"Services"
        }
    ],
    "sg:phone":"+1 719 633 7791",
    "sg:postcode":"80907",
    "sg:province":"CO",
    "sg:tags":[
        "petroleum",
        "product",
        "gas",
        "ho",
        "liquid"
    ],
    "wof:name":"All Star Gas Corporation",
    "wof:placetype":"venue"
},
  "geometry": {"coordinates":[-104.818718,38.885965],"type":"Point"}
}