{
  "type": "Feature",
  "properties": {
    "iso:country":"US",
    "sg:address":"87 Silverado Dr",
    "sg:city":"Basalt",
    "sg:classifiers":[
        {
            "category":"Building & Trades",
            "subcategory":"Construction",
            "type":"Services"
        }
    ],
    "sg:phone":"+1 970 927 4232",
    "sg:postcode":"81621",
    "sg:province":"CO",
    "sg:tags":[
        "house"
    ],
    "wof:name":"Total Builders Inc",
    "wof:placetype":"venue"
},
  "geometry": {"coordinates":[-107.06820999999999,39.370163],"type":"Point"}
}