{
  "type": "Feature",
  "properties": {
    "iso:country":"US",
    "sg:address":"1912 E Colfax Ave",
    "sg:city":"Denver",
    "sg:classifiers":[
        {
            "category":"Personal",
            "subcategory":"Barber",
            "type":"Services"
        }
    ],
    "sg:phone":"+1 303 377 5867",
    "sg:postcode":"80206",
    "sg:province":"CO",
    "wof:name":"Upper Cut",
    "wof:placetype":"venue"
},
  "geometry": {"coordinates":[-104.963588,39.739918],"type":"Point"}
}