{
  "type": "Feature",
  "properties": {
    "iso:country":"US",
    "sg:address":"1001 Beulah Ave",
    "sg:city":"Pueblo",
    "sg:classifiers":[
        {
            "category":"Autos & Motor Vehicles",
            "subcategory":"Automobile Sales",
            "type":"Retail Goods"
        }
    ],
    "sg:phone":"+1 719 566 0296",
    "sg:postcode":"81004",
    "sg:province":"CO",
    "sg:tags":[
        "car",
        "dealer"
    ],
    "wof:name":"Dale Spradley Motors",
    "wof:placetype":"venue"
},
  "geometry": {"coordinates":[-104.634609,38.247718],"type":"Point"}
}