{
  "type": "Feature",
  "properties": {
    "addr:full":"14401 W 65th Way Arvada CO 80004",
    "addr:housenumber":"14401",
    "addr:postcode":"80004",
    "addr:street":"W 65Th Way",
    "iso:country":"US",
    "sg:address":"14401 W 65th Way",
    "sg:city":"Arvada",
    "sg:classifiers":[
        {
            "category":"Wholesale",
            "subcategory":"Medical Equipment & Supplies",
            "type":"Manufacturing & Wholesale Goods"
        }
    ],
    "sg:phone":"+1 303 425 5508",
    "sg:postcode":"80004",
    "sg:province":"CO",
    "sg:tags":[
        "hospital",
        "supplies-wholesale",
        "manufacturer"
    ],
    "wof:name":"Cobe Cardiovascular Inc",
    "wof:placetype":"venue"
},
  "geometry": {"coordinates":[-105.16036200000001,39.81411],"type":"Point"}
}