{
  "type": "Feature",
  "properties": {
    "addr:full":"9940 Wadsworth Pkwy Broomfield CO 80021",
    "addr:housenumber":"9940",
    "addr:postcode":"80021",
    "addr:street":"Wadsworth Pkwy",
    "iso:country":"US",
    "sg:address":"9940 Wadsworth Pkwy",
    "sg:city":"Broomfield",
    "sg:classifiers":[
        {
            "category":"Retail",
            "subcategory":"Laundry & Dry Cleaning",
            "type":"Services"
        }
    ],
    "sg:phone":"+1 303 635 8000",
    "sg:postcode":"80021",
    "sg:province":"CO",
    "sg:tags":[
        "cleaners"
    ],
    "wof:name":"Dry Cleaning Home Svc",
    "wof:placetype":"venue"
},
  "geometry": {"coordinates":[-105.09458600000001,39.876047],"type":"Point"}
}