{
  "type": "Feature",
  "properties": {
    "iso:country":"US",
    "sg:address":"1921 Clover Ct",
    "sg:city":"Grand Junction",
    "sg:classifiers":[
        {
            "category":"Wholesale",
            "subcategory":"Groceries",
            "type":"Manufacturing & Wholesale Goods"
        }
    ],
    "sg:phone":"+1 970 245 0702",
    "sg:postcode":"81506",
    "sg:province":"CO",
    "wof:name":"Keebler",
    "wof:placetype":"venue"
},
  "geometry": {"coordinates":[-108.54179499999999,39.094678],"type":"Point"}
}