{
  "type": "Feature",
  "properties": {
    "iso:country":"US",
    "sg:address":"8339 Tabor Ct",
    "sg:city":"Arvada",
    "sg:classifiers":[
        {
            "category":"Professional",
            "subcategory":"Computer Services",
            "type":"Services"
        }
    ],
    "sg:phone":"+1 303 464 4666",
    "sg:postcode":"80005",
    "sg:province":"CO",
    "sg:tags":[
        "programing",
        "custom"
    ],
    "wof:name":"Sun Microsystems",
    "wof:placetype":"venue"
},
  "geometry": {"coordinates":[-105.133038,39.848454],"type":"Point"}
}