{
  "type": "Feature",
  "properties": {
    "iso:country":"US",
    "sg:address":"4199 Oneida St",
    "sg:city":"Denver",
    "sg:classifiers":[
        {
            "category":"Freight",
            "type":"Transportation"
        }
    ],
    "sg:phone":"+1 303 307 9489",
    "sg:postcode":"80216",
    "sg:province":"CO",
    "sg:tags":[
        "operator",
        "trucking"
    ],
    "wof:name":"Csi Crown",
    "wof:placetype":"venue"
},
  "geometry": {"coordinates":[-104.908287,39.774991],"type":"Point"}
}