{
  "type": "Feature",
  "properties": {
    "iso:country":"US",
    "sg:address":"51 Englewood Pkwy",
    "sg:city":"Englewood",
    "sg:classifiers":[
        {
            "category":"Food & Beverages",
            "subcategory":"Liquor & Beverages",
            "type":"Retail Goods"
        }
    ],
    "sg:phone":"+1 303 781 4433",
    "sg:postcode":"80110",
    "sg:province":"CO",
    "wof:name":"Off Broadway Wine & Spirits",
    "wof:placetype":"venue"
},
  "geometry": {"coordinates":[-104.988332,39.655062],"type":"Point"}
}