{
  "type": "Feature",
  "properties": {
    "addr:full":"1115 E Main St Cortez CO 81321",
    "addr:housenumber":"1115",
    "addr:postcode":"81321",
    "addr:street":"E Main St",
    "iso:country":"US",
    "sg:address":"1115 E Main St",
    "sg:city":"Cortez",
    "sg:classifiers":[
        {
            "category":"Retail",
            "subcategory":"Car Wash",
            "type":"Services"
        }
    ],
    "sg:phone":"+1 970 565 7839",
    "sg:postcode":"81321",
    "sg:province":"CO",
    "sg:tags":[
        "polishing",
        "washing"
    ],
    "wof:name":"Holgates East Main Car Wash",
    "wof:placetype":"venue"
},
  "geometry": {"coordinates":[-108.570803,37.348777],"type":"Point"}
}