{
  "type": "Feature",
  "properties": {
    "addr:full":"500 Jefferson County Pkwy Golden CO 80401",
    "addr:housenumber":"500",
    "addr:postcode":"80401",
    "addr:street":"Jefferson County Pkwy",
    "iso:country":"US",
    "sg:address":"500 Jefferson County Pkwy",
    "sg:city":"Golden",
    "sg:classifiers":[
        {
            "category":"Government",
            "subcategory":"Court House",
            "type":"Public Place"
        }
    ],
    "sg:phone":"+1 303 271 6800",
    "sg:postcode":"80401",
    "sg:province":"CO",
    "sg:tags":[
        "attorney",
        "district"
    ],
    "wof:name":"1st Judicial District",
    "wof:placetype":"venue"
},
  "geometry": {"coordinates":[-105.205759,39.731156],"type":"Point"}
}