{
  "type": "Feature",
  "properties": {
    "addr:full":"490 S Santa Fe Drive Denver CO 80223",
    "addr:housenumber":"490",
    "addr:postcode":"80223",
    "addr:street":"S Santa Fe Drive",
    "iso:country":"US",
    "sg:address":"490 S Santa Fe Drive",
    "sg:city":"Denver",
    "sg:classifiers":[
        {
            "category":"Real Estate",
            "subcategory":"Architect",
            "type":"Services"
        }
    ],
    "sg:phone":"+1 303 282 9100",
    "sg:postcode":"80223",
    "sg:province":"CO",
    "wof:name":"Designtrack",
    "wof:placetype":"venue"
},
  "geometry": {"coordinates":[-104.993537,39.701538],"type":"Point"}
}