{
  "type": "Feature",
  "properties": {
    "iso:country":"US",
    "sg:address":"16 Market Sq",
    "sg:city":"Denver",
    "sg:classifiers":[
        {
            "category":"Professional",
            "subcategory":"Lawyer & Legal Services",
            "type":"Services"
        }
    ],
    "sg:phone":"+1 303 292 7914",
    "sg:postcode":"80202",
    "sg:province":"CO",
    "wof:name":"Gokenbach Jennifer Atty",
    "wof:placetype":"venue"
},
  "geometry": {"coordinates":[-104.99574699999999,39.749758],"type":"Point"}
}