{
  "type": "Feature",
  "properties": {
    "iso:country":"US",
    "sg:address":"5412 Lone Tree Dr",
    "sg:city":"Loveland",
    "sg:classifiers":[
        {
            "category":"Manufacturing",
            "subcategory":"Toys & Sporting Goods",
            "type":"Manufacturing & Wholesale Goods"
        }
    ],
    "sg:phone":"+1 970 663 2495",
    "sg:postcode":"80537",
    "sg:province":"CO",
    "sg:tags":[
        "mfg"
    ],
    "wof:name":"Bs Specialities",
    "wof:placetype":"venue"
},
  "geometry": {"coordinates":[-105.135976,40.348137],"type":"Point"}
}