{
  "type": "Feature",
  "properties": {
    "iso:country":"US",
    "sg:address":"3537 E 117th Dr",
    "sg:city":"Denver",
    "sg:classifiers":[
        {
            "category":"Building & Trades",
            "subcategory":"Electrical",
            "type":"Services"
        }
    ],
    "sg:phone":"+1 303 457 2589",
    "sg:postcode":"80233",
    "sg:province":"CO",
    "sg:tags":[
        "telecommunication"
    ],
    "wof:name":"Alternative Communications",
    "wof:placetype":"venue"
},
  "geometry": {"coordinates":[-104.944523,39.909891],"type":"Point"}
}