{
  "type": "Feature",
  "properties": {
    "addr:full":"6031 S Marshall Dr Littleton CO 80123",
    "addr:housenumber":"6031",
    "addr:postcode":"80123",
    "addr:street":"S Marshall Dr",
    "iso:country":"US",
    "sg:address":"6031 S Marshall Dr",
    "sg:city":"Littleton",
    "sg:classifiers":[
        {
            "category":"Building & Trades",
            "subcategory":"Landscaping Services",
            "type":"Services"
        }
    ],
    "sg:phone":"+1 303 730 0203",
    "sg:postcode":"80123",
    "sg:province":"CO",
    "wof:name":"Total Lawn Care",
    "wof:placetype":"venue"
},
  "geometry": {"coordinates":[-105.070847,39.606127],"type":"Point"}
}