{
  "type": "Feature",
  "properties": {
    "addr:full":"11273 Plover Cir Parker CO 80134",
    "addr:housenumber":"11273",
    "addr:postcode":"80134",
    "addr:street":"Plover Cir",
    "iso:country":"US",
    "sg:address":"11273 Plover Cir",
    "sg:city":"Parker",
    "sg:classifiers":[
        {
            "category":"Shopping",
            "subcategory":"Gifts & Souvenirs",
            "type":"Retail Goods"
        }
    ],
    "sg:phone":"+1 720 851 1405",
    "sg:postcode":"80134",
    "sg:province":"CO",
    "sg:tags":[
        "party",
        "supply"
    ],
    "wof:name":"Cloud Nine Inflatable Party",
    "wof:placetype":"venue"
},
  "geometry": {"coordinates":[-104.80215800000001,39.513394],"type":"Point"}
}