{
  "type": "Feature",
  "properties": {
    "addr:full":"7359 Co Rd X Lamar CO 81052",
    "addr:housenumber":"7359",
    "addr:postcode":"81052",
    "addr:street":"Co Rd X Lamar",
    "iso:country":"US",
    "sg:address":"7359 Co Rd X",
    "sg:city":"Lamar",
    "sg:classifiers":[
        {
            "category":"Farming",
            "subcategory":"Livestock Farm",
            "type":"Manufacturing & Wholesale Goods"
        }
    ],
    "sg:phone":"+1 719 336 3111",
    "sg:postcode":"81052",
    "sg:province":"CO",
    "sg:tags":[
        "beef",
        "feedlot",
        "cattle"
    ],
    "wof:name":"Shelton Trucking",
    "wof:placetype":"venue"
},
  "geometry": {"coordinates":[-102.63180699999999,37.940341],"type":"Point"}
}