{
  "type": "Feature",
  "properties": {
    "addr:full":"650 Buck Hwy Bayfield CO 81122",
    "addr:housenumber":"650",
    "addr:postcode":"81122",
    "addr:street":"Buck Hwy",
    "iso:country":"US",
    "sg:address":"650 Buck Hwy",
    "sg:city":"Bayfield",
    "sg:classifiers":[
        {
            "category":"Organizations",
            "subcategory":"Religious Organization",
            "type":"Services"
        }
    ],
    "sg:phone":"+1 970 884 9308",
    "sg:postcode":"81122",
    "sg:province":"CO",
    "sg:tags":[
        "church"
    ],
    "wof:name":"First Baptist Church",
    "wof:placetype":"venue"
},
  "geometry": {"coordinates":[-107.608096,37.143203],"type":"Point"}
}