{
  "type": "Feature",
  "properties": {
    "addr:full":"734 E 3rd Ave Durango CO 81301",
    "addr:housenumber":"734",
    "addr:postcode":"co 81301",
    "addr:street":"E 3Rd Ave",
    "iso:country":"US",
    "sg:address":"734 E 3rd Ave",
    "sg:city":"Durango",
    "sg:classifiers":[
        {
            "category":"Building & Trades",
            "subcategory":"Construction",
            "type":"Services"
        }
    ],
    "sg:phone":"+1 970 385 8696",
    "sg:postcode":"81301",
    "sg:province":"CO",
    "sg:tags":[
        "house"
    ],
    "wof:name":"McCracken Construction",
    "wof:placetype":"venue"
},
  "geometry": {"coordinates":[-107.878344,37.271341],"type":"Point"}
}