{
  "type": "Feature",
  "properties": {
    "addr:full":"1088 S Mescal Dr Pueblo CO 81007",
    "addr:housenumber":"1088",
    "addr:postcode":"81007",
    "addr:street":"S Mescal Dr",
    "iso:country":"US",
    "sg:address":"1088 S Mescal Dr",
    "sg:city":"Pueblo",
    "sg:classifiers":[
        {
            "category":"Building & Trades",
            "subcategory":"Construction",
            "type":"Services"
        }
    ],
    "sg:phone":"+1 719 647 0302",
    "sg:postcode":"81007",
    "sg:province":"CO",
    "sg:tags":[
        "contractor"
    ],
    "wof:name":"Whiterock Drywall",
    "wof:placetype":"venue"
},
  "geometry": {"coordinates":[-104.771646,38.301161],"type":"Point"}
}