{
  "type": "Feature",
  "properties": {
    "addr:full":"901 N Saint Vrain Ave Estes Park CO 80517",
    "addr:housenumber":"901",
    "addr:postcode":"80517",
    "addr:street":"N Saint Vrain Ave",
    "iso:country":"US",
    "sg:address":"901 N Saint Vrain Ave",
    "sg:city":"Estes Park",
    "sg:classifiers":[
        {
            "category":"Government",
            "subcategory":"Fire Station",
            "type":"Public Place"
        }
    ],
    "sg:phone":"+1 970 577 0900",
    "sg:postcode":"80517",
    "sg:province":"CO",
    "sg:tags":[
        "department"
    ],
    "wof:name":"Estes Park Fire Dept",
    "wof:placetype":"venue"
},
  "geometry": {"coordinates":[-105.50790499999999,40.375748],"type":"Point"}
}