{
  "type": "Feature",
  "properties": {
    "addr:full":"1682 S Quitman St Denver CO 80219",
    "addr:housenumber":"1682",
    "addr:postcode":"80219",
    "addr:street":"S Quitman St",
    "iso:country":"US",
    "sg:address":"1682 S Quitman St",
    "sg:city":"Denver",
    "sg:classifiers":[
        {
            "category":"Building & Trades",
            "subcategory":"Construction",
            "type":"Services"
        }
    ],
    "sg:phone":"+1 303 936 1315",
    "sg:postcode":"80219",
    "sg:province":"CO",
    "sg:tags":[
        "carpentry",
        "contractor"
    ],
    "wof:name":"Stanley Custom Woodworking",
    "wof:placetype":"venue"
},
  "geometry": {"coordinates":[-105.041066,39.687522],"type":"Point"}
}