{
  "type": "Feature",
  "properties": {
    "addr:full":"1024 Longview Cir Steamboat Springs CO 80487",
    "addr:housenumber":"1024",
    "addr:postcode":"80487",
    "addr:street":"Longview Cir",
    "iso:country":"US",
    "sg:address":"1024 Longview Cir",
    "sg:city":"Steamboat Springs",
    "sg:classifiers":[
        {
            "category":"Real Estate",
            "subcategory":"Developer",
            "type":"Services"
        }
    ],
    "sg:phone":"+1 970 870 0697",
    "sg:postcode":"80487",
    "sg:province":"CO",
    "sg:tags":[
        "hardware"
    ],
    "wof:name":"True Mountain Home Inc",
    "wof:placetype":"venue"
},
  "geometry": {"coordinates":[-106.820835,40.470865],"type":"Point"}
}