{
  "type": "Feature",
  "properties": {
    "iso:country":"US",
    "sg:address":"657 Green St",
    "sg:city":"Craig",
    "sg:classifiers":[
        {
            "category":"Organizations",
            "subcategory":"Religious Organization",
            "type":"Services"
        }
    ],
    "sg:phone":"+1 970 824 3470",
    "sg:postcode":"81625",
    "sg:province":"CO",
    "sg:tags":[
        "church"
    ],
    "wof:name":"St Mark's Episcopal Chr",
    "wof:placetype":"venue"
},
  "geometry": {"coordinates":[-107.555622,40.517766],"type":"Point"}
}