{
  "type": "Feature",
  "properties": {
    "iso:country":"US",
    "sg:address":"750 N Jefferson Ave",
    "sg:city":"Loveland",
    "sg:classifiers":[
        {
            "category":"Freight",
            "type":"Transportation"
        }
    ],
    "sg:phone":"+1 970 667 7537",
    "sg:postcode":"80537",
    "sg:province":"CO",
    "sg:tags":[
        "hauler",
        "contract"
    ],
    "wof:name":"M & M Trucking",
    "wof:placetype":"venue"
},
  "geometry": {"coordinates":[-105.071741,40.399293],"type":"Point"}
}