{
  "type": "Feature",
  "properties": {
    "iso:country":"US",
    "sg:address":"162 Alhambra Dr",
    "sg:city":"Pueblo",
    "sg:classifiers":[
        {
            "category":"Building & Trades",
            "subcategory":"Electrical",
            "type":"Services"
        }
    ],
    "sg:phone":"+1 719 564 8859",
    "sg:postcode":"81005",
    "sg:province":"CO",
    "sg:tags":[
        "electrical",
        "contractor"
    ],
    "wof:name":"Danmarc Electric Inc",
    "wof:placetype":"venue"
},
  "geometry": {"coordinates":[-104.667697,38.218925],"type":"Point"}
}