{
  "type": "Feature",
  "properties": {
    "addr:full":"4330 E 6th Avenue Parkway Denver CO 80220",
    "addr:housenumber":"4330",
    "addr:postcode":"80220",
    "addr:street":"E 6Th Avenue Parkway",
    "iso:country":"US",
    "sg:address":"4330 E 6th Avenue Parkway",
    "sg:city":"Denver",
    "sg:classifiers":[
        {
            "category":"Education",
            "subcategory":"School",
            "type":"Public Place"
        }
    ],
    "sg:phone":"+1 303 321 3471",
    "sg:postcode":"80220",
    "sg:province":"CO",
    "wof:name":"French & Associates",
    "wof:placetype":"venue"
},
  "geometry": {"coordinates":[-104.936387,39.725198],"type":"Point"}
}