{
  "type": "Feature",
  "properties": {
    "iso:country":"US",
    "sg:address":"1170 Ford St",
    "sg:city":"Colorado Springs",
    "sg:classifiers":[
        {
            "category":"Home & Garden",
            "subcategory":"Building Materials",
            "type":"Retail Goods"
        }
    ],
    "sg:phone":"+1 719 596 5500",
    "sg:postcode":"80915",
    "sg:province":"CO",
    "sg:tags":[
        "door"
    ],
    "wof:name":"Overhead Door Corp",
    "wof:placetype":"venue"
},
  "geometry": {"coordinates":[-104.71186299999999,38.850508],"type":"Point"}
}