{
  "type": "Feature",
  "properties": {
    "iso:country":"US",
    "sg:address":"1575 Boulder St Ste D",
    "sg:city":"Denver",
    "sg:classifiers":[
        {
            "category":"Personal",
            "subcategory":"Beauty Salon",
            "type":"Services"
        }
    ],
    "sg:phone":"+1 720 855 7839",
    "sg:postcode":"80211",
    "sg:province":"CO",
    "sg:tags":[
        "hair"
    ],
    "sg:website":"www.scarletsalon.com",
    "wof:name":"Scarlet Salon",
    "wof:placetype":"venue"
},
  "geometry": {"coordinates":[-105.010918,39.759242],"type":"Point"}
}