{
  "type": "Feature",
  "properties": {
    "iso:country":"US",
    "sg:address":"1002 N Selig Ave",
    "sg:city":"Montrose",
    "sg:classifiers":[
        {
            "category":"Retail",
            "subcategory":"Repair Shop",
            "type":"Services"
        }
    ],
    "sg:phone":"+1 970 240 6180",
    "sg:postcode":"81401",
    "sg:province":"CO",
    "sg:tags":[
        "plumbing",
        "drain",
        "cleaning",
        "sewer"
    ],
    "wof:name":"Bercillio Plumbing & Repair",
    "wof:placetype":"venue"
},
  "geometry": {"coordinates":[-107.888334,38.486395],"type":"Point"}
}