{
  "type": "Feature",
  "properties": {
    "iso:country":"US",
    "sg:address":"1825 Sharp Point Dr",
    "sg:city":"Fort Collins",
    "sg:classifiers":[
        {
            "category":"Professional",
            "subcategory":"Computer Services",
            "type":"Services"
        }
    ],
    "sg:phone":"+1 970 482 7145",
    "sg:postcode":"80525",
    "sg:province":"CO",
    "sg:tags":[
        "design",
        "software"
    ],
    "wof:name":"Wind-2 Software Inc",
    "wof:placetype":"venue"
},
  "geometry": {"coordinates":[-105.028773,40.563056],"type":"Point"}
}