{
  "type": "Feature",
  "properties": {
    "addr:full":"12055 W 2nd Pl Denver CO 80228",
    "addr:housenumber":"12055",
    "addr:postcode":"80228",
    "addr:street":"W 2Nd Pl",
    "iso:country":"US",
    "sg:address":"12055 W 2nd Pl",
    "sg:city":"Denver",
    "sg:classifiers":[
        {
            "category":"Wholesale",
            "subcategory":"Durable Goods & Equipment",
            "type":"Manufacturing & Wholesale Goods"
        }
    ],
    "sg:phone":"+1 303 232 1244",
    "sg:postcode":"80228",
    "sg:province":"CO",
    "sg:tags":[
        "video",
        "educational",
        "produce",
        "tape",
        "training"
    ],
    "wof:name":"Video Professor Inc",
    "wof:placetype":"venue"
},
  "geometry": {"coordinates":[-105.133686,39.718317],"type":"Point"}
}