{
  "type": "Feature",
  "properties": {
    "iso:country":"US",
    "sg:address":"8992 E 34th Ave",
    "sg:city":"Denver",
    "sg:classifiers":[
        {
            "category":"Building & Trades",
            "subcategory":"Construction",
            "type":"Services"
        }
    ],
    "sg:phone":"+1 720 941 6891",
    "sg:postcode":"80238",
    "sg:province":"CO",
    "sg:tags":[
        "contractor"
    ],
    "sg:website":"www.kbhome.com",
    "wof:name":"Kb Homes",
    "wof:placetype":"venue"
},
  "geometry": {"coordinates":[-104.883708,39.763584],"type":"Point"}
}