{
  "type": "Feature",
  "properties": {
    "iso:country":"US",
    "sg:address":"1530 Grand Ave",
    "sg:city":"Norwood",
    "sg:classifiers":[
        {
            "category":"Insurance",
            "subcategory":"Insurance Agent",
            "type":"Services"
        }
    ],
    "sg:phone":"+1 970 327 0415",
    "sg:postcode":"81423",
    "sg:province":"CO",
    "wof:name":"Martin Agency Inc",
    "wof:placetype":"venue"
},
  "geometry": {"coordinates":[-108.29088900000001,38.130666],"type":"Point"}
}