{
  "type": "Feature",
  "properties": {
    "addr:full":"8490 Lamar Dr Arvada CO 80003",
    "addr:housenumber":"8490",
    "addr:postcode":"80003",
    "addr:street":"Lamar Dr",
    "iso:country":"US",
    "sg:address":"8490 Lamar Dr",
    "sg:city":"Arvada",
    "sg:classifiers":[
        {
            "category":"Manufacturing",
            "subcategory":"Printing",
            "type":"Manufacturing & Wholesale Goods"
        }
    ],
    "sg:phone":"+1 303 423 8906",
    "sg:postcode":"80003",
    "sg:province":"CO",
    "sg:tags":[
        "periodical"
    ],
    "wof:name":"Fall River Distributiong",
    "wof:placetype":"venue"
},
  "geometry": {"coordinates":[-105.063956,39.851489],"type":"Point"}
}