{
  "type": "Feature",
  "properties": {
    "addr:full":"4298 S Broadway Englewood CO 80113",
    "addr:housenumber":"4298",
    "addr:postcode":"80113",
    "addr:street":"S Broadway",
    "iso:country":"US",
    "sg:address":"4298 S Broadway",
    "sg:city":"Englewood",
    "sg:classifiers":[
        {
            "category":"Retail",
            "subcategory":"Auto Repair",
            "type":"Services"
        }
    ],
    "sg:phone":"+1 303 788 1718",
    "sg:postcode":"80113",
    "sg:province":"CO",
    "sg:tags":[
        "repairing",
        "automobile"
    ],
    "wof:name":"Honda & Acura Svc",
    "wof:placetype":"venue"
},
  "geometry": {"coordinates":[-104.98779500000001,39.640361],"type":"Point"}
}