{
  "type": "Feature",
  "properties": {
    "addr:full":"2600 S Oak Hurst Ct Glenwood Springs CO 81601",
    "addr:housenumber":"2600",
    "addr:postcode":"81601",
    "addr:street":"S Oak Hurst Ct",
    "iso:country":"US",
    "sg:address":"2600 S Oak Hurst Ct",
    "sg:city":"Glenwood Springs",
    "sg:classifiers":[
        {
            "category":"Shopping",
            "type":"Retail Goods"
        }
    ],
    "sg:phone":"+1 970 945 0179",
    "sg:postcode":"81601",
    "sg:province":"CO",
    "sg:tags":[
        "merchandise"
    ],
    "wof:name":"Lauries TLC Pet Serve",
    "wof:placetype":"venue"
},
  "geometry": {"coordinates":[-107.321173,39.526603],"type":"Point"}
}