{
  "type": "Feature",
  "properties": {
    "iso:country":"US",
    "sg:address":"2755 S Locust St",
    "sg:city":"Denver",
    "sg:classifiers":[
        {
            "category":"Real Estate",
            "subcategory":"Real Estate Agent",
            "type":"Services"
        }
    ],
    "sg:phone":"+1 303 782 9641",
    "sg:postcode":"80222",
    "sg:province":"CO",
    "sg:tags":[
        "investment"
    ],
    "wof:name":"R I A: Investments Inc",
    "wof:placetype":"venue"
},
  "geometry": {"coordinates":[-104.915482,39.66527],"type":"Point"}
}