{
  "type": "Feature",
  "properties": {
    "addr:full":"3050 S Laredo St Aurora CO 80013",
    "addr:housenumber":"3050",
    "addr:postcode":"80013",
    "addr:street":"S Laredo St",
    "iso:country":"US",
    "sg:address":"3050 S Laredo St",
    "sg:city":"Aurora",
    "sg:classifiers":[
        {
            "category":"Education",
            "subcategory":"School",
            "type":"Public Place"
        }
    ],
    "sg:phone":"+1 303 690 1155",
    "sg:postcode":"80013",
    "sg:province":"CO",
    "wof:name":"Dartmouth Elementary School",
    "wof:placetype":"venue"
},
  "geometry": {"coordinates":[-104.80037400000001,39.662458],"type":"Point"}
}