{
  "type": "Feature",
  "properties": {
    "iso:country":"US",
    "sg:address":"12323 Rock Ln",
    "sg:city":"Longmont",
    "sg:classifiers":[
        {
            "category":"Professional",
            "subcategory":"Research",
            "type":"Services"
        }
    ],
    "sg:phone":"+1 303 774 8262",
    "sg:postcode":"80501",
    "sg:province":"CO",
    "sg:tags":[
        "laboratory"
    ],
    "wof:name":"CII",
    "wof:placetype":"venue"
},
  "geometry": {"coordinates":[-105.062276,40.204],"type":"Point"}
}