{
  "type": "Feature",
  "properties": {
    "addr:full":"1208 E 21st Ct Loveland CO 80538",
    "addr:housenumber":"1208",
    "addr:postcode":"80538",
    "addr:street":"E 21St Ct",
    "iso:country":"US",
    "sg:address":"1208 E 21st Ct",
    "sg:city":"Loveland",
    "sg:classifiers":[
        {
            "category":"Professional",
            "subcategory":"Advertising",
            "type":"Services"
        }
    ],
    "sg:phone":"+1 970 667 1421",
    "sg:postcode":"80538",
    "sg:province":"CO",
    "wof:name":"Moore Enterprises",
    "wof:placetype":"venue"
},
  "geometry": {"coordinates":[-105.059743,40.414243],"type":"Point"}
}