{
  "type": "Feature",
  "properties": {
    "iso:country":"US",
    "sg:address":"47 Davidson Ln",
    "sg:city":"Snowmass",
    "sg:classifiers":[
        {
            "category":"Building & Trades",
            "subcategory":"Construction",
            "type":"Services"
        }
    ],
    "sg:phone":"+1 970 927 3742",
    "sg:postcode":"81654",
    "sg:province":"CO",
    "sg:tags":[
        "home",
        "general",
        "family",
        "contractor"
    ],
    "wof:name":"ACME Inc",
    "wof:placetype":"venue"
},
  "geometry": {"coordinates":[-107.008771,39.299762],"type":"Point"}
}