{
  "type": "Feature",
  "properties": {
    "iso:country":"US",
    "sg:address":"1240 Doctors Ln",
    "sg:city":"Fort Collins",
    "sg:classifiers":[
        {
            "category":"Personal",
            "type":"Services"
        }
    ],
    "sg:phone":"+1 970 988 1899",
    "sg:postcode":"80524",
    "sg:province":"CO",
    "sg:tags":[
        "therapist",
        "massage"
    ],
    "wof:name":"Maureen Carrigan",
    "wof:placetype":"venue"
},
  "geometry": {"coordinates":[-105.05623900000001,40.572978],"type":"Point"}
}