{
  "type": "Feature",
  "properties": {
    "addr:full":"7801 W Colfax Ave Denver CO 80214",
    "addr:housenumber":"7801",
    "addr:postcode":"80214",
    "addr:street":"W Colfax Ave",
    "iso:country":"US",
    "sg:address":"7801 W Colfax Ave",
    "sg:city":"Denver",
    "sg:classifiers":[
        {
            "category":"Shopping",
            "subcategory":"Used Merchandise",
            "type":"Retail Goods"
        }
    ],
    "sg:phone":"+1 303 238 2274",
    "sg:postcode":"80214",
    "sg:province":"CO",
    "wof:name":"Massa Auto Sales",
    "wof:placetype":"venue"
},
  "geometry": {"coordinates":[-105.0849,39.740291],"type":"Point"}
}