{
  "type": "Feature",
  "properties": {
    "iso:country":"US",
    "sg:address":"517 California St",
    "sg:city":"Sterling",
    "sg:classifiers":[
        {
            "category":"Banks & Credit Unions",
            "subcategory":"Bank",
            "type":"Services"
        }
    ],
    "sg:phone":"+1 970 521 7288",
    "sg:postcode":"80751",
    "sg:province":"CO",
    "sg:tags":[
        "loan",
        "real estate"
    ],
    "wof:name":"JKS Mortgage",
    "wof:placetype":"venue"
},
  "geometry": {"coordinates":[-103.202916,40.643397],"type":"Point"}
}