{
  "type": "Feature",
  "properties": {
    "addr:full":"589 High Llama Ln Durango CO 81301",
    "addr:housenumber":"589",
    "addr:postcode":"co 81301",
    "addr:street":"High Llama Ln",
    "iso:country":"US",
    "sg:address":"589 High Llama Ln",
    "sg:city":"Durango",
    "sg:classifiers":[
        {
            "category":"Farming",
            "subcategory":"Livestock Farm",
            "type":"Manufacturing & Wholesale Goods"
        }
    ],
    "sg:phone":"+1 970 382 0026",
    "sg:postcode":"81301",
    "sg:province":"CO",
    "sg:tags":[
        "llama"
    ],
    "wof:name":"Columbine Llamas",
    "wof:placetype":"venue"
},
  "geometry": {"coordinates":[-107.83271000000001,37.234623],"type":"Point"}
}