{
  "type": "Feature",
  "properties": {
    "iso:country":"US",
    "sg:address":"7313 E Colfax Avenue",
    "sg:city":"Denver",
    "sg:classifiers":[
        {
            "category":"Restaurant",
            "type":"Food & Drink"
        }
    ],
    "sg:phone":"+1 303 394 4053",
    "sg:postcode":"80220",
    "sg:province":"CO",
    "sg:website":"www.burgerking.com",
    "wof:name":"Burger King",
    "wof:placetype":"venue"
},
  "geometry": {"coordinates":[-104.903396,39.740302],"type":"Point"}
}