{
  "type": "Feature",
  "properties": {
    "iso:country":"US",
    "sg:address":"304 Co Rd 21",
    "sg:city":"Loveland",
    "sg:classifiers":[
        {
            "category":"Professional",
            "subcategory":"Computer Services",
            "type":"Services"
        }
    ],
    "sg:phone":"+1 970 663 7196",
    "sg:postcode":"80537",
    "sg:province":"CO",
    "sg:tags":[
        "website",
        "design"
    ],
    "wof:name":"Valley Graphics",
    "wof:placetype":"venue"
},
  "geometry": {"coordinates":[-105.13092899999999,40.388863],"type":"Point"}
}