{
  "type": "Feature",
  "properties": {
    "iso:country":"US",
    "sg:address":"120 N 31st St",
    "sg:city":"Colorado Springs",
    "sg:classifiers":[
        {
            "category":"Social Services",
            "subcategory":"Child Care",
            "type":"Services"
        }
    ],
    "sg:phone":"+1 719 632 9491",
    "sg:postcode":"80904",
    "sg:province":"CO",
    "sg:tags":[
        "day"
    ],
    "sg:website":"www.rockofageslcms.org",
    "wof:name":"Rock of Ages Lutheran Child Care Center",
    "wof:placetype":"venue"
},
  "geometry": {"coordinates":[-104.871002,38.8545],"type":"Point"}
}