{
  "type": "Feature",
  "properties": {
    "addr:full":"500 Theresa Dr Boulder CO 80303",
    "addr:housenumber":"500",
    "addr:postcode":"80303",
    "addr:street":"Theresa Dr",
    "iso:country":"US",
    "sg:address":"500 Theresa Dr",
    "sg:city":"Boulder",
    "sg:classifiers":[
        {
            "category":"Building & Trades",
            "subcategory":"Construction",
            "type":"Services"
        }
    ],
    "sg:phone":"+1 303 543 9549",
    "sg:postcode":"80303",
    "sg:province":"CO",
    "sg:tags":[
        "contractor"
    ],
    "wof:name":"Metro Contracting Services",
    "wof:placetype":"venue"
},
  "geometry": {"coordinates":[-105.16680100000001,39.997613],"type":"Point"}
}