{
  "type": "Feature",
  "properties": {
    "addr:full":"2826 Zuni St Denver CO 80211",
    "addr:housenumber":"2826",
    "addr:postcode":"80211",
    "addr:street":"Zuni St",
    "iso:country":"US",
    "sg:address":"2826 Zuni St",
    "sg:city":"Denver",
    "sg:classifiers":[
        {
            "category":"Wholesale",
            "subcategory":"Machinery & Supplies",
            "type":"Manufacturing & Wholesale Goods"
        }
    ],
    "sg:phone":"+1 303 455 5357",
    "sg:postcode":"80211",
    "sg:province":"CO",
    "sg:tags":[
        "fire",
        "department",
        "equipment",
        "firefighting",
        "policeman"
    ],
    "wof:name":"Ssi Emergency Equipment",
    "wof:placetype":"venue"
},
  "geometry": {"coordinates":[-105.01575800000001,39.758078],"type":"Point"}
}