{
  "type": "Feature",
  "properties": {
    "iso:country":"US",
    "sg:address":"1475 S Zephyr St",
    "sg:city":"Denver",
    "sg:classifiers":[
        {
            "category":"Retail",
            "subcategory":"Auto Repair",
            "type":"Services"
        }
    ],
    "sg:phone":"+1 303 989 4519",
    "sg:postcode":"80232",
    "sg:province":"CO",
    "sg:tags":[
        "general"
    ],
    "wof:name":"Rocky Mountain Big Brake Inc",
    "wof:placetype":"venue"
},
  "geometry": {"coordinates":[-105.084464,39.691792],"type":"Point"}
}