{
  "type": "Feature",
  "properties": {
    "iso:country":"US",
    "sg:address":"8743 Sheridan Blvd",
    "sg:city":"Arvada",
    "sg:classifiers":[
        {
            "category":"Banks & Credit Unions",
            "subcategory":"Bank",
            "type":"Services"
        }
    ],
    "sg:phone":"+1 303 540 7770",
    "sg:postcode":"80003",
    "sg:province":"CO",
    "sg:tags":[
        "loan"
    ],
    "wof:name":"Loan Mart-Payday Loans",
    "wof:placetype":"venue"
},
  "geometry": {"coordinates":[-105.053984,39.854864],"type":"Point"}
}