{
  "type": "Feature",
  "properties": {
    "addr:full":"418 S Newark Way Aurora CO 80012",
    "addr:housenumber":"418",
    "addr:postcode":"80012",
    "addr:street":"S Newark Way",
    "iso:country":"US",
    "sg:address":"418 S Newark Way",
    "sg:city":"Aurora",
    "sg:classifiers":[
        {
            "category":"Retail",
            "subcategory":"Portrait Studio",
            "type":"Services"
        }
    ],
    "sg:phone":"+1 303 365 0326",
    "sg:postcode":"80012",
    "sg:province":"CO",
    "sg:tags":[
        "photographer"
    ],
    "wof:name":"Photo Imagen",
    "wof:placetype":"venue"
},
  "geometry": {"coordinates":[-104.854367,39.707945],"type":"Point"}
}