{
  "type": "Feature",
  "properties": {
    "addr:full":"113 N 5th St Canon City CO 81212",
    "addr:housenumber":"113",
    "addr:postcode":"81212",
    "addr:street":"N 5Th St",
    "iso:country":"US",
    "sg:address":"113 N 5th St",
    "sg:city":"Canon City",
    "sg:classifiers":[
        {
            "category":"Education",
            "subcategory":"Dance Studio",
            "type":"Public Place"
        }
    ],
    "sg:phone":"+1 719 269 9775",
    "sg:postcode":"81212",
    "sg:province":"CO",
    "sg:tags":[
        "instruction",
        "dancing"
    ],
    "wof:name":"School Of Ballet Arts",
    "wof:placetype":"venue"
},
  "geometry": {"coordinates":[-105.24105,38.44083],"type":"Point"}
}