{
  "type": "Feature",
  "properties": {
    "iso:country":"US",
    "sg:address":"113 N 5th St",
    "sg:city":"Canon City",
    "sg:classifiers":[
        {
            "category":"Education",
            "subcategory":"Dance Studio",
            "type":"Public Place"
        }
    ],
    "sg:phone":"+1 719 269 9775",
    "sg:postcode":"81212",
    "sg:province":"CO",
    "sg:tags":[
        "instruction",
        "dancing"
    ],
    "wof:name":"School Of Ballet Arts",
    "wof:placetype":"venue"
},
  "geometry": {"coordinates":[-105.24105,38.44083],"type":"Point"}
}