{
  "type": "Feature",
  "properties": {
    "iso:country":"US",
    "sg:address":"3 Birdsilla Pl",
    "sg:city":"Longmont",
    "sg:classifiers":[
        {
            "category":"Professional",
            "subcategory":"Art Services",
            "type":"Services"
        }
    ],
    "sg:phone":"+1 303 772 9636",
    "sg:postcode":"80501",
    "sg:province":"CO",
    "sg:tags":[
        "graphic",
        "designer"
    ],
    "wof:name":"Visual Weight",
    "wof:placetype":"venue"
},
  "geometry": {"coordinates":[-105.0945,40.201167],"type":"Point"}
}