{
  "type": "Feature",
  "properties": {
    "addr:full":"1010 W 30th St Loveland CO 80538",
    "addr:housenumber":"1010",
    "addr:postcode":"80538",
    "addr:street":"W 30Th St",
    "iso:country":"US",
    "sg:address":"1010 W 30th St",
    "sg:city":"Loveland",
    "sg:classifiers":[
        {
            "category":"Retail",
            "subcategory":"Animal Services",
            "type":"Services"
        }
    ],
    "sg:phone":"+1 970 663 1786",
    "sg:postcode":"80538",
    "sg:province":"CO",
    "wof:name":"Perfect Companions",
    "wof:placetype":"venue"
},
  "geometry": {"coordinates":[-105.091087,40.422447],"type":"Point"}
}