{
  "type": "Feature",
  "properties": {
    "addr:full":"53 Meadow Lakes Dr Lyons CO 80540",
    "addr:housenumber":"53",
    "addr:postcode":"80540",
    "addr:street":"Meadow Lakes Dr",
    "iso:country":"US",
    "sg:address":"53 Meadow Lakes Dr",
    "sg:city":"Lyons",
    "sg:classifiers":[
        {
            "category":"Wholesale",
            "subcategory":"Durable Goods & Equipment",
            "type":"Manufacturing & Wholesale Goods"
        }
    ],
    "sg:phone":"+1 303 823 9570",
    "sg:postcode":"80540",
    "sg:province":"CO",
    "sg:tags":[
        "professional"
    ],
    "wof:name":"A G A Geodimeter",
    "wof:placetype":"venue"
},
  "geometry": {"coordinates":[-105.420473,40.261156],"type":"Point"}
}