{
  "type": "Feature",
  "properties": {
    "addr:full":"10393 Huron St Northglenn CO 80260",
    "addr:housenumber":"10393",
    "addr:postcode":"80260",
    "addr:street":"Huron St",
    "iso:country":"US",
    "sg:address":"10393 Huron St",
    "sg:city":"Northglenn",
    "sg:classifiers":[
        {
            "category":"Banks & Credit Unions",
            "subcategory":"Investment Brokerage",
            "type":"Services"
        }
    ],
    "sg:phone":"+1 303 331 3645",
    "sg:postcode":"80260",
    "sg:province":"CO",
    "sg:tags":[
        "security"
    ],
    "sg:website":"www.investfinancial.com",
    "wof:name":"Investment Centers Of America",
    "wof:placetype":"venue"
},
  "geometry": {"coordinates":[-104.996808,39.88417],"type":"Point"}
}