{
  "type": "Feature",
  "properties": {
    "addr:full":"1330 Leyden St Denver CO 80220",
    "addr:housenumber":"1330",
    "addr:postcode":"80220",
    "addr:street":"Leyden St",
    "iso:country":"US",
    "sg:address":"1330 Leyden St",
    "sg:city":"Denver",
    "sg:classifiers":[
        {
            "category":"Professional",
            "subcategory":"Lawyer & Legal Services",
            "type":"Services"
        }
    ],
    "sg:phone":"+1 303 997 4700",
    "sg:postcode":"80220",
    "sg:province":"CO",
    "wof:name":"Loretta Collins ESQ",
    "wof:placetype":"venue"
},
  "geometry": {"coordinates":[-104.914855,39.737248],"type":"Point"}
}