{
  "type": "Feature",
  "properties": {
    "addr:full":"9804 S Yosemite St Littleton CO 80124",
    "addr:housenumber":"9804",
    "addr:postcode":"80124",
    "addr:street":"S Yosemite St",
    "iso:country":"US",
    "sg:address":"9804 S Yosemite St",
    "sg:city":"Littleton",
    "sg:classifiers":[
        {
            "category":"Restaurant",
            "type":"Food & Drink"
        }
    ],
    "sg:menulink":"http://www.allmenus.com/co/sedalia/189422-kfc---kentucky-fried-chicken/menu/",
    "sg:phone":"+1 303 790 9595",
    "sg:postcode":"80124",
    "sg:province":"CO",
    "sg:tags":[
        "american",
        "chicken"
    ],
    "wof:name":"KFC - Kentucky Fried Chicken",
    "wof:placetype":"venue"
},
  "geometry": {"coordinates":[-104.884726,39.53716],"type":"Point"}
}