{
  "type": "Feature",
  "properties": {
    "iso:country":"US",
    "sg:address":"100 N Chestnut St",
    "sg:city":"Trinidad",
    "sg:classifiers":[
        {
            "category":"Freight",
            "type":"Transportation"
        }
    ],
    "sg:phone":"+1 719 845 0840",
    "sg:postcode":"81082",
    "sg:province":"CO",
    "sg:tags":[
        "trucking"
    ],
    "wof:name":"Bullocks Express",
    "wof:placetype":"venue"
},
  "geometry": {"coordinates":[-104.50368400000001,37.17039],"type":"Point"}
}