{
  "type": "Feature",
  "properties": {
    "iso:country":"US",
    "sg:address":"3295 Blake St",
    "sg:city":"Denver",
    "sg:classifiers":[
        {
            "category":"Sports & Exercise",
            "subcategory":"Golf",
            "type":"Entertainment"
        }
    ],
    "sg:phone":"+1 303 623 3466",
    "sg:postcode":"80205",
    "sg:province":"CO",
    "sg:tags":[
        "course"
    ],
    "wof:name":"Redstone Inc Golf Crse",
    "wof:placetype":"venue"
},
  "geometry": {"coordinates":[-104.987748,39.759464],"type":"Point"}
}