{
  "type": "Feature",
  "properties": {
    "addr:full":"8455 Pecos St Denver CO 80260",
    "addr:housenumber":"8455",
    "addr:postcode":"80260",
    "addr:street":"Pecos St",
    "iso:country":"US",
    "sg:address":"8455 Pecos St",
    "sg:city":"Denver",
    "sg:classifiers":[
        {
            "category":"Building & Trades",
            "subcategory":"Equipment Rental",
            "type":"Services"
        }
    ],
    "sg:phone":"+1 303 657 3000",
    "sg:postcode":"80260",
    "sg:province":"CO",
    "sg:tags":[
        "leasing",
        "furniture"
    ],
    "sg:website":"www.shopaarons.com",
    "wof:name":"Aarons Sales & Lease Ownership",
    "wof:placetype":"venue"
},
  "geometry": {"coordinates":[-105.006173,39.849423],"type":"Point"}
}