{
  "type": "Feature",
  "properties": {
    "addr:full":"10011 S Stratford Ln Littleton CO 80126",
    "addr:housenumber":"10011",
    "addr:postcode":"80126",
    "addr:street":"S Stratford Ln",
    "iso:country":"US",
    "sg:address":"10011 S Stratford Ln",
    "sg:city":"Littleton",
    "sg:classifiers":[
        {
            "category":"Banks & Credit Unions",
            "subcategory":"Investment Brokerage",
            "type":"Services"
        }
    ],
    "sg:phone":"+1 303 346 8663",
    "sg:postcode":"80126",
    "sg:province":"CO",
    "sg:tags":[
        "consultant",
        "planning",
        "financial"
    ],
    "wof:name":"Turner Financial Planning",
    "wof:placetype":"venue"
},
  "geometry": {"coordinates":[-104.963521,39.533799],"type":"Point"}
}