{
  "type": "Feature",
  "properties": {
    "iso:country":"US",
    "sg:address":"10376 Colorado Blvd",
    "sg:city":"Denver",
    "sg:classifiers":[
        {
            "category":"Restaurant",
            "type":"Food & Drink"
        }
    ],
    "sg:menulink":"http://www.allmenus.com/co/west-adams/128396-subway/menu/",
    "sg:phone":"+1 303 451 9231",
    "sg:postcode":"80229",
    "sg:province":"CO",
    "sg:tags":[
        "american",
        "sandwich"
    ],
    "wof:name":"Subway",
    "wof:placetype":"venue"
},
  "geometry": {"coordinates":[-104.94016499999999,39.88444],"type":"Point"}
}