{
  "type": "Feature",
  "properties": {
    "iso:country":"US",
    "sg:address":"1785 Kipling St",
    "sg:city":"Lakewood",
    "sg:classifiers":[
        {
            "category":"Health Services",
            "subcategory":"Doctor",
            "type":"Services"
        }
    ],
    "sg:phone":"+1 303 935 4681",
    "sg:postcode":"80215",
    "sg:province":"CO",
    "sg:tags":[
        "physician",
        "family",
        "practice",
        "surgeons",
        "medicine",
        "dermatology"
    ],
    "sg:website":"http://www.alpinederm.com",
    "wof:name":"Alpine Dermatology Associates PC",
    "wof:placetype":"venue"
},
  "geometry": {"coordinates":[-105.109586,39.745441],"type":"Point"}
}