{
  "type": "Feature",
  "properties": {
    "iso:country":"US",
    "sg:address":"8005 S Logan Dr",
    "sg:city":"Littleton",
    "sg:classifiers":[
        {
            "category":"Building & Trades",
            "subcategory":"Construction",
            "type":"Services"
        }
    ],
    "sg:phone":"+1 303 794 8426",
    "sg:postcode":"80122",
    "sg:province":"CO",
    "sg:tags":[
        "consultant",
        "management"
    ],
    "wof:name":"Dave Schwan",
    "wof:placetype":"venue"
},
  "geometry": {"coordinates":[-104.98333700000001,39.570793],"type":"Point"}
}