{
  "type": "Feature",
  "properties": {
    "addr:full":"5275 Co Rd 30 Sedgwick CO 80749",
    "addr:housenumber":"5275;30",
    "addr:postcode":"80749",
    "addr:street":"Co Rd",
    "iso:country":"US",
    "sg:address":"5275 Co Rd 30",
    "sg:city":"Sedgwick",
    "sg:classifiers":[
        {
            "category":"Farming",
            "subcategory":"Livestock Farm",
            "type":"Manufacturing & Wholesale Goods"
        }
    ],
    "sg:phone":"+1 970 463 5732",
    "sg:postcode":"80749",
    "sg:province":"CO",
    "sg:tags":[
        "beef",
        "feedlot",
        "cattle"
    ],
    "wof:name":"H V Ranch Inc",
    "wof:placetype":"venue"
},
  "geometry": {"coordinates":[-102.540813,40.954126],"type":"Point"}
}