{
  "type": "Feature",
  "properties": {
    "addr:full":"10730 W 102nd Pl Broomfield CO 80021",
    "addr:housenumber":"10730",
    "addr:postcode":"80021",
    "addr:street":"W 102Nd Pl",
    "iso:country":"US",
    "sg:address":"10730 W 102nd Pl",
    "sg:city":"Broomfield",
    "sg:classifiers":[
        {
            "category":"Wholesale",
            "subcategory":"Machinery & Supplies",
            "type":"Manufacturing & Wholesale Goods"
        }
    ],
    "sg:phone":"+1 303 469 9445",
    "sg:postcode":"80021",
    "sg:province":"CO",
    "sg:tags":[
        "business"
    ],
    "wof:name":"Quality Belt Service Inc",
    "wof:placetype":"venue"
},
  "geometry": {"coordinates":[-105.11848000000001,39.88186],"type":"Point"}
}