{
  "type": "Feature",
  "properties": {
    "addr:full":"1638 S Rosemary St Denver CO 80231",
    "addr:housenumber":"1638",
    "addr:postcode":"80231",
    "addr:street":"S Rosemary St",
    "iso:country":"US",
    "sg:address":"1638 S Rosemary St",
    "sg:city":"Denver",
    "sg:classifiers":[
        {
            "category":"Organizations",
            "subcategory":"Religious Organization",
            "type":"Services"
        }
    ],
    "sg:phone":"+1 303 755 7575",
    "sg:postcode":"80231",
    "sg:province":"CO",
    "sg:tags":[
        "church"
    ],
    "wof:name":"Rocky Mountain Marian Ctr",
    "wof:placetype":"venue"
},
  "geometry": {"coordinates":[-104.89991499999999,39.686228],"type":"Point"}
}