{
  "type": "Feature",
  "properties": {
    "addr:full":"1485 S Colorado Blvd Ste 140 Denver CO 80222",
    "addr:housenumber":"1485",
    "addr:postcode":"80222",
    "addr:street":"S Colorado Blvd Ste 140",
    "iso:country":"US",
    "sg:address":"1485 S Colorado Blvd Ste 140",
    "sg:city":"Denver",
    "sg:classifiers":[
        {
            "category":"Personal",
            "subcategory":"Tanning Parlor",
            "type":"Services"
        }
    ],
    "sg:phone":"+1 303 692 8590",
    "sg:postcode":"80222",
    "sg:province":"CO",
    "sg:website":"www.beachclubcolorado.com",
    "wof:name":"The Beach Club",
    "wof:placetype":"venue"
},
  "geometry": {"coordinates":[-104.941368,39.689849],"type":"Point"}
}