{
  "type": "Feature",
  "properties": {
    "iso:country":"US",
    "sg:address":"3783 Evergreen Pkwy",
    "sg:city":"Evergreen",
    "sg:classifiers":[
        {
            "category":"Shopping",
            "subcategory":"Gifts & Souvenirs",
            "type":"Retail Goods"
        }
    ],
    "sg:phone":"+1 303 670 1550",
    "sg:postcode":"80439",
    "sg:province":"CO",
    "sg:tags":[
        "shop"
    ],
    "sg:website":"www.foothillflurries.com",
    "wof:name":"Foothill Flurries",
    "wof:placetype":"venue"
},
  "geometry": {"coordinates":[-105.339787,39.647316],"type":"Point"}
}