{
  "type": "Feature",
  "properties": {
    "addr:full":"28236 Co Rd H Cortez CO 81321",
    "addr:housenumber":"28236",
    "addr:postcode":"81321",
    "addr:street":"Co Rd H",
    "iso:country":"US",
    "sg:address":"28236 Co Rd H",
    "sg:city":"Cortez",
    "sg:classifiers":[
        {
            "category":"Building & Trades",
            "subcategory":"Plumbing",
            "type":"Services"
        }
    ],
    "sg:phone":"+1 970 565 3202",
    "sg:postcode":"81321",
    "sg:province":"CO",
    "sg:tags":[
        "contractor"
    ],
    "wof:name":"Anci Asdstos",
    "wof:placetype":"venue"
},
  "geometry": {"coordinates":[-108.538471,37.327105],"type":"Point"}
}