{
  "type": "Feature",
  "properties": {
    "addr:full":"1114 Washington Ave Golden CO 80401",
    "addr:housenumber":"1114",
    "addr:postcode":"80401",
    "addr:street":"Washington Ave",
    "iso:country":"US",
    "sg:address":"1114 Washington Ave",
    "sg:city":"Golden",
    "sg:classifiers":[
        {
            "category":"Shopping",
            "type":"Retail Goods"
        }
    ],
    "sg:phone":"+1 303 277 0705",
    "sg:postcode":"80401",
    "sg:province":"CO",
    "sg:tags":[
        "art",
        "gallery",
        "dealer"
    ],
    "wof:name":"Colorado Connossier LTD",
    "wof:placetype":"venue"
},
  "geometry": {"coordinates":[-105.221467,39.755471],"type":"Point"}
}