{
  "type": "Feature",
  "properties": {
    "iso:country":"US",
    "sg:address":"2584 S Dexter St",
    "sg:city":"Denver",
    "sg:classifiers":[
        {
            "category":"Shopping",
            "subcategory":"Antiques",
            "type":"Retail Goods"
        }
    ],
    "sg:phone":"+1 303 756 2912",
    "sg:postcode":"80222",
    "sg:province":"CO",
    "wof:name":"Keystone Antique Engines",
    "wof:placetype":"venue"
},
  "geometry": {"coordinates":[-104.932549,39.669032],"type":"Point"}
}