{
  "type": "Feature",
  "properties": {
    "addr:full":"609 Iowa Ave Palisade CO 81526",
    "addr:housenumber":"609",
    "addr:postcode":"81526",
    "addr:street":"Iowa Ave",
    "iso:country":"US",
    "sg:address":"609 Iowa Ave",
    "sg:city":"Palisade",
    "sg:classifiers":[
        {
            "category":"Retail",
            "subcategory":"Auto Repair",
            "type":"Services"
        }
    ],
    "sg:phone":"+1 970 464 5271",
    "sg:postcode":"81526",
    "sg:province":"CO",
    "sg:tags":[
        "repairing",
        "automobile"
    ],
    "wof:name":"Coe's Automotive",
    "wof:placetype":"venue"
},
  "geometry": {"coordinates":[-108.35567399999999,39.107109],"type":"Point"}
}