{
  "type": "Feature",
  "properties": {
    "iso:country":"US",
    "sg:address":"805 Best Ave",
    "sg:city":"La Junta",
    "sg:classifiers":[
        {
            "category":"Retail",
            "subcategory":"Animal Services",
            "type":"Services"
        }
    ],
    "sg:phone":"+1 719 384 5282",
    "sg:postcode":"81050",
    "sg:province":"CO",
    "wof:name":"K9 Design Dog Grooming",
    "wof:placetype":"venue"
},
  "geometry": {"coordinates":[-103.53133800000001,37.978993],"type":"Point"}
}