{
  "type": "Feature",
  "properties": {
    "iso:country":"US",
    "sg:address":"8690 Wolff Ct",
    "sg:city":"Westminster",
    "sg:classifiers":[
        {
            "category":"Professional",
            "type":"Services"
        }
    ],
    "sg:phone":"+1 303 427 5590",
    "sg:postcode":"80031",
    "sg:province":"CO",
    "sg:tags":[
        "establishment"
    ],
    "wof:name":"Heintz & Co",
    "wof:placetype":"venue"
},
  "geometry": {"coordinates":[-105.049345,39.854499],"type":"Point"}
}