{
  "type": "Feature",
  "properties": {
    "addr:full":"685 10th St Boulder CO 80302",
    "addr:housenumber":"685",
    "addr:postcode":"80302",
    "addr:street":"10Th St",
    "iso:country":"US",
    "sg:address":"685 10th St",
    "sg:city":"Boulder",
    "sg:classifiers":[
        {
            "category":"Organizations",
            "subcategory":"Membership Organization",
            "type":"Services"
        }
    ],
    "sg:phone":"+1 303 449 2586",
    "sg:postcode":"80302",
    "sg:province":"CO",
    "wof:name":"Romanian Amrcn Freedom Aliance",
    "wof:placetype":"venue"
},
  "geometry": {"coordinates":[-105.279719,39.999359],"type":"Point"}
}