{
  "type": "Feature",
  "properties": {
    "addr:full":"5760 State Hwy 151 Ignacio CO 81137",
    "addr:housenumber":"5760",
    "addr:postcode":"81137",
    "addr:street":"State Hwy 151 Ignacio",
    "iso:country":"US",
    "sg:address":"5760 State Hwy 151",
    "sg:city":"Ignacio",
    "sg:classifiers":[
        {
            "category":"Manufacturing",
            "subcategory":"Metals",
            "type":"Manufacturing & Wholesale Goods"
        },
        {
            "category":"Shopping",
            "subcategory":"Bicycles & Sporting Goods",
            "type":"Retail Goods"
        }
    ],
    "sg:phone":"+1 970 883 2333",
    "sg:postcode":"81137",
    "sg:province":"CO",
    "sg:tags":[
        "building",
        "prefabricated",
        "horse",
        "furnishing",
        "mfg"
    ],
    "wof:name":"Stewart Operations & Cnstr",
    "wof:placetype":"venue"
},
  "geometry": {"coordinates":[-107.541415,37.095785],"type":"Point"}
}