{
  "type": "Feature",
  "properties": {
    "addr:full":"930 Salida Way Aurora CO 80011",
    "addr:housenumber":"930",
    "addr:postcode":"80011",
    "addr:street":"Salida Way",
    "iso:country":"US",
    "sg:address":"930 Salida Way",
    "sg:city":"Aurora",
    "sg:classifiers":[
        {
            "category":"Building & Trades",
            "subcategory":"Construction",
            "type":"Services"
        }
    ],
    "sg:phone":"+1 720 532 0825",
    "sg:postcode":"80011",
    "sg:province":"CO",
    "sg:tags":[
        "contractor",
        "mechanical"
    ],
    "wof:name":"Am Mechanical",
    "wof:placetype":"venue"
},
  "geometry": {"coordinates":[-104.783244,39.731611],"type":"Point"}
}