{
  "type": "Feature",
  "properties": {
    "addr:full":"6650 N Academy Blvd Colorado Springs CO 80918",
    "addr:housenumber":"6650",
    "addr:postcode":"80918",
    "addr:street":"N Academy Blvd",
    "iso:country":"US",
    "sg:address":"6650 N Academy Blvd",
    "sg:city":"Colorado Springs",
    "sg:classifiers":[
        {
            "category":"Retail",
            "subcategory":"Auto Repair",
            "type":"Services"
        }
    ],
    "sg:phone":"+1 719 590 7608",
    "sg:postcode":"80918",
    "sg:province":"CO",
    "sg:tags":[
        "repairing",
        "automobile"
    ],
    "wof:name":"Meineke Car Care Ctr",
    "wof:placetype":"venue"
},
  "geometry": {"coordinates":[-104.793487,38.92896],"type":"Point"}
}