{
  "type": "Feature",
  "properties": {
    "iso:country":"US",
    "sg:address":"4770 Fox St",
    "sg:city":"Denver",
    "sg:classifiers":[
        {
            "category":"Wholesale",
            "subcategory":"Medical Equipment & Supplies",
            "type":"Manufacturing & Wholesale Goods"
        },
        {
            "category":"Wholesale",
            "subcategory":"Durable Goods & Equipment",
            "type":"Manufacturing & Wholesale Goods"
        }
    ],
    "sg:phone":"+1 303 296 3664",
    "sg:postcode":"80216",
    "sg:province":"CO",
    "sg:tags":[
        "professional",
        "optical"
    ],
    "wof:name":"Mark It Optical",
    "wof:placetype":"venue"
},
  "geometry": {"coordinates":[-104.994226,39.783649],"type":"Point"}
}