{
  "type": "Feature",
  "properties": {
    "addr:full":"1340 Main St Louisville CO 80027",
    "addr:housenumber":"1340",
    "addr:postcode":"80027",
    "addr:street":"Main St",
    "iso:country":"US",
    "sg:address":"1340 Main St",
    "sg:city":"Louisville",
    "sg:classifiers":[
        {
            "category":"Recreation",
            "type":"Entertainment"
        }
    ],
    "sg:phone":"+1 303 665 0339",
    "sg:postcode":"80027",
    "sg:province":"CO",
    "sg:tags":[
        "martial",
        "arts",
        "instruction"
    ],
    "sg:website":"www.imamadani.com",
    "wof:name":"International Martial Arts",
    "wof:placetype":"venue"
},
  "geometry": {"coordinates":[-105.132094,39.983245],"type":"Point"}
}