{
  "type": "Feature",
  "properties": {
    "iso:country":"US",
    "sg:address":"34 W Main St",
    "sg:city":"Cortez",
    "sg:classifiers":[
        {
            "category":"Shopping",
            "subcategory":"Books",
            "type":"Retail Goods"
        }
    ],
    "sg:phone":"+1 970 565 8158",
    "sg:postcode":"81321",
    "sg:province":"CO",
    "wof:name":"Main Book Co",
    "wof:placetype":"venue"
},
  "geometry": {"coordinates":[-108.586117,37.348684],"type":"Point"}
}