{
  "type": "Feature",
  "properties": {
    "iso:country":"US",
    "sg:address":"3330 S Broadway",
    "sg:city":"Englewood",
    "sg:classifiers":[
        {
            "category":"Government",
            "subcategory":"Post Office",
            "type":"Public Place"
        }
    ],
    "sg:phone":"+1 303 806 8749",
    "sg:postcode":"80113",
    "sg:province":"CO",
    "sg:tags":[
        "postal",
        "us"
    ],
    "wof:name":"US Post Office",
    "wof:placetype":"venue"
},
  "geometry": {"coordinates":[-104.98751300000001,39.658353],"type":"Point"}
}