{
  "type": "Feature",
  "properties": {
    "iso:country":"US",
    "sg:address":"5120 Leetsdale Dr",
    "sg:city":"Denver",
    "sg:classifiers":[
        {
            "category":"Building & Trades",
            "subcategory":"Locksmith",
            "type":"Services"
        }
    ],
    "sg:phone":"+1 303 305 0149",
    "sg:postcode":"80246",
    "sg:province":"CO",
    "sg:tags":[
        "key"
    ],
    "wof:name":"AA01 24 7 Locksmith Service",
    "wof:placetype":"venue"
},
  "geometry": {"coordinates":[-104.927871,39.708149],"type":"Point"}
}