{
  "type": "Feature",
  "properties": {
    "addr:full":"2200 Apollo St Pueblo CO 81008",
    "addr:housenumber":"2200",
    "addr:postcode":"81008",
    "addr:street":"Apollo St",
    "iso:country":"US",
    "sg:address":"2200 Apollo St",
    "sg:city":"Pueblo",
    "sg:classifiers":[
        {
            "category":"Freight",
            "type":"Transportation"
        }
    ],
    "sg:phone":"+1 719 595 9774",
    "sg:postcode":"81008",
    "sg:province":"CO",
    "sg:tags":[
        "operator",
        "local",
        "trucking"
    ],
    "wof:name":"Dolphin Trucking",
    "wof:placetype":"venue"
},
  "geometry": {"coordinates":[-104.59997,38.341769],"type":"Point"}
}