{
  "type": "Feature",
  "properties": {
    "addr:full":"37495 Co Rd 33 Eaton CO 80615",
    "addr:housenumber":"37495;33",
    "addr:postcode":"80615",
    "addr:street":"Co Rd;Eaton",
    "iso:country":"US",
    "sg:address":"37495 Co Rd 33",
    "sg:city":"Eaton",
    "sg:classifiers":[
        {
            "category":"Farming",
            "subcategory":"Livestock Farm",
            "type":"Manufacturing & Wholesale Goods"
        }
    ],
    "sg:phone":"+1 970 454 2283",
    "sg:postcode":"80615",
    "sg:province":"CO",
    "sg:tags":[
        "corn",
        "beef",
        "feedlot",
        "cattle"
    ],
    "wof:name":"Charles Leffler",
    "wof:placetype":"venue"
},
  "geometry": {"coordinates":[-104.75431,40.546029],"type":"Point"}
}