{
  "type": "Feature",
  "properties": {
    "addr:full":"2820 W 92nd Ave Denver CO 80260",
    "addr:housenumber":"2820",
    "addr:postcode":"80260",
    "addr:street":"W 92Nd Ave",
    "iso:country":"US",
    "sg:address":"2820 W 92nd Ave",
    "sg:city":"Denver",
    "sg:classifiers":[
        {
            "category":"Organizations",
            "subcategory":"Religious Organization",
            "type":"Services"
        }
    ],
    "sg:phone":"+1 303 428 9535",
    "sg:postcode":"80260",
    "sg:province":"CO",
    "sg:tags":[
        "church"
    ],
    "wof:name":"New Life Worship Center",
    "wof:placetype":"venue"
},
  "geometry": {"coordinates":[-105.02268100000001,39.863496],"type":"Point"}
}