{
  "type": "Feature",
  "properties": {
    "iso:country":"US",
    "sg:address":"2698 S Parker Rd",
    "sg:city":"Aurora",
    "sg:classifiers":[
        {
            "category":"Autos & Motor Vehicles",
            "subcategory":"Fuel & Gas Station",
            "type":"Retail Goods"
        }
    ],
    "sg:phone":"+1 303 696 7037",
    "sg:postcode":"80014",
    "sg:province":"CO",
    "sg:tags":[
        "gasoline"
    ],
    "wof:name":"Smoker Friendly Gasamat",
    "wof:placetype":"venue"
},
  "geometry": {"coordinates":[-104.866051,39.670846],"type":"Point"}
}