{
  "type": "Feature",
  "properties": {
    "iso:country":"US",
    "sg:address":"201 Moffat Ave",
    "sg:city":"Yampa",
    "sg:classifiers":[
        {
            "category":"Restaurant",
            "type":"Food & Drink"
        }
    ],
    "sg:phone":"+1 970 638 4502",
    "sg:postcode":"80483",
    "sg:province":"CO",
    "wof:name":"Royal Cafe",
    "wof:placetype":"venue"
},
  "geometry": {"coordinates":[-106.907512,40.150372],"type":"Point"}
}