{
  "type": "Feature",
  "properties": {
    "addr:full":"1021 W Caley Ave Littleton CO 80120",
    "addr:housenumber":"1021",
    "addr:postcode":"80120",
    "addr:street":"W Caley Ave",
    "iso:country":"US",
    "sg:address":"1021 W Caley Ave",
    "sg:city":"Littleton",
    "sg:classifiers":[
        {
            "category":"Building & Trades",
            "subcategory":"Construction",
            "type":"Services"
        }
    ],
    "sg:phone":"+1 303 419 2896",
    "sg:postcode":"80120",
    "sg:province":"CO",
    "sg:tags":[
        "residential"
    ],
    "wof:name":"Benchmark Woodworks",
    "wof:placetype":"venue"
},
  "geometry": {"coordinates":[-105.002031,39.602452],"type":"Point"}
}