{
  "type": "Feature",
  "properties": {
    "addr:full":"4926 Broadmoor Ct Fort Collins CO 80528",
    "addr:housenumber":"4926",
    "addr:postcode":"80528",
    "addr:street":"Broadmoor Ct",
    "iso:country":"US",
    "sg:address":"4926 Broadmoor Ct",
    "sg:city":"Fort Collins",
    "sg:classifiers":[
        {
            "category":"Building & Trades",
            "subcategory":"Construction",
            "type":"Services"
        }
    ],
    "sg:phone":"+1 970 223 2998",
    "sg:postcode":"80528",
    "sg:province":"CO",
    "sg:tags":[
        "contractor"
    ],
    "wof:name":"Connor Aviation & Restoration",
    "wof:placetype":"venue"
},
  "geometry": {"coordinates":[-104.985637,40.478148],"type":"Point"}
}