{
  "type": "Feature",
  "properties": {
    "iso:country":"US",
    "sg:address":"3689 Co Rd 131",
    "sg:city":"Hesperus",
    "sg:classifiers":[
        {
            "category":"Farming",
            "subcategory":"Livestock Farm",
            "type":"Manufacturing & Wholesale Goods"
        }
    ],
    "sg:phone":"+1 970 588 3313",
    "sg:postcode":"81326",
    "sg:province":"CO",
    "sg:tags":[
        "feedlot",
        "field",
        "crop",
        "beef",
        "cattle"
    ],
    "wof:name":"Gerald Schmitt Farm",
    "wof:placetype":"venue"
},
  "geometry": {"coordinates":[-108.11021700000001,37.126005],"type":"Point"}
}