{
  "type": "Feature",
  "properties": {
    "iso:country":"US",
    "sg:address":"6150 Co Rd 516",
    "sg:city":"Bayfield",
    "sg:classifiers":[
        {
            "category":"Government",
            "subcategory":"Office",
            "type":"Public Place"
        }
    ],
    "sg:phone":"+1 970 884 7254",
    "sg:postcode":"81122",
    "sg:province":"CO",
    "sg:tags":[
        "conservation"
    ],
    "wof:name":"Valley Rich Top Soil",
    "wof:placetype":"venue"
},
  "geometry": {"coordinates":[-107.60449,37.215783],"type":"Point"}
}