{
  "type": "Feature",
  "properties": {
    "iso:country":"US",
    "sg:address":"16451 E 2nd Ave",
    "sg:city":"Aurora",
    "sg:classifiers":[
        {
            "category":"Freight",
            "type":"Transportation"
        }
    ],
    "sg:phone":"+1 303 343 4508",
    "sg:postcode":"80011",
    "sg:province":"CO",
    "sg:tags":[
        "recreational",
        "vehicle"
    ],
    "wof:name":"Alpine Rv & Boat Storage",
    "wof:placetype":"venue"
},
  "geometry": {"coordinates":[-104.798419,39.719344],"type":"Point"}
}