{
  "type": "Feature",
  "properties": {
    "iso:country":"US",
    "sg:address":"10827 Elder Ave",
    "sg:city":"Conifer",
    "sg:classifiers":[
        {
            "category":"Banks & Credit Unions",
            "subcategory":"Investment Brokerage",
            "type":"Services"
        }
    ],
    "sg:phone":"+1 303 697 0274",
    "sg:postcode":"80433",
    "sg:province":"CO",
    "sg:tags":[
        "consultant",
        "planning",
        "financial"
    ],
    "wof:name":"American Express Financial Adv",
    "wof:placetype":"venue"
},
  "geometry": {"coordinates":[-105.25709500000001,39.521468],"type":"Point"}
}