{
  "type": "Feature",
  "properties": {
    "addr:full":"937 6th St Meeker CO 81641",
    "addr:housenumber":"937",
    "addr:street":"6Th St",
    "iso:country":"US",
    "sg:address":"937 6th St",
    "sg:city":"Meeker",
    "sg:classifiers":[
        {
            "category":"Building & Trades",
            "subcategory":"Plumbing",
            "type":"Services"
        }
    ],
    "sg:phone":"+1 970 878 4201",
    "sg:postcode":"81641",
    "sg:province":"CO",
    "sg:tags":[
        "contractor"
    ],
    "wof:name":"Barkers Hvac/R Service",
    "wof:placetype":"venue"
},
  "geometry": {"coordinates":[-107.916115,40.045103],"type":"Point"}
}