{
  "type": "Feature",
  "properties": {
    "addr:full":"8156 S Wadsworth Blvd Littleton CO 80128",
    "addr:housenumber":"8156",
    "addr:postcode":"80128",
    "addr:street":"S Wadsworth Blvd",
    "iso:country":"US",
    "sg:address":"8156 S Wadsworth Blvd",
    "sg:city":"Littleton",
    "sg:classifiers":[
        {
            "category":"Real Estate",
            "subcategory":"Real Estate Agent",
            "type":"Services"
        }
    ],
    "sg:phone":"+1 303 690 5144",
    "sg:postcode":"80128",
    "sg:province":"CO",
    "sg:tags":[
        "management"
    ],
    "wof:name":"E Leasing Solutions",
    "wof:placetype":"venue"
},
  "geometry": {"coordinates":[-105.08261899999999,39.570701],"type":"Point"}
}