{
  "type": "Feature",
  "properties": {
    "iso:country":"US",
    "sg:address":"6681 Colorado Blvd",
    "sg:city":"Commerce City",
    "sg:classifiers":[
        {
            "category":"Building & Trades",
            "subcategory":"Construction",
            "type":"Services"
        }
    ],
    "sg:phone":"+1 303 287 7145",
    "sg:postcode":"80022",
    "sg:province":"CO",
    "sg:tags":[
        "concrete",
        "contractor"
    ],
    "wof:name":"Meadows Concrete Const",
    "wof:placetype":"venue"
},
  "geometry": {"coordinates":[-104.940495,39.813178],"type":"Point"}
}