{
  "type": "Feature",
  "properties": {
    "iso:country":"US",
    "sg:address":"485 Green Acres St",
    "sg:city":"Clifton",
    "sg:classifiers":[
        {
            "category":"Professional",
            "type":"Services"
        }
    ],
    "sg:phone":"+1 970 523 4426",
    "sg:postcode":"81520",
    "sg:province":"CO",
    "wof:name":"M D Conner",
    "wof:placetype":"venue"
},
  "geometry": {"coordinates":[-108.455414,39.075563],"type":"Point"}
}