{
  "type": "Feature",
  "properties": {
    "addr:full":"6872 Grapewood Cir Colorado Springs CO 80918",
    "addr:housenumber":"6872",
    "addr:postcode":"80918",
    "addr:street":"Grapewood Cir",
    "iso:country":"US",
    "sg:address":"6872 Grapewood Cir",
    "sg:city":"Colorado Springs",
    "sg:classifiers":[
        {
            "category":"Education",
            "subcategory":"Dance Studio",
            "type":"Public Place"
        }
    ],
    "sg:phone":"+1 719 598 4655",
    "sg:postcode":"80918",
    "sg:province":"CO",
    "sg:tags":[
        "school"
    ],
    "wof:name":"Ellis Barbara Studio of Dance",
    "wof:placetype":"venue"
},
  "geometry": {"coordinates":[-104.79258,38.931434],"type":"Point"}
}