{
  "type": "Feature",
  "properties": {
    "iso:country":"US",
    "sg:address":"700 Ken Pratt Blvd",
    "sg:city":"Longmont",
    "sg:classifiers":[
        {
            "category":"Social Services",
            "type":"Services"
        }
    ],
    "sg:phone":"+1 303 774 0688",
    "sg:postcode":"80501",
    "sg:province":"CO",
    "sg:tags":[
        "senior",
        "citizen"
    ],
    "wof:name":"Senior Planning Solutions",
    "wof:placetype":"venue"
},
  "geometry": {"coordinates":[-105.105503,40.152507],"type":"Point"}
}