{
  "type": "Feature",
  "properties": {
    "addr:full":"13655 W Jewell Ave Denver CO 80228",
    "addr:housenumber":"13655",
    "addr:postcode":"80228",
    "addr:street":"W Jewell Ave",
    "iso:country":"US",
    "sg:address":"13655 W Jewell Ave",
    "sg:city":"Denver",
    "sg:classifiers":[
        {
            "category":"Sports & Exercise",
            "subcategory":"Gym",
            "type":"Entertainment"
        }
    ],
    "sg:phone":"+1 303 716 0150",
    "sg:postcode":"80228",
    "sg:province":"CO",
    "sg:tags":[
        "fitness",
        "physical",
        "facility"
    ],
    "wof:name":"Women Workout Company",
    "wof:placetype":"venue"
},
  "geometry": {"coordinates":[-105.157786,39.681869],"type":"Point"}
}