{
  "type": "Feature",
  "properties": {
    "iso:country":"US",
    "sg:address":"2263 Greeley Mall",
    "sg:city":"Greeley",
    "sg:classifiers":[
        {
            "category":"Restaurant",
            "type":"Food & Drink"
        }
    ],
    "sg:menulink":"http://www.allmenus.com/co/greeley/74965-pizza-hut/menu/",
    "sg:phone":"+1 970 392 2500",
    "sg:postcode":"80631",
    "sg:province":"CO",
    "sg:tags":[
        "american",
        "pizza"
    ],
    "wof:name":"Pizza Hut",
    "wof:placetype":"venue"
},
  "geometry": {"coordinates":[-104.71496399999999,40.389195],"type":"Point"}
}