{
  "type": "Feature",
  "properties": {
    "iso:country":"US",
    "sg:address":"945 Main Ave",
    "sg:city":"Durango",
    "sg:classifiers":[
        {
            "category":"Shopping",
            "type":"Retail Goods"
        }
    ],
    "sg:phone":"+1 970 375 2708",
    "sg:postcode":"81301",
    "sg:province":"CO",
    "sg:tags":[
        "art",
        "gallery",
        "dealer"
    ],
    "wof:name":"Rain Dance Gallery Inc",
    "wof:placetype":"venue"
},
  "geometry": {"coordinates":[-107.88056899999999,37.274009],"type":"Point"}
}