{
  "type": "Feature",
  "properties": {
    "iso:country":"US",
    "sg:address":"5830 W 38th Ave",
    "sg:city":"Denver",
    "sg:classifiers":[
        {
            "category":"Shopping",
            "subcategory":"Hobbies, Toys, & Games",
            "type":"Retail Goods"
        },
        {
            "category":"Shopping",
            "subcategory":"Clothing, Apparel, & Fashions",
            "type":"Retail Goods"
        }
    ],
    "sg:phone":"+1 303 424 9129",
    "sg:postcode":"80212",
    "sg:province":"CO",
    "sg:tags":[
        "basket"
    ],
    "wof:name":"A Basket Boutique",
    "wof:placetype":"venue"
},
  "geometry": {"coordinates":[-105.06235599999999,39.769305],"type":"Point"}
}