{
  "type": "Feature",
  "properties": {
    "iso:country":"US",
    "sg:address":"1333 Broadway St",
    "sg:city":"Boulder",
    "sg:classifiers":[
        {
            "category":"Restaurant",
            "type":"Food & Drink"
        }
    ],
    "sg:menulink":"http://www.allmenus.com/co/boulder/40732-dots-diner/menu/",
    "sg:phone":"+1 303 447 9184",
    "sg:postcode":"80302",
    "sg:province":"CO",
    "sg:tags":[
        "american"
    ],
    "wof:name":"Dot's Diner",
    "wof:placetype":"venue"
},
  "geometry": {"coordinates":[-105.27645,40.009707],"type":"Point"}
}