{
  "type": "Feature",
  "properties": {
    "addr:full":"8870 W Long Ct Littleton CO 80123",
    "addr:housenumber":"8870",
    "addr:postcode":"80123",
    "addr:street":"W Long Ct",
    "iso:country":"US",
    "sg:address":"8870 W Long Ct",
    "sg:city":"Littleton",
    "sg:classifiers":[
        {
            "category":"Building & Trades",
            "subcategory":"Plumbing",
            "type":"Services"
        }
    ],
    "sg:phone":"+1 303 908 6479",
    "sg:postcode":"80123",
    "sg:province":"CO",
    "sg:tags":[
        "contractor"
    ],
    "wof:name":"Big TS Plumbing Services",
    "wof:placetype":"venue"
},
  "geometry": {"coordinates":[-105.104116,39.610901],"type":"Point"}
}