{
  "type": "Feature",
  "properties": {
    "iso:country":"US",
    "sg:address":"1410 Peninsula Cir",
    "sg:city":"Castle Rock",
    "sg:classifiers":[
        {
            "category":"Professional",
            "subcategory":"Lawyer & Legal Services",
            "type":"Services"
        }
    ],
    "sg:phone":"+1 303 935 4500",
    "sg:postcode":"80104",
    "sg:province":"CO",
    "wof:name":"Bradley D Chapman Attorney At Law",
    "wof:placetype":"venue"
},
  "geometry": {"coordinates":[-104.855003,39.356701],"type":"Point"}
}