{
  "type": "Feature",
  "properties": {
    "iso:country":"US",
    "sg:address":"464 Silver Mine Dr",
    "sg:city":"Colorado Springs",
    "sg:classifiers":[
        {
            "category":"Building & Trades",
            "subcategory":"Construction",
            "type":"Services"
        }
    ],
    "sg:phone":"+1 719 227 9737",
    "sg:postcode":"80904",
    "sg:province":"CO",
    "sg:tags":[
        "carpentry",
        "contractor"
    ],
    "wof:name":"Fosters Trim Works",
    "wof:placetype":"venue"
},
  "geometry": {"coordinates":[-104.854744,38.825833],"type":"Point"}
}