{
  "type": "Feature",
  "properties": {
    "addr:full":"3346 N el Paso St Colorado Springs CO 80907",
    "addr:housenumber":"3346",
    "addr:postcode":"80907",
    "addr:street":"N El Paso St",
    "iso:country":"US",
    "sg:address":"3346 N el Paso St",
    "sg:city":"Colorado Springs",
    "sg:classifiers":[
        {
            "category":"Manufacturing",
            "subcategory":"Tools & Machinery",
            "type":"Manufacturing & Wholesale Goods"
        }
    ],
    "sg:phone":"+1 719 577 4117",
    "sg:postcode":"80907",
    "sg:province":"CO",
    "sg:tags":[
        "machine",
        "shop"
    ],
    "wof:name":"Huston Quentin D and Sons",
    "wof:placetype":"venue"
},
  "geometry": {"coordinates":[-104.812788,38.882097],"type":"Point"}
}