{
  "type": "Feature",
  "properties": {
    "iso:country":"US",
    "sg:address":"11197 Tamarron Ct",
    "sg:city":"Parker",
    "sg:classifiers":[
        {
            "category":"Professional",
            "type":"Services"
        }
    ],
    "sg:phone":"+1 303 840 7590",
    "sg:postcode":"80138",
    "sg:province":"CO",
    "wof:name":"Mary & Michael Harris",
    "wof:placetype":"venue"
},
  "geometry": {"coordinates":[-104.714056,39.512523],"type":"Point"}
}