{
  "type": "Feature",
  "properties": {
    "iso:country":"US",
    "sg:address":"7270 Locust St",
    "sg:city":"Commerce City",
    "sg:classifiers":[
        {
            "category":"Autos & Motor Vehicles",
            "subcategory":"Auto Supplies",
            "type":"Retail Goods"
        }
    ],
    "sg:phone":"+1 303 286 1254",
    "sg:postcode":"80022",
    "sg:province":"CO",
    "wof:name":"AAAA Real Wheel Deal",
    "wof:placetype":"venue"
},
  "geometry": {"coordinates":[-104.913298,39.828836],"type":"Point"}
}