{
  "type": "Feature",
  "properties": {
    "iso:country":"US",
    "sg:address":"225 Lodgepole Way",
    "sg:city":"Monument",
    "sg:classifiers":[
        {
            "category":"Professional",
            "type":"Services"
        }
    ],
    "sg:phone":"+1 719 488 0719",
    "sg:postcode":"80132",
    "sg:province":"CO",
    "wof:name":"Anne M Odell",
    "wof:placetype":"venue"
},
  "geometry": {"coordinates":[-104.831745,39.085761],"type":"Point"}
}