{
  "type": "Feature",
  "properties": {
    "iso:country":"US",
    "sg:address":"1371 E Hecla Dr",
    "sg:city":"Louisville",
    "sg:classifiers":[
        {
            "category":"Banks & Credit Unions",
            "subcategory":"Investment Brokerage",
            "type":"Services"
        }
    ],
    "sg:phone":"+1 303 494 8558",
    "sg:postcode":"80027",
    "sg:province":"CO",
    "sg:tags":[
        "security"
    ],
    "wof:name":"Terry Hefty",
    "wof:placetype":"venue"
},
  "geometry": {"coordinates":[-105.126347,39.989562],"type":"Point"}
}