{
  "type": "Feature",
  "properties": {
    "addr:full":"82 Pine Needle Rd Boulder CO 80304",
    "addr:housenumber":"82",
    "addr:postcode":"80304",
    "addr:street":"Pine Needle Rd",
    "iso:country":"US",
    "sg:address":"82 Pine Needle Rd",
    "sg:city":"Boulder",
    "sg:classifiers":[
        {
            "category":"Building & Trades",
            "subcategory":"Construction",
            "type":"Services"
        }
    ],
    "sg:phone":"+1 303 443 2910",
    "sg:postcode":"80304",
    "sg:province":"CO",
    "sg:tags":[
        "house"
    ],
    "wof:name":"Valentine Jamey Construction",
    "wof:placetype":"venue"
},
  "geometry": {"coordinates":[-105.302723,40.050496],"type":"Point"}
}