{
  "type": "Feature",
  "properties": {
    "addr:full":"3574 Hartsel Dr Colorado Springs CO 80920",
    "addr:housenumber":"3574",
    "addr:postcode":"80920",
    "addr:street":"Hartsel Dr",
    "iso:country":"US",
    "sg:address":"3574 Hartsel Dr",
    "sg:city":"Colorado Springs",
    "sg:classifiers":[
        {
            "category":"Restaurant",
            "type":"Food & Drink"
        }
    ],
    "sg:menulink":"http://www.allmenus.com/co/colorado-springs/87166-little-caesars-pizza/menu/",
    "sg:phone":"+1 719 594 0800",
    "sg:postcode":"80920",
    "sg:province":"CO",
    "sg:tags":[
        "american",
        "pizza"
    ],
    "wof:name":"Little Caesar's Pizza",
    "wof:placetype":"venue"
},
  "geometry": {"coordinates":[-104.758321,38.939766],"type":"Point"}
}