{
  "type": "Feature",
  "properties": {
    "addr:full":"2301 Pearl St Boulder CO 80302",
    "addr:housenumber":"2301",
    "addr:postcode":"80302",
    "addr:street":"Pearl St",
    "iso:country":"US",
    "sg:address":"2301 Pearl St",
    "sg:city":"Boulder",
    "sg:classifiers":[
        {
            "category":"Shopping",
            "type":"Retail Goods"
        }
    ],
    "sg:phone":"+1 303 449 3108",
    "sg:postcode":"80302",
    "sg:province":"CO",
    "sg:tags":[
        "merchandise"
    ],
    "wof:name":"Ellen Kathryn Gallery",
    "wof:placetype":"venue"
},
  "geometry": {"coordinates":[-105.26439999999999,40.021085],"type":"Point"}
}