{
  "type": "Feature",
  "properties": {
    "addr:full":"1298 Spring Rd Durango CO 81303",
    "addr:housenumber":"1298",
    "addr:postcode":"co 81303",
    "addr:street":"Spring Rd",
    "iso:country":"US",
    "sg:address":"1298 Spring Rd",
    "sg:city":"Durango",
    "sg:classifiers":[
        {
            "category":"Building & Trades",
            "subcategory":"Construction",
            "type":"Services"
        }
    ],
    "sg:phone":"+1 970 259 3840",
    "sg:postcode":"81303",
    "sg:province":"CO",
    "sg:tags":[
        "marking",
        "maintenance",
        "parking"
    ],
    "wof:name":"Work Horse Unlimited",
    "wof:placetype":"venue"
},
  "geometry": {"coordinates":[-107.956031,37.247303],"type":"Point"}
}