{
  "type": "Feature",
  "properties": {
    "iso:country":"US",
    "sg:address":"5650 Greenwood Plaza Blvd",
    "sg:city":"Englewood",
    "sg:classifiers":[
        {
            "category":"Wholesale",
            "subcategory":"Durable Goods & Equipment",
            "type":"Manufacturing & Wholesale Goods"
        }
    ],
    "sg:phone":"+1 303 770 6331",
    "sg:postcode":"80111",
    "sg:province":"CO",
    "sg:tags":[
        "enforcement",
        "law",
        "supply"
    ],
    "wof:name":"Secure Concepts",
    "wof:placetype":"venue"
},
  "geometry": {"coordinates":[-104.89751099999999,39.612059],"type":"Point"}
}