{
  "type": "Feature",
  "properties": {
    "addr:full":"627 Wadas Ct Johnstown CO 80534",
    "addr:housenumber":"627",
    "addr:postcode":"80534",
    "addr:street":"Wadas Ct",
    "iso:country":"US",
    "sg:address":"627 Wadas Ct",
    "sg:city":"Johnstown",
    "sg:classifiers":[
        {
            "category":"Farming",
            "subcategory":"Farm",
            "type":"Manufacturing & Wholesale Goods"
        }
    ],
    "sg:phone":"+1 970 587 4796",
    "sg:postcode":"80534",
    "sg:province":"CO",
    "sg:tags":[
        "crop",
        "general"
    ],
    "wof:name":"East of Eaton Farms LLC",
    "wof:placetype":"venue"
},
  "geometry": {"coordinates":[-104.912948,40.334197],"type":"Point"}
}