{
  "type": "Feature",
  "properties": {
    "iso:country":"US",
    "sg:address":"219 W Main St",
    "sg:city":"New Castle",
    "sg:classifiers":[
        {
            "category":"Restaurant",
            "type":"Food & Drink"
        }
    ],
    "sg:phone":"+1 970 984 2301",
    "sg:postcode":"81647",
    "sg:province":"CO",
    "wof:name":"New Castle Cafe",
    "wof:placetype":"venue"
},
  "geometry": {"coordinates":[-107.53318299999999,39.571387],"type":"Point"}
}