{
  "type": "Feature",
  "properties": {
    "iso:country":"US",
    "sg:address":"947 State Hwy 115",
    "sg:city":"Penrose",
    "sg:classifiers":[
        {
            "category":"Wholesale",
            "subcategory":"Farm Supplies",
            "type":"Manufacturing & Wholesale Goods"
        }
    ],
    "sg:phone":"+1 719 372 6205",
    "sg:postcode":"81240",
    "sg:province":"CO",
    "wof:name":"D & K Supply",
    "wof:placetype":"venue"
},
  "geometry": {"coordinates":[-105.012597,38.455342],"type":"Point"}
}