{
  "type": "Feature",
  "properties": {
    "addr:full":"2029 S Federal Blvd Denver CO 80219",
    "addr:housenumber":"2029",
    "addr:postcode":"80219",
    "addr:street":"S Federal Blvd",
    "iso:country":"US",
    "sg:address":"2029 S Federal Blvd",
    "sg:city":"Denver",
    "sg:classifiers":[
        {
            "category":"Personal",
            "subcategory":"Beauty Salon",
            "type":"Services"
        }
    ],
    "sg:phone":"+1 303 922 7788",
    "sg:postcode":"80219",
    "sg:province":"CO",
    "wof:name":"Cost Cutters Family Hair Care",
    "wof:placetype":"venue"
},
  "geometry": {"coordinates":[-105.02513,39.67887],"type":"Point"}
}