{
  "type": "Feature",
  "properties": {
    "iso:country":"US",
    "sg:address":"301 W 104th Ave",
    "sg:city":"Denver",
    "sg:classifiers":[
        {
            "category":"Restaurant",
            "type":"Food & Drink"
        }
    ],
    "sg:phone":"+1 303 453 1956",
    "sg:postcode":"80234",
    "sg:province":"CO",
    "sg:tags":[
        "eating"
    ],
    "wof:name":"Gunther Toodys",
    "wof:placetype":"venue"
},
  "geometry": {"coordinates":[-104.992217,39.885351],"type":"Point"}
}