{
  "type": "Feature",
  "properties": {
    "iso:country":"US",
    "sg:address":"104 Co Rd 104",
    "sg:city":"Dillon",
    "sg:classifiers":[
        {
            "category":"Manufacturing",
            "subcategory":"Food",
            "type":"Manufacturing & Wholesale Goods"
        }
    ],
    "sg:phone":"+1 970 468 2145",
    "sg:postcode":"80435",
    "sg:province":"CO",
    "sg:tags":[
        "brewer"
    ],
    "sg:website":"www.pugryans.com",
    "wof:name":"Pug Ryan's",
    "wof:placetype":"venue"
},
  "geometry": {"coordinates":[-106.002439,39.601954],"type":"Point"}
}