{
  "type": "Feature",
  "properties": {
    "iso:country":"US",
    "sg:address":"177 E Bridge St",
    "sg:city":"Brighton",
    "sg:classifiers":[
        {
            "category":"Professional",
            "subcategory":"Computer Services",
            "type":"Services"
        }
    ],
    "sg:phone":"+1 303 289 4330",
    "sg:postcode":"80601",
    "sg:province":"CO",
    "sg:tags":[
        "related"
    ],
    "wof:name":"Jtm Consulting",
    "wof:placetype":"venue"
},
  "geometry": {"coordinates":[-104.820286,39.98689],"type":"Point"}
}