{
  "type": "Feature",
  "properties": {
    "iso:country":"US",
    "sg:address":"1564 S Broadway",
    "sg:city":"Denver",
    "sg:classifiers":[
        {
            "category":"Shopping",
            "type":"Retail Goods"
        }
    ],
    "sg:phone":"+1 303 722 1284",
    "sg:postcode":"80210",
    "sg:province":"CO",
    "sg:tags":[
        "picture",
        "frame"
    ],
    "wof:name":"Nina's Framing",
    "wof:placetype":"venue"
},
  "geometry": {"coordinates":[-104.98743,39.688765],"type":"Point"}
}