{
  "type": "Feature",
  "properties": {
    "iso:country":"US",
    "sg:address":"2919 17th Ave",
    "sg:city":"Longmont",
    "sg:classifiers":[
        {
            "category":"Professional",
            "subcategory":"Management & Consulting",
            "type":"Services"
        }
    ],
    "sg:phone":"+1 303 774 9445",
    "sg:postcode":"80501",
    "sg:province":"CO",
    "sg:tags":[
        "consultant",
        "business"
    ],
    "sg:website":"www.hrmc.net",
    "wof:name":"Human Resource Management",
    "wof:placetype":"venue"
},
  "geometry": {"coordinates":[-105.14145499999999,40.188522],"type":"Point"}
}