{
  "type": "Feature",
  "properties": {
    "addr:full":"1010 S Chelton Rd Colorado Springs CO 80910",
    "addr:housenumber":"1010",
    "addr:postcode":"80910",
    "addr:street":"S Chelton Rd",
    "iso:country":"US",
    "sg:address":"1010 S Chelton Rd",
    "sg:city":"Colorado Springs",
    "sg:classifiers":[
        {
            "category":"Professional",
            "type":"Services"
        }
    ],
    "sg:phone":"+1 719 477 0437",
    "sg:postcode":"80910",
    "sg:province":"CO",
    "wof:name":"Cruz Rosas Framing",
    "wof:placetype":"venue"
},
  "geometry": {"coordinates":[-104.766785,38.817704],"type":"Point"}
}