{
  "type": "Feature",
  "properties": {
    "addr:full":"737 Pine Slope Rd Idaho Springs CO 80452",
    "addr:housenumber":"737",
    "addr:postcode":"80452",
    "addr:street":"Pine Slope Rd",
    "iso:country":"US",
    "sg:address":"737 Pine Slope Rd",
    "sg:city":"Idaho Springs",
    "sg:classifiers":[
        {
            "category":"Building & Trades",
            "subcategory":"Construction",
            "type":"Services"
        }
    ],
    "sg:phone":"+1 303 567 2404",
    "sg:postcode":"80452",
    "sg:province":"CO",
    "sg:tags":[
        "contractor"
    ],
    "wof:name":"Lamberti Mike Custom Bulider",
    "wof:placetype":"venue"
},
  "geometry": {"coordinates":[-105.514999,39.736198],"type":"Point"}
}