{
  "type": "Feature",
  "properties": {
    "addr:full":"6989 S Jordan Rd Centennial CO 80112",
    "addr:housenumber":"6989",
    "addr:postcode":"80112",
    "addr:street":"S Jordan Rd",
    "iso:country":"US",
    "sg:address":"6989 S Jordan Rd",
    "sg:city":"Centennial",
    "sg:classifiers":[
        {
            "category":"Retail",
            "subcategory":"Auto Repair",
            "type":"Services"
        }
    ],
    "sg:phone":"+1 877 870 1247",
    "sg:postcode":"80112",
    "sg:province":"CO",
    "sg:tags":[
        "repairing",
        "automobile"
    ],
    "wof:name":"Japanese Car Care Center",
    "wof:placetype":"venue"
},
  "geometry": {"coordinates":[-104.81824,39.590052],"type":"Point"}
}