{
  "type": "Feature",
  "properties": {
    "addr:full":"2101 S Cook St Denver CO 80210",
    "addr:housenumber":"2101",
    "addr:postcode":"80210",
    "addr:street":"S Cook St",
    "iso:country":"US",
    "sg:address":"2101 S Cook St",
    "sg:city":"Denver",
    "sg:classifiers":[
        {
            "category":"Social Services",
            "subcategory":"Adult Care",
            "type":"Services"
        }
    ],
    "sg:phone":"+1 303 759 8207",
    "sg:postcode":"80210",
    "sg:province":"CO",
    "sg:tags":[
        "home"
    ],
    "wof:name":"Cook House",
    "wof:placetype":"venue"
},
  "geometry": {"coordinates":[-104.947992,39.676604],"type":"Point"}
}