{
  "type": "Feature",
  "properties": {
    "addr:full":"2065 S Hudson Street Denver CO 80222",
    "addr:housenumber":"2065",
    "addr:postcode":"80222",
    "addr:street":"S Hudson Street",
    "iso:country":"US",
    "sg:address":"2065 S Hudson Street",
    "sg:city":"Denver",
    "sg:classifiers":[
        {
            "category":"Building & Trades",
            "subcategory":"Cleaning & Sanitation",
            "type":"Services"
        }
    ],
    "sg:phone":"+1 303 753 9171",
    "sg:postcode":"80222",
    "sg:province":"CO",
    "sg:tags":[
        "carpet"
    ],
    "sg:website":"www.chasecarpetcare.com",
    "wof:name":"Chase Carpet Care Company",
    "wof:placetype":"venue"
},
  "geometry": {"coordinates":[-104.923732,39.678593],"type":"Point"}
}