{
  "type": "Feature",
  "properties": {
    "iso:country":"US",
    "sg:address":"5195 W Byron Place",
    "sg:city":"Denver",
    "sg:classifiers":[
        {
            "category":"Food & Beverages",
            "subcategory":"Groceries & Convenience Stores",
            "type":"Retail Goods"
        }
    ],
    "sg:phone":"+1 303 433 3293",
    "sg:postcode":"80212",
    "sg:province":"CO",
    "wof:name":"Seven-Eleven Stores",
    "wof:placetype":"venue"
},
  "geometry": {"coordinates":[-105.053181,39.752922],"type":"Point"}
}