{
  "type": "Feature",
  "properties": {
    "addr:full":"155 Boardwalk Dr Fort Collins CO 80525",
    "addr:housenumber":"155",
    "addr:postcode":"80525",
    "addr:street":"Boardwalk Dr",
    "iso:country":"US",
    "sg:address":"155 Boardwalk Dr",
    "sg:city":"Fort Collins",
    "sg:classifiers":[
        {
            "category":"Professional",
            "subcategory":"Computer Services",
            "type":"Services"
        },
        {
            "category":"Shopping",
            "subcategory":"Computers & Home Electronics",
            "type":"Retail Goods"
        }
    ],
    "sg:phone":"+1 970 225 2700",
    "sg:postcode":"80525",
    "sg:province":"CO",
    "sg:tags":[
        "software",
        "programing",
        "custom"
    ],
    "sg:website":"www.cheetahware.com",
    "wof:name":"Cheetah Advanced Technologies",
    "wof:placetype":"venue"
},
  "geometry": {"coordinates":[-105.075776,40.53256],"type":"Point"}
}