{
  "type": "Feature",
  "properties": {
    "iso:country":"US",
    "sg:address":"8531 Church Ranch Blvd",
    "sg:city":"Broomfield",
    "sg:classifiers":[
        {
            "category":"Banks & Credit Unions",
            "subcategory":"Bank",
            "type":"Services"
        }
    ],
    "sg:phone":"+1 720 566 3305",
    "sg:postcode":"80021",
    "sg:province":"CO",
    "sg:tags":[
        "state",
        "commercial"
    ],
    "wof:name":"First National Bank",
    "wof:placetype":"venue"
},
  "geometry": {"coordinates":[-105.09277299999999,39.878709],"type":"Point"}
}