{
  "type": "Feature",
  "properties": {
    "iso:country":"US",
    "sg:address":"705 W 62nd Ave",
    "sg:city":"Denver",
    "sg:classifiers":[
        {
            "category":"Building & Trades",
            "subcategory":"Equipment Rental",
            "type":"Services"
        }
    ],
    "sg:phone":"+1 303 428 7844",
    "sg:postcode":"80216",
    "sg:province":"CO",
    "sg:tags":[
        "construction",
        "rent"
    ],
    "wof:name":"Cpe",
    "wof:placetype":"venue"
},
  "geometry": {"coordinates":[-104.988365,39.809167],"type":"Point"}
}