{
  "type": "Feature",
  "properties": {
    "addr:full":"215 E Foothills Pkwy Fort Collins CO 80525",
    "addr:housenumber":"215",
    "addr:postcode":"80525",
    "addr:street":"E Foothills Pkwy",
    "iso:country":"US",
    "sg:address":"215 E Foothills Pkwy",
    "sg:city":"Fort Collins",
    "sg:classifiers":[
        {
            "category":"Shopping",
            "subcategory":"Department Store",
            "type":"Retail Goods"
        }
    ],
    "sg:phone":"+1 970 226 5555",
    "sg:postcode":"80525",
    "sg:province":"CO",
    "sg:website":"www.shopfoothills.com",
    "wof:name":"Foothills East Office",
    "wof:placetype":"venue"
},
  "geometry": {"coordinates":[-105.07463300000001,40.543772],"type":"Point"}
}