{
  "type": "Feature",
  "properties": {
    "iso:country":"US",
    "sg:address":"6707 Winchester Cir",
    "sg:city":"Boulder",
    "sg:phone":"+1 303 530 2261",
    "sg:postcode":"80301",
    "sg:province":"CO",
    "sg:tags":[
        "basket",
        "shopping",
        "cart"
    ],
    "wof:name":"Versa Cart Systems Inc",
    "wof:placetype":"venue"
},
  "geometry": {"coordinates":[-105.191686,40.078621],"type":"Point"}
}