{
  "type": "Feature",
  "properties": {
    "iso:country":"US",
    "sg:address":"602 13th St",
    "sg:city":"Greeley",
    "sg:classifiers":[
        {
            "category":"Retail",
            "subcategory":"Auto Repair",
            "type":"Services"
        }
    ],
    "sg:phone":"+1 970 356 4771",
    "sg:postcode":"80631",
    "sg:province":"CO",
    "sg:tags":[
        "repairing",
        "automobile"
    ],
    "wof:name":"Greeley Auto Tech",
    "wof:placetype":"venue"
},
  "geometry": {"coordinates":[-104.689052,40.418321],"type":"Point"}
}