{
  "type": "Feature",
  "properties": {
    "addr:full":"7203 W 55th Ave Arvada CO 80002",
    "addr:housenumber":"7203",
    "addr:postcode":"80002",
    "addr:street":"W 55Th Ave",
    "iso:country":"US",
    "sg:address":"7203 W 55th Ave",
    "sg:city":"Arvada",
    "sg:classifiers":[
        {
            "category":"Banks & Credit Unions",
            "subcategory":"Bank",
            "type":"Services"
        }
    ],
    "sg:phone":"+1 303 423 6779",
    "sg:postcode":"80002",
    "sg:province":"CO",
    "sg:website":"www.tcfbank.com",
    "wof:name":"Tcf Bank",
    "wof:placetype":"venue"
},
  "geometry": {"coordinates":[-105.078003,39.7962],"type":"Point"}
}