{
  "type": "Feature",
  "properties": {
    "iso:country":"US",
    "sg:address":"3001 S Federal Blvd",
    "sg:city":"Denver",
    "sg:classifiers":[
        {
            "category":"Real Estate",
            "subcategory":"Real Estate Operator",
            "type":"Services"
        }
    ],
    "sg:phone":"+1 303 937 4205",
    "sg:postcode":"80236",
    "sg:province":"CO",
    "sg:tags":[
        "building",
        "apartment"
    ],
    "wof:name":"Residence Hall Lodging",
    "wof:placetype":"venue"
},
  "geometry": {"coordinates":[-105.025038,39.660886],"type":"Point"}
}