{
  "type": "Feature",
  "properties": {
    "addr:full":"317 N Wisconsin St Gunnison CO 81230",
    "addr:housenumber":"317",
    "addr:postcode":"81230",
    "addr:street":"N Wisconsin St",
    "iso:country":"US",
    "sg:address":"317 N Wisconsin St",
    "sg:city":"Gunnison",
    "sg:classifiers":[
        {
            "category":"Building & Trades",
            "subcategory":"Construction",
            "type":"Services"
        }
    ],
    "sg:phone":"+1 970 641 3604",
    "sg:postcode":"81230",
    "sg:province":"CO",
    "sg:tags":[
        "resurfacing",
        "laying",
        "refinishing",
        "floor"
    ],
    "wof:name":"West Elk Woodfloors",
    "wof:placetype":"venue"
},
  "geometry": {"coordinates":[-106.928275,38.547553],"type":"Point"}
}