{
  "type": "Feature",
  "properties": {
    "iso:country":"US",
    "sg:address":"2081 W 80th Ave",
    "sg:city":"Denver",
    "sg:classifiers":[
        {
            "category":"Building & Trades",
            "subcategory":"Construction",
            "type":"Services"
        }
    ],
    "sg:phone":"+1 303 573 0890",
    "sg:postcode":"80221",
    "sg:province":"CO",
    "sg:tags":[
        "plastering",
        "contractor"
    ],
    "wof:name":"Pulido Plastering LLC",
    "wof:placetype":"venue"
},
  "geometry": {"coordinates":[-105.013447,39.841796],"type":"Point"}
}