{
  "type": "Feature",
  "properties": {
    "addr:full":"2081 W 80th Ave Denver CO 80221",
    "addr:housenumber":"2081",
    "addr:postcode":"80221",
    "addr:street":"W 80Th Ave",
    "iso:country":"US",
    "sg:address":"2081 W 80th Ave",
    "sg:city":"Denver",
    "sg:classifiers":[
        {
            "category":"Building & Trades",
            "subcategory":"Construction",
            "type":"Services"
        }
    ],
    "sg:phone":"+1 303 573 0890",
    "sg:postcode":"80221",
    "sg:province":"CO",
    "sg:tags":[
        "plastering",
        "contractor"
    ],
    "wof:name":"Pulido Plastering LLC",
    "wof:placetype":"venue"
},
  "geometry": {"coordinates":[-105.013447,39.841796],"type":"Point"}
}