{
  "type": "Feature",
  "properties": {
    "iso:country":"US",
    "sg:address":"323 Carroll Ln",
    "sg:city":"Breckenridge",
    "sg:classifiers":[
        {
            "category":"Building & Trades",
            "subcategory":"Construction",
            "type":"Services"
        }
    ],
    "sg:phone":"+1 970 389 1223",
    "sg:postcode":"80424",
    "sg:province":"CO",
    "sg:tags":[
        "general",
        "contractor"
    ],
    "wof:name":"Stone Construction & Contrctng",
    "wof:placetype":"venue"
},
  "geometry": {"coordinates":[-106.059605,39.375453],"type":"Point"}
}