{
  "type": "Feature",
  "properties": {
    "iso:country":"US",
    "sg:address":"1526 Spruce St",
    "sg:city":"Boulder",
    "sg:classifiers":[
        {
            "category":"Food & Beverages",
            "subcategory":"Specialty",
            "type":"Retail Goods"
        }
    ],
    "sg:phone":"+1 303 928 2340",
    "sg:postcode":"80302",
    "sg:province":"CO",
    "sg:tags":[
        "health",
        "diet"
    ],
    "wof:name":"Nuevo Latin Natural Foods LLC",
    "wof:placetype":"venue"
},
  "geometry": {"coordinates":[-105.27533699999999,40.019841],"type":"Point"}
}