{
  "type": "Feature",
  "properties": {
    "addr:full":"3121 Kintzley Ct Laporte CO 80535",
    "addr:housenumber":"3121",
    "addr:postcode":"80535",
    "addr:street":"Kintzley Ct",
    "iso:country":"US",
    "sg:address":"3121 Kintzley Ct",
    "sg:city":"Laporte",
    "sg:classifiers":[
        {
            "category":"Building & Trades",
            "subcategory":"Construction",
            "type":"Services"
        }
    ],
    "sg:phone":"+1 970 490 2403",
    "sg:postcode":"80535",
    "sg:province":"CO",
    "sg:tags":[
        "nonresidential"
    ],
    "wof:name":"Kintzley Plaza",
    "wof:placetype":"venue"
},
  "geometry": {"coordinates":[-105.13261,40.627478],"type":"Point"}
}