{
  "type": "Feature",
  "properties": {
    "addr:full":"51 W 4th Ave Denver CO 80223",
    "addr:housenumber":"51",
    "addr:postcode":"80223",
    "addr:street":"W 4Th Ave",
    "iso:country":"US",
    "sg:address":"51 W 4th Ave",
    "sg:city":"Denver",
    "sg:classifiers":[
        {
            "category":"Social Services",
            "subcategory":"Child Care",
            "type":"Services"
        }
    ],
    "sg:phone":"+1 303 871 0420",
    "sg:postcode":"80223",
    "sg:province":"CO",
    "sg:tags":[
        "elementary",
        "residential",
        "second",
        "rehabilitation",
        "center"
    ],
    "wof:name":"Excel",
    "wof:placetype":"venue"
},
  "geometry": {"coordinates":[-104.98843599999999,39.722612],"type":"Point"}
}