{
  "type": "Feature",
  "properties": {
    "addr:full":"634 Goodnight Ave Pueblo CO 81005",
    "addr:housenumber":"634",
    "addr:postcode":"81005",
    "addr:street":"Goodnight Ave",
    "iso:country":"US",
    "sg:address":"634 Goodnight Ave",
    "sg:city":"Pueblo",
    "sg:classifiers":[
        {
            "category":"Organizations",
            "subcategory":"Religious Organization",
            "type":"Services"
        }
    ],
    "sg:phone":"+1 719 561 1669",
    "sg:postcode":"81005",
    "sg:province":"CO",
    "sg:tags":[
        "church"
    ],
    "wof:name":"Church Of The Brethren Flwshp",
    "wof:placetype":"venue"
},
  "geometry": {"coordinates":[-104.650222,38.26386],"type":"Point"}
}