{
  "type": "Feature",
  "properties": {
    "iso:country":"US",
    "sg:address":"4105 Youngfield St",
    "sg:city":"Golden",
    "sg:classifiers":[
        {
            "category":"Government",
            "subcategory":"Office",
            "type":"Public Place"
        }
    ],
    "sg:phone":"+1 303 278 7575",
    "sg:postcode":"80401",
    "sg:province":"CO",
    "wof:name":"Table Mountain Animal Ctr",
    "wof:placetype":"venue"
},
  "geometry": {"coordinates":[-105.14258599999999,39.773614],"type":"Point"}
}