{
  "type": "Feature",
  "properties": {
    "addr:full":"425 S College Ave Fort Collins CO 80524",
    "addr:housenumber":"425",
    "addr:postcode":"80524",
    "addr:street":"S College Ave",
    "iso:country":"US",
    "sg:address":"425 S College Ave",
    "sg:city":"Fort Collins",
    "sg:classifiers":[
        {
            "category":"Shopping",
            "subcategory":"Bicycles & Sporting Goods",
            "type":"Retail Goods"
        }
    ],
    "sg:phone":"+1 970 482 5213",
    "sg:postcode":"80524",
    "sg:province":"CO",
    "wof:name":"Gart Sports",
    "wof:placetype":"venue"
},
  "geometry": {"coordinates":[-105.07713699999999,40.581813],"type":"Point"}
}