{
  "type": "Feature",
  "properties": {
    "iso:country":"US",
    "sg:address":"14570 Andrews Dr",
    "sg:city":"Denver",
    "sg:classifiers":[
        {
            "category":"Shopping",
            "subcategory":"Music",
            "type":"Retail Goods"
        }
    ],
    "sg:phone":"+1 303 371 5804",
    "sg:postcode":"80239",
    "sg:province":"CO",
    "wof:name":"Jagadan Records & Design",
    "wof:placetype":"venue"
},
  "geometry": {"coordinates":[-104.82364099999999,39.776863],"type":"Point"}
}