{
  "type": "Feature",
  "properties": {
    "iso:country":"US",
    "sg:address":"943 S Leyden St",
    "sg:city":"Denver",
    "sg:classifiers":[
        {
            "category":"Professional",
            "type":"Services"
        }
    ],
    "sg:phone":"+1 303 333 7727",
    "sg:postcode":"80224",
    "sg:province":"CO",
    "wof:name":"Classic Doorways LLC",
    "wof:placetype":"venue"
},
  "geometry": {"coordinates":[-104.915335,39.699209],"type":"Point"}
}