{
  "type": "Feature",
  "properties": {
    "iso:country":"US",
    "sg:address":"614 Sunshine Canyon Dr",
    "sg:city":"Boulder",
    "sg:classifiers":[
        {
            "category":"Manufacturing",
            "subcategory":"Rubber & Plastics",
            "type":"Manufacturing & Wholesale Goods"
        }
    ],
    "sg:phone":"+1 303 444 8008",
    "sg:postcode":"80302",
    "sg:province":"CO",
    "sg:tags":[
        "mfg",
        "advertising",
        "specialty"
    ],
    "wof:name":"J T I",
    "wof:placetype":"venue"
},
  "geometry": {"coordinates":[-105.30293899999999,40.024664],"type":"Point"}
}