{
  "type": "Feature",
  "properties": {
    "iso:country":"US",
    "sg:address":"128 Swope Ave",
    "sg:city":"Colorado Springs",
    "sg:classifiers":[
        {
            "category":"Personal",
            "subcategory":"Beauty Salon",
            "type":"Services"
        }
    ],
    "sg:phone":"+1 719 477 0141",
    "sg:postcode":"80909",
    "sg:province":"CO",
    "wof:name":"Friends Day Spa",
    "wof:placetype":"venue"
},
  "geometry": {"coordinates":[-104.791769,38.83529],"type":"Point"}
}