{
  "type": "Feature",
  "properties": {
    "iso:country":"US",
    "sg:address":"14253 E Harvard Ave",
    "sg:city":"Aurora",
    "sg:classifiers":[
        {
            "category":"Retail",
            "subcategory":"Laundry & Dry Cleaning",
            "type":"Services"
        }
    ],
    "sg:phone":"+1 303 696 1311",
    "sg:postcode":"80014",
    "sg:province":"CO",
    "sg:tags":[
        "cleaners",
        "rug",
        "carpet"
    ],
    "wof:name":"Pro Clean Carpets & Upholstery",
    "wof:placetype":"venue"
},
  "geometry": {"coordinates":[-104.821882,39.671678],"type":"Point"}
}