{
  "type": "Feature",
  "properties": {
    "iso:country":"US",
    "sg:address":"1096 Toedtli Dr",
    "sg:city":"Boulder",
    "sg:classifiers":[
        {
            "category":"Building & Trades",
            "subcategory":"Construction",
            "type":"Services"
        }
    ],
    "sg:phone":"+1 303 499 6122",
    "sg:postcode":"80305",
    "sg:province":"CO",
    "sg:tags":[
        "house"
    ],
    "wof:name":"Liscom Construction",
    "wof:placetype":"venue"
},
  "geometry": {"coordinates":[-105.24624799999999,39.979846],"type":"Point"}
}