{
  "type": "Feature",
  "properties": {
    "addr:full":"408 Primrose Rd Boulder CO 80302",
    "addr:housenumber":"408",
    "addr:postcode":"80302",
    "addr:street":"Primrose Rd",
    "iso:country":"US",
    "sg:address":"408 Primrose Rd",
    "sg:city":"Boulder",
    "sg:classifiers":[
        {
            "category":"Professional",
            "type":"Services"
        }
    ],
    "sg:phone":"+1 303 448 9658",
    "sg:postcode":"80302",
    "sg:province":"CO",
    "sg:tags":[
        "establishment"
    ],
    "wof:name":"Chautauqua Assoc",
    "wof:placetype":"venue"
},
  "geometry": {"coordinates":[-105.28162399999999,39.997184],"type":"Point"}
}