{
  "type": "Feature",
  "properties": {
    "iso:country":"US",
    "sg:address":"1410 Bellaire Dr",
    "sg:city":"Colorado Springs",
    "sg:classifiers":[
        {
            "category":"Building & Trades",
            "subcategory":"Construction",
            "type":"Services"
        }
    ],
    "sg:phone":"+1 719 632 7371",
    "sg:postcode":"80909",
    "sg:province":"CO",
    "sg:tags":[
        "hanging",
        "contractor"
    ],
    "wof:name":"Two Worlds Painting Inc",
    "wof:placetype":"venue"
},
  "geometry": {"coordinates":[-104.791346,38.851845],"type":"Point"}
}