{
  "type": "Feature",
  "properties": {
    "iso:country":"US",
    "sg:address":"1515 W Thomas Ave",
    "sg:city":"Englewood",
    "sg:classifiers":[
        {
            "category":"Home & Garden",
            "subcategory":"Home Furnishings",
            "type":"Retail Goods"
        }
    ],
    "sg:phone":"+1 303 797 6643",
    "sg:postcode":"80110",
    "sg:province":"CO",
    "sg:tags":[
        "curtain",
        "upholstery",
        "drapery",
        "store"
    ],
    "wof:name":"Custom Stitchery LTD",
    "wof:placetype":"venue"
},
  "geometry": {"coordinates":[-105.006478,39.632435],"type":"Point"}
}