{
  "type": "Feature",
  "properties": {
    "iso:country":"US",
    "sg:address":"105 W Main St",
    "sg:city":"Florence",
    "sg:classifiers":[
        {
            "category":"Professional",
            "subcategory":"Accounting & Tax Preparation",
            "type":"Services"
        }
    ],
    "sg:phone":"+1 719 784 1996",
    "sg:postcode":"81226",
    "sg:province":"CO",
    "sg:tags":[
        "accountant"
    ],
    "wof:name":"Hawkeye Business & Accounting",
    "wof:placetype":"venue"
},
  "geometry": {"coordinates":[-105.119366,38.390155],"type":"Point"}
}