{
  "type": "Feature",
  "properties": {
    "iso:country":"US",
    "sg:address":"8th St Off Santa Fe Ave",
    "sg:city":"Denver",
    "sg:classifiers":[
        {
            "category":"Arts & Performance",
            "subcategory":"Art Gallery",
            "type":"Entertainment"
        },
        {
            "category":"Arts & Performance",
            "subcategory":"Music",
            "type":"Entertainment"
        }
    ],
    "sg:postcode":"80204",
    "sg:province":"CO",
    "sg:tags":[
        "venue"
    ],
    "wof:name":"LG Gallery",
    "wof:placetype":"venue"
},
  "geometry": {"coordinates":[-105.007126,39.743894],"type":"Point"}
}