{
  "type": "Feature",
  "properties": {
    "iso:country":"US",
    "sg:address":"1049 Vaughn St",
    "sg:city":"Aurora",
    "sg:classifiers":[
        {
            "category":"Building & Trades",
            "subcategory":"Construction",
            "type":"Services"
        }
    ],
    "sg:phone":"+1 303 360 7930",
    "sg:postcode":"80011",
    "sg:province":"CO",
    "sg:tags":[
        "hanging",
        "contractor"
    ],
    "wof:name":"Valdevino Moreira Painting Con",
    "wof:placetype":"venue"
},
  "geometry": {"coordinates":[-104.83586200000001,39.733114],"type":"Point"}
}