{
  "type": "Feature",
  "properties": {
    "iso:country":"US",
    "sg:address":"3659 S Newport Way",
    "sg:city":"Denver",
    "sg:classifiers":[
        {
            "category":"Banks & Credit Unions",
            "subcategory":"Financial Services",
            "type":"Services"
        }
    ],
    "sg:phone":"+1 303 758 4956",
    "sg:postcode":"80237",
    "sg:province":"CO",
    "sg:tags":[
        "investor"
    ],
    "wof:name":"Longview Investments Ltd Lllp",
    "wof:placetype":"venue"
},
  "geometry": {"coordinates":[-104.911253,39.650113],"type":"Point"}
}