{
  "type": "Feature",
  "properties": {
    "addr:full":"385 S Pierce Ave Louisville CO 80027",
    "addr:housenumber":"385",
    "addr:postcode":"80027",
    "addr:street":"S Pierce Ave",
    "iso:country":"US",
    "sg:address":"385 S Pierce Ave",
    "sg:city":"Louisville",
    "sg:classifiers":[
        {
            "category":"Wholesale",
            "subcategory":"Medical Equipment & Supplies",
            "type":"Manufacturing & Wholesale Goods"
        },
        {
            "category":"Health Services",
            "subcategory":"Clinic",
            "type":"Services"
        }
    ],
    "sg:phone":"+1 303 604 2249",
    "sg:postcode":"80027",
    "sg:province":"CO",
    "sg:tags":[
        "home",
        "physician",
        "surgeon",
        "care"
    ],
    "wof:name":"Apria Healthcare Inc",
    "wof:placetype":"venue"
},
  "geometry": {"coordinates":[-105.122497,39.965044],"type":"Point"}
}