{
  "type": "Feature",
  "properties": {
    "iso:country":"US",
    "sg:address":"618 Surrey Rd",
    "sg:city":"Carbondale",
    "sg:classifiers":[
        {
            "category":"Retail",
            "subcategory":"Veterinary Services",
            "type":"Services"
        }
    ],
    "sg:phone":"+1 970 704 1604",
    "sg:postcode":"81623",
    "sg:province":"CO",
    "wof:name":"Alpine Animal Hospital",
    "wof:placetype":"venue"
},
  "geometry": {"coordinates":[-107.219004,39.410497],"type":"Point"}
}