{
  "type": "Feature",
  "properties": {
    "iso:country":"US",
    "sg:address":"2229 Wildcat Reserve Pkwy",
    "sg:city":"Littleton",
    "sg:classifiers":[
        {
            "category":"Restaurant",
            "type":"Food & Drink"
        }
    ],
    "sg:phone":"+1 303 470 9999",
    "sg:postcode":"80129",
    "sg:province":"CO",
    "sg:tags":[
        "pizza"
    ],
    "wof:name":"Abo's Pizza",
    "wof:placetype":"venue"
},
  "geometry": {"coordinates":[-105.015005,39.53518],"type":"Point"}
}