{
  "type": "Feature",
  "properties": {
    "iso:country":"US",
    "sg:address":"1601 E 19th Ave Suite 4200",
    "sg:city":"Denver",
    "sg:classifiers":[
        {
            "category":"Health Services",
            "subcategory":"Doctor",
            "type":"Services"
        }
    ],
    "sg:phone":"+1 303 225 9532",
    "sg:postcode":"80218",
    "sg:province":"CO",
    "sg:tags":[
        "physician",
        "family",
        "gynecology",
        "practice",
        "surgeons",
        "obstetrics",
        "medicine"
    ],
    "wof:name":"Rocky Mountain Women's Care",
    "wof:placetype":"venue"
},
  "geometry": {"coordinates":[-104.968422,39.746078],"type":"Point"}
}