{
  "type": "Feature",
  "properties": {
    "addr:full":"5715 N Academy Blvd Colorado Springs CO 80918",
    "addr:housenumber":"5715",
    "addr:postcode":"80918",
    "addr:street":"N Academy Blvd",
    "iso:country":"US",
    "sg:address":"5715 N Academy Blvd",
    "sg:city":"Colorado Springs",
    "sg:classifiers":[
        {
            "category":"Home & Garden",
            "subcategory":"Building Materials",
            "type":"Retail Goods"
        }
    ],
    "sg:phone":"+1 719 590 7091",
    "sg:postcode":"80918",
    "sg:province":"CO",
    "sg:tags":[
        "wallpaper"
    ],
    "wof:name":"Heritage Wallpaper and Blinds",
    "wof:placetype":"venue"
},
  "geometry": {"coordinates":[-104.787406,38.914719],"type":"Point"}
}