{
  "type": "Feature",
  "properties": {
    "iso:country":"US",
    "sg:address":"1972 W Iliff Ave",
    "sg:city":"Englewood",
    "sg:classifiers":[
        {
            "category":"Wholesale",
            "subcategory":"Construction Materials",
            "type":"Manufacturing & Wholesale Goods"
        }
    ],
    "sg:phone":"+1 303 936 3450",
    "sg:postcode":"80110",
    "sg:province":"CO",
    "sg:tags":[
        "hardware",
        "door"
    ],
    "wof:name":"G Wyant Inc",
    "wof:placetype":"venue"
},
  "geometry": {"coordinates":[-105.009424,39.674932],"type":"Point"}
}