{
  "type": "Feature",
  "properties": {
    "addr:full":"6404 W Canyon Ave Littleton CO 80128",
    "addr:housenumber":"6404",
    "addr:postcode":"80128",
    "addr:street":"W Canyon Ave",
    "iso:country":"US",
    "sg:address":"6404 W Canyon Ave",
    "sg:city":"Littleton",
    "sg:classifiers":[
        {
            "category":"Shopping",
            "subcategory":"Gifts & Souvenirs",
            "type":"Retail Goods"
        }
    ],
    "sg:phone":"+1 720 922 0984",
    "sg:postcode":"80128",
    "sg:province":"CO",
    "sg:tags":[
        "basket",
        "parcel"
    ],
    "wof:name":"Gift Basket Genie",
    "wof:placetype":"venue"
},
  "geometry": {"coordinates":[-105.06811399999999,39.575713],"type":"Point"}
}