{
  "type": "Feature",
  "properties": {
    "iso:country":"US",
    "sg:address":"6911 State Hwy 73",
    "sg:city":"Evergreen",
    "sg:classifiers":[
        {
            "category":"Building & Trades",
            "subcategory":"Construction",
            "type":"Services"
        }
    ],
    "sg:phone":"+1 303 670 4919",
    "sg:postcode":"80439",
    "sg:province":"CO",
    "sg:tags":[
        "house",
        "builder",
        "deck"
    ],
    "wof:name":"Rolling Ridge Deck Co Inc",
    "wof:placetype":"venue"
},
  "geometry": {"coordinates":[-105.31048800000001,39.590752],"type":"Point"}
}