{
  "type": "Feature",
  "properties": {
    "iso:country":"US",
    "sg:address":"15935 Ridge Tee Dr",
    "sg:city":"Morrison",
    "sg:classifiers":[
        {
            "category":"Professional",
            "type":"Services"
        }
    ],
    "sg:phone":"+1 303 697 2780",
    "sg:postcode":"80465",
    "sg:province":"CO",
    "wof:name":"Donna Hall Inc",
    "wof:placetype":"venue"
},
  "geometry": {"coordinates":[-105.17980300000001,39.611948],"type":"Point"}
}