{
  "type": "Feature",
  "properties": {
    "addr:full":"16037 E Lake Cir Aurora CO 80016",
    "addr:housenumber":"16037",
    "addr:postcode":"80016",
    "addr:street":"E Lake Cir",
    "iso:country":"US",
    "sg:address":"16037 E Lake Cir",
    "sg:city":"Aurora",
    "sg:classifiers":[
        {
            "category":"Real Estate",
            "subcategory":"Real Estate Services",
            "type":"Services"
        },
        {
            "category":"Building & Trades",
            "subcategory":"Cleaning & Sanitation",
            "type":"Services"
        }
    ],
    "sg:phone":"+1 303 870 1290",
    "sg:postcode":"80016",
    "sg:province":"CO",
    "sg:tags":[
        "maintenance",
        "cleaners-interior"
    ],
    "wof:name":"Ace Maintenance Inc",
    "wof:placetype":"venue"
},
  "geometry": {"coordinates":[-104.80198799999999,39.606223],"type":"Point"}
}