{
  "type": "Feature",
  "properties": {
    "iso:country":"US",
    "sg:address":"529 Main St",
    "sg:city":"Alamosa",
    "sg:classifiers":[
        {
            "category":"Organizations",
            "subcategory":"Membership Organization",
            "type":"Services"
        }
    ],
    "sg:phone":"+1 719 587 9663",
    "sg:postcode":"81101",
    "sg:province":"CO",
    "sg:tags":[
        "society",
        "humane"
    ],
    "wof:name":"San Luis Valley Animal Welfare",
    "wof:placetype":"venue"
},
  "geometry": {"coordinates":[-105.865126,37.468242],"type":"Point"}
}