{
  "type": "Feature",
  "properties": {
    "addr:full":"8501 W Bowles Ave Littleton CO 80123",
    "addr:housenumber":"8501",
    "addr:postcode":"80123",
    "addr:street":"W Bowles Ave",
    "iso:country":"US",
    "sg:address":"8501 W Bowles Ave",
    "sg:city":"Littleton",
    "sg:classifiers":[
        {
            "category":"Restaurant",
            "type":"Food & Drink"
        }
    ],
    "sg:menulink":"http://www.allmenus.com/co/northeast-jefferson/233397-pretzel-maker/menu/",
    "sg:phone":"+1 303 972 1893",
    "sg:postcode":"80123",
    "sg:province":"CO",
    "sg:tags":[
        "new",
        "american"
    ],
    "wof:name":"Pretzel Maker",
    "wof:placetype":"venue"
},
  "geometry": {"coordinates":[-105.096006,39.612034],"type":"Point"}
}