{
  "type": "Feature",
  "properties": {
    "addr:full":"1420 E Alameda Ave Denver CO 80209",
    "addr:housenumber":"1420",
    "addr:postcode":"80209",
    "addr:street":"E Alameda Ave",
    "iso:country":"US",
    "sg:address":"1420 E Alameda Ave",
    "sg:city":"Denver",
    "sg:classifiers":[
        {
            "category":"Shopping",
            "subcategory":"Department Store",
            "type":"Retail Goods"
        },
        {
            "category":"Shopping Center",
            "type":"Public Place"
        }
    ],
    "sg:phone":"+1 303 344 4120",
    "sg:postcode":"80209",
    "sg:province":"CO",
    "wof:name":"Aurora Mall",
    "wof:placetype":"venue"
},
  "geometry": {"coordinates":[-104.97077400000001,39.710965],"type":"Point"}
}