{
  "type": "Feature",
  "properties": {
    "iso:country":"US",
    "sg:address":"11800 W Colfax Ave",
    "sg:city":"Lakewood",
    "sg:classifiers":[
        {
            "category":"Food & Beverages",
            "subcategory":"Groceries & Convenience Stores",
            "type":"Retail Goods"
        }
    ],
    "sg:phone":"+1 303 234 0512",
    "sg:postcode":"80215",
    "sg:province":"CO",
    "wof:name":"U-Pump It",
    "wof:placetype":"venue"
},
  "geometry": {"coordinates":[-105.131804,39.740142],"type":"Point"}
}