{
  "type": "Feature",
  "properties": {
    "addr:full":"601 E 8th St Pueblo CO 81001",
    "addr:housenumber":"601",
    "addr:postcode":"81001",
    "addr:street":"E 8Th St",
    "iso:country":"US",
    "sg:address":"601 E 8th St",
    "sg:city":"Pueblo",
    "sg:classifiers":[
        {
            "category":"Retail",
            "subcategory":"Auto Repair",
            "type":"Services"
        }
    ],
    "sg:phone":"+1 719 542 0050",
    "sg:postcode":"81001",
    "sg:province":"CO",
    "sg:tags":[
        "repairing",
        "automobile",
        "used",
        "automotive"
    ],
    "wof:name":"Hinkle Fleet & Auto Repair",
    "wof:placetype":"venue"
},
  "geometry": {"coordinates":[-104.59836900000001,38.27457],"type":"Point"}
}