{
  "type": "Feature",
  "properties": {
    "iso:country":"US",
    "sg:address":"5050 Yulle Rd",
    "sg:city":"Strasburg",
    "sg:classifiers":[
        {
            "category":"Farming",
            "subcategory":"Farm",
            "type":"Manufacturing & Wholesale Goods"
        }
    ],
    "sg:phone":"+1 303 622 4516",
    "sg:postcode":"80136",
    "sg:province":"CO",
    "sg:tags":[
        "crop",
        "general"
    ],
    "wof:name":"Black Thunder Farms",
    "wof:placetype":"venue"
},
  "geometry": {"coordinates":[-104.37674,39.782187],"type":"Point"}
}