{
  "type": "Feature",
  "properties": {
    "iso:country":"US",
    "sg:address":"419 Garfield St",
    "sg:city":"Grand Lake",
    "sg:classifiers":[
        {
            "category":"Travel",
            "subcategory":"Hotels & Motels",
            "type":"Entertainment"
        }
    ],
    "sg:phone":"+1 970 627 3580",
    "sg:postcode":"80447",
    "sg:province":"CO",
    "sg:website":"www.westernriv.com",
    "wof:name":"Western Riviera Motel",
    "wof:placetype":"venue"
},
  "geometry": {"coordinates":[-105.819866,40.251313],"type":"Point"}
}