{
  "type": "Feature",
  "properties": {
    "addr:full":"200 S Ridge St Breckenridge CO 80424",
    "addr:housenumber":"200",
    "addr:postcode":"80424",
    "addr:street":"S Ridge St",
    "iso:country":"US",
    "sg:address":"200 S Ridge St",
    "sg:city":"Breckenridge",
    "sg:classifiers":[
        {
            "category":"Real Estate",
            "subcategory":"Real Estate Services",
            "type":"Services"
        }
    ],
    "sg:phone":"+1 970 453 2255",
    "sg:postcode":"80424",
    "sg:province":"CO",
    "sg:tags":[
        "company",
        "title"
    ],
    "sg:website":"www.ltgc.com",
    "wof:name":"Land Title Guarantee Co",
    "wof:placetype":"venue"
},
  "geometry": {"coordinates":[-106.04463699999999,39.480888],"type":"Point"}
}