{
  "type": "Feature",
  "properties": {
    "iso:country":"US",
    "sg:address":"1500 E 128th Ave",
    "sg:city":"Thornton",
    "sg:classifiers":[
        {
            "category":"Organizations",
            "subcategory":"Religious Organization",
            "type":"Services"
        }
    ],
    "sg:phone":"+1 303 469 9797",
    "sg:postcode":"80241",
    "sg:province":"CO",
    "sg:tags":[
        "church"
    ],
    "wof:name":"Genesis Community Church",
    "wof:placetype":"venue"
},
  "geometry": {"coordinates":[-104.970242,39.928424],"type":"Point"}
}