{
  "type": "Feature",
  "properties": {
    "iso:country":"US",
    "sg:address":"276 Galapago St",
    "sg:city":"Denver",
    "sg:classifiers":[
        {
            "category":"Building & Trades",
            "subcategory":"Landscaping Services",
            "type":"Services"
        }
    ],
    "sg:phone":"+1 720 904 9591",
    "sg:postcode":"80223",
    "sg:province":"CO",
    "sg:tags":[
        "tree"
    ],
    "wof:name":"Tree Of Life Studio",
    "wof:placetype":"venue"
},
  "geometry": {"coordinates":[-104.996287,39.719706],"type":"Point"}
}