{
  "type": "Feature",
  "properties": {
    "iso:country":"US",
    "sg:address":"6175 S Forest Ct",
    "sg:city":"Centennial",
    "sg:classifiers":[
        {
            "category":"Professional",
            "subcategory":"Computer Services",
            "type":"Services"
        }
    ],
    "sg:phone":"+1 303 770 1286",
    "sg:postcode":"80121",
    "sg:province":"CO",
    "sg:tags":[
        "consultant",
        "designer"
    ],
    "sg:website":"www.ezmailbox.com",
    "wof:name":"A Little Computing",
    "wof:placetype":"venue"
},
  "geometry": {"coordinates":[-104.92625,39.604998],"type":"Point"}
}