{
  "type": "Feature",
  "properties": {
    "iso:country":"US",
    "sg:address":"4288 Youngfield St",
    "sg:city":"Wheat Ridge",
    "sg:classifiers":[
        {
            "category":"Building & Trades",
            "subcategory":"Construction",
            "type":"Services"
        }
    ],
    "sg:phone":"+1 303 431 4973",
    "sg:postcode":"80033",
    "sg:province":"CO",
    "sg:tags":[
        "house"
    ],
    "sg:website":"www.modernloghomes.com",
    "wof:name":"Modern Log Homes",
    "wof:placetype":"venue"
},
  "geometry": {"coordinates":[-105.14249,39.775097],"type":"Point"}
}