{
  "type": "Feature",
  "properties": {
    "addr:full":"1819 N Circle Dr Colorado Springs CO 80909",
    "addr:housenumber":"1819",
    "addr:postcode":"80909",
    "addr:street":"N Circle Dr",
    "iso:country":"US",
    "sg:address":"1819 N Circle Dr",
    "sg:city":"Colorado Springs",
    "sg:classifiers":[
        {
            "category":"Health Services",
            "subcategory":"Doctor",
            "type":"Services"
        }
    ],
    "sg:phone":"+1 719 520 5884",
    "sg:postcode":"80909",
    "sg:province":"CO",
    "sg:tags":[
        "dentist"
    ],
    "wof:name":"Richard H Wiedey DDS",
    "wof:placetype":"venue"
},
  "geometry": {"coordinates":[-104.775665,38.858578],"type":"Point"}
}