{
  "type": "Feature",
  "properties": {
    "addr:full":"2 Garden Center Broomfield CO 80020",
    "addr:housenumber":"2",
    "addr:postcode":"80020",
    "addr:street":"Garden Center",
    "iso:country":"US",
    "sg:address":"2 Garden Center",
    "sg:city":"Broomfield",
    "sg:classifiers":[
        {
            "category":"Professional",
            "subcategory":"Lawyer & Legal Services",
            "type":"Services"
        }
    ],
    "sg:phone":"+1 303 465 5555",
    "sg:postcode":"80020",
    "sg:province":"CO",
    "sg:tags":[
        "attorney"
    ],
    "wof:name":"Buzek & Hudson",
    "wof:placetype":"venue"
},
  "geometry": {"coordinates":[-105.088273,39.923891],"type":"Point"}
}