{
  "type": "Feature",
  "properties": {
    "addr:full":"8735 Wadsworth Blvd Arvada CO 80003",
    "addr:housenumber":"8735",
    "addr:postcode":"80003",
    "addr:street":"Wadsworth Blvd",
    "iso:country":"US",
    "sg:address":"8735 Wadsworth Blvd",
    "sg:city":"Arvada",
    "sg:classifiers":[
        {
            "category":"Shopping",
            "subcategory":"Pharmacy",
            "type":"Retail Goods"
        }
    ],
    "sg:phone":"+1 303 420 5016",
    "sg:postcode":"80003",
    "sg:province":"CO",
    "sg:website":"www.walgreens.com",
    "wof:name":"Walgreens",
    "wof:placetype":"venue"
},
  "geometry": {"coordinates":[-105.081625,39.855072],"type":"Point"}
}