{
  "type": "Feature",
  "properties": {
    "iso:country":"US",
    "sg:address":"220 5th St",
    "sg:city":"Paonia",
    "sg:classifiers":[
        {
            "category":"Personal",
            "subcategory":"Beauty Salon",
            "type":"Services"
        }
    ],
    "sg:phone":"+1 970 527 7546",
    "sg:postcode":"81428",
    "sg:province":"CO",
    "sg:tags":[
        "treatment",
        "skin"
    ],
    "wof:name":"Paonia Skin Care",
    "wof:placetype":"venue"
},
  "geometry": {"coordinates":[-107.59760799999999,38.870903],"type":"Point"}
}