{
  "type": "Feature",
  "properties": {
    "addr:full":"1444 Folsom St Boulder CO 80302",
    "addr:housenumber":"1444",
    "addr:postcode":"80302",
    "addr:street":"Folsom St",
    "iso:country":"US",
    "sg:address":"1444 Folsom St",
    "sg:city":"Boulder",
    "sg:classifiers":[
        {
            "category":"Building & Trades",
            "subcategory":"Landscaping Services",
            "type":"Services"
        }
    ],
    "sg:phone":"+1 303 443 0688",
    "sg:postcode":"80302",
    "sg:province":"CO",
    "wof:name":"All Seasons Maintenance",
    "wof:placetype":"venue"
},
  "geometry": {"coordinates":[-105.263293,40.011116],"type":"Point"}
}