{
  "type": "Feature",
  "properties": {
    "iso:country":"US",
    "sg:address":"11951 W Dumbarton Dr",
    "sg:city":"Morrison",
    "sg:classifiers":[
        {
            "category":"Building & Trades",
            "subcategory":"Plumbing",
            "type":"Services"
        }
    ],
    "sg:phone":"+1 303 979 0047",
    "sg:postcode":"80465",
    "sg:province":"CO",
    "sg:tags":[
        "plumbing",
        "contractor"
    ],
    "wof:name":"A Bear Plumbing Co Inc",
    "wof:placetype":"venue"
},
  "geometry": {"coordinates":[-105.132265,39.62561],"type":"Point"}
}