{
  "type": "Feature",
  "properties": {
    "iso:country":"US",
    "sg:address":"8 S 5th St",
    "sg:city":"Montrose",
    "sg:classifiers":[
        {
            "category":"Education",
            "subcategory":"School",
            "type":"Public Place"
        }
    ],
    "sg:phone":"+1 970 249 2944",
    "sg:postcode":"81401",
    "sg:province":"CO",
    "wof:name":"West Central Boces",
    "wof:placetype":"venue"
},
  "geometry": {"coordinates":[-107.875569,38.473375],"type":"Point"}
}