{
  "type": "Feature",
  "properties": {
    "addr:full":"15 Silverview Ct Durango CO 81303",
    "addr:housenumber":"15",
    "addr:postcode":"co 81303",
    "addr:street":"Silverview Ct",
    "iso:country":"US",
    "sg:address":"15 Silverview Ct",
    "sg:city":"Durango",
    "sg:classifiers":[
        {
            "category":"Building & Trades",
            "subcategory":"Landscaping Services",
            "type":"Services"
        }
    ],
    "sg:phone":"+1 970 247 9274",
    "sg:postcode":"81303",
    "sg:province":"CO",
    "sg:tags":[
        "landscape",
        "contractor"
    ],
    "wof:name":"Authentic Landscaping",
    "wof:placetype":"venue"
},
  "geometry": {"coordinates":[-107.814573,37.224436],"type":"Point"}
}