{
  "type": "Feature",
  "properties": {
    "addr:full":"1634 Monaco Pkwy Denver CO 80220",
    "addr:housenumber":"1634",
    "addr:postcode":"80220",
    "addr:street":"Monaco Pkwy",
    "iso:country":"US",
    "sg:address":"1634 Monaco Pkwy",
    "sg:city":"Denver",
    "sg:classifiers":[
        {
            "category":"Building & Trades",
            "subcategory":"Cleaning & Sanitation",
            "type":"Services"
        }
    ],
    "sg:phone":"+1 303 237 9021",
    "sg:postcode":"80220",
    "sg:province":"CO",
    "wof:name":"Front Range Chemspray",
    "wof:placetype":"venue"
},
  "geometry": {"coordinates":[-104.912361,39.742315],"type":"Point"}
}