{
  "type": "Feature",
  "properties": {
    "addr:full":"6691 Colorado Blvd Commerce City CO 80022",
    "addr:housenumber":"6691",
    "addr:postcode":"80022",
    "addr:street":"Colorado Blvd",
    "iso:country":"US",
    "sg:address":"6691 Colorado Blvd",
    "sg:city":"Commerce City",
    "sg:classifiers":[
        {
            "category":"Retail",
            "subcategory":"Auto Repair",
            "type":"Services"
        }
    ],
    "sg:phone":"+1 303 289 4870",
    "sg:postcode":"80022",
    "sg:province":"CO",
    "sg:tags":[
        "conversion",
        "van"
    ],
    "wof:name":"Pro Vans USA",
    "wof:placetype":"venue"
},
  "geometry": {"coordinates":[-104.940496,39.813036],"type":"Point"}
}