{
  "type": "Feature",
  "properties": {
    "iso:country":"US",
    "sg:address":"13097 S Parker Rd",
    "sg:city":"Parker",
    "sg:classifiers":[
        {
            "category":"Restaurant",
            "type":"Food & Drink"
        }
    ],
    "sg:menulink":"http://www.allmenus.com/co/parker/128462-subway/menu/",
    "sg:phone":"+1 303 841 7917",
    "sg:postcode":"80134",
    "sg:province":"CO",
    "sg:tags":[
        "american",
        "sandwich"
    ],
    "wof:name":"Subway",
    "wof:placetype":"venue"
},
  "geometry": {"coordinates":[-104.759413,39.478975],"type":"Point"}
}