{
  "type": "Feature",
  "properties": {
    "addr:full":"10320 Moore Ct Broomfield CO 80021",
    "addr:housenumber":"10320",
    "addr:postcode":"80021",
    "addr:street":"Moore Ct",
    "iso:country":"US",
    "sg:address":"10320 Moore Ct",
    "sg:city":"Broomfield",
    "sg:classifiers":[
        {
            "category":"Building & Trades",
            "subcategory":"Electrical",
            "type":"Services"
        }
    ],
    "sg:phone":"+1 303 404 9329",
    "sg:postcode":"80021",
    "sg:province":"CO",
    "sg:tags":[
        "electrical",
        "contractor"
    ],
    "wof:name":"Rescom Electric",
    "wof:placetype":"venue"
},
  "geometry": {"coordinates":[-105.11666099999999,39.882353],"type":"Point"}
}