{
  "type": "Feature",
  "properties": {
    "addr:full":"34455 Co Rd 34 Mc Clave CO 81057",
    "addr:housenumber":"34455;34",
    "addr:postcode":"81057",
    "addr:street":"Co Rd;Mc Clave",
    "iso:country":"US",
    "sg:address":"34455 Co Rd 34",
    "sg:city":"Mc Clave",
    "sg:classifiers":[
        {
            "category":"Building & Trades",
            "subcategory":"Construction",
            "type":"Services"
        }
    ],
    "sg:phone":"+1 719 829 4466",
    "sg:postcode":"81057",
    "sg:province":"CO",
    "wof:name":"High Plains Builders Inc",
    "wof:placetype":"venue"
},
  "geometry": {"coordinates":[-102.778639,38.143651],"type":"Point"}
}