{
  "type": "Feature",
  "properties": {
    "addr:full":"401 23rd St Glenwood Springs CO 81601",
    "addr:housenumber":"401",
    "addr:postcode":"81601",
    "addr:street":"23Rd St",
    "iso:country":"US",
    "sg:address":"401 23rd St",
    "sg:city":"Glenwood Springs",
    "sg:classifiers":[
        {
            "category":"Wholesale",
            "subcategory":"Medical Equipment & Supplies",
            "type":"Manufacturing & Wholesale Goods"
        }
    ],
    "sg:phone":"+1 970 945 0377",
    "sg:postcode":"81601",
    "sg:province":"CO",
    "wof:name":"Alfini Chiropractic",
    "wof:placetype":"venue"
},
  "geometry": {"coordinates":[-107.32424899999999,39.529668],"type":"Point"}
}