{
  "type": "Feature",
  "properties": {
    "addr:full":"13955 Deere Ct Longmont CO 80504",
    "addr:housenumber":"13955",
    "addr:postcode":"80504",
    "addr:street":"Deere Ct",
    "iso:country":"US",
    "sg:address":"13955 Deere Ct",
    "sg:city":"Longmont",
    "sg:classifiers":[
        {
            "category":"Professional",
            "type":"Services"
        }
    ],
    "sg:phone":"+1 970 535 9554",
    "sg:postcode":"80504",
    "sg:province":"CO",
    "sg:tags":[
        "establishment"
    ],
    "wof:name":"Counties Corp",
    "wof:placetype":"venue"
},
  "geometry": {"coordinates":[-104.972145,40.203994],"type":"Point"}
}