{
  "type": "Feature",
  "properties": {
    "addr:full":"2460 S Steele St Denver CO 80210",
    "addr:housenumber":"2460",
    "addr:postcode":"80210",
    "addr:street":"S Steele St",
    "iso:country":"US",
    "sg:address":"2460 S Steele St",
    "sg:city":"Denver",
    "sg:classifiers":[
        {
            "category":"Building & Trades",
            "subcategory":"Construction",
            "type":"Services"
        }
    ],
    "sg:phone":"+1 303 691 0734",
    "sg:postcode":"80210",
    "sg:province":"CO",
    "sg:tags":[
        "house",
        "general",
        "contractor"
    ],
    "wof:name":"Guthrie Constructions Inc",
    "wof:placetype":"venue"
},
  "geometry": {"coordinates":[-104.949969,39.672301],"type":"Point"}
}