{
  "type": "Feature",
  "properties": {
    "iso:country":"US",
    "sg:address":"4955 S Ulster St",
    "sg:city":"Denver",
    "sg:classifiers":[
        {
            "category":"Restaurant",
            "type":"Food & Drink"
        }
    ],
    "sg:menulink":"http://www.allmenus.com/co/denver/40773-qdoba/menu/",
    "sg:phone":"+1 303 221 3366",
    "sg:postcode":"80237",
    "sg:province":"CO",
    "sg:tags":[
        "mexican"
    ],
    "wof:name":"Qdoba",
    "wof:placetype":"venue"
},
  "geometry": {"coordinates":[-104.894903,39.626061],"type":"Point"}
}