{
  "type": "Feature",
  "properties": {
    "addr:full":"4317 W Florida Avenue Denver CO 80219",
    "addr:housenumber":"4317",
    "addr:postcode":"80219",
    "addr:street":"W Florida Avenue",
    "iso:country":"US",
    "sg:address":"4317 W Florida Avenue",
    "sg:city":"Denver",
    "sg:classifiers":[
        {
            "category":"Food & Beverages",
            "subcategory":"Liquor & Beverages",
            "type":"Retail Goods"
        }
    ],
    "sg:phone":"+1 303 936 0202",
    "sg:postcode":"80219",
    "sg:province":"CO",
    "sg:tags":[
        "beer",
        "spirit",
        "wine"
    ],
    "wof:name":"Marlee Liquor Mart",
    "wof:placetype":"venue"
},
  "geometry": {"coordinates":[-105.043232,39.689342],"type":"Point"}
}