{
  "type": "Feature",
  "properties": {
    "iso:country":"US",
    "sg:address":"6801 S Yosemite St",
    "sg:city":"Centennial",
    "sg:classifiers":[
        {
            "category":"Health Services",
            "subcategory":"Hospital",
            "type":"Services"
        },
        {
            "category":"Social Services",
            "type":"Services"
        }
    ],
    "sg:phone":"+1 303 889 4805",
    "sg:postcode":"80112",
    "sg:province":"CO",
    "sg:tags":[
        "clinic",
        "mental",
        "outpatient",
        "specialty"
    ],
    "sg:website":"www.bhicares.org",
    "wof:name":"Behavioral Healthcare Inc",
    "wof:placetype":"venue"
},
  "geometry": {"coordinates":[-104.88548299999999,39.591209],"type":"Point"}
}