{
  "type": "Feature",
  "properties": {
    "addr:full":"7800 S Elati St Littleton CO 80120",
    "addr:housenumber":"7800",
    "addr:postcode":"80120",
    "addr:street":"S Elati St",
    "iso:country":"US",
    "sg:address":"7800 S Elati St",
    "sg:city":"Littleton",
    "sg:classifiers":[
        {
            "category":"Social Services",
            "type":"Services"
        }
    ],
    "sg:phone":"+1 303 794 4492",
    "sg:postcode":"80120",
    "sg:province":"CO",
    "sg:tags":[
        "counselor",
        "marriage",
        "family"
    ],
    "sg:website":"www.summitcounseling.com",
    "wof:name":"Summit Counseling",
    "wof:placetype":"venue"
},
  "geometry": {"coordinates":[-104.99739599999999,39.575756],"type":"Point"}
}