{
  "type": "Feature",
  "properties": {
    "addr:full":"5184 Golden Eagle Pkwy Brighton CO 80601",
    "addr:housenumber":"5184",
    "addr:postcode":"80601",
    "addr:street":"Golden Eagle Pkwy",
    "iso:country":"US",
    "sg:address":"5184 Golden Eagle Pkwy",
    "sg:city":"Brighton",
    "sg:classifiers":[
        {
            "category":"Building & Trades",
            "subcategory":"Construction",
            "type":"Services"
        }
    ],
    "sg:phone":"+1 303 554 1707",
    "sg:postcode":"80601",
    "sg:province":"CO",
    "sg:tags":[
        "contractor"
    ],
    "wof:name":"Other Fence Company",
    "wof:placetype":"venue"
},
  "geometry": {"coordinates":[-104.749185,39.978377],"type":"Point"}
}