{
  "type": "Feature",
  "properties": {
    "iso:country":"US",
    "sg:address":"4004 Ideal Dr",
    "sg:city":"Fort Collins",
    "sg:classifiers":[
        {
            "category":"Manufacturing",
            "subcategory":"Jewelry",
            "type":"Manufacturing & Wholesale Goods"
        }
    ],
    "sg:phone":"+1 970 482 2945",
    "sg:postcode":"80524",
    "sg:province":"CO",
    "sg:tags":[
        "precious",
        "metal",
        "mfg"
    ],
    "wof:name":"Kings Treasures",
    "wof:placetype":"venue"
},
  "geometry": {"coordinates":[-105.11727500000001,40.645484],"type":"Point"}
}