{
  "type": "Feature",
  "properties": {
    "iso:country":"US",
    "sg:address":"6616 S Parker Rd",
    "sg:city":"Aurora",
    "sg:classifiers":[
        {
            "category":"Shopping",
            "type":"Retail Goods"
        }
    ],
    "sg:phone":"+1 303 400 1977",
    "sg:postcode":"80016",
    "sg:province":"CO",
    "sg:tags":[
        "merchandise"
    ],
    "wof:name":"Wild Bird Landing",
    "wof:placetype":"venue"
},
  "geometry": {"coordinates":[-104.803318,39.597855],"type":"Point"}
}