{
  "type": "Feature",
  "properties": {
    "addr:full":"25797 Conifer Rd Conifer CO 80433",
    "addr:housenumber":"25797",
    "addr:postcode":"80433",
    "addr:street":"Conifer Rd",
    "iso:country":"US",
    "sg:address":"25797 Conifer Rd",
    "sg:city":"Conifer",
    "sg:classifiers":[
        {
            "category":"Building & Trades",
            "subcategory":"Construction",
            "type":"Services"
        }
    ],
    "sg:phone":"+1 303 816 7037",
    "sg:postcode":"80433",
    "sg:province":"CO",
    "sg:tags":[
        "planning",
        "remodeling",
        "kitchen"
    ],
    "wof:name":"N K Kitchen Design Studio LLC",
    "wof:placetype":"venue"
},
  "geometry": {"coordinates":[-105.29364200000001,39.543013],"type":"Point"}
}