{
  "type": "Feature",
  "properties": {
    "iso:country":"US",
    "sg:address":"850 E Harvard Avenue",
    "sg:city":"Denver",
    "sg:classifiers":[
        {
            "category":"Health Services",
            "subcategory":"Optometrist",
            "type":"Services"
        }
    ],
    "sg:phone":"+1 303 778 1910",
    "sg:postcode":"80210",
    "sg:province":"CO",
    "wof:name":"Retina Office",
    "wof:placetype":"venue"
},
  "geometry": {"coordinates":[-104.978077,39.671272],"type":"Point"}
}