{
  "type": "Feature",
  "properties": {
    "addr:full":"120 8th Ave Greeley CO 80631",
    "addr:housenumber":"120",
    "addr:postcode":"80631",
    "addr:street":"8Th Ave",
    "iso:country":"US",
    "sg:address":"120 8th Ave",
    "sg:city":"Greeley",
    "sg:classifiers":[
        {
            "category":"Banks & Credit Unions",
            "subcategory":"Bank",
            "type":"Services"
        }
    ],
    "sg:phone":"+1 970 356 7400",
    "sg:postcode":"80631",
    "sg:province":"CO",
    "sg:tags":[
        "cashing",
        "check"
    ],
    "wof:name":"Ok Check Cashing Co",
    "wof:placetype":"venue"
},
  "geometry": {"coordinates":[-104.69065399999999,40.432925],"type":"Point"}
}