{
  "type": "Feature",
  "properties": {
    "iso:country":"US",
    "sg:address":"1320 Pearl St",
    "sg:city":"Boulder",
    "sg:classifiers":[
        {
            "category":"Personal",
            "subcategory":"Beauty Salon",
            "type":"Services"
        }
    ],
    "sg:phone":"+1 303 938 8015",
    "sg:postcode":"80302",
    "sg:province":"CO",
    "sg:tags":[
        "shop"
    ],
    "sg:website":"www.pompadours.com",
    "wof:name":"Pompadours Hair Salon",
    "wof:placetype":"venue"
},
  "geometry": {"coordinates":[-105.277553,40.018319],"type":"Point"}
}