{
  "type": "Feature",
  "properties": {
    "addr:full":"13767 W Asbury Dr Denver CO 80228",
    "addr:housenumber":"13767",
    "addr:postcode":"80228",
    "addr:street":"W Asbury Dr",
    "iso:country":"US",
    "sg:address":"13767 W Asbury Dr",
    "sg:city":"Denver",
    "sg:classifiers":[
        {
            "category":"Freight",
            "type":"Transportation"
        }
    ],
    "sg:phone":"+1 303 988 7825",
    "sg:postcode":"80228",
    "sg:province":"CO",
    "sg:tags":[
        "operator",
        "local",
        "trucking"
    ],
    "wof:name":"Eldermove Services Inc",
    "wof:placetype":"venue"
},
  "geometry": {"coordinates":[-105.154275,39.680186],"type":"Point"}
}