{
  "type": "Feature",
  "properties": {
    "iso:country":"US",
    "sg:address":"109 Colorado Ave",
    "sg:city":"Pueblo",
    "sg:classifiers":[
        {
            "category":"Manufacturing",
            "subcategory":"Food",
            "type":"Manufacturing & Wholesale Goods"
        }
    ],
    "sg:phone":"+1 719 543 4631",
    "sg:postcode":"81004",
    "sg:province":"CO",
    "sg:tags":[
        "mfg"
    ],
    "wof:name":"Netties Colorado Candies",
    "wof:placetype":"venue"
},
  "geometry": {"coordinates":[-104.62190099999999,38.259326],"type":"Point"}
}