{
  "type": "Feature",
  "properties": {
    "iso:country":"US",
    "sg:address":"7571 Co Rd 38",
    "sg:city":"Johnstown",
    "sg:classifiers":[
        {
            "category":"Retail",
            "subcategory":"Repair Shop",
            "type":"Services"
        }
    ],
    "sg:phone":"+1 970 587 9001",
    "sg:postcode":"80534",
    "sg:province":"CO",
    "sg:tags":[
        "leather",
        "good"
    ],
    "wof:name":"Leathermedic",
    "wof:placetype":"venue"
},
  "geometry": {"coordinates":[-104.91527000000001,40.262487],"type":"Point"}
}