{
  "type": "Feature",
  "properties": {
    "iso:country":"US",
    "sg:address":"1040 S Pueblo Blvd",
    "sg:city":"Pueblo",
    "sg:classifiers":[
        {
            "category":"Food & Beverages",
            "subcategory":"Groceries & Convenience Stores",
            "type":"Retail Goods"
        }
    ],
    "sg:phone":"+1 719 564 3325",
    "sg:postcode":"81005",
    "sg:province":"CO",
    "wof:name":"7-Eleven",
    "wof:placetype":"venue"
},
  "geometry": {"coordinates":[-104.66202800000001,38.24818],"type":"Point"}
}