{
  "type": "Feature",
  "properties": {
    "addr:full":"1419 S Wahsatch Ave Colorado Springs CO 80906",
    "addr:housenumber":"1419",
    "addr:postcode":"80906",
    "addr:street":"S Wahsatch Ave",
    "iso:country":"US",
    "sg:address":"1419 S Wahsatch Ave",
    "sg:city":"Colorado Springs",
    "sg:classifiers":[
        {
            "category":"Wholesale",
            "subcategory":"Durable Goods & Equipment",
            "type":"Manufacturing & Wholesale Goods"
        }
    ],
    "sg:phone":"+1 719 473 2259",
    "sg:postcode":"80906",
    "sg:province":"CO",
    "sg:tags":[
        "fire",
        "extinguisher",
        "safety"
    ],
    "wof:name":"Colorado Safety Equipment",
    "wof:placetype":"venue"
},
  "geometry": {"coordinates":[-104.81912199999999,38.813011],"type":"Point"}
}