{
  "type": "Feature",
  "properties": {
    "iso:country":"US",
    "sg:address":"80 Fabrication Dr",
    "sg:city":"Pueblo",
    "sg:classifiers":[
        {
            "category":"Building & Trades",
            "subcategory":"Construction",
            "type":"Services"
        }
    ],
    "sg:phone":"+1 719 547 7082",
    "sg:postcode":"81007",
    "sg:province":"CO",
    "sg:tags":[
        "home",
        "restoration",
        "remodeling",
        "family"
    ],
    "wof:name":"Arrigo Construction",
    "wof:placetype":"venue"
},
  "geometry": {"coordinates":[-104.731258,38.336639],"type":"Point"}
}