{
  "type": "Feature",
  "properties": {
    "iso:country":"US",
    "sg:address":"39848 US Hwy 160",
    "sg:city":"Bayfield",
    "sg:classifiers":[
        {
            "category":"Freight",
            "type":"Transportation"
        }
    ],
    "sg:phone":"+1 970 884 2868",
    "sg:postcode":"81122",
    "sg:province":"CO",
    "sg:tags":[
        "commercial",
        "storage"
    ],
    "wof:name":"Gem Storage",
    "wof:placetype":"venue"
},
  "geometry": {"coordinates":[-107.63618,37.219151],"type":"Point"}
}