{
  "type": "Feature",
  "properties": {
    "iso:country":"US",
    "sg:address":"1220 11th St",
    "sg:city":"Rock Springs",
    "sg:classifiers":[
        {
            "category":"Organizations",
            "subcategory":"Community Association",
            "type":"Services"
        }
    ],
    "sg:phone":"+1 307 362 2278",
    "sg:postcode":"82901",
    "sg:province":"CO",
    "wof:name":"Croation Fraternal Union",
    "wof:placetype":"venue"
},
  "geometry": {"coordinates":[-109.21254,41.597286],"type":"Point"}
}