{
  "type": "Feature",
  "properties": {
    "iso:country":"US",
    "sg:address":"250 S Frontage Rd W",
    "sg:city":"Vail",
    "sg:classifiers":[
        {
            "category":"Travel",
            "subcategory":"Hotels & Motels",
            "type":"Entertainment"
        }
    ],
    "sg:phone":"+1 970 476 7810",
    "sg:postcode":"81657",
    "sg:province":"CO",
    "sg:website":"www.evergreenvail.com",
    "wof:name":"Evergreen Lodge",
    "wof:placetype":"venue"
},
  "geometry": {"coordinates":[-106.37891399999999,39.643481],"type":"Point"}
}