{
  "type": "Feature",
  "properties": {
    "iso:country":"US",
    "sg:address":"219 E Durant Ave",
    "sg:city":"Aspen",
    "sg:classifiers":[
        {
            "category":"Restaurant",
            "type":"Food & Drink"
        }
    ],
    "sg:phone":"+1 970 925 3525",
    "sg:postcode":"81611",
    "sg:province":"CO",
    "sg:tags":[
        "tavern"
    ],
    "wof:name":"Landrys Restaurants Inc",
    "wof:placetype":"venue"
},
  "geometry": {"coordinates":[-106.822495,39.187871],"type":"Point"}
}