{
  "type": "Feature",
  "properties": {
    "iso:country":"US",
    "sg:address":"1732 S Taft Hill Rd",
    "sg:city":"Fort Collins",
    "sg:classifiers":[
        {
            "category":"Banks & Credit Unions",
            "subcategory":"Investment Brokerage",
            "type":"Services"
        }
    ],
    "sg:phone":"+1 970 226 2744",
    "sg:postcode":"80526",
    "sg:province":"CO",
    "sg:tags":[
        "advisory",
        "financial"
    ],
    "wof:name":"Core Financial",
    "wof:placetype":"venue"
},
  "geometry": {"coordinates":[-105.11503999999999,40.566963],"type":"Point"}
}