{
  "type": "Feature",
  "properties": {
    "iso:country":"US",
    "sg:address":"1485 S Colorado Blvd Ste 220",
    "sg:city":"Denver",
    "sg:classifiers":[
        {
            "category":"Shopping",
            "subcategory":"Optician",
            "type":"Retail Goods"
        }
    ],
    "sg:phone":"+1 303 512 0177",
    "sg:postcode":"80222",
    "sg:province":"CO",
    "sg:tags":[
        "eyewear"
    ],
    "wof:name":"Empire Optical",
    "wof:placetype":"venue"
},
  "geometry": {"coordinates":[-104.941002,39.689499],"type":"Point"}
}