{
  "type": "Feature",
  "properties": {
    "addr:full":"14105 W Colfax Ave Golden CO 80401",
    "addr:housenumber":"14105",
    "addr:postcode":"80401",
    "addr:street":"W Colfax Ave",
    "iso:country":"US",
    "sg:address":"14105 W Colfax Ave",
    "sg:city":"Golden",
    "sg:classifiers":[
        {
            "category":"Shopping",
            "subcategory":"Department Store",
            "type":"Retail Goods"
        },
        {
            "category":"Wholesale",
            "subcategory":"Durable Goods & Equipment",
            "type":"Manufacturing & Wholesale Goods"
        }
    ],
    "sg:phone":"+1 303 279 8134",
    "sg:postcode":"80401",
    "sg:province":"CO",
    "sg:tags":[
        "shop"
    ],
    "wof:name":"Pier 1 Imports",
    "wof:placetype":"venue"
},
  "geometry": {"coordinates":[-105.159617,39.735174],"type":"Point"}
}