{
  "type": "Feature",
  "properties": {
    "addr:full":"5805 E 39th Ave Denver CO 80207",
    "addr:housenumber":"5805",
    "addr:postcode":"80207",
    "addr:street":"E 39Th Ave",
    "iso:country":"US",
    "sg:address":"5805 E 39th Ave",
    "sg:city":"Denver",
    "sg:classifiers":[
        {
            "category":"Home & Garden",
            "subcategory":"Garden Supply",
            "type":"Retail Goods"
        }
    ],
    "sg:phone":"+1 303 295 1777",
    "sg:postcode":"80207",
    "sg:province":"CO",
    "sg:tags":[
        "sprinkler"
    ],
    "sg:website":"www.dbcirrigation.com",
    "wof:name":"DBC Irrigation Supply",
    "wof:placetype":"venue"
},
  "geometry": {"coordinates":[-104.91931200000001,39.771137],"type":"Point"}
}