{
  "type": "Feature",
  "properties": {
    "addr:full":"3500 S Wadsworth Blvd Lakewood CO 80235",
    "addr:housenumber":"3500",
    "addr:postcode":"80235",
    "addr:street":"S Wadsworth Blvd",
    "iso:country":"US",
    "sg:address":"3500 S Wadsworth Blvd",
    "sg:city":"Lakewood",
    "sg:classifiers":[
        {
            "category":"Education",
            "subcategory":"Vocational School",
            "type":"Public Place"
        }
    ],
    "sg:phone":"+1 303 716 3326",
    "sg:postcode":"80235",
    "sg:province":"CO",
    "wof:name":"Horizon Counseling & Education",
    "wof:placetype":"venue"
},
  "geometry": {"coordinates":[-105.081337,39.653194],"type":"Point"}
}