{
  "type": "Feature",
  "properties": {
    "iso:country":"US",
    "sg:address":"8501 W Bowles Ave",
    "sg:city":"Littleton",
    "sg:classifiers":[
        {
            "category":"Shopping",
            "subcategory":"Clothing, Apparel, & Fashions",
            "type":"Retail Goods"
        }
    ],
    "sg:phone":"+1 303 973 0063",
    "sg:postcode":"80123",
    "sg:province":"CO",
    "sg:tags":[
        "family"
    ],
    "wof:name":"Gap",
    "wof:placetype":"venue"
},
  "geometry": {"coordinates":[-105.095545,39.609839],"type":"Point"}
}