{
  "type": "Feature",
  "properties": {
    "addr:full":"4634 S Broadway Englewood CO 80113",
    "addr:housenumber":"4634",
    "addr:postcode":"80113",
    "addr:street":"S Broadway",
    "iso:country":"US",
    "sg:address":"4634 S Broadway",
    "sg:city":"Englewood",
    "sg:classifiers":[
        {
            "category":"Building & Trades",
            "subcategory":"Construction",
            "type":"Services"
        }
    ],
    "sg:phone":"+1 303 781 8455",
    "sg:postcode":"80113",
    "sg:province":"CO",
    "sg:tags":[
        "commercial",
        "contractor"
    ],
    "sg:website":"www.financialenergy.com",
    "wof:name":"Financial Energy Management",
    "wof:placetype":"venue"
},
  "geometry": {"coordinates":[-104.98783899999999,39.631962],"type":"Point"}
}