{
  "type": "Feature",
  "properties": {
    "iso:country":"US",
    "sg:address":"4454 Tennyson Street",
    "sg:city":"Denver",
    "sg:classifiers":[
        {
            "category":"Professional",
            "subcategory":"Lawyer & Legal Services",
            "type":"Services"
        }
    ],
    "sg:phone":"+1 303 458 7205",
    "sg:postcode":"80212",
    "sg:province":"CO",
    "wof:name":"Valdez Jake R Atty",
    "wof:placetype":"venue"
},
  "geometry": {"coordinates":[-105.043828,39.777587],"type":"Point"}
}