{
  "type": "Feature",
  "properties": {
    "iso:country":"US",
    "sg:address":"3100 S Sheridan Blvd",
    "sg:city":"Denver",
    "sg:classifiers":[
        {
            "category":"Home & Garden",
            "subcategory":"Furniture",
            "type":"Retail Goods"
        }
    ],
    "sg:phone":"+1 303 936 6900",
    "sg:postcode":"80227",
    "sg:province":"CO",
    "sg:tags":[
        "cabinet",
        "kitchen"
    ],
    "wof:name":"Cabinet Wholesalers Inc",
    "wof:placetype":"venue"
},
  "geometry": {"coordinates":[-105.053189,39.654286],"type":"Point"}
}