{
  "type": "Feature",
  "properties": {
    "iso:country":"US",
    "sg:address":"11345 W 67th Pl",
    "sg:city":"Arvada",
    "sg:classifiers":[
        {
            "category":"Professional",
            "type":"Services"
        }
    ],
    "sg:phone":"+1 720 570 8909",
    "sg:postcode":"80004",
    "sg:province":"CO",
    "wof:name":"PC Guru Inc",
    "wof:placetype":"venue"
},
  "geometry": {"coordinates":[-105.126379,39.819695],"type":"Point"}
}