{
  "type": "Feature",
  "properties": {
    "addr:full":"312 Weant Blvd Carbondale CO 81623",
    "addr:housenumber":"312",
    "addr:postcode":"81623",
    "addr:street":"Weant Blvd",
    "iso:country":"US",
    "sg:address":"312 Weant Blvd",
    "sg:city":"Carbondale",
    "sg:classifiers":[
        {
            "category":"Building & Trades",
            "subcategory":"Construction",
            "type":"Services"
        }
    ],
    "sg:phone":"+1 970 963 2003",
    "sg:postcode":"81623",
    "sg:province":"CO",
    "sg:tags":[
        "general",
        "contractor"
    ],
    "wof:name":"Norton Construction Svc",
    "wof:placetype":"venue"
},
  "geometry": {"coordinates":[-107.212479,39.397883],"type":"Point"}
}