{
  "type": "Feature",
  "properties": {
    "addr:full":"538 Olathe St Ste F Aurora CO 80011",
    "addr:housenumber":"538",
    "addr:postcode":"80011",
    "addr:street":"Olathe St Ste F",
    "iso:country":"US",
    "sg:address":"538 Olathe St Ste F",
    "sg:city":"Aurora",
    "sg:classifiers":[
        {
            "category":"Autos & Motor Vehicles",
            "subcategory":"Auto Supplies",
            "type":"Retail Goods"
        },
        {
            "category":"Retail",
            "subcategory":"Auto Repair",
            "type":"Services"
        }
    ],
    "sg:phone":"+1 303 343 6333",
    "sg:postcode":"80011",
    "sg:province":"CO",
    "sg:tags":[
        "body",
        "repairing",
        "automobile",
        "accessory",
        "part",
        "brake",
        "painting"
    ],
    "wof:name":"Aurora Family Auto",
    "wof:placetype":"venue"
},
  "geometry": {"coordinates":[-104.79312,39.724635],"type":"Point"}
}