{
  "type": "Feature",
  "properties": {
    "addr:full":"14304 E Tennessee Ave Aurora CO 80012",
    "addr:housenumber":"14304",
    "addr:postcode":"80012",
    "addr:street":"E Tennessee Ave",
    "iso:country":"US",
    "sg:address":"14304 E Tennessee Ave",
    "sg:city":"Aurora",
    "sg:classifiers":[
        {
            "category":"Real Estate",
            "subcategory":"Real Estate Operator",
            "type":"Services"
        }
    ],
    "sg:phone":"+1 303 337 5301",
    "sg:postcode":"80012",
    "sg:province":"CO",
    "sg:tags":[
        "building",
        "apartment"
    ],
    "wof:name":"Four Horizons Apartments",
    "wof:placetype":"venue"
},
  "geometry": {"coordinates":[-104.822793,39.699138],"type":"Point"}
}