{
  "type": "Feature",
  "properties": {
    "iso:country":"US",
    "sg:address":"5630 S Curtice St",
    "sg:city":"Littleton",
    "sg:classifiers":[
        {
            "category":"Social Services",
            "subcategory":"Adult Care",
            "type":"Services"
        },
        {
            "category":"Building & Trades",
            "subcategory":"Construction",
            "type":"Services"
        }
    ],
    "sg:phone":"+1 303 795 2061",
    "sg:postcode":"80120",
    "sg:province":"CO",
    "sg:tags":[
        "house",
        "organization",
        "religious",
        "sch",
        "residential"
    ],
    "wof:name":"Good Shepherd Lutheran Hm of W",
    "wof:placetype":"venue"
},
  "geometry": {"coordinates":[-105.01832400000001,39.614218],"type":"Point"}
}