{
  "type": "Feature",
  "properties": {
    "addr:full":"71 Sipprelle Dr Parachute CO 81635",
    "addr:housenumber":"71",
    "addr:postcode":"81635",
    "addr:street":"Sipprelle Dr",
    "iso:country":"US",
    "sg:address":"71 Sipprelle Dr",
    "sg:city":"Parachute",
    "sg:classifiers":[
        {
            "category":"Banks & Credit Unions",
            "subcategory":"Bank",
            "type":"Services"
        }
    ],
    "sg:phone":"+1 970 285 7848",
    "sg:postcode":"81635",
    "sg:province":"CO",
    "wof:name":"Wells Fargo Bank",
    "wof:placetype":"venue"
},
  "geometry": {"coordinates":[-108.023308,39.44487],"type":"Point"}
}