{
  "type": "Feature",
  "properties": {
    "iso:country":"US",
    "sg:address":"23450 US Hwy 160",
    "sg:city":"Walsenburg",
    "sg:classifiers":[
        {
            "category":"Health Services",
            "subcategory":"Clinic",
            "type":"Services"
        }
    ],
    "sg:phone":"+1 719 738 4864",
    "sg:postcode":"81089",
    "sg:province":"CO",
    "sg:tags":[
        "kidney",
        "dialysis",
        "center"
    ],
    "wof:name":"Qualicenters Walsenburg Inc",
    "wof:placetype":"venue"
},
  "geometry": {"coordinates":[-104.81908300000001,37.607823],"type":"Point"}
}