{
  "type": "Feature",
  "properties": {
    "iso:country":"US",
    "sg:address":"1580 Lincoln St Ste 1180",
    "sg:city":"Denver",
    "sg:classifiers":[
        {
            "category":"Communications",
            "subcategory":"Film & Video Production",
            "type":"Services"
        }
    ],
    "sg:phone":"+1 303 863 8200",
    "sg:postcode":"80203",
    "sg:province":"CO",
    "sg:tags":[
        "services-commercial"
    ],
    "wof:name":"Laird Group The Productions",
    "wof:placetype":"venue"
},
  "geometry": {"coordinates":[-104.986131,39.741374],"type":"Point"}
}