{
  "type": "Feature",
  "properties": {
    "addr:full":"3685 Cherry Creek North Dr Denver CO 80209",
    "addr:housenumber":"3685",
    "addr:postcode":"80209",
    "addr:street":"Cherry Creek North Dr",
    "iso:country":"US",
    "sg:address":"3685 Cherry Creek North Dr",
    "sg:city":"Denver",
    "sg:classifiers":[
        {
            "category":"Health Services",
            "subcategory":"Doctor",
            "type":"Services"
        }
    ],
    "sg:phone":"+1 303 394 2421",
    "sg:postcode":"80209",
    "sg:province":"CO",
    "sg:tags":[
        "clinic"
    ],
    "wof:name":"Work Well",
    "wof:placetype":"venue"
},
  "geometry": {"coordinates":[-104.941548,39.707402],"type":"Point"}
}