{
  "type": "Feature",
  "properties": {
    "iso:country":"US",
    "sg:address":"925 T Ave",
    "sg:city":"Limon",
    "sg:classifiers":[
        {
            "category":"Travel",
            "subcategory":"Hotels & Motels",
            "type":"Entertainment"
        }
    ],
    "sg:phone":"+1 719 775 0277",
    "sg:postcode":"80828",
    "sg:province":"CO",
    "sg:website":"www.bestwestern.com",
    "wof:name":"Best Western Limon Inn",
    "wof:placetype":"venue"
},
  "geometry": {"coordinates":[-103.710337,39.272646],"type":"Point"}
}