{
  "type": "Feature",
  "properties": {
    "iso:country":"US",
    "sg:address":"7366 S Platte Canyon Dr",
    "sg:city":"Littleton",
    "sg:classifiers":[
        {
            "category":"Real Estate",
            "subcategory":"Real Estate Agent",
            "type":"Services"
        }
    ],
    "sg:phone":"+1 303 979 4904",
    "sg:postcode":"80128",
    "sg:province":"CO",
    "wof:name":"Kiddy Real Est Inc",
    "wof:placetype":"venue"
},
  "geometry": {"coordinates":[-105.05270299999999,39.582123],"type":"Point"}
}