{
  "type": "Feature",
  "properties": {
    "iso:country":"US",
    "sg:address":"2909 del Mar Cir",
    "sg:city":"Colorado Springs",
    "sg:classifiers":[
        {
            "category":"Freight",
            "type":"Transportation"
        }
    ],
    "sg:phone":"+1 719 448 9585",
    "sg:postcode":"80910",
    "sg:province":"CO",
    "sg:tags":[
        "provides",
        "gravel",
        "rubbish",
        "asphalt",
        "hauling"
    ],
    "wof:name":"DUMP Trucking",
    "wof:placetype":"venue"
},
  "geometry": {"coordinates":[-104.770731,38.808201],"type":"Point"}
}