{
  "type": "Feature",
  "properties": {
    "iso:country":"US",
    "sg:address":"499 Federal Boulevard",
    "sg:city":"Denver",
    "sg:classifiers":[
        {
            "category":"Shopping",
            "subcategory":"Clothing, Apparel, & Fashions",
            "type":"Retail Goods"
        }
    ],
    "sg:phone":"+1 303 922 0500",
    "sg:postcode":"80204",
    "sg:province":"CO",
    "sg:tags":[
        "accessory",
        "clothing",
        "women's"
    ],
    "wof:name":"Bbb Mart Fine Jewelery and Clothing",
    "wof:placetype":"venue"
},
  "geometry": {"coordinates":[-105.036173,39.725014],"type":"Point"}
}