{
  "type": "Feature",
  "properties": {
    "iso:country":"US",
    "sg:address":"9300 Smith Road",
    "sg:city":"Denver",
    "sg:classifiers":[
        {
            "category":"Building & Trades",
            "subcategory":"Plumbing",
            "type":"Services"
        }
    ],
    "sg:phone":"+1 303 576 9696",
    "sg:postcode":"80207",
    "sg:province":"CO",
    "wof:name":"Performance Building Systems",
    "wof:placetype":"venue"
},
  "geometry": {"coordinates":[-104.88643999999999,39.769952],"type":"Point"}
}