{
  "type": "Feature",
  "properties": {
    "iso:country":"US",
    "sg:address":"13086 Co Rd 30",
    "sg:city":"Haxtun",
    "sg:phone":"+1 970 774 6571",
    "sg:postcode":"80731",
    "sg:province":"CO",
    "sg:tags":[
        "farm",
        "corn",
        "wheat"
    ],
    "wof:name":"Legg Farms",
    "wof:placetype":"venue"
},
  "geometry": {"coordinates":[-102.534122,40.642504],"type":"Point"}
}