{
  "type": "Feature",
  "properties": {
    "addr:full":"9102 Co Rd 44 Milliken CO 80543",
    "addr:housenumber":"9102;44",
    "addr:postcode":"80543",
    "addr:street":"Co Rd",
    "iso:country":"US",
    "sg:address":"9102 Co Rd 44",
    "sg:city":"Milliken",
    "sg:classifiers":[
        {
            "category":"Real Estate",
            "subcategory":"Real Estate Operator",
            "type":"Services"
        }
    ],
    "sg:phone":"+1 970 587 2131",
    "sg:postcode":"80543",
    "sg:province":"CO",
    "sg:tags":[
        "property",
        "lessor"
    ],
    "wof:name":"Roger Dutton",
    "wof:placetype":"venue"
},
  "geometry": {"coordinates":[-104.884973,40.305277],"type":"Point"}
}