{
  "type": "Feature",
  "properties": {
    "addr:full":"605 N Main St Lamar CO 81052",
    "addr:housenumber":"605",
    "addr:postcode":"81052",
    "addr:street":"N Main St",
    "iso:country":"US",
    "sg:address":"605 N Main St",
    "sg:city":"Lamar",
    "sg:classifiers":[
        {
            "category":"Autos & Motor Vehicles",
            "subcategory":"Fuel & Gas Station",
            "type":"Retail Goods"
        }
    ],
    "sg:phone":"+1 719 336 5202",
    "sg:postcode":"81052",
    "sg:province":"CO",
    "sg:tags":[
        "convenience",
        "gift",
        "store"
    ],
    "wof:name":"Loves Trvl Stops Cntry Stores",
    "wof:placetype":"venue"
},
  "geometry": {"coordinates":[-102.619916,38.096208],"type":"Point"}
}