{
  "type": "Feature",
  "properties": {
    "addr:full":"309 S Main St Yuma CO 80759",
    "addr:housenumber":"309",
    "addr:postcode":"80759",
    "addr:street":"S Main St",
    "iso:country":"US",
    "sg:address":"309 S Main St",
    "sg:city":"Yuma",
    "sg:classifiers":[
        {
            "category":"Retail",
            "subcategory":"Auto Repair",
            "type":"Services"
        }
    ],
    "sg:phone":"+1 970 848 5418",
    "sg:postcode":"80759",
    "sg:province":"CO",
    "sg:tags":[
        "machine",
        "automobile",
        "shop"
    ],
    "wof:name":"Yuma County Auto Supply",
    "wof:placetype":"venue"
},
  "geometry": {"coordinates":[-102.72371699999999,40.123216],"type":"Point"}
}