{
  "type": "Feature",
  "properties": {
    "iso:country":"US",
    "sg:address":"424 Flicker Ave",
    "sg:city":"Longmont",
    "sg:classifiers":[
        {
            "category":"Building & Trades",
            "subcategory":"Construction",
            "type":"Services"
        }
    ],
    "sg:phone":"+1 303 684 6437",
    "sg:postcode":"80501",
    "sg:province":"CO",
    "sg:tags":[
        "carpentry",
        "contractor"
    ],
    "wof:name":"Harveys Homecare",
    "wof:placetype":"venue"
},
  "geometry": {"coordinates":[-105.100255,40.144684],"type":"Point"}
}