{
  "type": "Feature",
  "properties": {
    "iso:country":"US",
    "sg:address":"1140 US Hwy 287",
    "sg:city":"Broomfield",
    "sg:classifiers":[
        {
            "category":"Retail",
            "subcategory":"Laundry & Dry Cleaning",
            "type":"Services"
        }
    ],
    "sg:phone":"+1 303 404 8917",
    "sg:postcode":"80020",
    "sg:province":"CO",
    "sg:tags":[
        "cleaners"
    ],
    "sg:website":"www.heritagecleaners.com",
    "wof:name":"Heritage Cleaners",
    "wof:placetype":"venue"
},
  "geometry": {"coordinates":[-105.090929,39.933959],"type":"Point"}
}