{
  "type": "Feature",
  "properties": {
    "addr:full":"311 H St Salida CO 81201",
    "addr:housenumber":"311",
    "addr:postcode":"81201",
    "addr:street":"H St",
    "iso:country":"US",
    "sg:address":"311 H St",
    "sg:city":"Salida",
    "sg:classifiers":[
        {
            "category":"Manufacturing",
            "subcategory":"Tools & Machinery",
            "type":"Manufacturing & Wholesale Goods"
        }
    ],
    "sg:phone":"+1 719 539 7888",
    "sg:postcode":"81201",
    "sg:province":"CO",
    "sg:tags":[
        "machine",
        "shop"
    ],
    "wof:name":"Wheel Works",
    "wof:placetype":"venue"
},
  "geometry": {"coordinates":[-105.99557,38.535754],"type":"Point"}
}