{
  "type": "Feature",
  "properties": {
    "addr:full":"2751 E Stanford Dr Englewood CO 80113",
    "addr:housenumber":"2751",
    "addr:postcode":"80113",
    "addr:street":"E Stanford Dr",
    "iso:country":"US",
    "sg:address":"2751 E Stanford Dr",
    "sg:city":"Englewood",
    "sg:classifiers":[
        {
            "category":"Professional",
            "subcategory":"Lawyer & Legal Services",
            "type":"Services"
        }
    ],
    "sg:phone":"+1 303 762 8030",
    "sg:postcode":"80113",
    "sg:province":"CO",
    "sg:tags":[
        "attorney"
    ],
    "wof:name":"Robert J Flynn",
    "wof:placetype":"venue"
},
  "geometry": {"coordinates":[-104.952708,39.632031],"type":"Point"}
}