{
  "type": "Feature",
  "properties": {
    "iso:country":"US",
    "sg:address":"326 Hwy 133",
    "sg:city":"Carbondale",
    "sg:classifiers":[
        {
            "category":"Utilities",
            "subcategory":"Telephone",
            "type":"Services"
        }
    ],
    "sg:phone":"+1 970 963 7333",
    "sg:postcode":"81623",
    "sg:province":"CO",
    "sg:tags":[
        "communications",
        "retrieval",
        "information"
    ],
    "wof:name":"Onteecom",
    "wof:placetype":"venue"
},
  "geometry": {"coordinates":[-107.221408,39.410094],"type":"Point"}
}