{
  "type": "Feature",
  "properties": {
    "addr:full":"4365 E 74th Ave Commerce City CO 80022",
    "addr:housenumber":"4365",
    "addr:postcode":"80022",
    "addr:street":"E 74Th Ave",
    "iso:country":"US",
    "sg:address":"4365 E 74th Ave",
    "sg:city":"Commerce City",
    "sg:classifiers":[
        {
            "category":"Wholesale",
            "subcategory":"Construction Materials",
            "type":"Manufacturing & Wholesale Goods"
        }
    ],
    "sg:phone":"+1 303 287 5535",
    "sg:postcode":"80022",
    "sg:province":"CO",
    "sg:tags":[
        "wooden",
        "pallet"
    ],
    "wof:name":"Austin",
    "wof:placetype":"venue"
},
  "geometry": {"coordinates":[-104.93754800000001,39.830937],"type":"Point"}
}