{
  "type": "Feature",
  "properties": {
    "addr:full":"1107 N Academy Blvd Colorado Springs CO 80909",
    "addr:housenumber":"1107",
    "addr:postcode":"80909",
    "addr:street":"N Academy Blvd",
    "iso:country":"US",
    "sg:address":"1107 N Academy Blvd",
    "sg:city":"Colorado Springs",
    "sg:classifiers":[
        {
            "category":"Restaurant",
            "type":"Food & Drink"
        }
    ],
    "sg:menulink":"http://www.allmenus.com/co/colorado-springs/100584-captain-ds-seafood/menu/",
    "sg:phone":"+1 719 591 6320",
    "sg:postcode":"80909",
    "sg:province":"CO",
    "sg:tags":[
        "seafood",
        "american"
    ],
    "wof:name":"Captain D's Seafood",
    "wof:placetype":"venue"
},
  "geometry": {"coordinates":[-104.75680800000001,38.848179],"type":"Point"}
}