{
  "type": "Feature",
  "properties": {
    "addr:full":"33633 Hwy 550 Durango CO 81301",
    "addr:housenumber":"33633",
    "addr:postcode":"co 81301",
    "addr:street":"Hwy 550",
    "iso:country":"US",
    "sg:address":"33633 Hwy 550",
    "sg:city":"Durango",
    "sg:classifiers":[
        {
            "category":"Wholesale",
            "subcategory":"Groceries",
            "type":"Manufacturing & Wholesale Goods"
        }
    ],
    "sg:phone":"+1 970 247 1474",
    "sg:postcode":"81301",
    "sg:province":"CO",
    "sg:tags":[
        "honey"
    ],
    "sg:website":"www.honeyvillecolorado.com",
    "wof:name":"Honeyville Honey Farm",
    "wof:placetype":"venue"
},
  "geometry": {"coordinates":[-107.82261800000001,37.423492],"type":"Point"}
}