{
  "type": "Feature",
  "properties": {
    "iso:country":"US",
    "sg:address":"2764 Compass Dr",
    "sg:city":"Grand Junction",
    "sg:classifiers":[
        {
            "category":"Restaurant",
            "type":"Food & Drink"
        }
    ],
    "sg:phone":"+1 970 245 0898",
    "sg:postcode":"81506",
    "sg:province":"CO",
    "sg:tags":[
        "eating"
    ],
    "wof:name":"Taco Bell",
    "wof:placetype":"venue"
},
  "geometry": {"coordinates":[-108.54051800000001,39.116436],"type":"Point"}
}