{
  "type": "Feature",
  "properties": {
    "addr:full":"516 Main St Walsenburg CO 81089",
    "addr:housenumber":"516",
    "addr:postcode":"81089",
    "addr:street":"Main St",
    "iso:country":"US",
    "sg:address":"516 Main St",
    "sg:city":"Walsenburg",
    "sg:classifiers":[
        {
            "category":"Professional",
            "subcategory":"Advertising",
            "type":"Services"
        }
    ],
    "sg:phone":"+1 719 738 3636",
    "sg:postcode":"81089",
    "sg:province":"CO",
    "sg:website":"www.kspk.com",
    "wof:name":"KSPK",
    "wof:placetype":"venue"
},
  "geometry": {"coordinates":[-104.78125799999999,37.624521],"type":"Point"}
}