{
  "type": "Feature",
  "properties": {
    "addr:full":"2764 Landers Dr Larkspur CO 80118",
    "addr:housenumber":"2764",
    "addr:postcode":"80118",
    "addr:street":"Landers Dr",
    "iso:country":"US",
    "sg:address":"2764 Landers Dr",
    "sg:city":"Larkspur",
    "sg:classifiers":[
        {
            "category":"Building & Trades",
            "subcategory":"Construction",
            "type":"Services"
        }
    ],
    "sg:phone":"+1 719 481 2485",
    "sg:postcode":"80118",
    "sg:province":"CO",
    "sg:tags":[
        "contractor"
    ],
    "wof:name":"Tony L Walden Roofing",
    "wof:placetype":"venue"
},
  "geometry": {"coordinates":[-104.83302,39.137798],"type":"Point"}
}