{
  "type": "Feature",
  "properties": {
    "iso:country":"US",
    "sg:address":"14190 E Jewell Ave Ste 6",
    "sg:city":"Aurora",
    "sg:classifiers":[
        {
            "category":"Place Of Worship",
            "subcategory":"Church",
            "type":"Public Place"
        },
        {
            "category":"Place Of Worship",
            "type":"Public Place"
        }
    ],
    "sg:phone":"+1 303 337 6951",
    "sg:postcode":"80012",
    "sg:province":"CO",
    "sg:tags":[
        "churches-interdenominational",
        "denomination",
        "churches-various",
        "churches-non-denominational"
    ],
    "wof:name":"Christian Cornerstone Church",
    "wof:placetype":"venue"
},
  "geometry": {"coordinates":[-104.824852,39.68211],"type":"Point"}
}