{
  "type": "Feature",
  "properties": {
    "addr:full":"32681 E Colfax Ave Watkins CO 80137",
    "addr:housenumber":"32681",
    "addr:postcode":"80137",
    "addr:street":"E Colfax Ave",
    "iso:country":"US",
    "sg:address":"32681 E Colfax Ave",
    "sg:city":"Watkins",
    "sg:classifiers":[
        {
            "category":"Travel",
            "subcategory":"Hotels & Motels",
            "type":"Entertainment"
        }
    ],
    "sg:phone":"+1 303 261 9650",
    "sg:postcode":"80137",
    "sg:province":"CO",
    "sg:tags":[
        "operation",
        "grocery"
    ],
    "wof:name":"Country Store",
    "wof:placetype":"venue"
},
  "geometry": {"coordinates":[-104.605039,39.744051],"type":"Point"}
}