{
  "type": "Feature",
  "properties": {
    "iso:country":"US",
    "sg:address":"10303 E Dry Creek Rd",
    "sg:city":"Englewood",
    "sg:classifiers":[
        {
            "category":"Real Estate",
            "subcategory":"Real Estate Agent",
            "type":"Services"
        }
    ],
    "sg:phone":"+1 303 792 2500",
    "sg:postcode":"80112",
    "sg:province":"CO",
    "wof:name":"Frontier Gmac Real Estate",
    "wof:placetype":"venue"
},
  "geometry": {"coordinates":[-104.871696,39.580574],"type":"Point"}
}