{
  "type": "Feature",
  "properties": {
    "iso:country":"US",
    "sg:address":"2323 W Mulberry Pl",
    "sg:city":"Denver",
    "sg:classifiers":[
        {
            "category":"Wholesale",
            "subcategory":"Auto Parts",
            "type":"Manufacturing & Wholesale Goods"
        }
    ],
    "sg:phone":"+1 303 825 1049",
    "sg:postcode":"80204",
    "sg:province":"CO",
    "sg:tags":[
        "automobile",
        "rebuilt",
        "used",
        "new"
    ],
    "sg:website":"www.stadiumautoparts.com",
    "wof:name":"Stadium Auto & Truck Parts",
    "wof:placetype":"venue"
},
  "geometry": {"coordinates":[-105.01520499999999,39.731571],"type":"Point"}
}