{
  "type": "Feature",
  "properties": {
    "iso:country":"US",
    "sg:address":"211 Colorado Ave",
    "sg:city":"La Junta",
    "sg:classifiers":[
        {
            "category":"Shopping",
            "subcategory":"Gifts & Souvenirs",
            "type":"Retail Goods"
        }
    ],
    "sg:phone":"+1 719 384 7551",
    "sg:postcode":"81050",
    "sg:province":"CO",
    "wof:name":"10000 Billlages",
    "wof:placetype":"venue"
},
  "geometry": {"coordinates":[-103.543042,37.98686],"type":"Point"}
}