{
  "type": "Feature",
  "properties": {
    "addr:full":"8120 Sheridan Blvd Arvada CO 80003",
    "addr:housenumber":"8120",
    "addr:postcode":"80003",
    "addr:street":"Sheridan Blvd",
    "iso:country":"US",
    "sg:address":"8120 Sheridan Blvd",
    "sg:city":"Arvada",
    "sg:classifiers":[
        {
            "category":"Social Services",
            "type":"Services"
        }
    ],
    "sg:phone":"+1 303 657 9691",
    "sg:postcode":"80003",
    "sg:province":"CO",
    "sg:tags":[
        "counselor",
        "marriage",
        "family"
    ],
    "wof:name":"Lillie Lee",
    "wof:placetype":"venue"
},
  "geometry": {"coordinates":[-105.053309,39.844357],"type":"Point"}
}