{
  "type": "Feature",
  "properties": {
    "iso:country":"US",
    "sg:address":"2831 Tecumseh Rd",
    "sg:city":"Colorado Springs",
    "sg:classifiers":[
        {
            "category":"Home & Garden",
            "subcategory":"Furniture",
            "type":"Retail Goods"
        }
    ],
    "sg:phone":"+1 719 599 7321",
    "sg:postcode":"80920",
    "sg:province":"CO",
    "wof:name":"New Look Furniture",
    "wof:placetype":"venue"
},
  "geometry": {"coordinates":[-104.770399,38.940176],"type":"Point"}
}