{
  "type": "Feature",
  "properties": {
    "addr:full":"6520 Wadsworth Blvd Arvada CO 80003",
    "addr:housenumber":"6520",
    "addr:postcode":"80003",
    "addr:street":"Wadsworth Blvd",
    "iso:country":"US",
    "sg:address":"6520 Wadsworth Blvd",
    "sg:city":"Arvada",
    "sg:classifiers":[
        {
            "category":"Recreation",
            "type":"Entertainment"
        }
    ],
    "sg:phone":"+1 303 421 2932",
    "sg:postcode":"80003",
    "sg:province":"CO",
    "sg:tags":[
        "bingo",
        "game"
    ],
    "wof:name":"Bingo Co",
    "wof:placetype":"venue"
},
  "geometry": {"coordinates":[-105.081277,39.815048],"type":"Point"}
}