{
  "type": "Feature",
  "properties": {
    "iso:country":"US",
    "sg:address":"1400 S Collyer St",
    "sg:city":"Longmont",
    "sg:classifiers":[
        {
            "category":"Professional",
            "type":"Services"
        }
    ],
    "sg:phone":"+1 303 684 9662",
    "sg:postcode":"80501",
    "sg:province":"CO",
    "wof:name":"Janet A Vanthuyne",
    "wof:placetype":"venue"
},
  "geometry": {"coordinates":[-105.098214,40.138062],"type":"Point"}
}