{
  "type": "Feature",
  "properties": {
    "addr:full":"32156 Castle Ct Evergreen CO 80439",
    "addr:housenumber":"32156",
    "addr:postcode":"80439",
    "addr:street":"Castle Ct",
    "iso:country":"US",
    "sg:address":"32156 Castle Ct",
    "sg:city":"Evergreen",
    "sg:classifiers":[
        {
            "category":"Professional",
            "type":"Services"
        }
    ],
    "sg:phone":"+1 303 679 1852",
    "sg:postcode":"80439",
    "sg:province":"CO",
    "sg:tags":[
        "establishment"
    ],
    "wof:name":"Parkway Place Assoc",
    "wof:placetype":"venue"
},
  "geometry": {"coordinates":[-105.363209,39.681839],"type":"Point"}
}