{
  "type": "Feature",
  "properties": {
    "iso:country":"US",
    "sg:address":"1170 S Sheridan Blvd",
    "sg:city":"Denver",
    "sg:classifiers":[
        {
            "category":"Shopping",
            "subcategory":"Mobile Phones",
            "type":"Retail Goods"
        }
    ],
    "sg:phone":"+1 303 935 1006",
    "sg:postcode":"80232",
    "sg:province":"CO",
    "wof:name":"Unlimited Cellular",
    "wof:placetype":"venue"
},
  "geometry": {"coordinates":[-105.05300099999999,39.695499],"type":"Point"}
}