{
  "type": "Feature",
  "properties": {
    "iso:country":"US",
    "sg:address":"10726 W Berry Dr",
    "sg:city":"Littleton",
    "sg:classifiers":[
        {
            "category":"Building & Trades",
            "subcategory":"Construction",
            "type":"Services"
        }
    ],
    "sg:phone":"+1 303 773 3909",
    "sg:postcode":"80127",
    "sg:province":"CO",
    "sg:tags":[
        "contractor"
    ],
    "wof:name":"Ja Roofing Inc",
    "wof:placetype":"venue"
},
  "geometry": {"coordinates":[-105.11899099999999,39.615277],"type":"Point"}
}