{
  "type": "Feature",
  "properties": {
    "iso:country":"US",
    "sg:address":"950 17th St Ste 1800",
    "sg:city":"Denver",
    "sg:classifiers":[
        {
            "category":"Health Services",
            "subcategory":"Clinic",
            "type":"Services"
        }
    ],
    "sg:phone":"+1 303 346 1670",
    "sg:postcode":"80202",
    "sg:province":"CO",
    "sg:tags":[
        "counseling",
        "mental"
    ],
    "sg:website":"divorcemediationdenvercolorado.com/",
    "wof:name":"Family Mediation Services",
    "wof:placetype":"venue"
},
  "geometry": {"coordinates":[-104.993784,39.747652],"type":"Point"}
}