{
  "type": "Feature",
  "properties": {
    "iso:country":"US",
    "sg:address":"106 S Park Sq",
    "sg:city":"Fruita",
    "sg:classifiers":[
        {
            "category":"Food & Beverages",
            "subcategory":"Groceries & Convenience Stores",
            "type":"Retail Goods"
        }
    ],
    "sg:phone":"+1 970 858 4327",
    "sg:postcode":"81521",
    "sg:province":"CO",
    "wof:name":"Go-Fer Foods",
    "wof:placetype":"venue"
},
  "geometry": {"coordinates":[-108.73369,39.158416],"type":"Point"}
}