{
  "type": "Feature",
  "properties": {
    "addr:full":"1221 Auraria Pkwy Denver CO 80204",
    "addr:housenumber":"1221",
    "addr:postcode":"80204",
    "addr:street":"Auraria Pkwy",
    "iso:country":"US",
    "sg:address":"1221 Auraria Pkwy",
    "sg:city":"Denver",
    "sg:classifiers":[
        {
            "category":"Professional",
            "subcategory":"Computer Services",
            "type":"Services"
        }
    ],
    "sg:phone":"+1 303 390 2430",
    "sg:postcode":"80204",
    "sg:province":"CO",
    "sg:tags":[
        "prepackaged",
        "software"
    ],
    "wof:name":"Alliance Data Systems Corp",
    "wof:placetype":"venue"
},
  "geometry": {"coordinates":[-105.003405,39.748515],"type":"Point"}
}