{
  "type": "Feature",
  "properties": {
    "iso:country":"US",
    "sg:address":"588 US Hwy 287",
    "sg:city":"Lafayette",
    "sg:classifiers":[
        {
            "category":"Shopping",
            "type":"Retail Goods"
        }
    ],
    "sg:phone":"+1 303 443 2772",
    "sg:postcode":"80026",
    "sg:province":"CO",
    "sg:tags":[
        "hearing",
        "equipment",
        "supply",
        "impaired"
    ],
    "wof:name":"Boulder Valley Hearing Ctr",
    "wof:placetype":"venue"
},
  "geometry": {"coordinates":[-105.09068600000001,39.978963],"type":"Point"}
}