{
  "type": "Feature",
  "properties": {
    "iso:country":"US",
    "sg:address":"7202 S Robb St",
    "sg:city":"Littleton",
    "sg:classifiers":[
        {
            "category":"Shopping",
            "subcategory":"Bicycles & Sporting Goods",
            "type":"Retail Goods"
        }
    ],
    "sg:phone":"+1 303 972 3121",
    "sg:postcode":"80127",
    "sg:province":"CO",
    "wof:name":"M & M Tasmanian Devil",
    "wof:placetype":"venue"
},
  "geometry": {"coordinates":[-105.127112,39.585971],"type":"Point"}
}