{
  "type": "Feature",
  "properties": {
    "addr:full":"2919 Valmont Rd Boulder CO 80301",
    "addr:housenumber":"2919",
    "addr:postcode":"80301",
    "addr:street":"Valmont Rd",
    "iso:country":"US",
    "sg:address":"2919 Valmont Rd",
    "sg:city":"Boulder",
    "sg:classifiers":[
        {
            "category":"Health Services",
            "subcategory":"Doctor",
            "type":"Services"
        }
    ],
    "sg:phone":"+1 303 449 5242",
    "sg:postcode":"80301",
    "sg:province":"CO",
    "sg:tags":[
        "dentist"
    ],
    "wof:name":"Robert L Holden DDS",
    "wof:placetype":"venue"
},
  "geometry": {"coordinates":[-105.254008,40.029263],"type":"Point"}
}