{
  "type": "Feature",
  "properties": {
    "addr:full":"5602 Co Rd 15 Fort Lupton CO 80621",
    "addr:housenumber":"5602;15",
    "addr:postcode":"80621",
    "addr:street":"Co Rd;Fort Lupton",
    "iso:country":"US",
    "sg:address":"5602 Co Rd 15",
    "sg:city":"Fort Lupton",
    "sg:classifiers":[
        {
            "category":"Building & Trades",
            "subcategory":"Construction",
            "type":"Services"
        }
    ],
    "sg:phone":"+1 303 833 0842",
    "sg:postcode":"80621",
    "sg:province":"CO",
    "wof:name":"R & J Construction",
    "wof:placetype":"venue"
},
  "geometry": {"coordinates":[-104.92397099999999,40.080401],"type":"Point"}
}