{
  "type": "Feature",
  "properties": {
    "addr:full":"2736 W 23rd St Greeley CO 80634",
    "addr:housenumber":"2736",
    "addr:postcode":"80634",
    "addr:street":"W 23Rd St",
    "iso:country":"US",
    "sg:address":"2736 W 23rd St",
    "sg:city":"Greeley",
    "sg:classifiers":[
        {
            "category":"Building & Trades",
            "subcategory":"Construction",
            "type":"Services"
        }
    ],
    "sg:phone":"+1 970 330 7881",
    "sg:postcode":"80634",
    "sg:province":"CO",
    "sg:tags":[
        "contractor"
    ],
    "wof:name":"Slaughter Roofing",
    "wof:placetype":"venue"
},
  "geometry": {"coordinates":[-104.72739,40.399149],"type":"Point"}
}