{
  "type": "Feature",
  "properties": {
    "iso:country":"US",
    "sg:address":"3000 E 1st Ave Unit 11",
    "sg:city":"Denver",
    "sg:classifiers":[
        {
            "category":"Personal",
            "subcategory":"Day Spa",
            "type":"Services"
        }
    ],
    "sg:phone":"+1 303 333 0480",
    "sg:postcode":"80206",
    "sg:province":"CO",
    "wof:name":"Secret of Youth",
    "wof:placetype":"venue"
},
  "geometry": {"coordinates":[-104.953288,39.717893],"type":"Point"}
}