{
  "type": "Feature",
  "properties": {
    "iso:country":"US",
    "sg:address":"14 Wedge Way",
    "sg:city":"Littleton",
    "sg:classifiers":[
        {
            "category":"Wholesale",
            "subcategory":"Toys & Hobbies",
            "type":"Manufacturing & Wholesale Goods"
        },
        {
            "category":"Wholesale",
            "subcategory":"Apparel",
            "type":"Manufacturing & Wholesale Goods"
        }
    ],
    "sg:phone":"+1 303 297 8895",
    "sg:postcode":"80123",
    "sg:province":"CO",
    "sg:tags":[
        "wholesaler",
        "outdoor",
        "clothing"
    ],
    "wof:name":"The Archibald Group Inc",
    "wof:placetype":"venue"
},
  "geometry": {"coordinates":[-105.03556,39.59821],"type":"Point"}
}