{
  "type": "Feature",
  "properties": {
    "iso:country":"US",
    "sg:address":"50 S Steele Street Suite 377",
    "sg:city":"Denver",
    "sg:classifiers":[
        {
            "category":"Building & Trades",
            "subcategory":"Construction",
            "type":"Services"
        }
    ],
    "sg:phone":"+1 303 394 1851",
    "sg:postcode":"80209",
    "sg:province":"CO",
    "sg:tags":[
        "contractor"
    ],
    "wof:name":"Chaparral Homes",
    "wof:placetype":"venue"
},
  "geometry": {"coordinates":[-104.949752,39.715458],"type":"Point"}
}