{
  "type": "Feature",
  "properties": {
    "iso:country":"US",
    "sg:address":"15590 Hwy 392",
    "sg:city":"Greeley",
    "sg:classifiers":[
        {
            "category":"Building & Trades",
            "subcategory":"Construction",
            "type":"Services"
        }
    ],
    "sg:phone":"+1 970 224 1171",
    "sg:postcode":"80631",
    "sg:province":"CO",
    "sg:tags":[
        "designer",
        "dealer",
        "pool",
        "swimming"
    ],
    "wof:name":"Dolphin Pools",
    "wof:placetype":"venue"
},
  "geometry": {"coordinates":[-104.754105,40.480707],"type":"Point"}
}