{
  "type": "Feature",
  "properties": {
    "addr:full":"4100 S Parker Rd Aurora CO 80014",
    "addr:housenumber":"4100",
    "addr:postcode":"80014",
    "addr:street":"S Parker Rd",
    "iso:country":"US",
    "sg:address":"4100 S Parker Rd",
    "sg:city":"Aurora",
    "sg:classifiers":[
        {
            "category":"Professional",
            "type":"Services"
        }
    ],
    "sg:phone":"+1 303 699 0528",
    "sg:postcode":"80014",
    "sg:province":"CO",
    "wof:name":"Sports Therapy",
    "wof:placetype":"venue"
},
  "geometry": {"coordinates":[-104.82885899999999,39.639607],"type":"Point"}
}