{
  "type": "Feature",
  "properties": {
    "addr:full":"1543 Wazee St Denver CO 80202",
    "addr:housenumber":"1543",
    "addr:postcode":"80202",
    "addr:street":"Wazee St",
    "iso:country":"US",
    "sg:address":"1543 Wazee St",
    "sg:city":"Denver",
    "sg:classifiers":[
        {
            "category":"Real Estate",
            "subcategory":"Real Estate Agent",
            "type":"Services"
        }
    ],
    "sg:phone":"+1 303 782 1620",
    "sg:postcode":"80202",
    "sg:province":"CO",
    "sg:website":"www.homesincolorado.com",
    "wof:name":"Re/Max Alliance",
    "wof:placetype":"venue"
},
  "geometry": {"coordinates":[-105.000534,39.750871],"type":"Point"}
}