{
  "type": "Feature",
  "properties": {
    "iso:country":"US",
    "sg:address":"2227 Canyon Blvd",
    "sg:city":"Boulder",
    "sg:classifiers":[
        {
            "category":"Real Estate",
            "subcategory":"Architect",
            "type":"Services"
        }
    ],
    "sg:phone":"+1 303 544 0209",
    "sg:postcode":"80302",
    "sg:province":"CO",
    "sg:website":"www.doerr.org",
    "wof:name":"Doerr.Org Architecture",
    "wof:placetype":"venue"
},
  "geometry": {"coordinates":[-105.26496299999999,40.017414],"type":"Point"}
}