{
  "type": "Feature",
  "properties": {
    "addr:full":"740 Cleveland Ave Loveland CO 80537",
    "addr:housenumber":"740",
    "addr:postcode":"80537",
    "addr:street":"Cleveland Ave",
    "iso:country":"US",
    "sg:address":"740 Cleveland Ave",
    "sg:city":"Loveland",
    "sg:classifiers":[
        {
            "category":"Banks & Credit Unions",
            "subcategory":"Investment Brokerage",
            "type":"Services"
        }
    ],
    "sg:phone":"+1 970 669 3397",
    "sg:postcode":"80537",
    "sg:province":"CO",
    "sg:tags":[
        "consultant",
        "planning",
        "financial"
    ],
    "wof:name":"Wilson Financial Svc",
    "wof:placetype":"venue"
},
  "geometry": {"coordinates":[-105.074426,40.39919],"type":"Point"}
}