{
  "type": "Feature",
  "properties": {
    "addr:full":"102 S Tejon St Colorado Springs CO 80903",
    "addr:housenumber":"102",
    "addr:postcode":"80903",
    "addr:street":"S Tejon St",
    "iso:country":"US",
    "sg:address":"102 S Tejon St",
    "sg:city":"Colorado Springs",
    "sg:classifiers":[
        {
            "category":"Organizations",
            "subcategory":"Non-profit Organization",
            "type":"Services"
        }
    ],
    "sg:phone":"+1 719 635 4800",
    "sg:postcode":"80903",
    "sg:province":"CO",
    "wof:name":"Counsel & Capital",
    "wof:placetype":"venue"
},
  "geometry": {"coordinates":[-104.823711,38.831557],"type":"Point"}
}