{
  "type": "Feature",
  "properties": {
    "iso:country":"US",
    "sg:address":"2821 S Parker Rd",
    "sg:city":"Aurora",
    "sg:classifiers":[
        {
            "category":"Banks & Credit Unions",
            "subcategory":"Bank",
            "type":"Services"
        }
    ],
    "sg:phone":"+1 303 751 7067",
    "sg:postcode":"80014",
    "sg:province":"CO",
    "sg:tags":[
        "loan",
        "real estate"
    ],
    "wof:name":"PHH Mortgage",
    "wof:placetype":"venue"
},
  "geometry": {"coordinates":[-104.859865,39.665249],"type":"Point"}
}