{
  "type": "Feature",
  "properties": {
    "iso:country":"US",
    "sg:address":"7800 Miller Dr",
    "sg:city":"Longmont",
    "sg:classifiers":[
        {
            "category":"Building & Trades",
            "subcategory":"Construction",
            "type":"Services"
        }
    ],
    "sg:phone":"+1 303 356 7712",
    "sg:postcode":"80504",
    "sg:province":"CO",
    "sg:tags":[
        "house"
    ],
    "wof:name":"Sakota Builders Inc",
    "wof:placetype":"venue"
},
  "geometry": {"coordinates":[-104.97232700000001,40.116186],"type":"Point"}
}