{
  "type": "Feature",
  "properties": {
    "iso:country":"US",
    "sg:address":"30920 Stagecoach Blvd",
    "sg:city":"Evergreen",
    "sg:classifiers":[
        {
            "category":"Government",
            "subcategory":"Office",
            "type":"Public Place"
        }
    ],
    "sg:phone":"+1 303 674 4112",
    "sg:postcode":"80439",
    "sg:province":"CO",
    "sg:tags":[
        "village"
    ],
    "sg:website":"www.evergreenmetrodistrict.com",
    "wof:name":"El Rancho Metropolitan Dist",
    "wof:placetype":"venue"
},
  "geometry": {"coordinates":[-105.346394,39.652812],"type":"Point"}
}