{
  "type": "Feature",
  "properties": {
    "iso:country":"US",
    "sg:address":"502 Main St",
    "sg:city":"Westcliffe",
    "sg:classifiers":[
        {
            "category":"Insurance",
            "subcategory":"Insurance Agent",
            "type":"Services"
        }
    ],
    "sg:phone":"+1 719 783 2776",
    "sg:postcode":"81252",
    "sg:province":"CO",
    "wof:name":"Frederickson-Brown Insur Svc",
    "wof:placetype":"venue"
},
  "geometry": {"coordinates":[-105.44695900000001,38.136265],"type":"Point"}
}