{
  "type": "Feature",
  "properties": {
    "addr:full":"1110 Chapel Hills Dr Colorado Springs CO 80920",
    "addr:housenumber":"1110",
    "addr:postcode":"80920",
    "addr:street":"Chapel Hills Dr",
    "iso:country":"US",
    "sg:address":"1110 Chapel Hills Dr",
    "sg:city":"Colorado Springs",
    "sg:classifiers":[
        {
            "category":"Insurance",
            "subcategory":"Hazard Insurance",
            "type":"Services"
        }
    ],
    "sg:phone":"+1 888 891 0948",
    "sg:postcode":"80920",
    "sg:province":"CO",
    "sg:tags":[
        "underwrites",
        "property",
        "specialty",
        "rel"
    ],
    "wof:name":"Progressive Insurance",
    "wof:placetype":"venue"
},
  "geometry": {"coordinates":[-104.791887,38.954811],"type":"Point"}
}