{
  "type": "Feature",
  "properties": {
    "iso:country":"US",
    "sg:address":"5672 E 58th Ave",
    "sg:city":"Commerce City",
    "sg:classifiers":[
        {
            "category":"Restaurant",
            "type":"Food & Drink"
        },
        {
            "category":"Bakery",
            "type":"Food & Drink"
        }
    ],
    "sg:phone":"+1 303 288 5417",
    "sg:postcode":"80022",
    "sg:province":"CO",
    "sg:tags":[
        "mexican"
    ],
    "wof:name":"Colorado Tortilla Co",
    "wof:placetype":"venue"
},
  "geometry": {"coordinates":[-104.921997,39.801899],"type":"Point"}
}