{
  "type": "Feature",
  "properties": {
    "iso:country":"US",
    "sg:address":"9782 Titan Park Cir",
    "sg:city":"Littleton",
    "sg:classifiers":[
        {
            "category":"Real Estate",
            "subcategory":"Developer",
            "type":"Services"
        }
    ],
    "sg:phone":"+1 303 470 2969",
    "sg:postcode":"80125",
    "sg:province":"CO",
    "wof:name":"Titan Development LLC",
    "wof:placetype":"venue"
},
  "geometry": {"coordinates":[-105.01938199999999,39.501455],"type":"Point"}
}