{
  "type": "Feature",
  "properties": {
    "iso:country":"US",
    "sg:address":"2387 River Rd",
    "sg:city":"Grand Junction",
    "sg:classifiers":[
        {
            "category":"Building & Trades",
            "subcategory":"Plumbing",
            "type":"Services"
        }
    ],
    "sg:phone":"+1 970 254 1170",
    "sg:postcode":"81505",
    "sg:province":"CO",
    "sg:tags":[
        "system",
        "heating",
        "air",
        "ventilation",
        "conditioning",
        "contractor"
    ],
    "wof:name":"Comfort Air Grand Junction LLC",
    "wof:placetype":"venue"
},
  "geometry": {"coordinates":[-108.610169,39.091439],"type":"Point"}
}