{
  "type": "Feature",
  "properties": {
    "iso:country":"US",
    "sg:address":"8319 E Lightening View Dr",
    "sg:city":"Parker",
    "sg:classifiers":[
        {
            "category":"Professional",
            "subcategory":"Business Services",
            "type":"Services"
        }
    ],
    "sg:phone":"+1 303 840 1017",
    "sg:postcode":"80134",
    "sg:province":"CO",
    "sg:tags":[
        "teleconferencing"
    ],
    "wof:name":"Premiere Conferencing",
    "wof:placetype":"venue"
},
  "geometry": {"coordinates":[-104.730373,39.450186],"type":"Point"}
}