{
  "type": "Feature",
  "properties": {
    "addr:full":"2006 Broadway St Boulder CO 80304",
    "addr:housenumber":"2006",
    "addr:postcode":"80304",
    "addr:street":"Broadway St",
    "iso:country":"US",
    "sg:address":"2006 Broadway St",
    "sg:city":"Boulder",
    "sg:classifiers":[
        {
            "category":"Professional",
            "subcategory":"Computer Services",
            "type":"Services"
        }
    ],
    "sg:phone":"+1 303 449 8567",
    "sg:postcode":"80304",
    "sg:province":"CO",
    "sg:tags":[
        "website",
        "design"
    ],
    "wof:name":"Insight Designs Web Solutions",
    "wof:placetype":"venue"
},
  "geometry": {"coordinates":[-105.280243,40.018855],"type":"Point"}
}