{
  "type": "Feature",
  "properties": {
    "addr:full":"1295 Kelly Johnson Blvd Colorado Springs CO 80920",
    "addr:housenumber":"1295",
    "addr:postcode":"80920",
    "addr:street":"Kelly Johnson Blvd",
    "iso:country":"US",
    "sg:address":"1295 Kelly Johnson Blvd",
    "sg:city":"Colorado Springs",
    "sg:classifiers":[
        {
            "category":"Professional",
            "subcategory":"Accounting & Tax Preparation",
            "type":"Services"
        }
    ],
    "sg:phone":"+1 719 598 7140",
    "sg:postcode":"80920",
    "sg:province":"CO",
    "sg:tags":[
        "accountant"
    ],
    "wof:name":"James Brill CPA",
    "wof:placetype":"venue"
},
  "geometry": {"coordinates":[-104.807203,38.94525],"type":"Point"}
}