{
  "type": "Feature",
  "properties": {
    "addr:full":"432 Broadway Ave Pueblo CO 81004",
    "addr:housenumber":"432",
    "addr:postcode":"81004",
    "addr:street":"Broadway Ave",
    "iso:country":"US",
    "sg:address":"432 Broadway Ave",
    "sg:city":"Pueblo",
    "sg:classifiers":[
        {
            "category":"Personal",
            "subcategory":"Beauty Salon",
            "type":"Services"
        }
    ],
    "sg:phone":"+1 719 542 1303",
    "sg:postcode":"81004",
    "sg:province":"CO",
    "wof:name":"Timeless Beauty Salon",
    "wof:placetype":"venue"
},
  "geometry": {"coordinates":[-104.6246,38.255043],"type":"Point"}
}