{
  "type": "Feature",
  "properties": {
    "addr:full":"2714 S Victor St Aurora CO 80014",
    "addr:housenumber":"2714",
    "addr:postcode":"80014",
    "addr:street":"S Victor St",
    "iso:country":"US",
    "sg:address":"2714 S Victor St",
    "sg:city":"Aurora",
    "sg:classifiers":[
        {
            "category":"Professional",
            "subcategory":"Accounting & Tax Preparation",
            "type":"Services"
        }
    ],
    "sg:phone":"+1 303 671 7441",
    "sg:postcode":"80014",
    "sg:province":"CO",
    "sg:tags":[
        "billing"
    ],
    "wof:name":"Serendipity Office Systems",
    "wof:placetype":"venue"
},
  "geometry": {"coordinates":[-104.83619899999999,39.666921],"type":"Point"}
}