{
  "type": "Feature",
  "properties": {
    "addr:full":"200 Grand Ave Grand Junction CO 81501",
    "addr:housenumber":"200",
    "addr:postcode":"81501",
    "addr:street":"Grand Ave",
    "iso:country":"US",
    "sg:address":"200 Grand Ave",
    "sg:city":"Grand Junction",
    "sg:classifiers":[
        {
            "category":"Professional",
            "subcategory":"Advertising",
            "type":"Services"
        }
    ],
    "sg:phone":"+1 970 248 2900",
    "sg:postcode":"81501",
    "sg:province":"CO",
    "sg:tags":[
        "guide"
    ],
    "wof:name":"Dex Media Inc",
    "wof:placetype":"venue"
},
  "geometry": {"coordinates":[-108.567876,39.070313],"type":"Point"}
}