{
  "type": "Feature",
  "properties": {
    "addr:full":"436 E 56th Ave Denver CO 80216",
    "addr:housenumber":"436",
    "addr:postcode":"80216",
    "addr:street":"E 56Th Ave",
    "iso:country":"US",
    "sg:address":"436 E 56th Ave",
    "sg:city":"Denver",
    "sg:classifiers":[
        {
            "category":"Building & Trades",
            "subcategory":"Construction",
            "type":"Services"
        }
    ],
    "sg:phone":"+1 303 297 0708",
    "sg:postcode":"80216",
    "sg:province":"CO",
    "sg:tags":[
        "woodworker"
    ],
    "wof:name":"Hammen Woodworking LLC",
    "wof:placetype":"venue"
},
  "geometry": {"coordinates":[-104.980835,39.798252],"type":"Point"}
}