{
  "type": "Feature",
  "properties": {
    "addr:full":"20070 Flint Ln Morrison CO 80465",
    "addr:housenumber":"20070",
    "addr:postcode":"80465",
    "addr:street":"Flint Ln",
    "iso:country":"US",
    "sg:address":"20070 Flint Ln",
    "sg:city":"Morrison",
    "sg:classifiers":[
        {
            "category":"Manufacturing",
            "subcategory":"Paper Products",
            "type":"Manufacturing & Wholesale Goods"
        }
    ],
    "sg:phone":"+1 303 697 6603",
    "sg:postcode":"80465",
    "sg:province":"CO",
    "sg:tags":[
        "mill"
    ],
    "wof:name":"Aspen Park Paper Hangers",
    "wof:placetype":"venue"
},
  "geometry": {"coordinates":[-105.227058,39.562586],"type":"Point"}
}