{
  "type": "Feature",
  "properties": {
    "iso:country":"US",
    "sg:address":"730 S Jason St",
    "sg:city":"Denver",
    "sg:classifiers":[
        {
            "category":"Building & Trades",
            "subcategory":"Construction",
            "type":"Services"
        }
    ],
    "sg:phone":"+1 303 744 2525",
    "sg:postcode":"80223",
    "sg:province":"CO",
    "sg:tags":[
        "product",
        "asphalt"
    ],
    "wof:name":"TMT Milling & Pulverization",
    "wof:placetype":"venue"
},
  "geometry": {"coordinates":[-104.999267,39.704745],"type":"Point"}
}