{
  "type": "Feature",
  "properties": {
    "addr:full":"501 Grace Ave Pueblo CO 81004",
    "addr:housenumber":"501",
    "addr:postcode":"81004",
    "addr:street":"Grace Ave",
    "iso:country":"US",
    "sg:address":"501 Grace Ave",
    "sg:city":"Pueblo",
    "sg:classifiers":[
        {
            "category":"Insurance",
            "subcategory":"Hazard Insurance",
            "type":"Services"
        }
    ],
    "sg:phone":"+1 719 296 1472",
    "sg:postcode":"81004",
    "sg:province":"CO",
    "sg:tags":[
        "bond"
    ],
    "wof:name":"Rudy's Bail Bonds",
    "wof:placetype":"venue"
},
  "geometry": {"coordinates":[-104.6431,38.267452],"type":"Point"}
}