{
  "type": "Feature",
  "properties": {
    "iso:country":"US",
    "sg:address":"917 W Briarwood Ave",
    "sg:city":"Littleton",
    "sg:classifiers":[
        {
            "category":"Professional",
            "subcategory":"Art Services",
            "type":"Services"
        }
    ],
    "sg:phone":"+1 303 347 2799",
    "sg:postcode":"80120",
    "sg:province":"CO",
    "sg:tags":[
        "graphic",
        "commercial",
        "designer",
        "artist"
    ],
    "wof:name":"Aaron Tipton Graphic Desi",
    "wof:placetype":"venue"
},
  "geometry": {"coordinates":[-104.999282,39.592361],"type":"Point"}
}