{
  "type": "Feature",
  "properties": {
    "iso:country":"US",
    "sg:address":"18440 E Linvale Dr",
    "sg:city":"Aurora",
    "sg:classifiers":[
        {
            "category":"Real Estate",
            "subcategory":"Architect",
            "type":"Services"
        }
    ],
    "sg:phone":"+1 303 400 1301",
    "sg:postcode":"80013",
    "sg:province":"CO",
    "sg:tags":[
        "illustrator",
        "architectural"
    ],
    "wof:name":"Sigma Consulting Svc Inc",
    "wof:placetype":"venue"
},
  "geometry": {"coordinates":[-104.773529,39.664663],"type":"Point"}
}