{
  "type": "Feature",
  "properties": {
    "addr:full":"5590 Harlan St Arvada CO 80002",
    "addr:housenumber":"5590",
    "addr:postcode":"80002",
    "addr:street":"Harlan St",
    "iso:country":"US",
    "sg:address":"5590 Harlan St",
    "sg:city":"Arvada",
    "sg:classifiers":[
        {
            "category":"Retail",
            "subcategory":"Auto Repair",
            "type":"Services"
        }
    ],
    "sg:phone":"+1 303 420 3543",
    "sg:postcode":"80002",
    "sg:province":"CO",
    "sg:tags":[
        "machine",
        "automobile",
        "shop"
    ],
    "wof:name":"Ridge Reamer Inc",
    "wof:placetype":"venue"
},
  "geometry": {"coordinates":[-105.062505,39.797569],"type":"Point"}
}