{
  "type": "Feature",
  "properties": {
    "addr:full":"10431 Town Center Dr Broomfield CO 80021",
    "addr:housenumber":"10431",
    "addr:postcode":"80021",
    "addr:street":"Town Center Dr",
    "iso:country":"US",
    "sg:address":"10431 Town Center Dr",
    "sg:city":"Broomfield",
    "sg:classifiers":[
        {
            "category":"Restaurant",
            "type":"Food & Drink"
        }
    ],
    "sg:menulink":"http://www.allmenus.com/co/northeast-jefferson/247263-qdoba/menu/",
    "sg:phone":"+1 303 464 8855",
    "sg:postcode":"80021",
    "sg:province":"CO",
    "sg:tags":[
        "mexican"
    ],
    "wof:name":"Qdoba",
    "wof:placetype":"venue"
},
  "geometry": {"coordinates":[-105.074808,39.887015],"type":"Point"}
}