{
  "type": "Feature",
  "properties": {
    "addr:full":"1435 Stuart St Denver CO 80204",
    "addr:housenumber":"1435",
    "addr:postcode":"80204",
    "addr:street":"Stuart St",
    "iso:country":"US",
    "sg:address":"1435 Stuart St",
    "sg:city":"Denver",
    "sg:classifiers":[
        {
            "category":"Professional",
            "subcategory":"Lawyer & Legal Services",
            "type":"Services"
        }
    ],
    "sg:phone":"+1 303 825 9600",
    "sg:postcode":"80204",
    "sg:province":"CO",
    "sg:website":"www.pellowbeggan.com",
    "wof:name":"Pellow Beggan Llc",
    "wof:placetype":"venue"
},
  "geometry": {"coordinates":[-105.04302199999999,39.739115],"type":"Point"}
}