{
  "type": "Feature",
  "properties": {
    "addr:full":"13645 E Bayaud Ave Aurora CO 80012",
    "addr:housenumber":"13645",
    "addr:postcode":"80012",
    "addr:street":"E Bayaud Ave",
    "iso:country":"US",
    "sg:address":"13645 E Bayaud Ave",
    "sg:city":"Aurora",
    "sg:classifiers":[
        {
            "category":"Organizations",
            "subcategory":"Community Association",
            "type":"Services"
        }
    ],
    "sg:phone":"+1 303 365 9182",
    "sg:postcode":"80012",
    "sg:province":"CO",
    "sg:tags":[
        "fraternal"
    ],
    "wof:name":"Knights Of Columbus",
    "wof:placetype":"venue"
},
  "geometry": {"coordinates":[-104.82908399999999,39.714845],"type":"Point"}
}