{
  "type": "Feature",
  "properties": {
    "iso:country":"US",
    "sg:address":"705 Columbine Rd",
    "sg:city":"Breckenridge",
    "sg:classifiers":[
        {
            "category":"Real Estate",
            "subcategory":"Real Estate Agent",
            "type":"Services"
        }
    ],
    "sg:phone":"+1 970 453 6590",
    "sg:postcode":"80424",
    "sg:province":"CO",
    "sg:tags":[
        "management"
    ],
    "wof:name":"Blue River Property Management",
    "wof:placetype":"venue"
},
  "geometry": {"coordinates":[-106.045813,39.475205],"type":"Point"}
}