{
  "type": "Feature",
  "properties": {
    "addr:full":"5920 W 72nd Dr Arvada CO 80003",
    "addr:housenumber":"5920",
    "addr:postcode":"80003",
    "addr:street":"W 72Nd Dr",
    "iso:country":"US",
    "sg:address":"5920 W 72nd Dr",
    "sg:city":"Arvada",
    "sg:classifiers":[
        {
            "category":"Building & Trades",
            "subcategory":"Construction",
            "type":"Services"
        }
    ],
    "sg:phone":"+1 303 429 3944",
    "sg:postcode":"80003",
    "sg:province":"CO",
    "sg:tags":[
        "house"
    ],
    "wof:name":"Creative Renovation & Repair S",
    "wof:placetype":"venue"
},
  "geometry": {"coordinates":[-105.06291299999999,39.827854],"type":"Point"}
}