{
  "type": "Feature",
  "properties": {
    "addr:full":"325 King St Denver CO 80219",
    "addr:housenumber":"325",
    "addr:postcode":"80219",
    "addr:street":"King St",
    "iso:country":"US",
    "sg:address":"325 King St",
    "sg:city":"Denver",
    "sg:classifiers":[
        {
            "category":"Social Services",
            "subcategory":"Adult Care",
            "type":"Services"
        }
    ],
    "sg:phone":"+1 303 922 5576",
    "sg:postcode":"80219",
    "sg:province":"CO",
    "sg:tags":[
        "residential"
    ],
    "sg:website":"www.saviohouse.org",
    "wof:name":"Savio House",
    "wof:placetype":"venue"
},
  "geometry": {"coordinates":[-105.03377999999999,39.722537],"type":"Point"}
}