{
  "type": "Feature",
  "properties": {
    "iso:country":"US",
    "sg:address":"339 Lions Ln",
    "sg:city":"Fraser",
    "sg:classifiers":[
        {
            "category":"Building & Trades",
            "subcategory":"Construction",
            "type":"Services"
        }
    ],
    "sg:phone":"+1 970 887 3884",
    "sg:postcode":"80478",
    "sg:province":"CO",
    "sg:tags":[
        "concrete",
        "contractor"
    ],
    "wof:name":"Jennings Construction",
    "wof:placetype":"venue"
},
  "geometry": {"coordinates":[-105.888621,39.997298],"type":"Point"}
}