{
  "type": "Feature",
  "properties": {
    "iso:country":"US",
    "sg:address":"12116 E 14th Ave",
    "sg:city":"Aurora",
    "sg:classifiers":[
        {
            "category":"Personal",
            "subcategory":"Beauty Salon",
            "type":"Services"
        }
    ],
    "sg:phone":"+1 720 857 9183",
    "sg:postcode":"80011",
    "sg:province":"CO",
    "wof:name":"Imagen Beauty Salon",
    "wof:placetype":"venue"
},
  "geometry": {"coordinates":[-104.846097,39.738787],"type":"Point"}
}