{
  "type": "Feature",
  "properties": {
    "iso:country":"US",
    "sg:address":"460 E Warren Ave",
    "sg:city":"Denver",
    "sg:classifiers":[
        {
            "category":"Organizations",
            "subcategory":"Religious Organization",
            "type":"Services"
        }
    ],
    "sg:phone":"+1 303 698 7729",
    "sg:postcode":"80210",
    "sg:province":"CO",
    "sg:tags":[
        "church"
    ],
    "sg:website":"www.contemplativeoutreach-co.org",
    "wof:name":"Contemplative Outreach Of Co",
    "wof:placetype":"venue"
},
  "geometry": {"coordinates":[-104.97933399999999,39.676634],"type":"Point"}
}