{
  "type": "Feature",
  "properties": {
    "addr:full":"1506 Knotwood Ct Fort Collins CO 80521",
    "addr:housenumber":"1506",
    "addr:postcode":"80521",
    "addr:street":"Knotwood Ct",
    "iso:country":"US",
    "sg:address":"1506 Knotwood Ct",
    "sg:city":"Fort Collins",
    "sg:classifiers":[
        {
            "category":"Building & Trades",
            "subcategory":"Construction",
            "type":"Services"
        }
    ],
    "sg:phone":"+1 970 416 7708",
    "sg:postcode":"80521",
    "sg:province":"CO",
    "sg:tags":[
        "carpenter"
    ],
    "wof:name":"Pioneer Woodworks",
    "wof:placetype":"venue"
},
  "geometry": {"coordinates":[-105.125137,40.568802],"type":"Point"}
}