{
  "type": "Feature",
  "properties": {
    "addr:full":"9634 S Marauder Dr Conifer CO 80433",
    "addr:housenumber":"9634",
    "addr:postcode":"80433",
    "addr:street":"S Marauder Dr",
    "iso:country":"US",
    "sg:address":"9634 S Marauder Dr",
    "sg:city":"Conifer",
    "sg:classifiers":[
        {
            "category":"Building & Trades",
            "subcategory":"Construction",
            "type":"Services"
        }
    ],
    "sg:phone":"+1 303 838 1710",
    "sg:postcode":"80433",
    "sg:province":"CO",
    "sg:tags":[
        "contractor"
    ],
    "wof:name":"Boll Construction",
    "wof:placetype":"venue"
},
  "geometry": {"coordinates":[-105.344166,39.546329],"type":"Point"}
}