{
  "type": "Feature",
  "properties": {
    "iso:country":"US",
    "sg:address":"7750 S Broadway",
    "sg:city":"Littleton",
    "sg:classifiers":[
        {
            "category":"Real Estate",
            "subcategory":"Real Estate Agent",
            "type":"Services"
        }
    ],
    "sg:phone":"+1 303 320 0505",
    "sg:postcode":"80122",
    "sg:province":"CO",
    "sg:tags":[
        "property",
        "management"
    ],
    "wof:name":"Arapahoe Medical Park Plaza II",
    "wof:placetype":"venue"
},
  "geometry": {"coordinates":[-104.988485,39.573472],"type":"Point"}
}