{
  "type": "Feature",
  "properties": {
    "addr:full":"6468 S Van Gordon St Littleton CO 80127",
    "addr:housenumber":"6468",
    "addr:postcode":"80127",
    "addr:street":"S Van Gordon St",
    "iso:country":"US",
    "sg:address":"6468 S Van Gordon St",
    "sg:city":"Littleton",
    "sg:classifiers":[
        {
            "category":"Professional",
            "type":"Services"
        }
    ],
    "sg:phone":"+1 303 973 5067",
    "sg:postcode":"80127",
    "sg:province":"CO",
    "wof:name":"Todd E Knight",
    "wof:placetype":"venue"
},
  "geometry": {"coordinates":[-105.13444200000001,39.59981],"type":"Point"}
}