{
  "type": "Feature",
  "properties": {
    "addr:full":"1300 E Eisenhower Blvd Loveland CO 80537",
    "addr:housenumber":"1300",
    "addr:postcode":"80537",
    "addr:street":"E Eisenhower Blvd",
    "iso:country":"US",
    "sg:address":"1300 E Eisenhower Blvd",
    "sg:city":"Loveland",
    "sg:classifiers":[
        {
            "category":"Shopping",
            "subcategory":"Florist",
            "type":"Retail Goods"
        }
    ],
    "sg:phone":"+1 970 613 8000",
    "sg:postcode":"80537",
    "sg:province":"CO",
    "sg:website":"www.flowerama.com",
    "wof:name":"Flowerama",
    "wof:placetype":"venue"
},
  "geometry": {"coordinates":[-105.05817999999999,40.407291],"type":"Point"}
}