{
  "type": "Feature",
  "properties": {
    "addr:full":"7227 S Independence St Littleton CO 80128",
    "addr:housenumber":"7227",
    "addr:postcode":"80128",
    "addr:street":"S Independence St",
    "iso:country":"US",
    "sg:address":"7227 S Independence St",
    "sg:city":"Littleton",
    "sg:classifiers":[
        {
            "category":"Building & Trades",
            "subcategory":"Construction",
            "type":"Services"
        }
    ],
    "sg:phone":"+1 303 881 2853",
    "sg:postcode":"80128",
    "sg:province":"CO",
    "sg:tags":[
        "concrete",
        "contractor"
    ],
    "wof:name":"Innovative Concrete Inc",
    "wof:placetype":"venue"
},
  "geometry": {"coordinates":[-105.10629,39.584887],"type":"Point"}
}