{
  "type": "Feature",
  "properties": {
    "addr:full":"3615 S Tamarac Dr Denver CO 80237",
    "addr:housenumber":"3615",
    "addr:postcode":"80237",
    "addr:street":"S Tamarac Dr",
    "iso:country":"US",
    "sg:address":"3615 S Tamarac Dr",
    "sg:city":"Denver",
    "sg:classifiers":[
        {
            "category":"Insurance",
            "subcategory":"Insurance Agent",
            "type":"Services"
        }
    ],
    "sg:phone":"+1 303 770 2333",
    "sg:postcode":"80237",
    "sg:province":"CO",
    "wof:name":"Farmers Insurance Group",
    "wof:placetype":"venue"
},
  "geometry": {"coordinates":[-104.89869400000001,39.652622],"type":"Point"}
}