{
  "type": "Feature",
  "properties": {
    "iso:country":"US",
    "sg:address":"3210 E Rd",
    "sg:city":"Clifton",
    "sg:classifiers":[
        {
            "category":"Organizations",
            "subcategory":"Labor Organization",
            "type":"Services"
        }
    ],
    "sg:phone":"+1 970 242 3432",
    "sg:postcode":"81520",
    "sg:province":"CO",
    "wof:name":"IBEW",
    "wof:placetype":"venue"
},
  "geometry": {"coordinates":[-108.457695,39.077367],"type":"Point"}
}