{
  "type": "Feature",
  "properties": {
    "addr:full":"2120 W Colorado Ave Colorado Springs CO 80904",
    "addr:housenumber":"2120",
    "addr:postcode":"80904",
    "addr:street":"W Colorado Ave",
    "iso:country":"US",
    "sg:address":"2120 W Colorado Ave",
    "sg:city":"Colorado Springs",
    "sg:classifiers":[
        {
            "category":"Personal",
            "subcategory":"Beauty Salon",
            "type":"Services"
        }
    ],
    "sg:phone":"+1 719 635 1898",
    "sg:postcode":"80904",
    "sg:province":"CO",
    "wof:name":"Salon Critique Inc",
    "wof:placetype":"venue"
},
  "geometry": {"coordinates":[-104.857833,38.844318],"type":"Point"}
}