{
  "type": "Feature",
  "properties": {
    "iso:country":"US",
    "sg:address":"301 Manitou Ave",
    "sg:city":"Manitou Springs",
    "sg:classifiers":[
        {
            "category":"Restaurant",
            "type":"Food & Drink"
        }
    ],
    "sg:phone":"+1 719 685 3755",
    "sg:postcode":"80829",
    "sg:province":"CO",
    "sg:tags":[
        "pizza"
    ],
    "wof:name":"Savelli's Pizza",
    "wof:placetype":"venue"
},
  "geometry": {"coordinates":[-104.899002,38.856701],"type":"Point"}
}