{
  "type": "Feature",
  "properties": {
    "iso:country":"US",
    "sg:address":"2833 S Colorado Blvd",
    "sg:city":"Denver",
    "sg:classifiers":[
        {
            "category":"Building & Trades",
            "subcategory":"Construction",
            "type":"Services"
        }
    ],
    "sg:phone":"+1 303 300 0500",
    "sg:postcode":"80222",
    "sg:province":"CO",
    "sg:tags":[
        "restoration",
        "basement"
    ],
    "wof:name":"Basement Solutions Inc",
    "wof:placetype":"venue"
},
  "geometry": {"coordinates":[-104.940758,39.66379],"type":"Point"}
}