{
  "type": "Feature",
  "properties": {
    "iso:country":"US",
    "sg:address":"2500 Curtis St",
    "sg:city":"Denver",
    "sg:classifiers":[
        {
            "category":"Social Services",
            "subcategory":"Child Care",
            "type":"Services"
        },
        {
            "category":"Education",
            "subcategory":"Preschool",
            "type":"Public Place"
        }
    ],
    "sg:phone":"+1 303 623 2609",
    "sg:postcode":"80205",
    "sg:province":"CO",
    "sg:tags":[
        "day"
    ],
    "sg:website":"www.montessoriacademyofcolorado.org",
    "wof:name":"Montessori Academy of Colorado",
    "wof:placetype":"venue"
},
  "geometry": {"coordinates":[-104.983066,39.755895],"type":"Point"}
}