{
  "type": "Feature",
  "properties": {
    "addr:full":"905 Ken Pratt Blvd Longmont CO 80501",
    "addr:housenumber":"905",
    "addr:postcode":"80501",
    "addr:street":"Ken Pratt Blvd",
    "iso:country":"US",
    "sg:address":"905 Ken Pratt Blvd",
    "sg:city":"Longmont",
    "sg:classifiers":[
        {
            "category":"Autos & Motor Vehicles",
            "subcategory":"Automobile Sales",
            "type":"Retail Goods"
        }
    ],
    "sg:phone":"+1 303 444 9654",
    "sg:postcode":"80501",
    "sg:province":"CO",
    "wof:name":"Valley Subaru Inc",
    "wof:placetype":"venue"
},
  "geometry": {"coordinates":[-105.10730700000001,40.152401],"type":"Point"}
}