{
  "type": "Feature",
  "properties": {
    "iso:country":"US",
    "sg:address":"2027 East Colfax Avenue",
    "sg:city":"Denver",
    "sg:classifiers":[
        {
            "category":"Bakery",
            "type":"Food & Drink"
        }
    ],
    "sg:phone":"+1 303 282 1044",
    "sg:postcode":"80206",
    "sg:province":"CO",
    "sg:website":"www.mulberriescakeshop.com/",
    "wof:name":"Mulberries Cake Shop",
    "wof:placetype":"venue"
},
  "geometry": {"coordinates":[-104.96286,39.74002],"type":"Point"}
}