{
  "type": "Feature",
  "properties": {
    "iso:country":"US",
    "sg:address":"5430 E 56th Ave",
    "sg:city":"Commerce City",
    "sg:classifiers":[
        {
            "category":"Utilities",
            "subcategory":"Refuse",
            "type":"Services"
        }
    ],
    "sg:phone":"+1 303 286 9543",
    "sg:postcode":"80022",
    "sg:province":"CO",
    "sg:tags":[
        "rubbish",
        "collection"
    ],
    "wof:name":"Allied Waste North America",
    "wof:placetype":"venue"
},
  "geometry": {"coordinates":[-104.927109,39.798229],"type":"Point"}
}