{
  "type": "Feature",
  "properties": {
    "iso:country":"US",
    "sg:address":"11891 E 33rd Ave",
    "sg:city":"Aurora",
    "sg:classifiers":[
        {
            "category":"Professional",
            "subcategory":"Art Services",
            "type":"Services"
        },
        {
            "category":"Manufacturing",
            "subcategory":"Printing",
            "type":"Manufacturing & Wholesale Goods"
        }
    ],
    "sg:phone":"+1 303 367 4230",
    "sg:postcode":"80010",
    "sg:province":"CO",
    "sg:tags":[
        "commercial",
        "screen",
        "lithographic",
        "design",
        "p"
    ],
    "wof:name":"B & E Screen Printing & Spt AP",
    "wof:placetype":"venue"
},
  "geometry": {"coordinates":[-104.84819299999999,39.76394],"type":"Point"}
}