{
  "type": "Feature",
  "properties": {
    "iso:country":"US",
    "sg:address":"500 W 84th Ave",
    "sg:city":"Denver",
    "sg:classifiers":[
        {
            "category":"Personal",
            "subcategory":"Beauty Salon",
            "type":"Services"
        }
    ],
    "sg:phone":"+1 303 428 5391",
    "sg:postcode":"80260",
    "sg:province":"CO",
    "sg:tags":[
        "manicuring"
    ],
    "wof:name":"Ocean Nails",
    "wof:placetype":"venue"
},
  "geometry": {"coordinates":[-104.99373199999999,39.848864],"type":"Point"}
}