{
  "type": "Feature",
  "properties": {
    "addr:full":"405 S Main St Yuma CO 80759",
    "addr:housenumber":"405",
    "addr:postcode":"80759",
    "addr:street":"S Main St",
    "iso:country":"US",
    "sg:address":"405 S Main St",
    "sg:city":"Yuma",
    "sg:classifiers":[
        {
            "category":"Wholesale",
            "subcategory":"Farm Supplies",
            "type":"Manufacturing & Wholesale Goods"
        }
    ],
    "sg:phone":"+1 970 848 2128",
    "sg:postcode":"80759",
    "sg:province":"CO",
    "sg:tags":[
        "feed"
    ],
    "wof:name":"Sandhills Feed",
    "wof:placetype":"venue"
},
  "geometry": {"coordinates":[-102.723725,40.122298],"type":"Point"}
}