{
  "type": "Feature",
  "properties": {
    "addr:full":"588 W Sagebrush Ct Louisville CO 80027",
    "addr:housenumber":"588",
    "addr:postcode":"80027",
    "addr:street":"W Sagebrush Ct",
    "iso:country":"US",
    "sg:address":"588 W Sagebrush Ct",
    "sg:city":"Louisville",
    "sg:classifiers":[
        {
            "category":"Shopping",
            "type":"Retail Goods"
        }
    ],
    "sg:phone":"+1 303 666 9270",
    "sg:postcode":"80027",
    "sg:province":"CO",
    "sg:tags":[
        "merchandise"
    ],
    "wof:name":"Lenas Warehouse",
    "wof:placetype":"venue"
},
  "geometry": {"coordinates":[-105.151822,39.981044],"type":"Point"}
}