{
  "type": "Feature",
  "properties": {
    "addr:full":"2107 Sandstone Dr Fort Collins CO 80524",
    "addr:housenumber":"2107",
    "addr:postcode":"80524",
    "addr:street":"Sandstone Dr",
    "iso:country":"US",
    "sg:address":"2107 Sandstone Dr",
    "sg:city":"Fort Collins",
    "sg:classifiers":[
        {
            "category":"Education",
            "subcategory":"Special Training",
            "type":"Public Place"
        }
    ],
    "sg:phone":"+1 970 493 2507",
    "sg:postcode":"80524",
    "sg:province":"CO",
    "sg:tags":[
        "instruction",
        "music"
    ],
    "wof:name":"Drum Set Instruction",
    "wof:placetype":"venue"
},
  "geometry": {"coordinates":[-105.06814,40.617679],"type":"Point"}
}