{
  "type": "Feature",
  "properties": {
    "addr:full":"233 Dolomite Dr Colorado Springs CO 80919",
    "addr:housenumber":"233",
    "addr:postcode":"80919",
    "addr:street":"Dolomite Dr",
    "iso:country":"US",
    "sg:address":"233 Dolomite Dr",
    "sg:city":"Colorado Springs",
    "sg:classifiers":[
        {
            "category":"Professional",
            "type":"Services"
        }
    ],
    "sg:phone":"+1 719 260 6387",
    "sg:postcode":"80919",
    "sg:province":"CO",
    "wof:name":"Universal Net/John Squibb",
    "wof:placetype":"venue"
},
  "geometry": {"coordinates":[-104.822036,38.921715],"type":"Point"}
}