{
  "type": "Feature",
  "properties": {
    "iso:country":"US",
    "sg:address":"6395 W 56th Ave",
    "sg:city":"Arvada",
    "sg:classifiers":[
        {
            "category":"Manufacturing",
            "subcategory":"Tools & Machinery",
            "type":"Manufacturing & Wholesale Goods"
        }
    ],
    "sg:phone":"+1 303 425 0092",
    "sg:postcode":"80002",
    "sg:province":"CO",
    "sg:tags":[
        "sheet",
        "metal",
        "mfg"
    ],
    "wof:name":"Bull Sheet Metal LLC",
    "wof:placetype":"venue"
},
  "geometry": {"coordinates":[-105.066326,39.798428],"type":"Point"}
}