{
  "type": "Feature",
  "properties": {
    "addr:full":"15 E Main St Cortez CO 81321",
    "addr:housenumber":"15",
    "addr:postcode":"81321",
    "addr:street":"E Main St",
    "iso:country":"US",
    "sg:address":"15 E Main St",
    "sg:city":"Cortez",
    "sg:classifiers":[
        {
            "category":"Shopping",
            "subcategory":"Gifts & Souvenirs",
            "type":"Retail Goods"
        }
    ],
    "sg:phone":"+1 970 565 6456",
    "sg:postcode":"81321",
    "sg:province":"CO",
    "sg:tags":[
        "shop"
    ],
    "wof:name":"Dream Catcher",
    "wof:placetype":"venue"
},
  "geometry": {"coordinates":[-108.583991,37.348566],"type":"Point"}
}