{
  "type": "Feature",
  "properties": {
    "iso:country":"US",
    "sg:address":"133 Riverside Ct",
    "sg:city":"Avon",
    "sg:classifiers":[
        {
            "category":"Professional",
            "subcategory":"Engineering",
            "type":"Services"
        }
    ],
    "sg:phone":"+1 970 845 7910",
    "sg:postcode":"81620",
    "sg:province":"CO",
    "sg:tags":[
        "engineer"
    ],
    "wof:name":"Rader Engineering Inc",
    "wof:placetype":"venue"
},
  "geometry": {"coordinates":[-106.499292,39.624227],"type":"Point"}
}