{
  "type": "Feature",
  "properties": {
    "addr:full":"1247 Pearl St Boulder CO 80302",
    "addr:housenumber":"1247",
    "addr:postcode":"80302",
    "addr:street":"Pearl St",
    "iso:country":"US",
    "sg:address":"1247 Pearl St",
    "sg:city":"Boulder",
    "sg:classifiers":[
        {
            "category":"Restaurant",
            "type":"Food & Drink"
        }
    ],
    "sg:phone":"+1 303 444 4884",
    "sg:postcode":"80302",
    "sg:province":"CO",
    "sg:tags":[
        "cafe"
    ],
    "wof:name":"Boulder Cafe Corp",
    "wof:placetype":"venue"
},
  "geometry": {"coordinates":[-105.27917600000001,40.018123],"type":"Point"}
}