{
  "type": "Feature",
  "properties": {
    "iso:country":"US",
    "sg:address":"421 S Sherman St",
    "sg:city":"Byers",
    "sg:classifiers":[
        {
            "category":"Utilities",
            "subcategory":"Water",
            "type":"Services"
        }
    ],
    "sg:phone":"+1 303 822 5384",
    "sg:postcode":"80103",
    "sg:province":"CO",
    "sg:tags":[
        "company",
        "sewage"
    ],
    "wof:name":"Byers Water & Sanitation Dist",
    "wof:placetype":"venue"
},
  "geometry": {"coordinates":[-104.224864,39.705263],"type":"Point"}
}