{
  "type": "Feature",
  "properties": {
    "addr:full":"8580 Wranglers Way Colorado Springs CO 80908",
    "addr:postcode":"8580;80908",
    "addr:street":"Wranglers Way",
    "iso:country":"US",
    "sg:address":"8580 Wranglers Way",
    "sg:city":"Colorado Springs",
    "sg:classifiers":[
        {
            "category":"Professional",
            "subcategory":"Computer Services",
            "type":"Services"
        }
    ],
    "sg:phone":"+1 719 495 8668",
    "sg:postcode":"80908",
    "sg:province":"CO",
    "sg:tags":[
        "consultant",
        "designer"
    ],
    "wof:name":"Data Engineering",
    "wof:placetype":"venue"
},
  "geometry": {"coordinates":[-104.667357,39.059443],"type":"Point"}
}