{
  "type": "Feature",
  "properties": {
    "addr:full":"3425 Austin Bluffs Pkwy Colorado Springs CO 80918",
    "addr:housenumber":"3425",
    "addr:postcode":"80918",
    "addr:street":"Austin Bluffs Pkwy",
    "iso:country":"US",
    "sg:address":"3425 Austin Bluffs Pkwy",
    "sg:city":"Colorado Springs",
    "sg:classifiers":[
        {
            "category":"Insurance",
            "subcategory":"Insurance Agent",
            "type":"Services"
        }
    ],
    "sg:phone":"+1 719 594 0200",
    "sg:postcode":"80918",
    "sg:province":"CO",
    "wof:name":"Wilson Butz",
    "wof:placetype":"venue"
},
  "geometry": {"coordinates":[-104.76478299999999,38.890641],"type":"Point"}
}