{
  "type": "Feature",
  "properties": {
    "iso:country":"US",
    "sg:address":"750 17th Ave",
    "sg:city":"Longmont",
    "sg:classifiers":[
        {
            "category":"Banks & Credit Unions",
            "subcategory":"Bank",
            "type":"Services"
        }
    ],
    "sg:phone":"+1 303 678 8204",
    "sg:postcode":"80501",
    "sg:province":"CO",
    "sg:tags":[
        "loan",
        "real estate"
    ],
    "wof:name":"Long Peak Mortgage",
    "wof:placetype":"venue"
},
  "geometry": {"coordinates":[-105.105643,40.188644],"type":"Point"}
}