{
  "type": "Feature",
  "properties": {
    "iso:country":"US",
    "sg:address":"112 Main St",
    "sg:city":"Breckenridge",
    "sg:classifiers":[
        {
            "category":"Shopping",
            "subcategory":"Clothing, Apparel, & Fashions",
            "type":"Retail Goods"
        }
    ],
    "sg:phone":"+1 970 547 0778",
    "sg:postcode":"80424",
    "sg:province":"CO",
    "sg:tags":[
        "t"
    ],
    "wof:name":"Third Rock-Breckenridge Third",
    "wof:placetype":"venue"
},
  "geometry": {"coordinates":[-106.04619700000001,39.481328],"type":"Point"}
}