{
  "type": "Feature",
  "properties": {
    "addr:full":"510 Fruitvale Ct Grand Junction CO 81504",
    "addr:housenumber":"510",
    "addr:postcode":"81504",
    "addr:street":"Fruitvale Ct",
    "iso:country":"US",
    "sg:address":"510 Fruitvale Ct",
    "sg:city":"Grand Junction",
    "sg:classifiers":[
        {
            "category":"Professional",
            "type":"Services"
        }
    ],
    "sg:phone":"+1 970 256 1290",
    "sg:postcode":"81504",
    "sg:province":"CO",
    "wof:name":"United Locating Svc",
    "wof:placetype":"venue"
},
  "geometry": {"coordinates":[-108.49022100000001,39.079821],"type":"Point"}
}