{
  "type": "Feature",
  "properties": {
    "iso:country":"US",
    "sg:address":"3133 Cinema Pt",
    "sg:city":"Colorado Springs",
    "sg:classifiers":[
        {
            "category":"Shopping",
            "subcategory":"Bicycles & Sporting Goods",
            "type":"Retail Goods"
        }
    ],
    "sg:phone":"+1 719 638 3400",
    "sg:postcode":"80922",
    "sg:province":"CO",
    "wof:name":"Galyans First & Main",
    "wof:placetype":"venue"
},
  "geometry": {"coordinates":[-104.71704800000001,38.879795],"type":"Point"}
}