{
  "type": "Feature",
  "properties": {
    "iso:country":"US",
    "sg:address":"9520 E Jewell Ave",
    "sg:city":"Denver",
    "sg:classifiers":[
        {
            "category":"Wholesale",
            "subcategory":"Durable Goods & Equipment",
            "type":"Manufacturing & Wholesale Goods"
        }
    ],
    "sg:phone":"+1 303 306 6800",
    "sg:postcode":"80247",
    "sg:province":"CO",
    "sg:tags":[
        "representative",
        "manufacturer"
    ],
    "sg:website":"www.pearsonandpearson.com",
    "wof:name":"Pearson & Pearson",
    "wof:placetype":"venue"
},
  "geometry": {"coordinates":[-104.87745700000001,39.681971],"type":"Point"}
}