{
  "type": "Feature",
  "properties": {
    "addr:full":"232 Chamberlin Ave Colorado Springs CO 80906",
    "addr:housenumber":"232",
    "addr:postcode":"80906",
    "addr:street":"Chamberlin Ave",
    "iso:country":"US",
    "sg:address":"232 Chamberlin Ave",
    "sg:city":"Colorado Springs",
    "sg:classifiers":[
        {
            "category":"Freight",
            "type":"Transportation"
        }
    ],
    "sg:phone":"+1 719 540 9912",
    "sg:postcode":"80906",
    "sg:province":"CO",
    "sg:tags":[
        "local",
        "storage",
        "trucking"
    ],
    "wof:name":"My Three Sons Moving",
    "wof:placetype":"venue"
},
  "geometry": {"coordinates":[-104.794391,38.782099],"type":"Point"}
}