{
  "type": "Feature",
  "properties": {
    "iso:country":"US",
    "sg:address":"2242 Primrose Dr",
    "sg:city":"Fort Collins",
    "sg:classifiers":[
        {
            "category":"Building & Trades",
            "subcategory":"Construction",
            "type":"Services"
        }
    ],
    "sg:phone":"+1 970 206 0876",
    "sg:postcode":"80526",
    "sg:province":"CO",
    "sg:tags":[
        "house"
    ],
    "wof:name":"Polar Star Home Improvements",
    "wof:placetype":"venue"
},
  "geometry": {"coordinates":[-105.11900300000001,40.54329],"type":"Point"}
}