{
  "type": "Feature",
  "properties": {
    "iso:country":"US",
    "sg:address":"314 S Circle Dr",
    "sg:city":"Colorado Springs",
    "sg:classifiers":[
        {
            "category":"Organizations",
            "subcategory":"Religious Organization",
            "type":"Services"
        }
    ],
    "sg:phone":"+1 719 632 1844",
    "sg:postcode":"80910",
    "sg:province":"CO",
    "sg:tags":[
        "church"
    ],
    "wof:name":"Faith Baptist Church",
    "wof:placetype":"venue"
},
  "geometry": {"coordinates":[-104.77923,38.827039],"type":"Point"}
}