{
  "type": "Feature",
  "properties": {
    "addr:full":"320 Wooten Rd Colorado Springs CO 80916",
    "addr:housenumber":"320",
    "addr:postcode":"80916",
    "addr:street":"Wooten Rd",
    "iso:country":"US",
    "sg:address":"320 Wooten Rd",
    "sg:city":"Colorado Springs",
    "sg:classifiers":[
        {
            "category":"Manufacturing",
            "subcategory":"Aerospace",
            "type":"Manufacturing & Wholesale Goods"
        }
    ],
    "sg:phone":"+1 719 380 5800",
    "sg:postcode":"80916",
    "sg:province":"CO",
    "sg:tags":[
        "aircraft",
        "mfg"
    ],
    "wof:name":"Boeing",
    "wof:placetype":"venue"
},
  "geometry": {"coordinates":[-104.738826,38.838755],"type":"Point"}
}