{
  "type": "Feature",
  "properties": {
    "iso:country":"US",
    "sg:address":"7290 W 119th Pl",
    "sg:city":"Broomfield",
    "sg:classifiers":[
        {
            "category":"Building & Trades",
            "subcategory":"Electrical",
            "type":"Services"
        }
    ],
    "sg:phone":"+1 303 456 4500",
    "sg:postcode":"80020",
    "sg:province":"CO",
    "sg:tags":[
        "electric",
        "contractor"
    ],
    "wof:name":"Mach One Electric",
    "wof:placetype":"venue"
},
  "geometry": {"coordinates":[-105.077003,39.913289],"type":"Point"}
}