{
  "type": "Feature",
  "properties": {
    "addr:full":"210 N 3rd St Lamar CO 81052",
    "addr:housenumber":"210",
    "addr:postcode":"81052",
    "addr:street":"N 3Rd St",
    "iso:country":"US",
    "sg:address":"210 N 3rd St",
    "sg:city":"Lamar",
    "sg:classifiers":[
        {
            "category":"Shopping",
            "subcategory":"Used Merchandise",
            "type":"Retail Goods"
        }
    ],
    "sg:phone":"+1 719 336 8443",
    "sg:postcode":"81052",
    "sg:province":"CO",
    "sg:tags":[
        "antique"
    ],
    "wof:name":"Toni's Antique & Stuff",
    "wof:placetype":"venue"
},
  "geometry": {"coordinates":[-102.616765,38.092366],"type":"Point"}
}