{
  "type": "Feature",
  "properties": {
    "addr:full":"1322 Motor City Dr Colorado Springs CO 80906",
    "addr:housenumber":"1322",
    "addr:postcode":"80906",
    "addr:street":"Motor City Dr",
    "iso:country":"US",
    "sg:address":"1322 Motor City Dr",
    "sg:city":"Colorado Springs",
    "sg:classifiers":[
        {
            "category":"Retail",
            "subcategory":"Auto Rental",
            "type":"Services"
        }
    ],
    "sg:phone":"+1 719 635 8029",
    "sg:postcode":"80906",
    "sg:province":"CO",
    "sg:tags":[
        "renting",
        "automobile"
    ],
    "wof:name":"Enterprise Rent-A-Car",
    "wof:placetype":"venue"
},
  "geometry": {"coordinates":[-104.83084700000001,38.814018],"type":"Point"}
}