{
  "type": "Feature",
  "properties": {
    "iso:country":"US",
    "sg:address":"5017 S Federal Blvd",
    "sg:city":"Englewood",
    "sg:classifiers":[
        {
            "category":"Personal",
            "subcategory":"Beauty Salon",
            "type":"Services"
        }
    ],
    "sg:phone":"+1 303 797 6403",
    "sg:postcode":"80110",
    "sg:province":"CO",
    "sg:tags":[
        "manicuring"
    ],
    "wof:name":"Quality Nails",
    "wof:placetype":"venue"
},
  "geometry": {"coordinates":[-105.025498,39.626032],"type":"Point"}
}