{
  "type": "Feature",
  "properties": {
    "iso:country":"US",
    "sg:address":"9035 Wadsworth Pkwy",
    "sg:city":"Broomfield",
    "sg:classifiers":[
        {
            "category":"Real Estate",
            "subcategory":"Real Estate Agent",
            "type":"Services"
        }
    ],
    "sg:phone":"+1 303 410 0077",
    "sg:postcode":"80021",
    "sg:province":"CO",
    "wof:name":"Benchmark Realty LLC",
    "wof:placetype":"venue"
},
  "geometry": {"coordinates":[-105.081992,39.860532],"type":"Point"}
}