{
  "type": "Feature",
  "properties": {
    "addr:full":"773 W Garden of the Gods Rd Colorado Springs CO 80907",
    "addr:housenumber":"773",
    "addr:postcode":"springs;80907",
    "addr:street":"W Garden Of The Gods Rd",
    "iso:country":"US",
    "sg:address":"773 W Garden of the Gods Rd",
    "sg:city":"Colorado Springs",
    "sg:classifiers":[
        {
            "category":"Restaurant",
            "type":"Food & Drink"
        }
    ],
    "sg:phone":"+1 719 264 0893",
    "sg:postcode":"80907",
    "sg:province":"CO",
    "wof:name":"Giovanna Cafe",
    "wof:placetype":"venue"
},
  "geometry": {"coordinates":[-104.837716,38.89668],"type":"Point"}
}