{
  "type": "Feature",
  "properties": {
    "iso:country":"US",
    "sg:address":"159 Adams Street",
    "sg:city":"Denver",
    "sg:classifiers":[
        {
            "category":"Personal",
            "subcategory":"Skin Care",
            "type":"Services"
        }
    ],
    "sg:phone":"+1 303 377 1617",
    "sg:postcode":"80206",
    "sg:province":"CO",
    "sg:website":"www.editeurospa.com",
    "wof:name":"Edit Euro Spa",
    "wof:placetype":"venue"
},
  "geometry": {"coordinates":[-104.94871,39.718737],"type":"Point"}
}