{
  "type": "Feature",
  "properties": {
    "addr:full":"150 Clayton Ln Denver CO 80206",
    "addr:housenumber":"150",
    "addr:postcode":"80206",
    "addr:street":"Clayton Ln",
    "iso:country":"US",
    "sg:address":"150 Clayton Ln",
    "sg:city":"Denver",
    "sg:classifiers":[
        {
            "category":"Travel",
            "subcategory":"Hotels & Motels",
            "type":"Entertainment"
        }
    ],
    "sg:phone":"+1 303 316 2700",
    "sg:postcode":"80206",
    "sg:province":"CO",
    "wof:name":"Jw Marriott Denver At Cherry Creek",
    "wof:placetype":"venue"
},
  "geometry": {"coordinates":[-104.956817,39.71881],"type":"Point"}
}