{
  "type": "Feature",
  "properties": {
    "addr:full":"6185 Ampersand Way Colorado Springs CO 80918",
    "addr:housenumber":"6185",
    "addr:postcode":"80918",
    "addr:street":"Ampersand Way",
    "iso:country":"US",
    "sg:address":"6185 Ampersand Way",
    "sg:city":"Colorado Springs",
    "sg:classifiers":[
        {
            "category":"Manufacturing",
            "subcategory":"Printing",
            "type":"Manufacturing & Wholesale Goods"
        }
    ],
    "sg:phone":"+1 719 266 9191",
    "sg:postcode":"80918",
    "sg:province":"CO",
    "sg:tags":[
        "lithographic",
        "commercial"
    ],
    "wof:name":"All Printers Plus LLC",
    "wof:placetype":"venue"
},
  "geometry": {"coordinates":[-104.753227,38.919715],"type":"Point"}
}