{
  "type": "Feature",
  "properties": {
    "iso:country":"US",
    "sg:address":"9988 S Fallen Rock Rd",
    "sg:city":"Conifer",
    "sg:classifiers":[
        {
            "category":"Home & Garden",
            "subcategory":"Home Furnishings",
            "type":"Retail Goods"
        }
    ],
    "sg:phone":"+1 303 838 2804",
    "sg:postcode":"80433",
    "sg:province":"CO",
    "wof:name":"Naked Edge Cutlery",
    "wof:placetype":"venue"
},
  "geometry": {"coordinates":[-105.307547,39.537024],"type":"Point"}
}