{
  "type": "Feature",
  "properties": {
    "addr:full":"2145 Blake St Denver CO 80205",
    "addr:housenumber":"2145",
    "addr:postcode":"80205",
    "addr:street":"Blake St",
    "iso:country":"US",
    "sg:address":"2145 Blake St",
    "sg:city":"Denver",
    "sg:classifiers":[
        {
            "category":"Building & Trades",
            "subcategory":"Locksmith",
            "type":"Services"
        }
    ],
    "sg:phone":"+1 303 218 2478",
    "sg:postcode":"80205",
    "sg:province":"CO",
    "sg:tags":[
        "key"
    ],
    "wof:name":"Blake St 24 Hr Emerg Locksmith",
    "wof:placetype":"venue"
},
  "geometry": {"coordinates":[-104.99271299999999,39.755738],"type":"Point"}
}