{
  "type": "Feature",
  "properties": {
    "iso:country":"US",
    "sg:address":"455 W 115th Ave",
    "sg:city":"Denver",
    "sg:classifiers":[
        {
            "category":"Professional",
            "subcategory":"Computer Services",
            "type":"Services"
        }
    ],
    "sg:phone":"+1 303 452 5225",
    "sg:postcode":"80234",
    "sg:province":"CO",
    "sg:tags":[
        "integrator",
        "area",
        "local",
        "system",
        "network"
    ],
    "wof:name":"Axis Networks Inc",
    "wof:placetype":"venue"
},
  "geometry": {"coordinates":[-104.992852,39.905693],"type":"Point"}
}