{
  "type": "Feature",
  "properties": {
    "iso:country":"US",
    "sg:address":"1928 Pearl St",
    "sg:city":"Boulder",
    "sg:classifiers":[
        {
            "category":"Real Estate",
            "subcategory":"Architect",
            "type":"Services"
        }
    ],
    "sg:phone":"+1 303 444 5400",
    "sg:postcode":"80302",
    "sg:province":"CO",
    "wof:name":"Rocky Mountain Custom Constr",
    "wof:placetype":"venue"
},
  "geometry": {"coordinates":[-105.269876,40.019876],"type":"Point"}
}