{
  "type": "Feature",
  "properties": {
    "iso:country":"US",
    "sg:address":"235 Mathews St",
    "sg:city":"Fort Collins",
    "sg:classifiers":[
        {
            "category":"Government",
            "subcategory":"Office",
            "type":"Public Place"
        }
    ],
    "sg:phone":"+1 970 221 6243",
    "sg:postcode":"80524",
    "sg:province":"CO",
    "sg:tags":[
        "village"
    ],
    "sg:website":"www.nfrmpo.org",
    "wof:name":"North Front Range MPO",
    "wof:placetype":"venue"
},
  "geometry": {"coordinates":[-105.074175,40.584682],"type":"Point"}
}