{
  "type": "Feature",
  "properties": {
    "addr:full":"2355 Briargate Pkwy Colorado Springs CO 80920",
    "addr:housenumber":"2355",
    "addr:postcode":"80920",
    "addr:street":"Briargate Pkwy",
    "iso:country":"US",
    "sg:address":"2355 Briargate Pkwy",
    "sg:city":"Colorado Springs",
    "sg:classifiers":[
        {
            "category":"Insurance",
            "subcategory":"Insurance Agent",
            "type":"Services"
        }
    ],
    "sg:phone":"+1 719 262 2160",
    "sg:postcode":"80920",
    "sg:province":"CO",
    "wof:name":"Claim Reporting Center",
    "wof:placetype":"venue"
},
  "geometry": {"coordinates":[-104.782291,38.966733],"type":"Point"}
}