{
  "type": "Feature",
  "properties": {
    "iso:country":"US",
    "sg:address":"2090 Island Ln",
    "sg:city":"Evergreen",
    "sg:classifiers":[
        {
            "category":"Professional",
            "type":"Services"
        }
    ],
    "sg:phone":"+1 303 670 3826",
    "sg:postcode":"80439",
    "sg:province":"CO",
    "wof:name":"Ensi Ltd",
    "wof:placetype":"venue"
},
  "geometry": {"coordinates":[-105.35512,39.676868],"type":"Point"}
}