{
  "type": "Feature",
  "properties": {
    "iso:country":"US",
    "sg:address":"85 Fairway Ln",
    "sg:city":"Littleton",
    "sg:classifiers":[
        {
            "category":"Professional",
            "subcategory":"Management & Consulting",
            "type":"Services"
        }
    ],
    "sg:phone":"+1 303 738 8179",
    "sg:postcode":"80123",
    "sg:province":"CO",
    "sg:tags":[
        "consultant",
        "business"
    ],
    "wof:name":"Safetypath Aviation Consltnts",
    "wof:placetype":"venue"
},
  "geometry": {"coordinates":[-105.0386,39.595255],"type":"Point"}
}