{
  "type": "Feature",
  "properties": {
    "addr:full":"461 Tyler Ave Louisville CO 80027",
    "addr:housenumber":"461",
    "addr:postcode":"80027",
    "addr:street":"Tyler Ave",
    "iso:country":"US",
    "sg:address":"461 Tyler Ave",
    "sg:city":"Louisville",
    "sg:classifiers":[
        {
            "category":"Social Services",
            "subcategory":"Child Care",
            "type":"Services"
        }
    ],
    "sg:phone":"+1 303 665 2002",
    "sg:postcode":"80027",
    "sg:province":"CO",
    "sg:tags":[
        "school",
        "center",
        "daycare",
        "kindergarten",
        "academic",
        "preschool"
    ],
    "sg:website":"www.louisvillemontessorischool.com",
    "wof:name":"Louisville Montessori School",
    "wof:placetype":"venue"
},
  "geometry": {"coordinates":[-105.149086,39.975336],"type":"Point"}
}