{
  "type": "Feature",
  "properties": {
    "addr:full":"100 S Santa Fe Dr Denver CO 80223",
    "addr:housenumber":"100",
    "addr:postcode":"80223",
    "addr:street":"S Santa Fe Dr",
    "iso:country":"US",
    "sg:address":"100 S Santa Fe Dr",
    "sg:city":"Denver",
    "sg:classifiers":[
        {
            "category":"Professional",
            "subcategory":"Research",
            "type":"Services"
        }
    ],
    "sg:phone":"+1 303 777 9691",
    "sg:postcode":"80223",
    "sg:province":"CO",
    "sg:tags":[
        "development",
        "marketing",
        "product",
        "laboratory"
    ],
    "wof:name":"R-Solutions",
    "wof:placetype":"venue"
},
  "geometry": {"coordinates":[-104.998434,39.713871],"type":"Point"}
}