{
  "type": "Feature",
  "properties": {
    "iso:country":"US",
    "sg:address":"7910 Ralston Rd",
    "sg:city":"Arvada",
    "sg:classifiers":[
        {
            "category":"Professional",
            "subcategory":"Research",
            "type":"Services"
        }
    ],
    "sg:phone":"+1 303 425 6171",
    "sg:postcode":"80002",
    "sg:province":"CO",
    "sg:tags":[
        "environmental",
        "ecological"
    ],
    "wof:name":"U S Environmental Svc Inc",
    "wof:placetype":"venue"
},
  "geometry": {"coordinates":[-105.086085,39.80194],"type":"Point"}
}