{
  "type": "Feature",
  "properties": {
    "iso:country":"US",
    "sg:address":"4135 Thoreau Dr",
    "sg:city":"Colorado Springs",
    "sg:classifiers":[
        {
            "category":"Freight",
            "type":"Transportation"
        }
    ],
    "sg:phone":"+1 719 392 6981",
    "sg:postcode":"80916",
    "sg:province":"CO",
    "sg:tags":[
        "operator",
        "distance",
        "long",
        "trucking"
    ],
    "wof:name":"Macleod Trucking",
    "wof:placetype":"venue"
},
  "geometry": {"coordinates":[-104.752759,38.790955],"type":"Point"}
}