{
  "type": "Feature",
  "properties": {
    "iso:country":"US",
    "sg:address":"4984 Sonata Dr",
    "sg:city":"Colorado Springs",
    "sg:classifiers":[
        {
            "category":"Professional",
            "subcategory":"Business Services",
            "type":"Services"
        }
    ],
    "sg:phone":"+1 719 266 8905",
    "sg:postcode":"80918",
    "sg:province":"CO",
    "sg:tags":[
        "appraiser"
    ],
    "wof:name":"Aspen Leaf Appraisal Svc LLC",
    "wof:placetype":"venue"
},
  "geometry": {"coordinates":[-104.76701,38.903565],"type":"Point"}
}