{
  "type": "Feature",
  "properties": {
    "iso:country":"US",
    "sg:address":"2615 Grand Ave",
    "sg:city":"Grand Junction",
    "sg:classifiers":[
        {
            "category":"Health Services",
            "subcategory":"Chiropractor",
            "type":"Services"
        }
    ],
    "sg:phone":"+1 970 245 8121",
    "sg:postcode":"81501",
    "sg:province":"CO",
    "wof:name":"Jensen Chiropractic Ctr",
    "wof:placetype":"venue"
},
  "geometry": {"coordinates":[-108.534229,39.070078],"type":"Point"}
}