{
  "type": "Feature",
  "properties": {
    "addr:full":"3655 Brighton Blvd Denver CO 80216",
    "addr:housenumber":"3655",
    "addr:postcode":"80216",
    "addr:street":"Brighton Blvd",
    "iso:country":"US",
    "sg:address":"3655 Brighton Blvd",
    "sg:city":"Denver",
    "sg:classifiers":[
        {
            "category":"Building & Trades",
            "subcategory":"Plumbing",
            "type":"Services"
        }
    ],
    "sg:phone":"+1 303 308 9595",
    "sg:postcode":"80216",
    "sg:province":"CO",
    "sg:tags":[
        "contractor"
    ],
    "wof:name":"Aztec Plumbing",
    "wof:placetype":"venue"
},
  "geometry": {"coordinates":[-104.976046,39.772545],"type":"Point"}
}