{
  "type": "Feature",
  "properties": {
    "addr:full":"1627 Saratoga Dr Colorado Springs CO 80910",
    "addr:housenumber":"1627",
    "addr:postcode":"80910",
    "addr:street":"Saratoga Dr",
    "iso:country":"US",
    "sg:address":"1627 Saratoga Dr",
    "sg:city":"Colorado Springs",
    "sg:classifiers":[
        {
            "category":"Wholesale",
            "subcategory":"Electrical",
            "type":"Manufacturing & Wholesale Goods"
        }
    ],
    "sg:phone":"+1 719 471 7166",
    "sg:postcode":"80910",
    "sg:province":"CO",
    "sg:tags":[
        "communication",
        "radio",
        "system"
    ],
    "wof:name":"Brock Communications",
    "wof:placetype":"venue"
},
  "geometry": {"coordinates":[-104.775445,38.807615],"type":"Point"}
}