{
  "type": "Feature",
  "properties": {
    "addr:full":"5235 Co Rd 335 Pagosa Springs CO 81147",
    "addr:housenumber":"5235;335",
    "addr:postcode":"81147",
    "addr:street":"Co Rd",
    "iso:country":"US",
    "sg:address":"5235 Co Rd 335",
    "sg:city":"Pagosa Springs",
    "sg:classifiers":[
        {
            "category":"Professional",
            "subcategory":"Business Services",
            "type":"Services"
        }
    ],
    "sg:phone":"+1 970 264 6284",
    "sg:postcode":"81147",
    "sg:province":"CO",
    "sg:tags":[
        "drafting"
    ],
    "wof:name":"Wood's Design",
    "wof:placetype":"venue"
},
  "geometry": {"coordinates":[-107.00233799999999,37.137121],"type":"Point"}
}