{
  "type": "Feature",
  "properties": {
    "addr:full":"2129 13th St Boulder CO 80304",
    "addr:housenumber":"2129",
    "addr:postcode":"80304",
    "addr:street":"13Th St",
    "iso:country":"US",
    "sg:address":"2129 13th St",
    "sg:city":"Boulder",
    "sg:classifiers":[
        {
            "category":"Real Estate",
            "subcategory":"Architect",
            "type":"Services"
        }
    ],
    "sg:phone":"+1 303 444 2699",
    "sg:postcode":"80304",
    "sg:province":"CO",
    "wof:name":"Robert Netterstrom Arch & Dsgn",
    "wof:placetype":"venue"
},
  "geometry": {"coordinates":[-105.279352,40.019875],"type":"Point"}
}