{
  "type": "Feature",
  "properties": {
    "addr:full":"17851 W Colfax Ave Golden CO 80401",
    "addr:housenumber":"17851",
    "addr:postcode":"80401",
    "addr:street":"W Colfax Ave",
    "iso:country":"US",
    "sg:address":"17851 W Colfax Ave",
    "sg:city":"Golden",
    "sg:classifiers":[
        {
            "category":"Banks & Credit Unions",
            "subcategory":"Bank",
            "type":"Services"
        }
    ],
    "sg:phone":"+1 303 278 3548",
    "sg:postcode":"80401",
    "sg:province":"CO",
    "sg:tags":[
        "depository",
        "banking"
    ],
    "wof:name":"E T C Service Center",
    "wof:placetype":"venue"
},
  "geometry": {"coordinates":[-105.199174,39.720884],"type":"Point"}
}