{
  "type": "Feature",
  "properties": {
    "iso:country":"US",
    "sg:address":"30 Boulder Cres",
    "sg:city":"Colorado Springs",
    "sg:classifiers":[
        {
            "category":"Real Estate",
            "subcategory":"Real Estate Operator",
            "type":"Services"
        }
    ],
    "sg:phone":"+1 719 630 3564",
    "sg:postcode":"80903",
    "sg:province":"CO",
    "sg:tags":[
        "apartment"
    ],
    "wof:name":"Boulder Crescent Apartments",
    "wof:placetype":"venue"
},
  "geometry": {"coordinates":[-104.825903,38.838363],"type":"Point"}
}