{
  "type": "Feature",
  "properties": {
    "iso:country":"US",
    "sg:address":"2323 S Troy St",
    "sg:city":"Aurora",
    "sg:classifiers":[
        {
            "category":"Organizations",
            "subcategory":"Non-profit Organization",
            "type":"Services"
        }
    ],
    "sg:phone":"+1 303 752 2390",
    "sg:postcode":"80014",
    "sg:province":"CO",
    "sg:tags":[
        "information",
        "alcoholism",
        "treatment"
    ],
    "wof:name":"Creative Recovery Counseling",
    "wof:placetype":"venue"
},
  "geometry": {"coordinates":[-104.839353,39.674703],"type":"Point"}
}