{
  "type": "Feature",
  "properties": {
    "iso:country":"US",
    "sg:address":"10443 S Parker Rd",
    "sg:city":"Parker",
    "sg:classifiers":[
        {
            "category":"Shopping",
            "subcategory":"Bicycles & Sporting Goods",
            "type":"Retail Goods"
        }
    ],
    "sg:phone":"+1 303 805 1722",
    "sg:postcode":"80134",
    "sg:province":"CO",
    "sg:tags":[
        "shop",
        "ski"
    ],
    "wof:name":"Pro Sport Ski Rental",
    "wof:placetype":"venue"
},
  "geometry": {"coordinates":[-104.765021,39.517304],"type":"Point"}
}