{
  "type": "Feature",
  "properties": {
    "addr:full":"3805 Radiant Dr Colorado Springs CO 80917",
    "addr:housenumber":"3805",
    "addr:postcode":"80917",
    "addr:street":"Radiant Dr",
    "iso:country":"US",
    "sg:address":"3805 Radiant Dr",
    "sg:city":"Colorado Springs",
    "sg:classifiers":[
        {
            "category":"Retail",
            "subcategory":"Auto Repair",
            "type":"Services"
        }
    ],
    "sg:phone":"+1 719 574 4011",
    "sg:postcode":"80917",
    "sg:province":"CO",
    "sg:tags":[
        "body",
        "automobile",
        "painting"
    ],
    "wof:name":"Brothers & Sons Custom",
    "wof:placetype":"venue"
},
  "geometry": {"coordinates":[-104.75538899999999,38.86979],"type":"Point"}
}