{
  "type": "Feature",
  "properties": {
    "iso:country":"US",
    "sg:address":"5585 Erindale Dr",
    "sg:city":"Colorado Springs",
    "sg:classifiers":[
        {
            "category":"Travel",
            "subcategory":"Travel Agent",
            "type":"Entertainment"
        }
    ],
    "sg:phone":"+1 719 550 9500",
    "sg:postcode":"80918",
    "sg:province":"CO",
    "sg:tags":[
        "agency",
        "bureau"
    ],
    "wof:name":"Express Travel",
    "wof:placetype":"venue"
},
  "geometry": {"coordinates":[-104.78541199999999,38.912495],"type":"Point"}
}