{
  "type": "Feature",
  "properties": {
    "addr:full":"103 W Main St Florence CO 81226",
    "addr:housenumber":"103",
    "addr:postcode":"81226",
    "addr:street":"W Main St",
    "iso:country":"US",
    "sg:address":"103 W Main St",
    "sg:city":"Florence",
    "sg:classifiers":[
        {
            "category":"Freight",
            "type":"Transportation"
        }
    ],
    "sg:phone":"+1 719 784 6668",
    "sg:postcode":"81226",
    "sg:province":"CO",
    "sg:tags":[
        "commercial",
        "storage"
    ],
    "wof:name":"Robinson Storage Facility",
    "wof:placetype":"venue"
},
  "geometry": {"coordinates":[-105.119392,38.390161],"type":"Point"}
}