{
  "type": "Feature",
  "properties": {
    "addr:full":"158 S Forest St Denver CO 80246",
    "addr:housenumber":"158",
    "addr:postcode":"80246",
    "addr:street":"S Forest St",
    "iso:country":"US",
    "sg:address":"158 S Forest St",
    "sg:city":"Denver",
    "sg:classifiers":[
        {
            "category":"Professional",
            "type":"Services"
        }
    ],
    "sg:phone":"+1 303 780 7941",
    "sg:postcode":"80246",
    "sg:province":"CO",
    "wof:name":"Harr B Combs Jr",
    "wof:placetype":"venue"
},
  "geometry": {"coordinates":[-104.926897,39.714033],"type":"Point"}
}