{
  "type": "Feature",
  "properties": {
    "iso:country":"US",
    "sg:address":"201 E. 45th Ave",
    "sg:city":"Denver",
    "sg:classifiers":[
        {
            "category":"Restaurant",
            "type":"Food & Drink"
        }
    ],
    "sg:phone":"+1 720 468 7039",
    "sg:postcode":"80216",
    "sg:province":"CO",
    "sg:tags":[
        "mexican"
    ],
    "wof:name":"Tacos El Gordo",
    "wof:placetype":"venue"
},
  "geometry": {"coordinates":[-104.984554,39.778531],"type":"Point"}
}