{
  "type": "Feature",
  "properties": {
    "iso:country":"US",
    "sg:address":"1776 S Jackson St",
    "sg:city":"Denver",
    "sg:classifiers":[
        {
            "category":"Health Services",
            "subcategory":"Clinic",
            "type":"Services"
        }
    ],
    "sg:phone":"+1 303 584 9992",
    "sg:postcode":"80210",
    "sg:province":"CO",
    "sg:tags":[
        "counseling",
        "mental"
    ],
    "wof:name":"Jelinek J Michael Psyd",
    "wof:placetype":"venue"
},
  "geometry": {"coordinates":[-104.943001,39.684101],"type":"Point"}
}