{
  "type": "Feature",
  "properties": {
    "iso:country":"US",
    "sg:address":"5353 W Dartmouth Ave",
    "sg:city":"Denver",
    "sg:classifiers":[
        {
            "category":"Real Estate",
            "subcategory":"Real Estate Operator",
            "type":"Services"
        }
    ],
    "sg:phone":"+1 303 989 7300",
    "sg:postcode":"80227",
    "sg:province":"CO",
    "sg:tags":[
        "building",
        "nonresidential"
    ],
    "wof:name":"T & C Equities Ltd",
    "wof:placetype":"venue"
},
  "geometry": {"coordinates":[-105.054131,39.65622],"type":"Point"}
}