{
  "type": "Feature",
  "properties": {
    "iso:country":"US",
    "sg:address":"409 E Platte Ave",
    "sg:city":"Fort Morgan",
    "sg:classifiers":[
        {
            "category":"Health Services",
            "subcategory":"Optometrist",
            "type":"Services"
        }
    ],
    "sg:phone":"+1 970 867 3937",
    "sg:postcode":"80701",
    "sg:province":"CO",
    "wof:name":"Kiowa Eyecare Center",
    "wof:placetype":"venue"
},
  "geometry": {"coordinates":[-103.79663600000001,40.254057],"type":"Point"}
}