{
  "type": "Feature",
  "properties": {
    "iso:country":"US",
    "sg:address":"10345 Quivas St",
    "sg:city":"Denver",
    "sg:classifiers":[
        {
            "category":"Health Services",
            "subcategory":"Doctor",
            "type":"Services"
        }
    ],
    "sg:phone":"+1 303 452 5557",
    "sg:postcode":"80260",
    "sg:province":"CO",
    "sg:tags":[
        "dentist"
    ],
    "wof:name":"Edward Leone Jr DDS",
    "wof:placetype":"venue"
},
  "geometry": {"coordinates":[-105.00743900000001,39.885131],"type":"Point"}
}