{
  "type": "Feature",
  "properties": {
    "iso:country":"US",
    "sg:address":"6400 S Fiddlers Green Cir",
    "sg:city":"Englewood",
    "sg:classifiers":[
        {
            "category":"Real Estate",
            "subcategory":"Real Estate Agent",
            "type":"Services"
        }
    ],
    "sg:phone":"+1 303 930 5127",
    "sg:postcode":"80111",
    "sg:province":"CO",
    "wof:name":"Matchett Maker Team",
    "wof:placetype":"venue"
},
  "geometry": {"coordinates":[-104.89016700000001,39.60013],"type":"Point"}
}