{
  "type": "Feature",
  "properties": {
    "addr:full":"650 S Alton Way Denver CO 80247",
    "addr:housenumber":"650",
    "addr:postcode":"80247",
    "addr:street":"S Alton Way",
    "iso:country":"US",
    "sg:address":"650 S Alton Way",
    "sg:city":"Denver",
    "sg:classifiers":[
        {
            "category":"Professional",
            "subcategory":"Lawyer & Legal Services",
            "type":"Services"
        }
    ],
    "sg:phone":"+1 303 344 8074",
    "sg:postcode":"80247",
    "sg:province":"CO",
    "sg:tags":[
        "attorney"
    ],
    "wof:name":"Robert R Irwin",
    "wof:placetype":"venue"
},
  "geometry": {"coordinates":[-104.88263999999999,39.703571],"type":"Point"}
}