{
  "type": "Feature",
  "properties": {
    "iso:country":"US",
    "sg:address":"1820 Broadway",
    "sg:city":"Denver",
    "sg:classifiers":[
        {
            "category":"Organizations",
            "subcategory":"Religious Organization",
            "type":"Services"
        }
    ],
    "sg:phone":"+1 303 839 1493",
    "sg:postcode":"80203",
    "sg:province":"CO",
    "sg:tags":[
        "church"
    ],
    "sg:website":"www.trinityumc.org/",
    "wof:name":"Trinity United Methodist Church",
    "wof:placetype":"venue"
},
  "geometry": {"coordinates":[-104.986951,39.74538],"type":"Point"}
}