{
  "type": "Feature",
  "properties": {
    "addr:full":"4405 Waverly Way Littleton CO 80126",
    "addr:housenumber":"4405",
    "addr:postcode":"80126",
    "addr:street":"Waverly Way",
    "iso:country":"US",
    "sg:address":"4405 Waverly Way",
    "sg:city":"Littleton",
    "sg:classifiers":[
        {
            "category":"Building & Trades",
            "subcategory":"Construction",
            "type":"Services"
        }
    ],
    "sg:phone":"+1 303 470 9303",
    "sg:postcode":"80126",
    "sg:province":"CO",
    "sg:tags":[
        "nonresidential"
    ],
    "wof:name":"Functnal Dsign Rennovation LLC",
    "wof:placetype":"venue"
},
  "geometry": {"coordinates":[-104.937889,39.537669],"type":"Point"}
}