{
  "type": "Feature",
  "properties": {
    "addr:full":"309 6th St Crested Butte CO 81224",
    "addr:housenumber":"309",
    "addr:postcode":"81224",
    "addr:street":"6Th St",
    "iso:country":"US",
    "sg:address":"309 6th St",
    "sg:city":"Crested Butte",
    "sg:classifiers":[
        {
            "category":"Personal",
            "subcategory":"Beauty Salon",
            "type":"Services"
        }
    ],
    "sg:phone":"+1 970 349 0144",
    "sg:postcode":"81224",
    "sg:province":"CO",
    "wof:name":"Studio Xstream",
    "wof:placetype":"venue"
},
  "geometry": {"coordinates":[-106.98103399999999,38.8706],"type":"Point"}
}