{
  "type": "Feature",
  "properties": {
    "iso:country":"US",
    "sg:address":"12017 Pecos St",
    "sg:city":"Northglenn",
    "sg:classifiers":[
        {
            "category":"Shopping",
            "type":"Retail Goods"
        }
    ],
    "sg:phone":"+1 303 450 0505",
    "sg:postcode":"80234",
    "sg:province":"CO",
    "sg:tags":[
        "spa",
        "hot",
        "tub"
    ],
    "wof:name":"C & S The Hot Tub Store",
    "wof:placetype":"venue"
},
  "geometry": {"coordinates":[-105.006186,39.914351],"type":"Point"}
}