{
  "type": "Feature",
  "properties": {
    "addr:full":"1726 Clemson Dr Colorado Springs CO 80909",
    "addr:housenumber":"1726",
    "addr:postcode":"80909",
    "addr:street":"Clemson Dr",
    "iso:country":"US",
    "sg:address":"1726 Clemson Dr",
    "sg:city":"Colorado Springs",
    "sg:classifiers":[
        {
            "category":"Real Estate",
            "subcategory":"Real Estate Operator",
            "type":"Services"
        }
    ],
    "sg:phone":"+1 719 574 6260",
    "sg:postcode":"80909",
    "sg:province":"CO",
    "sg:tags":[
        "building",
        "apartment"
    ],
    "wof:name":"Clemson Manor Apartments",
    "wof:placetype":"venue"
},
  "geometry": {"coordinates":[-104.760239,38.85593],"type":"Point"}
}