{
  "type": "Feature",
  "properties": {
    "addr:full":"5944 Oneida St Commerce City CO 80022",
    "addr:housenumber":"5944",
    "addr:postcode":"80022",
    "addr:street":"Oneida St",
    "iso:country":"US",
    "sg:address":"5944 Oneida St",
    "sg:city":"Commerce City",
    "sg:classifiers":[
        {
            "category":"Professional",
            "type":"Services"
        }
    ],
    "sg:phone":"+1 303 287 1953",
    "sg:postcode":"80022",
    "sg:province":"CO",
    "wof:name":"Jorge C Esparza",
    "wof:placetype":"venue"
},
  "geometry": {"coordinates":[-104.90813199999999,39.804846],"type":"Point"}
}