{
  "type": "Feature",
  "properties": {
    "addr:full":"704 8th St Blanca CO 81123",
    "addr:housenumber":"704",
    "addr:postcode":"81123",
    "addr:street":"8Th St",
    "iso:country":"US",
    "sg:address":"704 8th St",
    "sg:city":"Blanca",
    "sg:classifiers":[
        {
            "category":"Government",
            "subcategory":"Fire Station",
            "type":"Public Place"
        }
    ],
    "sg:phone":"+1 719 379 3603",
    "sg:postcode":"81123",
    "sg:province":"CO",
    "sg:tags":[
        "department"
    ],
    "wof:name":"Blanca Fire Dept",
    "wof:placetype":"venue"
},
  "geometry": {"coordinates":[-105.516108,37.438594],"type":"Point"}
}