{
  "type": "Feature",
  "properties": {
    "iso:country":"US",
    "sg:address":"1001 Main St",
    "sg:city":"Longmont",
    "sg:classifiers":[
        {
            "category":"Retail",
            "subcategory":"Auto Repair",
            "type":"Services"
        }
    ],
    "sg:phone":"+1 303 772 8655",
    "sg:postcode":"80501",
    "sg:province":"CO",
    "sg:tags":[
        "repairing",
        "automobile"
    ],
    "wof:name":"Hi Tek Auto Repair",
    "wof:placetype":"venue"
},
  "geometry": {"coordinates":[-105.102436,40.177645],"type":"Point"}
}