{
  "type": "Feature",
  "properties": {
    "addr:full":"140 N Mesa St Fruita CO 81521",
    "addr:housenumber":"140",
    "addr:postcode":"81521",
    "addr:street":"N Mesa St",
    "iso:country":"US",
    "sg:address":"140 N Mesa St",
    "sg:city":"Fruita",
    "sg:classifiers":[
        {
            "category":"Shopping",
            "subcategory":"Optical Goods",
            "type":"Retail Goods"
        }
    ],
    "sg:phone":"+1 970 858 6600",
    "sg:postcode":"81521",
    "sg:province":"CO",
    "wof:name":"Visual Eyes Eye Care",
    "wof:placetype":"venue"
},
  "geometry": {"coordinates":[-108.733572,39.159853],"type":"Point"}
}