{
  "type": "Feature",
  "properties": {
    "iso:country":"US",
    "sg:address":"1001 Hwy 92",
    "sg:city":"Delta",
    "sg:classifiers":[
        {
            "category":"Cinema",
            "subcategory":"Movie Theater",
            "type":"Entertainment"
        }
    ],
    "sg:phone":"+1 970 874 9556",
    "sg:postcode":"81416",
    "sg:province":"CO",
    "wof:name":"Tru Vu Drive In Theatre",
    "wof:placetype":"venue"
},
  "geometry": {"coordinates":[-108.059189,38.75066],"type":"Point"}
}