{
  "type": "Feature",
  "properties": {
    "iso:country":"US",
    "sg:address":"4172 S Cathay Way",
    "sg:city":"Aurora",
    "sg:classifiers":[
        {
            "category":"Building & Trades",
            "subcategory":"Construction",
            "type":"Services"
        }
    ],
    "sg:phone":"+1 303 680 7323",
    "sg:postcode":"80013",
    "sg:province":"CO",
    "sg:tags":[
        "carpentry",
        "contractor"
    ],
    "wof:name":"Woodsmith Carpenter",
    "wof:placetype":"venue"
},
  "geometry": {"coordinates":[-104.767039,39.640703],"type":"Point"}
}