{
  "type": "Feature",
  "properties": {
    "iso:country":"US",
    "sg:address":"253 S Madison Ave",
    "sg:city":"Louisville",
    "sg:classifiers":[
        {
            "category":"Building & Trades",
            "subcategory":"Construction",
            "type":"Services"
        }
    ],
    "sg:phone":"+1 303 588 8372",
    "sg:postcode":"80027",
    "sg:province":"CO",
    "sg:tags":[
        "house"
    ],
    "wof:name":"Holly C O Neil",
    "wof:placetype":"venue"
},
  "geometry": {"coordinates":[-105.15295500000001,39.971716],"type":"Point"}
}