{
  "type": "Feature",
  "properties": {
    "addr:full":"7575 W Colfax Ave Denver CO 80214",
    "addr:housenumber":"7575",
    "addr:postcode":"80214",
    "addr:street":"W Colfax Ave",
    "iso:country":"US",
    "sg:address":"7575 W Colfax Ave",
    "sg:city":"Denver",
    "sg:classifiers":[
        {
            "category":"Banks & Credit Unions",
            "subcategory":"Bank",
            "type":"Services"
        }
    ],
    "sg:phone":"+1 303 863 6864",
    "sg:postcode":"80214",
    "sg:province":"CO",
    "sg:tags":[
        "federal",
        "savings",
        "institution"
    ],
    "wof:name":"Wells Fargo",
    "wof:placetype":"venue"
},
  "geometry": {"coordinates":[-105.079707,39.740389],"type":"Point"}
}