{
  "type": "Feature",
  "properties": {
    "addr:full":"11878 E Ida Pl Englewood CO 80111",
    "addr:housenumber":"11878",
    "addr:postcode":"80111",
    "addr:street":"E Ida Pl",
    "iso:country":"US",
    "sg:address":"11878 E Ida Pl",
    "sg:city":"Englewood",
    "sg:classifiers":[
        {
            "category":"Manufacturing",
            "subcategory":"Printing",
            "type":"Manufacturing & Wholesale Goods"
        }
    ],
    "sg:phone":"+1 303 694 2697",
    "sg:postcode":"80111",
    "sg:province":"CO",
    "sg:tags":[
        "publishing"
    ],
    "wof:name":"Transmit Publications Inc",
    "wof:placetype":"venue"
},
  "geometry": {"coordinates":[-104.850448,39.610884],"type":"Point"}
}