{
  "type": "Feature",
  "properties": {
    "iso:country":"US",
    "sg:address":"4797 S Co Rd 193",
    "sg:city":"Byers",
    "sg:classifiers":[
        {
            "category":"Farming",
            "subcategory":"Farm & Veterinary Services",
            "type":"Manufacturing & Wholesale Goods"
        }
    ],
    "sg:phone":"+1 303 822 5882",
    "sg:postcode":"80103",
    "sg:province":"CO",
    "sg:tags":[
        "livestock"
    ],
    "wof:name":"Bar BR Cattle Co",
    "wof:placetype":"venue"
},
  "geometry": {"coordinates":[-104.15435600000001,39.628891],"type":"Point"}
}