{
  "type": "Feature",
  "properties": {
    "addr:full":"6690 Barrell Race Dr Colorado Springs CO 80918",
    "addr:postcode":"6690;80918",
    "addr:street":"Barrell Race Dr",
    "iso:country":"US",
    "sg:address":"6690 Barrell Race Dr",
    "sg:city":"Colorado Springs",
    "sg:classifiers":[
        {
            "category":"Shopping",
            "subcategory":"Discount & Variety Stores",
            "type":"Retail Goods"
        }
    ],
    "sg:phone":"+1 719 264 1755",
    "sg:postcode":"80918",
    "sg:province":"CO",
    "sg:tags":[
        "merchandise",
        "general"
    ],
    "wof:name":"First-Impressions",
    "wof:placetype":"venue"
},
  "geometry": {"coordinates":[-104.745116,38.925162],"type":"Point"}
}