{
  "type": "Feature",
  "properties": {
    "iso:country":"US",
    "sg:address":"104 S Cascade Ave",
    "sg:city":"Colorado Springs",
    "sg:classifiers":[
        {
            "category":"Insurance",
            "subcategory":"Title Insurance",
            "type":"Services"
        },
        {
            "category":"Real Estate",
            "subcategory":"Real Estate Services",
            "type":"Services"
        }
    ],
    "sg:phone":"+1 719 475 8800",
    "sg:postcode":"80903",
    "sg:province":"CO",
    "sg:tags":[
        "company",
        "carrier",
        "abstract"
    ],
    "wof:name":"Commonwealth Land Title Insur",
    "wof:placetype":"venue"
},
  "geometry": {"coordinates":[-104.825417,38.829534],"type":"Point"}
}