{
  "type": "Feature",
  "properties": {
    "addr:full":"2732 Willamette Pl Colorado Springs CO 80909",
    "addr:housenumber":"2732",
    "addr:postcode":"80909",
    "addr:street":"Willamette Pl",
    "iso:country":"US",
    "sg:address":"2732 Willamette Pl",
    "sg:city":"Colorado Springs",
    "sg:classifiers":[
        {
            "category":"Retail",
            "subcategory":"Auto Repair",
            "type":"Services"
        }
    ],
    "sg:phone":"+1 719 577 7423",
    "sg:postcode":"80909",
    "sg:province":"CO",
    "sg:tags":[
        "body",
        "automobile",
        "painting"
    ],
    "wof:name":"Blosser's Collision Ctr",
    "wof:placetype":"venue"
},
  "geometry": {"coordinates":[-104.77650199999999,38.84122],"type":"Point"}
}