{
  "type": "Feature",
  "properties": {
    "iso:country":"US",
    "sg:address":"1130 7th Ave",
    "sg:city":"Greeley",
    "sg:classifiers":[
        {
            "category":"Home & Garden",
            "subcategory":"Building Materials",
            "type":"Retail Goods"
        }
    ],
    "sg:phone":"+1 970 352 5171",
    "sg:postcode":"80631",
    "sg:province":"CO",
    "sg:tags":[
        "lumber"
    ],
    "wof:name":"United Building Ctr",
    "wof:placetype":"venue"
},
  "geometry": {"coordinates":[-104.688987,40.420194],"type":"Point"}
}