{
  "type": "Feature",
  "properties": {
    "iso:country":"US",
    "sg:address":"2401 S Downing St",
    "sg:city":"Denver",
    "sg:classifiers":[
        {
            "category":"Social Services",
            "subcategory":"Job Training",
            "type":"Services"
        }
    ],
    "sg:phone":"+1 303 722 2300",
    "sg:postcode":"80210",
    "sg:province":"CO",
    "sg:tags":[
        "rehabilitation"
    ],
    "sg:website":"www.centen.net",
    "wof:name":"Centennial Group",
    "wof:placetype":"venue"
},
  "geometry": {"coordinates":[-104.973465,39.671278],"type":"Point"}
}