{
  "type": "Feature",
  "properties": {
    "iso:country":"US",
    "sg:address":"5491 W 88th Ave",
    "sg:city":"Westminster",
    "sg:classifiers":[
        {
            "category":"Restaurant",
            "type":"Food & Drink"
        }
    ],
    "sg:menulink":"http://www.allmenus.com/co/northeast-jefferson/128808-subway/menu/",
    "sg:phone":"+1 303 996 0056",
    "sg:postcode":"80031",
    "sg:province":"CO",
    "sg:tags":[
        "american",
        "sandwich"
    ],
    "wof:name":"Subway",
    "wof:placetype":"venue"
},
  "geometry": {"coordinates":[-105.0605,39.859452],"type":"Point"}
}