{
  "type": "Feature",
  "properties": {
    "addr:full":"6515 N Pinewood Dr Parker CO 80134",
    "addr:housenumber":"6515",
    "addr:postcode":"80134",
    "addr:street":"N Pinewood Dr",
    "iso:country":"US",
    "sg:address":"6515 N Pinewood Dr",
    "sg:city":"Parker",
    "sg:classifiers":[
        {
            "category":"Real Estate",
            "subcategory":"Real Estate Agent",
            "type":"Services"
        }
    ],
    "sg:phone":"+1 303 841 6177",
    "sg:postcode":"80134",
    "sg:province":"CO",
    "wof:name":"Daniel Property Maintenance",
    "wof:placetype":"venue"
},
  "geometry": {"coordinates":[-104.752703,39.456446],"type":"Point"}
}