{
  "type": "Feature",
  "properties": {
    "iso:country":"US",
    "sg:address":"168 E Bridge St",
    "sg:city":"Brighton",
    "sg:classifiers":[
        {
            "category":"Shopping",
            "subcategory":"Used Merchandise",
            "type":"Retail Goods"
        }
    ],
    "sg:phone":"+1 303 637 0187",
    "sg:postcode":"80601",
    "sg:province":"CO",
    "sg:tags":[
        "shop",
        "consignment"
    ],
    "wof:name":"Little Tykes Trading Post",
    "wof:placetype":"venue"
},
  "geometry": {"coordinates":[-104.820257,39.98674],"type":"Point"}
}