{
  "type": "Feature",
  "properties": {
    "iso:country":"US",
    "sg:address":"4141 Arapahoe Ave",
    "sg:city":"Boulder",
    "sg:classifiers":[
        {
            "category":"Real Estate",
            "subcategory":"Architect",
            "type":"Services"
        }
    ],
    "sg:phone":"+1 303 444 2987",
    "sg:postcode":"80303",
    "sg:province":"CO",
    "sg:tags":[
        "architectural"
    ],
    "wof:name":"Junge - Associates-Aia",
    "wof:placetype":"venue"
},
  "geometry": {"coordinates":[-105.244006,40.014717],"type":"Point"}
}