{
  "type": "Feature",
  "properties": {
    "iso:country":"US",
    "sg:address":"6980 E 54th Pl",
    "sg:city":"Commerce City",
    "sg:classifiers":[
        {
            "category":"Manufacturing",
            "subcategory":"Wood Products",
            "type":"Manufacturing & Wholesale Goods"
        }
    ],
    "sg:phone":"+1 303 287 8053",
    "sg:postcode":"80022",
    "sg:province":"CO",
    "sg:tags":[
        "pole",
        "mfg",
        "utility"
    ],
    "sg:website":"www.whatley.com",
    "wof:name":"W J Whatley Inc",
    "wof:placetype":"venue"
},
  "geometry": {"coordinates":[-104.905609,39.795593],"type":"Point"}
}