{
  "type": "Feature",
  "properties": {
    "iso:country":"US",
    "sg:address":"3107 Lake Ave",
    "sg:city":"Pueblo",
    "sg:classifiers":[
        {
            "category":"Restaurant",
            "type":"Food & Drink"
        }
    ],
    "sg:phone":"+1 719 564 9146",
    "sg:postcode":"81004",
    "sg:province":"CO",
    "sg:tags":[
        "eating"
    ],
    "wof:name":"Pepper Coach Cafe",
    "wof:placetype":"venue"
},
  "geometry": {"coordinates":[-104.625159,38.219985],"type":"Point"}
}