{
  "type": "Feature",
  "properties": {
    "iso:country":"US",
    "sg:address":"7416 Valmont Rd",
    "sg:city":"Boulder",
    "sg:classifiers":[
        {
            "category":"Professional",
            "type":"Services"
        }
    ],
    "sg:phone":"+1 303 666 6397",
    "sg:postcode":"80301",
    "sg:province":"CO",
    "sg:tags":[
        "establishment"
    ],
    "wof:name":"Cure Organic Farm",
    "wof:placetype":"venue"
},
  "geometry": {"coordinates":[-105.181573,40.032857],"type":"Point"}
}