{
  "type": "Feature",
  "properties": {
    "iso:country":"US",
    "sg:address":"15932 Co Rd 50",
    "sg:city":"Burlington",
    "sg:classifiers":[
        {
            "category":"Professional",
            "type":"Services"
        }
    ],
    "sg:phone":"+1 719 346 5025",
    "sg:postcode":"80807",
    "sg:province":"CO",
    "wof:name":"Greg Andrews",
    "wof:placetype":"venue"
},
  "geometry": {"coordinates":[-102.240987,39.264385],"type":"Point"}
}