{
  "type": "Feature",
  "properties": {
    "iso:country":"US",
    "sg:address":"8000 E 12th Ave",
    "sg:city":"Denver",
    "sg:classifiers":[
        {
            "category":"Manufacturing",
            "subcategory":"Tools & Machinery",
            "type":"Manufacturing & Wholesale Goods"
        }
    ],
    "sg:phone":"+1 303 321 9810",
    "sg:postcode":"80220",
    "sg:province":"CO",
    "sg:tags":[
        "surgical",
        "mfg"
    ],
    "wof:name":"Prime Medical Servic E",
    "wof:placetype":"venue"
},
  "geometry": {"coordinates":[-104.898769,39.735628],"type":"Point"}
}