{
  "type": "Feature",
  "properties": {
    "addr:full":"15 Empire Pl Longmont CO 80501",
    "addr:housenumber":"15",
    "addr:postcode":"80501",
    "addr:street":"Empire Pl",
    "iso:country":"US",
    "sg:address":"15 Empire Pl",
    "sg:city":"Longmont",
    "sg:classifiers":[
        {
            "category":"Banks & Credit Unions",
            "subcategory":"Financial Services",
            "type":"Services"
        }
    ],
    "sg:phone":"+1 303 776 4458",
    "sg:postcode":"80501",
    "sg:province":"CO",
    "sg:tags":[
        "investor"
    ],
    "wof:name":"Gholson & Son Investments Inc",
    "wof:placetype":"venue"
},
  "geometry": {"coordinates":[-105.09229999999999,40.178923],"type":"Point"}
}