{
  "type": "Feature",
  "properties": {
    "addr:full":"3411 Santa Rosa St Colorado Springs CO 80909",
    "addr:housenumber":"3411",
    "addr:postcode":"80909",
    "addr:street":"Santa Rosa St",
    "iso:country":"US",
    "sg:address":"3411 Santa Rosa St",
    "sg:city":"Colorado Springs",
    "sg:classifiers":[
        {
            "category":"Building & Trades",
            "subcategory":"Plumbing",
            "type":"Services"
        }
    ],
    "sg:phone":"+1 719 635 1124",
    "sg:postcode":"80909",
    "sg:province":"CO",
    "sg:tags":[
        "heating",
        "contractor"
    ],
    "wof:name":"American Heating & Cooling",
    "wof:placetype":"venue"
},
  "geometry": {"coordinates":[-104.76673599999999,38.842062],"type":"Point"}
}