{
  "type": "Feature",
  "properties": {
    "addr:full":"7195 W Princeton Ave Denver CO 80235",
    "addr:housenumber":"7195",
    "addr:postcode":"80235",
    "addr:street":"W Princeton Ave",
    "iso:country":"US",
    "sg:address":"7195 W Princeton Ave",
    "sg:city":"Denver",
    "sg:classifiers":[
        {
            "category":"Banks & Credit Unions",
            "subcategory":"Financial Services",
            "type":"Services"
        }
    ],
    "sg:phone":"+1 303 980 8363",
    "sg:postcode":"80235",
    "sg:province":"CO",
    "sg:tags":[
        "investor"
    ],
    "wof:name":"Cowtowne Investments",
    "wof:placetype":"venue"
},
  "geometry": {"coordinates":[-105.076018,39.639812],"type":"Point"}
}