{
  "type": "Feature",
  "properties": {
    "iso:country":"US",
    "sg:address":"1147 S Prairie Ave",
    "sg:city":"Pueblo",
    "sg:classifiers":[
        {
            "category":"Shopping",
            "subcategory":"Bicycles & Sporting Goods",
            "type":"Retail Goods"
        }
    ],
    "sg:phone":"+1 719 566 6925",
    "sg:postcode":"81005",
    "sg:province":"CO",
    "wof:name":"Vance's Bicycle World",
    "wof:placetype":"venue"
},
  "geometry": {"coordinates":[-104.643872,38.246696],"type":"Point"}
}