{
  "type": "Feature",
  "properties": {
    "iso:country":"US",
    "sg:address":"7420 Greenwood Blvd",
    "sg:city":"Denver",
    "sg:classifiers":[
        {
            "category":"Building & Trades",
            "subcategory":"Construction",
            "type":"Services"
        }
    ],
    "sg:phone":"+1 303 426 5862",
    "sg:postcode":"80221",
    "sg:province":"CO",
    "sg:tags":[
        "hardwood",
        "flooring"
    ],
    "wof:name":"Tc Hardwood Floor Inc",
    "wof:placetype":"venue"
},
  "geometry": {"coordinates":[-104.994787,39.831076],"type":"Point"}
}