{
  "type": "Feature",
  "properties": {
    "addr:full":"2720 4th St Boulder CO 80304",
    "addr:housenumber":"2720",
    "addr:postcode":"80304",
    "addr:street":"4Th St",
    "iso:country":"US",
    "sg:address":"2720 4th St",
    "sg:city":"Boulder",
    "sg:classifiers":[
        {
            "category":"Building & Trades",
            "subcategory":"Construction",
            "type":"Services"
        }
    ],
    "sg:phone":"+1 303 447 9749",
    "sg:postcode":"80304",
    "sg:province":"CO",
    "sg:tags":[
        "general",
        "contractor"
    ],
    "wof:name":"Jhi Designs Inc",
    "wof:placetype":"venue"
},
  "geometry": {"coordinates":[-105.291421,40.026491],"type":"Point"}
}