{
  "type": "Feature",
  "properties": {
    "addr:full":"1400 Carr St Denver CO 80214",
    "addr:housenumber":"1400",
    "addr:postcode":"80214",
    "addr:street":"Carr St",
    "iso:country":"US",
    "sg:address":"1400 Carr St",
    "sg:city":"Denver",
    "sg:classifiers":[
        {
            "category":"Professional",
            "subcategory":"Management & Consulting",
            "type":"Services"
        }
    ],
    "sg:phone":"+1 303 238 5123",
    "sg:postcode":"80214",
    "sg:province":"CO",
    "wof:name":"Personal Benefits Svcs Seminar",
    "wof:placetype":"venue"
},
  "geometry": {"coordinates":[-105.09075799999999,39.740261],"type":"Point"}
}