{
  "type": "Feature",
  "properties": {
    "addr:full":"30 Murray St Niwot CO 80544",
    "addr:housenumber":"30",
    "addr:postcode":"80544",
    "addr:street":"Murray St",
    "iso:country":"US",
    "sg:address":"30 Murray St",
    "sg:city":"Niwot",
    "sg:classifiers":[
        {
            "category":"Shopping",
            "type":"Retail Goods"
        }
    ],
    "sg:phone":"+1 303 652 2794",
    "sg:postcode":"80544",
    "sg:province":"CO",
    "sg:tags":[
        "water",
        "heater"
    ],
    "wof:name":"A-1 Plumbing & Heating Co",
    "wof:placetype":"venue"
},
  "geometry": {"coordinates":[-105.172854,40.103579],"type":"Point"}
}