{
  "type": "Feature",
  "properties": {
    "addr:full":"14160 E Evans Ave Aurora CO 80014",
    "addr:housenumber":"14160",
    "addr:postcode":"80014",
    "addr:street":"E Evans Ave",
    "iso:country":"US",
    "sg:address":"14160 E Evans Ave",
    "sg:city":"Aurora",
    "sg:classifiers":[
        {
            "category":"Professional",
            "type":"Services"
        }
    ],
    "sg:phone":"+1 303 752 9200",
    "sg:postcode":"80014",
    "sg:province":"CO",
    "wof:name":"Anne Richter Clsscal Hmoepathy",
    "wof:placetype":"venue"
},
  "geometry": {"coordinates":[-104.822142,39.677997],"type":"Point"}
}