{
  "type": "Feature",
  "properties": {
    "addr:full":"1910 14th Street Rd Greeley CO 80631",
    "addr:housenumber":"1910",
    "addr:postcode":"80631",
    "addr:street":"14Th Street Rd",
    "iso:country":"US",
    "sg:address":"1910 14th Street Rd",
    "sg:city":"Greeley",
    "sg:classifiers":[
        {
            "category":"Home & Garden",
            "subcategory":"Garden Supply",
            "type":"Retail Goods"
        }
    ],
    "sg:phone":"+1 970 356 9265",
    "sg:postcode":"80631",
    "sg:province":"CO",
    "wof:name":"D D Lawn Garden Care",
    "wof:placetype":"venue"
},
  "geometry": {"coordinates":[-104.711285,40.416627],"type":"Point"}
}