{
  "type": "Feature",
  "properties": {
    "iso:country":"US",
    "sg:address":"35 S Selig Ave",
    "sg:city":"Montrose",
    "sg:classifiers":[
        {
            "category":"Insurance",
            "subcategory":"Insurance Agent",
            "type":"Services"
        }
    ],
    "sg:phone":"+1 970 249 2222",
    "sg:postcode":"81401",
    "sg:province":"CO",
    "wof:name":"Insurance Center",
    "wof:placetype":"venue"
},
  "geometry": {"coordinates":[-107.878433,38.477804],"type":"Point"}
}