{
  "type": "Feature",
  "properties": {
    "iso:country":"US",
    "sg:address":"742 Laurel Hill Ct",
    "sg:city":"Loveland",
    "sg:classifiers":[
        {
            "category":"Professional",
            "subcategory":"Lawyer & Legal Services",
            "type":"Services"
        }
    ],
    "sg:phone":"+1 970 669 1266",
    "sg:postcode":"80537",
    "sg:province":"CO",
    "sg:tags":[
        "patent",
        "agent"
    ],
    "wof:name":"Tobey & Assoc",
    "wof:placetype":"venue"
},
  "geometry": {"coordinates":[-105.15300499999999,40.3866],"type":"Point"}
}