{
  "type": "Feature",
  "properties": {
    "iso:country":"US",
    "sg:address":"8405 S Park Meadows Center Dr",
    "sg:city":"Littleton",
    "sg:classifiers":[
        {
            "category":"Shopping",
            "subcategory":"Clothing, Apparel, & Fashions",
            "type":"Retail Goods"
        }
    ],
    "sg:phone":"+1 303 790 9173",
    "sg:postcode":"80124",
    "sg:province":"CO",
    "sg:tags":[
        "accessory"
    ],
    "wof:name":"Ties Etc",
    "wof:placetype":"venue"
},
  "geometry": {"coordinates":[-104.875241,39.559106],"type":"Point"}
}