{
  "type": "Feature",
  "properties": {
    "addr:full":"7012 S Eudora St Littleton CO 80122",
    "addr:housenumber":"7012",
    "addr:postcode":"80122",
    "addr:street":"S Eudora St",
    "iso:country":"US",
    "sg:address":"7012 S Eudora St",
    "sg:city":"Littleton",
    "sg:classifiers":[
        {
            "category":"Real Estate",
            "subcategory":"Real Estate Operator",
            "type":"Services"
        }
    ],
    "sg:phone":"+1 303 804 5923",
    "sg:postcode":"80122",
    "sg:province":"CO",
    "sg:tags":[
        "building",
        "nonresidential"
    ],
    "wof:name":"Pb &R Properties LLC",
    "wof:placetype":"venue"
},
  "geometry": {"coordinates":[-104.93037099999999,39.589586],"type":"Point"}
}