{
  "type": "Feature",
  "properties": {
    "iso:country":"US",
    "sg:address":"4001 S Mason St",
    "sg:city":"Fort Collins",
    "sg:classifiers":[
        {
            "category":"Travel",
            "subcategory":"Hotels & Motels",
            "type":"Entertainment"
        }
    ],
    "sg:phone":"+1 970 282 9047",
    "sg:postcode":"80525",
    "sg:province":"CO",
    "sg:website":"www.ftcollinsquality.com",
    "wof:name":"Quality Inn & Suites",
    "wof:placetype":"venue"
},
  "geometry": {"coordinates":[-105.07951799999999,40.53265],"type":"Point"}
}