{
  "type": "Feature",
  "properties": {
    "iso:country":"US",
    "sg:address":"410 E Railroad Ave",
    "sg:city":"Fort Morgan",
    "sg:classifiers":[
        {
            "category":"Home & Garden",
            "subcategory":"Household Appliances",
            "type":"Retail Goods"
        }
    ],
    "sg:phone":"+1 970 768 6929",
    "sg:postcode":"80701",
    "sg:province":"CO",
    "sg:tags":[
        "cleaners",
        "vacuum"
    ],
    "wof:name":"Ne Colorado Sew & Vac",
    "wof:placetype":"venue"
},
  "geometry": {"coordinates":[-103.796666,40.24842],"type":"Point"}
}