{
  "type": "Feature",
  "properties": {
    "iso:country":"US",
    "sg:address":"5755 Mark Dabling Blvd",
    "sg:city":"Colorado Springs",
    "sg:classifiers":[
        {
            "category":"Manufacturing",
            "subcategory":"Electronics",
            "type":"Manufacturing & Wholesale Goods"
        }
    ],
    "sg:phone":"+1 719 590 9811",
    "sg:postcode":"80919",
    "sg:province":"CO",
    "sg:tags":[
        "semiconductor",
        "devices"
    ],
    "wof:name":"Kyocera America Inc",
    "wof:placetype":"venue"
},
  "geometry": {"coordinates":[-104.822952,38.910618],"type":"Point"}
}