{
  "type": "Feature",
  "properties": {
    "iso:country":"US",
    "sg:address":"111 S Cascade Ave",
    "sg:city":"Colorado Springs",
    "sg:classifiers":[
        {
            "category":"Utilities",
            "type":"Services"
        }
    ],
    "sg:phone":"+1 719 448 8307",
    "sg:postcode":"80903",
    "sg:province":"CO",
    "sg:tags":[
        "electric",
        "combination"
    ],
    "wof:name":"Customer Service",
    "wof:placetype":"venue"
},
  "geometry": {"coordinates":[-104.82529,38.829657],"type":"Point"}
}