{
  "type": "Feature",
  "properties": {
    "iso:country":"US",
    "sg:address":"5005 Larkspur St",
    "sg:city":"Littleton",
    "sg:classifiers":[
        {
            "category":"Professional",
            "type":"Services"
        }
    ],
    "sg:phone":"+1 303 730 2088",
    "sg:postcode":"80123",
    "sg:province":"CO",
    "wof:name":"Brittoil Co LLC",
    "wof:placetype":"venue"
},
  "geometry": {"coordinates":[-105.050163,39.626543],"type":"Point"}
}