{
  "type": "Feature",
  "properties": {
    "addr:full":"4579 S Quail St Littleton CO 80127",
    "addr:housenumber":"4579",
    "addr:postcode":"80127",
    "addr:street":"S Quail St",
    "iso:country":"US",
    "sg:address":"4579 S Quail St",
    "sg:city":"Littleton",
    "sg:classifiers":[
        {
            "category":"Building & Trades",
            "subcategory":"Construction",
            "type":"Services"
        }
    ],
    "sg:phone":"+1 303 932 1767",
    "sg:postcode":"80127",
    "sg:province":"CO",
    "sg:tags":[
        "asbestos",
        "removal",
        "contractor"
    ],
    "wof:name":"Rocky Mountain Abatement Iinc",
    "wof:placetype":"venue"
},
  "geometry": {"coordinates":[-105.12406300000001,39.634384],"type":"Point"}
}