{
  "type": "Feature",
  "properties": {
    "addr:full":"4360 E Virginia Ave Denver CO 80246",
    "addr:housenumber":"4360",
    "addr:postcode":"80246",
    "addr:street":"E Virginia Ave",
    "iso:country":"US",
    "sg:address":"4360 E Virginia Ave",
    "sg:city":"Denver",
    "sg:classifiers":[
        {
            "category":"Government",
            "subcategory":"Office",
            "type":"Public Place"
        }
    ],
    "sg:phone":"+1 303 759 1513",
    "sg:postcode":"80246",
    "sg:province":"CO",
    "sg:tags":[
        "village"
    ],
    "sg:website":"www.glendale.co.us",
    "wof:name":"Glendale Sewer Plant",
    "wof:placetype":"venue"
},
  "geometry": {"coordinates":[-104.940144,39.707276],"type":"Point"}
}