{
  "type": "Feature",
  "properties": {
    "iso:country":"US",
    "sg:address":"4100 E Dry Creek Rd",
    "sg:city":"Littleton",
    "sg:classifiers":[
        {
            "category":"Utilities",
            "subcategory":"Cable",
            "type":"Services"
        }
    ],
    "sg:phone":"+1 720 482 0427",
    "sg:postcode":"80122",
    "sg:province":"CO",
    "sg:tags":[
        "television"
    ],
    "wof:name":"Northern Cable Vision",
    "wof:placetype":"venue"
},
  "geometry": {"coordinates":[-104.940815,39.58048],"type":"Point"}
}