{
  "type": "Feature",
  "properties": {
    "addr:full":"1444 Blake Street Denver CO 80202",
    "addr:housenumber":"1444",
    "addr:postcode":"80202",
    "addr:street":"Blake Street",
    "iso:country":"US",
    "sg:address":"1444 Blake Street",
    "sg:city":"Denver",
    "sg:classifiers":[
        {
            "category":"Professional",
            "subcategory":"Lawyer & Legal Services",
            "type":"Services"
        }
    ],
    "sg:phone":"+1 303 567 7990",
    "sg:postcode":"80202",
    "sg:province":"CO",
    "wof:name":"Forrest Loyce A",
    "wof:placetype":"venue"
},
  "geometry": {"coordinates":[-105.000756,39.749187],"type":"Point"}
}