{
  "type": "Feature",
  "properties": {
    "addr:full":"31195 Roberts Rd Pine CO 80470",
    "addr:housenumber":"31195",
    "addr:postcode":"80470",
    "addr:street":"Roberts Rd Pine Co",
    "iso:country":"US",
    "sg:address":"31195 Roberts Rd",
    "sg:city":"Pine",
    "sg:classifiers":[
        {
            "category":"Building & Trades",
            "subcategory":"Construction",
            "type":"Services"
        }
    ],
    "sg:phone":"+1 303 838 5467",
    "sg:postcode":"80470",
    "sg:province":"CO",
    "sg:tags":[
        "concrete",
        "contractor"
    ],
    "wof:name":"Burbach & Sons Foundations",
    "wof:placetype":"venue"
},
  "geometry": {"coordinates":[-105.357314,39.472876],"type":"Point"}
}