{
  "type": "Feature",
  "properties": {
    "addr:full":"603 S 1st St Lamar CO 81052",
    "addr:housenumber":"603",
    "addr:postcode":"81052",
    "addr:street":"S 1St St",
    "iso:country":"US",
    "sg:address":"603 S 1st St",
    "sg:city":"Lamar",
    "sg:classifiers":[
        {
            "category":"Health Services",
            "subcategory":"Doctor",
            "type":"Services"
        }
    ],
    "sg:phone":"+1 719 336 7719",
    "sg:postcode":"81052",
    "sg:province":"CO",
    "sg:tags":[
        "dentist"
    ],
    "wof:name":"Charles D Kelley DDS",
    "wof:placetype":"venue"
},
  "geometry": {"coordinates":[-102.613316,38.084338],"type":"Point"}
}