{
  "type": "Feature",
  "properties": {
    "addr:full":"1292 E Co Rd 14 Loveland CO 80537",
    "addr:housenumber":"1292;14",
    "addr:postcode":"80537",
    "addr:street":"E Co Rd",
    "iso:country":"US",
    "sg:address":"1292 E Co Rd 14",
    "sg:city":"Loveland",
    "sg:classifiers":[
        {
            "category":"Real Estate",
            "subcategory":"Real Estate Operator",
            "type":"Services"
        }
    ],
    "sg:phone":"+1 970 669 1375",
    "sg:postcode":"80537",
    "sg:province":"CO",
    "sg:tags":[
        "apartment"
    ],
    "wof:name":"Madison Avenue Apartments",
    "wof:placetype":"venue"
},
  "geometry": {"coordinates":[-105.060312,40.349214],"type":"Point"}
}