{
  "type": "Feature",
  "properties": {
    "iso:country":"US",
    "sg:address":"17 W Las Vegas St",
    "sg:city":"Colorado Springs",
    "sg:classifiers":[
        {
            "category":"Shopping",
            "subcategory":"Stationery & Office Supplies",
            "type":"Retail Goods"
        }
    ],
    "sg:phone":"+1 719 634 3372",
    "sg:postcode":"80903",
    "sg:province":"CO",
    "sg:website":"www.gotorhino.com",
    "wof:name":"Rhino Office Products Inc",
    "wof:placetype":"venue"
},
  "geometry": {"coordinates":[-104.829268,38.818587],"type":"Point"}
}