{
  "type": "Feature",
  "properties": {
    "iso:country":"US",
    "sg:address":"34526 Co Rd 24",
    "sg:city":"Mc Clave",
    "sg:phone":"+1 719 829 4566",
    "sg:postcode":"81057",
    "sg:province":"CO",
    "sg:tags":[
        "wheat",
        "beef",
        "farm",
        "corn",
        "cattle",
        "feedlot"
    ],
    "wof:name":"Phil Hemphill Farm",
    "wof:placetype":"venue"
},
  "geometry": {"coordinates":[-102.958522,38.135539],"type":"Point"}
}