{
  "type": "Feature",
  "properties": {
    "iso:country":"US",
    "sg:address":"5851 Palmer Park Blvd",
    "sg:city":"Colorado Springs",
    "sg:classifiers":[
        {
            "category":"Retail",
            "subcategory":"Laundry & Dry Cleaning",
            "type":"Services"
        }
    ],
    "sg:phone":"+1 719 570 9114",
    "sg:postcode":"80915",
    "sg:province":"CO",
    "sg:tags":[
        "cleaners"
    ],
    "wof:name":"Powers Cleaners",
    "wof:placetype":"venue"
},
  "geometry": {"coordinates":[-104.71972,38.857016],"type":"Point"}
}