{
  "type": "Feature",
  "properties": {
    "addr:full":"1800 Industrial Cir Longmont CO 80501",
    "addr:housenumber":"1800",
    "addr:postcode":"80501",
    "addr:street":"Industrial Cir",
    "iso:country":"US",
    "sg:address":"1800 Industrial Cir",
    "sg:city":"Longmont",
    "sg:classifiers":[
        {
            "category":"Autos & Motor Vehicles",
            "subcategory":"Automobile Sales",
            "type":"Retail Goods"
        }
    ],
    "sg:phone":"+1 303 776 2650",
    "sg:postcode":"80501",
    "sg:province":"CO",
    "sg:tags":[
        "car",
        "dealer"
    ],
    "sg:website":"www.herbertmotors.com",
    "wof:name":"Herbert Motors Inc",
    "wof:placetype":"venue"
},
  "geometry": {"coordinates":[-105.12513300000001,40.146772],"type":"Point"}
}