{
  "type": "Feature",
  "properties": {
    "iso:country":"US",
    "sg:address":"465 N Mill St",
    "sg:city":"Aspen",
    "sg:classifiers":[
        {
            "category":"Shopping",
            "subcategory":"Bicycles & Sporting Goods",
            "type":"Retail Goods"
        }
    ],
    "sg:phone":"+1 970 948 9283",
    "sg:postcode":"81611",
    "sg:province":"CO",
    "wof:name":"Power Play LLC",
    "wof:placetype":"venue"
},
  "geometry": {"coordinates":[-106.81832300000001,39.193057],"type":"Point"}
}