{
  "type": "Feature",
  "properties": {
    "addr:full":"215 S Monarch St Aspen CO 81611",
    "addr:housenumber":"215",
    "addr:postcode":"81611",
    "addr:street":"S Monarch St",
    "iso:country":"US",
    "sg:address":"215 S Monarch St",
    "sg:city":"Aspen",
    "sg:classifiers":[
        {
            "category":"Professional",
            "subcategory":"Accounting & Tax Preparation",
            "type":"Services"
        }
    ],
    "sg:phone":"+1 970 925 6481",
    "sg:postcode":"81611",
    "sg:province":"CO",
    "sg:tags":[
        "accountant"
    ],
    "wof:name":"Robert D Brining CPA",
    "wof:placetype":"venue"
},
  "geometry": {"coordinates":[-106.820787,39.19],"type":"Point"}
}