{
  "type": "Feature",
  "properties": {
    "addr:full":"11220 W Colfax Ave Lakewood CO 80215",
    "addr:housenumber":"11220",
    "addr:postcode":"80215",
    "addr:street":"W Colfax Ave",
    "iso:country":"US",
    "sg:address":"11220 W Colfax Ave",
    "sg:city":"Lakewood",
    "sg:classifiers":[
        {
            "category":"Health Services",
            "subcategory":"Chiropractor",
            "type":"Services"
        }
    ],
    "sg:phone":"+1 303 232 4321",
    "sg:postcode":"80215",
    "sg:province":"CO",
    "wof:name":"Bonnie Borman DC",
    "wof:placetype":"venue"
},
  "geometry": {"coordinates":[-105.124809,39.740095],"type":"Point"}
}