{
  "type": "Feature",
  "properties": {
    "addr:full":"1817 US Hwy 287 Fort Collins CO 80524",
    "addr:housenumber":"1817",
    "addr:postcode":"80524",
    "addr:street":"Us Hwy 287",
    "iso:country":"US",
    "sg:address":"1817 US Hwy 287",
    "sg:city":"Fort Collins",
    "sg:classifiers":[
        {
            "category":"Farming",
            "subcategory":"Dairy Farm",
            "type":"Manufacturing & Wholesale Goods"
        }
    ],
    "sg:phone":"+1 970 493 5180",
    "sg:postcode":"80524",
    "sg:province":"CO",
    "wof:name":"Stegner Dairy Farm",
    "wof:placetype":"venue"
},
  "geometry": {"coordinates":[-105.07652,40.612518],"type":"Point"}
}