{
  "type": "Feature",
  "properties": {
    "addr:full":"1150 E 5th St Delta CO 81416",
    "addr:housenumber":"1150",
    "addr:postcode":"81416",
    "addr:street":"E 5Th St",
    "iso:country":"US",
    "sg:address":"1150 E 5th St",
    "sg:city":"Delta",
    "sg:classifiers":[
        {
            "category":"Building & Trades",
            "subcategory":"Construction",
            "type":"Services"
        }
    ],
    "sg:phone":"+1 970 874 4850",
    "sg:postcode":"81416",
    "sg:province":"CO",
    "sg:tags":[
        "excavation",
        "contractor"
    ],
    "wof:name":"Huff Excavating",
    "wof:placetype":"venue"
},
  "geometry": {"coordinates":[-108.052272,38.740884],"type":"Point"}
}