{
  "type": "Feature",
  "properties": {
    "iso:country":"US",
    "sg:address":"2236 N Wahsatch Ave",
    "sg:city":"Colorado Springs",
    "sg:classifiers":[
        {
            "category":"Shopping",
            "type":"Retail Goods"
        }
    ],
    "sg:phone":"+1 719 636 2427",
    "sg:postcode":"80907",
    "sg:province":"CO",
    "sg:tags":[
        "picture",
        "frame"
    ],
    "wof:name":"Frameworks",
    "wof:placetype":"venue"
},
  "geometry": {"coordinates":[-104.816586,38.864905],"type":"Point"}
}