{
  "type": "Feature",
  "properties": {
    "addr:full":"2407 W Drake Rd Fort Collins CO 80526",
    "addr:housenumber":"2407",
    "addr:postcode":"80526",
    "addr:street":"W Drake Rd",
    "iso:country":"US",
    "sg:address":"2407 W Drake Rd",
    "sg:city":"Fort Collins",
    "sg:classifiers":[
        {
            "category":"Recreation",
            "type":"Entertainment"
        }
    ],
    "sg:phone":"+1 970 223 8404",
    "sg:postcode":"80526",
    "sg:province":"CO",
    "sg:tags":[
        "stable"
    ],
    "wof:name":"Town & Country Stables",
    "wof:placetype":"venue"
},
  "geometry": {"coordinates":[-105.12030300000001,40.552687],"type":"Point"}
}