{
  "type": "Feature",
  "properties": {
    "addr:full":"3001 Industrial Ln Broomfield CO 80020",
    "addr:housenumber":"3001",
    "addr:postcode":"80020",
    "addr:street":"Industrial Ln",
    "iso:country":"US",
    "sg:address":"3001 Industrial Ln",
    "sg:city":"Broomfield",
    "sg:classifiers":[
        {
            "category":"Education",
            "subcategory":"Dance Studio",
            "type":"Public Place"
        }
    ],
    "sg:phone":"+1 303 466 5685",
    "sg:postcode":"80020",
    "sg:province":"CO",
    "sg:website":"www.balletnouveaucolorado.org",
    "wof:name":"Ballet Nouveau Colorado",
    "wof:placetype":"venue"
},
  "geometry": {"coordinates":[-105.107253,39.923554],"type":"Point"}
}