{
  "type": "Feature",
  "properties": {
    "iso:country":"US",
    "sg:address":"45 Duroux Ln",
    "sg:city":"Basalt",
    "sg:classifiers":[
        {
            "category":"Wholesale",
            "subcategory":"Groceries",
            "type":"Manufacturing & Wholesale Goods"
        }
    ],
    "sg:phone":"+1 970 927 1006",
    "sg:postcode":"81621",
    "sg:province":"CO",
    "sg:tags":[
        "coffee",
        "roasting"
    ],
    "sg:website":"www.inkcoffee.com",
    "wof:name":"Ink Coffee Co",
    "wof:placetype":"venue"
},
  "geometry": {"coordinates":[-107.08268,39.373956],"type":"Point"}
}