{
  "type": "Feature",
  "properties": {
    "addr:full":"2706 Skyline Dr Grand Junction CO 81506",
    "addr:housenumber":"2706",
    "addr:postcode":"81506",
    "addr:street":"Skyline Dr",
    "iso:country":"US",
    "sg:address":"2706 Skyline Dr",
    "sg:city":"Grand Junction",
    "sg:classifiers":[
        {
            "category":"Professional",
            "type":"Services"
        }
    ],
    "sg:phone":"+1 970 243 3658",
    "sg:postcode":"81506",
    "sg:province":"CO",
    "wof:name":"Gerald B Feather",
    "wof:placetype":"venue"
},
  "geometry": {"coordinates":[-108.55217399999999,39.118321],"type":"Point"}
}