{
  "type": "Feature",
  "properties": {
    "iso:country":"US",
    "sg:address":"105 W 2nd St",
    "sg:city":"Cortez",
    "sg:classifiers":[
        {
            "category":"Professional",
            "subcategory":"Lawyer & Legal Services",
            "type":"Services"
        }
    ],
    "sg:phone":"+1 970 565 0645",
    "sg:postcode":"81321",
    "sg:province":"CO",
    "sg:tags":[
        "attorney"
    ],
    "wof:name":"Sheeran Law Offices",
    "wof:placetype":"venue"
},
  "geometry": {"coordinates":[-108.58651999999999,37.34642],"type":"Point"}
}