{
  "type": "Feature",
  "properties": {
    "iso:country":"US",
    "sg:address":"4999 E Kentucky Ave",
    "sg:city":"Denver",
    "sg:classifiers":[
        {
            "category":"Health Services",
            "subcategory":"Doctor",
            "type":"Services"
        }
    ],
    "sg:phone":"+1 303 758 5477",
    "sg:postcode":"80246",
    "sg:province":"CO",
    "sg:tags":[
        "medical"
    ],
    "wof:name":"Barmatz and Roe MD",
    "wof:placetype":"venue"
},
  "geometry": {"coordinates":[-104.93025299999999,39.700294],"type":"Point"}
}