{
  "type": "Feature",
  "properties": {
    "addr:full":"33846 US Hwy 160 South Fork CO 81154",
    "addr:postcode":"33846;81154",
    "addr:street":"Us Hwy 160 South",
    "iso:country":"US",
    "sg:address":"33846 US Hwy 160",
    "sg:city":"South Fork",
    "sg:classifiers":[
        {
            "category":"Travel",
            "subcategory":"Hotels & Motels",
            "type":"Entertainment"
        }
    ],
    "sg:phone":"+1 719 873 5344",
    "sg:postcode":"81154",
    "sg:province":"CO",
    "sg:tags":[
        "resort"
    ],
    "sg:website":"www.riverbend-resort.com",
    "wof:name":"Riverbend Resort",
    "wof:placetype":"venue"
},
  "geometry": {"coordinates":[-106.678326,37.630354],"type":"Point"}
}