{
  "type": "Feature",
  "properties": {
    "addr:full":"2529 N Murray Blvd Colorado Springs CO 80915",
    "addr:housenumber":"2529",
    "addr:postcode":"80915",
    "addr:street":"N Murray Blvd",
    "iso:country":"US",
    "sg:address":"2529 N Murray Blvd",
    "sg:city":"Colorado Springs",
    "sg:classifiers":[
        {
            "category":"Recreation",
            "type":"Entertainment"
        }
    ],
    "sg:phone":"+1 719 596 2958",
    "sg:postcode":"80915",
    "sg:province":"CO",
    "sg:tags":[
        "club",
        "tennis"
    ],
    "wof:name":"Colorado Springs Racquet Club",
    "wof:placetype":"venue"
},
  "geometry": {"coordinates":[-104.747827,38.868811],"type":"Point"}
}