{
  "type": "Feature",
  "properties": {
    "addr:full":"6018 Xenon St Arvada CO 80004",
    "addr:postcode":"6018;80004",
    "addr:street":"Xenon St",
    "iso:country":"US",
    "sg:address":"6018 Xenon St",
    "sg:city":"Arvada",
    "sg:classifiers":[
        {
            "category":"Building & Trades",
            "subcategory":"Construction",
            "type":"Services"
        }
    ],
    "sg:phone":"+1 303 452 0270",
    "sg:postcode":"80004",
    "sg:province":"CO",
    "sg:tags":[
        "house"
    ],
    "wof:name":"Meyer Kennethk & G Enterprises",
    "wof:placetype":"venue"
},
  "geometry": {"coordinates":[-105.140311,39.807293],"type":"Point"}
}