{
  "type": "Feature",
  "properties": {
    "addr:full":"10155 W Kentucky Dr Lakewood CO 80226",
    "addr:housenumber":"10155",
    "addr:postcode":"80226",
    "addr:street":"W Kentucky Dr",
    "iso:country":"US",
    "sg:address":"10155 W Kentucky Dr",
    "sg:city":"Lakewood",
    "sg:classifiers":[
        {
            "category":"Building & Trades",
            "subcategory":"Landscaping Services",
            "type":"Services"
        }
    ],
    "sg:phone":"+1 303 989 0496",
    "sg:postcode":"80226",
    "sg:province":"CO",
    "sg:tags":[
        "landscape",
        "contractor"
    ],
    "wof:name":"J's Landscape & Sprinkler Inc",
    "wof:placetype":"venue"
},
  "geometry": {"coordinates":[-105.112611,39.700425],"type":"Point"}
}