{
  "type": "Feature",
  "properties": {
    "addr:full":"701 E Hampden Ave Englewood CO 80113",
    "addr:housenumber":"701",
    "addr:postcode":"80113",
    "addr:street":"E Hampden Ave",
    "iso:country":"US",
    "sg:address":"701 E Hampden Ave",
    "sg:city":"Englewood",
    "sg:classifiers":[
        {
            "category":"Professional",
            "type":"Services"
        }
    ],
    "sg:phone":"+1 303 788 1345",
    "sg:postcode":"80113",
    "sg:province":"CO",
    "wof:name":"Rocky Mountain Nevro",
    "wof:placetype":"venue"
},
  "geometry": {"coordinates":[-104.978253,39.653138],"type":"Point"}
}