{
  "type": "Feature",
  "properties": {
    "addr:full":"3925 Centennial Blvd Colorado Springs CO 80907",
    "addr:housenumber":"3925",
    "addr:postcode":"80907",
    "addr:street":"Centennial Blvd",
    "iso:country":"US",
    "sg:address":"3925 Centennial Blvd",
    "sg:city":"Colorado Springs",
    "sg:classifiers":[
        {
            "category":"Social Services",
            "subcategory":"Child Care",
            "type":"Services"
        }
    ],
    "sg:phone":"+1 719 593 7711",
    "sg:postcode":"80907",
    "sg:province":"CO",
    "sg:tags":[
        "day"
    ],
    "wof:name":"Kindercare Learning Ctr 554",
    "wof:placetype":"venue"
},
  "geometry": {"coordinates":[-104.84752899999999,38.888642],"type":"Point"}
}