{
  "type": "Feature",
  "properties": {
    "addr:full":"600 Grant Street Suite 350 Denver CO 80203",
    "addr:housenumber":"600",
    "addr:postcode":"80203",
    "addr:street":"Grant Street Suite 350",
    "iso:country":"US",
    "sg:address":"600 Grant Street Suite 350",
    "sg:city":"Denver",
    "sg:classifiers":[
        {
            "category":"Professional",
            "subcategory":"Employment Agencies",
            "type":"Services"
        }
    ],
    "sg:phone":"+1 303 869 2990",
    "sg:postcode":"80203",
    "sg:province":"CO",
    "sg:website":"www.primesourcestaffing.com",
    "wof:name":"Primesource Staffing",
    "wof:placetype":"venue"
},
  "geometry": {"coordinates":[-104.98362899999999,39.72563],"type":"Point"}
}