{
  "type": "Feature",
  "properties": {
    "addr:full":"11295 Ranch Pl Denver CO 80234",
    "addr:housenumber":"11295",
    "addr:postcode":"80234",
    "addr:street":"Ranch Pl",
    "iso:country":"US",
    "sg:address":"11295 Ranch Pl",
    "sg:city":"Denver",
    "sg:classifiers":[
        {
            "category":"Wholesale",
            "subcategory":"Sporting Goods",
            "type":"Manufacturing & Wholesale Goods"
        }
    ],
    "sg:phone":"+1 303 460 0153",
    "sg:postcode":"80234",
    "sg:province":"CO",
    "wof:name":"Western Sports Marketing",
    "wof:placetype":"venue"
},
  "geometry": {"coordinates":[-105.012578,39.90207],"type":"Point"}
}