{
  "type": "Feature",
  "properties": {
    "addr:full":"118 S Glenrose Dr Pueblo West CO 81007",
    "addr:housenumber":"118",
    "addr:postcode":"81007",
    "addr:street":"S Glenrose Dr",
    "iso:country":"US",
    "sg:address":"118 S Glenrose Dr",
    "sg:city":"Pueblo West",
    "sg:classifiers":[
        {
            "category":"Building & Trades",
            "subcategory":"Construction",
            "type":"Services"
        }
    ],
    "sg:phone":"+1 719 547 1088",
    "sg:postcode":"81007",
    "sg:province":"CO",
    "sg:tags":[
        "home",
        "builder",
        "speculative"
    ],
    "wof:name":"Oakwood Construction Co",
    "wof:placetype":"venue"
},
  "geometry": {"coordinates":[-104.749488,38.331609],"type":"Point"}
}