{
  "type": "Feature",
  "properties": {
    "iso:country":"US",
    "sg:address":"67318 US Hwy 285",
    "sg:city":"Pine",
    "sg:classifiers":[
        {
            "category":"Shopping",
            "subcategory":"Florist",
            "type":"Retail Goods"
        }
    ],
    "sg:phone":"+1 303 816 0065",
    "sg:postcode":"80470",
    "sg:province":"CO",
    "wof:name":"Songbird Flowers",
    "wof:placetype":"venue"
},
  "geometry": {"coordinates":[-105.398049,39.464373],"type":"Point"}
}