{
  "type": "Feature",
  "properties": {
    "addr:full":"1133 Portland Pl Boulder CO 80304",
    "addr:housenumber":"1133",
    "addr:postcode":"80304",
    "addr:street":"Portland Pl",
    "iso:country":"US",
    "sg:address":"1133 Portland Pl",
    "sg:city":"Boulder",
    "sg:classifiers":[
        {
            "category":"Real Estate",
            "subcategory":"Real Estate Operator",
            "type":"Services"
        }
    ],
    "sg:phone":"+1 303 440 7331",
    "sg:postcode":"80304",
    "sg:province":"CO",
    "sg:tags":[
        "building",
        "apartment"
    ],
    "wof:name":"Northport Apts",
    "wof:placetype":"venue"
},
  "geometry": {"coordinates":[-105.282757,40.023353],"type":"Point"}
}