{
  "type": "Feature",
  "properties": {
    "addr:full":"11134 Co Rd 35 Stratton CO 80836",
    "addr:housenumber":"11134;35",
    "addr:postcode":"80836",
    "addr:street":"Co Rd",
    "iso:country":"US",
    "sg:address":"11134 Co Rd 35",
    "sg:city":"Stratton",
    "sg:classifiers":[
        {
            "category":"Farming",
            "subcategory":"Livestock Farm",
            "type":"Manufacturing & Wholesale Goods"
        }
    ],
    "sg:phone":"+1 719 348 5828",
    "sg:postcode":"80836",
    "sg:province":"CO",
    "sg:tags":[
        "beef",
        "feedlot",
        "cattle"
    ],
    "wof:name":"Keith Myrick",
    "wof:placetype":"venue"
},
  "geometry": {"coordinates":[-102.52110399999999,39.202587],"type":"Point"}
}