{
  "type": "Feature",
  "properties": {
    "addr:full":"64 Old Dory Hill Rd Golden CO 80403",
    "addr:housenumber":"64",
    "addr:postcode":"80403",
    "addr:street":"Old Dory Hill Rd",
    "iso:country":"US",
    "sg:address":"64 Old Dory Hill Rd",
    "sg:city":"Golden",
    "sg:classifiers":[
        {
            "category":"Freight",
            "type":"Transportation"
        }
    ],
    "sg:phone":"+1 303 582 3614",
    "sg:postcode":"80403",
    "sg:province":"CO",
    "sg:tags":[
        "operator",
        "trucking"
    ],
    "wof:name":"Huntington Transport",
    "wof:placetype":"venue"
},
  "geometry": {"coordinates":[-105.47564300000001,39.841632],"type":"Point"}
}