{
  "type": "Feature",
  "properties": {
    "addr:full":"6541 Brighton Blvd Commerce City CO 80022",
    "addr:housenumber":"6541",
    "addr:postcode":"80022",
    "addr:street":"Brighton Blvd",
    "iso:country":"US",
    "sg:address":"6541 Brighton Blvd",
    "sg:city":"Commerce City",
    "sg:classifiers":[
        {
            "category":"Manufacturing",
            "subcategory":"Metals",
            "type":"Manufacturing & Wholesale Goods"
        }
    ],
    "sg:phone":"+1 303 991 0900",
    "sg:postcode":"80022",
    "sg:province":"CO",
    "sg:tags":[
        "steel"
    ],
    "sg:website":"www.americanindustrial.us",
    "wof:name":"American Industrial Mfg",
    "wof:placetype":"venue"
},
  "geometry": {"coordinates":[-104.93622000000001,39.813604],"type":"Point"}
}