{
  "type": "Feature",
  "properties": {
    "addr:full":"360 S Cam del Rio Durango CO 81301",
    "addr:housenumber":"360",
    "addr:postcode":"co 81301",
    "addr:street":"S Cam Del Rio",
    "iso:country":"US",
    "sg:address":"360 S Cam del Rio",
    "sg:city":"Durango",
    "sg:classifiers":[
        {
            "category":"Shopping",
            "subcategory":"Bicycles & Sporting Goods",
            "type":"Retail Goods"
        }
    ],
    "sg:phone":"+1 970 259 3893",
    "sg:postcode":"81301",
    "sg:province":"CO",
    "sg:website":"www.riversports.com",
    "wof:name":"Four Corners River Sports",
    "wof:placetype":"venue"
},
  "geometry": {"coordinates":[-107.87444499999999,37.248139],"type":"Point"}
}