{
  "type": "Feature",
  "properties": {
    "addr:full":"3024 Jefferson St Boulder CO 80304",
    "addr:housenumber":"3024",
    "addr:postcode":"80304",
    "addr:street":"Jefferson St",
    "iso:country":"US",
    "sg:address":"3024 Jefferson St",
    "sg:city":"Boulder",
    "sg:classifiers":[
        {
            "category":"Professional",
            "subcategory":"Computer Services",
            "type":"Services"
        }
    ],
    "sg:phone":"+1 303 545 9371",
    "sg:postcode":"80304",
    "sg:province":"CO",
    "sg:tags":[
        "software"
    ],
    "wof:name":"Jnbridge LLC",
    "wof:placetype":"venue"
},
  "geometry": {"coordinates":[-105.278175,40.032617],"type":"Point"}
}