{
  "type": "Feature",
  "properties": {
    "iso:country":"US",
    "sg:address":"13770 E Rice Pl",
    "sg:city":"Aurora",
    "sg:classifiers":[
        {
            "category":"Real Estate",
            "subcategory":"Real Estate Agent",
            "type":"Services"
        }
    ],
    "sg:phone":"+1 303 680 3041",
    "sg:postcode":"80015",
    "sg:province":"CO",
    "wof:name":"A1 Remax Property Management C",
    "wof:placetype":"venue"
},
  "geometry": {"coordinates":[-104.828349,39.636887],"type":"Point"}
}