{
  "type": "Feature",
  "properties": {
    "addr:full":"26730 US Hwy 50 La Junta CO 81050",
    "addr:postcode":"26730;81050",
    "addr:street":"Us Hwy 50",
    "iso:country":"US",
    "sg:address":"26730 US Hwy 50",
    "sg:city":"La Junta",
    "sg:classifiers":[
        {
            "category":"Autos & Motor Vehicles",
            "subcategory":"Automobile Sales",
            "type":"Retail Goods"
        }
    ],
    "sg:phone":"+1 719 384 5421",
    "sg:postcode":"81050",
    "sg:province":"CO",
    "sg:tags":[
        "car",
        "dealer"
    ],
    "sg:website":"www.bigvalleychryslerdodge.com",
    "wof:name":"Big Valley Ford",
    "wof:placetype":"venue"
},
  "geometry": {"coordinates":[-103.58739199999999,37.998616],"type":"Point"}
}