{
  "type": "Feature",
  "properties": {
    "addr:full":"1545 E Evans Ave Pueblo CO 81004",
    "addr:housenumber":"1545",
    "addr:postcode":"81004",
    "addr:street":"E Evans Ave",
    "iso:country":"US",
    "sg:address":"1545 E Evans Ave",
    "sg:city":"Pueblo",
    "sg:classifiers":[
        {
            "category":"Autos & Motor Vehicles",
            "subcategory":"Automobile Sales",
            "type":"Retail Goods"
        }
    ],
    "sg:phone":"+1 719 560 9748",
    "sg:postcode":"81004",
    "sg:province":"CO",
    "sg:tags":[
        "used"
    ],
    "wof:name":"Medina Motors",
    "wof:placetype":"venue"
},
  "geometry": {"coordinates":[-104.615025,38.239743],"type":"Point"}
}