{
  "type": "Feature",
  "properties": {
    "addr:full":"715 Main St Alamosa CO 81101",
    "addr:housenumber":"715",
    "addr:postcode":"81101",
    "addr:street":"Main St",
    "iso:country":"US",
    "sg:address":"715 Main St",
    "sg:city":"Alamosa",
    "sg:classifiers":[
        {
            "category":"Professional",
            "subcategory":"Accounting & Tax Preparation",
            "type":"Services"
        }
    ],
    "sg:phone":"+1 719 589 5404",
    "sg:postcode":"81101",
    "sg:province":"CO",
    "sg:tags":[
        "accountant"
    ],
    "wof:name":"Christopher Schmitz CPA",
    "wof:placetype":"venue"
},
  "geometry": {"coordinates":[-105.868601,37.468257],"type":"Point"}
}