{
  "type": "Feature",
  "properties": {
    "iso:country":"US",
    "sg:address":"7343 S Alton Way",
    "sg:city":"Englewood",
    "sg:classifiers":[
        {
            "category":"Real Estate",
            "subcategory":"Developer",
            "type":"Services"
        }
    ],
    "sg:phone":"+1 720 200 0496",
    "sg:postcode":"80112",
    "sg:province":"CO",
    "wof:name":"T & S Development LLC",
    "wof:placetype":"venue"
},
  "geometry": {"coordinates":[-104.883959,39.582589],"type":"Point"}
}