{
  "type": "Feature",
  "properties": {
    "iso:country":"US",
    "sg:address":"7578 Sheridan Blvd",
    "sg:city":"Arvada",
    "sg:classifiers":[
        {
            "category":"Health Services",
            "subcategory":"Doctor",
            "type":"Services"
        }
    ],
    "sg:phone":"+1 303 427 9779",
    "sg:postcode":"80003",
    "sg:province":"CO",
    "sg:tags":[
        "dentist"
    ],
    "wof:name":"Jesse R Witkoff & Assoc",
    "wof:placetype":"venue"
},
  "geometry": {"coordinates":[-105.053263,39.833639],"type":"Point"}
}