{
  "type": "Feature",
  "properties": {
    "iso:country":"US",
    "sg:address":"19590 E Main St",
    "sg:city":"Parker",
    "sg:classifiers":[
        {
            "category":"Utilities",
            "subcategory":"Refuse",
            "type":"Services"
        }
    ],
    "sg:phone":"+1 303 646 4132",
    "sg:postcode":"80138",
    "sg:province":"CO",
    "sg:tags":[
        "garbage",
        "collection"
    ],
    "wof:name":"Refuse Management Inc",
    "wof:placetype":"venue"
},
  "geometry": {"coordinates":[-104.760436,39.518133],"type":"Point"}
}