{
  "type": "Feature",
  "properties": {
    "iso:country":"US",
    "sg:address":"19014 Co Rd 20.5",
    "sg:city":"Fort Morgan",
    "sg:classifiers":[
        {
            "category":"Building & Trades",
            "subcategory":"Construction",
            "type":"Services"
        }
    ],
    "sg:phone":"+1 970 867 6067",
    "sg:postcode":"80701",
    "sg:province":"CO",
    "sg:tags":[
        "downspouts",
        "gutter"
    ],
    "wof:name":"J G Gutter",
    "wof:placetype":"venue"
},
  "geometry": {"coordinates":[-103.76312,40.282224],"type":"Point"}
}