{
  "type": "Feature",
  "properties": {
    "iso:country":"US",
    "sg:address":"3900 E Mexico Ave Ste 102",
    "sg:city":"Denver",
    "sg:classifiers":[
        {
            "category":"Shopping",
            "subcategory":"Optician",
            "type":"Retail Goods"
        },
        {
            "category":"Health Services",
            "subcategory":"Doctor",
            "type":"Services"
        }
    ],
    "sg:phone":"+1 719 846 9236",
    "sg:postcode":"80210",
    "sg:province":"CO",
    "sg:tags":[
        "eyewear"
    ],
    "wof:name":"Total Vision Eye Care",
    "wof:placetype":"venue"
},
  "geometry": {"coordinates":[-104.942001,39.685699],"type":"Point"}
}