{
  "type": "Feature",
  "properties": {
    "iso:country":"US",
    "sg:address":"929 29th Street",
    "sg:city":"Denver",
    "sg:classifiers":[
        {
            "category":"Organizations",
            "subcategory":"Non-profit Organization",
            "type":"Services"
        }
    ],
    "sg:phone":"+1 303 295 2399",
    "sg:postcode":"80205",
    "sg:province":"CO",
    "sg:tags":[
        "service/non-profit",
        "community"
    ],
    "wof:name":"Curtis Park Community Center",
    "wof:placetype":"venue"
},
  "geometry": {"coordinates":[-104.97862,39.758819],"type":"Point"}
}