{
  "type": "Feature",
  "properties": {
    "iso:country":"US",
    "sg:address":"1449 Pennsylvania St",
    "sg:city":"Denver",
    "sg:classifiers":[
        {
            "category":"Personal",
            "subcategory":"Beauty Salon",
            "type":"Services"
        }
    ],
    "sg:phone":"+1 303 860 7688",
    "sg:postcode":"80203",
    "sg:province":"CO",
    "sg:tags":[
        "hair"
    ],
    "sg:website":"www.myspace.com/ocsalon",
    "wof:name":"OC Salon",
    "wof:placetype":"venue"
},
  "geometry": {"coordinates":[-104.98110699999999,39.739445],"type":"Point"}
}