{
  "type": "Feature",
  "properties": {
    "addr:full":"1330 S Dahlia St Denver CO 80222",
    "addr:housenumber":"1330",
    "addr:postcode":"80222",
    "addr:street":"S Dahlia St",
    "iso:country":"US",
    "sg:address":"1330 S Dahlia St",
    "sg:city":"Denver",
    "sg:classifiers":[
        {
            "category":"Shopping",
            "subcategory":"Optical Goods",
            "type":"Retail Goods"
        }
    ],
    "sg:phone":"+1 303 377 5724",
    "sg:postcode":"80222",
    "sg:province":"CO",
    "wof:name":"Reiter & Associates",
    "wof:placetype":"venue"
},
  "geometry": {"coordinates":[-104.93164899999999,39.692569],"type":"Point"}
}