{
  "type": "Feature",
  "properties": {
    "addr:full":"1713 W Baltic Pl Englewood CO 80110",
    "addr:housenumber":"1713",
    "addr:postcode":"80110",
    "addr:street":"W Baltic Pl",
    "iso:country":"US",
    "sg:address":"1713 W Baltic Pl",
    "sg:city":"Englewood",
    "sg:classifiers":[
        {
            "category":"Autos & Motor Vehicles",
            "subcategory":"Automobile Sales",
            "type":"Retail Goods"
        }
    ],
    "sg:phone":"+1 303 936 5592",
    "sg:postcode":"80110",
    "sg:province":"CO",
    "sg:tags":[
        "car",
        "dealer"
    ],
    "wof:name":"LPS Auto Sales",
    "wof:placetype":"venue"
},
  "geometry": {"coordinates":[-105.007707,39.675973],"type":"Point"}
}