{
  "type": "Feature",
  "properties": {
    "addr:full":"5354 S Field St Littleton CO 80123",
    "addr:housenumber":"5354",
    "addr:postcode":"80123",
    "addr:street":"S Field St",
    "iso:country":"US",
    "sg:address":"5354 S Field St",
    "sg:city":"Littleton",
    "sg:classifiers":[
        {
            "category":"Education",
            "subcategory":"School",
            "type":"Public Place"
        }
    ],
    "sg:phone":"+1 303 982 4625",
    "sg:postcode":"80123",
    "sg:province":"CO",
    "wof:name":"Governors Ranch Elementary",
    "wof:placetype":"venue"
},
  "geometry": {"coordinates":[-105.09989,39.620565],"type":"Point"}
}