{
  "type": "Feature",
  "properties": {
    "iso:country":"US",
    "sg:address":"1125 17th Street Lbby",
    "sg:city":"Denver",
    "sg:classifiers":[
        {
            "category":"Banks & Credit Unions",
            "subcategory":"Investment Brokerage",
            "type":"Services"
        }
    ],
    "sg:phone":"+1 303 534 2100",
    "sg:postcode":"80202",
    "sg:province":"CO",
    "sg:tags":[
        "investing"
    ],
    "wof:name":"Brownsfields Capital",
    "wof:placetype":"venue"
},
  "geometry": {"coordinates":[-104.994635,39.748956],"type":"Point"}
}