{
  "type": "Feature",
  "properties": {
    "iso:country":"US",
    "sg:address":"1673 York St",
    "sg:city":"Denver",
    "sg:classifiers":[
        {
            "category":"Retail",
            "subcategory":"Funeral Services",
            "type":"Services"
        }
    ],
    "sg:phone":"+1 303 322 7764",
    "sg:postcode":"80206",
    "sg:province":"CO",
    "wof:name":"Feldman Mortuary Inc",
    "wof:placetype":"venue"
},
  "geometry": {"coordinates":[-104.95985400000001,39.742052],"type":"Point"}
}