{
  "type": "Feature",
  "properties": {
    "addr:full":"2980 Sugarloaf Rd Boulder CO 80302",
    "addr:housenumber":"2980",
    "addr:postcode":"80302",
    "addr:street":"Sugarloaf Rd",
    "iso:country":"US",
    "sg:address":"2980 Sugarloaf Rd",
    "sg:city":"Boulder",
    "sg:classifiers":[
        {
            "category":"Manufacturing",
            "subcategory":"Retail Goods",
            "type":"Manufacturing & Wholesale Goods"
        }
    ],
    "sg:phone":"+1 720 565 1870",
    "sg:postcode":"80302",
    "sg:province":"CO",
    "sg:tags":[
        "manufacture",
        "pet",
        "product"
    ],
    "wof:name":"Ruff Rider Products",
    "wof:placetype":"venue"
},
  "geometry": {"coordinates":[-105.37646599999999,40.018336],"type":"Point"}
}