{
  "type": "Feature",
  "properties": {
    "iso:country":"US",
    "sg:address":"104 E 29th St",
    "sg:city":"Loveland",
    "sg:classifiers":[
        {
            "category":"Personal",
            "subcategory":"Beauty Salon",
            "type":"Services"
        }
    ],
    "sg:phone":"+1 970 962 9820",
    "sg:postcode":"80538",
    "sg:province":"CO",
    "wof:name":"Cost Cutters Family Hair Care",
    "wof:placetype":"venue"
},
  "geometry": {"coordinates":[-105.076193,40.421615],"type":"Point"}
}