{
  "type": "Feature",
  "properties": {
    "addr:full":"18121 E Hampden Ave Aurora CO 80013",
    "addr:housenumber":"18121",
    "addr:postcode":"80013",
    "addr:street":"E Hampden Ave",
    "iso:country":"US",
    "sg:address":"18121 E Hampden Ave",
    "sg:city":"Aurora",
    "sg:classifiers":[
        {
            "category":"Professional",
            "subcategory":"Business Services",
            "type":"Services"
        }
    ],
    "sg:phone":"+1 303 766 8771",
    "sg:postcode":"80013",
    "sg:province":"CO",
    "sg:tags":[
        "educational",
        "material",
        "design"
    ],
    "wof:name":"Expressions of A People Inc",
    "wof:placetype":"venue"
},
  "geometry": {"coordinates":[-104.776583,39.653121],"type":"Point"}
}