{
  "type": "Feature",
  "properties": {
    "addr:full":"802 S Public Rd Lafayette CO 80026",
    "addr:housenumber":"802",
    "addr:postcode":"80026",
    "addr:street":"S Public Rd",
    "iso:country":"US",
    "sg:address":"802 S Public Rd",
    "sg:city":"Lafayette",
    "sg:classifiers":[
        {
            "category":"Autos & Motor Vehicles",
            "subcategory":"Fuel & Gas Station",
            "type":"Retail Goods"
        }
    ],
    "sg:phone":"+1 303 666 7263",
    "sg:postcode":"80026",
    "sg:province":"CO",
    "sg:tags":[
        "station",
        "gasoline"
    ],
    "wof:name":"Conocophillips Holding Company",
    "wof:placetype":"venue"
},
  "geometry": {"coordinates":[-105.090411,39.992135],"type":"Point"}
}