{
  "type": "Feature",
  "properties": {
    "iso:country":"US",
    "sg:address":"2635 17th Street",
    "sg:city":"Denver",
    "sg:classifiers":[
        {
            "category":"Professional",
            "subcategory":"Lawyer & Legal Services",
            "type":"Services"
        }
    ],
    "sg:phone":"+1 303 458 5100",
    "sg:postcode":"80211",
    "sg:province":"CO",
    "sg:tags":[
        "divorce",
        "law",
        "family"
    ],
    "wof:name":"Schriner Bonnie M J Atty",
    "wof:placetype":"venue"
},
  "geometry": {"coordinates":[-105.009677,39.760522],"type":"Point"}
}