{
  "type": "Feature",
  "properties": {
    "addr:full":"3455 Sun River Pl Colorado Springs CO 80920",
    "addr:housenumber":"3455",
    "addr:postcode":"80920",
    "addr:street":"Sun River Pl",
    "iso:country":"US",
    "sg:address":"3455 Sun River Pl",
    "sg:city":"Colorado Springs",
    "sg:classifiers":[
        {
            "category":"Communications",
            "type":"Services"
        }
    ],
    "sg:phone":"+1 719 535 0394",
    "sg:postcode":"80920",
    "sg:province":"CO",
    "sg:tags":[
        "communication"
    ],
    "wof:name":"McGlairn Communications",
    "wof:placetype":"venue"
},
  "geometry": {"coordinates":[-104.761765,38.943705],"type":"Point"}
}