{
  "type": "Feature",
  "properties": {
    "addr:full":"410 W Main St Buena Vista CO 81236",
    "addr:housenumber":"410",
    "addr:postcode":"81236",
    "addr:street":"W Main St",
    "iso:country":"US",
    "sg:address":"410 W Main St",
    "sg:city":"Buena Vista",
    "sg:classifiers":[
        {
            "category":"Health Services",
            "subcategory":"Health Practitioner",
            "type":"Services"
        }
    ],
    "sg:phone":"+1 719 395 9086",
    "sg:postcode":"81236",
    "sg:province":"CO",
    "sg:tags":[
        "acupuncture"
    ],
    "wof:name":"Mountain Acupuncture Ctr",
    "wof:placetype":"venue"
},
  "geometry": {"coordinates":[-106.135836,38.840933],"type":"Point"}
}