{
  "type": "Feature",
  "properties": {
    "iso:country":"US",
    "sg:address":"2715 del Sol Way",
    "sg:city":"Parker",
    "sg:classifiers":[
        {
            "category":"Manufacturing",
            "subcategory":"Printing",
            "type":"Manufacturing & Wholesale Goods"
        }
    ],
    "sg:phone":"+1 303 646 4933",
    "sg:postcode":"80138",
    "sg:province":"CO",
    "sg:tags":[
        "commercial"
    ],
    "wof:name":"Value Added Serv",
    "wof:placetype":"venue"
},
  "geometry": {"coordinates":[-104.608422,39.471934],"type":"Point"}
}