{
  "type": "Feature",
  "properties": {
    "iso:country":"US",
    "sg:address":"1009 Grant St",
    "sg:city":"Denver",
    "sg:classifiers":[
        {
            "category":"Social Services",
            "type":"Services"
        }
    ],
    "sg:phone":"+1 303 830 0905",
    "sg:postcode":"80203",
    "sg:province":"CO",
    "sg:tags":[
        "counselor",
        "marriage",
        "family"
    ],
    "wof:name":"Colorado Women's Healing Prjct",
    "wof:placetype":"venue"
},
  "geometry": {"coordinates":[-104.98366799999999,39.733683],"type":"Point"}
}