{
  "type": "Feature",
  "properties": {
    "iso:country":"US",
    "sg:address":"3115 E. Colfax",
    "sg:city":"Denver",
    "sg:classifiers":[
        {
            "category":"Sports & Exercise",
            "subcategory":"Playing Field",
            "type":"Entertainment"
        }
    ],
    "sg:phone":"+1 303 887 1543",
    "sg:postcode":"80206",
    "sg:province":"CO",
    "sg:tags":[
        "instruction",
        "fitness"
    ],
    "sg:website":"www.qiryders.com/",
    "wof:name":"Qi Ryders",
    "wof:placetype":"venue"
},
  "geometry": {"coordinates":[-104.950836,39.740312],"type":"Point"}
}