{
  "type": "Feature",
  "properties": {
    "addr:full":"10750 E Arapahoe Rd Englewood CO 80112",
    "addr:housenumber":"10750",
    "addr:postcode":"80112",
    "addr:street":"E Arapahoe Rd",
    "iso:country":"US",
    "sg:address":"10750 E Arapahoe Rd",
    "sg:city":"Englewood",
    "sg:classifiers":[
        {
            "category":"Autos & Motor Vehicles",
            "subcategory":"Automobile Sales",
            "type":"Retail Goods"
        }
    ],
    "sg:phone":"+1 303 399 6517",
    "sg:postcode":"80112",
    "sg:province":"CO",
    "wof:name":"Empire Honda Inc",
    "wof:placetype":"venue"
},
  "geometry": {"coordinates":[-104.865807,39.594958],"type":"Point"}
}