{
  "type": "Feature",
  "properties": {
    "iso:country":"US",
    "sg:address":"8730 Chipita Park Rd",
    "sg:city":"Cascade",
    "sg:classifiers":[
        {
            "category":"Recreation",
            "type":"Entertainment"
        }
    ],
    "sg:phone":"+1 719 684 9606",
    "sg:postcode":"80809",
    "sg:province":"CO",
    "wof:name":"Valerie Clothier",
    "wof:placetype":"venue"
},
  "geometry": {"coordinates":[-104.98055600000001,38.912563],"type":"Point"}
}