{
  "type": "Feature",
  "properties": {
    "addr:full":"8135 N Academy Blvd Colorado Springs CO 80920",
    "addr:housenumber":"8135",
    "addr:postcode":"80920",
    "addr:street":"N Academy Blvd",
    "iso:country":"US",
    "sg:address":"8135 N Academy Blvd",
    "sg:city":"Colorado Springs",
    "sg:classifiers":[
        {
            "category":"Food & Beverages",
            "subcategory":"Groceries & Convenience Stores",
            "type":"Retail Goods"
        }
    ],
    "sg:phone":"+1 719 533 0530",
    "sg:postcode":"80920",
    "sg:province":"CO",
    "wof:name":"Jays Convenience Store Inc",
    "wof:placetype":"venue"
},
  "geometry": {"coordinates":[-104.80398099999999,38.948942],"type":"Point"}
}