{
  "type": "Feature",
  "properties": {
    "iso:country":"US",
    "sg:address":"690 Deer Blvd",
    "sg:city":"Avon",
    "sg:classifiers":[
        {
            "category":"Building & Trades",
            "subcategory":"Construction",
            "type":"Services"
        }
    ],
    "sg:phone":"+1 970 949 7133",
    "sg:postcode":"81620",
    "sg:province":"CO",
    "sg:tags":[
        "golf",
        "work",
        "feature",
        "contractor",
        "water",
        "course"
    ],
    "wof:name":"Alliance Golf Corporation",
    "wof:placetype":"venue"
},
  "geometry": {"coordinates":[-106.503212,39.622737],"type":"Point"}
}