{
  "type": "Feature",
  "properties": {
    "iso:country":"US",
    "sg:address":"105 S Sunset St",
    "sg:city":"Longmont",
    "sg:classifiers":[
        {
            "category":"Building & Trades",
            "subcategory":"Construction",
            "type":"Services"
        }
    ],
    "sg:phone":"+1 720 494 1675",
    "sg:postcode":"80501",
    "sg:province":"CO",
    "sg:tags":[
        "floor",
        "laying",
        "contractor"
    ],
    "wof:name":"Todays Flooring Installers",
    "wof:placetype":"venue"
},
  "geometry": {"coordinates":[-105.12144000000001,40.15727],"type":"Point"}
}