{
  "type": "Feature",
  "properties": {
    "iso:country":"US",
    "sg:address":"1422 Delgany Street",
    "sg:city":"Denver",
    "sg:classifiers":[
        {
            "category":"Banks & Credit Unions",
            "subcategory":"Financial Services",
            "type":"Services"
        }
    ],
    "sg:phone":"+1 303 825 1407",
    "sg:postcode":"80202",
    "sg:province":"CO",
    "sg:tags":[
        "broker",
        "mortgage"
    ],
    "wof:name":"Coast To Coast Mortgage",
    "wof:placetype":"venue"
},
  "geometry": {"coordinates":[-105.004718,39.751623],"type":"Point"}
}