{
  "type": "Feature",
  "properties": {
    "addr:full":"1279 Marion St Denver CO 80218",
    "addr:housenumber":"1279",
    "addr:postcode":"80218",
    "addr:street":"Marion St",
    "iso:country":"US",
    "sg:address":"1279 Marion St",
    "sg:city":"Denver",
    "sg:classifiers":[
        {
            "category":"Building & Trades",
            "subcategory":"Locksmith",
            "type":"Services"
        }
    ],
    "sg:phone":"+1 866 332 3182",
    "sg:postcode":"80218",
    "sg:province":"CO",
    "sg:tags":[
        "key"
    ],
    "wof:name":"Anytime Emergency Locksmith",
    "wof:placetype":"venue"
},
  "geometry": {"coordinates":[-104.971998,39.736537],"type":"Point"}
}