{
  "type": "Feature",
  "properties": {
    "addr:full":"825 Collyer St Longmont CO 80501",
    "addr:housenumber":"825",
    "addr:postcode":"80501",
    "addr:street":"Collyer St",
    "iso:country":"US",
    "sg:address":"825 Collyer St",
    "sg:city":"Longmont",
    "sg:classifiers":[
        {
            "category":"Organizations",
            "subcategory":"Non-profit Organization",
            "type":"Services"
        }
    ],
    "sg:phone":"+1 303 772 0017",
    "sg:postcode":"80501",
    "sg:province":"CO",
    "sg:tags":[
        "fund",
        "counselor",
        "raising"
    ],
    "sg:website":"www.churchfund-raising.com",
    "wof:name":"Church Fund-Raising Svc",
    "wof:placetype":"venue"
},
  "geometry": {"coordinates":[-105.098229,40.17353],"type":"Point"}
}