{
  "type": "Feature",
  "properties": {
    "addr:full":"3031 S Academy Blvd Colorado Springs CO 80916",
    "addr:housenumber":"3031",
    "addr:postcode":"80916",
    "addr:street":"S Academy Blvd",
    "iso:country":"US",
    "sg:address":"3031 S Academy Blvd",
    "sg:city":"Colorado Springs",
    "sg:classifiers":[
        {
            "category":"Health Services",
            "subcategory":"Chiropractor",
            "type":"Services"
        }
    ],
    "sg:phone":"+1 719 392 1218",
    "sg:postcode":"80916",
    "sg:province":"CO",
    "wof:name":"Koontz Chiropractic PC",
    "wof:placetype":"venue"
},
  "geometry": {"coordinates":[-104.757446,38.786137],"type":"Point"}
}