{
  "type": "Feature",
  "properties": {
    "addr:full":"12157 E Nevada Ave Aurora CO 80012",
    "addr:housenumber":"12157",
    "addr:postcode":"80012",
    "addr:street":"E Nevada Ave",
    "iso:country":"US",
    "sg:address":"12157 E Nevada Ave",
    "sg:city":"Aurora",
    "sg:classifiers":[
        {
            "category":"Bakery",
            "type":"Food & Drink"
        }
    ],
    "sg:phone":"+1 303 367 4666",
    "sg:postcode":"80012",
    "sg:province":"CO",
    "wof:name":"Diane's Treats",
    "wof:placetype":"venue"
},
  "geometry": {"coordinates":[-104.84686000000001,39.710489],"type":"Point"}
}