{
  "type": "Feature",
  "properties": {
    "addr:full":"1351 Collyer St Longmont CO 80501",
    "addr:housenumber":"1351",
    "addr:postcode":"80501",
    "addr:street":"Collyer St",
    "iso:country":"US",
    "sg:address":"1351 Collyer St",
    "sg:city":"Longmont",
    "sg:classifiers":[
        {
            "category":"Organizations",
            "subcategory":"Religious Organization",
            "type":"Services"
        }
    ],
    "sg:phone":"+1 303 776 2625",
    "sg:postcode":"80501",
    "sg:province":"CO",
    "sg:tags":[
        "church"
    ],
    "wof:name":"Church Of Christ",
    "wof:placetype":"venue"
},
  "geometry": {"coordinates":[-105.09775,40.18232],"type":"Point"}
}