{
  "type": "Feature",
  "properties": {
    "addr:full":"9668 E Arapahoe Rd Englewood CO 80112",
    "addr:housenumber":"9668",
    "addr:postcode":"80112",
    "addr:street":"E Arapahoe Rd",
    "iso:country":"US",
    "sg:address":"9668 E Arapahoe Rd",
    "sg:city":"Englewood",
    "sg:classifiers":[
        {
            "category":"Restaurant",
            "type":"Food & Drink"
        }
    ],
    "sg:phone":"+1 303 792 3474",
    "sg:postcode":"80112",
    "sg:province":"CO",
    "sg:tags":[
        "seafood"
    ],
    "wof:name":"Mesquite House Seafood Rest",
    "wof:placetype":"venue"
},
  "geometry": {"coordinates":[-104.877833,39.594962],"type":"Point"}
}