{
  "type": "Feature",
  "properties": {
    "addr:full":"605 Grant St Denver CO 80203",
    "addr:housenumber":"605",
    "addr:postcode":"80203",
    "addr:street":"Grant St",
    "iso:country":"US",
    "sg:address":"605 Grant St",
    "sg:city":"Denver",
    "sg:classifiers":[
        {
            "category":"Building & Trades",
            "subcategory":"Locksmith",
            "type":"Services"
        }
    ],
    "sg:phone":"+1 720 836 6030",
    "sg:postcode":"80203",
    "sg:province":"CO",
    "sg:tags":[
        "key"
    ],
    "wof:name":"AAA Anytime Locksmith",
    "wof:placetype":"venue"
},
  "geometry": {"coordinates":[-104.98379799999999,39.725699],"type":"Point"}
}