{
  "type": "Feature",
  "properties": {
    "addr:full":"8727 S Fairall Rd Morrison CO 80465",
    "addr:housenumber":"8727",
    "addr:postcode":"80465",
    "addr:street":"S Fairall Rd",
    "iso:country":"US",
    "sg:address":"8727 S Fairall Rd",
    "sg:city":"Morrison",
    "sg:classifiers":[
        {
            "category":"Building & Trades",
            "subcategory":"Construction",
            "type":"Services"
        }
    ],
    "sg:phone":"+1 303 697 6830",
    "sg:postcode":"80465",
    "sg:province":"CO",
    "sg:tags":[
        "house"
    ],
    "wof:name":"Rh Construction",
    "wof:placetype":"venue"
},
  "geometry": {"coordinates":[-105.263966,39.554788],"type":"Point"}
}