{
  "type": "Feature",
  "properties": {
    "addr:full":"733 E Boulder St Colorado Springs CO 80903",
    "addr:housenumber":"733",
    "addr:postcode":"80903",
    "addr:street":"E Boulder St",
    "iso:country":"US",
    "sg:address":"733 E Boulder St",
    "sg:city":"Colorado Springs",
    "sg:classifiers":[
        {
            "category":"Professional",
            "type":"Services"
        }
    ],
    "sg:phone":"+1 719 630 1911",
    "sg:postcode":"80903",
    "sg:province":"CO",
    "sg:tags":[
        "establishment"
    ],
    "wof:name":"Dog House",
    "wof:placetype":"venue"
},
  "geometry": {"coordinates":[-104.810413,38.839063],"type":"Point"}
}