{
  "type": "Feature",
  "properties": {
    "iso:country":"US",
    "sg:address":"530 Main St",
    "sg:city":"Grand Junction",
    "sg:classifiers":[
        {
            "category":"Government",
            "subcategory":"Office",
            "type":"Public Place"
        }
    ],
    "sg:phone":"+1 970 241 7294",
    "sg:postcode":"81501",
    "sg:province":"CO",
    "sg:tags":[
        "legislative",
        "body"
    ],
    "wof:name":"John Salazar For Congress",
    "wof:placetype":"venue"
},
  "geometry": {"coordinates":[-108.56323999999999,39.067431],"type":"Point"}
}