{
  "type": "Feature",
  "properties": {
    "addr:full":"501 W Platte Ave Fort Morgan CO 80701",
    "addr:housenumber":"501",
    "addr:postcode":"80701",
    "addr:street":"W Platte Ave",
    "iso:country":"US",
    "sg:address":"501 W Platte Ave",
    "sg:city":"Fort Morgan",
    "sg:classifiers":[
        {
            "category":"Insurance",
            "subcategory":"Insurance Agent",
            "type":"Services"
        }
    ],
    "sg:phone":"+1 970 867 3028",
    "sg:postcode":"80701",
    "sg:province":"CO",
    "wof:name":"State Farm Insurance",
    "wof:placetype":"venue"
},
  "geometry": {"coordinates":[-103.808566,40.254003],"type":"Point"}
}