{
  "type": "Feature",
  "properties": {
    "addr:full":"615 E Mesa Ave Pueblo CO 81006",
    "addr:housenumber":"615",
    "addr:postcode":"81006",
    "addr:street":"E Mesa Ave",
    "iso:country":"US",
    "sg:address":"615 E Mesa Ave",
    "sg:city":"Pueblo",
    "sg:classifiers":[
        {
            "category":"Restaurant",
            "type":"Food & Drink"
        }
    ],
    "sg:phone":"+1 719 542 9825",
    "sg:postcode":"81006",
    "sg:province":"CO",
    "sg:tags":[
        "drinking",
        "eating"
    ],
    "wof:name":"Grand Prix Restaurant & Lounge",
    "wof:placetype":"venue"
},
  "geometry": {"coordinates":[-104.605037,38.246204],"type":"Point"}
}