{
  "type": "Feature",
  "properties": {
    "iso:country":"US",
    "sg:address":"13200 W 43rd Dr",
    "sg:city":"Golden",
    "sg:classifiers":[
        {
            "category":"Autos & Motor Vehicles",
            "subcategory":"Auto Supplies",
            "type":"Retail Goods"
        }
    ],
    "sg:phone":"+1 303 279 6111",
    "sg:postcode":"80403",
    "sg:province":"CO",
    "sg:tags":[
        "automobile",
        "accessory"
    ],
    "wof:name":"Rhino Linings of Golden",
    "wof:placetype":"venue"
},
  "geometry": {"coordinates":[-105.150435,39.775881],"type":"Point"}
}