{
  "type": "Feature",
  "properties": {
    "addr:full":"734 Daffodil St Fountain CO 80817",
    "addr:housenumber":"734",
    "addr:postcode":"80817",
    "addr:street":"Daffodil St",
    "iso:country":"US",
    "sg:address":"734 Daffodil St",
    "sg:city":"Fountain",
    "sg:classifiers":[
        {
            "category":"Home & Garden",
            "subcategory":"Hardware",
            "type":"Retail Goods"
        }
    ],
    "sg:phone":"+1 719 382 0215",
    "sg:postcode":"80817",
    "sg:province":"CO",
    "wof:name":"True Spirit Financial LLC",
    "wof:placetype":"venue"
},
  "geometry": {"coordinates":[-104.682169,38.669112],"type":"Point"}
}