{
  "type": "Feature",
  "properties": {
    "addr:full":"7687 Concord Dr Boulder CO 80301",
    "addr:housenumber":"7687",
    "addr:postcode":"80301",
    "addr:street":"Concord Dr",
    "iso:country":"US",
    "sg:address":"7687 Concord Dr",
    "sg:city":"Boulder",
    "sg:classifiers":[
        {
            "category":"Wholesale",
            "subcategory":"Electrical",
            "type":"Manufacturing & Wholesale Goods"
        }
    ],
    "sg:phone":"+1 303 581 9526",
    "sg:postcode":"80301",
    "sg:province":"CO",
    "sg:tags":[
        "equipment"
    ],
    "wof:name":"Speedy Sing Works",
    "wof:placetype":"venue"
},
  "geometry": {"coordinates":[-105.174736,40.057995],"type":"Point"}
}