{
  "type": "Feature",
  "properties": {
    "iso:country":"US",
    "sg:address":"47517 Co Rd 17",
    "sg:city":"Elizabeth",
    "sg:classifiers":[
        {
            "category":"Shopping",
            "subcategory":"Bicycles & Sporting Goods",
            "type":"Retail Goods"
        }
    ],
    "sg:phone":"+1 303 841 0265",
    "sg:postcode":"80107",
    "sg:province":"CO",
    "sg:tags":[
        "turf",
        "tack",
        "supply"
    ],
    "wof:name":"Arapahoe Tack & Turf Supply",
    "wof:placetype":"venue"
},
  "geometry": {"coordinates":[-104.587838,39.558722],"type":"Point"}
}