{
  "type": "Feature",
  "properties": {
    "addr:full":"46465 Co Rd 6 Haxtun CO 80731",
    "addr:housenumber":"46465",
    "addr:postcode":"80731",
    "addr:street":"Co Rd 6 Haxtun",
    "iso:country":"US",
    "sg:address":"46465 Co Rd 6",
    "sg:city":"Haxtun",
    "sg:classifiers":[
        {
            "category":"Farming",
            "subcategory":"Farm",
            "type":"Manufacturing & Wholesale Goods"
        }
    ],
    "sg:phone":"+1 970 774 6446",
    "sg:postcode":"80731",
    "sg:province":"CO",
    "wof:name":"Hinde Farms",
    "wof:placetype":"venue"
},
  "geometry": {"coordinates":[-102.695915,40.467704],"type":"Point"}
}