{
  "type": "Feature",
  "properties": {
    "iso:country":"US",
    "sg:address":"11104 Ponderosa Ln",
    "sg:city":"Franktown",
    "sg:classifiers":[
        {
            "category":"Freight",
            "type":"Transportation"
        }
    ],
    "sg:phone":"+1 303 841 4494",
    "sg:postcode":"80116",
    "sg:province":"CO",
    "sg:tags":[
        "operator",
        "local",
        "trucking"
    ],
    "wof:name":"Burton Trucking",
    "wof:placetype":"venue"
},
  "geometry": {"coordinates":[-104.68013000000001,39.405329],"type":"Point"}
}