{
  "type": "Feature",
  "properties": {
    "iso:country":"US",
    "sg:address":"3273 Revere St",
    "sg:city":"Aurora",
    "sg:classifiers":[
        {
            "category":"Retail",
            "subcategory":"Laundry & Dry Cleaning",
            "type":"Services"
        }
    ],
    "sg:phone":"+1 303 340 4042",
    "sg:postcode":"80011",
    "sg:province":"CO",
    "sg:tags":[
        "cleaners",
        "rug",
        "carpet"
    ],
    "wof:name":"Looks Good Carpet Cleaning",
    "wof:placetype":"venue"
},
  "geometry": {"coordinates":[-104.84138799999999,39.762381],"type":"Point"}
}