{
  "type": "Feature",
  "properties": {
    "addr:full":"1284 S Abilene St Aurora CO 80012",
    "addr:housenumber":"1284",
    "addr:postcode":"80012",
    "addr:street":"S Abilene St",
    "iso:country":"US",
    "sg:address":"1284 S Abilene St",
    "sg:city":"Aurora",
    "sg:classifiers":[
        {
            "category":"Restaurant",
            "type":"Food & Drink"
        }
    ],
    "sg:phone":"+1 303 338 1424",
    "sg:postcode":"80012",
    "sg:province":"CO",
    "sg:tags":[
        "eating"
    ],
    "sg:website":"www.jasonsdeli.com",
    "wof:name":"Jason's Deli",
    "wof:placetype":"venue"
},
  "geometry": {"coordinates":[-104.828221,39.693891],"type":"Point"}
}