{
  "type": "Feature",
  "properties": {
    "iso:country":"US",
    "sg:address":"2755 S Locust Street Suite 104",
    "sg:city":"Denver",
    "sg:classifiers":[
        {
            "category":"Health Services",
            "subcategory":"Doctor",
            "type":"Services"
        }
    ],
    "sg:phone":"+1 303 753 9640",
    "sg:postcode":"80222",
    "sg:province":"CO",
    "sg:tags":[
        "psychiatrist"
    ],
    "wof:name":"Waldo Judy MD",
    "wof:placetype":"venue"
},
  "geometry": {"coordinates":[-104.915792,39.666715],"type":"Point"}
}