{
  "type": "Feature",
  "properties": {
    "addr:full":"721 Whiterock Ave Crested Butte CO 81224",
    "addr:housenumber":"721",
    "addr:postcode":"81224",
    "addr:street":"Whiterock Ave",
    "iso:country":"US",
    "sg:address":"721 Whiterock Ave",
    "sg:city":"Crested Butte",
    "sg:classifiers":[
        {
            "category":"Health Services",
            "subcategory":"Doctor",
            "type":"Services"
        }
    ],
    "sg:phone":"+1 970 349 2777",
    "sg:postcode":"81224",
    "sg:province":"CO",
    "sg:tags":[
        "physician",
        "surgeon"
    ],
    "wof:name":"Coal Creek Wellness Ctr",
    "wof:placetype":"venue"
},
  "geometry": {"coordinates":[-106.977929,38.868019],"type":"Point"}
}