{
  "type": "Feature",
  "properties": {
    "iso:country":"US",
    "sg:address":"1805 Shea Center Dr",
    "sg:city":"Littleton",
    "sg:classifiers":[
        {
            "category":"Building & Trades",
            "subcategory":"Construction",
            "type":"Services"
        }
    ],
    "sg:phone":"+1 720 348 1236",
    "sg:postcode":"80129",
    "sg:province":"CO",
    "sg:tags":[
        "home",
        "builder"
    ],
    "sg:website":"www.bellecreek.com",
    "wof:name":"Greentree Homes Bell Crk Sls",
    "wof:placetype":"venue"
},
  "geometry": {"coordinates":[-105.008816,39.553201],"type":"Point"}
}