{
  "type": "Feature",
  "properties": {
    "addr:full":"6413 S Hudson St Centennial CO 80121",
    "addr:housenumber":"6413",
    "addr:postcode":"80121",
    "addr:street":"S Hudson St",
    "iso:country":"US",
    "sg:address":"6413 S Hudson St",
    "sg:city":"Centennial",
    "sg:classifiers":[
        {
            "category":"Professional",
            "subcategory":"Business Services",
            "type":"Services"
        }
    ],
    "sg:phone":"+1 303 221 4771",
    "sg:postcode":"80121",
    "sg:province":"CO",
    "sg:tags":[
        "interior",
        "consultant",
        "design",
        "decorator"
    ],
    "wof:name":"Elisabete Hummel Interior Dsgn",
    "wof:placetype":"venue"
},
  "geometry": {"coordinates":[-104.923716,39.600234],"type":"Point"}
}