{
  "type": "Feature",
  "properties": {
    "addr:full":"31759 Co Rd B Stratton CO 80836",
    "addr:housenumber":"31759",
    "addr:postcode":"80836",
    "addr:street":"Co Rd B",
    "iso:country":"US",
    "sg:address":"31759 Co Rd B",
    "sg:city":"Stratton",
    "sg:classifiers":[
        {
            "category":"Farming",
            "subcategory":"Farm & Veterinary Services",
            "type":"Manufacturing & Wholesale Goods"
        }
    ],
    "sg:phone":"+1 719 348 5367",
    "sg:postcode":"80836",
    "sg:province":"CO",
    "sg:tags":[
        "breeder",
        "livestock"
    ],
    "wof:name":"Jim Mc Cormick Feed Lot",
    "wof:placetype":"venue"
},
  "geometry": {"coordinates":[-102.600871,39.054892],"type":"Point"}
}