{
  "type": "Feature",
  "properties": {
    "iso:country":"US",
    "sg:address":"18695 Pony Express Dr",
    "sg:city":"Parker",
    "sg:phone":"+1 800 275 8777",
    "sg:postcode":"80134",
    "sg:province":"CO",
    "sg:website":"http://www.usps.com",
    "wof:name":"United States Postal Service",
    "wof:placetype":"venue"
},
  "geometry": {"coordinates":[-104.77092399999999,39.521192],"type":"Point"}
}