{
  "type": "Feature",
  "properties": {
    "iso:country":"US",
    "sg:address":"210 3rd St",
    "sg:city":"Paonia",
    "sg:classifiers":[
        {
            "category":"Food & Beverages",
            "subcategory":"Bakery",
            "type":"Retail Goods"
        }
    ],
    "sg:phone":"+1 970 527 5551",
    "sg:postcode":"81428",
    "sg:province":"CO",
    "sg:tags":[
        "baker"
    ],
    "wof:name":"Moonrise Espresso & Bakery",
    "wof:placetype":"venue"
},
  "geometry": {"coordinates":[-107.597689,38.868619],"type":"Point"}
}