{
  "type": "Feature",
  "properties": {
    "iso:country":"US",
    "sg:address":"981 Cowen Dr",
    "sg:city":"Carbondale",
    "sg:classifiers":[
        {
            "category":"Sports & Exercise",
            "subcategory":"Gym",
            "type":"Entertainment"
        }
    ],
    "sg:phone":"+1 970 704 9889",
    "sg:postcode":"81623",
    "sg:province":"CO",
    "sg:tags":[
        "pilate"
    ],
    "wof:name":"Jobody Pilates",
    "wof:placetype":"venue"
},
  "geometry": {"coordinates":[-107.21917000000001,39.413135],"type":"Point"}
}