{
  "type": "Feature",
  "properties": {
    "iso:country":"US",
    "sg:address":"865 S Colorado Blvd",
    "sg:city":"Denver",
    "sg:classifiers":[
        {
            "category":"Building & Trades",
            "subcategory":"Locksmith",
            "type":"Services"
        }
    ],
    "sg:phone":"+1 303 495 1087",
    "sg:postcode":"80246",
    "sg:province":"CO",
    "sg:tags":[
        "key"
    ],
    "wof:name":"A 24 7 Able Locksmith",
    "wof:placetype":"venue"
},
  "geometry": {"coordinates":[-104.940948,39.700846],"type":"Point"}
}