{
  "type": "Feature",
  "properties": {
    "addr:full":"5462 Pueblo Pl Boulder CO 80303",
    "addr:housenumber":"5462",
    "addr:postcode":"80303",
    "addr:street":"Pueblo Pl",
    "iso:country":"US",
    "sg:address":"5462 Pueblo Pl",
    "sg:city":"Boulder",
    "sg:classifiers":[
        {
            "category":"Professional",
            "subcategory":"Business Services",
            "type":"Services"
        }
    ],
    "sg:phone":"+1 303 494 7882",
    "sg:postcode":"80303",
    "sg:province":"CO",
    "sg:tags":[
        "translator",
        "interpreter"
    ],
    "wof:name":"Translating Spanish",
    "wof:placetype":"venue"
},
  "geometry": {"coordinates":[-105.224951,39.994185],"type":"Point"}
}