{
  "type": "Feature",
  "properties": {
    "iso:country":"US",
    "sg:address":"4300 Ingalls St",
    "sg:city":"Wheat Ridge",
    "sg:classifiers":[
        {
            "category":"Retail",
            "subcategory":"Laundry & Dry Cleaning",
            "type":"Services"
        }
    ],
    "sg:phone":"+1 303 762 7387",
    "sg:postcode":"80033",
    "sg:province":"CO",
    "wof:name":"Americare",
    "wof:placetype":"venue"
},
  "geometry": {"coordinates":[-105.063722,39.775084],"type":"Point"}
}