{
  "type": "Feature",
  "properties": {
    "iso:country":"US",
    "sg:address":"2525 13th St",
    "sg:city":"Boulder",
    "sg:classifiers":[
        {
            "category":"Health Services",
            "subcategory":"Doctor",
            "type":"Services"
        }
    ],
    "sg:phone":"+1 303 440 0884",
    "sg:postcode":"80304",
    "sg:province":"CO",
    "sg:tags":[
        "clinic"
    ],
    "wof:name":"Kaiser Permanente Health Care",
    "wof:placetype":"venue"
},
  "geometry": {"coordinates":[-105.28063299999999,40.024232],"type":"Point"}
}