{
  "type": "Feature",
  "properties": {
    "addr:full":"6724 S Webster St Littleton CO 80128",
    "addr:housenumber":"6724",
    "addr:postcode":"80128",
    "addr:street":"S Webster St",
    "iso:country":"US",
    "sg:address":"6724 S Webster St",
    "sg:city":"Littleton",
    "sg:classifiers":[
        {
            "category":"Organizations",
            "subcategory":"Religious Organization",
            "type":"Services"
        }
    ],
    "sg:phone":"+1 303 972 1716",
    "sg:postcode":"80128",
    "sg:province":"CO",
    "sg:tags":[
        "church"
    ],
    "sg:website":"www.columbineuuchurch.org",
    "wof:name":"Columbine Unitarian Unvrslst",
    "wof:placetype":"venue"
},
  "geometry": {"coordinates":[-105.077322,39.594222],"type":"Point"}
}