{
  "type": "Feature",
  "properties": {
    "addr:full":"34215 US Hwy 6 Edwards CO 81632",
    "addr:postcode":"34215;81632",
    "addr:street":"Us Hwy 6 Edwards",
    "iso:country":"US",
    "sg:address":"34215 US Hwy 6",
    "sg:city":"Edwards",
    "sg:classifiers":[
        {
            "category":"Professional",
            "subcategory":"Advertising",
            "type":"Services"
        }
    ],
    "sg:phone":"+1 970 926 6700",
    "sg:postcode":"81632",
    "sg:province":"CO",
    "sg:tags":[
        "counselor"
    ],
    "sg:website":"www.hillncompany.com",
    "wof:name":"Hill & Co Integrated Mrktng",
    "wof:placetype":"venue"
},
  "geometry": {"coordinates":[-106.593728,39.64406],"type":"Point"}
}