{
  "type": "Feature",
  "properties": {
    "addr:full":"1244 N 1st St Montrose CO 81401",
    "addr:housenumber":"1244",
    "addr:postcode":"81401",
    "addr:street":"N 1St St",
    "iso:country":"US",
    "sg:address":"1244 N 1st St",
    "sg:city":"Montrose",
    "sg:classifiers":[
        {
            "category":"Freight",
            "type":"Transportation"
        }
    ],
    "sg:phone":"+1 970 249 7178",
    "sg:postcode":"81401",
    "sg:province":"CO",
    "sg:tags":[
        "operator",
        "local",
        "trucking"
    ],
    "wof:name":"Grimsley Trucking",
    "wof:placetype":"venue"
},
  "geometry": {"coordinates":[-107.868567,38.486284],"type":"Point"}
}