{
  "type": "Feature",
  "properties": {
    "addr:full":"3019 Toupal Dr Trinidad CO 81082",
    "addr:housenumber":"3019",
    "addr:postcode":"81082",
    "addr:street":"Toupal Dr",
    "iso:country":"US",
    "sg:address":"3019 Toupal Dr",
    "sg:city":"Trinidad",
    "sg:classifiers":[
        {
            "category":"Autos & Motor Vehicles",
            "subcategory":"Automobile Sales",
            "type":"Retail Goods"
        }
    ],
    "sg:phone":"+1 719 846 9805",
    "sg:postcode":"81082",
    "sg:province":"CO",
    "sg:tags":[
        "car",
        "dealer"
    ],
    "wof:name":"Circle Chevrolet-Buick",
    "wof:placetype":"venue"
},
  "geometry": {"coordinates":[-104.522684,37.138309],"type":"Point"}
}