{
  "type": "Feature",
  "properties": {
    "addr:full":"1715 70th Ave Greeley CO 80634",
    "addr:housenumber":"1715",
    "addr:postcode":"80634",
    "addr:street":"70Th Ave",
    "iso:country":"US",
    "sg:address":"1715 70th Ave",
    "sg:city":"Greeley",
    "sg:classifiers":[
        {
            "category":"Personal",
            "subcategory":"Beauty Salon",
            "type":"Services"
        }
    ],
    "sg:phone":"+1 970 356 1847",
    "sg:postcode":"80634",
    "sg:province":"CO",
    "wof:name":"Hair Co",
    "wof:placetype":"venue"
},
  "geometry": {"coordinates":[-104.793589,40.410085],"type":"Point"}
}