{
  "type": "Feature",
  "properties": {
    "iso:country":"US",
    "sg:address":"11990 Grant St",
    "sg:city":"Northglenn",
    "sg:classifiers":[
        {
            "category":"Mining & Drilling",
            "type":"Manufacturing & Wholesale Goods"
        }
    ],
    "sg:phone":"+1 303 280 4511",
    "sg:postcode":"80233",
    "sg:province":"CO",
    "sg:tags":[
        "development",
        "gas",
        "oil",
        "exploration"
    ],
    "wof:name":"Wellstar Corp",
    "wof:placetype":"venue"
},
  "geometry": {"coordinates":[-104.981416,39.911398],"type":"Point"}
}