{
  "type": "Feature",
  "properties": {
    "addr:full":"5539 Washington St Denver CO 80216",
    "addr:housenumber":"5539",
    "addr:postcode":"80216",
    "addr:street":"Washington St",
    "iso:country":"US",
    "sg:address":"5539 Washington St",
    "sg:city":"Denver",
    "sg:classifiers":[
        {
            "category":"Autos & Motor Vehicles",
            "subcategory":"Auto Supplies",
            "type":"Retail Goods"
        }
    ],
    "sg:phone":"+1 303 308 3008",
    "sg:postcode":"80216",
    "sg:province":"CO",
    "sg:tags":[
        "tire"
    ],
    "wof:name":"Llantas America",
    "wof:placetype":"venue"
},
  "geometry": {"coordinates":[-104.978317,39.797649],"type":"Point"}
}