{
  "type": "Feature",
  "properties": {
    "iso:country":"US",
    "sg:address":"524 Ski Rd",
    "sg:city":"Allenspark",
    "sg:classifiers":[
        {
            "category":"Professional",
            "subcategory":"Management & Consulting",
            "type":"Services"
        }
    ],
    "sg:phone":"+1 303 747 0716",
    "sg:postcode":"80510",
    "sg:province":"CO",
    "sg:tags":[
        "fire",
        "consultant",
        "protection"
    ],
    "wof:name":"Tahosa Forest Svc",
    "wof:placetype":"venue"
},
  "geometry": {"coordinates":[-105.524485,40.190766],"type":"Point"}
}