{
  "type": "Feature",
  "properties": {
    "addr:full":"831 S Perry St Castle Rock CO 80104",
    "addr:housenumber":"831",
    "addr:postcode":"80104",
    "addr:street":"S Perry St",
    "iso:country":"US",
    "sg:address":"831 S Perry St",
    "sg:city":"Castle Rock",
    "sg:classifiers":[
        {
            "category":"Insurance",
            "subcategory":"Insurance Agent",
            "type":"Services"
        }
    ],
    "sg:phone":"+1 303 688 9597",
    "sg:postcode":"80104",
    "sg:province":"CO",
    "wof:name":"Douglas County Insurance Svc",
    "wof:placetype":"venue"
},
  "geometry": {"coordinates":[-104.861493,39.364514],"type":"Point"}
}