{
  "type": "Feature",
  "properties": {
    "iso:country":"US",
    "sg:address":"795 Garrison Ct",
    "sg:city":"Grand Junction",
    "sg:classifiers":[
        {
            "category":"Real Estate",
            "subcategory":"Developer",
            "type":"Services"
        }
    ],
    "sg:phone":"+1 970 243 5902",
    "sg:postcode":"81506",
    "sg:province":"CO",
    "wof:name":"GNT Development Corp",
    "wof:placetype":"venue"
},
  "geometry": {"coordinates":[-108.556107,39.120805],"type":"Point"}
}