{
  "type": "Feature",
  "properties": {
    "iso:country":"US",
    "sg:address":"5785 Arapahoe Ave",
    "sg:city":"Boulder",
    "sg:classifiers":[
        {
            "category":"Sports & Exercise",
            "subcategory":"Gym",
            "type":"Entertainment"
        }
    ],
    "sg:phone":"+1 303 443 7667",
    "sg:postcode":"80303",
    "sg:province":"CO",
    "sg:tags":[
        "club",
        "health",
        "studio",
        "gymnasium"
    ],
    "wof:name":"Peak Physique Studio",
    "wof:placetype":"venue"
},
  "geometry": {"coordinates":[-105.216613,40.014797],"type":"Point"}
}