{
  "type": "Feature",
  "properties": {
    "addr:full":"1400 Walnut St Boulder CO 80302",
    "addr:housenumber":"1400",
    "addr:postcode":"80302",
    "addr:street":"Walnut St",
    "iso:country":"US",
    "sg:address":"1400 Walnut St",
    "sg:city":"Boulder",
    "sg:classifiers":[
        {
            "category":"Local Transit",
            "type":"Transportation"
        }
    ],
    "sg:phone":"+1 303 442 7332",
    "sg:postcode":"80302",
    "sg:province":"CO",
    "sg:tags":[
        "bus",
        "line"
    ],
    "wof:name":"Rtd",
    "wof:placetype":"venue"
},
  "geometry": {"coordinates":[-105.27569099999999,40.017686],"type":"Point"}
}