{
  "type": "Feature",
  "properties": {
    "iso:country":"US",
    "sg:address":"425 37th Avenue Ct",
    "sg:city":"Greeley",
    "sg:classifiers":[
        {
            "category":"Building & Trades",
            "subcategory":"Electrical",
            "type":"Services"
        }
    ],
    "sg:phone":"+1 970 356 6647",
    "sg:postcode":"80634",
    "sg:province":"CO",
    "sg:tags":[
        "contracting",
        "electrical"
    ],
    "wof:name":"S&D Electric",
    "wof:placetype":"venue"
},
  "geometry": {"coordinates":[-104.740295,40.428711],"type":"Point"}
}