{
  "type": "Feature",
  "properties": {
    "iso:country":"US",
    "sg:address":"805 Walnut St",
    "sg:city":"Boulder",
    "sg:classifiers":[
        {
            "category":"Wholesale",
            "subcategory":"Groceries",
            "type":"Manufacturing & Wholesale Goods"
        },
        {
            "category":"Manufacturing",
            "subcategory":"Chemicals & Compounds",
            "type":"Manufacturing & Wholesale Goods"
        }
    ],
    "sg:phone":"+1 303 443 0261",
    "sg:postcode":"80302",
    "sg:province":"CO",
    "sg:tags":[
        "med",
        "product",
        "mfg",
        "food",
        "medical",
        "doctor",
        "prep",
        "health",
        "pharmaceutical"
    ],
    "sg:website":"www.kroegerherb.com",
    "wof:name":"Kroeger Herb Wholesale Pdts Co",
    "wof:placetype":"venue"
},
  "geometry": {"coordinates":[-105.28362799999999,40.016134],"type":"Point"}
}