{
  "type": "Feature",
  "properties": {
    "addr:full":"517 E Hopkins Ave Aspen CO 81611",
    "addr:housenumber":"517",
    "addr:postcode":"81611",
    "addr:street":"E Hopkins Ave",
    "iso:country":"US",
    "sg:address":"517 E Hopkins Ave",
    "sg:city":"Aspen",
    "sg:classifiers":[
        {
            "category":"Manufacturing",
            "subcategory":"Printing",
            "type":"Manufacturing & Wholesale Goods"
        }
    ],
    "sg:phone":"+1 970 925 2220",
    "sg:postcode":"81611",
    "sg:province":"CO",
    "sg:tags":[
        "newspaper",
        "publisher"
    ],
    "wof:name":"Aspen Daily News The",
    "wof:placetype":"venue"
},
  "geometry": {"coordinates":[-106.818207,39.189498],"type":"Point"}
}