{
  "type": "Feature",
  "properties": {
    "iso:country":"US",
    "sg:address":"4450 Comanche Dr",
    "sg:city":"Boulder",
    "sg:classifiers":[
        {
            "category":"Real Estate",
            "subcategory":"Real Estate Agent",
            "type":"Services"
        }
    ],
    "sg:phone":"+1 303 499 8683",
    "sg:postcode":"80303",
    "sg:province":"CO",
    "wof:name":"Royal Retreats LLC",
    "wof:placetype":"venue"
},
  "geometry": {"coordinates":[-105.238275,39.997407],"type":"Point"}
}