{
  "type": "Feature",
  "properties": {
    "addr:full":"7350 E 29th Ave Ste 300 Denver CO 80238",
    "addr:housenumber":"7350",
    "addr:postcode":"80238",
    "addr:street":"E 29Th Ave Ste 300",
    "iso:country":"US",
    "sg:address":"7350 E 29th Ave Ste 300",
    "sg:city":"Denver",
    "sg:classifiers":[
        {
            "category":"Recreation",
            "type":"Entertainment"
        }
    ],
    "sg:phone":"+1 303 468 3260",
    "sg:postcode":"80238",
    "sg:province":"CO",
    "sg:tags":[
        "hiking"
    ],
    "sg:website":"www.sandcreekgreenway.org",
    "wof:name":"Sand Creek Regional Greenway",
    "wof:placetype":"venue"
},
  "geometry": {"coordinates":[-104.90253,39.758065],"type":"Point"}
}