{
  "type": "Feature",
  "properties": {
    "iso:country":"US",
    "sg:address":"29710 Denali Ln",
    "sg:city":"Evergreen",
    "sg:classifiers":[
        {
            "category":"Real Estate",
            "subcategory":"Real Estate Agent",
            "type":"Services"
        }
    ],
    "sg:phone":"+1 303 670 7866",
    "sg:postcode":"80439",
    "sg:province":"CO",
    "wof:name":"Candy Maijala Realtor",
    "wof:placetype":"venue"
},
  "geometry": {"coordinates":[-105.33756700000001,39.674446],"type":"Point"}
}