{
  "type": "Feature",
  "properties": {
    "iso:country":"US",
    "sg:address":"5701 Stapleton Dr N",
    "sg:city":"Denver",
    "sg:classifiers":[
        {
            "category":"Autos & Motor Vehicles",
            "subcategory":"Recreational Vehicle Sales",
            "type":"Retail Goods"
        }
    ],
    "sg:phone":"+1 303 321 2000",
    "sg:postcode":"80216",
    "sg:province":"CO",
    "sg:tags":[
        "canopy",
        "shell",
        "truck",
        "cap"
    ],
    "sg:website":"www.truckparts-specialists.com",
    "wof:name":"Truck Parts Specialists",
    "wof:placetype":"venue"
},
  "geometry": {"coordinates":[-104.92053199999999,39.778734],"type":"Point"}
}