{
  "type": "Feature",
  "properties": {
    "iso:country":"US",
    "sg:address":"226 N Tejon St",
    "sg:city":"Colorado Springs",
    "sg:classifiers":[
        {
            "category":"Professional",
            "subcategory":"Business Services",
            "type":"Services"
        }
    ],
    "sg:phone":"+1 719 520 0021",
    "sg:postcode":"80903",
    "sg:province":"CO",
    "wof:name":"Avalance Warning Information",
    "wof:placetype":"venue"
},
  "geometry": {"coordinates":[-104.82338300000001,38.837725],"type":"Point"}
}