{
  "type": "Feature",
  "properties": {
    "addr:full":"8654 Crimson Clover Ln Longmont CO 80503",
    "addr:housenumber":"8654",
    "addr:postcode":"80503",
    "addr:street":"Crimson Clover Ln",
    "iso:country":"US",
    "sg:address":"8654 Crimson Clover Ln",
    "sg:city":"Longmont",
    "sg:classifiers":[
        {
            "category":"Professional",
            "subcategory":"Management & Consulting",
            "type":"Services"
        }
    ],
    "sg:phone":"+1 303 651 1771",
    "sg:postcode":"80503",
    "sg:province":"CO",
    "sg:tags":[
        "counselor",
        "public",
        "relations"
    ],
    "wof:name":"Lynott & Assoc",
    "wof:placetype":"venue"
},
  "geometry": {"coordinates":[-105.174921,40.135284],"type":"Point"}
}