{
  "type": "Feature",
  "properties": {
    "iso:country":"US",
    "sg:address":"7911 York St",
    "sg:city":"Denver",
    "sg:classifiers":[
        {
            "category":"Farming",
            "subcategory":"Farm",
            "type":"Manufacturing & Wholesale Goods"
        }
    ],
    "sg:phone":"+1 303 288 3079",
    "sg:postcode":"80229",
    "sg:province":"CO",
    "sg:tags":[
        "crop"
    ],
    "wof:name":"Galaica Farms",
    "wof:placetype":"venue"
},
  "geometry": {"coordinates":[-104.95912800000001,39.84117],"type":"Point"}
}