{
  "type": "Feature",
  "properties": {
    "iso:country":"US",
    "sg:address":"2966 S Shoshone St",
    "sg:city":"Englewood",
    "sg:classifiers":[
        {
            "category":"Building & Trades",
            "subcategory":"Landscaping Services",
            "type":"Services"
        }
    ],
    "sg:phone":"+1 303 573 1473",
    "sg:postcode":"80110",
    "sg:province":"CO",
    "sg:tags":[
        "contractor"
    ],
    "wof:name":"Mitchs Greenthumb Ldscpg Corp",
    "wof:placetype":"venue"
},
  "geometry": {"coordinates":[-105.009823,39.663551],"type":"Point"}
}