{
  "type": "Feature",
  "properties": {
    "addr:full":"885 S Garfield St Denver CO 80209",
    "addr:housenumber":"885",
    "addr:postcode":"80209",
    "addr:street":"S Garfield St",
    "iso:country":"US",
    "sg:address":"885 S Garfield St",
    "sg:city":"Denver",
    "sg:classifiers":[
        {
            "category":"Real Estate",
            "subcategory":"Developer",
            "type":"Services"
        }
    ],
    "sg:phone":"+1 303 744 6550",
    "sg:postcode":"80209",
    "sg:province":"CO",
    "wof:name":"Powder River Land Exploration",
    "wof:placetype":"venue"
},
  "geometry": {"coordinates":[-104.944535,39.701694],"type":"Point"}
}