{
  "type": "Feature",
  "properties": {
    "iso:country":"US",
    "sg:address":"850 Englewood Pkwy",
    "sg:city":"Englewood",
    "sg:classifiers":[
        {
            "category":"Shopping",
            "subcategory":"Optical Goods",
            "type":"Retail Goods"
        },
        {
            "category":"Health Services",
            "subcategory":"Optometrist",
            "type":"Services"
        }
    ],
    "sg:phone":"+1 303 777 6633",
    "sg:postcode":"80110",
    "sg:province":"CO",
    "wof:name":"Vision Lab Family Eye Care",
    "wof:placetype":"venue"
},
  "geometry": {"coordinates":[-104.99722300000001,39.654811],"type":"Point"}
}