{
  "type": "Feature",
  "properties": {
    "iso:country":"US",
    "sg:address":"2253 Edgewood Dr",
    "sg:city":"Boulder",
    "sg:classifiers":[
        {
            "category":"Wholesale",
            "subcategory":"Groceries",
            "type":"Manufacturing & Wholesale Goods"
        }
    ],
    "sg:phone":"+1 303 449 5246",
    "sg:postcode":"80304",
    "sg:province":"CO",
    "sg:tags":[
        "a",
        "wholesaler",
        "as",
        "coffee",
        "operates"
    ],
    "wof:name":"Giuliana Imports LLC",
    "wof:placetype":"venue"
},
  "geometry": {"coordinates":[-105.267162,40.028457],"type":"Point"}
}