{
  "type": "Feature",
  "properties": {
    "addr:full":"999 Ogden St Denver CO 80218",
    "addr:housenumber":"999",
    "addr:postcode":"80218",
    "addr:street":"Ogden St",
    "iso:country":"US",
    "sg:address":"999 Ogden St",
    "sg:city":"Denver",
    "sg:classifiers":[
        {
            "category":"Professional",
            "type":"Services"
        }
    ],
    "sg:phone":"+1 303 863 7162",
    "sg:postcode":"80218",
    "sg:province":"CO",
    "wof:name":"Samaya Inc",
    "wof:placetype":"venue"
},
  "geometry": {"coordinates":[-104.975263,39.730449],"type":"Point"}
}