{
  "type": "Feature",
  "properties": {
    "addr:full":"2 Lake of the Falls Pkwy Mosca CO 81101",
    "addr:housenumber":"2",
    "addr:postcode":"81101",
    "addr:street":"Lake Of The Falls Pkwy Mosca",
    "iso:country":"US",
    "sg:address":"2 Lake of the Falls Pkwy",
    "sg:city":"Mosca",
    "sg:classifiers":[
        {
            "category":"Organizations",
            "subcategory":"Professional Association",
            "type":"Services"
        }
    ],
    "sg:phone":"+1 719 378 2099",
    "sg:postcode":"81101",
    "sg:province":"CO",
    "wof:name":"Zapata Homeowners Assn",
    "wof:placetype":"venue"
},
  "geometry": {"coordinates":[-105.58130300000001,37.651259],"type":"Point"}
}