{
  "type": "Feature",
  "properties": {
    "addr:full":"5390 Piedra Vis Colorado Springs CO 80908",
    "addr:housenumber":"5390",
    "addr:postcode":"80908",
    "addr:street":"Piedra Vis",
    "iso:country":"US",
    "sg:address":"5390 Piedra Vis",
    "sg:city":"Colorado Springs",
    "sg:classifiers":[
        {
            "category":"Building & Trades",
            "subcategory":"Plumbing",
            "type":"Services"
        }
    ],
    "sg:phone":"+1 719 494 1136",
    "sg:postcode":"80908",
    "sg:province":"CO",
    "sg:tags":[
        "contractor"
    ],
    "wof:name":"Atlantic Heating & AC",
    "wof:placetype":"venue"
},
  "geometry": {"coordinates":[-104.72106599999999,39.032834],"type":"Point"}
}