{
  "type": "Feature",
  "properties": {
    "iso:country":"US",
    "sg:address":"1905 W Harvard Ave",
    "sg:city":"Englewood",
    "sg:classifiers":[
        {
            "category":"Building & Trades",
            "subcategory":"Electrical",
            "type":"Services"
        }
    ],
    "sg:phone":"+1 720 981 4580",
    "sg:postcode":"80110",
    "sg:province":"CO",
    "sg:tags":[
        "breaker",
        "overhaul",
        "circuit",
        "maintenance"
    ],
    "wof:name":"Rocky Mtn Breaker Services",
    "wof:placetype":"venue"
},
  "geometry": {"coordinates":[-105.010102,39.671455],"type":"Point"}
}