{
  "type": "Feature",
  "properties": {
    "iso:country":"US",
    "sg:address":"2915 5th Ave",
    "sg:city":"Pueblo",
    "sg:classifiers":[
        {
            "category":"Building & Trades",
            "subcategory":"Construction",
            "type":"Services"
        }
    ],
    "sg:phone":"+1 719 251 0487",
    "sg:postcode":"81008",
    "sg:province":"CO",
    "sg:tags":[
        "handyman"
    ],
    "wof:name":"Tools On Wheels",
    "wof:placetype":"venue"
},
  "geometry": {"coordinates":[-104.621735,38.298525],"type":"Point"}
}