{
  "type": "Feature",
  "properties": {
    "addr:full":"11492 Dark Star Way Parker CO 80138",
    "addr:housenumber":"11492",
    "addr:postcode":"80138",
    "addr:street":"Dark Star Way",
    "iso:country":"US",
    "sg:address":"11492 Dark Star Way",
    "sg:city":"Parker",
    "sg:classifiers":[
        {
            "category":"Banks & Credit Unions",
            "subcategory":"Financial Services",
            "type":"Services"
        }
    ],
    "sg:phone":"+1 303 840 0232",
    "sg:postcode":"80138",
    "sg:province":"CO",
    "sg:tags":[
        "investor"
    ],
    "wof:name":"Dark Star Investments LLC",
    "wof:placetype":"venue"
},
  "geometry": {"coordinates":[-104.739616,39.509116],"type":"Point"}
}