{
  "type": "Feature",
  "properties": {
    "iso:country":"US",
    "sg:address":"165 Cook St",
    "sg:city":"Denver",
    "sg:classifiers":[
        {
            "category":"Banks & Credit Unions",
            "subcategory":"Bank",
            "type":"Services"
        }
    ],
    "sg:phone":"+1 303 526 2016",
    "sg:postcode":"80206",
    "sg:province":"CO",
    "sg:tags":[
        "loan",
        "real estate"
    ],
    "wof:name":"Charter Mortgage Group Inc",
    "wof:placetype":"venue"
},
  "geometry": {"coordinates":[-104.947451,39.718374],"type":"Point"}
}