{
  "type": "Feature",
  "properties": {
    "addr:full":"205 Commerce St Broomfield CO 80020",
    "addr:housenumber":"205",
    "addr:postcode":"80020",
    "addr:street":"Commerce St",
    "iso:country":"US",
    "sg:address":"205 Commerce St",
    "sg:city":"Broomfield",
    "sg:classifiers":[
        {
            "category":"Autos & Motor Vehicles",
            "subcategory":"Auto Supplies",
            "type":"Retail Goods"
        }
    ],
    "sg:phone":"+1 303 465 6300",
    "sg:postcode":"80020",
    "sg:province":"CO",
    "sg:website":"www.carquest.com",
    "wof:name":"Carquest Auto Parts",
    "wof:placetype":"venue"
},
  "geometry": {"coordinates":[-105.089671,39.91617],"type":"Point"}
}