{
  "type": "Feature",
  "properties": {
    "addr:full":"9340 S Waterford Ct Littleton CO 80130",
    "addr:housenumber":"9340",
    "addr:postcode":"80130",
    "addr:street":"S Waterford Ct",
    "iso:country":"US",
    "sg:address":"9340 S Waterford Ct",
    "sg:city":"Littleton",
    "sg:classifiers":[
        {
            "category":"Manufacturing",
            "subcategory":"Jewelry",
            "type":"Manufacturing & Wholesale Goods"
        }
    ],
    "sg:phone":"+1 303 470 9340",
    "sg:postcode":"80130",
    "sg:province":"CO",
    "sg:tags":[
        "precious",
        "metal",
        "mfg"
    ],
    "wof:name":"Chrysoula Ltd Inc",
    "wof:placetype":"venue"
},
  "geometry": {"coordinates":[-104.90654600000001,39.546181],"type":"Point"}
}