{
  "type": "Feature",
  "properties": {
    "addr:full":"730 Cleveland Ave Loveland CO 80537",
    "addr:housenumber":"730",
    "addr:postcode":"80537",
    "addr:street":"Cleveland Ave",
    "iso:country":"US",
    "sg:address":"730 Cleveland Ave",
    "sg:city":"Loveland",
    "sg:classifiers":[
        {
            "category":"Building & Trades",
            "subcategory":"Construction",
            "type":"Services"
        }
    ],
    "sg:phone":"+1 970 667 2735",
    "sg:postcode":"80537",
    "sg:province":"CO",
    "sg:tags":[
        "excavating",
        "contractor"
    ],
    "wof:name":"Haag Sand & Gravel Inc",
    "wof:placetype":"venue"
},
  "geometry": {"coordinates":[-105.07442500000001,40.399294],"type":"Point"}
}