{
  "type": "Feature",
  "properties": {
    "addr:full":"615 Main St Longmont CO 80501",
    "addr:housenumber":"615",
    "addr:postcode":"80501",
    "addr:street":"Main St",
    "iso:country":"US",
    "sg:address":"615 Main St",
    "sg:city":"Longmont",
    "sg:classifiers":[
        {
            "category":"Manufacturing",
            "subcategory":"Apparel",
            "type":"Manufacturing & Wholesale Goods"
        }
    ],
    "sg:phone":"+1 303 772 0880",
    "sg:postcode":"80501",
    "sg:province":"CO",
    "wof:name":"Acme",
    "wof:placetype":"venue"
},
  "geometry": {"coordinates":[-105.10257799999999,40.170433],"type":"Point"}
}