{
  "type": "Feature",
  "properties": {
    "iso:country":"US",
    "sg:address":"3720 Co Rd 214",
    "sg:city":"Silt",
    "sg:classifiers":[
        {
            "category":"Building & Trades",
            "subcategory":"Electrical",
            "type":"Services"
        }
    ],
    "sg:phone":"+1 970 876 5520",
    "sg:postcode":"81652",
    "sg:province":"CO",
    "sg:tags":[
        "electrical",
        "contractor"
    ],
    "wof:name":"Flatops Electric Inc",
    "wof:placetype":"venue"
},
  "geometry": {"coordinates":[-107.62145,39.556018],"type":"Point"}
}