{
  "type": "Feature",
  "properties": {
    "iso:country":"US",
    "sg:address":"13292 Clermont Ct",
    "sg:city":"Denver",
    "sg:classifiers":[
        {
            "category":"Building & Trades",
            "subcategory":"Construction",
            "type":"Services"
        }
    ],
    "sg:phone":"+1 303 451 6808",
    "sg:postcode":"80241",
    "sg:province":"CO",
    "sg:tags":[
        "general",
        "contractor"
    ],
    "wof:name":"B Dodd Construction",
    "wof:placetype":"venue"
},
  "geometry": {"coordinates":[-104.93499799999999,39.936806],"type":"Point"}
}