{
  "type": "Feature",
  "properties": {
    "addr:full":"12628 Pronghorn St Broomfield CO 80020",
    "addr:housenumber":"12628",
    "addr:postcode":"80020",
    "addr:street":"Pronghorn St",
    "iso:country":"US",
    "sg:address":"12628 Pronghorn St",
    "sg:city":"Broomfield",
    "sg:classifiers":[
        {
            "category":"Wholesale",
            "subcategory":"Machinery & Supplies",
            "type":"Manufacturing & Wholesale Goods"
        }
    ],
    "sg:phone":"+1 303 452 2452",
    "sg:postcode":"80020",
    "sg:province":"CO",
    "sg:tags":[
        "equipment",
        "irrigation",
        "system"
    ],
    "sg:website":"www.carmobil.com",
    "wof:name":"Hurricane/Carmobil Intl Inc",
    "wof:placetype":"venue"
},
  "geometry": {"coordinates":[-105.04127800000001,39.926877],"type":"Point"}
}