{
  "type": "Feature",
  "properties": {
    "addr:full":"612 Washington St Denver CO 80203",
    "addr:housenumber":"612",
    "addr:postcode":"80203",
    "addr:street":"Washington St",
    "iso:country":"US",
    "sg:address":"612 Washington St",
    "sg:city":"Denver",
    "sg:classifiers":[
        {
            "category":"Health Services",
            "subcategory":"Health Practitioner",
            "type":"Services"
        }
    ],
    "sg:phone":"+1 303 839 1010",
    "sg:postcode":"80203",
    "sg:province":"CO",
    "sg:tags":[
        "acupuncture"
    ],
    "wof:name":"Sheila J Compton",
    "wof:placetype":"venue"
},
  "geometry": {"coordinates":[-104.978696,39.72706],"type":"Point"}
}