{
  "type": "Feature",
  "properties": {
    "addr:full":"3301 Wedgewood Dr Pueblo CO 81005",
    "addr:housenumber":"3301",
    "addr:postcode":"81005",
    "addr:street":"Wedgewood Dr",
    "iso:country":"US",
    "sg:address":"3301 Wedgewood Dr",
    "sg:city":"Pueblo",
    "sg:classifiers":[
        {
            "category":"Shopping",
            "subcategory":"Gifts & Souvenirs",
            "type":"Retail Goods"
        }
    ],
    "sg:phone":"+1 719 564 9179",
    "sg:postcode":"81005",
    "sg:province":"CO",
    "wof:name":"Gift Bargains",
    "wof:placetype":"venue"
},
  "geometry": {"coordinates":[-104.647603,38.242095],"type":"Point"}
}