{
  "type": "Feature",
  "properties": {
    "addr:full":"5700 Dtc Pkwy Greenwood Vlg CO 80111",
    "addr:housenumber":"5700",
    "addr:postcode":"co 80111",
    "addr:street":"Dtc Pkwy",
    "iso:country":"US",
    "sg:address":"5700 Dtc Pkwy",
    "sg:city":"Greenwood Vlg",
    "sg:classifiers":[
        {
            "category":"Professional",
            "subcategory":"Computer Services",
            "type":"Services"
        }
    ],
    "sg:phone":"+1 303 770 2400",
    "sg:postcode":"80111",
    "sg:province":"CO",
    "sg:tags":[
        "processing",
        "datum"
    ],
    "sg:website":"www.wellsfargo.com",
    "wof:name":"Wells Fargo Svc",
    "wof:placetype":"venue"
},
  "geometry": {"coordinates":[-104.890434,39.612766],"type":"Point"}
}