{
  "type": "Feature",
  "properties": {
    "iso:country":"US",
    "sg:address":"3829 S Ventura St",
    "sg:city":"Aurora",
    "sg:classifiers":[
        {
            "category":"Building & Trades",
            "subcategory":"Landscaping Services",
            "type":"Services"
        }
    ],
    "sg:phone":"+1 303 922 0082",
    "sg:postcode":"80013",
    "sg:province":"CO",
    "wof:name":"D & H Landscaping & Home",
    "wof:placetype":"venue"
},
  "geometry": {"coordinates":[-104.778874,39.647505],"type":"Point"}
}