{
  "type": "Feature",
  "properties": {
    "iso:country":"US",
    "sg:address":"810 E 120th Ave",
    "sg:city":"Denver",
    "sg:classifiers":[
        {
            "category":"Restaurant",
            "type":"Food & Drink"
        }
    ],
    "sg:phone":"+1 303 450 6775",
    "sg:postcode":"80233",
    "sg:province":"CO",
    "sg:tags":[
        "eating"
    ],
    "wof:name":"Cafe Mexico Inc",
    "wof:placetype":"venue"
},
  "geometry": {"coordinates":[-104.972506,39.913832],"type":"Point"}
}