{
  "type": "Feature",
  "properties": {
    "iso:country":"US",
    "sg:address":"4550 E Alameda Ave",
    "sg:city":"Denver",
    "sg:classifiers":[
        {
            "category":"Organizations",
            "subcategory":"Religious Organization",
            "type":"Services"
        }
    ],
    "sg:phone":"+1 303 333 7794",
    "sg:postcode":"80246",
    "sg:province":"CO",
    "sg:tags":[
        "church"
    ],
    "sg:website":"www.denver.goarch.org",
    "wof:name":"Greek Orthodox Metropolis-Dnvr",
    "wof:placetype":"venue"
},
  "geometry": {"coordinates":[-104.934381,39.711421],"type":"Point"}
}