{
  "type": "Feature",
  "properties": {
    "addr:full":"6120 W 55th Ave Arvada CO 80002",
    "addr:housenumber":"6120",
    "addr:postcode":"80002",
    "addr:street":"W 55Th Ave",
    "iso:country":"US",
    "sg:address":"6120 W 55th Ave",
    "sg:city":"Arvada",
    "sg:classifiers":[
        {
            "category":"Retail",
            "subcategory":"Auto Repair",
            "type":"Services"
        }
    ],
    "sg:phone":"+1 303 940 7624",
    "sg:postcode":"80002",
    "sg:province":"CO",
    "sg:website":"www.ameritechtransmission.com",
    "wof:name":"Ameri-Tech Transmission Inc",
    "wof:placetype":"venue"
},
  "geometry": {"coordinates":[-105.06485499999999,39.796312],"type":"Point"}
}