{
  "type": "Feature",
  "properties": {
    "iso:country":"US",
    "sg:address":"13700 Legend Trl",
    "sg:city":"Broomfield",
    "sg:classifiers":[
        {
            "category":"Professional",
            "type":"Services"
        }
    ],
    "sg:phone":"+1 720 887 2778",
    "sg:postcode":"80023",
    "sg:province":"CO",
    "sg:tags":[
        "establishment"
    ],
    "wof:name":"Broadlands Active Adult Ctr",
    "wof:placetype":"venue"
},
  "geometry": {"coordinates":[-105.033113,39.947227],"type":"Point"}
}