{
  "type": "Feature",
  "properties": {
    "addr:full":"7945 Armadillo Trl Evergreen CO 80439",
    "addr:housenumber":"7945",
    "addr:postcode":"80439",
    "addr:street":"Armadillo Trl",
    "iso:country":"US",
    "sg:address":"7945 Armadillo Trl",
    "sg:city":"Evergreen",
    "sg:classifiers":[
        {
            "category":"Home & Garden",
            "subcategory":"Home Furnishings",
            "type":"Retail Goods"
        }
    ],
    "sg:phone":"+1 303 674 9816",
    "sg:postcode":"80439",
    "sg:province":"CO",
    "sg:tags":[
        "stove",
        "wood",
        "burning"
    ],
    "wof:name":"Gorman Sales Co",
    "wof:placetype":"venue"
},
  "geometry": {"coordinates":[-105.305446,39.57355],"type":"Point"}
}