{
  "type": "Feature",
  "properties": {
    "addr:full":"5090 W 6th Ave Denver CO 80204",
    "addr:housenumber":"5090",
    "addr:postcode":"80204",
    "addr:street":"W 6Th Ave",
    "iso:country":"US",
    "sg:address":"5090 W 6th Ave",
    "sg:city":"Denver",
    "sg:classifiers":[
        {
            "category":"Building & Trades",
            "subcategory":"Construction",
            "type":"Services"
        }
    ],
    "sg:phone":"+1 303 935 2025",
    "sg:postcode":"80204",
    "sg:province":"CO",
    "sg:tags":[
        "carpentry",
        "contractor"
    ],
    "wof:name":"A C Artistic Carpentry",
    "wof:placetype":"venue"
},
  "geometry": {"coordinates":[-105.05156100000001,39.725331],"type":"Point"}
}