{
  "type": "Feature",
  "properties": {
    "iso:country":"US",
    "sg:address":"101 W Abriendo Ave",
    "sg:city":"Pueblo",
    "sg:classifiers":[
        {
            "category":"Professional",
            "subcategory":"Computer Services",
            "type":"Services"
        }
    ],
    "sg:phone":"+1 719 542 5678",
    "sg:postcode":"81004",
    "sg:province":"CO",
    "sg:tags":[
        "repair"
    ],
    "wof:name":"A Plus Computer Solutions",
    "wof:placetype":"venue"
},
  "geometry": {"coordinates":[-104.621611,38.260135],"type":"Point"}
}