{
  "type": "Feature",
  "properties": {
    "iso:country":"US",
    "sg:address":"24 N River St",
    "sg:city":"Rico",
    "sg:classifiers":[
        {
            "category":"Professional",
            "type":"Services"
        }
    ],
    "sg:phone":"+1 970 967 1008",
    "sg:postcode":"81332",
    "sg:province":"CO",
    "sg:tags":[
        "establishment"
    ],
    "wof:name":"Clark & Clark",
    "wof:placetype":"venue"
},
  "geometry": {"coordinates":[-108.03225999999999,37.692641],"type":"Point"}
}