{
  "type": "Feature",
  "properties": {
    "iso:country":"US",
    "sg:address":"3915 E Exposition Ave Ste 200",
    "sg:city":"Denver",
    "sg:classifiers":[
        {
            "category":"Personal",
            "subcategory":"Massage",
            "type":"Services"
        },
        {
            "category":"Health Services",
            "subcategory":"Clinic",
            "type":"Services"
        }
    ],
    "sg:phone":"+1 303 333 4634",
    "sg:postcode":"80209",
    "sg:province":"CO",
    "sg:tags":[
        "medical"
    ],
    "sg:website":"www.integrateyourbody.com",
    "wof:name":"Integrative Bodyworks",
    "wof:placetype":"venue"
},
  "geometry": {"coordinates":[-104.941681,39.703823],"type":"Point"}
}