{
  "type": "Feature",
  "properties": {
    "addr:full":"408 Elm Ave Estes Park CO 80517",
    "addr:housenumber":"408",
    "addr:postcode":"80517",
    "addr:street":"Elm Ave",
    "iso:country":"US",
    "sg:address":"408 Elm Ave",
    "sg:city":"Estes Park",
    "sg:classifiers":[
        {
            "category":"Building & Trades",
            "subcategory":"Construction",
            "type":"Services"
        }
    ],
    "sg:phone":"+1 970 586 1179",
    "sg:postcode":"80517",
    "sg:province":"CO",
    "sg:tags":[
        "residential",
        "contractor"
    ],
    "wof:name":"OReilly Construction Inc",
    "wof:placetype":"venue"
},
  "geometry": {"coordinates":[-105.513575,40.371604],"type":"Point"}
}