{
  "type": "Feature",
  "properties": {
    "addr:full":"702 E Bridge St Brighton CO 80601",
    "addr:housenumber":"702",
    "addr:postcode":"80601",
    "addr:street":"E Bridge St",
    "iso:country":"US",
    "sg:address":"702 E Bridge St",
    "sg:city":"Brighton",
    "sg:classifiers":[
        {
            "category":"Restaurant",
            "type":"Food & Drink"
        }
    ],
    "sg:phone":"+1 303 659 6513",
    "sg:postcode":"80601",
    "sg:province":"CO",
    "sg:tags":[
        "chinese"
    ],
    "wof:name":"Sing On Chinese Restaurant",
    "wof:placetype":"venue"
},
  "geometry": {"coordinates":[-104.812579,39.986789],"type":"Point"}
}