{
  "type": "Feature",
  "properties": {
    "iso:country":"US",
    "sg:address":"10426 Co Rd 10",
    "sg:city":"Merino",
    "sg:classifiers":[
        {
            "category":"Farming",
            "subcategory":"Farm",
            "type":"Manufacturing & Wholesale Goods"
        }
    ],
    "sg:phone":"+1 970 522 7044",
    "sg:postcode":"80741",
    "sg:province":"CO",
    "sg:tags":[
        "crop",
        "general"
    ],
    "wof:name":"Ladd Keith & Sons",
    "wof:placetype":"venue"
},
  "geometry": {"coordinates":[-103.380956,40.493313],"type":"Point"}
}