{
  "type": "Feature",
  "properties": {
    "addr:full":"224 S Murray Blvd Colorado Springs CO 80916",
    "addr:housenumber":"224",
    "addr:postcode":"80916",
    "addr:street":"S Murray Blvd",
    "iso:country":"US",
    "sg:address":"224 S Murray Blvd",
    "sg:city":"Colorado Springs",
    "sg:classifiers":[
        {
            "category":"Professional",
            "subcategory":"Computer Services",
            "type":"Services"
        }
    ],
    "sg:phone":"+1 719 573 9580",
    "sg:postcode":"80916",
    "sg:province":"CO",
    "sg:tags":[
        "consultant",
        "designer"
    ],
    "wof:name":"Falsoft Computer Consulting",
    "wof:placetype":"venue"
},
  "geometry": {"coordinates":[-104.748653,38.831214],"type":"Point"}
}