{
  "type": "Feature",
  "properties": {
    "iso:country":"US",
    "sg:address":"1390 13th St",
    "sg:city":"Steamboat Spgs",
    "sg:classifiers":[
        {
            "category":"Retail",
            "subcategory":"Auto Repair",
            "type":"Services"
        }
    ],
    "sg:phone":"+1 970 879 1179",
    "sg:postcode":"80487",
    "sg:province":"CO",
    "sg:tags":[
        "wrecker"
    ],
    "wof:name":"American Towing & Road Svc",
    "wof:placetype":"venue"
},
  "geometry": {"coordinates":[-106.84983800000001,40.491306],"type":"Point"}
}