{
  "type": "Feature",
  "properties": {
    "iso:country":"US",
    "sg:address":"12612 Julian St",
    "sg:city":"Broomfield",
    "sg:classifiers":[
        {
            "category":"Arena",
            "subcategory":"Sports Club",
            "type":"Entertainment"
        }
    ],
    "sg:phone":"+1 303 466 0096",
    "sg:postcode":"80020",
    "sg:province":"CO",
    "sg:tags":[
        "soccer"
    ],
    "wof:name":"Broomfield Blast Soccer Club",
    "wof:placetype":"venue"
},
  "geometry": {"coordinates":[-105.030773,39.926425],"type":"Point"}
}