{
  "type": "Feature",
  "properties": {
    "iso:country":"US",
    "sg:address":"1530 W 13th Ave",
    "sg:city":"Denver",
    "sg:classifiers":[
        {
            "category":"Building & Trades",
            "subcategory":"Construction",
            "type":"Services"
        }
    ],
    "sg:phone":"+1 303 571 5377",
    "sg:postcode":"80204",
    "sg:province":"CO",
    "sg:tags":[
        "contractor"
    ],
    "sg:website":"www.geraldhphipps.com",
    "wof:name":"Gerald H Phipps Inc",
    "wof:placetype":"venue"
},
  "geometry": {"coordinates":[-105.00599699999999,39.737],"type":"Point"}
}