{
  "type": "Feature",
  "properties": {
    "addr:full":"7503 W Rainbow Creek Rd Sedalia CO 80135",
    "addr:housenumber":"7503",
    "addr:postcode":"80135",
    "addr:street":"W Rainbow Creek Rd",
    "iso:country":"US",
    "sg:address":"7503 W Rainbow Creek Rd",
    "sg:city":"Sedalia",
    "sg:classifiers":[
        {
            "category":"Farming",
            "subcategory":"Livestock Farm",
            "type":"Manufacturing & Wholesale Goods"
        }
    ],
    "sg:phone":"+1 303 688 1741",
    "sg:postcode":"80135",
    "sg:province":"CO",
    "sg:tags":[
        "animal",
        "general"
    ],
    "wof:name":"Iron Valley Ranch LLC",
    "wof:placetype":"venue"
},
  "geometry": {"coordinates":[-105.02680599999999,39.419612],"type":"Point"}
}