{
  "type": "Feature",
  "properties": {
    "addr:full":"247 1st Ave Monte Vista CO 81144",
    "addr:housenumber":"247",
    "addr:postcode":"81144",
    "addr:street":"1St Ave",
    "iso:country":"US",
    "sg:address":"247 1st Ave",
    "sg:city":"Monte Vista",
    "sg:classifiers":[
        {
            "category":"Retail",
            "subcategory":"Repair Shop",
            "type":"Services"
        }
    ],
    "sg:phone":"+1 719 852 0554",
    "sg:postcode":"81144",
    "sg:province":"CO",
    "sg:tags":[
        "cleaning"
    ],
    "wof:name":"Cleaning Specialist",
    "wof:placetype":"venue"
},
  "geometry": {"coordinates":[-106.155772,37.580589],"type":"Point"}
}