{
  "type": "Feature",
  "properties": {
    "iso:country":"US",
    "sg:address":"1430 Cinnamon Bear St",
    "sg:city":"Sedalia",
    "sg:classifiers":[
        {
            "category":"Building & Trades",
            "subcategory":"Construction",
            "type":"Services"
        }
    ],
    "sg:phone":"+1 303 660 8688",
    "sg:postcode":"80135",
    "sg:province":"CO",
    "sg:tags":[
        "carpentry",
        "contractor"
    ],
    "wof:name":"Duffys Interior Trim",
    "wof:placetype":"venue"
},
  "geometry": {"coordinates":[-105.12064700000001,39.340636],"type":"Point"}
}