{
  "type": "Feature",
  "properties": {
    "addr:full":"3650 N Perry Park Rd Sedalia CO 80135",
    "addr:housenumber":"3650",
    "addr:postcode":"80135",
    "addr:street":"N Perry Park Rd",
    "iso:country":"US",
    "sg:address":"3650 N Perry Park Rd",
    "sg:city":"Sedalia",
    "sg:classifiers":[
        {
            "category":"Building & Trades",
            "subcategory":"Construction",
            "type":"Services"
        }
    ],
    "sg:phone":"+1 303 688 3740",
    "sg:postcode":"80135",
    "sg:province":"CO",
    "sg:tags":[
        "concrete",
        "contractor"
    ],
    "wof:name":"J & N Concrete Inc",
    "wof:placetype":"venue"
},
  "geometry": {"coordinates":[-104.956622,39.420677],"type":"Point"}
}