{
  "type": "Feature",
  "properties": {
    "addr:full":"12120 W 64th Ave Arvada CO 80004",
    "addr:housenumber":"12120",
    "addr:postcode":"80004",
    "addr:street":"W 64Th Ave",
    "iso:country":"US",
    "sg:address":"12120 W 64th Ave",
    "sg:city":"Arvada",
    "sg:classifiers":[
        {
            "category":"Government",
            "subcategory":"Office",
            "type":"Public Place"
        }
    ],
    "sg:phone":"+1 303 431 9004",
    "sg:postcode":"80004",
    "sg:province":"CO",
    "sg:tags":[
        "village"
    ],
    "wof:name":"North Jeffco Racquetball Ctr",
    "wof:placetype":"venue"
},
  "geometry": {"coordinates":[-105.133152,39.812654],"type":"Point"}
}