{
  "type": "Feature",
  "properties": {
    "addr:full":"5229 Nighthawk Pkwy Brighton CO 80601",
    "addr:housenumber":"5229",
    "addr:postcode":"80601",
    "addr:street":"Nighthawk Pkwy",
    "iso:country":"US",
    "sg:address":"5229 Nighthawk Pkwy",
    "sg:city":"Brighton",
    "sg:classifiers":[
        {
            "category":"Wholesale",
            "subcategory":"Machinery & Supplies",
            "type":"Manufacturing & Wholesale Goods"
        }
    ],
    "sg:phone":"+1 303 655 9993",
    "sg:postcode":"80601",
    "sg:province":"CO",
    "sg:tags":[
        "forestry",
        "equipment"
    ],
    "wof:name":"Tree Machines",
    "wof:placetype":"venue"
},
  "geometry": {"coordinates":[-104.749971,39.981666],"type":"Point"}
}