{
  "type": "Feature",
  "properties": {
    "iso:country":"US",
    "sg:address":"2412 E Bridge St",
    "sg:city":"Brighton",
    "sg:classifiers":[
        {
            "category":"Personal",
            "subcategory":"Beauty Salon",
            "type":"Services"
        }
    ],
    "sg:phone":"+1 303 654 0214",
    "sg:postcode":"80601",
    "sg:province":"CO",
    "wof:name":"V Cuts Unlimited & Supplies",
    "wof:placetype":"venue"
},
  "geometry": {"coordinates":[-104.79236899999999,39.986706],"type":"Point"}
}