{
  "type": "Feature",
  "properties": {
    "addr:full":"2412 E Bridge St Brighton CO 80601",
    "addr:housenumber":"2412",
    "addr:postcode":"80601",
    "addr:street":"E Bridge St",
    "iso:country":"US",
    "sg:address":"2412 E Bridge St",
    "sg:city":"Brighton",
    "sg:classifiers":[
        {
            "category":"Personal",
            "subcategory":"Beauty Salon",
            "type":"Services"
        }
    ],
    "sg:phone":"+1 303 654 0214",
    "sg:postcode":"80601",
    "sg:province":"CO",
    "wof:name":"V Cuts Unlimited & Supplies",
    "wof:placetype":"venue"
},
  "geometry": {"coordinates":[-104.79236899999999,39.986706],"type":"Point"}
}