{
  "type": "Feature",
  "properties": {
    "addr:full":"9676 E Arapahoe Rd Englewood CO 80112",
    "addr:housenumber":"9676",
    "addr:postcode":"80112",
    "addr:street":"E Arapahoe Rd",
    "iso:country":"US",
    "sg:address":"9676 E Arapahoe Rd",
    "sg:city":"Englewood",
    "sg:classifiers":[
        {
            "category":"Food & Beverages",
            "subcategory":"Liquor & Beverages",
            "type":"Retail Goods"
        }
    ],
    "sg:phone":"+1 303 790 7362",
    "sg:postcode":"80112",
    "sg:province":"CO",
    "sg:tags":[
        "alcoholic"
    ],
    "wof:name":"Pride Wine & Liquors",
    "wof:placetype":"venue"
},
  "geometry": {"coordinates":[-104.87791,39.594963],"type":"Point"}
}