{
  "type": "Feature",
  "properties": {
    "addr:full":"13844 Gleneagle Dr Colorado Springs CO 80921",
    "addr:housenumber":"13844",
    "addr:postcode":"80921",
    "addr:street":"Gleneagle Dr",
    "iso:country":"US",
    "sg:address":"13844 Gleneagle Dr",
    "sg:city":"Colorado Springs",
    "sg:classifiers":[
        {
            "category":"Restaurant",
            "type":"Food & Drink"
        }
    ],
    "sg:menulink":"http://www.allmenus.com/co/black-forest-peyton/69507-dominos-pizza/menu/",
    "sg:phone":"+1 719 481 4100",
    "sg:postcode":"80921",
    "sg:province":"CO",
    "sg:tags":[
        "american",
        "wing",
        "pizza"
    ],
    "wof:name":"Domino's Pizza",
    "wof:placetype":"venue"
},
  "geometry": {"coordinates":[-104.82969199999999,39.03249],"type":"Point"}
}