{
  "type": "Feature",
  "properties": {
    "addr:full":"1090 S Havana St Aurora CO 80012",
    "addr:housenumber":"1090",
    "addr:postcode":"80012",
    "addr:street":"S Havana St",
    "iso:country":"US",
    "sg:address":"1090 S Havana St",
    "sg:city":"Aurora",
    "sg:classifiers":[
        {
            "category":"Autos & Motor Vehicles",
            "subcategory":"Fuel & Gas Station",
            "type":"Retail Goods"
        }
    ],
    "sg:phone":"+1 303 364 2004",
    "sg:postcode":"80012",
    "sg:province":"CO",
    "sg:tags":[
        "station",
        "gasoline"
    ],
    "wof:name":"Bradley Sinclair 71",
    "wof:placetype":"venue"
},
  "geometry": {"coordinates":[-104.865888,39.698223],"type":"Point"}
}