{
  "type": "Feature",
  "properties": {
    "iso:country":"US",
    "sg:address":"2124 Wake Forest Ct",
    "sg:city":"Colorado Springs",
    "sg:classifiers":[
        {
            "category":"Real Estate",
            "subcategory":"Real Estate Agent",
            "type":"Services"
        }
    ],
    "sg:phone":"+1 719 260 8465",
    "sg:postcode":"80918",
    "sg:province":"CO",
    "sg:tags":[
        "broker",
        "mortgage",
        "insurance"
    ],
    "wof:name":"Birger & Birger Inc",
    "wof:placetype":"venue"
},
  "geometry": {"coordinates":[-104.783582,38.899313],"type":"Point"}
}