{
  "type": "Feature",
  "properties": {
    "iso:country":"US",
    "sg:address":"129 Adams Street",
    "sg:city":"Denver",
    "sg:classifiers":[
        {
            "category":"Personal",
            "subcategory":"Beauty Salon",
            "type":"Services"
        }
    ],
    "sg:phone":"+1 303 377 2980",
    "sg:postcode":"80206",
    "sg:province":"CO",
    "sg:tags":[
        "hair"
    ],
    "wof:name":"Rembrandt's Salon",
    "wof:placetype":"venue"
},
  "geometry": {"coordinates":[-104.94871000000001,39.718624],"type":"Point"}
}