{
  "type": "Feature",
  "properties": {
    "addr:full":"235 N 1st St Montrose CO 81401",
    "addr:housenumber":"235",
    "addr:postcode":"81401",
    "addr:street":"N 1St St",
    "iso:country":"US",
    "sg:address":"235 N 1st St",
    "sg:city":"Montrose",
    "sg:classifiers":[
        {
            "category":"Autos & Motor Vehicles",
            "subcategory":"Automobile Sales",
            "type":"Retail Goods"
        }
    ],
    "sg:phone":"+1 970 240 9000",
    "sg:postcode":"81401",
    "sg:province":"CO",
    "sg:tags":[
        "body",
        "automotive",
        "rep"
    ],
    "wof:name":"Alpine Offroad & Prfmce LLC",
    "wof:placetype":"venue"
},
  "geometry": {"coordinates":[-107.878962,38.479331],"type":"Point"}
}