{
  "type": "Feature",
  "properties": {
    "iso:country":"US",
    "sg:address":"2739 E Monument St",
    "sg:city":"Colorado Springs",
    "sg:classifiers":[
        {
            "category":"Manufacturing",
            "subcategory":"Signs",
            "type":"Manufacturing & Wholesale Goods"
        }
    ],
    "sg:phone":"+1 719 598 5700",
    "sg:postcode":"80909",
    "sg:province":"CO",
    "wof:name":"Signs By Tomorrow",
    "wof:placetype":"venue"
},
  "geometry": {"coordinates":[-104.776642,38.842165],"type":"Point"}
}