{
  "type": "Feature",
  "properties": {
    "addr:full":"2410 N Dotsero Ave Loveland CO 80538",
    "addr:housenumber":"2410",
    "addr:postcode":"80538",
    "addr:street":"N Dotsero Ave",
    "iso:country":"US",
    "sg:address":"2410 N Dotsero Ave",
    "sg:city":"Loveland",
    "sg:classifiers":[
        {
            "category":"Building & Trades",
            "subcategory":"Construction",
            "type":"Services"
        }
    ],
    "sg:phone":"+1 970 663 7676",
    "sg:postcode":"80538",
    "sg:province":"CO",
    "sg:tags":[
        "floor",
        "laying",
        "contractor"
    ],
    "wof:name":"Joseph Hoover Installation",
    "wof:placetype":"venue"
},
  "geometry": {"coordinates":[-105.105605,40.416419],"type":"Point"}
}