{
  "type": "Feature",
  "properties": {
    "iso:country":"US",
    "sg:address":"2500 Pine Grove Rd",
    "sg:city":"Steamboat Spgs",
    "sg:classifiers":[
        {
            "category":"Recreation",
            "type":"Entertainment"
        }
    ],
    "sg:phone":"+1 970 879 8400",
    "sg:postcode":"80487",
    "sg:province":"CO",
    "sg:tags":[
        "tennis",
        "court"
    ],
    "wof:name":"Tennis Center At Steamboat",
    "wof:placetype":"venue"
},
  "geometry": {"coordinates":[-106.815665,40.455466],"type":"Point"}
}