{
  "type": "Feature",
  "properties": {
    "addr:full":"10770 Willow Reed Ct Parker CO 80134",
    "addr:housenumber":"10770",
    "addr:postcode":"80134",
    "addr:street":"Willow Reed Ct",
    "iso:country":"US",
    "sg:address":"10770 Willow Reed Ct",
    "sg:city":"Parker",
    "sg:classifiers":[
        {
            "category":"Shopping",
            "subcategory":"Crafts & Fabrics",
            "type":"Retail Goods"
        }
    ],
    "sg:phone":"+1 303 805 9524",
    "sg:postcode":"80134",
    "sg:province":"CO",
    "sg:tags":[
        "sewing"
    ],
    "wof:name":"Billies Stitching Post",
    "wof:placetype":"venue"
},
  "geometry": {"coordinates":[-104.794185,39.520963],"type":"Point"}
}