{
  "type": "Feature",
  "properties": {
    "iso:country":"US",
    "sg:address":"172 N Industrial Way",
    "sg:city":"Pueblo West",
    "sg:classifiers":[
        {
            "category":"Retail",
            "subcategory":"Repair Shop",
            "type":"Services"
        }
    ],
    "sg:phone":"+1 719 647 9445",
    "sg:postcode":"81007",
    "sg:province":"CO",
    "sg:tags":[
        "plumbing",
        "drain",
        "cleaning",
        "sewer"
    ],
    "wof:name":"AAA Jetting & Excavation",
    "wof:placetype":"venue"
},
  "geometry": {"coordinates":[-104.688079,38.32547],"type":"Point"}
}