{
  "type": "Feature",
  "properties": {
    "iso:country":"US",
    "sg:address":"3062 Shady Ln",
    "sg:city":"Littleton",
    "sg:classifiers":[
        {
            "category":"Shopping",
            "subcategory":"Hobbies, Toys, & Games",
            "type":"Retail Goods"
        }
    ],
    "sg:phone":"+1 303 791 1753",
    "sg:postcode":"80126",
    "sg:province":"CO",
    "wof:name":"Digital Beach",
    "wof:placetype":"venue"
},
  "geometry": {"coordinates":[-104.952713,39.565692],"type":"Point"}
}