{
  "type": "Feature",
  "properties": {
    "addr:full":"725 Eldorado Blvd Broomfield CO 80021",
    "addr:housenumber":"725",
    "addr:postcode":"80021",
    "addr:street":"Eldorado Blvd",
    "iso:country":"US",
    "sg:address":"725 Eldorado Blvd",
    "sg:city":"Broomfield",
    "sg:classifiers":[
        {
            "category":"Real Estate",
            "subcategory":"Real Estate Operator",
            "type":"Services"
        }
    ],
    "sg:phone":"+1 303 438 1114",
    "sg:postcode":"80021",
    "sg:province":"CO",
    "sg:tags":[
        "building",
        "apartment"
    ],
    "wof:name":"Marriott",
    "wof:placetype":"venue"
},
  "geometry": {"coordinates":[-105.13238800000001,39.9235],"type":"Point"}
}