{
  "type": "Feature",
  "properties": {
    "iso:country":"US",
    "sg:address":"795 Main St",
    "sg:city":"Minturn",
    "sg:classifiers":[
        {
            "category":"Building & Trades",
            "subcategory":"Construction",
            "type":"Services"
        }
    ],
    "sg:phone":"+1 970 476 1426",
    "sg:postcode":"81645",
    "sg:province":"CO",
    "sg:tags":[
        "general",
        "contractor"
    ],
    "wof:name":"S H Cole Construction Co",
    "wof:placetype":"venue"
},
  "geometry": {"coordinates":[-106.424632,39.582137],"type":"Point"}
}