{
  "type": "Feature",
  "properties": {
    "iso:country":"US",
    "sg:address":"1119 Ridglea Way",
    "sg:city":"Boulder",
    "sg:classifiers":[
        {
            "category":"Manufacturing",
            "subcategory":"Printing",
            "type":"Manufacturing & Wholesale Goods"
        }
    ],
    "sg:phone":"+1 303 499 0943",
    "sg:postcode":"80303",
    "sg:province":"CO",
    "sg:tags":[
        "periodical"
    ],
    "wof:name":"Cmdc Systems Inc",
    "wof:placetype":"venue"
},
  "geometry": {"coordinates":[-105.199943,40.008908],"type":"Point"}
}