{
  "type": "Feature",
  "properties": {
    "iso:country":"US",
    "sg:address":"1463 13th St",
    "sg:city":"Steamboat Spgs",
    "sg:classifiers":[
        {
            "category":"Government",
            "subcategory":"Office",
            "type":"Public Place"
        }
    ],
    "sg:phone":"+1 970 879 5585",
    "sg:postcode":"80487",
    "sg:province":"CO",
    "sg:tags":[
        "city",
        "program"
    ],
    "wof:name":"Steamboat Springs Transit",
    "wof:placetype":"venue"
},
  "geometry": {"coordinates":[-106.849546,40.490997],"type":"Point"}
}