{
  "type": "Feature",
  "properties": {
    "iso:country":"US",
    "sg:address":"1405 E Evans Avenue",
    "sg:city":"Denver",
    "sg:classifiers":[
        {
            "category":"Personal",
            "subcategory":"Beauty Salon",
            "type":"Services"
        },
        {
            "category":"Personal",
            "subcategory":"Day Spa",
            "type":"Services"
        }
    ],
    "sg:phone":"+1 303 722 6000",
    "sg:postcode":"80210",
    "sg:province":"CO",
    "sg:tags":[
        "hair"
    ],
    "sg:website":"www.ouisalonspa.com",
    "wof:name":"Oui Salon & Spa",
    "wof:placetype":"venue"
},
  "geometry": {"coordinates":[-104.970685,39.678615],"type":"Point"}
}