{
  "type": "Feature",
  "properties": {
    "iso:country":"US",
    "sg:address":"1640 E Pitkin St",
    "sg:city":"Fort Collins",
    "sg:classifiers":[
        {
            "category":"Building & Trades",
            "subcategory":"Construction",
            "type":"Services"
        }
    ],
    "sg:phone":"+1 970 407 0232",
    "sg:postcode":"80524",
    "sg:province":"CO",
    "sg:tags":[
        "carpentry",
        "contractor"
    ],
    "wof:name":"Adam Watts Carpentry",
    "wof:placetype":"venue"
},
  "geometry": {"coordinates":[-105.048648,40.571104],"type":"Point"}
}