{
  "type": "Feature",
  "properties": {
    "addr:full":"965 S Kipling St Denver CO 80226",
    "addr:housenumber":"965",
    "addr:postcode":"80226",
    "addr:street":"S Kipling St",
    "iso:country":"US",
    "sg:address":"965 S Kipling St",
    "sg:city":"Denver",
    "sg:classifiers":[
        {
            "category":"Restaurant",
            "type":"Food & Drink"
        }
    ],
    "sg:phone":"+1 303 985 8154",
    "sg:postcode":"80226",
    "sg:province":"CO",
    "sg:tags":[
        "eating",
        "caterer"
    ],
    "wof:name":"Bella Cena Catering Inc",
    "wof:placetype":"venue"
},
  "geometry": {"coordinates":[-105.111396,39.697771],"type":"Point"}
}