{
  "type": "Feature",
  "properties": {
    "iso:country":"US",
    "sg:address":"3030 S Tejon St",
    "sg:city":"Englewood",
    "sg:classifiers":[
        {
            "category":"Professional",
            "subcategory":"Computer Services",
            "type":"Services"
        }
    ],
    "sg:phone":"+1 303 789 5400",
    "sg:postcode":"80110",
    "sg:province":"CO",
    "sg:tags":[
        "wiring"
    ],
    "sg:website":"www.sequelcom.net",
    "wof:name":"Sequel Communications LLC",
    "wof:placetype":"venue"
},
  "geometry": {"coordinates":[-105.011005,39.661055],"type":"Point"}
}