{
  "type": "Feature",
  "properties": {
    "iso:country":"US",
    "sg:address":"222 F St",
    "sg:city":"Salida",
    "sg:classifiers":[
        {
            "category":"Shopping",
            "type":"Retail Goods"
        }
    ],
    "sg:phone":"+1 719 539 6171",
    "sg:postcode":"81201",
    "sg:province":"CO",
    "sg:tags":[
        "picture",
        "frame"
    ],
    "wof:name":"Willow Tree Frame Shop & Gllry",
    "wof:placetype":"venue"
},
  "geometry": {"coordinates":[-105.992823,38.535297],"type":"Point"}
}