{
  "type": "Feature",
  "properties": {
    "addr:full":"651 E 1st St Akron CO 80720",
    "addr:housenumber":"651",
    "addr:postcode":"80720",
    "addr:street":"E 1St St",
    "iso:country":"US",
    "sg:address":"651 E 1st St",
    "sg:city":"Akron",
    "sg:classifiers":[
        {
            "category":"Shopping",
            "subcategory":"Clothing, Apparel, & Fashions",
            "type":"Retail Goods"
        }
    ],
    "sg:phone":"+1 970 345 2305",
    "sg:postcode":"80720",
    "sg:province":"CO",
    "wof:name":"Bright Arrow Trading Post",
    "wof:placetype":"venue"
},
  "geometry": {"coordinates":[-103.205342,40.159272],"type":"Point"}
}