{
  "type": "Feature",
  "properties": {
    "iso:country":"US",
    "sg:address":"618 Moss Way",
    "sg:city":"Palisade",
    "sg:classifiers":[
        {
            "category":"Professional",
            "type":"Services"
        }
    ],
    "sg:phone":"+1 970 464 0222",
    "sg:postcode":"81526",
    "sg:province":"CO",
    "sg:tags":[
        "establishment"
    ],
    "wof:name":"Liddicoat & Liddicoat",
    "wof:placetype":"venue"
},
  "geometry": {"coordinates":[-108.363209,39.11106],"type":"Point"}
}