{
  "type": "Feature",
  "properties": {
    "iso:country":"US",
    "sg:address":"6915 Palmer Park Blvd",
    "sg:city":"Colorado Springs",
    "sg:classifiers":[
        {
            "category":"Organizations",
            "subcategory":"Religious Organization",
            "type":"Services"
        }
    ],
    "sg:phone":"+1 719 597 1880",
    "sg:postcode":"80915",
    "sg:province":"CO",
    "wof:name":"Hilltop Baptist Church",
    "wof:placetype":"venue"
},
  "geometry": {"coordinates":[-104.698155,38.85859],"type":"Point"}
}