{
  "type": "Feature",
  "properties": {
    "iso:country":"US",
    "sg:address":"390 Interlocken Cres",
    "sg:city":"Broomfield",
    "sg:classifiers":[
        {
            "category":"Shopping",
            "subcategory":"Computers & Home Electronics",
            "type":"Retail Goods"
        }
    ],
    "sg:phone":"+1 303 872 3500",
    "sg:postcode":"80021",
    "sg:province":"CO",
    "sg:tags":[
        "software"
    ],
    "wof:name":"Synopsys",
    "wof:placetype":"venue"
},
  "geometry": {"coordinates":[-105.115869,39.92425],"type":"Point"}
}