{
  "type": "Feature",
  "properties": {
    "iso:country":"US",
    "sg:address":"323 3rd Ave",
    "sg:city":"Longmont",
    "sg:classifiers":[
        {
            "category":"Professional",
            "type":"Services"
        }
    ],
    "sg:phone":"+1 303 684 8535",
    "sg:postcode":"80501",
    "sg:province":"CO",
    "wof:name":"Connections of Spirit",
    "wof:placetype":"venue"
},
  "geometry": {"coordinates":[-105.099554,40.163861],"type":"Point"}
}