{
  "type": "Feature",
  "properties": {
    "iso:country":"US",
    "sg:address":"3080 S Zuni St",
    "sg:city":"Englewood",
    "sg:classifiers":[
        {
            "category":"Professional",
            "type":"Services"
        }
    ],
    "sg:phone":"+1 303 984 2814",
    "sg:postcode":"80110",
    "sg:province":"CO",
    "sg:tags":[
        "establishment"
    ],
    "wof:name":"Vacation Connections",
    "wof:placetype":"venue"
},
  "geometry": {"coordinates":[-105.01572400000001,39.661522],"type":"Point"}
}