{
  "type": "Feature",
  "properties": {
    "iso:country":"US",
    "sg:address":"6657 W Ottawa Ave",
    "sg:city":"Littleton",
    "sg:classifiers":[
        {
            "category":"Freight",
            "type":"Transportation"
        },
        {
            "category":"Shopping",
            "subcategory":"Bicycles & Sporting Goods",
            "type":"Retail Goods"
        }
    ],
    "sg:phone":"+1 303 904 3340",
    "sg:postcode":"80128",
    "sg:province":"CO",
    "sg:tags":[
        "equipment",
        "general",
        "skateboard",
        "warehousing"
    ],
    "wof:name":"Surf Associates Inc",
    "wof:placetype":"venue"
},
  "geometry": {"coordinates":[-105.069642,39.591377],"type":"Point"}
}