{
  "type": "Feature",
  "properties": {
    "iso:country":"US",
    "sg:address":"2940 E Colfax Ave",
    "sg:city":"Denver",
    "sg:classifiers":[
        {
            "category":"Manufacturing",
            "subcategory":"Printing",
            "type":"Manufacturing & Wholesale Goods"
        }
    ],
    "sg:phone":"+1 303 830 1691",
    "sg:postcode":"80206",
    "sg:province":"CO",
    "sg:tags":[
        "book"
    ],
    "wof:name":"Western Images Publications",
    "wof:placetype":"venue"
},
  "geometry": {"coordinates":[-104.95288499999999,39.740098],"type":"Point"}
}