{
  "type": "Feature",
  "properties": {
    "addr:full":"2056 Calhoun Ct Loveland CO 80537",
    "addr:housenumber":"2056",
    "addr:postcode":"80537",
    "addr:street":"Calhoun Ct",
    "iso:country":"US",
    "sg:address":"2056 Calhoun Ct",
    "sg:city":"Loveland",
    "sg:classifiers":[
        {
            "category":"Restaurant",
            "type":"Food & Drink"
        }
    ],
    "sg:phone":"+1 970 667 3588",
    "sg:postcode":"80537",
    "sg:province":"CO",
    "sg:tags":[
        "eating"
    ],
    "wof:name":"Free To Believe",
    "wof:placetype":"venue"
},
  "geometry": {"coordinates":[-105.105805,40.392855],"type":"Point"}
}