{
  "type": "Feature",
  "properties": {
    "addr:full":"260 S Raritan St Denver CO 80223",
    "addr:housenumber":"260",
    "addr:postcode":"80223",
    "addr:street":"S Raritan St",
    "iso:country":"US",
    "sg:address":"260 S Raritan St",
    "sg:city":"Denver",
    "sg:classifiers":[
        {
            "category":"Building & Trades",
            "subcategory":"Electrical",
            "type":"Services"
        }
    ],
    "sg:phone":"+1 303 778 8787",
    "sg:postcode":"80223",
    "sg:province":"CO",
    "sg:tags":[
        "electric",
        "contractor"
    ],
    "sg:website":"www.mcbridelighting.com",
    "wof:name":"Mc Bride Lighting",
    "wof:placetype":"venue"
},
  "geometry": {"coordinates":[-105.008579,39.711398],"type":"Point"}
}