{
  "type": "Feature",
  "properties": {
    "iso:country":"US",
    "sg:address":"5470 S Greenwood St",
    "sg:city":"Littleton",
    "sg:classifiers":[
        {
            "category":"Real Estate",
            "subcategory":"Real Estate Operator",
            "type":"Services"
        }
    ],
    "sg:phone":"+1 303 794 1859",
    "sg:postcode":"80120",
    "sg:province":"CO",
    "sg:tags":[
        "property",
        "lessor",
        "oil"
    ],
    "wof:name":"A J Hunt Petroleum",
    "wof:placetype":"venue"
},
  "geometry": {"coordinates":[-105.000952,39.616918],"type":"Point"}
}