{
  "type": "Feature",
  "properties": {
    "iso:country":"US",
    "sg:address":"1617 E 22nd Ave",
    "sg:city":"Denver",
    "sg:classifiers":[
        {
            "category":"Building & Trades",
            "subcategory":"Construction",
            "type":"Services"
        }
    ],
    "sg:phone":"+1 303 430 1599",
    "sg:postcode":"80205",
    "sg:province":"CO",
    "sg:tags":[
        "masonry",
        "contractor"
    ],
    "wof:name":"Eskestrand Masonry",
    "wof:placetype":"venue"
},
  "geometry": {"coordinates":[-104.967333,39.749536],"type":"Point"}
}