{
  "type": "Feature",
  "properties": {
    "addr:full":"1675 S Fairfax St Denver CO 80222",
    "addr:housenumber":"1675",
    "addr:postcode":"80222",
    "addr:street":"S Fairfax St",
    "iso:country":"US",
    "sg:address":"1675 S Fairfax St",
    "sg:city":"Denver",
    "sg:classifiers":[
        {
            "category":"Organizations",
            "subcategory":"Professional Association",
            "type":"Services"
        }
    ],
    "sg:phone":"+1 303 756 2718",
    "sg:postcode":"80222",
    "sg:province":"CO",
    "wof:name":"Aurora Adams Medical Society",
    "wof:placetype":"venue"
},
  "geometry": {"coordinates":[-104.92846900000001,39.687065],"type":"Point"}
}