{
  "type": "Feature",
  "properties": {
    "addr:full":"956 W Cherry St Louisville CO 80027",
    "addr:housenumber":"956",
    "addr:postcode":"80027",
    "addr:street":"W Cherry St",
    "iso:country":"US",
    "sg:address":"956 W Cherry St",
    "sg:city":"Louisville",
    "sg:classifiers":[
        {
            "category":"Restaurant",
            "type":"Food & Drink"
        }
    ],
    "sg:phone":"+1 303 665 0300",
    "sg:postcode":"80027",
    "sg:province":"CO",
    "sg:tags":[
        "eating"
    ],
    "wof:name":"Domino's Pizza",
    "wof:placetype":"venue"
},
  "geometry": {"coordinates":[-105.148717,39.96507],"type":"Point"}
}