{
  "type": "Feature",
  "properties": {
    "iso:country":"US",
    "sg:address":"1127 Eagle Dr",
    "sg:city":"Loveland",
    "sg:classifiers":[
        {
            "category":"Personal",
            "subcategory":"Beauty Salon",
            "type":"Services"
        }
    ],
    "sg:phone":"+1 970 635 3035",
    "sg:postcode":"80537",
    "sg:province":"CO",
    "wof:name":"Cost Cutters Family Hair Care",
    "wof:placetype":"venue"
},
  "geometry": {"coordinates":[-105.098011,40.379384],"type":"Point"}
}