{
  "type": "Feature",
  "properties": {
    "addr:full":"5131 Crown Blvd Denver CO 80239",
    "addr:housenumber":"5131",
    "addr:postcode":"80239",
    "addr:street":"Crown Blvd",
    "iso:country":"US",
    "sg:address":"5131 Crown Blvd",
    "sg:city":"Denver",
    "sg:classifiers":[
        {
            "category":"Professional",
            "type":"Services"
        }
    ],
    "sg:phone":"+1 303 373 1762",
    "sg:postcode":"80239",
    "sg:province":"CO",
    "wof:name":"Miguel Ceballos",
    "wof:placetype":"venue"
},
  "geometry": {"coordinates":[-104.825774,39.790216],"type":"Point"}
}