{
  "type": "Feature",
  "properties": {
    "iso:country":"US",
    "sg:address":"1667 S Clay St",
    "sg:city":"Denver",
    "sg:classifiers":[
        {
            "category":"Building & Trades",
            "subcategory":"Construction",
            "type":"Services"
        }
    ],
    "sg:phone":"+1 303 934 8841",
    "sg:postcode":"80219",
    "sg:province":"CO",
    "sg:tags":[
        "house"
    ],
    "wof:name":"Antonson Remodeling",
    "wof:placetype":"venue"
},
  "geometry": {"coordinates":[-105.020449,39.687555],"type":"Point"}
}