{
  "type": "Feature",
  "properties": {
    "iso:country":"US",
    "sg:address":"10325 Kettering Ln",
    "sg:city":"Parker",
    "sg:classifiers":[
        {
            "category":"Banks & Credit Unions",
            "subcategory":"Financial Services",
            "type":"Services"
        }
    ],
    "sg:phone":"+1 303 840 4946",
    "sg:postcode":"80134",
    "sg:province":"CO",
    "sg:tags":[
        "investor"
    ],
    "wof:name":"Mtm Investments LLC",
    "wof:placetype":"venue"
},
  "geometry": {"coordinates":[-104.80106600000001,39.528984],"type":"Point"}
}