{
  "type": "Feature",
  "properties": {
    "addr:full":"4950 Dahlia St Denver CO 80216",
    "addr:housenumber":"4950",
    "addr:postcode":"80216",
    "addr:street":"Dahlia St",
    "iso:country":"US",
    "sg:address":"4950 Dahlia St",
    "sg:city":"Denver",
    "sg:classifiers":[
        {
            "category":"Freight",
            "type":"Transportation"
        }
    ],
    "sg:phone":"+1 303 373 1332",
    "sg:postcode":"80216",
    "sg:province":"CO",
    "sg:tags":[
        "mover"
    ],
    "wof:name":"North American Van Lines",
    "wof:placetype":"venue"
},
  "geometry": {"coordinates":[-104.931544,39.784305],"type":"Point"}
}