{
  "type": "Feature",
  "properties": {
    "addr:full":"230 W 1st St Haxtun CO 80731",
    "addr:housenumber":"230",
    "addr:postcode":"80731",
    "addr:street":"W 1St St",
    "iso:country":"US",
    "sg:address":"230 W 1st St",
    "sg:city":"Haxtun",
    "sg:classifiers":[
        {
            "category":"Food & Beverages",
            "subcategory":"Liquor & Beverages",
            "type":"Retail Goods"
        }
    ],
    "sg:phone":"+1 970 774 7114",
    "sg:postcode":"80731",
    "sg:province":"CO",
    "sg:tags":[
        "alcoholic"
    ],
    "wof:name":"Haxtun Liquor",
    "wof:placetype":"venue"
},
  "geometry": {"coordinates":[-102.632744,40.637902],"type":"Point"}
}