{
  "type": "Feature",
  "properties": {
    "iso:country":"US",
    "sg:address":"100 E Drake Rd",
    "sg:city":"Fort Collins",
    "sg:classifiers":[
        {
            "category":"Banks & Credit Unions",
            "subcategory":"Bank",
            "type":"Services"
        }
    ],
    "sg:phone":"+1 970 493 1234",
    "sg:postcode":"80525",
    "sg:province":"CO",
    "sg:tags":[
        "national"
    ],
    "wof:name":"Keybank National Association",
    "wof:placetype":"venue"
},
  "geometry": {"coordinates":[-105.075276,40.552566],"type":"Point"}
}