{
  "type": "Feature",
  "properties": {
    "addr:full":"737 McGraw Cir Fort Collins CO 80526",
    "addr:housenumber":"737",
    "addr:postcode":"80526",
    "addr:street":"Mcgraw Cir",
    "iso:country":"US",
    "sg:address":"737 McGraw Cir",
    "sg:city":"Fort Collins",
    "sg:classifiers":[
        {
            "category":"Freight",
            "type":"Transportation"
        }
    ],
    "sg:phone":"+1 970 282 0030",
    "sg:postcode":"80526",
    "sg:province":"CO",
    "sg:tags":[
        "arrangement"
    ],
    "wof:name":"Mark Seader",
    "wof:placetype":"venue"
},
  "geometry": {"coordinates":[-105.08782100000001,40.521359],"type":"Point"}
}