{
  "type": "Feature",
  "properties": {
    "iso:country":"US",
    "sg:address":"205 Laurel Ct",
    "sg:city":"Windsor",
    "sg:classifiers":[
        {
            "category":"Professional",
            "type":"Services"
        }
    ],
    "sg:phone":"+1 970 686 7772",
    "sg:postcode":"80550",
    "sg:province":"CO",
    "wof:name":"Atmosphere Sound & Light",
    "wof:placetype":"venue"
},
  "geometry": {"coordinates":[-104.90006,40.470634],"type":"Point"}
}