{
  "type": "Feature",
  "properties": {
    "addr:full":"703 Holly Dr Sterling CO 80751",
    "addr:housenumber":"703",
    "addr:postcode":"80751",
    "addr:street":"Holly Dr",
    "iso:country":"US",
    "sg:address":"703 Holly Dr",
    "sg:city":"Sterling",
    "sg:classifiers":[
        {
            "category":"Health Services",
            "subcategory":"Nursing And Care Facility",
            "type":"Services"
        }
    ],
    "sg:phone":"+1 970 526 2825",
    "sg:postcode":"80751",
    "sg:province":"CO",
    "sg:tags":[
        "skilled"
    ],
    "sg:website":"www.rosettahomes.com",
    "wof:name":"Rosetta Assisted Living",
    "wof:placetype":"venue"
},
  "geometry": {"coordinates":[-103.22138699999999,40.611124],"type":"Point"}
}