{
  "type": "Feature",
  "properties": {
    "iso:country":"US",
    "sg:address":"1665 33rd St",
    "sg:city":"Boulder",
    "sg:classifiers":[
        {
            "category":"Home & Garden",
            "subcategory":"Garden Supply",
            "type":"Retail Goods"
        }
    ],
    "sg:phone":"+1 303 449 9551",
    "sg:postcode":"80301",
    "sg:province":"CO",
    "sg:tags":[
        "nurseryman"
    ],
    "wof:name":"Fruehauf's",
    "wof:placetype":"venue"
},
  "geometry": {"coordinates":[-105.250191,40.015221],"type":"Point"}
}