{
  "type": "Feature",
  "properties": {
    "iso:country":"US",
    "sg:address":"3820 S Sherman St",
    "sg:city":"Englewood",
    "sg:classifiers":[
        {
            "category":"Manufacturing",
            "subcategory":"Signs",
            "type":"Manufacturing & Wholesale Goods"
        }
    ],
    "sg:phone":"+1 303 762 0987",
    "sg:postcode":"80113",
    "sg:province":"CO",
    "wof:name":"P Crago Pottery",
    "wof:placetype":"venue"
},
  "geometry": {"coordinates":[-104.985266,39.646189],"type":"Point"}
}