{
  "type": "Feature",
  "properties": {
    "addr:full":"208 N Dolores Rd Cortez CO 81321",
    "addr:housenumber":"208",
    "addr:postcode":"81321",
    "addr:street":"N Dolores Rd",
    "iso:country":"US",
    "sg:address":"208 N Dolores Rd",
    "sg:city":"Cortez",
    "sg:classifiers":[
        {
            "category":"Organizations",
            "subcategory":"Religious Organization",
            "type":"Services"
        }
    ],
    "sg:phone":"+1 970 565 9346",
    "sg:postcode":"81321",
    "sg:province":"CO",
    "sg:tags":[
        "church"
    ],
    "wof:name":"Trinity Lutheran Church",
    "wof:placetype":"venue"
},
  "geometry": {"coordinates":[-108.554475,37.349673],"type":"Point"}
}