{
  "type": "Feature",
  "properties": {
    "iso:country":"US",
    "sg:address":"59759 Hwy 90",
    "sg:city":"Montrose",
    "sg:classifiers":[
        {
            "category":"Farming",
            "subcategory":"Livestock Farm",
            "type":"Manufacturing & Wholesale Goods"
        }
    ],
    "sg:phone":"+1 970 249 3146",
    "sg:postcode":"81401",
    "sg:province":"CO",
    "sg:tags":[
        "beef",
        "feedlot",
        "cattle"
    ],
    "wof:name":"Jim Longwell",
    "wof:placetype":"venue"
},
  "geometry": {"coordinates":[-107.951697,38.43737],"type":"Point"}
}