{
  "type": "Feature",
  "properties": {
    "iso:country":"US",
    "sg:address":"8753 Yates Dr",
    "sg:city":"Westminster",
    "sg:classifiers":[
        {
            "category":"Insurance",
            "subcategory":"Insurance Agent",
            "type":"Services"
        }
    ],
    "sg:phone":"+1 303 301 2655",
    "sg:postcode":"80031",
    "sg:province":"CO",
    "sg:tags":[
        "broker"
    ],
    "wof:name":"Chatham Insurance Corporation",
    "wof:placetype":"venue"
},
  "geometry": {"coordinates":[-105.05070000000001,39.856456],"type":"Point"}
}