{
  "type": "Feature",
  "properties": {
    "addr:full":"1545 W Tufts Ave Englewood CO 80110",
    "addr:housenumber":"1545",
    "addr:postcode":"80110",
    "addr:street":"W Tufts Ave",
    "iso:country":"US",
    "sg:address":"1545 W Tufts Ave",
    "sg:city":"Englewood",
    "sg:classifiers":[
        {
            "category":"Wholesale",
            "subcategory":"Books, Periodicals, & Newspapers",
            "type":"Manufacturing & Wholesale Goods"
        }
    ],
    "sg:phone":"+1 303 783 2255",
    "sg:postcode":"80110",
    "sg:province":"CO",
    "sg:tags":[
        "dealer"
    ],
    "sg:website":"www.bennettandcurran.com",
    "wof:name":"Bennett & Curran",
    "wof:placetype":"venue"
},
  "geometry": {"coordinates":[-105.005371,39.633273],"type":"Point"}
}