{
  "type": "Feature",
  "properties": {
    "addr:full":"7381 W Alameda Avenue Lakewood CO 80226",
    "addr:housenumber":"7381",
    "addr:postcode":"80226",
    "addr:street":"W Alameda Avenue",
    "iso:country":"US",
    "sg:address":"7381 W Alameda Avenue",
    "sg:city":"Lakewood",
    "sg:classifiers":[
        {
            "category":"Restaurant",
            "type":"Food & Drink"
        }
    ],
    "sg:phone":"+1 303 232 7682",
    "sg:postcode":"80226",
    "sg:province":"CO",
    "wof:name":"Village Inn Restaurant",
    "wof:placetype":"venue"
},
  "geometry": {"coordinates":[-105.079233,39.710911],"type":"Point"}
}