{
  "type": "Feature",
  "properties": {
    "iso:country":"US",
    "sg:address":"630 Atchison Way",
    "sg:city":"Castle Rock",
    "sg:classifiers":[
        {
            "category":"Autos & Motor Vehicles",
            "subcategory":"Automobile Sales",
            "type":"Retail Goods"
        }
    ],
    "sg:phone":"+1 303 660 6055",
    "sg:postcode":"80109",
    "sg:province":"CO",
    "sg:tags":[
        "car",
        "dealer"
    ],
    "wof:name":"Capital Motors",
    "wof:placetype":"venue"
},
  "geometry": {"coordinates":[-104.870913,39.377339],"type":"Point"}
}