{
  "type": "Feature",
  "properties": {
    "addr:full":"280 Columbine St Denver CO 80206",
    "addr:housenumber":"280",
    "addr:postcode":"80206",
    "addr:street":"Columbine St",
    "iso:country":"US",
    "sg:address":"280 Columbine St",
    "sg:city":"Denver",
    "sg:classifiers":[
        {
            "category":"Communications",
            "subcategory":"Film & Video Production",
            "type":"Services"
        }
    ],
    "sg:phone":"+1 303 534 4021",
    "sg:postcode":"80206",
    "sg:province":"CO",
    "sg:tags":[
        "animated"
    ],
    "sg:website":"www.american3d.com",
    "wof:name":"American Animation Co",
    "wof:placetype":"venue"
},
  "geometry": {"coordinates":[-104.956982,39.719689],"type":"Point"}
}