{
  "type": "Feature",
  "properties": {
    "iso:country":"US",
    "sg:address":"8080 S Broadway",
    "sg:city":"Littleton",
    "sg:classifiers":[
        {
            "category":"Autos & Motor Vehicles",
            "subcategory":"Fuel & Gas Station",
            "type":"Retail Goods"
        }
    ],
    "sg:phone":"+1 303 794 2103",
    "sg:postcode":"80122",
    "sg:province":"CO",
    "sg:tags":[
        "oil"
    ],
    "sg:website":"www.bp.com",
    "wof:name":"Bp Oil",
    "wof:placetype":"venue"
},
  "geometry": {"coordinates":[-104.98845300000001,39.568565],"type":"Point"}
}