{
  "type": "Feature",
  "properties": {
    "iso:country":"US",
    "sg:address":"155 S Madison St",
    "sg:city":"Denver",
    "sg:classifiers":[
        {
            "category":"Professional",
            "subcategory":"Business Services",
            "type":"Services"
        }
    ],
    "sg:phone":"+1 303 329 3435",
    "sg:postcode":"80209",
    "sg:province":"CO",
    "sg:tags":[
        "arbitration"
    ],
    "sg:website":"www.centerforsolutions.com",
    "wof:name":"Center For Solutions Inc",
    "wof:placetype":"venue"
},
  "geometry": {"coordinates":[-104.946258,39.711625],"type":"Point"}
}