{
  "type": "Feature",
  "properties": {
    "iso:country":"US",
    "sg:address":"538 Cactus St",
    "sg:city":"Pueblo",
    "sg:classifiers":[
        {
            "category":"Building & Trades",
            "subcategory":"Construction",
            "type":"Services"
        }
    ],
    "sg:phone":"+1 719 561 8634",
    "sg:postcode":"81005",
    "sg:province":"CO",
    "sg:tags":[
        "painter"
    ],
    "wof:name":"Johns Professional Painting",
    "wof:placetype":"venue"
},
  "geometry": {"coordinates":[-104.66797800000001,38.25528],"type":"Point"}
}