{
  "type": "Feature",
  "properties": {
    "iso:country":"US",
    "sg:address":"3614 Bruce Randolph Ave",
    "sg:city":"Denver",
    "sg:classifiers":[
        {
            "category":"Professional",
            "subcategory":"Art Services",
            "type":"Services"
        },
        {
            "category":"Communications",
            "type":"Services"
        },
        {
            "category":"Professional",
            "subcategory":"Computer Services",
            "type":"Services"
        }
    ],
    "sg:phone":"+1 303 888 0727",
    "sg:postcode":"80205",
    "sg:province":"CO",
    "sg:tags":[
        "repair",
        "graphic",
        "design",
        "web"
    ],
    "sg:website":"www.tek-ease.com",
    "wof:name":"Tek Ease",
    "wof:placetype":"venue"
},
  "geometry": {"coordinates":[-104.944545,39.764164],"type":"Point"}
}