{
  "type": "Feature",
  "properties": {
    "addr:full":"6529 Co Rd 44 Fort Collins CO 80524",
    "addr:housenumber":"6529;44",
    "addr:postcode":"80524",
    "addr:street":"Co Rd",
    "iso:country":"US",
    "sg:address":"6529 Co Rd 44",
    "sg:city":"Fort Collins",
    "sg:classifiers":[
        {
            "category":"Farming",
            "subcategory":"Farm",
            "type":"Manufacturing & Wholesale Goods"
        }
    ],
    "sg:phone":"+1 970 221 2203",
    "sg:postcode":"80524",
    "sg:province":"CO",
    "sg:tags":[
        "crop",
        "general"
    ],
    "wof:name":"Ted Roselius",
    "wof:placetype":"venue"
},
  "geometry": {"coordinates":[-104.95493500000001,40.5663],"type":"Point"}
}