{
  "type": "Feature",
  "properties": {
    "addr:full":"1500 N Farm Rd Monte Vista CO 81144",
    "addr:housenumber":"1500",
    "addr:postcode":"81144",
    "addr:street":"N Farm Rd",
    "iso:country":"US",
    "sg:address":"1500 N Farm Rd",
    "sg:city":"Monte Vista",
    "sg:classifiers":[
        {
            "category":"Home & Garden",
            "subcategory":"Building Materials",
            "type":"Retail Goods"
        }
    ],
    "sg:phone":"+1 719 852 3732",
    "sg:postcode":"81144",
    "sg:province":"CO",
    "sg:tags":[
        "mixed",
        "concrete"
    ],
    "wof:name":"Mathias Concrete Inc",
    "wof:placetype":"venue"
},
  "geometry": {"coordinates":[-106.12198100000001,37.610834],"type":"Point"}
}