{
  "type": "Feature",
  "properties": {
    "iso:country":"US",
    "sg:address":"2896 North Ave",
    "sg:city":"Grand Junction",
    "sg:classifiers":[
        {
            "category":"Autos & Motor Vehicles",
            "subcategory":"Fuel & Gas Station",
            "type":"Retail Goods"
        }
    ],
    "sg:phone":"+1 970 241 7667",
    "sg:postcode":"81501",
    "sg:province":"CO",
    "sg:tags":[
        "grocery",
        "station",
        "gasoline"
    ],
    "wof:name":"Bgs",
    "wof:placetype":"venue"
},
  "geometry": {"coordinates":[-108.51569600000001,39.077406],"type":"Point"}
}