{
  "type": "Feature",
  "properties": {
    "iso:country":"US",
    "sg:address":"3033 Leslie Dr",
    "sg:city":"Colorado Springs",
    "sg:classifiers":[
        {
            "category":"Banks & Credit Unions",
            "subcategory":"Financial Services",
            "type":"Services"
        }
    ],
    "sg:phone":"+1 719 473 6954",
    "sg:postcode":"80909",
    "sg:province":"CO",
    "sg:tags":[
        "trust",
        "management"
    ],
    "wof:name":"Hayes Family Enterprises Lllp",
    "wof:placetype":"venue"
},
  "geometry": {"coordinates":[-104.783728,38.875827],"type":"Point"}
}