{
  "type": "Feature",
  "properties": {
    "addr:full":"5370 Cracker Barrel Cir Colorado Springs CO 80917",
    "addr:housenumber":"5370",
    "addr:postcode":"80917",
    "addr:street":"Cracker Barrel Cir",
    "iso:country":"US",
    "sg:address":"5370 Cracker Barrel Cir",
    "sg:city":"Colorado Springs",
    "sg:classifiers":[
        {
            "category":"Education",
            "subcategory":"School",
            "type":"Public Place"
        }
    ],
    "sg:phone":"+1 719 328 7600",
    "sg:postcode":"80917",
    "sg:province":"CO",
    "sg:website":"www.d11.org/rudy",
    "wof:name":"Rudy Elementary School",
    "wof:placetype":"venue"
},
  "geometry": {"coordinates":[-104.727619,38.892332],"type":"Point"}
}