{
  "type": "Feature",
  "properties": {
    "addr:full":"6310 S Syracuse Way Centennial CO 80111",
    "addr:housenumber":"6310",
    "addr:postcode":"80111",
    "addr:street":"S Syracuse Way",
    "iso:country":"US",
    "sg:address":"6310 S Syracuse Way",
    "sg:city":"Centennial",
    "sg:classifiers":[
        {
            "category":"Professional",
            "type":"Services"
        }
    ],
    "sg:phone":"+1 303 740 7779",
    "sg:postcode":"80111",
    "sg:province":"CO",
    "sg:tags":[
        "establishment"
    ],
    "wof:name":"HCIA Inc",
    "wof:placetype":"venue"
},
  "geometry": {"coordinates":[-104.899421,39.599997],"type":"Point"}
}