{
  "type": "Feature",
  "properties": {
    "iso:country":"US",
    "sg:address":"4016 Youngfield St",
    "sg:city":"Wheat Ridge",
    "sg:classifiers":[
        {
            "category":"Manufacturing",
            "subcategory":"Metals",
            "type":"Manufacturing & Wholesale Goods"
        }
    ],
    "sg:phone":"+1 303 331 2700",
    "sg:postcode":"80033",
    "sg:province":"CO",
    "sg:tags":[
        "coating"
    ],
    "wof:name":"Protective Coating",
    "wof:placetype":"venue"
},
  "geometry": {"coordinates":[-105.142586,39.773614],"type":"Point"}
}