{
  "type": "Feature",
  "properties": {
    "iso:country":"US",
    "sg:address":"23064 Co Rd 21",
    "sg:city":"Milliken",
    "sg:classifiers":[
        {
            "category":"Building & Trades",
            "subcategory":"Construction",
            "type":"Services"
        }
    ],
    "sg:phone":"+1 970 587 2162",
    "sg:postcode":"80543",
    "sg:province":"CO",
    "sg:tags":[
        "general",
        "nonresidential",
        "contractor"
    ],
    "wof:name":"Kielian Construction",
    "wof:placetype":"venue"
},
  "geometry": {"coordinates":[-104.8676,40.334163],"type":"Point"}
}