{
  "type": "Feature",
  "properties": {
    "iso:country":"US",
    "sg:address":"13900 E Harvard Ave",
    "sg:city":"Aurora",
    "sg:classifiers":[
        {
            "category":"Insurance",
            "subcategory":"Insurance Agent",
            "type":"Services"
        }
    ],
    "sg:phone":"+1 303 755 0059",
    "sg:postcode":"80014",
    "sg:province":"CO",
    "wof:name":"Chris Dern Country Ins & Fnncl",
    "wof:placetype":"venue"
},
  "geometry": {"coordinates":[-104.82834800000001,39.670996],"type":"Point"}
}