{
  "type": "Feature",
  "properties": {
    "addr:full":"2321 N Logan Ave Colorado Springs CO 80907",
    "addr:housenumber":"2321",
    "addr:postcode":"80907",
    "addr:street":"N Logan Ave",
    "iso:country":"US",
    "sg:address":"2321 N Logan Ave",
    "sg:city":"Colorado Springs",
    "sg:classifiers":[
        {
            "category":"Building & Trades",
            "subcategory":"Cleaning & Sanitation",
            "type":"Services"
        }
    ],
    "sg:phone":"+1 719 477 0635",
    "sg:postcode":"80907",
    "sg:province":"CO",
    "sg:tags":[
        "ceiling"
    ],
    "wof:name":"Awesome Cleaning Techniques",
    "wof:placetype":"venue"
},
  "geometry": {"coordinates":[-104.797361,38.863981],"type":"Point"}
}