{
  "type": "Feature",
  "properties": {
    "addr:full":"1103 S Co Rd 137 Bennett CO 80102",
    "addr:housenumber":"1103;137",
    "addr:postcode":"bennett;80102",
    "addr:street":"S Co Rd",
    "iso:country":"US",
    "sg:address":"1103 S Co Rd 137",
    "sg:city":"Bennett",
    "sg:phone":"+1 303 644 3455",
    "sg:postcode":"80102",
    "sg:province":"CO",
    "sg:tags":[
        "farm",
        "wheat"
    ],
    "wof:name":"Alvin Young",
    "wof:placetype":"venue"
},
  "geometry": {"coordinates":[-104.41536000000001,39.697781],"type":"Point"}
}