{
  "type": "Feature",
  "properties": {
    "addr:full":"305 Society Dr Telluride CO 81435",
    "addr:housenumber":"305",
    "addr:postcode":"81435",
    "addr:street":"Society Dr",
    "iso:country":"US",
    "sg:address":"305 Society Dr",
    "sg:city":"Telluride",
    "sg:classifiers":[
        {
            "category":"Professional",
            "subcategory":"Computer Services",
            "type":"Services"
        }
    ],
    "sg:phone":"+1 970 728 5154",
    "sg:postcode":"81435",
    "sg:province":"CO",
    "sg:tags":[
        "consultant",
        "designer"
    ],
    "wof:name":"Computercraft",
    "wof:placetype":"venue"
},
  "geometry": {"coordinates":[-107.882982,37.944077],"type":"Point"}
}