{
  "type": "Feature",
  "properties": {
    "iso:country":"US",
    "sg:address":"1500 E Abriendo Ave",
    "sg:city":"Pueblo",
    "sg:classifiers":[
        {
            "category":"Retail",
            "subcategory":"Auto Repair",
            "type":"Services"
        }
    ],
    "sg:phone":"+1 719 561 4591",
    "sg:postcode":"81004",
    "sg:province":"CO",
    "sg:tags":[
        "repairing",
        "automobile"
    ],
    "wof:name":"Palomar Auto Care Ctr",
    "wof:placetype":"venue"
},
  "geometry": {"coordinates":[-104.613772,38.238811],"type":"Point"}
}