{
  "type": "Feature",
  "properties": {
    "addr:full":"5115 Federal Blvd Denver CO 80211",
    "addr:housenumber":"5115",
    "addr:postcode":"80211",
    "addr:street":"Federal Blvd",
    "iso:country":"US",
    "sg:address":"5115 Federal Blvd",
    "sg:city":"Denver",
    "sg:classifiers":[
        {
            "category":"Organizations",
            "subcategory":"Community Association",
            "type":"Services"
        }
    ],
    "sg:phone":"+1 303 480 0302",
    "sg:postcode":"80211",
    "sg:province":"CO",
    "sg:tags":[
        "club"
    ],
    "wof:name":"Tequila Leclub",
    "wof:placetype":"venue"
},
  "geometry": {"coordinates":[-105.02526400000001,39.79069],"type":"Point"}
}