{
  "type": "Feature",
  "properties": {
    "addr:full":"2821 W 8th Ave Denver CO 80204",
    "addr:housenumber":"2821",
    "addr:postcode":"80204",
    "addr:street":"W 8Th Ave",
    "iso:country":"US",
    "sg:address":"2821 W 8th Ave",
    "sg:city":"Denver",
    "sg:classifiers":[
        {
            "category":"Retail",
            "subcategory":"Auto Repair",
            "type":"Services"
        },
        {
            "category":"Wholesale",
            "subcategory":"Auto Parts",
            "type":"Manufacturing & Wholesale Goods"
        }
    ],
    "sg:phone":"+1 303 892 6525",
    "sg:postcode":"80204",
    "sg:province":"CO",
    "sg:tags":[
        "repairing",
        "automobile",
        "used",
        "radiator"
    ],
    "wof:name":"A-Ace Auto Salvage",
    "wof:placetype":"venue"
},
  "geometry": {"coordinates":[-105.024902,39.729315],"type":"Point"}
}