{
  "type": "Feature",
  "properties": {
    "iso:country":"US",
    "sg:address":"209 W 3rd St",
    "sg:city":"Salida",
    "sg:classifiers":[
        {
            "category":"Autos & Motor Vehicles",
            "subcategory":"Auto Supplies",
            "type":"Retail Goods"
        }
    ],
    "sg:phone":"+1 719 539 6207",
    "sg:postcode":"81201",
    "sg:province":"CO",
    "wof:name":"Tire Town II",
    "wof:placetype":"venue"
},
  "geometry": {"coordinates":[-105.995544,38.535772],"type":"Point"}
}