{
  "type": "Feature",
  "properties": {
    "iso:country":"US",
    "sg:address":"1022 Depot Hill Rd",
    "sg:city":"Broomfield",
    "sg:classifiers":[
        {
            "category":"Health Services",
            "subcategory":"Doctor",
            "type":"Services"
        }
    ],
    "sg:phone":"+1 303 465 2323",
    "sg:postcode":"80020",
    "sg:province":"CO",
    "sg:tags":[
        "medical"
    ],
    "wof:name":"Yeash James M Do",
    "wof:placetype":"venue"
},
  "geometry": {"coordinates":[-105.09303300000001,39.929541],"type":"Point"}
}