{
  "type": "Feature",
  "properties": {
    "addr:full":"13302 Clarkson St Denver CO 80241",
    "addr:housenumber":"13302",
    "addr:postcode":"80241",
    "addr:street":"Clarkson St",
    "iso:country":"US",
    "sg:address":"13302 Clarkson St",
    "sg:city":"Denver",
    "sg:classifiers":[
        {
            "category":"Manufacturing",
            "subcategory":"Printing",
            "type":"Manufacturing & Wholesale Goods"
        }
    ],
    "sg:phone":"+1 303 252 8956",
    "sg:postcode":"80241",
    "sg:province":"CO",
    "sg:tags":[
        "lithographic",
        "commercial"
    ],
    "wof:name":"Kidstar Printing",
    "wof:placetype":"venue"
},
  "geometry": {"coordinates":[-104.97712799999999,39.93816],"type":"Point"}
}