{
  "type": "Feature",
  "properties": {
    "addr:full":"605 Coffman St Longmont CO 80501",
    "addr:housenumber":"605",
    "addr:postcode":"80501",
    "addr:street":"Coffman St",
    "iso:country":"US",
    "sg:address":"605 Coffman St",
    "sg:city":"Longmont",
    "sg:classifiers":[
        {
            "category":"Building & Trades",
            "subcategory":"Construction",
            "type":"Services"
        }
    ],
    "sg:phone":"+1 720 652 9798",
    "sg:postcode":"80501",
    "sg:province":"CO",
    "sg:tags":[
        "contractor"
    ],
    "wof:name":"Bob Behrends Roofing LLC",
    "wof:placetype":"venue"
},
  "geometry": {"coordinates":[-105.10390200000001,40.1706],"type":"Point"}
}