{
  "type": "Feature",
  "properties": {
    "addr:full":"1987 Overton Rd Pueblo CO 81008",
    "addr:housenumber":"1987",
    "addr:postcode":"81008",
    "addr:street":"Overton Rd",
    "iso:country":"US",
    "sg:address":"1987 Overton Rd",
    "sg:city":"Pueblo",
    "sg:classifiers":[
        {
            "category":"Home & Garden",
            "subcategory":"Carpets & Floor Coverings",
            "type":"Retail Goods"
        }
    ],
    "sg:phone":"+1 719 544 2924",
    "sg:postcode":"81008",
    "sg:province":"CO",
    "sg:tags":[
        "dealer",
        "rug"
    ],
    "wof:name":"Trani Designer Rugs and Carpet",
    "wof:placetype":"venue"
},
  "geometry": {"coordinates":[-104.604617,38.334584],"type":"Point"}
}