{
  "type": "Feature",
  "properties": {
    "iso:country":"US",
    "sg:address":"2 Wadsworth Blvd",
    "sg:city":"Lakewood",
    "sg:classifiers":[
        {
            "category":"Building & Trades",
            "subcategory":"Locksmith",
            "type":"Services"
        }
    ],
    "sg:phone":"+1 303 481 0692",
    "sg:postcode":"80226",
    "sg:province":"CO",
    "sg:tags":[
        "key"
    ],
    "wof:name":"A 24 Hour A Locksmith",
    "wof:placetype":"venue"
},
  "geometry": {"coordinates":[-105.081392,39.716625],"type":"Point"}
}