{
  "type": "Feature",
  "properties": {
    "iso:country":"US",
    "sg:address":"3547 E 117th Dr",
    "sg:city":"Denver",
    "sg:classifiers":[
        {
            "category":"Professional",
            "type":"Services"
        }
    ],
    "sg:phone":"+1 303 457 3653",
    "sg:postcode":"80233",
    "sg:province":"CO",
    "wof:name":"David J Valdez",
    "wof:placetype":"venue"
},
  "geometry": {"coordinates":[-104.944603,39.909829],"type":"Point"}
}