{
  "type": "Feature",
  "properties": {
    "addr:full":"350 Kimbark St Longmont CO 80501",
    "addr:housenumber":"350",
    "addr:postcode":"80501",
    "addr:street":"Kimbark St",
    "iso:country":"US",
    "sg:address":"350 Kimbark St",
    "sg:city":"Longmont",
    "sg:classifiers":[
        {
            "category":"Government",
            "subcategory":"Office",
            "type":"Public Place"
        }
    ],
    "sg:phone":"+1 303 651 8622",
    "sg:postcode":"80501",
    "sg:province":"CO",
    "sg:tags":[
        "village"
    ],
    "wof:name":"Finance Director",
    "wof:placetype":"venue"
},
  "geometry": {"coordinates":[-105.101113,40.164814],"type":"Point"}
}