{
  "type": "Feature",
  "properties": {
    "iso:country":"US",
    "sg:address":"4406 Morrison Rd",
    "sg:city":"Denver",
    "sg:classifiers":[
        {
            "category":"Home & Garden",
            "subcategory":"Building Materials",
            "type":"Retail Goods"
        }
    ],
    "sg:phone":"+1 303 981 0118",
    "sg:postcode":"80219",
    "sg:province":"CO",
    "sg:tags":[
        "truss"
    ],
    "wof:name":"O'Dell Crane Svc",
    "wof:placetype":"venue"
},
  "geometry": {"coordinates":[-105.044025,39.703412],"type":"Point"}
}