{
  "type": "Feature",
  "properties": {
    "addr:full":"4610 E Fair Pl Littleton CO 80121",
    "addr:housenumber":"4610",
    "addr:postcode":"80121",
    "addr:street":"E Fair Pl",
    "iso:country":"US",
    "sg:address":"4610 E Fair Pl",
    "sg:city":"Littleton",
    "sg:classifiers":[
        {
            "category":"Shopping",
            "type":"Retail Goods"
        }
    ],
    "sg:phone":"+1 303 752 3272",
    "sg:postcode":"80121",
    "sg:province":"CO",
    "sg:tags":[
        "household",
        "appliance",
        "merchandise"
    ],
    "wof:name":"Executive Tans",
    "wof:placetype":"venue"
},
  "geometry": {"coordinates":[-104.934308,39.602613],"type":"Point"}
}