{
  "type": "Feature",
  "properties": {
    "addr:full":"3924 37th St Evans CO 80620",
    "addr:housenumber":"3924",
    "addr:postcode":"80620",
    "addr:street":"37Th St",
    "iso:country":"US",
    "sg:address":"3924 37th St",
    "sg:city":"Evans",
    "sg:phone":"+1 970 330 3212",
    "sg:postcode":"80620",
    "sg:province":"CO",
    "sg:tags":[
        "farm",
        "corn"
    ],
    "wof:name":"Rhoadarmer Livestock",
    "wof:placetype":"venue"
},
  "geometry": {"coordinates":[-104.744342,40.377867],"type":"Point"}
}