{
  "type": "Feature",
  "properties": {
    "addr:full":"648 Main St Grand Junction CO 81501",
    "addr:housenumber":"648",
    "addr:postcode":"81501",
    "addr:street":"Main St",
    "iso:country":"US",
    "sg:address":"648 Main St",
    "sg:city":"Grand Junction",
    "sg:classifiers":[
        {
            "category":"Shopping",
            "subcategory":"Shoes",
            "type":"Retail Goods"
        }
    ],
    "sg:phone":"+1 970 243 4777",
    "sg:postcode":"81501",
    "sg:province":"CO",
    "wof:name":"Shoe Design",
    "wof:placetype":"venue"
},
  "geometry": {"coordinates":[-108.561824,39.0674],"type":"Point"}
}