{
  "type": "Feature",
  "properties": {
    "iso:country":"US",
    "sg:address":"12029 Hwy 550",
    "sg:city":"Durango",
    "sg:classifiers":[
        {
            "category":"Building & Trades",
            "subcategory":"Construction",
            "type":"Services"
        }
    ],
    "sg:phone":"+1 970 385 4561",
    "sg:postcode":"81303",
    "sg:province":"CO",
    "sg:tags":[
        "house",
        "nonresidential"
    ],
    "wof:name":"Durango Solariums",
    "wof:placetype":"venue"
},
  "geometry": {"coordinates":[-107.857882,37.162],"type":"Point"}
}