{
  "type": "Feature",
  "properties": {
    "iso:country":"US",
    "sg:address":"1012 N Santa Fe Ave",
    "sg:city":"Pueblo",
    "sg:classifiers":[
        {
            "category":"Travel",
            "subcategory":"Hotels & Motels",
            "type":"Entertainment"
        }
    ],
    "sg:phone":"+1 719 543 5451",
    "sg:postcode":"81003",
    "sg:province":"CO",
    "wof:name":"Travelers Motel",
    "wof:placetype":"venue"
},
  "geometry": {"coordinates":[-104.607103,38.277023],"type":"Point"}
}