{
  "type": "Feature",
  "properties": {
    "addr:full":"1501 E Evans Ave Pueblo CO 81004",
    "addr:housenumber":"1501",
    "addr:postcode":"81004",
    "addr:street":"E Evans Ave",
    "iso:country":"US",
    "sg:address":"1501 E Evans Ave",
    "sg:city":"Pueblo",
    "sg:classifiers":[
        {
            "category":"Bars & Pubs",
            "type":"Food & Drink"
        }
    ],
    "sg:phone":"+1 719 564 9851",
    "sg:postcode":"81004",
    "sg:province":"CO",
    "wof:name":"Capritta's Oasis",
    "wof:placetype":"venue"
},
  "geometry": {"coordinates":[-104.614943,38.238807],"type":"Point"}
}