{
  "type": "Feature",
  "properties": {
    "iso:country":"US",
    "sg:address":"2 Castle Ln",
    "sg:city":"Basalt",
    "sg:classifiers":[
        {
            "category":"Building & Trades",
            "subcategory":"Construction",
            "type":"Services"
        }
    ],
    "sg:phone":"+1 970 927 3761",
    "sg:postcode":"81621",
    "sg:province":"CO",
    "sg:tags":[
        "home",
        "builder"
    ],
    "wof:name":"Helmich Construction",
    "wof:placetype":"venue"
},
  "geometry": {"coordinates":[-106.95504099999999,39.383292],"type":"Point"}
}