{
  "type": "Feature",
  "properties": {
    "iso:country":"US",
    "sg:address":"1136 101st Avenue Ct",
    "sg:city":"Greeley",
    "sg:classifiers":[
        {
            "category":"Real Estate",
            "subcategory":"Real Estate Agent",
            "type":"Services"
        }
    ],
    "sg:phone":"+1 970 392 0038",
    "sg:postcode":"80634",
    "sg:province":"CO",
    "wof:name":"Lifestyle Homes At Promontory",
    "wof:placetype":"venue"
},
  "geometry": {"coordinates":[-104.84230100000001,40.419556],"type":"Point"}
}