{
  "type": "Feature",
  "properties": {
    "addr:full":"1900 Olive St Denver CO 80207",
    "addr:housenumber":"1900",
    "addr:postcode":"80207",
    "addr:street":"Olive St",
    "iso:country":"US",
    "sg:address":"1900 Olive St",
    "sg:city":"Denver",
    "sg:classifiers":[
        {
            "category":"Education",
            "subcategory":"College",
            "type":"Public Place"
        }
    ],
    "sg:phone":"+1 303 871 6041",
    "sg:postcode":"80207",
    "sg:province":"CO",
    "sg:tags":[
        "program",
        "tax",
        "graduate"
    ],
    "wof:name":"University of Denver",
    "wof:placetype":"venue"
},
  "geometry": {"coordinates":[-104.906954,39.747434],"type":"Point"}
}