{
  "type": "Feature",
  "properties": {
    "iso:country":"US",
    "sg:address":"20020 Co Rd P",
    "sg:city":"Fort Morgan",
    "sg:phone":"+1 970 867 6147",
    "sg:postcode":"80701",
    "sg:province":"CO",
    "sg:tags":[
        "farm",
        "corn",
        "cash",
        "crop",
        "field",
        "grain"
    ],
    "wof:name":"Weber Farms",
    "wof:placetype":"venue"
},
  "geometry": {"coordinates":[-103.754606,40.217869],"type":"Point"}
}