{
  "type": "Feature",
  "properties": {
    "iso:country":"US",
    "sg:address":"1229 6th Ave",
    "sg:city":"Denver",
    "sg:classifiers":[
        {
            "category":"Shopping",
            "subcategory":"Bicycles & Sporting Goods",
            "type":"Retail Goods"
        },
        {
            "category":"Recreation",
            "type":"Entertainment"
        }
    ],
    "sg:phone":"+1 303 339 0085",
    "sg:postcode":"80218",
    "sg:province":"CO",
    "sg:tags":[
        "active",
        "life",
        "bike"
    ],
    "sg:website":"www.velowoodbikeshop.com",
    "wof:name":"Velowood Bike Shop",
    "wof:placetype":"venue"
},
  "geometry": {"coordinates":[-104.972604,39.725595],"type":"Point"}
}