{
  "type": "Feature",
  "properties": {
    "addr:full":"7077 S Simms St Littleton CO 80127",
    "addr:housenumber":"7077",
    "addr:postcode":"80127",
    "addr:street":"S Simms St",
    "iso:country":"US",
    "sg:address":"7077 S Simms St",
    "sg:city":"Littleton",
    "sg:classifiers":[
        {
            "category":"Organizations",
            "subcategory":"Religious Organization",
            "type":"Services"
        }
    ],
    "sg:phone":"+1 303 979 8374",
    "sg:postcode":"80127",
    "sg:province":"CO",
    "sg:tags":[
        "church"
    ],
    "wof:name":"Heritage United Methdst Church",
    "wof:placetype":"venue"
},
  "geometry": {"coordinates":[-105.125486,39.59034],"type":"Point"}
}