{
  "type": "Feature",
  "properties": {
    "addr:full":"5526 Brentwood St Arvada CO 80002",
    "addr:housenumber":"5526",
    "addr:postcode":"80002",
    "addr:street":"Brentwood St",
    "iso:country":"US",
    "sg:address":"5526 Brentwood St",
    "sg:city":"Arvada",
    "sg:classifiers":[
        {
            "category":"Retail",
            "subcategory":"Laundry & Dry Cleaning",
            "type":"Services"
        }
    ],
    "sg:phone":"+1 303 989 3111",
    "sg:postcode":"80002",
    "sg:province":"CO",
    "sg:tags":[
        "cleaners",
        "rug",
        "carpet"
    ],
    "wof:name":"Chem-Dry By Regal",
    "wof:placetype":"venue"
},
  "geometry": {"coordinates":[-105.089732,39.797868],"type":"Point"}
}