{
  "type": "Feature",
  "properties": {
    "addr:full":"306 Colorado Ave Seibert CO 80834",
    "addr:housenumber":"306",
    "addr:postcode":"80834",
    "addr:street":"Colorado Ave",
    "iso:country":"US",
    "sg:address":"306 Colorado Ave",
    "sg:city":"Seibert",
    "sg:classifiers":[
        {
            "category":"Travel",
            "subcategory":"Campground",
            "type":"Entertainment"
        }
    ],
    "sg:phone":"+1 970 664 2218",
    "sg:postcode":"80834",
    "sg:province":"CO",
    "wof:name":"Shady Grove Campground",
    "wof:placetype":"venue"
},
  "geometry": {"coordinates":[-102.869558,39.298677],"type":"Point"}
}