{
  "type": "Feature",
  "properties": {
    "addr:full":"1225 Ken Pratt Blvd Longmont CO 80501",
    "addr:housenumber":"1225",
    "addr:postcode":"80501",
    "addr:street":"Ken Pratt Blvd",
    "iso:country":"US",
    "sg:address":"1225 Ken Pratt Blvd",
    "sg:city":"Longmont",
    "sg:classifiers":[
        {
            "category":"Food & Beverages",
            "subcategory":"Bakery",
            "type":"Retail Goods"
        }
    ],
    "sg:phone":"+1 303 776 2043",
    "sg:postcode":"80501",
    "sg:province":"CO",
    "sg:tags":[
        "baker"
    ],
    "wof:name":"Hummingbird Teahouse",
    "wof:placetype":"venue"
},
  "geometry": {"coordinates":[-105.115229,40.152257],"type":"Point"}
}