{
  "type": "Feature",
  "properties": {
    "addr:full":"546 Glen Rd Grand Junction CO 81501",
    "addr:housenumber":"546",
    "addr:postcode":"81501",
    "addr:street":"Glen Rd",
    "iso:country":"US",
    "sg:address":"546 Glen Rd",
    "sg:city":"Grand Junction",
    "sg:classifiers":[
        {
            "category":"Wholesale",
            "subcategory":"Books, Periodicals, & Newspapers",
            "type":"Manufacturing & Wholesale Goods"
        }
    ],
    "sg:phone":"+1 970 241 6955",
    "sg:postcode":"81501",
    "sg:province":"CO",
    "wof:name":"Splash Page Comics",
    "wof:placetype":"venue"
},
  "geometry": {"coordinates":[-108.52533,39.08356],"type":"Point"}
}