{
  "type": "Feature",
  "properties": {
    "iso:country":"US",
    "sg:address":"2510 E Colfax Ave",
    "sg:city":"Denver",
    "sg:phone":"+1 720 596 4740",
    "sg:postcode":"80206",
    "sg:province":"CO",
    "sg:website":"http://www.denverfilm.org",
    "wof:name":"Denver FilmCenter/Colfax",
    "wof:placetype":"venue"
},
  "geometry": {"coordinates":[-104.95728099999999,39.740188],"type":"Point"}
}