{
  "type": "Feature",
  "properties": {
    "iso:country":"US",
    "sg:address":"17326 Rimrock Dr",
    "sg:city":"Golden",
    "sg:classifiers":[
        {
            "category":"Professional",
            "subcategory":"Computer Services",
            "type":"Services"
        }
    ],
    "sg:phone":"+1 303 520 5840",
    "sg:postcode":"80401",
    "sg:province":"CO",
    "sg:tags":[
        "consultant",
        "equipment"
    ],
    "wof:name":"S T W Software Inc",
    "wof:placetype":"venue"
},
  "geometry": {"coordinates":[-105.197785,39.744347],"type":"Point"}
}