{
  "type": "Feature",
  "properties": {
    "iso:country":"US",
    "sg:address":"2221 Delores Way",
    "sg:city":"Carbondale",
    "sg:classifiers":[
        {
            "category":"Building & Trades",
            "subcategory":"Construction",
            "type":"Services"
        }
    ],
    "sg:phone":"+1 970 963 9246",
    "sg:postcode":"81623",
    "sg:province":"CO",
    "sg:tags":[
        "hanging",
        "painter",
        "contractor"
    ],
    "wof:name":"Dru Handy Custom Painting Inc",
    "wof:placetype":"venue"
},
  "geometry": {"coordinates":[-107.22435299999999,39.410613],"type":"Point"}
}