{
  "type": "Feature",
  "properties": {
    "addr:full":"7989 Eagle Ranch Rd Fort Collins CO 80528",
    "addr:housenumber":"7989",
    "addr:postcode":"80528",
    "addr:street":"Eagle Ranch Rd",
    "iso:country":"US",
    "sg:address":"7989 Eagle Ranch Rd",
    "sg:city":"Fort Collins",
    "sg:classifiers":[
        {
            "category":"Professional",
            "type":"Services"
        }
    ],
    "sg:phone":"+1 970 225 9094",
    "sg:postcode":"80528",
    "sg:province":"CO",
    "wof:name":"Highpoint Vista LLC",
    "wof:placetype":"venue"
},
  "geometry": {"coordinates":[-105.00337500000001,40.474819],"type":"Point"}
}