{
  "type": "Feature",
  "properties": {
    "addr:full":"22784 US Hwy 6 Keystone CO 80435",
    "addr:housenumber":"22784",
    "addr:postcode":"80435",
    "addr:street":"Us Hwy 6",
    "iso:country":"US",
    "sg:address":"22784 US Hwy 6",
    "sg:city":"Keystone",
    "sg:classifiers":[
        {
            "category":"Real Estate",
            "subcategory":"Real Estate Operator",
            "type":"Services"
        }
    ],
    "sg:phone":"+1 970 262 1543",
    "sg:postcode":"80435",
    "sg:province":"CO",
    "sg:tags":[
        "condominium"
    ],
    "wof:name":"Tenderfoot Lodge",
    "wof:placetype":"venue"
},
  "geometry": {"coordinates":[-105.956045,39.607897],"type":"Point"}
}