{
  "type": "Feature",
  "properties": {
    "iso:country":"US",
    "sg:address":"2979 N Highway 83",
    "sg:city":"Franktown",
    "sg:classifiers":[
        {
            "category":"Home & Garden",
            "subcategory":"Garden Supply",
            "type":"Retail Goods"
        }
    ],
    "sg:phone":"+1 303 688 2442",
    "sg:postcode":"80116",
    "sg:province":"CO",
    "sg:tags":[
        "nursery",
        "gardening"
    ],
    "sg:website":"www.countrylanewholesalenursery.com",
    "wof:name":"Country Lane Wholesale Nursery",
    "wof:placetype":"venue"
},
  "geometry": {"coordinates":[-104.758151,39.403291],"type":"Point"}
}