{
  "type": "Feature",
  "properties": {
    "addr:full":"7149 Cedarwood Cir Boulder CO 80301",
    "addr:housenumber":"7149",
    "addr:postcode":"80301",
    "addr:street":"Cedarwood Cir",
    "iso:country":"US",
    "sg:address":"7149 Cedarwood Cir",
    "sg:city":"Boulder",
    "sg:classifiers":[
        {
            "category":"Real Estate",
            "subcategory":"Real Estate Agent",
            "type":"Services"
        }
    ],
    "sg:phone":"+1 303 530 2149",
    "sg:postcode":"80301",
    "sg:province":"CO",
    "wof:name":"William Graff & Co",
    "wof:placetype":"venue"
},
  "geometry": {"coordinates":[-105.18756999999999,40.066539],"type":"Point"}
}