{
  "type": "Feature",
  "properties": {
    "iso:country":"US",
    "sg:address":"755 E Hwy 105",
    "sg:city":"Monument",
    "sg:classifiers":[
        {
            "category":"Professional",
            "type":"Services"
        }
    ],
    "sg:phone":"+1 719 488 8780",
    "sg:postcode":"80132",
    "sg:province":"CO",
    "sg:tags":[
        "establishment"
    ],
    "wof:name":"Smoot Kim Speech Pathologist",
    "wof:placetype":"venue"
},
  "geometry": {"coordinates":[-104.81011100000001,39.094097],"type":"Point"}
}