{
  "type": "Feature",
  "properties": {
    "addr:full":"4704 Harlan St Denver CO 80212",
    "addr:housenumber":"4704",
    "addr:postcode":"80212",
    "addr:street":"Harlan St",
    "iso:country":"US",
    "sg:address":"4704 Harlan St",
    "sg:city":"Denver",
    "sg:classifiers":[
        {
            "category":"Real Estate",
            "subcategory":"Real Estate Agent",
            "type":"Services"
        }
    ],
    "sg:phone":"+1 303 477 8822",
    "sg:postcode":"80212",
    "sg:province":"CO",
    "sg:tags":[
        "investment"
    ],
    "wof:name":"Lakeside Office Park",
    "wof:placetype":"venue"
},
  "geometry": {"coordinates":[-105.062506,39.782972],"type":"Point"}
}