{
  "type": "Feature",
  "properties": {
    "addr:full":"10389 W Rockland Pl Littleton CO 80127",
    "addr:housenumber":"10389",
    "addr:postcode":"80127",
    "addr:street":"W Rockland Pl",
    "iso:country":"US",
    "sg:address":"10389 W Rockland Pl",
    "sg:city":"Littleton",
    "sg:classifiers":[
        {
            "category":"Wholesale",
            "subcategory":"Books, Periodicals, & Newspapers",
            "type":"Manufacturing & Wholesale Goods"
        }
    ],
    "sg:phone":"+1 303 933 7804",
    "sg:postcode":"80127",
    "sg:province":"CO",
    "wof:name":"Denver Media Promotions",
    "wof:placetype":"venue"
},
  "geometry": {"coordinates":[-105.11533,39.563769],"type":"Point"}
}