{
  "type": "Feature",
  "properties": {
    "addr:full":"199 Dekker Dr Golden CO 80401",
    "addr:housenumber":"199",
    "addr:postcode":"80401",
    "addr:street":"Dekker Dr",
    "iso:country":"US",
    "sg:address":"199 Dekker Dr",
    "sg:city":"Golden",
    "sg:classifiers":[
        {
            "category":"Manufacturing",
            "subcategory":"Food",
            "type":"Manufacturing & Wholesale Goods"
        }
    ],
    "sg:phone":"+1 303 526 9488",
    "sg:postcode":"80401",
    "sg:province":"CO",
    "sg:tags":[
        "book",
        "mfg"
    ],
    "wof:name":"High Tech Noodle Inc",
    "wof:placetype":"venue"
},
  "geometry": {"coordinates":[-105.252555,39.712641],"type":"Point"}
}