{
  "type": "Feature",
  "properties": {
    "addr:full":"215 E Foothills Pkwy Fort Collins CO 80525",
    "addr:housenumber":"215",
    "addr:postcode":"80525",
    "addr:street":"E Foothills Pkwy",
    "iso:country":"US",
    "sg:address":"215 E Foothills Pkwy",
    "sg:city":"Fort Collins",
    "sg:classifiers":[
        {
            "category":"Shopping",
            "subcategory":"Hobbies, Toys, & Games",
            "type":"Retail Goods"
        },
        {
            "category":"Shopping",
            "subcategory":"Gifts & Souvenirs",
            "type":"Retail Goods"
        }
    ],
    "sg:phone":"+1 970 266 8133",
    "sg:postcode":"80525",
    "sg:province":"CO",
    "sg:tags":[
        "shop"
    ],
    "wof:name":"Life's Little Treasures",
    "wof:placetype":"venue"
},
  "geometry": {"coordinates":[-105.07463300000001,40.543772],"type":"Point"}
}