{
  "type": "Feature",
  "properties": {
    "addr:full":"564 Main St Nucla CO 81424",
    "addr:housenumber":"564",
    "addr:postcode":"81424",
    "addr:street":"Main St",
    "iso:country":"US",
    "sg:address":"564 Main St",
    "sg:city":"Nucla",
    "sg:classifiers":[
        {
            "category":"Building & Trades",
            "subcategory":"Construction",
            "type":"Services"
        }
    ],
    "sg:phone":"+1 970 864 7632",
    "sg:postcode":"81424",
    "sg:province":"CO",
    "sg:tags":[
        "general",
        "contractor"
    ],
    "wof:name":"Morgan Concrete Construction",
    "wof:placetype":"venue"
},
  "geometry": {"coordinates":[-108.545902,38.267953],"type":"Point"}
}