{
  "type": "Feature",
  "properties": {
    "iso:country":"US",
    "sg:address":"8822 Ridgeline Blvd",
    "sg:city":"Littleton",
    "sg:classifiers":[
        {
            "category":"Professional",
            "subcategory":"Lawyer & Legal Services",
            "type":"Services"
        }
    ],
    "sg:phone":"+1 303 730 3900",
    "sg:postcode":"80129",
    "sg:province":"CO",
    "sg:tags":[
        "attorney"
    ],
    "sg:website":"www.respect2000.com",
    "wof:name":"Lasater & Assoc",
    "wof:placetype":"venue"
},
  "geometry": {"coordinates":[-104.996323,39.556237],"type":"Point"}
}