{
  "type": "Feature",
  "properties": {
    "addr:full":"2865 W 44th Ave Denver CO 80211",
    "addr:housenumber":"2865",
    "addr:postcode":"80211",
    "addr:street":"W 44Th Ave",
    "iso:country":"US",
    "sg:address":"2865 W 44th Ave",
    "sg:city":"Denver",
    "sg:classifiers":[
        {
            "category":"Home & Garden",
            "subcategory":"Carpets & Floor Coverings",
            "type":"Retail Goods"
        }
    ],
    "sg:phone":"+1 303 455 1305",
    "sg:postcode":"80211",
    "sg:province":"CO",
    "sg:tags":[
        "dealer",
        "rug"
    ],
    "wof:name":"America's Carpet Broker",
    "wof:placetype":"venue"
},
  "geometry": {"coordinates":[-105.02396899999999,39.776641],"type":"Point"}
}