{
  "type": "Feature",
  "properties": {
    "addr:full":"169 Bear Lake Cir Divide CO 80814",
    "addr:housenumber":"169",
    "addr:postcode":"80814",
    "addr:street":"Bear Lake Cir Divide",
    "iso:country":"US",
    "sg:address":"169 Bear Lake Cir",
    "sg:city":"Divide",
    "sg:classifiers":[
        {
            "category":"Building & Trades",
            "subcategory":"Landscaping Services",
            "type":"Services"
        }
    ],
    "sg:phone":"+1 719 630 2144",
    "sg:postcode":"80814",
    "sg:province":"CO",
    "sg:tags":[
        "landscape"
    ],
    "wof:name":"Aimee Dejoy Design Studio",
    "wof:placetype":"venue"
},
  "geometry": {"coordinates":[-105.211974,38.960156],"type":"Point"}
}