{
  "type": "Feature",
  "properties": {
    "iso:country":"US",
    "sg:address":"400 N Colorado Ave",
    "sg:city":"Haxtun",
    "sg:classifiers":[
        {
            "category":"Organizations",
            "subcategory":"Religious Organization",
            "type":"Services"
        }
    ],
    "sg:phone":"+1 970 774 6236",
    "sg:postcode":"80731",
    "sg:province":"CO",
    "sg:tags":[
        "church"
    ],
    "wof:name":"Lutheran Church",
    "wof:placetype":"venue"
},
  "geometry": {"coordinates":[-102.62853200000001,40.645942],"type":"Point"}
}