{
  "type": "Feature",
  "properties": {
    "addr:full":"5581 E Jewell Ave Denver CO 80222",
    "addr:housenumber":"5581",
    "addr:postcode":"80222",
    "addr:street":"E Jewell Ave",
    "iso:country":"US",
    "sg:address":"5581 E Jewell Ave",
    "sg:city":"Denver",
    "sg:classifiers":[
        {
            "category":"Shopping",
            "subcategory":"Clothing, Apparel, & Fashions",
            "type":"Retail Goods"
        }
    ],
    "sg:phone":"+1 303 758 0387",
    "sg:postcode":"80222",
    "sg:province":"CO",
    "wof:name":"Freakin Shirts",
    "wof:placetype":"venue"
},
  "geometry": {"coordinates":[-104.924505,39.682175],"type":"Point"}
}