{
  "type": "Feature",
  "properties": {
    "iso:country":"US",
    "sg:address":"1365 N Park Dr",
    "sg:city":"Lafayette",
    "sg:classifiers":[
        {
            "category":"Professional",
            "subcategory":"Testing Lab",
            "type":"Services"
        },
        {
            "category":"Professional",
            "subcategory":"Business Services",
            "type":"Services"
        }
    ],
    "sg:phone":"+1 303 444 5253",
    "sg:postcode":"80026",
    "sg:province":"CO",
    "sg:tags":[
        "correction",
        "consulting",
        "radon"
    ],
    "wof:name":"RDS Environmental Inc",
    "wof:placetype":"venue"
},
  "geometry": {"coordinates":[-105.128613,40.012253],"type":"Point"}
}