{
  "type": "Feature",
  "properties": {
    "iso:country":"US",
    "sg:address":"96 Precision Dr",
    "sg:city":"Pueblo West",
    "sg:classifiers":[
        {
            "category":"Building & Trades",
            "subcategory":"Electrical",
            "type":"Services"
        }
    ],
    "sg:phone":"+1 719 547 3335",
    "sg:postcode":"81007",
    "sg:province":"CO",
    "sg:tags":[
        "electrical",
        "electric",
        "contractor"
    ],
    "wof:name":"Acme Electric Inc",
    "wof:placetype":"venue"
},
  "geometry": {"coordinates":[-104.726246,38.336677],"type":"Point"}
}