{
  "type": "Feature",
  "properties": {
    "iso:country":"US",
    "sg:address":"7018 Reed Ct",
    "sg:city":"Arvada",
    "sg:classifiers":[
        {
            "category":"Wholesale",
            "subcategory":"Hardware",
            "type":"Manufacturing & Wholesale Goods"
        }
    ],
    "sg:phone":"+1 303 431 2107",
    "sg:postcode":"80003",
    "sg:province":"CO",
    "sg:tags":[
        "plumbing"
    ],
    "wof:name":"Colorado Midland Pipe & Supply",
    "wof:placetype":"venue"
},
  "geometry": {"coordinates":[-105.07534699999999,39.825146],"type":"Point"}
}