{
  "type": "Feature",
  "properties": {
    "addr:full":"5920 Lamar St Arvada CO 80003",
    "addr:housenumber":"5920",
    "addr:postcode":"80003",
    "addr:street":"Lamar St",
    "iso:country":"US",
    "sg:address":"5920 Lamar St",
    "sg:city":"Arvada",
    "sg:classifiers":[
        {
            "category":"Building & Trades",
            "subcategory":"Construction",
            "type":"Services"
        }
    ],
    "sg:phone":"+1 303 422 7985",
    "sg:postcode":"80003",
    "sg:province":"CO",
    "sg:tags":[
        "contractor"
    ],
    "sg:website":"www.wlcontractors.com",
    "wof:name":"W L Contractors",
    "wof:placetype":"venue"
},
  "geometry": {"coordinates":[-105.065173,39.803848],"type":"Point"}
}