{
  "type": "Feature",
  "properties": {
    "iso:country":"US",
    "sg:address":"1717 S Acoma St",
    "sg:city":"Denver",
    "sg:classifiers":[
        {
            "category":"Professional",
            "subcategory":"Printing & Photocopies",
            "type":"Services"
        },
        {
            "category":"Manufacturing",
            "subcategory":"Signs",
            "type":"Manufacturing & Wholesale Goods"
        }
    ],
    "sg:phone":"+1 303 647 1754",
    "sg:postcode":"80223",
    "sg:province":"CO",
    "sg:tags":[
        "engraving"
    ],
    "sg:website":"http://www.artcraftsign.com",
    "wof:name":"Artcraft Signs",
    "wof:placetype":"venue"
},
  "geometry": {"coordinates":[-104.988767,39.685482],"type":"Point"}
}