{
  "type": "Feature",
  "properties": {
    "addr:full":"37440 Co Rd 51 Eaton CO 80615",
    "addr:housenumber":"37440;51",
    "addr:postcode":"80615",
    "addr:street":"Co Rd;Eaton",
    "iso:country":"US",
    "sg:address":"37440 Co Rd 51",
    "sg:city":"Eaton",
    "sg:classifiers":[
        {
            "category":"Farming",
            "subcategory":"Dairy Farm",
            "type":"Manufacturing & Wholesale Goods"
        }
    ],
    "sg:phone":"+1 970 454 3379",
    "sg:postcode":"80615",
    "sg:province":"CO",
    "wof:name":"Galeton Dairy",
    "wof:placetype":"venue"
},
  "geometry": {"coordinates":[-104.583146,40.549089],"type":"Point"}
}