{
  "type": "Feature",
  "properties": {
    "addr:full":"11811 E 33rd Ave Aurora CO 80010",
    "addr:housenumber":"11811",
    "addr:postcode":"80010",
    "addr:street":"E 33Rd Ave",
    "iso:country":"US",
    "sg:address":"11811 E 33rd Ave",
    "sg:city":"Aurora",
    "sg:classifiers":[
        {
            "category":"Building & Trades",
            "subcategory":"Cleaning & Sanitation",
            "type":"Services"
        }
    ],
    "sg:phone":"+1 303 343 2702",
    "sg:postcode":"80010",
    "sg:province":"CO",
    "sg:tags":[
        "janitor"
    ],
    "wof:name":"Mile Hi Mineral Cleaning Lab",
    "wof:placetype":"venue"
},
  "geometry": {"coordinates":[-104.851839,39.763845],"type":"Point"}
}