{
  "type": "Feature",
  "properties": {
    "addr:full":"700 Kipling St Lakewood CO 80215",
    "addr:housenumber":"700",
    "addr:postcode":"80215",
    "addr:street":"Kipling St",
    "iso:country":"US",
    "sg:address":"700 Kipling St",
    "sg:city":"Lakewood",
    "sg:classifiers":[
        {
            "category":"Government",
            "subcategory":"Fire Station",
            "type":"Public Place"
        }
    ],
    "sg:phone":"+1 303 239 4463",
    "sg:postcode":"80215",
    "sg:province":"CO",
    "sg:tags":[
        "state",
        "protection"
    ],
    "wof:name":"Fire Safety Div",
    "wof:placetype":"venue"
},
  "geometry": {"coordinates":[-105.109632,39.726796],"type":"Point"}
}