{
  "type": "Feature",
  "properties": {
    "iso:country":"US",
    "sg:address":"3700 S Mason St",
    "sg:city":"Fort Collins",
    "sg:classifiers":[
        {
            "category":"Personal",
            "subcategory":"Tanning Parlor",
            "type":"Services"
        }
    ],
    "sg:phone":"+1 970 223 6225",
    "sg:postcode":"80525",
    "sg:province":"CO",
    "sg:tags":[
        "salon"
    ],
    "wof:name":"A Desired Look Tanning Salon",
    "wof:placetype":"venue"
},
  "geometry": {"coordinates":[-105.079138,40.536518],"type":"Point"}
}