{
  "type": "Feature",
  "properties": {
    "addr:full":"1373 Osceola St Denver CO 80204",
    "addr:housenumber":"1373",
    "addr:postcode":"80204",
    "addr:street":"Osceola St",
    "iso:country":"US",
    "sg:address":"1373 Osceola St",
    "sg:city":"Denver",
    "sg:classifiers":[
        {
            "category":"Building & Trades",
            "subcategory":"Construction",
            "type":"Services"
        }
    ],
    "sg:phone":"+1 720 289 1947",
    "sg:postcode":"80204",
    "sg:province":"CO",
    "sg:tags":[
        "contractor"
    ],
    "wof:name":"Master Services",
    "wof:placetype":"venue"
},
  "geometry": {"coordinates":[-105.038222,39.737098],"type":"Point"}
}