{
  "type": "Feature",
  "properties": {
    "addr:full":"775 S Newton St Denver CO 80219",
    "addr:housenumber":"775",
    "addr:postcode":"80219",
    "addr:street":"S Newton St",
    "iso:country":"US",
    "sg:address":"775 S Newton St",
    "sg:city":"Denver",
    "sg:classifiers":[
        {
            "category":"Organizations",
            "subcategory":"Religious Organization",
            "type":"Services"
        }
    ],
    "sg:phone":"+1 303 936 5386",
    "sg:postcode":"80219",
    "sg:province":"CO",
    "wof:name":"St Anthony Of Padua Rel Ed",
    "wof:placetype":"venue"
},
  "geometry": {"coordinates":[-105.036845,39.702617],"type":"Point"}
}