{
  "type": "Feature",
  "properties": {
    "addr:full":"4805 Catalina Dr Fort Collins CO 80526",
    "addr:housenumber":"4805",
    "addr:postcode":"80526",
    "addr:street":"Catalina Dr",
    "iso:country":"US",
    "sg:address":"4805 Catalina Dr",
    "sg:city":"Fort Collins",
    "sg:classifiers":[
        {
            "category":"Building & Trades",
            "subcategory":"Construction",
            "type":"Services"
        }
    ],
    "sg:phone":"+1 970 226 4773",
    "sg:postcode":"80526",
    "sg:province":"CO",
    "sg:tags":[
        "home",
        "remodeling",
        "family"
    ],
    "wof:name":"Dons Welding",
    "wof:placetype":"venue"
},
  "geometry": {"coordinates":[-105.16983,40.520012],"type":"Point"}
}