{
  "type": "Feature",
  "properties": {
    "iso:country":"US",
    "sg:address":"11103 E Alameda Ave",
    "sg:city":"Aurora",
    "sg:classifiers":[
        {
            "category":"Real Estate",
            "subcategory":"Real Estate Agent",
            "type":"Services"
        }
    ],
    "sg:phone":"+1 720 532 0425",
    "sg:postcode":"80012",
    "sg:province":"CO",
    "wof:name":"Mosley Appraisal",
    "wof:placetype":"venue"
},
  "geometry": {"coordinates":[-104.857816,39.711181],"type":"Point"}
}