{
  "type": "Feature",
  "properties": {
    "iso:country":"US",
    "sg:address":"7107 Lipan St",
    "sg:city":"Denver",
    "sg:classifiers":[
        {
            "category":"Professional",
            "type":"Services"
        }
    ],
    "sg:phone":"+1 303 429 7014",
    "sg:postcode":"80221",
    "sg:province":"CO",
    "wof:name":"Craig P Staudt",
    "wof:placetype":"venue"
},
  "geometry": {"coordinates":[-105.002021,39.825968],"type":"Point"}
}