{
  "type": "Feature",
  "properties": {
    "addr:full":"4921 Terry Lake Rd Fort Collins CO 80524",
    "addr:housenumber":"4921",
    "addr:postcode":"80524",
    "addr:street":"Terry Lake Rd",
    "iso:country":"US",
    "sg:address":"4921 Terry Lake Rd",
    "sg:city":"Fort Collins",
    "sg:classifiers":[
        {
            "category":"Shopping",
            "subcategory":"Computers & Home Electronics",
            "type":"Retail Goods"
        }
    ],
    "sg:phone":"+1 970 493 9345",
    "sg:postcode":"80524",
    "sg:province":"CO",
    "sg:tags":[
        "software"
    ],
    "wof:name":"CBAS Co",
    "wof:placetype":"venue"
},
  "geometry": {"coordinates":[-105.070493,40.660929],"type":"Point"}
}