{
  "type": "Feature",
  "properties": {
    "iso:country":"US",
    "sg:address":"980 Cowen Dr",
    "sg:city":"Carbondale",
    "sg:classifiers":[
        {
            "category":"Restaurant",
            "type":"Food & Drink"
        }
    ],
    "sg:phone":"+1 970 963 0788",
    "sg:postcode":"81623",
    "sg:province":"CO",
    "wof:name":"Quiznos Sub",
    "wof:placetype":"venue"
},
  "geometry": {"coordinates":[-107.219086,39.41326],"type":"Point"}
}