{
  "type": "Feature",
  "properties": {
    "iso:country":"US",
    "sg:address":"307 S Cleveland Ave",
    "sg:city":"Loveland",
    "sg:classifiers":[
        {
            "category":"Manufacturing",
            "subcategory":"Retail Goods",
            "type":"Manufacturing & Wholesale Goods"
        }
    ],
    "sg:phone":"+1 970 635 9150",
    "sg:postcode":"80537",
    "sg:province":"CO",
    "sg:tags":[
        "assembly",
        "fabricating"
    ],
    "wof:name":"Save Electronics",
    "wof:placetype":"venue"
},
  "geometry": {"coordinates":[-105.074676,40.389761],"type":"Point"}
}