{
  "type": "Feature",
  "properties": {
    "iso:country":"US",
    "sg:address":"14825 US Hwy 285",
    "sg:city":"Salida",
    "sg:classifiers":[
        {
            "category":"Recreation",
            "type":"Entertainment"
        }
    ],
    "sg:phone":"+1 719 530 0937",
    "sg:postcode":"81201",
    "sg:province":"CO",
    "sg:tags":[
        "water",
        "white",
        "river",
        "rafting"
    ],
    "sg:website":"www.weraft.com",
    "wof:name":"Whitewater Encounters",
    "wof:placetype":"venue"
},
  "geometry": {"coordinates":[-106.081985,38.63792],"type":"Point"}
}