{
  "type": "Feature",
  "properties": {
    "iso:country":"US",
    "sg:address":"3396 S Downing St",
    "sg:city":"Englewood",
    "sg:classifiers":[
        {
            "category":"Manufacturing",
            "subcategory":"Retail Goods",
            "type":"Manufacturing & Wholesale Goods"
        }
    ],
    "sg:phone":"+1 720 570 2896",
    "sg:postcode":"80113",
    "sg:province":"CO",
    "sg:tags":[
        "product",
        "mfg"
    ],
    "wof:name":"Alan Ksionek Industries",
    "wof:placetype":"venue"
},
  "geometry": {"coordinates":[-104.973429,39.65675],"type":"Point"}
}