{
  "type": "Feature",
  "properties": {
    "iso:country":"US",
    "sg:address":"1165 E Tidy Dr",
    "sg:city":"Pueblo West",
    "sg:classifiers":[
        {
            "category":"Home & Garden",
            "subcategory":"Building Materials",
            "type":"Retail Goods"
        }
    ],
    "sg:phone":"+1 719 568 3113",
    "sg:postcode":"81007",
    "sg:province":"CO",
    "sg:tags":[
        "glass",
        "window",
        "plate"
    ],
    "wof:name":"Bullseye Windshield Repair",
    "wof:placetype":"venue"
},
  "geometry": {"coordinates":[-104.683988,38.352403],"type":"Point"}
}