{
  "type": "Feature",
  "properties": {
    "addr:full":"8055 W Bowles Ave Littleton CO 80123",
    "addr:housenumber":"8055",
    "addr:postcode":"80123",
    "addr:street":"W Bowles Ave",
    "iso:country":"US",
    "sg:address":"8055 W Bowles Ave",
    "sg:city":"Littleton",
    "sg:classifiers":[
        {
            "category":"Banks & Credit Unions",
            "subcategory":"Bank",
            "type":"Services"
        }
    ],
    "sg:phone":"+1 303 933 1323",
    "sg:postcode":"80123",
    "sg:province":"CO",
    "sg:tags":[
        "personal",
        "institution"
    ],
    "wof:name":"Wells Fargo",
    "wof:placetype":"venue"
},
  "geometry": {"coordinates":[-105.088719,39.609797],"type":"Point"}
}