{
  "type": "Feature",
  "properties": {
    "iso:country":"US",
    "sg:address":"110 Turner Ave",
    "sg:city":"Berthoud",
    "sg:classifiers":[
        {
            "category":"Manufacturing",
            "subcategory":"Metals",
            "type":"Manufacturing & Wholesale Goods"
        }
    ],
    "sg:phone":"+1 970 532 4201",
    "sg:postcode":"80513",
    "sg:province":"CO",
    "sg:tags":[
        "foundry",
        "bronze"
    ],
    "wof:name":"Madd Castings Inc",
    "wof:placetype":"venue"
},
  "geometry": {"coordinates":[-105.074377,40.307528],"type":"Point"}
}