{
  "type": "Feature",
  "properties": {
    "addr:full":"787 W Hemlock Cir Louisville CO 80027",
    "addr:housenumber":"787",
    "addr:postcode":"80027",
    "addr:street":"W Hemlock Cir",
    "iso:country":"US",
    "sg:address":"787 W Hemlock Cir",
    "sg:city":"Louisville",
    "sg:classifiers":[
        {
            "category":"Manufacturing",
            "subcategory":"Chemicals & Compounds",
            "type":"Manufacturing & Wholesale Goods"
        }
    ],
    "sg:phone":"+1 303 604 0527",
    "sg:postcode":"80027",
    "sg:province":"CO",
    "sg:tags":[
        "preparation",
        "pharmaceutical",
        "mfg"
    ],
    "wof:name":"Whitehead & Assoc",
    "wof:placetype":"venue"
},
  "geometry": {"coordinates":[-105.154989,39.972923],"type":"Point"}
}