{
  "type": "Feature",
  "properties": {
    "iso:country":"US",
    "sg:address":"31 Duroux Ln",
    "sg:city":"Basalt",
    "sg:classifiers":[
        {
            "category":"Government",
            "subcategory":"Office",
            "type":"Public Place"
        }
    ],
    "sg:phone":"+1 970 927 4077",
    "sg:postcode":"81621",
    "sg:province":"CO",
    "sg:tags":[
        "administrator"
    ],
    "wof:name":"Mid-Valley Metropolitain Dst",
    "wof:placetype":"venue"
},
  "geometry": {"coordinates":[-107.082734,39.373757],"type":"Point"}
}