{
  "type": "Feature",
  "properties": {
    "addr:full":"3621 W 73rd Ave Westminster CO 80030",
    "addr:housenumber":"3621",
    "addr:postcode":"80030",
    "addr:street":"W 73Rd Ave",
    "iso:country":"US",
    "sg:address":"3621 W 73rd Ave",
    "sg:city":"Westminster",
    "sg:classifiers":[
        {
            "category":"Organizations",
            "subcategory":"Non-profit Organization",
            "type":"Services"
        }
    ],
    "sg:phone":"+1 303 428 5264",
    "sg:postcode":"80030",
    "sg:province":"CO",
    "sg:tags":[
        "information",
        "alcoholism",
        "treatment"
    ],
    "wof:name":"TASC Northeast",
    "wof:placetype":"venue"
},
  "geometry": {"coordinates":[-105.035112,39.829165],"type":"Point"}
}