{
  "type": "Feature",
  "properties": {
    "addr:full":"7700 S Glencoe Way Centennial CO 80122",
    "addr:housenumber":"7700",
    "addr:postcode":"80122",
    "addr:street":"S Glencoe Way",
    "iso:country":"US",
    "sg:address":"7700 S Glencoe Way",
    "sg:city":"Centennial",
    "sg:classifiers":[
        {
            "category":"Professional",
            "subcategory":"Employment Agencies",
            "type":"Services"
        }
    ],
    "sg:phone":"+1 303 721 6644",
    "sg:postcode":"80122",
    "sg:province":"CO",
    "sg:tags":[
        "consultant",
        "search",
        "executive",
        "equipment"
    ],
    "wof:name":"Don V Poole & Associates Inc",
    "wof:placetype":"venue"
},
  "geometry": {"coordinates":[-104.927009,39.57651],"type":"Point"}
}