{
  "type": "Feature",
  "properties": {
    "iso:country":"US",
    "sg:address":"151 S Syracuse St",
    "sg:city":"Denver",
    "sg:classifiers":[
        {
            "category":"Building & Trades",
            "subcategory":"Construction",
            "type":"Services"
        }
    ],
    "sg:phone":"+1 303 360 7012",
    "sg:postcode":"80230",
    "sg:province":"CO",
    "sg:tags":[
        "home",
        "builder"
    ],
    "wof:name":"Standard Pacific Homes",
    "wof:placetype":"venue"
},
  "geometry": {"coordinates":[-104.898585,39.712975],"type":"Point"}
}