{
  "type": "Feature",
  "properties": {
    "iso:country":"US",
    "sg:address":"410 E 104th Ave",
    "sg:city":"Denver",
    "sg:classifiers":[
        {
            "category":"Autos & Motor Vehicles",
            "subcategory":"Fuel & Gas Station",
            "type":"Retail Goods"
        }
    ],
    "sg:phone":"+1 303 452 4531",
    "sg:postcode":"80233",
    "sg:province":"CO",
    "sg:tags":[
        "station",
        "gasoline"
    ],
    "wof:name":"Total 2363",
    "wof:placetype":"venue"
},
  "geometry": {"coordinates":[-104.97817999999999,39.884977],"type":"Point"}
}