{
  "type": "Feature",
  "properties": {
    "iso:country":"US",
    "sg:address":"855 Weaver Park Rd",
    "sg:city":"Longmont",
    "sg:classifiers":[
        {
            "category":"Retail",
            "subcategory":"Auto Repair",
            "type":"Services"
        }
    ],
    "sg:phone":"+1 303 776 1148",
    "sg:postcode":"80501",
    "sg:province":"CO",
    "sg:tags":[
        "repairing",
        "automobile"
    ],
    "wof:name":"4wd Xtreme",
    "wof:placetype":"venue"
},
  "geometry": {"coordinates":[-105.07749099999999,40.162079],"type":"Point"}
}