{
  "type": "Feature",
  "properties": {
    "iso:country":"US",
    "sg:address":"316 W 5th St",
    "sg:city":"Ordway",
    "sg:classifiers":[
        {
            "category":"Government",
            "subcategory":"Office",
            "type":"Public Place"
        }
    ],
    "sg:phone":"+1 719 743 2451",
    "sg:postcode":"81063",
    "sg:province":"CO",
    "sg:tags":[
        "federal"
    ],
    "wof:name":"US Consolidated Farm Svc Agcy",
    "wof:placetype":"venue"
},
  "geometry": {"coordinates":[-103.760462,38.220372],"type":"Point"}
}