{
  "type": "Feature",
  "properties": {
    "addr:full":"5233 W 9th St Greeley CO 80634",
    "addr:housenumber":"5233",
    "addr:postcode":"80634",
    "addr:street":"W 9Th St",
    "iso:country":"US",
    "sg:address":"5233 W 9th St",
    "sg:city":"Greeley",
    "sg:classifiers":[
        {
            "category":"Professional",
            "type":"Services"
        }
    ],
    "sg:phone":"+1 970 352 5693",
    "sg:postcode":"80634",
    "sg:province":"CO",
    "wof:name":"Aleta S Wagner Lowe",
    "wof:placetype":"venue"
},
  "geometry": {"coordinates":[-104.76704700000001,40.424156],"type":"Point"}
}