{
  "type": "Feature",
  "properties": {
    "iso:country":"US",
    "sg:address":"475 Millstream Ter",
    "sg:city":"Colorado Springs",
    "sg:classifiers":[
        {
            "category":"Home & Garden",
            "subcategory":"Building Materials",
            "type":"Retail Goods"
        }
    ],
    "sg:phone":"+1 719 630 8950",
    "sg:postcode":"80904",
    "sg:province":"CO",
    "wof:name":"Elliott Sales",
    "wof:placetype":"venue"
},
  "geometry": {"coordinates":[-104.855643,38.825303],"type":"Point"}
}