{
  "type": "Feature",
  "properties": {
    "addr:full":"5663 S Prince St Littleton CO 80120",
    "addr:housenumber":"5663",
    "addr:postcode":"80120",
    "addr:street":"S Prince St",
    "iso:country":"US",
    "sg:address":"5663 S Prince St",
    "sg:city":"Littleton",
    "sg:classifiers":[
        {
            "category":"Arts & Performance",
            "subcategory":"Theater",
            "type":"Entertainment"
        }
    ],
    "sg:phone":"+1 303 795 5006",
    "sg:postcode":"80120",
    "sg:province":"CO",
    "sg:tags":[
        "decoration",
        "e",
        "for",
        "special"
    ],
    "wof:name":"Reinke Bros Inc",
    "wof:placetype":"venue"
},
  "geometry": {"coordinates":[-105.016263,39.614722],"type":"Point"}
}