{
  "type": "Feature",
  "properties": {
    "addr:full":"6535 S Dayton St Greenwood Vlg CO 80111",
    "addr:housenumber":"6535",
    "addr:postcode":"co 80111",
    "addr:street":"S Dayton St",
    "iso:country":"US",
    "sg:address":"6535 S Dayton St",
    "sg:city":"Greenwood Vlg",
    "sg:classifiers":[
        {
            "category":"Professional",
            "type":"Services"
        }
    ],
    "sg:phone":"+1 303 790 9050",
    "sg:postcode":"80111",
    "sg:province":"CO",
    "sg:tags":[
        "establishment"
    ],
    "wof:name":"Cornell & Assoc",
    "wof:placetype":"venue"
},
  "geometry": {"coordinates":[-104.876287,39.595656],"type":"Point"}
}