{
  "type": "Feature",
  "properties": {
    "addr:full":"1220 33rd Ln Pueblo CO 81006",
    "addr:housenumber":"1220",
    "addr:postcode":"81006",
    "addr:street":"33Rd Ln",
    "iso:country":"US",
    "sg:address":"1220 33rd Ln",
    "sg:city":"Pueblo",
    "sg:classifiers":[
        {
            "category":"Building & Trades",
            "subcategory":"Construction",
            "type":"Services"
        }
    ],
    "sg:phone":"+1 719 948 9064",
    "sg:postcode":"81006",
    "sg:province":"CO",
    "sg:tags":[
        "wallpaper"
    ],
    "wof:name":"Potter's Papering Svc",
    "wof:placetype":"venue"
},
  "geometry": {"coordinates":[-104.482314,38.238485],"type":"Point"}
}