{
  "type": "Feature",
  "properties": {
    "iso:country":"US",
    "sg:address":"920 W 29th St",
    "sg:city":"Loveland",
    "sg:classifiers":[
        {
            "category":"Education",
            "subcategory":"School",
            "type":"Public Place"
        }
    ],
    "sg:phone":"+1 970 613 5200",
    "sg:postcode":"80538",
    "sg:province":"CO",
    "sg:tags":[
        "high"
    ],
    "wof:name":"Loveland High School",
    "wof:placetype":"venue"
},
  "geometry": {"coordinates":[-105.090619,40.421617],"type":"Point"}
}