{
  "type": "Feature",
  "properties": {
    "addr:full":"3130 S Parker Rd Aurora CO 80014",
    "addr:housenumber":"3130",
    "addr:postcode":"80014",
    "addr:street":"S Parker Rd",
    "iso:country":"US",
    "sg:address":"3130 S Parker Rd",
    "sg:city":"Aurora",
    "sg:classifiers":[
        {
            "category":"Retail",
            "subcategory":"Auto Repair",
            "type":"Services"
        }
    ],
    "sg:phone":"+1 720 309 3154",
    "sg:postcode":"80014",
    "sg:province":"CO",
    "sg:tags":[
        "body",
        "automobile",
        "painting"
    ],
    "wof:name":"Gemini Bodyworks",
    "wof:placetype":"venue"
},
  "geometry": {"coordinates":[-104.850335,39.659611],"type":"Point"}
}