{
  "type": "Feature",
  "properties": {
    "iso:country":"US",
    "sg:address":"2825 3rd St",
    "sg:city":"Boulder",
    "sg:classifiers":[
        {
            "category":"Manufacturing",
            "subcategory":"Motor Vehicles & Parts",
            "type":"Manufacturing & Wholesale Goods"
        }
    ],
    "sg:phone":"+1 720 564 1128",
    "sg:postcode":"80304",
    "sg:province":"CO",
    "sg:tags":[
        "mfg"
    ],
    "wof:name":"Boylan Enterprises LLC",
    "wof:placetype":"venue"
},
  "geometry": {"coordinates":[-105.29274100000001,40.027187],"type":"Point"}
}