{
  "type": "Feature",
  "properties": {
    "iso:country":"US",
    "sg:address":"15232 E Hampden Ave",
    "sg:city":"Aurora",
    "sg:classifiers":[
        {
            "category":"Shopping",
            "type":"Retail Goods"
        }
    ],
    "sg:phone":"+1 303 870 3199",
    "sg:postcode":"80014",
    "sg:province":"CO",
    "sg:tags":[
        "trophy",
        "medal",
        "award"
    ],
    "wof:name":"Awards Shoppe Inc",
    "wof:placetype":"venue"
},
  "geometry": {"coordinates":[-104.811809,39.653009],"type":"Point"}
}