{
  "type": "Feature",
  "properties": {
    "addr:full":"6455 Federal Blvd Denver CO 80221",
    "addr:housenumber":"6455",
    "addr:postcode":"80221",
    "addr:street":"Federal Blvd",
    "iso:country":"US",
    "sg:address":"6455 Federal Blvd",
    "sg:city":"Denver",
    "sg:classifiers":[
        {
            "category":"Travel",
            "subcategory":"Hotels & Motels",
            "type":"Entertainment"
        }
    ],
    "sg:phone":"+1 720 540 8359",
    "sg:postcode":"80221",
    "sg:province":"CO",
    "wof:name":"Sunrise Cottages Motel",
    "wof:placetype":"venue"
},
  "geometry": {"coordinates":[-105.02543900000001,39.81382],"type":"Point"}
}