{
  "type": "Feature",
  "properties": {
    "iso:country":"US",
    "sg:address":"417 E Eisenhower Blvd",
    "sg:city":"Loveland",
    "sg:classifiers":[
        {
            "category":"Travel",
            "subcategory":"Hotels & Motels",
            "type":"Entertainment"
        }
    ],
    "sg:phone":"+1 970 667 6486",
    "sg:postcode":"80537",
    "sg:province":"CO",
    "wof:name":"Gateway Motel",
    "wof:placetype":"venue"
},
  "geometry": {"coordinates":[-105.07155899999999,40.407308],"type":"Point"}
}