{
  "type": "Feature",
  "properties": {
    "addr:full":"448 S Link Ln Fort Collins CO 80524",
    "addr:housenumber":"448",
    "addr:postcode":"80524",
    "addr:street":"S Link Ln",
    "iso:country":"US",
    "sg:address":"448 S Link Ln",
    "sg:city":"Fort Collins",
    "sg:classifiers":[
        {
            "category":"Manufacturing",
            "subcategory":"Printing",
            "type":"Manufacturing & Wholesale Goods"
        }
    ],
    "sg:phone":"+1 970 419 8418",
    "sg:postcode":"80524",
    "sg:province":"CO",
    "sg:tags":[
        "screen"
    ],
    "wof:name":"Purple Mountain Prints",
    "wof:placetype":"venue"
},
  "geometry": {"coordinates":[-105.050124,40.582486],"type":"Point"}
}