{
  "type": "Feature",
  "properties": {
    "iso:country":"US",
    "sg:address":"100 Arapahoe Ave",
    "sg:city":"Boulder",
    "sg:classifiers":[
        {
            "category":"Professional",
            "subcategory":"Research",
            "type":"Services"
        }
    ],
    "sg:phone":"+1 303 443 5300",
    "sg:postcode":"80302",
    "sg:province":"CO",
    "sg:tags":[
        "market",
        "analysis"
    ],
    "wof:name":"TALMEY Drake",
    "wof:placetype":"venue"
},
  "geometry": {"coordinates":[-105.292877,40.01301],"type":"Point"}
}