{
  "type": "Feature",
  "properties": {
    "iso:country":"US",
    "sg:address":"420 E 57th St",
    "sg:city":"Loveland",
    "sg:classifiers":[
        {
            "category":"Real Estate",
            "subcategory":"Real Estate Operator",
            "type":"Services"
        }
    ],
    "sg:phone":"+1 970 669 1565",
    "sg:postcode":"80538",
    "sg:province":"CO",
    "sg:tags":[
        "mobile",
        "residential",
        "park",
        "home"
    ],
    "wof:name":"Lago Vista Mobile Home Park",
    "wof:placetype":"venue"
},
  "geometry": {"coordinates":[-105.07360799999999,40.450994],"type":"Point"}
}