{
  "type": "Feature",
  "properties": {
    "iso:country":"US",
    "sg:address":"1173 S Bellaire St",
    "sg:city":"Denver",
    "sg:classifiers":[
        {
            "category":"Mining & Drilling",
            "type":"Manufacturing & Wholesale Goods"
        }
    ],
    "sg:phone":"+1 303 861 2228",
    "sg:postcode":"80246",
    "sg:province":"CO",
    "sg:tags":[
        "crude",
        "gas",
        "production",
        "well"
    ],
    "wof:name":"Allison Drilling Company Inc",
    "wof:placetype":"venue"
},
  "geometry": {"coordinates":[-104.93738,39.696128],"type":"Point"}
}