{
  "type": "Feature",
  "properties": {
    "addr:full":"10720 Bradford Rd Littleton CO 80127",
    "addr:housenumber":"10720",
    "addr:postcode":"80127",
    "addr:street":"Bradford Rd",
    "iso:country":"US",
    "sg:address":"10720 Bradford Rd",
    "sg:city":"Littleton",
    "sg:classifiers":[
        {
            "category":"Wholesale",
            "subcategory":"Electrical",
            "type":"Manufacturing & Wholesale Goods"
        }
    ],
    "sg:phone":"+1 720 922 8303",
    "sg:postcode":"80127",
    "sg:province":"CO",
    "sg:tags":[
        "control",
        "security",
        "system"
    ],
    "wof:name":"Edelman Corp",
    "wof:placetype":"venue"
},
  "geometry": {"coordinates":[-105.11893999999999,39.568681],"type":"Point"}
}