{
  "type": "Feature",
  "properties": {
    "iso:country":"US",
    "sg:address":"106 2nd St",
    "sg:city":"Monument",
    "sg:classifiers":[
        {
            "category":"Personal",
            "subcategory":"Beauty Salon",
            "type":"Services"
        }
    ],
    "sg:phone":"+1 719 487 7366",
    "sg:postcode":"80132",
    "sg:province":"CO",
    "wof:name":"Attitudes",
    "wof:placetype":"venue"
},
  "geometry": {"coordinates":[-104.87257200000001,39.091429],"type":"Point"}
}