{
  "type": "Feature",
  "properties": {
    "addr:full":"19263 E US Highway 24 Woodland Park CO 80863",
    "addr:housenumber":"19263",
    "addr:postcode":"80863",
    "addr:street":"E Us Highway 24;Park",
    "iso:country":"US",
    "sg:address":"19263 E US Highway 24",
    "sg:city":"Woodland Park",
    "sg:classifiers":[
        {
            "category":"Travel",
            "subcategory":"Hotels & Motels",
            "type":"Entertainment"
        },
        {
            "category":"Restaurant",
            "type":"Food & Drink"
        },
        {
            "category":"Travel",
            "subcategory":"Bed & Breakfast",
            "type":"Entertainment"
        }
    ],
    "sg:phone":"+1 719 687 2001",
    "sg:postcode":"80863",
    "sg:province":"CO",
    "sg:website":"www.swisschaletofwoodlandpark.com",
    "wof:name":"Swiss Chalet",
    "wof:placetype":"venue"
},
  "geometry": {"coordinates":[-105.028999,38.960899],"type":"Point"}
}