{
  "type": "Feature",
  "properties": {
    "addr:full":"1601 Northwestern Rd Longmont CO 80503",
    "addr:housenumber":"1601",
    "addr:postcode":"80503",
    "addr:street":"Northwestern Rd",
    "iso:country":"US",
    "sg:address":"1601 Northwestern Rd",
    "sg:city":"Longmont",
    "sg:classifiers":[
        {
            "category":"Education",
            "subcategory":"School",
            "type":"Public Place"
        }
    ],
    "sg:phone":"+1 720 652 8101",
    "sg:postcode":"80503",
    "sg:province":"CO",
    "wof:name":"Longmont Estates Elementary",
    "wof:placetype":"venue"
},
  "geometry": {"coordinates":[-105.148104,40.18614],"type":"Point"}
}