{
  "type": "Feature",
  "properties": {
    "iso:country":"US",
    "sg:address":"2150 W 6th Ave",
    "sg:city":"Broomfield",
    "sg:classifiers":[
        {
            "category":"Professional",
            "subcategory":"Testing Lab",
            "type":"Services"
        },
        {
            "category":"Health Services",
            "subcategory":"Medical Lab",
            "type":"Services"
        }
    ],
    "sg:phone":"+1 303 469 8042",
    "sg:postcode":"80020",
    "sg:province":"CO",
    "sg:tags":[
        "analytical",
        "laboratory"
    ],
    "wof:name":"Forensic Laboratories Inc",
    "wof:placetype":"venue"
},
  "geometry": {"coordinates":[-105.096543,39.927241],"type":"Point"}
}