{
  "type": "Feature",
  "properties": {
    "iso:country":"US",
    "sg:address":"5660 Greenwood Plaza Blvd",
    "sg:city":"Englewood",
    "sg:classifiers":[
        {
            "category":"Education",
            "subcategory":"Junior College",
            "type":"Public Place"
        },
        {
            "category":"Education",
            "subcategory":"College",
            "type":"Public Place"
        }
    ],
    "sg:phone":"+1 303 734 3701",
    "sg:postcode":"80111",
    "sg:province":"CO",
    "sg:tags":[
        "academic",
        "school"
    ],
    "wof:name":"Arapahoe Community College",
    "wof:placetype":"venue"
},
  "geometry": {"coordinates":[-104.89876,39.614087],"type":"Point"}
}