{
  "type": "Feature",
  "properties": {
    "iso:country":"US",
    "sg:address":"8561 S Ammons St",
    "sg:city":"Littleton",
    "sg:classifiers":[
        {
            "category":"Freight",
            "type":"Transportation"
        },
        {
            "category":"Building & Trades",
            "subcategory":"Construction",
            "type":"Services"
        }
    ],
    "sg:phone":"+1 303 932 0632",
    "sg:postcode":"80128",
    "sg:province":"CO",
    "sg:tags":[
        "heavy",
        "excavating",
        "excavation",
        "local",
        "hauling",
        "contract",
        "contractor",
        "demolition"
    ],
    "wof:name":"Berry Trucking and Excavating",
    "wof:placetype":"venue"
},
  "geometry": {"coordinates":[-105.089229,39.559648],"type":"Point"}
}