{
  "type": "Feature",
  "properties": {
    "addr:full":"6492 Orion Ln Arvada CO 80007",
    "addr:housenumber":"6492",
    "addr:postcode":"80007",
    "addr:street":"Orion Ln",
    "iso:country":"US",
    "sg:address":"6492 Orion Ln",
    "sg:city":"Arvada",
    "sg:classifiers":[
        {
            "category":"Building & Trades",
            "subcategory":"Construction",
            "type":"Services"
        }
    ],
    "sg:phone":"+1 303 431 7465",
    "sg:postcode":"80007",
    "sg:province":"CO",
    "sg:tags":[
        "roofing",
        "contractor"
    ],
    "wof:name":"ARC Roofing Inc",
    "wof:placetype":"venue"
},
  "geometry": {"coordinates":[-105.18083900000001,39.814732],"type":"Point"}
}