{
  "type": "Feature",
  "properties": {
    "addr:full":"7105 W Colfax Ave Lakewood CO 80214",
    "addr:housenumber":"7105",
    "addr:postcode":"80214",
    "addr:street":"W Colfax Ave",
    "iso:country":"US",
    "sg:address":"7105 W Colfax Ave",
    "sg:city":"Lakewood",
    "sg:classifiers":[
        {
            "category":"Professional",
            "subcategory":"Business Services",
            "type":"Services"
        }
    ],
    "sg:phone":"+1 303 231 9337",
    "sg:postcode":"80214",
    "sg:province":"CO",
    "sg:tags":[
        "telemarketing"
    ],
    "wof:name":"Lupus Foundation Pick Up Svc",
    "wof:placetype":"venue"
},
  "geometry": {"coordinates":[-105.076633,39.740403],"type":"Point"}
}