{
  "type": "Feature",
  "properties": {
    "iso:country":"US",
    "sg:address":"1040 36th St",
    "sg:city":"Evans",
    "sg:classifiers":[
        {
            "category":"Building & Trades",
            "subcategory":"Plumbing",
            "type":"Services"
        }
    ],
    "sg:phone":"+1 970 330 2216",
    "sg:postcode":"80620",
    "sg:province":"CO",
    "sg:tags":[
        "plumbing",
        "contractor"
    ],
    "wof:name":"Corman Mechanical Contractors",
    "wof:placetype":"venue"
},
  "geometry": {"coordinates":[-104.69564800000001,40.378755],"type":"Point"}
}