{
  "type": "Feature",
  "properties": {
    "addr:full":"719 Picket Ln Longmont CO 80501",
    "addr:housenumber":"719",
    "addr:postcode":"80501",
    "addr:street":"Picket Ln",
    "iso:country":"US",
    "sg:address":"719 Picket Ln",
    "sg:city":"Longmont",
    "sg:classifiers":[
        {
            "category":"Building & Trades",
            "subcategory":"Electrical",
            "type":"Services"
        }
    ],
    "sg:phone":"+1 720 366 4211",
    "sg:postcode":"80501",
    "sg:province":"CO",
    "sg:tags":[
        "electrical",
        "contractor"
    ],
    "wof:name":"Professional SEC Solutions",
    "wof:placetype":"venue"
},
  "geometry": {"coordinates":[-105.077299,40.18637],"type":"Point"}
}