{
  "type": "Feature",
  "properties": {
    "iso:country":"US",
    "sg:address":"1651 S Vaughn St",
    "sg:city":"Aurora",
    "sg:classifiers":[
        {
            "category":"Building & Trades",
            "subcategory":"Construction",
            "type":"Services"
        }
    ],
    "sg:phone":"+1 303 523 4974",
    "sg:postcode":"80012",
    "sg:province":"CO",
    "sg:tags":[
        "contractor"
    ],
    "wof:name":"Ston Throw Construction Inc",
    "wof:placetype":"venue"
},
  "geometry": {"coordinates":[-104.836095,39.685302],"type":"Point"}
}