{
  "type": "Feature",
  "properties": {
    "iso:country":"US",
    "sg:address":"2594 S Colorado Boulevard",
    "sg:city":"Denver",
    "sg:classifiers":[
        {
            "category":"Shopping",
            "subcategory":"Shoes",
            "type":"Retail Goods"
        }
    ],
    "sg:phone":"+1 303 756 5500",
    "sg:postcode":"80222",
    "sg:province":"CO",
    "sg:tags":[
        "store"
    ],
    "wof:name":"Phelps Shoe Service",
    "wof:placetype":"venue"
},
  "geometry": {"coordinates":[-104.940561,39.669838],"type":"Point"}
}