{
  "type": "Feature",
  "properties": {
    "iso:country":"US",
    "sg:address":"960 S I- 25",
    "sg:city":"Castle Rock",
    "sg:classifiers":[
        {
            "category":"Professional",
            "subcategory":"Accounting & Tax Preparation",
            "type":"Services"
        }
    ],
    "sg:phone":"+1 720 733 0944",
    "sg:postcode":"80104",
    "sg:province":"CO",
    "sg:tags":[
        "accountant"
    ],
    "wof:name":"Omni Health Care Assoc Inc",
    "wof:placetype":"venue"
},
  "geometry": {"coordinates":[-104.867599,39.359865],"type":"Point"}
}