{
  "type": "Feature",
  "properties": {
    "iso:country":"US",
    "sg:address":"6206 W 98th Dr",
    "sg:city":"Broomfield",
    "sg:classifiers":[
        {
            "category":"Shopping",
            "subcategory":"Optical Goods",
            "type":"Retail Goods"
        }
    ],
    "sg:phone":"+1 303 455 1393",
    "sg:postcode":"80021",
    "sg:province":"CO",
    "wof:name":"Specialty Eyewear Inc",
    "wof:placetype":"venue"
},
  "geometry": {"coordinates":[-105.067138,39.877589],"type":"Point"}
}