{
  "type": "Feature",
  "properties": {
    "addr:full":"17255 Co Rd 55 La Salle CO 80645",
    "addr:housenumber":"17255",
    "addr:postcode":"80645",
    "addr:street":"Co Rd 55",
    "iso:country":"US",
    "sg:address":"17255 Co Rd 55",
    "sg:city":"La Salle",
    "sg:classifiers":[
        {
            "category":"Farming",
            "subcategory":"Farm",
            "type":"Manufacturing & Wholesale Goods"
        }
    ],
    "sg:phone":"+1 970 284 7759",
    "sg:postcode":"80645",
    "sg:province":"CO",
    "sg:tags":[
        "crop",
        "general"
    ],
    "wof:name":"Larry Gittlein",
    "wof:placetype":"venue"
},
  "geometry": {"coordinates":[-104.54666400000001,40.24975],"type":"Point"}
}