{
  "type": "Feature",
  "properties": {
    "addr:full":"15302 Singletree Dr Mead CO 80542",
    "addr:housenumber":"15302",
    "addr:postcode":"80542",
    "addr:street":"Singletree Dr",
    "iso:country":"US",
    "sg:address":"15302 Singletree Dr",
    "sg:city":"Mead",
    "sg:classifiers":[
        {
            "category":"Professional",
            "type":"Services"
        }
    ],
    "sg:phone":"+1 970 535 9868",
    "sg:postcode":"80542",
    "sg:province":"CO",
    "wof:name":"Llr LLC",
    "wof:placetype":"venue"
},
  "geometry": {"coordinates":[-104.984132,40.219937],"type":"Point"}
}