{
  "type": "Feature",
  "properties": {
    "iso:country":"US",
    "sg:address":"2552 15th St SW",
    "sg:city":"Loveland",
    "sg:classifiers":[
        {
            "category":"Professional",
            "subcategory":"Accounting & Tax Preparation",
            "type":"Services"
        }
    ],
    "sg:phone":"+1 970 622 0803",
    "sg:postcode":"80537",
    "sg:province":"CO",
    "sg:tags":[
        "bookkeeping",
        "general"
    ],
    "wof:name":"M-R Sum Books Inc",
    "wof:placetype":"venue"
},
  "geometry": {"coordinates":[-105.110333,40.377134],"type":"Point"}
}