{
  "type": "Feature",
  "properties": {
    "addr:full":"750 E 71st Ave Denver CO 80229",
    "addr:housenumber":"750",
    "addr:postcode":"80229",
    "addr:street":"E 71St Ave",
    "iso:country":"US",
    "sg:address":"750 E 71st Ave",
    "sg:city":"Denver",
    "sg:classifiers":[
        {
            "category":"Retail",
            "subcategory":"Auto Repair",
            "type":"Services"
        }
    ],
    "sg:phone":"+1 303 286 1949",
    "sg:postcode":"80229",
    "sg:province":"CO",
    "sg:tags":[
        "general"
    ],
    "wof:name":"Western Union Supply",
    "wof:placetype":"venue"
},
  "geometry": {"coordinates":[-104.971464,39.825349],"type":"Point"}
}