{
  "type": "Feature",
  "properties": {
    "iso:country":"US",
    "sg:address":"877 Federal Blvd",
    "sg:city":"Denver",
    "sg:classifiers":[
        {
            "category":"Social Services",
            "type":"Services"
        }
    ],
    "sg:phone":"+1 303 825 1115",
    "sg:postcode":"80204",
    "sg:province":"CO",
    "wof:name":"John Inmann-Work & Family Cent",
    "wof:placetype":"venue"
},
  "geometry": {"coordinates":[-105.02523100000001,39.730708],"type":"Point"}
}