{
  "type": "Feature",
  "properties": {
    "iso:country":"US",
    "sg:address":"4585 Bobolink Dr",
    "sg:city":"Castle Rock",
    "sg:classifiers":[
        {
            "category":"Retail",
            "subcategory":"Portrait Studio",
            "type":"Services"
        }
    ],
    "sg:phone":"+1 303 688 0606",
    "sg:postcode":"80109",
    "sg:province":"CO",
    "sg:tags":[
        "photographer"
    ],
    "wof:name":"Jolene Saiz Photography",
    "wof:placetype":"venue"
},
  "geometry": {"coordinates":[-104.91309699999999,39.413159],"type":"Point"}
}