{
  "type": "Feature",
  "properties": {
    "addr:full":"12400 US Hwy 491 Cortez CO 81321",
    "addr:housenumber":"12400",
    "addr:postcode":"81321",
    "addr:street":"Us Hwy 491",
    "iso:country":"US",
    "sg:address":"12400 US Hwy 491",
    "sg:city":"Cortez",
    "sg:classifiers":[
        {
            "category":"Mining & Drilling",
            "type":"Manufacturing & Wholesale Goods"
        }
    ],
    "sg:phone":"+1 970 564 1103",
    "sg:postcode":"81321",
    "sg:province":"CO",
    "sg:tags":[
        "field",
        "oil"
    ],
    "wof:name":"J E Merit Constructors Inc",
    "wof:placetype":"venue"
},
  "geometry": {"coordinates":[-108.616085,37.392527],"type":"Point"}
}