{
  "type": "Feature",
  "properties": {
    "iso:country":"US",
    "sg:address":"4200 Jackson Street",
    "sg:city":"Denver",
    "sg:classifiers":[
        {
            "category":"Autos & Motor Vehicles",
            "subcategory":"Auto Supplies",
            "type":"Retail Goods"
        }
    ],
    "sg:phone":"+1 303 393 1166",
    "sg:postcode":"80216",
    "sg:province":"CO",
    "sg:tags":[
        "tire"
    ],
    "wof:name":"Goodyear Wholesale Tire Center",
    "wof:placetype":"venue"
},
  "geometry": {"coordinates":[-104.942829,39.774685],"type":"Point"}
}