{
  "type": "Feature",
  "properties": {
    "addr:full":"1611 Lashelle Way Colorado Springs CO 80906",
    "addr:housenumber":"1611",
    "addr:postcode":"80906",
    "addr:street":"Lashelle Way",
    "iso:country":"US",
    "sg:address":"1611 Lashelle Way",
    "sg:city":"Colorado Springs",
    "sg:classifiers":[
        {
            "category":"Cinema",
            "subcategory":"Movie Rental",
            "type":"Entertainment"
        }
    ],
    "sg:phone":"+1 719 538 9675",
    "sg:postcode":"80906",
    "sg:province":"CO",
    "sg:tags":[
        "leasing",
        "video",
        "disc",
        "tape"
    ],
    "wof:name":"Las Vegas Video Palace",
    "wof:placetype":"venue"
},
  "geometry": {"coordinates":[-104.797194,38.767265],"type":"Point"}
}