{
  "type": "Feature",
  "properties": {
    "iso:country":"US",
    "sg:address":"805 S Broadway St",
    "sg:city":"Boulder",
    "sg:classifiers":[
        {
            "category":"Health Services",
            "subcategory":"Chiropractor",
            "type":"Services"
        }
    ],
    "sg:phone":"+1 303 494 0944",
    "sg:postcode":"80305",
    "sg:province":"CO",
    "wof:name":"Boulder Sport & Spine",
    "wof:placetype":"venue"
},
  "geometry": {"coordinates":[-105.242188,39.976961],"type":"Point"}
}