{
  "type": "Feature",
  "properties": {
    "addr:full":"6500 S Broadway Littleton CO 80121",
    "addr:housenumber":"6500",
    "addr:postcode":"80121",
    "addr:street":"S Broadway",
    "iso:country":"US",
    "sg:address":"6500 S Broadway",
    "sg:city":"Littleton",
    "sg:classifiers":[
        {
            "category":"Retail",
            "subcategory":"Auto Repair",
            "type":"Services"
        }
    ],
    "sg:phone":"+1 303 797 3368",
    "sg:postcode":"80121",
    "sg:province":"CO",
    "sg:tags":[
        "body",
        "automobile",
        "painting"
    ],
    "sg:website":"www.dentwiz.com",
    "wof:name":"Dent Wizard",
    "wof:placetype":"venue"
},
  "geometry": {"coordinates":[-104.98819399999999,39.600851],"type":"Point"}
}