{
  "type": "Feature",
  "properties": {
    "iso:country":"US",
    "sg:address":"777 29th St",
    "sg:city":"Boulder",
    "sg:classifiers":[
        {
            "category":"Health Services",
            "subcategory":"Health Practitioner",
            "type":"Services"
        }
    ],
    "sg:phone":"+1 303 444 8655",
    "sg:postcode":"80303",
    "sg:province":"CO",
    "sg:tags":[
        "psychologist"
    ],
    "wof:name":"Multicultural Resources",
    "wof:placetype":"venue"
},
  "geometry": {"coordinates":[-105.25600799999999,40.000285],"type":"Point"}
}