{
  "type": "Feature",
  "properties": {
    "iso:country":"US",
    "sg:address":"3795 Paris St",
    "sg:city":"Denver",
    "sg:classifiers":[
        {
            "category":"Wholesale",
            "subcategory":"Machinery & Supplies",
            "type":"Manufacturing & Wholesale Goods"
        },
        {
            "category":"Wholesale",
            "subcategory":"Durable Goods & Equipment",
            "type":"Manufacturing & Wholesale Goods"
        }
    ],
    "sg:phone":"+1 303 373 5404",
    "sg:postcode":"80239",
    "sg:province":"CO",
    "sg:tags":[
        "industrial",
        "mfg",
        "rep",
        "heating",
        "representative",
        "plumbing",
        "manufacturer"
    ],
    "wof:name":"Mc Coy Sales Corporation",
    "wof:placetype":"venue"
},
  "geometry": {"coordinates":[-104.84868,39.768156],"type":"Point"}
}