{
  "type": "Feature",
  "properties": {
    "iso:country":"US",
    "sg:address":"7347 S Revere Pkwy",
    "sg:city":"Centennial",
    "sg:classifiers":[
        {
            "category":"Building & Trades",
            "subcategory":"Construction",
            "type":"Services"
        }
    ],
    "sg:phone":"+1 303 799 7755",
    "sg:postcode":"80112",
    "sg:province":"CO",
    "sg:tags":[
        "general",
        "contractor"
    ],
    "wof:name":"Spiral Development",
    "wof:placetype":"venue"
},
  "geometry": {"coordinates":[-104.841842,39.587096],"type":"Point"}
}