{
  "type": "Feature",
  "properties": {
    "iso:country":"US",
    "sg:address":"5801 W 44th Ave",
    "sg:city":"Denver",
    "sg:classifiers":[
        {
            "category":"Autos & Motor Vehicles",
            "subcategory":"Auto Supplies",
            "type":"Retail Goods"
        }
    ],
    "sg:phone":"+1 303 403 1110",
    "sg:postcode":"80212",
    "sg:province":"CO",
    "sg:tags":[
        "wheel",
        "cover"
    ],
    "wof:name":"Wilderness On Wheels Fndtn",
    "wof:placetype":"venue"
},
  "geometry": {"coordinates":[-105.061459,39.776607],"type":"Point"}
}