{
  "type": "Feature",
  "properties": {
    "addr:full":"711 Kimbark St Lafayette CO 80026",
    "addr:housenumber":"711",
    "addr:postcode":"80026",
    "addr:street":"Kimbark St",
    "iso:country":"US",
    "sg:address":"711 Kimbark St",
    "sg:city":"Lafayette",
    "sg:classifiers":[
        {
            "category":"Professional",
            "subcategory":"Computer Services",
            "type":"Services"
        }
    ],
    "sg:phone":"+1 303 665 5397",
    "sg:postcode":"80026",
    "sg:province":"CO",
    "sg:tags":[
        "repair"
    ],
    "wof:name":"Advanced Computing & Network",
    "wof:placetype":"venue"
},
  "geometry": {"coordinates":[-105.099053,39.99247],"type":"Point"}
}