{
  "type": "Feature",
  "properties": {
    "iso:country":"US",
    "sg:address":"717 Edison St",
    "sg:city":"Brush",
    "sg:classifiers":[
        {
            "category":"Travel",
            "subcategory":"Hotels & Motels",
            "type":"Entertainment"
        }
    ],
    "sg:phone":"+1 970 842 2736",
    "sg:postcode":"80723",
    "sg:province":"CO",
    "wof:name":"KOZY KORT Motel",
    "wof:placetype":"venue"
},
  "geometry": {"coordinates":[-103.627431,40.255308],"type":"Point"}
}