{
  "type": "Feature",
  "properties": {
    "iso:country":"US",
    "sg:address":"34500 Co Rd 13",
    "sg:city":"Elizabeth",
    "sg:classifiers":[
        {
            "category":"Education",
            "subcategory":"School",
            "type":"Public Place"
        }
    ],
    "sg:phone":"+1 303 646 1600",
    "sg:postcode":"80107",
    "sg:province":"CO",
    "wof:name":"Elizabeth School District",
    "wof:placetype":"venue"
},
  "geometry": {"coordinates":[-104.60664300000001,39.370874],"type":"Point"}
}