{
  "type": "Feature",
  "properties": {
    "iso:country":"US",
    "sg:address":"17140 Jones Rd",
    "sg:city":"Peyton",
    "sg:classifiers":[
        {
            "category":"Retail",
            "subcategory":"Animal Services",
            "type":"Services"
        }
    ],
    "sg:phone":"+1 719 683 4617",
    "sg:postcode":"80831",
    "sg:province":"CO",
    "sg:tags":[
        "pet"
    ],
    "wof:name":"Avondale Pet Care Ctr",
    "wof:placetype":"venue"
},
  "geometry": {"coordinates":[-104.51751899999999,38.896396],"type":"Point"}
}