{
  "type": "Feature",
  "properties": {
    "addr:full":"5707 Constitution Ave Colorado Springs CO 80915",
    "addr:housenumber":"5707",
    "addr:postcode":"80915",
    "addr:street":"Constitution Ave",
    "iso:country":"US",
    "sg:address":"5707 Constitution Ave",
    "sg:city":"Colorado Springs",
    "sg:classifiers":[
        {
            "category":"Building & Trades",
            "subcategory":"Construction",
            "type":"Services"
        }
    ],
    "sg:phone":"+1 719 550 9000",
    "sg:postcode":"80915",
    "sg:province":"CO",
    "sg:tags":[
        "home",
        "speculative",
        "builder"
    ],
    "wof:name":"Oxbow Co Ltd",
    "wof:placetype":"venue"
},
  "geometry": {"coordinates":[-104.72198400000001,38.871731],"type":"Point"}
}