{
  "type": "Feature",
  "properties": {
    "iso:country":"US",
    "sg:address":"2239 E Colfax Ave",
    "sg:city":"Denver",
    "sg:classifiers":[
        {
            "category":"Restaurant",
            "type":"Food & Drink"
        }
    ],
    "sg:phone":"+1 303 295 3999",
    "sg:postcode":"80206",
    "sg:province":"CO",
    "sg:tags":[
        "caterer"
    ],
    "wof:name":"5280 Catering",
    "wof:placetype":"venue"
},
  "geometry": {"coordinates":[-104.960205,39.740063],"type":"Point"}
}