{
  "type": "Feature",
  "properties": {
    "iso:country":"US",
    "sg:address":"1908 Orchard Pl",
    "sg:city":"Fort Collins",
    "sg:classifiers":[
        {
            "category":"Professional",
            "type":"Services"
        }
    ],
    "sg:phone":"+1 970 407 1560",
    "sg:postcode":"80521",
    "sg:province":"CO",
    "wof:name":"Force For Womens Sports Inc T",
    "wof:placetype":"venue"
},
  "geometry": {"coordinates":[-105.114885,40.578572],"type":"Point"}
}