{
  "type": "Feature",
  "properties": {
    "iso:country":"US",
    "sg:address":"12330 Country Meadows Dr",
    "sg:city":"Parker",
    "sg:classifiers":[
        {
            "category":"Building & Trades",
            "subcategory":"Construction",
            "type":"Services"
        }
    ],
    "sg:phone":"+1 303 471 2710",
    "sg:postcode":"80134",
    "sg:province":"CO",
    "sg:tags":[
        "contractor"
    ],
    "wof:name":"Denver Cedar Roofing Inc",
    "wof:placetype":"venue"
},
  "geometry": {"coordinates":[-104.76275800000001,39.499731],"type":"Point"}
}