{
  "type": "Feature",
  "properties": {
    "iso:country":"US",
    "sg:address":"840 South Ave",
    "sg:city":"Grand Junction",
    "sg:classifiers":[
        {
            "category":"Freight",
            "type":"Transportation"
        }
    ],
    "sg:phone":"+1 970 241 5363",
    "sg:postcode":"81501",
    "sg:province":"CO",
    "sg:tags":[
        "general"
    ],
    "wof:name":"A A A Storage",
    "wof:placetype":"venue"
},
  "geometry": {"coordinates":[-108.55829199999999,39.063495],"type":"Point"}
}