{
  "type": "Feature",
  "properties": {
    "addr:full":"4400 S Quebec St Denver CO 80237",
    "addr:housenumber":"4400",
    "addr:postcode":"80237",
    "addr:street":"S Quebec St",
    "iso:country":"US",
    "sg:address":"4400 S Quebec St",
    "sg:city":"Denver",
    "sg:classifiers":[
        {
            "category":"Professional",
            "subcategory":"Business Services",
            "type":"Services"
        }
    ],
    "sg:phone":"+1 303 740 6161",
    "sg:postcode":"80237",
    "sg:province":"CO",
    "sg:tags":[
        "handwriting",
        "expert"
    ],
    "wof:name":"Jeanette Farmer",
    "wof:placetype":"venue"
},
  "geometry": {"coordinates":[-104.903852,39.6371],"type":"Point"}
}