{
  "type": "Feature",
  "properties": {
    "iso:country":"US",
    "sg:address":"12508 Co Rd 43",
    "sg:city":"Hudson",
    "sg:phone":"+1 303 536 4892",
    "sg:postcode":"80642",
    "sg:province":"CO",
    "sg:tags":[
        "farm",
        "corn"
    ],
    "wof:name":"Roland Ditson Farm",
    "wof:placetype":"venue"
},
  "geometry": {"coordinates":[-104.65906099999999,40.175084],"type":"Point"}
}