{
  "type": "Feature",
  "properties": {
    "iso:country":"US",
    "sg:address":"1573 48th St",
    "sg:city":"Boulder",
    "sg:classifiers":[
        {
            "category":"Home & Garden",
            "subcategory":"Carpets & Floor Coverings",
            "type":"Retail Goods"
        }
    ],
    "sg:phone":"+1 303 444 2703",
    "sg:postcode":"80303",
    "sg:province":"CO",
    "sg:tags":[
        "dealer",
        "rug"
    ],
    "wof:name":"Affordable/Boulder Interiors",
    "wof:placetype":"venue"
},
  "geometry": {"coordinates":[-105.23479500000001,40.014669],"type":"Point"}
}