{
  "type": "Feature",
  "properties": {
    "iso:country":"US",
    "sg:address":"216 Co Rd 520",
    "sg:city":"Bayfield",
    "sg:classifiers":[
        {
            "category":"Professional",
            "type":"Services"
        }
    ],
    "sg:phone":"+1 970 884 2148",
    "sg:postcode":"81122",
    "sg:province":"CO",
    "wof:name":"Donald W Wickman",
    "wof:placetype":"venue"
},
  "geometry": {"coordinates":[-107.618545,37.19854],"type":"Point"}
}