{
  "type": "Feature",
  "properties": {
    "iso:country":"US",
    "sg:address":"3210 Wedgewood Dr",
    "sg:city":"Pueblo",
    "sg:classifiers":[
        {
            "category":"Health Services",
            "subcategory":"Doctor",
            "type":"Services"
        }
    ],
    "sg:phone":"+1 719 561 8115",
    "sg:postcode":"81005",
    "sg:province":"CO",
    "sg:tags":[
        "dentist"
    ],
    "wof:name":"Josefina Fitzgerald DDS",
    "wof:placetype":"venue"
},
  "geometry": {"coordinates":[-104.64832,38.241888],"type":"Point"}
}