{
  "type": "Feature",
  "properties": {
    "iso:country":"US",
    "sg:address":"302 2nd St",
    "sg:city":"Ouray",
    "sg:classifiers":[
        {
            "category":"Government",
            "subcategory":"Office",
            "type":"Public Place"
        }
    ],
    "sg:phone":"+1 970 325 4670",
    "sg:postcode":"81427",
    "sg:province":"CO",
    "wof:name":"Ouray County Public Hlth Dept",
    "wof:placetype":"venue"
},
  "geometry": {"coordinates":[-107.67292500000001,38.020608],"type":"Point"}
}