{
  "type": "Feature",
  "properties": {
    "iso:country":"US",
    "sg:address":"18300 E 28th Ave",
    "sg:city":"Aurora",
    "sg:classifiers":[
        {
            "category":"Freight",
            "type":"Transportation"
        }
    ],
    "sg:phone":"+1 720 858 7300",
    "sg:postcode":"80011",
    "sg:province":"CO",
    "sg:tags":[
        "arrangement"
    ],
    "wof:name":"Eagle Global Logistics",
    "wof:placetype":"venue"
},
  "geometry": {"coordinates":[-104.772892,39.756061],"type":"Point"}
}