{
  "type": "Feature",
  "properties": {
    "iso:country":"US",
    "sg:address":"722 N Co Rd 1 E",
    "sg:city":"Monte Vista",
    "sg:classifiers":[
        {
            "category":"Farming",
            "subcategory":"Livestock Farm",
            "type":"Manufacturing & Wholesale Goods"
        }
    ],
    "sg:phone":"+1 719 587 6914",
    "sg:postcode":"81144",
    "sg:province":"CO",
    "sg:tags":[
        "horse"
    ],
    "wof:name":"Ron Rivale",
    "wof:placetype":"venue"
},
  "geometry": {"coordinates":[-106.1306,37.560425],"type":"Point"}
}