{
  "type": "Feature",
  "properties": {
    "addr:full":"200 W Tomichi Ave Gunnison CO 81230",
    "addr:housenumber":"200",
    "addr:postcode":"81230",
    "addr:street":"W Tomichi Ave",
    "iso:country":"US",
    "sg:address":"200 W Tomichi Ave",
    "sg:city":"Gunnison",
    "sg:classifiers":[
        {
            "category":"Shopping",
            "subcategory":"Clothing, Apparel, & Fashions",
            "type":"Retail Goods"
        }
    ],
    "sg:phone":"+1 970 641 6566",
    "sg:postcode":"81230",
    "sg:province":"CO",
    "sg:tags":[
        "western"
    ],
    "wof:name":"Western World Inc",
    "wof:placetype":"venue"
},
  "geometry": {"coordinates":[-106.92886900000001,38.544396],"type":"Point"}
}