{
  "type": "Feature",
  "properties": {
    "addr:full":"215 S Marshall St Lakewood CO 80226",
    "addr:housenumber":"215",
    "addr:postcode":"80226",
    "addr:street":"S Marshall St",
    "iso:country":"US",
    "sg:address":"215 S Marshall St",
    "sg:city":"Lakewood",
    "sg:classifiers":[
        {
            "category":"Building & Trades",
            "subcategory":"Landscaping Services",
            "type":"Services"
        }
    ],
    "sg:phone":"+1 303 232 0940",
    "sg:postcode":"80226",
    "sg:province":"CO",
    "sg:tags":[
        "tree"
    ],
    "wof:name":"Maintenance Consultants",
    "wof:placetype":"venue"
},
  "geometry": {"coordinates":[-105.06837899999999,39.712704],"type":"Point"}
}