{
  "type": "Feature",
  "properties": {
    "iso:country":"US",
    "sg:address":"103 N Josephine Ave",
    "sg:city":"Milliken",
    "sg:classifiers":[
        {
            "category":"Freight",
            "type":"Transportation"
        }
    ],
    "sg:phone":"+1 970 371 4672",
    "sg:postcode":"80543",
    "sg:province":"CO",
    "sg:tags":[
        "operator",
        "trucking"
    ],
    "wof:name":"Lc Trucking & Hauling",
    "wof:placetype":"venue"
},
  "geometry": {"coordinates":[-104.859306,40.331483],"type":"Point"}
}