{
  "type": "Feature",
  "properties": {
    "addr:full":"7062 Red Mesa Dr Littleton CO 80125",
    "addr:housenumber":"7062",
    "addr:postcode":"80125",
    "addr:street":"Red Mesa Dr",
    "iso:country":"US",
    "sg:address":"7062 Red Mesa Dr",
    "sg:city":"Littleton",
    "sg:classifiers":[
        {
            "category":"Professional",
            "subcategory":"Management & Consulting",
            "type":"Services"
        }
    ],
    "sg:phone":"+1 303 933 0674",
    "sg:postcode":"80125",
    "sg:province":"CO",
    "sg:tags":[
        "counselor",
        "public",
        "relations"
    ],
    "wof:name":"WISS Communications LLC",
    "wof:placetype":"venue"
},
  "geometry": {"coordinates":[-105.078611,39.467814],"type":"Point"}
}