{
  "type": "Feature",
  "properties": {
    "addr:full":"6634 Arrowhead Trl Elizabeth CO 80107",
    "addr:housenumber":"6634",
    "addr:postcode":"80107",
    "addr:street":"Arrowhead Trl",
    "iso:country":"US",
    "sg:address":"6634 Arrowhead Trl",
    "sg:city":"Elizabeth",
    "sg:classifiers":[
        {
            "category":"Manufacturing",
            "subcategory":"Building Materials",
            "type":"Manufacturing & Wholesale Goods"
        }
    ],
    "sg:phone":"+1 303 663 3545",
    "sg:postcode":"80107",
    "sg:province":"CO",
    "sg:tags":[
        "mfg"
    ],
    "wof:name":"Final Touch Woodworks Inc",
    "wof:placetype":"venue"
},
  "geometry": {"coordinates":[-104.542019,39.326656],"type":"Point"}
}