{
  "type": "Feature",
  "properties": {
    "iso:country":"US",
    "sg:address":"188 E Meadow Mile",
    "sg:city":"Fraser",
    "sg:classifiers":[
        {
            "category":"Building & Trades",
            "subcategory":"Construction",
            "type":"Services"
        }
    ],
    "sg:phone":"+1 970 726 5437",
    "sg:postcode":"80478",
    "sg:province":"CO",
    "sg:tags":[
        "excavating",
        "contractor"
    ],
    "wof:name":"Fleming Excavating",
    "wof:placetype":"venue"
},
  "geometry": {"coordinates":[-105.799728,39.945395],"type":"Point"}
}