{
  "type": "Feature",
  "properties": {
    "addr:full":"4341 N Academy Blvd Colorado Springs CO 80918",
    "addr:housenumber":"4341",
    "addr:postcode":"80918",
    "addr:street":"N Academy Blvd",
    "iso:country":"US",
    "sg:address":"4341 N Academy Blvd",
    "sg:city":"Colorado Springs",
    "sg:classifiers":[
        {
            "category":"Shopping",
            "type":"Retail Goods"
        }
    ],
    "sg:phone":"+1 719 528 5959",
    "sg:postcode":"80918",
    "sg:province":"CO",
    "sg:tags":[
        "cards",
        "sport",
        "baseball",
        "memorabilia"
    ],
    "wof:name":"Dalez Kardz & Komicz",
    "wof:placetype":"venue"
},
  "geometry": {"coordinates":[-104.75976,38.895731],"type":"Point"}
}