{
  "type": "Feature",
  "properties": {
    "iso:country":"US",
    "sg:address":"380 Brandywine Dr",
    "sg:city":"Colorado Springs",
    "sg:classifiers":[
        {
            "category":"Building & Trades",
            "subcategory":"Landscaping Services",
            "type":"Services"
        }
    ],
    "sg:phone":"+1 719 576 0720",
    "sg:postcode":"80906",
    "sg:province":"CO",
    "sg:tags":[
        "landscape",
        "contractor"
    ],
    "wof:name":"J P Lyle Landscapes",
    "wof:placetype":"venue"
},
  "geometry": {"coordinates":[-104.826088,38.767278],"type":"Point"}
}