{
  "type": "Feature",
  "properties": {
    "iso:country":"US",
    "sg:address":"2548 Alkire St",
    "sg:city":"Golden",
    "sg:classifiers":[
        {
            "category":"Building & Trades",
            "subcategory":"Construction",
            "type":"Services"
        }
    ],
    "sg:phone":"+1 303 279 5769",
    "sg:postcode":"80401",
    "sg:province":"CO",
    "sg:tags":[
        "contractor"
    ],
    "wof:name":"HLR Contracting Inc",
    "wof:placetype":"venue"
},
  "geometry": {"coordinates":[-105.147132,39.753666],"type":"Point"}
}