{
  "type": "Feature",
  "properties": {
    "addr:full":"8401 Park Meadows Dr Littleton CO 80124",
    "addr:housenumber":"8401",
    "addr:postcode":"80124",
    "addr:street":"Park Meadows Dr",
    "iso:country":"US",
    "sg:address":"8401 Park Meadows Dr",
    "sg:city":"Littleton",
    "sg:classifiers":[
        {
            "category":"Shopping",
            "subcategory":"Gifts & Souvenirs",
            "type":"Retail Goods"
        }
    ],
    "sg:phone":"+1 303 925 1823",
    "sg:postcode":"80124",
    "sg:province":"CO",
    "wof:name":"Successories of Missouri",
    "wof:placetype":"venue"
},
  "geometry": {"coordinates":[-104.88551,39.558306],"type":"Point"}
}