{
  "type": "Feature",
  "properties": {
    "iso:country":"US",
    "sg:address":"1144 S Colorado Boulevard",
    "sg:city":"Denver",
    "sg:classifiers":[
        {
            "category":"Professional",
            "subcategory":"Printing & Photocopies",
            "type":"Services"
        }
    ],
    "sg:phone":"+1 303 691 0626",
    "sg:postcode":"80246",
    "sg:province":"CO",
    "sg:website":"www.alphagraphics.com/centers/de...",
    "wof:name":"AlphaGraphics Colorado Blvd.",
    "wof:placetype":"venue"
},
  "geometry": {"coordinates":[-104.94067800000001,39.695772],"type":"Point"}
}