{
  "type": "Feature",
  "properties": {
    "iso:country":"US",
    "sg:address":"1299 S Kalamath St",
    "sg:city":"Denver",
    "sg:classifiers":[
        {
            "category":"Building & Trades",
            "subcategory":"Cleaning & Sanitation",
            "type":"Services"
        }
    ],
    "sg:phone":"+1 720 570 7890",
    "sg:postcode":"80223",
    "sg:province":"CO",
    "sg:tags":[
        "maintenance"
    ],
    "wof:name":"A & A Window Cleaning Services",
    "wof:placetype":"venue"
},
  "geometry": {"coordinates":[-105.000331,39.694898],"type":"Point"}
}