{
  "type": "Feature",
  "properties": {
    "addr:full":"6470 W 120th Ave Broomfield CO 80020",
    "addr:housenumber":"6470",
    "addr:postcode":"80020",
    "addr:street":"W 120Th Ave",
    "iso:country":"US",
    "sg:address":"6470 W 120th Ave",
    "sg:city":"Broomfield",
    "sg:classifiers":[
        {
            "category":"Home & Garden",
            "subcategory":"Household Appliances",
            "type":"Retail Goods"
        }
    ],
    "sg:phone":"+1 303 920 2525",
    "sg:postcode":"80020",
    "sg:province":"CO",
    "wof:name":"International Sew Chalets Corp",
    "wof:placetype":"venue"
},
  "geometry": {"coordinates":[-105.067151,39.914138],"type":"Point"}
}