{
  "type": "Feature",
  "properties": {
    "addr:full":"1415 Market St Denver CO 80202",
    "addr:housenumber":"1415",
    "addr:postcode":"80202",
    "addr:street":"Market St",
    "iso:country":"US",
    "sg:address":"1415 Market St",
    "sg:city":"Denver",
    "sg:classifiers":[
        {
            "category":"Restaurant",
            "type":"Food & Drink"
        }
    ],
    "sg:menulink":"http://www.allmenus.com/co/denver/71437-old-chicago/menu/",
    "sg:phone":"+1 303 893 1806",
    "sg:postcode":"80202",
    "sg:province":"CO",
    "sg:tags":[
        "american",
        "pizza"
    ],
    "wof:name":"Old Chicago",
    "wof:placetype":"venue"
},
  "geometry": {"coordinates":[-105.000394,39.748288],"type":"Point"}
}