{
  "type": "Feature",
  "properties": {
    "iso:country":"US",
    "sg:address":"1903 Cambridge Dr",
    "sg:city":"Longmont",
    "sg:classifiers":[
        {
            "category":"Building & Trades",
            "subcategory":"Construction",
            "type":"Services"
        }
    ],
    "sg:phone":"+1 303 772 7262",
    "sg:postcode":"80503",
    "sg:province":"CO",
    "sg:tags":[
        "contractor"
    ],
    "wof:name":"20/20 Home Inspection",
    "wof:placetype":"venue"
},
  "geometry": {"coordinates":[-105.13363200000001,40.191378],"type":"Point"}
}