{
  "type": "Feature",
  "properties": {
    "addr:full":"8250 W 80th Ave Arvada CO 80005",
    "addr:housenumber":"8250",
    "addr:postcode":"80005",
    "addr:street":"W 80Th Ave",
    "iso:country":"US",
    "sg:address":"8250 W 80th Ave",
    "sg:city":"Arvada",
    "sg:classifiers":[
        {
            "category":"Health Services",
            "subcategory":"Health Practitioner",
            "type":"Services"
        }
    ],
    "sg:phone":"+1 303 423 3008",
    "sg:postcode":"80005",
    "sg:province":"CO",
    "sg:tags":[
        "therapist",
        "physical"
    ],
    "wof:name":"Clear Creek Physical Therapy",
    "wof:placetype":"venue"
},
  "geometry": {"coordinates":[-105.08923799999999,39.841695],"type":"Point"}
}