{
  "type": "Feature",
  "properties": {
    "iso:country":"US",
    "sg:address":"65445 Co Hwy 109",
    "sg:city":"Genoa",
    "sg:classifiers":[
        {
            "category":"Farming",
            "subcategory":"Livestock Farm",
            "type":"Manufacturing & Wholesale Goods"
        }
    ],
    "sg:phone":"+1 719 763 2324",
    "sg:postcode":"80818",
    "sg:province":"CO",
    "sg:tags":[
        "beef",
        "feedlot",
        "cattle"
    ],
    "wof:name":"Andrew Johnson",
    "wof:placetype":"venue"
},
  "geometry": {"coordinates":[-103.491469,39.450351],"type":"Point"}
}