{
  "type": "Feature",
  "properties": {
    "iso:country":"US",
    "sg:address":"203 Rome Ct",
    "sg:city":"Fort Collins",
    "sg:classifiers":[
        {
            "category":"Manufacturing",
            "subcategory":"Tools & Machinery",
            "type":"Manufacturing & Wholesale Goods"
        }
    ],
    "sg:phone":"+1 970 495 9991",
    "sg:postcode":"80524",
    "sg:province":"CO",
    "sg:tags":[
        "mfg",
        "computer",
        "electrical",
        "custom"
    ],
    "wof:name":"CCI Electronics Inc",
    "wof:placetype":"venue"
},
  "geometry": {"coordinates":[-105.033207,40.588451],"type":"Point"}
}