{
  "type": "Feature",
  "properties": {
    "addr:full":"401 23rd St Glenwood Springs CO 81601",
    "addr:housenumber":"401",
    "addr:postcode":"81601",
    "addr:street":"23Rd St",
    "iso:country":"US",
    "sg:address":"401 23rd St",
    "sg:city":"Glenwood Springs",
    "sg:classifiers":[
        {
            "category":"Professional",
            "subcategory":"Lawyer & Legal Services",
            "type":"Services"
        }
    ],
    "sg:phone":"+1 970 945 2102",
    "sg:postcode":"81601",
    "sg:province":"CO",
    "sg:tags":[
        "attorney"
    ],
    "wof:name":"Daniel R Rosen Law Offices",
    "wof:placetype":"venue"
},
  "geometry": {"coordinates":[-107.32424899999999,39.529668],"type":"Point"}
}