{
  "type": "Feature",
  "properties": {
    "iso:country":"US",
    "sg:address":"3212 E Rd",
    "sg:city":"Clifton",
    "sg:classifiers":[
        {
            "category":"Building & Trades",
            "subcategory":"Landscaping Services",
            "type":"Services"
        }
    ],
    "sg:phone":"+1 970 858 3316",
    "sg:postcode":"81520",
    "sg:province":"CO",
    "wof:name":"Classic Tree Service & La",
    "wof:placetype":"venue"
},
  "geometry": {"coordinates":[-108.457982,39.077368],"type":"Point"}
}