{
  "type": "Feature",
  "properties": {
    "iso:country":"US",
    "sg:address":"16845 Mount Vernon Rd",
    "sg:city":"Golden",
    "sg:classifiers":[
        {
            "category":"Freight",
            "type":"Transportation"
        }
    ],
    "sg:phone":"+1 303 277 1658",
    "sg:postcode":"80401",
    "sg:province":"CO",
    "sg:tags":[
        "commercial",
        "self",
        "storage",
        "rental"
    ],
    "wof:name":"Nation Wide Self Storage",
    "wof:placetype":"venue"
},
  "geometry": {"coordinates":[-105.19110499999999,39.728904],"type":"Point"}
}