{
  "type": "Feature",
  "properties": {
    "addr:full":"6900 W 117th Ave Broomfield CO 80020",
    "addr:housenumber":"6900",
    "addr:postcode":"80020",
    "addr:street":"W 117Th Ave",
    "iso:country":"US",
    "sg:address":"6900 W 117th Ave",
    "sg:city":"Broomfield",
    "sg:classifiers":[
        {
            "category":"Autos & Motor Vehicles",
            "subcategory":"Motorcycle Sales",
            "type":"Retail Goods"
        }
    ],
    "sg:phone":"+1 303 770 6182",
    "sg:postcode":"80020",
    "sg:province":"CO",
    "sg:tags":[
        "scooter"
    ],
    "wof:name":"Systech INC/Cr One Motorsport",
    "wof:placetype":"venue"
},
  "geometry": {"coordinates":[-105.076455,39.909872],"type":"Point"}
}