{
  "type": "Feature",
  "properties": {
    "iso:country":"US",
    "sg:address":"18741 71st Ave",
    "sg:city":"Denver",
    "sg:classifiers":[
        {
            "category":"Travel",
            "subcategory":"Hotels & Motels",
            "type":"Entertainment"
        }
    ],
    "sg:phone":"+1 303 628 7777",
    "sg:postcode":"80249",
    "sg:province":"CO",
    "wof:name":"Hyatt Summerfield Suites Denver International Airport",
    "wof:placetype":"venue"
},
  "geometry": {"coordinates":[-104.67569399999999,39.824566],"type":"Point"}
}