{
  "type": "Feature",
  "properties": {
    "addr:full":"7531 S Kendall Blvd Littleton CO 80128",
    "addr:housenumber":"7531",
    "addr:postcode":"80128",
    "addr:street":"S Kendall Blvd",
    "iso:country":"US",
    "sg:address":"7531 S Kendall Blvd",
    "sg:city":"Littleton",
    "sg:classifiers":[
        {
            "category":"Social Services",
            "subcategory":"Child Care",
            "type":"Services"
        }
    ],
    "sg:phone":"+1 303 972 9774",
    "sg:postcode":"80128",
    "sg:province":"CO",
    "sg:tags":[
        "kindergarten",
        "academic",
        "school"
    ],
    "wof:name":"St Philip Early Learning Ctr",
    "wof:placetype":"venue"
},
  "geometry": {"coordinates":[-105.066306,39.580473],"type":"Point"}
}