{
  "type": "Feature",
  "properties": {
    "addr:full":"3555 Stanford Rd Fort Collins CO 80525",
    "addr:housenumber":"3555",
    "addr:postcode":"80525",
    "addr:street":"Stanford Rd",
    "iso:country":"US",
    "sg:address":"3555 Stanford Rd",
    "sg:city":"Fort Collins",
    "sg:classifiers":[
        {
            "category":"Banks & Credit Unions",
            "subcategory":"Bank",
            "type":"Services"
        }
    ],
    "sg:phone":"+1 970 223 5369",
    "sg:postcode":"80525",
    "sg:province":"CO",
    "sg:tags":[
        "loan",
        "real estate"
    ],
    "wof:name":"American Home Mortgage",
    "wof:placetype":"venue"
},
  "geometry": {"coordinates":[-105.07010200000001,40.53967],"type":"Point"}
}