{
  "type": "Feature",
  "properties": {
    "addr:full":"4084 S Oneida St Denver CO 80237",
    "addr:housenumber":"4084",
    "addr:postcode":"80237",
    "addr:street":"S Oneida St",
    "iso:country":"US",
    "sg:address":"4084 S Oneida St",
    "sg:city":"Denver",
    "sg:classifiers":[
        {
            "category":"Food & Beverages",
            "subcategory":"Groceries & Convenience Stores",
            "type":"Retail Goods"
        }
    ],
    "sg:phone":"+1 303 758 7209",
    "sg:postcode":"80237",
    "sg:province":"CO",
    "sg:tags":[
        "business"
    ],
    "wof:name":"Houchens Holding Co LLC",
    "wof:placetype":"venue"
},
  "geometry": {"coordinates":[-104.905357,39.645168],"type":"Point"}
}