{
  "type": "Feature",
  "properties": {
    "addr:full":"2570 Tamora Way Colorado Springs CO 80919",
    "addr:housenumber":"2570",
    "addr:postcode":"80919",
    "addr:street":"Tamora Way",
    "iso:country":"US",
    "sg:address":"2570 Tamora Way",
    "sg:city":"Colorado Springs",
    "sg:classifiers":[
        {
            "category":"Food & Beverages",
            "subcategory":"Specialty",
            "type":"Retail Goods"
        }
    ],
    "sg:phone":"+1 719 599 3226",
    "sg:postcode":"80919",
    "sg:province":"CO",
    "sg:tags":[
        "health",
        "store"
    ],
    "wof:name":"Maximum Sports Nutrition",
    "wof:placetype":"venue"
},
  "geometry": {"coordinates":[-104.879439,38.920344],"type":"Point"}
}