{
  "type": "Feature",
  "properties": {
    "iso:country":"US",
    "sg:address":"799 E 1st St",
    "sg:city":"Durango",
    "sg:classifiers":[
        {
            "category":"Health Services",
            "subcategory":"Health Practitioner",
            "type":"Services"
        }
    ],
    "sg:phone":"+1 970 375 2369",
    "sg:postcode":"81301",
    "sg:province":"CO",
    "sg:tags":[
        "audiologists",
        "merchandise"
    ],
    "wof:name":"Animas Valley Audiology",
    "wof:placetype":"venue"
},
  "geometry": {"coordinates":[-107.875973,37.263211],"type":"Point"}
}