{
  "type": "Feature",
  "properties": {
    "addr:full":"4722 S Himalaya Ct Aurora CO 80015",
    "addr:housenumber":"4722",
    "addr:postcode":"80015",
    "addr:street":"S Himalaya Ct",
    "iso:country":"US",
    "sg:address":"4722 S Himalaya Ct",
    "sg:city":"Aurora",
    "sg:classifiers":[
        {
            "category":"Shopping",
            "subcategory":"Catalog Store",
            "type":"Retail Goods"
        }
    ],
    "sg:phone":"+1 303 435 1130",
    "sg:postcode":"80015",
    "sg:province":"CO",
    "sg:tags":[
        "mail",
        "house"
    ],
    "wof:name":"Goinfishincom",
    "wof:placetype":"venue"
},
  "geometry": {"coordinates":[-104.753196,39.630593],"type":"Point"}
}