{
  "type": "Feature",
  "properties": {
    "addr:full":"1304 N Academy Blvd Colorado Springs CO 80909",
    "addr:housenumber":"1304",
    "addr:postcode":"80909",
    "addr:street":"N Academy Blvd",
    "iso:country":"US",
    "sg:address":"1304 N Academy Blvd",
    "sg:city":"Colorado Springs",
    "sg:classifiers":[
        {
            "category":"Health Services",
            "subcategory":"Doctor",
            "type":"Services"
        }
    ],
    "sg:phone":"+1 719 596 6700",
    "sg:postcode":"80909",
    "sg:province":"CO",
    "sg:tags":[
        "physician",
        "surgeon"
    ],
    "wof:name":"Pat Higgins DO",
    "wof:placetype":"venue"
},
  "geometry": {"coordinates":[-104.75749,38.854321],"type":"Point"}
}