{
  "type": "Feature",
  "properties": {
    "iso:country":"US",
    "sg:address":"1280 Ute Ave",
    "sg:city":"Aspen",
    "sg:classifiers":[
        {
            "category":"Professional",
            "subcategory":"Lawyer & Legal Services",
            "type":"Services"
        }
    ],
    "sg:phone":"+1 970 925 9003",
    "sg:postcode":"81611",
    "sg:province":"CO",
    "sg:tags":[
        "attorney"
    ],
    "wof:name":"Public Counsel Of The Rockies",
    "wof:placetype":"venue"
},
  "geometry": {"coordinates":[-106.813058,39.181843],"type":"Point"}
}