{
  "type": "Feature",
  "properties": {
    "iso:country":"US",
    "sg:address":"624 Main St",
    "sg:city":"Longmont",
    "sg:classifiers":[
        {
            "category":"Building & Trades",
            "subcategory":"Plumbing",
            "type":"Services"
        }
    ],
    "sg:phone":"+1 303 682 9504",
    "sg:postcode":"80501",
    "sg:province":"CO",
    "sg:tags":[
        "contractor"
    ],
    "wof:name":"Home Run Heating & Air",
    "wof:placetype":"venue"
},
  "geometry": {"coordinates":[-105.102428,40.170265],"type":"Point"}
}