{
  "type": "Feature",
  "properties": {
    "addr:full":"10590 W Raspberry Mtn Rd Littleton CO 80127",
    "addr:housenumber":"10590",
    "addr:postcode":"80127",
    "addr:street":"W Raspberry Mtn Rd",
    "iso:country":"US",
    "sg:address":"10590 W Raspberry Mtn Rd",
    "sg:city":"Littleton",
    "sg:classifiers":[
        {
            "category":"Building & Trades",
            "subcategory":"Landscaping Services",
            "type":"Services"
        }
    ],
    "sg:phone":"+1 303 904 2187",
    "sg:postcode":"80127",
    "sg:province":"CO",
    "wof:name":"Mojo Lawn & Landscape",
    "wof:placetype":"venue"
},
  "geometry": {"coordinates":[-105.11523099999999,39.57313],"type":"Point"}
}