{
  "type": "Feature",
  "properties": {
    "iso:country":"US",
    "sg:address":"1880 S Flatiron Ct",
    "sg:city":"Boulder",
    "sg:classifiers":[
        {
            "category":"Utilities",
            "subcategory":"Mobile Phone",
            "type":"Services"
        }
    ],
    "sg:phone":"+1 303 449 4330",
    "sg:postcode":"80301",
    "sg:province":"CO",
    "sg:tags":[
        "wireless",
        "communication",
        "datum",
        "network"
    ],
    "wof:name":"Intuicom Incorporated",
    "wof:placetype":"venue"
},
  "geometry": {"coordinates":[-105.218214,40.019443],"type":"Point"}
}