{
  "type": "Feature",
  "properties": {
    "addr:full":"2688 S Field St Denver CO 80227",
    "addr:housenumber":"2688",
    "addr:postcode":"80227",
    "addr:street":"S Field St",
    "iso:country":"US",
    "sg:address":"2688 S Field St",
    "sg:city":"Denver",
    "sg:classifiers":[
        {
            "category":"Banks & Credit Unions",
            "subcategory":"Bank",
            "type":"Services"
        }
    ],
    "sg:phone":"+1 303 691 5058",
    "sg:postcode":"80227",
    "sg:province":"CO",
    "sg:tags":[
        "mortgage"
    ],
    "wof:name":"Clairon Financial Inc",
    "wof:placetype":"venue"
},
  "geometry": {"coordinates":[-105.097663,39.668166],"type":"Point"}
}