{
  "type": "Feature",
  "properties": {
    "addr:full":"1152 S Manila Rd Bennett CO 80102",
    "addr:housenumber":"1152",
    "addr:postcode":"80102",
    "addr:street":"S Manila Rd",
    "iso:country":"US",
    "sg:address":"1152 S Manila Rd",
    "sg:city":"Bennett",
    "sg:classifiers":[
        {
            "category":"Shopping",
            "type":"Retail Goods"
        }
    ],
    "sg:phone":"+1 303 644 4042",
    "sg:postcode":"80102",
    "sg:province":"CO",
    "sg:tags":[
        "merchandise"
    ],
    "wof:name":"Button Box",
    "wof:placetype":"venue"
},
  "geometry": {"coordinates":[-104.527452,39.701728],"type":"Point"}
}