{
  "type": "Feature",
  "properties": {
    "iso:country":"US",
    "sg:address":"1201 S Downing St",
    "sg:city":"Denver",
    "sg:classifiers":[
        {
            "category":"Professional",
            "type":"Services"
        },
        {
            "category":"Real Estate",
            "subcategory":"Real Estate Agent",
            "type":"Services"
        }
    ],
    "sg:phone":"+1 303 778 7191",
    "sg:postcode":"80210",
    "sg:province":"CO",
    "wof:name":"2482 W Argyle LLC",
    "wof:placetype":"venue"
},
  "geometry": {"coordinates":[-104.97341299999999,39.692969],"type":"Point"}
}