{
  "type": "Feature",
  "properties": {
    "iso:country":"US",
    "sg:address":"1120 Grand Ave",
    "sg:city":"Glenwood Springs",
    "sg:classifiers":[
        {
            "category":"Professional",
            "subcategory":"Lawyer & Legal Services",
            "type":"Services"
        }
    ],
    "sg:phone":"+1 970 945 2361",
    "sg:postcode":"81601",
    "sg:province":"CO",
    "sg:tags":[
        "attorney"
    ],
    "wof:name":"Walter E Brown III",
    "wof:placetype":"venue"
},
  "geometry": {"coordinates":[-107.324809,39.542522],"type":"Point"}
}