{
  "type": "Feature",
  "properties": {
    "addr:full":"1642 S Parker Rd Denver CO 80231",
    "addr:housenumber":"1642",
    "addr:postcode":"80231",
    "addr:street":"S Parker Rd",
    "iso:country":"US",
    "sg:address":"1642 S Parker Rd",
    "sg:city":"Denver",
    "sg:classifiers":[
        {
            "category":"Social Services",
            "type":"Services"
        }
    ],
    "sg:phone":"+1 303 696 8086",
    "sg:postcode":"80231",
    "sg:province":"CO",
    "sg:tags":[
        "organization",
        "welfare"
    ],
    "wof:name":"National Council-Jewish Women",
    "wof:placetype":"venue"
},
  "geometry": {"coordinates":[-104.887874,39.68817],"type":"Point"}
}