{
  "type": "Feature",
  "properties": {
    "addr:full":"3515 S Tamarac Dr Suite 200 Denver CO 80237",
    "addr:housenumber":"3515",
    "addr:postcode":"80237",
    "addr:street":"S Tamarac Dr Suite 200",
    "iso:country":"US",
    "sg:address":"3515 S Tamarac Dr Suite 200",
    "sg:city":"Denver",
    "sg:classifiers":[
        {
            "category":"Professional",
            "subcategory":"Lawyer & Legal Services",
            "type":"Services"
        }
    ],
    "sg:phone":"+1 303 586 3968",
    "sg:postcode":"80237",
    "sg:province":"CO",
    "sg:tags":[
        "attorney",
        "dwi",
        "duo",
        "divorce",
        "criminal",
        "law"
    ],
    "sg:website":"http://www.boneylaw.com/",
    "wof:name":"The Boney Law Firm",
    "wof:placetype":"venue"
},
  "geometry": {"coordinates":[-104.898768,39.652573],"type":"Point"}
}