{
  "type": "Feature",
  "properties": {
    "addr:full":"1950 S Holly St Denver CO 80222",
    "addr:housenumber":"1950",
    "addr:postcode":"80222",
    "addr:street":"S Holly St",
    "iso:country":"US",
    "sg:address":"1950 S Holly St",
    "sg:city":"Denver",
    "sg:classifiers":[
        {
            "category":"Professional",
            "subcategory":"Accounting & Tax Preparation",
            "type":"Services"
        }
    ],
    "sg:phone":"+1 303 758 0930",
    "sg:postcode":"80222",
    "sg:province":"CO",
    "sg:tags":[
        "return",
        "filing"
    ],
    "wof:name":"H & R Block Tax Svc",
    "wof:placetype":"venue"
},
  "geometry": {"coordinates":[-104.922274,39.6804],"type":"Point"}
}