{
  "type": "Feature",
  "properties": {
    "iso:country":"US",
    "sg:address":"530 E Bromley Ln",
    "sg:city":"Brighton",
    "sg:classifiers":[
        {
            "category":"Personal",
            "subcategory":"Tanning Parlor",
            "type":"Services"
        }
    ],
    "sg:phone":"+1 303 659 7624",
    "sg:postcode":"80601",
    "sg:province":"CO",
    "sg:tags":[
        "salon"
    ],
    "wof:name":"Salon Silverado",
    "wof:placetype":"venue"
},
  "geometry": {"coordinates":[-104.816149,39.972207],"type":"Point"}
}