{
  "type": "Feature",
  "properties": {
    "addr:full":"1666 S University Blvd Denver CO 80210",
    "addr:housenumber":"1666",
    "addr:postcode":"80210",
    "addr:street":"S University Blvd",
    "iso:country":"US",
    "sg:address":"1666 S University Blvd",
    "sg:city":"Denver",
    "sg:classifiers":[
        {
            "category":"Home & Garden",
            "subcategory":"Household Appliances",
            "type":"Retail Goods"
        }
    ],
    "sg:phone":"+1 720 570 0981",
    "sg:postcode":"80210",
    "sg:province":"CO",
    "sg:tags":[
        "range",
        "canopy",
        "hood"
    ],
    "wof:name":"Captive Aire Systems",
    "wof:placetype":"venue"
},
  "geometry": {"coordinates":[-104.95937000000001,39.68555],"type":"Point"}
}