{
  "type": "Feature",
  "properties": {
    "addr:full":"8360 Chase Way Arvada CO 80003",
    "addr:housenumber":"8360",
    "addr:postcode":"80003",
    "addr:street":"Chase Way",
    "iso:country":"US",
    "sg:address":"8360 Chase Way",
    "sg:city":"Arvada",
    "sg:classifiers":[
        {
            "category":"Restaurant",
            "type":"Food & Drink"
        }
    ],
    "sg:phone":"+1 303 421 4698",
    "sg:postcode":"80003",
    "sg:province":"CO",
    "sg:tags":[
        "eating"
    ],
    "wof:name":"Relish Your Dog",
    "wof:placetype":"venue"
},
  "geometry": {"coordinates":[-105.05694200000001,39.848119],"type":"Point"}
}