{
  "type": "Feature",
  "properties": {
    "iso:country":"US",
    "sg:address":"2845 Ore Mill Rd",
    "sg:city":"Colorado Springs",
    "sg:classifiers":[
        {
            "category":"Recreation",
            "type":"Entertainment"
        }
    ],
    "sg:phone":"+1 719 633 6227",
    "sg:postcode":"80904",
    "sg:province":"CO",
    "sg:tags":[
        "equipment",
        "skiing"
    ],
    "wof:name":"Colorado Kite & Ski",
    "wof:placetype":"venue"
},
  "geometry": {"coordinates":[-104.868551,38.846921],"type":"Point"}
}