{
  "type": "Feature",
  "properties": {
    "addr:full":"663 Aspen Rd Golden CO 80401",
    "addr:housenumber":"663",
    "addr:postcode":"80401",
    "addr:street":"Aspen Rd",
    "iso:country":"US",
    "sg:address":"663 Aspen Rd",
    "sg:city":"Golden",
    "sg:classifiers":[
        {
            "category":"Wholesale",
            "subcategory":"Jewelry",
            "type":"Manufacturing & Wholesale Goods"
        }
    ],
    "sg:phone":"+1 303 526 2520",
    "sg:postcode":"80401",
    "sg:province":"CO",
    "sg:tags":[
        "stone"
    ],
    "wof:name":"Kreations By Kat",
    "wof:placetype":"venue"
},
  "geometry": {"coordinates":[-105.24462200000001,39.726357],"type":"Point"}
}