{
  "type": "Feature",
  "properties": {
    "iso:country":"US",
    "sg:address":"2550 S Parker Rd",
    "sg:city":"Aurora",
    "sg:classifiers":[
        {
            "category":"Professional",
            "subcategory":"Research",
            "type":"Services"
        }
    ],
    "sg:phone":"+1 303 337 0990",
    "sg:postcode":"80014",
    "sg:province":"CO",
    "sg:tags":[
        "organization",
        "consulting",
        "noncommercial",
        "business"
    ],
    "wof:name":"Mid-Cntnent Rgional Eductl Lab",
    "wof:placetype":"venue"
},
  "geometry": {"coordinates":[-104.86284499999999,39.668458],"type":"Point"}
}