{
  "type": "Feature",
  "properties": {
    "iso:country":"US",
    "sg:address":"3630 N Stone Ave",
    "sg:city":"Colorado Springs",
    "sg:classifiers":[
        {
            "category":"Building & Trades",
            "subcategory":"Construction",
            "type":"Services"
        }
    ],
    "sg:phone":"+1 719 634 2828",
    "sg:postcode":"80907",
    "sg:province":"CO",
    "sg:tags":[
        "residence",
        "contractor"
    ],
    "wof:name":"Schanel Construction Inc",
    "wof:placetype":"venue"
},
  "geometry": {"coordinates":[-104.81597499999999,38.882452],"type":"Point"}
}