{
  "type": "Feature",
  "properties": {
    "iso:country":"US",
    "sg:address":"461 E 6th Ter",
    "sg:city":"Florence",
    "sg:classifiers":[
        {
            "category":"Real Estate",
            "subcategory":"Real Estate Agent",
            "type":"Services"
        }
    ],
    "sg:phone":"+1 719 784 4476",
    "sg:postcode":"81226",
    "sg:province":"CO",
    "wof:name":"Lobo Rental Properties LLC",
    "wof:placetype":"venue"
},
  "geometry": {"coordinates":[-105.111997,38.394328],"type":"Point"}
}