{
  "type": "Feature",
  "properties": {
    "addr:full":"20101 Co Rd 27 Brush CO 80723",
    "addr:housenumber":"20101;27",
    "addr:postcode":"brush;80723",
    "addr:street":"Co Rd",
    "iso:country":"US",
    "sg:address":"20101 Co Rd 27",
    "sg:city":"Brush",
    "sg:classifiers":[
        {
            "category":"Farming",
            "subcategory":"Farm",
            "type":"Manufacturing & Wholesale Goods"
        }
    ],
    "sg:phone":"+1 970 842 2154",
    "sg:postcode":"80723",
    "sg:province":"CO",
    "sg:tags":[
        "crop",
        "general"
    ],
    "wof:name":"Lance Christensen",
    "wof:placetype":"venue"
},
  "geometry": {"coordinates":[-103.64076900000001,40.290803],"type":"Point"}
}