{
  "type": "Feature",
  "properties": {
    "addr:full":"5375 Orchard St Golden CO 80403",
    "addr:housenumber":"5375",
    "addr:postcode":"80403",
    "addr:street":"Orchard St",
    "iso:country":"US",
    "sg:address":"5375 Orchard St",
    "sg:city":"Golden",
    "sg:classifiers":[
        {
            "category":"Manufacturing",
            "subcategory":"Rubber & Plastics",
            "type":"Manufacturing & Wholesale Goods"
        }
    ],
    "sg:phone":"+1 303 279 7964",
    "sg:postcode":"80403",
    "sg:province":"CO",
    "sg:tags":[
        "devices",
        "mfg"
    ],
    "wof:name":"Great Gaskets",
    "wof:placetype":"venue"
},
  "geometry": {"coordinates":[-105.179416,39.793626],"type":"Point"}
}