{
  "type": "Feature",
  "properties": {
    "addr:full":"201 Main St Walden CO 80480",
    "addr:housenumber":"201",
    "addr:postcode":"80480",
    "addr:street":"Main St",
    "iso:country":"US",
    "sg:address":"201 Main St",
    "sg:city":"Walden",
    "sg:classifiers":[
        {
            "category":"Organizations",
            "subcategory":"Religious Organization",
            "type":"Services"
        }
    ],
    "sg:phone":"+1 970 723 8640",
    "sg:postcode":"80480",
    "sg:province":"CO",
    "sg:tags":[
        "church"
    ],
    "wof:name":"Mountain View Baptist Church",
    "wof:placetype":"venue"
},
  "geometry": {"coordinates":[-106.28205,40.73507],"type":"Point"}
}