{
  "type": "Feature",
  "properties": {
    "addr:full":"2277 W Eisenhower Blvd Loveland CO 80537",
    "addr:housenumber":"2277",
    "addr:postcode":"80537",
    "addr:street":"W Eisenhower Blvd",
    "iso:country":"US",
    "sg:address":"2277 W Eisenhower Blvd",
    "sg:city":"Loveland",
    "sg:classifiers":[
        {
            "category":"Restaurant",
            "type":"Food & Drink"
        }
    ],
    "sg:phone":"+1 970 635 0001",
    "sg:postcode":"80537",
    "sg:province":"CO",
    "wof:name":"Daddy O's Green Onion",
    "wof:placetype":"venue"
},
  "geometry": {"coordinates":[-105.110336,40.407402],"type":"Point"}
}