{
  "type": "Feature",
  "properties": {
    "addr:full":"2318 Co Rd 318 Ignacio CO 81137",
    "addr:housenumber":"2318",
    "addr:postcode":"81137",
    "addr:street":"Co Rd 318 Ignacio",
    "iso:country":"US",
    "sg:address":"2318 Co Rd 318",
    "sg:city":"Ignacio",
    "sg:classifiers":[
        {
            "category":"Retail",
            "subcategory":"Repair Shop",
            "type":"Services"
        }
    ],
    "sg:phone":"+1 970 563 3603",
    "sg:postcode":"81137",
    "sg:province":"CO",
    "wof:name":"Bent Propeller Aviation Inc",
    "wof:placetype":"venue"
},
  "geometry": {"coordinates":[-107.767421,37.096258],"type":"Point"}
}