{
  "type": "Feature",
  "properties": {
    "iso:country":"US",
    "sg:address":"11621 E Dorado Ave",
    "sg:city":"Englewood",
    "sg:classifiers":[
        {
            "category":"Shopping",
            "type":"Retail Goods"
        }
    ],
    "sg:phone":"+1 303 689 9097",
    "sg:postcode":"80111",
    "sg:province":"CO",
    "sg:tags":[
        "miscellaneous",
        "store"
    ],
    "wof:name":"Bower Honey Co",
    "wof:placetype":"venue"
},
  "geometry": {"coordinates":[-104.853982,39.612048],"type":"Point"}
}