{
  "type": "Feature",
  "properties": {
    "iso:country":"US",
    "sg:address":"455 Buckeye Dr",
    "sg:city":"Colorado Springs",
    "sg:classifiers":[
        {
            "category":"Real Estate",
            "subcategory":"Architect",
            "type":"Services"
        }
    ],
    "sg:phone":"+1 719 531 7779",
    "sg:postcode":"80919",
    "sg:province":"CO",
    "wof:name":"Ted Locke",
    "wof:placetype":"venue"
},
  "geometry": {"coordinates":[-104.835722,38.937351],"type":"Point"}
}