{
  "type": "Feature",
  "properties": {
    "iso:country":"US",
    "sg:address":"2846 Falcon Pt",
    "sg:city":"Lafayette",
    "sg:classifiers":[
        {
            "category":"Wholesale",
            "subcategory":"Electrical",
            "type":"Manufacturing & Wholesale Goods"
        }
    ],
    "sg:phone":"+1 303 665 6370",
    "sg:postcode":"80026",
    "sg:province":"CO",
    "sg:tags":[
        "vehicle",
        "parts",
        "supply"
    ],
    "wof:name":"Michael Amato & Company",
    "wof:placetype":"venue"
},
  "geometry": {"coordinates":[-105.094752,39.967021],"type":"Point"}
}