{
  "type": "Feature",
  "properties": {
    "iso:country":"US",
    "sg:address":"9800 Mount Pyramid Court Suite 130",
    "sg:city":"Englewood",
    "sg:classifiers":[
        {
            "category":"Professional",
            "subcategory":"Computer Services",
            "type":"Services"
        }
    ],
    "sg:phone":"+1 866 515 3874",
    "sg:postcode":"80112",
    "sg:province":"CO",
    "sg:website":"http://www.dts-global.com/",
    "wof:name":"Dimension Technology Solutions",
    "wof:placetype":"venue"
},
  "geometry": {"coordinates":[-104.865914,39.538881],"type":"Point"}
}