{
  "type": "Feature",
  "properties": {
    "addr:full":"829 S Alkire St Lakewood CO 80228",
    "addr:housenumber":"829",
    "addr:postcode":"80228",
    "addr:street":"S Alkire St",
    "iso:country":"US",
    "sg:address":"829 S Alkire St",
    "sg:city":"Lakewood",
    "sg:classifiers":[
        {
            "category":"Professional",
            "type":"Services"
        }
    ],
    "sg:phone":"+1 303 986 9020",
    "sg:postcode":"80228",
    "sg:province":"CO",
    "sg:tags":[
        "establishment"
    ],
    "wof:name":"Hudson Williams Inc",
    "wof:placetype":"venue"
},
  "geometry": {"coordinates":[-105.147789,39.698812],"type":"Point"}
}