{
  "type": "Feature",
  "properties": {
    "iso:country":"US",
    "sg:address":"333 W Hampden Ave",
    "sg:city":"Englewood",
    "sg:classifiers":[
        {
            "category":"Professional",
            "subcategory":"Engineering",
            "type":"Services"
        }
    ],
    "sg:phone":"+1 303 781 7070",
    "sg:postcode":"80110",
    "sg:province":"CO",
    "sg:tags":[
        "engineer"
    ],
    "wof:name":"SDG Inc",
    "wof:placetype":"venue"
},
  "geometry": {"coordinates":[-104.992165,39.653307],"type":"Point"}
}