{
  "type": "Feature",
  "properties": {
    "addr:full":"3902 Maizeland Rd Colorado Springs CO 80909",
    "addr:housenumber":"3902",
    "addr:postcode":"80909",
    "addr:street":"Maizeland Rd",
    "iso:country":"US",
    "sg:address":"3902 Maizeland Rd",
    "sg:city":"Colorado Springs",
    "sg:classifiers":[
        {
            "category":"Retail",
            "subcategory":"Auto Rental",
            "type":"Services"
        }
    ],
    "sg:phone":"+1 719 667 1426",
    "sg:postcode":"80909",
    "sg:province":"CO",
    "sg:tags":[
        "renting",
        "truck",
        "leasing"
    ],
    "wof:name":"U-Haul Co",
    "wof:placetype":"venue"
},
  "geometry": {"coordinates":[-104.7546,38.867928],"type":"Point"}
}