{
  "type": "Feature",
  "properties": {
    "addr:full":"2551 Waterdale Dr Loveland CO 80538",
    "addr:housenumber":"2551",
    "addr:postcode":"80538",
    "addr:street":"Waterdale Dr",
    "iso:country":"US",
    "sg:address":"2551 Waterdale Dr",
    "sg:city":"Loveland",
    "sg:classifiers":[
        {
            "category":"Building & Trades",
            "subcategory":"Construction",
            "type":"Services"
        }
    ],
    "sg:phone":"+1 970 635 1810",
    "sg:postcode":"80538",
    "sg:province":"CO",
    "sg:tags":[
        "contractor"
    ],
    "wof:name":"Taylor Masonry",
    "wof:placetype":"venue"
},
  "geometry": {"coordinates":[-105.206046,40.419691],"type":"Point"}
}