{
  "type": "Feature",
  "properties": {
    "addr:full":"110 Stearman Ct Erie CO 80516",
    "addr:housenumber":"110",
    "addr:postcode":"80516",
    "addr:street":"Stearman Ct",
    "iso:country":"US",
    "sg:address":"110 Stearman Ct",
    "sg:city":"Erie",
    "sg:classifiers":[
        {
            "category":"Building & Trades",
            "subcategory":"Construction",
            "type":"Services"
        }
    ],
    "sg:phone":"+1 303 465 3134",
    "sg:postcode":"80516",
    "sg:province":"CO",
    "sg:tags":[
        "house"
    ],
    "sg:website":"www.triresources.com",
    "wof:name":"Tri Resources Intl Inc",
    "wof:placetype":"venue"
},
  "geometry": {"coordinates":[-105.047025,40.01614],"type":"Point"}
}