{
  "type": "Feature",
  "properties": {
    "addr:full":"5961 Rain Dance Trl Littleton CO 80125",
    "addr:postcode":"5961;80125",
    "addr:street":"Rain Dance Trl",
    "iso:country":"US",
    "sg:address":"5961 Rain Dance Trl",
    "sg:city":"Littleton",
    "sg:classifiers":[
        {
            "category":"Building & Trades",
            "subcategory":"Construction",
            "type":"Services"
        }
    ],
    "sg:phone":"+1 720 981 4533",
    "sg:postcode":"80125",
    "sg:province":"CO",
    "sg:tags":[
        "steel",
        "fabrication",
        "welding"
    ],
    "wof:name":"Western Steel Building",
    "wof:placetype":"venue"
},
  "geometry": {"coordinates":[-105.08382899999999,39.449421],"type":"Point"}
}