{
  "type": "Feature",
  "properties": {
    "iso:country":"US",
    "sg:address":"341 4th St",
    "sg:city":"Stratton",
    "sg:classifiers":[
        {
            "category":"Retail",
            "subcategory":"Auto Repair",
            "type":"Services"
        }
    ],
    "sg:phone":"+1 719 348 5333",
    "sg:postcode":"80836",
    "sg:province":"CO",
    "sg:tags":[
        "truck"
    ],
    "wof:name":"Plains Diesel Svc",
    "wof:placetype":"venue"
},
  "geometry": {"coordinates":[-102.602858,39.301265],"type":"Point"}
}