{
  "type": "Feature",
  "properties": {
    "addr:full":"613 Grand Ave Grand Lake CO 80447",
    "addr:housenumber":"613",
    "addr:postcode":"80447",
    "addr:street":"Grand Ave",
    "iso:country":"US",
    "sg:address":"613 Grand Ave",
    "sg:city":"Grand Lake",
    "sg:classifiers":[
        {
            "category":"Travel",
            "subcategory":"Hotels & Motels",
            "type":"Entertainment"
        }
    ],
    "sg:phone":"+1 970 627 8101",
    "sg:postcode":"80447",
    "sg:province":"CO",
    "wof:name":"Bighorn Lodge Best Value Inn",
    "wof:placetype":"venue"
},
  "geometry": {"coordinates":[-105.82687199999999,40.252981],"type":"Point"}
}