{
  "type": "Feature",
  "properties": {
    "addr:full":"125 E 8th Ave Denver CO 80203",
    "addr:housenumber":"125",
    "addr:postcode":"80203",
    "addr:street":"E 8Th Ave",
    "iso:country":"US",
    "sg:address":"125 E 8th Ave",
    "sg:city":"Denver",
    "sg:classifiers":[
        {
            "category":"Education",
            "subcategory":"Music School",
            "type":"Public Place"
        }
    ],
    "sg:phone":"+1 303 777 4266",
    "sg:postcode":"80203",
    "sg:province":"CO",
    "sg:tags":[
        "instrument",
        "teacher",
        "musical"
    ],
    "wof:name":"Acoustic Piano Sales and Service Inc",
    "wof:placetype":"venue"
},
  "geometry": {"coordinates":[-104.98582399999999,39.729227],"type":"Point"}
}