{
  "type": "Feature",
  "properties": {
    "iso:country":"US",
    "sg:address":"1011 S Main St",
    "sg:city":"Longmont",
    "sg:classifiers":[
        {
            "category":"Autos & Motor Vehicles",
            "subcategory":"Automobile Sales",
            "type":"Retail Goods"
        }
    ],
    "sg:phone":"+1 303 678 0300",
    "sg:postcode":"80501",
    "sg:province":"CO",
    "sg:tags":[
        "car",
        "dealer"
    ],
    "wof:name":"Essex Motors",
    "wof:placetype":"venue"
},
  "geometry": {"coordinates":[-105.102575,40.147187],"type":"Point"}
}