{
  "type": "Feature",
  "properties": {
    "iso:country":"US",
    "sg:address":"1310 W Jewell Ave",
    "sg:city":"Denver",
    "sg:classifiers":[
        {
            "category":"Wholesale",
            "subcategory":"Medical Equipment & Supplies",
            "type":"Manufacturing & Wholesale Goods"
        }
    ],
    "sg:phone":"+1 303 934 7938",
    "sg:postcode":"80223",
    "sg:province":"CO",
    "sg:tags":[
        "wheel",
        "chair",
        "lift",
        "ramp"
    ],
    "wof:name":"Accessiblity Specialists USA",
    "wof:placetype":"venue"
},
  "geometry": {"coordinates":[-105.003242,39.682112],"type":"Point"}
}