{
  "type": "Feature",
  "properties": {
    "iso:country":"US",
    "sg:address":"2724 S Paris Pl",
    "sg:city":"Aurora",
    "sg:classifiers":[
        {
            "category":"Manufacturing",
            "subcategory":"Printing",
            "type":"Manufacturing & Wholesale Goods"
        }
    ],
    "sg:phone":"+1 303 338 9988",
    "sg:postcode":"80014",
    "sg:province":"CO",
    "sg:tags":[
        "commercial"
    ],
    "wof:name":"Fat Cat Enterprises",
    "wof:placetype":"venue"
},
  "geometry": {"coordinates":[-104.847931,39.666333],"type":"Point"}
}