{
  "type": "Feature",
  "properties": {
    "iso:country":"US",
    "sg:address":"6588 W Ottawa Pl",
    "sg:city":"Littleton",
    "sg:classifiers":[
        {
            "category":"Social Services",
            "subcategory":"Child Care",
            "type":"Services"
        }
    ],
    "sg:phone":"+1 303 972 0103",
    "sg:postcode":"80128",
    "sg:province":"CO",
    "sg:tags":[
        "center",
        "day"
    ],
    "wof:name":"Childrens World Learning Ctr",
    "wof:placetype":"venue"
},
  "geometry": {"coordinates":[-105.069712,39.592027],"type":"Point"}
}