{
  "type": "Feature",
  "properties": {
    "addr:full":"8470 S Little Rock Way Littleton CO 80126",
    "addr:housenumber":"8470",
    "addr:postcode":"80126",
    "addr:street":"Rock Way",
    "iso:country":"US",
    "sg:address":"8470 S Little Rock Way",
    "sg:city":"Littleton",
    "sg:classifiers":[
        {
            "category":"Restaurant",
            "type":"Food & Drink"
        }
    ],
    "sg:phone":"+1 303 221 2859",
    "sg:postcode":"80126",
    "sg:province":"CO",
    "sg:tags":[
        "shop",
        "parlor",
        "sandwich",
        "ice",
        "cream"
    ],
    "wof:name":"Professor Pibbyns Deli Rest",
    "wof:placetype":"venue"
},
  "geometry": {"coordinates":[-104.94253999999999,39.562944],"type":"Point"}
}