{
  "type": "Feature",
  "properties": {
    "addr:full":"1620 S Perry St Denver CO 80219",
    "addr:housenumber":"1620",
    "addr:postcode":"80219",
    "addr:street":"S Perry St",
    "iso:country":"US",
    "sg:address":"1620 S Perry St",
    "sg:city":"Denver",
    "sg:classifiers":[
        {
            "category":"Real Estate",
            "subcategory":"Real Estate Agent",
            "type":"Services"
        }
    ],
    "sg:phone":"+1 303 937 6244",
    "sg:postcode":"80219",
    "sg:province":"CO",
    "wof:name":"Schroeders",
    "wof:placetype":"venue"
},
  "geometry": {"coordinates":[-105.04004999999999,39.685738],"type":"Point"}
}