{
  "type": "Feature",
  "properties": {
    "iso:country":"US",
    "sg:address":"333 Custer Ave",
    "sg:city":"Akron",
    "sg:classifiers":[
        {
            "category":"Manufacturing",
            "subcategory":"Toys & Sporting Goods",
            "type":"Manufacturing & Wholesale Goods"
        }
    ],
    "sg:phone":"+1 970 245 0948",
    "sg:postcode":"80720",
    "sg:province":"CO",
    "sg:tags":[
        "craft",
        "manufacturer"
    ],
    "wof:name":"Wildfire Distributions",
    "wof:placetype":"venue"
},
  "geometry": {"coordinates":[-103.21702999999999,40.1618],"type":"Point"}
}