{
  "type": "Feature",
  "properties": {
    "iso:country":"US",
    "sg:address":"1570 Emerson Street",
    "sg:city":"Denver",
    "sg:classifiers":[
        {
            "category":"Professional",
            "subcategory":"Lawyer & Legal Services",
            "type":"Services"
        }
    ],
    "sg:phone":"+1 303 832 5138",
    "sg:postcode":"80218",
    "sg:province":"CO",
    "wof:name":"Pearson Jeffrey G",
    "wof:placetype":"venue"
},
  "geometry": {"coordinates":[-104.976016,39.741214],"type":"Point"}
}