{
  "type": "Feature",
  "properties": {
    "iso:country":"US",
    "sg:address":"136 E 10th St",
    "sg:city":"Rifle",
    "sg:classifiers":[
        {
            "category":"Building & Trades",
            "subcategory":"Construction",
            "type":"Services"
        }
    ],
    "sg:phone":"+1 970 625 1250",
    "sg:postcode":"81650",
    "sg:province":"CO",
    "sg:tags":[
        "contractor"
    ],
    "wof:name":"Reinke Roofing Inc",
    "wof:placetype":"venue"
},
  "geometry": {"coordinates":[-107.782843,39.538922],"type":"Point"}
}