{
  "type": "Feature",
  "properties": {
    "iso:country":"US",
    "sg:address":"6332 E 72nd Ave",
    "sg:city":"Commerce City",
    "sg:classifiers":[
        {
            "category":"Social Services",
            "type":"Services"
        }
    ],
    "sg:phone":"+1 303 287 4106",
    "sg:postcode":"80022",
    "sg:province":"CO",
    "sg:tags":[
        "information",
        "abuse",
        "domestic",
        "treatment"
    ],
    "wof:name":"LA Trenza",
    "wof:placetype":"venue"
},
  "geometry": {"coordinates":[-104.914145,39.827127],"type":"Point"}
}