{
  "type": "Feature",
  "properties": {
    "iso:country":"US",
    "sg:address":"1113 Washington Ave",
    "sg:city":"Golden",
    "sg:classifiers":[
        {
            "category":"Government",
            "subcategory":"Office",
            "type":"Public Place"
        }
    ],
    "sg:phone":"+1 303 273 9205",
    "sg:postcode":"80401",
    "sg:province":"CO",
    "sg:tags":[
        "armed",
        "force",
        "recruiting"
    ],
    "wof:name":"US Air Force Recruiting",
    "wof:placetype":"venue"
},
  "geometry": {"coordinates":[-105.222312,39.756631],"type":"Point"}
}