{
  "type": "Feature",
  "properties": {
    "addr:full":"7114 E Warren Dr Denver CO 80224",
    "addr:housenumber":"7114",
    "addr:postcode":"80224",
    "addr:street":"E Warren Dr",
    "iso:country":"US",
    "sg:address":"7114 E Warren Dr",
    "sg:city":"Denver",
    "sg:classifiers":[
        {
            "category":"Professional",
            "subcategory":"Computer Services",
            "type":"Services"
        }
    ],
    "sg:phone":"+1 303 504 4077",
    "sg:postcode":"80224",
    "sg:province":"CO",
    "sg:tags":[
        "internet"
    ],
    "sg:website":"www.chirongroup.com",
    "wof:name":"Chiron Group Inc",
    "wof:placetype":"venue"
},
  "geometry": {"coordinates":[-104.905637,39.675553],"type":"Point"}
}