{
  "type": "Feature",
  "properties": {
    "addr:full":"34185 US Hwy 6 Edwards CO 81632",
    "addr:postcode":"34185;81632",
    "addr:street":"Us Hwy 6 Edwards",
    "iso:country":"US",
    "sg:address":"34185 US Hwy 6",
    "sg:city":"Edwards",
    "sg:classifiers":[
        {
            "category":"Restaurant",
            "type":"Food & Drink"
        }
    ],
    "sg:phone":"+1 970 926 3613",
    "sg:postcode":"81632",
    "sg:province":"CO",
    "wof:name":"Gashouse",
    "wof:placetype":"venue"
},
  "geometry": {"coordinates":[-106.594154,39.644234],"type":"Point"}
}