{
  "type": "Feature",
  "properties": {
    "addr:full":"7202 W 116th Ave Broomfield CO 80020",
    "addr:housenumber":"7202",
    "addr:postcode":"80020",
    "addr:street":"W 116Th Ave",
    "iso:country":"US",
    "sg:address":"7202 W 116th Ave",
    "sg:city":"Broomfield",
    "sg:classifiers":[
        {
            "category":"Building & Trades",
            "subcategory":"Landscaping Services",
            "type":"Services"
        }
    ],
    "sg:phone":"+1 303 466 1253",
    "sg:postcode":"80020",
    "sg:province":"CO",
    "sg:tags":[
        "landscape",
        "contractor"
    ],
    "wof:name":"Accent Landscaping Inc",
    "wof:placetype":"venue"
},
  "geometry": {"coordinates":[-105.07794199999999,39.907546],"type":"Point"}
}