{
  "type": "Feature",
  "properties": {
    "addr:full":"3850 Mariposa St Denver CO 80211",
    "addr:housenumber":"3850",
    "addr:postcode":"80211",
    "addr:street":"Mariposa St",
    "iso:country":"US",
    "sg:address":"3850 Mariposa St",
    "sg:city":"Denver",
    "sg:classifiers":[
        {
            "category":"Professional",
            "subcategory":"Business Services",
            "type":"Services"
        }
    ],
    "sg:phone":"+1 303 964 0800",
    "sg:postcode":"80211",
    "sg:province":"CO",
    "wof:name":"Real Events Solutions",
    "wof:placetype":"venue"
},
  "geometry": {"coordinates":[-105.002893,39.769889],"type":"Point"}
}