{
  "type": "Feature",
  "properties": {
    "addr:full":"105 W Main St Rangely CO 81648",
    "addr:housenumber":"105",
    "addr:postcode":"81648",
    "addr:street":"W Main St",
    "iso:country":"US",
    "sg:address":"105 W Main St",
    "sg:city":"Rangely",
    "sg:classifiers":[
        {
            "category":"Home & Garden",
            "subcategory":"Hardware",
            "type":"Retail Goods"
        }
    ],
    "sg:phone":"+1 970 675 2454",
    "sg:postcode":"81648",
    "sg:province":"CO",
    "wof:name":"Rangely True Value Hardware",
    "wof:placetype":"venue"
},
  "geometry": {"coordinates":[-108.80453900000001,40.087445],"type":"Point"}
}