{
  "type": "Feature",
  "properties": {
    "iso:country":"US",
    "sg:address":"915 E Fillmore St",
    "sg:city":"Colorado Springs",
    "sg:classifiers":[
        {
            "category":"Government",
            "subcategory":"Office",
            "type":"Public Place"
        }
    ],
    "sg:phone":"+1 719 633 7518",
    "sg:postcode":"80907",
    "sg:province":"CO",
    "sg:tags":[
        "state"
    ],
    "wof:name":"Colorado Civil Rights Div",
    "wof:placetype":"venue"
},
  "geometry": {"coordinates":[-104.807924,38.873939],"type":"Point"}
}