{
  "type": "Feature",
  "properties": {
    "iso:country":"US",
    "sg:address":"414 Main St",
    "sg:city":"Wiggins",
    "sg:phone":"+1 970 483 7337",
    "sg:postcode":"80654",
    "sg:province":"CO",
    "sg:tags":[
        "product",
        "petroleum"
    ],
    "wof:name":"Cox Oil",
    "wof:placetype":"venue"
},
  "geometry": {"coordinates":[-104.074479,40.227236],"type":"Point"}
}