{
  "type": "Feature",
  "properties": {
    "iso:country":"US",
    "sg:address":"329 Detroit St",
    "sg:city":"Denver",
    "sg:classifiers":[
        {
            "category":"Real Estate",
            "subcategory":"Architect",
            "type":"Services"
        }
    ],
    "sg:phone":"+1 303 355 7999",
    "sg:postcode":"80206",
    "sg:province":"CO",
    "wof:name":"Tony Garza Architect",
    "wof:placetype":"venue"
},
  "geometry": {"coordinates":[-104.954702,39.722098],"type":"Point"}
}