{
  "type": "Feature",
  "properties": {
    "iso:country":"US",
    "sg:address":"440 Lipan Street",
    "sg:city":"Denver",
    "sg:classifiers":[
        {
            "category":"Building & Trades",
            "subcategory":"Construction",
            "type":"Services"
        }
    ],
    "sg:phone":"+1 303 477 8110",
    "sg:postcode":"80204",
    "sg:province":"CO",
    "sg:tags":[
        "contractor"
    ],
    "wof:name":"Engineered Construction Systems",
    "wof:placetype":"venue"
},
  "geometry": {"coordinates":[-105.001476,39.723475],"type":"Point"}
}