{
  "type": "Feature",
  "properties": {
    "addr:full":"14200 E Arapahoe Rd Centennial CO 80112",
    "addr:housenumber":"14200",
    "addr:postcode":"80112",
    "addr:street":"E Arapahoe Rd",
    "iso:country":"US",
    "sg:address":"14200 E Arapahoe Rd",
    "sg:city":"Centennial",
    "sg:classifiers":[
        {
            "category":"Professional",
            "type":"Services"
        }
    ],
    "sg:phone":"+1 720 870 6750",
    "sg:postcode":"80112",
    "sg:province":"CO",
    "sg:tags":[
        "establishment"
    ],
    "wof:name":"Columbia Psl Centennial",
    "wof:placetype":"venue"
},
  "geometry": {"coordinates":[-104.823127,39.594997],"type":"Point"}
}