{
  "type": "Feature",
  "properties": {
    "iso:country":"US",
    "sg:address":"4343 O St",
    "sg:city":"Greeley",
    "sg:classifiers":[
        {
            "category":"Farming",
            "subcategory":"Livestock Farm",
            "type":"Manufacturing & Wholesale Goods"
        }
    ],
    "sg:phone":"+1 970 356 7466",
    "sg:postcode":"80631",
    "sg:province":"CO",
    "sg:tags":[
        "animal",
        "general"
    ],
    "wof:name":"Dickens Jacy",
    "wof:placetype":"venue"
},
  "geometry": {"coordinates":[-104.74532600000001,40.455756],"type":"Point"}
}