{
  "type": "Feature",
  "properties": {
    "addr:full":"655 Broadway Denver CO 80203",
    "addr:housenumber":"655",
    "addr:postcode":"80203",
    "addr:street":"Broadway",
    "iso:country":"US",
    "sg:address":"655 Broadway",
    "sg:city":"Denver",
    "sg:classifiers":[
        {
            "category":"Banks & Credit Unions",
            "subcategory":"Bank",
            "type":"Services"
        }
    ],
    "sg:phone":"+1 303 534 4388",
    "sg:postcode":"80203",
    "sg:province":"CO",
    "sg:tags":[
        "loan",
        "real estate"
    ],
    "sg:website":"www.ahmweb.com",
    "wof:name":"American Home Mortgage",
    "wof:placetype":"venue"
},
  "geometry": {"coordinates":[-104.98750699999999,39.725916],"type":"Point"}
}