{
  "type": "Feature",
  "properties": {
    "addr:full":"830 Macon Ave Cotopaxi CO 81212",
    "addr:housenumber":"830",
    "addr:postcode":"81212",
    "addr:street":"Macon Ave",
    "iso:country":"US",
    "sg:address":"830 Macon Ave",
    "sg:city":"Cotopaxi",
    "sg:classifiers":[
        {
            "category":"Autos & Motor Vehicles",
            "subcategory":"Motorcycle Sales",
            "type":"Retail Goods"
        }
    ],
    "sg:phone":"+1 719 275 5730",
    "sg:postcode":"81212",
    "sg:province":"CO",
    "sg:tags":[
        "scooter"
    ],
    "wof:name":"Panzer Motorcycle Works",
    "wof:placetype":"venue"
},
  "geometry": {"coordinates":[-105.236492,38.443565],"type":"Point"}
}