{
  "type": "Feature",
  "properties": {
    "addr:full":"1765 S 8th St Colorado Springs CO 80906",
    "addr:housenumber":"1765",
    "addr:postcode":"80906",
    "addr:street":"S 8Th St",
    "iso:country":"US",
    "sg:address":"1765 S 8th St",
    "sg:city":"Colorado Springs",
    "sg:classifiers":[
        {
            "category":"Professional",
            "subcategory":"Lawyer & Legal Services",
            "type":"Services"
        }
    ],
    "sg:phone":"+1 719 475 7474",
    "sg:postcode":"80906",
    "sg:province":"CO",
    "sg:tags":[
        "attorney"
    ],
    "wof:name":"Robert C Irwin",
    "wof:placetype":"venue"
},
  "geometry": {"coordinates":[-104.84075900000001,38.805929],"type":"Point"}
}