{
  "type": "Feature",
  "properties": {
    "addr:full":"2112 E Wesley Avenue Denver CO 80210",
    "addr:housenumber":"2112",
    "addr:postcode":"80210",
    "addr:street":"E Wesley Avenue",
    "iso:country":"US",
    "sg:address":"2112 E Wesley Avenue",
    "sg:city":"Denver",
    "sg:classifiers":[
        {
            "category":"Education",
            "subcategory":"University",
            "type":"Public Place"
        }
    ],
    "sg:phone":"+1 303 871 2238",
    "sg:postcode":"80210",
    "sg:province":"CO",
    "sg:tags":[
        "college"
    ],
    "wof:name":"University of Denver",
    "wof:placetype":"venue"
},
  "geometry": {"coordinates":[-104.963137,39.673046],"type":"Point"}
}