{
  "type": "Feature",
  "properties": {
    "iso:country":"US",
    "sg:address":"830 S Hancock Ave",
    "sg:city":"Colorado Springs",
    "sg:classifiers":[
        {
            "category":"Shopping",
            "type":"Retail Goods"
        }
    ],
    "sg:phone":"+1 719 473 2737",
    "sg:postcode":"80903",
    "sg:province":"CO",
    "sg:tags":[
        "manufacture",
        "monument"
    ],
    "wof:name":"Rocky Mountain Memorials Inc",
    "wof:placetype":"venue"
},
  "geometry": {"coordinates":[-104.80443099999999,38.821546],"type":"Point"}
}