{
  "type": "Feature",
  "properties": {
    "iso:country":"US",
    "sg:address":"42 Holmes Gulch Way",
    "sg:city":"Bailey",
    "sg:classifiers":[
        {
            "category":"Professional",
            "type":"Services"
        }
    ],
    "sg:phone":"+1 303 838 1443",
    "sg:postcode":"80421",
    "sg:province":"CO",
    "wof:name":"Steve Vick",
    "wof:placetype":"venue"
},
  "geometry": {"coordinates":[-105.398906,39.412362],"type":"Point"}
}