{
  "type": "Feature",
  "properties": {
    "addr:full":"312 Mount View Ln Colorado Springs CO 80907",
    "addr:housenumber":"312",
    "addr:postcode":"80907",
    "addr:street":"Mount View Ln",
    "iso:country":"US",
    "sg:address":"312 Mount View Ln",
    "sg:city":"Colorado Springs",
    "sg:classifiers":[
        {
            "category":"Food & Beverages",
            "subcategory":"Groceries & Convenience Stores",
            "type":"Retail Goods"
        }
    ],
    "sg:phone":"+1 719 590 7683",
    "sg:postcode":"80907",
    "sg:province":"CO",
    "sg:website":"www.7-eleven.com",
    "wof:name":"7-Eleven",
    "wof:placetype":"venue"
},
  "geometry": {"coordinates":[-104.816258,38.889521],"type":"Point"}
}