{
  "type": "Feature",
  "properties": {
    "addr:full":"804 N Cascade Ave Montrose CO 81401",
    "addr:housenumber":"804",
    "addr:postcode":"81401",
    "addr:street":"N Cascade Ave",
    "iso:country":"US",
    "sg:address":"804 N Cascade Ave",
    "sg:city":"Montrose",
    "sg:classifiers":[
        {
            "category":"Professional",
            "type":"Services"
        }
    ],
    "sg:phone":"+1 970 240 1325",
    "sg:postcode":"81401",
    "sg:province":"CO",
    "sg:tags":[
        "establishment"
    ],
    "wof:name":"Community Options",
    "wof:placetype":"venue"
},
  "geometry": {"coordinates":[-107.884263,38.486365],"type":"Point"}
}