{
  "type": "Feature",
  "properties": {
    "iso:country":"US",
    "sg:address":"15210 Diamondhead Ct",
    "sg:city":"Colorado Springs",
    "sg:classifiers":[
        {
            "category":"Social Services",
            "type":"Services"
        }
    ],
    "sg:phone":"+1 719 488 2993",
    "sg:postcode":"80921",
    "sg:province":"CO",
    "sg:tags":[
        "organization",
        "welfare"
    ],
    "sg:website":"www.alphacommunities.org",
    "wof:name":"Alpha Communities Inc",
    "wof:placetype":"venue"
},
  "geometry": {"coordinates":[-104.818923,39.05259],"type":"Point"}
}