{
  "type": "Feature",
  "properties": {
    "addr:full":"1570 E Easter Ave Centennial CO 80122",
    "addr:housenumber":"1570",
    "addr:postcode":"80122",
    "addr:street":"E Easter Ave",
    "iso:country":"US",
    "sg:address":"1570 E Easter Ave",
    "sg:city":"Centennial",
    "sg:classifiers":[
        {
            "category":"Real Estate",
            "subcategory":"Real Estate Agent",
            "type":"Services"
        }
    ],
    "sg:phone":"+1 303 738 0197",
    "sg:postcode":"80122",
    "sg:province":"CO",
    "sg:tags":[
        "investment"
    ],
    "wof:name":"Nilges Commercial Realtors",
    "wof:placetype":"venue"
},
  "geometry": {"coordinates":[-104.96956900000001,39.58864],"type":"Point"}
}