{
  "type": "Feature",
  "properties": {
    "iso:country":"US",
    "sg:address":"118 Bradish Ave",
    "sg:city":"La Junta",
    "sg:classifiers":[
        {
            "category":"Retail",
            "subcategory":"Auto Repair",
            "type":"Services"
        }
    ],
    "sg:phone":"+1 719 384 8789",
    "sg:postcode":"81050",
    "sg:province":"CO",
    "sg:tags":[
        "automobile",
        "electric"
    ],
    "wof:name":"LA Junta Auto Electric",
    "wof:placetype":"venue"
},
  "geometry": {"coordinates":[-103.53334700000001,37.98777],"type":"Point"}
}