{
  "type": "Feature",
  "properties": {
    "addr:full":"9500 W 49th Ave Wheat Ridge CO 80033",
    "addr:housenumber":"9500",
    "addr:postcode":"80033",
    "addr:street":"W 49Th Ave",
    "iso:country":"US",
    "sg:address":"9500 W 49th Ave",
    "sg:city":"Wheat Ridge",
    "sg:classifiers":[
        {
            "category":"Professional",
            "subcategory":"Advertising",
            "type":"Services"
        }
    ],
    "sg:phone":"+1 303 432 7541",
    "sg:postcode":"80033",
    "sg:province":"CO",
    "sg:tags":[
        "distributing",
        "sample"
    ],
    "wof:name":"Auto Mart",
    "wof:placetype":"venue"
},
  "geometry": {"coordinates":[-105.10396,39.785593],"type":"Point"}
}