{
  "type": "Feature",
  "properties": {
    "iso:country":"US",
    "sg:address":"9684 E Arapahoe Rd",
    "sg:city":"Greenwood Vlg",
    "sg:classifiers":[
        {
            "category":"Personal",
            "subcategory":"Beauty Salon",
            "type":"Services"
        }
    ],
    "sg:phone":"+1 303 708 1251",
    "sg:postcode":"80112",
    "sg:province":"CO",
    "sg:tags":[
        "manicuring"
    ],
    "wof:name":"Pronails",
    "wof:placetype":"venue"
},
  "geometry": {"coordinates":[-104.87798600000001,39.594963],"type":"Point"}
}