{
  "type": "Feature",
  "properties": {
    "iso:country":"US",
    "sg:address":"2692 Hwy 50",
    "sg:city":"Grand Junction",
    "sg:classifiers":[
        {
            "category":"Shopping",
            "subcategory":"Crafts & Fabrics",
            "type":"Retail Goods"
        }
    ],
    "sg:phone":"+1 970 241 5080",
    "sg:postcode":"81503",
    "sg:province":"CO",
    "sg:tags":[
        "sewing",
        "yarn"
    ],
    "wof:name":"Yarn Store",
    "wof:placetype":"venue"
},
  "geometry": {"coordinates":[-108.55273,39.043237],"type":"Point"}
}