{
  "type": "Feature",
  "properties": {
    "iso:country":"US",
    "sg:address":"1685 W Uintah St",
    "sg:city":"Colorado Springs",
    "sg:classifiers":[
        {
            "category":"Organizations",
            "subcategory":"Religious Organization",
            "type":"Services"
        }
    ],
    "sg:phone":"+1 719 633 0453",
    "sg:postcode":"80904",
    "sg:province":"CO",
    "sg:tags":[
        "church"
    ],
    "wof:name":"Eckankar Of Colorado Springs",
    "wof:placetype":"venue"
},
  "geometry": {"coordinates":[-104.844499,38.847941],"type":"Point"}
}