{
  "type": "Feature",
  "properties": {
    "addr:full":"803 Main St Ouray CO 81427",
    "addr:housenumber":"803",
    "addr:postcode":"81427",
    "addr:street":"Main St",
    "iso:country":"US",
    "sg:address":"803 Main St",
    "sg:city":"Ouray",
    "sg:classifiers":[
        {
            "category":"Restaurant",
            "type":"Food & Drink"
        }
    ],
    "sg:phone":"+1 970 325 4958",
    "sg:postcode":"81427",
    "sg:province":"CO",
    "sg:tags":[
        "delicatessen"
    ],
    "wof:name":"Timberline Deli Of Ouray",
    "wof:placetype":"venue"
},
  "geometry": {"coordinates":[-107.671396,38.025976],"type":"Point"}
}