{
  "type": "Feature",
  "properties": {
    "addr:full":"992 N Potomac Cir Aurora CO 80011",
    "addr:housenumber":"992",
    "addr:postcode":"80011",
    "addr:street":"N Potomac Cir",
    "iso:country":"US",
    "sg:address":"992 N Potomac Cir",
    "sg:city":"Aurora",
    "sg:classifiers":[
        {
            "category":"Government",
            "subcategory":"Police Station",
            "type":"Public Place"
        }
    ],
    "sg:phone":"+1 303 344 0278",
    "sg:postcode":"80011",
    "sg:province":"CO",
    "sg:tags":[
        "department"
    ],
    "wof:name":"Rocky Mountain Law Enforcement",
    "wof:placetype":"venue"
},
  "geometry": {"coordinates":[-104.827805,39.731921],"type":"Point"}
}