{
  "type": "Feature",
  "properties": {
    "addr:full":"9365 Elm Ct Denver CO 80260",
    "addr:housenumber":"9365",
    "addr:postcode":"80260",
    "addr:street":"Elm Ct",
    "iso:country":"US",
    "sg:address":"9365 Elm Ct",
    "sg:city":"Denver",
    "sg:classifiers":[
        {
            "category":"Retail",
            "subcategory":"Auto Repair",
            "type":"Services"
        }
    ],
    "sg:phone":"+1 303 426 8915",
    "sg:postcode":"80260",
    "sg:province":"CO",
    "sg:tags":[
        "repairing",
        "automobile"
    ],
    "wof:name":"B & T Auto & Body Repair",
    "wof:placetype":"venue"
},
  "geometry": {"coordinates":[-105.02278,39.865974],"type":"Point"}
}