{
  "type": "Feature",
  "properties": {
    "iso:country":"US",
    "sg:address":"137 W Colorado Ave",
    "sg:city":"Telluride",
    "sg:classifiers":[
        {
            "category":"Real Estate",
            "subcategory":"Real Estate Agent",
            "type":"Services"
        }
    ],
    "sg:phone":"+1 970 728 0961",
    "sg:postcode":"81435",
    "sg:province":"CO",
    "wof:name":"A & K Destinations",
    "wof:placetype":"venue"
},
  "geometry": {"coordinates":[-107.811566,37.937438],"type":"Point"}
}