{
  "type": "Feature",
  "properties": {
    "iso:country":"US",
    "sg:address":"1902 E 5th St",
    "sg:city":"Pueblo",
    "sg:classifiers":[
        {
            "category":"Bars & Pubs",
            "type":"Food & Drink"
        }
    ],
    "sg:phone":"+1 719 542 1278",
    "sg:postcode":"81001",
    "sg:province":"CO",
    "sg:tags":[
        "dance",
        "drinking"
    ],
    "wof:name":"Arcadia Dance Hall Inc",
    "wof:placetype":"venue"
},
  "geometry": {"coordinates":[-104.572951,38.272436],"type":"Point"}
}