{
  "type": "Feature",
  "properties": {
    "addr:full":"437 Porphyry Rd Gypsum CO 81637",
    "addr:housenumber":"437",
    "addr:postcode":"81637",
    "addr:street":"Porphyry Rd",
    "iso:country":"US",
    "sg:address":"437 Porphyry Rd",
    "sg:city":"Gypsum",
    "sg:classifiers":[
        {
            "category":"Utilities",
            "subcategory":"Refuse",
            "type":"Services"
        }
    ],
    "sg:phone":"+1 970 524 9523",
    "sg:postcode":"81637",
    "sg:province":"CO",
    "sg:tags":[
        "garbage",
        "collection"
    ],
    "wof:name":"Gypsum Sanitation District",
    "wof:placetype":"venue"
},
  "geometry": {"coordinates":[-106.958961,39.649729],"type":"Point"}
}