{
  "type": "Feature",
  "properties": {
    "addr:full":"601 Pitkin Ave Grand Junction CO 81501",
    "addr:housenumber":"601",
    "addr:postcode":"81501",
    "addr:street":"Pitkin Ave",
    "iso:country":"US",
    "sg:address":"601 Pitkin Ave",
    "sg:city":"Grand Junction",
    "sg:classifiers":[
        {
            "category":"Wholesale",
            "subcategory":"Machinery & Supplies",
            "type":"Manufacturing & Wholesale Goods"
        }
    ],
    "sg:phone":"+1 970 242 7250",
    "sg:postcode":"81501",
    "sg:province":"CO",
    "sg:tags":[
        "janitor"
    ],
    "sg:website":"www.mesasupply.com",
    "wof:name":"Mesa Supply",
    "wof:placetype":"venue"
},
  "geometry": {"coordinates":[-108.561055,39.064381],"type":"Point"}
}