{
  "type": "Feature",
  "properties": {
    "addr:full":"950 E Harvard Ave Denver CO 80210",
    "addr:housenumber":"950",
    "addr:postcode":"80210",
    "addr:street":"E Harvard Ave",
    "iso:country":"US",
    "sg:address":"950 E Harvard Ave",
    "sg:city":"Denver",
    "sg:classifiers":[
        {
            "category":"Social Services",
            "subcategory":"Adult Care",
            "type":"Services"
        },
        {
            "category":"Health Services",
            "subcategory":"Hospital",
            "type":"Services"
        }
    ],
    "sg:phone":"+1 303 777 0303",
    "sg:postcode":"80210",
    "sg:province":"CO",
    "sg:tags":[
        "residential",
        "mental"
    ],
    "wof:name":"Community Care Corporation",
    "wof:placetype":"venue"
},
  "geometry": {"coordinates":[-104.974749,39.67121],"type":"Point"}
}