{
  "type": "Feature",
  "properties": {
    "addr:full":"6985 W Mexico Dr Lakewood CO 80232",
    "addr:housenumber":"6985",
    "addr:postcode":"80232",
    "addr:street":"W Mexico Dr",
    "iso:country":"US",
    "sg:address":"6985 W Mexico Dr",
    "sg:city":"Lakewood",
    "sg:classifiers":[
        {
            "category":"Retail",
            "subcategory":"Animal Services",
            "type":"Services"
        }
    ],
    "sg:phone":"+1 303 987 3261",
    "sg:postcode":"80232",
    "sg:province":"CO",
    "sg:tags":[
        "pet",
        "boarding",
        "sitting"
    ],
    "wof:name":"Quality Pet Care",
    "wof:placetype":"venue"
},
  "geometry": {"coordinates":[-105.07288,39.686526],"type":"Point"}
}