{
  "type": "Feature",
  "properties": {
    "iso:country":"US",
    "sg:address":"2527 S Oswego St",
    "sg:city":"Aurora",
    "sg:classifiers":[
        {
            "category":"Building & Trades",
            "subcategory":"Construction",
            "type":"Services"
        }
    ],
    "sg:phone":"+1 303 755 6915",
    "sg:postcode":"80014",
    "sg:province":"CO",
    "sg:tags":[
        "house"
    ],
    "wof:name":"Wildcat Homes Inc",
    "wof:placetype":"venue"
},
  "geometry": {"coordinates":[-104.85006799999999,39.670353],"type":"Point"}
}