{
  "type": "Feature",
  "properties": {
    "addr:full":"30 Cook Ct Hudson CO 80642",
    "addr:housenumber":"30",
    "addr:postcode":"80642",
    "addr:street":"Cook Ct",
    "iso:country":"US",
    "sg:address":"30 Cook Ct",
    "sg:city":"Hudson",
    "sg:classifiers":[
        {
            "category":"Professional",
            "type":"Services"
        }
    ],
    "sg:phone":"+1 303 536 4044",
    "sg:postcode":"80642",
    "sg:province":"CO",
    "wof:name":"John R Palermo",
    "wof:placetype":"venue"
},
  "geometry": {"coordinates":[-104.62805,40.071188],"type":"Point"}
}