{
  "type": "Feature",
  "properties": {
    "addr:full":"290 E Stanford Ave Englewood CO 80113",
    "addr:housenumber":"290",
    "addr:postcode":"80113",
    "addr:street":"E Stanford Ave",
    "iso:country":"US",
    "sg:address":"290 E Stanford Ave",
    "sg:city":"Englewood",
    "sg:classifiers":[
        {
            "category":"Professional",
            "type":"Services"
        }
    ],
    "sg:phone":"+1 303 761 2833",
    "sg:postcode":"80113",
    "sg:province":"CO",
    "wof:name":"Christian Singles Volleyball",
    "wof:placetype":"venue"
},
  "geometry": {"coordinates":[-104.98510400000001,39.634873],"type":"Point"}
}