{
  "type": "Feature",
  "properties": {
    "iso:country":"US",
    "sg:address":"4892 N Townsend Ave",
    "sg:city":"Montrose",
    "sg:classifiers":[
        {
            "category":"Building & Trades",
            "subcategory":"Construction",
            "type":"Services"
        }
    ],
    "sg:phone":"+1 970 249 7888",
    "sg:postcode":"81401",
    "sg:province":"CO",
    "sg:tags":[
        "concrete",
        "contractor"
    ],
    "wof:name":"Baird Concrete Inc",
    "wof:placetype":"venue"
},
  "geometry": {"coordinates":[-107.925422,38.521725],"type":"Point"}
}