{
  "type": "Feature",
  "properties": {
    "iso:country":"US",
    "sg:address":"20005 Elk Head Ln",
    "sg:city":"Steamboat Springs",
    "sg:classifiers":[
        {
            "category":"Shopping",
            "subcategory":"Bicycles & Sporting Goods",
            "type":"Retail Goods"
        }
    ],
    "sg:phone":"+1 970 871 7929",
    "sg:postcode":"80487",
    "sg:province":"CO",
    "wof:name":"Flat Tops Saddlery",
    "wof:placetype":"venue"
},
  "geometry": {"coordinates":[-106.90907900000001,40.561143],"type":"Point"}
}