{
  "type": "Feature",
  "properties": {
    "iso:country":"US",
    "sg:address":"4518 Bluefin Ct",
    "sg:city":"Fort Collins",
    "sg:classifiers":[
        {
            "category":"Shopping",
            "subcategory":"Gifts & Souvenirs",
            "type":"Retail Goods"
        }
    ],
    "sg:phone":"+1 970 282 9746",
    "sg:postcode":"80525",
    "sg:province":"CO",
    "wof:name":"Etc Etc",
    "wof:placetype":"venue"
},
  "geometry": {"coordinates":[-105.05874,40.526199],"type":"Point"}
}