{
  "type": "Feature",
  "properties": {
    "iso:country":"US",
    "sg:address":"1412 Elm Ave",
    "sg:city":"Canon City",
    "sg:classifiers":[
        {
            "category":"Building & Trades",
            "subcategory":"Construction",
            "type":"Services"
        }
    ],
    "sg:phone":"+1 719 269 9522",
    "sg:postcode":"81212",
    "sg:province":"CO",
    "sg:tags":[
        "contractor"
    ],
    "wof:name":"All American Gutter Man",
    "wof:placetype":"venue"
},
  "geometry": {"coordinates":[-105.216859,38.424782],"type":"Point"}
}