{
  "type": "Feature",
  "properties": {
    "iso:country":"US",
    "sg:address":"5350 Leetsdale Drive",
    "sg:city":"Denver",
    "sg:classifiers":[
        {
            "category":"Real Estate",
            "subcategory":"Real Estate Services",
            "type":"Services"
        }
    ],
    "sg:phone":"+1 303 377 1986",
    "sg:postcode":"80246",
    "sg:province":"CO",
    "wof:name":"Forest Park Realty Investments",
    "wof:placetype":"venue"
},
  "geometry": {"coordinates":[-104.931669,39.699447],"type":"Point"}
}