{
  "type": "Feature",
  "properties": {
    "addr:full":"7395 E Orchard Rd Greenwood Vlg CO 80111",
    "addr:housenumber":"7395",
    "addr:postcode":"co 80111",
    "addr:street":"E Orchard Rd",
    "iso:country":"US",
    "sg:address":"7395 E Orchard Rd",
    "sg:city":"Greenwood Vlg",
    "sg:classifiers":[
        {
            "category":"Insurance",
            "subcategory":"Insurance Agent",
            "type":"Services"
        }
    ],
    "sg:phone":"+1 720 280 0430",
    "sg:postcode":"80111",
    "sg:province":"CO",
    "wof:name":"Dan Rouse",
    "wof:placetype":"venue"
},
  "geometry": {"coordinates":[-104.90032100000001,39.609632],"type":"Point"}
}