{
  "type": "Feature",
  "properties": {
    "iso:country":"US",
    "sg:address":"80 Meadow Ranch",
    "sg:city":"Snowmass Village",
    "sg:classifiers":[
        {
            "category":"Building & Trades",
            "subcategory":"Construction",
            "type":"Services"
        }
    ],
    "sg:phone":"+1 970 923 3488",
    "sg:postcode":"81615",
    "sg:province":"CO",
    "sg:tags":[
        "home",
        "builder"
    ],
    "wof:name":"Mike Potter Builder Inc",
    "wof:placetype":"venue"
},
  "geometry": {"coordinates":[-106.935436,39.213308],"type":"Point"}
}