{
  "type": "Feature",
  "properties": {
    "addr:full":"697 E Bridge St Brighton CO 80601",
    "addr:housenumber":"697",
    "addr:postcode":"80601",
    "addr:street":"E Bridge St",
    "iso:country":"US",
    "sg:address":"697 E Bridge St",
    "sg:city":"Brighton",
    "sg:classifiers":[
        {
            "category":"Personal",
            "subcategory":"Beauty Salon",
            "type":"Services"
        }
    ],
    "sg:phone":"+1 303 655 1443",
    "sg:postcode":"80601",
    "sg:province":"CO",
    "sg:tags":[
        "shop"
    ],
    "wof:name":"Splashes Color Hair Design LLC",
    "wof:placetype":"venue"
},
  "geometry": {"coordinates":[-104.81504200000001,39.986868],"type":"Point"}
}