{
  "type": "Feature",
  "properties": {
    "addr:full":"1525 Spruce St Boulder CO 80302",
    "addr:housenumber":"1525",
    "addr:postcode":"80302",
    "addr:street":"Spruce St",
    "iso:country":"US",
    "sg:address":"1525 Spruce St",
    "sg:city":"Boulder",
    "sg:classifiers":[
        {
            "category":"Banks & Credit Unions",
            "subcategory":"Bank",
            "type":"Services"
        }
    ],
    "sg:phone":"+1 303 440 6900",
    "sg:postcode":"80302",
    "sg:province":"CO",
    "sg:tags":[
        "loan",
        "real estate"
    ],
    "sg:website":"www.mortgageamericainc.com",
    "wof:name":"Mortgage America",
    "wof:placetype":"venue"
},
  "geometry": {"coordinates":[-105.27535399999999,40.019991],"type":"Point"}
}