{
  "type": "Feature",
  "properties": {
    "addr:full":"31000 Bryan Cir Pueblo CO 81001",
    "addr:postcode":"31000;81001",
    "addr:street":"Bryan Cir",
    "iso:country":"US",
    "sg:address":"31000 Bryan Cir",
    "sg:city":"Pueblo",
    "sg:phone":"+1 719 948 2447",
    "sg:postcode":"81001",
    "sg:province":"CO",
    "sg:tags":[
        "aircraft",
        "refueling"
    ],
    "wof:name":"Flower Aviation of Pueblo",
    "wof:placetype":"venue"
},
  "geometry": {"coordinates":[-104.49379999999999,38.283404],"type":"Point"}
}