{
  "type": "Feature",
  "properties": {
    "addr:full":"718 Sherman St Denver CO 80203",
    "addr:housenumber":"718",
    "addr:postcode":"80203",
    "addr:street":"Sherman St",
    "iso:country":"US",
    "sg:address":"718 Sherman St",
    "sg:city":"Denver",
    "sg:classifiers":[
        {
            "category":"Manufacturing",
            "subcategory":"Metals",
            "type":"Manufacturing & Wholesale Goods"
        }
    ],
    "sg:phone":"+1 303 837 8490",
    "sg:postcode":"80203",
    "sg:province":"CO",
    "sg:tags":[
        "tool",
        "mfg"
    ],
    "wof:name":"Not Stooped Garden Tool LLC",
    "wof:placetype":"venue"
},
  "geometry": {"coordinates":[-104.984797,39.728741],"type":"Point"}
}