{
  "type": "Feature",
  "properties": {
    "iso:country":"US",
    "sg:address":"57 Fairway Ln",
    "sg:city":"Littleton",
    "sg:classifiers":[
        {
            "category":"Real Estate",
            "subcategory":"Real Estate Agent",
            "type":"Services"
        }
    ],
    "sg:phone":"+1 303 797 0838",
    "sg:postcode":"80123",
    "sg:province":"CO",
    "wof:name":"Hambrook Resources Inc",
    "wof:placetype":"venue"
},
  "geometry": {"coordinates":[-105.031513,39.596241],"type":"Point"}
}