{
  "type": "Feature",
  "properties": {
    "addr:full":"1527 E Bridge St Brighton CO 80601",
    "addr:housenumber":"1527",
    "addr:postcode":"80601",
    "addr:street":"E Bridge St",
    "iso:country":"US",
    "sg:address":"1527 E Bridge St",
    "sg:city":"Brighton",
    "sg:classifiers":[
        {
            "category":"Government",
            "subcategory":"Office",
            "type":"Public Place"
        }
    ],
    "sg:phone":"+1 303 659 5055",
    "sg:postcode":"80601",
    "sg:province":"CO",
    "sg:tags":[
        "transportation"
    ],
    "wof:name":"Drivers License Office",
    "wof:placetype":"venue"
},
  "geometry": {"coordinates":[-104.801396,39.986867],"type":"Point"}
}