{
  "type": "Feature",
  "properties": {
    "iso:country":"US",
    "sg:address":"37800 Buffalo Grass Dr",
    "sg:city":"Elizabeth",
    "sg:classifiers":[
        {
            "category":"Recreation",
            "type":"Entertainment"
        },
        {
            "category":"Retail",
            "subcategory":"Animal Services",
            "type":"Services"
        }
    ],
    "sg:phone":"+1 303 646 0581",
    "sg:postcode":"80107",
    "sg:province":"CO",
    "sg:tags":[
        "stable"
    ],
    "wof:name":"Gambel Oaks Equestrian Center",
    "wof:placetype":"venue"
},
  "geometry": {"coordinates":[-104.636664,39.4167],"type":"Point"}
}