{
  "type": "Feature",
  "properties": {
    "iso:country":"US",
    "sg:address":"3214 S Wadsworth Blvd",
    "sg:city":"Lakewood",
    "sg:classifiers":[
        {
            "category":"Restaurant",
            "type":"Food & Drink"
        }
    ],
    "sg:phone":"+1 303 988 1748",
    "sg:postcode":"80227",
    "sg:province":"CO",
    "wof:name":"Spicy Mexican Grill",
    "wof:placetype":"venue"
},
  "geometry": {"coordinates":[-105.08127399999999,39.6562],"type":"Point"}
}