{
  "type": "Feature",
  "properties": {
    "addr:full":"716 E Fontanero St Colorado Springs CO 80907",
    "addr:housenumber":"716",
    "addr:postcode":"80907",
    "addr:street":"E Fontanero St",
    "iso:country":"US",
    "sg:address":"716 E Fontanero St",
    "sg:city":"Colorado Springs",
    "sg:classifiers":[
        {
            "category":"Professional",
            "subcategory":"Lawyer & Legal Services",
            "type":"Services"
        }
    ],
    "sg:phone":"+1 719 473 8086",
    "sg:postcode":"80907",
    "sg:province":"CO",
    "sg:tags":[
        "attorney"
    ],
    "wof:name":"Ross A Wilson",
    "wof:placetype":"venue"
},
  "geometry": {"coordinates":[-104.810396,38.860335],"type":"Point"}
}