{
  "type": "Feature",
  "properties": {
    "addr:full":"920 Tammany Dr Colorado Springs CO 80916",
    "addr:housenumber":"920",
    "addr:postcode":"80916",
    "addr:street":"Tammany Dr",
    "iso:country":"US",
    "sg:address":"920 Tammany Dr",
    "sg:city":"Colorado Springs",
    "sg:classifiers":[
        {
            "category":"Shopping",
            "subcategory":"Clothing, Apparel, & Fashions",
            "type":"Retail Goods"
        }
    ],
    "sg:phone":"+1 719 574 4380",
    "sg:postcode":"80916",
    "sg:province":"CO",
    "sg:tags":[
        "theatrical",
        "costume"
    ],
    "wof:name":"Adams Costume Closet",
    "wof:placetype":"venue"
},
  "geometry": {"coordinates":[-104.74515599999999,38.820095],"type":"Point"}
}