{
  "type": "Feature",
  "properties": {
    "iso:country":"US",
    "sg:address":"950 17th St",
    "sg:city":"Denver",
    "sg:classifiers":[
        {
            "category":"Professional",
            "subcategory":"Lawyer & Legal Services",
            "type":"Services"
        }
    ],
    "sg:phone":"+1 303 860 8800",
    "sg:postcode":"80202",
    "sg:province":"CO",
    "sg:tags":[
        "attorney"
    ],
    "wof:name":"Mark A Dedrickson Law Offices",
    "wof:placetype":"venue"
},
  "geometry": {"coordinates":[-104.993342,39.747785],"type":"Point"}
}