{
  "type": "Feature",
  "properties": {
    "addr:full":"9078 E Westview Rd Lone Tree CO 80124",
    "addr:housenumber":"9078",
    "addr:postcode":"80124",
    "addr:street":"E Westview Rd",
    "iso:country":"US",
    "sg:address":"9078 E Westview Rd",
    "sg:city":"Lone Tree",
    "sg:classifiers":[
        {
            "category":"Professional",
            "type":"Services"
        }
    ],
    "sg:phone":"+1 303 649 9496",
    "sg:postcode":"80124",
    "sg:province":"CO",
    "sg:tags":[
        "establishment"
    ],
    "wof:name":"Casual Male Big & Tall",
    "wof:placetype":"venue"
},
  "geometry": {"coordinates":[-104.88326000000001,39.56479],"type":"Point"}
}