{
  "type": "Feature",
  "properties": {
    "addr:full":"400 West Ave Brush CO 80723",
    "addr:housenumber":"400",
    "addr:postcode":"80723",
    "addr:street":"West Ave",
    "iso:country":"US",
    "sg:address":"400 West Ave",
    "sg:city":"Brush",
    "sg:classifiers":[
        {
            "category":"Education",
            "subcategory":"School",
            "type":"Public Place"
        }
    ],
    "sg:phone":"+1 970 842 5171",
    "sg:postcode":"80723",
    "sg:province":"CO",
    "wof:name":"Brush High School",
    "wof:placetype":"venue"
},
  "geometry": {"coordinates":[-103.638116,40.257847],"type":"Point"}
}