{
  "type": "Feature",
  "properties": {
    "iso:country":"US",
    "sg:address":"7505 Tudor Rd",
    "sg:city":"Colorado Springs",
    "sg:classifiers":[
        {
            "category":"Food & Beverages",
            "subcategory":"Specialty",
            "type":"Retail Goods"
        },
        {
            "category":"Shopping",
            "subcategory":"Gifts & Souvenirs",
            "type":"Retail Goods"
        }
    ],
    "sg:phone":"+1 719 593 9458",
    "sg:postcode":"80919",
    "sg:province":"CO",
    "sg:tags":[
        "basket",
        "parcel"
    ],
    "wof:name":"Cachet Baskets Company",
    "wof:placetype":"venue"
},
  "geometry": {"coordinates":[-104.81737800000001,38.940369],"type":"Point"}
}