{
  "type": "Feature",
  "properties": {
    "iso:country":"US",
    "sg:address":"2261 Broadway",
    "sg:city":"Grand Junction",
    "sg:classifiers":[
        {
            "category":"Professional",
            "subcategory":"Management & Consulting",
            "type":"Services"
        }
    ],
    "sg:phone":"+1 970 242 3379",
    "sg:postcode":"81503",
    "sg:province":"CO",
    "sg:tags":[
        "planner"
    ],
    "wof:name":"Edward Delduca & Assoc",
    "wof:placetype":"venue"
},
  "geometry": {"coordinates":[-108.63359,39.077448],"type":"Point"}
}