{
  "type": "Feature",
  "properties": {
    "addr:full":"1508 9th St Rock Springs CO 82901",
    "addr:housenumber":"1508",
    "addr:postcode":"82901",
    "addr:street":"9Th St",
    "iso:country":"US",
    "sg:address":"1508 9th St",
    "sg:city":"Rock Springs",
    "sg:classifiers":[
        {
            "category":"Arts & Performance",
            "subcategory":"Theater",
            "type":"Entertainment"
        }
    ],
    "sg:phone":"+1 307 382 4128",
    "sg:postcode":"82901",
    "sg:province":"CO",
    "sg:tags":[
        "group"
    ],
    "wof:name":"Party Squad",
    "wof:placetype":"venue"
},
  "geometry": {"coordinates":[-109.2071,41.597647],"type":"Point"}
}