{
  "type": "Feature",
  "properties": {
    "addr:full":"15342 E Arkansas Pl Aurora CO 80017",
    "addr:housenumber":"15342",
    "addr:postcode":"80017",
    "addr:street":"E Arkansas Pl",
    "iso:country":"US",
    "sg:address":"15342 E Arkansas Pl",
    "sg:city":"Aurora",
    "sg:classifiers":[
        {
            "category":"Professional",
            "subcategory":"Lawyer & Legal Services",
            "type":"Services"
        }
    ],
    "sg:phone":"+1 303 521 1171",
    "sg:postcode":"80017",
    "sg:province":"CO",
    "sg:tags":[
        "attorney"
    ],
    "wof:name":"Sterling Occasion Enterprises Llp",
    "wof:placetype":"venue"
},
  "geometry": {"coordinates":[-104.80768500000001,39.690725],"type":"Point"}
}