{
  "type": "Feature",
  "properties": {
    "addr:full":"2227 E Colfax Ave Denver CO 80206",
    "addr:housenumber":"2227",
    "addr:postcode":"80206",
    "addr:street":"E Colfax Ave",
    "iso:country":"US",
    "sg:address":"2227 E Colfax Ave",
    "sg:city":"Denver",
    "sg:classifiers":[
        {
            "category":"Shopping",
            "type":"Retail Goods"
        }
    ],
    "sg:phone":"+1 303 394 3362",
    "sg:postcode":"80206",
    "sg:province":"CO",
    "sg:tags":[
        "picture",
        "frame",
        "art",
        "gallery"
    ],
    "wof:name":"AUM Framing & Gallery",
    "wof:placetype":"venue"
},
  "geometry": {"coordinates":[-104.96048500000001,39.740008],"type":"Point"}
}