{
  "type": "Feature",
  "properties": {
    "addr:full":"95 E Yucca Hills Rd Castle Rock CO 80109",
    "addr:housenumber":"95",
    "addr:postcode":"80109",
    "addr:street":"E Yucca Hills Rd",
    "iso:country":"US",
    "sg:address":"95 E Yucca Hills Rd",
    "sg:city":"Castle Rock",
    "sg:classifiers":[
        {
            "category":"Building & Trades",
            "subcategory":"Electrical",
            "type":"Services"
        }
    ],
    "sg:phone":"+1 303 660 4592",
    "sg:postcode":"80109",
    "sg:province":"CO",
    "sg:tags":[
        "electric",
        "contractor"
    ],
    "wof:name":"Harvard Construction Electric",
    "wof:placetype":"venue"
},
  "geometry": {"coordinates":[-104.870193,39.356897],"type":"Point"}
}