{
  "type": "Feature",
  "properties": {
    "addr:full":"913 S Sierra Madre St Colorado Springs CO 80903",
    "addr:housenumber":"913",
    "addr:postcode":"80903",
    "addr:street":"S Sierra Madre St",
    "iso:country":"US",
    "sg:address":"913 S Sierra Madre St",
    "sg:city":"Colorado Springs",
    "sg:classifiers":[
        {
            "category":"Wholesale",
            "subcategory":"Dairy",
            "type":"Manufacturing & Wholesale Goods"
        }
    ],
    "sg:phone":"+1 719 634 6244",
    "sg:postcode":"80903",
    "sg:province":"CO",
    "sg:tags":[
        "whole",
        "sale",
        "ice",
        "cream"
    ],
    "wof:name":"Frosty Freeze",
    "wof:placetype":"venue"
},
  "geometry": {"coordinates":[-104.829491,38.821637],"type":"Point"}
}