{
  "type": "Feature",
  "properties": {
    "iso:country":"US",
    "sg:address":"8394 S Brentwood St",
    "sg:city":"Littleton",
    "sg:classifiers":[
        {
            "category":"Building & Trades",
            "subcategory":"Construction",
            "type":"Services"
        }
    ],
    "sg:phone":"+1 303 237 3195",
    "sg:postcode":"80128",
    "sg:province":"CO",
    "sg:tags":[
        "house"
    ],
    "wof:name":"Innerwood Inc",
    "wof:placetype":"venue"
},
  "geometry": {"coordinates":[-105.091104,39.5659],"type":"Point"}
}