{
  "type": "Feature",
  "properties": {
    "iso:country":"US",
    "sg:address":"2627 Redwing Rd",
    "sg:city":"Fort Collins",
    "sg:classifiers":[
        {
            "category":"Shopping",
            "subcategory":"Computers & Home Electronics",
            "type":"Retail Goods"
        }
    ],
    "sg:phone":"+1 970 225 1135",
    "sg:postcode":"80526",
    "sg:province":"CO",
    "sg:tags":[
        "equipment",
        "electronic",
        "supply"
    ],
    "wof:name":"NEC Electronics America",
    "wof:placetype":"venue"
},
  "geometry": {"coordinates":[-105.080517,40.551116],"type":"Point"}
}