{
  "type": "Feature",
  "properties": {
    "addr:full":"813 Colorado Ave Glenwood Springs CO 81601",
    "addr:housenumber":"813",
    "addr:postcode":"81601",
    "addr:street":"Colorado Ave",
    "iso:country":"US",
    "sg:address":"813 Colorado Ave",
    "sg:city":"Glenwood Springs",
    "sg:classifiers":[
        {
            "category":"Insurance",
            "subcategory":"Insurance Agent",
            "type":"Services"
        }
    ],
    "sg:phone":"+1 970 945 8548",
    "sg:postcode":"81601",
    "sg:province":"CO",
    "sg:tags":[
        "adjuster"
    ],
    "wof:name":"Mc Millan Claim Service",
    "wof:placetype":"venue"
},
  "geometry": {"coordinates":[-107.325883,39.54656],"type":"Point"}
}