{
  "type": "Feature",
  "properties": {
    "addr:full":"621 Hutton Ave Rifle CO 81650",
    "addr:housenumber":"621",
    "addr:postcode":"81650",
    "addr:street":"Hutton Ave",
    "iso:country":"US",
    "sg:address":"621 Hutton Ave",
    "sg:city":"Rifle",
    "sg:classifiers":[
        {
            "category":"Shopping",
            "type":"Retail Goods"
        }
    ],
    "sg:phone":"+1 970 379 1941",
    "sg:postcode":"81650",
    "sg:province":"CO",
    "sg:tags":[
        "wedding",
        "supply"
    ],
    "wof:name":"JMK Ceremony Music",
    "wof:placetype":"venue"
},
  "geometry": {"coordinates":[-107.78943700000001,39.534874],"type":"Point"}
}