{
  "type": "Feature",
  "properties": {
    "addr:full":"2264 W 45th St Loveland CO 80538",
    "addr:housenumber":"2264",
    "addr:postcode":"80538",
    "addr:street":"W 45Th St",
    "iso:country":"US",
    "sg:address":"2264 W 45th St",
    "sg:city":"Loveland",
    "sg:classifiers":[
        {
            "category":"Building & Trades",
            "subcategory":"Electrical",
            "type":"Services"
        }
    ],
    "sg:phone":"+1 970 663 6793",
    "sg:postcode":"80538",
    "sg:province":"CO",
    "sg:tags":[
        "electrical",
        "contractor"
    ],
    "wof:name":"Front Range Data & Electric",
    "wof:placetype":"venue"
},
  "geometry": {"coordinates":[-105.10804,40.437672],"type":"Point"}
}