{
  "type": "Feature",
  "properties": {
    "addr:full":"125 Trump Ave Colorado Springs CO 80909",
    "addr:housenumber":"125",
    "addr:postcode":"80909",
    "addr:street":"Trump Ave",
    "iso:country":"US",
    "sg:address":"125 Trump Ave",
    "sg:city":"Colorado Springs",
    "sg:classifiers":[
        {
            "category":"Shopping",
            "subcategory":"Gifts & Souvenirs",
            "type":"Retail Goods"
        }
    ],
    "sg:phone":"+1 719 578 1700",
    "sg:postcode":"80909",
    "sg:province":"CO",
    "sg:tags":[
        "party",
        "supply"
    ],
    "wof:name":"A Happy Helium Greeting Co",
    "wof:placetype":"venue"
},
  "geometry": {"coordinates":[-104.779792,38.835299],"type":"Point"}
}