{
  "type": "Feature",
  "properties": {
    "addr:full":"5290 Tennyson St Denver CO 80212",
    "addr:housenumber":"5290",
    "addr:postcode":"80212",
    "addr:street":"Tennyson St",
    "iso:country":"US",
    "sg:address":"5290 Tennyson St",
    "sg:city":"Denver",
    "sg:classifiers":[
        {
            "category":"Building & Trades",
            "subcategory":"Locksmith",
            "type":"Services"
        }
    ],
    "sg:phone":"+1 303 390 0441",
    "sg:postcode":"80212",
    "sg:province":"CO",
    "sg:tags":[
        "key"
    ],
    "wof:name":"Emergency A Locksmith",
    "wof:placetype":"venue"
},
  "geometry": {"coordinates":[-105.043702,39.792544],"type":"Point"}
}