{
  "type": "Feature",
  "properties": {
    "iso:country":"US",
    "sg:address":"3360 N el Paso St",
    "sg:city":"Colorado Springs",
    "sg:classifiers":[
        {
            "category":"Retail",
            "subcategory":"Auto Repair",
            "type":"Services"
        }
    ],
    "sg:phone":"+1 719 633 3650",
    "sg:postcode":"80907",
    "sg:province":"CO",
    "sg:tags":[
        "glass",
        "coating",
        "tinting"
    ],
    "wof:name":"Alltint",
    "wof:placetype":"venue"
},
  "geometry": {"coordinates":[-104.812798,38.881812],"type":"Point"}
}