{
  "type": "Feature",
  "properties": {
    "addr:full":"3985 Tennyson St Denver CO 80212",
    "addr:housenumber":"3985",
    "addr:postcode":"80212",
    "addr:street":"Tennyson St",
    "iso:country":"US",
    "sg:address":"3985 Tennyson St",
    "sg:city":"Denver",
    "sg:classifiers":[
        {
            "category":"Home & Garden",
            "subcategory":"Garden Supply",
            "type":"Retail Goods"
        },
        {
            "category":"Shopping",
            "subcategory":"Antiques",
            "type":"Retail Goods"
        }
    ],
    "sg:phone":"+1 303 455 4484",
    "sg:postcode":"80212",
    "sg:province":"CO",
    "wof:name":"Green Door Furniture",
    "wof:placetype":"venue"
},
  "geometry": {"coordinates":[-105.043994,39.772279],"type":"Point"}
}