{
  "type": "Feature",
  "properties": {
    "iso:country":"US",
    "sg:address":"850 Hartford Dr",
    "sg:city":"Boulder",
    "sg:classifiers":[
        {
            "category":"Education",
            "subcategory":"Special Training",
            "type":"Public Place"
        }
    ],
    "sg:phone":"+1 303 543 9550",
    "sg:postcode":"80305",
    "sg:province":"CO",
    "sg:tags":[
        "tutoring"
    ],
    "wof:name":"Algebra With An A",
    "wof:placetype":"venue"
},
  "geometry": {"coordinates":[-105.256849,39.981992],"type":"Point"}
}