{
  "type": "Feature",
  "properties": {
    "iso:country":"US",
    "sg:address":"2500 S Raritan St",
    "sg:city":"Englewood",
    "sg:classifiers":[
        {
            "category":"Manufacturing",
            "subcategory":"Signs",
            "type":"Manufacturing & Wholesale Goods"
        }
    ],
    "sg:phone":"+1 303 975 1772",
    "sg:postcode":"80110",
    "sg:province":"CO",
    "sg:tags":[
        "electrical",
        "mfg"
    ],
    "sg:website":"www.advantagesigncompany.com",
    "wof:name":"Advantage Sign Co Inc",
    "wof:placetype":"venue"
},
  "geometry": {"coordinates":[-105.008674,39.669106],"type":"Point"}
}