{
  "type": "Feature",
  "properties": {
    "iso:country":"US",
    "sg:address":"1113 Spruce St",
    "sg:city":"Boulder",
    "sg:classifiers":[
        {
            "category":"Health Services",
            "subcategory":"Health Practitioner",
            "type":"Services"
        }
    ],
    "sg:phone":"+1 303 449 3028",
    "sg:postcode":"80302",
    "sg:province":"CO",
    "sg:tags":[
        "psychotherapist"
    ],
    "wof:name":"Karen Fiester",
    "wof:placetype":"venue"
},
  "geometry": {"coordinates":[-105.280474,40.018935],"type":"Point"}
}