{
  "type": "Feature",
  "properties": {
    "iso:country":"US",
    "sg:address":"20321 E 35th Dr",
    "sg:city":"Aurora",
    "sg:classifiers":[
        {
            "category":"Health Services",
            "subcategory":"Doctor",
            "type":"Services"
        }
    ],
    "sg:phone":"+1 303 371 9626",
    "sg:postcode":"80011",
    "sg:province":"CO",
    "sg:tags":[
        "dentist"
    ],
    "wof:name":"DDD",
    "wof:placetype":"venue"
},
  "geometry": {"coordinates":[-104.751289,39.762315],"type":"Point"}
}