{
  "type": "Feature",
  "properties": {
    "addr:full":"523 N Nevada Ave Colorado Springs CO 80903",
    "addr:housenumber":"523",
    "addr:postcode":"80903",
    "addr:street":"N Nevada Ave",
    "iso:country":"US",
    "sg:address":"523 N Nevada Ave",
    "sg:city":"Colorado Springs",
    "sg:classifiers":[
        {
            "category":"Health Services",
            "subcategory":"Doctor",
            "type":"Services"
        }
    ],
    "sg:phone":"+1 719 635 5815",
    "sg:postcode":"80903",
    "sg:province":"CO",
    "sg:tags":[
        "dentist"
    ],
    "wof:name":"Uptown Dental Assoc",
    "wof:placetype":"venue"
},
  "geometry": {"coordinates":[-104.821072,38.841875],"type":"Point"}
}