{
  "type": "Feature",
  "properties": {
    "addr:full":"10 Riverside Ct Avon CO 81620",
    "addr:housenumber":"10",
    "addr:postcode":"81620",
    "addr:street":"Riverside Ct",
    "iso:country":"US",
    "sg:address":"10 Riverside Ct",
    "sg:city":"Avon",
    "sg:classifiers":[
        {
            "category":"Professional",
            "subcategory":"Business Services",
            "type":"Services"
        }
    ],
    "sg:phone":"+1 970 949 6636",
    "sg:postcode":"81620",
    "sg:province":"CO",
    "sg:tags":[
        "interior",
        "consultant",
        "design",
        "decorator"
    ],
    "wof:name":"Custom Decors",
    "wof:placetype":"venue"
},
  "geometry": {"coordinates":[-106.497236,39.623842],"type":"Point"}
}