{
  "type": "Feature",
  "properties": {
    "iso:country":"US",
    "sg:address":"351 S Saint Vrain Ave",
    "sg:city":"Estes Park",
    "sg:classifiers":[
        {
            "category":"Autos & Motor Vehicles",
            "subcategory":"Auto Supplies",
            "type":"Retail Goods"
        }
    ],
    "sg:phone":"+1 970 586 2348",
    "sg:postcode":"80517",
    "sg:province":"CO",
    "sg:tags":[
        "automobile",
        "parts"
    ],
    "wof:name":"A-1 Auto Parts",
    "wof:placetype":"venue"
},
  "geometry": {"coordinates":[-105.50724200000001,40.372695],"type":"Point"}
}