{
  "type": "Feature",
  "properties": {
    "iso:country":"US",
    "sg:address":"2596 W Alamo Ave",
    "sg:city":"Littleton",
    "sg:classifiers":[
        {
            "category":"Professional",
            "subcategory":"Lawyer & Legal Services",
            "type":"Services"
        }
    ],
    "sg:phone":"+1 303 794 7422",
    "sg:postcode":"80120",
    "sg:province":"CO",
    "sg:tags":[
        "attorney"
    ],
    "wof:name":"Bahr & Kreidle",
    "wof:placetype":"venue"
},
  "geometry": {"coordinates":[-105.017582,39.612648],"type":"Point"}
}