{
  "type": "Feature",
  "properties": {
    "addr:full":"3015 Waterstone Ct Fort Collins CO 80525",
    "addr:housenumber":"3015",
    "addr:postcode":"80525",
    "addr:street":"Waterstone Ct",
    "iso:country":"US",
    "sg:address":"3015 Waterstone Ct",
    "sg:city":"Fort Collins",
    "sg:classifiers":[
        {
            "category":"Building & Trades",
            "subcategory":"Landscaping Services",
            "type":"Services"
        }
    ],
    "sg:phone":"+1 970 377 3337",
    "sg:postcode":"80525",
    "sg:province":"CO",
    "sg:tags":[
        "landscape"
    ],
    "wof:name":"B & B Landscaping",
    "wof:placetype":"venue"
},
  "geometry": {"coordinates":[-105.02303000000001,40.539485],"type":"Point"}
}