{
  "type": "Feature",
  "properties": {
    "iso:country":"US",
    "sg:address":"225 G St",
    "sg:city":"Salida",
    "sg:classifiers":[
        {
            "category":"Real Estate",
            "subcategory":"Real Estate Services",
            "type":"Services"
        }
    ],
    "sg:phone":"+1 719 539 2215",
    "sg:postcode":"81201",
    "sg:province":"CO",
    "sg:tags":[
        "abstract",
        "title"
    ],
    "wof:name":"Chaffee Closing and Services",
    "wof:placetype":"venue"
},
  "geometry": {"coordinates":[-105.993796,38.535846],"type":"Point"}
}