{
  "type": "Feature",
  "properties": {
    "iso:country":"US",
    "sg:address":"492 Morning Glory Ln",
    "sg:city":"Grand Junction",
    "sg:classifiers":[
        {
            "category":"Recreation",
            "type":"Entertainment"
        }
    ],
    "sg:phone":"+1 970 242 2878",
    "sg:postcode":"81504",
    "sg:province":"CO",
    "sg:tags":[
        "club",
        "bridge"
    ],
    "wof:name":"Blue Spruce Bridge Club",
    "wof:placetype":"venue"
},
  "geometry": {"coordinates":[-108.51163,39.074774],"type":"Point"}
}