{
  "type": "Feature",
  "properties": {
    "iso:country":"US",
    "sg:address":"449 San Juan St",
    "sg:city":"Pagosa Springs",
    "sg:classifiers":[
        {
            "category":"Government",
            "subcategory":"Office",
            "type":"Public Place"
        }
    ],
    "sg:phone":"+1 970 264 8375",
    "sg:postcode":"81147",
    "sg:province":"CO",
    "wof:name":"Veteran's Service Office",
    "wof:placetype":"venue"
},
  "geometry": {"coordinates":[-107.01424400000001,37.26624],"type":"Point"}
}