{
  "type": "Feature",
  "properties": {
    "addr:full":"48920 Co Rd 29 Nunn CO 80648",
    "addr:housenumber":"29",
    "addr:postcode":"48920;80648",
    "addr:street":"Co Rd",
    "iso:country":"US",
    "sg:address":"48920 Co Rd 29",
    "sg:city":"Nunn",
    "sg:classifiers":[
        {
            "category":"Building & Trades",
            "subcategory":"Construction",
            "type":"Services"
        }
    ],
    "sg:phone":"+1 970 897 2999",
    "sg:postcode":"80648",
    "sg:province":"CO",
    "sg:tags":[
        "house"
    ],
    "wof:name":"Dryland Home Improvement",
    "wof:placetype":"venue"
},
  "geometry": {"coordinates":[-104.791273,40.708739],"type":"Point"}
}