{
  "type": "Feature",
  "properties": {
    "addr:full":"9150 Lexington Dr Colorado Springs CO 80920",
    "addr:housenumber":"9150",
    "addr:postcode":"80920",
    "addr:street":"Lexington Dr",
    "iso:country":"US",
    "sg:address":"9150 Lexington Dr",
    "sg:city":"Colorado Springs",
    "sg:classifiers":[
        {
            "category":"Education",
            "subcategory":"School",
            "type":"Public Place"
        }
    ],
    "sg:phone":"+1 719 598 3622",
    "sg:postcode":"80920",
    "sg:province":"CO",
    "wof:name":"Mountain Ridge Middle School",
    "wof:placetype":"venue"
},
  "geometry": {"coordinates":[-104.777975,38.969646],"type":"Point"}
}