{
  "type": "Feature",
  "properties": {
    "addr:full":"7201 Otis Ct Arvada CO 80003",
    "addr:housenumber":"7201",
    "addr:postcode":"80003",
    "addr:street":"Otis Ct",
    "iso:country":"US",
    "sg:address":"7201 Otis Ct",
    "sg:city":"Arvada",
    "sg:classifiers":[
        {
            "category":"Travel",
            "subcategory":"Hotels & Motels",
            "type":"Entertainment"
        }
    ],
    "sg:phone":"+1 303 420 7500",
    "sg:postcode":"80003",
    "sg:province":"CO",
    "wof:name":"Hotel Concierge Of Colorado",
    "wof:placetype":"venue"
},
  "geometry": {"coordinates":[-105.071488,39.829063],"type":"Point"}
}