{
  "type": "Feature",
  "properties": {
    "iso:country":"US",
    "sg:address":"2245 Allyn Way",
    "sg:city":"Colorado Springs",
    "sg:classifiers":[
        {
            "category":"Building & Trades",
            "subcategory":"Landscaping Services",
            "type":"Services"
        }
    ],
    "sg:phone":"+1 719 550 9807",
    "sg:postcode":"80915",
    "sg:province":"CO",
    "wof:name":"Lawn Tech",
    "wof:placetype":"venue"
},
  "geometry": {"coordinates":[-104.69955,38.865089],"type":"Point"}
}