{
  "type": "Feature",
  "properties": {
    "iso:country":"US",
    "sg:address":"255 E 5th Ave",
    "sg:city":"Durango",
    "sg:classifiers":[
        {
            "category":"Education",
            "subcategory":"School",
            "type":"Public Place"
        }
    ],
    "sg:phone":"+1 970 247 3995",
    "sg:postcode":"81301",
    "sg:province":"CO",
    "wof:name":"Sacred Heart School",
    "wof:placetype":"venue"
},
  "geometry": {"coordinates":[-107.87759699999999,37.265217],"type":"Point"}
}