{
  "type": "Feature",
  "properties": {
    "iso:country":"US",
    "sg:address":"1701 S Corona St",
    "sg:city":"Denver",
    "sg:classifiers":[
        {
            "category":"Manufacturing",
            "subcategory":"Paper Products",
            "type":"Manufacturing & Wholesale Goods"
        }
    ],
    "sg:phone":"+1 303 282 1700",
    "sg:postcode":"80210",
    "sg:province":"CO",
    "sg:tags":[
        "stationery",
        "mfg"
    ],
    "wof:name":"Autolog LLC",
    "wof:placetype":"venue"
},
  "geometry": {"coordinates":[-104.974602,39.683982],"type":"Point"}
}