{
  "type": "Feature",
  "properties": {
    "addr:full":"17706 S Golden Rd Golden CO 80401",
    "addr:housenumber":"17706",
    "addr:postcode":"80401",
    "addr:street":"S Golden Rd",
    "iso:country":"US",
    "sg:address":"17706 S Golden Rd",
    "sg:city":"Golden",
    "sg:classifiers":[
        {
            "category":"Shopping",
            "subcategory":"Bicycles & Sporting Goods",
            "type":"Retail Goods"
        }
    ],
    "sg:phone":"+1 303 279 1207",
    "sg:postcode":"80401",
    "sg:province":"CO",
    "wof:name":"Sport Source",
    "wof:placetype":"venue"
},
  "geometry": {"coordinates":[-105.20025800000001,39.741678],"type":"Point"}
}