{
  "type": "Feature",
  "properties": {
    "iso:country":"US",
    "sg:address":"5175 N Academy Blvd",
    "sg:city":"Colorado Springs",
    "sg:classifiers":[
        {
            "category":"Banks & Credit Unions",
            "subcategory":"Bank",
            "type":"Services"
        }
    ],
    "sg:phone":"+1 719 388 1652",
    "sg:postcode":"80918",
    "sg:province":"CO",
    "wof:name":"Interbank",
    "wof:placetype":"venue"
},
  "geometry": {"coordinates":[-104.77932699999999,38.905956],"type":"Point"}
}