{
  "type": "Feature",
  "properties": {
    "iso:country":"US",
    "sg:address":"332 W Main St",
    "sg:city":"Aspen",
    "sg:classifiers":[
        {
            "category":"Professional",
            "subcategory":"Computer Services",
            "type":"Services"
        }
    ],
    "sg:phone":"+1 970 544 9916",
    "sg:postcode":"81611",
    "sg:province":"CO",
    "sg:tags":[
        "home",
        "consulting",
        "page",
        "dev",
        "internet"
    ],
    "wof:name":"Internet Outfitting",
    "wof:placetype":"venue"
},
  "geometry": {"coordinates":[-106.825197,39.191907],"type":"Point"}
}