{
  "type": "Feature",
  "properties": {
    "iso:country":"US",
    "sg:address":"1753 Rocky Mountain Ave",
    "sg:city":"Loveland",
    "sg:classifiers":[
        {
            "category":"Restaurant",
            "type":"Food & Drink"
        }
    ],
    "sg:menulink":"http://www.allmenus.com/co/loveland/128553-subway/menu/",
    "sg:phone":"+1 970 593 1845",
    "sg:postcode":"80538",
    "sg:province":"CO",
    "sg:tags":[
        "american",
        "sandwich"
    ],
    "wof:name":"Subway",
    "wof:placetype":"venue"
},
  "geometry": {"coordinates":[-105.002377,40.412304],"type":"Point"}
}