{
  "type": "Feature",
  "properties": {
    "iso:country":"US",
    "sg:address":"315 Craft Dr",
    "sg:city":"Alamosa",
    "sg:classifiers":[
        {
            "category":"Organizations",
            "subcategory":"Religious Organization",
            "type":"Services"
        }
    ],
    "sg:phone":"+1 719 589 2772",
    "sg:postcode":"81101",
    "sg:province":"CO",
    "sg:tags":[
        "church"
    ],
    "wof:name":"Seventh-Day Adventist Church",
    "wof:placetype":"venue"
},
  "geometry": {"coordinates":[-105.893748,37.48009],"type":"Point"}
}