{
  "type": "Feature",
  "properties": {
    "iso:country":"US",
    "sg:address":"413 E Main St",
    "sg:city":"Aspen",
    "sg:classifiers":[
        {
            "category":"Banks & Credit Unions",
            "subcategory":"Investment Brokerage",
            "type":"Services"
        }
    ],
    "sg:phone":"+1 970 925 7877",
    "sg:postcode":"81611",
    "sg:province":"CO",
    "sg:tags":[
        "advisory",
        "financial"
    ],
    "wof:name":"World Financial Group",
    "wof:placetype":"venue"
},
  "geometry": {"coordinates":[-106.819131,39.19057],"type":"Point"}
}