{
  "type": "Feature",
  "properties": {
    "iso:country":"US",
    "sg:address":"541 Locust Pl",
    "sg:city":"Boulder",
    "sg:classifiers":[
        {
            "category":"Shopping",
            "subcategory":"Jewelry",
            "type":"Retail Goods"
        }
    ],
    "sg:phone":"+1 303 442 8584",
    "sg:postcode":"80304",
    "sg:province":"CO",
    "wof:name":"Your Same Tribe",
    "wof:placetype":"venue"
},
  "geometry": {"coordinates":[-105.29009000000001,40.053453],"type":"Point"}
}