{
  "type": "Feature",
  "properties": {
    "iso:country":"US",
    "sg:address":"37 S Washington St",
    "sg:city":"Denver",
    "sg:classifiers":[
        {
            "category":"Real Estate",
            "subcategory":"Real Estate Agent",
            "type":"Services"
        }
    ],
    "sg:phone":"+1 303 321 2734",
    "sg:postcode":"80209",
    "sg:province":"CO",
    "wof:name":"Pooley & Associates",
    "wof:placetype":"venue"
},
  "geometry": {"coordinates":[-104.979237,39.715376],"type":"Point"}
}