{
  "type": "Feature",
  "properties": {
    "iso:country":"US",
    "sg:address":"32295 US Hwy 34",
    "sg:city":"Brush",
    "sg:classifiers":[
        {
            "category":"Farming",
            "subcategory":"Livestock Farm",
            "type":"Manufacturing & Wholesale Goods"
        }
    ],
    "sg:phone":"+1 970 842 0701",
    "sg:postcode":"80723",
    "sg:province":"CO",
    "sg:tags":[
        "feeding"
    ],
    "wof:name":"Pinneo Feedlot",
    "wof:placetype":"venue"
},
  "geometry": {"coordinates":[-103.54415899999999,40.261269],"type":"Point"}
}