{
  "type": "Feature",
  "properties": {
    "addr:full":"10056 Franklin St Thornton CO 80229",
    "addr:housenumber":"10056",
    "addr:postcode":"80229",
    "addr:street":"Franklin St",
    "iso:country":"US",
    "sg:address":"10056 Franklin St",
    "sg:city":"Thornton",
    "sg:classifiers":[
        {
            "category":"Professional",
            "subcategory":"Testing Lab",
            "type":"Services"
        }
    ],
    "sg:phone":"+1 303 424 4647",
    "sg:postcode":"80229",
    "sg:province":"CO",
    "sg:tags":[
        "asbestos"
    ],
    "wof:name":"Acclaim Environmental Svc Inc",
    "wof:placetype":"venue"
},
  "geometry": {"coordinates":[-104.967652,39.878869],"type":"Point"}
}