{
  "type": "Feature",
  "properties": {
    "addr:full":"14142 Denver West Pkwy Lakewood CO 80401",
    "addr:housenumber":"14142",
    "addr:postcode":"80401",
    "addr:street":"Denver West Pkwy",
    "iso:country":"US",
    "sg:address":"14142 Denver West Pkwy",
    "sg:city":"Lakewood",
    "sg:classifiers":[
        {
            "category":"Organizations",
            "subcategory":"Political Organization",
            "type":"Services"
        }
    ],
    "sg:phone":"+1 303 277 1113",
    "sg:postcode":"80401",
    "sg:province":"CO",
    "wof:name":"Republican Headquarters",
    "wof:placetype":"venue"
},
  "geometry": {"coordinates":[-105.15925900000001,39.741856],"type":"Point"}
}