{
  "type": "Feature",
  "properties": {
    "addr:full":"1950 Oak Hills Dr Colorado Springs CO 80919",
    "addr:housenumber":"1950",
    "addr:postcode":"80919",
    "addr:street":"Oak Hills Dr",
    "iso:country":"US",
    "sg:address":"1950 Oak Hills Dr",
    "sg:city":"Colorado Springs",
    "sg:classifiers":[
        {
            "category":"Wholesale",
            "subcategory":"Auto Parts",
            "type":"Manufacturing & Wholesale Goods"
        }
    ],
    "sg:phone":"+1 719 475 0150",
    "sg:postcode":"80919",
    "sg:province":"CO",
    "sg:tags":[
        "dist",
        "tire"
    ],
    "wof:name":"Tire Broker The",
    "wof:placetype":"venue"
},
  "geometry": {"coordinates":[-104.866135,38.938546],"type":"Point"}
}