{
  "type": "Feature",
  "properties": {
    "iso:country":"US",
    "sg:address":"113 W 3rd St",
    "sg:city":"Rifle",
    "sg:classifiers":[
        {
            "category":"Manufacturing",
            "subcategory":"Printing",
            "type":"Manufacturing & Wholesale Goods"
        }
    ],
    "sg:phone":"+1 970 625 3550",
    "sg:postcode":"81650",
    "sg:province":"CO",
    "sg:tags":[
        "printer"
    ],
    "wof:name":"Jean's Printing",
    "wof:placetype":"venue"
},
  "geometry": {"coordinates":[-107.784415,39.531496],"type":"Point"}
}