{
  "type": "Feature",
  "properties": {
    "iso:country":"US",
    "sg:address":"8013 1st St",
    "sg:city":"Wellington",
    "sg:classifiers":[
        {
            "category":"Farming",
            "subcategory":"Farm & Veterinary Services",
            "type":"Manufacturing & Wholesale Goods"
        }
    ],
    "sg:phone":"+1 970 568 0488",
    "sg:postcode":"80549",
    "sg:province":"CO",
    "sg:tags":[
        "control",
        "weed"
    ],
    "sg:website":"www.shawfabrics.com",
    "wof:name":"Shaw Fabric Products",
    "wof:placetype":"venue"
},
  "geometry": {"coordinates":[-105.007673,40.701601],"type":"Point"}
}