{
  "type": "Feature",
  "properties": {
    "addr:full":"650 S Wadsworth Blvd Lakewood CO 80226",
    "addr:housenumber":"650",
    "addr:postcode":"80226",
    "addr:street":"S Wadsworth Blvd",
    "iso:country":"US",
    "sg:address":"650 S Wadsworth Blvd",
    "sg:city":"Lakewood",
    "sg:classifiers":[
        {
            "category":"Personal",
            "subcategory":"Day Spa",
            "type":"Services"
        },
        {
            "category":"Personal",
            "subcategory":"Nail Salon",
            "type":"Services"
        }
    ],
    "sg:phone":"+1 303 936 7900",
    "sg:postcode":"80226",
    "sg:province":"CO",
    "wof:name":"Opl Salon & Spa",
    "wof:placetype":"venue"
},
  "geometry": {"coordinates":[-105.081362,39.704677],"type":"Point"}
}