{
  "type": "Feature",
  "properties": {
    "addr:full":"7988 James Ct Longmont CO 80503",
    "addr:housenumber":"7988",
    "addr:postcode":"80503",
    "addr:street":"James Ct",
    "iso:country":"US",
    "sg:address":"7988 James Ct",
    "sg:city":"Longmont",
    "sg:classifiers":[
        {
            "category":"Home & Garden",
            "subcategory":"Home Furnishings",
            "type":"Retail Goods"
        }
    ],
    "sg:phone":"+1 303 652 2362",
    "sg:postcode":"80503",
    "sg:province":"CO",
    "wof:name":"Niwot Window Works",
    "wof:placetype":"venue"
},
  "geometry": {"coordinates":[-105.166078,40.102381],"type":"Point"}
}