{
  "type": "Feature",
  "properties": {
    "addr:full":"440 Sunset Ln Towaoc CO 81301",
    "addr:housenumber":"440",
    "addr:postcode":"81301",
    "addr:street":"Sunset Ln",
    "iso:country":"US",
    "sg:address":"440 Sunset Ln",
    "sg:city":"Towaoc",
    "sg:classifiers":[
        {
            "category":"Health Services",
            "subcategory":"Clinic",
            "type":"Services"
        }
    ],
    "sg:phone":"+1 970 564 0301",
    "sg:postcode":"81301",
    "sg:province":"CO",
    "wof:name":"Casa Of The Four Corners Inc",
    "wof:placetype":"venue"
},
  "geometry": {"coordinates":[-107.699882,37.33516],"type":"Point"}
}