{
  "type": "Feature",
  "properties": {
    "addr:full":"2775 Iris Ave Boulder CO 80304",
    "addr:housenumber":"2775",
    "addr:postcode":"80304",
    "addr:street":"Iris Ave",
    "iso:country":"US",
    "sg:address":"2775 Iris Ave",
    "sg:city":"Boulder",
    "sg:classifiers":[
        {
            "category":"Real Estate",
            "subcategory":"Real Estate Operator",
            "type":"Services"
        }
    ],
    "sg:phone":"+1 303 440 0779",
    "sg:postcode":"80304",
    "sg:province":"CO",
    "sg:tags":[
        "shopping",
        "center"
    ],
    "wof:name":"Willow Springs Partnership",
    "wof:placetype":"venue"
},
  "geometry": {"coordinates":[-105.258518,40.036535],"type":"Point"}
}