{
  "type": "Feature",
  "properties": {
    "iso:country":"US",
    "sg:address":"435 E Willamette Ave",
    "sg:city":"Colorado Springs",
    "sg:classifiers":[
        {
            "category":"Building & Trades",
            "subcategory":"Construction",
            "type":"Services"
        }
    ],
    "sg:phone":"+1 719 641 7877",
    "sg:postcode":"80903",
    "sg:province":"CO",
    "sg:tags":[
        "commercial",
        "remodeling",
        "painting",
        "residential"
    ],
    "wof:name":"Alpine Enterprises",
    "wof:placetype":"venue"
},
  "geometry": {"coordinates":[-104.816303,38.841948],"type":"Point"}
}