{
  "type": "Feature",
  "properties": {
    "addr:full":"7500 E 41st Ave Denver CO 80207",
    "addr:housenumber":"7500",
    "addr:postcode":"80207",
    "addr:street":"E 41St Ave",
    "iso:country":"US",
    "sg:address":"7500 E 41st Ave",
    "sg:city":"Denver",
    "sg:classifiers":[
        {
            "category":"Autos & Motor Vehicles",
            "subcategory":"Automobile Sales",
            "type":"Retail Goods"
        }
    ],
    "sg:phone":"+1 303 370 1300",
    "sg:postcode":"80207",
    "sg:province":"CO",
    "sg:tags":[
        "limo"
    ],
    "sg:website":"www.execucar.com",
    "wof:name":"ExecuCar",
    "wof:placetype":"venue"
},
  "geometry": {"coordinates":[-104.901101,39.775134],"type":"Point"}
}