{
  "type": "Feature",
  "properties": {
    "iso:country":"US",
    "sg:address":"8545 S Quebec St",
    "sg:city":"Littleton",
    "sg:classifiers":[
        {
            "category":"Building & Trades",
            "subcategory":"Construction",
            "type":"Services"
        }
    ],
    "sg:phone":"+1 303 471 6541",
    "sg:postcode":"80124",
    "sg:province":"CO",
    "sg:tags":[
        "house"
    ],
    "wof:name":"Nicholas Custom Homes",
    "wof:placetype":"venue"
},
  "geometry": {"coordinates":[-104.90464299999999,39.559543],"type":"Point"}
}