{
  "type": "Feature",
  "properties": {
    "addr:full":"729 Quebec Street Denver CO 80230",
    "addr:housenumber":"729",
    "addr:postcode":"80230",
    "addr:street":"Quebec Street",
    "iso:country":"US",
    "sg:address":"729 Quebec Street",
    "sg:city":"Denver",
    "sg:classifiers":[
        {
            "category":"Health Services",
            "subcategory":"Clinic",
            "type":"Services"
        }
    ],
    "sg:phone":"+1 303 862 9906",
    "sg:postcode":"80230",
    "sg:province":"CO",
    "sg:tags":[
        "cannabis"
    ],
    "sg:website":"www.lowryleaf.com/",
    "wof:name":"Lowry Leaf",
    "wof:placetype":"venue"
},
  "geometry": {"coordinates":[-104.903474,39.727475],"type":"Point"}
}