{
  "type": "Feature",
  "properties": {
    "iso:country":"US",
    "sg:address":"215 W Oak St",
    "sg:city":"Fort Collins",
    "sg:classifiers":[
        {
            "category":"Banks & Credit Unions",
            "subcategory":"Bank",
            "type":"Services"
        }
    ],
    "sg:phone":"+1 970 495 1293",
    "sg:postcode":"80521",
    "sg:province":"CO",
    "sg:website":"www.1stnationalbank.com",
    "wof:name":"First National Bank-Colorado",
    "wof:placetype":"venue"
},
  "geometry": {"coordinates":[-105.079638,40.585526],"type":"Point"}
}