{
  "type": "Feature",
  "properties": {
    "iso:country":"US",
    "sg:address":"308 W Main St",
    "sg:city":"Trinidad",
    "sg:classifiers":[
        {
            "category":"Bars & Pubs",
            "type":"Food & Drink"
        }
    ],
    "sg:phone":"+1 719 846 9164",
    "sg:postcode":"81082",
    "sg:province":"CO",
    "wof:name":"Wildcat Saloon",
    "wof:placetype":"venue"
},
  "geometry": {"coordinates":[-104.507203,37.167687],"type":"Point"}
}