{
  "type": "Feature",
  "properties": {
    "iso:country":"US",
    "sg:address":"255 Weaver Park Rd",
    "sg:city":"Longmont",
    "sg:classifiers":[
        {
            "category":"Professional",
            "subcategory":"Accounting & Tax Preparation",
            "type":"Services"
        }
    ],
    "sg:phone":"+1 303 651 0771",
    "sg:postcode":"80501",
    "sg:province":"CO",
    "sg:tags":[
        "accountant"
    ],
    "wof:name":"James D Pieper CPA",
    "wof:placetype":"venue"
},
  "geometry": {"coordinates":[-105.086502,40.162199],"type":"Point"}
}