{
  "type": "Feature",
  "properties": {
    "addr:full":"142 Beaver Creek Pl Avon CO 81620",
    "addr:housenumber":"142",
    "addr:postcode":"81620",
    "addr:street":"Beaver Creek Pl",
    "iso:country":"US",
    "sg:address":"142 Beaver Creek Pl",
    "sg:city":"Avon",
    "sg:classifiers":[
        {
            "category":"Shopping",
            "subcategory":"Computers & Home Electronics",
            "type":"Retail Goods"
        }
    ],
    "sg:phone":"+1 970 949 1279",
    "sg:postcode":"81620",
    "sg:province":"CO",
    "sg:tags":[
        "equipment",
        "electronic",
        "supply"
    ],
    "wof:name":"Radio Shack",
    "wof:placetype":"venue"
},
  "geometry": {"coordinates":[-106.518416,39.634339],"type":"Point"}
}