{
  "type": "Feature",
  "properties": {
    "iso:country":"US",
    "sg:address":"18277 Co Rd 22",
    "sg:city":"Fort Lupton",
    "sg:classifiers":[
        {
            "category":"Farming",
            "subcategory":"Livestock Farm",
            "type":"Manufacturing & Wholesale Goods"
        }
    ],
    "sg:phone":"+1 303 536 9254",
    "sg:postcode":"80621",
    "sg:province":"CO",
    "sg:tags":[
        "feedlot",
        "field",
        "crop",
        "beef",
        "cattle"
    ],
    "wof:name":"Bradley Buum",
    "wof:placetype":"venue"
},
  "geometry": {"coordinates":[-104.708738,40.145898],"type":"Point"}
}