{
  "type": "Feature",
  "properties": {
    "addr:full":"924 N Wahsatch Ave Colorado Springs CO 80903",
    "addr:housenumber":"924",
    "addr:postcode":"80903",
    "addr:street":"N Wahsatch Ave",
    "iso:country":"US",
    "sg:address":"924 N Wahsatch Ave",
    "sg:city":"Colorado Springs",
    "sg:classifiers":[
        {
            "category":"Professional",
            "subcategory":"Lawyer & Legal Services",
            "type":"Services"
        }
    ],
    "sg:phone":"+1 719 634 8699",
    "sg:postcode":"80903",
    "sg:province":"CO",
    "sg:tags":[
        "attorney"
    ],
    "wof:name":"Michael N Satin",
    "wof:placetype":"venue"
},
  "geometry": {"coordinates":[-104.817486,38.847367],"type":"Point"}
}