{
  "type": "Feature",
  "properties": {
    "iso:country":"US",
    "sg:address":"7507 Co Rd 39",
    "sg:city":"Fort Lupton",
    "sg:classifiers":[
        {
            "category":"Airport",
            "type":"Transportation"
        }
    ],
    "sg:phone":"+1 303 536 0380",
    "sg:postcode":"80621",
    "sg:province":"CO",
    "wof:name":"Platte Valley Airport LTD",
    "wof:placetype":"venue"
},
  "geometry": {"coordinates":[-104.697315,40.106206],"type":"Point"}
}