{
  "type": "Feature",
  "properties": {
    "iso:country":"US",
    "sg:address":"214 W Kansas Ave",
    "sg:city":"Trinidad",
    "sg:classifiers":[
        {
            "category":"Organizations",
            "subcategory":"Religious Organization",
            "type":"Services"
        }
    ],
    "sg:phone":"+1 719 846 3773",
    "sg:postcode":"81082",
    "sg:province":"CO",
    "sg:tags":[
        "church"
    ],
    "wof:name":"Cornerstone Chapel",
    "wof:placetype":"venue"
},
  "geometry": {"coordinates":[-104.510625,37.176212],"type":"Point"}
}