{
  "type": "Feature",
  "properties": {
    "addr:full":"8101 E Lowry Blvd Ste 110 Denver CO 80230",
    "addr:housenumber":"8101",
    "addr:postcode":"80230",
    "addr:street":"E Lowry Blvd Ste 110",
    "iso:country":"US",
    "sg:address":"8101 E Lowry Blvd Ste 110",
    "sg:city":"Denver",
    "sg:classifiers":[
        {
            "category":"Health Services",
            "subcategory":"Optometrist",
            "type":"Services"
        }
    ],
    "sg:phone":"+1 303 671 0000",
    "sg:postcode":"80230",
    "sg:province":"CO",
    "sg:website":"www.coloradoeyedocs.com/location...",
    "wof:name":"Lowry Eye Care Specialists",
    "wof:placetype":"venue"
},
  "geometry": {"coordinates":[-104.895444,39.717652],"type":"Point"}
}