{
  "type": "Feature",
  "properties": {
    "iso:country":"US",
    "sg:address":"49 Research Dr",
    "sg:city":"Pueblo West",
    "sg:classifiers":[
        {
            "category":"Freight",
            "type":"Transportation"
        }
    ],
    "sg:phone":"+1 719 547 1855",
    "sg:postcode":"81007",
    "sg:province":"CO",
    "sg:tags":[
        "commercial",
        "storage"
    ],
    "wof:name":"Great Western Storage",
    "wof:placetype":"venue"
},
  "geometry": {"coordinates":[-104.734458,38.336495],"type":"Point"}
}