{
  "type": "Feature",
  "properties": {
    "iso:country":"US",
    "sg:address":"308 Ryan Gulch Rd",
    "sg:city":"Silverthorne",
    "sg:classifiers":[
        {
            "category":"Professional",
            "type":"Services"
        }
    ],
    "sg:phone":"+1 970 468 1778",
    "sg:postcode":"80498",
    "sg:province":"CO",
    "wof:name":"Michael A Tracy Jr",
    "wof:placetype":"venue"
},
  "geometry": {"coordinates":[-106.091835,39.617023],"type":"Point"}
}