{
  "type": "Feature",
  "properties": {
    "iso:country":"US",
    "sg:address":"114 Pinecliff Rd",
    "sg:city":"Pinecliffe",
    "sg:classifiers":[
        {
            "category":"Government",
            "subcategory":"Post Office",
            "type":"Public Place"
        }
    ],
    "sg:phone":"+1 303 642 7358",
    "sg:postcode":"80471",
    "sg:province":"CO",
    "wof:name":"US Post Office",
    "wof:placetype":"venue"
},
  "geometry": {"coordinates":[-105.43136699999999,39.932352],"type":"Point"}
}