{
  "type": "Feature",
  "properties": {
    "addr:full":"225 S 6th St La Salle CO 80645",
    "addr:housenumber":"225",
    "addr:postcode":"80645",
    "addr:street":"S 6Th St",
    "iso:country":"US",
    "sg:address":"225 S 6th St",
    "sg:city":"La Salle",
    "sg:classifiers":[
        {
            "category":"Organizations",
            "subcategory":"Religious Organization",
            "type":"Services"
        }
    ],
    "sg:phone":"+1 970 284 5101",
    "sg:postcode":"80645",
    "sg:province":"CO",
    "sg:tags":[
        "church"
    ],
    "wof:name":"Shepherd Of The Valley Luth",
    "wof:placetype":"venue"
},
  "geometry": {"coordinates":[-104.709923,40.351261],"type":"Point"}
}