{
  "type": "Feature",
  "properties": {
    "addr:full":"1009 Basin Ct Windsor CO 80550",
    "addr:housenumber":"1009",
    "addr:postcode":"80550",
    "addr:street":"Basin Ct",
    "iso:country":"US",
    "sg:address":"1009 Basin Ct",
    "sg:city":"Windsor",
    "sg:classifiers":[
        {
            "category":"Banks & Credit Unions",
            "subcategory":"Financial Services",
            "type":"Services"
        }
    ],
    "sg:phone":"+1 970 674 0436",
    "sg:postcode":"80550",
    "sg:province":"CO",
    "sg:tags":[
        "company",
        "holding"
    ],
    "wof:name":"G&H Holdings Inc",
    "wof:placetype":"venue"
},
  "geometry": {"coordinates":[-104.906846,40.469399],"type":"Point"}
}