{
  "type": "Feature",
  "properties": {
    "addr:full":"857 S Peterson Way Denver CO 80223",
    "addr:housenumber":"857",
    "addr:postcode":"80223",
    "addr:street":"S Peterson Way",
    "iso:country":"US",
    "sg:address":"857 S Peterson Way",
    "sg:city":"Denver",
    "sg:classifiers":[
        {
            "category":"Building & Trades",
            "subcategory":"Construction",
            "type":"Services"
        }
    ],
    "sg:phone":"+1 303 935 8945",
    "sg:postcode":"80223",
    "sg:province":"CO",
    "sg:tags":[
        "builder",
        "stair"
    ],
    "wof:name":"Johnson Mobile Welding Svc",
    "wof:placetype":"venue"
},
  "geometry": {"coordinates":[-105.005903,39.700279],"type":"Point"}
}