{
  "type": "Feature",
  "properties": {
    "iso:country":"US",
    "sg:address":"100 Wellington Ln",
    "sg:city":"Edwards",
    "sg:classifiers":[
        {
            "category":"Real Estate",
            "subcategory":"Real Estate Agent",
            "type":"Services"
        }
    ],
    "sg:phone":"+1 970 569 3319",
    "sg:postcode":"81632",
    "sg:province":"CO",
    "sg:tags":[
        "inspection"
    ],
    "wof:name":"National Property Inspections",
    "wof:placetype":"venue"
},
  "geometry": {"coordinates":[-106.59264400000001,39.647824],"type":"Point"}
}