{
  "type": "Feature",
  "properties": {
    "iso:country":"US",
    "sg:address":"3109 W Colorado Ave",
    "sg:city":"Colorado Springs",
    "sg:classifiers":[
        {
            "category":"Personal",
            "subcategory":"Nail Salon",
            "type":"Services"
        }
    ],
    "sg:phone":"+1 719 632 2331",
    "sg:postcode":"80904",
    "sg:province":"CO",
    "wof:name":"Tony's Nails",
    "wof:placetype":"venue"
},
  "geometry": {"coordinates":[-104.873001,38.8535],"type":"Point"}
}