{
  "type": "Feature",
  "properties": {
    "iso:country":"US",
    "sg:address":"10 Inverness Dr E",
    "sg:city":"Englewood",
    "sg:classifiers":[
        {
            "category":"Professional",
            "subcategory":"Research",
            "type":"Services"
        }
    ],
    "sg:phone":"+1 303 858 9912",
    "sg:postcode":"80112",
    "sg:province":"CO",
    "sg:tags":[
        "ergonomics"
    ],
    "sg:website":"www.humanscale.com",
    "wof:name":"Neutral By Design",
    "wof:placetype":"venue"
},
  "geometry": {"coordinates":[-104.866929,39.566722],"type":"Point"}
}