{
  "type": "Feature",
  "properties": {
    "addr:full":"3436 S Broadway Englewood CO 80113",
    "addr:housenumber":"3436",
    "addr:postcode":"80113",
    "addr:street":"S Broadway",
    "iso:country":"US",
    "sg:address":"3436 S Broadway",
    "sg:city":"Englewood",
    "sg:classifiers":[
        {
            "category":"Shopping",
            "subcategory":"Used Merchandise",
            "type":"Retail Goods"
        }
    ],
    "sg:phone":"+1 303 789 0305",
    "sg:postcode":"80113",
    "sg:province":"CO",
    "sg:tags":[
        "book",
        "rare",
        "dealer"
    ],
    "wof:name":"Christian Used Books",
    "wof:placetype":"venue"
},
  "geometry": {"coordinates":[-104.987551,39.65384],"type":"Point"}
}