{
  "type": "Feature",
  "properties": {
    "addr:full":"5975 N Academy Blvd Colorado Springs CO 80918",
    "addr:housenumber":"5975",
    "addr:postcode":"80918",
    "addr:street":"N Academy Blvd",
    "iso:country":"US",
    "sg:address":"5975 N Academy Blvd",
    "sg:city":"Colorado Springs",
    "sg:classifiers":[
        {
            "category":"Home & Garden",
            "subcategory":"Building Materials",
            "type":"Retail Goods"
        },
        {
            "category":"Building & Trades",
            "subcategory":"Construction",
            "type":"Services"
        }
    ],
    "sg:phone":"+1 719 634 2476",
    "sg:postcode":"80918",
    "sg:province":"CO",
    "sg:tags":[
        "glass"
    ],
    "wof:name":"City Glass Co Inc",
    "wof:placetype":"venue"
},
  "geometry": {"coordinates":[-104.786771,38.917973],"type":"Point"}
}