{
  "type": "Feature",
  "properties": {
    "iso:country":"US",
    "sg:address":"350 Interlocken Blvd",
    "sg:city":"Broomfield",
    "sg:classifiers":[
        {
            "category":"Organizations",
            "subcategory":"Professional Association",
            "type":"Services"
        }
    ],
    "sg:phone":"+1 303 466 1775",
    "sg:postcode":"80021",
    "sg:province":"CO",
    "sg:tags":[
        "chambers",
        "commerce"
    ],
    "wof:name":"Broomfield Chamber Of Commerce",
    "wof:placetype":"venue"
},
  "geometry": {"coordinates":[-105.111834,39.922287],"type":"Point"}
}