{
  "type": "Feature",
  "properties": {
    "iso:country":"US",
    "sg:address":"5685 McWhinney Blvd",
    "sg:city":"Loveland",
    "sg:classifiers":[
        {
            "category":"Shopping",
            "subcategory":"Clothing, Apparel, & Fashions",
            "type":"Retail Goods"
        }
    ],
    "sg:phone":"+1 970 679 4608",
    "sg:postcode":"80538",
    "sg:province":"CO",
    "wof:name":"IZOD",
    "wof:placetype":"venue"
},
  "geometry": {"coordinates":[-104.99354099999999,40.41097],"type":"Point"}
}