{
  "type": "Feature",
  "properties": {
    "iso:country":"US",
    "sg:address":"1860 Larimer St",
    "sg:city":"Denver",
    "sg:classifiers":[
        {
            "category":"Restaurant",
            "type":"Food & Drink"
        }
    ],
    "sg:phone":"+1 303 292 1131",
    "sg:postcode":"80205",
    "sg:province":"CO",
    "wof:name":"J C Healthy Cafe",
    "wof:placetype":"venue"
},
  "geometry": {"coordinates":[-104.994381,39.75139],"type":"Point"}
}