{
  "type": "Feature",
  "properties": {
    "iso:country":"US",
    "sg:address":"18 Harrison St",
    "sg:city":"Denver",
    "sg:classifiers":[
        {
            "category":"Health Services",
            "subcategory":"Health Practitioner",
            "type":"Services"
        }
    ],
    "sg:phone":"+1 303 320 1240",
    "sg:postcode":"80206",
    "sg:province":"CO",
    "sg:tags":[
        "acupuncture"
    ],
    "wof:name":"Arvada & Cherry Creek Acpnctr",
    "wof:placetype":"venue"
},
  "geometry": {"coordinates":[-104.941264,39.71754],"type":"Point"}
}