{
  "type": "Feature",
  "properties": {
    "iso:country":"US",
    "sg:address":"700 Main St",
    "sg:city":"Wray",
    "sg:classifiers":[
        {
            "category":"Recreation",
            "type":"Entertainment"
        }
    ],
    "sg:phone":"+1 970 332 4419",
    "sg:postcode":"80758",
    "sg:province":"CO",
    "sg:tags":[
        "parks"
    ],
    "wof:name":"WRAY Recreation Director",
    "wof:placetype":"venue"
},
  "geometry": {"coordinates":[-102.221557,40.074014],"type":"Point"}
}