{
  "type": "Feature",
  "properties": {
    "addr:full":"2266 S Colorado Blvd Denver CO 80222",
    "addr:housenumber":"2266",
    "addr:postcode":"80222",
    "addr:street":"S Colorado Blvd",
    "iso:country":"US",
    "sg:address":"2266 S Colorado Blvd",
    "sg:city":"Denver",
    "sg:classifiers":[
        {
            "category":"Bars & Pubs",
            "subcategory":"Hookah Bar",
            "type":"Food & Drink"
        }
    ],
    "sg:phone":"+1 303 758 9966",
    "sg:postcode":"80222",
    "sg:province":"CO",
    "wof:name":"Kasbah Cafe",
    "wof:placetype":"venue"
},
  "geometry": {"coordinates":[-104.940455,39.675392],"type":"Point"}
}