{
  "type": "Feature",
  "properties": {
    "iso:country":"US",
    "sg:address":"4879 W Tennessee Ave",
    "sg:city":"Denver",
    "sg:classifiers":[
        {
            "category":"Retail",
            "subcategory":"Repair Shop",
            "type":"Services"
        }
    ],
    "sg:phone":"+1 303 778 6699",
    "sg:postcode":"80219",
    "sg:province":"CO",
    "sg:tags":[
        "door"
    ],
    "wof:name":"Overhead Door Alert Svc Co",
    "wof:placetype":"venue"
},
  "geometry": {"coordinates":[-105.04939299999999,39.697658],"type":"Point"}
}