{
  "type": "Feature",
  "properties": {
    "iso:country":"US",
    "sg:address":"2601 Zephyr Dr",
    "sg:city":"Colorado Springs",
    "sg:classifiers":[
        {
            "category":"Building & Trades",
            "subcategory":"Landscaping Services",
            "type":"Services"
        }
    ],
    "sg:phone":"+1 719 522 0662",
    "sg:postcode":"80920",
    "sg:province":"CO",
    "sg:tags":[
        "designer",
        "landscape"
    ],
    "wof:name":"Smart Garden Design",
    "wof:placetype":"venue"
},
  "geometry": {"coordinates":[-104.77536000000001,38.944466],"type":"Point"}
}