{
  "type": "Feature",
  "properties": {
    "iso:country":"US",
    "sg:address":"3420 W Alameda Avenue",
    "sg:city":"Denver",
    "sg:classifiers":[
        {
            "category":"Food & Beverages",
            "subcategory":"Liquor & Beverages",
            "type":"Retail Goods"
        }
    ],
    "sg:phone":"+1 303 935 2532",
    "sg:postcode":"80219",
    "sg:province":"CO",
    "sg:tags":[
        "beer",
        "spirit",
        "wine"
    ],
    "wof:name":"Frank's Liquor Emporium",
    "wof:placetype":"venue"
},
  "geometry": {"coordinates":[-105.03156799999999,39.711251],"type":"Point"}
}