{
  "type": "Feature",
  "properties": {
    "iso:country":"US",
    "sg:address":"2532 Sheridan Blvd",
    "sg:city":"Denver",
    "sg:classifiers":[
        {
            "category":"Communications",
            "subcategory":"Television Station",
            "type":"Services"
        }
    ],
    "sg:phone":"+1 303 477 7444",
    "sg:postcode":"80214",
    "sg:province":"CO",
    "wof:name":"Tele Latino Inc",
    "wof:placetype":"venue"
},
  "geometry": {"coordinates":[-105.05331,39.754277],"type":"Point"}
}