{
  "type": "Feature",
  "properties": {
    "iso:country":"US",
    "sg:address":"6895 W 5th Ave",
    "sg:city":"Denver",
    "sg:classifiers":[
        {
            "category":"Autos & Motor Vehicles",
            "subcategory":"Automobile Sales",
            "type":"Retail Goods"
        }
    ],
    "sg:phone":"+1 303 239 6449",
    "sg:postcode":"80226",
    "sg:province":"CO",
    "sg:tags":[
        "used"
    ],
    "wof:name":"Bulldog Auto Sales Inc",
    "wof:placetype":"venue"
},
  "geometry": {"coordinates":[-105.07395200000001,39.724151],"type":"Point"}
}