{
  "type": "Feature",
  "properties": {
    "iso:country":"US",
    "sg:address":"81 Elk Ln",
    "sg:city":"Durango",
    "sg:classifiers":[
        {
            "category":"Building & Trades",
            "subcategory":"Construction",
            "type":"Services"
        }
    ],
    "sg:phone":"+1 970 749 9491",
    "sg:postcode":"81301",
    "sg:province":"CO",
    "sg:tags":[
        "painter"
    ],
    "wof:name":"All Ways Painting & Carpentry",
    "wof:placetype":"venue"
},
  "geometry": {"coordinates":[-107.68866800000001,37.364597],"type":"Point"}
}