{
  "type": "Feature",
  "properties": {
    "addr:full":"6689 Co Rd 346 Silt CO 81652",
    "addr:housenumber":"6689",
    "addr:postcode":"81652",
    "addr:street":"Co Rd 346",
    "iso:country":"US",
    "sg:address":"6689 Co Rd 346",
    "sg:city":"Silt",
    "sg:classifiers":[
        {
            "category":"Wholesale",
            "subcategory":"Construction Materials",
            "type":"Manufacturing & Wholesale Goods"
        }
    ],
    "sg:phone":"+1 970 876 0594",
    "sg:postcode":"81652",
    "sg:province":"CO",
    "wof:name":"Rock In K LLC",
    "wof:placetype":"venue"
},
  "geometry": {"coordinates":[-107.688422,39.53012],"type":"Point"}
}