{
  "type": "Feature",
  "properties": {
    "iso:country":"US",
    "sg:address":"6810 Downing St",
    "sg:city":"Denver",
    "sg:classifiers":[
        {
            "category":"Professional",
            "subcategory":"Business Services",
            "type":"Services"
        }
    ],
    "sg:phone":"+1 303 289 7710",
    "sg:postcode":"80229",
    "sg:province":"CO",
    "sg:tags":[
        "repossessing"
    ],
    "wof:name":"Pratt Adjustment Bureau",
    "wof:placetype":"venue"
},
  "geometry": {"coordinates":[-104.973218,39.820894],"type":"Point"}
}