{
  "type": "Feature",
  "properties": {
    "addr:full":"5951 S Middlefield Rd Littleton CO 80123",
    "addr:housenumber":"5951",
    "addr:postcode":"80123",
    "addr:street":"S Middlefield Rd",
    "iso:country":"US",
    "sg:address":"5951 S Middlefield Rd",
    "sg:city":"Littleton",
    "sg:classifiers":[
        {
            "category":"Professional",
            "subcategory":"Accounting & Tax Preparation",
            "type":"Services"
        }
    ],
    "sg:phone":"+1 303 730 3730",
    "sg:postcode":"80123",
    "sg:province":"CO",
    "sg:tags":[
        "accountant"
    ],
    "wof:name":"Richard S Simms CPA",
    "wof:placetype":"venue"
},
  "geometry": {"coordinates":[-105.035071,39.609083],"type":"Point"}
}