{
  "type": "Feature",
  "properties": {
    "iso:country":"US",
    "sg:address":"609 E Cooper Ave",
    "sg:city":"Aspen",
    "sg:classifiers":[
        {
            "category":"Shopping",
            "subcategory":"Clothing, Apparel, & Fashions",
            "type":"Retail Goods"
        }
    ],
    "sg:phone":"+1 970 544 3445",
    "sg:postcode":"81611",
    "sg:province":"CO",
    "wof:name":"Max Clothing Store",
    "wof:placetype":"venue"
},
  "geometry": {"coordinates":[-106.81359500000001,39.186879],"type":"Point"}
}