{
  "type": "Feature",
  "properties": {
    "iso:country":"US",
    "sg:address":"6035 W 55th Place",
    "sg:city":"Arvada",
    "sg:classifiers":[
        {
            "category":"Home & Garden",
            "subcategory":"Household Appliances",
            "type":"Retail Goods"
        }
    ],
    "sg:phone":"+1 303 431 2887",
    "sg:postcode":"80002",
    "sg:province":"CO",
    "wof:name":"Appliance Warehouse",
    "wof:placetype":"venue"
},
  "geometry": {"coordinates":[-105.062839,39.797253],"type":"Point"}
}