{
  "type": "Feature",
  "properties": {
    "addr:full":"4333 Purdy Mesa Rd Whitewater CO 81527",
    "addr:housenumber":"4333",
    "addr:postcode":"81527",
    "addr:street":"Purdy Mesa Rd",
    "iso:country":"US",
    "sg:address":"4333 Purdy Mesa Rd",
    "sg:city":"Whitewater",
    "sg:classifiers":[
        {
            "category":"Building & Trades",
            "subcategory":"Construction",
            "type":"Services"
        }
    ],
    "sg:phone":"+1 970 257 0192",
    "sg:postcode":"81527",
    "sg:province":"CO",
    "sg:tags":[
        "carpentry",
        "contractor"
    ],
    "wof:name":"Molnar Construction Inc",
    "wof:placetype":"venue"
},
  "geometry": {"coordinates":[-108.28648699999999,38.956541],"type":"Point"}
}