{
  "type": "Feature",
  "properties": {
    "iso:country":"US",
    "sg:address":"1147 S Huron St",
    "sg:city":"Denver",
    "sg:classifiers":[
        {
            "category":"Wholesale",
            "subcategory":"Non-durable Goods",
            "type":"Manufacturing & Wholesale Goods"
        }
    ],
    "sg:phone":"+1 303 933 1413",
    "sg:postcode":"80223",
    "sg:province":"CO",
    "wof:name":"Peak Distributing Inc",
    "wof:placetype":"venue"
},
  "geometry": {"coordinates":[-104.996878,39.695723],"type":"Point"}
}