{
  "type": "Feature",
  "properties": {
    "addr:full":"48 E Main St Cortez CO 81321",
    "addr:housenumber":"48",
    "addr:postcode":"81321",
    "addr:street":"E Main St",
    "iso:country":"US",
    "sg:address":"48 E Main St",
    "sg:city":"Cortez",
    "sg:classifiers":[
        {
            "category":"Shopping",
            "subcategory":"Optical Goods",
            "type":"Retail Goods"
        }
    ],
    "sg:phone":"+1 970 565 1580",
    "sg:postcode":"81321",
    "sg:province":"CO",
    "wof:name":"Optical Shoppe",
    "wof:placetype":"venue"
},
  "geometry": {"coordinates":[-108.584412,37.348709],"type":"Point"}
}