{
  "type": "Feature",
  "properties": {
    "addr:full":"2649 Hatch Cir Colorado Springs CO 80918",
    "addr:housenumber":"2649",
    "addr:postcode":"80918",
    "addr:street":"Hatch Cir",
    "iso:country":"US",
    "sg:address":"2649 Hatch Cir",
    "sg:city":"Colorado Springs",
    "sg:classifiers":[
        {
            "category":"Government",
            "subcategory":"Office",
            "type":"Public Place"
        }
    ],
    "sg:phone":"+1 719 554 5055",
    "sg:postcode":"80918",
    "sg:province":"CO",
    "sg:tags":[
        "national",
        "security"
    ],
    "wof:name":"Air Force US Dept of",
    "wof:placetype":"venue"
},
  "geometry": {"coordinates":[-104.779698,38.932068],"type":"Point"}
}