{
  "type": "Feature",
  "properties": {
    "iso:country":"US",
    "sg:address":"6888 Centennial Blvd",
    "sg:city":"Colorado Springs",
    "sg:classifiers":[
        {
            "category":"Restaurant",
            "type":"Food & Drink"
        }
    ],
    "sg:menulink":"http://www.allmenus.com/co/colorado-springs/77656-papa-murphys/menu/",
    "sg:phone":"+1 719 219 0014",
    "sg:postcode":"80919",
    "sg:province":"CO",
    "sg:tags":[
        "american",
        "pizza"
    ],
    "wof:name":"Papa Murphy's",
    "wof:placetype":"venue"
},
  "geometry": {"coordinates":[-104.86539399999999,38.930996],"type":"Point"}
}