{
  "type": "Feature",
  "properties": {
    "iso:country":"US",
    "sg:address":"910 W Cherry St",
    "sg:city":"Louisville",
    "sg:classifiers":[
        {
            "category":"Banks & Credit Unions",
            "subcategory":"Bank",
            "type":"Services"
        }
    ],
    "sg:phone":"+1 303 604 9872",
    "sg:postcode":"80027",
    "sg:province":"CO",
    "wof:name":"US Bank",
    "wof:placetype":"venue"
},
  "geometry": {"coordinates":[-105.14849100000001,39.965069],"type":"Point"}
}