{
  "type": "Feature",
  "properties": {
    "addr:full":"1212 Motor City Dr Colorado Springs CO 80906",
    "addr:housenumber":"1212",
    "addr:postcode":"80906",
    "addr:street":"Motor City Dr",
    "iso:country":"US",
    "sg:address":"1212 Motor City Dr",
    "sg:city":"Colorado Springs",
    "sg:classifiers":[
        {
            "category":"Autos & Motor Vehicles",
            "subcategory":"Automobile Sales",
            "type":"Retail Goods"
        }
    ],
    "sg:phone":"+1 719 575 7000",
    "sg:postcode":"80906",
    "sg:province":"CO",
    "sg:tags":[
        "use",
        "supply"
    ],
    "wof:name":"Saturn",
    "wof:placetype":"venue"
},
  "geometry": {"coordinates":[-104.830701,38.813825],"type":"Point"}
}