{
  "type": "Feature",
  "properties": {
    "addr:full":"4361 Raleigh St Denver CO 80212",
    "addr:housenumber":"4361",
    "addr:postcode":"80212",
    "addr:street":"Raleigh St",
    "iso:country":"US",
    "sg:address":"4361 Raleigh St",
    "sg:city":"Denver",
    "sg:classifiers":[
        {
            "category":"Professional",
            "type":"Services"
        }
    ],
    "sg:phone":"+1 303 455 2972",
    "sg:postcode":"80212",
    "sg:province":"CO",
    "wof:name":"Junkyard Studios",
    "wof:placetype":"venue"
},
  "geometry": {"coordinates":[-105.041704,39.775829],"type":"Point"}
}