{
  "type": "Feature",
  "properties": {
    "iso:country":"US",
    "sg:address":"3230 Youngfield St",
    "sg:city":"Wheat Ridge",
    "sg:classifiers":[
        {
            "category":"Professional",
            "type":"Services"
        }
    ],
    "sg:phone":"+1 303 988 7141",
    "sg:postcode":"80033",
    "sg:province":"CO",
    "sg:tags":[
        "establishment"
    ],
    "wof:name":"Verify Plus Systems",
    "wof:placetype":"venue"
},
  "geometry": {"coordinates":[-105.142455,39.764792],"type":"Point"}
}