{
  "type": "Feature",
  "properties": {
    "iso:country":"US",
    "sg:address":"303 W Aspen Ave",
    "sg:city":"Fruita",
    "sg:classifiers":[
        {
            "category":"Real Estate",
            "subcategory":"Real Estate Agent",
            "type":"Services"
        }
    ],
    "sg:phone":"+1 970 858 9577",
    "sg:postcode":"81521",
    "sg:province":"CO",
    "wof:name":"Fruita Realty Inc",
    "wof:placetype":"venue"
},
  "geometry": {"coordinates":[-108.735951,39.158949],"type":"Point"}
}