{
  "type": "Feature",
  "properties": {
    "addr:full":"1824 W Colfax Ave Denver CO 80204",
    "addr:housenumber":"1824",
    "addr:postcode":"80204",
    "addr:street":"W Colfax Ave",
    "iso:country":"US",
    "sg:address":"1824 W Colfax Ave",
    "sg:city":"Denver",
    "sg:classifiers":[
        {
            "category":"Wholesale",
            "subcategory":"Metals & Minerals",
            "type":"Manufacturing & Wholesale Goods"
        }
    ],
    "sg:phone":"+1 303 534 7075",
    "sg:postcode":"80204",
    "sg:province":"CO",
    "sg:tags":[
        "steel",
        "warehouse"
    ],
    "wof:name":"Atlas Metal Sales",
    "wof:placetype":"venue"
},
  "geometry": {"coordinates":[-105.00897500000001,39.740249],"type":"Point"}
}