{
  "type": "Feature",
  "properties": {
    "addr:full":"2110 W Elizabeth St Fort Collins CO 80521",
    "addr:housenumber":"2110",
    "addr:postcode":"80521",
    "addr:street":"W Elizabeth St",
    "iso:country":"US",
    "sg:address":"2110 W Elizabeth St",
    "sg:city":"Fort Collins",
    "sg:classifiers":[
        {
            "category":"Restaurant",
            "type":"Food & Drink"
        }
    ],
    "sg:menulink":"http://www.allmenus.com/co/fort-collins/69474-dominos-pizza/menu/",
    "sg:phone":"+1 970 484 3030",
    "sg:postcode":"80521",
    "sg:province":"CO",
    "sg:tags":[
        "american",
        "wing",
        "pizza"
    ],
    "wof:name":"Domino's Pizza",
    "wof:placetype":"venue"
},
  "geometry": {"coordinates":[-105.11600199999999,40.575162],"type":"Point"}
}