{
  "type": "Feature",
  "properties": {
    "iso:country":"US",
    "sg:address":"417 4th St",
    "sg:city":"Nunn",
    "sg:classifiers":[
        {
            "category":"Building & Trades",
            "subcategory":"Plumbing",
            "type":"Services"
        }
    ],
    "sg:phone":"+1 970 353 7553",
    "sg:postcode":"80648",
    "sg:province":"CO",
    "sg:tags":[
        "heating",
        "contractor"
    ],
    "wof:name":"Mike's Heating & Air Cond",
    "wof:placetype":"venue"
},
  "geometry": {"coordinates":[-104.787166,40.703443],"type":"Point"}
}