{
  "type": "Feature",
  "properties": {
    "addr:full":"6703 Gray Ct Arvada CO 80003",
    "addr:housenumber":"6703",
    "addr:postcode":"80003",
    "addr:street":"Gray Ct",
    "iso:country":"US",
    "sg:address":"6703 Gray Ct",
    "sg:city":"Arvada",
    "sg:classifiers":[
        {
            "category":"Shopping",
            "subcategory":"Used Merchandise",
            "type":"Retail Goods"
        }
    ],
    "sg:phone":"+1 303 940 8522",
    "sg:postcode":"80003",
    "sg:province":"CO",
    "wof:name":"Peddler Art",
    "wof:placetype":"venue"
},
  "geometry": {"coordinates":[-105.061286,39.820006],"type":"Point"}
}