{
  "type": "Feature",
  "properties": {
    "iso:country":"US",
    "sg:address":"5066 S Wadsworth Blvd",
    "sg:city":"Lakewood",
    "sg:classifiers":[
        {
            "category":"Shopping",
            "type":"Retail Goods"
        }
    ],
    "sg:phone":"+1 303 948 0134",
    "sg:postcode":"80123",
    "sg:province":"CO",
    "sg:tags":[
        "orthopedic",
        "appliance",
        "merchandise"
    ],
    "wof:name":"Orthopedic Rehab",
    "wof:placetype":"venue"
},
  "geometry": {"coordinates":[-105.081807,39.625911],"type":"Point"}
}