{
  "type": "Feature",
  "properties": {
    "addr:full":"6447 E Evans Ave Denver CO 80210",
    "addr:housenumber":"6447",
    "addr:postcode":"80210",
    "addr:street":"E Evans Ave",
    "iso:country":"US",
    "sg:address":"6447 E Evans Ave",
    "sg:city":"Denver",
    "sg:classifiers":[
        {
            "category":"Personal",
            "subcategory":"Beauty Salon",
            "type":"Services"
        }
    ],
    "sg:phone":"+1 303 759 2085",
    "sg:postcode":"80210",
    "sg:province":"CO",
    "sg:tags":[
        "shop"
    ],
    "wof:name":"Hair Company",
    "wof:placetype":"venue"
},
  "geometry": {"coordinates":[-104.91474700000001,39.678536],"type":"Point"}
}