{
  "type": "Feature",
  "properties": {
    "iso:country":"US",
    "sg:address":"1671 Upper Bear Creek Rd",
    "sg:city":"Evergreen",
    "sg:classifiers":[
        {
            "category":"Professional",
            "type":"Services"
        }
    ],
    "sg:phone":"+1 303 670 7275",
    "sg:postcode":"80439",
    "sg:province":"CO",
    "wof:name":"Anthony Reed",
    "wof:placetype":"venue"
},
  "geometry": {"coordinates":[-105.42237,39.628269],"type":"Point"}
}