{
  "type": "Feature",
  "properties": {
    "addr:full":"24016 Hwy 263 Greeley CO 80631",
    "addr:housenumber":"24016",
    "addr:postcode":"80631",
    "addr:street":"Hwy 263",
    "iso:country":"US",
    "sg:address":"24016 Hwy 263",
    "sg:city":"Greeley",
    "sg:classifiers":[
        {
            "category":"Manufacturing",
            "subcategory":"Tools & Machinery",
            "type":"Manufacturing & Wholesale Goods"
        }
    ],
    "sg:phone":"+1 970 352 8213",
    "sg:postcode":"80631",
    "sg:province":"CO",
    "sg:tags":[
        "machine",
        "shop"
    ],
    "wof:name":"Bob's Welding & Machine",
    "wof:placetype":"venue"
},
  "geometry": {"coordinates":[-104.60175099999999,40.427934],"type":"Point"}
}