{
  "type": "Feature",
  "properties": {
    "addr:full":"12102 W 84th Pl Arvada CO 80005",
    "addr:housenumber":"12102",
    "addr:postcode":"80005",
    "addr:street":"W 84Th Pl",
    "iso:country":"US",
    "sg:address":"12102 W 84th Pl",
    "sg:city":"Arvada",
    "sg:classifiers":[
        {
            "category":"Wholesale",
            "subcategory":"Drugs",
            "type":"Manufacturing & Wholesale Goods"
        }
    ],
    "sg:phone":"+1 303 420 9979",
    "sg:postcode":"80005",
    "sg:province":"CO",
    "wof:name":"Group Clarins USA",
    "wof:placetype":"venue"
},
  "geometry": {"coordinates":[-105.137384,39.849711],"type":"Point"}
}