{
  "type": "Feature",
  "properties": {
    "iso:country":"US",
    "sg:address":"445 Denver Ave",
    "sg:city":"Loveland",
    "sg:classifiers":[
        {
            "category":"Home & Garden",
            "subcategory":"Building Materials",
            "type":"Retail Goods"
        }
    ],
    "sg:phone":"+1 970 498 8995",
    "sg:postcode":"80537",
    "sg:province":"CO",
    "sg:tags":[
        "windows"
    ],
    "wof:name":"Window Center Inc",
    "wof:placetype":"venue"
},
  "geometry": {"coordinates":[-105.044786,40.396099],"type":"Point"}
}