{
  "type": "Feature",
  "properties": {
    "iso:country":"US",
    "sg:address":"1409 Ogden",
    "sg:city":"Denver",
    "sg:classifiers":[
        {
            "category":"Sports & Exercise",
            "subcategory":"Gym",
            "type":"Entertainment"
        }
    ],
    "sg:phone":"+1 720 235 2131",
    "sg:postcode":"80218",
    "sg:province":"CO",
    "sg:tags":[
        "pilate"
    ],
    "sg:website":"www.ph7pilates.com",
    "wof:name":"PH7 Pilates",
    "wof:placetype":"venue"
},
  "geometry": {"coordinates":[-104.975309,39.738646],"type":"Point"}
}