{
  "type": "Feature",
  "properties": {
    "addr:full":"521 Albion St Denver CO 80220",
    "addr:housenumber":"521",
    "addr:postcode":"80220",
    "addr:street":"Albion St",
    "iso:country":"US",
    "sg:address":"521 Albion St",
    "sg:city":"Denver",
    "sg:classifiers":[
        {
            "category":"Professional",
            "type":"Services"
        }
    ],
    "sg:phone":"+1 303 394 0036",
    "sg:postcode":"80220",
    "sg:province":"CO",
    "wof:name":"Jamie Lacasse",
    "wof:placetype":"venue"
},
  "geometry": {"coordinates":[-104.939407,39.725111],"type":"Point"}
}