{
  "type": "Feature",
  "properties": {
    "iso:country":"US",
    "sg:address":"410 W 24th St",
    "sg:city":"Pueblo",
    "sg:classifiers":[
        {
            "category":"Professional",
            "type":"Services"
        }
    ],
    "sg:phone":"+1 719 253 1353",
    "sg:postcode":"81003",
    "sg:province":"CO",
    "sg:tags":[
        "establishment"
    ],
    "wof:name":"L I",
    "wof:placetype":"venue"
},
  "geometry": {"coordinates":[-104.61263599999999,38.291135],"type":"Point"}
}