{
  "type": "Feature",
  "properties": {
    "iso:country":"US",
    "sg:address":"1450 Hoyt St",
    "sg:city":"Lakewood",
    "sg:classifiers":[
        {
            "category":"Organizations",
            "subcategory":"Non-profit Organization",
            "type":"Services"
        }
    ],
    "sg:phone":"+1 303 233 7151",
    "sg:postcode":"80215",
    "sg:province":"CO",
    "sg:tags":[
        "information",
        "alcoholism",
        "treatment"
    ],
    "wof:name":"Discovery-Anthony De Vonna",
    "wof:placetype":"venue"
},
  "geometry": {"coordinates":[-105.1036,39.739274],"type":"Point"}
}