{
  "type": "Feature",
  "properties": {
    "iso:country":"US",
    "sg:address":"1600 17th St",
    "sg:city":"Denver",
    "sg:classifiers":[
        {
            "category":"Wholesale",
            "subcategory":"Non-durable Goods",
            "type":"Manufacturing & Wholesale Goods"
        }
    ],
    "sg:phone":"+1 303 628 5485",
    "sg:postcode":"80202",
    "sg:province":"CO",
    "sg:tags":[
        "merchandise-wholesale"
    ],
    "wof:name":"Cs Wine Imports",
    "wof:placetype":"venue"
},
  "geometry": {"coordinates":[-104.99884,39.752159],"type":"Point"}
}