{
  "type": "Feature",
  "properties": {
    "iso:country":"US",
    "sg:address":"1800 15th St",
    "sg:city":"Denver",
    "sg:classifiers":[
        {
            "category":"Organizations",
            "subcategory":"Non-profit Organization",
            "type":"Services"
        }
    ],
    "sg:phone":"+1 303 534 5297",
    "sg:postcode":"80202",
    "sg:province":"CO",
    "wof:name":"Donated Dental Svc",
    "wof:placetype":"venue"
},
  "geometry": {"coordinates":[-105.003747,39.7521],"type":"Point"}
}