{
  "type": "Feature",
  "properties": {
    "iso:country":"US",
    "sg:address":"8086 Midway Dr",
    "sg:city":"Littleton",
    "sg:classifiers":[
        {
            "category":"Wholesale",
            "subcategory":"Construction Materials",
            "type":"Manufacturing & Wholesale Goods"
        },
        {
            "category":"Building & Trades",
            "subcategory":"Construction",
            "type":"Services"
        },
        {
            "category":"Military Area",
            "subcategory":"Armory",
            "type":"Public Place"
        }
    ],
    "sg:phone":"+1 720 344 8045",
    "sg:postcode":"80125",
    "sg:province":"CO",
    "sg:tags":[
        "repair",
        "fence",
        "contractor",
        "fence-wholesale",
        "manufacturer",
        "fence-sales"
    ],
    "wof:name":"Split-Rail Fence Co Inc",
    "wof:placetype":"venue"
},
  "geometry": {"coordinates":[-105.038161,39.547741],"type":"Point"}
}