{
  "type": "Feature",
  "properties": {
    "iso:country":"US",
    "sg:address":"7355 Ralston Rd",
    "sg:city":"Arvada",
    "sg:classifiers":[
        {
            "category":"Personal",
            "subcategory":"Beauty Salon",
            "type":"Services"
        }
    ],
    "sg:phone":"+1 303 940 9060",
    "sg:postcode":"80002",
    "sg:province":"CO",
    "sg:tags":[
        "hair"
    ],
    "wof:name":"Great Clips",
    "wof:placetype":"venue"
},
  "geometry": {"coordinates":[-105.078801,39.802062],"type":"Point"}
}