{
  "type": "Feature",
  "properties": {
    "addr:full":"532 Tamarack Dr Steamboat Spgs CO 80487",
    "addr:housenumber":"532",
    "addr:postcode":"80487",
    "addr:street":"Tamarack Dr;Spgs",
    "iso:country":"US",
    "sg:address":"532 Tamarack Dr",
    "sg:city":"Steamboat Spgs",
    "sg:classifiers":[
        {
            "category":"Travel",
            "subcategory":"Travel Agent",
            "type":"Entertainment"
        }
    ],
    "sg:phone":"+1 970 879 6250",
    "sg:postcode":"80487",
    "sg:province":"CO",
    "sg:tags":[
        "agency",
        "bureau"
    ],
    "wof:name":"Magic Carpet Travel",
    "wof:placetype":"venue"
},
  "geometry": {"coordinates":[-106.823283,40.478676],"type":"Point"}
}