{
  "type": "Feature",
  "properties": {
    "iso:country":"US",
    "sg:address":"1451 Depew Street",
    "sg:city":"Lakewood",
    "sg:classifiers":[
        {
            "category":"Retail",
            "subcategory":"Auto Repair",
            "type":"Services"
        }
    ],
    "sg:phone":"+1 303 232 7643",
    "sg:postcode":"80214",
    "sg:province":"CO",
    "wof:name":"Gaylord's Garage",
    "wof:placetype":"venue"
},
  "geometry": {"coordinates":[-105.058026,39.739766],"type":"Point"}
}