{
  "type": "Feature",
  "properties": {
    "addr:full":"2680 Broadway St Boulder CO 80304",
    "addr:housenumber":"2680",
    "addr:postcode":"80304",
    "addr:street":"Broadway St",
    "iso:country":"US",
    "sg:address":"2680 Broadway St",
    "sg:city":"Boulder",
    "sg:classifiers":[
        {
            "category":"Restaurant",
            "type":"Food & Drink"
        }
    ],
    "sg:phone":"+1 303 440 8209",
    "sg:postcode":"80304",
    "sg:province":"CO",
    "sg:tags":[
        "eating"
    ],
    "wof:name":"Vics",
    "wof:placetype":"venue"
},
  "geometry": {"coordinates":[-105.281971,40.02466],"type":"Point"}
}