{
  "type": "Feature",
  "properties": {
    "addr:full":"4085 E Mississippi Ave Denver CO 80246",
    "addr:housenumber":"4085",
    "addr:postcode":"80246",
    "addr:street":"E Mississippi Ave",
    "iso:country":"US",
    "sg:address":"4085 E Mississippi Ave",
    "sg:city":"Denver",
    "sg:classifiers":[
        {
            "category":"Building & Trades",
            "subcategory":"Locksmith",
            "type":"Services"
        }
    ],
    "sg:phone":"+1 866 686 5681",
    "sg:postcode":"80246",
    "sg:province":"CO",
    "sg:tags":[
        "key"
    ],
    "wof:name":"Anytime Emergency Locksmith",
    "wof:placetype":"venue"
},
  "geometry": {"coordinates":[-104.940095,39.696727],"type":"Point"}
}