{
  "type": "Feature",
  "properties": {
    "iso:country":"US",
    "sg:address":"444 S Federal Blvd",
    "sg:city":"Denver",
    "sg:classifiers":[
        {
            "category":"Wholesale",
            "subcategory":"Durable Goods & Equipment",
            "type":"Manufacturing & Wholesale Goods"
        }
    ],
    "sg:phone":"+1 303 975 9328",
    "sg:postcode":"80219",
    "sg:province":"CO",
    "sg:tags":[
        "importer"
    ],
    "wof:name":"Rising Sun Imports Inc",
    "wof:placetype":"venue"
},
  "geometry": {"coordinates":[-105.025007,39.708005],"type":"Point"}
}