{
  "type": "Feature",
  "properties": {
    "addr:full":"117 Crawford Cir Golden CO 80401",
    "addr:housenumber":"117",
    "addr:postcode":"80401",
    "addr:street":"Crawford Cir",
    "iso:country":"US",
    "sg:address":"117 Crawford Cir",
    "sg:city":"Golden",
    "sg:classifiers":[
        {
            "category":"Manufacturing",
            "subcategory":"Apparel",
            "type":"Manufacturing & Wholesale Goods"
        }
    ],
    "sg:phone":"+1 303 278 2401",
    "sg:postcode":"80401",
    "sg:province":"CO",
    "wof:name":"Ginnys Place LLC",
    "wof:placetype":"venue"
},
  "geometry": {"coordinates":[-105.212171,39.717213],"type":"Point"}
}