{
  "type": "Feature",
  "properties": {
    "iso:country":"US",
    "sg:address":"6085 Lake Shore Ct",
    "sg:city":"Colorado Springs",
    "sg:classifiers":[
        {
            "category":"Building & Trades",
            "subcategory":"Plumbing",
            "type":"Services"
        }
    ],
    "sg:phone":"+1 719 596 1900",
    "sg:postcode":"80915",
    "sg:province":"CO",
    "sg:tags":[
        "heating",
        "contractor"
    ],
    "wof:name":"Mech One",
    "wof:placetype":"venue"
},
  "geometry": {"coordinates":[-104.713031,38.86423],"type":"Point"}
}