{
  "type": "Feature",
  "properties": {
    "addr:full":"3270 S Park Dr Littleton CO 80132",
    "addr:housenumber":"3270",
    "addr:postcode":"80132",
    "addr:street":"S Park Dr",
    "iso:country":"US",
    "sg:address":"3270 S Park Dr",
    "sg:city":"Littleton",
    "sg:classifiers":[
        {
            "category":"Arena",
            "subcategory":"Sports Club",
            "type":"Entertainment"
        }
    ],
    "sg:phone":"+1 720 348 0283",
    "sg:postcode":"80132",
    "sg:province":"CO",
    "sg:tags":[
        "athletic",
        "fields",
        "stadium"
    ],
    "wof:name":"Shea Stadium",
    "wof:placetype":"venue"
},
  "geometry": {"coordinates":[-104.852631,39.096701],"type":"Point"}
}