{
  "type": "Feature",
  "properties": {
    "iso:country":"US",
    "sg:address":"511 E Geneseo St",
    "sg:city":"Lafayette",
    "sg:classifiers":[
        {
            "category":"Real Estate",
            "subcategory":"Real Estate Agent",
            "type":"Services"
        }
    ],
    "sg:phone":"+1 303 604 9093",
    "sg:postcode":"80026",
    "sg:province":"CO",
    "wof:name":"Ritz & Co",
    "wof:placetype":"venue"
},
  "geometry": {"coordinates":[-105.084299,39.999294],"type":"Point"}
}