{
  "type": "Feature",
  "properties": {
    "iso:country":"US",
    "sg:address":"425 S Cherry St",
    "sg:city":"Denver",
    "sg:classifiers":[
        {
            "category":"Professional",
            "subcategory":"Accounting & Tax Preparation",
            "type":"Services"
        }
    ],
    "sg:phone":"+1 303 321 9122",
    "sg:postcode":"80246",
    "sg:province":"CO",
    "sg:tags":[
        "accountant"
    ],
    "wof:name":"Stanley Reed & Co",
    "wof:placetype":"venue"
},
  "geometry": {"coordinates":[-104.933494,39.707982],"type":"Point"}
}