{
  "type": "Feature",
  "properties": {
    "iso:country":"US",
    "sg:address":"3000 S College Ave",
    "sg:city":"Fort Collins",
    "sg:classifiers":[
        {
            "category":"Health Services",
            "subcategory":"Doctor",
            "type":"Services"
        }
    ],
    "sg:phone":"+1 970 266 8822",
    "sg:postcode":"80525",
    "sg:province":"CO",
    "sg:tags":[
        "physician",
        "surgeon"
    ],
    "wof:name":"Family Health Care-The Rockies",
    "wof:placetype":"venue"
},
  "geometry": {"coordinates":[-105.07707000000001,40.545791],"type":"Point"}
}