{
  "type": "Feature",
  "properties": {
    "addr:full":"6201 E 49th Ave Commerce City CO 80022",
    "addr:housenumber":"6201",
    "addr:postcode":"80022",
    "addr:street":"E 49Th Ave",
    "iso:country":"US",
    "sg:address":"6201 E 49th Ave",
    "sg:city":"Commerce City",
    "sg:classifiers":[
        {
            "category":"Autos & Motor Vehicles",
            "subcategory":"Auto Supplies",
            "type":"Retail Goods"
        }
    ],
    "sg:phone":"+1 303 287 4054",
    "sg:postcode":"80022",
    "sg:province":"CO",
    "wof:name":"Interstate Battery",
    "wof:placetype":"venue"
},
  "geometry": {"coordinates":[-104.914475,39.785229],"type":"Point"}
}