{
  "type": "Feature",
  "properties": {
    "addr:full":"510 Fairfax St Denver CO 80220",
    "addr:housenumber":"510",
    "addr:postcode":"80220",
    "addr:street":"Fairfax St",
    "iso:country":"US",
    "sg:address":"510 Fairfax St",
    "sg:city":"Denver",
    "sg:classifiers":[
        {
            "category":"Retail",
            "subcategory":"Portrait Studio",
            "type":"Services"
        }
    ],
    "sg:phone":"+1 303 336 9501",
    "sg:postcode":"80220",
    "sg:province":"CO",
    "sg:tags":[
        "photographer"
    ],
    "wof:name":"Backcountry Images",
    "wof:placetype":"venue"
},
  "geometry": {"coordinates":[-104.92823300000001,39.723501],"type":"Point"}
}