{
  "type": "Feature",
  "properties": {
    "addr:full":"27972 Meadow Dr Evergreen CO 80439",
    "addr:housenumber":"27972",
    "addr:postcode":"80439",
    "addr:street":"Meadow Dr",
    "iso:country":"US",
    "sg:address":"27972 Meadow Dr",
    "sg:city":"Evergreen",
    "sg:classifiers":[
        {
            "category":"Professional",
            "subcategory":"Management & Consulting",
            "type":"Services"
        }
    ],
    "sg:phone":"+1 303 670 3522",
    "sg:postcode":"80439",
    "sg:province":"CO",
    "wof:name":"Tetra Tech Inc",
    "wof:placetype":"venue"
},
  "geometry": {"coordinates":[-105.315404,39.636301],"type":"Point"}
}