{
  "type": "Feature",
  "properties": {
    "iso:country":"US",
    "sg:address":"2420 W 26th Ave",
    "sg:city":"Denver",
    "sg:classifiers":[
        {
            "category":"Education",
            "subcategory":"College",
            "type":"Public Place"
        }
    ],
    "sg:phone":"+1 303 477 5864",
    "sg:postcode":"80211",
    "sg:province":"CO",
    "wof:name":"State Board For Community",
    "wof:placetype":"venue"
},
  "geometry": {"coordinates":[-105.017408,39.754741],"type":"Point"}
}