{
  "type": "Feature",
  "properties": {
    "addr:full":"7112 W Jefferson Ave Lakewood CO 80235",
    "addr:housenumber":"7112",
    "addr:postcode":"80235",
    "addr:street":"W Jefferson Ave",
    "iso:country":"US",
    "sg:address":"7112 W Jefferson Ave",
    "sg:city":"Lakewood",
    "sg:classifiers":[
        {
            "category":"Health Services",
            "subcategory":"Doctor",
            "type":"Services"
        }
    ],
    "sg:phone":"+1 303 989 1858",
    "sg:postcode":"80235",
    "sg:province":"CO",
    "sg:tags":[
        "clinic"
    ],
    "wof:name":"Samaritan Dialysis DME LLC",
    "wof:placetype":"venue"
},
  "geometry": {"coordinates":[-105.07904000000001,39.649846],"type":"Point"}
}