{
  "type": "Feature",
  "properties": {
    "iso:country":"US",
    "sg:address":"507 E Spaulding St",
    "sg:city":"Lafayette",
    "sg:classifiers":[
        {
            "category":"Real Estate",
            "subcategory":"Real Estate Operator",
            "type":"Services"
        }
    ],
    "sg:phone":"+1 303 665 6457",
    "sg:postcode":"80026",
    "sg:province":"CO",
    "sg:tags":[
        "mobile",
        "home",
        "site"
    ],
    "wof:name":"Arbordale Acres",
    "wof:placetype":"venue"
},
  "geometry": {"coordinates":[-105.08925600000001,39.991353],"type":"Point"}
}