{
  "type": "Feature",
  "properties": {
    "addr:full":"5717 W 11th Ave Denver CO 80214",
    "addr:housenumber":"5717",
    "addr:postcode":"80214",
    "addr:street":"W 11Th Ave",
    "iso:country":"US",
    "sg:address":"5717 W 11th Ave",
    "sg:city":"Denver",
    "sg:classifiers":[
        {
            "category":"Building & Trades",
            "subcategory":"Landscaping Services",
            "type":"Services"
        }
    ],
    "sg:phone":"+1 303 232 0666",
    "sg:postcode":"80214",
    "sg:province":"CO",
    "sg:tags":[
        "lawn",
        "removing",
        "tree",
        "spraying",
        "bush",
        "car",
        "trimming"
    ],
    "wof:name":"Mountain High Tree Svc & Lwn C",
    "wof:placetype":"venue"
},
  "geometry": {"coordinates":[-105.060838,39.734993],"type":"Point"}
}