{
  "type": "Feature",
  "properties": {
    "iso:country":"US",
    "sg:address":"960 Wolff St",
    "sg:city":"Denver",
    "sg:classifiers":[
        {
            "category":"Manufacturing",
            "subcategory":"Motor Vehicles & Parts",
            "type":"Manufacturing & Wholesale Goods"
        }
    ],
    "sg:phone":"+1 303 573 4995",
    "sg:postcode":"80204",
    "sg:province":"CO",
    "sg:tags":[
        "mfg"
    ],
    "wof:name":"Kurt L Buckeye",
    "wof:placetype":"venue"
},
  "geometry": {"coordinates":[-105.048603,39.732521],"type":"Point"}
}