{
  "type": "Feature",
  "properties": {
    "addr:full":"5727 Wadsworth Byp Arvada CO 80002",
    "addr:housenumber":"5727",
    "addr:postcode":"80002",
    "addr:street":"Wadsworth Byp",
    "iso:country":"US",
    "sg:address":"5727 Wadsworth Byp",
    "sg:city":"Arvada",
    "sg:classifiers":[
        {
            "category":"Personal",
            "subcategory":"Beauty Salon",
            "type":"Services"
        }
    ],
    "sg:phone":"+1 303 432 8006",
    "sg:postcode":"80002",
    "sg:province":"CO",
    "wof:name":"Heidie's Beauty Salon",
    "wof:placetype":"venue"
},
  "geometry": {"coordinates":[-105.076566,39.801279],"type":"Point"}
}