{
  "type": "Feature",
  "properties": {
    "iso:country":"US",
    "sg:address":"1483 Lodge Ct",
    "sg:city":"Boulder",
    "sg:classifiers":[
        {
            "category":"Social Services",
            "subcategory":"Job Training",
            "type":"Services"
        }
    ],
    "sg:phone":"+1 303 444 1944",
    "sg:postcode":"80303",
    "sg:province":"CO",
    "sg:tags":[
        "rehabilitation"
    ],
    "wof:name":"Donald Vogenthaler",
    "wof:placetype":"venue"
},
  "geometry": {"coordinates":[-105.22607499999999,40.013018],"type":"Point"}
}