{
  "type": "Feature",
  "properties": {
    "iso:country":"US",
    "sg:address":"151 Summit Blvd",
    "sg:city":"Englewood",
    "sg:classifiers":[
        {
            "category":"Building & Trades",
            "subcategory":"Landscaping Services",
            "type":"Services"
        },
        {
            "category":"Building & Trades",
            "subcategory":"Construction",
            "type":"Services"
        }
    ],
    "sg:phone":"+1 303 722 5043",
    "sg:postcode":"80113",
    "sg:province":"CO",
    "sg:tags":[
        "designer",
        "grading",
        "consultant",
        "tree",
        "contractor",
        "landscape"
    ],
    "wof:name":"Fairbairn Tree And Landscape Specialists",
    "wof:placetype":"venue"
},
  "geometry": {"coordinates":[-104.96762099999999,39.626068],"type":"Point"}
}