{
  "type": "Feature",
  "properties": {
    "iso:country":"US",
    "sg:address":"4835 W 73rd Ave",
    "sg:city":"Westminster",
    "sg:classifiers":[
        {
            "category":"Wholesale",
            "subcategory":"Farm Supplies",
            "type":"Manufacturing & Wholesale Goods"
        }
    ],
    "sg:phone":"+1 303 412 5767",
    "sg:postcode":"80030",
    "sg:province":"CO",
    "sg:tags":[
        "raw",
        "product",
        "material"
    ],
    "wof:name":"Kettle Corn",
    "wof:placetype":"venue"
},
  "geometry": {"coordinates":[-105.047837,39.829576],"type":"Point"}
}