{
  "type": "Feature",
  "properties": {
    "iso:country":"US",
    "sg:address":"2000 E County Line Rd",
    "sg:city":"Littleton",
    "sg:classifiers":[
        {
            "category":"Shopping",
            "subcategory":"Optical Goods",
            "type":"Retail Goods"
        }
    ],
    "sg:phone":"+1 303 794 2020",
    "sg:postcode":"80126",
    "sg:province":"CO",
    "wof:name":"Eyecare Center",
    "wof:placetype":"venue"
},
  "geometry": {"coordinates":[-104.96804899999999,39.566003],"type":"Point"}
}