{
  "type": "Feature",
  "properties": {
    "iso:country":"US",
    "sg:address":"15841 Dale Ave",
    "sg:city":"Fort Lupton",
    "sg:classifiers":[
        {
            "category":"Food & Beverages",
            "subcategory":"Specialty",
            "type":"Retail Goods"
        }
    ],
    "sg:phone":"+1 303 857 4210",
    "sg:postcode":"80621",
    "sg:province":"CO",
    "sg:tags":[
        "water",
        "bulk",
        "company"
    ],
    "wof:name":"Aristocrat Ranchettes Water",
    "wof:placetype":"venue"
},
  "geometry": {"coordinates":[-104.756128,40.113914],"type":"Point"}
}