{
  "type": "Feature",
  "properties": {
    "iso:country":"US",
    "sg:address":"708 Main St",
    "sg:city":"Springfield",
    "sg:classifiers":[
        {
            "category":"Food & Beverages",
            "subcategory":"Liquor & Beverages",
            "type":"Retail Goods"
        }
    ],
    "sg:phone":"+1 719 523 6636",
    "sg:postcode":"81073",
    "sg:province":"CO",
    "wof:name":"City Liquor",
    "wof:placetype":"venue"
},
  "geometry": {"coordinates":[-102.61647000000001,37.407053],"type":"Point"}
}