{
  "type": "Feature",
  "properties": {
    "iso:country":"US",
    "sg:address":"1421 S Potomac St",
    "sg:city":"Aurora",
    "sg:classifiers":[
        {
            "category":"Health Services",
            "subcategory":"Doctor",
            "type":"Services"
        }
    ],
    "sg:phone":"+1 303 337 5575",
    "sg:postcode":"80012",
    "sg:province":"CO",
    "sg:tags":[
        "physician",
        "surgeon"
    ],
    "sg:website":"www.rmimpc.com",
    "wof:name":"Rocky Mountain Internal Mdcn",
    "wof:placetype":"venue"
},
  "geometry": {"coordinates":[-104.83161200000001,39.685383],"type":"Point"}
}