{
  "type": "Feature",
  "properties": {
    "addr:full":"6455 S Dallas Ct Englewood CO 80111",
    "addr:housenumber":"6455",
    "addr:postcode":"80111",
    "addr:street":"S Dallas Ct",
    "iso:country":"US",
    "sg:address":"6455 S Dallas Ct",
    "sg:city":"Englewood",
    "sg:classifiers":[
        {
            "category":"Professional",
            "subcategory":"Advertising",
            "type":"Services"
        }
    ],
    "sg:phone":"+1 720 489 5001",
    "sg:postcode":"80111",
    "sg:province":"CO",
    "sg:website":"www.proforma.com",
    "wof:name":"Proforma Imagery",
    "wof:placetype":"venue"
},
  "geometry": {"coordinates":[-104.877847,39.59883],"type":"Point"}
}