{
  "type": "Feature",
  "properties": {
    "iso:country":"US",
    "sg:address":"32186 Castle Ct Ste 230",
    "sg:city":"Evergreen",
    "sg:classifiers":[
        {
            "category":"Insurance",
            "subcategory":"Insurance Agent",
            "type":"Services"
        },
        {
            "category":"Insurance",
            "subcategory":"Hazard Insurance",
            "type":"Services"
        },
        {
            "category":"Insurance",
            "subcategory":"Title Insurance",
            "type":"Services"
        }
    ],
    "sg:phone":"+1 303 670 2779",
    "sg:postcode":"80439",
    "sg:province":"CO",
    "sg:tags":[
        "auto",
        "homeowner"
    ],
    "sg:website":"http://apps.amfam.com/agentlocator/DALVARAD?sourceid=yp3",
    "wof:name":"American Family Insurance- Don Alvarado",
    "wof:placetype":"venue"
},
  "geometry": {"coordinates":[-105.363934,39.681963],"type":"Point"}
}