{
  "type": "Feature",
  "properties": {
    "addr:full":"174 White Water Dr Durango CO 81301",
    "addr:housenumber":"174",
    "addr:postcode":"co 81301",
    "addr:street":"White Water Dr",
    "iso:country":"US",
    "sg:address":"174 White Water Dr",
    "sg:city":"Durango",
    "sg:classifiers":[
        {
            "category":"Education",
            "subcategory":"Special Training",
            "type":"Public Place"
        }
    ],
    "sg:phone":"+1 970 385 8581",
    "sg:postcode":"81301",
    "sg:province":"CO",
    "sg:tags":[
        "tutoring"
    ],
    "wof:name":"Second Chance Tutoring",
    "wof:placetype":"venue"
},
  "geometry": {"coordinates":[-107.809308,37.437504],"type":"Point"}
}