{
  "type": "Feature",
  "properties": {
    "addr:full":"5146 Youngfield Ct Arvada CO 80002",
    "addr:housenumber":"5146",
    "addr:postcode":"80002",
    "addr:street":"Youngfield Ct",
    "iso:country":"US",
    "sg:address":"5146 Youngfield Ct",
    "sg:city":"Arvada",
    "sg:classifiers":[
        {
            "category":"Manufacturing",
            "subcategory":"Signs",
            "type":"Manufacturing & Wholesale Goods"
        }
    ],
    "sg:phone":"+1 303 420 9876",
    "sg:postcode":"80002",
    "sg:province":"CO",
    "sg:tags":[
        "specialty",
        "mfg"
    ],
    "wof:name":"J A K Creations",
    "wof:placetype":"venue"
},
  "geometry": {"coordinates":[-105.143075,39.790354],"type":"Point"}
}