{
  "type": "Feature",
  "properties": {
    "iso:country":"US",
    "sg:address":"4141 E Dickenson Pl",
    "sg:city":"Denver",
    "sg:classifiers":[
        {
            "category":"Health Services",
            "subcategory":"Hospital",
            "type":"Services"
        },
        {
            "category":"Health Services",
            "subcategory":"Clinic",
            "type":"Services"
        }
    ],
    "sg:phone":"+1 303 757 7227",
    "sg:postcode":"80222",
    "sg:province":"CO",
    "sg:tags":[
        "mental",
        "out"
    ],
    "sg:website":"www.mhcd.com",
    "wof:name":"Mental Health Corp Denver",
    "wof:placetype":"venue"
},
  "geometry": {"coordinates":[-104.939797,39.671961],"type":"Point"}
}