{
  "type": "Feature",
  "properties": {
    "addr:full":"5325 Zuni Street Denver CO 80221",
    "addr:housenumber":"5325",
    "addr:postcode":"80221",
    "addr:street":"Zuni Street",
    "iso:country":"US",
    "sg:address":"5325 Zuni Street",
    "sg:city":"Denver",
    "sg:classifiers":[
        {
            "category":"Restaurant",
            "type":"Food & Drink"
        }
    ],
    "sg:phone":"+1 303 433 6690",
    "sg:postcode":"80221",
    "sg:province":"CO",
    "wof:name":"The Sandwich Board",
    "wof:placetype":"venue"
},
  "geometry": {"coordinates":[-105.015972,39.793011],"type":"Point"}
}