{
  "type": "Feature",
  "properties": {
    "iso:country":"US",
    "sg:address":"1 N Tejon St",
    "sg:city":"Colorado Springs",
    "sg:classifiers":[
        {
            "category":"Shopping",
            "subcategory":"Clothing, Apparel, & Fashions",
            "type":"Retail Goods"
        }
    ],
    "sg:phone":"+1 719 633 0492",
    "sg:postcode":"80903",
    "sg:province":"CO",
    "sg:tags":[
        "lingerie"
    ],
    "wof:name":"Lace and Silk Traditions",
    "wof:placetype":"venue"
},
  "geometry": {"coordinates":[-104.823493,38.833942],"type":"Point"}
}