{
  "type": "Feature",
  "properties": {
    "addr:full":"15435 Gleneagle Dr Colorado Springs CO 80921",
    "addr:housenumber":"15435",
    "addr:postcode":"80921",
    "addr:street":"Gleneagle Dr",
    "iso:country":"US",
    "sg:address":"15435 Gleneagle Dr",
    "sg:city":"Colorado Springs",
    "sg:classifiers":[
        {
            "category":"Professional",
            "subcategory":"Computer Services",
            "type":"Services"
        }
    ],
    "sg:phone":"+1 719 534 9990",
    "sg:postcode":"80921",
    "sg:province":"CO",
    "sg:tags":[
        "engineer"
    ],
    "wof:name":"General Dynamics Advanced Info",
    "wof:placetype":"venue"
},
  "geometry": {"coordinates":[-104.823984,39.056365],"type":"Point"}
}