{
  "type": "Feature",
  "properties": {
    "addr:full":"6363 W 120th Ave Broomfield CO 80020",
    "addr:housenumber":"6363",
    "addr:postcode":"80020",
    "addr:street":"W 120Th Ave",
    "iso:country":"US",
    "sg:address":"6363 W 120th Ave",
    "sg:city":"Broomfield",
    "sg:classifiers":[
        {
            "category":"Banks & Credit Unions",
            "subcategory":"Bank",
            "type":"Services"
        }
    ],
    "sg:phone":"+1 303 460 4660",
    "sg:postcode":"80020",
    "sg:province":"CO",
    "sg:website":"www.usbank.com",
    "wof:name":"US Bank",
    "wof:placetype":"venue"
},
  "geometry": {"coordinates":[-105.066974,39.914296],"type":"Point"}
}