{
  "type": "Feature",
  "properties": {
    "iso:country":"US",
    "sg:address":"6707 McMurray Ranch Rd",
    "sg:city":"Bellvue",
    "sg:classifiers":[
        {
            "category":"Retail",
            "subcategory":"Repair Shop",
            "type":"Services"
        }
    ],
    "sg:phone":"+1 970 472 9119",
    "sg:postcode":"80512",
    "sg:province":"CO",
    "sg:tags":[
        "lock",
        "locksmith"
    ],
    "wof:name":"Data Lock",
    "wof:placetype":"venue"
},
  "geometry": {"coordinates":[-105.21470600000001,40.679934],"type":"Point"}
}