{
  "type": "Feature",
  "properties": {
    "iso:country":"US",
    "sg:address":"1621 W Canal Cir",
    "sg:city":"Littleton",
    "sg:classifiers":[
        {
            "category":"Shopping",
            "subcategory":"Pets & Pet Supplies",
            "type":"Retail Goods"
        },
        {
            "category":"Retail",
            "subcategory":"Animal Services",
            "type":"Services"
        }
    ],
    "sg:phone":"+1 303 730 1001",
    "sg:postcode":"80120",
    "sg:province":"CO",
    "sg:tags":[
        "grooming",
        "dog",
        "cat"
    ],
    "wof:name":"Central Bark Pet Grooming",
    "wof:placetype":"venue"
},
  "geometry": {"coordinates":[-105.008507,39.572495],"type":"Point"}
}