{
  "type": "Feature",
  "properties": {
    "iso:country":"US",
    "sg:address":"6030 Topaz Vista Pl",
    "sg:city":"Castle Rock",
    "sg:classifiers":[
        {
            "category":"Building & Trades",
            "subcategory":"Construction",
            "type":"Services"
        }
    ],
    "sg:phone":"+1 303 791 8500",
    "sg:postcode":"80104",
    "sg:province":"CO",
    "sg:tags":[
        "home",
        "builder"
    ],
    "wof:name":"Road Dorian Homes Inc",
    "wof:placetype":"venue"
},
  "geometry": {"coordinates":[-104.91864200000001,39.488617],"type":"Point"}
}