{
  "type": "Feature",
  "properties": {
    "addr:full":"622 S Albert Ave Walsenburg CO 81089",
    "addr:housenumber":"622",
    "addr:postcode":"81089",
    "addr:street":"S Albert Ave",
    "iso:country":"US",
    "sg:address":"622 S Albert Ave",
    "sg:city":"Walsenburg",
    "sg:classifiers":[
        {
            "category":"Insurance",
            "subcategory":"Insurance Agent",
            "type":"Services"
        }
    ],
    "sg:phone":"+1 719 738 1612",
    "sg:postcode":"81089",
    "sg:province":"CO",
    "wof:name":"Farm Bureau Insurance",
    "wof:placetype":"venue"
},
  "geometry": {"coordinates":[-104.78229899999999,37.623024],"type":"Point"}
}