{
  "type": "Feature",
  "properties": {
    "addr:full":"1325 Main St Longmont CO 80501",
    "addr:housenumber":"1325",
    "addr:postcode":"80501",
    "addr:street":"Main St",
    "iso:country":"US",
    "sg:address":"1325 Main St",
    "sg:city":"Longmont",
    "sg:classifiers":[
        {
            "category":"Autos & Motor Vehicles",
            "subcategory":"Automobile Sales",
            "type":"Retail Goods"
        }
    ],
    "sg:phone":"+1 303 776 0876",
    "sg:postcode":"80501",
    "sg:province":"CO",
    "sg:tags":[
        "used"
    ],
    "wof:name":"Phoenix Auto Sales",
    "wof:placetype":"venue"
},
  "geometry": {"coordinates":[-105.10241600000001,40.184447],"type":"Point"}
}