{
  "type": "Feature",
  "properties": {
    "addr:full":"1120 S Monroe St Denver CO 80210",
    "addr:housenumber":"1120",
    "addr:postcode":"80210",
    "addr:street":"S Monroe St",
    "iso:country":"US",
    "sg:address":"1120 S Monroe St",
    "sg:city":"Denver",
    "sg:classifiers":[
        {
            "category":"Food & Beverages",
            "subcategory":"Candy",
            "type":"Retail Goods"
        }
    ],
    "sg:phone":"+1 303 758 4053",
    "sg:postcode":"80210",
    "sg:province":"CO",
    "wof:name":"Sugar & Spice",
    "wof:placetype":"venue"
},
  "geometry": {"coordinates":[-104.94529900000001,39.695131],"type":"Point"}
}