{
  "type": "Feature",
  "properties": {
    "addr:full":"1402 Miner St Idaho Springs CO 80452",
    "addr:housenumber":"1402",
    "addr:postcode":"80452",
    "addr:street":"Miner St",
    "iso:country":"US",
    "sg:address":"1402 Miner St",
    "sg:city":"Idaho Springs",
    "sg:classifiers":[
        {
            "category":"Organizations",
            "subcategory":"Non-profit Organization",
            "type":"Services"
        }
    ],
    "sg:phone":"+1 303 567 2382",
    "sg:postcode":"80452",
    "sg:province":"CO",
    "sg:tags":[
        "human"
    ],
    "wof:name":"Volunteers Of America",
    "wof:placetype":"venue"
},
  "geometry": {"coordinates":[-105.51700700000001,39.741954],"type":"Point"}
}