{
  "type": "Feature",
  "properties": {
    "iso:country":"US",
    "sg:address":"8020 Tally Ct",
    "sg:city":"Colorado Springs",
    "sg:classifiers":[
        {
            "category":"Building & Trades",
            "subcategory":"Construction",
            "type":"Services"
        }
    ],
    "sg:phone":"+1 719 533 0804",
    "sg:postcode":"80920",
    "sg:province":"CO",
    "sg:tags":[
        "contractor"
    ],
    "wof:name":"Final Stage",
    "wof:placetype":"venue"
},
  "geometry": {"coordinates":[-104.783788,38.949058],"type":"Point"}
}