{
  "type": "Feature",
  "properties": {
    "addr:full":"605 Brownell St Georgetown CO 80444",
    "addr:housenumber":"605",
    "addr:postcode":"80444",
    "addr:street":"Brownell St",
    "iso:country":"US",
    "sg:address":"605 Brownell St",
    "sg:city":"Georgetown",
    "sg:classifiers":[
        {
            "category":"Travel",
            "subcategory":"Hotels & Motels",
            "type":"Entertainment"
        }
    ],
    "sg:phone":"+1 303 569 3400",
    "sg:postcode":"80444",
    "sg:province":"CO",
    "sg:tags":[
        "breakfast",
        "accommodation",
        "bed"
    ],
    "wof:name":"Hardy House Bed & Breakfast",
    "wof:placetype":"venue"
},
  "geometry": {"coordinates":[-105.698486,39.707244],"type":"Point"}
}