{
  "type": "Feature",
  "properties": {
    "iso:country":"US",
    "sg:address":"300 2nd Ave",
    "sg:city":"Longmont",
    "sg:classifiers":[
        {
            "category":"Personal",
            "subcategory":"Beauty Salon",
            "type":"Services"
        }
    ],
    "sg:phone":"+1 303 652 2229",
    "sg:postcode":"80501",
    "sg:province":"CO",
    "wof:name":"2nd Avenue Hair Studio",
    "wof:placetype":"venue"
},
  "geometry": {"coordinates":[-105.099886,40.16194],"type":"Point"}
}