{
  "type": "Feature",
  "properties": {
    "iso:country":"US",
    "sg:address":"8043 S Carr Ct",
    "sg:city":"Littleton",
    "sg:classifiers":[
        {
            "category":"Professional",
            "subcategory":"Computer Services",
            "type":"Services"
        }
    ],
    "sg:phone":"+1 303 932 0219",
    "sg:postcode":"80128",
    "sg:province":"CO",
    "sg:tags":[
        "d",
        "related"
    ],
    "wof:name":"Doucette Inc",
    "wof:placetype":"venue"
},
  "geometry": {"coordinates":[-105.09254900000001,39.572402],"type":"Point"}
}