{
  "type": "Feature",
  "properties": {
    "addr:full":"2229 Blake St Denver CO 80205",
    "addr:housenumber":"2229",
    "addr:postcode":"80205",
    "addr:street":"Blake St",
    "iso:country":"US",
    "sg:address":"2229 Blake St",
    "sg:city":"Denver",
    "sg:classifiers":[
        {
            "category":"Bars & Pubs",
            "type":"Food & Drink"
        }
    ],
    "sg:phone":"+1 303 298 8008",
    "sg:postcode":"80205",
    "sg:province":"CO",
    "sg:tags":[
        "lounge",
        "drinking",
        "cocktail"
    ],
    "wof:name":"Baja Beach Club",
    "wof:placetype":"venue"
},
  "geometry": {"coordinates":[-104.99157700000001,39.756407],"type":"Point"}
}