{
  "type": "Feature",
  "properties": {
    "iso:country":"US",
    "sg:address":"721 Bunting Ave",
    "sg:city":"Fountain",
    "sg:classifiers":[
        {
            "category":"Building & Trades",
            "subcategory":"Construction",
            "type":"Services"
        }
    ],
    "sg:phone":"+1 719 382 5477",
    "sg:postcode":"80817",
    "sg:province":"CO",
    "sg:tags":[
        "house"
    ],
    "wof:name":"D & L Construction",
    "wof:placetype":"venue"
},
  "geometry": {"coordinates":[-104.70354500000001,38.688806],"type":"Point"}
}