{
  "type": "Feature",
  "properties": {
    "iso:country":"US",
    "sg:address":"6830 Eastmoor Dr",
    "sg:city":"Denver",
    "sg:classifiers":[
        {
            "category":"Banks & Credit Unions",
            "subcategory":"Investment Brokerage",
            "type":"Services"
        }
    ],
    "sg:phone":"+1 303 758 5787",
    "sg:postcode":"80237",
    "sg:province":"CO",
    "sg:tags":[
        "consultant",
        "planning",
        "financial"
    ],
    "wof:name":"American Express Financial Adv",
    "wof:placetype":"venue"
},
  "geometry": {"coordinates":[-104.908332,39.642853],"type":"Point"}
}