{
  "type": "Feature",
  "properties": {
    "addr:full":"2318 E Platte Ave Colorado Springs CO 80909",
    "addr:housenumber":"2318",
    "addr:postcode":"80909",
    "addr:street":"E Platte Ave",
    "iso:country":"US",
    "sg:address":"2318 E Platte Ave",
    "sg:city":"Colorado Springs",
    "sg:classifiers":[
        {
            "category":"Food & Beverages",
            "subcategory":"Liquor & Beverages",
            "type":"Retail Goods"
        }
    ],
    "sg:phone":"+1 719 520 1188",
    "sg:postcode":"80909",
    "sg:province":"CO",
    "wof:name":"Platte Liquor",
    "wof:placetype":"venue"
},
  "geometry": {"coordinates":[-104.78624000000001,38.83706],"type":"Point"}
}