{
  "type": "Feature",
  "properties": {
    "iso:country":"US",
    "sg:address":"9400 E Iliff Ave",
    "sg:city":"Denver",
    "sg:classifiers":[
        {
            "category":"Wholesale",
            "subcategory":"Durable Goods & Equipment",
            "type":"Manufacturing & Wholesale Goods"
        }
    ],
    "sg:phone":"+1 303 695 9012",
    "sg:postcode":"80231",
    "sg:province":"CO",
    "wof:name":"Tronchin Franco & Associates",
    "wof:placetype":"venue"
},
  "geometry": {"coordinates":[-104.87938699999999,39.674712],"type":"Point"}
}