{
  "type": "Feature",
  "properties": {
    "addr:full":"4525 Monica Dr Colorado Springs CO 80916",
    "addr:housenumber":"4525",
    "addr:postcode":"80916",
    "addr:street":"Monica Dr",
    "iso:country":"US",
    "sg:address":"4525 Monica Dr",
    "sg:city":"Colorado Springs",
    "sg:classifiers":[
        {
            "category":"Wholesale",
            "subcategory":"Hardware",
            "type":"Manufacturing & Wholesale Goods"
        }
    ],
    "sg:phone":"+1 719 391 0072",
    "sg:postcode":"80916",
    "sg:province":"CO",
    "sg:tags":[
        "prevention",
        "flow",
        "back",
        "devices"
    ],
    "wof:name":"Steve Eastburn Co",
    "wof:placetype":"venue"
},
  "geometry": {"coordinates":[-104.74418799999999,38.793761],"type":"Point"}
}