{
  "type": "Feature",
  "properties": {
    "addr:full":"1722 14th St Boulder CO 80304",
    "addr:housenumber":"1722",
    "addr:postcode":"80304",
    "addr:street":"14Th St",
    "iso:country":"US",
    "sg:address":"1722 14th St",
    "sg:city":"Boulder",
    "sg:classifiers":[
        {
            "category":"Building & Trades",
            "subcategory":"Construction",
            "type":"Services"
        }
    ],
    "sg:phone":"+1 303 413 0493",
    "sg:postcode":"80304",
    "sg:province":"CO",
    "sg:tags":[
        "residential",
        "general",
        "association",
        "business",
        "contractor"
    ],
    "wof:name":"Harrington Homes Inc",
    "wof:placetype":"venue"
},
  "geometry": {"coordinates":[-105.27637300000001,40.015487],"type":"Point"}
}