{
  "type": "Feature",
  "properties": {
    "iso:country":"US",
    "sg:address":"3967 E Garnet Way",
    "sg:city":"Littleton",
    "sg:classifiers":[
        {
            "category":"Professional",
            "subcategory":"Research",
            "type":"Services"
        }
    ],
    "sg:phone":"+1 303 683 9200",
    "sg:postcode":"80126",
    "sg:province":"CO",
    "sg:tags":[
        "market",
        "analysis"
    ],
    "wof:name":"Strategic Insights Inc",
    "wof:placetype":"venue"
},
  "geometry": {"coordinates":[-104.943949,39.551598],"type":"Point"}
}