{
  "type": "Feature",
  "properties": {
    "iso:country":"US",
    "sg:address":"127 Colorado Ave",
    "sg:city":"Stratton",
    "sg:classifiers":[
        {
            "category":"Social Services",
            "type":"Services"
        }
    ],
    "sg:phone":"+1 719 348 5324",
    "sg:postcode":"80836",
    "sg:province":"CO",
    "sg:tags":[
        "senior",
        "citizen"
    ],
    "wof:name":"Stratton Senior Ctr",
    "wof:placetype":"venue"
},
  "geometry": {"coordinates":[-102.60488700000001,39.305876],"type":"Point"}
}