{
  "type": "Feature",
  "properties": {
    "iso:country":"US",
    "sg:address":"7897 S Pierce Way",
    "sg:city":"Littleton",
    "sg:classifiers":[
        {
            "category":"Restaurant",
            "type":"Food & Drink"
        }
    ],
    "sg:phone":"+1 303 904 2625",
    "sg:postcode":"80128",
    "sg:province":"CO",
    "sg:tags":[
        "eating"
    ],
    "wof:name":"Los Toros LLC",
    "wof:placetype":"venue"
},
  "geometry": {"coordinates":[-105.073852,39.574372],"type":"Point"}
}