{
  "type": "Feature",
  "properties": {
    "addr:full":"1049 Timbercrest Dr Castle Rock CO 80108",
    "addr:housenumber":"1049",
    "addr:postcode":"80108",
    "addr:street":"Timbercrest Dr",
    "iso:country":"US",
    "sg:address":"1049 Timbercrest Dr",
    "sg:city":"Castle Rock",
    "sg:classifiers":[
        {
            "category":"Banks & Credit Unions",
            "subcategory":"Investment Brokerage",
            "type":"Services"
        }
    ],
    "sg:phone":"+1 303 663 2604",
    "sg:postcode":"80108",
    "sg:province":"CO",
    "sg:tags":[
        "advisory",
        "financial"
    ],
    "wof:name":"Fisher Investments Inc",
    "wof:placetype":"venue"
},
  "geometry": {"coordinates":[-104.905091,39.467619],"type":"Point"}
}