{
  "type": "Feature",
  "properties": {
    "addr:full":"5815 W 52nd Ave Denver CO 80212",
    "addr:housenumber":"5815",
    "addr:postcode":"80212",
    "addr:street":"W 52Nd Ave",
    "iso:country":"US",
    "sg:address":"5815 W 52nd Ave",
    "sg:city":"Denver",
    "sg:classifiers":[
        {
            "category":"Manufacturing",
            "subcategory":"Retail Goods",
            "type":"Manufacturing & Wholesale Goods"
        }
    ],
    "sg:phone":"+1 303 431 9266",
    "sg:postcode":"80212",
    "sg:province":"CO",
    "sg:tags":[
        "slot",
        "machine",
        "mfg"
    ],
    "wof:name":"Royal Bell LTD",
    "wof:placetype":"venue"
},
  "geometry": {"coordinates":[-105.06131499999999,39.791148],"type":"Point"}
}