{
  "type": "Feature",
  "properties": {
    "addr:full":"6613 Marshall St Arvada CO 80003",
    "addr:housenumber":"6613",
    "addr:postcode":"80003",
    "addr:street":"Marshall St",
    "iso:country":"US",
    "sg:address":"6613 Marshall St",
    "sg:city":"Arvada",
    "sg:classifiers":[
        {
            "category":"Home & Garden",
            "subcategory":"Carpets & Floor Coverings",
            "type":"Retail Goods"
        }
    ],
    "sg:phone":"+1 303 423 9856",
    "sg:postcode":"80003",
    "sg:province":"CO",
    "wof:name":"Jr Carpet Installatn",
    "wof:placetype":"venue"
},
  "geometry": {"coordinates":[-105.068348,39.81805],"type":"Point"}
}