{
  "type": "Feature",
  "properties": {
    "iso:country":"US",
    "sg:address":"1352 Marys Lake Rd",
    "sg:city":"Estes Park",
    "sg:classifiers":[
        {
            "category":"Professional",
            "type":"Services"
        }
    ],
    "sg:phone":"+1 970 586 8767",
    "sg:postcode":"80517",
    "sg:province":"CO",
    "sg:tags":[
        "establishment"
    ],
    "wof:name":"Special Transit",
    "wof:placetype":"venue"
},
  "geometry": {"coordinates":[-105.541066,40.35893],"type":"Point"}
}