{
  "type": "Feature",
  "properties": {
    "iso:country":"US",
    "sg:address":"12651 Polo Pl",
    "sg:city":"Broomfield",
    "sg:classifiers":[
        {
            "category":"Shopping",
            "subcategory":"Bicycles & Sporting Goods",
            "type":"Retail Goods"
        }
    ],
    "sg:phone":"+1 303 466 2866",
    "sg:postcode":"80020",
    "sg:province":"CO",
    "wof:name":"My Racquet",
    "wof:placetype":"venue"
},
  "geometry": {"coordinates":[-105.05799,39.960034],"type":"Point"}
}