{
  "type": "Feature",
  "properties": {
    "iso:country":"US",
    "sg:address":"6535 York St",
    "sg:city":"Denver",
    "sg:classifiers":[
        {
            "category":"Retail",
            "subcategory":"Auto Repair",
            "type":"Services"
        }
    ],
    "sg:phone":"+1 303 288 8097",
    "sg:postcode":"80229",
    "sg:province":"CO",
    "sg:tags":[
        "automobile",
        "lubrication"
    ],
    "wof:name":"Action Port-A-Lube",
    "wof:placetype":"venue"
},
  "geometry": {"coordinates":[-104.959295,39.814457],"type":"Point"}
}