{
  "type": "Feature",
  "properties": {
    "addr:full":"14100 E Arapahoe Rd Centennial CO 80112",
    "addr:housenumber":"14100",
    "addr:postcode":"80112",
    "addr:street":"E Arapahoe Rd",
    "iso:country":"US",
    "sg:address":"14100 E Arapahoe Rd",
    "sg:city":"Centennial",
    "sg:classifiers":[
        {
            "category":"Shopping",
            "type":"Retail Goods"
        }
    ],
    "sg:phone":"+1 720 870 4620",
    "sg:postcode":"80112",
    "sg:province":"CO",
    "sg:tags":[
        "hearing",
        "equipment",
        "supply",
        "impaired"
    ],
    "wof:name":"Adult & Pediatric Hearing Ctr",
    "wof:placetype":"venue"
},
  "geometry": {"coordinates":[-104.824499,39.595002],"type":"Point"}
}