{
  "type": "Feature",
  "properties": {
    "iso:country":"US",
    "sg:address":"593 Chekwa Trl",
    "sg:city":"Gunnison",
    "sg:classifiers":[
        {
            "category":"Building & Trades",
            "subcategory":"Construction",
            "type":"Services"
        }
    ],
    "sg:phone":"+1 970 641 2803",
    "sg:postcode":"81230",
    "sg:province":"CO",
    "sg:tags":[
        "contractor"
    ],
    "wof:name":"C & E West Inc",
    "wof:placetype":"venue"
},
  "geometry": {"coordinates":[-106.934099,38.597448],"type":"Point"}
}