{
  "type": "Feature",
  "properties": {
    "iso:country":"US",
    "sg:address":"3080 Valmont Rd",
    "sg:city":"Boulder",
    "sg:classifiers":[
        {
            "category":"Professional",
            "subcategory":"Lawyer & Legal Services",
            "type":"Services"
        },
        {
            "category":"Personal",
            "type":"Services"
        }
    ],
    "sg:phone":"+1 303 443 1977",
    "sg:postcode":"80301",
    "sg:province":"CO",
    "sg:tags":[
        "attorney",
        "referral"
    ],
    "sg:website":"www.groupbiz.com",
    "wof:name":"Lawyer's Assurance Group",
    "wof:placetype":"venue"
},
  "geometry": {"coordinates":[-105.252578,40.029121],"type":"Point"}
}