{
  "type": "Feature",
  "properties": {
    "iso:country":"US",
    "sg:address":"1414 Hawk Pkwy",
    "sg:city":"Montrose",
    "sg:classifiers":[
        {
            "category":"Insurance",
            "subcategory":"Insurance Agent",
            "type":"Services"
        }
    ],
    "sg:phone":"+1 970 252 8960",
    "sg:postcode":"81401",
    "sg:province":"CO",
    "wof:name":"Mark Neill Insurance Svc",
    "wof:placetype":"venue"
},
  "geometry": {"coordinates":[-107.86753,38.449482],"type":"Point"}
}