{
  "type": "Feature",
  "properties": {
    "addr:full":"3320 Inspiration Dr Colorado Springs CO 80917",
    "addr:housenumber":"3320",
    "addr:postcode":"80917",
    "addr:street":"Inspiration Dr",
    "iso:country":"US",
    "sg:address":"3320 Inspiration Dr",
    "sg:city":"Colorado Springs",
    "sg:classifiers":[
        {
            "category":"Professional",
            "type":"Services"
        }
    ],
    "sg:phone":"+1 719 596 5972",
    "sg:postcode":"80917",
    "sg:province":"CO",
    "wof:name":"Milan M Markley",
    "wof:placetype":"venue"
},
  "geometry": {"coordinates":[-104.731998,38.879878],"type":"Point"}
}