{
  "type": "Feature",
  "properties": {
    "iso:country":"US",
    "sg:address":"8005 S Chester St",
    "sg:city":"Englewood",
    "sg:classifiers":[
        {
            "category":"Professional",
            "subcategory":"Management & Consulting",
            "type":"Services"
        }
    ],
    "sg:phone":"+1 303 858 0300",
    "sg:postcode":"80112",
    "sg:province":"CO",
    "sg:tags":[
        "consultant",
        "health"
    ],
    "wof:name":"Precyse Solutions LLC",
    "wof:placetype":"venue"
},
  "geometry": {"coordinates":[-104.878877,39.570297],"type":"Point"}
}