{
  "type": "Feature",
  "properties": {
    "addr:full":"626 S College Ave Fort Collins CO 80524",
    "addr:housenumber":"626",
    "addr:postcode":"80524",
    "addr:street":"S College Ave",
    "iso:country":"US",
    "sg:address":"626 S College Ave",
    "sg:city":"Fort Collins",
    "sg:classifiers":[
        {
            "category":"Restaurant",
            "type":"Food & Drink"
        }
    ],
    "sg:phone":"+1 970 416 0265",
    "sg:postcode":"80524",
    "sg:province":"CO",
    "sg:tags":[
        "mexican"
    ],
    "sg:website":"www.lostarascos.com",
    "wof:name":"Los Tarascos",
    "wof:placetype":"venue"
},
  "geometry": {"coordinates":[-105.07700699999999,40.578626],"type":"Point"}
}