{
  "type": "Feature",
  "properties": {
    "iso:country":"US",
    "sg:address":"421 Main St",
    "sg:city":"Wray",
    "sg:classifiers":[
        {
            "category":"Food & Beverages",
            "subcategory":"Specialty",
            "type":"Retail Goods"
        }
    ],
    "sg:phone":"+1 970 332 4064",
    "sg:postcode":"80758",
    "sg:province":"CO",
    "wof:name":"Strawberry Patch",
    "wof:placetype":"venue"
},
  "geometry": {"coordinates":[-102.222162,40.077744],"type":"Point"}
}