{
  "type": "Feature",
  "properties": {
    "iso:country":"US",
    "sg:address":"253 42nd St SW",
    "sg:city":"Loveland",
    "sg:classifiers":[
        {
            "category":"Food & Beverages",
            "subcategory":"Fruits & Vegetables",
            "type":"Retail Goods"
        }
    ],
    "sg:phone":"+1 970 635 2416",
    "sg:postcode":"80537",
    "sg:province":"CO",
    "sg:tags":[
        "produce"
    ],
    "wof:name":"Redrocks Produce & Brokerage",
    "wof:placetype":"venue"
},
  "geometry": {"coordinates":[-105.080522,40.349465],"type":"Point"}
}