{
  "type": "Feature",
  "properties": {
    "addr:full":"963 E Colorado Ave Colorado Springs CO 80903",
    "addr:housenumber":"963",
    "addr:postcode":"80903",
    "addr:street":"E Colorado Ave",
    "iso:country":"US",
    "sg:address":"963 E Colorado Ave",
    "sg:city":"Colorado Springs",
    "sg:classifiers":[
        {
            "category":"Health Services",
            "subcategory":"Doctor",
            "type":"Services"
        }
    ],
    "sg:phone":"+1 719 578 1119",
    "sg:postcode":"80903",
    "sg:province":"CO",
    "sg:tags":[
        "physician",
        "surgeon"
    ],
    "wof:name":"Kenneth R Gamblin PC",
    "wof:placetype":"venue"
},
  "geometry": {"coordinates":[-104.807565,38.831919],"type":"Point"}
}