{
  "type": "Feature",
  "properties": {
    "iso:country":"US",
    "sg:address":"400 S Cam del Rio",
    "sg:city":"Durango",
    "sg:classifiers":[
        {
            "category":"Health Services",
            "subcategory":"Doctor",
            "type":"Services"
        }
    ],
    "sg:phone":"+1 970 247 2214",
    "sg:postcode":"81301",
    "sg:province":"CO",
    "sg:tags":[
        "clinic"
    ],
    "wof:name":"Health Net Federal Svc",
    "wof:placetype":"venue"
},
  "geometry": {"coordinates":[-107.875066,37.249294],"type":"Point"}
}