{
  "type": "Feature",
  "properties": {
    "iso:country":"US",
    "sg:address":"302 Pearl St",
    "sg:city":"Boulder",
    "sg:classifiers":[
        {
            "category":"Travel",
            "subcategory":"Campground",
            "type":"Entertainment"
        }
    ],
    "sg:phone":"+1 303 786 9216",
    "sg:postcode":"80302",
    "sg:province":"CO",
    "sg:tags":[
        "camp"
    ],
    "wof:name":"Renaissance Adventures",
    "wof:placetype":"venue"
},
  "geometry": {"coordinates":[-105.290446,40.015685],"type":"Point"}
}