{
  "type": "Feature",
  "properties": {
    "addr:full":"5555 N Fork Ct Boulder CO 80301",
    "addr:housenumber":"5555",
    "addr:postcode":"80301",
    "addr:street":"N Fork Ct",
    "iso:country":"US",
    "sg:address":"5555 N Fork Ct",
    "sg:city":"Boulder",
    "sg:classifiers":[
        {
            "category":"Organizations",
            "subcategory":"Membership Organization",
            "type":"Services"
        }
    ],
    "sg:phone":"+1 303 581 0213",
    "sg:postcode":"80301",
    "sg:province":"CO",
    "wof:name":"Friends of Air Life",
    "wof:placetype":"venue"
},
  "geometry": {"coordinates":[-105.198182,40.075215],"type":"Point"}
}