{
  "type": "Feature",
  "properties": {
    "addr:full":"3483 S Broadway Englewood CO 80113",
    "addr:housenumber":"3483",
    "addr:postcode":"80113",
    "addr:street":"S Broadway",
    "iso:country":"US",
    "sg:address":"3483 S Broadway",
    "sg:city":"Englewood",
    "sg:classifiers":[
        {
            "category":"Manufacturing",
            "subcategory":"Glass & Minerals",
            "type":"Manufacturing & Wholesale Goods"
        }
    ],
    "sg:phone":"+1 303 781 0026",
    "sg:postcode":"80113",
    "sg:province":"CO",
    "sg:tags":[
        "product",
        "mfg"
    ],
    "sg:website":"www.glasswarehouse.com",
    "wof:name":"Glass Warehouse",
    "wof:placetype":"venue"
},
  "geometry": {"coordinates":[-104.987684,39.654703],"type":"Point"}
}