{
  "type": "Feature",
  "properties": {
    "addr:full":"6196 S Ammons Way Littleton CO 80123",
    "addr:housenumber":"6196",
    "addr:postcode":"80123",
    "addr:street":"S Ammons Way",
    "iso:country":"US",
    "sg:address":"6196 S Ammons Way",
    "sg:city":"Littleton",
    "sg:classifiers":[
        {
            "category":"Shopping",
            "subcategory":"Department Store",
            "type":"Retail Goods"
        },
        {
            "category":"Health Services",
            "subcategory":"Clinic",
            "type":"Services"
        },
        {
            "category":"Health Services",
            "subcategory":"Hospital",
            "type":"Services"
        }
    ],
    "sg:phone":"+1 303 932 6911",
    "sg:postcode":"80123",
    "sg:province":"CO",
    "sg:tags":[
        "equipment",
        "ultrasonic",
        "osteopathic",
        "supply"
    ],
    "sg:website":"http://www.swedishhospital.com/conditions_we_treat/emergency_services/southwest_er.htm",
    "wof:name":"Southwest Emergency Department",
    "wof:placetype":"venue"
},
  "geometry": {"coordinates":[-105.088179,39.604356],"type":"Point"}
}