{
  "type": "Feature",
  "properties": {
    "iso:country":"US",
    "sg:address":"1636 E Evans Ave",
    "sg:city":"Denver",
    "sg:classifiers":[
        {
            "category":"Personal",
            "subcategory":"Barber",
            "type":"Services"
        }
    ],
    "sg:phone":"+1 303 282 4605",
    "sg:postcode":"80210",
    "sg:province":"CO",
    "sg:website":"www.bulllocks.com",
    "wof:name":"Bull Locks Barber",
    "wof:placetype":"venue"
},
  "geometry": {"coordinates":[-104.967853,39.678484],"type":"Point"}
}