{
  "type": "Feature",
  "properties": {
    "iso:country":"US",
    "sg:address":"32558 Co Rd 32",
    "sg:city":"Mc Clave",
    "sg:phone":"+1 719 829 4595",
    "sg:postcode":"81057",
    "sg:province":"CO",
    "sg:tags":[
        "farm",
        "wheat",
        "grain",
        "cash"
    ],
    "wof:name":"Esther Root",
    "wof:placetype":"venue"
},
  "geometry": {"coordinates":[-102.815179,38.104067],"type":"Point"}
}