{
  "type": "Feature",
  "properties": {
    "addr:full":"450 Federal Blvd Denver CO 80204",
    "addr:housenumber":"450",
    "addr:postcode":"80204",
    "addr:street":"Federal Blvd",
    "iso:country":"US",
    "sg:address":"450 Federal Blvd",
    "sg:city":"Denver",
    "sg:classifiers":[
        {
            "category":"Utilities",
            "subcategory":"Mobile Phone",
            "type":"Services"
        }
    ],
    "sg:phone":"+1 303 820 2210",
    "sg:postcode":"80204",
    "sg:province":"CO",
    "sg:tags":[
        "communication",
        "radiotelephone"
    ],
    "wof:name":"Omid Enterprises Inc",
    "wof:placetype":"venue"
},
  "geometry": {"coordinates":[-105.025127,39.723492],"type":"Point"}
}