{
  "type": "Feature",
  "properties": {
    "iso:country":"US",
    "sg:address":"5401 N Peterson Rd",
    "sg:city":"Sedalia",
    "sg:classifiers":[
        {
            "category":"Building & Trades",
            "subcategory":"Construction",
            "type":"Services"
        }
    ],
    "sg:phone":"+1 303 688 0808",
    "sg:postcode":"80135",
    "sg:province":"CO",
    "sg:tags":[
        "pipe",
        "line",
        "contractor"
    ],
    "wof:name":"Proto Construction & Paving",
    "wof:placetype":"venue"
},
  "geometry": {"coordinates":[-104.969863,39.439764],"type":"Point"}
}