{
  "type": "Feature",
  "properties": {
    "iso:country":"US",
    "sg:address":"8620 Wolff Ct",
    "sg:city":"Westminster",
    "sg:classifiers":[
        {
            "category":"Professional",
            "subcategory":"Management & Consulting",
            "type":"Services"
        }
    ],
    "sg:phone":"+1 303 465 1800",
    "sg:postcode":"80031",
    "sg:province":"CO",
    "sg:tags":[
        "consultant",
        "training"
    ],
    "wof:name":"Knowledgetek",
    "wof:placetype":"venue"
},
  "geometry": {"coordinates":[-105.049601,39.854017],"type":"Point"}
}