{
  "type": "Feature",
  "properties": {
    "iso:country":"US",
    "sg:address":"4995 S Malaya Ct",
    "sg:city":"Aurora",
    "sg:classifiers":[
        {
            "category":"Shopping",
            "subcategory":"Hobbies, Toys, & Games",
            "type":"Retail Goods"
        }
    ],
    "sg:phone":"+1 303 693 5787",
    "sg:postcode":"80015",
    "sg:province":"CO",
    "wof:name":"Lasting Memories",
    "wof:placetype":"venue"
},
  "geometry": {"coordinates":[-104.745869,39.625111],"type":"Point"}
}