{
  "type": "Feature",
  "properties": {
    "iso:country":"US",
    "sg:address":"7376 McLaughlin Rd",
    "sg:city":"Peyton",
    "sg:classifiers":[
        {
            "category":"Wholesale",
            "subcategory":"Construction Materials",
            "type":"Manufacturing & Wholesale Goods"
        }
    ],
    "sg:phone":"+1 719 495 0696",
    "sg:postcode":"80831",
    "sg:province":"CO",
    "sg:tags":[
        "residential"
    ],
    "wof:name":"Hammers Construction",
    "wof:placetype":"venue"
},
  "geometry": {"coordinates":[-104.604483,38.940227],"type":"Point"}
}