{
  "type": "Feature",
  "properties": {
    "addr:full":"5534 Crestone Cir Boulder CO 80301",
    "addr:housenumber":"5534",
    "addr:postcode":"80301",
    "addr:street":"Crestone Cir",
    "iso:country":"US",
    "sg:address":"5534 Crestone Cir",
    "sg:city":"Boulder",
    "sg:classifiers":[
        {
            "category":"Manufacturing",
            "subcategory":"Toys & Sporting Goods",
            "type":"Manufacturing & Wholesale Goods"
        }
    ],
    "sg:phone":"+1 303 652 3009",
    "sg:postcode":"80301",
    "sg:province":"CO",
    "sg:tags":[
        "mfg"
    ],
    "wof:name":"Morgul Bismark Cycle",
    "wof:placetype":"venue"
},
  "geometry": {"coordinates":[-105.1908,40.074435],"type":"Point"}
}