{
  "type": "Feature",
  "properties": {
    "addr:full":"400 State Hwy 91 Leadville CO 80461",
    "addr:housenumber":"400",
    "addr:postcode":"hwy 91;80461",
    "addr:street":"State",
    "iso:country":"US",
    "sg:address":"400 State Hwy 91",
    "sg:city":"Leadville",
    "sg:classifiers":[
        {
            "category":"Government",
            "subcategory":"Office",
            "type":"Public Place"
        }
    ],
    "sg:phone":"+1 719 486 2035",
    "sg:postcode":"80461",
    "sg:province":"CO",
    "wof:name":"Leadville Water Treat Plant",
    "wof:placetype":"venue"
},
  "geometry": {"coordinates":[-106.289525,39.269847],"type":"Point"}
}