{
  "type": "Feature",
  "properties": {
    "addr:full":"408 E Fillmore St Colorado Springs CO 80907",
    "addr:housenumber":"408",
    "addr:postcode":"80907",
    "addr:street":"E Fillmore St",
    "iso:country":"US",
    "sg:address":"408 E Fillmore St",
    "sg:city":"Colorado Springs",
    "sg:classifiers":[
        {
            "category":"Professional",
            "subcategory":"Employment Agencies",
            "type":"Services"
        }
    ],
    "sg:phone":"+1 719 471 7373",
    "sg:postcode":"80907",
    "sg:province":"CO",
    "sg:tags":[
        "opportunity"
    ],
    "sg:website":"www.laborready.com",
    "wof:name":"Labor Ready Inc",
    "wof:placetype":"venue"
},
  "geometry": {"coordinates":[-104.812552,38.874171],"type":"Point"}
}