{
  "type": "Feature",
  "properties": {
    "iso:country":"US",
    "sg:address":"3773 Cherry Creek N Dr Ste 575",
    "sg:city":"Denver",
    "sg:classifiers":[
        {
            "category":"Communications",
            "type":"Services"
        }
    ],
    "sg:phone":"+1 303 690 1040",
    "sg:postcode":"80209",
    "sg:province":"CO",
    "sg:tags":[
        "web",
        "design"
    ],
    "sg:website":"www.achievewebdesign.com",
    "wof:name":"Achieve Web Design, Inc.",
    "wof:placetype":"venue"
},
  "geometry": {"coordinates":[-104.942543,39.708824],"type":"Point"}
}