{
  "type": "Feature",
  "properties": {
    "iso:country":"US",
    "sg:address":"165 Fontaine Blvd",
    "sg:city":"Colorado Springs",
    "sg:classifiers":[
        {
            "category":"Freight",
            "type":"Transportation"
        }
    ],
    "sg:phone":"+1 719 390 3579",
    "sg:postcode":"80911",
    "sg:province":"CO",
    "sg:tags":[
        "record",
        "management"
    ],
    "wof:name":"Iron Mountain Information MGT",
    "wof:placetype":"venue"
},
  "geometry": {"coordinates":[-104.72210699999999,38.737194],"type":"Point"}
}