{
  "type": "Feature",
  "properties": {
    "iso:country":"US",
    "sg:address":"1490 Tuskegee Pl",
    "sg:city":"Colorado Springs",
    "sg:classifiers":[
        {
            "category":"Manufacturing",
            "subcategory":"Furniture",
            "type":"Manufacturing & Wholesale Goods"
        }
    ],
    "sg:phone":"+1 719 570 7353",
    "sg:postcode":"80915",
    "sg:province":"CO",
    "sg:tags":[
        "product",
        "mfg"
    ],
    "wof:name":"Concepts In Millwork Inc",
    "wof:placetype":"venue"
},
  "geometry": {"coordinates":[-104.71445900000001,38.854761],"type":"Point"}
}