{
  "type": "Feature",
  "properties": {
    "iso:country":"US",
    "sg:address":"1735 York St",
    "sg:city":"Denver",
    "sg:classifiers":[
        {
            "category":"Health Services",
            "subcategory":"Clinic",
            "type":"Services"
        }
    ],
    "sg:phone":"+1 303 246 3219",
    "sg:postcode":"80206",
    "sg:province":"CO",
    "sg:tags":[
        "counseling",
        "mental"
    ],
    "wof:name":"Insight Counseling",
    "wof:placetype":"venue"
},
  "geometry": {"coordinates":[-104.960118,39.743915],"type":"Point"}
}