{
  "type": "Feature",
  "properties": {
    "addr:full":"7114 W Jefferson Ave Lakewood CO 80235",
    "addr:housenumber":"7114",
    "addr:postcode":"80235",
    "addr:street":"W Jefferson Ave",
    "iso:country":"US",
    "sg:address":"7114 W Jefferson Ave",
    "sg:city":"Lakewood",
    "sg:classifiers":[
        {
            "category":"Professional",
            "type":"Services"
        }
    ],
    "sg:phone":"+1 303 531 2099",
    "sg:postcode":"80235",
    "sg:province":"CO",
    "sg:tags":[
        "establishment"
    ],
    "wof:name":"Stratecast Partners-Div Frost",
    "wof:placetype":"venue"
},
  "geometry": {"coordinates":[-105.079031,39.649846],"type":"Point"}
}