{
  "type": "Feature",
  "properties": {
    "addr:full":"1420 W Canal Ct Littleton CO 80120",
    "addr:housenumber":"1420",
    "addr:postcode":"80120",
    "addr:street":"W Canal Ct",
    "iso:country":"US",
    "sg:address":"1420 W Canal Ct",
    "sg:city":"Littleton",
    "sg:classifiers":[
        {
            "category":"Health Services",
            "subcategory":"Doctor",
            "type":"Services"
        }
    ],
    "sg:phone":"+1 303 795 2030",
    "sg:postcode":"80120",
    "sg:province":"CO",
    "sg:tags":[
        "physician",
        "surgeon"
    ],
    "wof:name":"Apex Dermatology Group",
    "wof:placetype":"venue"
},
  "geometry": {"coordinates":[-105.002325,39.567439],"type":"Point"}
}