{
  "type": "Feature",
  "properties": {
    "addr:full":"1607 S Stuart St Denver CO 80219",
    "addr:housenumber":"1607",
    "addr:postcode":"80219",
    "addr:street":"S Stuart St",
    "iso:country":"US",
    "sg:address":"1607 S Stuart St",
    "sg:city":"Denver",
    "sg:classifiers":[
        {
            "category":"Professional",
            "type":"Services"
        }
    ],
    "sg:phone":"+1 303 922 2890",
    "sg:postcode":"80219",
    "sg:province":"CO",
    "wof:name":"Rivers of Care",
    "wof:placetype":"venue"
},
  "geometry": {"coordinates":[-105.04329199999999,39.685603],"type":"Point"}
}