{
  "type": "Feature",
  "properties": {
    "iso:country":"US",
    "sg:address":"1301 Grand Ave",
    "sg:city":"Glenwood Springs",
    "sg:classifiers":[
        {
            "category":"Wholesale",
            "subcategory":"Apparel",
            "type":"Manufacturing & Wholesale Goods"
        },
        {
            "category":"Manufacturing",
            "subcategory":"Apparel",
            "type":"Manufacturing & Wholesale Goods"
        }
    ],
    "sg:phone":"+1 970 945 7098",
    "sg:postcode":"81601",
    "sg:province":"CO",
    "sg:tags":[
        "woman",
        "mfg"
    ],
    "wof:name":"Structured Chaos Inc",
    "wof:placetype":"venue"
},
  "geometry": {"coordinates":[-107.32498,39.540448],"type":"Point"}
}