{
  "type": "Feature",
  "properties": {
    "iso:country":"US",
    "sg:address":"3741 E 64th Ave",
    "sg:city":"Commerce City",
    "sg:classifiers":[
        {
            "category":"Wholesale",
            "subcategory":"Machinery & Supplies",
            "type":"Manufacturing & Wholesale Goods"
        }
    ],
    "sg:phone":"+1 303 288 1638",
    "sg:postcode":"80022",
    "sg:province":"CO",
    "sg:tags":[
        "tank"
    ],
    "wof:name":"Baker Tanks",
    "wof:placetype":"venue"
},
  "geometry": {"coordinates":[-104.948256,39.812777],"type":"Point"}
}