{
  "type": "Feature",
  "properties": {
    "addr:full":"125 N 8th St Grand Junction CO 81501",
    "addr:housenumber":"125",
    "addr:postcode":"81501",
    "addr:street":"N 8Th St",
    "iso:country":"US",
    "sg:address":"125 N 8th St",
    "sg:city":"Grand Junction",
    "sg:classifiers":[
        {
            "category":"Restaurant",
            "type":"Food & Drink"
        }
    ],
    "sg:phone":"+1 970 242 5198",
    "sg:postcode":"81501",
    "sg:province":"CO",
    "wof:name":"Quiznos Sub",
    "wof:placetype":"venue"
},
  "geometry": {"coordinates":[-108.559448,39.068065],"type":"Point"}
}