{
  "type": "Feature",
  "properties": {
    "addr:full":"3550 N Academy Blvd Colorado Springs CO 80917",
    "addr:housenumber":"3550",
    "addr:postcode":"80917",
    "addr:street":"N Academy Blvd",
    "iso:country":"US",
    "sg:address":"3550 N Academy Blvd",
    "sg:city":"Colorado Springs",
    "sg:classifiers":[
        {
            "category":"Professional",
            "subcategory":"Accounting & Tax Preparation",
            "type":"Services"
        }
    ],
    "sg:phone":"+1 719 638 3555",
    "sg:postcode":"80917",
    "sg:province":"CO",
    "sg:tags":[
        "accountant"
    ],
    "wof:name":"S J Campbell & Assoc",
    "wof:placetype":"venue"
},
  "geometry": {"coordinates":[-104.757142,38.881833],"type":"Point"}
}