{
  "type": "Feature",
  "properties": {
    "addr:full":"468 Greenwood Ln Longmont CO 80501",
    "addr:housenumber":"468",
    "addr:postcode":"80501",
    "addr:street":"Greenwood Ln",
    "iso:country":"US",
    "sg:address":"468 Greenwood Ln",
    "sg:city":"Longmont",
    "sg:classifiers":[
        {
            "category":"Manufacturing",
            "subcategory":"Glass & Minerals",
            "type":"Manufacturing & Wholesale Goods"
        }
    ],
    "sg:phone":"+1 303 776 9821",
    "sg:postcode":"80501",
    "sg:province":"CO",
    "sg:tags":[
        "concrete",
        "product",
        "mfg"
    ],
    "wof:name":"Erie Precast Concrete",
    "wof:placetype":"venue"
},
  "geometry": {"coordinates":[-105.069643,40.165596],"type":"Point"}
}