{
  "type": "Feature",
  "properties": {
    "iso:country":"US",
    "sg:address":"609 Castle Rd",
    "sg:city":"Colorado Springs",
    "sg:classifiers":[
        {
            "category":"Retail",
            "subcategory":"Laundry & Dry Cleaning",
            "type":"Services"
        }
    ],
    "sg:phone":"+1 719 473 3656",
    "sg:postcode":"80904",
    "sg:province":"CO",
    "wof:name":"Chavez Cleaning Co",
    "wof:placetype":"venue"
},
  "geometry": {"coordinates":[-104.86353099999999,38.857182],"type":"Point"}
}