{
  "type": "Feature",
  "properties": {
    "addr:full":"20825 J D Johnson Rd Peyton CO 80831",
    "addr:housenumber":"20825",
    "addr:postcode":"80831",
    "addr:street":"J D Johnson Rd",
    "iso:country":"US",
    "sg:address":"20825 J D Johnson Rd",
    "sg:city":"Peyton",
    "sg:classifiers":[
        {
            "category":"Building & Trades",
            "subcategory":"Construction",
            "type":"Services"
        }
    ],
    "sg:phone":"+1 719 683 2157",
    "sg:postcode":"80831",
    "sg:province":"CO",
    "sg:tags":[
        "house",
        "electrical",
        "contractor"
    ],
    "wof:name":"Falcon Builders Inc",
    "wof:placetype":"venue"
},
  "geometry": {"coordinates":[-104.442696,38.881677],"type":"Point"}
}