{
  "type": "Feature",
  "properties": {
    "addr:full":"3701 S Logan St Englewood CO 80113",
    "addr:housenumber":"3701",
    "addr:postcode":"80113",
    "addr:street":"S Logan St",
    "iso:country":"US",
    "sg:address":"3701 S Logan St",
    "sg:city":"Englewood",
    "sg:classifiers":[
        {
            "category":"Organizations",
            "subcategory":"Religious Organization",
            "type":"Services"
        }
    ],
    "sg:phone":"+1 303 789 3913",
    "sg:postcode":"80113",
    "sg:province":"CO",
    "sg:tags":[
        "church"
    ],
    "wof:name":"Englewood First Church",
    "wof:placetype":"venue"
},
  "geometry": {"coordinates":[-104.98297100000001,39.648964],"type":"Point"}
}