{
  "type": "Feature",
  "properties": {
    "addr:full":"3045 S Decatur St Apt 1 Denver CO 80236",
    "addr:housenumber":"3045;1",
    "addr:postcode":"80236",
    "addr:street":"S Decatur St Apt",
    "iso:country":"US",
    "sg:address":"3045 S Decatur St Apt 1",
    "sg:city":"Denver",
    "sg:classifiers":[
        {
            "category":"Building & Trades",
            "subcategory":"Landscaping Services",
            "type":"Services"
        }
    ],
    "sg:phone":"+1 303 789 1472",
    "sg:postcode":"80236",
    "sg:province":"CO",
    "sg:tags":[
        "gardener"
    ],
    "wof:name":"Nguyen Gardening",
    "wof:placetype":"venue"
},
  "geometry": {"coordinates":[-105.02281000000001,39.661388],"type":"Point"}
}