{
  "type": "Feature",
  "properties": {
    "iso:country":"US",
    "sg:address":"4104 Outlook Blvd",
    "sg:city":"Pueblo",
    "sg:classifiers":[
        {
            "category":"Utilities",
            "subcategory":"Telephone",
            "type":"Services"
        }
    ],
    "sg:phone":"+1 719 229 1733",
    "sg:postcode":"81008",
    "sg:province":"CO",
    "sg:tags":[
        "communications"
    ],
    "wof:name":"Sprint",
    "wof:placetype":"venue"
},
  "geometry": {"coordinates":[-104.626942,38.313805],"type":"Point"}
}