{
  "type": "Feature",
  "properties": {
    "addr:full":"13274 Lackland Dr Denver CO 80239",
    "addr:housenumber":"13274",
    "addr:postcode":"80239",
    "addr:street":"Lackland Dr",
    "iso:country":"US",
    "sg:address":"13274 Lackland Dr",
    "sg:city":"Denver",
    "sg:classifiers":[
        {
            "category":"Food & Beverages",
            "subcategory":"Candy",
            "type":"Retail Goods"
        }
    ],
    "sg:phone":"+1 303 375 8635",
    "sg:postcode":"80239",
    "sg:province":"CO",
    "wof:name":"Pauls Sno Cone & Candy",
    "wof:placetype":"venue"
},
  "geometry": {"coordinates":[-104.835205,39.793889],"type":"Point"}
}