{
  "type": "Feature",
  "properties": {
    "iso:country":"US",
    "sg:address":"1030 S 21st St",
    "sg:city":"Colorado Springs",
    "sg:classifiers":[
        {
            "category":"Retail",
            "subcategory":"Veterinary Services",
            "type":"Services"
        }
    ],
    "sg:phone":"+1 719 578 1030",
    "sg:postcode":"80904",
    "sg:province":"CO",
    "wof:name":"Aspenwood Animal Clinic",
    "wof:placetype":"venue"
},
  "geometry": {"coordinates":[-104.859234,38.837886],"type":"Point"}
}