{
  "type": "Feature",
  "properties": {
    "iso:country":"US",
    "sg:address":"3000 E 1st Ave",
    "sg:city":"Denver",
    "sg:classifiers":[
        {
            "category":"Coffee & Tea",
            "type":"Food & Drink"
        },
        {
            "category":"Cafe",
            "type":"Food & Drink"
        },
        {
            "category":"Bakery",
            "type":"Food & Drink"
        }
    ],
    "sg:menulink":"http://www.allmenus.com/co/denver/234016-nestle-toll-house-cafe/menu/",
    "sg:phone":"+1 303 321 2590",
    "sg:postcode":"80206",
    "sg:province":"CO",
    "sg:tags":[
        "american",
        "pastry"
    ],
    "wof:name":"Nestle Toll House Cafe",
    "wof:placetype":"venue"
},
  "geometry": {"coordinates":[-104.95325800000001,39.718043],"type":"Point"}
}