{
  "type": "Feature",
  "properties": {
    "iso:country":"US",
    "sg:address":"5546 Fossil Ct E",
    "sg:city":"Fort Collins",
    "sg:classifiers":[
        {
            "category":"Building & Trades",
            "subcategory":"Construction",
            "type":"Services"
        }
    ],
    "sg:phone":"+1 970 223 2201",
    "sg:postcode":"80525",
    "sg:province":"CO",
    "sg:tags":[
        "house"
    ],
    "wof:name":"Circle H Construction Inc",
    "wof:placetype":"venue"
},
  "geometry": {"coordinates":[-105.07305700000001,40.509886],"type":"Point"}
}