{
  "type": "Feature",
  "properties": {
    "iso:country":"US",
    "sg:address":"1935 W 12th Ave",
    "sg:city":"Denver",
    "sg:classifiers":[
        {
            "category":"Wholesale",
            "subcategory":"Sporting Goods",
            "type":"Manufacturing & Wholesale Goods"
        }
    ],
    "sg:phone":"+1 303 534 1303",
    "sg:postcode":"80204",
    "sg:province":"CO",
    "wof:name":"Think Helmets",
    "wof:placetype":"venue"
},
  "geometry": {"coordinates":[-105.014202,39.735302],"type":"Point"}
}