{
  "type": "Feature",
  "properties": {
    "addr:full":"333 S Tejon St Colorado Springs CO 80903",
    "addr:housenumber":"333",
    "addr:postcode":"80903",
    "addr:street":"S Tejon St",
    "iso:country":"US",
    "sg:address":"333 S Tejon St",
    "sg:city":"Colorado Springs",
    "sg:classifiers":[
        {
            "category":"Restaurant",
            "type":"Food & Drink"
        }
    ],
    "sg:phone":"+1 719 636 3304",
    "sg:postcode":"80903",
    "sg:province":"CO",
    "sg:tags":[
        "eating"
    ],
    "wof:name":"Ichiban Japanese Cuisine",
    "wof:placetype":"venue"
},
  "geometry": {"coordinates":[-104.82370299999999,38.828666],"type":"Point"}
}