{
  "type": "Feature",
  "properties": {
    "addr:full":"64 Silver Springs Blvd Pine CO 80470",
    "addr:housenumber":"64",
    "addr:postcode":"80470",
    "addr:street":"Silver Springs Blvd Pine",
    "iso:country":"US",
    "sg:address":"64 Silver Springs Blvd",
    "sg:city":"Pine",
    "sg:classifiers":[
        {
            "category":"Real Estate",
            "subcategory":"Architect",
            "type":"Services"
        }
    ],
    "sg:phone":"+1 303 838 6146",
    "sg:postcode":"80470",
    "sg:province":"CO",
    "wof:name":"KMD Architectural Prod Co",
    "wof:placetype":"venue"
},
  "geometry": {"coordinates":[-105.396085,39.46016],"type":"Point"}
}