{
  "type": "Feature",
  "properties": {
    "addr:full":"218 Curtis St Brush CO 80723",
    "addr:housenumber":"218",
    "addr:postcode":"80723",
    "addr:street":"Curtis St",
    "iso:country":"US",
    "sg:address":"218 Curtis St",
    "sg:city":"Brush",
    "sg:classifiers":[
        {
            "category":"Building & Trades",
            "subcategory":"Construction",
            "type":"Services"
        }
    ],
    "sg:phone":"+1 970 842 2612",
    "sg:postcode":"80723",
    "sg:province":"CO",
    "sg:tags":[
        "concrete",
        "contractor"
    ],
    "wof:name":"Zeppelin Concrete Construction",
    "wof:placetype":"venue"
},
  "geometry": {"coordinates":[-103.619072,40.256203],"type":"Point"}
}