{
  "type": "Feature",
  "properties": {
    "iso:country":"US",
    "sg:address":"5075 Kingston St",
    "sg:city":"Denver",
    "sg:classifiers":[
        {
            "category":"Home & Garden",
            "subcategory":"Carpets & Floor Coverings",
            "type":"Retail Goods"
        }
    ],
    "sg:phone":"+1 303 425 1690",
    "sg:postcode":"80239",
    "sg:province":"CO",
    "sg:tags":[
        "dealer",
        "rug"
    ],
    "sg:website":"www.carpetdirect.biz",
    "wof:name":"Carpet Direct",
    "wof:placetype":"venue"
},
  "geometry": {"coordinates":[-104.859106,39.789486],"type":"Point"}
}