{
  "type": "Feature",
  "properties": {
    "addr:full":"1242 Bergen Pkwy Evergreen CO 80439",
    "addr:housenumber":"1242",
    "addr:postcode":"80439",
    "addr:street":"Bergen Pkwy",
    "iso:country":"US",
    "sg:address":"1242 Bergen Pkwy",
    "sg:city":"Evergreen",
    "sg:classifiers":[
        {
            "category":"Retail",
            "subcategory":"Repair Shop",
            "type":"Services"
        }
    ],
    "sg:phone":"+1 303 670 2604",
    "sg:postcode":"80439",
    "sg:province":"CO",
    "sg:tags":[
        "equipment",
        "video"
    ],
    "wof:name":"TV Man",
    "wof:placetype":"venue"
},
  "geometry": {"coordinates":[-105.35660799999999,39.69304],"type":"Point"}
}