{
  "type": "Feature",
  "properties": {
    "iso:country":"US",
    "sg:address":"2040 Airway Ave",
    "sg:city":"Fort Collins",
    "sg:classifiers":[
        {
            "category":"Wholesale",
            "subcategory":"Machinery & Supplies",
            "type":"Manufacturing & Wholesale Goods"
        }
    ],
    "sg:phone":"+1 970 221 4230",
    "sg:postcode":"80524",
    "sg:province":"CO",
    "sg:tags":[
        "engine",
        "aircraft",
        "parts"
    ],
    "wof:name":"Jta Inc",
    "wof:placetype":"venue"
},
  "geometry": {"coordinates":[-105.039526,40.585222],"type":"Point"}
}