{
  "type": "Feature",
  "properties": {
    "iso:country":"US",
    "sg:address":"717 Nichols Blvd",
    "sg:city":"Colorado Springs",
    "sg:classifiers":[
        {
            "category":"Food & Beverages",
            "subcategory":"Specialty",
            "type":"Retail Goods"
        },
        {
            "category":"Utilities",
            "subcategory":"Refuse",
            "type":"Services"
        }
    ],
    "sg:phone":"+1 719 475 2532",
    "sg:postcode":"80907",
    "sg:province":"CO",
    "sg:tags":[
        "water",
        "bulk",
        "company",
        "system"
    ],
    "wof:name":"Springs Mountain Water",
    "wof:placetype":"venue"
},
  "geometry": {"coordinates":[-104.81118499999999,38.88217],"type":"Point"}
}