{
  "type": "Feature",
  "properties": {
    "addr:full":"105 E Bridge St Brighton CO 80601",
    "addr:housenumber":"105",
    "addr:postcode":"80601",
    "addr:street":"E Bridge St",
    "iso:country":"US",
    "sg:address":"105 E Bridge St",
    "sg:city":"Brighton",
    "sg:classifiers":[
        {
            "category":"Professional",
            "subcategory":"Accounting & Tax Preparation",
            "type":"Services"
        }
    ],
    "sg:phone":"+1 303 659 4810",
    "sg:postcode":"80601",
    "sg:province":"CO",
    "sg:tags":[
        "bookkeeping",
        "general"
    ],
    "wof:name":"Susan Worth & Assoc",
    "wof:placetype":"venue"
},
  "geometry": {"coordinates":[-104.82048500000001,39.98689],"type":"Point"}
}