{
  "type": "Feature",
  "properties": {
    "iso:country":"US",
    "sg:address":"1941 Heath Pkwy",
    "sg:city":"Fort Collins",
    "sg:classifiers":[
        {
            "category":"Professional",
            "type":"Services"
        },
        {
            "category":"Manufacturing",
            "subcategory":"Toys & Sporting Goods",
            "type":"Manufacturing & Wholesale Goods"
        }
    ],
    "sg:phone":"+1 970 490 1802",
    "sg:postcode":"80524",
    "sg:province":"CO",
    "sg:tags":[
        "establishment",
        "mfg"
    ],
    "wof:name":"Donik Sports Inc",
    "wof:placetype":"venue"
},
  "geometry": {"coordinates":[-105.040566,40.583653],"type":"Point"}
}