{
  "type": "Feature",
  "properties": {
    "iso:country":"US",
    "sg:address":"200 Quebec St Bldg 600127",
    "sg:city":"Denver",
    "sg:classifiers":[
        {
            "category":"Personal",
            "type":"Services"
        }
    ],
    "sg:phone":"+1 303 360 8422",
    "sg:postcode":"80230",
    "sg:province":"CO",
    "sg:tags":[
        "party",
        "planning",
        "event"
    ],
    "sg:website":"www.colormemine.com",
    "wof:name":"Color Me Mine",
    "wof:placetype":"venue"
},
  "geometry": {"coordinates":[-104.902339,39.720102],"type":"Point"}
}