{
  "type": "Feature",
  "properties": {
    "iso:country":"US",
    "sg:address":"17981 W Colfax Ave",
    "sg:city":"Golden",
    "sg:classifiers":[
        {
            "category":"Insurance",
            "subcategory":"Hazard Insurance",
            "type":"Services"
        }
    ],
    "sg:phone":"+1 303 279 3174",
    "sg:postcode":"80401",
    "sg:province":"CO",
    "sg:tags":[
        "bond"
    ],
    "wof:name":"ASAP Express Bail Bonds",
    "wof:placetype":"venue"
},
  "geometry": {"coordinates":[-105.19992499999999,39.720507],"type":"Point"}
}