{
  "type": "Feature",
  "properties": {
    "iso:country":"US",
    "sg:address":"884 E Woodleaf Dr",
    "sg:city":"Pueblo West",
    "sg:classifiers":[
        {
            "category":"Wholesale",
            "subcategory":"Construction Materials",
            "type":"Manufacturing & Wholesale Goods"
        },
        {
            "category":"Building & Trades",
            "subcategory":"Construction",
            "type":"Services"
        }
    ],
    "sg:phone":"+1 719 240 5079",
    "sg:postcode":"81007",
    "sg:province":"CO",
    "sg:tags":[
        "house",
        "fence"
    ],
    "wof:name":"Double d Fence",
    "wof:placetype":"venue"
},
  "geometry": {"coordinates":[-104.704284,38.309985],"type":"Point"}
}