{
  "type": "Feature",
  "properties": {
    "iso:country":"US",
    "sg:address":"615 Beacon Lite Rd",
    "sg:city":"Monument",
    "sg:classifiers":[
        {
            "category":"Shopping",
            "subcategory":"Jewelry",
            "type":"Retail Goods"
        }
    ],
    "sg:phone":"+1 719 488 0484",
    "sg:postcode":"80132",
    "sg:province":"CO",
    "sg:tags":[
        "jeweler"
    ],
    "wof:name":"Goldsmith Gallery",
    "wof:placetype":"venue"
},
  "geometry": {"coordinates":[-104.868132,39.097509],"type":"Point"}
}