{
  "type": "Feature",
  "properties": {
    "addr:full":"5525 Erindale Dr Colorado Springs CO 80918",
    "addr:housenumber":"5525",
    "addr:postcode":"80918",
    "addr:street":"Erindale Dr",
    "iso:country":"US",
    "sg:address":"5525 Erindale Dr",
    "sg:city":"Colorado Springs",
    "sg:classifiers":[
        {
            "category":"Insurance",
            "subcategory":"Insurance Agent",
            "type":"Services"
        }
    ],
    "sg:phone":"+1 719 268 1227",
    "sg:postcode":"80918",
    "sg:province":"CO",
    "wof:name":"Bankers Life & Casualty Co",
    "wof:placetype":"venue"
},
  "geometry": {"coordinates":[-104.78534000000001,38.911747],"type":"Point"}
}