{
  "type": "Feature",
  "properties": {
    "iso:country":"US",
    "sg:address":"1300 Baystone Dr",
    "sg:city":"Fort Collins",
    "sg:classifiers":[
        {
            "category":"Organizations",
            "subcategory":"Community Association",
            "type":"Services"
        }
    ],
    "sg:phone":"+1 970 484 6658",
    "sg:postcode":"80521",
    "sg:province":"CO",
    "sg:tags":[
        "sorority",
        "fraternity"
    ],
    "wof:name":"Pi Kappa Phi Fraternity",
    "wof:placetype":"venue"
},
  "geometry": {"coordinates":[-105.099664,40.577534],"type":"Point"}
}