{
  "type": "Feature",
  "properties": {
    "iso:country":"US",
    "sg:address":"215 Eldon Wilson Rd",
    "sg:city":"Gypsum",
    "sg:classifiers":[
        {
            "category":"Building & Trades",
            "subcategory":"Equipment Rental",
            "type":"Services"
        }
    ],
    "sg:phone":"+1 970 524 1250",
    "sg:postcode":"81637",
    "sg:province":"CO",
    "sg:tags":[
        "aircraft",
        "leasing",
        "charter"
    ],
    "wof:name":"Corporate Aircraft Management",
    "wof:placetype":"venue"
},
  "geometry": {"coordinates":[-106.905985,39.640308],"type":"Point"}
}