{
  "type": "Feature",
  "properties": {
    "addr:full":"28001 Columbine Rd Evergreen CO 80439",
    "addr:housenumber":"28001",
    "addr:postcode":"80439",
    "addr:street":"Columbine Rd",
    "iso:country":"US",
    "sg:address":"28001 Columbine Rd",
    "sg:city":"Evergreen",
    "sg:classifiers":[
        {
            "category":"Wholesale",
            "subcategory":"Sporting Goods",
            "type":"Manufacturing & Wholesale Goods"
        }
    ],
    "sg:phone":"+1 303 674 0707",
    "sg:postcode":"80439",
    "sg:province":"CO",
    "wof:name":"Buck Tylers Co Inc",
    "wof:placetype":"venue"
},
  "geometry": {"coordinates":[-105.316378,39.63089],"type":"Point"}
}