{
  "type": "Feature",
  "properties": {
    "addr:full":"9307 N la Crosse Ln Parker CO 80138",
    "addr:housenumber":"9307",
    "addr:postcode":"80138",
    "addr:street":"N La Crosse Ln",
    "iso:country":"US",
    "sg:address":"9307 N la Crosse Ln",
    "sg:city":"Parker",
    "sg:classifiers":[
        {
            "category":"Building & Trades",
            "subcategory":"Construction",
            "type":"Services"
        }
    ],
    "sg:phone":"+1 303 841 0292",
    "sg:postcode":"80138",
    "sg:province":"CO",
    "sg:tags":[
        "company",
        "leasing"
    ],
    "wof:name":"Shellbourn Corporation",
    "wof:placetype":"venue"
},
  "geometry": {"coordinates":[-105.14631300000001,39.613924],"type":"Point"}
}