{
  "type": "Feature",
  "properties": {
    "addr:full":"579 W 66th St Loveland CO 80538",
    "addr:housenumber":"579",
    "addr:postcode":"80538",
    "addr:street":"W 66Th St",
    "iso:country":"US",
    "sg:address":"579 W 66th St",
    "sg:city":"Loveland",
    "sg:classifiers":[
        {
            "category":"Building & Trades",
            "subcategory":"Construction",
            "type":"Services"
        }
    ],
    "sg:phone":"+1 970 278 1930",
    "sg:postcode":"80538",
    "sg:province":"CO",
    "sg:tags":[
        "general"
    ],
    "sg:website":"www.basements4you.com",
    "wof:name":"Poehlmann Construction Co",
    "wof:placetype":"venue"
},
  "geometry": {"coordinates":[-105.081248,40.459695],"type":"Point"}
}