{
  "type": "Feature",
  "properties": {
    "iso:country":"US",
    "sg:address":"5055 S Kipling Pkwy",
    "sg:city":"Littleton",
    "sg:classifiers":[
        {
            "category":"Personal",
            "subcategory":"Nail Salon",
            "type":"Services"
        }
    ],
    "sg:phone":"+1 303 933 1976",
    "sg:postcode":"80127",
    "sg:province":"CO",
    "wof:name":"W B Nails",
    "wof:placetype":"venue"
},
  "geometry": {"coordinates":[-105.110094,39.625083],"type":"Point"}
}