{
  "type": "Feature",
  "properties": {
    "iso:country":"US",
    "sg:address":"405 Canyon Ave",
    "sg:city":"Fort Collins",
    "sg:classifiers":[
        {
            "category":"Professional",
            "subcategory":"Accounting & Tax Preparation",
            "type":"Services"
        }
    ],
    "sg:phone":"+1 970 482 4934",
    "sg:postcode":"80521",
    "sg:province":"CO",
    "sg:tags":[
        "accountant"
    ],
    "wof:name":"Dean Nunn & Assoc",
    "wof:placetype":"venue"
},
  "geometry": {"coordinates":[-105.085187,40.582375],"type":"Point"}
}