{
  "type": "Feature",
  "properties": {
    "iso:country":"US",
    "sg:address":"440 Santa Fe Dr",
    "sg:city":"Pueblo",
    "sg:classifiers":[
        {
            "category":"Retail",
            "subcategory":"Animal Services",
            "type":"Services"
        }
    ],
    "sg:phone":"+1 719 544 9034",
    "sg:postcode":"81006",
    "sg:province":"CO",
    "sg:tags":[
        "grooming",
        "dog"
    ],
    "wof:name":"Mudpuppy Grooming",
    "wof:placetype":"venue"
},
  "geometry": {"coordinates":[-104.604326,38.25139],"type":"Point"}
}