{
  "type": "Feature",
  "properties": {
    "addr:full":"5869 Broadway St Denver CO 80216",
    "addr:housenumber":"5869",
    "addr:postcode":"80216",
    "addr:street":"Broadway St",
    "iso:country":"US",
    "sg:address":"5869 Broadway St",
    "sg:city":"Denver",
    "sg:classifiers":[
        {
            "category":"Freight",
            "type":"Transportation"
        }
    ],
    "sg:phone":"+1 303 296 9099",
    "sg:postcode":"80216",
    "sg:province":"CO",
    "sg:tags":[
        "driver",
        "staffing"
    ],
    "wof:name":"Atd Noble Logistics",
    "wof:placetype":"venue"
},
  "geometry": {"coordinates":[-104.987551,39.804877],"type":"Point"}
}