{
  "type": "Feature",
  "properties": {
    "addr:full":"6500 S Quebec St Englewood CO 80111",
    "addr:housenumber":"6500",
    "addr:postcode":"80111",
    "addr:street":"S Quebec St",
    "iso:country":"US",
    "sg:address":"6500 S Quebec St",
    "sg:city":"Englewood",
    "sg:classifiers":[
        {
            "category":"Banks & Credit Unions",
            "subcategory":"Bank",
            "type":"Services"
        }
    ],
    "sg:phone":"+1 720 493 9199",
    "sg:postcode":"80111",
    "sg:province":"CO",
    "sg:tags":[
        "broker",
        "mortgage"
    ],
    "wof:name":"Alliance Mortgage Capital Inc",
    "wof:placetype":"venue"
},
  "geometry": {"coordinates":[-104.90415900000001,39.597055],"type":"Point"}
}