{
  "type": "Feature",
  "properties": {
    "addr:full":"13165 W Ohio Ave Denver CO 80228",
    "addr:housenumber":"13165",
    "addr:postcode":"80228",
    "addr:street":"W Ohio Ave",
    "iso:country":"US",
    "sg:address":"13165 W Ohio Ave",
    "sg:city":"Denver",
    "sg:classifiers":[
        {
            "category":"Education",
            "subcategory":"School",
            "type":"Public Place"
        }
    ],
    "sg:phone":"+1 303 982 9324",
    "sg:postcode":"80228",
    "sg:province":"CO",
    "wof:name":"Foothills Elementary School",
    "wof:placetype":"venue"
},
  "geometry": {"coordinates":[-105.144645,39.70047],"type":"Point"}
}