{
  "type": "Feature",
  "properties": {
    "iso:country":"US",
    "sg:address":"525 E 70th Ave",
    "sg:city":"Denver",
    "sg:classifiers":[
        {
            "category":"Wholesale",
            "subcategory":"Construction Materials",
            "type":"Manufacturing & Wholesale Goods"
        }
    ],
    "sg:phone":"+1 303 853 0171",
    "sg:postcode":"80229",
    "sg:province":"CO",
    "wof:name":"Sheds R US",
    "wof:placetype":"venue"
},
  "geometry": {"coordinates":[-104.97984700000001,39.823831],"type":"Point"}
}