{
  "type": "Feature",
  "properties": {
    "iso:country":"US",
    "sg:address":"979 S Teller Street",
    "sg:city":"Lakewood",
    "sg:classifiers":[
        {
            "category":"Building & Trades",
            "subcategory":"Locksmith",
            "type":"Services"
        }
    ],
    "sg:phone":"+1 720 240 2610",
    "sg:postcode":"80226",
    "sg:province":"CO",
    "sg:tags":[
        "key"
    ],
    "wof:name":"Leon's 24-7 Emergency Locksmith Service",
    "wof:placetype":"venue"
},
  "geometry": {"coordinates":[-105.077208,39.698351],"type":"Point"}
}