{
  "type": "Feature",
  "properties": {
    "iso:country":"US",
    "sg:address":"230 Clearwater Dr",
    "sg:city":"Pagosa Springs",
    "sg:classifiers":[
        {
            "category":"Building & Trades",
            "subcategory":"Construction",
            "type":"Services"
        }
    ],
    "sg:phone":"+1 970 264 6632",
    "sg:postcode":"81147",
    "sg:province":"CO",
    "sg:tags":[
        "contractor"
    ],
    "wof:name":"Southwest Insulation & Roofing",
    "wof:placetype":"venue"
},
  "geometry": {"coordinates":[-106.993239,37.221997],"type":"Point"}
}