{
  "type": "Feature",
  "properties": {
    "addr:full":"4706 E 127th Dr Denver CO 80241",
    "addr:housenumber":"4706",
    "addr:postcode":"80241",
    "addr:street":"E 127Th Dr",
    "iso:country":"US",
    "sg:address":"4706 E 127th Dr",
    "sg:city":"Denver",
    "sg:classifiers":[
        {
            "category":"Real Estate",
            "subcategory":"Real Estate Agent",
            "type":"Services"
        }
    ],
    "sg:phone":"+1 303 393 6766",
    "sg:postcode":"80241",
    "sg:province":"CO",
    "wof:name":"Johnson & Cobbs Realty",
    "wof:placetype":"venue"
},
  "geometry": {"coordinates":[-104.931541,39.926412],"type":"Point"}
}