{
  "type": "Feature",
  "properties": {
    "iso:country":"US",
    "sg:address":"2402 Lakeview Ave",
    "sg:city":"Pueblo",
    "sg:classifiers":[
        {
            "category":"Building & Trades",
            "subcategory":"Electrical",
            "type":"Services"
        }
    ],
    "sg:phone":"+1 719 564 1064",
    "sg:postcode":"81004",
    "sg:province":"CO",
    "sg:tags":[
        "electrical",
        "electric",
        "contractor"
    ],
    "wof:name":"A-Var Electric Inc",
    "wof:placetype":"venue"
},
  "geometry": {"coordinates":[-104.641364,38.234906],"type":"Point"}
}