{
  "type": "Feature",
  "properties": {
    "iso:country":"US",
    "sg:address":"738 Main St",
    "sg:city":"Ouray",
    "sg:classifiers":[
        {
            "category":"Food & Beverages",
            "subcategory":"Liquor & Beverages",
            "type":"Retail Goods"
        }
    ],
    "sg:phone":"+1 970 325 0784",
    "sg:postcode":"81427",
    "sg:province":"CO",
    "wof:name":"Ouray Liquors",
    "wof:placetype":"venue"
},
  "geometry": {"coordinates":[-107.671578,38.024553],"type":"Point"}
}