{
  "type": "Feature",
  "properties": {
    "addr:full":"5345 Newport St Commerce City CO 80022",
    "addr:housenumber":"5345",
    "addr:postcode":"80022",
    "addr:street":"Newport St",
    "iso:country":"US",
    "sg:address":"5345 Newport St",
    "sg:city":"Commerce City",
    "sg:classifiers":[
        {
            "category":"Autos & Motor Vehicles",
            "subcategory":"Automobile Sales",
            "type":"Retail Goods"
        }
    ],
    "sg:phone":"+1 303 288 1002",
    "sg:postcode":"80022",
    "sg:province":"CO",
    "sg:tags":[
        "new",
        "used",
        "truck"
    ],
    "wof:name":"Commercial Truck Sales Inc",
    "wof:placetype":"venue"
},
  "geometry": {"coordinates":[-104.909836,39.792096],"type":"Point"}
}