{
  "type": "Feature",
  "properties": {
    "iso:country":"US",
    "sg:address":"1900 S Cook Street",
    "sg:city":"Denver",
    "sg:classifiers":[
        {
            "category":"Organizations",
            "subcategory":"Religious Organization",
            "type":"Services"
        }
    ],
    "sg:phone":"+1 303 758 8627",
    "sg:postcode":"80210",
    "sg:province":"CO",
    "wof:name":"The Church In Denver",
    "wof:placetype":"venue"
},
  "geometry": {"coordinates":[-104.948101,39.681903],"type":"Point"}
}