{
  "type": "Feature",
  "properties": {
    "iso:country":"US",
    "sg:address":"1355 Elmira St",
    "sg:city":"Aurora",
    "sg:classifiers":[
        {
            "category":"Insurance",
            "subcategory":"Insurance Agent",
            "type":"Services"
        }
    ],
    "sg:phone":"+1 303 367 1532",
    "sg:postcode":"80010",
    "sg:province":"CO",
    "wof:name":"Senior Program",
    "wof:placetype":"venue"
},
  "geometry": {"coordinates":[-104.872968,39.737277],"type":"Point"}
}