{
  "type": "Feature",
  "properties": {
    "addr:full":"5299 Dtc Blvd Englewood CO 80111",
    "addr:housenumber":"5299",
    "addr:postcode":"80111",
    "addr:street":"Dtc Blvd",
    "iso:country":"US",
    "sg:address":"5299 Dtc Blvd",
    "sg:city":"Englewood",
    "sg:classifiers":[
        {
            "category":"Banks & Credit Unions",
            "subcategory":"Investment Brokerage",
            "type":"Services"
        }
    ],
    "sg:phone":"+1 303 790 1600",
    "sg:postcode":"80111",
    "sg:province":"CO",
    "sg:tags":[
        "advisory",
        "financial"
    ],
    "wof:name":"Icon Advisers Inc",
    "wof:placetype":"venue"
},
  "geometry": {"coordinates":[-104.88981699999999,39.620999],"type":"Point"}
}