{
  "type": "Feature",
  "properties": {
    "iso:country":"US",
    "sg:address":"4121 Sundown Rd",
    "sg:city":"Delta",
    "sg:classifiers":[
        {
            "category":"Professional",
            "subcategory":"Engineering",
            "type":"Services"
        }
    ],
    "sg:phone":"+1 970 874 0208",
    "sg:postcode":"81416",
    "sg:province":"CO",
    "sg:tags":[
        "steel",
        "erection",
        "structural"
    ],
    "wof:name":"Morris Detailing Inc",
    "wof:placetype":"venue"
},
  "geometry": {"coordinates":[-108.13292199999999,38.714317],"type":"Point"}
}