{
  "type": "Feature",
  "properties": {
    "iso:country":"US",
    "sg:address":"1420 North Ave",
    "sg:city":"Grand Junction",
    "sg:classifiers":[
        {
            "category":"Recreation",
            "type":"Entertainment"
        }
    ],
    "sg:phone":"+1 970 243 8477",
    "sg:postcode":"81501",
    "sg:province":"CO",
    "sg:tags":[
        "martial",
        "arts",
        "instruction"
    ],
    "wof:name":"Bill Brassette's Karate Studio",
    "wof:placetype":"venue"
},
  "geometry": {"coordinates":[-108.55238900000001,39.077391],"type":"Point"}
}