{
  "type": "Feature",
  "properties": {
    "addr:full":"1818 Vinewood Ln Pueblo CO 81005",
    "addr:housenumber":"1818",
    "addr:postcode":"81005",
    "addr:street":"Vinewood Ln",
    "iso:country":"US",
    "sg:address":"1818 Vinewood Ln",
    "sg:city":"Pueblo",
    "sg:classifiers":[
        {
            "category":"Insurance",
            "subcategory":"Insurance Agent",
            "type":"Services"
        }
    ],
    "sg:phone":"+1 719 561 8025",
    "sg:postcode":"81005",
    "sg:province":"CO",
    "wof:name":"Craig E Law Insurance Inc",
    "wof:placetype":"venue"
},
  "geometry": {"coordinates":[-104.660768,38.236044],"type":"Point"}
}