{
  "type": "Feature",
  "properties": {
    "iso:country":"US",
    "sg:address":"2270 Co Rd 5",
    "sg:city":"Fraser",
    "sg:classifiers":[
        {
            "category":"Building & Trades",
            "subcategory":"Construction",
            "type":"Services"
        }
    ],
    "sg:phone":"+1 970 726 4402",
    "sg:postcode":"80480",
    "sg:province":"CO",
    "sg:tags":[
        "general",
        "contractor"
    ],
    "wof:name":"Morrow & Sons Construction Inc",
    "wof:placetype":"venue"
},
  "geometry": {"coordinates":[-106.48973100000001,40.660798],"type":"Point"}
}