{
  "type": "Feature",
  "properties": {
    "iso:country":"US",
    "sg:address":"2507 Monterey Rd",
    "sg:city":"Colorado Springs",
    "sg:classifiers":[
        {
            "category":"Shopping",
            "subcategory":"Bicycles & Sporting Goods",
            "type":"Retail Goods"
        }
    ],
    "sg:phone":"+1 719 570 7796",
    "sg:postcode":"80910",
    "sg:province":"CO",
    "wof:name":"Disc Connection",
    "wof:placetype":"venue"
},
  "geometry": {"coordinates":[-104.76409099999999,38.795194],"type":"Point"}
}