{
  "type": "Feature",
  "properties": {
    "addr:full":"316 Co Rd 40 Meeker CO 81641",
    "addr:housenumber":"316;40",
    "addr:postcode":"81641",
    "addr:street":"Co Rd",
    "iso:country":"US",
    "sg:address":"316 Co Rd 40",
    "sg:city":"Meeker",
    "sg:phone":"+1 970 878 5291",
    "sg:postcode":"81641",
    "sg:province":"CO",
    "sg:tags":[
        "farm",
        "field",
        "crop"
    ],
    "wof:name":"Bertholson LLC",
    "wof:placetype":"venue"
},
  "geometry": {"coordinates":[-107.716199,40.030758],"type":"Point"}
}