{
  "type": "Feature",
  "properties": {
    "addr:full":"6647 Federal Blvd Denver CO 80221",
    "addr:housenumber":"6647",
    "addr:postcode":"80221",
    "addr:street":"Federal Blvd",
    "iso:country":"US",
    "sg:address":"6647 Federal Blvd",
    "sg:city":"Denver",
    "sg:classifiers":[
        {
            "category":"Restaurant",
            "type":"Food & Drink"
        }
    ],
    "sg:phone":"+1 303 426 8490",
    "sg:postcode":"80221",
    "sg:province":"CO",
    "sg:tags":[
        "drinking",
        "eating"
    ],
    "wof:name":"Casa De Bonilla",
    "wof:placetype":"venue"
},
  "geometry": {"coordinates":[-105.025338,39.817926],"type":"Point"}
}