{
  "type": "Feature",
  "properties": {
    "addr:full":"25476 State Hwy 135 Crested Butte CO 81224",
    "addr:housenumber":"25476",
    "addr:postcode":"81224",
    "addr:street":"State Hwy 135",
    "iso:country":"US",
    "sg:address":"25476 State Hwy 135",
    "sg:city":"Crested Butte",
    "sg:classifiers":[
        {
            "category":"Real Estate",
            "subcategory":"Real Estate Agent",
            "type":"Services"
        }
    ],
    "sg:phone":"+1 970 349 6364",
    "sg:postcode":"81224",
    "sg:province":"CO",
    "sg:tags":[
        "agency",
        "rental"
    ],
    "wof:name":"Riverland Rentals",
    "wof:placetype":"venue"
},
  "geometry": {"coordinates":[-106.95186200000001,38.851147],"type":"Point"}
}