{
  "type": "Feature",
  "properties": {
    "addr:full":"399 Butte Ct Grand Junction CO 81503",
    "addr:housenumber":"399",
    "addr:postcode":"81503",
    "addr:street":"Butte Ct",
    "iso:country":"US",
    "sg:address":"399 Butte Ct",
    "sg:city":"Grand Junction",
    "sg:classifiers":[
        {
            "category":"Building & Trades",
            "subcategory":"Construction",
            "type":"Services"
        }
    ],
    "sg:phone":"+1 970 254 0451",
    "sg:postcode":"81503",
    "sg:province":"CO",
    "sg:tags":[
        "masonry",
        "contractor"
    ],
    "wof:name":"Groves Masonry Construction",
    "wof:placetype":"venue"
},
  "geometry": {"coordinates":[-108.617307,39.064089],"type":"Point"}
}