{
  "type": "Feature",
  "properties": {
    "iso:country":"US",
    "sg:address":"12200 E Iliff Ave",
    "sg:city":"Aurora",
    "sg:classifiers":[
        {
            "category":"Health Services",
            "subcategory":"Clinic",
            "type":"Services"
        }
    ],
    "sg:phone":"+1 303 337 5505",
    "sg:postcode":"80014",
    "sg:province":"CO",
    "sg:tags":[
        "home"
    ],
    "wof:name":"Saturday Partners LLC",
    "wof:placetype":"venue"
},
  "geometry": {"coordinates":[-104.845714,39.674752],"type":"Point"}
}