{
  "type": "Feature",
  "properties": {
    "addr:full":"267 S Circle Dr Colorado Springs CO 80910",
    "addr:housenumber":"267",
    "addr:postcode":"80910",
    "addr:street":"S Circle Dr",
    "iso:country":"US",
    "sg:address":"267 S Circle Dr",
    "sg:city":"Colorado Springs",
    "sg:classifiers":[
        {
            "category":"Shopping",
            "subcategory":"Clothing, Apparel, & Fashions",
            "type":"Retail Goods"
        }
    ],
    "sg:phone":"+1 719 633 3789",
    "sg:postcode":"80910",
    "sg:province":"CO",
    "wof:name":"Yavidas Fashion",
    "wof:placetype":"venue"
},
  "geometry": {"coordinates":[-104.777704,38.827033],"type":"Point"}
}