{
  "type": "Feature",
  "properties": {
    "iso:country":"US",
    "sg:address":"7586 W Jewell Ave",
    "sg:city":"Lakewood",
    "sg:classifiers":[
        {
            "category":"Professional",
            "subcategory":"Lawyer & Legal Services",
            "type":"Services"
        }
    ],
    "sg:phone":"+1 303 763 8988",
    "sg:postcode":"80232",
    "sg:province":"CO",
    "sg:tags":[
        "attorney"
    ],
    "wof:name":"Wadsworth & Jewell",
    "wof:placetype":"venue"
},
  "geometry": {"coordinates":[-105.080853,39.682158],"type":"Point"}
}