{
  "type": "Feature",
  "properties": {
    "iso:country":"US",
    "sg:address":"30 N Market St",
    "sg:city":"Cortez",
    "sg:classifiers":[
        {
            "category":"Shopping",
            "subcategory":"Florist",
            "type":"Retail Goods"
        }
    ],
    "sg:phone":"+1 970 565 3471",
    "sg:postcode":"81321",
    "sg:province":"CO",
    "wof:name":"Flower Cottage Inc",
    "wof:placetype":"venue"
},
  "geometry": {"coordinates":[-108.585127,37.349386],"type":"Point"}
}