{
  "type": "Feature",
  "properties": {
    "addr:full":"364 Bellaire Street Denver CO 80220",
    "addr:housenumber":"364",
    "addr:postcode":"80220",
    "addr:street":"Bellaire Street",
    "iso:country":"US",
    "sg:address":"364 Bellaire Street",
    "sg:city":"Denver",
    "sg:classifiers":[
        {
            "category":"Shopping",
            "subcategory":"Stationery & Office Supplies",
            "type":"Retail Goods"
        }
    ],
    "sg:phone":"+1 303 329 9545",
    "sg:postcode":"80220",
    "sg:province":"CO",
    "sg:tags":[
        "equipment"
    ],
    "wof:name":"Information Management Specialists",
    "wof:placetype":"venue"
},
  "geometry": {"coordinates":[-104.937146,39.72248],"type":"Point"}
}