{
  "type": "Feature",
  "properties": {
    "iso:country":"US",
    "sg:address":"6035 S Monaco Way",
    "sg:city":"Englewood",
    "sg:classifiers":[
        {
            "category":"Professional",
            "subcategory":"Accounting & Tax Preparation",
            "type":"Services"
        }
    ],
    "sg:phone":"+1 303 779 1421",
    "sg:postcode":"80111",
    "sg:province":"CO",
    "wof:name":"Ball Accounting & Data Center",
    "wof:placetype":"venue"
},
  "geometry": {"coordinates":[-104.91297299999999,39.606123],"type":"Point"}
}