{
  "type": "Feature",
  "properties": {
    "iso:country":"US",
    "sg:address":"1855 Allegheny Dr",
    "sg:city":"Colorado Springs",
    "sg:classifiers":[
        {
            "category":"Real Estate",
            "subcategory":"Real Estate Operator",
            "type":"Services"
        }
    ],
    "sg:phone":"+1 719 260 8958",
    "sg:postcode":"80919",
    "sg:province":"CO",
    "sg:tags":[
        "building",
        "nonresidential"
    ],
    "wof:name":"Timbervw 2 Prop Ownrs Assn",
    "wof:placetype":"venue"
},
  "geometry": {"coordinates":[-104.860837,38.930377],"type":"Point"}
}