{
  "type": "Feature",
  "properties": {
    "addr:full":"720 S. Colorado Blvd. Suite 500 N. Denver CO 80246",
    "addr:housenumber":"720",
    "addr:postcode":"80246",
    "addr:street":"S. Colorado Blvd. Suite 500 N.",
    "iso:country":"US",
    "sg:address":"720 S. Colorado Blvd. Suite 500 N.",
    "sg:city":"Denver",
    "sg:classifiers":[
        {
            "category":"Professional",
            "subcategory":"Computer Services",
            "type":"Services"
        }
    ],
    "sg:phone":"+1 303 333 7880",
    "sg:postcode":"80246",
    "sg:province":"CO",
    "sg:tags":[
        "qualitative-market-research",
        "online-market-research",
        "moderators--online-qualitative",
        "market-research-company",
        "online-research-company"
    ],
    "sg:website":"http://www.imoderate.com",
    "wof:name":"iModerate Research Technologies",
    "wof:placetype":"venue"
},
  "geometry": {"coordinates":[-104.940635,39.70351],"type":"Point"}
}