{
  "type": "Feature",
  "properties": {
    "addr:full":"13198 Co Rd 35.6 Mancos CO 81328",
    "addr:housenumber":"13198",
    "addr:postcode":"81328",
    "addr:street":"Co Rd 35.6",
    "iso:country":"US",
    "sg:address":"13198 Co Rd 35.6",
    "sg:city":"Mancos",
    "sg:classifiers":[
        {
            "category":"Wholesale",
            "subcategory":"Farm Supplies",
            "type":"Manufacturing & Wholesale Goods"
        }
    ],
    "sg:phone":"+1 970 882 8805",
    "sg:postcode":"81328",
    "sg:province":"CO",
    "sg:tags":[
        "bean"
    ],
    "wof:name":"Summit Bridge Buiders",
    "wof:placetype":"venue"
},
  "geometry": {"coordinates":[-108.396936,37.402879],"type":"Point"}
}