{
  "type": "Feature",
  "properties": {
    "iso:country":"US",
    "sg:address":"3773 Cherry Creek North D",
    "sg:city":"Denver",
    "sg:classifiers":[
        {
            "category":"Professional",
            "subcategory":"Lawyer & Legal Services",
            "type":"Services"
        }
    ],
    "sg:phone":"+1 303 320 0023",
    "sg:postcode":"80209",
    "sg:province":"CO",
    "wof:name":"Zisman Sanford Atty",
    "wof:placetype":"venue"
},
  "geometry": {"coordinates":[-104.944127,39.709037],"type":"Point"}
}