{
  "type": "Feature",
  "properties": {
    "addr:full":"3445 E 28th Ave Denver CO 80205",
    "addr:housenumber":"3445",
    "addr:postcode":"80205",
    "addr:street":"E 28Th Ave",
    "iso:country":"US",
    "sg:address":"3445 E 28th Ave",
    "sg:city":"Denver",
    "sg:classifiers":[
        {
            "category":"Restaurant",
            "type":"Food & Drink"
        },
        {
            "category":"Professional",
            "subcategory":"Business Services",
            "type":"Services"
        }
    ],
    "sg:phone":"+1 303 861 8236",
    "sg:postcode":"80205",
    "sg:province":"CO",
    "sg:tags":[
        "delivery",
        "cajun/creole"
    ],
    "sg:website":"www.pierresmobile.com/",
    "wof:name":"Pierre's Food Service",
    "wof:placetype":"venue"
},
  "geometry": {"coordinates":[-104.94699900000001,39.757099],"type":"Point"}
}