{
  "type": "Feature",
  "properties": {
    "iso:country":"US",
    "sg:address":"933 US Hwy 287",
    "sg:city":"Fort Collins",
    "sg:classifiers":[
        {
            "category":"Professional",
            "subcategory":"Accounting & Tax Preparation",
            "type":"Services"
        }
    ],
    "sg:phone":"+1 970 221 2455",
    "sg:postcode":"80524",
    "sg:province":"CO",
    "sg:tags":[
        "accountant"
    ],
    "wof:name":"Maurice Cady CPA",
    "wof:placetype":"venue"
},
  "geometry": {"coordinates":[-105.077151,40.574611],"type":"Point"}
}