{
  "type": "Feature",
  "properties": {
    "iso:country":"US",
    "sg:address":"3905 Inspiration Dr",
    "sg:city":"Colorado Springs",
    "sg:classifiers":[
        {
            "category":"Health Services",
            "subcategory":"Nursing And Care Facility",
            "type":"Services"
        },
        {
            "category":"Health Services",
            "subcategory":"Clinic",
            "type":"Services"
        }
    ],
    "sg:phone":"+1 719 572 0299",
    "sg:postcode":"80917",
    "sg:province":"CO",
    "sg:tags":[
        "home"
    ],
    "wof:name":"Home Helpers Colorado Springs",
    "wof:placetype":"venue"
},
  "geometry": {"coordinates":[-104.727558,38.888335],"type":"Point"}
}