{
  "type": "Feature",
  "properties": {
    "iso:country":"US",
    "sg:address":"2722 11th Ave",
    "sg:city":"Greeley",
    "sg:classifiers":[
        {
            "category":"Food & Beverages",
            "subcategory":"Liquor & Beverages",
            "type":"Retail Goods"
        }
    ],
    "sg:phone":"+1 970 353 7444",
    "sg:postcode":"80631",
    "sg:province":"CO",
    "sg:tags":[
        "alcoholic"
    ],
    "wof:name":"Johnnys Liquor",
    "wof:placetype":"venue"
},
  "geometry": {"coordinates":[-104.696836,40.392343],"type":"Point"}
}