{
  "type": "Feature",
  "properties": {
    "iso:country":"US",
    "sg:address":"2219 Sanford Dr",
    "sg:city":"Grand Junction",
    "sg:classifiers":[
        {
            "category":"Building & Trades",
            "subcategory":"Equipment Rental",
            "type":"Services"
        }
    ],
    "sg:phone":"+1 970 244 8349",
    "sg:postcode":"81505",
    "sg:province":"CO",
    "sg:tags":[
        "crane"
    ],
    "wof:name":"Perry Crane & Rigging",
    "wof:placetype":"venue"
},
  "geometry": {"coordinates":[-108.63930499999999,39.112297],"type":"Point"}
}