{
  "type": "Feature",
  "properties": {
    "addr:full":"3021 W Bear Creek Dr Englewood CO 80110",
    "addr:housenumber":"3021",
    "addr:postcode":"80110",
    "addr:street":"W Bear Creek Dr",
    "iso:country":"US",
    "sg:address":"3021 W Bear Creek Dr",
    "sg:city":"Englewood",
    "sg:classifiers":[
        {
            "category":"Wholesale",
            "subcategory":"Stationery",
            "type":"Manufacturing & Wholesale Goods"
        }
    ],
    "sg:phone":"+1 303 762 0033",
    "sg:postcode":"80110",
    "sg:province":"CO",
    "sg:tags":[
        "paper"
    ],
    "wof:name":"Paper Rolls Unlimited",
    "wof:placetype":"venue"
},
  "geometry": {"coordinates":[-105.026923,39.650163],"type":"Point"}
}