{
  "type": "Feature",
  "properties": {
    "addr:full":"1550 Dover St Lakewood CO 80215",
    "addr:housenumber":"1550",
    "addr:postcode":"80215",
    "addr:street":"Dover St",
    "iso:country":"US",
    "sg:address":"1550 Dover St",
    "sg:city":"Lakewood",
    "sg:classifiers":[
        {
            "category":"Professional",
            "subcategory":"Engineering",
            "type":"Services"
        }
    ],
    "sg:phone":"+1 303 232 6200",
    "sg:postcode":"80215",
    "sg:province":"CO",
    "sg:tags":[
        "engineer"
    ],
    "sg:website":"www.catorruma.com",
    "wof:name":"Cator Ruma & Assoc",
    "wof:placetype":"venue"
},
  "geometry": {"coordinates":[-105.093028,39.741461],"type":"Point"}
}