{
  "type": "Feature",
  "properties": {
    "iso:country":"US",
    "sg:address":"2885 Aurora Ave",
    "sg:city":"Boulder",
    "sg:classifiers":[
        {
            "category":"Professional",
            "subcategory":"Art Services",
            "type":"Services"
        }
    ],
    "sg:phone":"+1 303 541 0838",
    "sg:postcode":"80303",
    "sg:province":"CO",
    "sg:tags":[
        "graphic",
        "designer"
    ],
    "wof:name":"Bradford Creative",
    "wof:placetype":"venue"
},
  "geometry": {"coordinates":[-105.257701,40.00381],"type":"Point"}
}