{
  "type": "Feature",
  "properties": {
    "iso:country":"US",
    "sg:address":"2875 Chickaree Pl SW",
    "sg:city":"Loveland",
    "sg:classifiers":[
        {
            "category":"Banks & Credit Unions",
            "subcategory":"Bank",
            "type":"Services"
        }
    ],
    "sg:phone":"+1 970 461 0799",
    "sg:postcode":"80537",
    "sg:province":"CO",
    "sg:tags":[
        "mortgage"
    ],
    "wof:name":"Page Prudential Huntoon",
    "wof:placetype":"venue"
},
  "geometry": {"coordinates":[-105.117074,40.385863],"type":"Point"}
}