{
  "type": "Feature",
  "properties": {
    "iso:country":"US",
    "sg:address":"6467 W Colfax Ave",
    "sg:city":"Denver",
    "sg:classifiers":[
        {
            "category":"Manufacturing",
            "subcategory":"Printing",
            "type":"Manufacturing & Wholesale Goods"
        }
    ],
    "sg:phone":"+1 303 237 7694",
    "sg:postcode":"80214",
    "sg:province":"CO",
    "sg:tags":[
        "printer",
        "commercial"
    ],
    "wof:name":"Super Express Printing Inc",
    "wof:placetype":"venue"
},
  "geometry": {"coordinates":[-105.06900400000001,39.740413],"type":"Point"}
}