{
  "type": "Feature",
  "properties": {
    "addr:full":"442 S Mc Culloch Blvd Pueblo CO 81007",
    "addr:housenumber":"442",
    "addr:postcode":"81007",
    "addr:street":"S Mc Culloch Blvd",
    "iso:country":"US",
    "sg:address":"442 S Mc Culloch Blvd",
    "sg:city":"Pueblo",
    "sg:classifiers":[
        {
            "category":"Shopping",
            "type":"Retail Goods"
        }
    ],
    "sg:phone":"+1 719 547 8742",
    "sg:postcode":"81007",
    "sg:province":"CO",
    "sg:tags":[
        "merchandise"
    ],
    "wof:name":"Luceros Trophy Emporium",
    "wof:placetype":"venue"
},
  "geometry": {"coordinates":[-104.76517800000001,38.300263],"type":"Point"}
}