{
  "type": "Feature",
  "properties": {
    "addr:full":"1115 W 10th Avenue Denver CO 80204",
    "addr:housenumber":"1115",
    "addr:postcode":"80204",
    "addr:street":"W 10Th Avenue",
    "iso:country":"US",
    "sg:address":"1115 W 10th Avenue",
    "sg:city":"Denver",
    "sg:classifiers":[
        {
            "category":"Animal Shelter",
            "type":"Public Place"
        },
        {
            "category":"Shopping",
            "subcategory":"Pets & Pet Supplies",
            "type":"Retail Goods"
        }
    ],
    "sg:phone":"+1 303 623 6851",
    "sg:postcode":"80204",
    "sg:province":"CO",
    "sg:tags":[
        "store"
    ],
    "wof:name":"A Emergency Tree Service",
    "wof:placetype":"venue"
},
  "geometry": {"coordinates":[-105.00052100000001,39.731987],"type":"Point"}
}