{
  "type": "Feature",
  "properties": {
    "addr:full":"4700 Boardwalk Dr Fort Collins CO 80525",
    "addr:housenumber":"4700",
    "addr:postcode":"80525",
    "addr:street":"Boardwalk Dr",
    "iso:country":"US",
    "sg:address":"4700 Boardwalk Dr",
    "sg:city":"Fort Collins",
    "sg:classifiers":[
        {
            "category":"Utilities",
            "subcategory":"Mobile Phone",
            "type":"Services"
        }
    ],
    "sg:phone":"+1 970 225 0539",
    "sg:postcode":"80525",
    "sg:province":"CO",
    "sg:tags":[
        "cellular"
    ],
    "wof:name":"Wireless Retail",
    "wof:placetype":"venue"
},
  "geometry": {"coordinates":[-105.065291,40.522276],"type":"Point"}
}