{
  "type": "Feature",
  "properties": {
    "addr:full":"4650 Blackhawk Way Denver CO 80239",
    "addr:housenumber":"4650",
    "addr:postcode":"80239",
    "addr:street":"Blackhawk Way",
    "iso:country":"US",
    "sg:address":"4650 Blackhawk Way",
    "sg:city":"Denver",
    "sg:classifiers":[
        {
            "category":"Building & Trades",
            "subcategory":"Construction",
            "type":"Services"
        }
    ],
    "sg:phone":"+1 303 525 7890",
    "sg:postcode":"80239",
    "sg:province":"CO",
    "sg:tags":[
        "house"
    ],
    "wof:name":"Works By Yogi",
    "wof:placetype":"venue"
},
  "geometry": {"coordinates":[-104.832427,39.780362],"type":"Point"}
}