{
  "type": "Feature",
  "properties": {
    "addr:full":"1624 Foothills Dr S Golden CO 80401",
    "addr:housenumber":"1624",
    "addr:postcode":"80401",
    "addr:street":"Foothills Dr S",
    "iso:country":"US",
    "sg:address":"1624 Foothills Dr S",
    "sg:city":"Golden",
    "sg:classifiers":[
        {
            "category":"Banks & Credit Unions",
            "subcategory":"Investment Brokerage",
            "type":"Services"
        },
        {
            "category":"Banks & Credit Unions",
            "subcategory":"Bank",
            "type":"Services"
        }
    ],
    "sg:phone":"+1 303 526 9696",
    "sg:postcode":"80401",
    "sg:province":"CO",
    "sg:tags":[
        "institution",
        "business"
    ],
    "wof:name":"Regenesis Group LLC",
    "wof:placetype":"venue"
},
  "geometry": {"coordinates":[-105.27874799999999,39.685375],"type":"Point"}
}