{
  "type": "Feature",
  "properties": {
    "iso:country":"US",
    "sg:address":"1312 Elm St",
    "sg:city":"Denver",
    "sg:classifiers":[
        {
            "category":"Banks & Credit Unions",
            "subcategory":"Financial Services",
            "type":"Services"
        }
    ],
    "sg:phone":"+1 303 300 6610",
    "sg:postcode":"80220",
    "sg:province":"CO",
    "sg:tags":[
        "investor"
    ],
    "wof:name":"Bredeblue Investments LLC",
    "wof:placetype":"venue"
},
  "geometry": {"coordinates":[-104.929152,39.738072],"type":"Point"}
}