{
  "type": "Feature",
  "properties": {
    "iso:country":"US",
    "sg:address":"20209 E Smoky Hill Rd",
    "sg:city":"Centennial",
    "sg:classifiers":[
        {
            "category":"Cinema",
            "subcategory":"Movie Rental",
            "type":"Entertainment"
        }
    ],
    "sg:phone":"+1 303 400 1755",
    "sg:postcode":"80015",
    "sg:province":"CO",
    "sg:tags":[
        "leasing",
        "video",
        "disc",
        "tape"
    ],
    "wof:name":"Hollywood Video",
    "wof:placetype":"venue"
},
  "geometry": {"coordinates":[-104.752059,39.610703],"type":"Point"}
}