{
  "type": "Feature",
  "properties": {
    "addr:full":"1607 Grand Ave Glenwood Springs CO 81601",
    "addr:housenumber":"1607",
    "addr:postcode":"81601",
    "addr:street":"Grand Ave",
    "iso:country":"US",
    "sg:address":"1607 Grand Ave",
    "sg:city":"Glenwood Springs",
    "sg:classifiers":[
        {
            "category":"Professional",
            "subcategory":"Business Services",
            "type":"Services"
        }
    ],
    "sg:phone":"+1 970 945 0150",
    "sg:postcode":"81601",
    "sg:province":"CO",
    "wof:name":"Juliann Gornick Bus Svc Inc",
    "wof:placetype":"venue"
},
  "geometry": {"coordinates":[-107.32511100000001,39.53832],"type":"Point"}
}