{
  "type": "Feature",
  "properties": {
    "addr:full":"2740 Canyon Heights Rd Pueblo CO 81005",
    "addr:housenumber":"2740",
    "addr:postcode":"81005",
    "addr:street":"Canyon Heights Rd",
    "iso:country":"US",
    "sg:address":"2740 Canyon Heights Rd",
    "sg:city":"Pueblo",
    "sg:classifiers":[
        {
            "category":"Insurance",
            "subcategory":"Insurance Agent",
            "type":"Services"
        }
    ],
    "sg:phone":"+1 719 485 2891",
    "sg:postcode":"81005",
    "sg:province":"CO",
    "wof:name":"Brown Insurance",
    "wof:placetype":"venue"
},
  "geometry": {"coordinates":[-104.92967299999999,38.150229],"type":"Point"}
}