{
  "type": "Feature",
  "properties": {
    "addr:full":"391 E Davies Ave Centennial CO 80122",
    "addr:housenumber":"391",
    "addr:postcode":"80122",
    "addr:street":"E Davies Ave",
    "iso:country":"US",
    "sg:address":"391 E Davies Ave",
    "sg:city":"Centennial",
    "sg:classifiers":[
        {
            "category":"Professional",
            "type":"Services"
        }
    ],
    "sg:phone":"+1 303 798 5503",
    "sg:postcode":"80122",
    "sg:province":"CO",
    "sg:tags":[
        "establishment"
    ],
    "wof:name":"Quiet Quiet",
    "wof:placetype":"venue"
},
  "geometry": {"coordinates":[-104.98381000000001,39.589316],"type":"Point"}
}