{
  "type": "Feature",
  "properties": {
    "iso:country":"US",
    "sg:address":"5616 S Gibraltar Way",
    "sg:city":"Centennial",
    "sg:classifiers":[
        {
            "category":"Restaurant",
            "type":"Food & Drink"
        }
    ],
    "sg:phone":"+1 303 766 9019",
    "sg:postcode":"80015",
    "sg:province":"CO",
    "wof:name":"Simply Dinner",
    "wof:placetype":"venue"
},
  "geometry": {"coordinates":[-104.755094,39.615326],"type":"Point"}
}