{
  "type": "Feature",
  "properties": {
    "addr:full":"7780 W Jewell Ave Lakewood CO 80232",
    "addr:housenumber":"7780",
    "addr:postcode":"80232",
    "addr:street":"W Jewell Ave",
    "iso:country":"US",
    "sg:address":"7780 W Jewell Ave",
    "sg:city":"Lakewood",
    "sg:classifiers":[
        {
            "category":"Building & Trades",
            "subcategory":"Locksmith",
            "type":"Services"
        }
    ],
    "sg:phone":"+1 303 928 1086",
    "sg:postcode":"80232",
    "sg:province":"CO",
    "sg:tags":[
        "key"
    ],
    "wof:name":"AAA 24 7 Advanced Locksmith",
    "wof:placetype":"venue"
},
  "geometry": {"coordinates":[-105.082801,39.682029],"type":"Point"}
}