{
  "type": "Feature",
  "properties": {
    "iso:country":"US",
    "sg:address":"2460 W 26th Ave, Ste 120C",
    "sg:city":"Denver",
    "sg:classifiers":[
        {
            "category":"Real Estate",
            "subcategory":"Real Estate Agent",
            "type":"Services"
        }
    ],
    "sg:phone":"+1 303 289 7009",
    "sg:postcode":"80211",
    "sg:province":"CO",
    "sg:website":"iregroup.com",
    "wof:name":"Innovative Real Estate Group",
    "wof:placetype":"venue"
},
  "geometry": {"coordinates":[-105.017236,39.754821],"type":"Point"}
}