{
  "type": "Feature",
  "properties": {
    "addr:full":"725 S Broadway Denver CO 80210",
    "addr:housenumber":"725",
    "addr:postcode":"80210",
    "addr:street":"S Broadway",
    "iso:country":"US",
    "sg:address":"725 S Broadway",
    "sg:city":"Denver",
    "sg:classifiers":[
        {
            "category":"Education",
            "subcategory":"School",
            "type":"Public Place"
        }
    ],
    "sg:phone":"+1 303 302 2200",
    "sg:postcode":"80210",
    "sg:province":"CO",
    "wof:name":"High Wire Media",
    "wof:placetype":"venue"
},
  "geometry": {"coordinates":[-104.98757000000001,39.702565],"type":"Point"}
}