{
  "type": "Feature",
  "properties": {
    "addr:full":"723 Wilcox Street Castle Rock CO 80104",
    "addr:housenumber":"723",
    "addr:postcode":"80104",
    "addr:street":"Wilcox Street",
    "iso:country":"US",
    "sg:address":"723 Wilcox Street",
    "sg:city":"Castle Rock",
    "sg:classifiers":[
        {
            "category":"Personal",
            "subcategory":"Beauty Salon",
            "type":"Services"
        }
    ],
    "sg:phone":"+1 720 733 0730",
    "sg:postcode":"80104",
    "sg:province":"CO",
    "sg:tags":[
        "hair"
    ],
    "wof:name":"Hair On the Rock",
    "wof:placetype":"venue"
},
  "geometry": {"coordinates":[-104.859928,39.376791],"type":"Point"}
}