{
  "type": "Feature",
  "properties": {
    "iso:country":"US",
    "sg:address":"4853 N Academy Blvd",
    "sg:city":"Colorado Springs",
    "sg:classifiers":[
        {
            "category":"Retail",
            "subcategory":"Laundry & Dry Cleaning",
            "type":"Services"
        }
    ],
    "sg:phone":"+1 719 528 6166",
    "sg:postcode":"80918",
    "sg:province":"CO",
    "sg:tags":[
        "cleaners"
    ],
    "wof:name":"JSK Cleaners",
    "wof:placetype":"venue"
},
  "geometry": {"coordinates":[-104.771227,38.9027],"type":"Point"}
}