{
  "type": "Feature",
  "properties": {
    "iso:country":"US",
    "sg:address":"27198 E 75th Ave",
    "sg:city":"Denver",
    "sg:classifiers":[
        {
            "category":"Wholesale",
            "subcategory":"Machinery & Supplies",
            "type":"Manufacturing & Wholesale Goods"
        }
    ],
    "sg:phone":"+1 303 371 2360",
    "sg:postcode":"80249",
    "sg:province":"CO",
    "sg:tags":[
        "equipment",
        "industrial"
    ],
    "wof:name":"Grainger Inc",
    "wof:placetype":"venue"
},
  "geometry": {"coordinates":[-104.671648,39.833156],"type":"Point"}
}