{
  "type": "Feature",
  "properties": {
    "addr:full":"18790 E Oregon Dr Aurora CO 80017",
    "addr:housenumber":"18790",
    "addr:postcode":"80017",
    "addr:street":"E Oregon Dr",
    "iso:country":"US",
    "sg:address":"18790 E Oregon Dr",
    "sg:city":"Aurora",
    "sg:classifiers":[
        {
            "category":"Building & Trades",
            "subcategory":"Construction",
            "type":"Services"
        }
    ],
    "sg:phone":"+1 303 369 6819",
    "sg:postcode":"80017",
    "sg:province":"CO",
    "sg:tags":[
        "house",
        "improvement",
        "home"
    ],
    "wof:name":"Visions Home Improvements Inc",
    "wof:placetype":"venue"
},
  "geometry": {"coordinates":[-104.768512,39.68577],"type":"Point"}
}