{
  "type": "Feature",
  "properties": {
    "iso:country":"US",
    "sg:address":"420 Ridge Trl",
    "sg:city":"Grand Junction",
    "sg:classifiers":[
        {
            "category":"Building & Trades",
            "subcategory":"Construction",
            "type":"Services"
        }
    ],
    "sg:phone":"+1 970 523 9100",
    "sg:postcode":"81504",
    "sg:province":"CO",
    "sg:tags":[
        "nonresidential"
    ],
    "wof:name":"C&S Contracting",
    "wof:placetype":"venue"
},
  "geometry": {"coordinates":[-108.47923,39.064739],"type":"Point"}
}