{
  "type": "Feature",
  "properties": {
    "addr:full":"1515 9th St Rock Springs CO 82901",
    "addr:housenumber":"1515",
    "addr:postcode":"82901",
    "addr:street":"9Th St",
    "iso:country":"US",
    "sg:address":"1515 9th St",
    "sg:city":"Rock Springs",
    "sg:classifiers":[
        {
            "category":"Mining & Drilling",
            "type":"Manufacturing & Wholesale Goods"
        }
    ],
    "sg:phone":"+1 307 352 5190",
    "sg:postcode":"82901",
    "sg:province":"CO",
    "sg:tags":[
        "crude",
        "production",
        "gas"
    ],
    "wof:name":"Texaco Enp Producing Inc",
    "wof:placetype":"venue"
},
  "geometry": {"coordinates":[-109.206912,41.597895],"type":"Point"}
}