{
  "type": "Feature",
  "properties": {
    "iso:country":"US",
    "sg:address":"130 W Denver St",
    "sg:city":"Holyoke",
    "sg:classifiers":[
        {
            "category":"Restaurant",
            "type":"Food & Drink"
        }
    ],
    "sg:phone":"+1 970 854 2150",
    "sg:postcode":"80734",
    "sg:province":"CO",
    "wof:name":"Skillet",
    "wof:placetype":"venue"
},
  "geometry": {"coordinates":[-102.302922,40.585571],"type":"Point"}
}