{
  "type": "Feature",
  "properties": {
    "iso:country":"US",
    "sg:address":"22725 E Maplewood Ln",
    "sg:city":"Aurora",
    "sg:classifiers":[
        {
            "category":"Communications",
            "subcategory":"Film & Video Production",
            "type":"Services"
        }
    ],
    "sg:phone":"+1 303 451 5443",
    "sg:postcode":"80015",
    "sg:province":"CO",
    "sg:tags":[
        "taping"
    ],
    "wof:name":"Colorado Weddings",
    "wof:placetype":"venue"
},
  "geometry": {"coordinates":[-104.7251,39.605194],"type":"Point"}
}