{
  "type": "Feature",
  "properties": {
    "iso:country":"US",
    "sg:address":"41152 Needle Rock Rd",
    "sg:city":"Crawford",
    "sg:classifiers":[
        {
            "category":"Freight",
            "type":"Transportation"
        }
    ],
    "sg:phone":"+1 970 921 5857",
    "sg:postcode":"81415",
    "sg:province":"CO",
    "sg:tags":[
        "general"
    ],
    "wof:name":"Horse Back Riding",
    "wof:placetype":"venue"
},
  "geometry": {"coordinates":[-107.58790999999999,38.713363],"type":"Point"}
}