{
  "type": "Feature",
  "properties": {
    "addr:full":"10045 US Hwy 50 Poncha Springs CO 81242",
    "addr:housenumber":"10045",
    "addr:postcode":"81242",
    "addr:street":"Us Hwy 50 Poncha Springs Co",
    "iso:country":"US",
    "sg:address":"10045 US Hwy 50",
    "sg:city":"Poncha Springs",
    "sg:classifiers":[
        {
            "category":"Health Services",
            "subcategory":"Chiropractor",
            "type":"Services"
        }
    ],
    "sg:phone":"+1 719 539 7775",
    "sg:postcode":"81242",
    "sg:province":"CO",
    "wof:name":"Helland Chiropractic Clinic",
    "wof:placetype":"venue"
},
  "geometry": {"coordinates":[-106.07017,38.515428],"type":"Point"}
}