{
  "type": "Feature",
  "properties": {
    "addr:full":"679 E 2nd Ave Durango CO 81301",
    "addr:housenumber":"679",
    "addr:postcode":"co 81301",
    "addr:street":"E 2Nd Ave",
    "iso:country":"US",
    "sg:address":"679 E 2nd Ave",
    "sg:city":"Durango",
    "sg:classifiers":[
        {
            "category":"Real Estate",
            "subcategory":"Real Estate Agent",
            "type":"Services"
        }
    ],
    "sg:phone":"+1 970 259 5612",
    "sg:postcode":"81301",
    "sg:province":"CO",
    "sg:tags":[
        "management"
    ],
    "sg:website":"www.durangorentals.com",
    "wof:name":"Durango Property Management",
    "wof:placetype":"venue"
},
  "geometry": {"coordinates":[-107.880393,37.270125],"type":"Point"}
}