{
  "type": "Feature",
  "properties": {
    "iso:country":"US",
    "sg:address":"1650 16th St",
    "sg:city":"Greeley",
    "sg:classifiers":[
        {
            "category":"Professional",
            "type":"Services"
        }
    ],
    "sg:phone":"+1 970 353 9843",
    "sg:postcode":"80631",
    "sg:province":"CO",
    "sg:tags":[
        "establishment"
    ],
    "wof:name":"North Colorado",
    "wof:placetype":"venue"
},
  "geometry": {"coordinates":[-104.707725,40.413759],"type":"Point"}
}