{
  "type": "Feature",
  "properties": {
    "iso:country":"US",
    "sg:address":"1900 Downing St",
    "sg:city":"Denver",
    "sg:classifiers":[
        {
            "category":"Education",
            "subcategory":"School",
            "type":"Public Place"
        }
    ],
    "sg:phone":"+1 303 839 5076",
    "sg:postcode":"80218",
    "sg:province":"CO",
    "wof:name":"Boettcher School",
    "wof:placetype":"venue"
},
  "geometry": {"coordinates":[-104.973314,39.744852],"type":"Point"}
}