{
  "type": "Feature",
  "properties": {
    "iso:country":"US",
    "sg:address":"1560 S. Broadway",
    "sg:city":"Denver",
    "sg:classifiers":[
        {
            "category":"Arts & Performance",
            "subcategory":"Art Gallery",
            "type":"Entertainment"
        }
    ],
    "sg:phone":"+1 303 333 6700",
    "sg:postcode":"80210",
    "sg:province":"CO",
    "sg:website":"www.hendrixart.com/",
    "wof:name":"Brenda Hendrix Studio & Gallery",
    "wof:placetype":"venue"
},
  "geometry": {"coordinates":[-104.987521,39.688289],"type":"Point"}
}