{
  "type": "Feature",
  "properties": {
    "addr:full":"1900 E Pikes Peak Ave Colorado Springs CO 80909",
    "addr:housenumber":"1900",
    "addr:postcode":"80909",
    "addr:street":"E Pikes Peak Ave",
    "iso:country":"US",
    "sg:address":"1900 E Pikes Peak Ave",
    "sg:city":"Colorado Springs",
    "sg:classifiers":[
        {
            "category":"Health Services",
            "subcategory":"Podiatrist",
            "type":"Services"
        }
    ],
    "sg:phone":"+1 719 473 1828",
    "sg:postcode":"80909",
    "sg:province":"CO",
    "wof:name":"Stanton C Southward DPM",
    "wof:placetype":"venue"
},
  "geometry": {"coordinates":[-104.79253,38.832877],"type":"Point"}
}