{
  "type": "Feature",
  "properties": {
    "iso:country":"US",
    "sg:address":"9151 S Princeton St",
    "sg:city":"Littleton",
    "sg:classifiers":[
        {
            "category":"Manufacturing",
            "subcategory":"Tools & Machinery",
            "type":"Manufacturing & Wholesale Goods"
        },
        {
            "category":"Mining & Drilling",
            "type":"Manufacturing & Wholesale Goods"
        }
    ],
    "sg:phone":"+1 303 471 5573",
    "sg:postcode":"80130",
    "sg:province":"CO",
    "sg:tags":[
        "company",
        "mfg"
    ],
    "wof:name":"Taurus Resources USA Inc",
    "wof:placetype":"venue"
},
  "geometry": {"coordinates":[-104.914075,39.550127],"type":"Point"}
}