{
  "type": "Feature",
  "properties": {
    "iso:country":"US",
    "sg:address":"7671 King St",
    "sg:city":"Westminster",
    "sg:classifiers":[
        {
            "category":"Building & Trades",
            "subcategory":"Construction",
            "type":"Services"
        }
    ],
    "sg:phone":"+1 303 428 8849",
    "sg:postcode":"80030",
    "sg:province":"CO",
    "sg:tags":[
        "screen",
        "enclosure"
    ],
    "wof:name":"Carpenter Screen Repairing Svc",
    "wof:placetype":"venue"
},
  "geometry": {"coordinates":[-105.033226,39.835825],"type":"Point"}
}