{
  "type": "Feature",
  "properties": {
    "addr:full":"5113 Jellison St Arvada CO 80002",
    "addr:housenumber":"5113",
    "addr:postcode":"80002",
    "addr:street":"Jellison St",
    "iso:country":"US",
    "sg:address":"5113 Jellison St",
    "sg:city":"Arvada",
    "sg:classifiers":[
        {
            "category":"Professional",
            "subcategory":"Business Services",
            "type":"Services"
        }
    ],
    "sg:phone":"+1 303 423 2055",
    "sg:postcode":"80002",
    "sg:province":"CO",
    "wof:name":"St Clair Group LLC",
    "wof:placetype":"venue"
},
  "geometry": {"coordinates":[-105.10683400000001,39.791789],"type":"Point"}
}