{
  "type": "Feature",
  "properties": {
    "iso:country":"US",
    "sg:address":"15 Gloria Pl",
    "sg:city":"Crested Butte",
    "sg:classifiers":[
        {
            "category":"Professional",
            "subcategory":"Business Services",
            "type":"Services"
        }
    ],
    "sg:phone":"+1 970 349 5762",
    "sg:postcode":"81224",
    "sg:province":"CO",
    "sg:tags":[
        "interior",
        "consultant",
        "design",
        "decorator"
    ],
    "wof:name":"Interiors West",
    "wof:placetype":"venue"
},
  "geometry": {"coordinates":[-106.890226,38.823471],"type":"Point"}
}