{
  "type": "Feature",
  "properties": {
    "addr:full":"1776 Grant St Denver CO 80203",
    "addr:housenumber":"1776",
    "addr:postcode":"80203",
    "addr:street":"Grant St",
    "iso:country":"US",
    "sg:address":"1776 Grant St",
    "sg:city":"Denver",
    "sg:classifiers":[
        {
            "category":"Travel",
            "subcategory":"Hotels & Motels",
            "type":"Entertainment"
        },
        {
            "category":"Restaurant",
            "type":"Food & Drink"
        }
    ],
    "sg:phone":"+1 303 861 2000",
    "sg:postcode":"80203",
    "sg:province":"CO",
    "sg:website":"www.warwickdenver.com",
    "wof:name":"Warwick Hotel",
    "wof:placetype":"venue"
},
  "geometry": {"coordinates":[-104.983374,39.744401],"type":"Point"}
}