{
  "type": "Feature",
  "properties": {
    "iso:country":"US",
    "sg:address":"6755 Earl Dr",
    "sg:city":"Colorado Springs",
    "sg:classifiers":[
        {
            "category":"Building & Trades",
            "subcategory":"Construction",
            "type":"Services"
        }
    ],
    "sg:phone":"+1 719 596 3414",
    "sg:postcode":"80918",
    "sg:province":"CO",
    "sg:tags":[
        "contractor"
    ],
    "wof:name":"CJ Roofing Company",
    "wof:placetype":"venue"
},
  "geometry": {"coordinates":[-104.796572,38.928967],"type":"Point"}
}