{
  "type": "Feature",
  "properties": {
    "addr:full":"927 Park St Castle Rock CO 80109",
    "addr:housenumber":"927",
    "addr:postcode":"80109",
    "addr:street":"Park St",
    "iso:country":"US",
    "sg:address":"927 Park St",
    "sg:city":"Castle Rock",
    "sg:classifiers":[
        {
            "category":"Banks & Credit Unions",
            "subcategory":"Financial Services",
            "type":"Services"
        }
    ],
    "sg:phone":"+1 303 663 2225",
    "sg:postcode":"80109",
    "sg:province":"CO",
    "sg:tags":[
        "investment",
        "market",
        "stock"
    ],
    "wof:name":"Castle Rock Trading Company",
    "wof:placetype":"venue"
},
  "geometry": {"coordinates":[-104.865967,39.379642],"type":"Point"}
}