{
  "type": "Feature",
  "properties": {
    "iso:country":"US",
    "sg:address":"1020 Grand Ave",
    "sg:city":"Grand Junction",
    "sg:classifiers":[
        {
            "category":"Social Services",
            "subcategory":"Adult Care",
            "type":"Services"
        }
    ],
    "sg:phone":"+1 970 244 8882",
    "sg:postcode":"81501",
    "sg:province":"CO",
    "sg:tags":[
        "elementary",
        "residential",
        "rehabilitation",
        "center"
    ],
    "wof:name":"Youthtrack Inc",
    "wof:placetype":"venue"
},
  "geometry": {"coordinates":[-108.554616,39.070394],"type":"Point"}
}