{
  "type": "Feature",
  "properties": {
    "addr:full":"8300 Fairmount Dr Denver CO 80247",
    "addr:housenumber":"8300",
    "addr:postcode":"80247",
    "addr:street":"Fairmount Dr",
    "iso:country":"US",
    "sg:address":"8300 Fairmount Dr",
    "sg:city":"Denver",
    "sg:classifiers":[
        {
            "category":"Insurance",
            "subcategory":"Insurance Agent",
            "type":"Services"
        }
    ],
    "sg:phone":"+1 303 596 0252",
    "sg:postcode":"80247",
    "sg:province":"CO",
    "wof:name":"Scott Cain Insurance Brkg",
    "wof:placetype":"venue"
},
  "geometry": {"coordinates":[-104.892914,39.711307],"type":"Point"}
}