{
  "type": "Feature",
  "properties": {
    "iso:country":"US",
    "sg:address":"1711 W Barberry Cir",
    "sg:city":"Louisville",
    "sg:classifiers":[
        {
            "category":"Communications",
            "subcategory":"Film & Video Production",
            "type":"Services"
        }
    ],
    "sg:phone":"+1 303 665 8701",
    "sg:postcode":"80027",
    "sg:province":"CO",
    "sg:tags":[
        "taping"
    ],
    "wof:name":"R T Editing",
    "wof:placetype":"venue"
},
  "geometry": {"coordinates":[-105.15966400000001,39.988177],"type":"Point"}
}