{
  "type": "Feature",
  "properties": {
    "addr:full":"6632 Fig St Arvada CO 80004",
    "addr:housenumber":"6632",
    "addr:postcode":"80004",
    "addr:street":"Fig St",
    "iso:country":"US",
    "sg:address":"6632 Fig St",
    "sg:city":"Arvada",
    "sg:classifiers":[
        {
            "category":"Wholesale",
            "subcategory":"Hardware",
            "type":"Manufacturing & Wholesale Goods"
        }
    ],
    "sg:phone":"+1 303 425 9608",
    "sg:postcode":"80004",
    "sg:province":"CO",
    "sg:tags":[
        "tool"
    ],
    "wof:name":"Snap-On Tools Co",
    "wof:placetype":"venue"
},
  "geometry": {"coordinates":[-105.15830699999999,39.818637],"type":"Point"}
}