{
  "type": "Feature",
  "properties": {
    "addr:full":"1873 Tynan Dr Erie CO 80516",
    "addr:housenumber":"1873",
    "addr:postcode":"80516",
    "addr:street":"Tynan Dr",
    "iso:country":"US",
    "sg:address":"1873 Tynan Dr",
    "sg:city":"Erie",
    "sg:classifiers":[
        {
            "category":"Restaurant",
            "type":"Food & Drink"
        }
    ],
    "sg:phone":"+1 303 828 1333",
    "sg:postcode":"80516",
    "sg:province":"CO",
    "sg:tags":[
        "delicatessen"
    ],
    "wof:name":"Briggs St Works",
    "wof:placetype":"venue"
},
  "geometry": {"coordinates":[-105.072391,40.041894],"type":"Point"}
}