{
  "type": "Feature",
  "properties": {
    "iso:country":"US",
    "sg:address":"15155 E 46th Ave",
    "sg:city":"Denver",
    "sg:classifiers":[
        {
            "category":"Building & Trades",
            "subcategory":"Plumbing",
            "type":"Services"
        }
    ],
    "sg:phone":"+1 303 375 9536",
    "sg:postcode":"80239",
    "sg:province":"CO",
    "sg:tags":[
        "contractor"
    ],
    "wof:name":"AA Heating",
    "wof:placetype":"venue"
},
  "geometry": {"coordinates":[-104.81160300000001,39.776936],"type":"Point"}
}