{
  "type": "Feature",
  "properties": {
    "addr:full":"1840 Oak Ave Boulder CO 80304",
    "addr:housenumber":"1840",
    "addr:postcode":"80304",
    "addr:street":"Oak Ave",
    "iso:country":"US",
    "sg:address":"1840 Oak Ave",
    "sg:city":"Boulder",
    "sg:classifiers":[
        {
            "category":"Shopping",
            "type":"Retail Goods"
        }
    ],
    "sg:phone":"+1 303 444 2664",
    "sg:postcode":"80304",
    "sg:province":"CO",
    "sg:tags":[
        "miscellaneous",
        "store"
    ],
    "wof:name":"Collapsible Calendars",
    "wof:placetype":"venue"
},
  "geometry": {"coordinates":[-105.274635,40.044802],"type":"Point"}
}