{
  "type": "Feature",
  "properties": {
    "iso:country":"US",
    "sg:address":"1754 Blake St",
    "sg:city":"Denver",
    "sg:classifiers":[
        {
            "category":"Banks & Credit Unions",
            "subcategory":"Bank",
            "type":"Services"
        }
    ],
    "sg:phone":"+1 303 458 7400",
    "sg:postcode":"80202",
    "sg:province":"CO",
    "sg:tags":[
        "broker",
        "mortgage"
    ],
    "wof:name":"PSI Financial Corporation",
    "wof:placetype":"venue"
},
  "geometry": {"coordinates":[-104.997269,39.75184],"type":"Point"}
}