{
  "type": "Feature",
  "properties": {
    "addr:full":"6214 S Tempe Way Aurora CO 80015",
    "addr:housenumber":"6214",
    "addr:postcode":"80015",
    "addr:street":"S Tempe Way",
    "iso:country":"US",
    "sg:address":"6214 S Tempe Way",
    "sg:city":"Aurora",
    "sg:classifiers":[
        {
            "category":"Professional",
            "subcategory":"Management & Consulting",
            "type":"Services"
        }
    ],
    "sg:phone":"+1 720 870 6649",
    "sg:postcode":"80015",
    "sg:province":"CO",
    "sg:tags":[
        "personnel",
        "consultant"
    ],
    "wof:name":"Qwik Staff",
    "wof:placetype":"venue"
},
  "geometry": {"coordinates":[-104.725307,39.603904],"type":"Point"}
}