{
  "type": "Feature",
  "properties": {
    "addr:full":"1775 S 8th St Colorado Springs CO 80906",
    "addr:housenumber":"1775",
    "addr:postcode":"80906",
    "addr:street":"S 8Th St",
    "iso:country":"US",
    "sg:address":"1775 S 8th St",
    "sg:city":"Colorado Springs",
    "sg:classifiers":[
        {
            "category":"Real Estate",
            "subcategory":"Real Estate Agent",
            "type":"Services"
        }
    ],
    "sg:phone":"+1 719 475 8020",
    "sg:postcode":"80906",
    "sg:province":"CO",
    "sg:tags":[
        "appraiser"
    ],
    "wof:name":"Mazolla Appraisal Svc",
    "wof:placetype":"venue"
},
  "geometry": {"coordinates":[-104.84075300000001,38.806654],"type":"Point"}
}