{
  "type": "Feature",
  "properties": {
    "addr:full":"9791 Brighton Rd Henderson CO 80640",
    "addr:housenumber":"9791",
    "addr:postcode":"80640",
    "addr:street":"Brighton Rd",
    "iso:country":"US",
    "sg:address":"9791 Brighton Rd",
    "sg:city":"Henderson",
    "sg:classifiers":[
        {
            "category":"Wholesale",
            "subcategory":"Machinery & Supplies",
            "type":"Manufacturing & Wholesale Goods"
        }
    ],
    "sg:phone":"+1 303 286 9282",
    "sg:postcode":"80640",
    "sg:province":"CO",
    "sg:tags":[
        "equipment",
        "industrial"
    ],
    "wof:name":"Windmill Construction Mchnry",
    "wof:placetype":"venue"
},
  "geometry": {"coordinates":[-104.89810300000001,39.873815],"type":"Point"}
}