{
  "type": "Feature",
  "properties": {
    "addr:full":"4067 Omer Rd Divide CO 80814",
    "addr:housenumber":"4067",
    "addr:postcode":"80814",
    "addr:street":"Omer Rd",
    "iso:country":"US",
    "sg:address":"4067 Omer Rd",
    "sg:city":"Divide",
    "sg:classifiers":[
        {
            "category":"Professional",
            "subcategory":"Management & Consulting",
            "type":"Services"
        }
    ],
    "sg:phone":"+1 719 687 2243",
    "sg:postcode":"80814",
    "sg:province":"CO",
    "sg:tags":[
        "business"
    ],
    "wof:name":"Eduscape",
    "wof:placetype":"venue"
},
  "geometry": {"coordinates":[-105.147694,38.998591],"type":"Point"}
}