{
  "type": "Feature",
  "properties": {
    "iso:country":"US",
    "sg:address":"15496 E 101st Pl",
    "sg:city":"Commerce City",
    "sg:classifiers":[
        {
            "category":"Banks & Credit Unions",
            "subcategory":"Bank",
            "type":"Services"
        }
    ],
    "sg:phone":"+1 303 287 3215",
    "sg:postcode":"80022",
    "sg:province":"CO",
    "sg:tags":[
        "short",
        "institution",
        "business"
    ],
    "wof:name":"IBC Funding",
    "wof:placetype":"venue"
},
  "geometry": {"coordinates":[-104.80686300000001,39.880464],"type":"Point"}
}