{
  "type": "Feature",
  "properties": {
    "addr:full":"678 King Street Denver CO 80204",
    "addr:housenumber":"678",
    "addr:postcode":"80204",
    "addr:street":"King Street",
    "iso:country":"US",
    "sg:address":"678 King Street",
    "sg:city":"Denver",
    "sg:classifiers":[
        {
            "category":"Education",
            "subcategory":"Preschool",
            "type":"Public Place"
        },
        {
            "category":"Education",
            "subcategory":"School",
            "type":"Public Place"
        }
    ],
    "sg:phone":"+1 303 629 6112",
    "sg:postcode":"80204",
    "sg:province":"CO",
    "sg:tags":[
        "elementary"
    ],
    "wof:name":"Rocky Mountain Ser Headstart",
    "wof:placetype":"venue"
},
  "geometry": {"coordinates":[-105.033563,39.727492],"type":"Point"}
}