{
  "type": "Feature",
  "properties": {
    "addr:full":"525 24th St Golden CO 80401",
    "addr:housenumber":"525",
    "addr:postcode":"80401",
    "addr:street":"24Th St",
    "iso:country":"US",
    "sg:address":"525 24th St",
    "sg:city":"Golden",
    "sg:classifiers":[
        {
            "category":"Sports & Exercise",
            "subcategory":"Bowling",
            "type":"Entertainment"
        }
    ],
    "sg:phone":"+1 303 279 7846",
    "sg:postcode":"80401",
    "sg:province":"CO",
    "sg:tags":[
        "center"
    ],
    "wof:name":"Golden Bowl",
    "wof:placetype":"venue"
},
  "geometry": {"coordinates":[-105.20982100000001,39.746862],"type":"Point"}
}