{
  "type": "Feature",
  "properties": {
    "iso:country":"US",
    "sg:address":"5315 Crystal St",
    "sg:city":"Denver",
    "sg:classifiers":[
        {
            "category":"Shopping",
            "subcategory":"Computers & Home Electronics",
            "type":"Retail Goods"
        }
    ],
    "sg:phone":"+1 303 375 1670",
    "sg:postcode":"80239",
    "sg:province":"CO",
    "wof:name":"Ibcc",
    "wof:placetype":"venue"
},
  "geometry": {"coordinates":[-104.82126,39.79176],"type":"Point"}
}