{
  "type": "Feature",
  "properties": {
    "addr:full":"5614 Newland Way Arvada CO 80002",
    "addr:housenumber":"5614",
    "addr:postcode":"80002",
    "addr:street":"Newland Way",
    "iso:country":"US",
    "sg:address":"5614 Newland Way",
    "sg:city":"Arvada",
    "sg:classifiers":[
        {
            "category":"Manufacturing",
            "subcategory":"Tools & Machinery",
            "type":"Manufacturing & Wholesale Goods"
        }
    ],
    "sg:phone":"+1 303 422 9397",
    "sg:postcode":"80002",
    "sg:province":"CO",
    "sg:tags":[
        "machine",
        "shop",
        "industrial",
        "mfg"
    ],
    "wof:name":"R E B Products Inc",
    "wof:placetype":"venue"
},
  "geometry": {"coordinates":[-105.070126,39.797426],"type":"Point"}
}