{
  "type": "Feature",
  "properties": {
    "iso:country":"US",
    "sg:address":"3213 Fairplay Ct",
    "sg:city":"Fort Collins",
    "sg:classifiers":[
        {
            "category":"Real Estate",
            "subcategory":"Real Estate Agent",
            "type":"Services"
        }
    ],
    "sg:phone":"+1 970 266 0343",
    "sg:postcode":"80526",
    "sg:province":"CO",
    "wof:name":"Ernst Appraisal Group Inc",
    "wof:placetype":"venue"
},
  "geometry": {"coordinates":[-105.090613,40.542593],"type":"Point"}
}