{
  "type": "Feature",
  "properties": {
    "iso:country":"US",
    "sg:address":"1110 W 95th Cir",
    "sg:city":"Denver",
    "sg:classifiers":[
        {
            "category":"Professional",
            "subcategory":"Computer Services",
            "type":"Services"
        }
    ],
    "sg:phone":"+1 303 426 8448",
    "sg:postcode":"80260",
    "sg:province":"CO",
    "sg:tags":[
        "repair"
    ],
    "wof:name":"Metro Office Resources Inc",
    "wof:placetype":"venue"
},
  "geometry": {"coordinates":[-105.00186100000001,39.87033],"type":"Point"}
}