{
  "type": "Feature",
  "properties": {
    "iso:country":"US",
    "sg:address":"2717 E Louisiana Ave",
    "sg:city":"Denver",
    "sg:classifiers":[
        {
            "category":"Recreation",
            "type":"Entertainment"
        }
    ],
    "sg:phone":"+1 303 733 9949",
    "sg:postcode":"80210",
    "sg:province":"CO",
    "sg:tags":[
        "amusement"
    ],
    "wof:name":"Simply Coaching",
    "wof:placetype":"venue"
},
  "geometry": {"coordinates":[-104.95359999999999,39.69303],"type":"Point"}
}