{
  "type": "Feature",
  "properties": {
    "iso:country":"US",
    "sg:address":"28577 Buffalo Park Rd",
    "sg:city":"Evergreen",
    "sg:classifiers":[
        {
            "category":"Home & Garden",
            "subcategory":"Home Furnishings",
            "type":"Retail Goods"
        }
    ],
    "sg:phone":"+1 303 679 2557",
    "sg:postcode":"80439",
    "sg:province":"CO",
    "sg:tags":[
        "venetian",
        "blind"
    ],
    "wof:name":"Colorado Blinds Of Evergreen",
    "wof:placetype":"venue"
},
  "geometry": {"coordinates":[-105.326472,39.625529],"type":"Point"}
}