{
  "type": "Feature",
  "properties": {
    "iso:country":"US",
    "sg:address":"53 E Mill St",
    "sg:city":"Bayfield",
    "sg:classifiers":[
        {
            "category":"Health Services",
            "subcategory":"Chiropractor",
            "type":"Services"
        }
    ],
    "sg:phone":"+1 970 884 2128",
    "sg:postcode":"81122",
    "sg:province":"CO",
    "wof:name":"Garcia Family Chiropractic",
    "wof:placetype":"venue"
},
  "geometry": {"coordinates":[-107.60004000000001,37.225395],"type":"Point"}
}