{
  "type": "Feature",
  "properties": {
    "iso:country":"US",
    "sg:address":"15 Lathyrus Ct",
    "sg:city":"Pueblo",
    "sg:classifiers":[
        {
            "category":"Building & Trades",
            "subcategory":"Construction",
            "type":"Services"
        }
    ],
    "sg:phone":"+1 719 544 6097",
    "sg:postcode":"81001",
    "sg:province":"CO",
    "sg:tags":[
        "residential"
    ],
    "wof:name":"Sierra Homes",
    "wof:placetype":"venue"
},
  "geometry": {"coordinates":[-104.588629,38.315805],"type":"Point"}
}