{
  "type": "Feature",
  "properties": {
    "addr:full":"1134 Manitou Ave Manitou Springs CO 80829",
    "addr:housenumber":"1134",
    "addr:postcode":"80829",
    "addr:street":"Manitou Ave",
    "iso:country":"US",
    "sg:address":"1134 Manitou Ave",
    "sg:city":"Manitou Springs",
    "sg:classifiers":[
        {
            "category":"Manufacturing",
            "subcategory":"Building Materials",
            "type":"Manufacturing & Wholesale Goods"
        }
    ],
    "sg:phone":"+1 719 685 4514",
    "sg:postcode":"80829",
    "sg:province":"CO",
    "sg:tags":[
        "mfg",
        "wood",
        "kitchen",
        "cabinet"
    ],
    "wof:name":"L J E Cabinet Maker Inc",
    "wof:placetype":"venue"
},
  "geometry": {"coordinates":[-104.9208,38.860459],"type":"Point"}
}