{
  "type": "Feature",
  "properties": {
    "addr:full":"1551 Larimer St Denver CO 80202",
    "addr:housenumber":"1551",
    "addr:postcode":"80202",
    "addr:street":"Larimer St",
    "iso:country":"US",
    "sg:address":"1551 Larimer St",
    "sg:city":"Denver",
    "sg:classifiers":[
        {
            "category":"Professional",
            "subcategory":"Management & Consulting",
            "type":"Services"
        }
    ],
    "sg:phone":"+1 303 893 3330",
    "sg:postcode":"80202",
    "sg:province":"CO",
    "sg:tags":[
        "consultant",
        "business"
    ],
    "wof:name":"Michael Smith & Assoc Inc",
    "wof:placetype":"venue"
},
  "geometry": {"coordinates":[-104.998012,39.74879],"type":"Point"}
}