{
  "type": "Feature",
  "properties": {
    "addr:full":"7411 E 19th Ave Denver CO 80220",
    "addr:housenumber":"7411",
    "addr:postcode":"80220",
    "addr:street":"E 19Th Ave",
    "iso:country":"US",
    "sg:address":"7411 E 19th Ave",
    "sg:city":"Denver",
    "sg:classifiers":[
        {
            "category":"Building & Trades",
            "subcategory":"Landscaping Services",
            "type":"Services"
        }
    ],
    "sg:phone":"+1 303 333 6168",
    "sg:postcode":"80220",
    "sg:province":"CO",
    "sg:tags":[
        "landscape"
    ],
    "wof:name":"Three Hundred Days of Sun LLC",
    "wof:placetype":"venue"
},
  "geometry": {"coordinates":[-104.901186,39.745691],"type":"Point"}
}