{
  "type": "Feature",
  "properties": {
    "addr:full":"661 E Kentucky Ave Denver CO 80209",
    "addr:housenumber":"661",
    "addr:postcode":"80209",
    "addr:street":"E Kentucky Ave",
    "iso:country":"US",
    "sg:address":"661 E Kentucky Ave",
    "sg:city":"Denver",
    "sg:classifiers":[
        {
            "category":"Retail",
            "subcategory":"Auto Repair",
            "type":"Services"
        }
    ],
    "sg:phone":"+1 303 691 0717",
    "sg:postcode":"80209",
    "sg:province":"CO",
    "sg:tags":[
        "oil",
        "change"
    ],
    "sg:website":"www.communityautorepairshop.com/",
    "wof:name":"Community Auto Repair",
    "wof:placetype":"venue"
},
  "geometry": {"coordinates":[-104.979697,39.700389],"type":"Point"}
}