{
  "type": "Feature",
  "properties": {
    "addr:full":"5290 E Yale Cir Denver CO 80222",
    "addr:housenumber":"5290",
    "addr:postcode":"80222",
    "addr:street":"E Yale Cir",
    "iso:country":"US",
    "sg:address":"5290 E Yale Cir",
    "sg:city":"Denver",
    "sg:classifiers":[
        {
            "category":"Shopping",
            "subcategory":"Pharmacy",
            "type":"Retail Goods"
        }
    ],
    "sg:phone":"+1 303 691 3377",
    "sg:postcode":"80222",
    "sg:province":"CO",
    "sg:tags":[
        "drugstore"
    ],
    "wof:name":"Pharmacy Resources",
    "wof:placetype":"venue"
},
  "geometry": {"coordinates":[-104.927397,39.667445],"type":"Point"}
}