{
  "type": "Feature",
  "properties": {
    "addr:full":"1526 Hwy 50 Delta CO 81416",
    "addr:housenumber":"1526",
    "addr:postcode":"81416",
    "addr:street":"Hwy 50",
    "iso:country":"US",
    "sg:address":"1526 Hwy 50",
    "sg:city":"Delta",
    "sg:classifiers":[
        {
            "category":"Retail",
            "subcategory":"Auto Repair",
            "type":"Services"
        }
    ],
    "sg:phone":"+1 970 874 5631",
    "sg:postcode":"81416",
    "sg:province":"CO",
    "sg:tags":[
        "repairing",
        "automobile"
    ],
    "wof:name":"Grand Mesa Imports",
    "wof:placetype":"venue"
},
  "geometry": {"coordinates":[-108.076784,38.762687],"type":"Point"}
}