{
  "type": "Feature",
  "properties": {
    "iso:country":"US",
    "sg:address":"101 Main St",
    "sg:city":"Frisco",
    "sg:classifiers":[
        {
            "category":"Professional",
            "subcategory":"Accounting & Tax Preparation",
            "type":"Services"
        }
    ],
    "sg:phone":"+1 970 668 5502",
    "sg:postcode":"80443",
    "sg:province":"CO",
    "sg:tags":[
        "accountant"
    ],
    "wof:name":"Bradley J Stuhr CPA",
    "wof:placetype":"venue"
},
  "geometry": {"coordinates":[-106.095164,39.576302],"type":"Point"}
}