{
  "type": "Feature",
  "properties": {
    "iso:country":"US",
    "sg:address":"901 19th St",
    "sg:city":"Denver",
    "sg:classifiers":[
        {
            "category":"Professional",
            "subcategory":"Secretarial Services",
            "type":"Services"
        }
    ],
    "sg:phone":"+1 303 893 2835",
    "sg:postcode":"80202",
    "sg:province":"CO",
    "sg:tags":[
        "convention",
        "court",
        "reporter"
    ],
    "wof:name":"Janet Morrissey",
    "wof:placetype":"venue"
},
  "geometry": {"coordinates":[-104.991196,39.750005],"type":"Point"}
}