{
  "type": "Feature",
  "properties": {
    "iso:country":"US",
    "sg:address":"376 Mackenzie Ave",
    "sg:city":"Canon City",
    "sg:classifiers":[
        {
            "category":"Restaurant",
            "type":"Food & Drink"
        }
    ],
    "sg:phone":"+1 719 276 0128",
    "sg:postcode":"81212",
    "sg:province":"CO",
    "sg:tags":[
        "eating"
    ],
    "wof:name":"Happy Wagon",
    "wof:placetype":"venue"
},
  "geometry": {"coordinates":[-105.1786,38.435383],"type":"Point"}
}