{
  "type": "Feature",
  "properties": {
    "iso:country":"US",
    "sg:address":"138 Howard St",
    "sg:city":"Eagle",
    "sg:classifiers":[
        {
            "category":"Organizations",
            "subcategory":"Religious Organization",
            "type":"Services"
        }
    ],
    "sg:phone":"+1 970 328 6598",
    "sg:postcode":"81631",
    "sg:province":"CO",
    "sg:tags":[
        "church"
    ],
    "wof:name":"Eagle Community Methodist",
    "wof:placetype":"venue"
},
  "geometry": {"coordinates":[-106.825441,39.655742],"type":"Point"}
}