{
  "type": "Feature",
  "properties": {
    "iso:country":"US",
    "sg:address":"1317 N 3rd St",
    "sg:city":"Grand Junction",
    "sg:classifiers":[
        {
            "category":"Health Services",
            "subcategory":"Doctor",
            "type":"Services"
        }
    ],
    "sg:phone":"+1 970 241 2430",
    "sg:postcode":"81501",
    "sg:province":"CO",
    "sg:tags":[
        "dentist"
    ],
    "wof:name":"Herbert D Gearhart DDS",
    "wof:placetype":"venue"
},
  "geometry": {"coordinates":[-108.56793500000001,39.079834],"type":"Point"}
}