{
  "type": "Feature",
  "properties": {
    "addr:full":"134 Eagle Trl Bailey CO 80421",
    "addr:housenumber":"134",
    "addr:postcode":"80421",
    "addr:street":"Eagle Trl",
    "iso:country":"US",
    "sg:address":"134 Eagle Trl",
    "sg:city":"Bailey",
    "sg:classifiers":[
        {
            "category":"Building & Trades",
            "subcategory":"Plumbing",
            "type":"Services"
        }
    ],
    "sg:phone":"+1 303 838 2110",
    "sg:postcode":"80421",
    "sg:province":"CO",
    "sg:tags":[
        "plumbing",
        "contractor"
    ],
    "wof:name":"Black Timber Plumbing & Htg",
    "wof:placetype":"venue"
},
  "geometry": {"coordinates":[-105.423483,39.409219],"type":"Point"}
}