{
  "type": "Feature",
  "properties": {
    "addr:full":"1434 Wood Ln Fort Collins CO 80524",
    "addr:housenumber":"1434",
    "addr:postcode":"80524",
    "addr:street":"Wood Ln",
    "iso:country":"US",
    "sg:address":"1434 Wood Ln",
    "sg:city":"Fort Collins",
    "sg:classifiers":[
        {
            "category":"Professional",
            "type":"Services"
        }
    ],
    "sg:phone":"+1 970 223 6855",
    "sg:postcode":"80524",
    "sg:province":"CO",
    "wof:name":"Blue Horse",
    "wof:placetype":"venue"
},
  "geometry": {"coordinates":[-105.0908,40.608129],"type":"Point"}
}