{
  "type": "Feature",
  "properties": {
    "iso:country":"US",
    "sg:address":"4984 Leetsdale Drive",
    "sg:city":"Denver",
    "sg:classifiers":[
        {
            "category":"Sports & Exercise",
            "subcategory":"Bicycle Rental",
            "type":"Entertainment"
        }
    ],
    "sg:phone":"+1 303 322 3776",
    "sg:postcode":"80246",
    "sg:province":"CO",
    "sg:tags":[
        "wear"
    ],
    "sg:website":"www.advantage-soccer.com",
    "wof:name":"Advantage Soccer",
    "wof:placetype":"venue"
},
  "geometry": {"coordinates":[-104.929991,39.708572],"type":"Point"}
}