{
  "type": "Feature",
  "properties": {
    "iso:country":"US",
    "sg:address":"11400 Canterberry Pkwy",
    "sg:city":"Parker",
    "sg:classifiers":[
        {
            "category":"Sports & Exercise",
            "subcategory":"Golf",
            "type":"Entertainment"
        }
    ],
    "sg:phone":"+1 303 840 3100",
    "sg:postcode":"80138",
    "sg:province":"CO",
    "sg:tags":[
        "course",
        "public"
    ],
    "sg:website":"www.canterberrygolfcourse.com",
    "wof:name":"Canterberry Golf Course",
    "wof:placetype":"venue"
},
  "geometry": {"coordinates":[-104.72603599999999,39.509799],"type":"Point"}
}