{
  "type": "Feature",
  "properties": {
    "iso:country":"US",
    "sg:address":"4085 N Mississippi Ave E",
    "sg:city":"Denver",
    "sg:classifiers":[
        {
            "category":"Food & Beverages",
            "subcategory":"Groceries & Convenience Stores",
            "type":"Retail Goods"
        }
    ],
    "sg:phone":"+1 303 758 0538",
    "sg:postcode":"80202",
    "sg:province":"CO",
    "sg:website":"www.7-eleven.com",
    "wof:name":"Seven-Eleven Stores",
    "wof:placetype":"venue"
},
  "geometry": {"coordinates":[-105.041231,39.696916],"type":"Point"}
}