{
  "type": "Feature",
  "properties": {
    "iso:country":"US",
    "sg:address":"1810 Airport Rd",
    "sg:city":"Breckenridge",
    "sg:classifiers":[
        {
            "category":"Banks & Credit Unions",
            "subcategory":"Bank",
            "type":"Services"
        }
    ],
    "sg:phone":"+1 970 453 1951",
    "sg:postcode":"80424",
    "sg:province":"CO",
    "sg:tags":[
        "loan"
    ],
    "wof:name":"Bankers Mortgage Corp",
    "wof:placetype":"venue"
},
  "geometry": {"coordinates":[-106.051672,39.508346],"type":"Point"}
}