{
  "type": "Feature",
  "properties": {
    "iso:country":"US",
    "sg:address":"1652 S Pitkin St",
    "sg:city":"Aurora",
    "sg:classifiers":[
        {
            "category":"Health Services",
            "subcategory":"Clinic",
            "type":"Services"
        }
    ],
    "sg:phone":"+1 303 283 1476",
    "sg:postcode":"80017",
    "sg:province":"CO",
    "wof:name":"Dependable Nursing Svc",
    "wof:placetype":"venue"
},
  "geometry": {"coordinates":[-104.78733,39.688001],"type":"Point"}
}