{
  "type": "Feature",
  "properties": {
    "addr:full":"5195 W Byron Pl Denver CO 80212",
    "addr:housenumber":"5195",
    "addr:postcode":"80212",
    "addr:street":"W Byron Pl",
    "iso:country":"US",
    "sg:address":"5195 W Byron Pl",
    "sg:city":"Denver",
    "sg:classifiers":[
        {
            "category":"Food & Beverages",
            "subcategory":"Groceries & Convenience Stores",
            "type":"Retail Goods"
        }
    ],
    "sg:phone":"+1 303 455 1329",
    "sg:postcode":"80212",
    "sg:province":"CO",
    "sg:website":"www.7-11.com",
    "wof:name":"7-Eleven",
    "wof:placetype":"venue"
},
  "geometry": {"coordinates":[-105.0522,39.753105],"type":"Point"}
}