{
  "type": "Feature",
  "properties": {
    "iso:country":"US",
    "sg:address":"5249 E 114th Pl",
    "sg:city":"Denver",
    "sg:classifiers":[
        {
            "category":"Building & Trades",
            "subcategory":"Cleaning & Sanitation",
            "type":"Services"
        }
    ],
    "sg:phone":"+1 303 452 7272",
    "sg:postcode":"80233",
    "sg:province":"CO",
    "sg:tags":[
        "fireplace",
        "chimney"
    ],
    "wof:name":"Complete Chimney Cleaning",
    "wof:placetype":"venue"
},
  "geometry": {"coordinates":[-104.926118,39.903991],"type":"Point"}
}