{
  "type": "Feature",
  "properties": {
    "iso:country":"US",
    "sg:address":"413 Cormorant Ct",
    "sg:city":"Fort Collins",
    "sg:classifiers":[
        {
            "category":"Real Estate",
            "subcategory":"Architect",
            "type":"Services"
        }
    ],
    "sg:phone":"+1 970 481 3366",
    "sg:postcode":"80525",
    "sg:province":"CO",
    "sg:tags":[
        "building",
        "designer"
    ],
    "wof:name":"Carson Design Studio",
    "wof:placetype":"venue"
},
  "geometry": {"coordinates":[-105.070956,40.533397],"type":"Point"}
}