{
  "type": "Feature",
  "properties": {
    "iso:country":"US",
    "sg:address":"3441 Grand Ave",
    "sg:city":"Glenwood Springs",
    "sg:classifiers":[
        {
            "category":"Building & Trades",
            "subcategory":"Plumbing",
            "type":"Services"
        }
    ],
    "sg:phone":"+1 970 384 0511",
    "sg:postcode":"81601",
    "sg:province":"CO",
    "sg:tags":[
        "contractor"
    ],
    "wof:name":"All-State Fire Protection",
    "wof:placetype":"venue"
},
  "geometry": {"coordinates":[-107.31720900000001,39.515446],"type":"Point"}
}