{
  "type": "Feature",
  "properties": {
    "addr:full":"516 N 10th St Canon City CO 81212",
    "addr:housenumber":"516",
    "addr:postcode":"81212",
    "addr:street":"N 10Th St",
    "iso:country":"US",
    "sg:address":"516 N 10th St",
    "sg:city":"Canon City",
    "sg:classifiers":[
        {
            "category":"Organizations",
            "subcategory":"Religious Organization",
            "type":"Services"
        }
    ],
    "sg:phone":"+1 719 275 9107",
    "sg:postcode":"81212",
    "sg:province":"CO",
    "sg:tags":[
        "church"
    ],
    "wof:name":"College Avenue Community",
    "wof:placetype":"venue"
},
  "geometry": {"coordinates":[-105.236847,38.447118],"type":"Point"}
}