{
  "type": "Feature",
  "properties": {
    "iso:country":"US",
    "sg:address":"631 King St",
    "sg:city":"Denver",
    "sg:classifiers":[
        {
            "category":"Freight",
            "type":"Transportation"
        }
    ],
    "sg:phone":"+1 303 893 6478",
    "sg:postcode":"80204",
    "sg:province":"CO",
    "sg:tags":[
        "operator",
        "trucking"
    ],
    "wof:name":"Servin Emiterio",
    "wof:placetype":"venue"
},
  "geometry": {"coordinates":[-105.033801,39.727227],"type":"Point"}
}