{
  "type": "Feature",
  "properties": {
    "iso:country":"US",
    "sg:address":"4473 Hollyhock St",
    "sg:city":"Fort Collins",
    "sg:classifiers":[
        {
            "category":"Building & Trades",
            "subcategory":"Plumbing",
            "type":"Services"
        }
    ],
    "sg:phone":"+1 970 225 1144",
    "sg:postcode":"80526",
    "sg:province":"CO",
    "sg:tags":[
        "plumbing",
        "contractor"
    ],
    "wof:name":"Rmp Plumbing & Heating LLC",
    "wof:placetype":"venue"
},
  "geometry": {"coordinates":[-105.093855,40.525157],"type":"Point"}
}