{
  "type": "Feature",
  "properties": {
    "iso:country":"US",
    "sg:address":"1565 Grand Ave",
    "sg:city":"Norwood",
    "sg:classifiers":[
        {
            "category":"Freight",
            "type":"Transportation"
        }
    ],
    "sg:phone":"+1 970 327 4095",
    "sg:postcode":"81423",
    "sg:province":"CO",
    "sg:tags":[
        "commercial",
        "storage"
    ],
    "wof:name":"4 R Storage Inc",
    "wof:placetype":"venue"
},
  "geometry": {"coordinates":[-108.29012,38.130816],"type":"Point"}
}