{
  "type": "Feature",
  "properties": {
    "iso:country":"US",
    "sg:address":"2000 Coronado Pkwy N",
    "sg:city":"Thornton",
    "sg:classifiers":[
        {
            "category":"Freight",
            "type":"Transportation"
        }
    ],
    "sg:phone":"+1 303 252 1032",
    "sg:postcode":"80229",
    "sg:province":"CO",
    "sg:tags":[
        "commercial",
        "storage"
    ],
    "wof:name":"A Handy Storage",
    "wof:placetype":"venue"
},
  "geometry": {"coordinates":[-104.964735,39.842073],"type":"Point"}
}