{
  "type": "Feature",
  "properties": {
    "addr:full":"11934 Washington St Northglenn CO 80233",
    "addr:housenumber":"11934",
    "addr:postcode":"80233",
    "addr:street":"Washington St",
    "iso:country":"US",
    "sg:address":"11934 Washington St",
    "sg:city":"Northglenn",
    "sg:classifiers":[
        {
            "category":"Personal",
            "type":"Services"
        }
    ],
    "sg:phone":"+1 303 451 8165",
    "sg:postcode":"80233",
    "sg:province":"CO",
    "sg:tags":[
        "program",
        "physical",
        "exercise",
        "fitness"
    ],
    "wof:name":"Jazzercise",
    "wof:placetype":"venue"
},
  "geometry": {"coordinates":[-104.977711,39.912717],"type":"Point"}
}