{
  "type": "Feature",
  "properties": {
    "iso:country":"US",
    "sg:address":"2504 Weslo Ave",
    "sg:city":"Grand Junction",
    "sg:classifiers":[
        {
            "category":"Wholesale",
            "subcategory":"Machinery & Supplies",
            "type":"Manufacturing & Wholesale Goods"
        }
    ],
    "sg:phone":"+1 970 243 0009",
    "sg:postcode":"81505",
    "sg:province":"CO",
    "sg:tags":[
        "fastener",
        "industrial"
    ],
    "wof:name":"Fasteners Inc",
    "wof:placetype":"venue"
},
  "geometry": {"coordinates":[-108.58668,39.088753],"type":"Point"}
}