{
  "type": "Feature",
  "properties": {
    "addr:full":"2162 W Eisenhower Blvd Loveland CO 80537",
    "addr:housenumber":"2162",
    "addr:postcode":"80537",
    "addr:street":"W Eisenhower Blvd",
    "iso:country":"US",
    "sg:address":"2162 W Eisenhower Blvd",
    "sg:city":"Loveland",
    "sg:classifiers":[
        {
            "category":"Professional",
            "type":"Services"
        }
    ],
    "sg:phone":"+1 970 663 2538",
    "sg:postcode":"80537",
    "sg:province":"CO",
    "wof:name":"Douglas & Janet Schroer",
    "wof:placetype":"venue"
},
  "geometry": {"coordinates":[-105.10659800000001,40.407169],"type":"Point"}
}