{
  "type": "Feature",
  "properties": {
    "iso:country":"US",
    "sg:address":"2324 Dennison Ln",
    "sg:city":"Boulder",
    "sg:classifiers":[
        {
            "category":"Professional",
            "type":"Services"
        }
    ],
    "sg:phone":"+1 303 440 1397",
    "sg:postcode":"80305",
    "sg:province":"CO",
    "wof:name":"Bielanski Inc",
    "wof:placetype":"venue"
},
  "geometry": {"coordinates":[-105.262427,39.98386],"type":"Point"}
}