{
  "type": "Feature",
  "properties": {
    "addr:full":"515 Fairview Ave Canon City CO 81212",
    "addr:housenumber":"515",
    "addr:postcode":"81212",
    "addr:street":"Fairview Ave",
    "iso:country":"US",
    "sg:address":"515 Fairview Ave",
    "sg:city":"Canon City",
    "sg:classifiers":[
        {
            "category":"Health Services",
            "subcategory":"Nursing And Care Facility",
            "type":"Services"
        }
    ],
    "sg:phone":"+1 719 275 0665",
    "sg:postcode":"81212",
    "sg:province":"CO",
    "sg:tags":[
        "home",
        "convalescent"
    ],
    "wof:name":"Skyline Ridge Nursing & Rehab",
    "wof:placetype":"venue"
},
  "geometry": {"coordinates":[-105.244811,38.453873],"type":"Point"}
}