{
  "type": "Feature",
  "properties": {
    "addr:full":"2339 Main St Longmont CO 80501",
    "addr:housenumber":"2339",
    "addr:postcode":"80501",
    "addr:street":"Main St",
    "iso:country":"US",
    "sg:address":"2339 Main St",
    "sg:city":"Longmont",
    "sg:classifiers":[
        {
            "category":"Restaurant",
            "type":"Food & Drink"
        }
    ],
    "sg:menulink":"http://www.allmenus.com/co/longmont/206967-sonic/menu/",
    "sg:phone":"+1 303 651 9613",
    "sg:postcode":"80501",
    "sg:province":"CO",
    "sg:tags":[
        "burger",
        "american"
    ],
    "wof:name":"Sonic",
    "wof:placetype":"venue"
},
  "geometry": {"coordinates":[-105.103089,40.201369],"type":"Point"}
}