{
  "type": "Feature",
  "properties": {
    "addr:full":"8833 Co Rd 12 Cotopaxi CO 81223",
    "addr:housenumber":"8833;12",
    "addr:postcode":"81223",
    "addr:street":"Co Rd",
    "iso:country":"US",
    "sg:address":"8833 Co Rd 12",
    "sg:city":"Cotopaxi",
    "sg:classifiers":[
        {
            "category":"Building & Trades",
            "subcategory":"Construction",
            "type":"Services"
        }
    ],
    "sg:phone":"+1 719 942 4237",
    "sg:postcode":"81223",
    "sg:province":"CO",
    "sg:tags":[
        "concrete",
        "contractor"
    ],
    "wof:name":"Cotopaxi Enterprises Con Pmpg",
    "wof:placetype":"venue"
},
  "geometry": {"coordinates":[-105.698961,38.49497],"type":"Point"}
}