{
  "type": "Feature",
  "properties": {
    "iso:country":"US",
    "sg:address":"2060 S Havana St",
    "sg:city":"Aurora",
    "sg:classifiers":[
        {
            "category":"Food & Beverages",
            "subcategory":"Liquor & Beverages",
            "type":"Retail Goods"
        }
    ],
    "sg:phone":"+1 303 745 3373",
    "sg:postcode":"80014",
    "sg:province":"CO",
    "wof:name":"Best Buys Liquors",
    "wof:placetype":"venue"
},
  "geometry": {"coordinates":[-104.86588399999999,39.679501],"type":"Point"}
}