{
  "type": "Feature",
  "properties": {
    "iso:country":"US",
    "sg:address":"1733 S Wadsworth Blvd",
    "sg:city":"Lakewood",
    "sg:classifiers":[
        {
            "category":"Freight",
            "type":"Transportation"
        }
    ],
    "sg:phone":"+1 303 989 6330",
    "sg:postcode":"80232",
    "sg:province":"CO",
    "sg:tags":[
        "commercial",
        "storage"
    ],
    "wof:name":"Colorado Self Storage Svc Ctr",
    "wof:placetype":"venue"
},
  "geometry": {"coordinates":[-105.081497,39.685467],"type":"Point"}
}