{
  "type": "Feature",
  "properties": {
    "addr:full":"7820 Sheridan Blvd Arvada CO 80003",
    "addr:housenumber":"7820",
    "addr:postcode":"80003",
    "addr:street":"Sheridan Blvd",
    "iso:country":"US",
    "sg:address":"7820 Sheridan Blvd",
    "sg:city":"Arvada",
    "sg:classifiers":[
        {
            "category":"Restaurant",
            "type":"Food & Drink"
        }
    ],
    "sg:menulink":"http://www.allmenus.com/co/west-adams/74932-pizza-hut/menu/",
    "sg:phone":"+1 303 429 7887",
    "sg:postcode":"80003",
    "sg:province":"CO",
    "sg:tags":[
        "american",
        "pizza"
    ],
    "wof:name":"Pizza Hut",
    "wof:placetype":"venue"
},
  "geometry": {"coordinates":[-105.052818,39.83871],"type":"Point"}
}