{
  "type": "Feature",
  "properties": {
    "addr:full":"955 Lincoln St Denver CO 80203",
    "addr:housenumber":"955",
    "addr:postcode":"80203",
    "addr:street":"Lincoln St",
    "iso:country":"US",
    "sg:address":"955 Lincoln St",
    "sg:city":"Denver",
    "sg:classifiers":[
        {
            "category":"Restaurant",
            "type":"Food & Drink"
        }
    ],
    "sg:phone":"+1 303 860 0041",
    "sg:postcode":"80203",
    "sg:province":"CO",
    "wof:name":"Wholly Tomato",
    "wof:placetype":"venue"
},
  "geometry": {"coordinates":[-104.98620200000001,39.731809],"type":"Point"}
}