{
  "type": "Feature",
  "properties": {
    "iso:country":"US",
    "sg:address":"14316 W Wesley Cir",
    "sg:city":"Lakewood",
    "sg:classifiers":[
        {
            "category":"Real Estate",
            "subcategory":"Real Estate Agent",
            "type":"Services"
        }
    ],
    "sg:phone":"+1 303 984 7052",
    "sg:postcode":"80228",
    "sg:province":"CO",
    "sg:tags":[
        "appraiser"
    ],
    "wof:name":"Alliance Appraisal",
    "wof:placetype":"venue"
},
  "geometry": {"coordinates":[-105.161199,39.671482],"type":"Point"}
}