{
  "type": "Feature",
  "properties": {
    "iso:country":"US",
    "sg:address":"1714 Topaz Dr",
    "sg:city":"Loveland",
    "sg:classifiers":[
        {
            "category":"Insurance",
            "subcategory":"Insurance Agent",
            "type":"Services"
        }
    ],
    "sg:phone":"+1 970 402 8747",
    "sg:postcode":"80537",
    "sg:province":"CO",
    "wof:name":"Blake D Blewitt",
    "wof:placetype":"venue"
},
  "geometry": {"coordinates":[-105.051513,40.406596],"type":"Point"}
}