{
  "type": "Feature",
  "properties": {
    "iso:country":"US",
    "sg:address":"688 Rood Ave",
    "sg:city":"Grand Junction",
    "sg:classifiers":[
        {
            "category":"Building & Trades",
            "subcategory":"Construction",
            "type":"Services"
        }
    ],
    "sg:phone":"+1 970 241 2980",
    "sg:postcode":"81501",
    "sg:province":"CO",
    "sg:tags":[
        "commercial",
        "refrigeration",
        "contractor"
    ],
    "wof:name":"Colorado Contracting Inc",
    "wof:placetype":"venue"
},
  "geometry": {"coordinates":[-108.562528,39.068379],"type":"Point"}
}