{
  "type": "Feature",
  "properties": {
    "iso:country":"US",
    "sg:address":"307 Elderberry Dr",
    "sg:city":"Fruita",
    "sg:classifiers":[
        {
            "category":"Manufacturing",
            "subcategory":"Metals",
            "type":"Manufacturing & Wholesale Goods"
        }
    ],
    "sg:phone":"+1 970 858 4279",
    "sg:postcode":"81521",
    "sg:province":"CO",
    "sg:tags":[
        "nonferrous"
    ],
    "wof:name":"Civan Metals Limited",
    "wof:placetype":"venue"
},
  "geometry": {"coordinates":[-108.735636,39.16836],"type":"Point"}
}