{
  "type": "Feature",
  "properties": {
    "iso:country":"US",
    "sg:address":"3625 E 48th Ave",
    "sg:city":"Denver",
    "sg:classifiers":[
        {
            "category":"Home & Garden",
            "subcategory":"Household Appliances",
            "type":"Retail Goods"
        }
    ],
    "sg:phone":"+1 303 320 4833",
    "sg:postcode":"80216",
    "sg:province":"CO",
    "sg:tags":[
        "repair"
    ],
    "wof:name":"Ferguson Bath Kitchen & Lighting Gallery",
    "wof:placetype":"venue"
},
  "geometry": {"coordinates":[-104.944,39.783901],"type":"Point"}
}