{
  "type": "Feature",
  "properties": {
    "iso:country":"US",
    "sg:address":"2445 E. 3rd Avenue Unit 5",
    "sg:city":"Denver",
    "sg:classifiers":[
        {
            "category":"Shopping",
            "subcategory":"Baby Store",
            "type":"Retail Goods"
        }
    ],
    "sg:phone":"+1 303 333 4463",
    "sg:postcode":"80206",
    "sg:province":"CO",
    "sg:tags":[
        "gear",
        "furniture"
    ],
    "sg:website":"www.fireflyfurnishings.com",
    "wof:name":"Firefly Furnishings",
    "wof:placetype":"venue"
},
  "geometry": {"coordinates":[-104.957391,39.72115],"type":"Point"}
}