{
  "type": "Feature",
  "properties": {
    "iso:country":"US",
    "sg:address":"251 16th St",
    "sg:city":"Burlington",
    "sg:classifiers":[
        {
            "category":"Government",
            "subcategory":"Office",
            "type":"Public Place"
        }
    ],
    "sg:phone":"+1 719 346 8133",
    "sg:postcode":"80807",
    "sg:province":"CO",
    "wof:name":"Kit Carson Commissioners",
    "wof:placetype":"venue"
},
  "geometry": {"coordinates":[-102.27075600000001,39.302849],"type":"Point"}
}