{
  "type": "Feature",
  "properties": {
    "iso:country":"US",
    "sg:address":"1942 Broadway St",
    "sg:city":"Boulder",
    "sg:classifiers":[
        {
            "category":"Banks & Credit Unions",
            "subcategory":"Investment Brokerage",
            "type":"Services"
        }
    ],
    "sg:phone":"+1 303 442 7136",
    "sg:postcode":"80304",
    "sg:province":"CO",
    "sg:tags":[
        "security"
    ],
    "wof:name":"Tal Mor Capitol Management Inc",
    "wof:placetype":"venue"
},
  "geometry": {"coordinates":[-105.279916,40.017911],"type":"Point"}
}