{
  "type": "Feature",
  "properties": {
    "addr:full":"7530 N Flintwood Rd Parker CO 80138",
    "addr:housenumber":"7530",
    "addr:postcode":"80138",
    "addr:street":"N Flintwood Rd",
    "iso:country":"US",
    "sg:address":"7530 N Flintwood Rd",
    "sg:city":"Parker",
    "sg:classifiers":[
        {
            "category":"Building & Trades",
            "subcategory":"Construction",
            "type":"Services"
        }
    ],
    "sg:phone":"+1 303 805 0868",
    "sg:postcode":"80138",
    "sg:province":"CO",
    "sg:tags":[
        "concrete",
        "contractor"
    ],
    "wof:name":"Costwise Concrete Contractors",
    "wof:placetype":"venue"
},
  "geometry": {"coordinates":[-104.680796,39.473973],"type":"Point"}
}