{
  "type": "Feature",
  "properties": {
    "iso:country":"US",
    "sg:address":"5304 Arapahoe Ave",
    "sg:city":"Boulder",
    "sg:classifiers":[
        {
            "category":"Restaurant",
            "type":"Food & Drink"
        }
    ],
    "sg:menulink":"http://www.allmenus.com/co/boulder/4117-snarfs/menu/",
    "sg:phone":"+1 303 444 3404",
    "sg:postcode":"80303",
    "sg:province":"CO",
    "sg:tags":[
        "american"
    ],
    "wof:name":"Snarf's",
    "wof:placetype":"venue"
},
  "geometry": {"coordinates":[-105.22904800000001,40.014609],"type":"Point"}
}