{
  "type": "Feature",
  "properties": {
    "iso:country":"US",
    "sg:address":"1835 Cherry St",
    "sg:city":"Denver",
    "sg:classifiers":[
        {
            "category":"Professional",
            "subcategory":"Advertising",
            "type":"Services"
        }
    ],
    "sg:phone":"+1 303 355 4980",
    "sg:postcode":"80220",
    "sg:province":"CO",
    "sg:tags":[
        "agency",
        "specialty"
    ],
    "wof:name":"Hesse & Hesse",
    "wof:placetype":"venue"
},
  "geometry": {"coordinates":[-104.93378199999999,39.745337],"type":"Point"}
}