{
  "type": "Feature",
  "properties": {
    "iso:country":"US",
    "sg:address":"490 S Federal Blvd",
    "sg:city":"Denver",
    "sg:classifiers":[
        {
            "category":"Shopping",
            "subcategory":"Tobacco",
            "type":"Retail Goods"
        }
    ],
    "sg:phone":"+1 303 937 9515",
    "sg:postcode":"80219",
    "sg:province":"CO",
    "sg:tags":[
        "product"
    ],
    "wof:name":"Wholy Smokes",
    "wof:placetype":"venue"
},
  "geometry": {"coordinates":[-105.025004,39.707619],"type":"Point"}
}