{
  "type": "Feature",
  "properties": {
    "addr:full":"8160 W 50th Ave Arvada CO 80002",
    "addr:housenumber":"8160",
    "addr:postcode":"80002",
    "addr:street":"W 50Th Ave",
    "iso:country":"US",
    "sg:address":"8160 W 50th Ave",
    "sg:city":"Arvada",
    "sg:classifiers":[
        {
            "category":"Building & Trades",
            "subcategory":"Construction",
            "type":"Services"
        }
    ],
    "sg:phone":"+1 303 422 6811",
    "sg:postcode":"80002",
    "sg:province":"CO",
    "sg:tags":[
        "house"
    ],
    "wof:name":"Greg Unseth Painting",
    "wof:placetype":"venue"
},
  "geometry": {"coordinates":[-105.089342,39.78742],"type":"Point"}
}