{
  "type": "Feature",
  "properties": {
    "addr:full":"12894 US Hwy 160 Del Norte CO 81132",
    "addr:housenumber":"12894",
    "addr:postcode":"81132",
    "addr:street":"Us Hwy 160 Del Norte",
    "iso:country":"US",
    "sg:address":"12894 US Hwy 160",
    "sg:city":"Del Norte",
    "sg:classifiers":[
        {
            "category":"Farming",
            "subcategory":"Livestock Farm",
            "type":"Manufacturing & Wholesale Goods"
        }
    ],
    "sg:phone":"+1 719 657 3703",
    "sg:postcode":"81132",
    "sg:province":"CO",
    "sg:tags":[
        "animal",
        "general"
    ],
    "wof:name":"Twin Pines Ranch LLC",
    "wof:placetype":"venue"
},
  "geometry": {"coordinates":[-106.334324,37.676296],"type":"Point"}
}