{
  "type": "Feature",
  "properties": {
    "addr:full":"101 Hickory Ave Boulder CO 80303",
    "addr:housenumber":"101",
    "addr:postcode":"80303",
    "addr:street":"Hickory Ave",
    "iso:country":"US",
    "sg:address":"101 Hickory Ave",
    "sg:city":"Boulder",
    "sg:classifiers":[
        {
            "category":"Health Services",
            "subcategory":"Health Practitioner",
            "type":"Services"
        }
    ],
    "sg:phone":"+1 303 494 1116",
    "sg:postcode":"80303",
    "sg:province":"CO",
    "sg:tags":[
        "psychologist"
    ],
    "wof:name":"Neil J Rosen",
    "wof:placetype":"venue"
},
  "geometry": {"coordinates":[-105.23200900000001,40.002164],"type":"Point"}
}