{
  "type": "Feature",
  "properties": {
    "addr:full":"9650 W 105th Ave Broomfield CO 80021",
    "addr:housenumber":"9650",
    "addr:postcode":"80021",
    "addr:street":"W 105Th Ave",
    "iso:country":"US",
    "sg:address":"9650 W 105th Ave",
    "sg:city":"Broomfield",
    "sg:classifiers":[
        {
            "category":"Banks & Credit Unions",
            "subcategory":"Bank",
            "type":"Services"
        }
    ],
    "sg:phone":"+1 303 863 5434",
    "sg:postcode":"80021",
    "sg:province":"CO",
    "sg:tags":[
        "national",
        "commercial"
    ],
    "wof:name":"Wells Fargo",
    "wof:placetype":"venue"
},
  "geometry": {"coordinates":[-105.106933,39.884407],"type":"Point"}
}