{
  "type": "Feature",
  "properties": {
    "addr:full":"702 Fairhurst St Sterling CO 80751",
    "addr:housenumber":"702",
    "addr:postcode":"80751",
    "addr:street":"Fairhurst St",
    "iso:country":"US",
    "sg:address":"702 Fairhurst St",
    "sg:city":"Sterling",
    "sg:phone":"+1 970 522 5095",
    "sg:postcode":"80751",
    "sg:province":"CO",
    "sg:tags":[
        "farm",
        "wheat"
    ],
    "wof:name":"Gordon Sonnenberg Farms Inc",
    "wof:placetype":"venue"
},
  "geometry": {"coordinates":[-103.221538,40.613732],"type":"Point"}
}