{
  "type": "Feature",
  "properties": {
    "addr:full":"8345 Urban Ct Arvada CO 80005",
    "addr:housenumber":"8345",
    "addr:postcode":"80005",
    "addr:street":"Urban Ct",
    "iso:country":"US",
    "sg:address":"8345 Urban Ct",
    "sg:city":"Arvada",
    "sg:classifiers":[
        {
            "category":"Wholesale",
            "subcategory":"Non-durable Goods",
            "type":"Manufacturing & Wholesale Goods"
        }
    ],
    "sg:phone":"+1 303 432 0528",
    "sg:postcode":"80005",
    "sg:province":"CO",
    "wof:name":"Executive Link",
    "wof:placetype":"venue"
},
  "geometry": {"coordinates":[-105.136714,39.848474],"type":"Point"}
}