{
  "type": "Feature",
  "properties": {
    "addr:full":"625 Lorah Ln Hotchkiss CO 81419",
    "addr:housenumber":"625",
    "addr:postcode":"81419",
    "addr:street":"Lorah Ln",
    "iso:country":"US",
    "sg:address":"625 Lorah Ln",
    "sg:city":"Hotchkiss",
    "sg:classifiers":[
        {
            "category":"Travel",
            "subcategory":"Travel Agent",
            "type":"Entertainment"
        }
    ],
    "sg:phone":"+1 970 872 3959",
    "sg:postcode":"81419",
    "sg:province":"CO",
    "sg:tags":[
        "tours",
        "promoter"
    ],
    "wof:name":"Jurassic Tours Inc",
    "wof:placetype":"venue"
},
  "geometry": {"coordinates":[-107.711972,38.802508],"type":"Point"}
}