{
  "type": "Feature",
  "properties": {
    "iso:country":"US",
    "sg:address":"1534 11th Ave",
    "sg:city":"Greeley",
    "sg:classifiers":[
        {
            "category":"Real Estate",
            "subcategory":"Real Estate Operator",
            "type":"Services"
        }
    ],
    "sg:phone":"+1 970 353 9275",
    "sg:postcode":"80631",
    "sg:province":"CO",
    "sg:tags":[
        "apartment"
    ],
    "wof:name":"University Plaza",
    "wof:placetype":"venue"
},
  "geometry": {"coordinates":[-104.696265,40.414441],"type":"Point"}
}