{
  "type": "Feature",
  "properties": {
    "addr:full":"246 Moraine Ave Estes Park CO 80517",
    "addr:housenumber":"246",
    "addr:postcode":"80517",
    "addr:street":"Moraine Ave",
    "iso:country":"US",
    "sg:address":"246 Moraine Ave",
    "sg:city":"Estes Park",
    "sg:classifiers":[
        {
            "category":"Bars & Pubs",
            "type":"Food & Drink"
        }
    ],
    "sg:phone":"+1 970 577 0666",
    "sg:postcode":"80517",
    "sg:province":"CO",
    "wof:name":"Cavanaughs Pub",
    "wof:placetype":"venue"
},
  "geometry": {"coordinates":[-105.523484,40.374062],"type":"Point"}
}