{
  "type": "Feature",
  "properties": {
    "addr:full":"8935 S Blue Sage Cir Colorado Springs CO 80908",
    "addr:housenumber":"8935",
    "addr:postcode":"80908",
    "addr:street":"S Blue Sage Cir",
    "iso:country":"US",
    "sg:address":"8935 S Blue Sage Cir",
    "sg:city":"Colorado Springs",
    "sg:classifiers":[
        {
            "category":"Professional",
            "subcategory":"Computer Services",
            "type":"Services"
        }
    ],
    "sg:phone":"+1 719 495 9614",
    "sg:postcode":"80908",
    "sg:province":"CO",
    "sg:tags":[
        "consultant",
        "designer"
    ],
    "wof:name":"Table Rock Ent Inc",
    "wof:placetype":"venue"
},
  "geometry": {"coordinates":[-104.660634,39.11205],"type":"Point"}
}