{
  "type": "Feature",
  "properties": {
    "addr:full":"17610 Person Dr Peyton CO 80831",
    "addr:postcode":"17610;80831",
    "addr:street":"Person Dr",
    "iso:country":"US",
    "sg:address":"17610 Person Dr",
    "sg:city":"Peyton",
    "sg:classifiers":[
        {
            "category":"Building & Trades",
            "subcategory":"Landscaping Services",
            "type":"Services"
        }
    ],
    "sg:phone":"+1 719 520 0012",
    "sg:postcode":"80831",
    "sg:province":"CO",
    "wof:name":"Mikes Lawn Service Inc",
    "wof:placetype":"venue"
},
  "geometry": {"coordinates":[-104.50899200000001,39.076846],"type":"Point"}
}