{
  "type": "Feature",
  "properties": {
    "addr:full":"19375 Glen Hollow Cir Monument CO 80132",
    "addr:housenumber":"19375",
    "addr:postcode":"80132",
    "addr:street":"Glen Hollow Cir",
    "iso:country":"US",
    "sg:address":"19375 Glen Hollow Cir",
    "sg:city":"Monument",
    "sg:classifiers":[
        {
            "category":"Professional",
            "subcategory":"Management & Consulting",
            "type":"Services"
        }
    ],
    "sg:phone":"+1 719 481 3678",
    "sg:postcode":"80132",
    "sg:province":"CO",
    "sg:tags":[
        "consultant"
    ],
    "wof:name":"Berk Achenbach Consulting",
    "wof:placetype":"venue"
},
  "geometry": {"coordinates":[-104.832958,39.110927],"type":"Point"}
}