{
  "type": "Feature",
  "properties": {
    "addr:full":"10030 W Hampden Ave Denver CO 80227",
    "addr:housenumber":"10030",
    "addr:postcode":"80227",
    "addr:street":"W Hampden Ave",
    "iso:country":"US",
    "sg:address":"10030 W Hampden Ave",
    "sg:city":"Denver",
    "sg:classifiers":[
        {
            "category":"Autos & Motor Vehicles",
            "subcategory":"Fuel & Gas Station",
            "type":"Retail Goods"
        }
    ],
    "sg:phone":"+1 303 986 1221",
    "sg:postcode":"80227",
    "sg:province":"CO",
    "sg:tags":[
        "convenience",
        "gasoline",
        "store"
    ],
    "wof:name":"Valero Energy Corporation",
    "wof:placetype":"venue"
},
  "geometry": {"coordinates":[-105.113355,39.654508],"type":"Point"}
}