{
  "type": "Feature",
  "properties": {
    "addr:full":"4549 E Platte Ave Colorado Springs CO 80915",
    "addr:housenumber":"4549",
    "addr:postcode":"80915",
    "addr:street":"E Platte Ave",
    "iso:country":"US",
    "sg:address":"4549 E Platte Ave",
    "sg:city":"Colorado Springs",
    "sg:classifiers":[
        {
            "category":"Manufacturing",
            "subcategory":"Metals",
            "type":"Manufacturing & Wholesale Goods"
        }
    ],
    "sg:phone":"+1 719 633 6778",
    "sg:postcode":"80915",
    "sg:province":"CO",
    "sg:tags":[
        "finisher"
    ],
    "wof:name":"Front Range Custom Polishing",
    "wof:placetype":"venue"
},
  "geometry": {"coordinates":[-104.744016,38.839624],"type":"Point"}
}