{
  "type": "Feature",
  "properties": {
    "iso:country":"US",
    "sg:address":"PO BOX 141",
    "sg:city":"Denver",
    "sg:classifiers":[
        {
            "category":"Professional",
            "subcategory":"Computer Services",
            "type":"Services"
        }
    ],
    "sg:phone":"+1 303 974 7244",
    "sg:postcode":"80201-0141",
    "sg:province":"CO",
    "sg:tags":[
        "saas",
        "on-demand",
        "software",
        "development",
        "hosting",
        "ajax",
        "applications",
        "web",
        "database",
        "bi",
        "bpm",
        "crm"
    ],
    "sg:website":"http://x13.com",
    "wof:name":"X13",
    "wof:placetype":"venue"
},
  "geometry": {"coordinates":[-104.856808,39.726303],"type":"Point"}
}