{
  "type": "Feature",
  "properties": {
    "addr:full":"2404 E Bridge St Brighton CO 80601",
    "addr:housenumber":"2404",
    "addr:postcode":"80601",
    "addr:street":"E Bridge St",
    "iso:country":"US",
    "sg:address":"2404 E Bridge St",
    "sg:city":"Brighton",
    "sg:classifiers":[
        {
            "category":"Professional",
            "type":"Services"
        }
    ],
    "sg:phone":"+1 303 659 9834",
    "sg:postcode":"80601",
    "sg:province":"CO",
    "wof:name":"Check Into Cash",
    "wof:placetype":"venue"
},
  "geometry": {"coordinates":[-104.792322,39.986706],"type":"Point"}
}