{
  "type": "Feature",
  "properties": {
    "addr:full":"246 Sunlight Dr Dillon CO 80435",
    "addr:housenumber":"246",
    "addr:postcode":"80435",
    "addr:street":"Sunlight Dr",
    "iso:country":"US",
    "sg:address":"246 Sunlight Dr",
    "sg:city":"Dillon",
    "sg:classifiers":[
        {
            "category":"Building & Trades",
            "subcategory":"Construction",
            "type":"Services"
        }
    ],
    "sg:phone":"+1 970 468 1911",
    "sg:postcode":"80435",
    "sg:province":"CO",
    "sg:tags":[
        "general",
        "contractor"
    ],
    "wof:name":"Mountain Elegance Design",
    "wof:placetype":"venue"
},
  "geometry": {"coordinates":[-106.009292,39.595795],"type":"Point"}
}