{
  "type": "Feature",
  "properties": {
    "addr:full":"2060 Broadway St Boulder CO 80304",
    "addr:housenumber":"2060",
    "addr:postcode":"80304",
    "addr:street":"Broadway St",
    "iso:country":"US",
    "sg:address":"2060 Broadway St",
    "sg:city":"Boulder",
    "sg:classifiers":[
        {
            "category":"Banks & Credit Unions",
            "subcategory":"Investment Brokerage",
            "type":"Services"
        }
    ],
    "sg:phone":"+1 303 444 8840",
    "sg:postcode":"80304",
    "sg:province":"CO",
    "sg:tags":[
        "consultant",
        "planning",
        "financial"
    ],
    "sg:website":"www.danday.com",
    "wof:name":"Daniel M Day & Assoc",
    "wof:placetype":"venue"
},
  "geometry": {"coordinates":[-105.2801,40.018313],"type":"Point"}
}