{
  "type": "Feature",
  "properties": {
    "addr:full":"2805 Jet Wing Dr Colorado Springs CO 80916",
    "addr:housenumber":"2805",
    "addr:postcode":"80916",
    "addr:street":"Jet Wing Dr",
    "iso:country":"US",
    "sg:address":"2805 Jet Wing Dr",
    "sg:city":"Colorado Springs",
    "sg:classifiers":[
        {
            "category":"Organizations",
            "subcategory":"Religious Organization",
            "type":"Services"
        }
    ],
    "sg:phone":"+1 719 390 4104",
    "sg:postcode":"80916",
    "sg:province":"CO",
    "wof:name":"Church Of Christ",
    "wof:placetype":"venue"
},
  "geometry": {"coordinates":[-104.75403900000001,38.792145],"type":"Point"}
}