{
  "type": "Feature",
  "properties": {
    "addr:full":"2001 S Havana St Aurora CO 80014",
    "addr:housenumber":"2001",
    "addr:postcode":"80014",
    "addr:street":"S Havana St",
    "iso:country":"US",
    "sg:address":"2001 S Havana St",
    "sg:city":"Aurora",
    "sg:classifiers":[
        {
            "category":"Autos & Motor Vehicles",
            "subcategory":"Automobile Sales",
            "type":"Retail Goods"
        },
        {
            "category":"Autos & Motor Vehicles",
            "subcategory":"Auto Supplies",
            "type":"Retail Goods"
        }
    ],
    "sg:phone":"+1 303 751 2342",
    "sg:postcode":"80014",
    "sg:province":"CO",
    "sg:tags":[
        "car",
        "part",
        "new",
        "accessory"
    ],
    "wof:name":"Chevy On Havana",
    "wof:placetype":"venue"
},
  "geometry": {"coordinates":[-104.86592899999999,39.68018],"type":"Point"}
}