{
  "type": "Feature",
  "properties": {
    "iso:country":"US",
    "sg:address":"9890 W Girton Dr",
    "sg:city":"Lakewood",
    "sg:classifiers":[
        {
            "category":"Bars & Pubs",
            "type":"Food & Drink"
        },
        {
            "category":"Restaurant",
            "type":"Food & Drink"
        },
        {
            "category":"Bars & Pubs",
            "subcategory":"Nightclub",
            "type":"Food & Drink"
        }
    ],
    "sg:phone":"+1 303 989 2991",
    "sg:postcode":"80227",
    "sg:province":"CO",
    "sg:tags":[
        "club",
        "style",
        "family",
        "night"
    ],
    "wof:name":"Ecks Saloon",
    "wof:placetype":"venue"
},
  "geometry": {"coordinates":[-105.10936599999999,39.655526],"type":"Point"}
}