{
  "type": "Feature",
  "properties": {
    "iso:country":"US",
    "sg:address":"7131 Dunklau Rd",
    "sg:city":"Fort Garland",
    "sg:classifiers":[
        {
            "category":"Travel",
            "subcategory":"Travel Agent",
            "type":"Entertainment"
        }
    ],
    "sg:phone":"+1 719 379 3133",
    "sg:postcode":"81133",
    "sg:province":"CO",
    "sg:tags":[
        "cruise"
    ],
    "wof:name":"Cruises Inc-Kd's Cruises/Tours",
    "wof:placetype":"venue"
},
  "geometry": {"coordinates":[-105.325073,37.39535],"type":"Point"}
}