{
  "type": "Feature",
  "properties": {
    "iso:country":"US",
    "sg:address":"581 County Line Rd",
    "sg:city":"Monument",
    "sg:classifiers":[
        {
            "category":"Wholesale",
            "subcategory":"Meat",
            "type":"Manufacturing & Wholesale Goods"
        }
    ],
    "sg:phone":"+1 719 488 0530",
    "sg:postcode":"80118",
    "sg:province":"CO",
    "sg:tags":[
        "prod",
        "prepared"
    ],
    "wof:name":"Sara's Sausage",
    "wof:placetype":"venue"
},
  "geometry": {"coordinates":[-104.87535800000001,39.129744],"type":"Point"}
}