{
  "type": "Feature",
  "properties": {
    "iso:country":"US",
    "sg:address":"7512 S Fillmore Way",
    "sg:city":"Littleton",
    "sg:classifiers":[
        {
            "category":"Banks & Credit Unions",
            "subcategory":"Bank",
            "type":"Services"
        }
    ],
    "sg:phone":"+1 303 796 7297",
    "sg:postcode":"80122",
    "sg:province":"CO",
    "sg:tags":[
        "mortgage"
    ],
    "wof:name":"MB Mortgage",
    "wof:placetype":"venue"
},
  "geometry": {"coordinates":[-104.95345500000001,39.580121],"type":"Point"}
}