{
  "type": "Feature",
  "properties": {
    "iso:country":"US",
    "sg:address":"1800 Commerce St",
    "sg:city":"Boulder",
    "sg:classifiers":[
        {
            "category":"Manufacturing",
            "subcategory":"Retail Goods",
            "type":"Manufacturing & Wholesale Goods"
        },
        {
            "category":"Wholesale",
            "subcategory":"Electrical",
            "type":"Manufacturing & Wholesale Goods"
        }
    ],
    "sg:phone":"+1 303 417 1800",
    "sg:postcode":"80301",
    "sg:province":"CO",
    "sg:tags":[
        "mfg",
        "communication",
        "equipment",
        "computer",
        "facsimile",
        "carbon",
        "ribbon"
    ],
    "wof:name":"Rainbow Ink Jet Inc",
    "wof:placetype":"venue"
},
  "geometry": {"coordinates":[-105.231904,40.018606],"type":"Point"}
}