{
  "type": "Feature",
  "properties": {
    "iso:country":"US",
    "sg:address":"1475 Boise Ave",
    "sg:city":"Loveland",
    "sg:classifiers":[
        {
            "category":"Bars & Pubs",
            "type":"Food & Drink"
        }
    ],
    "sg:phone":"+1 970 669 8503",
    "sg:postcode":"80538",
    "sg:province":"CO",
    "sg:tags":[
        "drinking"
    ],
    "wof:name":"Martys Place",
    "wof:placetype":"venue"
},
  "geometry": {"coordinates":[-105.05376699999999,40.407601],"type":"Point"}
}