{
  "type": "Feature",
  "properties": {
    "iso:country":"US",
    "sg:address":"711 Grant St",
    "sg:city":"Denver",
    "sg:classifiers":[
        {
            "category":"Restaurant",
            "type":"Food & Drink"
        }
    ],
    "sg:phone":"+1 303 831 8090",
    "sg:postcode":"80203",
    "sg:province":"CO",
    "sg:tags":[
        "eating"
    ],
    "wof:name":"China Hill Restaurant",
    "wof:placetype":"venue"
},
  "geometry": {"coordinates":[-104.983676,39.728889],"type":"Point"}
}