{
  "type": "Feature",
  "properties": {
    "addr:full":"5555 W 16th Ave Denver CO 80214",
    "addr:housenumber":"5555",
    "addr:postcode":"80214",
    "addr:street":"W 16Th Ave",
    "iso:country":"US",
    "sg:address":"5555 W 16th Ave",
    "sg:city":"Denver",
    "sg:classifiers":[
        {
            "category":"Utilities",
            "subcategory":"Telephone",
            "type":"Services"
        }
    ],
    "sg:phone":"+1 303 726 3696",
    "sg:postcode":"80214",
    "sg:province":"CO",
    "sg:tags":[
        "communications"
    ],
    "wof:name":"Communication Network",
    "wof:placetype":"venue"
},
  "geometry": {"coordinates":[-105.057405,39.742249],"type":"Point"}
}