{
  "type": "Feature",
  "properties": {
    "addr:full":"128 Market St Alamosa CO 81101",
    "addr:housenumber":"128",
    "addr:postcode":"81101",
    "addr:street":"Market St",
    "iso:country":"US",
    "sg:address":"128 Market St",
    "sg:city":"Alamosa",
    "sg:classifiers":[
        {
            "category":"Health Services",
            "subcategory":"Clinic",
            "type":"Services"
        },
        {
            "category":"Health Services",
            "subcategory":"Doctor",
            "type":"Services"
        }
    ],
    "sg:phone":"+1 719 589 5161",
    "sg:postcode":"81101",
    "sg:province":"CO",
    "wof:name":"Valley Wide Health Systems Inc",
    "wof:placetype":"venue"
},
  "geometry": {"coordinates":[-105.89172499999999,37.474519],"type":"Point"}
}