{
  "type": "Feature",
  "properties": {
    "addr:full":"11747 W Ken Caryl Ave Littleton CO 80127",
    "addr:housenumber":"11747",
    "addr:postcode":"80127",
    "addr:street":"W Ken Caryl Ave",
    "iso:country":"US",
    "sg:address":"11747 W Ken Caryl Ave",
    "sg:city":"Littleton",
    "sg:classifiers":[
        {
            "category":"Coffee & Tea",
            "type":"Food & Drink"
        }
    ],
    "sg:menulink":"http://www.allmenus.com/co/northeast-jefferson/118076-starbucks-coffee/menu/",
    "sg:phone":"+1 303 933 5100",
    "sg:postcode":"80127",
    "sg:province":"CO",
    "sg:tags":[
        "american"
    ],
    "wof:name":"Starbucks Coffee",
    "wof:placetype":"venue"
},
  "geometry": {"coordinates":[-105.130529,39.5822],"type":"Point"}
}