{
  "type": "Feature",
  "properties": {
    "iso:country":"US",
    "sg:address":"6301 S Williams St",
    "sg:city":"Centennial",
    "sg:classifiers":[
        {
            "category":"Building & Trades",
            "subcategory":"Plumbing",
            "type":"Services"
        }
    ],
    "sg:phone":"+1 303 781 3007",
    "sg:postcode":"80121",
    "sg:province":"CO",
    "sg:tags":[
        "mechanical",
        "contractor"
    ],
    "wof:name":"ACT Mechanical",
    "wof:placetype":"venue"
},
  "geometry": {"coordinates":[-104.968008,39.600638],"type":"Point"}
}