{
  "type": "Feature",
  "properties": {
    "iso:country":"US",
    "sg:address":"537 Primavera St",
    "sg:city":"Clifton",
    "sg:classifiers":[
        {
            "category":"Shopping",
            "type":"Retail Goods"
        }
    ],
    "sg:phone":"+1 970 434 0785",
    "sg:postcode":"81520",
    "sg:province":"CO",
    "sg:tags":[
        "merchandise"
    ],
    "wof:name":"Monument Medical Consultants L",
    "wof:placetype":"venue"
},
  "geometry": {"coordinates":[-108.44630600000001,39.082424],"type":"Point"}
}