{
  "type": "Feature",
  "properties": {
    "addr:full":"1005 Parkview Blvd Colorado Springs CO 80906",
    "addr:housenumber":"1005",
    "addr:postcode":"80906",
    "addr:street":"Parkview Blvd",
    "iso:country":"US",
    "sg:address":"1005 Parkview Blvd",
    "sg:city":"Colorado Springs",
    "sg:classifiers":[
        {
            "category":"Retail",
            "subcategory":"Portrait Studio",
            "type":"Services"
        }
    ],
    "sg:phone":"+1 719 634 7080",
    "sg:postcode":"80906",
    "sg:province":"CO",
    "sg:tags":[
        "photographer"
    ],
    "wof:name":"Ernie Ferguson Classic",
    "wof:placetype":"venue"
},
  "geometry": {"coordinates":[-104.84824399999999,38.812245],"type":"Point"}
}