{
  "type": "Feature",
  "properties": {
    "iso:country":"US",
    "sg:address":"3760 Vance St",
    "sg:city":"Wheat Ridge",
    "sg:classifiers":[
        {
            "category":"Professional",
            "subcategory":"Advertising",
            "type":"Services"
        }
    ],
    "sg:phone":"+1 303 463 5739",
    "sg:postcode":"80033",
    "sg:province":"CO",
    "sg:tags":[
        "distribution"
    ],
    "sg:website":"www.solutions-atm.com",
    "wof:name":"American Data Solutions Inc",
    "wof:placetype":"venue"
},
  "geometry": {"coordinates":[-105.079643,39.769004],"type":"Point"}
}