{
  "type": "Feature",
  "properties": {
    "addr:full":"665 Westridge Rd Craig CO 81625",
    "addr:housenumber":"665",
    "addr:postcode":"81625",
    "addr:street":"Westridge Rd",
    "iso:country":"US",
    "sg:address":"665 Westridge Rd",
    "sg:city":"Craig",
    "sg:classifiers":[
        {
            "category":"Organizations",
            "subcategory":"Religious Organization",
            "type":"Services"
        }
    ],
    "sg:phone":"+1 970 824 2101",
    "sg:postcode":"81625",
    "sg:province":"CO",
    "sg:tags":[
        "church"
    ],
    "wof:name":"Craig Congregation-Jehovah's",
    "wof:placetype":"venue"
},
  "geometry": {"coordinates":[-107.59119,40.515553],"type":"Point"}
}