{
  "type": "Feature",
  "properties": {
    "addr:full":"12925 N Sierra Cir Parker CO 80138",
    "addr:housenumber":"12925",
    "addr:postcode":"80138",
    "addr:street":"N Sierra Cir",
    "iso:country":"US",
    "sg:address":"12925 N Sierra Cir",
    "sg:city":"Parker",
    "sg:classifiers":[
        {
            "category":"Government",
            "subcategory":"Office",
            "type":"Public Place"
        }
    ],
    "sg:phone":"+1 303 841 7788",
    "sg:postcode":"80138",
    "sg:province":"CO",
    "sg:tags":[
        "administrative",
        "program",
        "economic",
        "general"
    ],
    "wof:name":"Altresco International",
    "wof:placetype":"venue"
},
  "geometry": {"coordinates":[-104.7581,39.550013],"type":"Point"}
}