{
  "type": "Feature",
  "properties": {
    "addr:full":"4210 S Biscay Cir Aurora CO 80013",
    "addr:housenumber":"4210",
    "addr:postcode":"80013",
    "addr:street":"S Biscay Cir",
    "iso:country":"US",
    "sg:address":"4210 S Biscay Cir",
    "sg:city":"Aurora",
    "sg:classifiers":[
        {
            "category":"Professional",
            "subcategory":"Accounting & Tax Preparation",
            "type":"Services"
        }
    ],
    "sg:phone":"+1 303 690 5150",
    "sg:postcode":"80013",
    "sg:province":"CO",
    "sg:tags":[
        "accountant"
    ],
    "wof:name":"Brian Alexander CPA",
    "wof:placetype":"venue"
},
  "geometry": {"coordinates":[-104.768688,39.641366],"type":"Point"}
}