{
  "type": "Feature",
  "properties": {
    "addr:full":"379 W Littleton Blvd Littleton CO 80120",
    "addr:housenumber":"379",
    "addr:postcode":"80120",
    "addr:street":"W Littleton Blvd",
    "iso:country":"US",
    "sg:address":"379 W Littleton Blvd",
    "sg:city":"Littleton",
    "sg:classifiers":[
        {
            "category":"Retail",
            "subcategory":"Laundry & Dry Cleaning",
            "type":"Services"
        }
    ],
    "sg:phone":"+1 303 730 2104",
    "sg:postcode":"80120",
    "sg:province":"CO",
    "sg:tags":[
        "cleaners"
    ],
    "wof:name":"Park's Cleaners",
    "wof:placetype":"venue"
},
  "geometry": {"coordinates":[-104.99186400000001,39.613246],"type":"Point"}
}