{
  "type": "Feature",
  "properties": {
    "iso:country":"US",
    "sg:address":"102 E Parmenter St",
    "sg:city":"Lamar",
    "sg:classifiers":[
        {
            "category":"Government",
            "subcategory":"Office",
            "type":"Public Place"
        }
    ],
    "sg:phone":"+1 719 336 4376",
    "sg:postcode":"81052",
    "sg:province":"CO",
    "sg:tags":[
        "municipality"
    ],
    "wof:name":"City of Lamar",
    "wof:placetype":"venue"
},
  "geometry": {"coordinates":[-102.617638,38.085049],"type":"Point"}
}