{
  "type": "Feature",
  "properties": {
    "iso:country":"US",
    "sg:address":"2801 W Hampden Ave",
    "sg:city":"Englewood",
    "sg:classifiers":[
        {
            "category":"Retail",
            "subcategory":"Auto Repair",
            "type":"Services"
        }
    ],
    "sg:phone":"+1 303 761 0677",
    "sg:postcode":"80110",
    "sg:province":"CO",
    "sg:tags":[
        "body",
        "automotive",
        "painting",
        "shop",
        "automobile"
    ],
    "sg:website":"www.hampdenautobody.com",
    "wof:name":"Hampden Auto Body",
    "wof:placetype":"venue"
},
  "geometry": {"coordinates":[-105.02412099999999,39.653276],"type":"Point"}
}