{
  "type": "Feature",
  "properties": {
    "addr:full":"850 Main Ct Carbondale CO 81623",
    "addr:housenumber":"850",
    "addr:postcode":"81623",
    "addr:street":"Main Ct",
    "iso:country":"US",
    "sg:address":"850 Main Ct",
    "sg:city":"Carbondale",
    "sg:classifiers":[
        {
            "category":"Social Services",
            "subcategory":"Adult Care",
            "type":"Services"
        }
    ],
    "sg:phone":"+1 970 963 1284",
    "sg:postcode":"81623",
    "sg:province":"CO",
    "sg:tags":[
        "residential"
    ],
    "wof:name":"Columbine House",
    "wof:placetype":"venue"
},
  "geometry": {"coordinates":[-107.21623700000001,39.400623],"type":"Point"}
}