{
  "type": "Feature",
  "properties": {
    "iso:country":"US",
    "sg:address":"2905 San Bernardo Dr",
    "sg:city":"Telluride",
    "sg:classifiers":[
        {
            "category":"Communications",
            "subcategory":"Film & Video Production",
            "type":"Services"
        }
    ],
    "sg:phone":"+1 970 728 7008",
    "sg:postcode":"81426",
    "sg:province":"CO",
    "sg:tags":[
        "taping"
    ],
    "wof:name":"Mountain Video Productions",
    "wof:placetype":"venue"
},
  "geometry": {"coordinates":[-107.897723,37.843503],"type":"Point"}
}