{
  "type": "Feature",
  "properties": {
    "iso:country":"US",
    "sg:address":"6844 S Webster St",
    "sg:city":"Littleton",
    "sg:classifiers":[
        {
            "category":"Professional",
            "type":"Services"
        }
    ],
    "sg:phone":"+1 303 904 0954",
    "sg:postcode":"80128",
    "sg:province":"CO",
    "wof:name":"Michael Alvarado",
    "wof:placetype":"venue"
},
  "geometry": {"coordinates":[-105.076819,39.591726],"type":"Point"}
}