{
  "type": "Feature",
  "properties": {
    "iso:country":"US",
    "sg:address":"961 Main St",
    "sg:city":"Ouray",
    "sg:classifiers":[
        {
            "category":"Wholesale",
            "subcategory":"Durable Goods & Equipment",
            "type":"Manufacturing & Wholesale Goods"
        }
    ],
    "sg:phone":"+1 970 325 0241",
    "sg:postcode":"81427",
    "sg:province":"CO",
    "sg:tags":[
        "exporter"
    ],
    "sg:website":"www.amrsales.com",
    "wof:name":"American Material Resources",
    "wof:placetype":"venue"
},
  "geometry": {"coordinates":[-107.67141700000001,38.02759],"type":"Point"}
}