{
  "type": "Feature",
  "properties": {
    "iso:country":"US",
    "sg:address":"706 W Pearl St",
    "sg:city":"Lamar",
    "sg:classifiers":[
        {
            "category":"Organizations",
            "subcategory":"Religious Organization",
            "type":"Services"
        }
    ],
    "sg:phone":"+1 719 336 7548",
    "sg:postcode":"81052",
    "sg:province":"CO",
    "sg:tags":[
        "church"
    ],
    "wof:name":"First Southern Baptist Church",
    "wof:placetype":"venue"
},
  "geometry": {"coordinates":[-102.62666299999999,38.083921],"type":"Point"}
}