{
  "type": "Feature",
  "properties": {
    "addr:full":"137 N Kansas St Walsh CO 81090",
    "addr:housenumber":"137",
    "addr:postcode":"81090",
    "addr:street":"N Kansas St",
    "iso:country":"US",
    "sg:address":"137 N Kansas St",
    "sg:city":"Walsh",
    "sg:classifiers":[
        {
            "category":"Health Services",
            "subcategory":"Chiropractor",
            "type":"Services"
        }
    ],
    "sg:phone":"+1 719 324 5242",
    "sg:postcode":"81090",
    "sg:province":"CO",
    "wof:name":"Lease Chiropractic Clinic",
    "wof:placetype":"venue"
},
  "geometry": {"coordinates":[-102.279563,37.384539],"type":"Point"}
}