{
  "type": "Feature",
  "properties": {
    "addr:full":"406 Karr Rd Colorado Springs CO 80916",
    "addr:housenumber":"406",
    "addr:postcode":"80916",
    "addr:street":"Karr Rd",
    "iso:country":"US",
    "sg:address":"406 Karr Rd",
    "sg:city":"Colorado Springs",
    "sg:classifiers":[
        {
            "category":"Building & Trades",
            "subcategory":"Electrical",
            "type":"Services"
        }
    ],
    "sg:phone":"+1 719 573 1907",
    "sg:postcode":"80916",
    "sg:province":"CO",
    "sg:tags":[
        "electrical",
        "contractor"
    ],
    "wof:name":"Commonwealth Enterprises",
    "wof:placetype":"venue"
},
  "geometry": {"coordinates":[-104.73649899999999,38.826799],"type":"Point"}
}