{
  "type": "Feature",
  "properties": {
    "addr:full":"17721 Cottonwood Dr Parker CO 80134",
    "addr:housenumber":"17721",
    "addr:postcode":"80134",
    "addr:street":"Cottonwood Dr",
    "iso:country":"US",
    "sg:address":"17721 Cottonwood Dr",
    "sg:city":"Parker",
    "sg:classifiers":[
        {
            "category":"Food & Beverages",
            "subcategory":"Liquor & Beverages",
            "type":"Retail Goods"
        }
    ],
    "sg:phone":"+1 303 680 9463",
    "sg:postcode":"80134",
    "sg:province":"CO",
    "wof:name":"Lacd Inc",
    "wof:placetype":"venue"
},
  "geometry": {"coordinates":[-104.781442,39.558014],"type":"Point"}
}