{
  "type": "Feature",
  "properties": {
    "addr:full":"3302 S Newcombe St Lakewood CO 80227",
    "addr:housenumber":"3302",
    "addr:postcode":"80227",
    "addr:street":"S Newcombe St",
    "iso:country":"US",
    "sg:address":"3302 S Newcombe St",
    "sg:city":"Lakewood",
    "sg:classifiers":[
        {
            "category":"Professional",
            "subcategory":"Research",
            "type":"Services"
        }
    ],
    "sg:phone":"+1 303 985 1190",
    "sg:postcode":"80227",
    "sg:province":"CO",
    "wof:name":"CTS Research",
    "wof:placetype":"venue"
},
  "geometry": {"coordinates":[-105.118331,39.654147],"type":"Point"}
}