{
  "type": "Feature",
  "properties": {
    "iso:country":"US",
    "sg:address":"12152 E Mississippi Ave",
    "sg:city":"Aurora",
    "sg:classifiers":[
        {
            "category":"Retail",
            "subcategory":"Laundry & Dry Cleaning",
            "type":"Services"
        }
    ],
    "sg:phone":"+1 720 744 9802",
    "sg:postcode":"80012",
    "sg:province":"CO",
    "sg:tags":[
        "cleaners"
    ],
    "wof:name":"Super Bowl",
    "wof:placetype":"venue"
},
  "geometry": {"coordinates":[-104.845242,39.696529],"type":"Point"}
}