{
  "type": "Feature",
  "properties": {
    "addr:full":"19 N Tejon St Colorado Springs CO 80903",
    "addr:housenumber":"19",
    "addr:postcode":"80903",
    "addr:street":"N Tejon St",
    "iso:country":"US",
    "sg:address":"19 N Tejon St",
    "sg:city":"Colorado Springs",
    "sg:classifiers":[
        {
            "category":"Professional",
            "subcategory":"Lawyer & Legal Services",
            "type":"Services"
        }
    ],
    "sg:phone":"+1 719 219 2544",
    "sg:postcode":"80903",
    "sg:province":"CO",
    "sg:tags":[
        "attorney",
        "referral"
    ],
    "wof:name":"Legal Service Ctr Of America",
    "wof:placetype":"venue"
},
  "geometry": {"coordinates":[-104.823351,38.835151],"type":"Point"}
}