{
  "type": "Feature",
  "properties": {
    "iso:country":"US",
    "sg:address":"301 S Weber St",
    "sg:city":"Colorado Springs",
    "sg:classifiers":[
        {
            "category":"Health Services",
            "subcategory":"Health Practitioner",
            "type":"Services"
        }
    ],
    "sg:phone":"+1 719 473 1813",
    "sg:postcode":"80903",
    "sg:province":"CO",
    "sg:tags":[
        "psychotherapist"
    ],
    "wof:name":"Lisa Routh",
    "wof:placetype":"venue"
},
  "geometry": {"coordinates":[-104.820144,38.828098],"type":"Point"}
}