{
  "type": "Feature",
  "properties": {
    "iso:country":"US",
    "sg:address":"10 Mill St",
    "sg:city":"Copper Mountain",
    "sg:classifiers":[
        {
            "category":"Recreation",
            "type":"Entertainment"
        }
    ],
    "sg:phone":"+1 970 968 2372",
    "sg:postcode":"80455",
    "sg:province":"CO",
    "sg:tags":[
        "equipment",
        "skiing"
    ],
    "wof:name":"Peak Sports",
    "wof:placetype":"venue"
},
  "geometry": {"coordinates":[-105.384379,40.114443],"type":"Point"}
}