{
  "type": "Feature",
  "properties": {
    "iso:country":"US",
    "sg:address":"14967 E Wagon Trail Pl",
    "sg:city":"Aurora",
    "sg:classifiers":[
        {
            "category":"Professional",
            "type":"Services"
        }
    ],
    "sg:phone":"+1 303 400 8488",
    "sg:postcode":"80015",
    "sg:province":"CO",
    "sg:tags":[
        "establishment"
    ],
    "wof:name":"Backyard Putting Greens",
    "wof:placetype":"venue"
},
  "geometry": {"coordinates":[-104.813641,39.629648],"type":"Point"}
}