{
  "type": "Feature",
  "properties": {
    "addr:full":"2005 S Holly St Denver CO 80222",
    "addr:housenumber":"2005",
    "addr:postcode":"80222",
    "addr:street":"S Holly St",
    "iso:country":"US",
    "sg:address":"2005 S Holly St",
    "sg:city":"Denver",
    "sg:classifiers":[
        {
            "category":"Retail",
            "subcategory":"Auto Repair",
            "type":"Services"
        }
    ],
    "sg:phone":"+1 303 691 9484",
    "sg:postcode":"80222",
    "sg:province":"CO",
    "sg:tags":[
        "body",
        "shop"
    ],
    "sg:website":"www.AddisonAuto.com",
    "wof:name":"Addison Auto Repair & Body Shop",
    "wof:placetype":"venue"
},
  "geometry": {"coordinates":[-104.923007,39.680164],"type":"Point"}
}