{
  "type": "Feature",
  "properties": {
    "iso:country":"US",
    "sg:address":"10525 E 40th Ave",
    "sg:city":"Denver",
    "sg:classifiers":[
        {
            "category":"Local Transit",
            "type":"Transportation"
        }
    ],
    "sg:phone":"+1 303 307 9059",
    "sg:postcode":"80239",
    "sg:province":"CO",
    "sg:tags":[
        "limousine"
    ],
    "wof:name":"Majestic Limousine",
    "wof:placetype":"venue"
},
  "geometry": {"coordinates":[-104.86523699999999,39.772996],"type":"Point"}
}