{
  "type": "Feature",
  "properties": {
    "addr:full":"2895 Stephens Rd Boulder CO 80305",
    "addr:housenumber":"2895",
    "addr:postcode":"80305",
    "addr:street":"Stephens Rd",
    "iso:country":"US",
    "sg:address":"2895 Stephens Rd",
    "sg:city":"Boulder",
    "sg:classifiers":[
        {
            "category":"Communications",
            "type":"Services"
        }
    ],
    "sg:phone":"+1 303 494 4601",
    "sg:postcode":"80305",
    "sg:province":"CO",
    "sg:tags":[
        "communication"
    ],
    "wof:name":"Sjm Communications",
    "wof:placetype":"venue"
},
  "geometry": {"coordinates":[-105.25856899999999,39.981201],"type":"Point"}
}