{
  "type": "Feature",
  "properties": {
    "addr:full":"6703 E 47th Avenue Dr Denver CO 80216",
    "addr:housenumber":"6703",
    "addr:postcode":"80216",
    "addr:street":"E 47Th Avenue Dr",
    "iso:country":"US",
    "sg:address":"6703 E 47th Avenue Dr",
    "sg:city":"Denver",
    "sg:classifiers":[
        {
            "category":"Professional",
            "subcategory":"Detective & Security Services",
            "type":"Services"
        }
    ],
    "sg:phone":"+1 303 355 2071",
    "sg:postcode":"80216",
    "sg:province":"CO",
    "sg:tags":[
        "car",
        "armored"
    ],
    "wof:name":"Brink's Inc",
    "wof:placetype":"venue"
},
  "geometry": {"coordinates":[-104.90956799999999,39.782494],"type":"Point"}
}