{
  "type": "Feature",
  "properties": {
    "addr:full":"3275 E Platte Ave Colorado Springs CO 80909",
    "addr:housenumber":"3275",
    "addr:postcode":"80909",
    "addr:street":"E Platte Ave",
    "iso:country":"US",
    "sg:address":"3275 E Platte Ave",
    "sg:city":"Colorado Springs",
    "sg:classifiers":[
        {
            "category":"Banks & Credit Unions",
            "subcategory":"Bank",
            "type":"Services"
        }
    ],
    "sg:phone":"+1 719 634 7477",
    "sg:postcode":"80909",
    "sg:province":"CO",
    "sg:tags":[
        "cashing",
        "check"
    ],
    "wof:name":"United Check Cashing Co",
    "wof:placetype":"venue"
},
  "geometry": {"coordinates":[-104.76944399999999,38.839576],"type":"Point"}
}