{
  "type": "Feature",
  "properties": {
    "addr:full":"1400 10th St Golden CO 80401",
    "addr:housenumber":"1400",
    "addr:postcode":"80401",
    "addr:street":"10Th St",
    "iso:country":"US",
    "sg:address":"1400 10th St",
    "sg:city":"Golden",
    "sg:classifiers":[
        {
            "category":"Travel",
            "subcategory":"Campground",
            "type":"Entertainment"
        }
    ],
    "sg:phone":"+1 303 278 1437",
    "sg:postcode":"80401",
    "sg:province":"CO",
    "sg:website":"www.ci.golden.co.us",
    "wof:name":"Golden Clear Creek Rv Park",
    "wof:placetype":"venue"
},
  "geometry": {"coordinates":[-105.227254,39.755597],"type":"Point"}
}