{
  "type": "Feature",
  "properties": {
    "iso:country":"US",
    "sg:address":"8086 W Bowles Ave",
    "sg:city":"Littleton",
    "sg:classifiers":[
        {
            "category":"Restaurant",
            "type":"Food & Drink"
        }
    ],
    "sg:menulink":"http://www.allmenus.com/co/northeast-jefferson/152256-honeybaked-ham/menu/",
    "sg:phone":"+1 303 948 2128",
    "sg:postcode":"80123",
    "sg:province":"CO",
    "sg:tags":[
        "american"
    ],
    "wof:name":"The HoneyBaked Ham Company",
    "wof:placetype":"venue"
},
  "geometry": {"coordinates":[-105.086243,39.609632],"type":"Point"}
}