{
  "type": "Feature",
  "properties": {
    "iso:country":"US",
    "sg:address":"2610 Baseline Rd",
    "sg:city":"Boulder",
    "sg:classifiers":[
        {
            "category":"Travel",
            "subcategory":"Travel Agent",
            "type":"Entertainment"
        }
    ],
    "sg:phone":"+1 303 499 2242",
    "sg:postcode":"80305",
    "sg:province":"CO",
    "sg:tags":[
        "agency"
    ],
    "sg:website":"www.destinationtravelinc.com",
    "wof:name":"Destination Travel",
    "wof:placetype":"venue"
},
  "geometry": {"coordinates":[-105.263518,40.00007],"type":"Point"}
}