{
  "type": "Feature",
  "properties": {
    "addr:full":"4656 S Wolff St Denver CO 80236",
    "addr:housenumber":"4656",
    "addr:postcode":"80236",
    "addr:street":"S Wolff St",
    "iso:country":"US",
    "sg:address":"4656 S Wolff St",
    "sg:city":"Denver",
    "sg:classifiers":[
        {
            "category":"Travel",
            "subcategory":"Travel Agent",
            "type":"Entertainment"
        }
    ],
    "sg:phone":"+1 303 730 3802",
    "sg:postcode":"80236",
    "sg:province":"CO",
    "sg:tags":[
        "agency"
    ],
    "wof:name":"Sherry Mees Inc",
    "wof:placetype":"venue"
},
  "geometry": {"coordinates":[-105.04985000000001,39.632027],"type":"Point"}
}