{
  "type": "Feature",
  "properties": {
    "iso:country":"US",
    "sg:address":"642 S College Ave",
    "sg:city":"Fort Collins",
    "sg:classifiers":[
        {
            "category":"Shopping",
            "type":"Retail Goods"
        }
    ],
    "sg:phone":"+1 970 493 7233",
    "sg:postcode":"80524",
    "sg:province":"CO",
    "sg:tags":[
        "merchandise"
    ],
    "wof:name":"Imagemaker",
    "wof:placetype":"venue"
},
  "geometry": {"coordinates":[-105.077005,40.578954],"type":"Point"}
}