{
  "type": "Feature",
  "properties": {
    "addr:full":"1350 E 4th St Pueblo CO 81001",
    "addr:housenumber":"1350",
    "addr:postcode":"81001",
    "addr:street":"E 4Th St",
    "iso:country":"US",
    "sg:address":"1350 E 4th St",
    "sg:city":"Pueblo",
    "sg:classifiers":[
        {
            "category":"Autos & Motor Vehicles",
            "subcategory":"Fuel & Gas Station",
            "type":"Retail Goods"
        }
    ],
    "sg:phone":"+1 719 546 2227",
    "sg:postcode":"81001",
    "sg:province":"CO",
    "sg:tags":[
        "oil"
    ],
    "wof:name":"First Stop Phillips 66",
    "wof:placetype":"venue"
},
  "geometry": {"coordinates":[-104.58754399999999,38.271061],"type":"Point"}
}