{
  "type": "Feature",
  "properties": {
    "iso:country":"US",
    "sg:address":"6651 S University Blvd",
    "sg:city":"Centennial",
    "sg:classifiers":[
        {
            "category":"Shopping",
            "subcategory":"Gifts & Souvenirs",
            "type":"Retail Goods"
        },
        {
            "category":"Banks & Credit Unions",
            "subcategory":"Bank",
            "type":"Services"
        }
    ],
    "sg:phone":"+1 303 781 1234",
    "sg:postcode":"80121",
    "sg:province":"CO",
    "sg:tags":[
        "company",
        "indian",
        "finance"
    ],
    "wof:name":"Sante Fe Market",
    "wof:placetype":"venue"
},
  "geometry": {"coordinates":[-104.95944,39.596201],"type":"Point"}
}