{
  "type": "Feature",
  "properties": {
    "iso:country":"US",
    "sg:address":"4323 30th St",
    "sg:city":"Boulder",
    "sg:classifiers":[
        {
            "category":"Shopping",
            "subcategory":"Optical Goods",
            "type":"Retail Goods"
        }
    ],
    "sg:phone":"+1 303 442 7306",
    "sg:postcode":"80301",
    "sg:province":"CO",
    "wof:name":"Focused X Rays L L C",
    "wof:placetype":"venue"
},
  "geometry": {"coordinates":[-105.253911,40.05349],"type":"Point"}
}