{
  "type": "Feature",
  "properties": {
    "iso:country":"US",
    "sg:address":"102 W Pitkin Ave",
    "sg:city":"Pueblo",
    "sg:classifiers":[
        {
            "category":"Personal",
            "subcategory":"Beauty Salon",
            "type":"Services"
        }
    ],
    "sg:phone":"+1 719 545 3535",
    "sg:postcode":"81004",
    "sg:province":"CO",
    "sg:tags":[
        "manicuring"
    ],
    "wof:name":"Unique Nail Boutique & Day Spa",
    "wof:placetype":"venue"
},
  "geometry": {"coordinates":[-104.62564500000001,38.257123],"type":"Point"}
}