{
  "type": "Feature",
  "properties": {
    "addr:full":"1604 9th St Greeley CO 80631",
    "addr:housenumber":"1604",
    "addr:postcode":"80631",
    "addr:street":"9Th St",
    "iso:country":"US",
    "sg:address":"1604 9th St",
    "sg:city":"Greeley",
    "sg:classifiers":[
        {
            "category":"Retail",
            "subcategory":"Auto Repair",
            "type":"Services"
        }
    ],
    "sg:phone":"+1 970 356 6667",
    "sg:postcode":"80631",
    "sg:province":"CO",
    "sg:tags":[
        "repairing",
        "automobile"
    ],
    "wof:name":"Greeley West Auto",
    "wof:placetype":"venue"
},
  "geometry": {"coordinates":[-104.706463,40.423939],"type":"Point"}
}