{
  "type": "Feature",
  "properties": {
    "iso:country":"US",
    "sg:address":"1325 S Colorado Blvd Ste 204",
    "sg:city":"Denver",
    "sg:classifiers":[
        {
            "category":"Organizations",
            "subcategory":"Non-profit Organization",
            "type":"Services"
        }
    ],
    "sg:phone":"+1 303 830 1839",
    "sg:postcode":"80222",
    "sg:province":"CO",
    "sg:tags":[
        "service/non-profit",
        "community"
    ],
    "sg:website":"www.parkinsonrockies.org",
    "wof:name":"Parkinson Association of the Rockies",
    "wof:placetype":"venue"
},
  "geometry": {"coordinates":[-104.94185,39.692018],"type":"Point"}
}