{
  "type": "Feature",
  "properties": {
    "iso:country":"US",
    "sg:address":"1774 Platte St",
    "sg:city":"Denver",
    "sg:classifiers":[
        {
            "category":"Professional",
            "subcategory":"Advertising",
            "type":"Services"
        }
    ],
    "sg:phone":"+1 303 623 1190",
    "sg:postcode":"80202",
    "sg:province":"CO",
    "sg:tags":[
        "counselor",
        "agency"
    ],
    "wof:name":"Aramada Medical Marketing",
    "wof:placetype":"venue"
},
  "geometry": {"coordinates":[-105.00580600000001,39.758962],"type":"Point"}
}