{
  "type": "Feature",
  "properties": {
    "iso:country":"US",
    "sg:address":"235 Main St",
    "sg:city":"Palisade",
    "sg:classifiers":[
        {
            "category":"Cafe",
            "type":"Food & Drink"
        },
        {
            "category":"Restaurant",
            "type":"Food & Drink"
        }
    ],
    "sg:menulink":"http://www.allmenus.com/co/clifton/278382-red-rose-cafe/menu/",
    "sg:phone":"+1 970 464 7673",
    "sg:postcode":"81526",
    "sg:province":"CO",
    "sg:tags":[
        "american",
        "diner"
    ],
    "wof:name":"Red Rose Cafe",
    "wof:placetype":"venue"
},
  "geometry": {"coordinates":[-108.350804,39.11074],"type":"Point"}
}