{
  "type": "Feature",
  "properties": {
    "iso:country":"US",
    "sg:address":"7200 E Dry Creek Rd",
    "sg:city":"Centennial",
    "sg:classifiers":[
        {
            "category":"Professional",
            "subcategory":"Computer Services",
            "type":"Services"
        }
    ],
    "sg:phone":"+1 720 493 1442",
    "sg:postcode":"80112",
    "sg:province":"CO",
    "sg:tags":[
        "consultant",
        "designer"
    ],
    "wof:name":"Titamus Technologies",
    "wof:placetype":"venue"
},
  "geometry": {"coordinates":[-104.904267,39.580525],"type":"Point"}
}