{
  "type": "Feature",
  "properties": {
    "addr:full":"620 E 6th Ave Denver CO 80203",
    "addr:housenumber":"620",
    "addr:postcode":"80203",
    "addr:street":"E 6Th Ave",
    "iso:country":"US",
    "sg:address":"620 E 6th Ave",
    "sg:city":"Denver",
    "sg:classifiers":[
        {
            "category":"Building & Trades",
            "subcategory":"Locksmith",
            "type":"Services"
        }
    ],
    "sg:phone":"+1 303 209 9303",
    "sg:postcode":"80203",
    "sg:province":"CO",
    "sg:tags":[
        "key"
    ],
    "wof:name":"1 A1 L O C K Smith",
    "wof:placetype":"venue"
},
  "geometry": {"coordinates":[-104.979699,39.725493],"type":"Point"}
}