{
  "type": "Feature",
  "properties": {
    "addr:full":"104 Inverness Ter E Englewood CO 80112",
    "addr:housenumber":"104",
    "addr:postcode":"80112",
    "addr:street":"Inverness Ter E",
    "iso:country":"US",
    "sg:address":"104 Inverness Ter E",
    "sg:city":"Englewood",
    "sg:classifiers":[
        {
            "category":"Real Estate",
            "subcategory":"Real Estate Operator",
            "type":"Services"
        }
    ],
    "sg:phone":"+1 303 799 1111",
    "sg:postcode":"80112",
    "sg:province":"CO",
    "sg:tags":[
        "building",
        "nonresidential"
    ],
    "wof:name":"Mgma Realty Corp",
    "wof:placetype":"venue"
},
  "geometry": {"coordinates":[-104.865567,39.576838],"type":"Point"}
}