{
  "type": "Feature",
  "properties": {
    "iso:country":"US",
    "sg:address":"4898 S Indian Trl",
    "sg:city":"Evergreen",
    "sg:classifiers":[
        {
            "category":"Building & Trades",
            "subcategory":"Construction",
            "type":"Services"
        }
    ],
    "sg:phone":"+1 303 670 9919",
    "sg:postcode":"80439",
    "sg:province":"CO",
    "sg:tags":[
        "handyman"
    ],
    "wof:name":"Handy Man Husbands",
    "wof:placetype":"venue"
},
  "geometry": {"coordinates":[-105.31117,39.627279],"type":"Point"}
}