{
  "type": "Feature",
  "properties": {
    "iso:country":"US",
    "sg:address":"1936 Sussex Ln",
    "sg:city":"Colorado Springs",
    "sg:classifiers":[
        {
            "category":"Retail",
            "subcategory":"Photofinishing",
            "type":"Services"
        }
    ],
    "sg:phone":"+1 719 637 8575",
    "sg:postcode":"80909",
    "sg:province":"CO",
    "sg:tags":[
        "photo",
        "finishing"
    ],
    "wof:name":"My Darkroom",
    "wof:placetype":"venue"
},
  "geometry": {"coordinates":[-104.759518,38.860828],"type":"Point"}
}