{
  "type": "Feature",
  "properties": {
    "iso:country":"US",
    "sg:address":"11454 US Hwy 385",
    "sg:city":"Burlington",
    "sg:classifiers":[
        {
            "category":"Real Estate",
            "subcategory":"Architect",
            "type":"Services"
        }
    ],
    "sg:phone":"+1 719 346 7589",
    "sg:postcode":"80807",
    "sg:province":"CO",
    "sg:tags":[
        "illustrator",
        "architectural"
    ],
    "wof:name":"Pekarek's Building Designs",
    "wof:placetype":"venue"
},
  "geometry": {"coordinates":[-102.277709,39.214303],"type":"Point"}
}