{
  "type": "Feature",
  "properties": {
    "iso:country":"US",
    "sg:address":"2379 G Rd",
    "sg:city":"Grand Junction",
    "sg:classifiers":[
        {
            "category":"Wholesale",
            "subcategory":"Machinery & Supplies",
            "type":"Manufacturing & Wholesale Goods"
        }
    ],
    "sg:phone":"+1 970 245 1250",
    "sg:postcode":"81505",
    "sg:province":"CO",
    "sg:tags":[
        "heavy",
        "equipment"
    ],
    "wof:name":"Riverbend Machinery Inc",
    "wof:placetype":"venue"
},
  "geometry": {"coordinates":[-108.610254,39.106238],"type":"Point"}
}