{
  "type": "Feature",
  "properties": {
    "addr:full":"13918 E Mississippi Ave Aurora CO 80012",
    "addr:housenumber":"13918",
    "addr:postcode":"80012",
    "addr:street":"E Mississippi Ave",
    "iso:country":"US",
    "sg:address":"13918 E Mississippi Ave",
    "sg:city":"Aurora",
    "sg:classifiers":[
        {
            "category":"Communications",
            "subcategory":"Radio Station",
            "type":"Services"
        }
    ],
    "sg:phone":"+1 303 881 6366",
    "sg:postcode":"80012",
    "sg:province":"CO",
    "sg:tags":[
        "broadcast",
        "consulting",
        "management"
    ],
    "wof:name":"Virtual Broadcast Media Inc",
    "wof:placetype":"venue"
},
  "geometry": {"coordinates":[-104.826285,39.69654],"type":"Point"}
}