{
  "type": "Feature",
  "properties": {
    "iso:country":"US",
    "sg:address":"1860 Larimer Street Suite 300",
    "sg:city":"Denver",
    "sg:classifiers":[
        {
            "category":"Health Services",
            "subcategory":"Dentist",
            "type":"Services"
        }
    ],
    "sg:phone":"+1 303 296 8527",
    "sg:postcode":"80202",
    "sg:province":"CO",
    "wof:name":"Brian Gurinsky, DDS",
    "wof:placetype":"venue"
},
  "geometry": {"coordinates":[-104.994156,39.751358],"type":"Point"}
}