{
  "type": "Feature",
  "properties": {
    "iso:country":"US",
    "sg:address":"6398 E Mineral Dr",
    "sg:city":"Englewood",
    "sg:classifiers":[
        {
            "category":"Professional",
            "type":"Services"
        }
    ],
    "sg:phone":"+1 303 220 5124",
    "sg:postcode":"80112",
    "sg:province":"CO",
    "wof:name":"Taxtime Inc",
    "wof:placetype":"venue"
},
  "geometry": {"coordinates":[-104.91653599999999,39.572838],"type":"Point"}
}