{
  "type": "Feature",
  "properties": {
    "iso:country":"US",
    "sg:address":"200 E 1st St",
    "sg:city":"Trinidad",
    "sg:classifiers":[
        {
            "category":"Government",
            "subcategory":"Office",
            "type":"Public Place"
        }
    ],
    "sg:phone":"+1 719 846 2081",
    "sg:postcode":"81082",
    "sg:province":"CO",
    "wof:name":"Las Animas Clerk-Commissioners",
    "wof:placetype":"venue"
},
  "geometry": {"coordinates":[-104.50280600000001,37.168833],"type":"Point"}
}