{
  "type": "Feature",
  "properties": {
    "iso:country":"US",
    "sg:address":"727 Pearl St",
    "sg:city":"Denver",
    "sg:classifiers":[
        {
            "category":"Banks & Credit Unions",
            "subcategory":"Financial Services",
            "type":"Services"
        }
    ],
    "sg:phone":"+1 303 863 8938",
    "sg:postcode":"80203",
    "sg:province":"CO",
    "sg:tags":[
        "investor"
    ],
    "wof:name":"Brother John Investments LLC",
    "wof:placetype":"venue"
},
  "geometry": {"coordinates":[-104.980007,39.729016],"type":"Point"}
}