{
  "type": "Feature",
  "properties": {
    "addr:full":"5038 S Linden Dr Englewood CO 80110",
    "addr:housenumber":"5038",
    "addr:postcode":"80110",
    "addr:street":"S Linden Dr",
    "iso:country":"US",
    "sg:address":"5038 S Linden Dr",
    "sg:city":"Englewood",
    "sg:classifiers":[
        {
            "category":"Wholesale",
            "subcategory":"Construction Materials",
            "type":"Manufacturing & Wholesale Goods"
        }
    ],
    "sg:phone":"+1 303 794 5730",
    "sg:postcode":"80110",
    "sg:province":"CO",
    "sg:tags":[
        "fence"
    ],
    "wof:name":"B & B Drilling Co",
    "wof:placetype":"venue"
},
  "geometry": {"coordinates":[-105.03317,39.624881],"type":"Point"}
}