{
  "type": "Feature",
  "properties": {
    "addr:full":"1560 Teller St Lakewood CO 80214",
    "addr:housenumber":"1560",
    "addr:postcode":"80214",
    "addr:street":"Teller St",
    "iso:country":"US",
    "sg:address":"1560 Teller St",
    "sg:city":"Lakewood",
    "sg:classifiers":[
        {
            "category":"Building & Trades",
            "subcategory":"Cleaning & Sanitation",
            "type":"Services"
        }
    ],
    "sg:phone":"+1 303 937 0717",
    "sg:postcode":"80214",
    "sg:province":"CO",
    "sg:tags":[
        "carpet"
    ],
    "wof:name":"Disaster Solutions",
    "wof:placetype":"venue"
},
  "geometry": {"coordinates":[-105.075896,39.741006],"type":"Point"}
}