{
  "type": "Feature",
  "properties": {
    "addr:full":"316 20th St Kremmling CO 80459",
    "addr:housenumber":"316",
    "addr:postcode":"80459",
    "addr:street":"20Th St",
    "iso:country":"US",
    "sg:address":"316 20th St",
    "sg:city":"Kremmling",
    "sg:classifiers":[
        {
            "category":"Building & Trades",
            "subcategory":"Construction",
            "type":"Services"
        }
    ],
    "sg:phone":"+1 970 724 2942",
    "sg:postcode":"80459",
    "sg:province":"CO",
    "sg:tags":[
        "concrete",
        "contractor"
    ],
    "wof:name":"F & I Flatwork",
    "wof:placetype":"venue"
},
  "geometry": {"coordinates":[-106.369353,40.059975],"type":"Point"}
}