{
  "type": "Feature",
  "properties": {
    "iso:country":"US",
    "sg:address":"203 Highland Ter",
    "sg:city":"Breckenridge",
    "sg:classifiers":[
        {
            "category":"Travel",
            "subcategory":"Hotels & Motels",
            "type":"Entertainment"
        }
    ],
    "sg:phone":"+1 970 453 5983",
    "sg:postcode":"80424",
    "sg:province":"CO",
    "sg:tags":[
        "cottage",
        "cabin"
    ],
    "wof:name":"Cwh & Janeslodges",
    "wof:placetype":"venue"
},
  "geometry": {"coordinates":[-106.040463,39.480115],"type":"Point"}
}