{
  "type": "Feature",
  "properties": {
    "addr:full":"5646 Orion Ct Golden CO 80403",
    "addr:housenumber":"5646",
    "addr:postcode":"80403",
    "addr:street":"Orion Ct",
    "iso:country":"US",
    "sg:address":"5646 Orion Ct",
    "sg:city":"Golden",
    "sg:classifiers":[
        {
            "category":"Building & Trades",
            "subcategory":"Construction",
            "type":"Services"
        }
    ],
    "sg:phone":"+1 303 431 1685",
    "sg:postcode":"80403",
    "sg:province":"CO",
    "sg:tags":[
        "excavation",
        "contractor"
    ],
    "wof:name":"Baerg Bros Inc",
    "wof:placetype":"venue"
},
  "geometry": {"coordinates":[-105.179528,39.799198],"type":"Point"}
}