{
  "type": "Feature",
  "properties": {
    "iso:country":"US",
    "sg:address":"6087 E 52nd Ave",
    "sg:city":"Commerce City",
    "sg:classifiers":[
        {
            "category":"Building & Trades",
            "subcategory":"Construction",
            "type":"Services"
        }
    ],
    "sg:phone":"+1 303 289 5770",
    "sg:postcode":"80022",
    "sg:province":"CO",
    "sg:tags":[
        "tank"
    ],
    "wof:name":"Onnen",
    "wof:placetype":"venue"
},
  "geometry": {"coordinates":[-104.918779,39.791169],"type":"Point"}
}