{
  "type": "Feature",
  "properties": {
    "iso:country":"US",
    "sg:address":"2235 Broadway St",
    "sg:city":"Boulder",
    "sg:classifiers":[
        {
            "category":"Professional",
            "subcategory":"Lawyer & Legal Services",
            "type":"Services"
        }
    ],
    "sg:phone":"+1 303 440 0123",
    "sg:postcode":"80302",
    "sg:province":"CO",
    "sg:tags":[
        "attorney"
    ],
    "sg:website":"www.merteslaw.com",
    "wof:name":"Mertes Law Ofc",
    "wof:placetype":"venue"
},
  "geometry": {"coordinates":[-105.28098900000001,40.020555],"type":"Point"}
}