{
  "type": "Feature",
  "properties": {
    "iso:country":"US",
    "sg:address":"9992 E Idaho Cir",
    "sg:city":"Denver",
    "sg:classifiers":[
        {
            "category":"Food & Beverages",
            "subcategory":"Liquor & Beverages",
            "type":"Retail Goods"
        }
    ],
    "sg:phone":"+1 303 755 3849",
    "sg:postcode":"80247",
    "sg:province":"CO",
    "sg:tags":[
        "alcoholic"
    ],
    "wof:name":"Beaver Creek Wines & Spirits",
    "wof:placetype":"venue"
},
  "geometry": {"coordinates":[-104.87244,39.691599],"type":"Point"}
}