{
  "type": "Feature",
  "properties": {
    "iso:country":"US",
    "sg:address":"6355 Basalt Ct",
    "sg:city":"Colorado Springs",
    "sg:classifiers":[
        {
            "category":"Food & Beverages",
            "subcategory":"Groceries & Convenience Stores",
            "type":"Retail Goods"
        }
    ],
    "sg:phone":"+1 719 638 4525",
    "sg:postcode":"80922",
    "sg:province":"CO",
    "wof:name":"Mayas Mystical Market",
    "wof:placetype":"venue"
},
  "geometry": {"coordinates":[-104.710385,38.907182],"type":"Point"}
}