{
  "type": "Feature",
  "properties": {
    "iso:country":"US",
    "sg:address":"88 Lamar St",
    "sg:city":"Broomfield",
    "sg:classifiers":[
        {
            "category":"Health Services",
            "subcategory":"Doctor",
            "type":"Services"
        }
    ],
    "sg:phone":"+1 303 466 7300",
    "sg:postcode":"80020",
    "sg:province":"CO",
    "sg:tags":[
        "dentist"
    ],
    "wof:name":"George D Pollard DDS",
    "wof:placetype":"venue"
},
  "geometry": {"coordinates":[-105.066974,39.914296],"type":"Point"}
}