{
  "type": "Feature",
  "properties": {
    "iso:country":"US",
    "sg:address":"2069 Stagecoach Ct",
    "sg:city":"Grand Junction",
    "sg:classifiers":[
        {
            "category":"Shopping",
            "subcategory":"Gifts & Souvenirs",
            "type":"Retail Goods"
        }
    ],
    "sg:phone":"+1 970 245 1303",
    "sg:postcode":"81503",
    "sg:province":"CO",
    "sg:tags":[
        "party",
        "supply"
    ],
    "wof:name":"Elite Events",
    "wof:placetype":"venue"
},
  "geometry": {"coordinates":[-108.665498,39.103606],"type":"Point"}
}