{
  "type": "Feature",
  "properties": {
    "iso:country":"US",
    "sg:address":"34604 Co Rd 15",
    "sg:city":"Windsor",
    "sg:classifiers":[
        {
            "category":"Farming",
            "subcategory":"Farm",
            "type":"Manufacturing & Wholesale Goods"
        }
    ],
    "sg:phone":"+1 970 686 2257",
    "sg:postcode":"80550",
    "sg:province":"CO",
    "sg:tags":[
        "crop",
        "general"
    ],
    "wof:name":"Greenacres Farm",
    "wof:placetype":"venue"
},
  "geometry": {"coordinates":[-104.926467,40.499337],"type":"Point"}
}