{
  "type": "Feature",
  "properties": {
    "iso:country":"US",
    "sg:address":"112 W Montezuma Ave",
    "sg:city":"Cortez",
    "sg:classifiers":[
        {
            "category":"Professional",
            "type":"Services"
        }
    ],
    "sg:phone":"+1 970 565 4465",
    "sg:postcode":"81321",
    "sg:province":"CO",
    "sg:tags":[
        "establishment"
    ],
    "wof:name":"Souder Miller & Assoc",
    "wof:placetype":"venue"
},
  "geometry": {"coordinates":[-108.587749,37.350934],"type":"Point"}
}