{
  "type": "Feature",
  "properties": {
    "iso:country":"US",
    "sg:address":"1108 S Marshall St",
    "sg:city":"Denver",
    "sg:classifiers":[
        {
            "category":"Manufacturing",
            "subcategory":"Printing",
            "type":"Manufacturing & Wholesale Goods"
        }
    ],
    "sg:phone":"+1 303 727 8314",
    "sg:postcode":"80232",
    "sg:province":"CO",
    "sg:tags":[
        "publishing"
    ],
    "wof:name":"Risk Management Publishing",
    "wof:placetype":"venue"
},
  "geometry": {"coordinates":[-105.06803600000001,39.696605],"type":"Point"}
}