{
  "type": "Feature",
  "properties": {
    "addr:full":"3855 W Radcliff Ave Denver CO 80236",
    "addr:housenumber":"3855",
    "addr:postcode":"80236",
    "addr:street":"W Radcliff Ave",
    "iso:country":"US",
    "sg:address":"3855 W Radcliff Ave",
    "sg:city":"Denver",
    "sg:classifiers":[
        {
            "category":"Real Estate",
            "subcategory":"Real Estate Services",
            "type":"Services"
        }
    ],
    "sg:phone":"+1 303 219 6994",
    "sg:postcode":"80236",
    "sg:province":"CO",
    "sg:tags":[
        "apartment",
        "rental",
        "finder"
    ],
    "wof:name":"Rent 2 Own Vehicle Locators Co",
    "wof:placetype":"venue"
},
  "geometry": {"coordinates":[-105.03917,39.63654],"type":"Point"}
}