{
  "type": "Feature",
  "properties": {
    "iso:country":"US",
    "sg:address":"815 W Furry St",
    "sg:city":"Holyoke",
    "sg:phone":"+1 970 854 2100",
    "sg:postcode":"80734",
    "sg:province":"CO",
    "sg:tags":[
        "wheat",
        "beef",
        "farm",
        "corn",
        "cattle",
        "feedlot"
    ],
    "wof:name":"Perry Carruthers",
    "wof:placetype":"venue"
},
  "geometry": {"coordinates":[-102.31150100000001,40.583611],"type":"Point"}
}