{
  "type": "Feature",
  "properties": {
    "addr:full":"365 Warren Ave Silverthorne CO 80498",
    "addr:housenumber":"365",
    "addr:postcode":"80498",
    "addr:street":"Warren Ave",
    "iso:country":"US",
    "sg:address":"365 Warren Ave",
    "sg:city":"Silverthorne",
    "sg:classifiers":[
        {
            "category":"Building & Trades",
            "subcategory":"Construction",
            "type":"Services"
        }
    ],
    "sg:phone":"+1 970 262 6968",
    "sg:postcode":"80498",
    "sg:province":"CO",
    "sg:tags":[
        "resurfacing",
        "laying",
        "refinishing",
        "floor"
    ],
    "wof:name":"Ohana Floor Designs",
    "wof:placetype":"venue"
},
  "geometry": {"coordinates":[-106.077933,39.629047],"type":"Point"}
}