{
  "type": "Feature",
  "properties": {
    "iso:country":"US",
    "sg:address":"333 W Hampden Ave",
    "sg:city":"Englewood",
    "sg:classifiers":[
        {
            "category":"Insurance",
            "subcategory":"Insurance Agent",
            "type":"Services"
        }
    ],
    "sg:phone":"+1 303 789 1854",
    "sg:postcode":"80110",
    "sg:province":"CO",
    "wof:name":"Colorado Insurors Svc",
    "wof:placetype":"venue"
},
  "geometry": {"coordinates":[-104.992165,39.653307],"type":"Point"}
}