{
  "type": "Feature",
  "properties": {
    "iso:country":"US",
    "sg:address":"2485 Curtis St",
    "sg:city":"Denver",
    "sg:classifiers":[
        {
            "category":"Building & Trades",
            "subcategory":"Locksmith",
            "type":"Services"
        }
    ],
    "sg:phone":"+1 866 577 4661",
    "sg:postcode":"80205",
    "sg:province":"CO",
    "sg:tags":[
        "key"
    ],
    "wof:name":"1 24 7 Available Emergency Locksmith",
    "wof:placetype":"venue"
},
  "geometry": {"coordinates":[-104.98419199999999,39.755602],"type":"Point"}
}