{
  "type": "Feature",
  "properties": {
    "addr:full":"301 Denver Ave Fort Lupton CO 80621",
    "addr:housenumber":"301",
    "addr:postcode":"80621",
    "addr:street":"Denver Ave",
    "iso:country":"US",
    "sg:address":"301 Denver Ave",
    "sg:city":"Fort Lupton",
    "sg:classifiers":[
        {
            "category":"Wholesale",
            "subcategory":"Hardware",
            "type":"Manufacturing & Wholesale Goods"
        }
    ],
    "sg:phone":"+1 303 857 9500",
    "sg:postcode":"80621",
    "sg:province":"CO",
    "sg:tags":[
        "fastener"
    ],
    "wof:name":"Fastenal Co",
    "wof:placetype":"venue"
},
  "geometry": {"coordinates":[-104.810506,40.083245],"type":"Point"}
}