{
  "type": "Feature",
  "properties": {
    "iso:country":"US",
    "sg:address":"9121 Stuart St",
    "sg:city":"Westminster",
    "sg:classifiers":[
        {
            "category":"Building & Trades",
            "subcategory":"Construction",
            "type":"Services"
        }
    ],
    "sg:phone":"+1 303 427 1151",
    "sg:postcode":"80031",
    "sg:province":"CO",
    "sg:tags":[
        "contractor"
    ],
    "wof:name":"Strange Stone Art Inc",
    "wof:placetype":"venue"
},
  "geometry": {"coordinates":[-105.04069699999999,39.861538],"type":"Point"}
}