{
  "type": "Feature",
  "properties": {
    "iso:country":"US",
    "sg:address":"23 S Indiana Pl",
    "sg:city":"Golden",
    "sg:classifiers":[
        {
            "category":"Professional",
            "subcategory":"Business Services",
            "type":"Services"
        }
    ],
    "sg:phone":"+1 303 277 9488",
    "sg:postcode":"80401",
    "sg:province":"CO",
    "sg:tags":[
        "lecture",
        "bureau",
        "seminar"
    ],
    "sg:website":"www.linmcneil.com",
    "wof:name":"Choices & Changes Unlimited",
    "wof:placetype":"venue"
},
  "geometry": {"coordinates":[-105.165504,39.716157],"type":"Point"}
}