{
  "type": "Feature",
  "properties": {
    "addr:full":"251 N Commercial St Trinidad CO 81082",
    "addr:housenumber":"251",
    "addr:postcode":"81082",
    "addr:street":"N Commercial St",
    "iso:country":"US",
    "sg:address":"251 N Commercial St",
    "sg:city":"Trinidad",
    "sg:classifiers":[
        {
            "category":"Freight",
            "type":"Transportation"
        }
    ],
    "sg:phone":"+1 719 846 1522",
    "sg:postcode":"81082",
    "sg:province":"CO",
    "sg:tags":[
        "dry",
        "bulk",
        "trucking"
    ],
    "wof:name":"Northwest Logistics",
    "wof:placetype":"venue"
},
  "geometry": {"coordinates":[-104.506148,37.16918],"type":"Point"}
}