{
  "type": "Feature",
  "properties": {
    "addr:full":"2415 N Wahsatch Ave Colorado Springs CO 80907",
    "addr:housenumber":"2415",
    "addr:postcode":"80907",
    "addr:street":"N Wahsatch Ave",
    "iso:country":"US",
    "sg:address":"2415 N Wahsatch Ave",
    "sg:city":"Colorado Springs",
    "sg:classifiers":[
        {
            "category":"Shopping",
            "subcategory":"Florist",
            "type":"Retail Goods"
        }
    ],
    "sg:phone":"+1 719 444 8650",
    "sg:postcode":"80907",
    "sg:province":"CO",
    "wof:name":"Jmk Petal Pusher X Press LLC",
    "wof:placetype":"venue"
},
  "geometry": {"coordinates":[-104.816118,38.869686],"type":"Point"}
}