{
  "type": "Feature",
  "properties": {
    "iso:country":"US",
    "sg:address":"4600 S Syracuse St",
    "sg:city":"Denver",
    "sg:classifiers":[
        {
            "category":"Professional",
            "subcategory":"Management & Consulting",
            "type":"Services"
        }
    ],
    "sg:phone":"+1 303 256 6500",
    "sg:postcode":"80237",
    "sg:province":"CO",
    "sg:tags":[
        "agency",
        "employment",
        "business"
    ],
    "wof:name":"Icon Solutions LLC",
    "wof:placetype":"venue"
},
  "geometry": {"coordinates":[-104.89976299999999,39.62815],"type":"Point"}
}