{
  "type": "Feature",
  "properties": {
    "addr:full":"1328 Pearl St Boulder CO 80302",
    "addr:housenumber":"1328",
    "addr:postcode":"80302",
    "addr:street":"Pearl St",
    "iso:country":"US",
    "sg:address":"1328 Pearl St",
    "sg:city":"Boulder",
    "sg:classifiers":[
        {
            "category":"Home & Garden",
            "subcategory":"Furniture",
            "type":"Retail Goods"
        }
    ],
    "sg:phone":"+1 303 442 2533",
    "sg:postcode":"80302",
    "sg:province":"CO",
    "sg:tags":[
        "hammock"
    ],
    "wof:name":"Hangouts Handwoven Hammocks",
    "wof:placetype":"venue"
},
  "geometry": {"coordinates":[-105.277636,40.018297],"type":"Point"}
}