{
  "type": "Feature",
  "properties": {
    "iso:country":"US",
    "sg:address":"275 Clayton St",
    "sg:city":"Denver",
    "sg:classifiers":[
        {
            "category":"Personal",
            "subcategory":"Beauty Salon",
            "type":"Services"
        }
    ],
    "sg:phone":"+1 303 831 7546",
    "sg:postcode":"80206",
    "sg:province":"CO",
    "sg:tags":[
        "treatment",
        "skin"
    ],
    "wof:name":"Euphora Skin Spa",
    "wof:placetype":"venue"
},
  "geometry": {"coordinates":[-104.955918,39.719782],"type":"Point"}
}