{
  "type": "Feature",
  "properties": {
    "iso:country":"US",
    "sg:address":"418 State Ave",
    "sg:city":"Alamosa",
    "sg:classifiers":[
        {
            "category":"Banks & Credit Unions",
            "subcategory":"Investment Brokerage",
            "type":"Services"
        }
    ],
    "sg:phone":"+1 719 587 0091",
    "sg:postcode":"81101",
    "sg:province":"CO",
    "sg:tags":[
        "security"
    ],
    "wof:name":"Edward Jones 06145",
    "wof:placetype":"venue"
},
  "geometry": {"coordinates":[-105.865414,37.469096],"type":"Point"}
}