{
  "type": "Feature",
  "properties": {
    "addr:full":"3709 Windflower Cir Colorado Springs CO 80918",
    "addr:housenumber":"3709",
    "addr:postcode":"80918",
    "addr:street":"Windflower Cir",
    "iso:country":"US",
    "sg:address":"3709 Windflower Cir",
    "sg:city":"Colorado Springs",
    "sg:classifiers":[
        {
            "category":"Shopping",
            "type":"Retail Goods"
        }
    ],
    "sg:phone":"+1 719 599 4248",
    "sg:postcode":"80918",
    "sg:province":"CO",
    "sg:tags":[
        "cosmetic",
        "perfume"
    ],
    "wof:name":"Jafra Cosmetics",
    "wof:placetype":"venue"
},
  "geometry": {"coordinates":[-104.761792,38.8964],"type":"Point"}
}