{
  "type": "Feature",
  "properties": {
    "iso:country":"US",
    "sg:address":"204 W Laurel St",
    "sg:city":"Fort Collins",
    "sg:classifiers":[
        {
            "category":"Professional",
            "subcategory":"Management & Consulting",
            "type":"Services"
        }
    ],
    "sg:phone":"+1 970 484 7555",
    "sg:postcode":"80521",
    "sg:province":"CO",
    "sg:tags":[
        "consultant",
        "educational"
    ],
    "wof:name":"International Studies Abroad",
    "wof:placetype":"venue"
},
  "geometry": {"coordinates":[-105.079292,40.578186],"type":"Point"}
}