{
  "type": "Feature",
  "properties": {
    "addr:full":"4045 Wadsworth Blvd Wheat Ridge CO 80033",
    "addr:housenumber":"4045",
    "addr:postcode":"80033",
    "addr:street":"Wadsworth Blvd",
    "iso:country":"US",
    "sg:address":"4045 Wadsworth Blvd",
    "sg:city":"Wheat Ridge",
    "sg:classifiers":[
        {
            "category":"Health Services",
            "subcategory":"Medical Lab",
            "type":"Services"
        }
    ],
    "sg:phone":"+1 303 420 0802",
    "sg:postcode":"80033",
    "sg:province":"CO",
    "sg:tags":[
        "laboratory"
    ],
    "wof:name":"Laboratory Corp Of America",
    "wof:placetype":"venue"
},
  "geometry": {"coordinates":[-105.081474,39.771687],"type":"Point"}
}