{
  "type": "Feature",
  "properties": {
    "addr:full":"1605 E Evans Avenue Denver CO 80210",
    "addr:housenumber":"1605",
    "addr:postcode":"80210",
    "addr:street":"E Evans Avenue",
    "iso:country":"US",
    "sg:address":"1605 E Evans Avenue",
    "sg:city":"Denver",
    "sg:classifiers":[
        {
            "category":"Utilities",
            "subcategory":"Mobile Phone",
            "type":"Services"
        },
        {
            "category":"Coffee & Tea",
            "type":"Food & Drink"
        }
    ],
    "sg:phone":"+1 303 722 2901",
    "sg:postcode":"80210",
    "sg:province":"CO",
    "sg:tags":[
        "shop",
        "wi-fi",
        "espresso",
        "hotspot",
        "restaurant"
    ],
    "sg:website":"http://www.starbuckscoffee.com",
    "wof:name":"Starbucks Coffee",
    "wof:placetype":"venue"
},
  "geometry": {"coordinates":[-104.968339,39.678612],"type":"Point"}
}