{
  "type": "Feature",
  "properties": {
    "iso:country":"US",
    "sg:address":"709 E Riverview Ave",
    "sg:city":"Fort Morgan",
    "sg:classifiers":[
        {
            "category":"Communications",
            "subcategory":"Radio Station",
            "type":"Services"
        }
    ],
    "sg:phone":"+1 970 867 0970",
    "sg:postcode":"80701",
    "sg:province":"CO",
    "sg:tags":[
        "company",
        "broadcasting"
    ],
    "wof:name":"JMS Broadcasting",
    "wof:placetype":"venue"
},
  "geometry": {"coordinates":[-103.792967,40.261282],"type":"Point"}
}