{
  "type": "Feature",
  "properties": {
    "addr:full":"1920 Pine Grove Rd Steamboat Spgs CO 80487",
    "addr:housenumber":"1920",
    "addr:postcode":"80487",
    "addr:street":"Pine Grove Rd Steamboat Spgs",
    "iso:country":"US",
    "sg:address":"1920 Pine Grove Rd",
    "sg:city":"Steamboat Spgs",
    "sg:classifiers":[
        {
            "category":"Personal",
            "subcategory":"Beauty Salon",
            "type":"Services"
        }
    ],
    "sg:phone":"+1 970 870 6541",
    "sg:postcode":"80487",
    "sg:province":"CO",
    "wof:name":"Applause Hair & Nail Salon",
    "wof:placetype":"venue"
},
  "geometry": {"coordinates":[-106.81987700000001,40.462254],"type":"Point"}
}