{
  "type": "Feature",
  "properties": {
    "addr:full":"3801 E Florida Ave Denver CO 80210",
    "addr:housenumber":"3801",
    "addr:postcode":"80210",
    "addr:street":"E Florida Ave",
    "iso:country":"US",
    "sg:address":"3801 E Florida Ave",
    "sg:city":"Denver",
    "sg:classifiers":[
        {
            "category":"Professional",
            "type":"Services"
        }
    ],
    "sg:phone":"+1 303 691 1964",
    "sg:postcode":"80210",
    "sg:province":"CO",
    "wof:name":"Hartthrob Fo Denver Inc",
    "wof:placetype":"venue"
},
  "geometry": {"coordinates":[-104.940629,39.689319],"type":"Point"}
}