{
  "type": "Feature",
  "properties": {
    "iso:country":"US",
    "sg:address":"2259 Kearney St",
    "sg:city":"Denver",
    "sg:classifiers":[
        {
            "category":"Professional",
            "subcategory":"Accounting & Tax Preparation",
            "type":"Services"
        }
    ],
    "sg:phone":"+1 303 355 7385",
    "sg:postcode":"80207",
    "sg:province":"CO",
    "sg:tags":[
        "return",
        "filing"
    ],
    "wof:name":"Apt Accounting & Tax Svc",
    "wof:placetype":"venue"
},
  "geometry": {"coordinates":[-104.917626,39.750008],"type":"Point"}
}