{
  "type": "Feature",
  "properties": {
    "iso:country":"US",
    "sg:address":"21 Crystal Cir",
    "sg:city":"Carbondale",
    "sg:classifiers":[
        {
            "category":"Building & Trades",
            "subcategory":"Plumbing",
            "type":"Services"
        }
    ],
    "sg:phone":"+1 970 963 8584",
    "sg:postcode":"81623",
    "sg:province":"CO",
    "sg:tags":[
        "plumbing",
        "contractor"
    ],
    "wof:name":"APD Heating & Plumbing Inc",
    "wof:placetype":"venue"
},
  "geometry": {"coordinates":[-107.208549,39.395325],"type":"Point"}
}