{
  "type": "Feature",
  "properties": {
    "iso:country":"US",
    "sg:address":"2580 Kerr Gulch Rd",
    "sg:city":"Evergreen",
    "sg:classifiers":[
        {
            "category":"Professional",
            "subcategory":"Management & Consulting",
            "type":"Services"
        }
    ],
    "sg:phone":"+1 303 674 7864",
    "sg:postcode":"80439",
    "sg:province":"CO",
    "sg:tags":[
        "consultant",
        "business"
    ],
    "wof:name":"Mid-America Freight Ways",
    "wof:placetype":"venue"
},
  "geometry": {"coordinates":[-105.308773,39.673636],"type":"Point"}
}