{
  "type": "Feature",
  "properties": {
    "iso:country":"US",
    "sg:address":"215 Carson Ave",
    "sg:city":"Alamosa",
    "sg:classifiers":[
        {
            "category":"Shopping",
            "type":"Retail Goods"
        }
    ],
    "sg:phone":"+1 719 589 3889",
    "sg:postcode":"81101",
    "sg:province":"CO",
    "sg:tags":[
        "equipment",
        "care",
        "health",
        "home"
    ],
    "wof:name":"Roth Medical Inc",
    "wof:placetype":"venue"
},
  "geometry": {"coordinates":[-105.881846,37.471292],"type":"Point"}
}