{
  "type": "Feature",
  "properties": {
    "addr:full":"6370 Kearney St Commerce City CO 80022",
    "addr:housenumber":"6370",
    "addr:postcode":"80022",
    "addr:street":"Kearney St",
    "iso:country":"US",
    "sg:address":"6370 Kearney St",
    "sg:city":"Commerce City",
    "sg:classifiers":[
        {
            "category":"Retail",
            "subcategory":"Auto Repair",
            "type":"Services"
        }
    ],
    "sg:phone":"+1 303 227 3564",
    "sg:postcode":"80022",
    "sg:province":"CO",
    "sg:tags":[
        "body",
        "automobile",
        "painting"
    ],
    "wof:name":"Manuel's Body & Paint",
    "wof:placetype":"venue"
},
  "geometry": {"coordinates":[-104.917494,39.812468],"type":"Point"}
}