{
  "type": "Feature",
  "properties": {
    "iso:country":"US",
    "sg:address":"1776 S Jackson St",
    "sg:city":"Denver",
    "sg:classifiers":[
        {
            "category":"Professional",
            "type":"Services"
        }
    ],
    "sg:phone":"+1 303 639 6021",
    "sg:postcode":"80210",
    "sg:province":"CO",
    "sg:tags":[
        "establishment"
    ],
    "wof:name":"JDH Capital LLC",
    "wof:placetype":"venue"
},
  "geometry": {"coordinates":[-104.942943,39.685306],"type":"Point"}
}