{
  "type": "Feature",
  "properties": {
    "iso:country":"US",
    "sg:address":"746 Cleveland Ave",
    "sg:city":"Loveland",
    "sg:classifiers":[
        {
            "category":"Banks & Credit Unions",
            "subcategory":"Bank",
            "type":"Services"
        }
    ],
    "sg:phone":"+1 970 669 4747",
    "sg:postcode":"80537",
    "sg:province":"CO",
    "sg:tags":[
        "state"
    ],
    "wof:name":"Big Thompson Federal Credit Un",
    "wof:placetype":"venue"
},
  "geometry": {"coordinates":[-105.074426,40.399127],"type":"Point"}
}