{
  "type": "Feature",
  "properties": {
    "iso:country":"US",
    "sg:address":"404 Broadway",
    "sg:city":"Denver",
    "sg:classifiers":[
        {
            "category":"Restaurant",
            "type":"Food & Drink"
        }
    ],
    "sg:phone":"+1 303 778 9605",
    "sg:postcode":"80203",
    "sg:province":"CO",
    "sg:tags":[
        "traditional",
        "american"
    ],
    "sg:website":"www.myspace.com/club404",
    "wof:name":"404 Club",
    "wof:placetype":"venue"
},
  "geometry": {"coordinates":[-104.98699999999999,39.722698],"type":"Point"}
}