{
  "type": "Feature",
  "properties": {
    "addr:full":"8178 E Phillips Ave Englewood CO 80112",
    "addr:housenumber":"8178",
    "addr:postcode":"80112",
    "addr:street":"E Phillips Ave",
    "iso:country":"US",
    "sg:address":"8178 E Phillips Ave",
    "sg:city":"Englewood",
    "sg:classifiers":[
        {
            "category":"Professional",
            "type":"Services"
        }
    ],
    "sg:phone":"+1 303 694 3859",
    "sg:postcode":"80112",
    "sg:province":"CO",
    "wof:name":"John S Hoofnagle LLc",
    "wof:placetype":"venue"
},
  "geometry": {"coordinates":[-104.894706,39.56747],"type":"Point"}
}