{
  "type": "Feature",
  "properties": {
    "iso:country":"US",
    "sg:address":"425 Coffman St",
    "sg:city":"Longmont",
    "sg:classifiers":[
        {
            "category":"Real Estate",
            "subcategory":"Real Estate Agent",
            "type":"Services"
        }
    ],
    "sg:phone":"+1 303 776 1105",
    "sg:postcode":"80501",
    "sg:province":"CO",
    "sg:tags":[
        "builder",
        "agency",
        "r",
        "family"
    ],
    "wof:name":"Turner Realty",
    "wof:placetype":"venue"
},
  "geometry": {"coordinates":[-105.10390599999999,40.166974],"type":"Point"}
}