{
  "type": "Feature",
  "properties": {
    "addr:full":"301 S Howes St Fort Collins CO 80521",
    "addr:housenumber":"301",
    "addr:postcode":"80521",
    "addr:street":"S Howes St",
    "iso:country":"US",
    "sg:address":"301 S Howes St",
    "sg:city":"Fort Collins",
    "sg:classifiers":[
        {
            "category":"Government",
            "subcategory":"Police Station",
            "type":"Public Place"
        }
    ],
    "sg:phone":"+1 970 482 3422",
    "sg:postcode":"80521",
    "sg:province":"CO",
    "sg:tags":[
        "federal"
    ],
    "wof:name":"Federal Bureau-Investigation",
    "wof:placetype":"venue"
},
  "geometry": {"coordinates":[-105.080719,40.58287],"type":"Point"}
}