{
  "type": "Feature",
  "properties": {
    "addr:full":"1044 Lincoln Street Denver CO 80203",
    "addr:housenumber":"1044",
    "addr:postcode":"80203",
    "addr:street":"Lincoln Street",
    "iso:country":"US",
    "sg:address":"1044 Lincoln Street",
    "sg:city":"Denver",
    "sg:classifiers":[
        {
            "category":"Communications",
            "subcategory":"Television Station",
            "type":"Services"
        }
    ],
    "sg:phone":"+1 303 830 6555",
    "sg:postcode":"80203",
    "sg:province":"CO",
    "wof:name":"Kcnc Tv News 4",
    "wof:placetype":"venue"
},
  "geometry": {"coordinates":[-104.98600500000001,39.73263],"type":"Point"}
}