{
  "type": "Feature",
  "properties": {
    "iso:country":"US",
    "sg:address":"1044 Lincoln Street",
    "sg:city":"Denver",
    "sg:classifiers":[
        {
            "category":"Communications",
            "subcategory":"Television Station",
            "type":"Services"
        }
    ],
    "sg:phone":"+1 303 830 6555",
    "sg:postcode":"80203",
    "sg:province":"CO",
    "wof:name":"Kcnc Tv News 4",
    "wof:placetype":"venue"
},
  "geometry": {"coordinates":[-104.986005,39.73263],"type":"Point"}
}