{
  "type": "Feature",
  "properties": {
    "addr:full":"3996 Red Cedar Dr Littleton CO 80126",
    "addr:housenumber":"3996",
    "addr:postcode":"80126",
    "addr:street":"Red Cedar Dr",
    "iso:country":"US",
    "sg:address":"3996 Red Cedar Dr",
    "sg:city":"Littleton",
    "sg:classifiers":[
        {
            "category":"Restaurant",
            "type":"Food & Drink"
        }
    ],
    "sg:menulink":"http://www.allmenus.com/co/sedalia/128759-subway/menu/",
    "sg:phone":"+1 720 344 2319",
    "sg:postcode":"80126",
    "sg:province":"CO",
    "sg:tags":[
        "american",
        "sandwich"
    ],
    "wof:name":"Subway",
    "wof:placetype":"venue"
},
  "geometry": {"coordinates":[-104.94152099999999,39.524625],"type":"Point"}
}