{
  "type": "Feature",
  "properties": {
    "addr:full":"1716 Lansing St Aurora CO 80010",
    "addr:housenumber":"1716",
    "addr:postcode":"80010",
    "addr:street":"Lansing St",
    "iso:country":"US",
    "sg:address":"1716 Lansing St",
    "sg:city":"Aurora",
    "sg:classifiers":[
        {
            "category":"Shopping",
            "subcategory":"Books",
            "type":"Retail Goods"
        }
    ],
    "sg:phone":"+1 720 859 8288",
    "sg:postcode":"80010",
    "sg:province":"CO",
    "wof:name":"Liberia Cristiana Peniel",
    "wof:placetype":"venue"
},
  "geometry": {"coordinates":[-104.85750400000001,39.745457],"type":"Point"}
}