{
  "type": "Feature",
  "properties": {
    "iso:country":"US",
    "sg:address":"950 S Cherry St",
    "sg:city":"Denver",
    "sg:classifiers":[
        {
            "category":"Health Services",
            "subcategory":"Health Practitioner",
            "type":"Services"
        }
    ],
    "sg:phone":"+1 303 399 8459",
    "sg:postcode":"80246",
    "sg:province":"CO",
    "sg:tags":[
        "psychologist"
    ],
    "wof:name":"Sandra S Rhodes",
    "wof:placetype":"venue"
},
  "geometry": {"coordinates":[-104.93392900000001,39.699179],"type":"Point"}
}