{
  "type": "Feature",
  "properties": {
    "iso:country":"US",
    "sg:address":"12550 W Colfax Ave",
    "sg:city":"Denver",
    "sg:classifiers":[
        {
            "category":"Organizations",
            "subcategory":"Labor Organization",
            "type":"Services"
        },
        {
            "category":"Manufacturing",
            "subcategory":"Printing",
            "type":"Manufacturing & Wholesale Goods"
        }
    ],
    "sg:phone":"+1 303 233 6141",
    "sg:postcode":"80215",
    "sg:province":"CO",
    "sg:tags":[
        "printer"
    ],
    "wof:name":"Indox Services Inc",
    "wof:placetype":"venue"
},
  "geometry": {"coordinates":[-105.138687,39.739979],"type":"Point"}
}