{
  "type": "Feature",
  "properties": {
    "iso:country":"US",
    "sg:address":"11458 E Hilltop Rd",
    "sg:city":"Parker",
    "sg:classifiers":[
        {
            "category":"Recreation",
            "type":"Entertainment"
        }
    ],
    "sg:phone":"+1 720 851 0442",
    "sg:postcode":"80134",
    "sg:province":"CO",
    "sg:tags":[
        "stable"
    ],
    "wof:name":"Chelsea Farms Of Colorado",
    "wof:placetype":"venue"
},
  "geometry": {"coordinates":[-104.669259,39.439514],"type":"Point"}
}