{
  "type": "Feature",
  "properties": {
    "addr:full":"6325 Arapahoe Rd Boulder CO 80303",
    "addr:housenumber":"6325",
    "addr:postcode":"80303",
    "addr:street":"Arapahoe Rd",
    "iso:country":"US",
    "sg:address":"6325 Arapahoe Rd",
    "sg:city":"Boulder",
    "sg:classifiers":[
        {
            "category":"Restaurant",
            "type":"Food & Drink"
        }
    ],
    "sg:phone":"+1 303 673 9899",
    "sg:postcode":"80303",
    "sg:province":"CO",
    "sg:tags":[
        "box",
        "lunch"
    ],
    "wof:name":"Sage & Savory Catering",
    "wof:placetype":"venue"
},
  "geometry": {"coordinates":[-105.205867,40.014768],"type":"Point"}
}