{
  "type": "Feature",
  "properties": {
    "iso:country":"US",
    "sg:address":"131 S Main St",
    "sg:city":"Pueblo",
    "sg:classifiers":[
        {
            "category":"Government",
            "subcategory":"Office",
            "type":"Public Place"
        }
    ],
    "sg:phone":"+1 719 583 4323",
    "sg:postcode":"81003",
    "sg:province":"CO",
    "sg:tags":[
        "city",
        "program"
    ],
    "wof:name":"Pueblo City Environmental Hlth",
    "wof:placetype":"venue"
},
  "geometry": {"coordinates":[-104.612692,38.263605],"type":"Point"}
}