{
  "type": "Feature",
  "properties": {
    "addr:full":"6744 S Dexter St Centennial CO 80122",
    "addr:housenumber":"6744",
    "addr:postcode":"80122",
    "addr:street":"S Dexter St",
    "iso:country":"US",
    "sg:address":"6744 S Dexter St",
    "sg:city":"Centennial",
    "sg:classifiers":[
        {
            "category":"Building & Trades",
            "subcategory":"Landscaping Services",
            "type":"Services"
        }
    ],
    "sg:phone":"+1 720 529 1432",
    "sg:postcode":"80122",
    "sg:province":"CO",
    "sg:tags":[
        "landscape",
        "contractor"
    ],
    "wof:name":"D & D Property Management Inc",
    "wof:placetype":"venue"
},
  "geometry": {"coordinates":[-104.932847,39.594874],"type":"Point"}
}