{
  "type": "Feature",
  "properties": {
    "iso:country":"US",
    "sg:address":"6155 Lehman Dr",
    "sg:city":"Colorado Springs",
    "sg:classifiers":[
        {
            "category":"Organizations",
            "subcategory":"Membership Organization",
            "type":"Services"
        }
    ],
    "sg:phone":"+1 719 598 8181",
    "sg:postcode":"80918",
    "sg:province":"CO",
    "sg:tags":[
        "amateur",
        "wrestling",
        "association"
    ],
    "sg:website":"www.usawrestling.org",
    "wof:name":"USA Wrestling",
    "wof:placetype":"venue"
},
  "geometry": {"coordinates":[-104.790132,38.919207],"type":"Point"}
}