{
  "type": "Feature",
  "properties": {
    "iso:country":"US",
    "sg:address":"420 E Hyman Ave",
    "sg:city":"Aspen",
    "sg:classifiers":[
        {
            "category":"Shopping",
            "subcategory":"Gifts & Souvenirs",
            "type":"Retail Goods"
        }
    ],
    "sg:phone":"+1 970 925 5848",
    "sg:postcode":"81611",
    "sg:province":"CO",
    "sg:website":"www.cbpaws.com",
    "wof:name":"C B Paws A Dog & Cat Boutique",
    "wof:placetype":"venue"
},
  "geometry": {"coordinates":[-106.819537,39.189113],"type":"Point"}
}