{
  "type": "Feature",
  "properties": {
    "addr:full":"28076 State Hwy 74 Evergreen CO 80439",
    "addr:housenumber":"28076",
    "addr:postcode":"80439",
    "addr:street":"State Hwy 74",
    "iso:country":"US",
    "sg:address":"28076 State Hwy 74",
    "sg:city":"Evergreen",
    "sg:classifiers":[
        {
            "category":"Home & Garden",
            "subcategory":"Furniture",
            "type":"Retail Goods"
        }
    ],
    "sg:phone":"+1 303 670 8597",
    "sg:postcode":"80439",
    "sg:province":"CO",
    "wof:name":"Lauren Brooks Fine Furniture",
    "wof:placetype":"venue"
},
  "geometry": {"coordinates":[-105.31806,39.633289],"type":"Point"}
}