{
  "type": "Feature",
  "properties": {
    "addr:full":"1075 Tennessee Ave Canon City CO 81212",
    "addr:housenumber":"1075",
    "addr:postcode":"81212",
    "addr:street":"Tennessee Ave",
    "iso:country":"US",
    "sg:address":"1075 Tennessee Ave",
    "sg:city":"Canon City",
    "sg:classifiers":[
        {
            "category":"Building & Trades",
            "subcategory":"Plumbing",
            "type":"Services"
        }
    ],
    "sg:phone":"+1 719 275 1981",
    "sg:postcode":"81212",
    "sg:province":"CO",
    "sg:tags":[
        "conditioning",
        "air",
        "system",
        "contractor"
    ],
    "wof:name":"Gordon's Air",
    "wof:placetype":"venue"
},
  "geometry": {"coordinates":[-105.230349,38.469414],"type":"Point"}
}