{
  "type": "Feature",
  "properties": {
    "addr:full":"2701 Columbine Dr Durango CO 81301",
    "addr:housenumber":"2701",
    "addr:postcode":"co 81301",
    "addr:street":"Columbine Dr",
    "iso:country":"US",
    "sg:address":"2701 Columbine Dr",
    "sg:city":"Durango",
    "sg:classifiers":[
        {
            "category":"Retail",
            "subcategory":"Repair Shop",
            "type":"Services"
        }
    ],
    "sg:phone":"+1 970 259 2009",
    "sg:postcode":"81301",
    "sg:province":"CO",
    "sg:tags":[
        "appliance"
    ],
    "wof:name":"Goodman's Major Appliance Svc",
    "wof:placetype":"venue"
},
  "geometry": {"coordinates":[-107.881478,37.297968],"type":"Point"}
}