{
  "type": "Feature",
  "properties": {
    "addr:full":"2336 Dayton St Aurora CO 80010",
    "addr:housenumber":"2336",
    "addr:postcode":"80010",
    "addr:street":"Dayton St",
    "iso:country":"US",
    "sg:address":"2336 Dayton St",
    "sg:city":"Aurora",
    "sg:classifiers":[
        {
            "category":"Wholesale",
            "subcategory":"Machinery & Supplies",
            "type":"Manufacturing & Wholesale Goods"
        },
        {
            "category":"Retail",
            "subcategory":"Repair Shop",
            "type":"Services"
        }
    ],
    "sg:phone":"+1 303 364 7669",
    "sg:postcode":"80010",
    "sg:province":"CO",
    "sg:tags":[
        "valve"
    ],
    "wof:name":"Warburton Valve  LP",
    "wof:placetype":"venue"
},
  "geometry": {"coordinates":[-104.875147,39.752564],"type":"Point"}
}