{
  "type": "Feature",
  "properties": {
    "addr:full":"3254 Fraser St Aurora CO 80011",
    "addr:housenumber":"3254",
    "addr:postcode":"80011",
    "addr:street":"Fraser St",
    "iso:country":"US",
    "sg:address":"3254 Fraser St",
    "sg:city":"Aurora",
    "sg:classifiers":[
        {
            "category":"Manufacturing",
            "subcategory":"Glass & Minerals",
            "type":"Manufacturing & Wholesale Goods"
        },
        {
            "category":"Retail",
            "subcategory":"Auto Repair",
            "type":"Services"
        }
    ],
    "sg:phone":"+1 303 428 3478",
    "sg:postcode":"80011",
    "sg:province":"CO",
    "sg:tags":[
        "plate",
        "window",
        "windshield",
        "glass-auto"
    ],
    "wof:name":"SAFELITE AUTO GLASS",
    "wof:placetype":"venue"
},
  "geometry": {"coordinates":[-104.81256399999999,39.763173],"type":"Point"}
}