{
  "type": "Feature",
  "properties": {
    "iso:country":"US",
    "sg:address":"1397 S Aspen Rd",
    "sg:city":"Pueblo",
    "sg:classifiers":[
        {
            "category":"Utilities",
            "subcategory":"Water",
            "type":"Services"
        }
    ],
    "sg:phone":"+1 719 542 4380",
    "sg:postcode":"81006",
    "sg:province":"CO",
    "sg:tags":[
        "company",
        "sewage"
    ],
    "sg:website":"www.stcharlesmesawaterdistrict.org",
    "wof:name":"St Charles Mesa Water District",
    "wof:placetype":"venue"
},
  "geometry": {"coordinates":[-104.579797,38.238541],"type":"Point"}
}