{
  "type": "Feature",
  "properties": {
    "addr:full":"448 Dakota Ave Telluride CO 81435",
    "addr:housenumber":"448",
    "addr:postcode":"81435",
    "addr:street":"Dakota Ave",
    "iso:country":"US",
    "sg:address":"448 Dakota Ave",
    "sg:city":"Telluride",
    "sg:classifiers":[
        {
            "category":"Professional",
            "type":"Services"
        }
    ],
    "sg:phone":"+1 970 369 0001",
    "sg:postcode":"81435",
    "sg:province":"CO",
    "sg:tags":[
        "establishment"
    ],
    "wof:name":"Windamere Venture Partners",
    "wof:placetype":"venue"
},
  "geometry": {"coordinates":[-107.81384799999999,37.940636],"type":"Point"}
}