{
  "type": "Feature",
  "properties": {
    "iso:country":"US",
    "sg:address":"2930 W 20th Ave",
    "sg:city":"Denver",
    "sg:classifiers":[
        {
            "category":"Building & Trades",
            "subcategory":"Construction",
            "type":"Services"
        }
    ],
    "sg:phone":"+1 303 458 5305",
    "sg:postcode":"80211",
    "sg:province":"CO",
    "sg:tags":[
        "decorating",
        "painting",
        "painter",
        "contractor"
    ],
    "wof:name":"Centennial Painting & Decor",
    "wof:placetype":"venue"
},
  "geometry": {"coordinates":[-105.02477399999999,39.747504],"type":"Point"}
}