{
  "type": "Feature",
  "properties": {
    "addr:full":"9365 S Greening Dr Conifer CO 80433",
    "addr:housenumber":"9365",
    "addr:postcode":"80433",
    "addr:street":"S Greening Dr",
    "iso:country":"US",
    "sg:address":"9365 S Greening Dr",
    "sg:city":"Conifer",
    "sg:classifiers":[
        {
            "category":"Professional",
            "type":"Services"
        }
    ],
    "sg:phone":"+1 303 670 3671",
    "sg:postcode":"80433",
    "sg:province":"CO",
    "wof:name":"Tarassasaran",
    "wof:placetype":"venue"
},
  "geometry": {"coordinates":[-105.371746,39.544764],"type":"Point"}
}