{
  "type": "Feature",
  "properties": {
    "iso:country":"US",
    "sg:address":"790 Grand Ave",
    "sg:city":"Del Norte",
    "sg:classifiers":[
        {
            "category":"Education",
            "subcategory":"Library",
            "type":"Public Place"
        }
    ],
    "sg:phone":"+1 719 657 2633",
    "sg:postcode":"81132",
    "sg:province":"CO",
    "wof:name":"Del Norte Public Library",
    "wof:placetype":"venue"
},
  "geometry": {"coordinates":[-106.352012,37.678737],"type":"Point"}
}