{
  "type": "Feature",
  "properties": {
    "iso:country":"US",
    "sg:address":"13510 Halleluiah Trl",
    "sg:city":"Elbert",
    "sg:classifiers":[
        {
            "category":"Shopping",
            "type":"Retail Goods"
        }
    ],
    "sg:phone":"+1 719 495 4819",
    "sg:postcode":"80106",
    "sg:province":"CO",
    "sg:tags":[
        "cosmetic",
        "perfume"
    ],
    "wof:name":"Mary Kay Cosmetics",
    "wof:placetype":"venue"
},
  "geometry": {"coordinates":[-104.575745,39.020086],"type":"Point"}
}