{
  "type": "Feature",
  "properties": {
    "iso:country":"US",
    "sg:address":"2112 E Platte Ave",
    "sg:city":"Colorado Springs",
    "sg:classifiers":[
        {
            "category":"Banks & Credit Unions",
            "subcategory":"Bank",
            "type":"Services"
        }
    ],
    "sg:phone":"+1 719 227 8694",
    "sg:postcode":"80909",
    "sg:province":"CO",
    "sg:tags":[
        "loan"
    ],
    "wof:name":"Fast Payday Loans Of Colorado",
    "wof:placetype":"venue"
},
  "geometry": {"coordinates":[-104.788177,38.837004],"type":"Point"}
}