{
  "type": "Feature",
  "properties": {
    "addr:full":"7208 S Tucson Way Englewood CO 80112",
    "addr:housenumber":"7208",
    "addr:postcode":"80112",
    "addr:street":"S Tucson Way",
    "iso:country":"US",
    "sg:address":"7208 S Tucson Way",
    "sg:city":"Englewood",
    "sg:classifiers":[
        {
            "category":"Professional",
            "subcategory":"Management & Consulting",
            "type":"Services"
        }
    ],
    "sg:phone":"+1 303 790 1340",
    "sg:postcode":"80112",
    "sg:province":"CO",
    "sg:tags":[
        "specializing",
        "business"
    ],
    "wof:name":"Envirogroup Limited",
    "wof:placetype":"venue"
},
  "geometry": {"coordinates":[-104.835566,39.586689],"type":"Point"}
}