{
  "type": "Feature",
  "properties": {
    "addr:full":"404 E Aspen Ave Fruita CO 81521",
    "addr:housenumber":"404",
    "addr:postcode":"81521",
    "addr:street":"E Aspen Ave",
    "iso:country":"US",
    "sg:address":"404 E Aspen Ave",
    "sg:city":"Fruita",
    "sg:classifiers":[
        {
            "category":"Building & Trades",
            "subcategory":"Construction",
            "type":"Services"
        }
    ],
    "sg:phone":"+1 970 858 8091",
    "sg:postcode":"81521",
    "sg:province":"CO",
    "sg:tags":[
        "general",
        "contractor"
    ],
    "wof:name":"Mc Gregor Construction",
    "wof:placetype":"venue"
},
  "geometry": {"coordinates":[-108.73018399999999,39.158807],"type":"Point"}
}