{
  "type": "Feature",
  "properties": {
    "iso:country":"US",
    "sg:address":"126 Elk Ave",
    "sg:city":"Crested Butte",
    "sg:classifiers":[
        {
            "category":"Home & Garden",
            "subcategory":"Home Furnishings",
            "type":"Retail Goods"
        }
    ],
    "sg:phone":"+1 970 349 6459",
    "sg:postcode":"81224",
    "sg:province":"CO",
    "sg:tags":[
        "pottery"
    ],
    "wof:name":"Creekside Pottery",
    "wof:placetype":"venue"
},
  "geometry": {"coordinates":[-106.987483,38.86968],"type":"Point"}
}