{
  "type": "Feature",
  "properties": {
    "addr:full":"4575 S Navajo St Englewood CO 80110",
    "addr:housenumber":"4575",
    "addr:postcode":"80110",
    "addr:street":"S Navajo St",
    "iso:country":"US",
    "sg:address":"4575 S Navajo St",
    "sg:city":"Englewood",
    "sg:classifiers":[
        {
            "category":"Wholesale",
            "subcategory":"Machinery & Supplies",
            "type":"Manufacturing & Wholesale Goods"
        }
    ],
    "sg:phone":"+1 303 936 2244",
    "sg:postcode":"80110",
    "sg:province":"CO",
    "sg:tags":[
        "machine",
        "equipment",
        "tool",
        "metal",
        "working"
    ],
    "sg:website":"www.metalfinishingsystems.com",
    "wof:name":"Metal Finishing Systems Inc",
    "wof:placetype":"venue"
},
  "geometry": {"coordinates":[-105.00467500000001,39.633753],"type":"Point"}
}