{
  "type": "Feature",
  "properties": {
    "iso:country":"US",
    "sg:address":"655 Main St",
    "sg:city":"Delta",
    "sg:classifiers":[
        {
            "category":"Autos & Motor Vehicles",
            "subcategory":"Automobile Sales",
            "type":"Retail Goods"
        }
    ],
    "sg:phone":"+1 970 874 5461",
    "sg:postcode":"81416",
    "sg:province":"CO",
    "sg:tags":[
        "car",
        "used",
        "dealer"
    ],
    "wof:name":"Orval's Used Cars",
    "wof:placetype":"venue"
},
  "geometry": {"coordinates":[-108.070904,38.738464],"type":"Point"}
}