{
  "type": "Feature",
  "properties": {
    "iso:country":"US",
    "sg:address":"7720 E Belleview Ave",
    "sg:city":"Englewood",
    "sg:classifiers":[
        {
            "category":"Building & Trades",
            "subcategory":"Construction",
            "type":"Services"
        }
    ],
    "sg:phone":"+1 720 857 8745",
    "sg:postcode":"80111",
    "sg:province":"CO",
    "sg:tags":[
        "nonresidential"
    ],
    "wof:name":"Co Svc Construction Inc",
    "wof:placetype":"venue"
},
  "geometry": {"coordinates":[-104.898985,39.624023],"type":"Point"}
}