{
  "type": "Feature",
  "properties": {
    "iso:country":"US",
    "sg:address":"18 Co Rd 100",
    "sg:city":"Frisco",
    "sg:classifiers":[
        {
            "category":"Health Services",
            "subcategory":"Health Practitioner",
            "type":"Services"
        }
    ],
    "sg:phone":"+1 970 668 0888",
    "sg:postcode":"80435",
    "sg:province":"CO",
    "sg:tags":[
        "therapist",
        "physical"
    ],
    "wof:name":"Avalanche Physical Therapy",
    "wof:placetype":"venue"
},
  "geometry": {"coordinates":[-106.004479,39.600034],"type":"Point"}
}