{
  "type": "Feature",
  "properties": {
    "iso:country":"US",
    "sg:address":"209 N Main St",
    "sg:city":"Pueblo",
    "sg:classifiers":[
        {
            "category":"Real Estate",
            "subcategory":"Real Estate Agent",
            "type":"Services"
        }
    ],
    "sg:phone":"+1 719 543 9037",
    "sg:postcode":"81003",
    "sg:province":"CO",
    "wof:name":"209 North Main St LLC",
    "wof:placetype":"venue"
},
  "geometry": {"coordinates":[-104.608647,38.269199],"type":"Point"}
}