{
  "type": "Feature",
  "properties": {
    "iso:country":"US",
    "sg:address":"555 Burbank St",
    "sg:city":"Broomfield",
    "sg:classifiers":[
        {
            "category":"Professional",
            "subcategory":"Business Services",
            "type":"Services"
        },
        {
            "category":"Manufacturing",
            "subcategory":"Apparel",
            "type":"Manufacturing & Wholesale Goods"
        }
    ],
    "sg:phone":"+1 303 464 9999",
    "sg:postcode":"80020",
    "sg:province":"CO",
    "sg:tags":[
        "embroidery"
    ],
    "wof:name":"Burbank Embroidery Co",
    "wof:placetype":"venue"
},
  "geometry": {"coordinates":[-105.095439,39.923524],"type":"Point"}
}