{
  "type": "Feature",
  "properties": {
    "addr:full":"1664 Wetterhorn St Montrose CO 81401",
    "addr:housenumber":"1664",
    "addr:postcode":"81401",
    "addr:street":"Wetterhorn St",
    "iso:country":"US",
    "sg:address":"1664 Wetterhorn St",
    "sg:city":"Montrose",
    "sg:classifiers":[
        {
            "category":"Professional",
            "type":"Services"
        }
    ],
    "sg:phone":"+1 970 240 5903",
    "sg:postcode":"81401",
    "sg:province":"CO",
    "wof:name":"Rodney M Bunyard",
    "wof:placetype":"venue"
},
  "geometry": {"coordinates":[-107.85883200000001,38.455702],"type":"Point"}
}