{
  "type": "Feature",
  "properties": {
    "iso:country":"US",
    "sg:address":"14697 E Easter Ave",
    "sg:city":"Centennial",
    "sg:classifiers":[
        {
            "category":"Autos & Motor Vehicles",
            "subcategory":"Auto Supplies",
            "type":"Retail Goods"
        }
    ],
    "sg:phone":"+1 303 693 2527",
    "sg:postcode":"80112",
    "sg:province":"CO",
    "sg:tags":[
        "equipment",
        "racing",
        "car",
        "automobile"
    ],
    "wof:name":"Pro Street Motor Sports",
    "wof:placetype":"venue"
},
  "geometry": {"coordinates":[-104.81759,39.587985],"type":"Point"}
}