{
  "type": "Feature",
  "properties": {
    "iso:country":"US",
    "sg:address":"6380 Pushmataha Dr",
    "sg:city":"Colorado Springs",
    "sg:classifiers":[
        {
            "category":"Banks & Credit Unions",
            "subcategory":"Financial Services",
            "type":"Services"
        }
    ],
    "sg:phone":"+1 719 570 7380",
    "sg:postcode":"80915",
    "sg:province":"CO",
    "sg:tags":[
        "investor"
    ],
    "wof:name":"J & K Real Estate Investment",
    "wof:placetype":"venue"
},
  "geometry": {"coordinates":[-104.709844,38.859492],"type":"Point"}
}