{
  "type": "Feature",
  "properties": {
    "iso:country":"US",
    "sg:address":"1310 S Washington St",
    "sg:city":"Denver",
    "sg:classifiers":[
        {
            "category":"Organizations",
            "subcategory":"Religious Organization",
            "type":"Services"
        }
    ],
    "sg:phone":"+1 303 744 9699",
    "sg:postcode":"80210",
    "sg:province":"CO",
    "sg:website":"www.WashParkJewishCenter.com",
    "wof:name":"Chabad of DU",
    "wof:placetype":"venue"
},
  "geometry": {"coordinates":[-104.979267,39.692789],"type":"Point"}
}