{
  "type": "Feature",
  "properties": {
    "addr:full":"75 E 2nd St Nederland CO 80466",
    "addr:housenumber":"75",
    "addr:postcode":"80466",
    "addr:street":"E 2Nd St",
    "iso:country":"US",
    "sg:address":"75 E 2nd St",
    "sg:city":"Nederland",
    "sg:classifiers":[
        {
            "category":"Retail",
            "subcategory":"Veterinary Services",
            "type":"Services"
        }
    ],
    "sg:phone":"+1 303 258 7004",
    "sg:postcode":"80466",
    "sg:province":"CO",
    "sg:tags":[
        "veterinarian"
    ],
    "wof:name":"Peak To Peak Animal Hospital",
    "wof:placetype":"venue"
},
  "geometry": {"coordinates":[-105.509502,39.962799],"type":"Point"}
}