{
  "type": "Feature",
  "properties": {
    "iso:country":"US",
    "sg:address":"1214 Santa Fe Dr",
    "sg:city":"Denver",
    "sg:classifiers":[
        {
            "category":"Retail",
            "subcategory":"Repair Shop",
            "type":"Services"
        }
    ],
    "sg:phone":"+1 303 595 3213",
    "sg:postcode":"80204",
    "sg:province":"CO",
    "sg:tags":[
        "equipment",
        "photographic"
    ],
    "wof:name":"Ray's Camera Repair",
    "wof:placetype":"venue"
},
  "geometry": {"coordinates":[-104.99861300000001,39.736638],"type":"Point"}
}