{
  "type": "Feature",
  "properties": {
    "iso:country":"US",
    "sg:address":"3937 Tennyson St",
    "sg:city":"Denver",
    "sg:classifiers":[
        {
            "category":"Restaurant",
            "type":"Food & Drink"
        }
    ],
    "sg:phone":"+1 303 433 4887",
    "sg:postcode":"80212",
    "sg:province":"CO",
    "wof:name":"Moka Caffee",
    "wof:placetype":"venue"
},
  "geometry": {"coordinates":[-105.044198,39.771857],"type":"Point"}
}