{
  "type": "Feature",
  "properties": {
    "addr:full":"3937 Tennyson St Denver CO 80212",
    "addr:housenumber":"3937",
    "addr:postcode":"80212",
    "addr:street":"Tennyson St",
    "iso:country":"US",
    "sg:address":"3937 Tennyson St",
    "sg:city":"Denver",
    "sg:classifiers":[
        {
            "category":"Restaurant",
            "type":"Food & Drink"
        }
    ],
    "sg:phone":"+1 303 433 4887",
    "sg:postcode":"80212",
    "sg:province":"CO",
    "wof:name":"Moka Caffee",
    "wof:placetype":"venue"
},
  "geometry": {"coordinates":[-105.04419799999999,39.771857],"type":"Point"}
}