{
  "type": "Feature",
  "properties": {
    "addr:full":"425 S Cherry St Denver CO 80246",
    "addr:housenumber":"425",
    "addr:postcode":"80246",
    "addr:street":"S Cherry St",
    "iso:country":"US",
    "sg:address":"425 S Cherry St",
    "sg:city":"Denver",
    "sg:classifiers":[
        {
            "category":"Health Services",
            "subcategory":"Doctor",
            "type":"Services"
        }
    ],
    "sg:phone":"+1 303 388 4076",
    "sg:postcode":"80246",
    "sg:province":"CO",
    "sg:tags":[
        "physician",
        "clinic",
        "surgeon",
        "medical"
    ],
    "sg:website":"www.newwestpc.com",
    "wof:name":"New West Physicians",
    "wof:placetype":"venue"
},
  "geometry": {"coordinates":[-104.933494,39.707982],"type":"Point"}
}