{
  "type": "Feature",
  "properties": {
    "addr:full":"3829 Cleveland Ave Wellington CO 80549",
    "addr:housenumber":"3829",
    "addr:postcode":"80549",
    "addr:street":"Cleveland Ave",
    "iso:country":"US",
    "sg:address":"3829 Cleveland Ave",
    "sg:city":"Wellington",
    "sg:classifiers":[
        {
            "category":"Government",
            "subcategory":"Post Office",
            "type":"Public Place"
        }
    ],
    "sg:phone":"+1 970 568 3913",
    "sg:postcode":"80549",
    "sg:province":"CO",
    "sg:website":"www.usps.gov",
    "wof:name":"US Post Office",
    "wof:placetype":"venue"
},
  "geometry": {"coordinates":[-105.00463999999999,40.703872],"type":"Point"}
}