{
  "type": "Feature",
  "properties": {
    "iso:country":"US",
    "sg:address":"6333 Co Rd 60",
    "sg:city":"Windsor",
    "sg:classifiers":[
        {
            "category":"Autos & Motor Vehicles",
            "subcategory":"Automobile Sales",
            "type":"Retail Goods"
        }
    ],
    "sg:phone":"+1 970 674 1376",
    "sg:postcode":"80550",
    "sg:province":"CO",
    "wof:name":"Colorado Sandcars",
    "wof:placetype":"venue"
},
  "geometry": {"coordinates":[-104.940077,40.421526],"type":"Point"}
}