{
  "type": "Feature",
  "properties": {
    "iso:country":"US",
    "sg:address":"2553 River Rd",
    "sg:city":"Grand Junction",
    "sg:classifiers":[
        {
            "category":"Government",
            "subcategory":"Office",
            "type":"Public Place"
        }
    ],
    "sg:phone":"+1 970 244 1571",
    "sg:postcode":"81501",
    "sg:province":"CO",
    "sg:tags":[
        "village"
    ],
    "wof:name":"Grand Junction Street Mntnc",
    "wof:placetype":"venue"
},
  "geometry": {"coordinates":[-108.58554700000001,39.076806],"type":"Point"}
}