{
  "type": "Feature",
  "properties": {
    "iso:country":"US",
    "sg:address":"570 S Owens Cir",
    "sg:city":"Byers",
    "sg:classifiers":[
        {
            "category":"Building & Trades",
            "subcategory":"Cleaning & Sanitation",
            "type":"Services"
        }
    ],
    "sg:phone":"+1 303 340 2466",
    "sg:postcode":"80103",
    "sg:province":"CO",
    "sg:tags":[
        "window"
    ],
    "wof:name":"All About Window Cleaning",
    "wof:placetype":"venue"
},
  "geometry": {"coordinates":[-104.222781,39.703223],"type":"Point"}
}