{
  "type": "Feature",
  "properties": {
    "addr:full":"9601 Grant St Denver CO 80229",
    "addr:housenumber":"9601",
    "addr:postcode":"80229",
    "addr:street":"Grant St",
    "iso:country":"US",
    "sg:address":"9601 Grant St",
    "sg:city":"Denver",
    "sg:classifiers":[
        {
            "category":"Food & Beverages",
            "subcategory":"Liquor & Beverages",
            "type":"Retail Goods"
        }
    ],
    "sg:phone":"+1 303 453 4964",
    "sg:postcode":"80229",
    "sg:province":"CO",
    "sg:tags":[
        "alcoholic"
    ],
    "wof:name":"Warehouse Liquor",
    "wof:placetype":"venue"
},
  "geometry": {"coordinates":[-104.98300999999999,39.8745],"type":"Point"}
}