{
  "type": "Feature",
  "properties": {
    "addr:full":"1728 Paonia St Colorado Springs CO 80915",
    "addr:housenumber":"1728",
    "addr:postcode":"80915",
    "addr:street":"Paonia St",
    "iso:country":"US",
    "sg:address":"1728 Paonia St",
    "sg:city":"Colorado Springs",
    "sg:classifiers":[
        {
            "category":"Manufacturing",
            "subcategory":"Tools & Machinery",
            "type":"Manufacturing & Wholesale Goods"
        }
    ],
    "sg:phone":"+1 719 622 5322",
    "sg:postcode":"80915",
    "sg:province":"CO",
    "sg:tags":[
        "industry",
        "mfg"
    ],
    "sg:website":"www.usfilter.com",
    "wof:name":"US Filter",
    "wof:placetype":"venue"
},
  "geometry": {"coordinates":[-104.715594,38.856448],"type":"Point"}
}