{
  "type": "Feature",
  "properties": {
    "iso:country":"US",
    "sg:address":"100 Zante St",
    "sg:city":"Lochbuie",
    "sg:classifiers":[
        {
            "category":"Building & Trades",
            "subcategory":"Construction",
            "type":"Services"
        }
    ],
    "sg:phone":"+1 303 654 1019",
    "sg:postcode":"80603",
    "sg:province":"CO",
    "sg:tags":[
        "painter"
    ],
    "wof:name":"Fuller Painting & Wallpapering",
    "wof:placetype":"venue"
},
  "geometry": {"coordinates":[-104.71679899999999,40.003012],"type":"Point"}
}