{
  "type": "Feature",
  "properties": {
    "iso:country":"US",
    "sg:address":"6610 Battle Mountain Rd",
    "sg:city":"Colorado Springs",
    "sg:classifiers":[
        {
            "category":"Professional",
            "subcategory":"Business Services",
            "type":"Services"
        }
    ],
    "sg:phone":"+1 719 572 9537",
    "sg:postcode":"80922",
    "sg:province":"CO",
    "sg:tags":[
        "drycleaning",
        "plant"
    ],
    "wof:name":"Spring Crest Drap Unlimited",
    "wof:placetype":"venue"
},
  "geometry": {"coordinates":[-104.704459,38.871118],"type":"Point"}
}