{
  "type": "Feature",
  "properties": {
    "addr:full":"211 Cleveland Ave Loveland CO 80537",
    "addr:housenumber":"211",
    "addr:postcode":"80537",
    "addr:street":"Cleveland Ave",
    "iso:country":"US",
    "sg:address":"211 Cleveland Ave",
    "sg:city":"Loveland",
    "sg:classifiers":[
        {
            "category":"Home & Garden",
            "subcategory":"Garden Supply",
            "type":"Retail Goods"
        }
    ],
    "sg:phone":"+1 970 278 1111",
    "sg:postcode":"80537",
    "sg:province":"CO",
    "sg:tags":[
        "fountain",
        "display"
    ],
    "wof:name":"Concrete Goose",
    "wof:placetype":"venue"
},
  "geometry": {"coordinates":[-105.07462200000001,40.394317],"type":"Point"}
}