{
  "type": "Feature",
  "properties": {
    "iso:country":"US",
    "sg:address":"14030 E Mississippi Ave",
    "sg:city":"Aurora",
    "sg:classifiers":[
        {
            "category":"Shopping",
            "subcategory":"Stationery & Office Supplies",
            "type":"Retail Goods"
        }
    ],
    "sg:phone":"+1 303 752 0040",
    "sg:postcode":"80012",
    "sg:province":"CO",
    "sg:tags":[
        "furniture"
    ],
    "wof:name":"Office Max",
    "wof:placetype":"venue"
},
  "geometry": {"coordinates":[-104.824181,39.696534],"type":"Point"}
}