{
  "type": "Feature",
  "properties": {
    "addr:full":"4375 Allesandro Dr Colorado Springs CO 80916",
    "addr:postcode":"4375;80916",
    "addr:street":"Allesandro Dr",
    "iso:country":"US",
    "sg:address":"4375 Allesandro Dr",
    "sg:city":"Colorado Springs",
    "sg:classifiers":[
        {
            "category":"Restaurant",
            "type":"Food & Drink"
        }
    ],
    "sg:phone":"+1 719 596 2077",
    "sg:postcode":"80916",
    "sg:province":"CO",
    "sg:tags":[
        "eating"
    ],
    "wof:name":"Rose Purple Restaurant",
    "wof:placetype":"venue"
},
  "geometry": {"coordinates":[-104.746666,38.818484],"type":"Point"}
}