{
  "type": "Feature",
  "properties": {
    "addr:full":"2125 S Valentia Street Denver CO 80231",
    "addr:housenumber":"2125",
    "addr:postcode":"80231",
    "addr:street":"S Valentia Street",
    "iso:country":"US",
    "sg:address":"2125 S Valentia Street",
    "sg:city":"Denver",
    "sg:classifiers":[
        {
            "category":"Building & Trades",
            "subcategory":"Construction",
            "type":"Services"
        }
    ],
    "sg:phone":"+1 303 369 5100",
    "sg:postcode":"80231",
    "sg:province":"CO",
    "sg:tags":[
        "contractor"
    ],
    "wof:name":"C & A Companies",
    "wof:placetype":"venue"
},
  "geometry": {"coordinates":[-104.89169099999999,39.678135],"type":"Point"}
}