{
  "type": "Feature",
  "properties": {
    "iso:country":"US",
    "sg:address":"2109 Breckenridge Dr",
    "sg:city":"Berthoud",
    "sg:classifiers":[
        {
            "category":"Professional",
            "subcategory":"Computer Services",
            "type":"Services"
        }
    ],
    "sg:phone":"+1 970 532 5550",
    "sg:postcode":"80513",
    "sg:province":"CO",
    "sg:tags":[
        "home",
        "consulting",
        "page",
        "dev",
        "internet"
    ],
    "wof:name":"Inventive Wireless",
    "wof:placetype":"venue"
},
  "geometry": {"coordinates":[-105.086984,40.32729],"type":"Point"}
}