{
  "type": "Feature",
  "properties": {
    "addr:full":"4615 Town Center Dr Colorado Springs CO 80916",
    "addr:housenumber":"4615",
    "addr:postcode":"80916",
    "addr:street":"Town Center Dr",
    "iso:country":"US",
    "sg:address":"4615 Town Center Dr",
    "sg:city":"Colorado Springs",
    "sg:classifiers":[
        {
            "category":"Building & Trades",
            "subcategory":"Construction",
            "type":"Services"
        }
    ],
    "sg:phone":"+1 719 380 7663",
    "sg:postcode":"80916",
    "sg:province":"CO",
    "sg:tags":[
        "roofing",
        "contractor"
    ],
    "wof:name":"Peak View Roofing",
    "wof:placetype":"venue"
},
  "geometry": {"coordinates":[-104.74209500000001,38.839006],"type":"Point"}
}