{
  "type": "Feature",
  "properties": {
    "iso:country":"US",
    "sg:address":"1750 Humboldt St",
    "sg:city":"Denver",
    "sg:classifiers":[
        {
            "category":"Health Services",
            "subcategory":"Health Practitioner",
            "type":"Services"
        }
    ],
    "sg:phone":"+1 303 850 7717",
    "sg:postcode":"80218",
    "sg:province":"CO",
    "sg:tags":[
        "therapist",
        "physical"
    ],
    "sg:website":"www.southvalleypt.com",
    "wof:name":"South Valley Physical Therapy",
    "wof:placetype":"venue"
},
  "geometry": {"coordinates":[-104.96960199999999,39.744014],"type":"Point"}
}