{
  "type": "Feature",
  "properties": {
    "iso:country":"US",
    "sg:address":"6602 Delmonico Dr",
    "sg:city":"Colorado Springs",
    "sg:classifiers":[
        {
            "category":"Restaurant",
            "type":"Food & Drink"
        }
    ],
    "sg:phone":"+1 719 598 7775",
    "sg:postcode":"80919",
    "sg:province":"CO",
    "sg:tags":[
        "eating"
    ],
    "wof:name":"TCBY",
    "wof:placetype":"venue"
},
  "geometry": {"coordinates":[-104.83090300000001,38.928932],"type":"Point"}
}