{
  "type": "Feature",
  "properties": {
    "addr:full":"5375 Airport Rd Colorado Springs CO 80916",
    "addr:housenumber":"5375",
    "addr:postcode":"80916",
    "addr:street":"Airport Rd",
    "iso:country":"US",
    "sg:address":"5375 Airport Rd",
    "sg:city":"Colorado Springs",
    "sg:classifiers":[
        {
            "category":"Deli",
            "type":"Food & Drink"
        }
    ],
    "sg:menulink":"http://www.allmenus.com/co/colorado-springs/125951-blimpie-subs--sandwiches/menu/",
    "sg:phone":"+1 719 570 0994",
    "sg:postcode":"80916",
    "sg:province":"CO",
    "sg:tags":[
        "wrap",
        "american",
        "sandwich"
    ],
    "wof:name":"Blimpie Subs & Sandwiches",
    "wof:placetype":"venue"
},
  "geometry": {"coordinates":[-104.72881700000001,38.824201],"type":"Point"}
}