{
  "type": "Feature",
  "properties": {
    "iso:country":"US",
    "sg:address":"4550 51st St",
    "sg:city":"Greeley",
    "sg:classifiers":[
        {
            "category":"Health Services",
            "subcategory":"Health Practitioner",
            "type":"Services"
        }
    ],
    "sg:phone":"+1 970 330 8149",
    "sg:postcode":"80634",
    "sg:province":"CO",
    "sg:tags":[
        "dietitian"
    ],
    "wof:name":"Dietary Consultants",
    "wof:placetype":"venue"
},
  "geometry": {"coordinates":[-104.751606,40.361033],"type":"Point"}
}