{
  "type": "Feature",
  "properties": {
    "iso:country":"US",
    "sg:address":"9550 Ernst Dr",
    "sg:city":"Denver",
    "sg:classifiers":[
        {
            "category":"Building & Trades",
            "subcategory":"Construction",
            "type":"Services"
        }
    ],
    "sg:phone":"+1 303 237 6008",
    "sg:postcode":"80226",
    "sg:province":"CO",
    "sg:tags":[
        "floor",
        "laying",
        "contractor"
    ],
    "wof:name":"Flo",
    "wof:placetype":"venue"
},
  "geometry": {"coordinates":[-105.103011,39.720803],"type":"Point"}
}