{
  "type": "Feature",
  "properties": {
    "iso:country":"US",
    "sg:address":"37625 Astra Way",
    "sg:city":"Watkins",
    "sg:classifiers":[
        {
            "category":"Airport",
            "type":"Transportation"
        }
    ],
    "sg:phone":"+1 303 261 0333",
    "sg:postcode":"80137",
    "sg:province":"CO",
    "sg:tags":[
        "help",
        "supply"
    ],
    "wof:name":"Victory Aviation LLC",
    "wof:placetype":"venue"
},
  "geometry": {"coordinates":[-104.547674,39.787722],"type":"Point"}
}