{
  "type": "Feature",
  "properties": {
    "addr:full":"1816 E Colfax Avenue Denver CO 80218",
    "addr:housenumber":"1816",
    "addr:postcode":"80218",
    "addr:street":"E Colfax Avenue",
    "iso:country":"US",
    "sg:address":"1816 E Colfax Avenue",
    "sg:city":"Denver",
    "sg:classifiers":[
        {
            "category":"Food & Beverages",
            "subcategory":"Liquor & Beverages",
            "type":"Retail Goods"
        }
    ],
    "sg:phone":"+1 303 321 4378",
    "sg:postcode":"80218",
    "sg:province":"CO",
    "sg:tags":[
        "beer",
        "spirit",
        "wine"
    ],
    "wof:name":"John's Liquor Store",
    "wof:placetype":"venue"
},
  "geometry": {"coordinates":[-104.965355,39.739901],"type":"Point"}
}