{
  "type": "Feature",
  "properties": {
    "addr:full":"637 US Hwy 287 Fort Collins CO 80524",
    "addr:housenumber":"637",
    "addr:postcode":"80524",
    "addr:street":"Us Hwy 287",
    "iso:country":"US",
    "sg:address":"637 US Hwy 287",
    "sg:city":"Fort Collins",
    "sg:classifiers":[
        {
            "category":"Retail",
            "subcategory":"Repair Shop",
            "type":"Services"
        }
    ],
    "sg:phone":"+1 970 482 3348",
    "sg:postcode":"80524",
    "sg:province":"CO",
    "sg:tags":[
        "contractor"
    ],
    "wof:name":"Roto-Rooter",
    "wof:placetype":"venue"
},
  "geometry": {"coordinates":[-105.076784,40.59538],"type":"Point"}
}