{
  "type": "Feature",
  "properties": {
    "addr:full":"122 County Road 37 Brighton CO 80603",
    "addr:housenumber":"122",
    "addr:postcode":"80603",
    "addr:street":"County Road 37",
    "iso:country":"US",
    "sg:address":"122 County Road 37",
    "sg:city":"Brighton",
    "sg:classifiers":[
        {
            "category":"Building & Trades",
            "subcategory":"Cleaning & Sanitation",
            "type":"Services"
        }
    ],
    "sg:phone":"+1 303 637 9853",
    "sg:postcode":"80603",
    "sg:province":"CO",
    "sg:tags":[
        "janitorial"
    ],
    "wof:name":"Joel Reyes Janitorial",
    "wof:placetype":"venue"
},
  "geometry": {"coordinates":[-104.71613499999999,40.003795],"type":"Point"}
}