{
  "type": "Feature",
  "properties": {
    "iso:country":"US",
    "sg:address":"111 Summit Blvd",
    "sg:city":"Englewood",
    "sg:classifiers":[
        {
            "category":"Real Estate",
            "subcategory":"Real Estate Agent",
            "type":"Services"
        }
    ],
    "sg:phone":"+1 303 332 5291",
    "sg:postcode":"80113",
    "sg:province":"CO",
    "wof:name":"In Wick of Time LLC",
    "wof:placetype":"venue"
},
  "geometry": {"coordinates":[-104.968091,39.625016],"type":"Point"}
}