{
  "type": "Feature",
  "properties": {
    "iso:country":"US",
    "sg:address":"2515 Hwy 6 and 50",
    "sg:city":"Grand Junction",
    "sg:classifiers":[
        {
            "category":"Food & Beverages",
            "subcategory":"Groceries & Convenience Stores",
            "type":"Retail Goods"
        }
    ],
    "sg:phone":"+1 970 243 7560",
    "sg:postcode":"81505",
    "sg:province":"CO",
    "wof:name":"Go-Fer Foods",
    "wof:placetype":"venue"
},
  "geometry": {"coordinates":[-108.58734,39.08234],"type":"Point"}
}