{
  "type": "Feature",
  "properties": {
    "addr:full":"14991 E Hampden Ave Ste 300 Aurora CO 80014",
    "addr:housenumber":"14991",
    "addr:postcode":"80014",
    "addr:street":"E Hampden Ave Ste 300",
    "iso:country":"US",
    "sg:address":"14991 E Hampden Ave Ste 300",
    "sg:city":"Aurora",
    "sg:classifiers":[
        {
            "category":"Health Services",
            "subcategory":"Dentist",
            "type":"Services"
        }
    ],
    "sg:phone":"+1 303 690 7778",
    "sg:postcode":"80014",
    "sg:province":"CO",
    "wof:name":"Wallace Richard J Dds",
    "wof:placetype":"venue"
},
  "geometry": {"coordinates":[-104.813277,39.65316],"type":"Point"}
}