{
  "type": "Feature",
  "properties": {
    "iso:country":"US",
    "sg:address":"335 E 11th St",
    "sg:city":"Loveland",
    "sg:classifiers":[
        {
            "category":"Freight",
            "type":"Transportation"
        }
    ],
    "sg:phone":"+1 970 667 0924",
    "sg:postcode":"80537",
    "sg:province":"CO",
    "wof:name":"Ncts",
    "wof:placetype":"venue"
},
  "geometry": {"coordinates":[-105.07213299999999,40.403224],"type":"Point"}
}