{
  "type": "Feature",
  "properties": {
    "addr:full":"1697 Co Rd 329 Ignacio CO 81137",
    "addr:housenumber":"1697",
    "addr:postcode":"81137",
    "addr:street":"Co Rd 329 Ignacio",
    "iso:country":"US",
    "sg:address":"1697 Co Rd 329",
    "sg:city":"Ignacio",
    "sg:classifiers":[
        {
            "category":"Wholesale",
            "subcategory":"Machinery & Supplies",
            "type":"Manufacturing & Wholesale Goods"
        }
    ],
    "sg:phone":"+1 970 883 5448",
    "sg:postcode":"81137",
    "sg:province":"CO",
    "sg:tags":[
        "equipment",
        "industrial"
    ],
    "wof:name":"Colorado Tank & Plumbing",
    "wof:placetype":"venue"
},
  "geometry": {"coordinates":[-107.51188,37.02459],"type":"Point"}
}