{
  "type": "Feature",
  "properties": {
    "iso:country":"US",
    "sg:address":"7595 Louviers Blvd",
    "sg:city":"Louviers",
    "sg:classifiers":[
        {
            "category":"Organizations",
            "subcategory":"Religious Organization",
            "type":"Services"
        }
    ],
    "sg:phone":"+1 303 791 7595",
    "sg:postcode":"80131",
    "sg:province":"CO",
    "sg:tags":[
        "church"
    ],
    "wof:name":"Faith Evangelical Free Church",
    "wof:placetype":"venue"
},
  "geometry": {"coordinates":[-105.001987,39.471461],"type":"Point"}
}