{
  "type": "Feature",
  "properties": {
    "addr:full":"3685 S Federal Blvd Englewood CO 80110",
    "addr:housenumber":"3685",
    "addr:postcode":"80110",
    "addr:street":"S Federal Blvd",
    "iso:country":"US",
    "sg:address":"3685 S Federal Blvd",
    "sg:city":"Englewood",
    "sg:classifiers":[
        {
            "category":"Retail",
            "subcategory":"Auto Repair",
            "type":"Services"
        }
    ],
    "sg:phone":"+1 303 762 7817",
    "sg:postcode":"80110",
    "sg:province":"CO",
    "sg:tags":[
        "repairing",
        "automobile"
    ],
    "wof:name":"Auto Imports",
    "wof:placetype":"venue"
},
  "geometry": {"coordinates":[-105.025373,39.649832],"type":"Point"}
}