{
  "type": "Feature",
  "properties": {
    "iso:country":"US",
    "sg:address":"3279 Sunshine Canyon Dr",
    "sg:city":"Boulder",
    "sg:classifiers":[
        {
            "category":"Professional",
            "type":"Services"
        }
    ],
    "sg:phone":"+1 303 449 2219",
    "sg:postcode":"80302",
    "sg:province":"CO",
    "wof:name":"Robert Steinway",
    "wof:placetype":"venue"
},
  "geometry": {"coordinates":[-105.32564499999999,40.036029],"type":"Point"}
}