{
  "type": "Feature",
  "properties": {
    "addr:full":"2215 Silent Rain Dr Colorado Springs CO 80919",
    "addr:housenumber":"2215",
    "addr:postcode":"80919",
    "addr:street":"Silent Rain Dr",
    "iso:country":"US",
    "sg:address":"2215 Silent Rain Dr",
    "sg:city":"Colorado Springs",
    "sg:classifiers":[
        {
            "category":"Manufacturing",
            "subcategory":"Tools & Machinery",
            "type":"Manufacturing & Wholesale Goods"
        }
    ],
    "sg:phone":"+1 719 593 7082",
    "sg:postcode":"80919",
    "sg:province":"CO",
    "sg:tags":[
        "equipment",
        "lighting",
        "mfg"
    ],
    "wof:name":"Illuminati Stage Lighting",
    "wof:placetype":"venue"
},
  "geometry": {"coordinates":[-104.868701,38.933547],"type":"Point"}
}