{
  "type": "Feature",
  "properties": {
    "addr:full":"619 Dotson St Manassa CO 81141",
    "addr:housenumber":"619",
    "addr:postcode":"81141",
    "addr:street":"Dotson St",
    "iso:country":"US",
    "sg:address":"619 Dotson St",
    "sg:city":"Manassa",
    "sg:classifiers":[
        {
            "category":"Building & Trades",
            "subcategory":"Construction",
            "type":"Services"
        }
    ],
    "sg:phone":"+1 719 843 5774",
    "sg:postcode":"81141",
    "sg:province":"CO",
    "sg:tags":[
        "general",
        "contractor"
    ],
    "wof:name":"Williams Building Systems Inc",
    "wof:placetype":"venue"
},
  "geometry": {"coordinates":[-105.941299,37.179137],"type":"Point"}
}