{
  "type": "Feature",
  "properties": {
    "iso:country":"US",
    "sg:address":"1243 Sherman Dr",
    "sg:city":"Longmont",
    "sg:classifiers":[
        {
            "category":"Building & Trades",
            "subcategory":"Construction",
            "type":"Services"
        },
        {
            "category":"Home & Garden",
            "subcategory":"Furniture",
            "type":"Retail Goods"
        }
    ],
    "sg:phone":"+1 303 678 5948",
    "sg:postcode":"80501",
    "sg:province":"CO",
    "sg:tags":[
        "cabinet",
        "carpentry",
        "contractor"
    ],
    "wof:name":"Bunta Fine Cabinetry",
    "wof:placetype":"venue"
},
  "geometry": {"coordinates":[-105.11502400000001,40.153039],"type":"Point"}
}