{
  "type": "Feature",
  "properties": {
    "addr:full":"2021 Fossil Creek Pkwy Fort Collins CO 80528",
    "addr:housenumber":"2021",
    "addr:postcode":"80528",
    "addr:street":"Fossil Creek Pkwy",
    "iso:country":"US",
    "sg:address":"2021 Fossil Creek Pkwy",
    "sg:city":"Fort Collins",
    "sg:classifiers":[
        {
            "category":"Building & Trades",
            "subcategory":"Construction",
            "type":"Services"
        }
    ],
    "sg:phone":"+1 970 282 9166",
    "sg:postcode":"80528",
    "sg:province":"CO",
    "sg:tags":[
        "home",
        "builder"
    ],
    "wof:name":"Centex Homes",
    "wof:placetype":"venue"
},
  "geometry": {"coordinates":[-105.042073,40.499275],"type":"Point"}
}