{
  "type": "Feature",
  "properties": {
    "iso:country":"US",
    "sg:address":"3228 Tennyson St",
    "sg:city":"Denver",
    "sg:classifiers":[
        {
            "category":"Real Estate",
            "subcategory":"Real Estate Agent",
            "type":"Services"
        }
    ],
    "sg:phone":"+1 303 433 8230",
    "sg:postcode":"80212",
    "sg:province":"CO",
    "wof:name":"April Ritchie Real E State",
    "wof:placetype":"venue"
},
  "geometry": {"coordinates":[-105.04392799999999,39.762495],"type":"Point"}
}