{
  "type": "Feature",
  "properties": {
    "addr:full":"15239 E Nassau Pl Aurora CO 80014",
    "addr:housenumber":"15239",
    "addr:postcode":"80014",
    "addr:street":"E Nassau Pl",
    "iso:country":"US",
    "sg:address":"15239 E Nassau Pl",
    "sg:city":"Aurora",
    "sg:classifiers":[
        {
            "category":"Shopping",
            "subcategory":"Gifts & Souvenirs",
            "type":"Retail Goods"
        }
    ],
    "sg:phone":"+1 303 369 4886",
    "sg:postcode":"80014",
    "sg:province":"CO",
    "wof:name":"Pack Mail",
    "wof:placetype":"venue"
},
  "geometry": {"coordinates":[-104.810968,39.644814],"type":"Point"}
}