{
  "type": "Feature",
  "properties": {
    "addr:full":"12951 Monarch Ct Broomfield CO 80020",
    "addr:housenumber":"12951",
    "addr:postcode":"80020",
    "addr:street":"Monarch Ct",
    "iso:country":"US",
    "sg:address":"12951 Monarch Ct",
    "sg:city":"Broomfield",
    "sg:classifiers":[
        {
            "category":"Manufacturing",
            "subcategory":"Tools & Machinery",
            "type":"Manufacturing & Wholesale Goods"
        }
    ],
    "sg:phone":"+1 303 635 0994",
    "sg:postcode":"80020",
    "sg:province":"CO",
    "sg:tags":[
        "electric",
        "mfg",
        "system",
        "drive",
        "automated",
        "starter"
    ],
    "wof:name":"Benshaw Inc",
    "wof:placetype":"venue"
},
  "geometry": {"coordinates":[-105.026217,39.930916],"type":"Point"}
}