{
  "type": "Feature",
  "properties": {
    "iso:country":"US",
    "sg:address":"170 Hemlock St",
    "sg:city":"Broomfield",
    "sg:classifiers":[
        {
            "category":"Building & Trades",
            "subcategory":"Electrical",
            "type":"Services"
        }
    ],
    "sg:phone":"+1 303 460 0942",
    "sg:postcode":"80020",
    "sg:province":"CO",
    "sg:tags":[
        "electrical",
        "electric",
        "contractor"
    ],
    "wof:name":"Holder Electric Inc",
    "wof:placetype":"venue"
},
  "geometry": {"coordinates":[-105.080386,39.916934],"type":"Point"}
}