{
  "type": "Feature",
  "properties": {
    "iso:country":"US",
    "sg:address":"4235 Decatur St",
    "sg:city":"Denver",
    "sg:classifiers":[
        {
            "category":"Wholesale",
            "subcategory":"Computers",
            "type":"Manufacturing & Wholesale Goods"
        }
    ],
    "sg:phone":"+1 303 583 6722",
    "sg:postcode":"80211",
    "sg:province":"CO",
    "wof:name":"Dimelow Enterprises LLC",
    "wof:placetype":"venue"
},
  "geometry": {"coordinates":[-105.02213500000001,39.774904],"type":"Point"}
}