{
  "type": "Feature",
  "properties": {
    "addr:full":"13587 W 22nd Pl Golden CO 80401",
    "addr:housenumber":"13587",
    "addr:postcode":"co 80401",
    "addr:street":"W 22Nd Pl",
    "iso:country":"US",
    "sg:address":"13587 W 22nd Pl",
    "sg:city":"Golden",
    "sg:classifiers":[
        {
            "category":"Professional",
            "subcategory":"Accounting & Tax Preparation",
            "type":"Services"
        }
    ],
    "sg:phone":"+1 303 278 0885",
    "sg:postcode":"80401",
    "sg:province":"CO",
    "sg:tags":[
        "accountant"
    ],
    "wof:name":"Padgett Business Svc",
    "wof:placetype":"venue"
},
  "geometry": {"coordinates":[-105.151038,39.753431],"type":"Point"}
}