{
  "type": "Feature",
  "properties": {
    "addr:full":"1934 13th St Steamboat Spgs CO 80487",
    "addr:housenumber":"1934",
    "addr:postcode":"80487",
    "addr:street":"13Th St Steamboat Spgs",
    "iso:country":"US",
    "sg:address":"1934 13th St",
    "sg:city":"Steamboat Spgs",
    "sg:classifiers":[
        {
            "category":"Wholesale",
            "subcategory":"Groceries",
            "type":"Manufacturing & Wholesale Goods"
        }
    ],
    "sg:phone":"+1 970 879 4276",
    "sg:postcode":"80487",
    "sg:province":"CO",
    "sg:tags":[
        "tea",
        "coffee"
    ],
    "sg:website":"www.steamboatcoffee.com",
    "wof:name":"Steamboat Coffee Roasters",
    "wof:placetype":"venue"
},
  "geometry": {"coordinates":[-106.85095099999999,40.491804],"type":"Point"}
}