{
  "type": "Feature",
  "properties": {
    "addr:full":"2780 Kendrick St Golden CO 80401",
    "addr:housenumber":"2780",
    "addr:postcode":"80401",
    "addr:street":"Kendrick St",
    "iso:country":"US",
    "sg:address":"2780 Kendrick St",
    "sg:city":"Golden",
    "sg:classifiers":[
        {
            "category":"Food & Beverages",
            "subcategory":"Meat & Fish",
            "type":"Retail Goods"
        }
    ],
    "sg:phone":"+1 303 271 1047",
    "sg:postcode":"80401",
    "sg:province":"CO",
    "wof:name":"Dannys Meat Service",
    "wof:placetype":"venue"
},
  "geometry": {"coordinates":[-105.17013300000001,39.757859],"type":"Point"}
}