{
  "type": "Feature",
  "properties": {
    "addr:full":"28071 Camel Heights Cir Evergreen CO 80439",
    "addr:postcode":"28071;80439",
    "addr:street":"Camel Heights Cir",
    "iso:country":"US",
    "sg:address":"28071 Camel Heights Cir",
    "sg:city":"Evergreen",
    "sg:classifiers":[
        {
            "category":"Manufacturing",
            "subcategory":"Furniture",
            "type":"Manufacturing & Wholesale Goods"
        }
    ],
    "sg:phone":"+1 303 674 5459",
    "sg:postcode":"80439",
    "sg:province":"CO",
    "sg:tags":[
        "household",
        "wood",
        "mfg"
    ],
    "wof:name":"Out of Forest LLC",
    "wof:placetype":"venue"
},
  "geometry": {"coordinates":[-105.321333,39.623991],"type":"Point"}
}