{
  "type": "Feature",
  "properties": {
    "addr:full":"113 S 2nd St Sterling CO 80751",
    "addr:housenumber":"113",
    "addr:postcode":"80751",
    "addr:street":"S 2Nd St",
    "iso:country":"US",
    "sg:address":"113 S 2nd St",
    "sg:city":"Sterling",
    "sg:classifiers":[
        {
            "category":"Professional",
            "subcategory":"Lawyer & Legal Services",
            "type":"Services"
        }
    ],
    "sg:phone":"+1 970 522 8689",
    "sg:postcode":"80751",
    "sg:province":"CO",
    "sg:tags":[
        "attorney"
    ],
    "wof:name":"Nicholas E Schaefer",
    "wof:placetype":"venue"
},
  "geometry": {"coordinates":[-103.207559,40.622943],"type":"Point"}
}