{
  "type": "Feature",
  "properties": {
    "addr:full":"2432 S Colorado Blvd Denver CO 80222",
    "addr:housenumber":"2432",
    "addr:postcode":"80222",
    "addr:street":"S Colorado Blvd",
    "iso:country":"US",
    "sg:address":"2432 S Colorado Blvd",
    "sg:city":"Denver",
    "sg:classifiers":[
        {
            "category":"Food & Beverages",
            "subcategory":"Bakery",
            "type":"Retail Goods"
        }
    ],
    "sg:phone":"+1 303 757 3944",
    "sg:postcode":"80222",
    "sg:province":"CO",
    "sg:tags":[
        "sandwich"
    ],
    "wof:name":"Taste of Philly",
    "wof:placetype":"venue"
},
  "geometry": {"coordinates":[-104.94059,39.672342],"type":"Point"}
}