{
  "type": "Feature",
  "properties": {
    "iso:country":"US",
    "sg:address":"1524 Belford Ct",
    "sg:city":"Evergreen",
    "sg:classifiers":[
        {
            "category":"Insurance",
            "subcategory":"Insurance Agent",
            "type":"Services"
        }
    ],
    "sg:phone":"+1 303 670 0935",
    "sg:postcode":"80439",
    "sg:province":"CO",
    "wof:name":"Evergreen Benefits Group",
    "wof:placetype":"venue"
},
  "geometry": {"coordinates":[-105.36636,39.688226],"type":"Point"}
}