{
  "type": "Feature",
  "properties": {
    "addr:full":"1610 Little Raven St Denver CO 80202",
    "addr:housenumber":"1610",
    "addr:postcode":"80202",
    "addr:street":"Little Raven St",
    "iso:country":"US",
    "sg:address":"1610 Little Raven St",
    "sg:city":"Denver",
    "sg:classifiers":[
        {
            "category":"Real Estate",
            "subcategory":"Real Estate Services",
            "type":"Services"
        }
    ],
    "sg:phone":"+1 720 904 6904",
    "sg:postcode":"80202",
    "sg:province":"CO",
    "sg:tags":[
        "management",
        "property"
    ],
    "sg:website":"www.eastwesturban.com",
    "wof:name":"East West Urban Mgmt",
    "wof:placetype":"venue"
},
  "geometry": {"coordinates":[-105.003998,39.7561],"type":"Point"}
}