{
  "type": "Feature",
  "properties": {
    "addr:full":"124 E Elkhorn Ave Estes Park CO 80517",
    "addr:housenumber":"124",
    "addr:postcode":"80517",
    "addr:street":"E Elkhorn Ave",
    "iso:country":"US",
    "sg:address":"124 E Elkhorn Ave",
    "sg:city":"Estes Park",
    "sg:classifiers":[
        {
            "category":"Shopping",
            "subcategory":"Gifts & Souvenirs",
            "type":"Retail Goods"
        }
    ],
    "sg:phone":"+1 970 586 2130",
    "sg:postcode":"80517",
    "sg:province":"CO",
    "sg:tags":[
        "shop"
    ],
    "wof:name":"Rocky Mountain Traders",
    "wof:placetype":"venue"
},
  "geometry": {"coordinates":[-105.522858,40.376214],"type":"Point"}
}