{
  "type": "Feature",
  "properties": {
    "addr:full":"1618 N College Ave Fort Collins CO 80524",
    "addr:housenumber":"1618",
    "addr:postcode":"80524",
    "addr:street":"N College Ave",
    "iso:country":"US",
    "sg:address":"1618 N College Ave",
    "sg:city":"Fort Collins",
    "sg:classifiers":[
        {
            "category":"Banks & Credit Unions",
            "subcategory":"Investment Brokerage",
            "type":"Services"
        }
    ],
    "sg:phone":"+1 970 416 8766",
    "sg:postcode":"80524",
    "sg:province":"CO",
    "sg:tags":[
        "security"
    ],
    "wof:name":"Edward Jones Co",
    "wof:placetype":"venue"
},
  "geometry": {"coordinates":[-105.07642300000001,40.610089],"type":"Point"}
}