{
  "type": "Feature",
  "properties": {
    "iso:country":"US",
    "sg:address":"4901 N Co Rd 11C",
    "sg:city":"Loveland",
    "sg:classifiers":[
        {
            "category":"Manufacturing",
            "subcategory":"Printing",
            "type":"Manufacturing & Wholesale Goods"
        }
    ],
    "sg:phone":"+1 970 667 1477",
    "sg:postcode":"80538",
    "sg:province":"CO",
    "sg:tags":[
        "lithographic",
        "commercial"
    ],
    "wof:name":"Gold Spike Printing Inc",
    "wof:placetype":"venue"
},
  "geometry": {"coordinates":[-105.044471,40.448847],"type":"Point"}
}