{
  "type": "Feature",
  "properties": {
    "addr:full":"1241 Ceres Dr Lafayette CO 80026",
    "addr:housenumber":"1241",
    "addr:postcode":"80026",
    "addr:street":"Ceres Dr",
    "iso:country":"US",
    "sg:address":"1241 Ceres Dr",
    "sg:city":"Lafayette",
    "sg:classifiers":[
        {
            "category":"Organizations",
            "subcategory":"Religious Organization",
            "type":"Services"
        }
    ],
    "sg:phone":"+1 303 665 4280",
    "sg:postcode":"80026",
    "sg:province":"CO",
    "sg:tags":[
        "church"
    ],
    "sg:website":"www.theuufellowship.org",
    "wof:name":"Unitarian Universalist Fllwshp",
    "wof:placetype":"venue"
},
  "geometry": {"coordinates":[-105.11379599999999,39.987799],"type":"Point"}
}