{
  "type": "Feature",
  "properties": {
    "iso:country":"US",
    "sg:address":"1330 Leyden St",
    "sg:city":"Denver",
    "sg:classifiers":[
        {
            "category":"Insurance",
            "subcategory":"Insurance Agent",
            "type":"Services"
        }
    ],
    "sg:phone":"+1 303 388 6530",
    "sg:postcode":"80220",
    "sg:province":"CO",
    "wof:name":"Gonzales Ida",
    "wof:placetype":"venue"
},
  "geometry": {"coordinates":[-104.914978,39.737855],"type":"Point"}
}