{
  "type": "Feature",
  "properties": {
    "addr:full":"4701 Kiowa Dr Greeley CO 80634",
    "addr:housenumber":"4701",
    "addr:postcode":"80634",
    "addr:street":"Kiowa Dr",
    "iso:country":"US",
    "sg:address":"4701 Kiowa Dr",
    "sg:city":"Greeley",
    "sg:classifiers":[
        {
            "category":"Building & Trades",
            "subcategory":"Construction",
            "type":"Services"
        }
    ],
    "sg:phone":"+1 970 330 8378",
    "sg:postcode":"80634",
    "sg:province":"CO",
    "sg:tags":[
        "contractor"
    ],
    "wof:name":"Eagle Profit Systems Inc",
    "wof:placetype":"venue"
},
  "geometry": {"coordinates":[-104.758937,40.371543],"type":"Point"}
}