{
  "type": "Feature",
  "properties": {
    "iso:country":"US",
    "sg:address":"1808 E Colfax Ave",
    "sg:city":"Denver",
    "sg:classifiers":[
        {
            "category":"Building & Trades",
            "subcategory":"Locksmith",
            "type":"Services"
        }
    ],
    "sg:phone":"+1 303 557 6724",
    "sg:postcode":"80218",
    "sg:province":"CO",
    "sg:tags":[
        "key"
    ],
    "wof:name":"Locksmith",
    "wof:placetype":"venue"
},
  "geometry": {"coordinates":[-104.965867,39.739873],"type":"Point"}
}