{
  "type": "Feature",
  "properties": {
    "addr:full":"351 Ranney St Craig CO 81625",
    "addr:housenumber":"351",
    "addr:postcode":"81625",
    "addr:street":"Ranney St",
    "iso:country":"US",
    "sg:address":"351 Ranney St",
    "sg:city":"Craig",
    "sg:classifiers":[
        {
            "category":"Restaurant",
            "type":"Food & Drink"
        }
    ],
    "sg:phone":"+1 970 824 5455",
    "sg:postcode":"81625",
    "sg:province":"CO",
    "sg:tags":[
        "eating"
    ],
    "wof:name":"Casa Loya",
    "wof:placetype":"venue"
},
  "geometry": {"coordinates":[-107.55296800000001,40.511166],"type":"Point"}
}