{
  "type": "Feature",
  "properties": {
    "iso:country":"US",
    "sg:address":"111 22nd Ct",
    "sg:city":"Grand Junction",
    "sg:classifiers":[
        {
            "category":"Shopping",
            "subcategory":"Used Merchandise",
            "type":"Retail Goods"
        }
    ],
    "sg:phone":"+1 970 263 9373",
    "sg:postcode":"81501",
    "sg:province":"CO",
    "sg:tags":[
        "furniture"
    ],
    "wof:name":"Used Furniture Outlet",
    "wof:placetype":"venue"
},
  "geometry": {"coordinates":[-108.53976299999999,39.068581],"type":"Point"}
}