{
  "type": "Feature",
  "properties": {
    "addr:full":"1 S Washington St Denver CO 80209",
    "addr:housenumber":"1",
    "addr:postcode":"80209",
    "addr:street":"S Washington St",
    "iso:country":"US",
    "sg:address":"1 S Washington St",
    "sg:city":"Denver",
    "sg:classifiers":[
        {
            "category":"Real Estate",
            "subcategory":"Real Estate Operator",
            "type":"Services"
        }
    ],
    "sg:phone":"+1 303 282 8640",
    "sg:postcode":"80209",
    "sg:province":"CO",
    "sg:tags":[
        "building",
        "nonresidential"
    ],
    "wof:name":"Cln Properties LLC",
    "wof:placetype":"venue"
},
  "geometry": {"coordinates":[-104.979169,39.714714],"type":"Point"}
}