{
  "type": "Feature",
  "properties": {
    "addr:full":"10101 E Dry Creek Rd Englewood CO 80112",
    "addr:housenumber":"10101",
    "addr:postcode":"80112",
    "addr:street":"E Dry Creek Rd",
    "iso:country":"US",
    "sg:address":"10101 E Dry Creek Rd",
    "sg:city":"Englewood",
    "sg:classifiers":[
        {
            "category":"Mining & Drilling",
            "type":"Manufacturing & Wholesale Goods"
        }
    ],
    "sg:phone":"+1 303 708 4200",
    "sg:postcode":"80112",
    "sg:province":"CO",
    "sg:tags":[
        "ore",
        "milling",
        "gold"
    ],
    "wof:name":"Newmont Mining Corporation",
    "wof:placetype":"venue"
},
  "geometry": {"coordinates":[-104.86977899999999,39.580926],"type":"Point"}
}