{
  "type": "Feature",
  "properties": {
    "addr:full":"2661 Catalina Dr Grand Junction CO 81506",
    "addr:housenumber":"2661",
    "addr:postcode":"81506",
    "addr:street":"Catalina Dr",
    "iso:country":"US",
    "sg:address":"2661 Catalina Dr",
    "sg:city":"Grand Junction",
    "sg:classifiers":[
        {
            "category":"Manufacturing",
            "subcategory":"Electronics",
            "type":"Manufacturing & Wholesale Goods"
        }
    ],
    "sg:phone":"+1 970 256 9081",
    "sg:postcode":"81506",
    "sg:province":"CO",
    "sg:tags":[
        "equipment",
        "mfg",
        "communications"
    ],
    "wof:name":"Orions Belt LLC",
    "wof:placetype":"venue"
},
  "geometry": {"coordinates":[-108.55811,39.126484],"type":"Point"}
}