{
  "type": "Feature",
  "properties": {
    "iso:country":"US",
    "sg:address":"12900 Murphy Rd",
    "sg:city":"Elbert",
    "sg:classifiers":[
        {
            "category":"Retail",
            "subcategory":"Animal Services",
            "type":"Services"
        }
    ],
    "sg:phone":"+1 719 495 0677",
    "sg:postcode":"80106",
    "sg:province":"CO",
    "sg:tags":[
        "pet",
        "boarding",
        "sitting"
    ],
    "wof:name":"Castleton Boarding & Grooming",
    "wof:placetype":"venue"
},
  "geometry": {"coordinates":[-104.58983600000001,39.042534],"type":"Point"}
}