{
  "type": "Feature",
  "properties": {
    "addr:full":"9380 Utica St Westminster CO 80031",
    "addr:housenumber":"9380",
    "addr:postcode":"80031",
    "addr:street":"Utica St",
    "iso:country":"US",
    "sg:address":"9380 Utica St",
    "sg:city":"Westminster",
    "sg:classifiers":[
        {
            "category":"Real Estate",
            "subcategory":"Real Estate Agent",
            "type":"Services"
        }
    ],
    "sg:phone":"+1 303 466 5600",
    "sg:postcode":"80031",
    "sg:province":"CO",
    "wof:name":"Camelot Brokers LLC",
    "wof:placetype":"venue"
},
  "geometry": {"coordinates":[-105.043147,39.865902],"type":"Point"}
}