{
  "type": "Feature",
  "properties": {
    "iso:country":"US",
    "sg:address":"570 Co Rd 250",
    "sg:city":"Durango",
    "sg:classifiers":[
        {
            "category":"Building & Trades",
            "subcategory":"Plumbing",
            "type":"Services"
        }
    ],
    "sg:phone":"+1 970 382 0030",
    "sg:postcode":"81301",
    "sg:province":"CO",
    "sg:tags":[
        "plumbing",
        "contractor"
    ],
    "wof:name":"Timberland Plumbing & Heating",
    "wof:placetype":"venue"
},
  "geometry": {"coordinates":[-107.83709,37.307502],"type":"Point"}
}