{
  "type": "Feature",
  "properties": {
    "addr:full":"1901 Kipling St Lakewood CO 80215",
    "addr:housenumber":"1901",
    "addr:postcode":"80215",
    "addr:street":"Kipling St",
    "iso:country":"US",
    "sg:address":"1901 Kipling St",
    "sg:city":"Lakewood",
    "sg:classifiers":[
        {
            "category":"Personal",
            "subcategory":"Beauty Salon",
            "type":"Services"
        }
    ],
    "sg:phone":"+1 303 232 5005",
    "sg:postcode":"80215",
    "sg:province":"CO",
    "wof:name":"Amalie Hue",
    "wof:placetype":"venue"
},
  "geometry": {"coordinates":[-105.109566,39.747423],"type":"Point"}
}