{
  "type": "Feature",
  "properties": {
    "iso:country":"US",
    "sg:address":"1040 S Gaylord St",
    "sg:city":"Denver",
    "sg:classifiers":[
        {
            "category":"Real Estate",
            "subcategory":"Real Estate Agent",
            "type":"Services"
        }
    ],
    "sg:phone":"+1 720 570 3707",
    "sg:postcode":"80209",
    "sg:province":"CO",
    "wof:name":"Ventures & Valuations",
    "wof:placetype":"venue"
},
  "geometry": {"coordinates":[-104.961669,39.697327],"type":"Point"}
}