{
  "type": "Feature",
  "properties": {
    "iso:country":"US",
    "sg:address":"225 12th St SE",
    "sg:city":"Loveland",
    "sg:classifiers":[
        {
            "category":"Building & Trades",
            "subcategory":"Construction",
            "type":"Services"
        }
    ],
    "sg:phone":"+1 970 962 9908",
    "sg:postcode":"80537",
    "sg:province":"CO",
    "sg:tags":[
        "house",
        "remodeling"
    ],
    "wof:name":"Rust Construction Inc",
    "wof:placetype":"venue"
},
  "geometry": {"coordinates":[-105.076903,40.380223],"type":"Point"}
}