{
  "type": "Feature",
  "properties": {
    "iso:country":"US",
    "sg:address":"724 N 30th St",
    "sg:city":"Colorado Springs",
    "sg:classifiers":[
        {
            "category":"Banks & Credit Unions",
            "subcategory":"Financial Services",
            "type":"Services"
        }
    ],
    "sg:phone":"+1 719 634 4781",
    "sg:postcode":"80904",
    "sg:province":"CO",
    "sg:tags":[
        "company",
        "holding"
    ],
    "wof:name":"Me & Mike Inc",
    "wof:placetype":"venue"
},
  "geometry": {"coordinates":[-104.865577,38.860805],"type":"Point"}
}