{
  "type": "Feature",
  "properties": {
    "addr:full":"138 W Sycamore Ln Louisville CO 80027",
    "addr:housenumber":"138",
    "addr:postcode":"80027",
    "addr:street":"W Sycamore Ln",
    "iso:country":"US",
    "sg:address":"138 W Sycamore Ln",
    "sg:city":"Louisville",
    "sg:classifiers":[
        {
            "category":"Building & Trades",
            "subcategory":"Construction",
            "type":"Services"
        }
    ],
    "sg:phone":"+1 303 666 9465",
    "sg:postcode":"80027",
    "sg:province":"CO",
    "sg:tags":[
        "trenching",
        "contractor"
    ],
    "wof:name":"Front Range Trenching Co",
    "wof:placetype":"venue"
},
  "geometry": {"coordinates":[-105.140952,39.973804],"type":"Point"}
}