{
  "type": "Feature",
  "properties": {
    "iso:country":"US",
    "sg:address":"2535 W Barberry Pl",
    "sg:city":"Denver",
    "sg:classifiers":[
        {
            "category":"Wholesale",
            "subcategory":"Hardware",
            "type":"Manufacturing & Wholesale Goods"
        }
    ],
    "sg:phone":"+1 303 623 1411",
    "sg:postcode":"80204",
    "sg:province":"CO",
    "sg:tags":[
        "system",
        "equipment",
        "air",
        "heating",
        "supply"
    ],
    "wof:name":"Air Handlers Supply Inc",
    "wof:placetype":"venue"
},
  "geometry": {"coordinates":[-105.018676,39.730371],"type":"Point"}
}