{
  "type": "Feature",
  "properties": {
    "iso:country":"US",
    "sg:address":"3435 Macgregor Dr",
    "sg:city":"Colorado Springs",
    "sg:classifiers":[
        {
            "category":"Shopping",
            "type":"Retail Goods"
        }
    ],
    "sg:phone":"+1 719 596 4518",
    "sg:postcode":"80922",
    "sg:province":"CO",
    "sg:tags":[
        "merchandise"
    ],
    "wof:name":"More Than Just Names",
    "wof:placetype":"venue"
},
  "geometry": {"coordinates":[-104.70125299999999,38.881488],"type":"Point"}
}