{
  "type": "Feature",
  "properties": {
    "iso:country":"US",
    "sg:address":"1900 Snowy Owl Dr",
    "sg:city":"Broomfield",
    "sg:classifiers":[
        {
            "category":"Building & Trades",
            "subcategory":"Electrical",
            "type":"Services"
        }
    ],
    "sg:phone":"+1 303 438 8055",
    "sg:postcode":"80020",
    "sg:province":"CO",
    "sg:tags":[
        "electrical",
        "contractor"
    ],
    "wof:name":"Accent Electrical Services Cor",
    "wof:placetype":"venue"
},
  "geometry": {"coordinates":[-105.06298,39.942467],"type":"Point"}
}