{
  "type": "Feature",
  "properties": {
    "addr:full":"206 S Washington St Otis CO 80743",
    "addr:housenumber":"206",
    "addr:postcode":"80743",
    "addr:street":"S Washington St",
    "iso:country":"US",
    "sg:address":"206 S Washington St",
    "sg:city":"Otis",
    "sg:classifiers":[
        {
            "category":"Social Services",
            "type":"Services"
        }
    ],
    "sg:phone":"+1 970 246 3476",
    "sg:postcode":"80743",
    "sg:province":"CO",
    "sg:tags":[
        "senior",
        "citizen"
    ],
    "wof:name":"Otis Senior Ctr",
    "wof:placetype":"venue"
},
  "geometry": {"coordinates":[-102.961495,40.147631],"type":"Point"}
}