{
  "type": "Feature",
  "properties": {
    "addr:full":"3225 W Ada Pl Denver CO 80219",
    "addr:housenumber":"3225",
    "addr:postcode":"80219",
    "addr:street":"W Ada Pl",
    "iso:country":"US",
    "sg:address":"3225 W Ada Pl",
    "sg:city":"Denver",
    "sg:classifiers":[
        {
            "category":"Home & Garden",
            "subcategory":"Carpets & Floor Coverings",
            "type":"Retail Goods"
        }
    ],
    "sg:phone":"+1 303 935 8092",
    "sg:postcode":"80219",
    "sg:province":"CO",
    "wof:name":"Cisneros Javier Carpet & Vinyl",
    "wof:placetype":"venue"
},
  "geometry": {"coordinates":[-105.028837,39.701413],"type":"Point"}
}