{
  "type": "Feature",
  "properties": {
    "iso:country":"US",
    "sg:address":"265 Co Rd 5",
    "sg:city":"Meeker",
    "sg:classifiers":[
        {
            "category":"Government",
            "subcategory":"Office",
            "type":"Public Place"
        }
    ],
    "sg:phone":"+1 970 878 5548",
    "sg:postcode":"81641",
    "sg:province":"CO",
    "sg:tags":[
        "state",
        "program"
    ],
    "wof:name":"Driver's License Office",
    "wof:placetype":"venue"
},
  "geometry": {"coordinates":[-107.951359,39.737855],"type":"Point"}
}