{
  "type": "Feature",
  "properties": {
    "iso:country":"US",
    "sg:address":"1255 Lake Plaza Dr",
    "sg:city":"Colorado Springs",
    "sg:classifiers":[
        {
            "category":"Banks & Credit Unions",
            "subcategory":"Bank",
            "type":"Services"
        }
    ],
    "sg:phone":"+1 719 636 2550",
    "sg:postcode":"80906",
    "sg:province":"CO",
    "sg:tags":[
        "loan",
        "real estate"
    ],
    "wof:name":"Peak Financial Group",
    "wof:placetype":"venue"
},
  "geometry": {"coordinates":[-104.806634,38.793593],"type":"Point"}
}