{
  "type": "Feature",
  "properties": {
    "iso:country":"US",
    "sg:address":"3901 S Santa Fe Dr",
    "sg:city":"Sheridan",
    "sg:classifiers":[
        {
            "category":"Arts & Performance",
            "subcategory":"Theater",
            "type":"Entertainment"
        }
    ],
    "sg:phone":"+1 303 762 1379",
    "sg:postcode":"80110",
    "sg:province":"CO",
    "sg:tags":[
        "entertainer"
    ],
    "wof:name":"Adult Palace",
    "wof:placetype":"venue"
},
  "geometry": {"coordinates":[-105.0043,39.648147],"type":"Point"}
}