{
  "type": "Feature",
  "properties": {
    "addr:full":"1329 Constitution Rd Pueblo CO 81001",
    "addr:housenumber":"1329",
    "addr:postcode":"81001",
    "addr:street":"Constitution Rd",
    "iso:country":"US",
    "sg:address":"1329 Constitution Rd",
    "sg:city":"Pueblo",
    "sg:classifiers":[
        {
            "category":"Building & Trades",
            "subcategory":"Construction",
            "type":"Services"
        }
    ],
    "sg:phone":"+1 719 583 0261",
    "sg:postcode":"81001",
    "sg:province":"CO",
    "sg:tags":[
        "contractor"
    ],
    "wof:name":"Tk Roofing",
    "wof:placetype":"venue"
},
  "geometry": {"coordinates":[-104.586618,38.288189],"type":"Point"}
}