{
  "type": "Feature",
  "properties": {
    "addr:full":"3840 E 10th Ave Denver CO 80206",
    "addr:housenumber":"3840",
    "addr:postcode":"80206",
    "addr:street":"E 10Th Ave",
    "iso:country":"US",
    "sg:address":"3840 E 10th Ave",
    "sg:city":"Denver",
    "sg:classifiers":[
        {
            "category":"Banks & Credit Unions",
            "subcategory":"Bank",
            "type":"Services"
        }
    ],
    "sg:phone":"+1 303 244 5770",
    "sg:postcode":"80206",
    "sg:province":"CO",
    "wof:name":"Bank One",
    "wof:placetype":"venue"
},
  "geometry": {"coordinates":[-104.94221899999999,39.732003],"type":"Point"}
}