{
  "type": "Feature",
  "properties": {
    "addr:full":"9940 E Costilla Ave Centennial CO 80112",
    "addr:housenumber":"9940",
    "addr:postcode":"80112",
    "addr:street":"E Costilla Ave",
    "iso:country":"US",
    "sg:address":"9940 E Costilla Ave",
    "sg:city":"Centennial",
    "sg:classifiers":[
        {
            "category":"Shopping",
            "subcategory":"Computers & Home Electronics",
            "type":"Retail Goods"
        },
        {
            "category":"Professional",
            "subcategory":"Computer Services",
            "type":"Services"
        }
    ],
    "sg:phone":"+1 303 799 0477",
    "sg:postcode":"80112",
    "sg:province":"CO",
    "sg:tags":[
        "construction",
        "internet"
    ],
    "sg:website":"www.dcsracing.com",
    "wof:name":"Digital Communication Services",
    "wof:placetype":"venue"
},
  "geometry": {"coordinates":[-104.871819,39.591349],"type":"Point"}
}