{
  "type": "Feature",
  "properties": {
    "addr:full":"27300 State Hwy 74 Evergreen CO 80439",
    "addr:housenumber":"27300",
    "addr:postcode":"80439",
    "addr:street":"State Hwy 74",
    "iso:country":"US",
    "sg:address":"27300 State Hwy 74",
    "sg:city":"Evergreen",
    "sg:classifiers":[
        {
            "category":"Professional",
            "type":"Services"
        }
    ],
    "sg:phone":"+1 303 674 4411",
    "sg:postcode":"80439",
    "sg:province":"CO",
    "wof:name":"Lynne Sparks",
    "wof:placetype":"venue"
},
  "geometry": {"coordinates":[-105.30777999999999,39.643837],"type":"Point"}
}