{
  "type": "Feature",
  "properties": {
    "addr:full":"1221 S 12th St Canon City CO 81212",
    "addr:housenumber":"1221",
    "addr:postcode":"81212",
    "addr:street":"S 12Th St",
    "iso:country":"US",
    "sg:address":"1221 S 12th St",
    "sg:city":"Canon City",
    "sg:classifiers":[
        {
            "category":"Restaurant",
            "type":"Food & Drink"
        }
    ],
    "sg:phone":"+1 719 276 2920",
    "sg:postcode":"81212",
    "sg:province":"CO",
    "sg:tags":[
        "eating"
    ],
    "wof:name":"McClellans Brew & Grill LLC",
    "wof:placetype":"venue"
},
  "geometry": {"coordinates":[-105.226185,38.431675],"type":"Point"}
}