{
  "type": "Feature",
  "properties": {
    "iso:country":"US",
    "sg:address":"4425 W Hayward Pl",
    "sg:city":"Denver",
    "sg:classifiers":[
        {
            "category":"Freight",
            "type":"Transportation"
        }
    ],
    "sg:phone":"+1 303 284 0195",
    "sg:postcode":"80212",
    "sg:province":"CO",
    "sg:tags":[
        "logistics",
        "full",
        "provider"
    ],
    "wof:name":"The Select Carrier Group",
    "wof:placetype":"venue"
},
  "geometry": {"coordinates":[-105.046116,39.759474],"type":"Point"}
}