{
  "type": "Feature",
  "properties": {
    "addr:full":"5405 W 56th Ave Unit A Arvada CO 80002",
    "addr:housenumber":"5405",
    "addr:postcode":"80002",
    "addr:street":"W 56Th Ave Unit A",
    "iso:country":"US",
    "sg:address":"5405 W 56th Ave Unit A",
    "sg:city":"Arvada",
    "sg:classifiers":[
        {
            "category":"Autos & Motor Vehicles",
            "subcategory":"Motorcycle Sales",
            "type":"Retail Goods"
        }
    ],
    "sg:phone":"+1 303 456 4757",
    "sg:postcode":"80002",
    "sg:province":"CO",
    "sg:website":"www.motogearoutlet.com",
    "wof:name":"Motogear Outlet",
    "wof:placetype":"venue"
},
  "geometry": {"coordinates":[-105.054834,39.800478],"type":"Point"}
}