{
  "type": "Feature",
  "properties": {
    "addr:full":"1921 S Pagosa St Aurora CO 80013",
    "addr:housenumber":"1921",
    "addr:postcode":"80013",
    "addr:street":"S Pagosa St",
    "iso:country":"US",
    "sg:address":"1921 S Pagosa St",
    "sg:city":"Aurora",
    "sg:classifiers":[
        {
            "category":"Professional",
            "subcategory":"Detective & Security Services",
            "type":"Services"
        }
    ],
    "sg:phone":"+1 303 337 4326",
    "sg:postcode":"80013",
    "sg:province":"CO",
    "sg:tags":[
        "investigator"
    ],
    "wof:name":"Adams & Adams Investigations",
    "wof:placetype":"venue"
},
  "geometry": {"coordinates":[-104.790327,39.68085],"type":"Point"}
}