{
  "type": "Feature",
  "properties": {
    "iso:country":"US",
    "sg:address":"12739 Rd 5 S",
    "sg:city":"Alamosa",
    "sg:classifiers":[
        {
            "category":"Real Estate",
            "subcategory":"Real Estate Agent",
            "type":"Services"
        }
    ],
    "sg:phone":"+1 719 589 1479",
    "sg:postcode":"81101",
    "sg:province":"CO",
    "wof:name":"Dreamers and Doers LLC",
    "wof:placetype":"venue"
},
  "geometry": {"coordinates":[-105.807692,37.502794],"type":"Point"}
}