{
  "type": "Feature",
  "properties": {
    "iso:country":"US",
    "sg:address":"688 University Dr",
    "sg:city":"Woodland Park",
    "sg:classifiers":[
        {
            "category":"Professional",
            "type":"Services"
        }
    ],
    "sg:phone":"+1 719 684 2180",
    "sg:postcode":"80863",
    "sg:province":"CO",
    "wof:name":"HI Buy LLC",
    "wof:placetype":"venue"
},
  "geometry": {"coordinates":[-105.100707,38.964502],"type":"Point"}
}