{
  "type": "Feature",
  "properties": {
    "addr:full":"198 Sunlight Dr Grand Junction CO 81503",
    "addr:housenumber":"198",
    "addr:postcode":"81503",
    "addr:street":"Sunlight Dr",
    "iso:country":"US",
    "sg:address":"198 Sunlight Dr",
    "sg:city":"Grand Junction",
    "sg:classifiers":[
        {
            "category":"Organizations",
            "subcategory":"Religious Organization",
            "type":"Services"
        }
    ],
    "sg:phone":"+1 970 245 7068",
    "sg:postcode":"81503",
    "sg:province":"CO",
    "sg:tags":[
        "church"
    ],
    "wof:name":"House Of Prayer Pentecostal",
    "wof:placetype":"venue"
},
  "geometry": {"coordinates":[-108.528088,39.031839],"type":"Point"}
}