{
  "type": "Feature",
  "properties": {
    "addr:full":"1124 Manitou Ave Manitou Springs CO 80829",
    "addr:housenumber":"1124",
    "addr:postcode":"80829",
    "addr:street":"Manitou Ave",
    "iso:country":"US",
    "sg:address":"1124 Manitou Ave",
    "sg:city":"Manitou Springs",
    "sg:classifiers":[
        {
            "category":"Restaurant",
            "type":"Food & Drink"
        }
    ],
    "sg:phone":"+1 719 685 0986",
    "sg:postcode":"80829",
    "sg:province":"CO",
    "sg:tags":[
        "eating"
    ],
    "wof:name":"Organic Earth Cafe",
    "wof:placetype":"venue"
},
  "geometry": {"coordinates":[-104.92115,38.86143],"type":"Point"}
}