{
  "type": "Feature",
  "properties": {
    "addr:full":"627 W Colorado Ave Telluride CO 81435",
    "addr:housenumber":"627",
    "addr:postcode":"81435",
    "addr:street":"W Colorado Ave",
    "iso:country":"US",
    "sg:address":"627 W Colorado Ave",
    "sg:city":"Telluride",
    "sg:classifiers":[
        {
            "category":"Travel",
            "subcategory":"Hotels & Motels",
            "type":"Entertainment"
        }
    ],
    "sg:phone":"+1 970 728 4241",
    "sg:postcode":"81435",
    "sg:province":"CO",
    "sg:tags":[
        "breakfast",
        "accommodation",
        "bed"
    ],
    "sg:website":"www.franklinmanor.com",
    "wof:name":"Franklin Manor Bed & Breakfast",
    "wof:placetype":"venue"
},
  "geometry": {"coordinates":[-107.818248,37.939161],"type":"Point"}
}