{
  "type": "Feature",
  "properties": {
    "addr:full":"1828 S Wahsatch Ave Colorado Springs CO 80906",
    "addr:housenumber":"1828",
    "addr:postcode":"80906",
    "addr:street":"S Wahsatch Ave",
    "iso:country":"US",
    "sg:address":"1828 S Wahsatch Ave",
    "sg:city":"Colorado Springs",
    "sg:classifiers":[
        {
            "category":"Government",
            "subcategory":"Post Office",
            "type":"Public Place"
        }
    ],
    "sg:phone":"+1 719 000 1111",
    "sg:postcode":"80906",
    "sg:province":"CO",
    "wof:name":"US Post Office",
    "wof:placetype":"venue"
},
  "geometry": {"coordinates":[-104.81909899999999,38.807345],"type":"Point"}
}