{
  "type": "Feature",
  "properties": {
    "addr:full":"570 S Commercial Dr Grand Junction CO 81505",
    "addr:housenumber":"570",
    "addr:postcode":"81505",
    "addr:street":"S Commercial Dr",
    "iso:country":"US",
    "sg:address":"570 S Commercial Dr",
    "sg:city":"Grand Junction",
    "sg:classifiers":[
        {
            "category":"Building & Trades",
            "subcategory":"Pest Control",
            "type":"Services"
        },
        {
            "category":"Building & Trades",
            "subcategory":"Landscaping Services",
            "type":"Services"
        }
    ],
    "sg:phone":"+1 970 256 1928",
    "sg:postcode":"81505",
    "sg:province":"CO",
    "sg:tags":[
        "lawn",
        "garden"
    ],
    "wof:name":"Liqui-Green Lawn Care Inc",
    "wof:placetype":"venue"
},
  "geometry": {"coordinates":[-108.585339,39.08648],"type":"Point"}
}