{
  "type": "Feature",
  "properties": {
    "addr:full":"6890 S Tucson Way Englewood CO 80112",
    "addr:housenumber":"6890",
    "addr:postcode":"80112",
    "addr:street":"S Tucson Way",
    "iso:country":"US",
    "sg:address":"6890 S Tucson Way",
    "sg:city":"Englewood",
    "sg:classifiers":[
        {
            "category":"Professional",
            "subcategory":"Employment Agencies",
            "type":"Services"
        }
    ],
    "sg:phone":"+1 303 290 9800",
    "sg:postcode":"80112",
    "sg:province":"CO",
    "sg:tags":[
        "consultant",
        "search",
        "executive"
    ],
    "wof:name":"Media Management Resources",
    "wof:placetype":"venue"
},
  "geometry": {"coordinates":[-104.835297,39.59161],"type":"Point"}
}