{
  "type": "Feature",
  "properties": {
    "iso:country":"US",
    "sg:address":"2125 Bear Dr",
    "sg:city":"Steamboat Spgs",
    "sg:classifiers":[
        {
            "category":"Building & Trades",
            "subcategory":"Construction",
            "type":"Services"
        }
    ],
    "sg:phone":"+1 970 879 5677",
    "sg:postcode":"80487",
    "sg:province":"CO",
    "sg:tags":[
        "general",
        "contractor"
    ],
    "wof:name":"Townsend Construction",
    "wof:placetype":"venue"
},
  "geometry": {"coordinates":[-106.79807,40.444711],"type":"Point"}
}