{
  "type": "Feature",
  "properties": {
    "addr:full":"3960 Palmer Park Blvd Colorado Springs CO 80909",
    "addr:housenumber":"3960",
    "addr:postcode":"80909",
    "addr:street":"Palmer Park Blvd",
    "iso:country":"US",
    "sg:address":"3960 Palmer Park Blvd",
    "sg:city":"Colorado Springs",
    "sg:classifiers":[
        {
            "category":"Shopping",
            "subcategory":"Pharmacy",
            "type":"Retail Goods"
        }
    ],
    "sg:phone":"+1 719 591 0225",
    "sg:postcode":"80909",
    "sg:province":"CO",
    "sg:tags":[
        "photofinishing",
        "store",
        "variety"
    ],
    "wof:name":"Longs Drug Store",
    "wof:placetype":"venue"
},
  "geometry": {"coordinates":[-104.75360499999999,38.854415],"type":"Point"}
}