{
  "type": "Feature",
  "properties": {
    "addr:full":"4357 S Halifax St Centennial CO 80015",
    "addr:housenumber":"4357",
    "addr:postcode":"80015",
    "addr:street":"S Halifax St",
    "iso:country":"US",
    "sg:address":"4357 S Halifax St",
    "sg:city":"Centennial",
    "sg:classifiers":[
        {
            "category":"Building & Trades",
            "subcategory":"Cleaning & Sanitation",
            "type":"Services"
        }
    ],
    "sg:phone":"+1 303 933 7947",
    "sg:postcode":"80015",
    "sg:province":"CO",
    "sg:tags":[
        "janitor"
    ],
    "wof:name":"Everclean",
    "wof:placetype":"venue"
},
  "geometry": {"coordinates":[-104.754908,39.637143],"type":"Point"}
}