{
  "type": "Feature",
  "properties": {
    "iso:country":"US",
    "sg:address":"1874 Powell St",
    "sg:city":"Erie",
    "sg:classifiers":[
        {
            "category":"Shopping",
            "subcategory":"Gifts & Souvenirs",
            "type":"Retail Goods"
        }
    ],
    "sg:phone":"+1 720 371 8629",
    "sg:postcode":"80516",
    "sg:province":"CO",
    "wof:name":"Web Wedding A",
    "wof:placetype":"venue"
},
  "geometry": {"coordinates":[-105.088577,40.017761],"type":"Point"}
}