{
  "type": "Feature",
  "properties": {
    "iso:country":"US",
    "sg:address":"1605 N Union Blvd",
    "sg:city":"Colorado Springs",
    "sg:classifiers":[
        {
            "category":"Health Services",
            "subcategory":"Doctor",
            "type":"Services"
        }
    ],
    "sg:phone":"+1 719 231 4108",
    "sg:postcode":"80909",
    "sg:province":"CO",
    "sg:tags":[
        "physician",
        "surgeon"
    ],
    "wof:name":"Academy Allergy Asthma & Sinus",
    "wof:placetype":"venue"
},
  "geometry": {"coordinates":[-104.79412499999999,38.856235],"type":"Point"}
}