{
  "type": "Feature",
  "properties": {
    "iso:country":"US",
    "sg:address":"4803 S I- 25",
    "sg:city":"Pueblo",
    "sg:classifiers":[
        {
            "category":"Retail",
            "subcategory":"Auto Repair",
            "type":"Services"
        }
    ],
    "sg:phone":"+1 719 544 6661",
    "sg:postcode":"81082",
    "sg:province":"CO",
    "sg:tags":[
        "truck"
    ],
    "wof:name":"Chiarito's Truck Svc",
    "wof:placetype":"venue"
},
  "geometry": {"coordinates":[-104.523162,37.059327],"type":"Point"}
}