{
  "type": "Feature",
  "properties": {
    "iso:country":"US",
    "sg:address":"5904 S Kipling St",
    "sg:city":"Littleton",
    "sg:classifiers":[
        {
            "category":"Retail",
            "subcategory":"Car Wash",
            "type":"Services"
        }
    ],
    "sg:phone":"+1 303 972 8254",
    "sg:postcode":"80127",
    "sg:province":"CO",
    "sg:tags":[
        "operated",
        "polishing",
        "washing"
    ],
    "wof:name":"South Kipling Carousel Wash",
    "wof:placetype":"venue"
},
  "geometry": {"coordinates":[-105.109916,39.606226],"type":"Point"}
}