{
  "type": "Feature",
  "properties": {
    "addr:full":"802 S Sherman St Longmont CO 80501",
    "addr:housenumber":"802",
    "addr:postcode":"80501",
    "addr:street":"S Sherman St",
    "iso:country":"US",
    "sg:address":"802 S Sherman St",
    "sg:city":"Longmont",
    "sg:classifiers":[
        {
            "category":"Professional",
            "subcategory":"Secretarial Services",
            "type":"Services"
        }
    ],
    "sg:phone":"+1 303 774 8059",
    "sg:postcode":"80501",
    "sg:province":"CO",
    "sg:tags":[
        "transcription",
        "medical"
    ],
    "wof:name":"Pro Med Transcription Svc",
    "wof:placetype":"venue"
},
  "geometry": {"coordinates":[-105.115487,40.148739],"type":"Point"}
}