{
  "type": "Feature",
  "properties": {
    "addr:full":"125 Broadway Ave Pueblo CO 81004",
    "addr:housenumber":"125",
    "addr:postcode":"81004",
    "addr:street":"Broadway Ave",
    "iso:country":"US",
    "sg:address":"125 Broadway Ave",
    "sg:city":"Pueblo",
    "sg:classifiers":[
        {
            "category":"Professional",
            "type":"Services"
        }
    ],
    "sg:phone":"+1 719 404 0087",
    "sg:postcode":"81004",
    "sg:province":"CO",
    "wof:name":"Affordable Dental Cleanings",
    "wof:placetype":"venue"
},
  "geometry": {"coordinates":[-104.620537,38.258474],"type":"Point"}
}