{
  "type": "Feature",
  "properties": {
    "iso:country":"US",
    "sg:address":"7475 W 5th Ave Ste 204",
    "sg:city":"Lakewood",
    "sg:phone":"+1 303 231 9690",
    "sg:postcode":"80226",
    "sg:province":"CO",
    "wof:name":"Sports Monster Corp",
    "wof:placetype":"venue"
},
  "geometry": {"coordinates":[-105.079812,39.723911],"type":"Point"}
}