{
  "type": "Feature",
  "properties": {
    "addr:full":"7475 W 5th Ave Ste 204 Lakewood CO 80226",
    "addr:housenumber":"7475",
    "addr:postcode":"80226",
    "addr:street":"W 5Th Ave Ste 204",
    "iso:country":"US",
    "sg:address":"7475 W 5th Ave Ste 204",
    "sg:city":"Lakewood",
    "sg:phone":"+1 303 231 9690",
    "sg:postcode":"80226",
    "sg:province":"CO",
    "wof:name":"Sports Monster Corp",
    "wof:placetype":"venue"
},
  "geometry": {"coordinates":[-105.079812,39.723911],"type":"Point"}
}