{
  "type": "Feature",
  "properties": {
    "addr:full":"4475 Pennsylvania St Denver CO 80216",
    "addr:housenumber":"4475",
    "addr:postcode":"80216",
    "addr:street":"Pennsylvania St",
    "iso:country":"US",
    "sg:address":"4475 Pennsylvania St",
    "sg:city":"Denver",
    "sg:classifiers":[
        {
            "category":"Shopping",
            "subcategory":"Gifts & Souvenirs",
            "type":"Retail Goods"
        }
    ],
    "sg:phone":"+1 303 292 9126",
    "sg:postcode":"80216",
    "sg:province":"CO",
    "wof:name":"Country Home Creations",
    "wof:placetype":"venue"
},
  "geometry": {"coordinates":[-104.981375,39.776968],"type":"Point"}
}