{
  "type": "Feature",
  "properties": {
    "addr:full":"197 Jessen Dr Loveland CO 80537",
    "addr:housenumber":"197",
    "addr:postcode":"80537",
    "addr:street":"Jessen Dr",
    "iso:country":"US",
    "sg:address":"197 Jessen Dr",
    "sg:city":"Loveland",
    "sg:classifiers":[
        {
            "category":"Building & Trades",
            "subcategory":"Construction",
            "type":"Services"
        }
    ],
    "sg:phone":"+1 970 663 1015",
    "sg:postcode":"80537",
    "sg:province":"CO",
    "sg:tags":[
        "house"
    ],
    "wof:name":"Colorado Cambridge Homes",
    "wof:placetype":"venue"
},
  "geometry": {"coordinates":[-105.087177,40.393553],"type":"Point"}
}