{
  "type": "Feature",
  "properties": {
    "addr:full":"90 Madison St Ste 506 Denver CO 80206",
    "addr:housenumber":"90",
    "addr:postcode":"80206",
    "addr:street":"Madison St Ste 506",
    "iso:country":"US",
    "sg:address":"90 Madison St Ste 506",
    "sg:city":"Denver",
    "sg:classifiers":[
        {
            "category":"Health Services",
            "subcategory":"Doctor",
            "type":"Services"
        },
        {
            "category":"Health Services",
            "subcategory":"Dentist",
            "type":"Services"
        }
    ],
    "sg:phone":"+1 720 256 2156",
    "sg:postcode":"80206",
    "sg:province":"CO",
    "sg:tags":[
        "physician",
        "product",
        "dentists-cosmetic",
        "dentistry",
        "surgeons",
        "whitening",
        "teeth",
        "surgery",
        "oral",
        "dentists-orthodontists"
    ],
    "sg:website":"http://denver.citysearch.com/profile/external/1851136/denver_co/druckman_roger_dds.html?publisher=yellowpages&reference_id=1&placement=ypwebsitemip",
    "wof:name":"Druckman, Roger, DDS",
    "wof:placetype":"venue"
},
  "geometry": {"coordinates":[-104.946161,39.717687],"type":"Point"}
}