{
  "type": "Feature",
  "properties": {
    "addr:full":"11200 W 102nd Ave Broomfield CO 80021",
    "addr:housenumber":"11200",
    "addr:postcode":"80021",
    "addr:street":"W 102Nd Ave",
    "iso:country":"US",
    "sg:address":"11200 W 102nd Ave",
    "sg:city":"Broomfield",
    "sg:classifiers":[
        {
            "category":"Sports & Exercise",
            "subcategory":"Gym",
            "type":"Entertainment"
        }
    ],
    "sg:phone":"+1 303 439 8501",
    "sg:postcode":"80021",
    "sg:province":"CO",
    "sg:tags":[
        "personal",
        "trainer"
    ],
    "wof:name":"Ed's Personal Training",
    "wof:placetype":"venue"
},
  "geometry": {"coordinates":[-105.124416,39.880255],"type":"Point"}
}