{
  "type": "Feature",
  "properties": {
    "iso:country":"US",
    "sg:address":"Highlands Wellness Center 2416 W 32nd Ave",
    "sg:city":"Denver",
    "sg:classifiers":[
        {
            "category":"Health Services",
            "subcategory":"Health Practitioner",
            "type":"Services"
        },
        {
            "category":"Health Services",
            "subcategory":"Chiropractor",
            "type":"Services"
        }
    ],
    "sg:phone":"+1 303 621 4028",
    "sg:postcode":"80211",
    "sg:province":"CO",
    "sg:tags":[
        "therapy",
        "physical"
    ],
    "sg:website":"www.rolfingsolutions.com",
    "wof:name":"Rolfing Solutions",
    "wof:placetype":"venue"
},
  "geometry": {"coordinates":[-105.016395,39.762008],"type":"Point"}
}