{
  "type": "Feature",
  "properties": {
    "iso:country":"US",
    "sg:address":"8752 S Yosemite St",
    "sg:city":"Lone Tree",
    "sg:classifiers":[
        {
            "category":"Travel",
            "subcategory":"Hotels & Motels",
            "type":"Entertainment"
        }
    ],
    "sg:phone":"+1 303 662 1511",
    "sg:postcode":"80124",
    "sg:province":"CO",
    "sg:tags":[
        "operation"
    ],
    "sg:website":"www.extendedstay.com",
    "wof:name":"Extended Stay America",
    "wof:placetype":"venue"
},
  "geometry": {"coordinates":[-104.882386,39.556801],"type":"Point"}
}