{
  "type": "Feature",
  "properties": {
    "iso:country":"US",
    "sg:address":"9540 E Jewell Ave",
    "sg:city":"Denver",
    "sg:classifiers":[
        {
            "category":"Restaurant",
            "type":"Food & Drink"
        }
    ],
    "sg:phone":"+1 303 755 0805",
    "sg:postcode":"80247",
    "sg:province":"CO",
    "sg:tags":[
        "eating"
    ],
    "wof:name":"Pizza Hut",
    "wof:placetype":"venue"
},
  "geometry": {"coordinates":[-104.87768,39.681972],"type":"Point"}
}