{
  "type": "Feature",
  "properties": {
    "addr:full":"16400 W 54th Ave Golden CO 80403",
    "addr:housenumber":"16400",
    "addr:postcode":"80403",
    "addr:street":"W 54Th Ave",
    "iso:country":"US",
    "sg:address":"16400 W 54th Ave",
    "sg:city":"Golden",
    "sg:classifiers":[
        {
            "category":"Retail",
            "subcategory":"Animal Services",
            "type":"Services"
        }
    ],
    "sg:phone":"+1 303 279 6969",
    "sg:postcode":"80403",
    "sg:province":"CO",
    "sg:tags":[
        "pet",
        "grooming",
        "washing"
    ],
    "wof:name":"Sage Valley Pet Center",
    "wof:placetype":"venue"
},
  "geometry": {"coordinates":[-105.18678,39.794455],"type":"Point"}
}