{
  "type": "Feature",
  "properties": {
    "iso:country":"US",
    "sg:address":"1010 S Teller St",
    "sg:city":"Lakewood",
    "sg:classifiers":[
        {
            "category":"Professional",
            "subcategory":"Computer Services",
            "type":"Services"
        }
    ],
    "sg:phone":"+1 303 250 9003",
    "sg:postcode":"80226",
    "sg:province":"CO",
    "sg:tags":[
        "design",
        "system",
        "network"
    ],
    "wof:name":"Blue Ice Crypto",
    "wof:placetype":"venue"
},
  "geometry": {"coordinates":[-105.077347,39.698057],"type":"Point"}
}