{
  "type": "Feature",
  "properties": {
    "addr:full":"80 Wildwood Ln Glenwood Springs CO 81601",
    "addr:housenumber":"80",
    "addr:postcode":"81601",
    "addr:street":"Wildwood Ln",
    "iso:country":"US",
    "sg:address":"80 Wildwood Ln",
    "sg:city":"Glenwood Springs",
    "sg:classifiers":[
        {
            "category":"Building & Trades",
            "subcategory":"Construction",
            "type":"Services"
        }
    ],
    "sg:phone":"+1 970 945 8434",
    "sg:postcode":"81601",
    "sg:province":"CO",
    "sg:tags":[
        "house"
    ],
    "wof:name":"Alpine Building Consultants",
    "wof:placetype":"venue"
},
  "geometry": {"coordinates":[-107.294606,39.560056],"type":"Point"}
}