{
  "type": "Feature",
  "properties": {
    "iso:country":"US",
    "sg:address":"7148 E County Line Rd",
    "sg:city":"Littleton",
    "sg:classifiers":[
        {
            "category":"Professional",
            "type":"Services"
        }
    ],
    "sg:phone":"+1 720 200 2091",
    "sg:postcode":"80126",
    "sg:province":"CO",
    "wof:name":"Scissory Ltd",
    "wof:placetype":"venue"
},
  "geometry": {"coordinates":[-104.90999100000001,39.566003],"type":"Point"}
}