{
  "type": "Feature",
  "properties": {
    "addr:full":"3808 Running Deer Dr Castle Rock CO 80109",
    "addr:housenumber":"3808",
    "addr:postcode":"80109",
    "addr:street":"Running Deer Dr",
    "iso:country":"US",
    "sg:address":"3808 Running Deer Dr",
    "sg:city":"Castle Rock",
    "sg:classifiers":[
        {
            "category":"Wholesale",
            "subcategory":"Vending Machines",
            "type":"Manufacturing & Wholesale Goods"
        }
    ],
    "sg:phone":"+1 720 733 2088",
    "sg:postcode":"80109",
    "sg:province":"CO",
    "sg:tags":[
        "operator"
    ],
    "wof:name":"Cmt Vending Inc",
    "wof:placetype":"venue"
},
  "geometry": {"coordinates":[-104.918561,39.400801],"type":"Point"}
}