{
  "type": "Feature",
  "properties": {
    "addr:full":"14500 W Colfax Ave Lakewood CO 80401",
    "addr:housenumber":"14500",
    "addr:postcode":"80401",
    "addr:street":"W Colfax Ave",
    "iso:country":"US",
    "sg:address":"14500 W Colfax Ave",
    "sg:city":"Lakewood",
    "sg:classifiers":[
        {
            "category":"Professional",
            "type":"Services"
        }
    ],
    "sg:phone":"+1 303 590 1856",
    "sg:postcode":"80401",
    "sg:province":"CO",
    "sg:tags":[
        "establishment"
    ],
    "wof:name":"Molehill Mountain Equipment",
    "wof:placetype":"venue"
},
  "geometry": {"coordinates":[-105.165448,39.732095],"type":"Point"}
}