{
  "type": "Feature",
  "properties": {
    "addr:full":"38561 Co Rd 43 Eaton CO 80615",
    "addr:housenumber":"38561;43",
    "addr:postcode":"80615",
    "addr:street":"Co Rd;Eaton",
    "iso:country":"US",
    "sg:address":"38561 Co Rd 43",
    "sg:city":"Eaton",
    "sg:classifiers":[
        {
            "category":"Government",
            "subcategory":"Office",
            "type":"Public Place"
        }
    ],
    "sg:phone":"+1 970 834 1166",
    "sg:postcode":"80615",
    "sg:province":"CO",
    "sg:tags":[
        "development"
    ],
    "wof:name":"P L Helms Inc",
    "wof:placetype":"venue"
},
  "geometry": {"coordinates":[-104.65892599999999,40.561208],"type":"Point"}
}