{
  "type": "Feature",
  "properties": {
    "addr:full":"492 Mancos St Carbondale CO 81623",
    "addr:housenumber":"492",
    "addr:postcode":"81623",
    "addr:street":"Mancos St",
    "iso:country":"US",
    "sg:address":"492 Mancos St",
    "sg:city":"Carbondale",
    "sg:classifiers":[
        {
            "category":"Shopping",
            "subcategory":"Florist",
            "type":"Retail Goods"
        }
    ],
    "sg:phone":"+1 970 963 3155",
    "sg:postcode":"81623",
    "sg:province":"CO",
    "wof:name":"Heavenly Scent Inc",
    "wof:placetype":"venue"
},
  "geometry": {"coordinates":[-107.213634,39.406296],"type":"Point"}
}