{
  "type": "Feature",
  "properties": {
    "iso:country":"US",
    "sg:address":"2810 Meadowlark Ave",
    "sg:city":"Fort Collins",
    "sg:classifiers":[
        {
            "category":"Organizations",
            "subcategory":"Religious Organization",
            "type":"Services"
        }
    ],
    "sg:phone":"+1 970 223 7788",
    "sg:postcode":"80526",
    "sg:province":"CO",
    "sg:tags":[
        "church"
    ],
    "sg:website":"www.meadowlarkchurch.org",
    "wof:name":"Meadowlark Church Of Christ",
    "wof:placetype":"venue"
},
  "geometry": {"coordinates":[-105.085803,40.548032],"type":"Point"}
}