{
  "type": "Feature",
  "properties": {
    "addr:full":"333 S 22nd Avenue Ct Brighton CO 80601",
    "addr:housenumber":"333",
    "addr:postcode":"80601",
    "addr:street":"S 22Nd Avenue Ct",
    "iso:country":"US",
    "sg:address":"333 S 22nd Avenue Ct",
    "sg:city":"Brighton",
    "sg:classifiers":[
        {
            "category":"Professional",
            "type":"Services"
        }
    ],
    "sg:phone":"+1 303 659 4445",
    "sg:postcode":"80601",
    "sg:province":"CO",
    "wof:name":"Lanyo LLC",
    "wof:placetype":"venue"
},
  "geometry": {"coordinates":[-104.79454200000001,39.979905],"type":"Point"}
}