{
  "type": "Feature",
  "properties": {
    "addr:full":"4575 US Hwy 285 Center CO 81125",
    "addr:housenumber":"4575",
    "addr:postcode":"81125",
    "addr:street":"Us Hwy 285 Center",
    "iso:country":"US",
    "sg:address":"4575 US Hwy 285",
    "sg:city":"Center",
    "sg:classifiers":[
        {
            "category":"Wholesale",
            "subcategory":"Farm Supplies",
            "type":"Manufacturing & Wholesale Goods"
        }
    ],
    "sg:phone":"+1 719 754 3300",
    "sg:postcode":"81125",
    "sg:province":"CO",
    "sg:tags":[
        "alfalfa",
        "hay"
    ],
    "wof:name":"Hi-Valley Hay",
    "wof:placetype":"venue"
},
  "geometry": {"coordinates":[-106.148089,37.806161],"type":"Point"}
}