{
  "type": "Feature",
  "properties": {
    "iso:country":"US",
    "sg:address":"9921 US Hwy 34",
    "sg:city":"Grand Lake",
    "sg:classifiers":[
        {
            "category":"Manufacturing",
            "subcategory":"Aerospace",
            "type":"Manufacturing & Wholesale Goods"
        }
    ],
    "sg:phone":"+1 970 627 3955",
    "sg:postcode":"80447",
    "sg:province":"CO",
    "sg:tags":[
        "aircraft"
    ],
    "wof:name":"Roberts Aircraft Co",
    "wof:placetype":"venue"
},
  "geometry": {"coordinates":[-105.879104,40.192977],"type":"Point"}
}