{
  "type": "Feature",
  "properties": {
    "iso:country":"US",
    "sg:address":"1875 Lawrence Street",
    "sg:city":"Denver",
    "sg:classifiers":[
        {
            "category":"Organizations",
            "subcategory":"Non-profit Organization",
            "type":"Services"
        }
    ],
    "sg:phone":"+1 303 634 4302",
    "sg:postcode":"80202",
    "sg:province":"CO",
    "sg:tags":[
        "service/non-profit",
        "community"
    ],
    "wof:name":"Colorado Leadership Alliance",
    "wof:placetype":"venue"
},
  "geometry": {"coordinates":[-104.993332,39.751086],"type":"Point"}
}