{
  "type": "Feature",
  "properties": {
    "iso:country":"US",
    "sg:address":"353 D Ave",
    "sg:city":"Limon",
    "sg:classifiers":[
        {
            "category":"Social Services",
            "subcategory":"Child Care",
            "type":"Services"
        }
    ],
    "sg:phone":"+1 719 775 9555",
    "sg:postcode":"80828",
    "sg:province":"CO",
    "wof:name":"Limon Child Care Development",
    "wof:placetype":"venue"
},
  "geometry": {"coordinates":[-103.686622,39.263876],"type":"Point"}
}