{
  "type": "Feature",
  "properties": {
    "addr:full":"528 Park Cir Basalt CO 81621",
    "addr:housenumber":"528",
    "addr:postcode":"81621",
    "addr:street":"Park Cir",
    "iso:country":"US",
    "sg:address":"528 Park Cir",
    "sg:city":"Basalt",
    "sg:classifiers":[
        {
            "category":"Building & Trades",
            "subcategory":"Construction",
            "type":"Services"
        }
    ],
    "sg:phone":"+1 970 927 4515",
    "sg:postcode":"81621",
    "sg:province":"CO",
    "sg:tags":[
        "installment",
        "cabinet"
    ],
    "wof:name":"Wooldridge Co",
    "wof:placetype":"venue"
},
  "geometry": {"coordinates":[-107.02636800000001,39.367172],"type":"Point"}
}