{
  "type": "Feature",
  "properties": {
    "iso:country":"US",
    "sg:address":"164 Gordon Creek Rd",
    "sg:city":"Boulder",
    "sg:classifiers":[
        {
            "category":"Personal",
            "subcategory":"Beauty Salon",
            "type":"Services"
        }
    ],
    "sg:phone":"+1 303 417 9503",
    "sg:postcode":"80302",
    "sg:province":"CO",
    "sg:tags":[
        "treatment",
        "skin"
    ],
    "wof:name":"Face Of The Goddess",
    "wof:placetype":"venue"
},
  "geometry": {"coordinates":[-105.478838,40.003453],"type":"Point"}
}