{
  "type": "Feature",
  "properties": {
    "addr:full":"10351 W 44th Ave Wheat Ridge CO 80033",
    "addr:housenumber":"10351",
    "addr:postcode":"80033",
    "addr:street":"W 44Th Ave",
    "iso:country":"US",
    "sg:address":"10351 W 44th Ave",
    "sg:city":"Wheat Ridge",
    "sg:classifiers":[
        {
            "category":"Food & Beverages",
            "subcategory":"Fruits & Vegetables",
            "type":"Retail Goods"
        }
    ],
    "sg:phone":"+1 303 422 0346",
    "sg:postcode":"80033",
    "sg:province":"CO",
    "sg:tags":[
        "produce"
    ],
    "wof:name":"Garramone Produce",
    "wof:placetype":"venue"
},
  "geometry": {"coordinates":[-105.112993,39.778227],"type":"Point"}
}