{
  "type": "Feature",
  "properties": {
    "iso:country":"US",
    "sg:address":"6617 W Colfax Ave",
    "sg:city":"Lakewood",
    "sg:classifiers":[
        {
            "category":"Shopping",
            "subcategory":"Department Store",
            "type":"Retail Goods"
        }
    ],
    "sg:phone":"+1 303 237 4815",
    "sg:postcode":"80214",
    "sg:province":"CO",
    "sg:tags":[
        "shop",
        "discount"
    ],
    "sg:website":"www.dollartree.com",
    "wof:name":"Dollar Tree",
    "wof:placetype":"venue"
},
  "geometry": {"coordinates":[-105.069855,39.7404],"type":"Point"}
}