{
  "type": "Feature",
  "properties": {
    "iso:country":"US",
    "sg:address":"800 E Cottonwood Ave",
    "sg:city":"Littleton",
    "sg:classifiers":[
        {
            "category":"Manufacturing",
            "subcategory":"Printing",
            "type":"Manufacturing & Wholesale Goods"
        }
    ],
    "sg:phone":"+1 303 794 5710",
    "sg:postcode":"80121",
    "sg:province":"CO",
    "sg:tags":[
        "commercial"
    ],
    "wof:name":"Basic Bling Bling LLC",
    "wof:placetype":"venue"
},
  "geometry": {"coordinates":[-104.97541699999999,39.603376],"type":"Point"}
}