{
  "type": "Feature",
  "properties": {
    "iso:country":"US",
    "sg:address":"2231 S Broadway",
    "sg:city":"Denver",
    "sg:classifiers":[
        {
            "category":"Restaurant",
            "type":"Food & Drink"
        }
    ],
    "sg:phone":"+1 303 733 4511",
    "sg:postcode":"80210",
    "sg:province":"CO",
    "sg:tags":[
        "pizza"
    ],
    "sg:website":"www.rebellionpizza.com",
    "wof:name":"The Rebellion",
    "wof:placetype":"venue"
},
  "geometry": {"coordinates":[-104.98796900000001,39.67621],"type":"Point"}
}