{
  "type": "Feature",
  "properties": {
    "addr:full":"4945 N Hwy 67 Sedalia CO 80135",
    "addr:housenumber":"4945",
    "addr:postcode":"80135",
    "addr:street":"N Hwy 67",
    "iso:country":"US",
    "sg:address":"4945 N Hwy 67",
    "sg:city":"Sedalia",
    "sg:classifiers":[
        {
            "category":"Professional",
            "subcategory":"Business Services",
            "type":"Services"
        }
    ],
    "sg:phone":"+1 303 688 4752",
    "sg:postcode":"80135",
    "sg:province":"CO",
    "sg:tags":[
        "water",
        "treatment"
    ],
    "wof:name":"Watersearch",
    "wof:placetype":"venue"
},
  "geometry": {"coordinates":[-104.978016,39.424293],"type":"Point"}
}