{
  "type": "Feature",
  "properties": {
    "addr:full":"11135 Ralston Rd Arvada CO 80004",
    "addr:housenumber":"11135",
    "addr:postcode":"80004",
    "addr:street":"Ralston Rd",
    "iso:country":"US",
    "sg:address":"11135 Ralston Rd",
    "sg:city":"Arvada",
    "sg:classifiers":[
        {
            "category":"Real Estate",
            "subcategory":"Real Estate Operator",
            "type":"Services"
        }
    ],
    "sg:phone":"+1 303 431 2243",
    "sg:postcode":"80004",
    "sg:province":"CO",
    "sg:tags":[
        "building",
        "apartment"
    ],
    "wof:name":"Quail Ridge Apartments",
    "wof:placetype":"venue"
},
  "geometry": {"coordinates":[-105.121523,39.812811],"type":"Point"}
}