{
  "type": "Feature",
  "properties": {
    "addr:full":"617 10th St Golden CO 80401",
    "addr:housenumber":"617",
    "addr:postcode":"80401",
    "addr:street":"10Th St",
    "iso:country":"US",
    "sg:address":"617 10th St",
    "sg:city":"Golden",
    "sg:classifiers":[
        {
            "category":"Food & Beverages",
            "subcategory":"Specialty",
            "type":"Retail Goods"
        }
    ],
    "sg:phone":"+1 303 273 2945",
    "sg:postcode":"80401",
    "sg:province":"CO",
    "wof:name":"Healthfirst LLC",
    "wof:placetype":"venue"
},
  "geometry": {"coordinates":[-105.22207,39.758161],"type":"Point"}
}