{
  "type": "Feature",
  "properties": {
    "addr:full":"795 S Harlan St Lakewood CO 80226",
    "addr:housenumber":"795",
    "addr:postcode":"80226",
    "addr:street":"S Harlan St",
    "iso:country":"US",
    "sg:address":"795 S Harlan St",
    "sg:city":"Lakewood",
    "sg:classifiers":[
        {
            "category":"Building & Trades",
            "subcategory":"Cleaning & Sanitation",
            "type":"Services"
        }
    ],
    "sg:phone":"+1 303 922 5422",
    "sg:postcode":"80226",
    "sg:province":"CO",
    "sg:tags":[
        "repairing",
        "window",
        "shades"
    ],
    "wof:name":"Ultra Clean Blinds & More",
    "wof:placetype":"venue"
},
  "geometry": {"coordinates":[-105.062758,39.70317],"type":"Point"}
}