{
  "type": "Feature",
  "properties": {
    "addr:full":"1301 S 8th St Colorado Springs CO 80906",
    "addr:housenumber":"1301",
    "addr:postcode":"80906",
    "addr:street":"S 8Th St",
    "iso:country":"US",
    "sg:address":"1301 S 8th St",
    "sg:city":"Colorado Springs",
    "sg:classifiers":[
        {
            "category":"Personal",
            "type":"Services"
        }
    ],
    "sg:phone":"+1 719 634 0745",
    "sg:postcode":"80906",
    "sg:province":"CO",
    "sg:tags":[
        "therapist",
        "massage"
    ],
    "wof:name":"Life Force",
    "wof:placetype":"venue"
},
  "geometry": {"coordinates":[-104.842232,38.81845],"type":"Point"}
}