{
  "type": "Feature",
  "properties": {
    "addr:full":"2017 Brookwood Dr Colorado Springs CO 80918",
    "addr:housenumber":"2017",
    "addr:postcode":"80918",
    "addr:street":"Brookwood Dr",
    "iso:country":"US",
    "sg:address":"2017 Brookwood Dr",
    "sg:city":"Colorado Springs",
    "sg:classifiers":[
        {
            "category":"Professional",
            "type":"Services"
        }
    ],
    "sg:phone":"+1 719 471 4909",
    "sg:postcode":"80918",
    "sg:province":"CO",
    "wof:name":"Gwen Fox Studio",
    "wof:placetype":"venue"
},
  "geometry": {"coordinates":[-104.78778,38.93006],"type":"Point"}
}