{
  "type": "Feature",
  "properties": {
    "iso:country":"US",
    "sg:address":"9855 E Colfax Ave",
    "sg:city":"Aurora",
    "sg:classifiers":[
        {
            "category":"Home & Garden",
            "subcategory":"Building Materials",
            "type":"Retail Goods"
        }
    ],
    "sg:phone":"+1 303 361 6242",
    "sg:postcode":"80010",
    "sg:province":"CO",
    "sg:tags":[
        "floor",
        "covering"
    ],
    "wof:name":"Sherwin-Williams",
    "wof:placetype":"venue"
},
  "geometry": {"coordinates":[-104.873386,39.740287],"type":"Point"}
}