{
  "type": "Feature",
  "properties": {
    "iso:country":"US",
    "sg:address":"1015 15th St",
    "sg:city":"Boulder",
    "sg:classifiers":[
        {
            "category":"Organizations",
            "subcategory":"Community Association",
            "type":"Services"
        }
    ],
    "sg:phone":"+1 303 443 0546",
    "sg:postcode":"80302",
    "sg:province":"CO",
    "sg:tags":[
        "sorority"
    ],
    "wof:name":"Alpha Omicron Pi",
    "wof:placetype":"venue"
},
  "geometry": {"coordinates":[-105.273768,40.006473],"type":"Point"}
}