{
  "type": "Feature",
  "properties": {
    "iso:country":"US",
    "sg:address":"430 Bimson Ave",
    "sg:city":"Berthoud",
    "sg:classifiers":[
        {
            "category":"Health Services",
            "subcategory":"Doctor",
            "type":"Services"
        }
    ],
    "sg:phone":"+1 970 532 4209",
    "sg:postcode":"80513",
    "sg:province":"CO",
    "sg:tags":[
        "dentist"
    ],
    "wof:name":"Berthoud Dental Care",
    "wof:placetype":"venue"
},
  "geometry": {"coordinates":[-105.0808,40.303174],"type":"Point"}
}