{
  "type": "Feature",
  "properties": {
    "addr:full":"328 Remington St Fort Collins CO 80524",
    "addr:housenumber":"328",
    "addr:postcode":"80524",
    "addr:street":"Remington St",
    "iso:country":"US",
    "sg:address":"328 Remington St",
    "sg:city":"Fort Collins",
    "sg:classifiers":[
        {
            "category":"Organizations",
            "subcategory":"Religious Organization",
            "type":"Services"
        }
    ],
    "sg:phone":"+1 970 482 5688",
    "sg:postcode":"80524",
    "sg:province":"CO",
    "sg:tags":[
        "church"
    ],
    "sg:website":"www.north-pointe.org",
    "wof:name":"North Pointe Community Church",
    "wof:placetype":"venue"
},
  "geometry": {"coordinates":[-105.075478,40.583231],"type":"Point"}
}