{
  "type": "Feature",
  "properties": {
    "iso:country":"US",
    "sg:address":"2741 Mapleton Ave",
    "sg:city":"Boulder",
    "sg:classifiers":[
        {
            "category":"Professional",
            "subcategory":"Employment Agencies",
            "type":"Services"
        }
    ],
    "sg:phone":"+1 303 443 1700",
    "sg:postcode":"80304",
    "sg:province":"CO",
    "sg:tags":[
        "help",
        "contractor"
    ],
    "sg:website":"www.staffingsolutions.com",
    "wof:name":"Staffing Solutions",
    "wof:placetype":"venue"
},
  "geometry": {"coordinates":[-105.258897,40.025515],"type":"Point"}
}