{
  "type": "Feature",
  "properties": {
    "iso:country":"US",
    "sg:address":"365 Warren Ave",
    "sg:city":"Silverthorne",
    "sg:classifiers":[
        {
            "category":"Building & Trades",
            "subcategory":"Construction",
            "type":"Services"
        }
    ],
    "sg:phone":"+1 970 468 0454",
    "sg:postcode":"80498",
    "sg:province":"CO",
    "sg:tags":[
        "general",
        "contractor"
    ],
    "wof:name":"Travis Construction",
    "wof:placetype":"venue"
},
  "geometry": {"coordinates":[-106.077933,39.629047],"type":"Point"}
}