{
  "type": "Feature",
  "properties": {
    "addr:full":"330 Riverside Dr Basalt CO 81621",
    "addr:housenumber":"330",
    "addr:postcode":"81621",
    "addr:street":"Riverside Dr",
    "iso:country":"US",
    "sg:address":"330 Riverside Dr",
    "sg:city":"Basalt",
    "sg:classifiers":[
        {
            "category":"Banks & Credit Unions",
            "subcategory":"Financial Services",
            "type":"Services"
        }
    ],
    "sg:phone":"+1 970 927 3199",
    "sg:postcode":"81621",
    "sg:province":"CO",
    "sg:tags":[
        "investor"
    ],
    "wof:name":"Eagle Capital Funding LLC",
    "wof:placetype":"venue"
},
  "geometry": {"coordinates":[-107.028344,39.369315],"type":"Point"}
}