{
  "type": "Feature",
  "properties": {
    "addr:full":"7277 Poudre Canyon Hwy Bellvue CO 80512",
    "addr:housenumber":"7277",
    "addr:postcode":"80512",
    "addr:street":"Poudre Canyon Hwy",
    "iso:country":"US",
    "sg:address":"7277 Poudre Canyon Hwy",
    "sg:city":"Bellvue",
    "sg:classifiers":[
        {
            "category":"Building & Trades",
            "subcategory":"Construction",
            "type":"Services"
        }
    ],
    "sg:phone":"+1 970 224 4887",
    "sg:postcode":"80512",
    "sg:province":"CO",
    "sg:tags":[
        "house",
        "general",
        "contractor"
    ],
    "wof:name":"Grey Rock Builders Inc",
    "wof:placetype":"venue"
},
  "geometry": {"coordinates":[-105.26772200000001,40.696492],"type":"Point"}
}