{
  "type": "Feature",
  "properties": {
    "addr:full":"3141 S College Ave Fort Collins CO 80525",
    "addr:housenumber":"3141",
    "addr:postcode":"80525",
    "addr:street":"S College Ave",
    "iso:country":"US",
    "sg:address":"3141 S College Ave",
    "sg:city":"Fort Collins",
    "sg:classifiers":[
        {
            "category":"Retail",
            "subcategory":"Car Wash",
            "type":"Services"
        }
    ],
    "sg:phone":"+1 970 223 4221",
    "sg:postcode":"80525",
    "sg:province":"CO",
    "sg:tags":[
        "polishing",
        "washing"
    ],
    "wof:name":"Richie's Fort Collins Express",
    "wof:placetype":"venue"
},
  "geometry": {"coordinates":[-105.07716499999999,40.542651],"type":"Point"}
}