{
  "type": "Feature",
  "properties": {
    "iso:country":"US",
    "sg:address":"1453 Larimer St",
    "sg:city":"Denver",
    "sg:classifiers":[
        {
            "category":"Restaurant",
            "type":"Food & Drink"
        }
    ],
    "sg:phone":"+1 303 825 4747",
    "sg:postcode":"80202",
    "sg:province":"CO",
    "sg:tags":[
        "eating"
    ],
    "sg:website":"www.delmardenver.com",
    "wof:name":"Del Mar Crab House",
    "wof:placetype":"venue"
},
  "geometry": {"coordinates":[-104.99900100000001,39.748001],"type":"Point"}
}