{
  "type": "Feature",
  "properties": {
    "addr:full":"202 Lone Pine Rd Aspen CO 81611",
    "addr:housenumber":"202",
    "addr:postcode":"81611",
    "addr:street":"Lone Pine Rd",
    "iso:country":"US",
    "sg:address":"202 Lone Pine Rd",
    "sg:city":"Aspen",
    "sg:classifiers":[
        {
            "category":"Building & Trades",
            "subcategory":"Construction",
            "type":"Services"
        }
    ],
    "sg:phone":"+1 970 925 6564",
    "sg:postcode":"81611",
    "sg:province":"CO",
    "sg:tags":[
        "general",
        "contractor"
    ],
    "wof:name":"Paul Rasmussen Construction Co",
    "wof:placetype":"venue"
},
  "geometry": {"coordinates":[-106.814453,39.19441],"type":"Point"}
}