{
  "type": "Feature",
  "properties": {
    "addr:full":"15684 N Co Rd 7 Wellington CO 80549",
    "addr:housenumber":"15684",
    "addr:postcode":"80549",
    "addr:street":"N Co Rd 7",
    "iso:country":"US",
    "sg:address":"15684 N Co Rd 7",
    "sg:city":"Wellington",
    "sg:classifiers":[
        {
            "category":"Farming",
            "subcategory":"Nursery",
            "type":"Manufacturing & Wholesale Goods"
        }
    ],
    "sg:phone":"+1 970 635 0692",
    "sg:postcode":"80549",
    "sg:province":"CO",
    "sg:tags":[
        "ornamental"
    ],
    "wof:name":"Deschner Earth Movers LLC",
    "wof:placetype":"venue"
},
  "geometry": {"coordinates":[-105.000618,40.811924],"type":"Point"}
}