{
  "type": "Feature",
  "properties": {
    "iso:country":"US",
    "sg:address":"1000 W 104th Ave",
    "sg:city":"Denver",
    "sg:classifiers":[
        {
            "category":"Food & Beverages",
            "subcategory":"Groceries & Convenience Stores",
            "type":"Retail Goods"
        }
    ],
    "sg:phone":"+1 303 457 0650",
    "sg:postcode":"80234",
    "sg:province":"CO",
    "sg:tags":[
        "supermarket",
        "chain"
    ],
    "wof:name":"Albertsons 854",
    "wof:placetype":"venue"
},
  "geometry": {"coordinates":[-104.999424,39.885007],"type":"Point"}
}