{
  "type": "Feature",
  "properties": {
    "addr:full":"725 Manitou Ave Manitou Springs CO 80829",
    "addr:housenumber":"725",
    "addr:postcode":"80829",
    "addr:street":"Manitou Ave",
    "iso:country":"US",
    "sg:address":"725 Manitou Ave",
    "sg:city":"Manitou Springs",
    "sg:classifiers":[
        {
            "category":"Shopping",
            "subcategory":"Used Merchandise",
            "type":"Retail Goods"
        }
    ],
    "sg:phone":"+1 719 685 5779",
    "sg:postcode":"80829",
    "sg:province":"CO",
    "sg:tags":[
        "antique"
    ],
    "wof:name":"Legrande Accents",
    "wof:placetype":"venue"
},
  "geometry": {"coordinates":[-104.915001,38.856998],"type":"Point"}
}