{
  "type": "Feature",
  "properties": {
    "iso:country":"US",
    "sg:address":"2100 W 100th Ave",
    "sg:city":"Denver",
    "sg:classifiers":[
        {
            "category":"Food & Beverages",
            "subcategory":"Candy",
            "type":"Retail Goods"
        }
    ],
    "sg:phone":"+1 303 438 7295",
    "sg:postcode":"80260",
    "sg:province":"CO",
    "wof:name":"Gregg Winn",
    "wof:placetype":"venue"
},
  "geometry": {"coordinates":[-105.014942,39.878054],"type":"Point"}
}