{
  "type": "Feature",
  "properties": {
    "addr:full":"595 Maxwell Dr Grand Junction CO 81504",
    "addr:housenumber":"595",
    "addr:postcode":"81504",
    "addr:street":"Maxwell Dr",
    "iso:country":"US",
    "sg:address":"595 Maxwell Dr",
    "sg:city":"Grand Junction",
    "sg:classifiers":[
        {
            "category":"Professional",
            "type":"Services"
        }
    ],
    "sg:phone":"+1 970 523 7852",
    "sg:postcode":"81504",
    "sg:province":"CO",
    "sg:tags":[
        "art",
        "restoring"
    ],
    "wof:name":"Hensley & Hensley Fine Art",
    "wof:placetype":"venue"
},
  "geometry": {"coordinates":[-108.468146,39.08585],"type":"Point"}
}