{
  "type": "Feature",
  "properties": {
    "iso:country":"US",
    "sg:address":"321 Elk Ave",
    "sg:city":"Crested Butte",
    "sg:classifiers":[
        {
            "category":"Restaurant",
            "type":"Food & Drink"
        }
    ],
    "sg:phone":"+1 970 349 5457",
    "sg:postcode":"81224",
    "sg:province":"CO",
    "wof:name":"Lil's Land & Sea",
    "wof:placetype":"venue"
},
  "geometry": {"coordinates":[-106.984499,38.869841],"type":"Point"}
}