{
  "type": "Feature",
  "properties": {
    "addr:full":"1618 Robin Rd Sterling CO 80751",
    "addr:housenumber":"1618",
    "addr:postcode":"80751",
    "addr:street":"Robin Rd",
    "iso:country":"US",
    "sg:address":"1618 Robin Rd",
    "sg:city":"Sterling",
    "sg:classifiers":[
        {
            "category":"Building & Trades",
            "subcategory":"Landscaping Services",
            "type":"Services"
        }
    ],
    "sg:phone":"+1 970 521 9668",
    "sg:postcode":"80751",
    "sg:province":"CO",
    "sg:tags":[
        "lawn",
        "maintenance",
        "grounds"
    ],
    "wof:name":"Logan County K Lawn",
    "wof:placetype":"venue"
},
  "geometry": {"coordinates":[-103.22244499999999,40.609006],"type":"Point"}
}