{
  "type": "Feature",
  "properties": {
    "iso:country":"US",
    "sg:address":"721 Stratton Dr",
    "sg:city":"Cortez",
    "sg:classifiers":[
        {
            "category":"Building & Trades",
            "subcategory":"Construction",
            "type":"Services"
        }
    ],
    "sg:phone":"+1 970 565 2332",
    "sg:postcode":"81321",
    "sg:province":"CO",
    "sg:tags":[
        "hanging",
        "contractor"
    ],
    "wof:name":"Kevin Scott T N T Prof Paintng",
    "wof:placetype":"venue"
},
  "geometry": {"coordinates":[-108.597385,37.343335],"type":"Point"}
}