{
  "type": "Feature",
  "properties": {
    "addr:full":"5929 Constitution Ave Colorado Springs CO 80915",
    "addr:housenumber":"5929",
    "addr:postcode":"80915",
    "addr:street":"Constitution Ave",
    "iso:country":"US",
    "sg:address":"5929 Constitution Ave",
    "sg:city":"Colorado Springs",
    "sg:classifiers":[
        {
            "category":"Health Services",
            "subcategory":"Doctor",
            "type":"Services"
        }
    ],
    "sg:phone":"+1 719 638 1986",
    "sg:postcode":"80915",
    "sg:province":"CO",
    "wof:name":"Perfect Teeth Powers PC",
    "wof:placetype":"venue"
},
  "geometry": {"coordinates":[-104.716274,38.87127],"type":"Point"}
}