{
  "type": "Feature",
  "properties": {
    "iso:country":"US",
    "sg:address":"709 W Littleton Blvd # 10",
    "sg:city":"Littleton",
    "sg:classifiers":[
        {
            "category":"Personal",
            "subcategory":"Massage",
            "type":"Services"
        }
    ],
    "sg:phone":"+1 303 730 3868",
    "sg:postcode":"80120",
    "sg:province":"CO",
    "wof:name":"Body Tensegrity Clinic",
    "wof:placetype":"venue"
},
  "geometry": {"coordinates":[-104.996349,39.613289],"type":"Point"}
}