{
  "type": "Feature",
  "properties": {
    "iso:country":"US",
    "sg:address":"1425 Meeker Dr",
    "sg:city":"Fort Collins",
    "sg:classifiers":[
        {
            "category":"Manufacturing",
            "subcategory":"Building Materials",
            "type":"Manufacturing & Wholesale Goods"
        }
    ],
    "sg:phone":"+1 970 416 0240",
    "sg:postcode":"80524",
    "sg:province":"CO",
    "sg:tags":[
        "mfg"
    ],
    "wof:name":"Erickson Woodworks Inc",
    "wof:placetype":"venue"
},
  "geometry": {"coordinates":[-105.050487,40.568455],"type":"Point"}
}