{
  "type": "Feature",
  "properties": {
    "addr:full":"4886 Hopkins Pl Boulder CO 80301",
    "addr:housenumber":"4886",
    "addr:postcode":"80301",
    "addr:street":"Hopkins Pl",
    "iso:country":"US",
    "sg:address":"4886 Hopkins Pl",
    "sg:city":"Boulder",
    "sg:classifiers":[
        {
            "category":"Building & Trades",
            "subcategory":"Electrical",
            "type":"Services"
        }
    ],
    "sg:phone":"+1 303 444 5156",
    "sg:postcode":"80301",
    "sg:province":"CO",
    "sg:tags":[
        "electrical",
        "contractor"
    ],
    "wof:name":"Tampa Electric Company",
    "wof:placetype":"venue"
},
  "geometry": {"coordinates":[-105.24009700000001,40.035095],"type":"Point"}
}