{
  "type": "Feature",
  "properties": {
    "iso:country":"US",
    "sg:address":"9224 Teddy Ln",
    "sg:city":"Lone Tree",
    "sg:classifiers":[
        {
            "category":"Health Services",
            "subcategory":"Doctor",
            "type":"Services"
        }
    ],
    "sg:phone":"+1 303 869 2121",
    "sg:postcode":"80124",
    "sg:province":"CO",
    "sg:tags":[
        "physician",
        "surgeon"
    ],
    "sg:website":"www.rmpgi.com",
    "wof:name":"Rocky Mtn Pediatric Gstrntrlgy",
    "wof:placetype":"venue"
},
  "geometry": {"coordinates":[-104.880695,39.55169],"type":"Point"}
}