{
  "type": "Feature",
  "properties": {
    "addr:full":"553 14th St Burlington CO 80807",
    "addr:housenumber":"553",
    "addr:postcode":"80807",
    "addr:street":"14Th St",
    "iso:country":"US",
    "sg:address":"553 14th St",
    "sg:city":"Burlington",
    "sg:classifiers":[
        {
            "category":"Shopping",
            "subcategory":"Shoes",
            "type":"Retail Goods"
        }
    ],
    "sg:phone":"+1 719 346 8204",
    "sg:postcode":"80807",
    "sg:province":"CO",
    "wof:name":"Burlington Locker & Slaughter",
    "wof:placetype":"venue"
},
  "geometry": {"coordinates":[-102.268091,39.306338],"type":"Point"}
}