{
  "type": "Feature",
  "properties": {
    "addr:full":"1650 38th St Boulder CO 80301",
    "addr:housenumber":"1650",
    "addr:postcode":"80301",
    "addr:street":"38Th St",
    "iso:country":"US",
    "sg:address":"1650 38th St",
    "sg:city":"Boulder",
    "sg:classifiers":[
        {
            "category":"Professional",
            "subcategory":"Accounting & Tax Preparation",
            "type":"Services"
        }
    ],
    "sg:phone":"+1 303 440 4711",
    "sg:postcode":"80301",
    "sg:province":"CO",
    "sg:tags":[
        "accountant"
    ],
    "wof:name":"Hayward & Assoc",
    "wof:placetype":"venue"
},
  "geometry": {"coordinates":[-105.245195,40.01779],"type":"Point"}
}