{
  "type": "Feature",
  "properties": {
    "addr:full":"417 South Broadway Denver CO 80209",
    "addr:housenumber":"417",
    "addr:postcode":"80209",
    "addr:street":"South Broadway",
    "iso:country":"US",
    "sg:address":"417 South Broadway",
    "sg:city":"Denver",
    "sg:classifiers":[
        {
            "category":"Home & Garden",
            "subcategory":"Hardware",
            "type":"Retail Goods"
        }
    ],
    "sg:phone":"+1 303 733 3200",
    "sg:postcode":"80209",
    "sg:province":"CO",
    "sg:tags":[
        "store"
    ],
    "sg:website":"www.acealamedastation.com/",
    "wof:name":"Ace Hardware Alameda Station",
    "wof:placetype":"venue"
},
  "geometry": {"coordinates":[-104.987604,39.709179],"type":"Point"}
}