{
  "type": "Feature",
  "properties": {
    "addr:full":"1342 E Ellicott Rd S Calhan CO 80808",
    "addr:housenumber":"1342",
    "addr:postcode":"80808",
    "addr:street":"E Ellicott Rd",
    "iso:country":"US",
    "sg:address":"1342 E Ellicott Rd S",
    "sg:city":"Calhan",
    "sg:classifiers":[
        {
            "category":"Freight",
            "type":"Transportation"
        }
    ],
    "sg:phone":"+1 719 683 4355",
    "sg:postcode":"80808",
    "sg:province":"CO",
    "wof:name":"Colorado Master Transporters",
    "wof:placetype":"venue"
},
  "geometry": {"coordinates":[-104.368972,38.810708],"type":"Point"}
}