{
  "type": "Feature",
  "properties": {
    "iso:country":"US",
    "sg:address":"724 Grand Ave",
    "sg:city":"Glenwood Springs",
    "sg:classifiers":[
        {
            "category":"Restaurant",
            "type":"Food & Drink"
        }
    ],
    "sg:phone":"+1 970 625 4056",
    "sg:postcode":"81601",
    "sg:province":"CO",
    "sg:tags":[
        "eating"
    ],
    "wof:name":"Doc Hollidays Saloon & Rest",
    "wof:placetype":"venue"
},
  "geometry": {"coordinates":[-107.32463,39.547379],"type":"Point"}
}