{
  "type": "Feature",
  "properties": {
    "addr:full":"775 Yampa Ave Craig CO 81625",
    "addr:housenumber":"775",
    "addr:postcode":"81625",
    "addr:street":"Yampa Ave",
    "iso:country":"US",
    "sg:address":"775 Yampa Ave",
    "sg:city":"Craig",
    "sg:classifiers":[
        {
            "category":"Education",
            "subcategory":"School",
            "type":"Public Place"
        }
    ],
    "sg:phone":"+1 970 374 2265",
    "sg:postcode":"81625",
    "sg:province":"CO",
    "wof:name":"Dinosaur Elementary",
    "wof:placetype":"venue"
},
  "geometry": {"coordinates":[-107.547248,40.521167],"type":"Point"}
}