{
  "type": "Feature",
  "properties": {
    "iso:country":"US",
    "sg:address":"1990 Victor Pl",
    "sg:city":"Colorado Springs",
    "sg:classifiers":[
        {
            "category":"Manufacturing",
            "subcategory":"Printing",
            "type":"Manufacturing & Wholesale Goods"
        }
    ],
    "sg:phone":"+1 719 591 0575",
    "sg:postcode":"80915",
    "sg:province":"CO",
    "sg:tags":[
        "commercial",
        "lithographic"
    ],
    "wof:name":"Printcolor",
    "wof:placetype":"venue"
},
  "geometry": {"coordinates":[-104.722506,38.862601],"type":"Point"}
}