{
  "type": "Feature",
  "properties": {
    "iso:country":"US",
    "sg:address":"1675 Larimer St",
    "sg:city":"Denver",
    "sg:classifiers":[
        {
            "category":"Retail",
            "subcategory":"Auto Repair",
            "type":"Services"
        }
    ],
    "sg:phone":"+1 303 927 0629",
    "sg:postcode":"80202",
    "sg:province":"CO",
    "sg:tags":[
        "windshield"
    ],
    "wof:name":"Imperial Auto Glass",
    "wof:placetype":"venue"
},
  "geometry": {"coordinates":[-104.996343,39.75001],"type":"Point"}
}