{
  "type": "Feature",
  "properties": {
    "addr:full":"2406 15th Avenue Ct Greeley CO 80631",
    "addr:housenumber":"2406",
    "addr:postcode":"80631",
    "addr:street":"15Th Avenue Ct",
    "iso:country":"US",
    "sg:address":"2406 15th Avenue Ct",
    "sg:city":"Greeley",
    "sg:classifiers":[
        {
            "category":"Organizations",
            "subcategory":"Membership Organization",
            "type":"Services"
        }
    ],
    "sg:phone":"+1 970 356 8509",
    "sg:postcode":"80631",
    "sg:province":"CO",
    "sg:tags":[
        "association"
    ],
    "wof:name":"Colorado Wild Horse Burrow",
    "wof:placetype":"venue"
},
  "geometry": {"coordinates":[-104.704195,40.397474],"type":"Point"}
}