{
  "type": "Feature",
  "properties": {
    "iso:country":"US",
    "sg:address":"2527 Howbert St",
    "sg:city":"Colorado Springs",
    "sg:classifiers":[
        {
            "category":"Wholesale",
            "subcategory":"Auto Parts",
            "type":"Manufacturing & Wholesale Goods"
        }
    ],
    "sg:phone":"+1 719 633 0483",
    "sg:postcode":"80904",
    "sg:province":"CO",
    "sg:tags":[
        "repair"
    ],
    "wof:name":"Car-Go Auto Equip Sls & Svc",
    "wof:placetype":"venue"
},
  "geometry": {"coordinates":[-104.86961599999999,38.841487],"type":"Point"}
}