{
  "type": "Feature",
  "properties": {
    "iso:country":"US",
    "sg:address":"66920 E Co Rd 10",
    "sg:city":"Byers",
    "sg:classifiers":[
        {
            "category":"Manufacturing",
            "subcategory":"Tools & Machinery",
            "type":"Manufacturing & Wholesale Goods"
        }
    ],
    "sg:phone":"+1 303 324 9626",
    "sg:postcode":"80103",
    "sg:province":"CO",
    "sg:tags":[
        "excavation",
        "mfg",
        "construction",
        "contractor"
    ],
    "wof:name":"Popejoy Backhoe",
    "wof:placetype":"venue"
},
  "geometry": {"coordinates":[-104.20466,39.711517],"type":"Point"}
}