{
  "type": "Feature",
  "properties": {
    "addr:full":"1963 S Federal Blvd Denver CO 80219",
    "addr:housenumber":"1963",
    "addr:postcode":"80219",
    "addr:street":"S Federal Blvd",
    "iso:country":"US",
    "sg:address":"1963 S Federal Blvd",
    "sg:city":"Denver",
    "sg:classifiers":[
        {
            "category":"Shopping",
            "subcategory":"Jewelry",
            "type":"Retail Goods"
        }
    ],
    "sg:phone":"+1 303 922 0553",
    "sg:postcode":"80219",
    "sg:province":"CO",
    "sg:tags":[
        "stone",
        "including",
        "precious",
        "store"
    ],
    "wof:name":"Fine Jewelers Corp",
    "wof:placetype":"venue"
},
  "geometry": {"coordinates":[-105.025109,39.681621],"type":"Point"}
}