{
  "type": "Feature",
  "properties": {
    "iso:country":"US",
    "sg:address":"6721 York St",
    "sg:city":"Denver",
    "sg:classifiers":[
        {
            "category":"Wholesale",
            "subcategory":"Groceries",
            "type":"Manufacturing & Wholesale Goods"
        }
    ],
    "sg:phone":"+1 303 289 8801",
    "sg:postcode":"80229",
    "sg:province":"CO",
    "sg:tags":[
        "food",
        "product",
        "pizza"
    ],
    "sg:website":"www.vistarvsa.com",
    "wof:name":"Vistar Vsa",
    "wof:placetype":"venue"
},
  "geometry": {"coordinates":[-104.959,39.818401],"type":"Point"}
}