{
  "type": "Feature",
  "properties": {
    "iso:country":"US",
    "sg:address":"5500 W 44th Ave",
    "sg:city":"Denver",
    "sg:classifiers":[
        {
            "category":"Government",
            "subcategory":"Post Office",
            "type":"Public Place"
        }
    ],
    "sg:phone":"+1 303 000 1111",
    "sg:postcode":"80212",
    "sg:province":"CO",
    "wof:name":"US Post Office",
    "wof:placetype":"venue"
},
  "geometry": {"coordinates":[-105.05787100000001,39.776603],"type":"Point"}
}