{
  "type": "Feature",
  "properties": {
    "iso:country":"US",
    "sg:address":"710 S Main St",
    "sg:city":"Brighton",
    "sg:classifiers":[
        {
            "category":"Shopping",
            "type":"Retail Goods"
        }
    ],
    "sg:phone":"+1 720 685 8600",
    "sg:postcode":"80601",
    "sg:province":"CO",
    "sg:tags":[
        "merchandise"
    ],
    "wof:name":"Cellular Junction Inc",
    "wof:placetype":"venue"
},
  "geometry": {"coordinates":[-104.826177,39.974229],"type":"Point"}
}