{
  "type": "Feature",
  "properties": {
    "iso:country":"US",
    "sg:address":"310 Elk Ave",
    "sg:city":"Crested Butte",
    "sg:classifiers":[
        {
            "category":"Shopping",
            "subcategory":"Clothing, Apparel, & Fashions",
            "type":"Retail Goods"
        }
    ],
    "sg:phone":"+1 970 349 2107",
    "sg:postcode":"81224",
    "sg:province":"CO",
    "wof:name":"Milky Way",
    "wof:placetype":"venue"
},
  "geometry": {"coordinates":[-106.984296,38.86969],"type":"Point"}
}