{
  "type": "Feature",
  "properties": {
    "iso:country":"US",
    "sg:address":"2675 Birch Ct",
    "sg:city":"Grand Junction",
    "sg:classifiers":[
        {
            "category":"Insurance",
            "subcategory":"Insurance Agent",
            "type":"Services"
        }
    ],
    "sg:phone":"+1 970 245 7600",
    "sg:postcode":"81506",
    "sg:province":"CO",
    "wof:name":"Western Slope Financial Svc",
    "wof:placetype":"venue"
},
  "geometry": {"coordinates":[-108.534933,39.102149],"type":"Point"}
}