{
  "type": "Feature",
  "properties": {
    "iso:country":"US",
    "sg:address":"6565 Gunpark Dr",
    "sg:city":"Boulder",
    "sg:classifiers":[
        {
            "category":"Shopping",
            "type":"Retail Goods"
        }
    ],
    "sg:phone":"+1 303 530 3118",
    "sg:postcode":"80301",
    "sg:province":"CO",
    "sg:tags":[
        "art",
        "dealer"
    ],
    "wof:name":"Silver Song Studio",
    "wof:placetype":"venue"
},
  "geometry": {"coordinates":[-105.198421,40.071159],"type":"Point"}
}