{
  "type": "Feature",
  "properties": {
    "addr:full":"1515 N Academy Blvd Colorado Springs CO 80909",
    "addr:housenumber":"1515",
    "addr:postcode":"80909",
    "addr:street":"N Academy Blvd",
    "iso:country":"US",
    "sg:address":"1515 N Academy Blvd",
    "sg:city":"Colorado Springs",
    "sg:classifiers":[
        {
            "category":"Real Estate",
            "subcategory":"Real Estate Operator",
            "type":"Services"
        }
    ],
    "sg:phone":"+1 719 573 8979",
    "sg:postcode":"80909",
    "sg:province":"CO",
    "sg:tags":[
        "building",
        "parks"
    ],
    "wof:name":"RWH Office Bldg",
    "wof:placetype":"venue"
},
  "geometry": {"coordinates":[-104.75638600000001,38.854882],"type":"Point"}
}