{
  "type": "Feature",
  "properties": {
    "iso:country":"US",
    "sg:address":"376 2nd Ave",
    "sg:city":"Niwot",
    "sg:classifiers":[
        {
            "category":"Health Services",
            "subcategory":"Doctor",
            "type":"Services"
        }
    ],
    "sg:phone":"+1 303 915 8900",
    "sg:postcode":"80544",
    "sg:province":"CO",
    "sg:tags":[
        "dentist"
    ],
    "wof:name":"Onsight Dental Surgery",
    "wof:placetype":"venue"
},
  "geometry": {"coordinates":[-105.17186,40.102917],"type":"Point"}
}