{
  "type": "Feature",
  "properties": {
    "iso:country":"US",
    "sg:address":"10372 Colorado Blvd",
    "sg:city":"Denver",
    "sg:classifiers":[
        {
            "category":"Food & Beverages",
            "subcategory":"Liquor & Beverages",
            "type":"Retail Goods"
        }
    ],
    "sg:phone":"+1 303 457 2692",
    "sg:postcode":"80229",
    "sg:province":"CO",
    "wof:name":"Larkspur Liquors",
    "wof:placetype":"venue"
},
  "geometry": {"coordinates":[-104.940091,39.882237],"type":"Point"}
}