{
  "type": "Feature",
  "properties": {
    "iso:country":"US",
    "sg:address":"8575 E Arapahoe Rd",
    "sg:city":"Greenwood Vlg",
    "sg:classifiers":[
        {
            "category":"Personal",
            "subcategory":"Beauty Salon",
            "type":"Services"
        }
    ],
    "sg:phone":"+1 720 987 6740",
    "sg:postcode":"80112",
    "sg:province":"CO",
    "wof:name":"GBSN",
    "wof:placetype":"venue"
},
  "geometry": {"coordinates":[-104.89257600000001,39.595112],"type":"Point"}
}