{
  "type": "Feature",
  "properties": {
    "iso:country":"US",
    "sg:address":"3415 Brompton Ct",
    "sg:city":"Colorado Springs",
    "sg:classifiers":[
        {
            "category":"Communications",
            "type":"Services"
        }
    ],
    "sg:phone":"+1 719 282 9156",
    "sg:postcode":"80920",
    "sg:province":"CO",
    "sg:tags":[
        "communication"
    ],
    "wof:name":"Telecomm Support Inc",
    "wof:placetype":"venue"
},
  "geometry": {"coordinates":[-104.762332,38.958166],"type":"Point"}
}