{
  "type": "Feature",
  "properties": {
    "iso:country":"US",
    "sg:address":"410 17th St Suite 570",
    "sg:city":"Denver",
    "sg:classifiers":[
        {
            "category":"Professional",
            "subcategory":"Computer Services",
            "type":"Services"
        }
    ],
    "sg:phone":"+1 303 984 4727",
    "sg:postcode":"80202 ",
    "sg:province":"CO",
    "sg:website":"http://www.selero.com",
    "wof:name":"Selero",
    "wof:placetype":"venue"
},
  "geometry": {"coordinates":[-104.988767,39.744314],"type":"Point"}
}