{
  "type": "Feature",
  "properties": {
    "iso:country":"US",
    "sg:address":"8000 E Prentice Ave",
    "sg:city":"Englewood",
    "sg:classifiers":[
        {
            "category":"Health Services",
            "subcategory":"Hospital",
            "type":"Services"
        }
    ],
    "sg:phone":"+1 303 694 3829",
    "sg:postcode":"80111",
    "sg:province":"CO",
    "sg:tags":[
        "clinic",
        "specialty",
        "outpatient"
    ],
    "wof:name":"Valley Hope Otptent Trtmnt Ctr",
    "wof:placetype":"venue"
},
  "geometry": {"coordinates":[-104.895183,39.620609],"type":"Point"}
}