{
  "type": "Feature",
  "properties": {
    "addr:full":"4704 Harlan St Denver CO 80212",
    "addr:housenumber":"4704",
    "addr:postcode":"80212",
    "addr:street":"Harlan St",
    "iso:country":"US",
    "sg:address":"4704 Harlan St",
    "sg:city":"Denver",
    "sg:classifiers":[
        {
            "category":"Health Services",
            "subcategory":"Nursing And Care Facility",
            "type":"Services"
        },
        {
            "category":"Organizations",
            "subcategory":"Non-profit Organization",
            "type":"Services"
        }
    ],
    "sg:phone":"+1 303 423 7660",
    "sg:postcode":"80212",
    "sg:province":"CO",
    "sg:tags":[
        "skilled",
        "disability"
    ],
    "sg:website":"www.dungarvin.com",
    "wof:name":"Dungarvin Colorado Inc",
    "wof:placetype":"venue"
},
  "geometry": {"coordinates":[-105.062506,39.782972],"type":"Point"}
}