{
  "type": "Feature",
  "properties": {
    "iso:country":"US",
    "sg:address":"7692 Shenandoah Dr",
    "sg:city":"Elizabeth",
    "sg:classifiers":[
        {
            "category":"Building & Trades",
            "subcategory":"Landscaping Services",
            "type":"Services"
        }
    ],
    "sg:phone":"+1 303 646 8454",
    "sg:postcode":"80107",
    "sg:province":"CO",
    "sg:tags":[
        "landscape",
        "contractor"
    ],
    "wof:name":"Back Woods Landscaping Inc",
    "wof:placetype":"venue"
},
  "geometry": {"coordinates":[-104.51656699999999,39.504575],"type":"Point"}
}