{
  "type": "Feature",
  "properties": {
    "iso:country":"US",
    "sg:address":"48 Grenadier Pl",
    "sg:city":"Pagosa Springs",
    "sg:classifiers":[
        {
            "category":"Shopping",
            "subcategory":"Computers & Home Electronics",
            "type":"Retail Goods"
        }
    ],
    "sg:phone":"+1 970 731 3315",
    "sg:postcode":"81147",
    "sg:province":"CO",
    "wof:name":"Sight & Sound",
    "wof:placetype":"venue"
},
  "geometry": {"coordinates":[-107.126053,37.320294],"type":"Point"}
}