{
  "type": "Feature",
  "properties": {
    "addr:full":"5811 Gleneagles Village Pkwy Littleton CO 80130",
    "addr:housenumber":"5811",
    "addr:postcode":"80130",
    "addr:street":"Gleneagles Village Pkwy",
    "iso:country":"US",
    "sg:address":"5811 Gleneagles Village Pkwy",
    "sg:city":"Littleton",
    "sg:classifiers":[
        {
            "category":"Social Services",
            "subcategory":"Child Care",
            "type":"Services"
        }
    ],
    "sg:phone":"+1 303 471 1110",
    "sg:postcode":"80130",
    "sg:province":"CO",
    "wof:name":"Espree Child Learning Ctr",
    "wof:placetype":"venue"
},
  "geometry": {"coordinates":[-104.92707900000001,39.550609],"type":"Point"}
}