{
  "type": "Feature",
  "properties": {
    "addr:full":"739 Windmill Pl Littleton CO 80126",
    "addr:housenumber":"739",
    "addr:postcode":"80126",
    "addr:street":"Windmill Pl",
    "iso:country":"US",
    "sg:address":"739 Windmill Pl",
    "sg:city":"Littleton",
    "sg:classifiers":[
        {
            "category":"Building & Trades",
            "subcategory":"Construction",
            "type":"Services"
        }
    ],
    "sg:phone":"+1 303 697 3028",
    "sg:postcode":"80126",
    "sg:province":"CO",
    "sg:tags":[
        "excavating",
        "contractor"
    ],
    "wof:name":"Marshall Excavating LLC",
    "wof:placetype":"venue"
},
  "geometry": {"coordinates":[-104.978409,39.560604],"type":"Point"}
}