{
  "type": "Feature",
  "properties": {
    "addr:full":"7822 Hidden Pine Dr Colorado Springs CO 80925",
    "addr:housenumber":"7822",
    "addr:postcode":"80925",
    "addr:street":"Hidden Pine Dr",
    "iso:country":"US",
    "sg:address":"7822 Hidden Pine Dr",
    "sg:city":"Colorado Springs",
    "sg:classifiers":[
        {
            "category":"Building & Trades",
            "subcategory":"Construction",
            "type":"Services"
        }
    ],
    "sg:phone":"+1 719 392 8518",
    "sg:postcode":"80925",
    "sg:province":"CO",
    "sg:tags":[
        "home",
        "builder"
    ],
    "sg:website":"www.newgenhomes.com",
    "wof:name":"New Generation Homes",
    "wof:placetype":"venue"
},
  "geometry": {"coordinates":[-104.681634,38.729286],"type":"Point"}
}