{
  "type": "Feature",
  "properties": {
    "iso:country":"US",
    "sg:address":"7125 Reynolds Dr",
    "sg:city":"Sedalia",
    "sg:classifiers":[
        {
            "category":"Building & Trades",
            "subcategory":"Construction",
            "type":"Services"
        }
    ],
    "sg:phone":"+1 303 791 3229",
    "sg:postcode":"80135",
    "sg:province":"CO",
    "sg:tags":[
        "excavating",
        "contractor"
    ],
    "wof:name":"K R Swerdfeger Construction",
    "wof:placetype":"venue"
},
  "geometry": {"coordinates":[-104.990667,39.467017],"type":"Point"}
}