{
  "type": "Feature",
  "properties": {
    "addr:full":"8827 Lone Tree Pkwy Lone Tree CO 80124",
    "addr:housenumber":"8827",
    "addr:postcode":"80124",
    "addr:street":"Lone Tree Pkwy",
    "iso:country":"US",
    "sg:address":"8827 Lone Tree Pkwy",
    "sg:city":"Lone Tree",
    "sg:classifiers":[
        {
            "category":"Education",
            "subcategory":"Library",
            "type":"Public Place"
        }
    ],
    "sg:phone":"+1 303 799 4446",
    "sg:postcode":"80124",
    "sg:province":"CO",
    "sg:website":"www.douglas.lib.co.us",
    "wof:name":"Lone Tree Public Library",
    "wof:placetype":"venue"
},
  "geometry": {"coordinates":[-104.889177,39.548097],"type":"Point"}
}