{
  "type": "Feature",
  "properties": {
    "iso:country":"US",
    "sg:address":"3701 W 1st Ave",
    "sg:city":"Denver",
    "sg:classifiers":[
        {
            "category":"Shopping",
            "subcategory":"Clothing, Apparel, & Fashions",
            "type":"Retail Goods"
        }
    ],
    "sg:phone":"+1 303 884 0161",
    "sg:postcode":"80219",
    "sg:province":"CO",
    "wof:name":"Labonita Fashions",
    "wof:placetype":"venue"
},
  "geometry": {"coordinates":[-105.037308,39.718152],"type":"Point"}
}