{
  "type": "Feature",
  "properties": {
    "iso:country":"US",
    "sg:address":"12015 E 46th Ave",
    "sg:city":"Denver",
    "sg:classifiers":[
        {
            "category":"Professional",
            "subcategory":"Detective & Security Services",
            "type":"Services"
        }
    ],
    "sg:phone":"+1 303 574 0000",
    "sg:postcode":"80239",
    "sg:province":"CO",
    "sg:tags":[
        "guard",
        "patrol"
    ],
    "sg:website":"www.twincitysecurity.com",
    "wof:name":"Twin City Security Inc",
    "wof:placetype":"venue"
},
  "geometry": {"coordinates":[-104.847477,39.779663],"type":"Point"}
}