{
  "type": "Feature",
  "properties": {
    "addr:full":"3031 S Tejon St Englewood CO 80110",
    "addr:housenumber":"3031",
    "addr:postcode":"80110",
    "addr:street":"S Tejon St",
    "iso:country":"US",
    "sg:address":"3031 S Tejon St",
    "sg:city":"Englewood",
    "sg:classifiers":[
        {
            "category":"Home & Garden",
            "subcategory":"Building Materials",
            "type":"Retail Goods"
        }
    ],
    "sg:phone":"+1 303 946 5195",
    "sg:postcode":"80110",
    "sg:province":"CO",
    "wof:name":"Commerical Door",
    "wof:placetype":"venue"
},
  "geometry": {"coordinates":[-105.011155,39.661053],"type":"Point"}
}