{
  "type": "Feature",
  "properties": {
    "iso:country":"US",
    "sg:address":"2465 S Jasmine St",
    "sg:city":"Denver",
    "sg:classifiers":[
        {
            "category":"Restaurant",
            "type":"Food & Drink"
        }
    ],
    "sg:phone":"+1 303 514 3202",
    "sg:postcode":"80222",
    "sg:province":"CO",
    "sg:tags":[
        "eating"
    ],
    "wof:name":"Whole Control LLC",
    "wof:placetype":"venue"
},
  "geometry": {"coordinates":[-104.92007599999999,39.67068],"type":"Point"}
}