{
  "type": "Feature",
  "properties": {
    "iso:country":"US",
    "sg:address":"886 Larkspur Ct",
    "sg:city":"Louisville",
    "sg:classifiers":[
        {
            "category":"Professional",
            "subcategory":"Advertising",
            "type":"Services"
        }
    ],
    "sg:phone":"+1 303 665 7193",
    "sg:postcode":"80027",
    "sg:province":"CO",
    "sg:tags":[
        "agency"
    ],
    "wof:name":"Subway",
    "wof:placetype":"venue"
},
  "geometry": {"coordinates":[-105.162075,39.974794],"type":"Point"}
}