{
  "type": "Feature",
  "properties": {
    "addr:full":"417 N Circle Dr Colorado Springs CO 80909",
    "addr:housenumber":"417",
    "addr:postcode":"80909",
    "addr:street":"N Circle Dr",
    "iso:country":"US",
    "sg:address":"417 N Circle Dr",
    "sg:city":"Colorado Springs",
    "sg:classifiers":[
        {
            "category":"Professional",
            "subcategory":"Employment Agencies",
            "type":"Services"
        }
    ],
    "sg:phone":"+1 719 520 9101",
    "sg:postcode":"80909",
    "sg:province":"CO",
    "sg:tags":[
        "help",
        "contractor"
    ],
    "wof:name":"American Staffing & Personnel",
    "wof:placetype":"venue"
},
  "geometry": {"coordinates":[-104.77583199999999,38.837483],"type":"Point"}
}