{
  "type": "Feature",
  "properties": {
    "iso:country":"US",
    "sg:address":"1193 Bergen Pkwy",
    "sg:city":"Evergreen",
    "sg:classifiers":[
        {
            "category":"Home & Garden",
            "subcategory":"Building Materials",
            "type":"Retail Goods"
        },
        {
            "category":"Building & Trades",
            "subcategory":"Construction",
            "type":"Services"
        }
    ],
    "sg:phone":"+1 303 674 1605",
    "sg:postcode":"80439",
    "sg:province":"CO",
    "sg:tags":[
        "paint",
        "wallpaper",
        "contractor"
    ],
    "wof:name":"Bergen Park Paints",
    "wof:placetype":"venue"
},
  "geometry": {"coordinates":[-105.35628800000001,39.694013],"type":"Point"}
}