{
  "type": "Feature",
  "properties": {
    "addr:full":"805 W Ottley Ave Fruita CO 81521",
    "addr:housenumber":"805",
    "addr:postcode":"81521",
    "addr:street":"W Ottley Ave",
    "iso:country":"US",
    "sg:address":"805 W Ottley Ave",
    "sg:city":"Fruita",
    "sg:classifiers":[
        {
            "category":"Health Services",
            "subcategory":"Nursing And Care Facility",
            "type":"Services"
        }
    ],
    "sg:phone":"+1 970 858 2178",
    "sg:postcode":"81521",
    "sg:province":"CO",
    "sg:tags":[
        "intermediate"
    ],
    "wof:name":"Oaks",
    "wof:placetype":"venue"
},
  "geometry": {"coordinates":[-108.743781,39.164371],"type":"Point"}
}