{
  "type": "Feature",
  "properties": {
    "iso:country":"US",
    "sg:address":"5724 Snowmass Creek Rd",
    "sg:city":"Snowmass",
    "sg:classifiers":[
        {
            "category":"Building & Trades",
            "subcategory":"Construction",
            "type":"Services"
        }
    ],
    "sg:phone":"+1 970 923 3840",
    "sg:postcode":"81654",
    "sg:province":"CO",
    "sg:tags":[
        "general",
        "contractor"
    ],
    "wof:name":"Ragged Bear Ranch Construction",
    "wof:placetype":"venue"
},
  "geometry": {"coordinates":[-106.964949,39.260202],"type":"Point"}
}