{
  "type": "Feature",
  "properties": {
    "iso:country":"US",
    "sg:address":"11151 E 51st Ave",
    "sg:city":"Denver",
    "sg:classifiers":[
        {
            "category":"Professional",
            "subcategory":"Engineering",
            "type":"Services"
        },
        {
            "category":"Home & Garden",
            "subcategory":"Building Materials",
            "type":"Retail Goods"
        }
    ],
    "sg:phone":"+1 303 373 8100",
    "sg:postcode":"80239",
    "sg:province":"CO",
    "sg:tags":[
        "product",
        "consultant",
        "energy",
        "conservation",
        "insulation"
    ],
    "wof:name":"Enerflex Energy Systems Inc.",
    "wof:placetype":"venue"
},
  "geometry": {"coordinates":[-104.858448,39.790329],"type":"Point"}
}