{
  "type": "Feature",
  "properties": {
    "addr:full":"20476 Co Rd 29 Platteville CO 80651",
    "addr:housenumber":"20476;29",
    "addr:postcode":"80651",
    "addr:street":"Co Rd",
    "iso:country":"US",
    "sg:address":"20476 Co Rd 29",
    "sg:city":"Platteville",
    "sg:classifiers":[
        {
            "category":"Retail",
            "subcategory":"Auto Repair",
            "type":"Services"
        }
    ],
    "sg:phone":"+1 970 737 0107",
    "sg:postcode":"80651",
    "sg:province":"CO",
    "sg:tags":[
        "truck"
    ],
    "wof:name":"D & D Ag Repair",
    "wof:placetype":"venue"
},
  "geometry": {"coordinates":[-104.79178400000001,40.302785],"type":"Point"}
}