{
  "type": "Feature",
  "properties": {
    "addr:full":"15427 E Fremont Dr Englewood CO 80112",
    "addr:housenumber":"15427",
    "addr:postcode":"80112",
    "addr:street":"E Fremont Dr",
    "iso:country":"US",
    "sg:address":"15427 E Fremont Dr",
    "sg:city":"Englewood",
    "sg:classifiers":[
        {
            "category":"Building & Trades",
            "subcategory":"Construction",
            "type":"Services"
        }
    ],
    "sg:phone":"+1 303 791 7473",
    "sg:postcode":"80112",
    "sg:province":"CO",
    "sg:tags":[
        "general",
        "contractor"
    ],
    "sg:website":"www.ticus.com",
    "wof:name":"ERS Constructors-Pipeline",
    "wof:placetype":"venue"
},
  "geometry": {"coordinates":[-104.808424,39.586492],"type":"Point"}
}