{
  "type": "Feature",
  "properties": {
    "iso:country":"US",
    "sg:address":"1164 S Los Charros Dr",
    "sg:city":"Pueblo",
    "sg:classifiers":[
        {
            "category":"Wholesale",
            "subcategory":"Furniture",
            "type":"Manufacturing & Wholesale Goods"
        }
    ],
    "sg:phone":"+1 719 406 3564",
    "sg:postcode":"81007",
    "sg:province":"CO",
    "sg:tags":[
        "beds-wholesale",
        "manufacturer"
    ],
    "wof:name":"Red Rooster Bed & Breakfast",
    "wof:placetype":"venue"
},
  "geometry": {"coordinates":[-104.800197,38.300762],"type":"Point"}
}