{
  "type": "Feature",
  "properties": {
    "addr:full":"339 Olympus Cir Littleton CO 80124",
    "addr:housenumber":"339",
    "addr:postcode":"80124",
    "addr:street":"Olympus Cir",
    "iso:country":"US",
    "sg:address":"339 Olympus Cir",
    "sg:city":"Littleton",
    "sg:classifiers":[
        {
            "category":"Building & Trades",
            "subcategory":"Landscaping Services",
            "type":"Services"
        }
    ],
    "sg:phone":"+1 303 799 9788",
    "sg:postcode":"80124",
    "sg:province":"CO",
    "sg:tags":[
        "landscape",
        "contractor"
    ],
    "wof:name":"Turfscape Inc",
    "wof:placetype":"venue"
},
  "geometry": {"coordinates":[-104.890922,39.557163],"type":"Point"}
}