{
  "type": "Feature",
  "properties": {
    "addr:full":"329 7th St Meeker CO 81641",
    "addr:housenumber":"329",
    "addr:street":"7Th St",
    "iso:country":"US",
    "sg:address":"329 7th St",
    "sg:city":"Meeker",
    "sg:classifiers":[
        {
            "category":"Wholesale",
            "subcategory":"Chemicals & Plastics",
            "type":"Manufacturing & Wholesale Goods"
        }
    ],
    "sg:phone":"+1 970 878 5893",
    "sg:postcode":"81641",
    "sg:province":"CO",
    "sg:tags":[
        "oxygen"
    ],
    "sg:website":"www.psakids.com",
    "wof:name":"PSA Home Healthcare",
    "wof:placetype":"venue"
},
  "geometry": {"coordinates":[-107.915211,40.037303],"type":"Point"}
}