{
  "type": "Feature",
  "properties": {
    "iso:country":"US",
    "sg:address":"1690 S Abilene St",
    "sg:city":"Aurora",
    "sg:classifiers":[
        {
            "category":"Shopping",
            "type":"Retail Goods"
        }
    ],
    "sg:phone":"+1 303 745 9191",
    "sg:postcode":"80012",
    "sg:province":"CO",
    "sg:tags":[
        "spa",
        "hot",
        "tub"
    ],
    "sg:website":"www.spa-brokers.com",
    "wof:name":"Spa Brokers Fireplace & Stove",
    "wof:placetype":"venue"
},
  "geometry": {"coordinates":[-104.82819000000001,39.685585],"type":"Point"}
}