{
  "type": "Feature",
  "properties": {
    "addr:full":"1109 Rangeview Dr Golden CO 80403",
    "addr:housenumber":"1109",
    "addr:postcode":"80403",
    "addr:street":"Rangeview Dr",
    "iso:country":"US",
    "sg:address":"1109 Rangeview Dr",
    "sg:city":"Golden",
    "sg:classifiers":[
        {
            "category":"Building & Trades",
            "subcategory":"Construction",
            "type":"Services"
        }
    ],
    "sg:phone":"+1 303 582 5377",
    "sg:postcode":"80403",
    "sg:province":"CO",
    "sg:tags":[
        "house"
    ],
    "wof:name":"Dominic Salerno",
    "wof:placetype":"venue"
},
  "geometry": {"coordinates":[-105.476833,39.825955],"type":"Point"}
}