{
  "type": "Feature",
  "properties": {
    "iso:country":"US",
    "sg:address":"1627 Columbine Ave",
    "sg:city":"Boulder",
    "sg:classifiers":[
        {
            "category":"Building & Trades",
            "subcategory":"Construction",
            "type":"Services"
        }
    ],
    "sg:phone":"+1 303 443 2697",
    "sg:postcode":"80302",
    "sg:province":"CO",
    "sg:tags":[
        "residential"
    ],
    "wof:name":"Builders Studio Inc",
    "wof:placetype":"venue"
},
  "geometry": {"coordinates":[-105.271505,39.999207],"type":"Point"}
}