{
  "type": "Feature",
  "properties": {
    "addr:full":"6323 Jay Rd Boulder CO 80301",
    "addr:housenumber":"6323",
    "addr:postcode":"80301",
    "addr:street":"Jay Rd",
    "iso:country":"US",
    "sg:address":"6323 Jay Rd",
    "sg:city":"Boulder",
    "sg:classifiers":[
        {
            "category":"Building & Trades",
            "subcategory":"Construction",
            "type":"Services"
        }
    ],
    "sg:phone":"+1 303 530 2057",
    "sg:postcode":"80301",
    "sg:province":"CO",
    "sg:tags":[
        "gutter",
        "painting",
        "contractor"
    ],
    "wof:name":"Bluebell Farms Inc",
    "wof:placetype":"venue"
},
  "geometry": {"coordinates":[-105.205219,40.051026],"type":"Point"}
}