{
  "type": "Feature",
  "properties": {
    "addr:full":"1607 Brentford Ln Fort Collins CO 80525",
    "addr:housenumber":"1607",
    "addr:postcode":"80525",
    "addr:street":"Brentford Ln",
    "iso:country":"US",
    "sg:address":"1607 Brentford Ln",
    "sg:city":"Fort Collins",
    "sg:classifiers":[
        {
            "category":"Banks & Credit Unions",
            "subcategory":"Investment Brokerage",
            "type":"Services"
        }
    ],
    "sg:phone":"+1 970 266 8044",
    "sg:postcode":"80525",
    "sg:province":"CO",
    "sg:tags":[
        "stock",
        "bond"
    ],
    "wof:name":"Central Discount Brokers Inc",
    "wof:placetype":"venue"
},
  "geometry": {"coordinates":[-105.048204,40.545113],"type":"Point"}
}