{
  "type": "Feature",
  "properties": {
    "addr:full":"1834 Main St Longmont CO 80504",
    "addr:housenumber":"1834",
    "addr:postcode":"80504",
    "addr:street":"Main St",
    "iso:country":"US",
    "sg:address":"1834 Main St",
    "sg:city":"Longmont",
    "sg:classifiers":[
        {
            "category":"Professional",
            "subcategory":"Accounting & Tax Preparation",
            "type":"Services"
        }
    ],
    "sg:phone":"+1 303 776 1048",
    "sg:postcode":"80504",
    "sg:province":"CO",
    "sg:tags":[
        "return",
        "filing"
    ],
    "wof:name":"Jackson Hewitt Tax Svc",
    "wof:placetype":"venue"
},
  "geometry": {"coordinates":[-105.102293,40.188568],"type":"Point"}
}