{
  "type": "Feature",
  "properties": {
    "addr:full":"6730 Grove St Denver CO 80221",
    "addr:housenumber":"6730",
    "addr:postcode":"80221",
    "addr:street":"Grove St",
    "iso:country":"US",
    "sg:address":"6730 Grove St",
    "sg:city":"Denver",
    "sg:classifiers":[
        {
            "category":"Building & Trades",
            "subcategory":"Construction",
            "type":"Services"
        }
    ],
    "sg:phone":"+1 303 429 7688",
    "sg:postcode":"80221",
    "sg:province":"CO",
    "sg:tags":[
        "house"
    ],
    "wof:name":"Pwp Construction Expressions",
    "wof:placetype":"venue"
},
  "geometry": {"coordinates":[-105.027502,39.819475],"type":"Point"}
}