{
  "type": "Feature",
  "properties": {
    "iso:country":"US",
    "sg:address":"11707 W 64th Ave",
    "sg:city":"Arvada",
    "sg:classifiers":[
        {
            "category":"Manufacturing",
            "subcategory":"Rubber & Plastics",
            "type":"Manufacturing & Wholesale Goods"
        },
        {
            "category":"Autos & Motor Vehicles",
            "subcategory":"Auto Supplies",
            "type":"Retail Goods"
        }
    ],
    "sg:phone":"+1 303 425 9574",
    "sg:postcode":"80004",
    "sg:province":"CO",
    "sg:tags":[
        "wheel",
        "tires-wholesale",
        "tire",
        "manufacturer"
    ],
    "sg:website":"http://www.discounttire.com/dtcs/home.do?utm_source=YellowPages&utm_medium=iyp&utm_campaign=YellowPagesIYPOrg",
    "wof:name":"Discount Tire",
    "wof:placetype":"venue"
},
  "geometry": {"coordinates":[-105.12921799999999,39.812823],"type":"Point"}
}