{
  "type": "Feature",
  "properties": {
    "addr:full":"1875 Lawrence St Denver CO 80202",
    "addr:housenumber":"1875",
    "addr:postcode":"80202",
    "addr:street":"Lawrence St",
    "iso:country":"US",
    "sg:address":"1875 Lawrence St",
    "sg:city":"Denver",
    "sg:classifiers":[
        {
            "category":"Professional",
            "subcategory":"Computer Services",
            "type":"Services"
        }
    ],
    "sg:phone":"+1 303 293 0212",
    "sg:postcode":"80202",
    "sg:province":"CO",
    "sg:tags":[
        "development",
        "software"
    ],
    "wof:name":"FINDNOW",
    "wof:placetype":"venue"
},
  "geometry": {"coordinates":[-104.99373199999999,39.750687],"type":"Point"}
}