{
  "type": "Feature",
  "properties": {
    "iso:country":"US",
    "sg:address":"1030 Market St",
    "sg:city":"Meeker",
    "sg:classifiers":[
        {
            "category":"Food & Beverages",
            "subcategory":"Liquor & Beverages",
            "type":"Retail Goods"
        }
    ],
    "sg:phone":"+1 970 878 5485",
    "sg:postcode":"81641",
    "sg:province":"CO",
    "wof:name":"Night Owl Liquors",
    "wof:placetype":"venue"
},
  "geometry": {"coordinates":[-107.919273,40.035134],"type":"Point"}
}