{
  "type": "Feature",
  "properties": {
    "addr:full":"10542 Hoyt St Broomfield CO 80021",
    "addr:housenumber":"10542",
    "addr:postcode":"80021",
    "addr:street":"Hoyt St",
    "iso:country":"US",
    "sg:address":"10542 Hoyt St",
    "sg:city":"Broomfield",
    "sg:classifiers":[
        {
            "category":"Food & Beverages",
            "subcategory":"Specialty",
            "type":"Retail Goods"
        }
    ],
    "sg:phone":"+1 303 469 2053",
    "sg:postcode":"80021",
    "sg:province":"CO",
    "wof:name":"Thermojetics",
    "wof:placetype":"venue"
},
  "geometry": {"coordinates":[-105.102836,39.88815],"type":"Point"}
}