{
  "type": "Feature",
  "properties": {
    "iso:country":"US",
    "sg:address":"2648 Santa Fe Dr",
    "sg:city":"Pueblo",
    "sg:classifiers":[
        {
            "category":"Home & Garden",
            "subcategory":"Home Furnishings",
            "type":"Retail Goods"
        },
        {
            "category":"Shopping",
            "subcategory":"Crafts & Fabrics",
            "type":"Retail Goods"
        }
    ],
    "sg:phone":"+1 719 544 8897",
    "sg:postcode":"81006",
    "sg:province":"CO",
    "sg:tags":[
        "sewing",
        "quilting"
    ],
    "wof:name":"Grandma's Quilting Threads",
    "wof:placetype":"venue"
},
  "geometry": {"coordinates":[-104.564086,38.24542],"type":"Point"}
}