{
  "type": "Feature",
  "properties": {
    "addr:full":"2352 N 7th St Grand Junction CO 81501",
    "addr:housenumber":"2352",
    "addr:postcode":"81501",
    "addr:street":"N 7Th St",
    "iso:country":"US",
    "sg:address":"2352 N 7th St",
    "sg:city":"Grand Junction",
    "sg:classifiers":[
        {
            "category":"Wholesale",
            "subcategory":"Medical Equipment & Supplies",
            "type":"Manufacturing & Wholesale Goods"
        }
    ],
    "sg:phone":"+1 970 241 9562",
    "sg:postcode":"81501",
    "sg:province":"CO",
    "sg:tags":[
        "physician",
        "surgeon"
    ],
    "wof:name":"Rehabilicare/Orthofix",
    "wof:placetype":"venue"
},
  "geometry": {"coordinates":[-108.560945,39.088883],"type":"Point"}
}