{
  "type": "Feature",
  "properties": {
    "addr:full":"7304 Poudre River Rd Greeley CO 80634",
    "addr:housenumber":"7304",
    "addr:postcode":"80634",
    "addr:street":"Poudre River Rd",
    "iso:country":"US",
    "sg:address":"7304 Poudre River Rd",
    "sg:city":"Greeley",
    "sg:classifiers":[
        {
            "category":"Building & Trades",
            "subcategory":"Construction",
            "type":"Services"
        }
    ],
    "sg:phone":"+1 970 412 5509",
    "sg:postcode":"80634",
    "sg:province":"CO",
    "sg:tags":[
        "hanging",
        "contractor"
    ],
    "wof:name":"All Pros Painting & Remodeling",
    "wof:placetype":"venue"
},
  "geometry": {"coordinates":[-104.79705300000001,40.441399],"type":"Point"}
}