{
  "type": "Feature",
  "properties": {
    "iso:country":"US",
    "sg:address":"11701 Community Center Dr",
    "sg:city":"Northglenn",
    "sg:classifiers":[
        {
            "category":"Government",
            "subcategory":"Office",
            "type":"Public Place"
        }
    ],
    "sg:phone":"+1 303 450 8756",
    "sg:postcode":"80233",
    "sg:province":"CO",
    "sg:tags":[
        "city"
    ],
    "wof:name":"Northglenn Records-City Clerk",
    "wof:placetype":"venue"
},
  "geometry": {"coordinates":[-104.987067,39.909439],"type":"Point"}
}