{
  "type": "Feature",
  "properties": {
    "iso:country":"US",
    "sg:address":"5100 W 38th Ave",
    "sg:city":"Denver",
    "sg:classifiers":[
        {
            "category":"Personal",
            "subcategory":"Beauty Salon",
            "type":"Services"
        }
    ],
    "sg:phone":"+1 303 477 6902",
    "sg:postcode":"80212",
    "sg:province":"CO",
    "wof:name":"Dekada Beauty Salon",
    "wof:placetype":"venue"
},
  "geometry": {"coordinates":[-105.05324,39.769332],"type":"Point"}
}