{
  "type": "Feature",
  "properties": {
    "iso:country":"US",
    "sg:address":"315 N Spruce St",
    "sg:city":"Grand Junction",
    "sg:classifiers":[
        {
            "category":"Government",
            "subcategory":"Office",
            "type":"Public Place"
        }
    ],
    "sg:phone":"+1 970 244 3230",
    "sg:postcode":"81501",
    "sg:province":"CO",
    "wof:name":"Mesa County Facilities Mgmt",
    "wof:placetype":"venue"
},
  "geometry": {"coordinates":[-108.572238,39.07018],"type":"Point"}
}