{
  "type": "Feature",
  "properties": {
    "addr:full":"7465 W Clifton Ave Littleton CO 80128",
    "addr:housenumber":"7465",
    "addr:postcode":"80128",
    "addr:street":"W Clifton Ave",
    "iso:country":"US",
    "sg:address":"7465 W Clifton Ave",
    "sg:city":"Littleton",
    "sg:classifiers":[
        {
            "category":"Real Estate",
            "subcategory":"Real Estate Agent",
            "type":"Services"
        }
    ],
    "sg:phone":"+1 303 973 0918",
    "sg:postcode":"80128",
    "sg:province":"CO",
    "sg:tags":[
        "business"
    ],
    "wof:name":"Evans Partners Inc",
    "wof:placetype":"venue"
},
  "geometry": {"coordinates":[-105.08142700000001,39.569452],"type":"Point"}
}