{
  "type": "Feature",
  "properties": {
    "addr:full":"719 Saddleback Dr Pagosa Springs CO 81147",
    "addr:housenumber":"719",
    "addr:postcode":"81147",
    "addr:street":"Saddleback Dr",
    "iso:country":"US",
    "sg:address":"719 Saddleback Dr",
    "sg:city":"Pagosa Springs",
    "sg:classifiers":[
        {
            "category":"Real Estate",
            "subcategory":"Real Estate Operator",
            "type":"Services"
        }
    ],
    "sg:phone":"+1 970 264 3611",
    "sg:postcode":"81147",
    "sg:province":"CO",
    "sg:tags":[
        "building",
        "apartment"
    ],
    "wof:name":"Pagosa Heights Apts LLC",
    "wof:placetype":"venue"
},
  "geometry": {"coordinates":[-106.969002,37.191068],"type":"Point"}
}