{
  "type": "Feature",
  "properties": {
    "iso:country":"US",
    "sg:address":"966 Daffodil St",
    "sg:city":"Fountain",
    "sg:classifiers":[
        {
            "category":"Wholesale",
            "subcategory":"Vending Machines",
            "type":"Manufacturing & Wholesale Goods"
        }
    ],
    "sg:phone":"+1 719 382 7287",
    "sg:postcode":"80817",
    "sg:province":"CO",
    "sg:tags":[
        "operator"
    ],
    "wof:name":"Sundys Vending",
    "wof:placetype":"venue"
},
  "geometry": {"coordinates":[-104.674668,38.669817],"type":"Point"}
}