{
  "type": "Feature",
  "properties": {
    "addr:full":"31 Avondale Ln Avon CO 81620",
    "addr:housenumber":"31",
    "addr:postcode":"81620",
    "addr:street":"Avondale Ln",
    "iso:country":"US",
    "sg:address":"31 Avondale Ln",
    "sg:city":"Avon",
    "sg:classifiers":[
        {
            "category":"Travel",
            "subcategory":"Hotels & Motels",
            "type":"Entertainment"
        }
    ],
    "sg:phone":"+1 970 845 5561",
    "sg:postcode":"81620",
    "sg:province":"CO",
    "wof:name":"Oxford Court",
    "wof:placetype":"venue"
},
  "geometry": {"coordinates":[-106.51840199999999,39.604749],"type":"Point"}
}