{
  "type": "Feature",
  "properties": {
    "iso:country":"US",
    "sg:address":"1491 S Havana St",
    "sg:city":"Aurora",
    "sg:classifiers":[
        {
            "category":"Restaurant",
            "type":"Food & Drink"
        }
    ],
    "sg:menulink":"http://www.allmenus.com/co/south-aurora/8547-red-robin/menu/",
    "sg:phone":"+1 303 671 7055",
    "sg:postcode":"80012",
    "sg:province":"CO",
    "sg:tags":[
        "american"
    ],
    "wof:name":"Red Robin",
    "wof:placetype":"venue"
},
  "geometry": {"coordinates":[-104.86583299999999,39.690807],"type":"Point"}
}