{
  "type": "Feature",
  "properties": {
    "iso:country":"US",
    "sg:address":"1350 Irving St",
    "sg:city":"Denver",
    "sg:classifiers":[
        {
            "category":"Real Estate",
            "subcategory":"Real Estate Operator",
            "type":"Services"
        }
    ],
    "sg:phone":"+1 303 825 3909",
    "sg:postcode":"80204",
    "sg:province":"CO",
    "sg:tags":[
        "apartment"
    ],
    "wof:name":"WSV Dorchester Overlook Apt",
    "wof:placetype":"venue"
},
  "geometry": {"coordinates":[-105.029769,39.738316],"type":"Point"}
}