{
  "type": "Feature",
  "properties": {
    "addr:full":"23331 Co Rd 93 Haxtun CO 80731",
    "addr:housenumber":"23331;93",
    "addr:postcode":"80731",
    "addr:street":"Co Rd",
    "iso:country":"US",
    "sg:address":"23331 Co Rd 93",
    "sg:city":"Haxtun",
    "sg:classifiers":[
        {
            "category":"Farming",
            "subcategory":"Farm",
            "type":"Manufacturing & Wholesale Goods"
        }
    ],
    "sg:phone":"+1 970 774 7653",
    "sg:postcode":"80731",
    "sg:province":"CO",
    "sg:tags":[
        "crop",
        "animal",
        "general"
    ],
    "wof:name":"Kent Stephens",
    "wof:placetype":"venue"
},
  "geometry": {"coordinates":[-102.690423,40.784696],"type":"Point"}
}