{
  "type": "Feature",
  "properties": {
    "addr:full":"242 Blackstock Dr Crested Butte CO 81224",
    "addr:housenumber":"242",
    "addr:postcode":"81224",
    "addr:street":"Blackstock Dr",
    "iso:country":"US",
    "sg:address":"242 Blackstock Dr",
    "sg:city":"Crested Butte",
    "sg:classifiers":[
        {
            "category":"Building & Trades",
            "subcategory":"Construction",
            "type":"Services"
        }
    ],
    "sg:phone":"+1 970 349 7088",
    "sg:postcode":"81224",
    "sg:province":"CO",
    "sg:tags":[
        "contractor"
    ],
    "wof:name":"M B Builders",
    "wof:placetype":"venue"
},
  "geometry": {"coordinates":[-106.885758,38.81581],"type":"Point"}
}