{
  "type": "Feature",
  "properties": {
    "addr:full":"3940 S Teller St Denver CO 80235",
    "addr:housenumber":"3940",
    "addr:postcode":"80235",
    "addr:street":"S Teller St",
    "iso:country":"US",
    "sg:address":"3940 S Teller St",
    "sg:city":"Denver",
    "sg:classifiers":[
        {
            "category":"Professional",
            "subcategory":"Business Services",
            "type":"Services"
        }
    ],
    "sg:phone":"+1 303 716 6939",
    "sg:postcode":"80235",
    "sg:province":"CO",
    "wof:name":"Viad Corp",
    "wof:placetype":"venue"
},
  "geometry": {"coordinates":[-105.076911,39.64723],"type":"Point"}
}