{
  "type": "Feature",
  "properties": {
    "iso:country":"US",
    "sg:address":"3356 S Glencoe St",
    "sg:city":"Denver",
    "sg:classifiers":[
        {
            "category":"Building & Trades",
            "subcategory":"Construction",
            "type":"Services"
        }
    ],
    "sg:phone":"+1 303 692 9110",
    "sg:postcode":"80222",
    "sg:province":"CO",
    "sg:tags":[
        "residential"
    ],
    "wof:name":"Johnson M&M Inc",
    "wof:placetype":"venue"
},
  "geometry": {"coordinates":[-104.926041,39.654002],"type":"Point"}
}