{
  "type": "Feature",
  "properties": {
    "iso:country":"US",
    "sg:address":"1107 S Lincoln Ave",
    "sg:city":"Steamboat Spgs",
    "sg:classifiers":[
        {
            "category":"Professional",
            "subcategory":"Accounting & Tax Preparation",
            "type":"Services"
        }
    ],
    "sg:phone":"+1 970 879 0282",
    "sg:postcode":"80487",
    "sg:province":"CO",
    "sg:tags":[
        "accountant"
    ],
    "wof:name":"Walsh Corr & Assoc",
    "wof:placetype":"venue"
},
  "geometry": {"coordinates":[-106.82642,40.469443],"type":"Point"}
}