{
  "type": "Feature",
  "properties": {
    "iso:country":"US",
    "sg:address":"1626 Market St Unit B",
    "sg:city":"Denver",
    "sg:classifiers":[
        {
            "category":"Manufacturing",
            "subcategory":"Glass & Minerals",
            "type":"Manufacturing & Wholesale Goods"
        },
        {
            "category":"Retail",
            "subcategory":"Auto Repair",
            "type":"Services"
        }
    ],
    "sg:phone":"+1 888 348 9678",
    "sg:postcode":"80202",
    "sg:province":"CO",
    "sg:tags":[
        "plate",
        "window",
        "windshield",
        "glass-auto",
        "replacement"
    ],
    "wof:name":"Zip Auto Glass & Windshield",
    "wof:placetype":"venue"
},
  "geometry": {"coordinates":[-104.997978,39.750131],"type":"Point"}
}