{
  "type": "Feature",
  "properties": {
    "iso:country":"US",
    "sg:address":"1035 S Monroe St",
    "sg:city":"Denver",
    "sg:classifiers":[
        {
            "category":"Real Estate",
            "subcategory":"Real Estate Agent",
            "type":"Services"
        }
    ],
    "sg:phone":"+1 303 722 0174",
    "sg:postcode":"80209",
    "sg:province":"CO",
    "wof:name":"Intercontinental Realty Inc",
    "wof:placetype":"venue"
},
  "geometry": {"coordinates":[-104.94544500000001,39.6972],"type":"Point"}
}