{
  "type": "Feature",
  "properties": {
    "iso:country":"US",
    "sg:address":"12893 W Roanoke Pl",
    "sg:city":"Morrison",
    "sg:classifiers":[
        {
            "category":"Building & Trades",
            "subcategory":"Plumbing",
            "type":"Services"
        }
    ],
    "sg:phone":"+1 720 981 3420",
    "sg:postcode":"80465",
    "sg:province":"CO",
    "sg:tags":[
        "heating",
        "contractor"
    ],
    "wof:name":"Evergreen Heating & Air Cond",
    "wof:placetype":"venue"
},
  "geometry": {"coordinates":[-105.14306500000001,39.635839],"type":"Point"}
}