{
  "type": "Feature",
  "properties": {
    "addr:full":"1241 Meadowlark Dr Boulder CO 80303",
    "addr:housenumber":"1241",
    "addr:postcode":"80303",
    "addr:street":"Meadowlark Dr",
    "iso:country":"US",
    "sg:address":"1241 Meadowlark Dr",
    "sg:city":"Boulder",
    "sg:classifiers":[
        {
            "category":"Real Estate",
            "subcategory":"Real Estate Agent",
            "type":"Services"
        }
    ],
    "sg:phone":"+1 303 499 6537",
    "sg:postcode":"80303",
    "sg:province":"CO",
    "wof:name":"Konecne Betty",
    "wof:placetype":"venue"
},
  "geometry": {"coordinates":[-105.197468,40.011229],"type":"Point"}
}