{
  "type": "Feature",
  "properties": {
    "addr:full":"2905 F Rd Grand Junction CO 81504",
    "addr:housenumber":"2905",
    "addr:postcode":"81504",
    "addr:street":"F Rd",
    "iso:country":"US",
    "sg:address":"2905 F Rd",
    "sg:city":"Grand Junction",
    "sg:classifiers":[
        {
            "category":"Shopping",
            "subcategory":"Gifts & Souvenirs",
            "type":"Retail Goods"
        }
    ],
    "sg:phone":"+1 970 242 2458",
    "sg:postcode":"81504",
    "sg:province":"CO",
    "sg:tags":[
        "shop"
    ],
    "wof:name":"Andrew's Hallmark",
    "wof:placetype":"venue"
},
  "geometry": {"coordinates":[-108.514577,39.091727],"type":"Point"}
}