{
  "type": "Feature",
  "properties": {
    "addr:full":"95 Huckleberry Ln Steamboat Spgs CO 80487",
    "addr:housenumber":"95",
    "addr:postcode":"80487",
    "addr:street":"Huckleberry Ln;Spgs",
    "iso:country":"US",
    "sg:address":"95 Huckleberry Ln",
    "sg:city":"Steamboat Spgs",
    "sg:classifiers":[
        {
            "category":"Wholesale",
            "subcategory":"Machinery & Supplies",
            "type":"Manufacturing & Wholesale Goods"
        }
    ],
    "sg:phone":"+1 970 879 7236",
    "sg:postcode":"80487",
    "sg:province":"CO",
    "sg:tags":[
        "equipment",
        "irrigation",
        "system"
    ],
    "wof:name":"Raindance Irrigation Systems",
    "wof:placetype":"venue"
},
  "geometry": {"coordinates":[-106.805385,40.482936],"type":"Point"}
}