{
  "type": "Feature",
  "properties": {
    "iso:country":"US",
    "sg:address":"7500 S Broadway",
    "sg:city":"Littleton",
    "sg:classifiers":[
        {
            "category":"Autos & Motor Vehicles",
            "subcategory":"Fuel & Gas Station",
            "type":"Retail Goods"
        }
    ],
    "sg:phone":"+1 303 730 0354",
    "sg:postcode":"80122",
    "sg:province":"CO",
    "sg:tags":[
        "grocery",
        "station",
        "gasoline"
    ],
    "wof:name":"Sinclair Merchant Oil",
    "wof:placetype":"venue"
},
  "geometry": {"coordinates":[-104.988432,39.580554],"type":"Point"}
}