{
  "type": "Feature",
  "properties": {
    "addr:full":"595 Nucla Way Aurora CO 80011",
    "addr:housenumber":"595",
    "addr:postcode":"80011",
    "addr:street":"Nucla Way",
    "iso:country":"US",
    "sg:address":"595 Nucla Way",
    "sg:city":"Aurora",
    "sg:classifiers":[
        {
            "category":"Manufacturing",
            "subcategory":"Signs",
            "type":"Manufacturing & Wholesale Goods"
        }
    ],
    "sg:phone":"+1 303 295 7779",
    "sg:postcode":"80011",
    "sg:province":"CO",
    "sg:tags":[
        "specialty",
        "mfg"
    ],
    "wof:name":"Lighted Signs Inc",
    "wof:placetype":"venue"
},
  "geometry": {"coordinates":[-104.793431,39.723781],"type":"Point"}
}