{
  "type": "Feature",
  "properties": {
    "iso:country":"US",
    "sg:address":"1226 E Monument St",
    "sg:city":"Colorado Springs",
    "sg:classifiers":[
        {
            "category":"Home & Garden",
            "subcategory":"Carpets & Floor Coverings",
            "type":"Retail Goods"
        }
    ],
    "sg:phone":"+1 719 632 4623",
    "sg:postcode":"80909",
    "sg:province":"CO",
    "sg:tags":[
        "dealer",
        "rug"
    ],
    "wof:name":"French & Co",
    "wof:placetype":"venue"
},
  "geometry": {"coordinates":[-104.80282200000001,38.843204],"type":"Point"}
}