{
  "type": "Feature",
  "properties": {
    "iso:country":"US",
    "sg:address":"486 Wyoming Cir",
    "sg:city":"Golden",
    "sg:classifiers":[
        {
            "category":"Building & Trades",
            "subcategory":"Construction",
            "type":"Services"
        }
    ],
    "sg:phone":"+1 303 278 4209",
    "sg:postcode":"80403",
    "sg:province":"CO",
    "sg:tags":[
        "house"
    ],
    "wof:name":"Shawn Gillis Construction",
    "wof:placetype":"venue"
},
  "geometry": {"coordinates":[-105.228995,39.779307],"type":"Point"}
}