{
  "type": "Feature",
  "properties": {
    "iso:country":"US",
    "sg:address":"547 E Cimarron St",
    "sg:city":"Colorado Springs",
    "sg:classifiers":[
        {
            "category":"Health Services",
            "subcategory":"Health Practitioner",
            "type":"Services"
        }
    ],
    "sg:phone":"+1 719 475 8044",
    "sg:postcode":"80903",
    "sg:province":"CO",
    "sg:tags":[
        "medicine",
        "alternative"
    ],
    "wof:name":"Nuvisions",
    "wof:placetype":"venue"
},
  "geometry": {"coordinates":[-104.81418600000001,38.826665],"type":"Point"}
}