{
  "type": "Feature",
  "properties": {
    "addr:full":"2617 E 3rd Ave Denver CO 80206",
    "addr:housenumber":"2617",
    "addr:postcode":"80206",
    "addr:street":"E 3Rd Ave",
    "iso:country":"US",
    "sg:address":"2617 E 3rd Ave",
    "sg:city":"Denver",
    "sg:classifiers":[
        {
            "category":"Health Services",
            "subcategory":"Dentist",
            "type":"Services"
        }
    ],
    "sg:phone":"+1 303 225 1015",
    "sg:postcode":"80206",
    "sg:province":"CO",
    "sg:tags":[
        "dentists-orthodontists"
    ],
    "sg:website":"http://www.clearchoices.com",
    "wof:name":"Clear Choice Orthodontics",
    "wof:placetype":"venue"
},
  "geometry": {"coordinates":[-104.95634200000001,39.720982],"type":"Point"}
}