{
  "type": "Feature",
  "properties": {
    "addr:full":"1640 S Broadway Denver CO 80210",
    "addr:housenumber":"1640",
    "addr:postcode":"80210",
    "addr:street":"S Broadway",
    "iso:country":"US",
    "sg:address":"1640 S Broadway",
    "sg:city":"Denver",
    "sg:classifiers":[
        {
            "category":"Retail",
            "subcategory":"Repair Shop",
            "type":"Services"
        }
    ],
    "sg:phone":"+1 303 778 1126",
    "sg:postcode":"80210",
    "sg:province":"CO",
    "sg:tags":[
        "equipment"
    ],
    "sg:website":"www.metroapplianceservice.com",
    "wof:name":"Metro Appliance Svc",
    "wof:placetype":"venue"
},
  "geometry": {"coordinates":[-104.98745099999999,39.686509],"type":"Point"}
}