{
  "type": "Feature",
  "properties": {
    "addr:full":"6720 Cramer Rd Alamosa CO 81101",
    "addr:housenumber":"6720",
    "addr:postcode":"81101",
    "addr:street":"Cramer Rd",
    "iso:country":"US",
    "sg:address":"6720 Cramer Rd",
    "sg:city":"Alamosa",
    "sg:classifiers":[
        {
            "category":"Freight",
            "type":"Transportation"
        }
    ],
    "sg:phone":"+1 719 589 5996",
    "sg:postcode":"81101",
    "sg:province":"CO",
    "sg:tags":[
        "warehouse",
        "self",
        "storage",
        "general"
    ],
    "wof:name":"U Loc It Security Self Storage",
    "wof:placetype":"venue"
},
  "geometry": {"coordinates":[-105.91202699999999,37.481909],"type":"Point"}
}