{
  "type": "Feature",
  "properties": {
    "iso:country":"US",
    "sg:address":"1860 S Chelton Rd",
    "sg:city":"Colorado Springs",
    "sg:classifiers":[
        {
            "category":"Education",
            "subcategory":"School",
            "type":"Public Place"
        }
    ],
    "sg:phone":"+1 719 579 2155",
    "sg:postcode":"80910",
    "sg:province":"CO",
    "wof:name":"Centennial Elementary School",
    "wof:placetype":"venue"
},
  "geometry": {"coordinates":[-104.762084,38.80617],"type":"Point"}
}