{
  "type": "Feature",
  "properties": {
    "addr:full":"1552 Fillmore St Sterling CO 80751",
    "addr:housenumber":"1552",
    "addr:postcode":"80751",
    "addr:street":"Fillmore St",
    "iso:country":"US",
    "sg:address":"1552 Fillmore St",
    "sg:city":"Sterling",
    "sg:classifiers":[
        {
            "category":"Professional",
            "subcategory":"Management & Consulting",
            "type":"Services"
        }
    ],
    "sg:phone":"+1 970 522 1442",
    "sg:postcode":"80751",
    "sg:province":"CO",
    "sg:tags":[
        "battery",
        "to",
        "train",
        "dealership",
        "recondition"
    ],
    "wof:name":"W W",
    "wof:placetype":"venue"
},
  "geometry": {"coordinates":[-103.20885800000001,40.644189],"type":"Point"}
}