{
  "type": "Feature",
  "properties": {
    "addr:full":"730 S Tejon St Colorado Springs CO 80903",
    "addr:housenumber":"730",
    "addr:postcode":"80903",
    "addr:street":"S Tejon St",
    "iso:country":"US",
    "sg:address":"730 S Tejon St",
    "sg:city":"Colorado Springs",
    "sg:classifiers":[
        {
            "category":"Shopping",
            "type":"Retail Goods"
        }
    ],
    "sg:phone":"+1 719 630 3371",
    "sg:postcode":"80903",
    "sg:province":"CO",
    "sg:tags":[
        "art",
        "gallery",
        "dealer"
    ],
    "wof:name":"Orly's Art Gallery & Framing",
    "wof:placetype":"venue"
},
  "geometry": {"coordinates":[-104.824136,38.823522],"type":"Point"}
}