{
  "type": "Feature",
  "properties": {
    "addr:full":"315 S Bowen St Longmont CO 80501",
    "addr:housenumber":"315",
    "addr:postcode":"80501",
    "addr:street":"S Bowen St",
    "iso:country":"US",
    "sg:address":"315 S Bowen St",
    "sg:city":"Longmont",
    "sg:classifiers":[
        {
            "category":"Organizations",
            "subcategory":"Community Association",
            "type":"Services"
        }
    ],
    "sg:phone":"+1 303 776 2034",
    "sg:postcode":"80501",
    "sg:province":"CO",
    "sg:tags":[
        "military"
    ],
    "wof:name":"American Legion",
    "wof:placetype":"venue"
},
  "geometry": {"coordinates":[-105.111998,40.15525],"type":"Point"}
}