{
  "type": "Feature",
  "properties": {
    "iso:country":"US",
    "sg:address":"2810 Wilderness Pl",
    "sg:city":"Boulder",
    "sg:classifiers":[
        {
            "category":"Communications",
            "subcategory":"Film & Video Production",
            "type":"Services"
        }
    ],
    "sg:phone":"+1 303 443 9039",
    "sg:postcode":"80301",
    "sg:province":"CO",
    "sg:tags":[
        "audio"
    ],
    "wof:name":"Alarion Press",
    "wof:placetype":"venue"
},
  "geometry": {"coordinates":[-105.248762,40.025885],"type":"Point"}
}