{
  "type": "Feature",
  "properties": {
    "iso:country":"US",
    "sg:address":"26 W Kiowa St",
    "sg:city":"Colorado Springs",
    "sg:classifiers":[
        {
            "category":"Restaurant",
            "type":"Food & Drink"
        }
    ],
    "sg:menulink":"http://www.allmenus.com/co/colorado-springs/36275-bistro-de-pinto/menu/",
    "sg:phone":"+1 719 473 3538",
    "sg:postcode":"80903",
    "sg:province":"CO",
    "sg:tags":[
        "american"
    ],
    "wof:name":"Bistro de Pinto",
    "wof:placetype":"venue"
},
  "geometry": {"coordinates":[-104.826014,38.835731],"type":"Point"}
}