{
  "type": "Feature",
  "properties": {
    "addr:full":"1410 S Valentine Way Lakewood CO 80228",
    "addr:housenumber":"1410",
    "addr:postcode":"80228",
    "addr:street":"S Valentine Way",
    "iso:country":"US",
    "sg:address":"1410 S Valentine Way",
    "sg:city":"Lakewood",
    "sg:classifiers":[
        {
            "category":"Professional",
            "subcategory":"Computer Services",
            "type":"Services"
        }
    ],
    "sg:phone":"+1 303 985 9460",
    "sg:postcode":"80228",
    "sg:province":"CO",
    "sg:tags":[
        "publisher",
        "developer",
        "software"
    ],
    "wof:name":"Sommers Computer Consulting Service",
    "wof:placetype":"venue"
},
  "geometry": {"coordinates":[-105.133258,39.690708],"type":"Point"}
}