{
  "type": "Feature",
  "properties": {
    "iso:country":"US",
    "sg:address":"149 Lakeview Cir W",
    "sg:city":"Breckenridge",
    "sg:classifiers":[
        {
            "category":"Home & Garden",
            "subcategory":"Mobile Homes",
            "type":"Retail Goods"
        }
    ],
    "sg:phone":"+1 970 453 1432",
    "sg:postcode":"80424",
    "sg:province":"CO",
    "wof:name":"Mountain Sky Cstm Prbilt Homes",
    "wof:placetype":"venue"
},
  "geometry": {"coordinates":[-106.052463,39.558144],"type":"Point"}
}