{
  "type": "Feature",
  "properties": {
    "addr:full":"4200 E 9th Ave Denver CO 80220",
    "addr:housenumber":"4200",
    "addr:postcode":"80220",
    "addr:street":"E 9Th Ave",
    "iso:country":"US",
    "sg:address":"4200 E 9th Ave",
    "sg:city":"Denver",
    "sg:classifiers":[
        {
            "category":"Health Services",
            "subcategory":"Doctor",
            "type":"Services"
        },
        {
            "category":"Professional",
            "subcategory":"Lawyer & Legal Services",
            "type":"Services"
        },
        {
            "category":"Health Services",
            "subcategory":"Chiropractor",
            "type":"Services"
        }
    ],
    "sg:phone":"+1 303 493 8333",
    "sg:postcode":"80220",
    "sg:province":"CO",
    "wof:name":"Michael Manco-Johnson MD",
    "wof:placetype":"venue"
},
  "geometry": {"coordinates":[-104.93788499999999,39.730107],"type":"Point"}
}