{
  "type": "Feature",
  "properties": {
    "iso:country":"US",
    "sg:address":"4200 E 9th Ave",
    "sg:city":"Denver",
    "sg:classifiers":[
        {
            "category":"Health Services",
            "subcategory":"Doctor",
            "type":"Services"
        },
        {
            "category":"Professional",
            "subcategory":"Lawyer & Legal Services",
            "type":"Services"
        },
        {
            "category":"Health Services",
            "subcategory":"Chiropractor",
            "type":"Services"
        }
    ],
    "sg:phone":"+1 303 493 8333",
    "sg:postcode":"80220",
    "sg:province":"CO",
    "wof:name":"Michael Manco-Johnson MD",
    "wof:placetype":"venue"
},
  "geometry": {"coordinates":[-104.937885,39.730107],"type":"Point"}
}