{
  "type": "Feature",
  "properties": {
    "addr:full":"17655 E 25th Dr Aurora CO 80011",
    "addr:housenumber":"17655",
    "addr:postcode":"80011",
    "addr:street":"E 25Th Dr",
    "iso:country":"US",
    "sg:address":"17655 E 25th Dr",
    "sg:city":"Aurora",
    "sg:classifiers":[
        {
            "category":"Home & Garden",
            "subcategory":"Household Appliances",
            "type":"Retail Goods"
        },
        {
            "category":"Home & Garden",
            "subcategory":"Home Furnishings",
            "type":"Retail Goods"
        },
        {
            "category":"Wholesale",
            "subcategory":"Construction Materials",
            "type":"Manufacturing & Wholesale Goods"
        },
        {
            "category":"Wholesale",
            "subcategory":"Home Furnishings",
            "type":"Manufacturing & Wholesale Goods"
        }
    ],
    "sg:phone":"+1 303 739 8000",
    "sg:postcode":"80011",
    "sg:province":"CO",
    "sg:tags":[
        "major",
        "supply",
        "fixture",
        "part",
        "lighting",
        "plumbing",
        "fixtures",
        "supplies-wholesale",
        "manufacturer"
    ],
    "sg:website":"http://www.ferguson.com/homeowner.shtml",
    "wof:name":"Ferguson Bath, Kitchen & Lighting Gallery",
    "wof:placetype":"venue"
},
  "geometry": {"coordinates":[-104.781614,39.753542],"type":"Point"}
}