{
  "type": "Feature",
  "properties": {
    "iso:country":"US",
    "sg:address":"915 Grand Ave",
    "sg:city":"Grand Lake",
    "sg:classifiers":[
        {
            "category":"Manufacturing",
            "subcategory":"Food",
            "type":"Manufacturing & Wholesale Goods"
        }
    ],
    "sg:phone":"+1 970 627 1711",
    "sg:postcode":"80447",
    "sg:province":"CO",
    "sg:tags":[
        "brewer"
    ],
    "wof:name":"Grand Lake Brewing Co",
    "wof:placetype":"venue"
},
  "geometry": {"coordinates":[-105.821147,40.251996],"type":"Point"}
}