{
  "type": "Feature",
  "properties": {
    "addr:full":"3318 Red Tail Way Evans CO 80620",
    "addr:housenumber":"3318",
    "addr:postcode":"80620",
    "addr:street":"Red Tail Way",
    "iso:country":"US",
    "sg:address":"3318 Red Tail Way",
    "sg:city":"Evans",
    "sg:classifiers":[
        {
            "category":"Professional",
            "type":"Services"
        }
    ],
    "sg:phone":"+1 970 506 9668",
    "sg:postcode":"80620",
    "sg:province":"CO",
    "wof:name":"Chris Packer",
    "wof:placetype":"venue"
},
  "geometry": {"coordinates":[-104.731584,40.373803],"type":"Point"}
}