{
  "type": "Feature",
  "properties": {
    "iso:country":"US",
    "sg:address":"145 S Garland St",
    "sg:city":"Denver",
    "sg:classifiers":[
        {
            "category":"Wholesale",
            "subcategory":"Medical Equipment & Supplies",
            "type":"Manufacturing & Wholesale Goods"
        }
    ],
    "sg:phone":"+1 303 237 5336",
    "sg:postcode":"80226",
    "sg:province":"CO",
    "wof:name":"Carson Dnels Otptent Sell Rent",
    "wof:placetype":"venue"
},
  "geometry": {"coordinates":[-105.10168299999999,39.714064],"type":"Point"}
}