{
  "type": "Feature",
  "properties": {
    "addr:full":"306 N 16th St Canon City CO 81212",
    "addr:housenumber":"306",
    "addr:postcode":"81212",
    "addr:street":"N 16Th St",
    "iso:country":"US",
    "sg:address":"306 N 16th St",
    "sg:city":"Canon City",
    "sg:classifiers":[
        {
            "category":"Manufacturing",
            "subcategory":"Tools & Machinery",
            "type":"Manufacturing & Wholesale Goods"
        }
    ],
    "sg:phone":"+1 719 784 3609",
    "sg:postcode":"81212",
    "sg:province":"CO",
    "sg:tags":[
        "photographic",
        "mfg"
    ],
    "wof:name":"Film In A Flash LLC",
    "wof:placetype":"venue"
},
  "geometry": {"coordinates":[-105.225798,38.449513],"type":"Point"}
}