{
  "type": "Feature",
  "properties": {
    "addr:full":"7142 Grandview Ave Arvada CO 80002",
    "addr:housenumber":"7142",
    "addr:postcode":"80002",
    "addr:street":"Grandview Ave",
    "iso:country":"US",
    "sg:address":"7142 Grandview Ave",
    "sg:city":"Arvada",
    "sg:classifiers":[
        {
            "category":"Building & Trades",
            "subcategory":"Locksmith",
            "type":"Services"
        }
    ],
    "sg:phone":"+1 303 729 0636",
    "sg:postcode":"80002",
    "sg:province":"CO",
    "sg:tags":[
        "key"
    ],
    "wof:name":"A and A 24 7 Immediate Locksmith",
    "wof:placetype":"venue"
},
  "geometry": {"coordinates":[-105.076752,39.799686],"type":"Point"}
}