{
  "type": "Feature",
  "properties": {
    "iso:country":"US",
    "sg:address":"718 Main St",
    "sg:city":"Fort Morgan",
    "sg:classifiers":[
        {
            "category":"Health Services",
            "subcategory":"Health Practitioner",
            "type":"Services"
        }
    ],
    "sg:phone":"+1 970 867 1882",
    "sg:postcode":"80701",
    "sg:province":"CO",
    "sg:tags":[
        "occupational",
        "therapist"
    ],
    "wof:name":"Muscle Manager",
    "wof:placetype":"venue"
},
  "geometry": {"coordinates":[-103.801433,40.256489],"type":"Point"}
}