{
  "type": "Feature",
  "properties": {
    "addr:full":"1201 S 9th St Canon City CO 81212",
    "addr:housenumber":"1201",
    "addr:postcode":"81212",
    "addr:street":"S 9Th St",
    "iso:country":"US",
    "sg:address":"1201 S 9th St",
    "sg:city":"Canon City",
    "sg:classifiers":[
        {
            "category":"Shopping",
            "subcategory":"Florist",
            "type":"Retail Goods"
        }
    ],
    "sg:phone":"+1 719 275 0617",
    "sg:postcode":"81212",
    "sg:province":"CO",
    "sg:tags":[
        "shop",
        "gift"
    ],
    "wof:name":"Touch Of Love Florists",
    "wof:placetype":"venue"
},
  "geometry": {"coordinates":[-105.232005,38.431062],"type":"Point"}
}