{
  "type": "Feature",
  "properties": {
    "iso:country":"US",
    "sg:address":"28677 Buffalo Park Rd",
    "sg:city":"Evergreen",
    "sg:classifiers":[
        {
            "category":"Professional",
            "type":"Services"
        }
    ],
    "sg:phone":"+1 303 674 2803",
    "sg:postcode":"80439",
    "sg:province":"CO",
    "sg:tags":[
        "establishment"
    ],
    "wof:name":"James Carder & Assoc",
    "wof:placetype":"venue"
},
  "geometry": {"coordinates":[-105.325048,39.624729],"type":"Point"}
}