{
  "type": "Feature",
  "properties": {
    "addr:full":"6260 Wilson Rd Colorado Springs CO 80919",
    "addr:housenumber":"6260",
    "addr:postcode":"80919",
    "addr:street":"Wilson Rd",
    "iso:country":"US",
    "sg:address":"6260 Wilson Rd",
    "sg:city":"Colorado Springs",
    "sg:classifiers":[
        {
            "category":"Freight",
            "type":"Transportation"
        }
    ],
    "sg:phone":"+1 719 598 5409",
    "sg:postcode":"80919",
    "sg:province":"CO",
    "sg:tags":[
        "general"
    ],
    "wof:name":"Storage Mgt Sltions Consulting",
    "wof:placetype":"venue"
},
  "geometry": {"coordinates":[-104.882941,38.921994],"type":"Point"}
}