{
  "type": "Feature",
  "properties": {
    "iso:country":"US",
    "sg:address":"6565 S Cook Way",
    "sg:city":"Centennial",
    "sg:classifiers":[
        {
            "category":"Retail",
            "subcategory":"Laundry & Dry Cleaning",
            "type":"Services"
        }
    ],
    "sg:phone":"+1 303 455 1818",
    "sg:postcode":"80121",
    "sg:province":"CO",
    "sg:tags":[
        "cleaners",
        "rug",
        "carpet"
    ],
    "wof:name":"Aquamatic Complete Cleaning",
    "wof:placetype":"venue"
},
  "geometry": {"coordinates":[-104.94932300000001,39.597011],"type":"Point"}
}