{
  "type": "Feature",
  "properties": {
    "iso:country":"US",
    "sg:address":"221 S Colorado Ave",
    "sg:city":"Haxtun",
    "sg:classifiers":[
        {
            "category":"Professional",
            "subcategory":"Business Services",
            "type":"Services"
        }
    ],
    "sg:phone":"+1 970 774 4500",
    "sg:postcode":"80731",
    "sg:province":"CO",
    "sg:tags":[
        "auctioneer"
    ],
    "wof:name":"Knode Realty & Auction LLC",
    "wof:placetype":"venue"
},
  "geometry": {"coordinates":[-102.62863,40.641184],"type":"Point"}
}