{
  "type": "Feature",
  "properties": {
    "addr:full":"525 E Mississippi Ave Denver CO 80210",
    "addr:housenumber":"525",
    "addr:postcode":"80210",
    "addr:street":"E Mississippi Ave",
    "iso:country":"US",
    "sg:address":"525 E Mississippi Ave",
    "sg:city":"Denver",
    "sg:classifiers":[
        {
            "category":"Building & Trades",
            "subcategory":"Plumbing",
            "type":"Services"
        }
    ],
    "sg:phone":"+1 303 777 7151",
    "sg:postcode":"80210",
    "sg:province":"CO",
    "sg:tags":[
        "mechanical",
        "contractor"
    ],
    "wof:name":"Colorado Piping & Mechanical",
    "wof:placetype":"venue"
},
  "geometry": {"coordinates":[-104.980638,39.696697],"type":"Point"}
}