{
  "type": "Feature",
  "properties": {
    "addr:full":"615 S Weber St Colorado Springs CO 80903",
    "addr:housenumber":"615",
    "addr:postcode":"80903",
    "addr:street":"S Weber St",
    "iso:country":"US",
    "sg:address":"615 S Weber St",
    "sg:city":"Colorado Springs",
    "sg:classifiers":[
        {
            "category":"Professional",
            "subcategory":"Lawyer & Legal Services",
            "type":"Services"
        }
    ],
    "sg:phone":"+1 719 475 9994",
    "sg:postcode":"80903",
    "sg:province":"CO",
    "sg:tags":[
        "attorney"
    ],
    "wof:name":"Mary Kay Kramer Attorney",
    "wof:placetype":"venue"
},
  "geometry": {"coordinates":[-104.820243,38.824592],"type":"Point"}
}