{
  "type": "Feature",
  "properties": {
    "iso:country":"US",
    "sg:address":"6100 S Devinney Way",
    "sg:city":"Littleton",
    "sg:classifiers":[
        {
            "category":"Organizations",
            "subcategory":"Religious Organization",
            "type":"Services"
        }
    ],
    "sg:phone":"+1 303 904 4322",
    "sg:postcode":"80127",
    "sg:province":"CO",
    "sg:tags":[
        "church"
    ],
    "sg:website":"www.4fbc.org",
    "wof:name":"Foothills Bible Church",
    "wof:placetype":"venue"
},
  "geometry": {"coordinates":[-105.155219,39.607945],"type":"Point"}
}