{
  "type": "Feature",
  "properties": {
    "addr:full":"6253 W 28th St Greeley CO 80634",
    "addr:housenumber":"6253",
    "addr:postcode":"80634",
    "addr:street":"W 28Th St",
    "iso:country":"US",
    "sg:address":"6253 W 28th St",
    "sg:city":"Greeley",
    "sg:classifiers":[
        {
            "category":"Organizations",
            "subcategory":"Religious Organization",
            "type":"Services"
        }
    ],
    "sg:phone":"+1 970 330 1830",
    "sg:postcode":"80634",
    "sg:province":"CO",
    "sg:tags":[
        "church"
    ],
    "sg:website":"www.mountainviewchurchgreeley.org",
    "wof:name":"Mountain View Evangelical Chr",
    "wof:placetype":"venue"
},
  "geometry": {"coordinates":[-104.78119700000001,40.392544],"type":"Point"}
}