{
  "type": "Feature",
  "properties": {
    "iso:country":"US",
    "sg:address":"800 Tracey Pkwy",
    "sg:city":"Fort Collins",
    "sg:classifiers":[
        {
            "category":"Building & Trades",
            "subcategory":"Construction",
            "type":"Services"
        }
    ],
    "sg:phone":"+1 970 215 7010",
    "sg:postcode":"80524",
    "sg:province":"CO",
    "sg:tags":[
        "house"
    ],
    "wof:name":"Krehbiel Construction",
    "wof:placetype":"venue"
},
  "geometry": {"coordinates":[-105.02686300000001,40.577628],"type":"Point"}
}