{
  "type": "Feature",
  "properties": {
    "addr:full":"498 S Church St Bayfield CO 81122",
    "addr:housenumber":"498",
    "addr:postcode":"81122",
    "addr:street":"S Church St",
    "iso:country":"US",
    "sg:address":"498 S Church St",
    "sg:city":"Bayfield",
    "sg:classifiers":[
        {
            "category":"Shopping",
            "subcategory":"Pharmacy",
            "type":"Retail Goods"
        }
    ],
    "sg:phone":"+1 970 884 9133",
    "sg:postcode":"81122",
    "sg:province":"CO",
    "wof:name":"Mill Street Drug Store",
    "wof:placetype":"venue"
},
  "geometry": {"coordinates":[-107.599273,37.22587],"type":"Point"}
}