{
  "type": "Feature",
  "properties": {
    "iso:country":"US",
    "sg:address":"1326 7th Ave",
    "sg:city":"Greeley",
    "sg:classifiers":[
        {
            "category":"Organizations",
            "subcategory":"Religious Organization",
            "type":"Services"
        }
    ],
    "sg:phone":"+1 970 352 9268",
    "sg:postcode":"80631",
    "sg:province":"CO",
    "sg:tags":[
        "church"
    ],
    "wof:name":"Templo Evangelico Ministries",
    "wof:placetype":"venue"
},
  "geometry": {"coordinates":[-104.689014,40.417387],"type":"Point"}
}