{
  "type": "Feature",
  "properties": {
    "iso:country":"US",
    "sg:address":"620 Elkton Dr",
    "sg:city":"Colorado Springs",
    "sg:classifiers":[
        {
            "category":"Building & Trades",
            "subcategory":"Plumbing",
            "type":"Services"
        }
    ],
    "sg:phone":"+1 719 268 0446",
    "sg:postcode":"80907",
    "sg:province":"CO",
    "sg:tags":[
        "fire",
        "protection",
        "contractor"
    ],
    "wof:name":"Fire Systems West Inc",
    "wof:placetype":"venue"
},
  "geometry": {"coordinates":[-104.836102,38.900786],"type":"Point"}
}