{
  "type": "Feature",
  "properties": {
    "addr:full":"18541 E Hampden Ave Aurora CO 80013",
    "addr:housenumber":"18541",
    "addr:postcode":"80013",
    "addr:street":"E Hampden Ave",
    "iso:country":"US",
    "sg:address":"18541 E Hampden Ave",
    "sg:city":"Aurora",
    "sg:phone":"+1 303 400 6117",
    "sg:postcode":"80013",
    "sg:province":"CO",
    "sg:website":"http://honeybeeasianbistro.com",
    "wof:name":"Honeybee Asian Bistro",
    "wof:placetype":"venue"
},
  "geometry": {"coordinates":[-104.77192100000001,39.653114],"type":"Point"}
}