{
  "type": "Feature",
  "properties": {
    "addr:full":"4390 Stone Post Dr Castle Rock CO 80108",
    "addr:housenumber":"4390",
    "addr:postcode":"80108",
    "addr:street":"Stone Post Dr",
    "iso:country":"US",
    "sg:address":"4390 Stone Post Dr",
    "sg:city":"Castle Rock",
    "sg:classifiers":[
        {
            "category":"Real Estate",
            "subcategory":"Real Estate Agent",
            "type":"Services"
        }
    ],
    "sg:phone":"+1 303 918 8886",
    "sg:postcode":"80108",
    "sg:province":"CO",
    "sg:tags":[
        "property",
        "management"
    ],
    "wof:name":"Highpoint I Investments LLC",
    "wof:placetype":"venue"
},
  "geometry": {"coordinates":[-104.80714,39.397558],"type":"Point"}
}