{
  "type": "Feature",
  "properties": {
    "iso:country":"US",
    "sg:address":"1161 S Raleigh St",
    "sg:city":"Denver",
    "sg:classifiers":[
        {
            "category":"Building & Trades",
            "subcategory":"Construction",
            "type":"Services"
        }
    ],
    "sg:phone":"+1 303 935 5861",
    "sg:postcode":"80219",
    "sg:province":"CO",
    "sg:tags":[
        "floor",
        "laying",
        "contractor"
    ],
    "wof:name":"Bb Flooring",
    "wof:placetype":"venue"
},
  "geometry": {"coordinates":[-105.042637,39.696063],"type":"Point"}
}