{
  "type": "Feature",
  "properties": {
    "iso:country":"US",
    "sg:address":"7119 Estes Dr",
    "sg:city":"Arvada",
    "sg:classifiers":[
        {
            "category":"Building & Trades",
            "subcategory":"Construction",
            "type":"Services"
        }
    ],
    "sg:phone":"+1 303 431 5542",
    "sg:postcode":"80004",
    "sg:province":"CO",
    "sg:tags":[
        "house"
    ],
    "wof:name":"Terry L Bond",
    "wof:placetype":"venue"
},
  "geometry": {"coordinates":[-105.09438400000001,39.825851],"type":"Point"}
}