{
  "type": "Feature",
  "properties": {
    "addr:full":"2025 Broadway St Boulder CO 80302",
    "addr:housenumber":"2025",
    "addr:postcode":"80302",
    "addr:street":"Broadway St",
    "iso:country":"US",
    "sg:address":"2025 Broadway St",
    "sg:city":"Boulder",
    "sg:classifiers":[
        {
            "category":"Shopping",
            "subcategory":"Clothing, Apparel, & Fashions",
            "type":"Retail Goods"
        }
    ],
    "sg:phone":"+1 303 444 6776",
    "sg:postcode":"80302",
    "sg:province":"CO",
    "wof:name":"Knit Wit",
    "wof:placetype":"venue"
},
  "geometry": {"coordinates":[-105.280331,40.018896],"type":"Point"}
}