{
  "type": "Feature",
  "properties": {
    "addr:full":"1290 S Colorado Blvd Denver CO 80246",
    "addr:housenumber":"1290",
    "addr:postcode":"80246",
    "addr:street":"S Colorado Blvd",
    "iso:country":"US",
    "sg:address":"1290 S Colorado Blvd",
    "sg:city":"Denver",
    "sg:classifiers":[
        {
            "category":"Retail",
            "subcategory":"Animal Services",
            "type":"Services"
        }
    ],
    "sg:phone":"+1 303 757 5646",
    "sg:postcode":"80246",
    "sg:province":"CO",
    "sg:tags":[
        "pet",
        "veterinary",
        "veterinarian",
        "boarding/pet",
        "sitting"
    ],
    "sg:website":"http://ad.doubleclick.net/clk;226007916;49913701;g?http://www.vcahospitals.com/main/offer?utm_source=iyp&utm_medium=iyp&utm_campaign=yellowpages",
    "wof:name":"Aspenwood Animal Hospital PC",
    "wof:placetype":"venue"
},
  "geometry": {"coordinates":[-104.941002,39.6931],"type":"Point"}
}