{
  "type": "Feature",
  "properties": {
    "addr:full":"110 W Harvard St Fort Collins CO 80525",
    "addr:housenumber":"110",
    "addr:postcode":"80525",
    "addr:street":"W Harvard St",
    "iso:country":"US",
    "sg:address":"110 W Harvard St",
    "sg:city":"Fort Collins",
    "sg:classifiers":[
        {
            "category":"Organizations",
            "subcategory":"Professional Association",
            "type":"Services"
        }
    ],
    "sg:phone":"+1 970 223 2900",
    "sg:postcode":"80525",
    "sg:province":"CO",
    "sg:tags":[
        "business",
        "real estate"
    ],
    "wof:name":"Fort Collins Board Of Realtors",
    "wof:placetype":"venue"
},
  "geometry": {"coordinates":[-105.07719400000001,40.548969],"type":"Point"}
}