{
  "type": "Feature",
  "properties": {
    "iso:country":"US",
    "sg:address":"13228 State Hwy 12",
    "sg:city":"La Veta",
    "sg:classifiers":[
        {
            "category":"Building & Trades",
            "subcategory":"Construction",
            "type":"Services"
        }
    ],
    "sg:phone":"+1 719 742 3200",
    "sg:postcode":"81055",
    "sg:province":"CO",
    "sg:tags":[
        "general",
        "contractor"
    ],
    "wof:name":"Bright & Early Constr & Tree",
    "wof:placetype":"venue"
},
  "geometry": {"coordinates":[-105.070778,37.411001],"type":"Point"}
}