{
  "type": "Feature",
  "properties": {
    "iso:country":"US",
    "sg:address":"13203 Maxwell Pl",
    "sg:city":"Denver",
    "sg:classifiers":[
        {
            "category":"Freight",
            "type":"Transportation"
        }
    ],
    "sg:phone":"+1 303 373 2843",
    "sg:postcode":"80239",
    "sg:province":"CO",
    "wof:name":"Dp Storage & Moving",
    "wof:placetype":"venue"
},
  "geometry": {"coordinates":[-104.834045,39.794927],"type":"Point"}
}