{
  "type": "Feature",
  "properties": {
    "addr:full":"4821 US Hwy 84 Pagosa Springs CO 81147",
    "addr:housenumber":"4821",
    "addr:postcode":"81147",
    "addr:street":"Us Hwy 84",
    "iso:country":"US",
    "sg:address":"4821 US Hwy 84",
    "sg:city":"Pagosa Springs",
    "sg:classifiers":[
        {
            "category":"Shopping",
            "subcategory":"Bicycles & Sporting Goods",
            "type":"Retail Goods"
        }
    ],
    "sg:phone":"+1 970 264 5546",
    "sg:postcode":"81147",
    "sg:province":"CO",
    "sg:tags":[
        "outfitter"
    ],
    "sg:website":"www.lobooutfitters.com",
    "wof:name":"Lobo Outfitters",
    "wof:placetype":"venue"
},
  "geometry": {"coordinates":[-106.978959,37.209471],"type":"Point"}
}