{
  "type": "Feature",
  "properties": {
    "iso:country":"US",
    "sg:address":"590 W Kenosha Dr",
    "sg:city":"Pueblo",
    "sg:classifiers":[
        {
            "category":"Professional",
            "type":"Services"
        }
    ],
    "sg:phone":"+1 719 547 0274",
    "sg:postcode":"81007",
    "sg:province":"CO",
    "wof:name":"Samuel & Mercedes Martinez",
    "wof:placetype":"venue"
},
  "geometry": {"coordinates":[-104.767624,38.303849],"type":"Point"}
}