{
  "type": "Feature",
  "properties": {
    "addr:full":"2027 Hillcrest Dr Rock Springs CO 82901",
    "addr:housenumber":"2027",
    "addr:postcode":"82901",
    "addr:street":"Hillcrest Dr",
    "iso:country":"US",
    "sg:address":"2027 Hillcrest Dr",
    "sg:city":"Rock Springs",
    "sg:classifiers":[
        {
            "category":"Restaurant",
            "type":"Food & Drink"
        }
    ],
    "sg:phone":"+1 307 382 8840",
    "sg:postcode":"82901",
    "sg:province":"CO",
    "sg:tags":[
        "eating"
    ],
    "wof:name":"Cherry Pie LLC",
    "wof:placetype":"venue"
},
  "geometry": {"coordinates":[-109.19777999999999,41.58418],"type":"Point"}
}