{
  "type": "Feature",
  "properties": {
    "addr:full":"5569 N Co Rd 29 Loveland CO 80538",
    "addr:housenumber":"5569;29",
    "addr:postcode":"80538",
    "addr:street":"N Co Rd",
    "iso:country":"US",
    "sg:address":"5569 N Co Rd 29",
    "sg:city":"Loveland",
    "sg:classifiers":[
        {
            "category":"Professional",
            "type":"Services"
        }
    ],
    "sg:phone":"+1 970 679 4294",
    "sg:postcode":"80538",
    "sg:province":"CO",
    "sg:tags":[
        "establishment"
    ],
    "wof:name":"Educo",
    "wof:placetype":"venue"
},
  "geometry": {"coordinates":[-105.21895000000001,40.449039],"type":"Point"}
}