{
  "type": "Feature",
  "properties": {
    "iso:country":"US",
    "sg:address":"2110 Market St",
    "sg:city":"Denver",
    "sg:classifiers":[
        {
            "category":"Shopping",
            "type":"Retail Goods"
        }
    ],
    "sg:phone":"+1 303 292 3281",
    "sg:postcode":"80202",
    "sg:province":"CO",
    "sg:tags":[
        "art",
        "gallery",
        "dealer"
    ],
    "wof:name":"Andenken Gallery & Design",
    "wof:placetype":"venue"
},
  "geometry": {"coordinates":[-104.991086,39.755342],"type":"Point"}
}