{
  "type": "Feature",
  "properties": {
    "addr:full":"20662 Tulip Cir Montrose CO 81401",
    "addr:housenumber":"20662",
    "addr:postcode":"81401",
    "addr:street":"Tulip Cir",
    "iso:country":"US",
    "sg:address":"20662 Tulip Cir",
    "sg:city":"Montrose",
    "sg:classifiers":[
        {
            "category":"Professional",
            "subcategory":"Management & Consulting",
            "type":"Services"
        }
    ],
    "sg:phone":"+1 970 252 8107",
    "sg:postcode":"81401",
    "sg:province":"CO",
    "sg:tags":[
        "consultant",
        "business"
    ],
    "wof:name":"Dudley Harris Consultants",
    "wof:placetype":"venue"
},
  "geometry": {"coordinates":[-107.819543,38.382361],"type":"Point"}
}