{
  "type": "Feature",
  "properties": {
    "addr:full":"1250 S Hover St Longmont CO 80501",
    "addr:housenumber":"1250",
    "addr:postcode":"80501",
    "addr:street":"S Hover St",
    "iso:country":"US",
    "sg:address":"1250 S Hover St",
    "sg:city":"Longmont",
    "sg:classifiers":[
        {
            "category":"Restaurant",
            "type":"Food & Drink"
        }
    ],
    "sg:menulink":"http://www.allmenus.com/co/longmont/166468-burger-king/menu/",
    "sg:phone":"+1 303 772 2987",
    "sg:postcode":"80501",
    "sg:province":"CO",
    "sg:tags":[
        "burger",
        "american"
    ],
    "wof:name":"Burger King",
    "wof:placetype":"venue"
},
  "geometry": {"coordinates":[-105.128713,40.145424],"type":"Point"}
}