{
  "type": "Feature",
  "properties": {
    "addr:full":"928 Smith Ave Trinidad CO 81082",
    "addr:housenumber":"928",
    "addr:postcode":"81082",
    "addr:street":"Smith Ave",
    "iso:country":"US",
    "sg:address":"928 Smith Ave",
    "sg:city":"Trinidad",
    "sg:classifiers":[
        {
            "category":"Social Services",
            "subcategory":"Adult Care",
            "type":"Services"
        }
    ],
    "sg:phone":"+1 719 846 1645",
    "sg:postcode":"81082",
    "sg:province":"CO",
    "sg:tags":[
        "home",
        "residential"
    ],
    "wof:name":"Fisher's Peak Assisted Care",
    "wof:placetype":"venue"
},
  "geometry": {"coordinates":[-104.521883,37.167138],"type":"Point"}
}