{
  "type": "Feature",
  "properties": {
    "iso:country":"US",
    "sg:address":"6400 S Fiddlers Green Cir",
    "sg:city":"Englewood",
    "sg:classifiers":[
        {
            "category":"Professional",
            "subcategory":"Lawyer & Legal Services",
            "type":"Services"
        }
    ],
    "sg:phone":"+1 303 796 2626",
    "sg:postcode":"80111",
    "sg:province":"CO",
    "sg:tags":[
        "attorney",
        "law",
        "at"
    ],
    "wof:name":"Burns Figa & Will PC",
    "wof:placetype":"venue"
},
  "geometry": {"coordinates":[-104.89016700000001,39.60013],"type":"Point"}
}