{
  "type": "Feature",
  "properties": {
    "iso:country":"US",
    "sg:address":"3158 Larimer St",
    "sg:city":"Denver",
    "sg:classifiers":[
        {
            "category":"Restaurant",
            "type":"Food & Drink"
        }
    ],
    "sg:phone":"+1 303 295 1752",
    "sg:postcode":"80205",
    "sg:province":"CO",
    "wof:name":"LA Casa De Manual",
    "wof:placetype":"venue"
},
  "geometry": {"coordinates":[-104.978645,39.76355],"type":"Point"}
}