{
  "type": "Feature",
  "properties": {
    "iso:country":"US",
    "sg:address":"101 Briscoe Ln",
    "sg:city":"Castle Rock",
    "sg:classifiers":[
        {
            "category":"Personal",
            "type":"Services"
        }
    ],
    "sg:phone":"+1 303 814 3136",
    "sg:postcode":"80109",
    "sg:province":"CO",
    "sg:tags":[
        "consultant",
        "program",
        "health",
        "fitness"
    ],
    "wof:name":"Center-Family WELLNESS LLC",
    "wof:placetype":"venue"
},
  "geometry": {"coordinates":[-104.88108,39.345867],"type":"Point"}
}