{
  "type": "Feature",
  "properties": {
    "iso:country":"US",
    "sg:address":"556 S Elm St",
    "sg:city":"Denver",
    "sg:classifiers":[
        {
            "category":"Real Estate",
            "subcategory":"Real Estate Agent",
            "type":"Services"
        }
    ],
    "sg:phone":"+1 303 333 9489",
    "sg:postcode":"80246",
    "sg:province":"CO",
    "wof:name":"Exquisite Real Estatecom Inc",
    "wof:placetype":"venue"
},
  "geometry": {"coordinates":[-104.92965599999999,39.707332],"type":"Point"}
}