{
  "type": "Feature",
  "properties": {
    "iso:country":"US",
    "sg:address":"84 S Hwy 105",
    "sg:city":"Palmer Lake",
    "sg:classifiers":[
        {
            "category":"Food & Beverages",
            "subcategory":"Specialty",
            "type":"Retail Goods"
        }
    ],
    "sg:phone":"+1 719 488 2007",
    "sg:postcode":"80133",
    "sg:province":"CO",
    "wof:name":"Speedtrap Coffeebar",
    "wof:placetype":"venue"
},
  "geometry": {"coordinates":[-104.91522500000001,39.122075],"type":"Point"}
}