{
  "type": "Feature",
  "properties": {
    "iso:country":"US",
    "sg:address":"5475 Peoria St",
    "sg:city":"Denver",
    "sg:classifiers":[
        {
            "category":"Professional",
            "subcategory":"Advertising",
            "type":"Services"
        }
    ],
    "sg:phone":"+1 303 373 4291",
    "sg:postcode":"80239",
    "sg:province":"CO",
    "sg:website":"www.theprimeconcepts.com",
    "wof:name":"Prime Concepts Inc",
    "wof:placetype":"venue"
},
  "geometry": {"coordinates":[-104.847223,39.794742],"type":"Point"}
}