{
  "type": "Feature",
  "properties": {
    "addr:full":"9681 Adams St Denver CO 80229",
    "addr:housenumber":"9681",
    "addr:postcode":"80229",
    "addr:street":"Adams St",
    "iso:country":"US",
    "sg:address":"9681 Adams St",
    "sg:city":"Denver",
    "sg:classifiers":[
        {
            "category":"Shopping",
            "subcategory":"Hobbies, Toys, & Games",
            "type":"Retail Goods"
        }
    ],
    "sg:phone":"+1 720 872 3706",
    "sg:postcode":"80229",
    "sg:province":"CO",
    "wof:name":"Create A Basket",
    "wof:placetype":"venue"
},
  "geometry": {"coordinates":[-104.94855200000001,39.872778],"type":"Point"}
}