{
  "type": "Feature",
  "properties": {
    "iso:country":"US",
    "sg:address":"4900 Lowell Blvd",
    "sg:city":"Denver",
    "sg:classifiers":[
        {
            "category":"Food & Beverages",
            "subcategory":"Liquor & Beverages",
            "type":"Retail Goods"
        }
    ],
    "sg:phone":"+1 303 458 7401",
    "sg:postcode":"80221",
    "sg:province":"CO",
    "sg:tags":[
        "beer",
        "spirit",
        "wine"
    ],
    "wof:name":"Busby's Liquors",
    "wof:placetype":"venue"
},
  "geometry": {"coordinates":[-105.033997,39.785801],"type":"Point"}
}