{
  "type": "Feature",
  "properties": {
    "addr:full":"417 Monument Rd Grand Junction CO 81503",
    "addr:housenumber":"417",
    "addr:postcode":"81503",
    "addr:street":"Monument Rd",
    "iso:country":"US",
    "sg:address":"417 Monument Rd",
    "sg:city":"Grand Junction",
    "sg:classifiers":[
        {
            "category":"Manufacturing",
            "subcategory":"Printing",
            "type":"Manufacturing & Wholesale Goods"
        }
    ],
    "sg:phone":"+1 970 257 9781",
    "sg:postcode":"81503",
    "sg:province":"CO",
    "sg:tags":[
        "publishing"
    ],
    "wof:name":"Josies Java Express",
    "wof:placetype":"venue"
},
  "geometry": {"coordinates":[-108.58600199999999,39.065946],"type":"Point"}
}