{
  "type": "Feature",
  "properties": {
    "iso:country":"US",
    "sg:address":"325 Lashley St",
    "sg:city":"Longmont",
    "sg:classifiers":[
        {
            "category":"Professional",
            "type":"Services"
        }
    ],
    "sg:phone":"+1 303 772 6844",
    "sg:postcode":"80501",
    "sg:province":"CO",
    "wof:name":"Latortilleria Azteca Inc",
    "wof:placetype":"venue"
},
  "geometry": {"coordinates":[-105.088171,40.165163],"type":"Point"}
}