{
  "type": "Feature",
  "properties": {
    "addr:full":"2248 Vintage Dr Colorado Springs CO 80920",
    "addr:housenumber":"2248",
    "addr:postcode":"80920",
    "addr:street":"Vintage Dr",
    "iso:country":"US",
    "sg:address":"2248 Vintage Dr",
    "sg:city":"Colorado Springs",
    "sg:classifiers":[
        {
            "category":"Education",
            "subcategory":"School",
            "type":"Public Place"
        }
    ],
    "sg:phone":"+1 719 594 0797",
    "sg:postcode":"80920",
    "sg:province":"CO",
    "wof:name":"High Plains Elementary School",
    "wof:placetype":"venue"
},
  "geometry": {"coordinates":[-104.78353799999999,38.946525],"type":"Point"}
}