{
  "type": "Feature",
  "properties": {
    "addr:full":"927 W Ellsworth Ave Denver CO 80223",
    "addr:housenumber":"927",
    "addr:postcode":"80223",
    "addr:street":"W Ellsworth Ave",
    "iso:country":"US",
    "sg:address":"927 W Ellsworth Ave",
    "sg:city":"Denver",
    "sg:classifiers":[
        {
            "category":"Professional",
            "type":"Services"
        }
    ],
    "sg:phone":"+1 720 932 5449",
    "sg:postcode":"80223",
    "sg:province":"CO",
    "sg:tags":[
        "establishment"
    ],
    "wof:name":"Streamline Inc",
    "wof:placetype":"venue"
},
  "geometry": {"coordinates":[-104.99978,39.716663],"type":"Point"}
}