{
  "type": "Feature",
  "properties": {
    "iso:country":"US",
    "sg:address":"2831 W 23rd Ave",
    "sg:city":"Denver",
    "sg:classifiers":[
        {
            "category":"Building & Trades",
            "subcategory":"Landscaping Services",
            "type":"Services"
        }
    ],
    "sg:phone":"+1 303 583 6749",
    "sg:postcode":"80211",
    "sg:province":"CO",
    "sg:tags":[
        "landscape"
    ],
    "wof:name":"Sergios Landscaping",
    "wof:placetype":"venue"
},
  "geometry": {"coordinates":[-105.02318699999999,39.751279],"type":"Point"}
}