{
  "type": "Feature",
  "properties": {
    "iso:country":"US",
    "sg:address":"41605 Co Rd G",
    "sg:city":"Del Norte",
    "sg:classifiers":[
        {
            "category":"Autos & Motor Vehicles",
            "subcategory":"Fuel & Gas Station",
            "type":"Retail Goods"
        }
    ],
    "sg:phone":"+1 719 754 3755",
    "sg:postcode":"81132",
    "sg:province":"CO",
    "sg:tags":[
        "station",
        "gasoline"
    ],
    "wof:name":"Lagarita Trading Post",
    "wof:placetype":"venue"
},
  "geometry": {"coordinates":[-106.247342,37.839893],"type":"Point"}
}