{
  "type": "Feature",
  "properties": {
    "iso:country":"US",
    "sg:address":"4468 Barnes Rd",
    "sg:city":"Colorado Springs",
    "sg:classifiers":[
        {
            "category":"Wholesale",
            "subcategory":"Computers",
            "type":"Manufacturing & Wholesale Goods"
        }
    ],
    "sg:phone":"+1 719 638 9804",
    "sg:postcode":"80917",
    "sg:province":"CO",
    "sg:tags":[
        "equipment",
        "processing",
        "datum"
    ],
    "wof:name":"Storage Technology Corp",
    "wof:placetype":"venue"
},
  "geometry": {"coordinates":[-104.744207,38.897057],"type":"Point"}
}