{
  "type": "Feature",
  "properties": {
    "iso:country":"US",
    "sg:address":"3030 Frazier Ln",
    "sg:city":"Colorado Springs",
    "sg:classifiers":[
        {
            "category":"Arts & Performance",
            "subcategory":"Theater",
            "type":"Entertainment"
        }
    ],
    "sg:phone":"+1 719 233 7735",
    "sg:postcode":"80922",
    "sg:province":"CO",
    "sg:tags":[
        "live",
        "music"
    ],
    "wof:name":"Sensational Sounds Pro DJ Svc",
    "wof:placetype":"venue"
},
  "geometry": {"coordinates":[-104.70018399999999,38.87499],"type":"Point"}
}