{
  "type": "Feature",
  "properties": {
    "addr:full":"1899 S Irving Street Denver CO 80219",
    "addr:housenumber":"1899",
    "addr:postcode":"80219",
    "addr:street":"S Irving Street",
    "iso:country":"US",
    "sg:address":"1899 S Irving Street",
    "sg:city":"Denver",
    "sg:classifiers":[
        {
            "category":"Organizations",
            "subcategory":"Religious Organization",
            "type":"Services"
        }
    ],
    "sg:phone":"+1 303 936 3447",
    "sg:postcode":"80219",
    "sg:province":"CO",
    "sg:website":"www.umc.org",
    "wof:name":"Brentwood United Methodist Church",
    "wof:placetype":"venue"
},
  "geometry": {"coordinates":[-105.029641,39.682775],"type":"Point"}
}