{
  "type": "Feature",
  "properties": {
    "addr:full":"1751 S Juliana Ave Loveland CO 80537",
    "addr:housenumber":"1751",
    "addr:postcode":"80537",
    "addr:street":"S Juliana Ave",
    "iso:country":"US",
    "sg:address":"1751 S Juliana Ave",
    "sg:city":"Loveland",
    "sg:classifiers":[
        {
            "category":"Real Estate",
            "subcategory":"Real Estate Operator",
            "type":"Services"
        }
    ],
    "sg:phone":"+1 970 667 2928",
    "sg:postcode":"80537",
    "sg:province":"CO",
    "sg:tags":[
        "wheat",
        "lessor",
        "f",
        "farm",
        "corn",
        "cash",
        "grain",
        "property"
    ],
    "wof:name":"Stone Farm",
    "wof:placetype":"venue"
},
  "geometry": {"coordinates":[-105.107917,40.376599],"type":"Point"}
}