{
  "type": "Feature",
  "properties": {
    "addr:full":"8696 Streamcrest Dr Boulder CO 80302",
    "addr:housenumber":"8696",
    "addr:postcode":"80302",
    "addr:street":"Streamcrest Dr",
    "iso:country":"US",
    "sg:address":"8696 Streamcrest Dr",
    "sg:city":"Boulder",
    "sg:classifiers":[
        {
            "category":"Building & Trades",
            "subcategory":"Plumbing",
            "type":"Services"
        },
        {
            "category":"Home & Garden",
            "subcategory":"Garden Supply",
            "type":"Retail Goods"
        }
    ],
    "sg:phone":"+1 303 447 2025",
    "sg:postcode":"80302",
    "sg:province":"CO",
    "sg:tags":[
        "m",
        "sprinkler",
        "contractor"
    ],
    "wof:name":"Canyon Sprinkler Company",
    "wof:placetype":"venue"
},
  "geometry": {"coordinates":[-105.286908,40.132084],"type":"Point"}
}