{
  "type": "Feature",
  "properties": {
    "iso:country":"US",
    "sg:address":"5705 Corinth Dr",
    "sg:city":"Colorado Springs",
    "sg:classifiers":[
        {
            "category":"Organizations",
            "subcategory":"Non-profit Organization",
            "type":"Services"
        }
    ],
    "sg:phone":"+1 719 268 7124",
    "sg:postcode":"80918",
    "sg:province":"CO",
    "wof:name":"Colorado For Family Values",
    "wof:placetype":"venue"
},
  "geometry": {"coordinates":[-104.729843,38.918036],"type":"Point"}
}