{
  "type": "Feature",
  "properties": {
    "iso:country":"US",
    "sg:address":"303 Oak Ln",
    "sg:city":"Aspen",
    "sg:classifiers":[
        {
            "category":"Building & Trades",
            "subcategory":"Landscaping Services",
            "type":"Services"
        }
    ],
    "sg:phone":"+1 970 920 1389",
    "sg:postcode":"81611",
    "sg:province":"CO",
    "sg:tags":[
        "landscape",
        "contractor"
    ],
    "wof:name":"Thumbs Up Landscaping",
    "wof:placetype":"venue"
},
  "geometry": {"coordinates":[-106.812186,39.192867],"type":"Point"}
}