{
  "type": "Feature",
  "properties": {
    "iso:country":"US",
    "sg:address":"2120 W Alameda Avenue",
    "sg:city":"Denver",
    "sg:classifiers":[
        {
            "category":"Restaurant",
            "type":"Food & Drink"
        }
    ],
    "sg:phone":"+1 303 937 3883",
    "sg:postcode":"80223",
    "sg:province":"CO",
    "wof:name":"Rico Pollo # 5",
    "wof:placetype":"venue"
},
  "geometry": {"coordinates":[-105.01266,39.711313],"type":"Point"}
}