{
  "type": "Feature",
  "properties": {
    "addr:full":"143 W Main St Aguilar CO 81020",
    "addr:housenumber":"143",
    "addr:postcode":"81020",
    "addr:street":"W Main St",
    "iso:country":"US",
    "sg:address":"143 W Main St",
    "sg:city":"Aguilar",
    "sg:classifiers":[
        {
            "category":"Real Estate",
            "subcategory":"Real Estate Agent",
            "type":"Services"
        }
    ],
    "sg:phone":"+1 719 941 4013",
    "sg:postcode":"81020",
    "sg:province":"CO",
    "wof:name":"Colorado Homestead Properties",
    "wof:placetype":"venue"
},
  "geometry": {"coordinates":[-104.65690600000001,37.401303],"type":"Point"}
}