{
  "type": "Feature",
  "properties": {
    "iso:country":"US",
    "sg:address":"2800 N 9th St",
    "sg:city":"Canon City",
    "sg:classifiers":[
        {
            "category":"Retail",
            "subcategory":"Auto Repair",
            "type":"Services"
        }
    ],
    "sg:phone":"+1 719 275 1996",
    "sg:postcode":"81212",
    "sg:province":"CO",
    "sg:tags":[
        "repairing",
        "automobile"
    ],
    "wof:name":"Fred's Auto Repair & Svc",
    "wof:placetype":"venue"
},
  "geometry": {"coordinates":[-105.23874000000001,38.468509],"type":"Point"}
}