{
  "type": "Feature",
  "properties": {
    "addr:full":"3220 C Rd Grand Junction CO 81503",
    "addr:housenumber":"3220",
    "addr:postcode":"81503",
    "addr:street":"C Rd",
    "iso:country":"US",
    "sg:address":"3220 C Rd",
    "sg:city":"Grand Junction",
    "sg:classifiers":[
        {
            "category":"Building & Trades",
            "subcategory":"Construction",
            "type":"Services"
        }
    ],
    "sg:phone":"+1 970 261 4486",
    "sg:postcode":"81503",
    "sg:province":"CO",
    "sg:tags":[
        "general",
        "contractor"
    ],
    "wof:name":"Red Rock Construction-W Slope",
    "wof:placetype":"venue"
},
  "geometry": {"coordinates":[-108.459602,39.048503],"type":"Point"}
}