{
  "type": "Feature",
  "properties": {
    "addr:full":"5450 Parmalee Gulch Rd Indian Hills CO 80454",
    "addr:housenumber":"5450",
    "addr:postcode":"80454",
    "addr:street":"Parmalee Gulch Rd",
    "iso:country":"US",
    "sg:address":"5450 Parmalee Gulch Rd",
    "sg:city":"Indian Hills",
    "sg:classifiers":[
        {
            "category":"Restaurant",
            "type":"Food & Drink"
        }
    ],
    "sg:phone":"+1 303 697 4523",
    "sg:postcode":"80454",
    "sg:province":"CO",
    "wof:name":"Wildman's Cabin Bar & Grille",
    "wof:placetype":"venue"
},
  "geometry": {"coordinates":[-105.23857599999999,39.619912],"type":"Point"}
}