{
  "type": "Feature",
  "properties": {
    "iso:country":"US",
    "sg:address":"400 N Faver Dr",
    "sg:city":"Castle Rock",
    "sg:classifiers":[
        {
            "category":"Shopping",
            "subcategory":"Music",
            "type":"Retail Goods"
        }
    ],
    "sg:phone":"+1 303 688 9719",
    "sg:postcode":"80109",
    "sg:province":"CO",
    "sg:tags":[
        "prerecorded",
        "record",
        "tape",
        "store"
    ],
    "wof:name":"Movie Time",
    "wof:placetype":"venue"
},
  "geometry": {"coordinates":[-104.91636099999999,39.368271],"type":"Point"}
}