{
  "type": "Feature",
  "properties": {
    "addr:full":"827 Exmoor Cir Craig CO 81625",
    "addr:housenumber":"827",
    "addr:postcode":"81625",
    "addr:street":"Exmoor Cir",
    "iso:country":"US",
    "sg:address":"827 Exmoor Cir",
    "sg:city":"Craig",
    "sg:classifiers":[
        {
            "category":"Freight",
            "type":"Transportation"
        }
    ],
    "sg:phone":"+1 970 824 7781",
    "sg:postcode":"81625",
    "sg:province":"CO",
    "sg:tags":[
        "operator",
        "trucking"
    ],
    "wof:name":"Hatten Ent",
    "wof:placetype":"venue"
},
  "geometry": {"coordinates":[-107.59202000000001,40.519],"type":"Point"}
}