{
  "type": "Feature",
  "properties": {
    "iso:country":"US",
    "sg:address":"4500 E 9th Ave",
    "sg:city":"Denver",
    "sg:classifiers":[
        {
            "category":"Health Services",
            "subcategory":"Clinic",
            "type":"Services"
        }
    ],
    "sg:phone":"+1 303 595 4100",
    "sg:postcode":"80220",
    "sg:province":"CO",
    "sg:tags":[
        "information",
        "abortion"
    ],
    "wof:name":"Fertility & Family Planning",
    "wof:placetype":"venue"
},
  "geometry": {"coordinates":[-104.93397299999999,39.731064],"type":"Point"}
}