{
  "type": "Feature",
  "properties": {
    "iso:country":"US",
    "sg:address":"7091 Co Rd 228",
    "sg:city":"Bayfield",
    "sg:classifiers":[
        {
            "category":"Professional",
            "type":"Services"
        }
    ],
    "sg:phone":"+1 970 382 0693",
    "sg:postcode":"81122",
    "sg:province":"CO",
    "wof:name":"Eggebraten Family Ltd Partnr",
    "wof:placetype":"venue"
},
  "geometry": {"coordinates":[-107.70904899999999,37.288403],"type":"Point"}
}