{
  "type": "Feature",
  "properties": {
    "addr:full":"3125 Austin Bluffs Pkwy Colorado Springs CO 80918",
    "addr:housenumber":"3125",
    "addr:postcode":"80918",
    "addr:street":"Austin Bluffs Pkwy",
    "iso:country":"US",
    "sg:address":"3125 Austin Bluffs Pkwy",
    "sg:city":"Colorado Springs",
    "sg:classifiers":[
        {
            "category":"Professional",
            "subcategory":"Accounting & Tax Preparation",
            "type":"Services"
        }
    ],
    "sg:phone":"+1 719 598 9202",
    "sg:postcode":"80918",
    "sg:province":"CO",
    "sg:tags":[
        "accountant"
    ],
    "wof:name":"Michael Matthews & Assoc",
    "wof:placetype":"venue"
},
  "geometry": {"coordinates":[-104.76835,38.890176],"type":"Point"}
}