{
  "type": "Feature",
  "properties": {
    "iso:country":"US",
    "sg:address":"124 N Main St",
    "sg:city":"Creede",
    "sg:classifiers":[
        {
            "category":"Organizations",
            "subcategory":"Non-profit Organization",
            "type":"Services"
        }
    ],
    "sg:phone":"+1 719 658 2540",
    "sg:postcode":"81130",
    "sg:province":"CO",
    "sg:website":"www.creederep.com",
    "wof:name":"Creede Repertory Theatre",
    "wof:placetype":"venue"
},
  "geometry": {"coordinates":[-106.927104,37.85395],"type":"Point"}
}