{
  "type": "Feature",
  "properties": {
    "iso:country":"US",
    "sg:address":"4032 S Kalispell St",
    "sg:city":"Aurora",
    "sg:classifiers":[
        {
            "category":"Professional",
            "type":"Services"
        }
    ],
    "sg:phone":"+1 303 699 8829",
    "sg:postcode":"80013",
    "sg:province":"CO",
    "wof:name":"Peter Wilson Inc",
    "wof:placetype":"venue"
},
  "geometry": {"coordinates":[-104.803399,39.643526],"type":"Point"}
}