{
  "type": "Feature",
  "properties": {
    "iso:country":"US",
    "sg:address":"805 Burbank St",
    "sg:city":"Broomfield",
    "sg:classifiers":[
        {
            "category":"Education",
            "subcategory":"School",
            "type":"Public Place"
        }
    ],
    "sg:phone":"+1 720 887 9033",
    "sg:postcode":"80020",
    "sg:province":"CO",
    "wof:name":"Soar High School",
    "wof:placetype":"venue"
},
  "geometry": {"coordinates":[-105.09473699999999,39.927596],"type":"Point"}
}