{
  "type": "Feature",
  "properties": {
    "addr:full":"5081 Kingston St Denver CO 80239",
    "addr:housenumber":"5081",
    "addr:postcode":"80239",
    "addr:street":"Kingston St",
    "iso:country":"US",
    "sg:address":"5081 Kingston St",
    "sg:city":"Denver",
    "sg:classifiers":[
        {
            "category":"Home & Garden",
            "subcategory":"Furniture",
            "type":"Retail Goods"
        }
    ],
    "sg:phone":"+1 303 373 5035",
    "sg:postcode":"80239",
    "sg:province":"CO",
    "sg:tags":[
        "warehouse",
        "equipment",
        "storage"
    ],
    "sg:website":"www.shelvingracklockers.com",
    "wof:name":"Shelving Rack & Lockers Inc",
    "wof:placetype":"venue"
},
  "geometry": {"coordinates":[-104.859106,39.789457],"type":"Point"}
}