{
  "type": "Feature",
  "properties": {
    "addr:full":"1200 Clayton St Denver CO 80206",
    "addr:housenumber":"1200",
    "addr:postcode":"80206",
    "addr:street":"Clayton St",
    "iso:country":"US",
    "sg:address":"1200 Clayton St",
    "sg:city":"Denver",
    "sg:classifiers":[
        {
            "category":"Coffee & Tea",
            "type":"Food & Drink"
        }
    ],
    "sg:phone":"+1 303 320 4721",
    "sg:postcode":"80206",
    "sg:province":"CO",
    "sg:website":"www.dazbog.com",
    "wof:name":"Dazbog Coffee",
    "wof:placetype":"venue"
},
  "geometry": {"coordinates":[-104.95500199999999,39.735298],"type":"Point"}
}