{
  "type": "Feature",
  "properties": {
    "addr:full":"8851 Washington St Denver CO 80229",
    "addr:housenumber":"8851",
    "addr:postcode":"80229",
    "addr:street":"Washington St",
    "iso:country":"US",
    "sg:address":"8851 Washington St",
    "sg:city":"Denver",
    "sg:classifiers":[
        {
            "category":"Personal",
            "subcategory":"Beauty Salon",
            "type":"Services"
        }
    ],
    "sg:phone":"+1 303 412 0433",
    "sg:postcode":"80229",
    "sg:province":"CO",
    "sg:tags":[
        "shop"
    ],
    "wof:name":"Espirits Day Spa",
    "wof:placetype":"venue"
},
  "geometry": {"coordinates":[-104.978026,39.859325],"type":"Point"}
}