{
  "type": "Feature",
  "properties": {
    "addr:full":"1325 Allegheny Dr Colorado Springs CO 80919",
    "addr:housenumber":"1325",
    "addr:postcode":"80919",
    "addr:street":"Allegheny Dr",
    "iso:country":"US",
    "sg:address":"1325 Allegheny Dr",
    "sg:city":"Colorado Springs",
    "sg:classifiers":[
        {
            "category":"Building & Trades",
            "subcategory":"Construction",
            "type":"Services"
        }
    ],
    "sg:phone":"+1 719 599 5545",
    "sg:postcode":"80919",
    "sg:province":"CO",
    "sg:tags":[
        "contractor"
    ],
    "wof:name":"Fencingrepairmancom",
    "wof:placetype":"venue"
},
  "geometry": {"coordinates":[-104.85308000000001,38.92939],"type":"Point"}
}