{
  "type": "Feature",
  "properties": {
    "addr:full":"16526 E Prentice Ave Centennial CO 80015",
    "addr:housenumber":"16526",
    "addr:postcode":"80015",
    "addr:street":"E Prentice Ave",
    "iso:country":"US",
    "sg:address":"16526 E Prentice Ave",
    "sg:city":"Centennial",
    "sg:classifiers":[
        {
            "category":"Retail",
            "subcategory":"Laundry & Dry Cleaning",
            "type":"Services"
        }
    ],
    "sg:phone":"+1 303 690 5622",
    "sg:postcode":"80015",
    "sg:province":"CO",
    "sg:tags":[
        "cleaners",
        "rug",
        "carpet"
    ],
    "wof:name":"P S Carpet Cleaning",
    "wof:placetype":"venue"
},
  "geometry": {"coordinates":[-104.796147,39.619986],"type":"Point"}
}