{
  "type": "Feature",
  "properties": {
    "iso:country":"US",
    "sg:address":"9831 Upham Ct",
    "sg:city":"Broomfield",
    "sg:classifiers":[
        {
            "category":"Wholesale",
            "subcategory":"Non-durable Goods",
            "type":"Manufacturing & Wholesale Goods"
        }
    ],
    "sg:phone":"+1 303 430 4126",
    "sg:postcode":"80021",
    "sg:province":"CO",
    "wof:name":"Performance Dynamics LLC",
    "wof:placetype":"venue"
},
  "geometry": {"coordinates":[-105.078676,39.875782],"type":"Point"}
}