{
  "type": "Feature",
  "properties": {
    "iso:country":"US",
    "sg:address":"8670 Wolff Ct",
    "sg:city":"Westminster",
    "sg:classifiers":[
        {
            "category":"Insurance",
            "subcategory":"Insurance Agent",
            "type":"Services"
        }
    ],
    "sg:phone":"+1 720 938 1101",
    "sg:postcode":"80031",
    "sg:province":"CO",
    "wof:name":"Farmers Insurance Group",
    "wof:placetype":"venue"
},
  "geometry": {"coordinates":[-105.049296,39.854586],"type":"Point"}
}