{
  "type": "Feature",
  "properties": {
    "iso:country":"US",
    "sg:address":"4100 W 38th Ave",
    "sg:city":"Denver",
    "sg:classifiers":[
        {
            "category":"Health Services",
            "subcategory":"Chiropractor",
            "type":"Services"
        }
    ],
    "sg:phone":"+1 720 855 8863",
    "sg:postcode":"80212",
    "sg:province":"CO",
    "wof:name":"Angel Chiropractic",
    "wof:placetype":"venue"
},
  "geometry": {"coordinates":[-105.041674,39.769445],"type":"Point"}
}