{
  "type": "Feature",
  "properties": {
    "iso:country":"US",
    "sg:address":"6654 W 99th Ave",
    "sg:city":"Broomfield",
    "sg:classifiers":[
        {
            "category":"Shopping",
            "subcategory":"Florist",
            "type":"Retail Goods"
        }
    ],
    "sg:phone":"+1 303 487 0800",
    "sg:postcode":"80021",
    "sg:province":"CO",
    "wof:name":"Jos Floral Creations",
    "wof:placetype":"venue"
},
  "geometry": {"coordinates":[-105.070003,39.877585],"type":"Point"}
}