{
  "type": "Feature",
  "properties": {
    "iso:country":"US",
    "sg:address":"444 17th St",
    "sg:city":"Denver",
    "sg:classifiers":[
        {
            "category":"Building & Trades",
            "subcategory":"Locksmith",
            "type":"Services"
        }
    ],
    "sg:phone":"+1 866 689 9171",
    "sg:postcode":"80202",
    "sg:province":"CO",
    "sg:tags":[
        "key"
    ],
    "wof:name":"Anytime Emergency Locksmith",
    "wof:placetype":"venue"
},
  "geometry": {"coordinates":[-104.988869,39.744295],"type":"Point"}
}