{
  "type": "Feature",
  "properties": {
    "addr:full":"444 17th St Denver CO 80202",
    "addr:housenumber":"444",
    "addr:postcode":"80202",
    "addr:street":"17Th St",
    "iso:country":"US",
    "sg:address":"444 17th St",
    "sg:city":"Denver",
    "sg:classifiers":[
        {
            "category":"Building & Trades",
            "subcategory":"Locksmith",
            "type":"Services"
        }
    ],
    "sg:phone":"+1 866 689 9171",
    "sg:postcode":"80202",
    "sg:province":"CO",
    "sg:tags":[
        "key"
    ],
    "wof:name":"Anytime Emergency Locksmith",
    "wof:placetype":"venue"
},
  "geometry": {"coordinates":[-104.98886899999999,39.744295],"type":"Point"}
}