{
  "type": "Feature",
  "properties": {
    "addr:full":"2200 Airway Ave Fort Collins CO 80524",
    "addr:housenumber":"2200",
    "addr:postcode":"80524",
    "addr:street":"Airway Ave",
    "iso:country":"US",
    "sg:address":"2200 Airway Ave",
    "sg:city":"Fort Collins",
    "sg:classifiers":[
        {
            "category":"Professional",
            "subcategory":"Advertising",
            "type":"Services"
        }
    ],
    "sg:phone":"+1 970 482 9008",
    "sg:postcode":"80524",
    "sg:province":"CO",
    "sg:tags":[
        "counselor"
    ],
    "wof:name":"Kelly Rizley Advertising & Pr",
    "wof:placetype":"venue"
},
  "geometry": {"coordinates":[-105.036541,40.583352],"type":"Point"}
}