{
  "type": "Feature",
  "properties": {
    "iso:country":"US",
    "sg:address":"19553 E Main St",
    "sg:city":"Parker",
    "sg:classifiers":[
        {
            "category":"Restaurant",
            "type":"Food & Drink"
        }
    ],
    "sg:phone":"+1 303 840 0325",
    "sg:postcode":"80138",
    "sg:province":"CO",
    "wof:name":"Las Delicias",
    "wof:placetype":"venue"
},
  "geometry": {"coordinates":[-104.759947,39.518205],"type":"Point"}
}