{
  "type": "Feature",
  "properties": {
    "addr:full":"1018 Huntington Hills Dr Fort Collins CO 80525",
    "addr:housenumber":"1018",
    "addr:postcode":"80525",
    "addr:street":"Huntington Hills Dr",
    "iso:country":"US",
    "sg:address":"1018 Huntington Hills Dr",
    "sg:city":"Fort Collins",
    "sg:classifiers":[
        {
            "category":"Building & Trades",
            "subcategory":"Construction",
            "type":"Services"
        }
    ],
    "sg:phone":"+1 970 223 9592",
    "sg:postcode":"80525",
    "sg:province":"CO",
    "sg:tags":[
        "house",
        "real estate"
    ],
    "wof:name":"Griess Construction Inc",
    "wof:placetype":"venue"
},
  "geometry": {"coordinates":[-105.059926,40.502059],"type":"Point"}
}