{
  "type": "Feature",
  "properties": {
    "addr:full":"1111 S Prairie Ave Pueblo CO 81005",
    "addr:housenumber":"1111",
    "addr:postcode":"81005",
    "addr:street":"S Prairie Ave",
    "iso:country":"US",
    "sg:address":"1111 S Prairie Ave",
    "sg:city":"Pueblo",
    "sg:classifiers":[
        {
            "category":"Retail",
            "subcategory":"Laundry & Dry Cleaning",
            "type":"Services"
        }
    ],
    "sg:phone":"+1 719 561 9177",
    "sg:postcode":"81005",
    "sg:province":"CO",
    "sg:tags":[
        "cleaners"
    ],
    "wof:name":"Care Cleaners Inc",
    "wof:placetype":"venue"
},
  "geometry": {"coordinates":[-104.64386399999999,38.246029],"type":"Point"}
}