{
  "type": "Feature",
  "properties": {
    "addr:full":"620 Central Ave Wiggins CO 80654",
    "addr:housenumber":"620",
    "addr:postcode":"80654",
    "addr:street":"Central Ave",
    "iso:country":"US",
    "sg:address":"620 Central Ave",
    "sg:city":"Wiggins",
    "sg:classifiers":[
        {
            "category":"Personal",
            "subcategory":"Beauty Salon",
            "type":"Services"
        }
    ],
    "sg:phone":"+1 970 483 7257",
    "sg:postcode":"80654",
    "sg:province":"CO",
    "sg:tags":[
        "manicuring"
    ],
    "wof:name":"Get Nailed",
    "wof:placetype":"venue"
},
  "geometry": {"coordinates":[-104.06905500000001,40.235673],"type":"Point"}
}