{
  "type": "Feature",
  "properties": {
    "iso:country":"US",
    "sg:address":"82 el Rio Dr",
    "sg:city":"Alamosa",
    "sg:classifiers":[
        {
            "category":"Restaurant",
            "type":"Food & Drink"
        }
    ],
    "sg:phone":"+1 719 589 4202",
    "sg:postcode":"81101",
    "sg:province":"CO",
    "sg:tags":[
        "eating"
    ],
    "wof:name":"Campus Cafe",
    "wof:placetype":"venue"
},
  "geometry": {"coordinates":[-105.876068,37.474809],"type":"Point"}
}