{
  "type": "Feature",
  "properties": {
    "addr:full":"4976 Carefree Tr Parker CO 80108",
    "addr:housenumber":"4976",
    "addr:postcode":"80108",
    "addr:street":"Carefree Tr",
    "iso:country":"US",
    "sg:address":"4976 Carefree Tr",
    "sg:city":"Parker",
    "sg:classifiers":[
        {
            "category":"Arts & Performance",
            "subcategory":"Art Gallery",
            "type":"Entertainment"
        }
    ],
    "sg:phone":"+1 303 955 6957",
    "sg:postcode":"80108",
    "sg:province":"CO",
    "sg:website":"joanfullerton.com",
    "wof:name":"Joan Fullerton Fine Art",
    "wof:placetype":"venue"
},
  "geometry": {"coordinates":[-104.79553199999999,39.432297],"type":"Point"}
}