{
  "type": "Feature",
  "properties": {
    "iso:country":"US",
    "sg:address":"407 N Lincoln Ave",
    "sg:city":"Loveland",
    "sg:classifiers":[
        {
            "category":"Professional",
            "subcategory":"Management & Consulting",
            "type":"Services"
        }
    ],
    "sg:phone":"+1 970 663 1677",
    "sg:postcode":"80537",
    "sg:province":"CO",
    "sg:tags":[
        "construction"
    ],
    "wof:name":"Professional Construction Mgmt",
    "wof:placetype":"venue"
},
  "geometry": {"coordinates":[-105.07326999999999,40.396416],"type":"Point"}
}