{
  "type": "Feature",
  "properties": {
    "addr:full":"46 Moffat Ave Yampa CO 80483",
    "addr:housenumber":"46",
    "addr:postcode":"80483",
    "addr:street":"Moffat Ave",
    "iso:country":"US",
    "sg:address":"46 Moffat Ave",
    "sg:city":"Yampa",
    "sg:classifiers":[
        {
            "category":"Restaurant",
            "type":"Food & Drink"
        }
    ],
    "sg:phone":"+1 970 638 4555",
    "sg:postcode":"80483",
    "sg:province":"CO",
    "sg:tags":[
        "eating"
    ],
    "wof:name":"Antler's Cafe & Bar",
    "wof:placetype":"venue"
},
  "geometry": {"coordinates":[-106.90867799999999,40.150392],"type":"Point"}
}