{
  "type": "Feature",
  "properties": {
    "addr:full":"17800 E 22nd Ave Aurora CO 80011",
    "addr:housenumber":"17800",
    "addr:postcode":"80011",
    "addr:street":"E 22Nd Ave",
    "iso:country":"US",
    "sg:address":"17800 E 22nd Ave",
    "sg:city":"Aurora",
    "sg:classifiers":[
        {
            "category":"Building & Trades",
            "subcategory":"Construction",
            "type":"Services"
        }
    ],
    "sg:phone":"+1 303 755 1281",
    "sg:postcode":"80011",
    "sg:province":"CO",
    "sg:tags":[
        "well",
        "drilling"
    ],
    "wof:name":"Layne Western Co",
    "wof:placetype":"venue"
},
  "geometry": {"coordinates":[-104.78149999999999,39.749088],"type":"Point"}
}