{
  "type": "Feature",
  "properties": {
    "addr:full":"3131 Century St Colorado Springs CO 80907",
    "addr:housenumber":"3131",
    "addr:postcode":"80907",
    "addr:street":"Century St",
    "iso:country":"US",
    "sg:address":"3131 Century St",
    "sg:city":"Colorado Springs",
    "sg:classifiers":[
        {
            "category":"Building & Trades",
            "subcategory":"Construction",
            "type":"Services"
        }
    ],
    "sg:phone":"+1 719 633 6222",
    "sg:postcode":"80907",
    "sg:province":"CO",
    "sg:tags":[
        "roofing",
        "contractor"
    ],
    "wof:name":"Douglass Roofing Co",
    "wof:placetype":"venue"
},
  "geometry": {"coordinates":[-104.814042,38.877797],"type":"Point"}
}