{
  "type": "Feature",
  "properties": {
    "addr:full":"207 Francis St Longmont CO 80501",
    "addr:housenumber":"207",
    "addr:postcode":"80501",
    "addr:street":"Francis St",
    "iso:country":"US",
    "sg:address":"207 Francis St",
    "sg:city":"Longmont",
    "sg:classifiers":[
        {
            "category":"Mining & Drilling",
            "type":"Manufacturing & Wholesale Goods"
        }
    ],
    "sg:phone":"+1 303 776 3397",
    "sg:postcode":"80501",
    "sg:province":"CO",
    "sg:tags":[
        "exploration"
    ],
    "wof:name":"Bdem Inc",
    "wof:placetype":"venue"
},
  "geometry": {"coordinates":[-105.11727,40.166674],"type":"Point"}
}