{
  "type": "Feature",
  "properties": {
    "iso:country":"US",
    "sg:address":"8605 Explorer Dr",
    "sg:city":"Colorado Springs",
    "sg:classifiers":[
        {
            "category":"Manufacturing",
            "subcategory":"Printing",
            "type":"Manufacturing & Wholesale Goods"
        }
    ],
    "sg:phone":"+1 719 531 3300",
    "sg:postcode":"80920",
    "sg:province":"CO",
    "sg:tags":[
        "multimedia"
    ],
    "sg:website":"www.briargatemedia.com",
    "wof:name":"Briargate Media",
    "wof:placetype":"venue"
},
  "geometry": {"coordinates":[-104.791703,38.960849],"type":"Point"}
}