{
  "type": "Feature",
  "properties": {
    "iso:country":"US",
    "sg:address":"9715 S Cove Creek Dr",
    "sg:city":"Littleton",
    "sg:classifiers":[
        {
            "category":"Manufacturing",
            "subcategory":"Metals",
            "type":"Manufacturing & Wholesale Goods"
        }
    ],
    "sg:phone":"+1 303 901 4711",
    "sg:postcode":"80129",
    "sg:province":"CO",
    "sg:tags":[
        "metalwork",
        "architectural",
        "mfg"
    ],
    "wof:name":"Inline Ironworks Inc",
    "wof:placetype":"venue"
},
  "geometry": {"coordinates":[-105.016513,39.538492],"type":"Point"}
}