{
  "type": "Feature",
  "properties": {
    "addr:full":"3061 S Tejon St Englewood CO 80110",
    "addr:housenumber":"3061",
    "addr:postcode":"80110",
    "addr:street":"S Tejon St",
    "iso:country":"US",
    "sg:address":"3061 S Tejon St",
    "sg:city":"Englewood",
    "sg:classifiers":[
        {
            "category":"Retail",
            "subcategory":"Auto Repair",
            "type":"Services"
        }
    ],
    "sg:phone":"+1 303 789 2551",
    "sg:postcode":"80110",
    "sg:province":"CO",
    "sg:tags":[
        "automobile",
        "restoration",
        "classic"
    ],
    "wof:name":"Blazin' 4X4",
    "wof:placetype":"venue"
},
  "geometry": {"coordinates":[-105.011162,39.661599],"type":"Point"}
}