{
  "type": "Feature",
  "properties": {
    "iso:country":"US",
    "sg:address":"4501 Broadway St",
    "sg:city":"Boulder",
    "sg:classifiers":[
        {
            "category":"Mining & Drilling",
            "type":"Manufacturing & Wholesale Goods"
        }
    ],
    "sg:phone":"+1 303 786 8189",
    "sg:postcode":"80304",
    "sg:province":"CO",
    "sg:tags":[
        "oil",
        "gas",
        "producer"
    ],
    "wof:name":"Silco Oil",
    "wof:placetype":"venue"
},
  "geometry": {"coordinates":[-105.282117,40.054572],"type":"Point"}
}