{
  "type": "Feature",
  "properties": {
    "addr:full":"10191 W Evans Ave Denver CO 80227",
    "addr:housenumber":"10191",
    "addr:postcode":"80227",
    "addr:street":"W Evans Ave",
    "iso:country":"US",
    "sg:address":"10191 W Evans Ave",
    "sg:city":"Denver",
    "sg:classifiers":[
        {
            "category":"Building & Trades",
            "subcategory":"Construction",
            "type":"Services"
        }
    ],
    "sg:phone":"+1 303 988 2837",
    "sg:postcode":"80227",
    "sg:province":"CO",
    "sg:tags":[
        "concrete",
        "contractor"
    ],
    "wof:name":"Concrete Energy Features",
    "wof:placetype":"venue"
},
  "geometry": {"coordinates":[-105.11163999999999,39.678972],"type":"Point"}
}