{
  "type": "Feature",
  "properties": {
    "addr:full":"2835 S Broadway Englewood CO 80113",
    "addr:housenumber":"2835",
    "addr:postcode":"80113",
    "addr:street":"S Broadway",
    "iso:country":"US",
    "sg:address":"2835 S Broadway",
    "sg:city":"Englewood",
    "sg:classifiers":[
        {
            "category":"Shopping",
            "subcategory":"Comic Books",
            "type":"Retail Goods"
        }
    ],
    "sg:phone":"+1 303 781 6166",
    "sg:postcode":"80113",
    "sg:province":"CO",
    "wof:name":"Clockwork Comics",
    "wof:placetype":"venue"
},
  "geometry": {"coordinates":[-104.98699999999999,39.665401],"type":"Point"}
}