{
  "type": "Feature",
  "properties": {
    "addr:full":"3205 Dillon Dr Pueblo CO 81008",
    "addr:housenumber":"3205",
    "addr:postcode":"81008",
    "addr:street":"Dillon Dr",
    "iso:country":"US",
    "sg:address":"3205 Dillon Dr",
    "sg:city":"Pueblo",
    "sg:classifiers":[
        {
            "category":"Personal",
            "subcategory":"Massage",
            "type":"Services"
        }
    ],
    "sg:phone":"+1 719 545 2498",
    "sg:postcode":"81008",
    "sg:province":"CO",
    "sg:tags":[
        "therapist"
    ],
    "wof:name":"Chinese Massage",
    "wof:placetype":"venue"
},
  "geometry": {"coordinates":[-104.606455,38.303074],"type":"Point"}
}