{
  "type": "Feature",
  "properties": {
    "iso:country":"US",
    "sg:address":"1100 N Main St",
    "sg:city":"Lamar",
    "sg:classifiers":[
        {
            "category":"Wholesale",
            "subcategory":"Machinery & Supplies",
            "type":"Manufacturing & Wholesale Goods"
        }
    ],
    "sg:phone":"+1 719 336 7433",
    "sg:postcode":"81052",
    "sg:province":"CO",
    "sg:tags":[
        "farm",
        "equipment"
    ],
    "sg:website":"www.who-mfg.com",
    "wof:name":"WHO Mfg Co",
    "wof:placetype":"venue"
},
  "geometry": {"coordinates":[-102.618329,38.100669],"type":"Point"}
}