{
  "type": "Feature",
  "properties": {
    "addr:full":"168 Midway Ave Pueblo CO 81004",
    "addr:housenumber":"168",
    "addr:postcode":"81004",
    "addr:street":"Midway Ave",
    "iso:country":"US",
    "sg:address":"168 Midway Ave",
    "sg:city":"Pueblo",
    "sg:classifiers":[
        {
            "category":"Retail",
            "subcategory":"Repair Shop",
            "type":"Services"
        }
    ],
    "sg:phone":"+1 719 546 0242",
    "sg:postcode":"81004",
    "sg:province":"CO",
    "sg:tags":[
        "repairing",
        "piano",
        "refinishing"
    ],
    "wof:name":"T M Galusha Piano Svc",
    "wof:placetype":"venue"
},
  "geometry": {"coordinates":[-104.620717,38.260557],"type":"Point"}
}