{
  "type": "Feature",
  "properties": {
    "iso:country":"US",
    "sg:address":"5445 Dtc Pkwy",
    "sg:city":"Englewood",
    "sg:classifiers":[
        {
            "category":"Banks & Credit Unions",
            "subcategory":"Bank",
            "type":"Services"
        }
    ],
    "sg:phone":"+1 303 486 6933",
    "sg:postcode":"80111",
    "sg:province":"CO",
    "sg:tags":[
        "broker",
        "mortgage"
    ],
    "wof:name":"1st American Mortgage & Ln LLC",
    "wof:placetype":"venue"
},
  "geometry": {"coordinates":[-104.896162,39.617378],"type":"Point"}
}