{
  "type": "Feature",
  "properties": {
    "addr:full":"1121 13th St Boulder CO 80302",
    "addr:housenumber":"1121",
    "addr:postcode":"80302",
    "addr:street":"13Th St",
    "iso:country":"US",
    "sg:address":"1121 13th St",
    "sg:city":"Boulder",
    "sg:classifiers":[
        {
            "category":"Restaurant",
            "type":"Food & Drink"
        }
    ],
    "sg:menulink":"http://www.allmenus.com/co/boulder/40679-albums-bistro/menu/",
    "sg:phone":"0",
    "sg:postcode":"80302",
    "sg:province":"CO",
    "sg:tags":[
        "american"
    ],
    "wof:name":"Albums Bistro",
    "wof:placetype":"venue"
},
  "geometry": {"coordinates":[-105.2762,40.007558],"type":"Point"}
}