{
  "type": "Feature",
  "properties": {
    "iso:country":"US",
    "sg:address":"7475 W 5th Ave",
    "sg:city":"Lakewood",
    "sg:classifiers":[
        {
            "category":"Social Services",
            "type":"Services"
        }
    ],
    "sg:phone":"+1 303 988 8840",
    "sg:postcode":"80226",
    "sg:province":"CO",
    "sg:tags":[
        "counselor",
        "marriage",
        "family"
    ],
    "wof:name":"Life Management",
    "wof:placetype":"venue"
},
  "geometry": {"coordinates":[-105.079176,39.723937],"type":"Point"}
}