{
  "type": "Feature",
  "properties": {
    "iso:country":"US",
    "sg:address":"15201 E Moncrieff Pl",
    "sg:city":"Aurora",
    "sg:classifiers":[
        {
            "category":"Health Services",
            "subcategory":"Doctor",
            "type":"Services"
        }
    ],
    "sg:phone":"+1 303 916 5607",
    "sg:postcode":"80011",
    "sg:province":"CO",
    "sg:tags":[
        "physician",
        "surgeon"
    ],
    "wof:name":"Rehabilitation Associates",
    "wof:placetype":"venue"
},
  "geometry": {"coordinates":[-104.81183799999999,39.762644],"type":"Point"}
}