{
  "type": "Feature",
  "properties": {
    "iso:country":"US",
    "sg:address":"623 Main St",
    "sg:city":"Walsenburg",
    "sg:classifiers":[
        {
            "category":"Shopping",
            "subcategory":"Used Merchandise",
            "type":"Retail Goods"
        }
    ],
    "sg:phone":"+1 719 738 2510",
    "sg:postcode":"81089",
    "sg:province":"CO",
    "sg:tags":[
        "antique"
    ],
    "wof:name":"Fallen Angel",
    "wof:placetype":"venue"
},
  "geometry": {"coordinates":[-104.78081299999999,37.623424],"type":"Point"}
}