{
  "type": "Feature",
  "properties": {
    "addr:full":"6771 Co Rd 79 Fleming CO 80728",
    "addr:housenumber":"6771;79",
    "addr:postcode":"80728",
    "addr:street":"Co Rd",
    "iso:country":"US",
    "sg:address":"6771 Co Rd 79",
    "sg:city":"Fleming",
    "sg:classifiers":[
        {
            "category":"Professional",
            "subcategory":"Management & Consulting",
            "type":"Services"
        }
    ],
    "sg:phone":"+1 303 644 5076",
    "sg:postcode":"80728",
    "sg:province":"CO",
    "sg:tags":[
        "consultant",
        "training"
    ],
    "wof:name":"Wegener Training Manager",
    "wof:placetype":"venue"
},
  "geometry": {"coordinates":[-102.837321,40.533575],"type":"Point"}
}