{
  "type": "Feature",
  "properties": {
    "addr:full":"12040 Country Club Dr Conifer CO 80433",
    "addr:housenumber":"12040",
    "addr:postcode":"80433",
    "addr:street":"Country Club Dr",
    "iso:country":"US",
    "sg:address":"12040 Country Club Dr",
    "sg:city":"Conifer",
    "sg:classifiers":[
        {
            "category":"Restaurant",
            "type":"Food & Drink"
        }
    ],
    "sg:phone":"+1 303 816 9123",
    "sg:postcode":"80433",
    "sg:province":"CO",
    "sg:tags":[
        "eating"
    ],
    "wof:name":"Wing Wagon LLC",
    "wof:placetype":"venue"
},
  "geometry": {"coordinates":[-105.351381,39.496981],"type":"Point"}
}