{
  "type": "Feature",
  "properties": {
    "iso:country":"US",
    "sg:address":"2900 Valmont Rd",
    "sg:city":"Boulder",
    "sg:classifiers":[
        {
            "category":"Professional",
            "type":"Services"
        }
    ],
    "sg:phone":"+1 720 564 0397",
    "sg:postcode":"80301",
    "sg:province":"CO",
    "sg:tags":[
        "establishment"
    ],
    "wof:name":"Colorado BPW",
    "wof:placetype":"venue"
},
  "geometry": {"coordinates":[-105.253675,40.029191],"type":"Point"}
}