{
  "type": "Feature",
  "properties": {
    "iso:country":"US",
    "sg:address":"8200 S Quebec St",
    "sg:city":"Centennial",
    "sg:classifiers":[
        {
            "category":"Wholesale",
            "subcategory":"Machinery & Supplies",
            "type":"Manufacturing & Wholesale Goods"
        },
        {
            "category":"Home & Garden",
            "subcategory":"Household Appliances",
            "type":"Retail Goods"
        }
    ],
    "sg:phone":"+1 303 290 0393",
    "sg:postcode":"80112",
    "sg:province":"CO",
    "sg:tags":[
        "machine",
        "sewing"
    ],
    "wof:name":"Jma Sewing Machine Co",
    "wof:placetype":"venue"
},
  "geometry": {"coordinates":[-104.904321,39.566816],"type":"Point"}
}