{
  "type": "Feature",
  "properties": {
    "iso:country":"US",
    "sg:address":"1026 Main St",
    "sg:city":"Delta",
    "sg:classifiers":[
        {
            "category":"Organizations",
            "subcategory":"Non-profit Organization",
            "type":"Services"
        }
    ],
    "sg:phone":"+1 970 874 1787",
    "sg:postcode":"81416",
    "sg:province":"CO",
    "wof:name":"Adult Services",
    "wof:placetype":"venue"
},
  "geometry": {"coordinates":[-108.07055699999999,38.733491],"type":"Point"}
}