{
  "type": "Feature",
  "properties": {
    "addr:full":"141 Union Blvd Denver CO 80228",
    "addr:housenumber":"141",
    "addr:postcode":"80228",
    "addr:street":"Union Blvd",
    "iso:country":"US",
    "sg:address":"141 Union Blvd",
    "sg:city":"Denver",
    "sg:classifiers":[
        {
            "category":"Professional",
            "subcategory":"Lawyer & Legal Services",
            "type":"Services"
        }
    ],
    "sg:phone":"+1 303 987 3800",
    "sg:postcode":"80228",
    "sg:province":"CO",
    "wof:name":"Waller William C",
    "wof:placetype":"venue"
},
  "geometry": {"coordinates":[-105.13324,39.715588],"type":"Point"}
}