{
  "type": "Feature",
  "properties": {
    "iso:country":"US",
    "sg:address":"729 D St",
    "sg:city":"Salida",
    "sg:classifiers":[
        {
            "category":"Travel",
            "subcategory":"Travel Agent",
            "type":"Entertainment"
        }
    ],
    "sg:phone":"+1 719 539 2962",
    "sg:postcode":"81201",
    "sg:province":"CO",
    "sg:tags":[
        "tours",
        "sightseeing"
    ],
    "sg:website":"www.funtimejeeptours.com",
    "wof:name":"Fun Time Jeep Tours",
    "wof:placetype":"venue"
},
  "geometry": {"coordinates":[-105.99475099999999,38.529698],"type":"Point"}
}