{
  "type": "Feature",
  "properties": {
    "addr:full":"841 S Dover St Lakewood CO 80226",
    "addr:housenumber":"841",
    "addr:postcode":"80226",
    "addr:street":"S Dover St",
    "iso:country":"US",
    "sg:address":"841 S Dover St",
    "sg:city":"Lakewood",
    "sg:classifiers":[
        {
            "category":"Building & Trades",
            "subcategory":"Landscaping Services",
            "type":"Services"
        }
    ],
    "sg:phone":"+1 303 551 3085",
    "sg:postcode":"80226",
    "sg:province":"CO",
    "sg:tags":[
        "landscape",
        "contractor"
    ],
    "wof:name":"Firmly Rooted Gardens Inc",
    "wof:placetype":"venue"
},
  "geometry": {"coordinates":[-105.09336399999999,39.701052],"type":"Point"}
}