{
  "type": "Feature",
  "properties": {
    "addr:full":"5598 N Academy Blvd Colorado Springs CO 80918",
    "addr:housenumber":"5598",
    "addr:postcode":"80918",
    "addr:street":"N Academy Blvd",
    "iso:country":"US",
    "sg:address":"5598 N Academy Blvd",
    "sg:city":"Colorado Springs",
    "sg:classifiers":[
        {
            "category":"Restaurant",
            "type":"Food & Drink"
        }
    ],
    "sg:phone":"+1 719 266 1999",
    "sg:postcode":"80918",
    "sg:province":"CO",
    "wof:name":"Pueblo Viejo Mexican Rstrnt",
    "wof:placetype":"venue"
},
  "geometry": {"coordinates":[-104.787873,38.910634],"type":"Point"}
}