{
  "type": "Feature",
  "properties": {
    "addr:full":"6565 Greenwood Plaza Blvd Greenwood Vlg CO 80111",
    "addr:housenumber":"6565",
    "addr:postcode":"co 80111",
    "addr:street":"Greenwood Plaza Blvd",
    "iso:country":"US",
    "sg:address":"6565 Greenwood Plaza Blvd",
    "sg:city":"Greenwood Vlg",
    "sg:classifiers":[
        {
            "category":"Professional",
            "subcategory":"Advertising",
            "type":"Services"
        }
    ],
    "sg:phone":"+1 303 649 9888",
    "sg:postcode":"80111",
    "sg:province":"CO",
    "sg:tags":[
        "mail"
    ],
    "wof:name":"Direct Marketing Designs",
    "wof:placetype":"venue"
},
  "geometry": {"coordinates":[-104.893649,39.596057],"type":"Point"}
}