{
  "type": "Feature",
  "properties": {
    "iso:country":"US",
    "sg:address":"207 Basalt Center Rd",
    "sg:city":"Basalt",
    "sg:classifiers":[
        {
            "category":"Banks & Credit Unions",
            "subcategory":"Investment Brokerage",
            "type":"Services"
        }
    ],
    "sg:phone":"+1 970 927 6777",
    "sg:postcode":"81621",
    "sg:province":"CO",
    "sg:tags":[
        "advisory",
        "financial"
    ],
    "wof:name":"Flagstone Financial Advisors",
    "wof:placetype":"venue"
},
  "geometry": {"coordinates":[-107.034436,39.368491],"type":"Point"}
}