{
  "type": "Feature",
  "properties": {
    "addr:full":"2730 S Colorado Blvd Denver CO 80222",
    "addr:housenumber":"2730",
    "addr:postcode":"80222",
    "addr:street":"S Colorado Blvd",
    "iso:country":"US",
    "sg:address":"2730 S Colorado Blvd",
    "sg:city":"Denver",
    "sg:classifiers":[
        {
            "category":"Personal",
            "subcategory":"Beauty Salon",
            "type":"Services"
        }
    ],
    "sg:phone":"+1 303 639 8550",
    "sg:postcode":"80222",
    "sg:province":"CO",
    "wof:name":"Great Clips",
    "wof:placetype":"venue"
},
  "geometry": {"coordinates":[-104.94060500000001,39.66804],"type":"Point"}
}