{
  "type": "Feature",
  "properties": {
    "iso:country":"US",
    "sg:address":"3103 Peoria St",
    "sg:city":"Aurora",
    "sg:classifiers":[
        {
            "category":"Retail",
            "subcategory":"Car Wash",
            "type":"Services"
        }
    ],
    "sg:phone":"+1 303 751 2732",
    "sg:postcode":"80010",
    "sg:province":"CO",
    "sg:tags":[
        "operated",
        "polishing",
        "washing"
    ],
    "wof:name":"Power Wash",
    "wof:placetype":"venue"
},
  "geometry": {"coordinates":[-104.847049,39.759821],"type":"Point"}
}