{
  "type": "Feature",
  "properties": {
    "addr:full":"6825 Mission Rd Colorado Springs CO 80915",
    "addr:housenumber":"6825",
    "addr:postcode":"80915",
    "addr:street":"Mission Rd",
    "iso:country":"US",
    "sg:address":"6825 Mission Rd",
    "sg:city":"Colorado Springs",
    "sg:classifiers":[
        {
            "category":"Building & Trades",
            "subcategory":"Construction",
            "type":"Services"
        }
    ],
    "sg:phone":"+1 719 574 3908",
    "sg:postcode":"80915",
    "sg:province":"CO",
    "sg:tags":[
        "contractor"
    ],
    "wof:name":"Radspinner Masonry",
    "wof:placetype":"venue"
},
  "geometry": {"coordinates":[-104.70388199999999,38.845011],"type":"Point"}
}