{
  "type": "Feature",
  "properties": {
    "iso:country":"US",
    "sg:address":"737 29th St",
    "sg:city":"Boulder",
    "sg:classifiers":[
        {
            "category":"Recreation",
            "type":"Entertainment"
        }
    ],
    "sg:phone":"+1 720 565 2821",
    "sg:postcode":"80303",
    "sg:province":"CO",
    "sg:tags":[
        "instruction",
        "yoga"
    ],
    "wof:name":"Tree House Yoga Studio",
    "wof:placetype":"venue"
},
  "geometry": {"coordinates":[-105.256017,40.000749],"type":"Point"}
}