{
  "type": "Feature",
  "properties": {
    "iso:country":"US",
    "sg:address":"440 4th St",
    "sg:city":"Castle Rock",
    "sg:classifiers":[
        {
            "category":"Banks & Credit Unions",
            "subcategory":"Financial Services",
            "type":"Services"
        }
    ],
    "sg:phone":"+1 720 279 7560",
    "sg:postcode":"80104",
    "sg:province":"CO",
    "sg:tags":[
        "broker",
        "mortgage"
    ],
    "wof:name":"Fundamental Advisors",
    "wof:placetype":"venue"
},
  "geometry": {"coordinates":[-104.858177,39.373146],"type":"Point"}
}