{
  "type": "Feature",
  "properties": {
    "addr:full":"1432 W 3rd St Florence CO 81226",
    "addr:housenumber":"1432",
    "addr:postcode":"florence;81226",
    "addr:street":"W 3Rd St",
    "iso:country":"US",
    "sg:address":"1432 W 3rd St",
    "sg:city":"Florence",
    "sg:classifiers":[
        {
            "category":"Shopping",
            "subcategory":"Bicycles & Sporting Goods",
            "type":"Retail Goods"
        }
    ],
    "sg:phone":"+1 719 784 3353",
    "sg:postcode":"81226",
    "sg:province":"CO",
    "sg:tags":[
        "gun",
        "gunsmith"
    ],
    "wof:name":"Dan's Little Shop Of Repair",
    "wof:placetype":"venue"
},
  "geometry": {"coordinates":[-105.134754,38.400895],"type":"Point"}
}