{
  "type": "Feature",
  "properties": {
    "addr:full":"8547 E Arapahoe Rd Greenwood Vlg CO 80112",
    "addr:housenumber":"8547",
    "addr:postcode":"co 80112",
    "addr:street":"E Arapahoe Rd",
    "iso:country":"US",
    "sg:address":"8547 E Arapahoe Rd",
    "sg:city":"Greenwood Vlg",
    "sg:classifiers":[
        {
            "category":"Professional",
            "subcategory":"Computer Services",
            "type":"Services"
        }
    ],
    "sg:phone":"+1 720 493 0618",
    "sg:postcode":"80112",
    "sg:province":"CO",
    "sg:tags":[
        "repair"
    ],
    "wof:name":"AAA Computer Svc-Mobile",
    "wof:placetype":"venue"
},
  "geometry": {"coordinates":[-104.89237300000001,39.595112],"type":"Point"}
}