{
  "type": "Feature",
  "properties": {
    "iso:country":"US",
    "sg:address":"59939 Joey Rd",
    "sg:city":"Montrose",
    "sg:classifiers":[
        {
            "category":"Building & Trades",
            "subcategory":"Construction",
            "type":"Services"
        }
    ],
    "sg:phone":"+1 970 252 8560",
    "sg:postcode":"81401",
    "sg:province":"CO",
    "sg:tags":[
        "excavation",
        "contractor"
    ],
    "wof:name":"Midwest Backhoe Service",
    "wof:placetype":"venue"
},
  "geometry": {"coordinates":[-107.968226,38.535766],"type":"Point"}
}