{
  "type": "Feature",
  "properties": {
    "addr:full":"560 S Commercial Dr Grand Junction CO 81505",
    "addr:housenumber":"560",
    "addr:postcode":"81505",
    "addr:street":"S Commercial Dr",
    "iso:country":"US",
    "sg:address":"560 S Commercial Dr",
    "sg:city":"Grand Junction",
    "sg:classifiers":[
        {
            "category":"Building & Trades",
            "subcategory":"Cleaning & Sanitation",
            "type":"Services"
        }
    ],
    "sg:phone":"+1 970 244 8597",
    "sg:postcode":"81505",
    "sg:province":"CO",
    "sg:tags":[
        "house"
    ],
    "wof:name":"Merry Maids",
    "wof:placetype":"venue"
},
  "geometry": {"coordinates":[-108.585342,39.086723],"type":"Point"}
}