{
  "type": "Feature",
  "properties": {
    "iso:country":"US",
    "sg:address":"16500 E 2nd Ave",
    "sg:city":"Aurora",
    "sg:classifiers":[
        {
            "category":"Building & Trades",
            "subcategory":"Landscaping Services",
            "type":"Services"
        }
    ],
    "sg:phone":"+1 303 693 0930",
    "sg:postcode":"80011",
    "sg:province":"CO",
    "sg:tags":[
        "lawn",
        "maintenance",
        "grounds"
    ],
    "wof:name":"Aeration Service",
    "wof:placetype":"venue"
},
  "geometry": {"coordinates":[-104.798779,39.719188],"type":"Point"}
}