{
  "type": "Feature",
  "properties": {
    "addr:full":"321 Gregory St Central City CO 80427",
    "addr:housenumber":"321",
    "addr:postcode":"80427",
    "addr:street":"Gregory St",
    "iso:country":"US",
    "sg:address":"321 Gregory St",
    "sg:city":"Central City",
    "sg:classifiers":[
        {
            "category":"Casinos & Gambling",
            "type":"Entertainment"
        }
    ],
    "sg:phone":"+1 800 924 6646",
    "sg:postcode":"80427",
    "sg:province":"CO",
    "sg:website":"www.fortunevalleycasino.com",
    "wof:name":"Fortune Valley",
    "wof:placetype":"venue"
},
  "geometry": {"coordinates":[-105.509225,39.799972],"type":"Point"}
}