{
  "type": "Feature",
  "properties": {
    "addr:full":"5115 Topaz Dr Colorado Springs CO 80918",
    "addr:housenumber":"5115",
    "addr:postcode":"80918",
    "addr:street":"Topaz Dr",
    "iso:country":"US",
    "sg:address":"5115 Topaz Dr",
    "sg:city":"Colorado Springs",
    "sg:classifiers":[
        {
            "category":"Professional",
            "type":"Services"
        }
    ],
    "sg:phone":"+1 719 592 1760",
    "sg:postcode":"80918",
    "sg:province":"CO",
    "wof:name":"Kanagy Lawnscapes",
    "wof:placetype":"venue"
},
  "geometry": {"coordinates":[-104.751165,38.909146],"type":"Point"}
}