{
  "type": "Feature",
  "properties": {
    "iso:country":"US",
    "sg:address":"82 E 2nd Ave",
    "sg:city":"Longmont",
    "sg:classifiers":[
        {
            "category":"Building & Trades",
            "subcategory":"Construction",
            "type":"Services"
        }
    ],
    "sg:phone":"+1 303 402 3283",
    "sg:postcode":"80501",
    "sg:province":"CO",
    "sg:tags":[
        "nonresidential"
    ],
    "wof:name":"Dans General Mntnc & RPR",
    "wof:placetype":"venue"
},
  "geometry": {"coordinates":[-105.08978,40.162318],"type":"Point"}
}