{
  "type": "Feature",
  "properties": {
    "iso:country":"US",
    "sg:address":"23 Old Town Sq",
    "sg:city":"Fort Collins",
    "sg:classifiers":[
        {
            "category":"Restaurant",
            "type":"Food & Drink"
        }
    ],
    "sg:phone":"+1 970 224 0888",
    "sg:postcode":"80524",
    "sg:province":"CO",
    "sg:website":"www.mystiqultralounge.com",
    "wof:name":"Mystiq Ultra Lounge",
    "wof:placetype":"venue"
},
  "geometry": {"coordinates":[-105.075452,40.58802],"type":"Point"}
}