{
  "type": "Feature",
  "properties": {
    "addr:full":"7707 Ralston Rd Arvada CO 80002",
    "addr:housenumber":"7707",
    "addr:postcode":"80002",
    "addr:street":"Ralston Rd",
    "iso:country":"US",
    "sg:address":"7707 Ralston Rd",
    "sg:city":"Arvada",
    "sg:classifiers":[
        {
            "category":"Insurance",
            "subcategory":"Insurance Agent",
            "type":"Services"
        }
    ],
    "sg:phone":"+1 303 420 4766",
    "sg:postcode":"80002",
    "sg:province":"CO",
    "wof:name":"Stolte Insurance",
    "wof:placetype":"venue"
},
  "geometry": {"coordinates":[-105.083691,39.802075],"type":"Point"}
}