{
  "type": "Feature",
  "properties": {
    "iso:country":"US",
    "sg:address":"2056 S Co Rd 7",
    "sg:city":"Loveland",
    "sg:classifiers":[
        {
            "category":"Farming",
            "subcategory":"Dairy Farm",
            "type":"Manufacturing & Wholesale Goods"
        }
    ],
    "sg:phone":"+1 970 667 5470",
    "sg:postcode":"80537",
    "sg:province":"CO",
    "wof:name":"Longmont Dairy Farm Inc",
    "wof:placetype":"venue"
},
  "geometry": {"coordinates":[-105.002459,40.363723],"type":"Point"}
}