{
  "type": "Feature",
  "properties": {
    "addr:full":"5630 Pennsylvania Ave Boulder CO 80303",
    "addr:housenumber":"5630",
    "addr:postcode":"80303",
    "addr:street":"Pennsylvania Ave",
    "iso:country":"US",
    "sg:address":"5630 Pennsylvania Ave",
    "sg:city":"Boulder",
    "sg:classifiers":[
        {
            "category":"Banks & Credit Unions",
            "subcategory":"Investment Brokerage",
            "type":"Services"
        }
    ],
    "sg:phone":"+1 303 494 9311",
    "sg:postcode":"80303",
    "sg:province":"CO",
    "sg:tags":[
        "security"
    ],
    "wof:name":"Edward Jones 28853",
    "wof:placetype":"venue"
},
  "geometry": {"coordinates":[-105.222857,40.005891],"type":"Point"}
}