{
  "type": "Feature",
  "properties": {
    "iso:country":"US",
    "sg:address":"999 18th St",
    "sg:city":"Denver",
    "sg:classifiers":[
        {
            "category":"Professional",
            "subcategory":"Computer Services",
            "type":"Services"
        }
    ],
    "sg:phone":"+1 303 293 2911",
    "sg:postcode":"80206",
    "sg:province":"CO",
    "sg:tags":[
        "prepackaged",
        "custom",
        "programing",
        "software"
    ],
    "wof:name":"Information Structures Inc",
    "wof:placetype":"venue"
},
  "geometry": {"coordinates":[-104.99151999999999,39.748394],"type":"Point"}
}