{
  "type": "Feature",
  "properties": {
    "iso:country":"US",
    "sg:address":"7399 S Tucson Way",
    "sg:city":"Centennial",
    "sg:classifiers":[
        {
            "category":"Professional",
            "type":"Services"
        }
    ],
    "sg:phone":"+1 303 708 8000",
    "sg:postcode":"80112",
    "sg:province":"CO",
    "sg:tags":[
        "establishment"
    ],
    "wof:name":"Itex Inc",
    "wof:placetype":"venue"
},
  "geometry": {"coordinates":[-104.836483,39.583265],"type":"Point"}
}