{
  "type": "Feature",
  "properties": {
    "addr:full":"483 E Purcell Plz Pueblo CO 81007",
    "addr:housenumber":"483",
    "addr:postcode":"81007",
    "addr:street":"E Purcell Plz",
    "iso:country":"US",
    "sg:address":"483 E Purcell Plz",
    "sg:city":"Pueblo",
    "sg:phone":"+1 719 547 0181",
    "sg:postcode":"81007",
    "sg:province":"CO",
    "sg:tags":[
        "petroleum",
        "electrical",
        "install",
        "equipment"
    ],
    "wof:name":"Petroleum & Electric Cnstr",
    "wof:placetype":"venue"
},
  "geometry": {"coordinates":[-104.719033,38.309738],"type":"Point"}
}