{
  "type": "Feature",
  "properties": {
    "iso:country":"US",
    "sg:address":"1900 Wazee St",
    "sg:city":"Denver",
    "sg:classifiers":[
        {
            "category":"Professional",
            "subcategory":"Lawyer & Legal Services",
            "type":"Services"
        }
    ],
    "sg:phone":"+1 303 298 8603",
    "sg:postcode":"80202",
    "sg:province":"CO",
    "wof:name":"Schimberg Timothy",
    "wof:placetype":"venue"
},
  "geometry": {"coordinates":[-104.996002,39.754002],"type":"Point"}
}