{
  "type": "Feature",
  "properties": {
    "addr:full":"3830 W 10th St Greeley CO 80634",
    "addr:housenumber":"3830",
    "addr:postcode":"80634",
    "addr:street":"W 10Th St",
    "iso:country":"US",
    "sg:address":"3830 W 10th St",
    "sg:city":"Greeley",
    "sg:classifiers":[
        {
            "category":"Health Services",
            "subcategory":"Clinic",
            "type":"Services"
        }
    ],
    "sg:phone":"+1 970 346 1817",
    "sg:postcode":"80634",
    "sg:province":"CO",
    "wof:name":"Health First Clinic",
    "wof:placetype":"venue"
},
  "geometry": {"coordinates":[-104.744764,40.422012],"type":"Point"}
}