{
  "type": "Feature",
  "properties": {
    "addr:full":"135 Deer Trl Pagosa Springs CO 81147",
    "addr:housenumber":"135",
    "addr:postcode":"81147",
    "addr:street":"Deer Trl",
    "iso:country":"US",
    "sg:address":"135 Deer Trl",
    "sg:city":"Pagosa Springs",
    "sg:classifiers":[
        {
            "category":"Shopping",
            "subcategory":"Books",
            "type":"Retail Goods"
        }
    ],
    "sg:phone":"+1 970 731 6020",
    "sg:postcode":"81147",
    "sg:province":"CO",
    "sg:tags":[
        "dealer"
    ],
    "wof:name":"Wolftracks Bookstore & Coffee",
    "wof:placetype":"venue"
},
  "geometry": {"coordinates":[-107.167001,37.239741],"type":"Point"}
}