{
  "type": "Feature",
  "properties": {
    "iso:country":"US",
    "sg:address":"2410 N Grand Ave",
    "sg:city":"Pueblo",
    "sg:classifiers":[
        {
            "category":"Health Services",
            "subcategory":"Clinic",
            "type":"Services"
        }
    ],
    "sg:phone":"+1 719 561 2616",
    "sg:postcode":"81003",
    "sg:province":"CO",
    "sg:tags":[
        "aids",
        "testing",
        "information"
    ],
    "wof:name":"Southern Colorado Aids Project",
    "wof:placetype":"venue"
},
  "geometry": {"coordinates":[-104.611929,38.292397],"type":"Point"}
}