{
  "type": "Feature",
  "properties": {
    "addr:full":"2863 35th Ave Greeley CO 80634",
    "addr:housenumber":"2863",
    "addr:postcode":"80634",
    "addr:street":"35Th Ave",
    "iso:country":"US",
    "sg:address":"2863 35th Ave",
    "sg:city":"Greeley",
    "sg:classifiers":[
        {
            "category":"Shopping",
            "subcategory":"Books",
            "type":"Retail Goods"
        }
    ],
    "sg:phone":"+1 970 506 9692",
    "sg:postcode":"80634",
    "sg:province":"CO",
    "sg:tags":[
        "music"
    ],
    "wof:name":"Borders",
    "wof:placetype":"venue"
},
  "geometry": {"coordinates":[-104.734973,40.392145],"type":"Point"}
}