{
  "type": "Feature",
  "properties": {
    "addr:full":"525 S 4th Ave Brighton CO 80601",
    "addr:housenumber":"525",
    "addr:postcode":"80601",
    "addr:street":"S 4Th Ave",
    "iso:country":"US",
    "sg:address":"525 S 4th Ave",
    "sg:city":"Brighton",
    "sg:classifiers":[
        {
            "category":"Personal",
            "subcategory":"Barber",
            "type":"Services"
        }
    ],
    "sg:phone":"+1 303 659 1658",
    "sg:postcode":"80601",
    "sg:province":"CO",
    "wof:name":"Phil's Matador Barbers",
    "wof:placetype":"venue"
},
  "geometry": {"coordinates":[-104.818185,39.977792],"type":"Point"}
}