{
  "type": "Feature",
  "properties": {
    "addr:full":"2717 Co Rd 215 Parachute CO 81635",
    "addr:housenumber":"2717;215",
    "addr:postcode":"81635",
    "addr:street":"Co Rd",
    "iso:country":"US",
    "sg:address":"2717 Co Rd 215",
    "sg:city":"Parachute",
    "sg:classifiers":[
        {
            "category":"Utilities",
            "subcategory":"Natural Gas",
            "type":"Services"
        }
    ],
    "sg:phone":"+1 970 625 4209",
    "sg:postcode":"81635",
    "sg:province":"CO",
    "sg:tags":[
        "company"
    ],
    "wof:name":"Encana Oil & Gas USA",
    "wof:placetype":"venue"
},
  "geometry": {"coordinates":[-108.09781700000001,39.477363],"type":"Point"}
}