{
  "type": "Feature",
  "properties": {
    "addr:full":"69 Edwards Access Rd #6 Edwards CO 81632",
    "addr:housenumber":"69",
    "addr:postcode":"81632",
    "addr:street":"Edwards Access Rd # 6 Edwards",
    "iso:country":"US",
    "sg:address":"69 Edwards Access Rd #6",
    "sg:city":"Edwards",
    "sg:classifiers":[
        {
            "category":"Restaurant",
            "type":"Food & Drink"
        }
    ],
    "sg:menulink":"http://www.allmenus.com/co/minturn-red-cliff/269890-matthews---edwards/menu/",
    "sg:phone":"+1 970 926 8646",
    "sg:postcode":"81632",
    "sg:province":"CO",
    "wof:name":"Matthew's - Edwards",
    "wof:placetype":"venue"
},
  "geometry": {"coordinates":[-106.59324599999999,39.645115],"type":"Point"}
}