{
  "type": "Feature",
  "properties": {
    "addr:full":"1645 Court Pl Denver CO 80202",
    "addr:housenumber":"1645",
    "addr:postcode":"80202",
    "addr:street":"Court Pl",
    "iso:country":"US",
    "sg:address":"1645 Court Pl",
    "sg:city":"Denver",
    "sg:classifiers":[
        {
            "category":"Professional",
            "type":"Services"
        }
    ],
    "sg:phone":"+1 720 946 9239",
    "sg:postcode":"80202",
    "sg:province":"CO",
    "sg:tags":[
        "consultant",
        "geological"
    ],
    "wof:name":"Richard D Robertson",
    "wof:placetype":"venue"
},
  "geometry": {"coordinates":[-104.988542,39.742711],"type":"Point"}
}