{
  "type": "Feature",
  "properties": {
    "iso:country":"US",
    "sg:address":"266 Pinto St",
    "sg:city":"Golden",
    "sg:classifiers":[
        {
            "category":"Building & Trades",
            "subcategory":"Construction",
            "type":"Services"
        }
    ],
    "sg:phone":"+1 303 216 1512",
    "sg:postcode":"80401",
    "sg:province":"CO",
    "sg:tags":[
        "house"
    ],
    "wof:name":"Highmark Services Inc",
    "wof:placetype":"venue"
},
  "geometry": {"coordinates":[-105.201654,39.722096],"type":"Point"}
}