{
  "type": "Feature",
  "properties": {
    "addr:full":"910 Meeker St Longmont CO 80501",
    "addr:housenumber":"910",
    "addr:postcode":"80501",
    "addr:street":"Meeker St",
    "iso:country":"US",
    "sg:address":"910 Meeker St",
    "sg:city":"Longmont",
    "sg:classifiers":[
        {
            "category":"Building & Trades",
            "subcategory":"Construction",
            "type":"Services"
        }
    ],
    "sg:phone":"+1 303 485 8258",
    "sg:postcode":"80501",
    "sg:province":"CO",
    "sg:tags":[
        "residential"
    ],
    "wof:name":"Smithers Brothers Co",
    "wof:placetype":"venue"
},
  "geometry": {"coordinates":[-105.085825,40.174287],"type":"Point"}
}