{
  "type": "Feature",
  "properties": {
    "addr:full":"32481 N Elbert Rd Kiowa CO 80117",
    "addr:housenumber":"32481",
    "addr:postcode":"80117",
    "addr:street":"N Elbert Rd",
    "iso:country":"US",
    "sg:address":"32481 N Elbert Rd",
    "sg:city":"Kiowa",
    "sg:phone":"+1 303 621 2860",
    "sg:postcode":"80117",
    "sg:province":"CO",
    "sg:tags":[
        "oil",
        "gasoline"
    ],
    "wof:name":"A One Petroleum Inc",
    "wof:placetype":"venue"
},
  "geometry": {"coordinates":[-104.48075900000001,39.338227],"type":"Point"}
}