{
  "type": "Feature",
  "properties": {
    "iso:country":"US",
    "sg:address":"5565 E Amherst Ave",
    "sg:city":"Denver",
    "sg:classifiers":[
        {
            "category":"Education",
            "subcategory":"Special Training",
            "type":"Public Place"
        }
    ],
    "sg:phone":"+1 303 692 1801",
    "sg:postcode":"80222",
    "sg:province":"CO",
    "sg:tags":[
        "tutoring"
    ],
    "wof:name":"Club Z In Home Tutoring Svc",
    "wof:placetype":"venue"
},
  "geometry": {"coordinates":[-104.923046,39.666631],"type":"Point"}
}