{
  "type": "Feature",
  "properties": {
    "addr:full":"413 Cam del Mundo Fort Collins CO 80524",
    "addr:housenumber":"413",
    "addr:postcode":"80524",
    "addr:street":"Cam Del Mundo",
    "iso:country":"US",
    "sg:address":"413 Cam del Mundo",
    "sg:city":"Fort Collins",
    "sg:classifiers":[
        {
            "category":"Home & Garden",
            "subcategory":"Mobile Homes",
            "type":"Retail Goods"
        }
    ],
    "sg:phone":"+1 970 493 1125",
    "sg:postcode":"80524",
    "sg:province":"CO",
    "wof:name":"Pine Lake Village LLC",
    "wof:placetype":"venue"
},
  "geometry": {"coordinates":[-104.988353,40.582416],"type":"Point"}
}