{
  "type": "Feature",
  "properties": {
    "iso:country":"US",
    "sg:address":"1428 N Circle Dr",
    "sg:city":"Colorado Springs",
    "sg:classifiers":[
        {
            "category":"Insurance",
            "subcategory":"Insurance Agent",
            "type":"Services"
        }
    ],
    "sg:phone":"+1 719 632 0607",
    "sg:postcode":"80909",
    "sg:province":"CO",
    "sg:tags":[
        "broker"
    ],
    "wof:name":"Shelter Insurance",
    "wof:placetype":"venue"
},
  "geometry": {"coordinates":[-104.775876,38.854222],"type":"Point"}
}