{
  "type": "Feature",
  "properties": {
    "addr:full":"860 E 29th St Loveland CO 80538",
    "addr:housenumber":"860",
    "addr:postcode":"80538",
    "addr:street":"E 29Th St",
    "iso:country":"US",
    "sg:address":"860 E 29th St",
    "sg:city":"Loveland",
    "sg:classifiers":[
        {
            "category":"Education",
            "subcategory":"School",
            "type":"Public Place"
        }
    ],
    "sg:phone":"+1 970 613 6400",
    "sg:postcode":"80538",
    "sg:province":"CO",
    "sg:tags":[
        "elementary"
    ],
    "wof:name":"Mary Blair Elementary School",
    "wof:placetype":"venue"
},
  "geometry": {"coordinates":[-105.065326,40.42173],"type":"Point"}
}