{
  "type": "Feature",
  "properties": {
    "addr:full":"1333 Coho Run Fort Collins CO 80524",
    "addr:housenumber":"1333",
    "addr:postcode":"80524",
    "addr:street":"Coho Run",
    "iso:country":"US",
    "sg:address":"1333 Coho Run",
    "sg:city":"Fort Collins",
    "sg:classifiers":[
        {
            "category":"Real Estate",
            "subcategory":"Real Estate Agent",
            "type":"Services"
        }
    ],
    "sg:phone":"+1 970 493 5689",
    "sg:postcode":"80524",
    "sg:province":"CO",
    "wof:name":"Trost Family Ltd",
    "wof:placetype":"venue"
},
  "geometry": {"coordinates":[-104.975054,40.598629],"type":"Point"}
}