{
  "type": "Feature",
  "properties": {
    "addr:full":"5116 Alta Loma Rd Colorado Springs CO 80918",
    "addr:housenumber":"5116",
    "addr:postcode":"80918",
    "addr:street":"Alta Loma Rd",
    "iso:country":"US",
    "sg:address":"5116 Alta Loma Rd",
    "sg:city":"Colorado Springs",
    "sg:classifiers":[
        {
            "category":"Shopping",
            "type":"Retail Goods"
        }
    ],
    "sg:phone":"+1 719 593 8620",
    "sg:postcode":"80918",
    "sg:province":"CO",
    "sg:tags":[
        "cosmetic",
        "perfume"
    ],
    "wof:name":"Mary Kay Cosmetics",
    "wof:placetype":"venue"
},
  "geometry": {"coordinates":[-104.752779,38.905024],"type":"Point"}
}