{
  "type": "Feature",
  "properties": {
    "iso:country":"US",
    "sg:address":"2598 Palmer Park Blvd",
    "sg:city":"Colorado Springs",
    "sg:classifiers":[
        {
            "category":"Building & Trades",
            "subcategory":"Construction",
            "type":"Services"
        }
    ],
    "sg:phone":"+1 719 520 5100",
    "sg:postcode":"80909",
    "sg:province":"CO",
    "sg:tags":[
        "general",
        "nonresidential",
        "contractor"
    ],
    "sg:website":"www.highlandbuilders.com",
    "wof:name":"Highland Builders Corporation",
    "wof:placetype":"venue"
},
  "geometry": {"coordinates":[-104.78154499999999,38.854202],"type":"Point"}
}