{
  "type": "Feature",
  "properties": {
    "addr:full":"2813 Hall Ave Grand Junction CO 81501",
    "addr:housenumber":"2813",
    "addr:postcode":"81501",
    "addr:street":"Hall Ave",
    "iso:country":"US",
    "sg:address":"2813 Hall Ave",
    "sg:city":"Grand Junction",
    "sg:classifiers":[
        {
            "category":"Manufacturing",
            "subcategory":"Toys & Sporting Goods",
            "type":"Manufacturing & Wholesale Goods"
        }
    ],
    "sg:phone":"+1 970 241 6897",
    "sg:postcode":"81501",
    "sg:province":"CO",
    "sg:tags":[
        "mfg"
    ],
    "wof:name":"Quad-Cycle LLC",
    "wof:placetype":"venue"
},
  "geometry": {"coordinates":[-108.529073,39.084144],"type":"Point"}
}