{
  "type": "Feature",
  "properties": {
    "iso:country":"US",
    "sg:address":"7800 W Jewell Avenue",
    "sg:city":"Lakewood",
    "sg:classifiers":[
        {
            "category":"Autos & Motor Vehicles",
            "subcategory":"Automobile Sales",
            "type":"Retail Goods"
        },
        {
            "category":"Airline",
            "type":"Transportation"
        }
    ],
    "sg:phone":"+1 303 986 9449",
    "sg:postcode":"80232",
    "sg:province":"CO",
    "sg:tags":[
        "shuttle",
        "airport",
        "limo"
    ],
    "sg:website":"www.a-championlimousine.com",
    "wof:name":"Champion Limousine",
    "wof:placetype":"venue"
},
  "geometry": {"coordinates":[-105.08286200000001,39.682073],"type":"Point"}
}