{
  "type": "Feature",
  "properties": {
    "iso:country":"US",
    "sg:address":"711 Grand Ave",
    "sg:city":"Glenwood Springs",
    "sg:classifiers":[
        {
            "category":"Organizations",
            "subcategory":"Non-profit Organization",
            "type":"Services"
        }
    ],
    "sg:phone":"+1 970 945 8439",
    "sg:postcode":"81601",
    "sg:province":"CO",
    "sg:tags":[
        "information",
        "alcoholism",
        "treatment"
    ],
    "sg:website":"www.cwrmhc.org",
    "wof:name":"Colorado West Recovery Ctr",
    "wof:placetype":"venue"
},
  "geometry": {"coordinates":[-107.324758,39.547614],"type":"Point"}
}