{
  "type": "Feature",
  "properties": {
    "iso:country":"US",
    "sg:address":"710 Cooper Ave",
    "sg:city":"Glenwood Springs",
    "sg:classifiers":[
        {
            "category":"Personal",
            "subcategory":"Beauty Salon",
            "type":"Services"
        }
    ],
    "sg:phone":"+1 970 945 2844",
    "sg:postcode":"81601",
    "sg:province":"CO",
    "sg:tags":[
        "treatment",
        "skin"
    ],
    "wof:name":"Patricia's Essential Skin Care",
    "wof:placetype":"venue"
},
  "geometry": {"coordinates":[-107.323579,39.547707],"type":"Point"}
}