{
  "type": "Feature",
  "properties": {
    "iso:country":"US",
    "sg:address":"2480 S Downing St",
    "sg:city":"Denver",
    "sg:classifiers":[
        {
            "category":"Health Services",
            "subcategory":"Doctor",
            "type":"Services"
        }
    ],
    "sg:phone":"+1 303 777 3277",
    "sg:postcode":"80210",
    "sg:province":"CO",
    "wof:name":"Center For Hines-Sight",
    "wof:placetype":"venue"
},
  "geometry": {"coordinates":[-104.973377,39.672773],"type":"Point"}
}