{
  "type": "Feature",
  "properties": {
    "addr:full":"313 3rd St La Junta CO 81050",
    "addr:housenumber":"313",
    "addr:postcode":"81050",
    "addr:street":"3Rd St",
    "iso:country":"US",
    "sg:address":"313 3rd St",
    "sg:city":"La Junta",
    "sg:classifiers":[
        {
            "category":"Health Services",
            "subcategory":"Optometrist",
            "type":"Services"
        }
    ],
    "sg:phone":"+1 719 384 2582",
    "sg:postcode":"81050",
    "sg:province":"CO",
    "wof:name":"Donald S Swanz OD",
    "wof:placetype":"venue"
},
  "geometry": {"coordinates":[-103.62848200000001,38.014558],"type":"Point"}
}