{
  "type": "Feature",
  "properties": {
    "iso:country":"US",
    "sg:address":"2450 E 13th St",
    "sg:city":"Loveland",
    "sg:classifiers":[
        {
            "category":"Mining & Drilling",
            "type":"Manufacturing & Wholesale Goods"
        }
    ],
    "sg:phone":"+1 970 667 1039",
    "sg:postcode":"80537",
    "sg:province":"CO",
    "sg:tags":[
        "field",
        "oil"
    ],
    "sg:website":"www.teamindustrialservices.com",
    "wof:name":"Team Inc",
    "wof:placetype":"venue"
},
  "geometry": {"coordinates":[-105.041257,40.405076],"type":"Point"}
}