{
  "type": "Feature",
  "properties": {
    "addr:full":"1406 S Nevada Ave Colorado Springs CO 80906",
    "addr:housenumber":"1406",
    "addr:postcode":"80906",
    "addr:street":"S Nevada Ave",
    "iso:country":"US",
    "sg:address":"1406 S Nevada Ave",
    "sg:city":"Colorado Springs",
    "sg:classifiers":[
        {
            "category":"Banks & Credit Unions",
            "subcategory":"Bank",
            "type":"Services"
        }
    ],
    "sg:phone":"+1 719 634 4268",
    "sg:postcode":"80906",
    "sg:province":"CO",
    "sg:tags":[
        "depository",
        "banking"
    ],
    "wof:name":"Alicia & Lyndi Inc",
    "wof:placetype":"venue"
},
  "geometry": {"coordinates":[-104.822425,38.813152],"type":"Point"}
}