{
  "type": "Feature",
  "properties": {
    "addr:full":"541 Ridgestone Ct Grand Junction CO 81503",
    "addr:housenumber":"541",
    "addr:postcode":"81503",
    "addr:street":"Ridgestone Ct",
    "iso:country":"US",
    "sg:address":"541 Ridgestone Ct",
    "sg:city":"Grand Junction",
    "sg:classifiers":[
        {
            "category":"Real Estate",
            "subcategory":"Surveying",
            "type":"Services"
        }
    ],
    "sg:phone":"+1 970 242 8298",
    "sg:postcode":"81503",
    "sg:province":"CO",
    "sg:tags":[
        "surveyor"
    ],
    "wof:name":"Cartographic Edge",
    "wof:placetype":"venue"
},
  "geometry": {"coordinates":[-108.626661,39.082691],"type":"Point"}
}