{
  "type": "Feature",
  "properties": {
    "iso:country":"US",
    "sg:address":"2413 Washington St",
    "sg:city":"Denver",
    "sg:classifiers":[
        {
            "category":"Banks & Credit Unions",
            "subcategory":"Investment Brokerage",
            "type":"Services"
        }
    ],
    "sg:phone":"+1 303 292 4020",
    "sg:postcode":"80205",
    "sg:province":"CO",
    "sg:tags":[
        "advisory"
    ],
    "wof:name":"Mfs Corporation",
    "wof:placetype":"venue"
},
  "geometry": {"coordinates":[-104.978261,39.752782],"type":"Point"}
}