{
  "type": "Feature",
  "properties": {
    "iso:country":"US",
    "sg:address":"13256 Co Rd P",
    "sg:city":"La Jara",
    "sg:classifiers":[
        {
            "category":"Building & Trades",
            "subcategory":"Construction",
            "type":"Services"
        }
    ],
    "sg:phone":"+1 719 843 5790",
    "sg:postcode":"81140",
    "sg:province":"CO",
    "sg:tags":[
        "contractor"
    ],
    "wof:name":"J G Insulating",
    "wof:placetype":"venue"
},
  "geometry": {"coordinates":[-106.014084,37.18186],"type":"Point"}
}