{
  "type": "Feature",
  "properties": {
    "iso:country":"US",
    "sg:address":"177 Summitview Cir",
    "sg:city":"Parker",
    "sg:classifiers":[
        {
            "category":"Building & Trades",
            "subcategory":"Plumbing",
            "type":"Services"
        }
    ],
    "sg:phone":"+1 303 873 7469",
    "sg:postcode":"80138",
    "sg:province":"CO",
    "sg:tags":[
        "contractor"
    ],
    "wof:name":"L & L Heating & A/C",
    "wof:placetype":"venue"
},
  "geometry": {"coordinates":[-104.657906,39.48882],"type":"Point"}
}