{
  "type": "Feature",
  "properties": {
    "iso:country":"US",
    "sg:address":"26 W Dry Creek Cir",
    "sg:city":"Littleton",
    "sg:classifiers":[
        {
            "category":"Professional",
            "subcategory":"Computer Services",
            "type":"Services"
        }
    ],
    "sg:phone":"+1 303 420 4218",
    "sg:postcode":"80120",
    "sg:province":"CO",
    "sg:tags":[
        "website",
        "design"
    ],
    "wof:name":"Whitestone Bridge Group Corp",
    "wof:placetype":"venue"
},
  "geometry": {"coordinates":[-104.991429,39.581897],"type":"Point"}
}