{
  "type": "Feature",
  "properties": {
    "iso:country":"US",
    "sg:address":"1580 Logan Street Suite 510",
    "sg:city":"Denver",
    "sg:classifiers":[
        {
            "category":"Banks & Credit Unions",
            "subcategory":"Bank",
            "type":"Services"
        }
    ],
    "sg:phone":"+1 303 832 2000",
    "sg:postcode":"80203",
    "sg:province":"CO",
    "wof:name":"Independent Bankers of Colorado Ibc",
    "wof:placetype":"venue"
},
  "geometry": {"coordinates":[-104.982315,39.741253],"type":"Point"}
}