{
  "type": "Feature",
  "properties": {
    "iso:country":"US",
    "sg:address":"1780 S Bellaire Street",
    "sg:city":"Denver",
    "sg:classifiers":[
        {
            "category":"Real Estate",
            "subcategory":"Real Estate Services",
            "type":"Services"
        }
    ],
    "sg:phone":"+1 303 758 4355",
    "sg:postcode":"80222",
    "sg:province":"CO",
    "sg:website":"www.miralagoatmarstonlake.com",
    "wof:name":"Skyline Management",
    "wof:placetype":"venue"
},
  "geometry": {"coordinates":[-104.937291,39.684539],"type":"Point"}
}