{
  "type": "Feature",
  "properties": {
    "iso:country":"US",
    "sg:address":"11084 W Hinsdale Dr",
    "sg:city":"Littleton",
    "sg:classifiers":[
        {
            "category":"Wholesale",
            "subcategory":"Non-durable Goods",
            "type":"Manufacturing & Wholesale Goods"
        }
    ],
    "sg:phone":"+1 303 972 8485",
    "sg:postcode":"80127",
    "sg:province":"CO",
    "wof:name":"Majestic Packaging",
    "wof:placetype":"venue"
},
  "geometry": {"coordinates":[-105.122398,39.58347],"type":"Point"}
}