{
  "type": "Feature",
  "properties": {
    "iso:country":"US",
    "sg:address":"2024 W 37th Ave",
    "sg:city":"Denver",
    "sg:classifiers":[
        {
            "category":"Professional",
            "subcategory":"Engineering",
            "type":"Services"
        },
        {
            "category":"Real Estate",
            "subcategory":"Architect",
            "type":"Services"
        }
    ],
    "sg:phone":"+1 303 955 4945",
    "sg:postcode":"80211",
    "sg:province":"CO",
    "sg:tags":[
        "architects'",
        "consulting",
        "consultant",
        "specification",
        "builders'",
        "construction",
        "architectural",
        "conservation",
        "energy",
        "engineer"
    ],
    "sg:website":"http://www.dalglishdaylighting.com",
    "wof:name":"Dalglish Daylighting",
    "wof:placetype":"venue"
},
  "geometry": {"coordinates":[-105.012081,39.767798],"type":"Point"}
}