{
  "type": "Feature",
  "properties": {
    "addr:full":"3912 Orchard Ct Boulder CO 80304",
    "addr:housenumber":"3912",
    "addr:postcode":"80304",
    "addr:street":"Orchard Ct",
    "iso:country":"US",
    "sg:address":"3912 Orchard Ct",
    "sg:city":"Boulder",
    "sg:classifiers":[
        {
            "category":"Shopping",
            "subcategory":"Shoes",
            "type":"Retail Goods"
        }
    ],
    "sg:phone":"+1 303 442 8084",
    "sg:postcode":"80304",
    "sg:province":"CO",
    "wof:name":"AR Nicholson Ltd",
    "wof:placetype":"venue"
},
  "geometry": {"coordinates":[-105.286708,40.045697],"type":"Point"}
}