{
  "type": "Feature",
  "properties": {
    "iso:country":"US",
    "sg:address":"2005 Falls Ct",
    "sg:city":"Loveland",
    "sg:classifiers":[
        {
            "category":"Real Estate",
            "subcategory":"Real Estate Operator",
            "type":"Services"
        }
    ],
    "sg:phone":"+1 970 635 9588",
    "sg:postcode":"80538",
    "sg:province":"CO",
    "sg:tags":[
        "building",
        "nonresidential"
    ],
    "wof:name":"Juliana Properties LLC",
    "wof:placetype":"venue"
},
  "geometry": {"coordinates":[-105.12143399999999,40.41333],"type":"Point"}
}