{
  "type": "Feature",
  "properties": {
    "addr:full":"5323 Fossil Ridge Dr Fort Collins CO 80525",
    "addr:housenumber":"5323",
    "addr:postcode":"80525",
    "addr:street":"Fossil Ridge Dr",
    "iso:country":"US",
    "sg:address":"5323 Fossil Ridge Dr",
    "sg:city":"Fort Collins",
    "sg:classifiers":[
        {
            "category":"Mining & Drilling",
            "type":"Manufacturing & Wholesale Goods"
        }
    ],
    "sg:phone":"+1 970 204 1044",
    "sg:postcode":"80525",
    "sg:province":"CO",
    "sg:tags":[
        "company"
    ],
    "wof:name":"Excalibur Industries",
    "wof:placetype":"venue"
},
  "geometry": {"coordinates":[-105.075594,40.512398],"type":"Point"}
}