{
  "type": "Feature",
  "properties": {
    "iso:country":"US",
    "sg:address":"5251 Dtc Pkwy",
    "sg:city":"Englewood",
    "sg:classifiers":[
        {
            "category":"Restaurant",
            "type":"Food & Drink"
        }
    ],
    "sg:phone":"+1 303 779 0444",
    "sg:postcode":"80111",
    "sg:province":"CO",
    "sg:tags":[
        "eating"
    ],
    "wof:name":"McDonalds",
    "wof:placetype":"venue"
},
  "geometry": {"coordinates":[-104.89943700000001,39.62284],"type":"Point"}
}