{
  "type": "Feature",
  "properties": {
    "addr:full":"3747 Wonderland Hill Ave Boulder CO 80304",
    "addr:housenumber":"3747",
    "addr:postcode":"80304",
    "addr:street":"Wonderland Hill Ave",
    "iso:country":"US",
    "sg:address":"3747 Wonderland Hill Ave",
    "sg:city":"Boulder",
    "sg:classifiers":[
        {
            "category":"Real Estate",
            "subcategory":"Real Estate Operator",
            "type":"Services"
        }
    ],
    "sg:phone":"+1 303 443 5638",
    "sg:postcode":"80304",
    "sg:province":"CO",
    "sg:tags":[
        "building",
        "nonresidential"
    ],
    "wof:name":"Ria Properties LLP",
    "wof:placetype":"venue"
},
  "geometry": {"coordinates":[-105.289046,40.04318],"type":"Point"}
}