{
  "type": "Feature",
  "properties": {
    "addr:full":"223 Main St Limon CO 80828",
    "addr:housenumber":"223",
    "addr:postcode":"80828",
    "addr:street":"Main St",
    "iso:country":"US",
    "sg:address":"223 Main St",
    "sg:city":"Limon",
    "sg:classifiers":[
        {
            "category":"Real Estate",
            "subcategory":"Real Estate Services",
            "type":"Services"
        }
    ],
    "sg:phone":"+1 719 740 0465",
    "sg:postcode":"80828",
    "sg:province":"CO",
    "sg:tags":[
        "company",
        "title"
    ],
    "wof:name":"Homestead Title Co",
    "wof:placetype":"venue"
},
  "geometry": {"coordinates":[-103.678916,39.262868],"type":"Point"}
}