{
  "type": "Feature",
  "properties": {
    "iso:country":"US",
    "sg:address":"925 Lincoln St",
    "sg:city":"Denver",
    "sg:classifiers":[
        {
            "category":"Sports & Exercise",
            "subcategory":"Gym",
            "type":"Entertainment"
        }
    ],
    "sg:phone":"+1 303 863 7770",
    "sg:postcode":"80203",
    "sg:province":"CO",
    "sg:tags":[
        "club",
        "gymnasium",
        "health",
        "spa",
        "studio",
        "day"
    ],
    "sg:website":"www.matrixfitnessandspa.com",
    "wof:name":"Matrix Fitness & Spa",
    "wof:placetype":"venue"
},
  "geometry": {"coordinates":[-104.98616,39.730851],"type":"Point"}
}