{
  "type": "Feature",
  "properties": {
    "addr:full":"6982 Hunter Pl Boulder CO 80301",
    "addr:housenumber":"6982",
    "addr:postcode":"80301",
    "addr:street":"Hunter Pl",
    "iso:country":"US",
    "sg:address":"6982 Hunter Pl",
    "sg:city":"Boulder",
    "sg:classifiers":[
        {
            "category":"Professional",
            "subcategory":"Computer Services",
            "type":"Services"
        },
        {
            "category":"Shopping",
            "subcategory":"Computers & Home Electronics",
            "type":"Retail Goods"
        }
    ],
    "sg:phone":"+1 303 530 2112",
    "sg:postcode":"80301",
    "sg:province":"CO",
    "sg:tags":[
        "software",
        "design",
        "system",
        "programing",
        "custom"
    ],
    "sg:website":"www.granitesystems.com",
    "wof:name":"Granite Systems Inc",
    "wof:placetype":"venue"
},
  "geometry": {"coordinates":[-105.192033,40.071712],"type":"Point"}
}