{
  "type": "Feature",
  "properties": {
    "addr:full":"125 N Campbell Ave Holyoke CO 80734",
    "addr:housenumber":"125",
    "addr:postcode":"80734",
    "addr:street":"N Campbell Ave",
    "iso:country":"US",
    "sg:address":"125 N Campbell Ave",
    "sg:city":"Holyoke",
    "sg:classifiers":[
        {
            "category":"Professional",
            "type":"Services"
        }
    ],
    "sg:phone":"+1 970 854 3111",
    "sg:postcode":"80734",
    "sg:province":"CO",
    "sg:tags":[
        "establishment"
    ],
    "wof:name":"Lions Den",
    "wof:placetype":"venue"
},
  "geometry": {"coordinates":[-102.300752,40.585864],"type":"Point"}
}