{
  "type": "Feature",
  "properties": {
    "iso:country":"US",
    "sg:address":"1103 State Hwy 402",
    "sg:city":"Loveland",
    "sg:classifiers":[
        {
            "category":"Retail",
            "subcategory":"Repair Shop",
            "type":"Services"
        },
        {
            "category":"Retail",
            "subcategory":"Auto Repair",
            "type":"Services"
        }
    ],
    "sg:phone":"+1 970 663 3053",
    "sg:postcode":"80537",
    "sg:province":"CO",
    "sg:tags":[
        "lock",
        "locksmith",
        "automotive"
    ],
    "wof:name":"Superior Towing Inc",
    "wof:placetype":"venue"
},
  "geometry": {"coordinates":[-105.05919799999999,40.378319],"type":"Point"}
}