{
  "type": "Feature",
  "properties": {
    "iso:country":"US",
    "sg:address":"2061 Main St",
    "sg:city":"Alamosa",
    "sg:classifiers":[
        {
            "category":"Banks & Credit Unions",
            "subcategory":"Bank",
            "type":"Services"
        }
    ],
    "sg:phone":"+1 719 587 2734",
    "sg:postcode":"81101",
    "sg:province":"CO",
    "wof:name":"Community Banks Of The Rockies",
    "wof:placetype":"venue"
},
  "geometry": {"coordinates":[-105.88670999999999,37.471705],"type":"Point"}
}