{
  "type": "Feature",
  "properties": {
    "addr:full":"6296 W 68th Pl Arvada CO 80003",
    "addr:housenumber":"6296",
    "addr:postcode":"80003",
    "addr:street":"W 68Th Pl",
    "iso:country":"US",
    "sg:address":"6296 W 68th Pl",
    "sg:city":"Arvada",
    "sg:classifiers":[
        {
            "category":"Building & Trades",
            "subcategory":"Construction",
            "type":"Services"
        }
    ],
    "sg:phone":"+1 303 940 9350",
    "sg:postcode":"80003",
    "sg:province":"CO",
    "sg:tags":[
        "house"
    ],
    "wof:name":"Poltechnica",
    "wof:placetype":"venue"
},
  "geometry": {"coordinates":[-105.066425,39.821052],"type":"Point"}
}