{
  "type": "Feature",
  "properties": {
    "iso:country":"US",
    "sg:address":"9250 E Costilla Ave",
    "sg:city":"Englewood",
    "sg:classifiers":[
        {
            "category":"Manufacturing",
            "subcategory":"Rubber & Plastics",
            "type":"Manufacturing & Wholesale Goods"
        }
    ],
    "sg:phone":"+1 303 799 4721",
    "sg:postcode":"80112",
    "sg:province":"CO",
    "sg:tags":[
        "body",
        "mfg",
        "caliper",
        "fat",
        "to",
        "measure"
    ],
    "wof:name":"Accumeasure LLC",
    "wof:placetype":"venue"
},
  "geometry": {"coordinates":[-104.880101,39.591329],"type":"Point"}
}