{
  "type": "Feature",
  "properties": {
    "iso:country":"US",
    "sg:address":"565 Sherman St",
    "sg:city":"Ridgway",
    "sg:classifiers":[
        {
            "category":"Restaurant",
            "type":"Food & Drink"
        }
    ],
    "sg:phone":"+1 970 626 4486",
    "sg:postcode":"81432",
    "sg:province":"CO",
    "sg:tags":[
        "eating"
    ],
    "wof:name":"Sun Palace",
    "wof:placetype":"venue"
},
  "geometry": {"coordinates":[-107.756883,38.151511],"type":"Point"}
}