{
  "type": "Feature",
  "properties": {
    "iso:country":"US",
    "sg:address":"622 S Magnolia St",
    "sg:city":"Denver",
    "sg:classifiers":[
        {
            "category":"Building & Trades",
            "subcategory":"Electrical",
            "type":"Services"
        }
    ],
    "sg:phone":"+1 303 320 3517",
    "sg:postcode":"80224",
    "sg:province":"CO",
    "sg:tags":[
        "electrical",
        "contractor"
    ],
    "wof:name":"BAC Electrical Maintenance",
    "wof:placetype":"venue"
},
  "geometry": {"coordinates":[-104.91152599999999,39.704875],"type":"Point"}
}