{
  "type": "Feature",
  "properties": {
    "iso:country":"US",
    "sg:address":"401 Main St",
    "sg:city":"Frisco",
    "sg:classifiers":[
        {
            "category":"Professional",
            "type":"Services"
        }
    ],
    "sg:phone":"+1 970 668 3235",
    "sg:postcode":"80443",
    "sg:province":"CO",
    "sg:tags":[
        "establishment"
    ],
    "wof:name":"Summit Legacy Designs Inc",
    "wof:placetype":"venue"
},
  "geometry": {"coordinates":[-106.109993,39.575187],"type":"Point"}
}