{
  "type": "Feature",
  "properties": {
    "iso:country":"US",
    "sg:address":"3650 Endicott Dr",
    "sg:city":"Boulder",
    "sg:classifiers":[
        {
            "category":"Shopping",
            "subcategory":"Clothing, Apparel, & Fashions",
            "type":"Retail Goods"
        }
    ],
    "sg:phone":"+1 303 543 8200",
    "sg:postcode":"80305",
    "sg:province":"CO",
    "sg:tags":[
        "alteration"
    ],
    "wof:name":"Kings Langley Antiques",
    "wof:placetype":"venue"
},
  "geometry": {"coordinates":[-105.251245,39.974308],"type":"Point"}
}