{
  "type": "Feature",
  "properties": {
    "iso:country":"US",
    "sg:address":"4011 S Broadway Ste C",
    "sg:city":"Englewood",
    "sg:classifiers":[
        {
            "category":"Personal",
            "subcategory":"Barber",
            "type":"Services"
        }
    ],
    "sg:phone":"+1 303 762 0283",
    "sg:postcode":"80113",
    "sg:province":"CO",
    "wof:name":"Peggy's Barber Shop",
    "wof:placetype":"venue"
},
  "geometry": {"coordinates":[-104.987742,39.643815],"type":"Point"}
}