{
  "type": "Feature",
  "properties": {
    "addr:full":"1490 Valley St Colorado Springs CO 80915",
    "addr:housenumber":"1490",
    "addr:postcode":"80915",
    "addr:street":"Valley St",
    "iso:country":"US",
    "sg:address":"1490 Valley St",
    "sg:city":"Colorado Springs",
    "sg:classifiers":[
        {
            "category":"Building & Trades",
            "subcategory":"Equipment Rental",
            "type":"Services"
        }
    ],
    "sg:phone":"+1 719 591 8705",
    "sg:postcode":"80915",
    "sg:province":"CO",
    "sg:tags":[
        "leasing"
    ],
    "sg:website":"www.unitedrentals.com",
    "wof:name":"United Rentals",
    "wof:placetype":"venue"
},
  "geometry": {"coordinates":[-104.71388899999999,38.848062],"type":"Point"}
}