{
  "type": "Feature",
  "properties": {
    "iso:country":"US",
    "sg:address":"1010 S Joliet St",
    "sg:city":"Aurora",
    "sg:classifiers":[
        {
            "category":"Real Estate",
            "subcategory":"Real Estate Agent",
            "type":"Services"
        }
    ],
    "sg:phone":"+1 303 360 0701",
    "sg:postcode":"80012",
    "sg:province":"CO",
    "wof:name":"Marco Real Estate",
    "wof:placetype":"venue"
},
  "geometry": {"coordinates":[-104.861186,39.696756],"type":"Point"}
}