{
  "type": "Feature",
  "properties": {
    "addr:full":"5706 Arapahoe Ave Boulder CO 80303",
    "addr:housenumber":"5706",
    "addr:postcode":"80303",
    "addr:street":"Arapahoe Ave",
    "iso:country":"US",
    "sg:address":"5706 Arapahoe Ave",
    "sg:city":"Boulder",
    "sg:classifiers":[
        {
            "category":"Restaurant",
            "type":"Food & Drink"
        }
    ],
    "sg:phone":"+1 303 444 3452",
    "sg:postcode":"80303",
    "sg:province":"CO",
    "sg:tags":[
        "banquet",
        "rooms"
    ],
    "wof:name":"A Spice Of Life Event Ctr Svc",
    "wof:placetype":"venue"
},
  "geometry": {"coordinates":[-105.216487,40.014621],"type":"Point"}
}