{
  "type": "Feature",
  "properties": {
    "addr:full":"425 E Cheyenne Mountain Blvd Colorado Springs CO 80906",
    "addr:housenumber":"425",
    "addr:postcode":"80906",
    "addr:street":"E Cheyenne Mountain Blvd",
    "iso:country":"US",
    "sg:address":"425 E Cheyenne Mountain Blvd",
    "sg:city":"Colorado Springs",
    "sg:classifiers":[
        {
            "category":"Retail",
            "subcategory":"Auto Repair",
            "type":"Services"
        }
    ],
    "sg:phone":"+1 719 527 1199",
    "sg:postcode":"80906",
    "sg:province":"CO",
    "sg:tags":[
        "automobile",
        "oil",
        "change",
        "lubrication"
    ],
    "wof:name":"Grease Monkey",
    "wof:placetype":"venue"
},
  "geometry": {"coordinates":[-104.819806,38.788254],"type":"Point"}
}