{
  "type": "Feature",
  "properties": {
    "addr:full":"2290 S Joliet Way Aurora CO 80014",
    "addr:housenumber":"2290",
    "addr:postcode":"80014",
    "addr:street":"S Joliet Way",
    "iso:country":"US",
    "sg:address":"2290 S Joliet Way",
    "sg:city":"Aurora",
    "sg:classifiers":[
        {
            "category":"Freight",
            "type":"Transportation"
        }
    ],
    "sg:phone":"+1 303 752 2353",
    "sg:postcode":"80014",
    "sg:province":"CO",
    "sg:tags":[
        "local",
        "without",
        "storage",
        "trucking"
    ],
    "wof:name":"Sorli Trucking",
    "wof:placetype":"venue"
},
  "geometry": {"coordinates":[-104.86073,39.676071],"type":"Point"}
}