{
  "type": "Feature",
  "properties": {
    "iso:country":"US",
    "sg:address":"236 S Oak St",
    "sg:city":"Telluride",
    "sg:classifiers":[
        {
            "category":"Real Estate",
            "subcategory":"Real Estate Agent",
            "type":"Services"
        }
    ],
    "sg:phone":"+1 970 728 4581",
    "sg:postcode":"81435",
    "sg:province":"CO",
    "sg:tags":[
        "agency",
        "rental"
    ],
    "sg:website":"www.paragontelluride.com",
    "wof:name":"Oak Street Rentals & Svc",
    "wof:placetype":"venue"
},
  "geometry": {"coordinates":[-107.813067,37.936689],"type":"Point"}
}