{
  "type": "Feature",
  "properties": {
    "iso:country":"US",
    "sg:address":"18 Deer Valley Dr",
    "sg:city":"Glenwood Springs",
    "sg:classifiers":[
        {
            "category":"Banks & Credit Unions",
            "subcategory":"Investment Brokerage",
            "type":"Services"
        }
    ],
    "sg:phone":"+1 970 384 2722",
    "sg:postcode":"81601",
    "sg:province":"CO",
    "sg:tags":[
        "advisory"
    ],
    "wof:name":"Marshall Capital Group",
    "wof:placetype":"venue"
},
  "geometry": {"coordinates":[-107.313287,39.469698],"type":"Point"}
}