{
  "type": "Feature",
  "properties": {
    "iso:country":"US",
    "sg:address":"127 Cedar Ln",
    "sg:city":"Bailey",
    "sg:classifiers":[
        {
            "category":"Building & Trades",
            "subcategory":"Construction",
            "type":"Services"
        }
    ],
    "sg:phone":"+1 303 838 8503",
    "sg:postcode":"80421",
    "sg:province":"CO",
    "sg:tags":[
        "contractor"
    ],
    "wof:name":"Mikes Installation Inc",
    "wof:placetype":"venue"
},
  "geometry": {"coordinates":[-105.42577300000001,39.454974],"type":"Point"}
}