{
  "type": "Feature",
  "properties": {
    "addr:full":"3131 S College Ave Fort Collins CO 80525",
    "addr:housenumber":"3131",
    "addr:postcode":"80525",
    "addr:street":"S College Ave",
    "iso:country":"US",
    "sg:address":"3131 S College Ave",
    "sg:city":"Fort Collins",
    "sg:classifiers":[
        {
            "category":"Professional",
            "subcategory":"Accounting & Tax Preparation",
            "type":"Services"
        }
    ],
    "sg:phone":"+1 970 223 8486",
    "sg:postcode":"80525",
    "sg:province":"CO",
    "sg:tags":[
        "return",
        "filing"
    ],
    "wof:name":"K C's Tax Svc",
    "wof:placetype":"venue"
},
  "geometry": {"coordinates":[-105.07716499999999,40.542598],"type":"Point"}
}