{
  "type": "Feature",
  "properties": {
    "addr:full":"12265 Race St Northglenn CO 80241",
    "addr:housenumber":"12265",
    "addr:postcode":"80241",
    "addr:street":"Race St",
    "iso:country":"US",
    "sg:address":"12265 Race St",
    "sg:city":"Northglenn",
    "sg:classifiers":[
        {
            "category":"Wholesale",
            "subcategory":"Dairy",
            "type":"Manufacturing & Wholesale Goods"
        }
    ],
    "sg:phone":"+1 303 452 4152",
    "sg:postcode":"80241",
    "sg:province":"CO",
    "sg:tags":[
        "product"
    ],
    "wof:name":"Wholesome Milk Products",
    "wof:placetype":"venue"
},
  "geometry": {"coordinates":[-104.963832,39.917437],"type":"Point"}
}