{
  "type": "Feature",
  "properties": {
    "addr:full":"361 Bennett Dr Cripple Creek CO 80813",
    "addr:housenumber":"361",
    "addr:postcode":"80813",
    "addr:street":"Bennett Dr",
    "iso:country":"US",
    "sg:address":"361 Bennett Dr",
    "sg:city":"Cripple Creek",
    "sg:classifiers":[
        {
            "category":"Shopping",
            "type":"Retail Goods"
        }
    ],
    "sg:phone":"+1 719 689 0833",
    "sg:postcode":"80813",
    "sg:province":"CO",
    "sg:tags":[
        "merchandise"
    ],
    "wof:name":"Maudie S Incredible Emporium",
    "wof:placetype":"venue"
},
  "geometry": {"coordinates":[-105.199691,38.794652],"type":"Point"}
}