{
  "type": "Feature",
  "properties": {
    "addr:full":"427 N Chelton Rd Colorado Springs CO 80909",
    "addr:housenumber":"427",
    "addr:postcode":"80909",
    "addr:street":"N Chelton Rd",
    "iso:country":"US",
    "sg:address":"427 N Chelton Rd",
    "sg:city":"Colorado Springs",
    "sg:classifiers":[
        {
            "category":"Home & Garden",
            "subcategory":"Furniture",
            "type":"Retail Goods"
        }
    ],
    "sg:phone":"+1 719 597 7177",
    "sg:postcode":"80909",
    "sg:province":"CO",
    "wof:name":"Kidz Bedzzz",
    "wof:placetype":"venue"
},
  "geometry": {"coordinates":[-104.766507,38.839518],"type":"Point"}
}