{
  "type": "Feature",
  "properties": {
    "iso:country":"US",
    "sg:address":"11365 W Coal Mine Dr",
    "sg:city":"Littleton",
    "sg:classifiers":[
        {
            "category":"Professional",
            "subcategory":"Engineering",
            "type":"Services"
        }
    ],
    "sg:phone":"+1 303 933 1500",
    "sg:postcode":"80127",
    "sg:province":"CO",
    "sg:tags":[
        "engineer"
    ],
    "wof:name":"Practical Engineering LLC",
    "wof:placetype":"venue"
},
  "geometry": {"coordinates":[-105.124382,39.59898],"type":"Point"}
}