{
  "type": "Feature",
  "properties": {
    "addr:full":"6622 Fonder Dr Parker CO 80134",
    "addr:postcode":"6622;80134",
    "addr:street":"Fonder Dr",
    "iso:country":"US",
    "sg:address":"6622 Fonder Dr",
    "sg:city":"Parker",
    "sg:classifiers":[
        {
            "category":"Banks & Credit Unions",
            "subcategory":"Bank",
            "type":"Services"
        }
    ],
    "sg:phone":"+1 303 805 5418",
    "sg:postcode":"80134",
    "sg:province":"CO",
    "sg:tags":[
        "loan",
        "real estate"
    ],
    "wof:name":"Knowlton Mortgage Inc",
    "wof:placetype":"venue"
},
  "geometry": {"coordinates":[-104.76312799999999,39.437796],"type":"Point"}
}