{
  "type": "Feature",
  "properties": {
    "addr:full":"5039 S Federal Blvd Englewood CO 80110",
    "addr:housenumber":"5039",
    "addr:postcode":"80110",
    "addr:street":"S Federal Blvd",
    "iso:country":"US",
    "sg:address":"5039 S Federal Blvd",
    "sg:city":"Englewood",
    "sg:classifiers":[
        {
            "category":"Health Services",
            "subcategory":"Health Practitioner",
            "type":"Services"
        }
    ],
    "sg:phone":"+1 303 794 9505",
    "sg:postcode":"80110",
    "sg:province":"CO",
    "sg:tags":[
        "acupuncture"
    ],
    "wof:name":"Acu-Choice Health Care Clinic",
    "wof:placetype":"venue"
},
  "geometry": {"coordinates":[-105.02548899999999,39.626387],"type":"Point"}
}