{
  "type": "Feature",
  "properties": {
    "addr:full":"12162 E Mississippi Ave Aurora CO 80012",
    "addr:housenumber":"12162",
    "addr:postcode":"80012",
    "addr:street":"E Mississippi Ave",
    "iso:country":"US",
    "sg:address":"12162 E Mississippi Ave",
    "sg:city":"Aurora",
    "sg:classifiers":[
        {
            "category":"Banks & Credit Unions",
            "subcategory":"Bank",
            "type":"Services"
        }
    ],
    "sg:phone":"+1 303 368 1177",
    "sg:postcode":"80012",
    "sg:province":"CO",
    "sg:tags":[
        "loan",
        "mortgage",
        "real estate"
    ],
    "wof:name":"Creative Enterprises LLC",
    "wof:placetype":"venue"
},
  "geometry": {"coordinates":[-104.84533500000001,39.696529],"type":"Point"}
}