{
  "type": "Feature",
  "properties": {
    "addr:full":"2594 S Lewis Way Lakewood CO 80227",
    "addr:housenumber":"2594",
    "addr:postcode":"80227",
    "addr:street":"S Lewis Way",
    "iso:country":"US",
    "sg:address":"2594 S Lewis Way",
    "sg:city":"Lakewood",
    "sg:classifiers":[
        {
            "category":"Insurance",
            "subcategory":"Insurance Agent",
            "type":"Services"
        }
    ],
    "sg:phone":"+1 303 797 3327",
    "sg:postcode":"80227",
    "sg:province":"CO",
    "sg:website":"www.statefarm.com",
    "wof:name":"Segeth-Grodkiewicz Insurance",
    "wof:placetype":"venue"
},
  "geometry": {"coordinates":[-105.112712,39.670158],"type":"Point"}
}