{
  "type": "Feature",
  "properties": {
    "addr:full":"3636 Larkwood Ct Boulder CO 80304",
    "addr:housenumber":"3636",
    "addr:postcode":"80304",
    "addr:street":"Larkwood Ct",
    "iso:country":"US",
    "sg:address":"3636 Larkwood Ct",
    "sg:city":"Boulder",
    "sg:classifiers":[
        {
            "category":"Banks & Credit Unions",
            "subcategory":"Investment Brokerage",
            "type":"Services"
        }
    ],
    "sg:phone":"+1 303 473 9231",
    "sg:postcode":"80304",
    "sg:province":"CO",
    "sg:tags":[
        "advisory"
    ],
    "wof:name":"Summit Capital Management Inc",
    "wof:placetype":"venue"
},
  "geometry": {"coordinates":[-105.261527,40.040753],"type":"Point"}
}