{
  "type": "Feature",
  "properties": {
    "addr:full":"7561 S Grant St Littleton CO 80122",
    "addr:housenumber":"7561",
    "addr:postcode":"80122",
    "addr:street":"S Grant St",
    "iso:country":"US",
    "sg:address":"7561 S Grant St",
    "sg:city":"Littleton",
    "sg:classifiers":[
        {
            "category":"Home & Garden",
            "subcategory":"Furniture",
            "type":"Retail Goods"
        }
    ],
    "sg:phone":"+1 303 347 1345",
    "sg:postcode":"80122",
    "sg:province":"CO",
    "sg:tags":[
        "top",
        "counter"
    ],
    "wof:name":"Sander & Sons",
    "wof:placetype":"venue"
},
  "geometry": {"coordinates":[-104.984556,39.579475],"type":"Point"}
}