{
  "type": "Feature",
  "properties": {
    "iso:country":"US",
    "sg:address":"3609 S Wadsworth Blvd",
    "sg:city":"Lakewood",
    "sg:classifiers":[
        {
            "category":"Professional",
            "subcategory":"Lawyer & Legal Services",
            "type":"Services"
        }
    ],
    "sg:phone":"+1 303 987 1126",
    "sg:postcode":"80235",
    "sg:province":"CO",
    "sg:tags":[
        "attorney"
    ],
    "sg:website":"www.mrwpc.com",
    "wof:name":"Mary Ray White",
    "wof:placetype":"venue"
},
  "geometry": {"coordinates":[-105.08147200000001,39.649919],"type":"Point"}
}