{
  "type": "Feature",
  "properties": {
    "addr:full":"427 E Market St Meeker CO 81641",
    "addr:housenumber":"427",
    "addr:street":"E Market St",
    "iso:country":"US",
    "sg:address":"427 E Market St",
    "sg:city":"Meeker",
    "sg:classifiers":[
        {
            "category":"Utilities",
            "subcategory":"Fuel Oil & Lpg",
            "type":"Services"
        }
    ],
    "sg:phone":"+1 970 878 5059",
    "sg:postcode":"81641",
    "sg:province":"CO",
    "sg:tags":[
        "dealer"
    ],
    "wof:name":"Flat Tops Fuel Inc",
    "wof:placetype":"venue"
},
  "geometry": {"coordinates":[-107.90102,40.037734],"type":"Point"}
}