{
  "type": "Feature",
  "properties": {
    "iso:country":"US",
    "sg:address":"2937 Welton Street",
    "sg:city":"Denver",
    "sg:classifiers":[
        {
            "category":"Communications",
            "subcategory":"Newspaper",
            "type":"Services"
        }
    ],
    "sg:phone":"+1 303 292 5158",
    "sg:postcode":"80205",
    "sg:province":"CO",
    "sg:tags":[
        "print",
        "medium"
    ],
    "wof:name":"Denver Weekly News",
    "wof:placetype":"venue"
},
  "geometry": {"coordinates":[-104.974952,39.75733],"type":"Point"}
}