{
  "type": "Feature",
  "properties": {
    "iso:country":"US",
    "sg:address":"1915 Oak Hills Dr",
    "sg:city":"Colorado Springs",
    "sg:classifiers":[
        {
            "category":"Food & Beverages",
            "subcategory":"Specialty",
            "type":"Retail Goods"
        },
        {
            "category":"Real Estate",
            "subcategory":"Real Estate Agent",
            "type":"Services"
        }
    ],
    "sg:phone":"+1 719 598 8291",
    "sg:postcode":"80919",
    "sg:province":"CO",
    "sg:tags":[
        "consulting",
        "management",
        "vitamin"
    ],
    "wof:name":"Biggers & Associates",
    "wof:placetype":"venue"
},
  "geometry": {"coordinates":[-104.86528800000001,38.938798],"type":"Point"}
}