{
  "type": "Feature",
  "properties": {
    "iso:country":"US",
    "sg:address":"503 E Routt Ave",
    "sg:city":"Pueblo",
    "sg:classifiers":[
        {
            "category":"Real Estate",
            "subcategory":"Surveying",
            "type":"Services"
        }
    ],
    "sg:phone":"+1 719 253 0874",
    "sg:postcode":"81004",
    "sg:province":"CO",
    "sg:tags":[
        "surveyor"
    ],
    "wof:name":"Matt Cordova",
    "wof:placetype":"venue"
},
  "geometry": {"coordinates":[-104.618275,38.253375],"type":"Point"}
}