{
  "type": "Feature",
  "properties": {
    "iso:country":"US",
    "sg:address":"1425 Hawk Pkwy",
    "sg:city":"Montrose",
    "sg:classifiers":[
        {
            "category":"Health Services",
            "subcategory":"Doctor",
            "type":"Services"
        }
    ],
    "sg:phone":"+1 970 249 4249",
    "sg:postcode":"81401",
    "sg:province":"CO",
    "sg:tags":[
        "dentist"
    ],
    "wof:name":"Nory Garcia DDS",
    "wof:placetype":"venue"
},
  "geometry": {"coordinates":[-107.867681,38.449308],"type":"Point"}
}