{
  "type": "Feature",
  "properties": {
    "iso:country":"US",
    "sg:address":"943 W 8th Dr",
    "sg:city":"Craig",
    "sg:classifiers":[
        {
            "category":"Health Services",
            "subcategory":"Nursing And Care Facility",
            "type":"Services"
        }
    ],
    "sg:phone":"+1 970 826 4100",
    "sg:postcode":"81625",
    "sg:province":"CO",
    "sg:tags":[
        "home",
        "convalescent"
    ],
    "wof:name":"Sandrock Ridge Care & Rehab",
    "wof:placetype":"venue"
},
  "geometry": {"coordinates":[-107.560299,40.51843],"type":"Point"}
}