{
  "type": "Feature",
  "properties": {
    "iso:country":"US",
    "sg:address":"3676 S Natches Ct",
    "sg:city":"Englewood",
    "sg:classifiers":[
        {
            "category":"Building & Trades",
            "subcategory":"Construction",
            "type":"Services"
        }
    ],
    "sg:phone":"+1 303 789 1800",
    "sg:postcode":"80110",
    "sg:province":"CO",
    "sg:tags":[
        "seamless",
        "flooring",
        "contractor"
    ],
    "wof:name":"General Industrial Flooring",
    "wof:placetype":"venue"
},
  "geometry": {"coordinates":[-105.00461300000001,39.653193],"type":"Point"}
}