{
  "type": "Feature",
  "properties": {
    "iso:country":"US",
    "sg:address":"808 23rd Ave",
    "sg:city":"Greeley",
    "sg:phone":"+1 970 352 0495",
    "sg:postcode":"80634",
    "sg:province":"CO",
    "sg:tags":[
        "irrigation",
        "company",
        "system"
    ],
    "wof:name":"Greeley Loveland Irrigation Co",
    "wof:placetype":"venue"
},
  "geometry": {"coordinates":[-104.71581399999999,40.424156],"type":"Point"}
}