{
  "type": "Feature",
  "properties": {
    "addr:full":"1315 Westview Dr Sterling CO 80751",
    "addr:housenumber":"1315",
    "addr:postcode":"80751",
    "addr:street":"Westview Dr",
    "iso:country":"US",
    "sg:address":"1315 Westview Dr",
    "sg:city":"Sterling",
    "sg:classifiers":[
        {
            "category":"Building & Trades",
            "subcategory":"Construction",
            "type":"Services"
        }
    ],
    "sg:phone":"+1 970 522 5019",
    "sg:postcode":"80751",
    "sg:province":"CO",
    "sg:tags":[
        "concrete",
        "contractor"
    ],
    "wof:name":"John Brunner Concrete Contr",
    "wof:placetype":"venue"
},
  "geometry": {"coordinates":[-103.22944099999999,40.61286],"type":"Point"}
}