{
  "type": "Feature",
  "properties": {
    "addr:full":"11 1st St Fort Lupton CO 80621",
    "addr:housenumber":"11",
    "addr:postcode":"80621",
    "addr:street":"1St St",
    "iso:country":"US",
    "sg:address":"11 1st St",
    "sg:city":"Fort Lupton",
    "sg:classifiers":[
        {
            "category":"Restaurant",
            "type":"Food & Drink"
        }
    ],
    "sg:phone":"+1 303 857 6770",
    "sg:postcode":"80621",
    "sg:province":"CO",
    "wof:name":"Branding Iron Restaurant",
    "wof:placetype":"venue"
},
  "geometry": {"coordinates":[-104.81956700000001,40.080197],"type":"Point"}
}