{
  "type": "Feature",
  "properties": {
    "addr:full":"680 46th Ln Pueblo CO 81006",
    "addr:housenumber":"680",
    "addr:postcode":"81006",
    "addr:street":"46Th Ln",
    "iso:country":"US",
    "sg:address":"680 46th Ln",
    "sg:city":"Pueblo",
    "sg:classifiers":[
        {
            "category":"Building & Trades",
            "subcategory":"Construction",
            "type":"Services"
        }
    ],
    "sg:phone":"+1 719 947 4130",
    "sg:postcode":"81006",
    "sg:province":"CO",
    "sg:tags":[
        "house"
    ],
    "wof:name":"Phillips Construction",
    "wof:placetype":"venue"
},
  "geometry": {"coordinates":[-104.367492,38.257572],"type":"Point"}
}