{
  "type": "Feature",
  "properties": {
    "iso:country":"US",
    "sg:address":"4240 Kipling St",
    "sg:city":"Wheat Ridge",
    "sg:classifiers":[
        {
            "category":"Sports & Exercise",
            "subcategory":"Gym",
            "type":"Entertainment"
        }
    ],
    "sg:phone":"+1 303 456 0076",
    "sg:postcode":"80033",
    "sg:province":"CO",
    "sg:tags":[
        "club",
        "health",
        "studio",
        "gymnasium"
    ],
    "wof:name":"Colorado Pro Gym 2K",
    "wof:placetype":"venue"
},
  "geometry": {"coordinates":[-105.10954099999999,39.776011],"type":"Point"}
}