{
  "type": "Feature",
  "properties": {
    "iso:country":"US",
    "sg:address":"27124 Co Rd 70",
    "sg:city":"Gill",
    "sg:classifiers":[
        {
            "category":"Retail",
            "subcategory":"Animal Services",
            "type":"Services"
        }
    ],
    "sg:phone":"+1 970 351 0610",
    "sg:postcode":"80624",
    "sg:province":"CO",
    "wof:name":"Little Rush Syndicate LLC",
    "wof:placetype":"venue"
},
  "geometry": {"coordinates":[-104.528818,40.493258],"type":"Point"}
}