{
  "type": "Feature",
  "properties": {
    "addr:full":"150 Pagosa St Pagosa Springs CO 81147",
    "addr:housenumber":"150",
    "addr:postcode":"81147",
    "addr:street":"Pagosa St",
    "iso:country":"US",
    "sg:address":"150 Pagosa St",
    "sg:city":"Pagosa Springs",
    "sg:classifiers":[
        {
            "category":"Professional",
            "type":"Services"
        }
    ],
    "sg:phone":"+1 970 264 8080",
    "sg:postcode":"81147",
    "sg:province":"CO",
    "wof:name":"Babys On A Budget",
    "wof:placetype":"venue"
},
  "geometry": {"coordinates":[-107.00366099999999,37.268988],"type":"Point"}
}