{
  "type": "Feature",
  "properties": {
    "addr:full":"482 Riverland Dr Crested Butte CO 81224",
    "addr:housenumber":"482",
    "addr:postcode":"81224",
    "addr:street":"Riverland Dr",
    "iso:country":"US",
    "sg:address":"482 Riverland Dr",
    "sg:city":"Crested Butte",
    "sg:classifiers":[
        {
            "category":"Building & Trades",
            "subcategory":"Construction",
            "type":"Services"
        }
    ],
    "sg:phone":"+1 970 349 5486",
    "sg:postcode":"81224",
    "sg:province":"CO",
    "sg:tags":[
        "excavating",
        "contractor"
    ],
    "wof:name":"JCI",
    "wof:placetype":"venue"
},
  "geometry": {"coordinates":[-106.949043,38.848449],"type":"Point"}
}