{
  "type": "Feature",
  "properties": {
    "iso:country":"US",
    "sg:address":"3023 W 44th Ave",
    "sg:city":"Denver",
    "sg:classifiers":[
        {
            "category":"Restaurant",
            "type":"Food & Drink"
        }
    ],
    "sg:phone":"+1 720 854 0539",
    "sg:postcode":"80211",
    "sg:province":"CO",
    "sg:tags":[
        "mexican"
    ],
    "wof:name":"El Bronquito Cafe",
    "wof:placetype":"venue"
},
  "geometry": {"coordinates":[-105.02600099999999,39.776501],"type":"Point"}
}