{
  "type": "Feature",
  "properties": {
    "iso:country":"US",
    "sg:address":"2310 S Syracuse Way",
    "sg:city":"Denver",
    "sg:classifiers":[
        {
            "category":"Manufacturing",
            "subcategory":"Tools & Machinery",
            "type":"Manufacturing & Wholesale Goods"
        }
    ],
    "sg:phone":"+1 303 772 4372",
    "sg:postcode":"80231",
    "sg:province":"CO",
    "sg:tags":[
        "spraying",
        "equipment"
    ],
    "wof:name":"Pwcs",
    "wof:placetype":"venue"
},
  "geometry": {"coordinates":[-104.898929,39.672754],"type":"Point"}
}