{
  "type": "Feature",
  "properties": {
    "addr:full":"21899 Grandview Ave Golden CO 80401",
    "addr:housenumber":"21899",
    "addr:postcode":"80401",
    "addr:street":"Grandview Ave",
    "iso:country":"US",
    "sg:address":"21899 Grandview Ave",
    "sg:city":"Golden",
    "sg:classifiers":[
        {
            "category":"Wholesale",
            "subcategory":"Medical Equipment & Supplies",
            "type":"Manufacturing & Wholesale Goods"
        }
    ],
    "sg:phone":"+1 303 526 7307",
    "sg:postcode":"80401",
    "sg:province":"CO",
    "sg:tags":[
        "wholesaler"
    ],
    "wof:name":"Phil Durango LLC",
    "wof:placetype":"venue"
},
  "geometry": {"coordinates":[-105.244741,39.721477],"type":"Point"}
}