{
  "type": "Feature",
  "properties": {
    "addr:full":"23659 Co Rd 44 La Salle CO 80645",
    "addr:housenumber":"23659",
    "addr:postcode":"80645",
    "addr:street":"Co Rd 44",
    "iso:country":"US",
    "sg:address":"23659 Co Rd 44",
    "sg:city":"La Salle",
    "sg:classifiers":[
        {
            "category":"Farming",
            "subcategory":"Livestock Farm",
            "type":"Manufacturing & Wholesale Goods"
        }
    ],
    "sg:phone":"+1 970 284 5531",
    "sg:postcode":"80645",
    "sg:province":"CO",
    "sg:tags":[
        "beef",
        "feedlot",
        "cattle"
    ],
    "wof:name":"Timmerman Sons Feeding Co Inc",
    "wof:placetype":"venue"
},
  "geometry": {"coordinates":[-104.608553,40.305077],"type":"Point"}
}