{
  "type": "Feature",
  "properties": {
    "iso:country":"US",
    "sg:address":"34555 US Hwy 24",
    "sg:city":"Ramah",
    "sg:classifiers":[
        {
            "category":"Freight",
            "type":"Transportation"
        }
    ],
    "sg:phone":"+1 719 541 2026",
    "sg:postcode":"80832",
    "sg:province":"CO",
    "sg:tags":[
        "operator",
        "trucking"
    ],
    "wof:name":"Blasingame & Blasingame LLC",
    "wof:placetype":"venue"
},
  "geometry": {"coordinates":[-104.18177,39.107824],"type":"Point"}
}