{
  "type": "Feature",
  "properties": {
    "iso:country":"US",
    "sg:address":"2129 Delta Dr",
    "sg:city":"Colorado Springs",
    "sg:classifiers":[
        {
            "category":"Real Estate",
            "subcategory":"Real Estate Operator",
            "type":"Services"
        }
    ],
    "sg:phone":"+1 719 591 0826",
    "sg:postcode":"80910",
    "sg:province":"CO",
    "sg:tags":[
        "building",
        "apartment"
    ],
    "wof:name":"Whitney Young Manor Apartments",
    "wof:placetype":"venue"
},
  "geometry": {"coordinates":[-104.759541,38.803479],"type":"Point"}
}