{
  "type": "Feature",
  "properties": {
    "iso:country":"US",
    "sg:address":"13120 E Mississippi Ave",
    "sg:city":"Aurora",
    "sg:classifiers":[
        {
            "category":"Shopping",
            "subcategory":"Tobacco",
            "type":"Retail Goods"
        }
    ],
    "sg:phone":"+1 303 671 6624",
    "sg:postcode":"80012",
    "sg:province":"CO",
    "sg:tags":[
        "cigarette",
        "cigar"
    ],
    "wof:name":"King Of Cigarettes & Cigars",
    "wof:placetype":"venue"
},
  "geometry": {"coordinates":[-104.84094899999999,39.696608],"type":"Point"}
}