{
  "type": "Feature",
  "properties": {
    "iso:country":"US",
    "sg:address":"23078 Pinecrest Rd",
    "sg:city":"Golden",
    "sg:classifiers":[
        {
            "category":"Wholesale",
            "subcategory":"Hardware",
            "type":"Manufacturing & Wholesale Goods"
        }
    ],
    "sg:phone":"+1 303 526 4550",
    "sg:postcode":"80401",
    "sg:province":"CO",
    "sg:tags":[
        "conditioning",
        "mfg"
    ],
    "sg:website":"www.acemechanical.com",
    "wof:name":"Ace Mechanical Equipment Inc",
    "wof:placetype":"venue"
},
  "geometry": {"coordinates":[-105.257204,39.724339],"type":"Point"}
}