{
  "type": "Feature",
  "properties": {
    "iso:country":"US",
    "sg:address":"18520 Shannon Rd",
    "sg:city":"Colorado Springs",
    "sg:classifiers":[
        {
            "category":"Manufacturing",
            "subcategory":"Lumber",
            "type":"Manufacturing & Wholesale Goods"
        }
    ],
    "sg:phone":"+1 719 481 4946",
    "sg:postcode":"80908",
    "sg:province":"CO",
    "sg:tags":[
        "operation",
        "timber",
        "tract"
    ],
    "wof:name":"Merry Christmas Tree Farm",
    "wof:placetype":"venue"
},
  "geometry": {"coordinates":[-104.767627,39.100048],"type":"Point"}
}