{
  "type": "Feature",
  "properties": {
    "iso:country":"US",
    "sg:address":"826 Coal Creek Cir",
    "sg:city":"Louisville",
    "sg:classifiers":[
        {
            "category":"Manufacturing",
            "subcategory":"Tools & Machinery",
            "type":"Manufacturing & Wholesale Goods"
        }
    ],
    "sg:phone":"+1 720 890 3200",
    "sg:postcode":"80027",
    "sg:province":"CO",
    "sg:tags":[
        "physician",
        "surgeon"
    ],
    "sg:website":"www.medtronic.com",
    "wof:name":"Medtronic Surgical Navigation",
    "wof:placetype":"venue"
},
  "geometry": {"coordinates":[-105.1584,39.957693],"type":"Point"}
}