{
  "type": "Feature",
  "properties": {
    "addr:full":"5315 Preserve Dr Littleton CO 80121",
    "addr:housenumber":"5315",
    "addr:postcode":"80121",
    "addr:street":"Preserve Dr",
    "iso:country":"US",
    "sg:address":"5315 Preserve Dr",
    "sg:city":"Littleton",
    "sg:classifiers":[
        {
            "category":"Banks & Credit Unions",
            "subcategory":"Financial Services",
            "type":"Services"
        }
    ],
    "sg:phone":"+1 303 995 5507",
    "sg:postcode":"80121",
    "sg:province":"CO",
    "sg:tags":[
        "investment",
        "closed"
    ],
    "wof:name":"Pisani Investments LLC",
    "wof:placetype":"venue"
},
  "geometry": {"coordinates":[-104.923182,39.61996],"type":"Point"}
}