{
  "type": "Feature",
  "properties": {
    "iso:country":"US",
    "sg:address":"1221 Cook St",
    "sg:city":"Denver",
    "sg:classifiers":[
        {
            "category":"Professional",
            "subcategory":"Management & Consulting",
            "type":"Services"
        }
    ],
    "sg:phone":"+1 303 322 5352",
    "sg:postcode":"80206",
    "sg:province":"CO",
    "sg:tags":[
        "consultant",
        "business"
    ],
    "sg:website":"www.bstonetech.com",
    "wof:name":"Blackstone Technology Group",
    "wof:placetype":"venue"
},
  "geometry": {"coordinates":[-104.947354,39.736433],"type":"Point"}
}