{
  "type": "Feature",
  "properties": {
    "addr:full":"827 Elm St Fort Collins CO 80521",
    "addr:housenumber":"827",
    "addr:postcode":"80521",
    "addr:street":"Elm St",
    "iso:country":"US",
    "sg:address":"827 Elm St",
    "sg:city":"Fort Collins",
    "sg:classifiers":[
        {
            "category":"Building & Trades",
            "subcategory":"Construction",
            "type":"Services"
        }
    ],
    "sg:phone":"+1 970 482 6984",
    "sg:postcode":"80521",
    "sg:province":"CO",
    "sg:tags":[
        "house"
    ],
    "wof:name":"Phelps Construction",
    "wof:placetype":"venue"
},
  "geometry": {"coordinates":[-105.08967,40.594873],"type":"Point"}
}