{
  "type": "Feature",
  "properties": {
    "addr:full":"717 Grant Pl Boulder CO 80302",
    "addr:housenumber":"717",
    "addr:postcode":"80302",
    "addr:street":"Grant Pl",
    "iso:country":"US",
    "sg:address":"717 Grant Pl",
    "sg:city":"Boulder",
    "sg:classifiers":[
        {
            "category":"Building & Trades",
            "subcategory":"Construction",
            "type":"Services"
        }
    ],
    "sg:phone":"+1 303 440 0373",
    "sg:postcode":"80302",
    "sg:province":"CO",
    "sg:tags":[
        "company"
    ],
    "wof:name":"Shifrin Construction",
    "wof:placetype":"venue"
},
  "geometry": {"coordinates":[-105.283171,40.001538],"type":"Point"}
}