{
  "type": "Feature",
  "properties": {
    "addr:full":"12575 E Ford Ave Aurora CO 80012",
    "addr:housenumber":"12575",
    "addr:postcode":"80012",
    "addr:street":"E Ford Ave",
    "iso:country":"US",
    "sg:address":"12575 E Ford Ave",
    "sg:city":"Aurora",
    "sg:classifiers":[
        {
            "category":"Real Estate",
            "subcategory":"Real Estate Operator",
            "type":"Services"
        }
    ],
    "sg:phone":"+1 303 341 6371",
    "sg:postcode":"80012",
    "sg:province":"CO",
    "sg:tags":[
        "townhouses"
    ],
    "wof:name":"Meadowlark Apartments",
    "wof:placetype":"venue"
},
  "geometry": {"coordinates":[-104.84262200000001,39.699331],"type":"Point"}
}