{
  "type": "Feature",
  "properties": {
    "addr:full":"35800 Co Rd Ss Wiley CO 81092",
    "addr:housenumber":"35800",
    "addr:postcode":"81092",
    "addr:street":"Co Rd Ss Wiley",
    "iso:country":"US",
    "sg:address":"35800 Co Rd Ss",
    "sg:city":"Wiley",
    "sg:classifiers":[
        {
            "category":"Farming",
            "subcategory":"Livestock Farm",
            "type":"Manufacturing & Wholesale Goods"
        }
    ],
    "sg:phone":"+1 719 829 4408",
    "sg:postcode":"81092",
    "sg:province":"CO",
    "sg:tags":[
        "corn",
        "wheat",
        "feedlot",
        "beef",
        "cattle"
    ],
    "wof:name":"Spitzer Farms",
    "wof:placetype":"venue"
},
  "geometry": {"coordinates":[-102.742661,38.201404],"type":"Point"}
}