{
  "type": "Feature",
  "properties": {
    "iso:country":"US",
    "sg:address":"7120 E 49th Ave",
    "sg:city":"Commerce City",
    "sg:classifiers":[
        {
            "category":"Retail",
            "subcategory":"Car Wash",
            "type":"Services"
        }
    ],
    "sg:phone":"+1 303 287 6320",
    "sg:postcode":"80022",
    "sg:province":"CO",
    "sg:tags":[
        "truck",
        "cleaning"
    ],
    "wof:name":"Eagle Truck Wash",
    "wof:placetype":"venue"
},
  "geometry": {"coordinates":[-104.90397400000001,39.785191],"type":"Point"}
}