{
  "type": "Feature",
  "properties": {
    "iso:country":"US",
    "sg:address":"1150 Academy Park Loop",
    "sg:city":"Colorado Springs",
    "sg:classifiers":[
        {
            "category":"Professional",
            "subcategory":"Management & Consulting",
            "type":"Services"
        }
    ],
    "sg:phone":"+1 719 591 5600",
    "sg:postcode":"80910",
    "sg:province":"CO",
    "wof:name":"SDS International",
    "wof:placetype":"venue"
},
  "geometry": {"coordinates":[-104.759141,38.816759],"type":"Point"}
}