{
  "type": "Feature",
  "properties": {
    "iso:country":"US",
    "sg:address":"605 Coffman St",
    "sg:city":"Longmont",
    "sg:classifiers":[
        {
            "category":"Home & Garden",
            "subcategory":"Home Furnishings",
            "type":"Retail Goods"
        }
    ],
    "sg:phone":"+1 303 485 1131",
    "sg:postcode":"80501",
    "sg:province":"CO",
    "sg:tags":[
        "window",
        "covering"
    ],
    "wof:name":"Budget Blinds",
    "wof:placetype":"venue"
},
  "geometry": {"coordinates":[-105.10390200000001,40.1706],"type":"Point"}
}