{
  "type": "Feature",
  "properties": {
    "iso:country":"US",
    "sg:address":"5901 N 79th St",
    "sg:city":"Longmont",
    "sg:classifiers":[
        {
            "category":"Insurance",
            "subcategory":"Insurance Agent",
            "type":"Services"
        }
    ],
    "sg:phone":"+1 303 652 2929",
    "sg:postcode":"80503",
    "sg:province":"CO",
    "wof:name":"Co West Of Niwot",
    "wof:placetype":"venue"
},
  "geometry": {"coordinates":[-105.16914800000001,40.083574],"type":"Point"}
}