{
  "type": "Feature",
  "properties": {
    "addr:full":"2453 S Wabash St Denver CO 80231",
    "addr:housenumber":"2453",
    "addr:postcode":"80231",
    "addr:street":"S Wabash St",
    "iso:country":"US",
    "sg:address":"2453 S Wabash St",
    "sg:city":"Denver",
    "sg:classifiers":[
        {
            "category":"Building & Trades",
            "subcategory":"Landscaping Services",
            "type":"Services"
        }
    ],
    "sg:phone":"+1 303 695 6166",
    "sg:postcode":"80231",
    "sg:province":"CO",
    "sg:tags":[
        "lawn",
        "maintenance",
        "grounds"
    ],
    "wof:name":"American Quality Landscape Inc",
    "wof:placetype":"venue"
},
  "geometry": {"coordinates":[-104.889422,39.673983],"type":"Point"}
}