{
  "type": "Feature",
  "properties": {
    "addr:full":"8305 S Harvest Ln Littleton CO 80126",
    "addr:housenumber":"8305",
    "addr:postcode":"80126",
    "addr:street":"S Harvest Ln",
    "iso:country":"US",
    "sg:address":"8305 S Harvest Ln",
    "sg:city":"Littleton",
    "sg:classifiers":[
        {
            "category":"Real Estate",
            "subcategory":"Real Estate Operator",
            "type":"Services"
        }
    ],
    "sg:phone":"+1 303 741 2600",
    "sg:postcode":"80126",
    "sg:province":"CO",
    "sg:tags":[
        "building",
        "apartment"
    ],
    "wof:name":"Autumn Chase Apartments",
    "wof:placetype":"venue"
},
  "geometry": {"coordinates":[-104.951911,39.565722],"type":"Point"}
}