{
  "type": "Feature",
  "properties": {
    "iso:country":"US",
    "sg:address":"325 N Kuner Rd",
    "sg:city":"Brighton",
    "sg:classifiers":[
        {
            "category":"Government",
            "subcategory":"Office",
            "type":"Public Place"
        }
    ],
    "sg:phone":"+1 303 655 2092",
    "sg:postcode":"80601",
    "sg:province":"CO",
    "sg:tags":[
        "water",
        "plant",
        "waste",
        "municipal"
    ],
    "wof:name":"Brighton Waste Water Plant",
    "wof:placetype":"venue"
},
  "geometry": {"coordinates":[-104.823127,39.992046],"type":"Point"}
}