{
  "type": "Feature",
  "properties": {
    "addr:full":"1240 Umatilla St Denver CO 80204",
    "addr:housenumber":"1240",
    "addr:postcode":"80204",
    "addr:street":"Umatilla St",
    "iso:country":"US",
    "sg:address":"1240 Umatilla St",
    "sg:city":"Denver",
    "sg:classifiers":[
        {
            "category":"Retail",
            "subcategory":"Auto Repair",
            "type":"Services"
        }
    ],
    "sg:phone":"+1 303 892 1672",
    "sg:postcode":"80204",
    "sg:province":"CO",
    "sg:tags":[
        "repairing",
        "automobile"
    ],
    "wof:name":"Auto Know How",
    "wof:placetype":"venue"
},
  "geometry": {"coordinates":[-105.012253,39.735885],"type":"Point"}
}