{
  "type": "Feature",
  "properties": {
    "iso:country":"US",
    "sg:address":"8725 E Lowry Blvd",
    "sg:city":"Denver",
    "sg:classifiers":[
        {
            "category":"Government",
            "subcategory":"Office",
            "type":"Public Place"
        }
    ],
    "sg:phone":"+1 303 676 2609",
    "sg:postcode":"80230",
    "sg:province":"CO",
    "sg:tags":[
        "training",
        "center"
    ],
    "wof:name":"Technical Training Center",
    "wof:placetype":"venue"
},
  "geometry": {"coordinates":[-104.88739,39.721814],"type":"Point"}
}