{
  "type": "Feature",
  "properties": {
    "iso:country":"US",
    "sg:address":"511 N Main St",
    "sg:city":"Pueblo",
    "sg:classifiers":[
        {
            "category":"Professional",
            "subcategory":"Accounting & Tax Preparation",
            "type":"Services"
        }
    ],
    "sg:phone":"+1 719 545 2333",
    "sg:postcode":"81003",
    "sg:province":"CO",
    "sg:tags":[
        "accountant"
    ],
    "wof:name":"Harper & Assoc",
    "wof:placetype":"venue"
},
  "geometry": {"coordinates":[-104.60869,38.272404],"type":"Point"}
}