{
  "type": "Feature",
  "properties": {
    "iso:country":"US",
    "sg:address":"12101 E Iliff Ave",
    "sg:city":"Aurora",
    "sg:classifiers":[
        {
            "category":"Restaurant",
            "type":"Food & Drink"
        }
    ],
    "sg:phone":"+1 303 337 2709",
    "sg:postcode":"80014",
    "sg:province":"CO",
    "sg:tags":[
        "parlor",
        "ice",
        "cream"
    ],
    "wof:name":"Josh & John's Ice Cream",
    "wof:placetype":"venue"
},
  "geometry": {"coordinates":[-104.84519,39.674842],"type":"Point"}
}