{
  "type": "Feature",
  "properties": {
    "addr:full":"10576 W 107th Ave Broomfield CO 80021",
    "addr:housenumber":"10576",
    "addr:postcode":"80021",
    "addr:street":"W 107Th Ave",
    "iso:country":"US",
    "sg:address":"10576 W 107th Ave",
    "sg:city":"Broomfield",
    "sg:classifiers":[
        {
            "category":"Restaurant",
            "type":"Food & Drink"
        }
    ],
    "sg:phone":"+1 303 469 0508",
    "sg:postcode":"80021",
    "sg:province":"CO",
    "sg:tags":[
        "eating"
    ],
    "wof:name":"Red Rooster Delivery",
    "wof:placetype":"venue"
},
  "geometry": {"coordinates":[-105.113478,39.889204],"type":"Point"}
}