{
  "type": "Feature",
  "properties": {
    "addr:full":"205 W 16th St Craig CO 81625",
    "addr:housenumber":"205",
    "addr:postcode":"81625",
    "addr:street":"W 16Th St",
    "iso:country":"US",
    "sg:address":"205 W 16th St",
    "sg:city":"Craig",
    "sg:classifiers":[
        {
            "category":"Building & Trades",
            "subcategory":"Landscaping Services",
            "type":"Services"
        }
    ],
    "sg:phone":"+1 970 824 2688",
    "sg:postcode":"81625",
    "sg:province":"CO",
    "wof:name":"Craig Prks Rcration Maint Dept",
    "wof:placetype":"venue"
},
  "geometry": {"coordinates":[-107.548153,40.535114],"type":"Point"}
}