{
  "type": "Feature",
  "properties": {
    "addr:full":"2406 Cochetopa Ct Fort Collins CO 80525",
    "addr:housenumber":"2406",
    "addr:postcode":"80525",
    "addr:street":"Cochetopa Ct",
    "iso:country":"US",
    "sg:address":"2406 Cochetopa Ct",
    "sg:city":"Fort Collins",
    "sg:classifiers":[
        {
            "category":"Professional",
            "subcategory":"Computer Services",
            "type":"Services"
        }
    ],
    "sg:phone":"+1 970 690 0419",
    "sg:postcode":"80525",
    "sg:province":"CO",
    "sg:tags":[
        "support",
        "management",
        "land"
    ],
    "wof:name":"Data Base Camp Inc",
    "wof:placetype":"venue"
},
  "geometry": {"coordinates":[-105.031691,40.53863],"type":"Point"}
}