{
  "type": "Feature",
  "properties": {
    "iso:country":"US",
    "sg:address":"3280 Downing St",
    "sg:city":"Denver",
    "sg:classifiers":[
        {
            "category":"Government",
            "subcategory":"Court House",
            "type":"Public Place"
        }
    ],
    "sg:phone":"+1 303 299 1828",
    "sg:postcode":"80205",
    "sg:province":"CO",
    "wof:name":"County Court",
    "wof:placetype":"venue"
},
  "geometry": {"coordinates":[-104.973344,39.762422],"type":"Point"}
}