{
  "type": "Feature",
  "properties": {
    "addr:full":"3176 6th St Boulder CO 80304",
    "addr:housenumber":"3176",
    "addr:postcode":"80304",
    "addr:street":"6Th St",
    "iso:country":"US",
    "sg:address":"3176 6th St",
    "sg:city":"Boulder",
    "sg:classifiers":[
        {
            "category":"Shopping",
            "subcategory":"Computers & Home Electronics",
            "type":"Retail Goods"
        }
    ],
    "sg:phone":"+1 303 440 3813",
    "sg:postcode":"80304",
    "sg:province":"CO",
    "sg:tags":[
        "equipment"
    ],
    "wof:name":"Buy Used Telecom Equipment",
    "wof:placetype":"venue"
},
  "geometry": {"coordinates":[-105.28907599999999,40.031466],"type":"Point"}
}