{
  "type": "Feature",
  "properties": {
    "addr:full":"15586 E Greenwood Dr Aurora CO 80013",
    "addr:housenumber":"15586 e",
    "addr:postcode":"80013",
    "addr:street":"Greenwood Dr",
    "iso:country":"US",
    "sg:address":"15586 E Greenwood Dr",
    "sg:city":"Aurora",
    "sg:classifiers":[
        {
            "category":"Wholesale",
            "subcategory":"Groceries",
            "type":"Manufacturing & Wholesale Goods"
        }
    ],
    "sg:phone":"+1 303 374 0063",
    "sg:postcode":"80013",
    "sg:province":"CO",
    "wof:name":"Salt of Earth",
    "wof:placetype":"venue"
},
  "geometry": {"coordinates":[-104.806437,39.656255],"type":"Point"}
}