{
  "type": "Feature",
  "properties": {
    "addr:full":"2523 S Richfield St Aurora CO 80013",
    "addr:housenumber":"2523",
    "addr:postcode":"80013",
    "addr:street":"S Richfield St",
    "iso:country":"US",
    "sg:address":"2523 S Richfield St",
    "sg:city":"Aurora",
    "sg:classifiers":[
        {
            "category":"Building & Trades",
            "subcategory":"Construction",
            "type":"Services"
        }
    ],
    "sg:phone":"+1 303 751 4529",
    "sg:postcode":"80013",
    "sg:province":"CO",
    "sg:tags":[
        "house"
    ],
    "wof:name":"Wood Doctor Plus",
    "wof:placetype":"venue"
},
  "geometry": {"coordinates":[-104.785858,39.669147],"type":"Point"}
}