{
  "type": "Feature",
  "properties": {
    "iso:country":"US",
    "sg:address":"1400 Glenarm Pl",
    "sg:city":"Denver",
    "sg:classifiers":[
        {
            "category":"Government",
            "subcategory":"Office",
            "type":"Public Place"
        }
    ],
    "sg:phone":"+1 303 571 2400",
    "sg:postcode":"80202",
    "sg:province":"CO",
    "sg:tags":[
        "company",
        "utility"
    ],
    "wof:name":"Public Service Company Colo",
    "wof:placetype":"venue"
},
  "geometry": {"coordinates":[-104.991653,39.742912],"type":"Point"}
}