{
  "type": "Feature",
  "properties": {
    "iso:country":"US",
    "sg:address":"3625 E Colfax Ave",
    "sg:city":"Denver",
    "sg:classifiers":[
        {
            "category":"Autos & Motor Vehicles",
            "subcategory":"Automobile Sales",
            "type":"Retail Goods"
        }
    ],
    "sg:phone":"+1 303 321 3673",
    "sg:postcode":"80206",
    "sg:province":"CO",
    "sg:tags":[
        "car",
        "dealer"
    ],
    "sg:website":"www.johnelwayautonation.com",
    "wof:name":"John Elway Ford",
    "wof:placetype":"venue"
},
  "geometry": {"coordinates":[-104.945409,39.740239],"type":"Point"}
}