{
  "type": "Feature",
  "properties": {
    "iso:country":"US",
    "sg:address":"505 Ensign St",
    "sg:city":"Fort Morgan",
    "sg:classifiers":[
        {
            "category":"Wholesale",
            "subcategory":"Machinery & Supplies",
            "type":"Manufacturing & Wholesale Goods"
        }
    ],
    "sg:phone":"+1 970 867 3857",
    "sg:postcode":"80701",
    "sg:province":"CO",
    "sg:tags":[
        "equipment",
        "establishment",
        "repair"
    ],
    "wof:name":"Dreaming Badger Taxidermy",
    "wof:placetype":"venue"
},
  "geometry": {"coordinates":[-103.80288899999999,40.253943],"type":"Point"}
}