{
  "type": "Feature",
  "properties": {
    "addr:full":"4251 E Mississippi Ave Glendale CO 80246",
    "addr:housenumber":"4251",
    "addr:postcode":"80246",
    "addr:street":"E Mississippi Ave",
    "iso:country":"US",
    "sg:address":"4251 E Mississippi Ave",
    "sg:city":"Glendale",
    "sg:classifiers":[
        {
            "category":"Building & Trades",
            "subcategory":"Locksmith",
            "type":"Services"
        }
    ],
    "sg:phone":"+1 720 438 7586",
    "sg:postcode":"80246",
    "sg:province":"CO",
    "sg:tags":[
        "key"
    ],
    "wof:name":"Lock and Lockout Service Denver",
    "wof:placetype":"venue"
},
  "geometry": {"coordinates":[-104.937332,39.696727],"type":"Point"}
}