{
  "type": "Feature",
  "properties": {
    "addr:full":"2021 E Colfax Ave Denver CO 80206",
    "addr:housenumber":"2021",
    "addr:postcode":"80206",
    "addr:street":"E Colfax Ave",
    "iso:country":"US",
    "sg:address":"2021 E Colfax Ave",
    "sg:city":"Denver",
    "sg:classifiers":[
        {
            "category":"Shopping",
            "subcategory":"Clothing, Apparel, & Fashions",
            "type":"Retail Goods"
        }
    ],
    "sg:phone":"+1 303 320 0797",
    "sg:postcode":"80206",
    "sg:province":"CO",
    "sg:tags":[
        "accessory"
    ],
    "wof:name":"Unique Boutique",
    "wof:placetype":"venue"
},
  "geometry": {"coordinates":[-104.962997,39.740101],"type":"Point"}
}