{
  "type": "Feature",
  "properties": {
    "iso:country":"US",
    "sg:address":"1065 Market St",
    "sg:city":"Meeker",
    "sg:classifiers":[
        {
            "category":"Home & Garden",
            "subcategory":"Building Materials",
            "type":"Retail Goods"
        }
    ],
    "sg:phone":"+1 970 878 0333",
    "sg:postcode":"81641",
    "sg:province":"CO",
    "sg:tags":[
        "shop",
        "glass",
        "automotive",
        "replacement"
    ],
    "wof:name":"Son Lite Stained Glass Supply",
    "wof:placetype":"venue"
},
  "geometry": {"coordinates":[-107.919864,40.035184],"type":"Point"}
}