{
  "type": "Feature",
  "properties": {
    "addr:full":"310 W Iowa Ave Denver CO 80223",
    "addr:housenumber":"310",
    "addr:postcode":"80223",
    "addr:street":"W Iowa Ave",
    "iso:country":"US",
    "sg:address":"310 W Iowa Ave",
    "sg:city":"Denver",
    "sg:classifiers":[
        {
            "category":"Wholesale",
            "subcategory":"Machinery & Supplies",
            "type":"Manufacturing & Wholesale Goods"
        }
    ],
    "sg:phone":"+1 303 278 0342",
    "sg:postcode":"80223",
    "sg:province":"CO",
    "sg:tags":[
        "equipment",
        "industrial"
    ],
    "wof:name":"Hem-Saw",
    "wof:placetype":"venue"
},
  "geometry": {"coordinates":[-104.99084499999999,39.687496],"type":"Point"}
}