{
  "type": "Feature",
  "properties": {
    "iso:country":"US",
    "sg:address":"815 9th St",
    "sg:city":"Golden",
    "sg:classifiers":[
        {
            "category":"Arts & Performance",
            "subcategory":"Theater",
            "type":"Entertainment"
        }
    ],
    "sg:phone":"+1 303 278 4178",
    "sg:postcode":"80401",
    "sg:province":"CO",
    "sg:tags":[
        "musician"
    ],
    "wof:name":"Barbara Goodrich Clscl Hrpst",
    "wof:placetype":"venue"
},
  "geometry": {"coordinates":[-105.22501699999999,39.757763],"type":"Point"}
}