{
  "type": "Feature",
  "properties": {
    "iso:country":"US",
    "sg:address":"111 E Railroad Ave",
    "sg:city":"Fort Morgan",
    "sg:classifiers":[
        {
            "category":"Professional",
            "subcategory":"Accounting & Tax Preparation",
            "type":"Services"
        }
    ],
    "sg:phone":"+1 970 867 9040",
    "sg:postcode":"80701",
    "sg:province":"CO",
    "sg:tags":[
        "accountant"
    ],
    "wof:name":"Larry French Accounting",
    "wof:placetype":"venue"
},
  "geometry": {"coordinates":[-103.801458,40.248553],"type":"Point"}
}