{
  "type": "Feature",
  "properties": {
    "addr:full":"8740 W 68th Ave Arvada CO 80004",
    "addr:housenumber":"8740",
    "addr:postcode":"80004",
    "addr:street":"W 68Th Ave",
    "iso:country":"US",
    "sg:address":"8740 W 68th Ave",
    "sg:city":"Arvada",
    "sg:classifiers":[
        {
            "category":"Building & Trades",
            "subcategory":"Construction",
            "type":"Services"
        }
    ],
    "sg:phone":"+1 303 288 7041",
    "sg:postcode":"80004",
    "sg:province":"CO",
    "sg:tags":[
        "general",
        "contractor"
    ],
    "wof:name":"Quality Construction of The Fr",
    "wof:placetype":"venue"
},
  "geometry": {"coordinates":[-105.094221,39.820184],"type":"Point"}
}