{
  "type": "Feature",
  "properties": {
    "iso:country":"US",
    "sg:address":"302 Manitou Ave",
    "sg:city":"Manitou Springs",
    "sg:classifiers":[
        {
            "category":"Restaurant",
            "type":"Food & Drink"
        }
    ],
    "sg:menulink":"http://www.allmenus.com/co/monument/128682-subway/menu/",
    "sg:phone":"+1 719 685 0644",
    "sg:postcode":"80829",
    "sg:province":"CO",
    "sg:tags":[
        "american",
        "sandwich"
    ],
    "wof:name":"Subway",
    "wof:placetype":"venue"
},
  "geometry": {"coordinates":[-104.89888500000001,38.856714],"type":"Point"}
}