{
  "type": "Feature",
  "properties": {
    "iso:country":"US",
    "sg:address":"1620 Pleier Dr",
    "sg:city":"Colorado Springs",
    "sg:classifiers":[
        {
            "category":"Airport",
            "type":"Transportation"
        }
    ],
    "sg:phone":"+1 719 488 1146",
    "sg:postcode":"80921",
    "sg:province":"CO",
    "wof:name":"Tailwind Aviation Service",
    "wof:placetype":"venue"
},
  "geometry": {"coordinates":[-104.79741799999999,39.040236],"type":"Point"}
}