{
  "type": "Feature",
  "properties": {
    "iso:country":"US",
    "sg:address":"211 3rd St",
    "sg:city":"Clifton",
    "sg:classifiers":[
        {
            "category":"Professional",
            "subcategory":"Business Services",
            "type":"Services"
        }
    ],
    "sg:phone":"+1 970 434 2136",
    "sg:postcode":"81520",
    "sg:province":"CO",
    "wof:name":"Morris Professional Enterprise",
    "wof:placetype":"venue"
},
  "geometry": {"coordinates":[-108.44838,39.090387],"type":"Point"}
}