{
  "type": "Feature",
  "properties": {
    "addr:full":"328 W 13th Ave Denver CO 80204",
    "addr:housenumber":"328",
    "addr:postcode":"80204",
    "addr:street":"W 13Th Ave",
    "iso:country":"US",
    "sg:address":"328 W 13th Ave",
    "sg:city":"Denver",
    "sg:classifiers":[
        {
            "category":"Insurance",
            "subcategory":"Hazard Insurance",
            "type":"Services"
        }
    ],
    "sg:phone":"+1 303 595 3733",
    "sg:postcode":"80204",
    "sg:province":"CO",
    "sg:tags":[
        "bond"
    ],
    "wof:name":"Bail-Ten Percent",
    "wof:placetype":"venue"
},
  "geometry": {"coordinates":[-104.99259499999999,39.736783],"type":"Point"}
}