{
  "type": "Feature",
  "properties": {
    "addr:full":"3625 23rd Ave Evans CO 80620",
    "addr:housenumber":"3625",
    "addr:postcode":"80620",
    "addr:street":"23Rd Ave",
    "iso:country":"US",
    "sg:address":"3625 23rd Ave",
    "sg:city":"Evans",
    "sg:classifiers":[
        {
            "category":"Food & Beverages",
            "subcategory":"Liquor & Beverages",
            "type":"Retail Goods"
        }
    ],
    "sg:phone":"+1 970 339 5620",
    "sg:postcode":"80620",
    "sg:province":"CO",
    "sg:tags":[
        "alcoholic"
    ],
    "wof:name":"37th Liquors LLC",
    "wof:placetype":"venue"
},
  "geometry": {"coordinates":[-104.715772,40.378364],"type":"Point"}
}