{
  "type": "Feature",
  "properties": {
    "iso:country":"US",
    "sg:address":"413 Elk Ave",
    "sg:city":"Crested Butte",
    "sg:classifiers":[
        {
            "category":"Real Estate",
            "subcategory":"Real Estate Agent",
            "type":"Services"
        }
    ],
    "sg:phone":"+1 970 349 0378",
    "sg:postcode":"81224",
    "sg:province":"CO",
    "sg:tags":[
        "appraiser"
    ],
    "wof:name":"Charles A Peterson & Assoc",
    "wof:placetype":"venue"
},
  "geometry": {"coordinates":[-106.98401,38.869837],"type":"Point"}
}