{
  "type": "Feature",
  "properties": {
    "iso:country":"US",
    "sg:address":"3401 Quebec St",
    "sg:city":"Denver",
    "sg:classifiers":[
        {
            "category":"Manufacturing",
            "subcategory":"Food",
            "type":"Manufacturing & Wholesale Goods"
        }
    ],
    "sg:phone":"+1 303 399 6883",
    "sg:postcode":"80207",
    "sg:province":"CO",
    "sg:tags":[
        "mfg",
        "eating",
        "milk",
        "fluid"
    ],
    "wof:name":"Dannon Yougert",
    "wof:placetype":"venue"
},
  "geometry": {"coordinates":[-104.903515,39.764727],"type":"Point"}
}