{
  "type": "Feature",
  "properties": {
    "addr:full":"1402 W Pikes Peak Ave Colorado Springs CO 80904",
    "addr:housenumber":"1402",
    "addr:postcode":"80904",
    "addr:street":"W Pikes Peak Ave",
    "iso:country":"US",
    "sg:address":"1402 W Pikes Peak Ave",
    "sg:city":"Colorado Springs",
    "sg:classifiers":[
        {
            "category":"Organizations",
            "subcategory":"Religious Organization",
            "type":"Services"
        }
    ],
    "sg:phone":"+1 719 634 6138",
    "sg:postcode":"80904",
    "sg:province":"CO",
    "sg:tags":[
        "church"
    ],
    "sg:website":"www.pikespeakchurchofchrist.org",
    "wof:name":"Pikes Peak Church Of Christ",
    "wof:placetype":"venue"
},
  "geometry": {"coordinates":[-104.847543,38.839719],"type":"Point"}
}