{
  "type": "Feature",
  "properties": {
    "iso:country":"US",
    "sg:address":"870 S Colorado Boulevard",
    "sg:city":"Denver",
    "sg:classifiers":[
        {
            "category":"Education",
            "subcategory":"Vocational School",
            "type":"Public Place"
        }
    ],
    "sg:phone":"+1 303 733 9798",
    "sg:postcode":"80246",
    "sg:province":"CO",
    "sg:tags":[
        "cosmetology"
    ],
    "wof:name":"Antoine Du Chez Hair Dressing Academy",
    "wof:placetype":"venue"
},
  "geometry": {"coordinates":[-104.940558,39.700601],"type":"Point"}
}