{
  "type": "Feature",
  "properties": {
    "iso:country":"US",
    "sg:address":"2300 Dayton St",
    "sg:city":"Aurora",
    "sg:classifiers":[
        {
            "category":"Manufacturing",
            "subcategory":"Building Materials",
            "type":"Manufacturing & Wholesale Goods"
        },
        {
            "category":"Manufacturing",
            "subcategory":"Glass & Minerals",
            "type":"Manufacturing & Wholesale Goods"
        },
        {
            "category":"Retail",
            "subcategory":"Auto Repair",
            "type":"Services"
        }
    ],
    "sg:phone":"+1 303 344 8952",
    "sg:postcode":"80010",
    "sg:province":"CO",
    "sg:tags":[
        "plate",
        "glazier",
        "window",
        "replacement",
        "glass-wholesale",
        "glass-auto",
        "shape",
        "circle",
        "windshield",
        "special",
        "manufacturer"
    ],
    "wof:name":"B & M House Of Glass",
    "wof:placetype":"venue"
},
  "geometry": {"coordinates":[-104.875221,39.75108],"type":"Point"}
}