{
  "type": "Feature",
  "properties": {
    "iso:country":"US",
    "sg:address":"1001 N 5th St",
    "sg:city":"Grand Junction",
    "sg:classifiers":[
        {
            "category":"Banks & Credit Unions",
            "subcategory":"Bank",
            "type":"Services"
        }
    ],
    "sg:phone":"+1 970 243 3436",
    "sg:postcode":"81501",
    "sg:province":"CO",
    "sg:tags":[
        "mortgage"
    ],
    "wof:name":"Clarion Mortgage Capital Inc",
    "wof:placetype":"venue"
},
  "geometry": {"coordinates":[-108.564435,39.077411],"type":"Point"}
}