{
  "type": "Feature",
  "properties": {
    "addr:full":"4910 Fox Street Denver CO 80216",
    "addr:housenumber":"4910",
    "addr:postcode":"80216",
    "addr:street":"Fox Street",
    "iso:country":"US",
    "sg:address":"4910 Fox Street",
    "sg:city":"Denver",
    "sg:classifiers":[
        {
            "category":"Building & Trades",
            "subcategory":"Construction",
            "type":"Services"
        }
    ],
    "sg:phone":"+1 303 639 1300",
    "sg:postcode":"80216",
    "sg:province":"CO",
    "sg:tags":[
        "contractor"
    ],
    "wof:name":"Land Development & Construction Consultants",
    "wof:placetype":"venue"
},
  "geometry": {"coordinates":[-104.993849,39.786303],"type":"Point"}
}