{
  "type": "Feature",
  "properties": {
    "iso:country":"US",
    "sg:address":"446 Whitetail Ln",
    "sg:city":"Grand Junction",
    "sg:classifiers":[
        {
            "category":"Wholesale",
            "subcategory":"Groceries",
            "type":"Manufacturing & Wholesale Goods"
        }
    ],
    "sg:phone":"+1 970 242 5809",
    "sg:postcode":"81503",
    "sg:province":"CO",
    "sg:tags":[
        "general"
    ],
    "wof:name":"Dp Distributing",
    "wof:placetype":"venue"
},
  "geometry": {"coordinates":[-108.663231,39.072092],"type":"Point"}
}