{
  "type": "Feature",
  "properties": {
    "addr:full":"517 N Airport Rd Gypsum CO 81637",
    "addr:housenumber":"517",
    "addr:postcode":"81637",
    "addr:street":"N Airport Rd",
    "iso:country":"US",
    "sg:address":"517 N Airport Rd",
    "sg:city":"Gypsum",
    "sg:classifiers":[
        {
            "category":"Professional",
            "type":"Services"
        }
    ],
    "sg:phone":"+1 970 524 7185",
    "sg:postcode":"81637",
    "sg:province":"CO",
    "sg:tags":[
        "establishment"
    ],
    "wof:name":"Skatefish Co",
    "wof:placetype":"venue"
},
  "geometry": {"coordinates":[-106.917796,39.646843],"type":"Point"}
}