{
  "type": "Feature",
  "properties": {
    "addr:full":"4924 S Evanston St Aurora CO 80015",
    "addr:housenumber":"4924",
    "addr:postcode":"80015",
    "addr:street":"S Evanston St",
    "iso:country":"US",
    "sg:address":"4924 S Evanston St",
    "sg:city":"Aurora",
    "sg:classifiers":[
        {
            "category":"Professional",
            "type":"Services"
        }
    ],
    "sg:phone":"+1 303 680 3169",
    "sg:postcode":"80015",
    "sg:province":"CO",
    "wof:name":"Macburg LLC",
    "wof:placetype":"venue"
},
  "geometry": {"coordinates":[-104.814182,39.627729],"type":"Point"}
}