{
  "type": "Feature",
  "properties": {
    "iso:country":"US",
    "sg:address":"777 21st Ave",
    "sg:city":"Longmont",
    "sg:classifiers":[
        {
            "category":"Banks & Credit Unions",
            "subcategory":"Bank",
            "type":"Services"
        }
    ],
    "sg:phone":"+1 303 772 7776",
    "sg:postcode":"80501",
    "sg:province":"CO",
    "sg:tags":[
        "state"
    ],
    "wof:name":"St Vrain Valley Credit Union",
    "wof:placetype":"venue"
},
  "geometry": {"coordinates":[-105.104213,40.195606],"type":"Point"}
}