{
  "type": "Feature",
  "properties": {
    "addr:full":"2522 Paseo Rd Colorado Springs CO 80907",
    "addr:housenumber":"2522",
    "addr:postcode":"80907",
    "addr:street":"Paseo Rd",
    "iso:country":"US",
    "sg:address":"2522 Paseo Rd",
    "sg:city":"Colorado Springs",
    "sg:classifiers":[
        {
            "category":"Real Estate",
            "subcategory":"Real Estate Agent",
            "type":"Services"
        }
    ],
    "sg:phone":"+1 719 634 4560",
    "sg:postcode":"80907",
    "sg:province":"CO",
    "wof:name":"Jim Walker LLC",
    "wof:placetype":"venue"
},
  "geometry": {"coordinates":[-104.799421,38.86873],"type":"Point"}
}