{
  "type": "Feature",
  "properties": {
    "addr:full":"762 Cottage Ln Boulder CO 80304",
    "addr:housenumber":"762",
    "addr:postcode":"80304",
    "addr:street":"Cottage Ln",
    "iso:country":"US",
    "sg:address":"762 Cottage Ln",
    "sg:city":"Boulder",
    "sg:classifiers":[
        {
            "category":"Professional",
            "subcategory":"Art Services",
            "type":"Services"
        }
    ],
    "sg:phone":"+1 303 449 7444",
    "sg:postcode":"80304",
    "sg:province":"CO",
    "sg:tags":[
        "graphic",
        "designer"
    ],
    "wof:name":"Inspired Design",
    "wof:placetype":"venue"
},
  "geometry": {"coordinates":[-105.285788,40.051587],"type":"Point"}
}