{
  "type": "Feature",
  "properties": {
    "addr:full":"4 Woodfern Littleton CO 80127",
    "addr:housenumber":"4",
    "addr:postcode":"80127",
    "addr:street":"Woodfern",
    "iso:country":"US",
    "sg:address":"4 Woodfern",
    "sg:city":"Littleton",
    "sg:classifiers":[
        {
            "category":"Building & Trades",
            "subcategory":"Construction",
            "type":"Services"
        }
    ],
    "sg:phone":"+1 303 933 8860",
    "sg:postcode":"80127",
    "sg:province":"CO",
    "sg:tags":[
        "house"
    ],
    "wof:name":"Sovereign Construction Svcs",
    "wof:placetype":"venue"
},
  "geometry": {"coordinates":[-105.16228,39.576234],"type":"Point"}
}