{
  "type": "Feature",
  "properties": {
    "iso:country":"US",
    "sg:address":"15416 E Hampden Ave",
    "sg:city":"Aurora",
    "sg:classifiers":[
        {
            "category":"Personal",
            "subcategory":"Beauty Salon",
            "type":"Services"
        }
    ],
    "sg:phone":"+1 303 627 0778",
    "sg:postcode":"80013",
    "sg:province":"CO",
    "sg:tags":[
        "manicuring"
    ],
    "wof:name":"Golden Nail",
    "wof:placetype":"venue"
},
  "geometry": {"coordinates":[-104.808516,39.653006],"type":"Point"}
}