{
  "type": "Feature",
  "properties": {
    "iso:country":"US",
    "sg:address":"913 High Rd",
    "sg:city":"Manitou Springs",
    "sg:classifiers":[
        {
            "category":"Wholesale",
            "subcategory":"Fruits & Vegetables",
            "type":"Manufacturing & Wholesale Goods"
        }
    ],
    "sg:phone":"+1 719 351 0149",
    "sg:postcode":"80829",
    "sg:province":"CO",
    "sg:tags":[
        "veggie"
    ],
    "wof:name":"Youngevity",
    "wof:placetype":"venue"
},
  "geometry": {"coordinates":[-104.91819099999999,38.85496],"type":"Point"}
}