{
  "type": "Feature",
  "properties": {
    "iso:country":"US",
    "sg:address":"20034 Co Rd B",
    "sg:city":"Cortez",
    "sg:classifiers":[
        {
            "category":"Farming",
            "subcategory":"Livestock Farm",
            "type":"Manufacturing & Wholesale Goods"
        }
    ],
    "sg:phone":"+1 970 565 3518",
    "sg:postcode":"81321",
    "sg:province":"CO",
    "sg:tags":[
        "beef",
        "feedlot",
        "cattle"
    ],
    "wof:name":"Drew Gordanier",
    "wof:placetype":"venue"
},
  "geometry": {"coordinates":[-108.681522,37.239301],"type":"Point"}
}