{
  "type": "Feature",
  "properties": {
    "addr:full":"2016 21st St Boulder CO 80302",
    "addr:housenumber":"2016",
    "addr:postcode":"80302",
    "addr:street":"21St St",
    "iso:country":"US",
    "sg:address":"2016 21st St",
    "sg:city":"Boulder",
    "sg:classifiers":[
        {
            "category":"Building & Trades",
            "subcategory":"Plumbing",
            "type":"Services"
        }
    ],
    "sg:phone":"+1 303 442 4825",
    "sg:postcode":"80302",
    "sg:province":"CO",
    "sg:tags":[
        "plumbing",
        "heating",
        "contractor"
    ],
    "wof:name":"Chesebro Plumbing & Heating Co",
    "wof:placetype":"venue"
},
  "geometry": {"coordinates":[-105.26840799999999,40.021179],"type":"Point"}
}