{
  "type": "Feature",
  "properties": {
    "addr:full":"1305 N Union Blvd Colorado Springs CO 80909",
    "addr:housenumber":"1305",
    "addr:postcode":"80909",
    "addr:street":"N Union Blvd",
    "iso:country":"US",
    "sg:address":"1305 N Union Blvd",
    "sg:city":"Colorado Springs",
    "sg:classifiers":[
        {
            "category":"Organizations",
            "subcategory":"Religious Organization",
            "type":"Services"
        }
    ],
    "sg:phone":"+1 719 634 1682",
    "sg:postcode":"80909",
    "sg:province":"CO",
    "sg:tags":[
        "church"
    ],
    "wof:name":"Central Seventh-Day Adventist",
    "wof:placetype":"venue"
},
  "geometry": {"coordinates":[-104.794144,38.850621],"type":"Point"}
}