{
  "type": "Feature",
  "properties": {
    "addr:full":"1850 Baldwin Park Rd Castle Rock CO 80104",
    "addr:housenumber":"1850",
    "addr:postcode":"80104",
    "addr:street":"Baldwin Park Rd",
    "iso:country":"US",
    "sg:address":"1850 Baldwin Park Rd",
    "sg:city":"Castle Rock",
    "sg:classifiers":[
        {
            "category":"Building & Trades",
            "subcategory":"Construction",
            "type":"Services"
        }
    ],
    "sg:phone":"+1 303 660 0755",
    "sg:postcode":"80104",
    "sg:province":"CO",
    "sg:tags":[
        "painter"
    ],
    "wof:name":"Crenshaws' Old World",
    "wof:placetype":"venue"
},
  "geometry": {"coordinates":[-104.841257,39.358335],"type":"Point"}
}