{
  "type": "Feature",
  "properties": {
    "iso:country":"US",
    "sg:address":"5855 Wadsworth Byp",
    "sg:city":"Arvada",
    "sg:classifiers":[
        {
            "category":"Professional",
            "subcategory":"Engineering",
            "type":"Services"
        }
    ],
    "sg:phone":"+1 303 423 6036",
    "sg:postcode":"80003",
    "sg:province":"CO",
    "sg:tags":[
        "consulting",
        "engineer"
    ],
    "sg:website":"www.jehnengineering.com",
    "wof:name":"Jehn Engineering",
    "wof:placetype":"venue"
},
  "geometry": {"coordinates":[-105.076606,39.802898],"type":"Point"}
}