{
  "type": "Feature",
  "properties": {
    "addr:full":"2021 Battlecreek Dr Fort Collins CO 80528",
    "addr:housenumber":"2021",
    "addr:postcode":"80528",
    "addr:street":"Battlecreek Dr",
    "iso:country":"US",
    "sg:address":"2021 Battlecreek Dr",
    "sg:city":"Fort Collins",
    "sg:classifiers":[
        {
            "category":"Health Services",
            "subcategory":"Doctor",
            "type":"Services"
        }
    ],
    "sg:phone":"+1 970 206 0851",
    "sg:postcode":"80528",
    "sg:province":"CO",
    "sg:tags":[
        "physician",
        "surgeon",
        "medical"
    ],
    "wof:name":"Adamson Family Care",
    "wof:placetype":"venue"
},
  "geometry": {"coordinates":[-105.04112600000001,40.514546],"type":"Point"}
}