{
  "type": "Feature",
  "properties": {
    "iso:country":"US",
    "sg:address":"225 S Pearl St",
    "sg:city":"Bayfield",
    "sg:classifiers":[
        {
            "category":"Shopping",
            "subcategory":"Used Merchandise",
            "type":"Retail Goods"
        }
    ],
    "sg:phone":"+1 970 884 4466",
    "sg:postcode":"81122",
    "sg:province":"CO",
    "sg:tags":[
        "antique"
    ],
    "wof:name":"Good Ol' Days Antiques",
    "wof:placetype":"venue"
},
  "geometry": {"coordinates":[-107.600182,37.228219],"type":"Point"}
}