{
  "type": "Feature",
  "properties": {
    "iso:country":"US",
    "sg:address":"3825 Brushland Ct",
    "sg:city":"Colorado Springs",
    "sg:classifiers":[
        {
            "category":"Food & Beverages",
            "subcategory":"Specialty",
            "type":"Retail Goods"
        }
    ],
    "sg:phone":"+1 719 385 0079",
    "sg:postcode":"80904",
    "sg:province":"CO",
    "sg:tags":[
        "health",
        "diet"
    ],
    "wof:name":"Mannatech Presidentials",
    "wof:placetype":"venue"
},
  "geometry": {"coordinates":[-104.854117,38.885448],"type":"Point"}
}