{
  "type": "Feature",
  "properties": {
    "addr:full":"5881 S Kenton Way Englewood CO 80111",
    "addr:housenumber":"5881",
    "addr:postcode":"80111",
    "addr:street":"S Kenton Way",
    "iso:country":"US",
    "sg:address":"5881 S Kenton Way",
    "sg:city":"Englewood",
    "sg:classifiers":[
        {
            "category":"Wholesale",
            "subcategory":"Non-durable Goods",
            "type":"Manufacturing & Wholesale Goods"
        }
    ],
    "sg:phone":"+1 303 850 5417",
    "sg:postcode":"80111",
    "sg:province":"CO",
    "wof:name":"Thansuong Trading LLC",
    "wof:placetype":"venue"
},
  "geometry": {"coordinates":[-104.860269,39.613321],"type":"Point"}
}