{
  "type": "Feature",
  "properties": {
    "iso:country":"US",
    "sg:address":"115 W Bijou Ave",
    "sg:city":"Fort Morgan",
    "sg:classifiers":[
        {
            "category":"Personal",
            "subcategory":"Beauty Salon",
            "type":"Services"
        }
    ],
    "sg:phone":"+1 970 867 5956",
    "sg:postcode":"80701",
    "sg:province":"CO",
    "wof:name":"Fantastic Beauty Salon",
    "wof:placetype":"venue"
},
  "geometry": {"coordinates":[-103.801625,40.252706],"type":"Point"}
}