{
  "type": "Feature",
  "properties": {
    "iso:country":"US",
    "sg:address":"379 S Troy St",
    "sg:city":"Aurora",
    "sg:classifiers":[
        {
            "category":"Social Services",
            "subcategory":"Adult Care",
            "type":"Services"
        }
    ],
    "sg:phone":"+1 303 739 9804",
    "sg:postcode":"80012",
    "sg:province":"CO",
    "sg:tags":[
        "home",
        "residential"
    ],
    "wof:name":"Ra Quita's Home Away From Home",
    "wof:placetype":"venue"
},
  "geometry": {"coordinates":[-104.841328,39.708874],"type":"Point"}
}