{
  "type": "Feature",
  "properties": {
    "addr:full":"109 N Campbell Ave Holyoke CO 80734",
    "addr:housenumber":"109",
    "addr:postcode":"80734",
    "addr:street":"N Campbell Ave",
    "iso:country":"US",
    "sg:address":"109 N Campbell Ave",
    "sg:city":"Holyoke",
    "sg:classifiers":[
        {
            "category":"Banks & Credit Unions",
            "subcategory":"Bank",
            "type":"Services"
        }
    ],
    "sg:phone":"+1 970 854 7800",
    "sg:postcode":"80734",
    "sg:province":"CO",
    "sg:tags":[
        "loan"
    ],
    "wof:name":"Team Financial",
    "wof:placetype":"venue"
},
  "geometry": {"coordinates":[-102.300748,40.586036],"type":"Point"}
}