{
  "type": "Feature",
  "properties": {
    "iso:country":"US",
    "sg:address":"1726 Constitution Rd",
    "sg:city":"Pueblo",
    "sg:classifiers":[
        {
            "category":"Retail",
            "subcategory":"Self-service Laundry",
            "type":"Services"
        }
    ],
    "sg:phone":"+1 719 546 8154",
    "sg:postcode":"81001",
    "sg:province":"CO",
    "wof:name":"Troy Village Laundry",
    "wof:placetype":"venue"
},
  "geometry": {"coordinates":[-104.573566,38.288116],"type":"Point"}
}