{
  "type": "Feature",
  "properties": {
    "iso:country":"US",
    "sg:address":"717 Main St",
    "sg:city":"Alamosa",
    "sg:classifiers":[
        {
            "category":"Shopping",
            "subcategory":"Used Merchandise",
            "type":"Retail Goods"
        },
        {
            "category":"Wholesale",
            "subcategory":"Home Furnishings",
            "type":"Manufacturing & Wholesale Goods"
        }
    ],
    "sg:phone":"+1 719 589 5232",
    "sg:postcode":"81101",
    "sg:province":"CO",
    "sg:tags":[
        "on",
        "secondhand",
        "closet",
        "accessory",
        "consignment",
        "clothing"
    ],
    "wof:name":"Classy Closet II",
    "wof:placetype":"venue"
},
  "geometry": {"coordinates":[-105.868574,37.468257],"type":"Point"}
}