{
  "type": "Feature",
  "properties": {
    "addr:full":"701 W Colorado Ave Colorado Springs CO 80905",
    "addr:housenumber":"701",
    "addr:postcode":"80905",
    "addr:street":"W Colorado Ave",
    "iso:country":"US",
    "sg:address":"701 W Colorado Ave",
    "sg:city":"Colorado Springs",
    "sg:classifiers":[
        {
            "category":"Home & Garden",
            "subcategory":"Garden Supply",
            "type":"Retail Goods"
        }
    ],
    "sg:phone":"+1 719 475 2748",
    "sg:postcode":"80905",
    "sg:province":"CO",
    "sg:tags":[
        "nurseryman"
    ],
    "wof:name":"Betterway Nursery & Garden Ctr",
    "wof:placetype":"venue"
},
  "geometry": {"coordinates":[-104.83813600000001,38.833019],"type":"Point"}
}