{
  "type": "Feature",
  "properties": {
    "iso:country":"US",
    "sg:address":"437 S Gilpin St",
    "sg:city":"Denver",
    "sg:classifiers":[
        {
            "category":"Manufacturing",
            "subcategory":"Tools & Machinery",
            "type":"Manufacturing & Wholesale Goods"
        }
    ],
    "sg:phone":"+1 303 715 1782",
    "sg:postcode":"80209",
    "sg:province":"CO",
    "sg:tags":[
        "equipment",
        "calculating",
        "mfg"
    ],
    "wof:name":"Kordinn Point LLC",
    "wof:placetype":"venue"
},
  "geometry": {"coordinates":[-104.967556,39.708155],"type":"Point"}
}