{
  "type": "Feature",
  "properties": {
    "addr:full":"3947 York St Denver CO 80205",
    "addr:housenumber":"3947",
    "addr:postcode":"80205",
    "addr:street":"York St",
    "iso:country":"US",
    "sg:address":"3947 York St",
    "sg:city":"Denver",
    "sg:classifiers":[
        {
            "category":"Building & Trades",
            "subcategory":"Locksmith",
            "type":"Services"
        }
    ],
    "sg:phone":"+1 303 395 2070",
    "sg:postcode":"80205",
    "sg:province":"CO",
    "sg:tags":[
        "key"
    ],
    "wof:name":"A Emergency Locksmith",
    "wof:placetype":"venue"
},
  "geometry": {"coordinates":[-104.95987,39.77203],"type":"Point"}
}