{
  "type": "Feature",
  "properties": {
    "addr:full":"928 Quail St Denver CO 80215",
    "addr:housenumber":"928",
    "addr:postcode":"80215",
    "addr:street":"Quail St",
    "iso:country":"US",
    "sg:address":"928 Quail St",
    "sg:city":"Denver",
    "sg:classifiers":[
        {
            "category":"Communications",
            "type":"Services"
        }
    ],
    "sg:phone":"+1 303 233 2800",
    "sg:postcode":"80215",
    "sg:province":"CO",
    "sg:tags":[
        "datum",
        "center"
    ],
    "wof:name":"Bax Global Inc",
    "wof:placetype":"venue"
},
  "geometry": {"coordinates":[-105.123627,39.732169],"type":"Point"}
}