{
  "type": "Feature",
  "properties": {
    "iso:country":"US",
    "sg:address":"7401 E Jamison Cir",
    "sg:city":"Centennial",
    "sg:classifiers":[
        {
            "category":"Real Estate",
            "subcategory":"Real Estate Agent",
            "type":"Services"
        }
    ],
    "sg:phone":"+1 720 488 7371",
    "sg:postcode":"80112",
    "sg:province":"CO",
    "sg:tags":[
        "finding",
        "apartment",
        "rental"
    ],
    "wof:name":"Apartment Blue Book",
    "wof:placetype":"venue"
},
  "geometry": {"coordinates":[-104.90301700000001,39.577345],"type":"Point"}
}