{
  "type": "Feature",
  "properties": {
    "iso:country":"US",
    "sg:address":"9082 W Layton Ave",
    "sg:city":"Denver",
    "sg:classifiers":[
        {
            "category":"Building & Trades",
            "subcategory":"Construction",
            "type":"Services"
        }
    ],
    "sg:phone":"+1 303 932 7270",
    "sg:postcode":"80123",
    "sg:province":"CO",
    "sg:tags":[
        "tile",
        "dealer"
    ],
    "wof:name":"Boyd Enterprises",
    "wof:placetype":"venue"
},
  "geometry": {"coordinates":[-105.099632,39.630144],"type":"Point"}
}