{
  "type": "Feature",
  "properties": {
    "addr:full":"109 W Midland Ave Woodland Park CO 80863",
    "addr:housenumber":"109",
    "addr:postcode":"80863",
    "addr:street":"W Midland Ave",
    "iso:country":"US",
    "sg:address":"109 W Midland Ave",
    "sg:city":"Woodland Park",
    "sg:classifiers":[
        {
            "category":"Real Estate",
            "subcategory":"Real Estate Agent",
            "type":"Services"
        }
    ],
    "sg:phone":"+1 719 636 5147",
    "sg:postcode":"80863",
    "sg:province":"CO",
    "sg:tags":[
        "rental",
        "vacation"
    ],
    "wof:name":"Colorado Mountain Cabin",
    "wof:placetype":"venue"
},
  "geometry": {"coordinates":[-105.06464200000001,38.993568],"type":"Point"}
}