{
  "type": "Feature",
  "properties": {
    "iso:country":"US",
    "sg:address":"2443 W Stuart St",
    "sg:city":"Fort Collins",
    "sg:classifiers":[
        {
            "category":"Building & Trades",
            "subcategory":"Cleaning & Sanitation",
            "type":"Services"
        }
    ],
    "sg:phone":"+1 970 493 4832",
    "sg:postcode":"80526",
    "sg:province":"CO",
    "sg:tags":[
        "janitor"
    ],
    "wof:name":"Freedom Enterprises",
    "wof:placetype":"venue"
},
  "geometry": {"coordinates":[-105.122179,40.56177],"type":"Point"}
}