{
  "type": "Feature",
  "properties": {
    "iso:country":"US",
    "sg:address":"719 E 17th Ave",
    "sg:city":"Denver",
    "sg:classifiers":[
        {
            "category":"Restaurant",
            "type":"Food & Drink"
        }
    ],
    "sg:phone":"+1 303 861 5050",
    "sg:postcode":"80203",
    "sg:province":"CO",
    "sg:tags":[
        "breakfast",
        "mediterranean",
        "brunch"
    ],
    "sg:website":"olivearestaurant.com",
    "wof:name":"Oliv?a",
    "wof:placetype":"venue"
},
  "geometry": {"coordinates":[-104.97808000000001,39.743566],"type":"Point"}
}