{
  "type": "Feature",
  "properties": {
    "iso:country":"US",
    "sg:address":"9420 Green Ct",
    "sg:city":"Westminster",
    "sg:classifiers":[
        {
            "category":"Building & Trades",
            "subcategory":"Construction",
            "type":"Services"
        }
    ],
    "sg:phone":"+1 303 657 3420",
    "sg:postcode":"80031",
    "sg:province":"CO",
    "sg:tags":[
        "contractor"
    ],
    "wof:name":"Lots A Stripes Inc",
    "wof:placetype":"venue"
},
  "geometry": {"coordinates":[-105.025767,39.867492],"type":"Point"}
}