{
  "type": "Feature",
  "properties": {
    "iso:country":"US",
    "sg:address":"11641 Logan St",
    "sg:city":"Denver",
    "sg:classifiers":[
        {
            "category":"Manufacturing",
            "subcategory":"Printing",
            "type":"Manufacturing & Wholesale Goods"
        }
    ],
    "sg:phone":"+1 303 457 0948",
    "sg:postcode":"80233",
    "sg:province":"CO",
    "sg:tags":[
        "book"
    ],
    "wof:name":"Konopka Publications",
    "wof:placetype":"venue"
},
  "geometry": {"coordinates":[-104.98030799999999,39.908504],"type":"Point"}
}