{
  "type": "Feature",
  "properties": {
    "iso:country":"US",
    "sg:address":"105 Fordham Cir",
    "sg:city":"Pueblo",
    "sg:classifiers":[
        {
            "category":"Organizations",
            "subcategory":"Community Association",
            "type":"Services"
        }
    ],
    "sg:phone":"+1 719 561 0568",
    "sg:postcode":"81005",
    "sg:province":"CO",
    "wof:name":"Silver Lakes Trout Club",
    "wof:placetype":"venue"
},
  "geometry": {"coordinates":[-104.65618600000001,38.251196],"type":"Point"}
}