{
  "type": "Feature",
  "properties": {
    "addr:full":"2945 W 23rd Avenue Denver CO 80211",
    "addr:housenumber":"2945",
    "addr:postcode":"80211",
    "addr:street":"W 23Rd Avenue",
    "iso:country":"US",
    "sg:address":"2945 W 23rd Avenue",
    "sg:city":"Denver",
    "sg:classifiers":[
        {
            "category":"Restaurant",
            "type":"Food & Drink"
        }
    ],
    "sg:phone":"+1 303 480 5332",
    "sg:postcode":"80211",
    "sg:province":"CO",
    "sg:tags":[
        "mexican"
    ],
    "wof:name":"Tacos Mi Pueblo",
    "wof:placetype":"venue"
},
  "geometry": {"coordinates":[-105.024872,39.751101],"type":"Point"}
}