{
  "type": "Feature",
  "properties": {
    "addr:full":"14240 W 71st Ave Arvada CO 80004",
    "addr:housenumber":"14240",
    "addr:postcode":"80004",
    "addr:street":"W 71St Ave",
    "iso:country":"US",
    "sg:address":"14240 W 71st Ave",
    "sg:city":"Arvada",
    "sg:classifiers":[
        {
            "category":"Building & Trades",
            "subcategory":"Construction",
            "type":"Services"
        }
    ],
    "sg:phone":"+1 303 423 4086",
    "sg:postcode":"80004",
    "sg:province":"CO",
    "sg:tags":[
        "house"
    ],
    "wof:name":"Team One Remodelers Inc",
    "wof:placetype":"venue"
},
  "geometry": {"coordinates":[-105.160167,39.825124],"type":"Point"}
}