{
  "type": "Feature",
  "properties": {
    "iso:country":"US",
    "sg:address":"1830 Cornice Rd",
    "sg:city":"Steamboat Spgs",
    "sg:classifiers":[
        {
            "category":"Real Estate",
            "subcategory":"Real Estate Agent",
            "type":"Services"
        }
    ],
    "sg:phone":"+1 970 870 0497",
    "sg:postcode":"80487",
    "sg:province":"CO",
    "sg:tags":[
        "management"
    ],
    "wof:name":"Abet Owner Svc",
    "wof:placetype":"venue"
},
  "geometry": {"coordinates":[-106.80818499999999,40.462343],"type":"Point"}
}