{
  "type": "Feature",
  "properties": {
    "addr:full":"4615 Castor Dr Pueblo CO 81001",
    "addr:housenumber":"4615",
    "addr:postcode":"81001",
    "addr:street":"Castor Dr",
    "iso:country":"US",
    "sg:address":"4615 Castor Dr",
    "sg:city":"Pueblo",
    "sg:classifiers":[
        {
            "category":"Retail",
            "subcategory":"Portrait Studio",
            "type":"Services"
        }
    ],
    "sg:phone":"+1 719 544 8131",
    "sg:postcode":"81001",
    "sg:province":"CO",
    "sg:tags":[
        "photo"
    ],
    "wof:name":"Napesta Trading",
    "wof:placetype":"venue"
},
  "geometry": {"coordinates":[-104.598068,38.318804],"type":"Point"}
}