{
  "type": "Feature",
  "properties": {
    "addr:full":"12 S Main St Alma CO 80420",
    "addr:housenumber":"12",
    "addr:postcode":"80420",
    "addr:street":"S Main St",
    "iso:country":"US",
    "sg:address":"12 S Main St",
    "sg:city":"Alma",
    "sg:classifiers":[
        {
            "category":"Bars & Pubs",
            "type":"Food & Drink"
        }
    ],
    "sg:phone":"+1 719 836 1609",
    "sg:postcode":"80420",
    "sg:province":"CO",
    "wof:name":"Alma's Only Bar",
    "wof:placetype":"venue"
},
  "geometry": {"coordinates":[-106.06242399999999,39.283533],"type":"Point"}
}