{
  "type": "Feature",
  "properties": {
    "addr:full":"5969 N Academy Blvd Colorado Springs CO 80918",
    "addr:housenumber":"5969",
    "addr:postcode":"80918",
    "addr:street":"N Academy Blvd",
    "iso:country":"US",
    "sg:address":"5969 N Academy Blvd",
    "sg:city":"Colorado Springs",
    "sg:classifiers":[
        {
            "category":"Shopping",
            "subcategory":"Hobbies, Toys, & Games",
            "type":"Retail Goods"
        }
    ],
    "sg:phone":"+1 719 268 0765",
    "sg:postcode":"80918",
    "sg:province":"CO",
    "sg:tags":[
        "supply"
    ],
    "wof:name":"Gamers Gathering",
    "wof:placetype":"venue"
},
  "geometry": {"coordinates":[-104.78678600000001,38.918115],"type":"Point"}
}