{
  "type": "Feature",
  "properties": {
    "iso:country":"US",
    "sg:address":"7585 W 66th Avenue",
    "sg:city":"Arvada",
    "sg:classifiers":[
        {
            "category":"Professional",
            "subcategory":"Computer Services",
            "type":"Services"
        }
    ],
    "sg:phone":"+1 303 424 7015",
    "sg:postcode":"80003",
    "sg:province":"CO",
    "sg:tags":[
        "repair"
    ],
    "wof:name":"Countertrade Products",
    "wof:placetype":"venue"
},
  "geometry": {"coordinates":[-105.08090300000001,39.816512],"type":"Point"}
}