{
  "type": "Feature",
  "properties": {
    "addr:full":"1699 Green Oaks Dr Littleton CO 80121",
    "addr:housenumber":"1699",
    "addr:postcode":"80121",
    "addr:street":"Green Oaks Dr",
    "iso:country":"US",
    "sg:address":"1699 Green Oaks Dr",
    "sg:city":"Littleton",
    "sg:classifiers":[
        {
            "category":"Insurance",
            "subcategory":"Insurance Agent",
            "type":"Services"
        }
    ],
    "sg:phone":"+1 303 796 8008",
    "sg:postcode":"80121",
    "sg:province":"CO",
    "wof:name":"Creative Capital Inc",
    "wof:placetype":"venue"
},
  "geometry": {"coordinates":[-104.959975,39.611559],"type":"Point"}
}