{
  "type": "Feature",
  "properties": {
    "addr:full":"3912 Fawn Trl Loveland CO 80537",
    "addr:housenumber":"3912",
    "addr:postcode":"80537",
    "addr:street":"Fawn Trl",
    "iso:country":"US",
    "sg:address":"3912 Fawn Trl",
    "sg:city":"Loveland",
    "sg:classifiers":[
        {
            "category":"Building & Trades",
            "subcategory":"Construction",
            "type":"Services"
        }
    ],
    "sg:phone":"+1 970 663 3112",
    "sg:postcode":"80537",
    "sg:province":"CO",
    "sg:tags":[
        "house"
    ],
    "wof:name":"Sky Country Construction",
    "wof:placetype":"venue"
},
  "geometry": {"coordinates":[-105.20295299999999,40.351226],"type":"Point"}
}