{
  "type": "Feature",
  "properties": {
    "iso:country":"US",
    "sg:address":"4600 S Ulster St",
    "sg:city":"Denver",
    "sg:classifiers":[
        {
            "category":"Professional",
            "subcategory":"Management & Consulting",
            "type":"Services"
        }
    ],
    "sg:phone":"+1 303 771 1800",
    "sg:postcode":"80237",
    "sg:province":"CO",
    "sg:tags":[
        "consultant",
        "business"
    ],
    "wof:name":"HRC/Svl",
    "wof:placetype":"venue"
},
  "geometry": {"coordinates":[-104.896646,39.631329],"type":"Point"}
}