{
  "type": "Feature",
  "properties": {
    "addr:full":"6378 S Miller St Littleton CO 80127",
    "addr:housenumber":"6378",
    "addr:postcode":"80127",
    "addr:street":"S Miller St",
    "iso:country":"US",
    "sg:address":"6378 S Miller St",
    "sg:city":"Littleton",
    "sg:classifiers":[
        {
            "category":"Building & Trades",
            "subcategory":"Construction",
            "type":"Services"
        }
    ],
    "sg:phone":"+1 720 981 9332",
    "sg:postcode":"80127",
    "sg:province":"CO",
    "sg:tags":[
        "home",
        "builder"
    ],
    "wof:name":"Continental Homes",
    "wof:placetype":"venue"
},
  "geometry": {"coordinates":[-105.114085,39.601595],"type":"Point"}
}