{
  "type": "Feature",
  "properties": {
    "addr:full":"117 Colorado Ave Pueblo CO 81004",
    "addr:housenumber":"117",
    "addr:postcode":"81004",
    "addr:street":"Colorado Ave",
    "iso:country":"US",
    "sg:address":"117 Colorado Ave",
    "sg:city":"Pueblo",
    "sg:classifiers":[
        {
            "category":"Education",
            "subcategory":"Dance Studio",
            "type":"Public Place"
        }
    ],
    "sg:phone":"+1 719 542 2143",
    "sg:postcode":"81004",
    "sg:province":"CO",
    "sg:tags":[
        "instruction",
        "dancing"
    ],
    "wof:name":"Connie's School Of Dance",
    "wof:placetype":"venue"
},
  "geometry": {"coordinates":[-104.621835,38.259396],"type":"Point"}
}