{
  "type": "Feature",
  "properties": {
    "iso:country":"US",
    "sg:address":"311 Main St",
    "sg:city":"Ouray",
    "sg:classifiers":[
        {
            "category":"Mining & Drilling",
            "type":"Manufacturing & Wholesale Goods"
        }
    ],
    "sg:phone":"+1 970 325 4482",
    "sg:postcode":"81427",
    "sg:province":"CO",
    "sg:tags":[
        "company"
    ],
    "wof:name":"Idarado Legacy",
    "wof:placetype":"venue"
},
  "geometry": {"coordinates":[-107.671435,38.020477],"type":"Point"}
}