{
  "type": "Feature",
  "properties": {
    "addr:full":"4320 Danceglen Dr Colorado Springs CO 80906",
    "addr:housenumber":"4320",
    "addr:postcode":"80906",
    "addr:street":"Danceglen Dr",
    "iso:country":"US",
    "sg:address":"4320 Danceglen Dr",
    "sg:city":"Colorado Springs",
    "sg:classifiers":[
        {
            "category":"Wholesale",
            "subcategory":"Construction Materials",
            "type":"Manufacturing & Wholesale Goods"
        }
    ],
    "sg:phone":"+1 719 538 9067",
    "sg:postcode":"80906",
    "sg:province":"CO",
    "sg:tags":[
        "concrete",
        "contractor"
    ],
    "wof:name":"Stevens Concrete",
    "wof:placetype":"venue"
},
  "geometry": {"coordinates":[-104.815478,38.756116],"type":"Point"}
}