{
  "type": "Feature",
  "properties": {
    "iso:country":"US",
    "sg:address":"1504 13th Ave",
    "sg:city":"Greeley",
    "sg:classifiers":[
        {
            "category":"Professional",
            "subcategory":"Management & Consulting",
            "type":"Services"
        }
    ],
    "sg:phone":"+1 970 356 9472",
    "sg:postcode":"80631",
    "sg:province":"CO",
    "sg:tags":[
        "consultant",
        "educational"
    ],
    "wof:name":"Educational Research & Trnng",
    "wof:placetype":"venue"
},
  "geometry": {"coordinates":[-104.69987500000001,40.413872],"type":"Point"}
}