{
  "type": "Feature",
  "properties": {
    "addr:full":"3755 S Jason St Englewood CO 80110",
    "addr:housenumber":"3755",
    "addr:postcode":"80110",
    "addr:street":"S Jason St",
    "iso:country":"US",
    "sg:address":"3755 S Jason St",
    "sg:city":"Englewood",
    "sg:classifiers":[
        {
            "category":"Manufacturing",
            "subcategory":"Metals",
            "type":"Manufacturing & Wholesale Goods"
        }
    ],
    "sg:phone":"+1 303 762 8744",
    "sg:postcode":"80110",
    "sg:province":"CO",
    "sg:tags":[
        "coating",
        "mfg"
    ],
    "sg:website":"www.empiremetalspray.com",
    "wof:name":"Empire Metal Spray Inc",
    "wof:placetype":"venue"
},
  "geometry": {"coordinates":[-104.99946300000001,39.648598],"type":"Point"}
}