{
  "type": "Feature",
  "properties": {
    "iso:country":"US",
    "sg:address":"341 Main St",
    "sg:city":"Delta",
    "sg:classifiers":[
        {
            "category":"Shopping",
            "subcategory":"Clothing, Apparel, & Fashions",
            "type":"Retail Goods"
        }
    ],
    "sg:phone":"+1 970 874 3317",
    "sg:postcode":"81416",
    "sg:province":"CO",
    "sg:tags":[
        "ready",
        "lady"
    ],
    "wof:name":"Taras",
    "wof:placetype":"venue"
},
  "geometry": {"coordinates":[-108.070958,38.742202],"type":"Point"}
}