{
  "type": "Feature",
  "properties": {
    "iso:country":"US",
    "sg:address":"321 E Platte Ave",
    "sg:city":"Fort Morgan",
    "sg:classifiers":[
        {
            "category":"Professional",
            "subcategory":"Art Services",
            "type":"Services"
        }
    ],
    "sg:phone":"+1 970 867 2214",
    "sg:postcode":"80701",
    "sg:province":"CO",
    "sg:tags":[
        "photographer"
    ],
    "wof:name":"Frances Photography",
    "wof:placetype":"venue"
},
  "geometry": {"coordinates":[-103.79821099999999,40.25406],"type":"Point"}
}