{
  "type": "Feature",
  "properties": {
    "addr:full":"3230 Walnut St. Denver CO 80205",
    "addr:housenumber":"3230",
    "addr:postcode":"80205",
    "addr:street":"Walnut St.",
    "iso:country":"US",
    "sg:address":"3230 Walnut St.",
    "sg:city":"Denver",
    "sg:classifiers":[
        {
            "category":"Arts & Performance",
            "subcategory":"Art Gallery",
            "type":"Entertainment"
        }
    ],
    "sg:phone":"+1 303 296 2141",
    "sg:postcode":"80205",
    "sg:province":"CO",
    "sg:website":"www.claudevictorart.com/",
    "wof:name":"Claude Victor Art Studio",
    "wof:placetype":"venue"
},
  "geometry": {"coordinates":[-104.978117,39.765493],"type":"Point"}
}