{
  "type": "Feature",
  "properties": {
    "addr:full":"102 S Main St Gunnison CO 81230",
    "addr:housenumber":"102",
    "addr:postcode":"81230",
    "addr:street":"S Main St",
    "iso:country":"US",
    "sg:address":"102 S Main St",
    "sg:city":"Gunnison",
    "sg:classifiers":[
        {
            "category":"Museum",
            "type":"Entertainment"
        }
    ],
    "sg:phone":"+1 970 641 4029",
    "sg:postcode":"81230",
    "sg:province":"CO",
    "sg:tags":[
        "organization",
        "arts",
        "information"
    ],
    "wof:name":"Gunnison Arts Ctr",
    "wof:placetype":"venue"
},
  "geometry": {"coordinates":[-106.92686,38.544389],"type":"Point"}
}