{
  "type": "Feature",
  "properties": {
    "iso:country":"US",
    "sg:address":"1831 Main St",
    "sg:city":"Colorado Springs",
    "sg:classifiers":[
        {
            "category":"Bars & Pubs",
            "type":"Food & Drink"
        }
    ],
    "sg:phone":"+1 719 393 7299",
    "sg:postcode":"80911",
    "sg:province":"CO",
    "wof:name":"Shots",
    "wof:placetype":"venue"
},
  "geometry": {"coordinates":[-104.739193,38.767647],"type":"Point"}
}