{
  "type": "Feature",
  "properties": {
    "iso:country":"US",
    "sg:address":"120 W 2nd St",
    "sg:city":"Salida",
    "sg:classifiers":[
        {
            "category":"Building & Trades",
            "subcategory":"Construction",
            "type":"Services"
        }
    ],
    "sg:phone":"+1 719 539 9389",
    "sg:postcode":"81201",
    "sg:province":"CO",
    "sg:tags":[
        "general",
        "contractor"
    ],
    "wof:name":"Fred Soldow",
    "wof:placetype":"venue"
},
  "geometry": {"coordinates":[-105.993477,38.536024],"type":"Point"}
}