{
  "type": "Feature",
  "properties": {
    "iso:country":"US",
    "sg:address":"14001 E Iliff Ave",
    "sg:city":"Aurora",
    "sg:classifiers":[
        {
            "category":"Shopping",
            "subcategory":"Computers & Home Electronics",
            "type":"Retail Goods"
        }
    ],
    "sg:phone":"+1 303 696 8150",
    "sg:postcode":"80014",
    "sg:province":"CO",
    "sg:tags":[
        "program"
    ],
    "wof:name":"C C I Triad",
    "wof:placetype":"venue"
},
  "geometry": {"coordinates":[-104.825309,39.674931],"type":"Point"}
}