{
  "type": "Feature",
  "properties": {
    "addr:full":"1555 S Kipling Ct Lakewood CO 80232",
    "addr:housenumber":"1555",
    "addr:postcode":"80232",
    "addr:street":"S Kipling Ct",
    "iso:country":"US",
    "sg:address":"1555 S Kipling Ct",
    "sg:city":"Lakewood",
    "sg:classifiers":[
        {
            "category":"Personal",
            "subcategory":"Beauty Salon",
            "type":"Services"
        }
    ],
    "sg:phone":"+1 303 984 9695",
    "sg:postcode":"80232",
    "sg:province":"CO",
    "wof:name":"Signature Salon",
    "wof:placetype":"venue"
},
  "geometry": {"coordinates":[-105.111092,39.687554],"type":"Point"}
}