{
  "type": "Feature",
  "properties": {
    "iso:country":"US",
    "sg:address":"1600 S Lemay Ave",
    "sg:city":"Fort Collins",
    "sg:classifiers":[
        {
            "category":"Food & Beverages",
            "subcategory":"Groceries & Convenience Stores",
            "type":"Retail Goods"
        }
    ],
    "sg:phone":"+1 970 224 5730",
    "sg:postcode":"80525",
    "sg:province":"CO",
    "wof:name":"7-Eleven",
    "wof:placetype":"venue"
},
  "geometry": {"coordinates":[-105.057942,40.565214],"type":"Point"}
}