{
  "type": "Feature",
  "properties": {
    "addr:full":"4012 Sky Ranch Dr Glenwood Springs CO 81601",
    "addr:housenumber":"4012",
    "addr:postcode":"81601",
    "addr:street":"Sky Ranch Dr",
    "iso:country":"US",
    "sg:address":"4012 Sky Ranch Dr",
    "sg:city":"Glenwood Springs",
    "sg:classifiers":[
        {
            "category":"Professional",
            "subcategory":"Business Services",
            "type":"Services"
        }
    ],
    "sg:phone":"+1 970 945 2928",
    "sg:postcode":"81601",
    "sg:province":"CO",
    "sg:tags":[
        "interior",
        "consultant",
        "design",
        "decorator"
    ],
    "wof:name":"Wildflower Design Inc",
    "wof:placetype":"venue"
},
  "geometry": {"coordinates":[-107.312121,39.510897],"type":"Point"}
}