{
  "type": "Feature",
  "properties": {
    "iso:country":"US",
    "sg:address":"3226 E 18th St",
    "sg:city":"Greeley",
    "sg:classifiers":[
        {
            "category":"Farming",
            "subcategory":"Livestock Farm",
            "type":"Manufacturing & Wholesale Goods"
        }
    ],
    "sg:phone":"+1 970 356 6919",
    "sg:postcode":"80631",
    "sg:province":"CO",
    "sg:tags":[
        "equine"
    ],
    "wof:name":"Broken Spoke Ranch",
    "wof:placetype":"venue"
},
  "geometry": {"coordinates":[-104.629007,40.410281],"type":"Point"}
}