{
  "type": "Feature",
  "properties": {
    "iso:country":"US",
    "sg:address":"1250 Orchard Rd",
    "sg:city":"Golden",
    "sg:classifiers":[
        {
            "category":"Personal",
            "type":"Services"
        }
    ],
    "sg:phone":"+1 303 427 3348",
    "sg:postcode":"80401",
    "sg:province":"CO",
    "sg:tags":[
        "credit",
        "debt",
        "counseling"
    ],
    "wof:name":"Premier Business Solutions",
    "wof:placetype":"venue"
},
  "geometry": {"coordinates":[-105.15109,39.737849],"type":"Point"}
}