{
  "type": "Feature",
  "properties": {
    "addr:full":"2236 Suffolk St Fort Collins CO 80526",
    "addr:housenumber":"2236",
    "addr:postcode":"80526",
    "addr:street":"Suffolk St",
    "iso:country":"US",
    "sg:address":"2236 Suffolk St",
    "sg:city":"Fort Collins",
    "sg:classifiers":[
        {
            "category":"Banks & Credit Unions",
            "subcategory":"Bank",
            "type":"Services"
        }
    ],
    "sg:phone":"+1 970 472 6066",
    "sg:postcode":"80526",
    "sg:province":"CO",
    "sg:tags":[
        "broker",
        "mortgage"
    ],
    "wof:name":"Alpine Financial Group Inc",
    "wof:placetype":"venue"
},
  "geometry": {"coordinates":[-105.119516,40.563852],"type":"Point"}
}