{
  "type": "Feature",
  "properties": {
    "addr:full":"745 Meadows Rd Aspen CO 81611",
    "addr:housenumber":"745",
    "addr:postcode":"81611",
    "addr:street":"Meadows Rd",
    "iso:country":"US",
    "sg:address":"745 Meadows Rd",
    "sg:city":"Aspen",
    "sg:classifiers":[
        {
            "category":"Recreation",
            "type":"Entertainment"
        }
    ],
    "sg:phone":"+1 970 925 6782",
    "sg:postcode":"81611",
    "sg:province":"CO",
    "sg:tags":[
        "organization",
        "skiing"
    ],
    "wof:name":"Velocity Peak Inc",
    "wof:placetype":"venue"
},
  "geometry": {"coordinates":[-106.82972700000001,39.196968],"type":"Point"}
}