{
  "type": "Feature",
  "properties": {
    "iso:country":"US",
    "sg:address":"2005 10th St",
    "sg:city":"Boulder",
    "sg:classifiers":[
        {
            "category":"Wholesale",
            "subcategory":"Machinery & Supplies",
            "type":"Manufacturing & Wholesale Goods"
        },
        {
            "category":"Wholesale",
            "subcategory":"Electrical",
            "type":"Manufacturing & Wholesale Goods"
        }
    ],
    "sg:phone":"+1 303 449 8000",
    "sg:postcode":"80302",
    "sg:province":"CO",
    "sg:tags":[
        "control",
        "instrument",
        "meter",
        "equipment"
    ],
    "sg:website":"www.metrontechnology.com",
    "wof:name":"Metron Technology Inc",
    "wof:placetype":"venue"
},
  "geometry": {"coordinates":[-105.28301500000001,40.01829],"type":"Point"}
}