{
  "type": "Feature",
  "properties": {
    "addr:full":"6340 W Summit Dr Littleton CO 80123",
    "addr:housenumber":"6340",
    "addr:postcode":"80123",
    "addr:street":"W Summit Dr",
    "iso:country":"US",
    "sg:address":"6340 W Summit Dr",
    "sg:city":"Littleton",
    "sg:classifiers":[
        {
            "category":"Building & Trades",
            "subcategory":"Plumbing",
            "type":"Services"
        }
    ],
    "sg:phone":"+1 303 795 6066",
    "sg:postcode":"80123",
    "sg:province":"CO",
    "sg:tags":[
        "plumbing",
        "contractor"
    ],
    "wof:name":"Water Master Inc",
    "wof:placetype":"venue"
},
  "geometry": {"coordinates":[-105.067669,39.597002],"type":"Point"}
}