{
  "type": "Feature",
  "properties": {
    "iso:country":"US",
    "sg:address":"1565 Nokomis Dr",
    "sg:city":"Colorado Springs",
    "sg:classifiers":[
        {
            "category":"Wholesale",
            "subcategory":"Computers",
            "type":"Manufacturing & Wholesale Goods"
        }
    ],
    "sg:phone":"+1 719 380 9170",
    "sg:postcode":"80915",
    "sg:province":"CO",
    "sg:tags":[
        "manufacture",
        "retail",
        "software"
    ],
    "wof:name":"Practical Solutions",
    "wof:placetype":"venue"
},
  "geometry": {"coordinates":[-104.706777,38.85474],"type":"Point"}
}