{
  "type": "Feature",
  "properties": {
    "addr:full":"1335 Cinnamon St Longmont CO 80501",
    "addr:housenumber":"1335",
    "addr:postcode":"80501",
    "addr:street":"Cinnamon St",
    "iso:country":"US",
    "sg:address":"1335 Cinnamon St",
    "sg:city":"Longmont",
    "sg:classifiers":[
        {
            "category":"Social Services",
            "subcategory":"Adult Care",
            "type":"Services"
        }
    ],
    "sg:phone":"+1 303 772 2882",
    "sg:postcode":"80501",
    "sg:province":"CO",
    "sg:tags":[
        "home",
        "residential"
    ],
    "wof:name":"Cinnamon Park Assisted Living",
    "wof:placetype":"venue"
},
  "geometry": {"coordinates":[-105.108705,40.181797],"type":"Point"}
}