{
  "type": "Feature",
  "properties": {
    "iso:country":"US",
    "sg:address":"850 E Harvard Avenue Suite 405",
    "sg:city":"Denver",
    "sg:classifiers":[
        {
            "category":"Health Services",
            "subcategory":"Doctor",
            "type":"Services"
        }
    ],
    "sg:phone":"+1 303 722 2724",
    "sg:postcode":"80210",
    "sg:province":"CO",
    "sg:tags":[
        "medicine",
        "internal"
    ],
    "wof:name":"Palmquist David MD",
    "wof:placetype":"venue"
},
  "geometry": {"coordinates":[-104.978077,39.671272],"type":"Point"}
}