{
  "type": "Feature",
  "properties": {
    "addr:full":"909 E 62nd Ave Denver CO 80216",
    "addr:housenumber":"909",
    "addr:postcode":"80216",
    "addr:street":"E 62Nd Ave",
    "iso:country":"US",
    "sg:address":"909 E 62nd Ave",
    "sg:city":"Denver",
    "sg:classifiers":[
        {
            "category":"Building & Trades",
            "subcategory":"Locksmith",
            "type":"Services"
        }
    ],
    "sg:phone":"+1 866 823 2580",
    "sg:postcode":"80216",
    "sg:province":"CO",
    "sg:tags":[
        "key"
    ],
    "wof:name":"24 7 Available Locksmith",
    "wof:placetype":"venue"
},
  "geometry": {"coordinates":[-104.97610299999999,39.809287],"type":"Point"}
}