{
  "type": "Feature",
  "properties": {
    "iso:country":"US",
    "sg:address":"909 E 62nd Ave",
    "sg:city":"Denver",
    "sg:classifiers":[
        {
            "category":"Building & Trades",
            "subcategory":"Locksmith",
            "type":"Services"
        }
    ],
    "sg:phone":"+1 866 823 2580",
    "sg:postcode":"80216",
    "sg:province":"CO",
    "sg:tags":[
        "key"
    ],
    "wof:name":"24 7 Available Locksmith",
    "wof:placetype":"venue"
},
  "geometry": {"coordinates":[-104.976103,39.809287],"type":"Point"}
}