{
  "type": "Feature",
  "properties": {
    "iso:country":"US",
    "sg:address":"4283 Ulysses Way",
    "sg:city":"Golden",
    "sg:classifiers":[
        {
            "category":"Wholesale",
            "subcategory":"Durable Goods & Equipment",
            "type":"Manufacturing & Wholesale Goods"
        },
        {
            "category":"Manufacturing",
            "subcategory":"Tools & Machinery",
            "type":"Manufacturing & Wholesale Goods"
        }
    ],
    "sg:phone":"+1 303 277 0731",
    "sg:postcode":"80403",
    "sg:province":"CO",
    "sg:tags":[
        "mfg",
        "electrical",
        "representative",
        "manufacturer"
    ],
    "wof:name":"Hi Tech Sales Inc",
    "wof:placetype":"venue"
},
  "geometry": {"coordinates":[-105.19489299999999,39.773763],"type":"Point"}
}