{
  "type": "Feature",
  "properties": {
    "iso:country":"US",
    "sg:address":"509 Fall River Ln",
    "sg:city":"Estes Park",
    "sg:classifiers":[
        {
            "category":"Freight",
            "type":"Transportation"
        }
    ],
    "sg:phone":"+1 970 586 5549",
    "sg:postcode":"80517",
    "sg:province":"CO",
    "sg:tags":[
        "general"
    ],
    "wof:name":"Estes Valley Self Storage",
    "wof:placetype":"venue"
},
  "geometry": {"coordinates":[-105.541572,40.381584],"type":"Point"}
}