{
  "type": "Feature",
  "properties": {
    "addr:full":"1778 Gilpin St Denver CO 80218",
    "addr:housenumber":"1778",
    "addr:postcode":"80218",
    "addr:street":"Gilpin St",
    "iso:country":"US",
    "sg:address":"1778 Gilpin St",
    "sg:city":"Denver",
    "sg:classifiers":[
        {
            "category":"Professional",
            "subcategory":"Management & Consulting",
            "type":"Services"
        }
    ],
    "sg:phone":"+1 303 780 0509",
    "sg:postcode":"80218",
    "sg:province":"CO",
    "sg:tags":[
        "consultant",
        "business"
    ],
    "wof:name":"Colorado Management & Realty",
    "wof:placetype":"venue"
},
  "geometry": {"coordinates":[-104.96713800000001,39.743557],"type":"Point"}
}