{
  "type": "Feature",
  "properties": {
    "addr:full":"29740 Gay Ln Evergreen CO 80439",
    "addr:housenumber":"29740",
    "addr:postcode":"80439",
    "addr:street":"Gay Ln",
    "iso:country":"US",
    "sg:address":"29740 Gay Ln",
    "sg:city":"Evergreen",
    "sg:classifiers":[
        {
            "category":"Shopping",
            "subcategory":"Pharmacy",
            "type":"Retail Goods"
        }
    ],
    "sg:phone":"+1 303 670 1267",
    "sg:postcode":"80439",
    "sg:province":"CO",
    "sg:tags":[
        "aid",
        "first",
        "supply"
    ],
    "wof:name":"First Aid 2000",
    "wof:placetype":"venue"
},
  "geometry": {"coordinates":[-105.339822,39.618797],"type":"Point"}
}