{
  "type": "Feature",
  "properties": {
    "iso:country":"US",
    "sg:address":"6229 Stuart St",
    "sg:city":"Arvada",
    "sg:classifiers":[
        {
            "category":"Shopping",
            "subcategory":"Music",
            "type":"Retail Goods"
        }
    ],
    "sg:phone":"+1 303 426 0864",
    "sg:postcode":"80003",
    "sg:province":"CO",
    "wof:name":"El Toro Palomo",
    "wof:placetype":"venue"
},
  "geometry": {"coordinates":[-105.04262,39.809909],"type":"Point"}
}