{
  "type": "Feature",
  "properties": {
    "addr:full":"12517 Ln 5 N Mosca CO 81146",
    "addr:housenumber":"12517;5",
    "addr:postcode":"81146",
    "addr:street":"Ln;N Mosca",
    "iso:country":"US",
    "sg:address":"12517 Ln 5 N",
    "sg:city":"Mosca",
    "sg:classifiers":[
        {
            "category":"Freight",
            "type":"Transportation"
        }
    ],
    "sg:phone":"+1 719 378 2207",
    "sg:postcode":"81146",
    "sg:province":"CO",
    "sg:tags":[
        "operator",
        "trucking"
    ],
    "wof:name":"Bar Z Farms",
    "wof:placetype":"venue"
},
  "geometry": {"coordinates":[-105.800788,37.648641],"type":"Point"}
}