{
  "type": "Feature",
  "properties": {
    "addr:full":"28153 War Admiral Trl Evergreen CO 80439",
    "addr:housenumber":"28153",
    "addr:postcode":"80439",
    "addr:street":"War Admiral Trl",
    "iso:country":"US",
    "sg:address":"28153 War Admiral Trl",
    "sg:city":"Evergreen",
    "sg:classifiers":[
        {
            "category":"Manufacturing",
            "subcategory":"Printing",
            "type":"Manufacturing & Wholesale Goods"
        }
    ],
    "sg:phone":"+1 303 679 1361",
    "sg:postcode":"80439",
    "sg:province":"CO",
    "sg:tags":[
        "multimedia"
    ],
    "wof:name":"Media Culture Identity",
    "wof:placetype":"venue"
},
  "geometry": {"coordinates":[-105.317072,39.577368],"type":"Point"}
}