{
  "type": "Feature",
  "properties": {
    "addr:full":"5491 Lantana Dr Colorado Springs CO 80915",
    "addr:housenumber":"5491",
    "addr:postcode":"80915",
    "addr:street":"Lantana Dr",
    "iso:country":"US",
    "sg:address":"5491 Lantana Dr",
    "sg:city":"Colorado Springs",
    "sg:classifiers":[
        {
            "category":"Shopping",
            "subcategory":"Hobbies, Toys, & Games",
            "type":"Retail Goods"
        }
    ],
    "sg:phone":"+1 719 596 5876",
    "sg:postcode":"80915",
    "sg:province":"CO",
    "wof:name":"Alan Kraft",
    "wof:placetype":"venue"
},
  "geometry": {"coordinates":[-104.724751,38.868952],"type":"Point"}
}