{
  "type": "Feature",
  "properties": {
    "iso:country":"US",
    "sg:address":"4848 Chambers Rd",
    "sg:city":"Denver",
    "sg:classifiers":[
        {
            "category":"Personal",
            "subcategory":"Barber",
            "type":"Services"
        }
    ],
    "sg:phone":"+1 303 371 4394",
    "sg:postcode":"80239",
    "sg:province":"CO",
    "wof:name":"Montbello Barbers",
    "wof:placetype":"venue"
},
  "geometry": {"coordinates":[-104.809791,39.779077],"type":"Point"}
}