{
  "type": "Feature",
  "properties": {
    "iso:country":"US",
    "sg:address":"270 N Cherrywood Dr",
    "sg:city":"Lafayette",
    "sg:classifiers":[
        {
            "category":"Health Services",
            "subcategory":"Medical Lab",
            "type":"Services"
        }
    ],
    "sg:phone":"+1 303 661 9002",
    "sg:postcode":"80026",
    "sg:province":"CO",
    "sg:tags":[
        "laboratory"
    ],
    "wof:name":"Cherrywood Dental Arts",
    "wof:placetype":"venue"
},
  "geometry": {"coordinates":[-105.093171,39.975644],"type":"Point"}
}