{
  "type": "Feature",
  "properties": {
    "addr:full":"1816 Heath Pkwy Fort Collins CO 80524",
    "addr:housenumber":"1816",
    "addr:postcode":"80524",
    "addr:street":"Heath Pkwy",
    "iso:country":"US",
    "sg:address":"1816 Heath Pkwy",
    "sg:city":"Fort Collins",
    "sg:classifiers":[
        {
            "category":"Home & Garden",
            "subcategory":"Garden Supply",
            "type":"Retail Goods"
        }
    ],
    "sg:phone":"+1 970 224 4374",
    "sg:postcode":"80524",
    "sg:province":"CO",
    "sg:tags":[
        "lawn",
        "mower"
    ],
    "wof:name":"Dan's Small Engine",
    "wof:placetype":"venue"
},
  "geometry": {"coordinates":[-105.043561,40.584887],"type":"Point"}
}