{
  "type": "Feature",
  "properties": {
    "iso:country":"US",
    "sg:address":"300 S McCaslin Blvd",
    "sg:city":"Louisville",
    "sg:classifiers":[
        {
            "category":"Food & Beverages",
            "subcategory":"Groceries & Convenience Stores",
            "type":"Retail Goods"
        }
    ],
    "sg:phone":"+1 303 666 4368",
    "sg:postcode":"80027",
    "sg:province":"CO",
    "wof:name":"7-Eleven",
    "wof:placetype":"venue"
},
  "geometry": {"coordinates":[-105.163601,39.965059],"type":"Point"}
}