{
  "type": "Feature",
  "properties": {
    "iso:country":"US",
    "sg:address":"1822 Vinewood Ln",
    "sg:city":"Pueblo",
    "sg:classifiers":[
        {
            "category":"Professional",
            "type":"Services"
        }
    ],
    "sg:phone":"+1 719 565 0325",
    "sg:postcode":"81005",
    "sg:province":"CO",
    "wof:name":"PSC Industrial Outsourcing Inc",
    "wof:placetype":"venue"
},
  "geometry": {"coordinates":[-104.66072800000001,38.235992],"type":"Point"}
}