{
  "type": "Feature",
  "properties": {
    "iso:country":"US",
    "sg:address":"4335 Morning Glory Rd",
    "sg:city":"Colorado Springs",
    "sg:classifiers":[
        {
            "category":"Professional",
            "subcategory":"Computer Services",
            "type":"Services"
        }
    ],
    "sg:phone":"+1 719 282 7656",
    "sg:postcode":"80920",
    "sg:province":"CO",
    "sg:tags":[
        "website",
        "design"
    ],
    "wof:name":"DV Web Solutions",
    "wof:placetype":"venue"
},
  "geometry": {"coordinates":[-104.753585,38.966432],"type":"Point"}
}