{
  "type": "Feature",
  "properties": {
    "iso:country":"US",
    "sg:address":"425 S Cherry Street Suite 920",
    "sg:city":"Denver",
    "sg:classifiers":[
        {
            "category":"Professional",
            "subcategory":"Lawyer & Legal Services",
            "type":"Services"
        }
    ],
    "sg:phone":"+1 303 320 8576",
    "sg:postcode":"80246",
    "sg:province":"CO",
    "wof:name":"Soulliere Law Office P C",
    "wof:placetype":"venue"
},
  "geometry": {"coordinates":[-104.933396,39.708653],"type":"Point"}
}