{
  "type": "Feature",
  "properties": {
    "iso:country":"US",
    "sg:address":"46240 Co Rd 3t",
    "sg:city":"Arriba",
    "sg:classifiers":[
        {
            "category":"Farming",
            "subcategory":"Livestock Farm",
            "type":"Manufacturing & Wholesale Goods"
        }
    ],
    "sg:phone":"+1 719 768 3230",
    "sg:postcode":"80804",
    "sg:province":"CO",
    "sg:tags":[
        "beef",
        "feedlot",
        "cattle"
    ],
    "wof:name":"C & D Farms Inc",
    "wof:placetype":"venue"
},
  "geometry": {"coordinates":[-103.208878,39.418558],"type":"Point"}
}