{
  "type": "Feature",
  "properties": {
    "addr:full":"1270 W Cedar Ave Denver CO 80223",
    "addr:housenumber":"1270",
    "addr:postcode":"80223",
    "addr:street":"W Cedar Ave",
    "iso:country":"US",
    "sg:address":"1270 W Cedar Ave",
    "sg:city":"Denver",
    "sg:classifiers":[
        {
            "category":"Professional",
            "type":"Services"
        }
    ],
    "sg:phone":"+1 303 282 1117",
    "sg:postcode":"80223",
    "sg:province":"CO",
    "sg:tags":[
        "establishment"
    ],
    "wof:name":"Monolithic Sculptures Inc",
    "wof:placetype":"venue"
},
  "geometry": {"coordinates":[-105.002729,39.712963],"type":"Point"}
}