{
  "type": "Feature",
  "properties": {
    "iso:country":"US",
    "sg:address":"3010 Ladore St",
    "sg:city":"Grand Junction",
    "sg:classifiers":[
        {
            "category":"Building & Trades",
            "subcategory":"Plumbing",
            "type":"Services"
        }
    ],
    "sg:phone":"+1 970 434 3326",
    "sg:postcode":"81504",
    "sg:province":"CO",
    "sg:tags":[
        "contractor"
    ],
    "wof:name":"Bc Sprinkler Installation",
    "wof:placetype":"venue"
},
  "geometry": {"coordinates":[-108.49643399999999,39.105207],"type":"Point"}
}