{
  "type": "Feature",
  "properties": {
    "addr:full":"5390 E Davies Dr Littleton CO 80122",
    "addr:housenumber":"5390",
    "addr:postcode":"80122",
    "addr:street":"E Davies Dr",
    "iso:country":"US",
    "sg:address":"5390 E Davies Dr",
    "sg:city":"Littleton",
    "sg:classifiers":[
        {
            "category":"Home & Garden",
            "subcategory":"Building Materials",
            "type":"Retail Goods"
        }
    ],
    "sg:phone":"+1 303 773 6984",
    "sg:postcode":"80122",
    "sg:province":"CO",
    "wof:name":"Reliable Auto Glass Inc",
    "wof:placetype":"venue"
},
  "geometry": {"coordinates":[-104.926014,39.58953],"type":"Point"}
}