{
  "type": "Feature",
  "properties": {
    "iso:country":"US",
    "sg:address":"2648 Santa Fe Dr",
    "sg:city":"Pueblo",
    "sg:classifiers":[
        {
            "category":"Shopping",
            "subcategory":"Gifts & Souvenirs",
            "type":"Retail Goods"
        }
    ],
    "sg:phone":"+1 719 545 6159",
    "sg:postcode":"81006",
    "sg:province":"CO",
    "wof:name":"Gift World Flower Shop",
    "wof:placetype":"venue"
},
  "geometry": {"coordinates":[-104.564086,38.24542],"type":"Point"}
}