{
  "type": "Feature",
  "properties": {
    "addr:full":"800 Holland St Denver CO 80215",
    "addr:housenumber":"800",
    "addr:postcode":"80215",
    "addr:street":"Holland St",
    "iso:country":"US",
    "sg:address":"800 Holland St",
    "sg:city":"Denver",
    "sg:classifiers":[
        {
            "category":"Building & Trades",
            "subcategory":"Construction",
            "type":"Services"
        }
    ],
    "sg:phone":"+1 303 374 9842",
    "sg:postcode":"80215",
    "sg:province":"CO",
    "sg:tags":[
        "house"
    ],
    "wof:name":"Xray Construction Inc",
    "wof:placetype":"venue"
},
  "geometry": {"coordinates":[-105.10335600000001,39.730772],"type":"Point"}
}