{
  "type": "Feature",
  "properties": {
    "iso:country":"US",
    "sg:address":"2695 W Eisenhower Blvd",
    "sg:city":"Loveland",
    "sg:classifiers":[
        {
            "category":"Professional",
            "subcategory":"Lawyer & Legal Services",
            "type":"Services"
        }
    ],
    "sg:phone":"+1 970 461 1465",
    "sg:postcode":"80537",
    "sg:province":"CO",
    "sg:tags":[
        "attorney"
    ],
    "wof:name":"Bath & Assoc",
    "wof:placetype":"venue"
},
  "geometry": {"coordinates":[-105.112003,40.407423],"type":"Point"}
}