{
  "type": "Feature",
  "properties": {
    "addr:full":"22421 E Powers Pl Aurora CO 80015",
    "addr:housenumber":"22421",
    "addr:postcode":"80015",
    "addr:street":"E Powers Pl",
    "iso:country":"US",
    "sg:address":"22421 E Powers Pl",
    "sg:city":"Aurora",
    "sg:classifiers":[
        {
            "category":"Building & Trades",
            "subcategory":"Construction",
            "type":"Services"
        }
    ],
    "sg:phone":"+1 303 400 4575",
    "sg:postcode":"80015",
    "sg:province":"CO",
    "sg:tags":[
        "home",
        "builder",
        "operative",
        "family"
    ],
    "wof:name":"Pulte",
    "wof:placetype":"venue"
},
  "geometry": {"coordinates":[-104.72564,39.614109],"type":"Point"}
}