{
  "type": "Feature",
  "properties": {
    "iso:country":"US",
    "sg:address":"549 Flatiron Blvd",
    "sg:city":"Broomfield",
    "sg:classifiers":[
        {
            "category":"Shopping",
            "subcategory":"Bicycles & Sporting Goods",
            "type":"Retail Goods"
        }
    ],
    "sg:phone":"+1 303 410 1800",
    "sg:postcode":"80021",
    "sg:province":"CO",
    "sg:tags":[
        "equipment",
        "golf",
        "supply"
    ],
    "wof:name":"Golf Etc",
    "wof:placetype":"venue"
},
  "geometry": {"coordinates":[-105.130956,39.927569],"type":"Point"}
}