{
  "type": "Feature",
  "properties": {
    "iso:country":"US",
    "sg:address":"4814 Chambers Rd",
    "sg:city":"Denver",
    "sg:classifiers":[
        {
            "category":"Restaurant",
            "type":"Food & Drink"
        }
    ],
    "sg:phone":"+1 720 374 1959",
    "sg:postcode":"80239",
    "sg:province":"CO",
    "sg:tags":[
        "eating"
    ],
    "wof:name":"Uncle Buck's Bbq",
    "wof:placetype":"venue"
},
  "geometry": {"coordinates":[-104.809786,39.779491],"type":"Point"}
}