{
  "type": "Feature",
  "properties": {
    "addr:full":"1193 S Sable Blvd Aurora CO 80012",
    "addr:housenumber":"1193",
    "addr:postcode":"80012",
    "addr:street":"S Sable Blvd",
    "iso:country":"US",
    "sg:address":"1193 S Sable Blvd",
    "sg:city":"Aurora",
    "sg:classifiers":[
        {
            "category":"Manufacturing",
            "subcategory":"Rubber & Plastics",
            "type":"Manufacturing & Wholesale Goods"
        }
    ],
    "sg:phone":"+1 303 755 3729",
    "sg:postcode":"80012",
    "sg:province":"CO",
    "sg:tags":[
        "tube",
        "mfg"
    ],
    "wof:name":"BF Enterpries (bfe)",
    "wof:placetype":"venue"
},
  "geometry": {"coordinates":[-104.819333,39.694911],"type":"Point"}
}