{
  "type": "Feature",
  "properties": {
    "addr:full":"21 Montebello Rd Pueblo CO 81001",
    "addr:housenumber":"21",
    "addr:postcode":"81001",
    "addr:street":"Montebello Rd",
    "iso:country":"US",
    "sg:address":"21 Montebello Rd",
    "sg:city":"Pueblo",
    "sg:classifiers":[
        {
            "category":"Organizations",
            "subcategory":"Community Association",
            "type":"Services"
        }
    ],
    "sg:phone":"+1 719 543 4690",
    "sg:postcode":"81001",
    "sg:province":"CO",
    "wof:name":"Girl Scouts Columbine Council",
    "wof:placetype":"venue"
},
  "geometry": {"coordinates":[-104.599839,38.305688],"type":"Point"}
}