{
  "type": "Feature",
  "properties": {
    "iso:country":"US",
    "sg:address":"21 Montebello Rd",
    "sg:city":"Pueblo",
    "sg:classifiers":[
        {
            "category":"Organizations",
            "subcategory":"Community Association",
            "type":"Services"
        }
    ],
    "sg:phone":"+1 719 543 4690",
    "sg:postcode":"81001",
    "sg:province":"CO",
    "wof:name":"Girl Scouts Columbine Council",
    "wof:placetype":"venue"
},
  "geometry": {"coordinates":[-104.599839,38.305688],"type":"Point"}
}