{
  "type": "Feature",
  "properties": {
    "addr:full":"3303 E 42nd Ave Denver CO 80216",
    "addr:housenumber":"3303",
    "addr:postcode":"80216",
    "addr:street":"E 42Nd Ave",
    "iso:country":"US",
    "sg:address":"3303 E 42nd Ave",
    "sg:city":"Denver",
    "sg:classifiers":[
        {
            "category":"Autos & Motor Vehicles",
            "subcategory":"Automobile Sales",
            "type":"Retail Goods"
        },
        {
            "category":"Retail",
            "subcategory":"Auto Repair",
            "type":"Services"
        }
    ],
    "sg:phone":"+1 303 388 9788",
    "sg:postcode":"80216",
    "sg:province":"CO",
    "sg:tags":[
        "body",
        "used",
        "classic"
    ],
    "sg:website":"www.classicinvest.com",
    "wof:name":"Classic Investments Inc",
    "wof:placetype":"venue"
},
  "geometry": {"coordinates":[-104.94754399999999,39.775193],"type":"Point"}
}