{
  "type": "Feature",
  "properties": {
    "iso:country":"US",
    "sg:address":"5082 E Hampden Ave",
    "sg:city":"Denver",
    "sg:classifiers":[
        {
            "category":"Organizations",
            "subcategory":"Professional Association",
            "type":"Services"
        }
    ],
    "sg:phone":"+1 303 369 6444",
    "sg:postcode":"80222",
    "sg:province":"CO",
    "sg:tags":[
        "business"
    ],
    "wof:name":"Diningwarecom",
    "wof:placetype":"venue"
},
  "geometry": {"coordinates":[-104.929146,39.65297],"type":"Point"}
}