{
  "type": "Feature",
  "properties": {
    "iso:country":"US",
    "sg:address":"1225 17th Street Suite 2300",
    "sg:city":"Denver",
    "sg:classifiers":[
        {
            "category":"Professional",
            "subcategory":"Lawyer & Legal Services",
            "type":"Services"
        }
    ],
    "sg:phone":"+1 303 299 7301",
    "sg:postcode":"80202",
    "sg:province":"CO",
    "wof:name":"Thomasch Roger P Atty",
    "wof:placetype":"venue"
},
  "geometry": {"coordinates":[-104.995584,39.749657],"type":"Point"}
}