{
  "type": "Feature",
  "properties": {
    "iso:country":"US",
    "sg:address":"2401 Ginny Way",
    "sg:city":"Lafayette",
    "sg:classifiers":[
        {
            "category":"Restaurant",
            "type":"Food & Drink"
        }
    ],
    "sg:phone":"+1 303 666 8847",
    "sg:postcode":"80026",
    "sg:province":"CO",
    "sg:tags":[
        "eating"
    ],
    "wof:name":"Colorado Subs Inc",
    "wof:placetype":"venue"
},
  "geometry": {"coordinates":[-105.122136,40.019457],"type":"Point"}
}