{
  "type": "Feature",
  "properties": {
    "addr:full":"5370 Magnolia Street Commerce City CO 80022",
    "addr:housenumber":"5370",
    "addr:postcode":"80022",
    "addr:street":"Magnolia Street",
    "iso:country":"US",
    "sg:address":"5370 Magnolia Street",
    "sg:city":"Commerce City",
    "sg:classifiers":[
        {
            "category":"Building & Trades",
            "subcategory":"Pest Control",
            "type":"Services"
        }
    ],
    "sg:phone":"+1 303 288 8821",
    "sg:postcode":"80022",
    "sg:province":"CO",
    "wof:name":"Acme Tree Service",
    "wof:placetype":"venue"
},
  "geometry": {"coordinates":[-104.912147,39.793798],"type":"Point"}
}