{
  "type": "Feature",
  "properties": {
    "addr:full":"4667 Decatur St Denver CO 80211",
    "addr:housenumber":"4667",
    "addr:postcode":"80211",
    "addr:street":"Decatur St",
    "iso:country":"US",
    "sg:address":"4667 Decatur St",
    "sg:city":"Denver",
    "sg:classifiers":[
        {
            "category":"Restaurant",
            "type":"Food & Drink"
        }
    ],
    "sg:phone":"+1 303 455 5779",
    "sg:postcode":"80211",
    "sg:province":"CO",
    "sg:tags":[
        "eating"
    ],
    "wof:name":"Los Potreros Colorado Cafe",
    "wof:placetype":"venue"
},
  "geometry": {"coordinates":[-105.021744,39.780803],"type":"Point"}
}