{
  "type": "Feature",
  "properties": {
    "iso:country":"US",
    "sg:address":"5187 W 64th Avenue",
    "sg:city":"Arvada",
    "sg:classifiers":[
        {
            "category":"Shopping",
            "subcategory":"Department Store",
            "type":"Retail Goods"
        }
    ],
    "sg:phone":"+1 303 426 7876",
    "sg:postcode":"80003",
    "sg:province":"CO",
    "wof:name":"Family Dollar Store",
    "wof:placetype":"venue"
},
  "geometry": {"coordinates":[-105.05240999999999,39.812681],"type":"Point"}
}