{
  "type": "Feature",
  "properties": {
    "addr:full":"18782 E Hamilton Dr Aurora CO 80013",
    "addr:housenumber":"18782",
    "addr:postcode":"80013",
    "addr:street":"E Hamilton Dr",
    "iso:country":"US",
    "sg:address":"18782 E Hamilton Dr",
    "sg:city":"Aurora",
    "sg:classifiers":[
        {
            "category":"Freight",
            "type":"Transportation"
        }
    ],
    "sg:phone":"+1 720 886 0565",
    "sg:postcode":"80013",
    "sg:province":"CO",
    "sg:tags":[
        "operator",
        "local",
        "trucking"
    ],
    "wof:name":"Anmol Trucking LLC",
    "wof:placetype":"venue"
},
  "geometry": {"coordinates":[-104.76987200000001,39.655593],"type":"Point"}
}