{
  "type": "Feature",
  "properties": {
    "addr:full":"201 Centennial Dr Glenwood Springs CO 81601",
    "addr:housenumber":"201",
    "addr:postcode":"81601",
    "addr:street":"Centennial Dr",
    "iso:country":"US",
    "sg:address":"201 Centennial Dr",
    "sg:city":"Glenwood Springs",
    "sg:classifiers":[
        {
            "category":"Banks & Credit Unions",
            "subcategory":"Investment Brokerage",
            "type":"Services"
        }
    ],
    "sg:phone":"+1 970 945 8686",
    "sg:postcode":"81601",
    "sg:province":"CO",
    "sg:tags":[
        "commodity",
        "contract"
    ],
    "wof:name":"Cqg Inc",
    "wof:placetype":"venue"
},
  "geometry": {"coordinates":[-107.33608099999999,39.554266],"type":"Point"}
}