{
  "type": "Feature",
  "properties": {
    "addr:full":"1254 Sherman Dr Longmont CO 80501",
    "addr:housenumber":"1254",
    "addr:postcode":"80501",
    "addr:street":"Sherman Dr",
    "iso:country":"US",
    "sg:address":"1254 Sherman Dr",
    "sg:city":"Longmont",
    "sg:classifiers":[
        {
            "category":"Professional",
            "type":"Services"
        }
    ],
    "sg:phone":"+1 303 485 3201",
    "sg:postcode":"80501",
    "sg:province":"CO",
    "sg:tags":[
        "establishment"
    ],
    "wof:name":"Mc Stain Enterprises",
    "wof:placetype":"venue"
},
  "geometry": {"coordinates":[-105.11499000000001,40.153327],"type":"Point"}
}