{
  "type": "Feature",
  "properties": {
    "iso:country":"US",
    "sg:address":"3562 22nd St",
    "sg:city":"Boulder",
    "sg:classifiers":[
        {
            "category":"Building & Trades",
            "subcategory":"Construction",
            "type":"Services"
        }
    ],
    "sg:phone":"+1 303 544 0800",
    "sg:postcode":"80304",
    "sg:province":"CO",
    "sg:tags":[
        "house"
    ],
    "wof:name":"Left Hand Foundation",
    "wof:placetype":"venue"
},
  "geometry": {"coordinates":[-105.2684,40.037407],"type":"Point"}
}