{
  "type": "Feature",
  "properties": {
    "iso:country":"US",
    "sg:address":"906 Lincoln Ave",
    "sg:city":"Steamboat Spgs",
    "sg:classifiers":[
        {
            "category":"Shopping",
            "type":"Retail Goods"
        }
    ],
    "sg:phone":"+1 970 871 6882",
    "sg:postcode":"80487",
    "sg:province":"CO",
    "sg:tags":[
        "art",
        "gallery",
        "dealer"
    ],
    "wof:name":"Allure Galleries",
    "wof:placetype":"venue"
},
  "geometry": {"coordinates":[-106.836624,40.487248],"type":"Point"}
}