{
  "type": "Feature",
  "properties": {
    "addr:full":"1615 Coalton Rd Superior CO 80027",
    "addr:housenumber":"1615",
    "addr:postcode":"80027",
    "addr:street":"Coalton Rd",
    "iso:country":"US",
    "sg:address":"1615 Coalton Rd",
    "sg:city":"Superior",
    "sg:classifiers":[
        {
            "category":"Retail",
            "subcategory":"Laundry & Dry Cleaning",
            "type":"Services"
        }
    ],
    "sg:phone":"+1 303 499 2776",
    "sg:postcode":"80027",
    "sg:province":"CO",
    "sg:tags":[
        "cleaners"
    ],
    "wof:name":"John's Cleaners",
    "wof:placetype":"venue"
},
  "geometry": {"coordinates":[-105.138785,39.929009],"type":"Point"}
}