{
  "type": "Feature",
  "properties": {
    "addr:full":"85 Mapel Ln Durango CO 81301",
    "addr:housenumber":"85",
    "addr:postcode":"co 81301",
    "addr:street":"Mapel Ln",
    "iso:country":"US",
    "sg:address":"85 Mapel Ln",
    "sg:city":"Durango",
    "sg:classifiers":[
        {
            "category":"Professional",
            "subcategory":"Management & Consulting",
            "type":"Services"
        }
    ],
    "sg:phone":"+1 970 259 6817",
    "sg:postcode":"81301",
    "sg:province":"CO",
    "sg:tags":[
        "consultant",
        "business"
    ],
    "wof:name":"Riess Research & Planning",
    "wof:placetype":"venue"
},
  "geometry": {"coordinates":[-107.775255,37.315459],"type":"Point"}
}