{
  "type": "Feature",
  "properties": {
    "addr:full":"1250 W 124th Ave Denver CO 80234",
    "addr:housenumber":"1250",
    "addr:postcode":"80234",
    "addr:street":"W 124Th Ave",
    "iso:country":"US",
    "sg:address":"1250 W 124th Ave",
    "sg:city":"Denver",
    "sg:classifiers":[
        {
            "category":"Shopping",
            "subcategory":"Discount & Variety Stores",
            "type":"Retail Goods"
        }
    ],
    "sg:phone":"+1 303 280 2500",
    "sg:postcode":"80234",
    "sg:province":"CO",
    "sg:tags":[
        "merchandise",
        "general"
    ],
    "wof:name":"Key Products Inc",
    "wof:placetype":"venue"
},
  "geometry": {"coordinates":[-104.996827,39.922025],"type":"Point"}
}