{
  "type": "Feature",
  "properties": {
    "iso:country":"US",
    "sg:address":"10771 Co Rd 26",
    "sg:city":"Cortez",
    "sg:classifiers":[
        {
            "category":"Professional",
            "subcategory":"Computer Services",
            "type":"Services"
        }
    ],
    "sg:phone":"+1 970 565 1156",
    "sg:postcode":"81321",
    "sg:province":"CO",
    "sg:tags":[
        "home",
        "consulting",
        "page",
        "dev",
        "internet"
    ],
    "wof:name":"Extreme Web Solutions LLC",
    "wof:placetype":"venue"
},
  "geometry": {"coordinates":[-108.572762,37.370201],"type":"Point"}
}