{
  "type": "Feature",
  "properties": {
    "iso:country":"US",
    "sg:address":"235 N Main St",
    "sg:city":"Mancos",
    "sg:classifiers":[
        {
            "category":"Shopping",
            "type":"Retail Goods"
        }
    ],
    "sg:phone":"+1 970 533 7005",
    "sg:postcode":"81328",
    "sg:province":"CO",
    "sg:tags":[
        "wood",
        "carving"
    ],
    "wof:name":"Wolff Carvers",
    "wof:placetype":"venue"
},
  "geometry": {"coordinates":[-108.289081,37.346797],"type":"Point"}
}