{
  "type": "Feature",
  "properties": {
    "iso:country":"US",
    "sg:address":"14363 Dakota Rd",
    "sg:city":"Sterling",
    "sg:classifiers":[
        {
            "category":"Insurance",
            "subcategory":"Insurance Agent",
            "type":"Services"
        }
    ],
    "sg:phone":"+1 970 521 9198",
    "sg:postcode":"80751",
    "sg:province":"CO",
    "wof:name":"AFLAC",
    "wof:placetype":"venue"
},
  "geometry": {"coordinates":[-103.239441,40.645827],"type":"Point"}
}