{
  "type": "Feature",
  "properties": {
    "addr:full":"2810 Welton St Denver CO 80205",
    "addr:housenumber":"2810",
    "addr:postcode":"80205",
    "addr:street":"Welton St",
    "iso:country":"US",
    "sg:address":"2810 Welton St",
    "sg:city":"Denver",
    "sg:classifiers":[
        {
            "category":"Manufacturing",
            "subcategory":"Tools & Machinery",
            "type":"Manufacturing & Wholesale Goods"
        }
    ],
    "sg:phone":"+1 303 293 0045",
    "sg:postcode":"80205",
    "sg:province":"CO",
    "sg:tags":[
        "grill",
        "mfg",
        "barbecue"
    ],
    "wof:name":"Joe L Jordan",
    "wof:placetype":"venue"
},
  "geometry": {"coordinates":[-104.975686,39.75652],"type":"Point"}
}