{
  "type": "Feature",
  "properties": {
    "iso:country":"US",
    "sg:address":"3824 W Princeton Cir",
    "sg:city":"Denver",
    "sg:classifiers":[
        {
            "category":"Government",
            "subcategory":"Office",
            "type":"Public Place"
        }
    ],
    "sg:phone":"+1 303 866 7450",
    "sg:postcode":"80236",
    "sg:province":"CO",
    "sg:tags":[
        "state",
        "resource"
    ],
    "sg:website":"www.colorado.gov",
    "wof:name":"Developmental Disabilities",
    "wof:placetype":"venue"
},
  "geometry": {"coordinates":[-105.037935,39.642276],"type":"Point"}
}