{
  "type": "Feature",
  "properties": {
    "addr:full":"2645 S Clarkson St Denver CO 80210",
    "addr:housenumber":"2645",
    "addr:postcode":"80210",
    "addr:street":"S Clarkson St",
    "iso:country":"US",
    "sg:address":"2645 S Clarkson St",
    "sg:city":"Denver",
    "sg:classifiers":[
        {
            "category":"Building & Trades",
            "subcategory":"Construction",
            "type":"Services"
        }
    ],
    "sg:phone":"+1 303 777 3900",
    "sg:postcode":"80210",
    "sg:province":"CO",
    "sg:tags":[
        "general",
        "contractor"
    ],
    "wof:name":"TAY Construction Svc",
    "wof:placetype":"venue"
},
  "geometry": {"coordinates":[-104.978611,39.668344],"type":"Point"}
}