{
  "type": "Feature",
  "properties": {
    "iso:country":"US",
    "sg:address":"2436 Garrison St",
    "sg:city":"Lakewood",
    "sg:classifiers":[
        {
            "category":"Professional",
            "subcategory":"Art Services",
            "type":"Services"
        }
    ],
    "sg:phone":"+1 303 274 2294",
    "sg:postcode":"80215",
    "sg:province":"CO",
    "sg:tags":[
        "graphic",
        "designer"
    ],
    "wof:name":"Anderson Creative",
    "wof:placetype":"venue"
},
  "geometry": {"coordinates":[-105.10005200000001,39.747474],"type":"Point"}
}