{
  "type": "Feature",
  "properties": {
    "addr:full":"39640 Co Rd J Yuma CO 80759",
    "addr:housenumber":"39640",
    "addr:postcode":"80759",
    "addr:street":"Co Rd J",
    "iso:country":"US",
    "sg:address":"39640 Co Rd J",
    "sg:city":"Yuma",
    "sg:phone":"+1 970 848 2504",
    "sg:postcode":"80759",
    "sg:province":"CO",
    "sg:tags":[
        "farm",
        "corn",
        "wheat",
        "livestock",
        "general"
    ],
    "wof:name":"Stephen Monk",
    "wof:placetype":"venue"
},
  "geometry": {"coordinates":[-102.661703,40.140524],"type":"Point"}
}