{
  "type": "Feature",
  "properties": {
    "iso:country":"US",
    "sg:address":"1223 N Franklin St",
    "sg:city":"Colorado Springs",
    "sg:classifiers":[
        {
            "category":"Building & Trades",
            "subcategory":"Cleaning & Sanitation",
            "type":"Services"
        }
    ],
    "sg:phone":"+1 719 632 8689",
    "sg:postcode":"80903",
    "sg:province":"CO",
    "sg:tags":[
        "maintenance"
    ],
    "wof:name":"Cricket Cleaning",
    "wof:placetype":"venue"
},
  "geometry": {"coordinates":[-104.81111300000001,38.85131],"type":"Point"}
}