{
  "type": "Feature",
  "properties": {
    "iso:country":"US",
    "sg:address":"729 W Fortino Blvd",
    "sg:city":"Pueblo",
    "sg:classifiers":[
        {
            "category":"Wholesale",
            "subcategory":"Electrical",
            "type":"Manufacturing & Wholesale Goods"
        }
    ],
    "sg:phone":"+1 719 542 1924",
    "sg:postcode":"81008",
    "sg:province":"CO",
    "sg:tags":[
        "equipment",
        "parts",
        "electronic",
        "supply"
    ],
    "wof:name":"Pueblo Wintronic Co",
    "wof:placetype":"venue"
},
  "geometry": {"coordinates":[-104.617617,38.311905],"type":"Point"}
}