{
  "type": "Feature",
  "properties": {
    "iso:country":"US",
    "sg:address":"3773 Cherry Creek North Dr",
    "sg:city":"Denver",
    "sg:classifiers":[
        {
            "category":"Professional",
            "subcategory":"Accounting & Tax Preparation",
            "type":"Services"
        }
    ],
    "sg:phone":"+1 303 331 6460",
    "sg:postcode":"80209",
    "sg:province":"CO",
    "sg:tags":[
        "accountant"
    ],
    "wof:name":"John M Hanson Jr CPA",
    "wof:placetype":"venue"
},
  "geometry": {"coordinates":[-104.942498,39.707777],"type":"Point"}
}