{
  "type": "Feature",
  "properties": {
    "iso:country":"US",
    "sg:address":"41672 US Hwy 6",
    "sg:city":"Holyoke",
    "sg:classifiers":[
        {
            "category":"Farming",
            "subcategory":"Farm",
            "type":"Manufacturing & Wholesale Goods"
        }
    ],
    "sg:phone":"+1 970 854 3242",
    "sg:postcode":"80734",
    "sg:province":"CO",
    "wof:name":"Tac Farms",
    "wof:placetype":"venue"
},
  "geometry": {"coordinates":[-102.27249399999999,40.585622],"type":"Point"}
}