{
  "type": "Feature",
  "properties": {
    "iso:country":"US",
    "sg:address":"797 Simms St",
    "sg:city":"Golden",
    "sg:classifiers":[
        {
            "category":"Food & Beverages",
            "subcategory":"Groceries & Convenience Stores",
            "type":"Retail Goods"
        }
    ],
    "sg:phone":"+1 303 233 5925",
    "sg:postcode":"80401",
    "sg:province":"CO",
    "sg:tags":[
        "station",
        "gas"
    ],
    "wof:name":"Simms Bp",
    "wof:placetype":"venue"
},
  "geometry": {"coordinates":[-105.12872299999999,39.726903],"type":"Point"}
}