{
  "type": "Feature",
  "properties": {
    "iso:country":"US",
    "sg:address":"120 Zerex St",
    "sg:city":"Fraser",
    "sg:classifiers":[
        {
            "category":"Government",
            "subcategory":"Office",
            "type":"Public Place"
        }
    ],
    "sg:phone":"+1 970 726 8312",
    "sg:postcode":"80442",
    "sg:province":"CO",
    "sg:tags":[
        "village"
    ],
    "wof:name":"Fraser Visitor Ctr",
    "wof:placetype":"venue"
},
  "geometry": {"coordinates":[-105.814453,39.945525],"type":"Point"}
}