{
  "type": "Feature",
  "properties": {
    "iso:country":"US",
    "sg:address":"6741 Albion St",
    "sg:city":"Commerce City",
    "sg:classifiers":[
        {
            "category":"Manufacturing",
            "subcategory":"Toys & Sporting Goods",
            "type":"Manufacturing & Wholesale Goods"
        }
    ],
    "sg:phone":"+1 303 286 7927",
    "sg:postcode":"80022",
    "sg:province":"CO",
    "sg:tags":[
        "mfg"
    ],
    "wof:name":"Lure Wrap LLC",
    "wof:placetype":"venue"
},
  "geometry": {"coordinates":[-104.939443,39.817227],"type":"Point"}
}