{
  "type": "Feature",
  "properties": {
    "addr:full":"5050 Wagon Master Dr Colorado Springs CO 80917",
    "addr:housenumber":"5050",
    "addr:postcode":"80917",
    "addr:street":"Wagon Master Dr",
    "iso:country":"US",
    "sg:address":"5050 Wagon Master Dr",
    "sg:city":"Colorado Springs",
    "sg:classifiers":[
        {
            "category":"Building & Trades",
            "subcategory":"Construction",
            "type":"Services"
        }
    ],
    "sg:phone":"+1 719 596 1709",
    "sg:postcode":"80917",
    "sg:province":"CO",
    "sg:tags":[
        "wallpaper",
        "contractor"
    ],
    "wof:name":"Bohlen Wall Covering",
    "wof:placetype":"venue"
},
  "geometry": {"coordinates":[-104.733716,38.888812],"type":"Point"}
}