{
  "type": "Feature",
  "properties": {
    "iso:country":"US",
    "sg:address":"5353 W Dartmouth Ave",
    "sg:city":"Denver",
    "sg:classifiers":[
        {
            "category":"Wholesale",
            "subcategory":"Metals & Minerals",
            "type":"Manufacturing & Wholesale Goods"
        }
    ],
    "sg:phone":"+1 303 423 4280",
    "sg:postcode":"80227",
    "sg:province":"CO",
    "wof:name":"Service Center of Colorado Inc",
    "wof:placetype":"venue"
},
  "geometry": {"coordinates":[-105.054131,39.65622],"type":"Point"}
}