{
  "type": "Feature",
  "properties": {
    "addr:full":"510 Main St Westcliffe CO 81252",
    "addr:housenumber":"510",
    "addr:postcode":"81252",
    "addr:street":"Main St",
    "iso:country":"US",
    "sg:address":"510 Main St",
    "sg:city":"Westcliffe",
    "sg:classifiers":[
        {
            "category":"Professional",
            "type":"Services"
        }
    ],
    "sg:phone":"+1 719 783 3737",
    "sg:postcode":"81252",
    "sg:province":"CO",
    "wof:name":"Sagewood Gallery Co",
    "wof:placetype":"venue"
},
  "geometry": {"coordinates":[-105.446856,38.136261],"type":"Point"}
}