{
  "type": "Feature",
  "properties": {
    "iso:country":"US",
    "sg:address":"666 Patterson Rd",
    "sg:city":"Grand Junction",
    "sg:classifiers":[
        {
            "category":"Building & Trades",
            "subcategory":"Equipment Rental",
            "type":"Services"
        }
    ],
    "sg:phone":"+1 970 245 1604",
    "sg:postcode":"81506",
    "sg:province":"CO",
    "sg:tags":[
        "home",
        "health",
        "rent",
        "care"
    ],
    "wof:name":"Apria Healthcare Inc",
    "wof:placetype":"venue"
},
  "geometry": {"coordinates":[-108.561606,39.091837],"type":"Point"}
}