{
  "type": "Feature",
  "properties": {
    "addr:full":"1579 Madison St Denver CO 80206",
    "addr:housenumber":"1579",
    "addr:postcode":"80206",
    "addr:street":"Madison St",
    "iso:country":"US",
    "sg:address":"1579 Madison St",
    "sg:city":"Denver",
    "sg:classifiers":[
        {
            "category":"Shopping",
            "subcategory":"Florist",
            "type":"Retail Goods"
        }
    ],
    "sg:phone":"+1 303 329 8506",
    "sg:postcode":"80206",
    "sg:province":"CO",
    "wof:name":"Urban Wilds Inc",
    "wof:placetype":"venue"
},
  "geometry": {"coordinates":[-104.946608,39.74052],"type":"Point"}
}