{
  "type": "Feature",
  "properties": {
    "iso:country":"US",
    "sg:address":"4670 Co Rd 740",
    "sg:city":"Crested Butte",
    "sg:classifiers":[
        {
            "category":"Travel",
            "subcategory":"Hotels & Motels",
            "type":"Entertainment"
        }
    ],
    "sg:phone":"+1 970 349 5586",
    "sg:postcode":"81224",
    "sg:province":"CO",
    "sg:tags":[
        "ranch",
        "guest"
    ],
    "wof:name":"Cement Creek Ranch",
    "wof:placetype":"venue"
},
  "geometry": {"coordinates":[-106.841347,38.827765],"type":"Point"}
}