{
  "type": "Feature",
  "properties": {
    "iso:country":"US",
    "sg:address":"6586 Brighton Boulevard",
    "sg:city":"Commerce City",
    "sg:classifiers":[
        {
            "category":"Autos & Motor Vehicles",
            "subcategory":"Fuel & Gas Station",
            "type":"Retail Goods"
        }
    ],
    "sg:phone":"+1 303 428 9242",
    "sg:postcode":"80022",
    "sg:province":"CO",
    "sg:website":"www.denvertowing.com",
    "wof:name":"Joe's Towing & Recovery",
    "wof:placetype":"venue"
},
  "geometry": {"coordinates":[-104.93491899999999,39.815827],"type":"Point"}
}