{
  "type": "Feature",
  "properties": {
    "addr:full":"3996 Ponderosa Dr Evergreen CO 80439",
    "addr:housenumber":"3996",
    "addr:postcode":"80439",
    "addr:street":"Ponderosa Dr",
    "iso:country":"US",
    "sg:address":"3996 Ponderosa Dr",
    "sg:city":"Evergreen",
    "sg:classifiers":[
        {
            "category":"Professional",
            "subcategory":"Accounting & Tax Preparation",
            "type":"Services"
        }
    ],
    "sg:phone":"+1 303 674 9729",
    "sg:postcode":"80439",
    "sg:province":"CO",
    "sg:tags":[
        "accountant"
    ],
    "wof:name":"Accurate Accounting",
    "wof:placetype":"venue"
},
  "geometry": {"coordinates":[-105.334746,39.645631],"type":"Point"}
}