{
  "type": "Feature",
  "properties": {
    "addr:full":"1143 Hemlock Dr Windsor CO 80550",
    "addr:housenumber":"1143",
    "addr:postcode":"80550",
    "addr:street":"Hemlock Dr",
    "iso:country":"US",
    "sg:address":"1143 Hemlock Dr",
    "sg:city":"Windsor",
    "sg:classifiers":[
        {
            "category":"Building & Trades",
            "subcategory":"Construction",
            "type":"Services"
        }
    ],
    "sg:phone":"+1 970 215 1927",
    "sg:postcode":"80550",
    "sg:province":"CO",
    "sg:tags":[
        "roofing",
        "siding",
        "work"
    ],
    "wof:name":"Urethane Systems",
    "wof:placetype":"venue"
},
  "geometry": {"coordinates":[-104.909902,40.469951],"type":"Point"}
}