{
  "type": "Feature",
  "properties": {
    "iso:country":"US",
    "sg:address":"7025 W 116th Ave",
    "sg:city":"Broomfield",
    "sg:classifiers":[
        {
            "category":"Manufacturing",
            "subcategory":"Tools & Machinery",
            "type":"Manufacturing & Wholesale Goods"
        }
    ],
    "sg:phone":"+1 303 469 2700",
    "sg:postcode":"80020",
    "sg:province":"CO",
    "sg:tags":[
        "industrial",
        "she",
        "mfg"
    ],
    "wof:name":"Precision Carts",
    "wof:placetype":"venue"
},
  "geometry": {"coordinates":[-105.07359099999999,39.907645],"type":"Point"}
}