{
  "type": "Feature",
  "properties": {
    "addr:full":"10757 E Virginia Ave Aurora CO 80012",
    "addr:housenumber":"10757",
    "addr:postcode":"80012",
    "addr:street":"E Virginia Ave",
    "iso:country":"US",
    "sg:address":"10757 E Virginia Ave",
    "sg:city":"Aurora",
    "sg:classifiers":[
        {
            "category":"Banks & Credit Unions",
            "subcategory":"Financial Services",
            "type":"Services"
        }
    ],
    "sg:phone":"+1 303 361 6744",
    "sg:postcode":"80012",
    "sg:province":"CO",
    "sg:tags":[
        "investment",
        "closed"
    ],
    "wof:name":"Gold Eagle Investments LLC",
    "wof:placetype":"venue"
},
  "geometry": {"coordinates":[-104.863052,39.707518],"type":"Point"}
}