{
  "type": "Feature",
  "properties": {
    "addr:full":"5865 Marion Dr Denver CO 80216",
    "addr:housenumber":"5865",
    "addr:postcode":"80216",
    "addr:street":"Marion Dr",
    "iso:country":"US",
    "sg:address":"5865 Marion Dr",
    "sg:city":"Denver",
    "sg:classifiers":[
        {
            "category":"Building & Trades",
            "subcategory":"Equipment Rental",
            "type":"Services"
        }
    ],
    "sg:phone":"+1 303 232 3540",
    "sg:postcode":"80216",
    "sg:province":"CO",
    "sg:tags":[
        "sound"
    ],
    "wof:name":"Dowlen Sound Inc",
    "wof:placetype":"venue"
},
  "geometry": {"coordinates":[-104.971749,39.804292],"type":"Point"}
}