{
  "type": "Feature",
  "properties": {
    "iso:country":"US",
    "sg:address":"1425 Edison St",
    "sg:city":"Brush",
    "sg:classifiers":[
        {
            "category":"Manufacturing",
            "subcategory":"Food",
            "type":"Manufacturing & Wholesale Goods"
        }
    ],
    "sg:phone":"+1 970 842 0836",
    "sg:postcode":"80723",
    "sg:province":"CO",
    "sg:tags":[
        "preparation",
        "mfg"
    ],
    "wof:name":"Tortilleria Flores",
    "wof:placetype":"venue"
},
  "geometry": {"coordinates":[-103.63696,40.254975],"type":"Point"}
}