{
  "type": "Feature",
  "properties": {
    "iso:country":"US",
    "sg:address":"6331 Washington St",
    "sg:city":"Denver",
    "sg:classifiers":[
        {
            "category":"Bars & Pubs",
            "type":"Food & Drink"
        }
    ],
    "sg:phone":"+1 303 286 1130",
    "sg:postcode":"80216",
    "sg:province":"CO",
    "sg:tags":[
        "drinking"
    ],
    "wof:name":"Why Not Lounge",
    "wof:placetype":"venue"
},
  "geometry": {"coordinates":[-104.978128,39.810393],"type":"Point"}
}