{
  "type": "Feature",
  "properties": {
    "iso:country":"US",
    "sg:address":"1841 W Evans Ave",
    "sg:city":"Denver",
    "sg:classifiers":[
        {
            "category":"Home & Garden",
            "subcategory":"Carpets & Floor Coverings",
            "type":"Retail Goods"
        }
    ],
    "sg:phone":"+1 303 937 1699",
    "sg:postcode":"80223",
    "sg:province":"CO",
    "sg:tags":[
        "dealer",
        "rug"
    ],
    "wof:name":"Cash & Carry Carpets",
    "wof:placetype":"venue"
},
  "geometry": {"coordinates":[-105.010653,39.678718],"type":"Point"}
}