{
  "type": "Feature",
  "properties": {
    "iso:country":"US",
    "sg:address":"121 E Virginia Ave",
    "sg:city":"Gunnison",
    "sg:classifiers":[
        {
            "category":"Personal",
            "subcategory":"Beauty Salon",
            "type":"Services"
        }
    ],
    "sg:phone":"+1 970 641 1997",
    "sg:postcode":"81230",
    "sg:province":"CO",
    "wof:name":"Grape Vine Hair Design",
    "wof:placetype":"venue"
},
  "geometry": {"coordinates":[-106.92680900000001,38.545151],"type":"Point"}
}