{
  "type": "Feature",
  "properties": {
    "iso:country":"US",
    "sg:address":"4301 E Colfax Ave Rm 314",
    "sg:city":"Denver",
    "sg:classifiers":[
        {
            "category":"Utilities",
            "subcategory":"Telephone",
            "type":"Services"
        }
    ],
    "sg:phone":"+1 303 507 4469",
    "sg:postcode":"80220",
    "sg:province":"CO",
    "sg:tags":[
        "communication"
    ],
    "wof:name":"Qwest Wireless",
    "wof:placetype":"venue"
},
  "geometry": {"coordinates":[-104.937218,39.740211],"type":"Point"}
}