{
  "type": "Feature",
  "properties": {
    "iso:country":"US",
    "sg:address":"2350 S Chambers Rd",
    "sg:city":"Aurora",
    "sg:classifiers":[
        {
            "category":"Restaurant",
            "type":"Food & Drink"
        }
    ],
    "sg:phone":"+1 303 755 5447",
    "sg:postcode":"80014",
    "sg:province":"CO",
    "wof:name":"Korea House Sake Ctr",
    "wof:placetype":"venue"
},
  "geometry": {"coordinates":[-104.80985099999999,39.673542],"type":"Point"}
}