{
  "type": "Feature",
  "properties": {
    "addr:full":"5840 E Evans Ave Denver CO 80222",
    "addr:housenumber":"5840",
    "addr:postcode":"80222",
    "addr:street":"E Evans Ave",
    "iso:country":"US",
    "sg:address":"5840 E Evans Ave",
    "sg:city":"Denver",
    "sg:classifiers":[
        {
            "category":"Professional",
            "subcategory":"Employment Agencies",
            "type":"Services"
        }
    ],
    "sg:phone":"+1 303 300 6976",
    "sg:postcode":"80222",
    "sg:province":"CO",
    "wof:name":"Boomerang Staffing Services",
    "wof:placetype":"venue"
},
  "geometry": {"coordinates":[-104.91999800000001,39.678398],"type":"Point"}
}