{
  "type": "Feature",
  "properties": {
    "addr:full":"2771 W Mansfield Ave Englewood CO 80110",
    "addr:housenumber":"2771",
    "addr:postcode":"80110",
    "addr:street":"W Mansfield Ave",
    "iso:country":"US",
    "sg:address":"2771 W Mansfield Ave",
    "sg:city":"Englewood",
    "sg:classifiers":[
        {
            "category":"Building & Trades",
            "subcategory":"Plumbing",
            "type":"Services"
        }
    ],
    "sg:phone":"+1 303 806 5400",
    "sg:postcode":"80110",
    "sg:province":"CO",
    "sg:tags":[
        "sheet",
        "work",
        "metal",
        "heating",
        "electrical",
        "mechanical",
        "air conditioning"
    ],
    "sg:website":"www.frontiermechanicalinc.com",
    "wof:name":"Frontier Mechanical Inc",
    "wof:placetype":"venue"
},
  "geometry": {"coordinates":[-105.022042,39.645732],"type":"Point"}
}