{
  "type": "Feature",
  "properties": {
    "iso:country":"US",
    "sg:address":"15400 E 14th Pl",
    "sg:city":"Aurora",
    "sg:classifiers":[
        {
            "category":"Organizations",
            "subcategory":"Non-profit Organization",
            "type":"Services"
        }
    ],
    "sg:phone":"+1 303 344 9016",
    "sg:postcode":"80011",
    "sg:province":"CO",
    "sg:tags":[
        "human"
    ],
    "wof:name":"Project Safeguard",
    "wof:placetype":"venue"
},
  "geometry": {"coordinates":[-104.80865799999999,39.738716],"type":"Point"}
}