{
  "type": "Feature",
  "properties": {
    "iso:country":"US",
    "sg:address":"245 S High School Ave",
    "sg:city":"Holyoke",
    "sg:classifiers":[
        {
            "category":"Freight",
            "type":"Transportation"
        }
    ],
    "sg:phone":"+1 970 854 3905",
    "sg:postcode":"80734",
    "sg:province":"CO",
    "sg:tags":[
        "trucking"
    ],
    "wof:name":"T C Transport Inc",
    "wof:placetype":"venue"
},
  "geometry": {"coordinates":[-102.296682,40.584133],"type":"Point"}
}