{
  "type": "Feature",
  "properties": {
    "addr:full":"6175 W 10th St Greeley CO 80634",
    "addr:housenumber":"6175",
    "addr:postcode":"80634",
    "addr:street":"W 10Th St",
    "iso:country":"US",
    "sg:address":"6175 W 10th St",
    "sg:city":"Greeley",
    "sg:classifiers":[
        {
            "category":"Autos & Motor Vehicles",
            "subcategory":"Automobile Sales",
            "type":"Retail Goods"
        }
    ],
    "sg:phone":"+1 970 351 0707",
    "sg:postcode":"80634",
    "sg:province":"CO",
    "sg:tags":[
        "car",
        "dealer"
    ],
    "wof:name":"Advantage Auto Brokers",
    "wof:placetype":"venue"
},
  "geometry": {"coordinates":[-104.77722900000001,40.421388],"type":"Point"}
}