{
  "type": "Feature",
  "properties": {
    "iso:country":"US",
    "sg:address":"109 E C St",
    "sg:city":"Pueblo",
    "sg:classifiers":[
        {
            "category":"Bars & Pubs",
            "type":"Food & Drink"
        }
    ],
    "sg:phone":"+1 719 584 2671",
    "sg:postcode":"81003",
    "sg:province":"CO",
    "wof:name":"Phill's Radiator Svc & Beer",
    "wof:placetype":"venue"
},
  "geometry": {"coordinates":[-104.61444899999999,38.263046],"type":"Point"}
}