{
  "type": "Feature",
  "properties": {
    "addr:full":"3306 S Geneva St Denver CO 80231",
    "addr:housenumber":"3306",
    "addr:postcode":"80231",
    "addr:street":"S Geneva St",
    "iso:country":"US",
    "sg:address":"3306 S Geneva St",
    "sg:city":"Denver",
    "sg:classifiers":[
        {
            "category":"Professional",
            "type":"Services"
        }
    ],
    "sg:phone":"+1 303 691 3441",
    "sg:postcode":"80231",
    "sg:province":"CO",
    "wof:name":"Wintergreen Properti Es",
    "wof:placetype":"venue"
},
  "geometry": {"coordinates":[-104.86870399999999,39.658411],"type":"Point"}
}