{
  "type": "Feature",
  "properties": {
    "iso:country":"US",
    "sg:address":"6657 Colorado Blvd",
    "sg:city":"Commerce City",
    "sg:classifiers":[
        {
            "category":"Wholesale",
            "subcategory":"Construction Materials",
            "type":"Manufacturing & Wholesale Goods"
        }
    ],
    "sg:phone":"+1 303 287 0845",
    "sg:postcode":"80022",
    "sg:province":"CO",
    "sg:tags":[
        "concrete",
        "product"
    ],
    "wof:name":"Northside Supply",
    "wof:placetype":"venue"
},
  "geometry": {"coordinates":[-104.940495,39.813519],"type":"Point"}
}