{
  "type": "Feature",
  "properties": {
    "addr:full":"655 Mariposa St Denver CO 80204",
    "addr:housenumber":"655",
    "addr:postcode":"80204",
    "addr:street":"Mariposa St",
    "iso:country":"US",
    "sg:address":"655 Mariposa St",
    "sg:city":"Denver",
    "sg:classifiers":[
        {
            "category":"Freight",
            "type":"Transportation"
        }
    ],
    "sg:phone":"+1 303 299 3424",
    "sg:postcode":"80204",
    "sg:province":"CO",
    "wof:name":"RTD Light Rail",
    "wof:placetype":"venue"
},
  "geometry": {"coordinates":[-105.00293000000001,39.726467],"type":"Point"}
}