{
  "type": "Feature",
  "properties": {
    "addr:full":"4950 W Co Rd 38E Fort Collins CO 80526",
    "addr:housenumber":"4950;38e",
    "addr:postcode":"80526",
    "addr:street":"W Co Rd",
    "iso:country":"US",
    "sg:address":"4950 W Co Rd 38E",
    "sg:city":"Fort Collins",
    "sg:classifiers":[
        {
            "category":"Building & Trades",
            "subcategory":"Construction",
            "type":"Services"
        }
    ],
    "sg:phone":"+1 970 226 4714",
    "sg:postcode":"80526",
    "sg:province":"CO",
    "sg:tags":[
        "road",
        "contractor"
    ],
    "wof:name":"White Trucking & Construction",
    "wof:placetype":"venue"
},
  "geometry": {"coordinates":[-105.170795,40.521006],"type":"Point"}
}