{
  "type": "Feature",
  "properties": {
    "iso:country":"US",
    "sg:address":"15906 Cala Rojo Dr",
    "sg:city":"Colorado Springs",
    "sg:classifiers":[
        {
            "category":"Building & Trades",
            "subcategory":"Construction",
            "type":"Services"
        }
    ],
    "sg:phone":"+1 719 576 6129",
    "sg:postcode":"80926",
    "sg:province":"CO",
    "sg:tags":[
        "paint",
        "drywall",
        "contractor"
    ],
    "wof:name":"H & S Painting Ltd",
    "wof:placetype":"venue"
},
  "geometry": {"coordinates":[-104.91586700000001,38.599682],"type":"Point"}
}