{
  "type": "Feature",
  "properties": {
    "iso:country":"US",
    "sg:address":"1104 Co Rd 308",
    "sg:city":"Parachute",
    "sg:classifiers":[
        {
            "category":"Building & Trades",
            "subcategory":"Construction",
            "type":"Services"
        }
    ],
    "sg:phone":"+1 970 285 7481",
    "sg:postcode":"81635",
    "sg:province":"CO",
    "sg:tags":[
        "general",
        "contractor"
    ],
    "wof:name":"Tonder Construction",
    "wof:placetype":"venue"
},
  "geometry": {"coordinates":[-108.01604500000001,39.443054],"type":"Point"}
}