{
  "type": "Feature",
  "properties": {
    "addr:full":"7615 S Cook Way Littleton CO 80122",
    "addr:housenumber":"7615",
    "addr:postcode":"80122",
    "addr:street":"S Cook Way",
    "iso:country":"US",
    "sg:address":"7615 S Cook Way",
    "sg:city":"Littleton",
    "sg:classifiers":[
        {
            "category":"Building & Trades",
            "subcategory":"Construction",
            "type":"Services"
        }
    ],
    "sg:phone":"+1 303 773 3644",
    "sg:postcode":"80122",
    "sg:province":"CO",
    "sg:tags":[
        "hanging",
        "contractor"
    ],
    "wof:name":"Historic Decorating",
    "wof:placetype":"venue"
},
  "geometry": {"coordinates":[-104.948734,39.578907],"type":"Point"}
}