{
  "type": "Feature",
  "properties": {
    "iso:country":"US",
    "sg:address":"1412 S Parker Rd",
    "sg:city":"Denver",
    "sg:classifiers":[
        {
            "category":"Retail",
            "subcategory":"Repair Shop",
            "type":"Services"
        }
    ],
    "sg:phone":"+1 303 337 4355",
    "sg:postcode":"80231",
    "sg:province":"CO",
    "sg:tags":[
        "electronics"
    ],
    "sg:website":"www.tvdesija.com/",
    "wof:name":"International TV Sales & Service",
    "wof:placetype":"venue"
},
  "geometry": {"coordinates":[-104.890683,39.690312],"type":"Point"}
}