{
  "type": "Feature",
  "properties": {
    "iso:country":"US",
    "sg:address":"7295 Antelope Ln",
    "sg:city":"Colorado Springs",
    "sg:classifiers":[
        {
            "category":"Shopping",
            "subcategory":"Stationery & Office Supplies",
            "type":"Retail Goods"
        }
    ],
    "sg:phone":"+1 719 260 9163",
    "sg:postcode":"80920",
    "sg:province":"CO",
    "sg:tags":[
        "stationer"
    ],
    "sg:website":"www.simplystickers.com",
    "wof:name":"Simply Stickers",
    "wof:placetype":"venue"
},
  "geometry": {"coordinates":[-104.778373,38.938363],"type":"Point"}
}