{
  "type": "Feature",
  "properties": {
    "addr:full":"805 S Public Rd Lafayette CO 80026",
    "addr:housenumber":"805",
    "addr:postcode":"80026",
    "addr:street":"S Public Rd",
    "iso:country":"US",
    "sg:address":"805 S Public Rd",
    "sg:city":"Lafayette",
    "sg:classifiers":[
        {
            "category":"Retail",
            "subcategory":"Veterinary Services",
            "type":"Services"
        }
    ],
    "sg:phone":"+1 303 665 4230",
    "sg:postcode":"80026",
    "sg:province":"CO",
    "sg:tags":[
        "hospital",
        "veterinarian",
        "animal"
    ],
    "sg:website":"www.vcapets.com",
    "wof:name":"VCA All Pets Animal Hospital",
    "wof:placetype":"venue"
},
  "geometry": {"coordinates":[-105.09056099999999,39.992149],"type":"Point"}
}