{
  "type": "Feature",
  "properties": {
    "addr:full":"15590 W 64th Ave Arvada CO 80007",
    "addr:housenumber":"15590",
    "addr:postcode":"80007",
    "addr:street":"W 64Th Ave",
    "iso:country":"US",
    "sg:address":"15590 W 64th Ave",
    "sg:city":"Arvada",
    "sg:classifiers":[
        {
            "category":"Banks & Credit Unions",
            "subcategory":"Bank",
            "type":"Services"
        },
        {
            "category":"Banks & Credit Unions",
            "subcategory":"Financial Services",
            "type":"Services"
        }
    ],
    "sg:phone":"+1 720 587 6392",
    "sg:postcode":"80007",
    "sg:province":"CO",
    "sg:tags":[
        "saving",
        "loan",
        "commercial"
    ],
    "sg:website":"http://www.key.com",
    "wof:name":"Keybank National Association",
    "wof:placetype":"venue"
},
  "geometry": {"coordinates":[-105.172686,39.812523],"type":"Point"}
}