{
  "type": "Feature",
  "properties": {
    "addr:full":"3613 Galley Rd Colorado Springs CO 80909",
    "addr:housenumber":"3613",
    "addr:postcode":"80909",
    "addr:street":"Galley Rd",
    "iso:country":"US",
    "sg:address":"3613 Galley Rd",
    "sg:city":"Colorado Springs",
    "sg:classifiers":[
        {
            "category":"Restaurant",
            "type":"Food & Drink"
        }
    ],
    "sg:phone":"+1 719 574 7380",
    "sg:postcode":"80909",
    "sg:province":"CO",
    "wof:name":"Mi Rancho Taqueria",
    "wof:placetype":"venue"
},
  "geometry": {"coordinates":[-104.761347,38.847007],"type":"Point"}
}