{
  "type": "Feature",
  "properties": {
    "iso:country":"US",
    "sg:address":"14500 W Colfax Ave",
    "sg:city":"Lakewood",
    "sg:classifiers":[
        {
            "category":"Home & Garden",
            "subcategory":"Home Furnishings",
            "type":"Retail Goods"
        }
    ],
    "sg:phone":"+1 303 590 1490",
    "sg:postcode":"80401",
    "sg:province":"CO",
    "sg:tags":[
        "blanket"
    ],
    "wof:name":"Dori Potpourri & Quilt Outlet",
    "wof:placetype":"venue"
},
  "geometry": {"coordinates":[-105.165448,39.732095],"type":"Point"}
}