{
  "type": "Feature",
  "properties": {
    "addr:full":"623 W Vermijo St Colorado Springs CO 80905",
    "addr:housenumber":"623",
    "addr:postcode":"80905",
    "addr:street":"W Vermijo St",
    "iso:country":"US",
    "sg:address":"623 W Vermijo St",
    "sg:city":"Colorado Springs",
    "sg:classifiers":[
        {
            "category":"Manufacturing",
            "subcategory":"Metals",
            "type":"Manufacturing & Wholesale Goods"
        }
    ],
    "sg:phone":"+1 719 632 4659",
    "sg:postcode":"80905",
    "sg:province":"CO",
    "sg:tags":[
        "fabricator",
        "sheet"
    ],
    "wof:name":"Integrated Metal Systems LLC",
    "wof:placetype":"venue"
},
  "geometry": {"coordinates":[-104.837554,38.830277],"type":"Point"}
}