{
  "type": "Feature",
  "properties": {
    "addr:full":"10037 Allison St Broomfield CO 80021",
    "addr:housenumber":"10037",
    "addr:postcode":"80021",
    "addr:street":"Allison St",
    "iso:country":"US",
    "sg:address":"10037 Allison St",
    "sg:city":"Broomfield",
    "sg:classifiers":[
        {
            "category":"Building & Trades",
            "subcategory":"Landscaping Services",
            "type":"Services"
        }
    ],
    "sg:phone":"+1 303 271 9755",
    "sg:postcode":"80021",
    "sg:province":"CO",
    "sg:tags":[
        "lawn",
        "maintenance",
        "grounds"
    ],
    "wof:name":"Mike's Custom Lawn Care",
    "wof:placetype":"venue"
},
  "geometry": {"coordinates":[-105.085863,39.879645],"type":"Point"}
}