{
  "type": "Feature",
  "properties": {
    "addr:full":"1194 S Bannock St Denver CO 80223",
    "addr:housenumber":"1194",
    "addr:postcode":"80223",
    "addr:street":"S Bannock St",
    "iso:country":"US",
    "sg:address":"1194 S Bannock St",
    "sg:city":"Denver",
    "sg:classifiers":[
        {
            "category":"Manufacturing",
            "subcategory":"Building Materials",
            "type":"Manufacturing & Wholesale Goods"
        }
    ],
    "sg:phone":"+1 303 765 0001",
    "sg:postcode":"80223",
    "sg:province":"CO",
    "wof:name":"Kerf Woodworks",
    "wof:placetype":"venue"
},
  "geometry": {"coordinates":[-104.990053,39.696569],"type":"Point"}
}