{
  "type": "Feature",
  "properties": {
    "iso:country":"US",
    "sg:address":"3250 Benton St",
    "sg:city":"Wheat Ridge",
    "sg:classifiers":[
        {
            "category":"Building & Trades",
            "subcategory":"Locksmith",
            "type":"Services"
        }
    ],
    "sg:phone":"+1 303 218 7254",
    "sg:postcode":"80212",
    "sg:province":"CO",
    "sg:tags":[
        "key"
    ],
    "wof:name":"Locksmith 24 Hours",
    "wof:placetype":"venue"
},
  "geometry": {"coordinates":[-105.055432,39.763005],"type":"Point"}
}