{
  "type": "Feature",
  "properties": {
    "iso:country":"US",
    "sg:address":"1593 S Ogden St",
    "sg:city":"Denver",
    "sg:classifiers":[
        {
            "category":"Farming",
            "subcategory":"Farm",
            "type":"Manufacturing & Wholesale Goods"
        }
    ],
    "sg:phone":"+1 303 698 1632",
    "sg:postcode":"80210",
    "sg:province":"CO",
    "sg:tags":[
        "crop",
        "general"
    ],
    "wof:name":"Lintz Land & Cat Co L L C",
    "wof:placetype":"venue"
},
  "geometry": {"coordinates":[-104.97584999999999,39.689264],"type":"Point"}
}