{
  "type": "Feature",
  "properties": {
    "addr:full":"9530 King Way Westminster CO 80031",
    "addr:housenumber":"9530",
    "addr:postcode":"80031",
    "addr:street":"King Way",
    "iso:country":"US",
    "sg:address":"9530 King Way",
    "sg:city":"Westminster",
    "sg:classifiers":[
        {
            "category":"Professional",
            "type":"Services"
        }
    ],
    "sg:phone":"+1 303 657 8440",
    "sg:postcode":"80031",
    "sg:province":"CO",
    "wof:name":"Earningsathome Net",
    "wof:placetype":"venue"
},
  "geometry": {"coordinates":[-105.033281,39.870303],"type":"Point"}
}