{
  "type": "Feature",
  "properties": {
    "addr:full":"931 S Clay St Denver CO 80219",
    "addr:housenumber":"931",
    "addr:postcode":"80219",
    "addr:street":"S Clay St",
    "iso:country":"US",
    "sg:address":"931 S Clay St",
    "sg:city":"Denver",
    "sg:classifiers":[
        {
            "category":"Building & Trades",
            "subcategory":"Landscaping Services",
            "type":"Services"
        }
    ],
    "sg:phone":"+1 303 936 5150",
    "sg:postcode":"80219",
    "sg:province":"CO",
    "sg:tags":[
        "tree"
    ],
    "wof:name":"All Phase Tree Service",
    "wof:placetype":"venue"
},
  "geometry": {"coordinates":[-105.020691,39.699742],"type":"Point"}
}