{
  "type": "Feature",
  "properties": {
    "iso:country":"US",
    "sg:address":"2280 S Columbine Street",
    "sg:city":"Denver",
    "sg:classifiers":[
        {
            "category":"Organizations",
            "subcategory":"Religious Organization",
            "type":"Services"
        }
    ],
    "sg:phone":"+1 303 777 3799",
    "sg:postcode":"80210",
    "sg:province":"CO",
    "wof:name":"Mountain View Friends Meeting",
    "wof:placetype":"venue"
},
  "geometry": {"coordinates":[-104.956641,39.675091],"type":"Point"}
}