{
  "type": "Feature",
  "properties": {
    "addr:full":"492 8th St Burlington CO 80807",
    "addr:housenumber":"492",
    "addr:postcode":"80807",
    "addr:street":"8Th St",
    "iso:country":"US",
    "sg:address":"492 8th St",
    "sg:city":"Burlington",
    "sg:classifiers":[
        {
            "category":"Insurance",
            "subcategory":"Insurance Agent",
            "type":"Services"
        }
    ],
    "sg:phone":"+1 719 346 8803",
    "sg:postcode":"80807",
    "sg:province":"CO",
    "wof:name":"Norman Travis Insurance",
    "wof:placetype":"venue"
},
  "geometry": {"coordinates":[-102.260049,39.30583],"type":"Point"}
}