{
  "type": "Feature",
  "properties": {
    "addr:full":"10735 Longs Way Parker CO 80138",
    "addr:housenumber":"10735",
    "addr:postcode":"80138",
    "addr:street":"Longs Way",
    "iso:country":"US",
    "sg:address":"10735 Longs Way",
    "sg:city":"Parker",
    "sg:classifiers":[
        {
            "category":"Real Estate",
            "subcategory":"Real Estate Agent",
            "type":"Services"
        }
    ],
    "sg:phone":"+1 303 841 8230",
    "sg:postcode":"80138",
    "sg:province":"CO",
    "wof:name":"Anderson Larry Real Estate",
    "wof:placetype":"venue"
},
  "geometry": {"coordinates":[-104.76230700000001,39.522546],"type":"Point"}
}