{
  "type": "Feature",
  "properties": {
    "addr:full":"455 E Cheyenne Mountain Blvd Colorado Springs CO 80906",
    "addr:housenumber":"455",
    "addr:postcode":"80906",
    "addr:street":"E Cheyenne Mountain Blvd",
    "iso:country":"US",
    "sg:address":"455 E Cheyenne Mountain Blvd",
    "sg:city":"Colorado Springs",
    "sg:classifiers":[
        {
            "category":"Banks & Credit Unions",
            "subcategory":"Bank",
            "type":"Services"
        }
    ],
    "sg:phone":"+1 719 227 6630",
    "sg:postcode":"80906",
    "sg:province":"CO",
    "sg:tags":[
        "national",
        "commercial"
    ],
    "wof:name":"Bank One  National Association",
    "wof:placetype":"venue"
},
  "geometry": {"coordinates":[-104.82016400000001,38.788564],"type":"Point"}
}