{
  "type": "Feature",
  "properties": {
    "iso:country":"US",
    "sg:address":"4468 E Bails Pl",
    "sg:city":"Denver",
    "sg:classifiers":[
        {
            "category":"Manufacturing",
            "subcategory":"Printing",
            "type":"Manufacturing & Wholesale Goods"
        }
    ],
    "sg:phone":"+1 303 639 5848",
    "sg:postcode":"80222",
    "sg:province":"CO",
    "sg:tags":[
        "publisher"
    ],
    "wof:name":"Reidco",
    "wof:placetype":"venue"
},
  "geometry": {"coordinates":[-104.936914,39.68272],"type":"Point"}
}