{
  "type": "Feature",
  "properties": {
    "iso:country":"US",
    "sg:address":"14985 E Stanford Dr",
    "sg:city":"Aurora",
    "sg:classifiers":[
        {
            "category":"Building & Trades",
            "subcategory":"Construction",
            "type":"Services"
        }
    ],
    "sg:phone":"+1 303 693 2330",
    "sg:postcode":"80015",
    "sg:province":"CO",
    "sg:tags":[
        "residential",
        "commercial",
        "remodeling"
    ],
    "wof:name":"Knc Remodeling",
    "wof:placetype":"venue"
},
  "geometry": {"coordinates":[-104.812701,39.633977],"type":"Point"}
}