{
  "type": "Feature",
  "properties": {
    "iso:country":"US",
    "sg:address":"1305 N Cascade Ave",
    "sg:city":"Colorado Springs",
    "sg:classifiers":[
        {
            "category":"Banks & Credit Unions",
            "subcategory":"Investment Brokerage",
            "type":"Services"
        }
    ],
    "sg:phone":"+1 719 488 3983",
    "sg:postcode":"80903",
    "sg:province":"CO",
    "sg:tags":[
        "advisory"
    ],
    "wof:name":"Help Desk Institute",
    "wof:placetype":"venue"
},
  "geometry": {"coordinates":[-104.824178,38.852247],"type":"Point"}
}