{
  "type": "Feature",
  "properties": {
    "iso:country":"US",
    "sg:address":"7369 W Grant Ranch Blvd",
    "sg:city":"Littleton",
    "sg:classifiers":[
        {
            "category":"Manufacturing",
            "subcategory":"Printing",
            "type":"Manufacturing & Wholesale Goods"
        }
    ],
    "sg:phone":"+1 303 796 7853",
    "sg:postcode":"80123",
    "sg:province":"CO",
    "sg:tags":[
        "lithographic",
        "commercial"
    ],
    "wof:name":"Aptco Printing",
    "wof:placetype":"venue"
},
  "geometry": {"coordinates":[-105.081131,39.6185],"type":"Point"}
}