{
  "type": "Feature",
  "properties": {
    "iso:country":"US",
    "sg:address":"403 Royal Gorge Blvd",
    "sg:city":"Canon City",
    "sg:classifiers":[
        {
            "category":"Professional",
            "subcategory":"Management & Consulting",
            "type":"Services"
        }
    ],
    "sg:phone":"+1 719 276 0224",
    "sg:postcode":"81212",
    "sg:province":"CO",
    "sg:tags":[
        "development",
        "economic",
        "agency"
    ],
    "wof:name":"Main Street USA",
    "wof:placetype":"venue"
},
  "geometry": {"coordinates":[-105.24013100000001,38.439781],"type":"Point"}
}