{
  "type": "Feature",
  "properties": {
    "addr:full":"243 Robbers Nest Dr Breckenridge CO 80424",
    "addr:housenumber":"243",
    "addr:postcode":"80424",
    "addr:street":"Robbers Nest Dr",
    "iso:country":"US",
    "sg:address":"243 Robbers Nest Dr",
    "sg:city":"Breckenridge",
    "sg:classifiers":[
        {
            "category":"Retail",
            "subcategory":"Repair Shop",
            "type":"Services"
        }
    ],
    "sg:phone":"+1 970 453 6941",
    "sg:postcode":"80424",
    "sg:province":"CO",
    "sg:tags":[
        "plumbing",
        "drain",
        "cleaning",
        "sewer"
    ],
    "wof:name":"All Plumbing & Heating",
    "wof:placetype":"venue"
},
  "geometry": {"coordinates":[-106.032551,39.471815],"type":"Point"}
}