{
  "type": "Feature",
  "properties": {
    "iso:country":"US",
    "sg:address":"200 Rio Grande Blvd",
    "sg:city":"Denver",
    "sg:classifiers":[
        {
            "category":"Retail",
            "subcategory":"Repair Shop",
            "type":"Services"
        },
        {
            "category":"Wholesale",
            "subcategory":"Electrical",
            "type":"Manufacturing & Wholesale Goods"
        }
    ],
    "sg:phone":"+1 303 893 0022",
    "sg:postcode":"80223",
    "sg:province":"CO",
    "sg:tags":[
        "large",
        "electric",
        "motor"
    ],
    "wof:name":"Industrial Services & Sales",
    "wof:placetype":"venue"
},
  "geometry": {"coordinates":[-105.00427999999999,39.719404],"type":"Point"}
}