{
  "type": "Feature",
  "properties": {
    "addr:full":"1517 Point Dr Frisco CO 80443",
    "addr:housenumber":"1517",
    "addr:postcode":"80443",
    "addr:street":"Point Dr",
    "iso:country":"US",
    "sg:address":"1517 Point Dr",
    "sg:city":"Frisco",
    "sg:classifiers":[
        {
            "category":"Shopping",
            "subcategory":"Shoes",
            "type":"Retail Goods"
        }
    ],
    "sg:phone":"+1 970 668 8002",
    "sg:postcode":"80443",
    "sg:province":"CO",
    "wof:name":"Salamander Designs",
    "wof:placetype":"venue"
},
  "geometry": {"coordinates":[-106.09110800000001,39.595312],"type":"Point"}
}