{
  "type": "Feature",
  "properties": {
    "addr:full":"650 S Lipan St Denver CO 80223",
    "addr:housenumber":"650",
    "addr:postcode":"80223",
    "addr:street":"S Lipan St",
    "iso:country":"US",
    "sg:address":"650 S Lipan St",
    "sg:city":"Denver",
    "sg:classifiers":[
        {
            "category":"Manufacturing",
            "subcategory":"Printing",
            "type":"Manufacturing & Wholesale Goods"
        }
    ],
    "sg:phone":"+1 303 722 7600",
    "sg:postcode":"80223",
    "sg:province":"CO",
    "sg:tags":[
        "newspaper",
        "publisher"
    ],
    "sg:website":"www.wlj.net",
    "wof:name":"Western Livestock Journal",
    "wof:placetype":"venue"
},
  "geometry": {"coordinates":[-105.001439,39.705691],"type":"Point"}
}