{
  "type": "Feature",
  "properties": {
    "addr:full":"190 Ridge Rd Durango CO 81303",
    "addr:housenumber":"190",
    "addr:postcode":"co 81303",
    "addr:street":"Ridge Rd",
    "iso:country":"US",
    "sg:address":"190 Ridge Rd",
    "sg:city":"Durango",
    "sg:classifiers":[
        {
            "category":"Building & Trades",
            "subcategory":"Construction",
            "type":"Services"
        }
    ],
    "sg:phone":"+1 970 385 4247",
    "sg:postcode":"81303",
    "sg:province":"CO",
    "sg:tags":[
        "resurfacing",
        "laying",
        "refinishing",
        "floor"
    ],
    "wof:name":"Le Gault Floor Finishing Co",
    "wof:placetype":"venue"
},
  "geometry": {"coordinates":[-107.95036,37.255826],"type":"Point"}
}