{
  "type": "Feature",
  "properties": {
    "iso:country":"US",
    "sg:address":"11674 W 28th Pl",
    "sg:city":"Denver",
    "sg:classifiers":[
        {
            "category":"Building & Trades",
            "subcategory":"Electrical",
            "type":"Services"
        }
    ],
    "sg:phone":"+1 303 445 8879",
    "sg:postcode":"80215",
    "sg:province":"CO",
    "sg:tags":[
        "electrical",
        "contractor"
    ],
    "wof:name":"Genesis Network Development",
    "wof:placetype":"venue"
},
  "geometry": {"coordinates":[-105.12991100000001,39.758249],"type":"Point"}
}