{
  "type": "Feature",
  "properties": {
    "iso:country":"US",
    "sg:address":"950 S Cherry Street Suite 900",
    "sg:city":"Denver",
    "sg:classifiers":[
        {
            "category":"Professional",
            "subcategory":"Lawyer & Legal Services",
            "type":"Services"
        }
    ],
    "sg:phone":"+1 303 753 9000",
    "sg:postcode":"80246",
    "sg:province":"CO",
    "sg:tags":[
        "personal",
        "injury"
    ],
    "wof:name":"Jacobs Charles H Atty",
    "wof:placetype":"venue"
},
  "geometry": {"coordinates":[-104.934049,39.699333],"type":"Point"}
}