{
  "type": "Feature",
  "properties": {
    "iso:country":"US",
    "sg:address":"5975 N Academy Blvd",
    "sg:city":"Colorado Springs",
    "sg:classifiers":[
        {
            "category":"Home & Garden",
            "subcategory":"Furniture",
            "type":"Retail Goods"
        }
    ],
    "sg:phone":"+1 719 593 1577",
    "sg:postcode":"80918",
    "sg:province":"CO",
    "sg:tags":[
        "merchandise"
    ],
    "wof:name":"Bed Masters",
    "wof:placetype":"venue"
},
  "geometry": {"coordinates":[-104.786771,38.917973],"type":"Point"}
}