{
  "type": "Feature",
  "properties": {
    "iso:country":"US",
    "sg:address":"20245 US Hwy 285",
    "sg:city":"La Jara",
    "sg:classifiers":[
        {
            "category":"Restaurant",
            "type":"Food & Drink"
        }
    ],
    "sg:phone":"+1 719 274 0144",
    "sg:postcode":"81140",
    "sg:province":"CO",
    "wof:name":"Wagon Wheel Saloon",
    "wof:placetype":"venue"
},
  "geometry": {"coordinates":[-105.95665200000001,37.29217],"type":"Point"}
}