{
  "type": "Feature",
  "properties": {
    "iso:country":"US",
    "sg:address":"6651 S Marion St",
    "sg:city":"Littleton",
    "sg:classifiers":[
        {
            "category":"Shopping",
            "subcategory":"Florist",
            "type":"Retail Goods"
        }
    ],
    "sg:phone":"+1 303 798 3625",
    "sg:postcode":"80121",
    "sg:province":"CO",
    "wof:name":"A Rose Gallery",
    "wof:placetype":"venue"
},
  "geometry": {"coordinates":[-104.972368,39.596267],"type":"Point"}
}