{
  "type": "Feature",
  "properties": {
    "addr:full":"1044 Spruce St Pueblo CO 81004",
    "addr:housenumber":"1044",
    "addr:postcode":"81004",
    "addr:street":"Spruce St",
    "iso:country":"US",
    "sg:address":"1044 Spruce St",
    "sg:city":"Pueblo",
    "sg:classifiers":[
        {
            "category":"Organizations",
            "subcategory":"Religious Organization",
            "type":"Services"
        }
    ],
    "sg:phone":"+1 719 542 0420",
    "sg:postcode":"81004",
    "sg:province":"CO",
    "sg:tags":[
        "church"
    ],
    "wof:name":"Bethlehem Baptist Church",
    "wof:placetype":"venue"
},
  "geometry": {"coordinates":[-104.617268,38.248672],"type":"Point"}
}