{
  "type": "Feature",
  "properties": {
    "addr:full":"13926 Marine Rd Montrose CO 81401",
    "addr:housenumber":"13926;rd",
    "addr:postcode":"81401",
    "addr:street":"Marine",
    "iso:country":"US",
    "sg:address":"13926 Marine Rd",
    "sg:city":"Montrose",
    "sg:classifiers":[
        {
            "category":"Building & Trades",
            "subcategory":"Landscaping Services",
            "type":"Services"
        }
    ],
    "sg:phone":"+1 970 240 4611",
    "sg:postcode":"81401",
    "sg:province":"CO",
    "wof:name":"Beaver Lakes Tree Farm & Nurs",
    "wof:placetype":"venue"
},
  "geometry": {"coordinates":[-107.906009,38.49366],"type":"Point"}
}