{
  "type": "Feature",
  "properties": {
    "iso:country":"US",
    "sg:address":"310 E Main St",
    "sg:city":"Aspen",
    "sg:classifiers":[
        {
            "category":"Manufacturing",
            "subcategory":"Printing",
            "type":"Manufacturing & Wholesale Goods"
        }
    ],
    "sg:phone":"+1 970 925 3414",
    "sg:postcode":"81611",
    "sg:province":"CO",
    "sg:tags":[
        "newspaper"
    ],
    "sg:website":"www.aspentimes.com",
    "wof:name":"Aspen Times",
    "wof:placetype":"venue"
},
  "geometry": {"coordinates":[-106.820297,39.190964],"type":"Point"}
}