{
  "type": "Feature",
  "properties": {
    "addr:full":"1331 Vine St Denver CO 80206",
    "addr:housenumber":"1331",
    "addr:postcode":"80206",
    "addr:street":"Vine St",
    "iso:country":"US",
    "sg:address":"1331 Vine St",
    "sg:city":"Denver",
    "sg:classifiers":[
        {
            "category":"Health Services",
            "subcategory":"Health Practitioner",
            "type":"Services"
        },
        {
            "category":"Shopping",
            "subcategory":"Beauty & Cosmetics",
            "type":"Retail Goods"
        }
    ],
    "sg:phone":"+1 303 333 6886",
    "sg:postcode":"80206",
    "sg:province":"CO",
    "sg:tags":[
        "acupuncture",
        "merchandise"
    ],
    "wof:name":"A Cosmetics Acupuncture Clinic",
    "wof:placetype":"venue"
},
  "geometry": {"coordinates":[-104.962321,39.73791],"type":"Point"}
}