{
  "type": "Feature",
  "properties": {
    "iso:country":"US",
    "sg:address":"2422 S Trenton Way",
    "sg:city":"Denver",
    "sg:classifiers":[
        {
            "category":"Professional",
            "subcategory":"Detective & Security Services",
            "type":"Services"
        }
    ],
    "sg:phone":"+1 303 321 2428",
    "sg:postcode":"80231",
    "sg:province":"CO",
    "sg:tags":[
        "control",
        "monitoring",
        "system"
    ],
    "wof:name":"United Systems",
    "wof:placetype":"venue"
},
  "geometry": {"coordinates":[-104.895685,39.672242],"type":"Point"}
}