{
  "type": "Feature",
  "properties": {
    "addr:full":"333 Airport Blvd Aurora CO 80011",
    "addr:housenumber":"333",
    "addr:postcode":"80011",
    "addr:street":"Airport Blvd",
    "iso:country":"US",
    "sg:address":"333 Airport Blvd",
    "sg:city":"Aurora",
    "sg:classifiers":[
        {
            "category":"Wholesale",
            "subcategory":"Machinery & Supplies",
            "type":"Manufacturing & Wholesale Goods"
        }
    ],
    "sg:phone":"+1 303 343 1123",
    "sg:postcode":"80011",
    "sg:province":"CO",
    "sg:tags":[
        "engine",
        "equipment",
        "industrial"
    ],
    "wof:name":"Denver Diesel Injection LLC",
    "wof:placetype":"venue"
},
  "geometry": {"coordinates":[-104.791239,39.720687],"type":"Point"}
}