{
  "type": "Feature",
  "properties": {
    "iso:country":"US",
    "sg:address":"1075 S Fox St",
    "sg:city":"Denver",
    "sg:classifiers":[
        {
            "category":"Building & Trades",
            "subcategory":"Plumbing",
            "type":"Services"
        }
    ],
    "sg:phone":"+1 303 777 2056",
    "sg:postcode":"80223",
    "sg:province":"CO",
    "sg:tags":[
        "air",
        "refrigeration",
        "conditioning",
        "heating"
    ],
    "sg:website":"www.climateengineering.com",
    "wof:name":"Climate Engineering Inc",
    "wof:placetype":"venue"
},
  "geometry": {"coordinates":[-104.994541,39.698242],"type":"Point"}
}