{
  "type": "Feature",
  "properties": {
    "addr:full":"801 Main St Longmont CO 80501",
    "addr:housenumber":"801",
    "addr:postcode":"80501",
    "addr:street":"Main St",
    "iso:country":"US",
    "sg:address":"801 Main St",
    "sg:city":"Longmont",
    "sg:classifiers":[
        {
            "category":"Home & Garden",
            "subcategory":"Building Materials",
            "type":"Retail Goods"
        },
        {
            "category":"Wholesale",
            "subcategory":"Auto Parts",
            "type":"Manufacturing & Wholesale Goods"
        }
    ],
    "sg:phone":"+1 303 776 5623",
    "sg:postcode":"80501",
    "sg:province":"CO",
    "sg:tags":[
        "paint",
        "motor",
        "vehicle"
    ],
    "wof:name":"Bart's Automotive Paint",
    "wof:placetype":"venue"
},
  "geometry": {"coordinates":[-105.102495,40.173932],"type":"Point"}
}