{
  "type": "Feature",
  "properties": {
    "addr:full":"5526 N Academy Blvd Colorado Springs CO 80918",
    "addr:housenumber":"5526",
    "addr:postcode":"80918",
    "addr:street":"N Academy Blvd",
    "iso:country":"US",
    "sg:address":"5526 N Academy Blvd",
    "sg:city":"Colorado Springs",
    "sg:classifiers":[
        {
            "category":"Professional",
            "subcategory":"Employment Agencies",
            "type":"Services"
        }
    ],
    "sg:phone":"+1 719 528 5353",
    "sg:postcode":"80918",
    "sg:province":"CO",
    "sg:tags":[
        "opportunity"
    ],
    "wof:name":"Adecco",
    "wof:placetype":"venue"
},
  "geometry": {"coordinates":[-104.78586799999999,38.908505],"type":"Point"}
}