{
  "type": "Feature",
  "properties": {
    "iso:country":"US",
    "sg:address":"880 Happy Canyon Rd Ste 130",
    "sg:city":"Castle Rock",
    "sg:classifiers":[
        {
            "category":"Personal",
            "subcategory":"Day Spa",
            "type":"Services"
        }
    ],
    "sg:phone":"+1 303 660 1511",
    "sg:postcode":"80108",
    "sg:province":"CO",
    "sg:website":"www.aspenfallsspa.com",
    "wof:name":"AspenFalls Spa",
    "wof:placetype":"venue"
},
  "geometry": {"coordinates":[-104.901716,39.427007],"type":"Point"}
}