{
  "type": "Feature",
  "properties": {
    "addr:full":"104 Anderson St La Junta CO 81050",
    "addr:housenumber":"104",
    "addr:postcode":"81050",
    "addr:street":"Anderson St",
    "iso:country":"US",
    "sg:address":"104 Anderson St",
    "sg:city":"La Junta",
    "sg:classifiers":[
        {
            "category":"Restaurant",
            "type":"Food & Drink"
        }
    ],
    "sg:menulink":"http://www.allmenus.com/co/la-junta/206961-sonic/menu/",
    "sg:phone":"+1 719 384 5540",
    "sg:postcode":"81050",
    "sg:province":"CO",
    "sg:tags":[
        "burger",
        "american"
    ],
    "wof:name":"Sonic",
    "wof:placetype":"venue"
},
  "geometry": {"coordinates":[-103.551395,37.98783],"type":"Point"}
}