{
  "type": "Feature",
  "properties": {
    "iso:country":"US",
    "sg:address":"2205 Broadway St",
    "sg:city":"Boulder",
    "sg:classifiers":[
        {
            "category":"Shopping",
            "subcategory":"Clothing, Apparel, & Fashions",
            "type":"Retail Goods"
        }
    ],
    "sg:phone":"+1 720 406 1818",
    "sg:postcode":"80302",
    "sg:province":"CO",
    "sg:tags":[
        "wear"
    ],
    "wof:name":"Stand Up For Kids Boulder",
    "wof:placetype":"venue"
},
  "geometry": {"coordinates":[-105.28106699999999,40.020865],"type":"Point"}
}