{
  "type": "Feature",
  "properties": {
    "addr:full":"4944 Pearl St Boulder CO 80301",
    "addr:housenumber":"4944",
    "addr:postcode":"80301",
    "addr:street":"Pearl St",
    "iso:country":"US",
    "sg:address":"4944 Pearl St",
    "sg:city":"Boulder",
    "sg:classifiers":[
        {
            "category":"Retail",
            "subcategory":"Auto Repair",
            "type":"Services"
        }
    ],
    "sg:phone":"+1 303 444 0995",
    "sg:postcode":"80301",
    "sg:province":"CO",
    "sg:tags":[
        "automobile",
        "top",
        "upholstery"
    ],
    "wof:name":"Mark Spenard Enterprises",
    "wof:placetype":"venue"
},
  "geometry": {"coordinates":[-105.23759099999999,40.025625],"type":"Point"}
}