{
  "type": "Feature",
  "properties": {
    "addr:full":"2683 E 120th Ave Ste B4 Denver CO 80233",
    "addr:housenumber":"2683",
    "addr:postcode":"80233",
    "addr:street":"E 120Th Ave Ste B4",
    "iso:country":"US",
    "sg:address":"2683 E 120th Ave Ste B4",
    "sg:city":"Denver",
    "sg:classifiers":[
        {
            "category":"Personal",
            "subcategory":"Nail Salon",
            "type":"Services"
        }
    ],
    "sg:phone":"+1 303 252 7421",
    "sg:postcode":"80233",
    "sg:province":"CO",
    "wof:name":"Nail Center",
    "wof:placetype":"venue"
},
  "geometry": {"coordinates":[-104.953485,39.913929],"type":"Point"}
}