{
  "type": "Feature",
  "properties": {
    "addr:full":"8726 Tall Grass Pl Lone Tree CO 80124",
    "addr:housenumber":"8726",
    "addr:postcode":"80124",
    "addr:street":"Tall Grass Pl",
    "iso:country":"US",
    "sg:address":"8726 Tall Grass Pl",
    "sg:city":"Lone Tree",
    "sg:classifiers":[
        {
            "category":"Professional",
            "subcategory":"Business Services",
            "type":"Services"
        }
    ],
    "sg:phone":"+1 303 790 8797",
    "sg:postcode":"80124",
    "sg:province":"CO",
    "sg:tags":[
        "paralegal"
    ],
    "wof:name":"Lonetree Resource Ctr",
    "wof:placetype":"venue"
},
  "geometry": {"coordinates":[-104.888294,39.538956],"type":"Point"}
}