{
  "type": "Feature",
  "properties": {
    "addr:full":"4111 Andrew Dr Colorado City CO 81069",
    "addr:housenumber":"4111",
    "addr:postcode":"81069",
    "addr:street":"Andrew Dr",
    "iso:country":"US",
    "sg:address":"4111 Andrew Dr",
    "sg:city":"Colorado City",
    "sg:classifiers":[
        {
            "category":"Organizations",
            "subcategory":"Professional Association",
            "type":"Services"
        }
    ],
    "sg:phone":"+1 719 676 3090",
    "sg:postcode":"81069",
    "sg:province":"CO",
    "sg:tags":[
        "sales"
    ],
    "sg:website":"www.germanmugs.com",
    "wof:name":"B G Youngkrantz Co",
    "wof:placetype":"venue"
},
  "geometry": {"coordinates":[-104.851152,37.93416],"type":"Point"}
}