{
  "type": "Feature",
  "properties": {
    "addr:full":"19711 E Smoky Hill Rd Aurora CO 80015",
    "addr:housenumber":"19711",
    "addr:postcode":"80015",
    "addr:street":"E Smoky Hill Rd",
    "iso:country":"US",
    "sg:address":"19711 E Smoky Hill Rd",
    "sg:city":"Aurora",
    "sg:classifiers":[
        {
            "category":"Banks & Credit Unions",
            "subcategory":"Bank",
            "type":"Services"
        }
    ],
    "sg:phone":"+1 303 699 5574",
    "sg:postcode":"80015",
    "sg:province":"CO",
    "wof:name":"US Bank",
    "wof:placetype":"venue"
},
  "geometry": {"coordinates":[-104.757408,39.613068],"type":"Point"}
}