{
  "type": "Feature",
  "properties": {
    "addr:full":"1010 Cherokee Street Denver CO 80204",
    "addr:housenumber":"1010",
    "addr:postcode":"80204",
    "addr:street":"Cherokee Street",
    "iso:country":"US",
    "sg:address":"1010 Cherokee Street",
    "sg:city":"Denver",
    "sg:classifiers":[
        {
            "category":"Building & Trades",
            "subcategory":"Construction",
            "type":"Services"
        }
    ],
    "sg:phone":"+1 303 572 1858",
    "sg:postcode":"80204",
    "sg:province":"CO",
    "sg:tags":[
        "contractor"
    ],
    "wof:name":"Findlay Criss & Company",
    "wof:placetype":"venue"
},
  "geometry": {"coordinates":[-104.99150899999999,39.732487],"type":"Point"}
}