{
  "type": "Feature",
  "properties": {
    "iso:country":"US",
    "sg:address":"11780 E 53rd Ave",
    "sg:city":"Denver",
    "sg:classifiers":[
        {
            "category":"Manufacturing",
            "subcategory":"Printing",
            "type":"Manufacturing & Wholesale Goods"
        }
    ],
    "sg:phone":"+1 303 373 4066",
    "sg:postcode":"80239",
    "sg:province":"CO",
    "sg:tags":[
        "publishing"
    ],
    "wof:name":"Aims Express",
    "wof:placetype":"venue"
},
  "geometry": {"coordinates":[-104.85120999999999,39.793024],"type":"Point"}
}