{
  "type": "Feature",
  "properties": {
    "iso:country":"US",
    "sg:address":"3900 Thatcher Ave",
    "sg:city":"Pueblo",
    "sg:classifiers":[
        {
            "category":"Sports & Exercise",
            "subcategory":"Golf",
            "type":"Entertainment"
        }
    ],
    "sg:phone":"+1 719 561 4946",
    "sg:postcode":"81005",
    "sg:province":"CO",
    "sg:tags":[
        "course"
    ],
    "wof:name":"Elmwood Golf Course",
    "wof:placetype":"venue"
},
  "geometry": {"coordinates":[-104.650549,38.258389],"type":"Point"}
}