{
  "type": "Feature",
  "properties": {
    "iso:country":"US",
    "sg:address":"149 S Zang Way",
    "sg:city":"Lakewood",
    "sg:classifiers":[
        {
            "category":"Real Estate",
            "subcategory":"Real Estate Operator",
            "type":"Services"
        }
    ],
    "sg:phone":"+1 303 986 2180",
    "sg:postcode":"80228",
    "sg:province":"CO",
    "sg:tags":[
        "condominium"
    ],
    "wof:name":"West Ridge Condominiums",
    "wof:placetype":"venue"
},
  "geometry": {"coordinates":[-105.144218,39.713006],"type":"Point"}
}