{
  "type": "Feature",
  "properties": {
    "iso:country":"US",
    "sg:address":"6730 S Washington St",
    "sg:city":"Centennial",
    "sg:classifiers":[
        {
            "category":"Professional",
            "subcategory":"Business Services",
            "type":"Services"
        }
    ],
    "sg:phone":"+1 303 627 7700",
    "sg:postcode":"80122",
    "sg:province":"CO",
    "sg:tags":[
        "repossessing"
    ],
    "wof:name":"Acme Collateral Recovery",
    "wof:placetype":"venue"
},
  "geometry": {"coordinates":[-104.97826499999999,39.593399],"type":"Point"}
}