{
  "type": "Feature",
  "properties": {
    "iso:country":"US",
    "sg:address":"9625 E Arapahoe Rd",
    "sg:city":"Englewood",
    "sg:classifiers":[
        {
            "category":"Restaurant",
            "type":"Food & Drink"
        }
    ],
    "sg:menulink":"http://www.allmenus.com/co/southwest-arapahoe/82505-blackjack-pizza/menu/",
    "sg:phone":"+1 303 649 1212",
    "sg:postcode":"80112",
    "sg:province":"CO",
    "sg:tags":[
        "american",
        "pizza"
    ],
    "wof:name":"Blackjack Pizza",
    "wof:placetype":"venue"
},
  "geometry": {"coordinates":[-104.8767,39.595706],"type":"Point"}
}