{
  "type": "Feature",
  "properties": {
    "addr:full":"23600 Everett Rd Pueblo CO 81006",
    "addr:housenumber":"23600",
    "addr:postcode":"81006",
    "addr:street":"Everett Rd",
    "iso:country":"US",
    "sg:address":"23600 Everett Rd",
    "sg:city":"Pueblo",
    "sg:classifiers":[
        {
            "category":"Education",
            "subcategory":"School",
            "type":"Public Place"
        }
    ],
    "sg:phone":"+1 719 542 7813",
    "sg:postcode":"81006",
    "sg:province":"CO",
    "sg:tags":[
        "secondary"
    ],
    "wof:name":"Pleasant View",
    "wof:placetype":"venue"
},
  "geometry": {"coordinates":[-104.54958600000001,38.252546],"type":"Point"}
}