{
  "type": "Feature",
  "properties": {
    "iso:country":"US",
    "sg:address":"5650 Greenwood Plaza Blvd",
    "sg:city":"Greenwood Vlg",
    "sg:classifiers":[
        {
            "category":"Professional",
            "subcategory":"Lawyer & Legal Services",
            "type":"Services"
        }
    ],
    "sg:phone":"+1 303 691 9047",
    "sg:postcode":"80111",
    "sg:province":"CO",
    "sg:tags":[
        "attorney"
    ],
    "wof:name":"John P Beutelschies",
    "wof:placetype":"venue"
},
  "geometry": {"coordinates":[-104.89751099999999,39.612059],"type":"Point"}
}