{
  "type": "Feature",
  "properties": {
    "addr:full":"1500 E 104th Ave Denver CO 80233",
    "addr:housenumber":"1500",
    "addr:postcode":"80233",
    "addr:street":"E 104Th Ave",
    "iso:country":"US",
    "sg:address":"1500 E 104th Ave",
    "sg:city":"Denver",
    "sg:classifiers":[
        {
            "category":"Restaurant",
            "type":"Food & Drink"
        }
    ],
    "sg:menulink":"http://www.allmenus.com/co/west-adams/173832-wendys/menu/",
    "sg:phone":"+1 303 252 7006",
    "sg:postcode":"80233",
    "sg:province":"CO",
    "sg:tags":[
        "burger",
        "american",
        "soup"
    ],
    "wof:name":"Wendy's",
    "wof:placetype":"venue"
},
  "geometry": {"coordinates":[-104.96791899999999,39.884593],"type":"Point"}
}