{
  "type": "Feature",
  "properties": {
    "iso:country":"US",
    "sg:address":"10121 Montview Blvd",
    "sg:city":"Aurora",
    "sg:classifiers":[
        {
            "category":"Personal",
            "subcategory":"Barber",
            "type":"Services"
        }
    ],
    "sg:phone":"+1 303 341 5863",
    "sg:postcode":"80010",
    "sg:province":"CO",
    "wof:name":"Dewayne's Barber Shop",
    "wof:placetype":"venue"
},
  "geometry": {"coordinates":[-104.869536,39.747494],"type":"Point"}
}