{
  "type": "Feature",
  "properties": {
    "iso:country":"US",
    "sg:address":"2501 Blichman Ave",
    "sg:city":"Grand Junction",
    "sg:classifiers":[
        {
            "category":"Building & Trades",
            "subcategory":"Construction",
            "type":"Services"
        }
    ],
    "sg:phone":"+1 970 243 7950",
    "sg:postcode":"81505",
    "sg:province":"CO",
    "sg:tags":[
        "general",
        "contractor"
    ],
    "wof:name":"Associated Builders & Contrs",
    "wof:placetype":"venue"
},
  "geometry": {"coordinates":[-108.586738,39.096838],"type":"Point"}
}