{
  "type": "Feature",
  "properties": {
    "addr:full":"6317 Kyle Ave Fort Collins CO 80525",
    "addr:housenumber":"6317",
    "addr:postcode":"80525",
    "addr:street":"Kyle Ave",
    "iso:country":"US",
    "sg:address":"6317 Kyle Ave",
    "sg:city":"Fort Collins",
    "sg:classifiers":[
        {
            "category":"Government",
            "subcategory":"Office",
            "type":"Public Place"
        }
    ],
    "sg:phone":"+1 970 226 3647",
    "sg:postcode":"80525",
    "sg:province":"CO",
    "sg:tags":[
        "village"
    ],
    "wof:name":"Larimer County Animal Control",
    "wof:placetype":"venue"
},
  "geometry": {"coordinates":[-105.06917199999999,40.500476],"type":"Point"}
}