{
  "type": "Feature",
  "properties": {
    "iso:country":"US",
    "sg:address":"498 E 133rd Way",
    "sg:city":"Denver",
    "sg:classifiers":[
        {
            "category":"Manufacturing",
            "subcategory":"Wood Products",
            "type":"Manufacturing & Wholesale Goods"
        }
    ],
    "sg:phone":"+1 303 252 0447",
    "sg:postcode":"80241",
    "sg:province":"CO",
    "sg:tags":[
        "container",
        "mfg"
    ],
    "wof:name":"Creations By Angela",
    "wof:placetype":"venue"
},
  "geometry": {"coordinates":[-104.98102,39.93812],"type":"Point"}
}