{
  "type": "Feature",
  "properties": {
    "addr:full":"444 N 1st St Berthoud CO 80513",
    "addr:housenumber":"444",
    "addr:postcode":"80513",
    "addr:street":"N 1St St",
    "iso:country":"US",
    "sg:address":"444 N 1st St",
    "sg:city":"Berthoud",
    "sg:classifiers":[
        {
            "category":"Travel",
            "subcategory":"Hotels & Motels",
            "type":"Entertainment"
        }
    ],
    "sg:phone":"+1 970 532 4566",
    "sg:postcode":"80513",
    "sg:province":"CO",
    "sg:tags":[
        "breakfast",
        "accommodation",
        "bed"
    ],
    "wof:name":"Berthoud Bed & Breakfast",
    "wof:placetype":"venue"
},
  "geometry": {"coordinates":[-105.074141,40.304666],"type":"Point"}
}