{
  "type": "Feature",
  "properties": {
    "iso:country":"US",
    "sg:address":"901 Walnut St",
    "sg:city":"Boulder",
    "sg:classifiers":[
        {
            "category":"Real Estate",
            "subcategory":"Real Estate Operator",
            "type":"Services"
        }
    ],
    "sg:phone":"+1 303 402 1863",
    "sg:postcode":"80302",
    "sg:province":"CO",
    "sg:tags":[
        "building",
        "nonresidential"
    ],
    "wof:name":"901 Walnut Street LLC",
    "wof:placetype":"venue"
},
  "geometry": {"coordinates":[-105.282117,40.016366],"type":"Point"}
}