{
  "type": "Feature",
  "properties": {
    "addr:full":"540 S Saint Vrain Ave Estes Park CO 80517",
    "addr:housenumber":"540",
    "addr:postcode":"80517",
    "addr:street":"S Saint Vrain Ave",
    "iso:country":"US",
    "sg:address":"540 S Saint Vrain Ave",
    "sg:city":"Estes Park",
    "sg:classifiers":[
        {
            "category":"Restaurant",
            "type":"Food & Drink"
        }
    ],
    "sg:phone":"+1 970 586 9001",
    "sg:postcode":"80517",
    "sg:province":"CO",
    "wof:name":"Mountaineer Restaurant",
    "wof:placetype":"venue"
},
  "geometry": {"coordinates":[-105.504717,40.36988],"type":"Point"}
}