{
  "type": "Feature",
  "properties": {
    "addr:full":"1415 W Cedar Ave Denver CO 80223",
    "addr:housenumber":"1415",
    "addr:postcode":"80223",
    "addr:street":"W Cedar Ave",
    "iso:country":"US",
    "sg:address":"1415 W Cedar Ave",
    "sg:city":"Denver",
    "sg:classifiers":[
        {
            "category":"Banks & Credit Unions",
            "subcategory":"Bank",
            "type":"Services"
        }
    ],
    "sg:phone":"+1 303 282 6040",
    "sg:postcode":"80223",
    "sg:province":"CO",
    "wof:name":"Pendum Inc",
    "wof:placetype":"venue"
},
  "geometry": {"coordinates":[-105.006559,39.713169],"type":"Point"}
}