{
  "type": "Feature",
  "properties": {
    "addr:full":"110 E Olive St Lamar CO 81052",
    "addr:housenumber":"110",
    "addr:postcode":"81052",
    "addr:street":"E Olive St",
    "iso:country":"US",
    "sg:address":"110 E Olive St",
    "sg:city":"Lamar",
    "sg:classifiers":[
        {
            "category":"Shopping",
            "subcategory":"Shoes",
            "type":"Retail Goods"
        }
    ],
    "sg:phone":"+1 719 336 4424",
    "sg:postcode":"81052",
    "sg:province":"CO",
    "sg:tags":[
        "parlor",
        "shoe"
    ],
    "wof:name":"Millers Boot Store",
    "wof:placetype":"venue"
},
  "geometry": {"coordinates":[-102.61793400000001,38.088171],"type":"Point"}
}