{
  "type": "Feature",
  "properties": {
    "iso:country":"US",
    "sg:address":"113 Broken Wheel Ct",
    "sg:city":"Divide",
    "sg:classifiers":[
        {
            "category":"Professional",
            "type":"Services"
        }
    ],
    "sg:phone":"+1 719 687 3418",
    "sg:postcode":"80814",
    "sg:province":"CO",
    "sg:tags":[
        "establishment"
    ],
    "wof:name":"Bill Gremmert Digital",
    "wof:placetype":"venue"
},
  "geometry": {"coordinates":[-105.197219,38.975058],"type":"Point"}
}