{
  "type": "Feature",
  "properties": {
    "iso:country":"US",
    "sg:address":"3647 W Grand Ave",
    "sg:city":"Littleton",
    "sg:classifiers":[
        {
            "category":"Building & Trades",
            "subcategory":"Construction",
            "type":"Services"
        }
    ],
    "sg:phone":"+1 303 798 4476",
    "sg:postcode":"80123",
    "sg:province":"CO",
    "sg:tags":[
        "excavation",
        "contractor"
    ],
    "wof:name":"Don Blair Excavating Inc",
    "wof:placetype":"venue"
},
  "geometry": {"coordinates":[-105.03685400000001,39.627267],"type":"Point"}
}