{
  "type": "Feature",
  "properties": {
    "addr:full":"7250 W 116th Pl Broomfield CO 80020",
    "addr:housenumber":"7250",
    "addr:postcode":"80020",
    "addr:street":"W 116Th Pl",
    "iso:country":"US",
    "sg:address":"7250 W 116th Pl",
    "sg:city":"Broomfield",
    "sg:classifiers":[
        {
            "category":"Building & Trades",
            "subcategory":"Construction",
            "type":"Services"
        }
    ],
    "sg:phone":"+1 303 404 2333",
    "sg:postcode":"80020",
    "sg:province":"CO",
    "sg:tags":[
        "fence",
        "contractor"
    ],
    "wof:name":"American Fence",
    "wof:placetype":"venue"
},
  "geometry": {"coordinates":[-105.077645,39.908725],"type":"Point"}
}