{
  "type": "Feature",
  "properties": {
    "iso:country":"US",
    "sg:address":"425 Hickory St",
    "sg:city":"Johnstown",
    "sg:classifiers":[
        {
            "category":"Health Services",
            "subcategory":"Clinic",
            "type":"Services"
        }
    ],
    "sg:phone":"+1 970 396 8781",
    "sg:postcode":"80524",
    "sg:province":"CO",
    "wof:name":"Affordable Health Care Options",
    "wof:placetype":"venue"
},
  "geometry": {"coordinates":[-105.08208500000001,40.603415],"type":"Point"}
}