{
  "type": "Feature",
  "properties": {
    "addr:full":"8315 Park Meadows Center Dr Littleton CO 80124",
    "addr:housenumber":"8315",
    "addr:postcode":"80124",
    "addr:street":"Park Meadows Center Dr",
    "iso:country":"US",
    "sg:address":"8315 Park Meadows Center Dr",
    "sg:city":"Littleton",
    "sg:classifiers":[
        {
            "category":"Restaurant",
            "type":"Food & Drink"
        }
    ],
    "sg:menulink":"http://www.allmenus.com/co/sedalia/6699-pf-changs/menu/",
    "sg:phone":"+1 303 790 7744",
    "sg:postcode":"80124",
    "sg:province":"CO",
    "sg:tags":[
        "japanese",
        "chinese",
        "asian"
    ],
    "wof:name":"P.F. Chang's",
    "wof:placetype":"venue"
},
  "geometry": {"coordinates":[-104.875974,39.565674],"type":"Point"}
}