{
  "type": "Feature",
  "properties": {
    "iso:country":"US",
    "sg:address":"17301 W Colfax Ave",
    "sg:city":"Golden",
    "sg:classifiers":[
        {
            "category":"Education",
            "subcategory":"Dance Studio",
            "type":"Public Place"
        }
    ],
    "sg:phone":"+1 303 215 9814",
    "sg:postcode":"80401",
    "sg:province":"CO",
    "sg:tags":[
        "instruction",
        "dancing"
    ],
    "wof:name":"Colorado Centre Of Dance",
    "wof:placetype":"venue"
},
  "geometry": {"coordinates":[-105.196716,39.721979],"type":"Point"}
}