{
  "type": "Feature",
  "properties": {
    "addr:full":"3120 E Main St Canon City CO 81212",
    "addr:housenumber":"3120",
    "addr:postcode":"81212",
    "addr:street":"E Main St",
    "iso:country":"US",
    "sg:address":"3120 E Main St",
    "sg:city":"Canon City",
    "sg:classifiers":[
        {
            "category":"Travel",
            "subcategory":"Campground",
            "type":"Entertainment"
        }
    ],
    "sg:phone":"+1 719 275 4576",
    "sg:postcode":"81212",
    "sg:province":"CO",
    "wof:name":"Rv Station Campground",
    "wof:placetype":"venue"
},
  "geometry": {"coordinates":[-105.19319299999999,38.446654],"type":"Point"}
}