{
  "type": "Feature",
  "properties": {
    "iso:country":"US",
    "sg:address":"8439 Ames St",
    "sg:city":"Arvada",
    "sg:classifiers":[
        {
            "category":"Building & Trades",
            "subcategory":"Construction",
            "type":"Services"
        }
    ],
    "sg:phone":"+1 303 428 7885",
    "sg:postcode":"80003",
    "sg:province":"CO",
    "sg:tags":[
        "painter"
    ],
    "wof:name":"Advanced Designer Faux Finish",
    "wof:placetype":"venue"
},
  "geometry": {"coordinates":[-105.055052,39.851702],"type":"Point"}
}