{
  "type": "Feature",
  "properties": {
    "iso:country":"US",
    "sg:address":"1695 W Sheri Ln",
    "sg:city":"Littleton",
    "sg:classifiers":[
        {
            "category":"Manufacturing",
            "subcategory":"Rubber & Plastics",
            "type":"Manufacturing & Wholesale Goods"
        }
    ],
    "sg:phone":"+1 303 797 4807",
    "sg:postcode":"80120",
    "sg:province":"CO",
    "sg:tags":[
        "product",
        "mfg"
    ],
    "wof:name":"All 4u LLC",
    "wof:placetype":"venue"
},
  "geometry": {"coordinates":[-105.008408,39.622904],"type":"Point"}
}