{
  "type": "Feature",
  "properties": {
    "iso:country":"US",
    "sg:address":"10800 E Bethany Dr",
    "sg:city":"Aurora",
    "sg:classifiers":[
        {
            "category":"Building & Trades",
            "subcategory":"Construction",
            "type":"Services"
        }
    ],
    "sg:phone":"+1 303 671 5556",
    "sg:postcode":"80014",
    "sg:province":"CO",
    "sg:tags":[
        "home",
        "builder"
    ],
    "sg:website":"www.amberhomes.com",
    "wof:name":"Amber Homes",
    "wof:placetype":"venue"
},
  "geometry": {"coordinates":[-104.86433,39.661768],"type":"Point"}
}