{
  "type": "Feature",
  "properties": {
    "addr:full":"332 Denver Ave Fort Lupton CO 80621",
    "addr:housenumber":"332",
    "addr:postcode":"80621",
    "addr:street":"Denver Ave",
    "iso:country":"US",
    "sg:address":"332 Denver Ave",
    "sg:city":"Fort Lupton",
    "sg:classifiers":[
        {
            "category":"Professional",
            "subcategory":"Lawyer & Legal Services",
            "type":"Services"
        }
    ],
    "sg:phone":"+1 303 857 4667",
    "sg:postcode":"80621",
    "sg:province":"CO",
    "sg:tags":[
        "attorney"
    ],
    "wof:name":"John R Dent Law Office",
    "wof:placetype":"venue"
},
  "geometry": {"coordinates":[-104.81043099999999,40.08295],"type":"Point"}
}