{
  "type": "Feature",
  "properties": {
    "iso:country":"US",
    "sg:address":"8226 Centaur Dr",
    "sg:city":"Evergreen",
    "sg:classifiers":[
        {
            "category":"Banks & Credit Unions",
            "subcategory":"Investment Brokerage",
            "type":"Services"
        }
    ],
    "sg:phone":"+1 303 670 3327",
    "sg:postcode":"80439",
    "sg:province":"CO",
    "sg:tags":[
        "advisory",
        "financial"
    ],
    "sg:website":"www.nanababa.com",
    "wof:name":"Mountain Spruce Investment",
    "wof:placetype":"venue"
},
  "geometry": {"coordinates":[-105.31689,39.567921],"type":"Point"}
}