{
  "type": "Feature",
  "properties": {
    "addr:full":"1703 Pearl St Boulder CO 80302",
    "addr:housenumber":"1703",
    "addr:postcode":"80302",
    "addr:street":"Pearl St",
    "iso:country":"US",
    "sg:address":"1703 Pearl St",
    "sg:city":"Boulder",
    "sg:classifiers":[
        {
            "category":"Shopping",
            "subcategory":"Clothing, Apparel, & Fashions",
            "type":"Retail Goods"
        }
    ],
    "sg:phone":"+1 303 447 8650",
    "sg:postcode":"80302",
    "sg:province":"CO",
    "sg:tags":[
        "woman"
    ],
    "wof:name":"Sunneshine Couture Ltd Corp",
    "wof:placetype":"venue"
},
  "geometry": {"coordinates":[-105.272148,40.019576],"type":"Point"}
}