{
  "type": "Feature",
  "properties": {
    "iso:country":"US",
    "sg:address":"8000 E Belleview Ave",
    "sg:city":"Englewood",
    "sg:classifiers":[
        {
            "category":"Banks & Credit Unions",
            "subcategory":"Bank",
            "type":"Services"
        }
    ],
    "sg:phone":"+1 303 779 6462",
    "sg:postcode":"80111",
    "sg:province":"CO",
    "sg:tags":[
        "mortgage"
    ],
    "wof:name":"Countrywide",
    "wof:placetype":"venue"
},
  "geometry": {"coordinates":[-104.89687000000001,39.624044],"type":"Point"}
}