{
  "type": "Feature",
  "properties": {
    "addr:full":"965 Morgan Dr Boulder CO 80303",
    "addr:housenumber":"965",
    "addr:postcode":"80303",
    "addr:street":"Morgan Dr",
    "iso:country":"US",
    "sg:address":"965 Morgan Dr",
    "sg:city":"Boulder",
    "sg:classifiers":[
        {
            "category":"Health Services",
            "subcategory":"Clinic",
            "type":"Services"
        }
    ],
    "sg:phone":"+1 303 499 9727",
    "sg:postcode":"80303",
    "sg:province":"CO",
    "sg:tags":[
        "home",
        "care"
    ],
    "wof:name":"S Tc Community Inc",
    "wof:placetype":"venue"
},
  "geometry": {"coordinates":[-105.238427,40.005472],"type":"Point"}
}