{
  "type": "Feature",
  "properties": {
    "iso:country":"US",
    "sg:address":"3251 Revere St",
    "sg:city":"Aurora",
    "sg:classifiers":[
        {
            "category":"Communications",
            "subcategory":"Film & Video Production",
            "type":"Services"
        },
        {
            "category":"Professional",
            "subcategory":"Business Services",
            "type":"Services"
        }
    ],
    "sg:phone":"+1 303 341 0079",
    "sg:postcode":"80011",
    "sg:province":"CO",
    "sg:tags":[
        "motion",
        "packaging"
    ],
    "wof:name":"Pathways Production",
    "wof:placetype":"venue"
},
  "geometry": {"coordinates":[-104.841009,39.7627],"type":"Point"}
}