{
  "type": "Feature",
  "properties": {
    "addr:full":"35 Bear Canyon Dr Bayfield CO 81122",
    "addr:housenumber":"35",
    "addr:postcode":"81122",
    "addr:street":"Bear Canyon Dr",
    "iso:country":"US",
    "sg:address":"35 Bear Canyon Dr",
    "sg:city":"Bayfield",
    "sg:classifiers":[
        {
            "category":"Building & Trades",
            "subcategory":"Construction",
            "type":"Services"
        }
    ],
    "sg:phone":"+1 970 884 4077",
    "sg:postcode":"81122",
    "sg:province":"CO",
    "sg:tags":[
        "heavy",
        "house"
    ],
    "wof:name":"Senti Construction",
    "wof:placetype":"venue"
},
  "geometry": {"coordinates":[-107.492875,37.306798],"type":"Point"}
}