{
  "type": "Feature",
  "properties": {
    "iso:country":"US",
    "sg:address":"1830 Platte Street",
    "sg:city":"Denver",
    "sg:classifiers":[
        {
            "category":"Banks & Credit Unions",
            "subcategory":"Financial Services",
            "type":"Services"
        }
    ],
    "sg:phone":"+1 303 458 1100",
    "sg:postcode":"80202",
    "sg:province":"CO",
    "sg:tags":[
        "broker",
        "mortgage"
    ],
    "wof:name":"Cardinal Financial",
    "wof:placetype":"venue"
},
  "geometry": {"coordinates":[-105.00543999999999,39.75928],"type":"Point"}
}