{
  "type": "Feature",
  "properties": {
    "iso:country":"US",
    "sg:address":"624 Agana Dr",
    "sg:city":"Grand Junction",
    "sg:classifiers":[
        {
            "category":"Shopping",
            "subcategory":"Bicycles & Sporting Goods",
            "type":"Retail Goods"
        }
    ],
    "sg:phone":"+1 970 434 7997",
    "sg:postcode":"81504",
    "sg:province":"CO",
    "wof:name":"Kidsports",
    "wof:placetype":"venue"
},
  "geometry": {"coordinates":[-108.494311,39.094193],"type":"Point"}
}