{
  "type": "Feature",
  "properties": {
    "addr:full":"1316 Main Ave Durango CO 81301",
    "addr:housenumber":"1316",
    "addr:postcode":"co 81301",
    "addr:street":"Main Ave",
    "iso:country":"US",
    "sg:address":"1316 Main Ave",
    "sg:city":"Durango",
    "sg:classifiers":[
        {
            "category":"Shopping",
            "subcategory":"Clothing, Apparel, & Fashions",
            "type":"Retail Goods"
        }
    ],
    "sg:phone":"+1 970 247 2925",
    "sg:postcode":"81301",
    "sg:province":"CO",
    "sg:tags":[
        "merchandise"
    ],
    "wof:name":"Levis Outlet",
    "wof:placetype":"venue"
},
  "geometry": {"coordinates":[-107.878895,37.278577],"type":"Point"}
}