{
  "type": "Feature",
  "properties": {
    "addr:full":"3007 Zuni St Denver CO 80211",
    "addr:housenumber":"3007",
    "addr:postcode":"80211",
    "addr:street":"Zuni St",
    "iso:country":"US",
    "sg:address":"3007 Zuni St",
    "sg:city":"Denver",
    "sg:classifiers":[
        {
            "category":"Food & Beverages",
            "subcategory":"Bakery",
            "type":"Retail Goods"
        }
    ],
    "sg:phone":"+1 303 458 9999",
    "sg:postcode":"80211",
    "sg:province":"CO",
    "sg:tags":[
        "sandwich"
    ],
    "sg:website":"www.zunikitchen.com",
    "wof:name":"Zuni Kitchen",
    "wof:placetype":"venue"
},
  "geometry": {"coordinates":[-105.01579,39.759723],"type":"Point"}
}