{
  "type": "Feature",
  "properties": {
    "addr:full":"7534 Copper Gulch Rd Cotopaxi CO 81223",
    "addr:housenumber":"7534",
    "addr:postcode":"81223",
    "addr:street":"Copper Gulch Rd",
    "iso:country":"US",
    "sg:address":"7534 Copper Gulch Rd",
    "sg:city":"Cotopaxi",
    "sg:classifiers":[
        {
            "category":"Building & Trades",
            "subcategory":"Construction",
            "type":"Services"
        }
    ],
    "sg:phone":"+1 719 942 3585",
    "sg:postcode":"81223",
    "sg:province":"CO",
    "sg:tags":[
        "house",
        "general",
        "contractor"
    ],
    "wof:name":"North Fork Construction",
    "wof:placetype":"venue"
},
  "geometry": {"coordinates":[-105.464567,38.364633],"type":"Point"}
}