{
  "type": "Feature",
  "properties": {
    "addr:full":"854 W Battlement Pkwy Parachute CO 81635",
    "addr:housenumber":"854",
    "addr:postcode":"81635",
    "addr:street":"W Battlement Pkwy",
    "iso:country":"US",
    "sg:address":"854 W Battlement Pkwy",
    "sg:city":"Parachute",
    "sg:classifiers":[
        {
            "category":"Professional",
            "type":"Services"
        }
    ],
    "sg:phone":"+1 970 285 9443",
    "sg:postcode":"81635",
    "sg:province":"CO",
    "sg:tags":[
        "establishment"
    ],
    "wof:name":"Golden Cllc",
    "wof:placetype":"venue"
},
  "geometry": {"coordinates":[-108.037102,39.44678],"type":"Point"}
}