{
  "type": "Feature",
  "properties": {
    "iso:country":"US",
    "sg:address":"8120 Sheridan Blvd",
    "sg:city":"Arvada",
    "sg:classifiers":[
        {
            "category":"Organizations",
            "subcategory":"Professional Association",
            "type":"Services"
        }
    ],
    "sg:phone":"+1 303 428 0479",
    "sg:postcode":"80003",
    "sg:province":"CO",
    "wof:name":"Reprographic Services Assn",
    "wof:placetype":"venue"
},
  "geometry": {"coordinates":[-105.053309,39.844357],"type":"Point"}
}