{
  "type": "Feature",
  "properties": {
    "iso:country":"US",
    "sg:address":"2390 S Delaware Street",
    "sg:city":"Denver",
    "sg:classifiers":[
        {
            "category":"Animal Shelter",
            "type":"Public Place"
        },
        {
            "category":"Shopping",
            "subcategory":"Pets & Pet Supplies",
            "type":"Retail Goods"
        },
        {
            "category":"Retail",
            "subcategory":"Animal Services",
            "type":"Services"
        }
    ],
    "sg:phone":"+1 303 744 6076",
    "sg:postcode":"80223",
    "sg:province":"CO",
    "sg:tags":[
        "store"
    ],
    "wof:name":"Animal Rescue & Adoption Society",
    "wof:placetype":"venue"
},
  "geometry": {"coordinates":[-104.992396,39.67337],"type":"Point"}
}