{
  "type": "Feature",
  "properties": {
    "addr:full":"2502 Meade Cir Colorado Springs CO 80907",
    "addr:housenumber":"2502",
    "addr:postcode":"80907",
    "addr:street":"Meade Cir",
    "iso:country":"US",
    "sg:address":"2502 Meade Cir",
    "sg:city":"Colorado Springs",
    "sg:classifiers":[
        {
            "category":"Building & Trades",
            "subcategory":"Construction",
            "type":"Services"
        },
        {
            "category":"Home & Garden",
            "subcategory":"Carpets & Floor Coverings",
            "type":"Retail Goods"
        }
    ],
    "sg:phone":"+1 719 477 0807",
    "sg:postcode":"80907",
    "sg:province":"CO",
    "sg:tags":[
        "material",
        "flooring",
        "contractor"
    ],
    "wof:name":"All Phase Commercial Flooring",
    "wof:placetype":"venue"
},
  "geometry": {"coordinates":[-104.801385,38.870608],"type":"Point"}
}