{
  "type": "Feature",
  "properties": {
    "addr:full":"2324 N Prospect St Colorado Springs CO 80907",
    "addr:housenumber":"2324",
    "addr:postcode":"80907",
    "addr:street":"N Prospect St",
    "iso:country":"US",
    "sg:address":"2324 N Prospect St",
    "sg:city":"Colorado Springs",
    "sg:classifiers":[
        {
            "category":"Building & Trades",
            "subcategory":"Landscaping Services",
            "type":"Services"
        }
    ],
    "sg:phone":"+1 719 634 1983",
    "sg:postcode":"80907",
    "sg:province":"CO",
    "wof:name":"Snyder Tree Service",
    "wof:placetype":"venue"
},
  "geometry": {"coordinates":[-104.809231,38.866869],"type":"Point"}
}