{
  "type": "Feature",
  "properties": {
    "iso:country":"US",
    "sg:address":"7083 Winona Ct",
    "sg:city":"Westminster",
    "sg:classifiers":[
        {
            "category":"Building & Trades",
            "subcategory":"Construction",
            "type":"Services"
        }
    ],
    "sg:phone":"+1 303 428 7168",
    "sg:postcode":"80030",
    "sg:province":"CO",
    "sg:tags":[
        "contractor"
    ],
    "wof:name":"Garcia Acoustical Ceilings",
    "wof:placetype":"venue"
},
  "geometry": {"coordinates":[-105.04708599999999,39.825813],"type":"Point"}
}