{
  "type": "Feature",
  "properties": {
    "iso:country":"US",
    "sg:address":"6909 S Holly Cir",
    "sg:city":"Centennial",
    "sg:classifiers":[
        {
            "category":"Real Estate",
            "subcategory":"Real Estate Agent",
            "type":"Services"
        }
    ],
    "sg:phone":"+1 303 471 5320",
    "sg:postcode":"80112",
    "sg:province":"CO",
    "wof:name":"Quest Real Estate Svc",
    "wof:placetype":"venue"
},
  "geometry": {"coordinates":[-104.92156300000001,39.59219],"type":"Point"}
}