{
  "type": "Feature",
  "properties": {
    "iso:country":"US",
    "sg:address":"13101 Broncos Pkwy",
    "sg:city":"Englewood",
    "sg:classifiers":[
        {
            "category":"Health Services",
            "subcategory":"Health Practitioner",
            "type":"Services"
        }
    ],
    "sg:phone":"+1 303 795 4956",
    "sg:postcode":"80112",
    "sg:province":"CO",
    "wof:name":"Coroners Office",
    "wof:placetype":"venue"
},
  "geometry": {"coordinates":[-104.840638,39.578695],"type":"Point"}
}