{
  "type": "Feature",
  "properties": {
    "addr:full":"1900 Remington St Fort Collins CO 80525",
    "addr:housenumber":"1900",
    "addr:postcode":"80525",
    "addr:street":"Remington St",
    "iso:country":"US",
    "sg:address":"1900 Remington St",
    "sg:city":"Fort Collins",
    "sg:classifiers":[
        {
            "category":"Social Services",
            "subcategory":"Child Care",
            "type":"Services"
        },
        {
            "category":"Education",
            "subcategory":"School",
            "type":"Public Place"
        }
    ],
    "sg:phone":"+1 970 224 4240",
    "sg:postcode":"80525",
    "sg:province":"CO",
    "sg:tags":[
        "day"
    ],
    "sg:website":"www.springcreekschool.com",
    "wof:name":"Spring Creek Country Day Sch",
    "wof:placetype":"venue"
},
  "geometry": {"coordinates":[-105.075523,40.560525],"type":"Point"}
}