{
  "type": "Feature",
  "properties": {
    "iso:country":"US",
    "sg:address":"555 S Saint Vrain Ave",
    "sg:city":"Estes Park",
    "sg:classifiers":[
        {
            "category":"Recreation",
            "subcategory":"Amusement Park",
            "type":"Entertainment"
        }
    ],
    "sg:phone":"+1 970 586 8625",
    "sg:postcode":"80517",
    "sg:province":"CO",
    "wof:name":"Estes Park Recreation Ctr",
    "wof:placetype":"venue"
},
  "geometry": {"coordinates":[-105.504715,40.369644],"type":"Point"}
}