{
  "type": "Feature",
  "properties": {
    "addr:full":"455 W Elkhorn Ave Estes Park CO 80517",
    "addr:housenumber":"455",
    "addr:postcode":"80517",
    "addr:street":"W Elkhorn Ave",
    "iso:country":"US",
    "sg:address":"455 W Elkhorn Ave",
    "sg:city":"Estes Park",
    "sg:classifiers":[
        {
            "category":"Personal",
            "subcategory":"Beauty Salon",
            "type":"Services"
        }
    ],
    "sg:phone":"+1 970 586 3585",
    "sg:postcode":"80517",
    "sg:province":"CO",
    "wof:name":"Pati's Hair Care",
    "wof:placetype":"venue"
},
  "geometry": {"coordinates":[-105.52985200000001,40.376408],"type":"Point"}
}