{
  "type": "Feature",
  "properties": {
    "addr:full":"3890 Federal Blvd Unit 1 Denver CO 80211",
    "addr:housenumber":"3890;1",
    "addr:postcode":"80211",
    "addr:street":"Federal Blvd Unit",
    "iso:country":"US",
    "sg:address":"3890 Federal Blvd Unit 1",
    "sg:city":"Denver",
    "sg:classifiers":[
        {
            "category":"Health Services",
            "subcategory":"Chiropractor",
            "type":"Services"
        }
    ],
    "sg:phone":"+1 303 455 2225",
    "sg:postcode":"80211",
    "sg:province":"CO",
    "sg:website":"www.denvercoloradochiropractic.com/",
    "wof:name":"Denver Chiropractic, LLC",
    "wof:placetype":"venue"
},
  "geometry": {"coordinates":[-105.02489799999999,39.770962],"type":"Point"}
}