{
  "type": "Feature",
  "properties": {
    "iso:country":"US",
    "sg:address":"2342 E Platte Ave",
    "sg:city":"Colorado Springs",
    "sg:classifiers":[
        {
            "category":"Wholesale",
            "subcategory":"Auto Parts",
            "type":"Manufacturing & Wholesale Goods"
        }
    ],
    "sg:phone":"+1 719 578 9121",
    "sg:postcode":"80909",
    "sg:province":"CO",
    "sg:tags":[
        "battery"
    ],
    "wof:name":"American Battery Corp",
    "wof:placetype":"venue"
},
  "geometry": {"coordinates":[-104.787279,38.837003],"type":"Point"}
}