{
  "type": "Feature",
  "properties": {
    "iso:country":"US",
    "sg:address":"8511 N Co Rd 27",
    "sg:city":"Loveland",
    "sg:classifiers":[
        {
            "category":"Personal",
            "subcategory":"Beauty Salon",
            "type":"Services"
        }
    ],
    "sg:phone":"+1 970 663 4015",
    "sg:postcode":"80538",
    "sg:province":"CO",
    "sg:tags":[
        "manicuring"
    ],
    "wof:name":"Nail Elegance & Hair Salon",
    "wof:placetype":"venue"
},
  "geometry": {"coordinates":[-105.213364,40.481609],"type":"Point"}
}