{
  "type": "Feature",
  "properties": {
    "iso:country":"US",
    "sg:address":"7200 W Alameda Ave",
    "sg:city":"Lakewood",
    "sg:classifiers":[
        {
            "category":"Personal",
            "subcategory":"Beauty Salon",
            "type":"Services"
        }
    ],
    "sg:phone":"+1 303 922 3714",
    "sg:postcode":"80226",
    "sg:province":"CO",
    "wof:name":"Fantastic Sam's",
    "wof:placetype":"venue"
},
  "geometry": {"coordinates":[-105.079778,39.711019],"type":"Point"}
}