{
  "type": "Feature",
  "properties": {
    "iso:country":"US",
    "sg:address":"320 S Hazel Ct",
    "sg:city":"Denver",
    "sg:classifiers":[
        {
            "category":"Wholesale",
            "subcategory":"Groceries",
            "type":"Manufacturing & Wholesale Goods"
        }
    ],
    "sg:phone":"+1 303 727 1111",
    "sg:postcode":"80219",
    "sg:province":"CO",
    "sg:tags":[
        "food"
    ],
    "wof:name":"Wahoh Wholesale",
    "wof:placetype":"venue"
},
  "geometry": {"coordinates":[-105.027462,39.71065],"type":"Point"}
}