{
  "type": "Feature",
  "properties": {
    "iso:country":"US",
    "sg:address":"23200 Horsefly Rd",
    "sg:city":"Montrose",
    "sg:classifiers":[
        {
            "category":"Recreation",
            "type":"Entertainment"
        }
    ],
    "sg:phone":"+1 970 641 3381",
    "sg:postcode":"81401",
    "sg:province":"CO",
    "sg:tags":[
        "guide"
    ],
    "wof:name":"High Country Outfitters Inc",
    "wof:placetype":"venue"
},
  "geometry": {"coordinates":[-107.817037,38.346173],"type":"Point"}
}