{
  "type": "Feature",
  "properties": {
    "iso:country":"US",
    "sg:address":"86 N Center St",
    "sg:city":"Rock Springs",
    "sg:classifiers":[
        {
            "category":"Autos & Motor Vehicles",
            "subcategory":"Fuel & Gas Station",
            "type":"Retail Goods"
        },
        {
            "category":"Retail",
            "subcategory":"Auto Repair",
            "type":"Services"
        }
    ],
    "sg:phone":"+1 307 362 6901",
    "sg:postcode":"82901",
    "sg:province":"CO",
    "sg:tags":[
        "gasoline",
        "station",
        "wrecker"
    ],
    "wof:name":"Center Street Svc",
    "wof:placetype":"venue"
},
  "geometry": {"coordinates":[-109.225373,41.587951],"type":"Point"}
}