{
  "type": "Feature",
  "properties": {
    "iso:country":"US",
    "sg:address":"1414 S 21st St",
    "sg:city":"Colorado Springs",
    "sg:classifiers":[
        {
            "category":"Shopping",
            "subcategory":"Clothing, Apparel, & Fashions",
            "type":"Retail Goods"
        }
    ],
    "sg:phone":"+1 719 227 7467",
    "sg:postcode":"80904",
    "sg:province":"CO",
    "wof:name":"Uniform Shop",
    "wof:placetype":"venue"
},
  "geometry": {"coordinates":[-104.859177,38.832891],"type":"Point"}
}