{
  "type": "Feature",
  "properties": {
    "iso:country":"US",
    "sg:address":"1100 Patterson Rd",
    "sg:city":"Grand Junction",
    "sg:classifiers":[
        {
            "category":"Health Services",
            "subcategory":"Health Practitioner",
            "type":"Services"
        }
    ],
    "sg:phone":"+1 970 244 6100",
    "sg:postcode":"81506",
    "sg:province":"CO",
    "sg:tags":[
        "therapist",
        "physical"
    ],
    "wof:name":"St Mary's Life Ctr",
    "wof:placetype":"venue"
},
  "geometry": {"coordinates":[-108.552353,39.091854],"type":"Point"}
}