{
  "type": "Feature",
  "properties": {
    "addr:full":"3618 E Uintah St Colorado Springs CO 80909",
    "addr:housenumber":"3618",
    "addr:postcode":"80909",
    "addr:street":"E Uintah St",
    "iso:country":"US",
    "sg:address":"3618 E Uintah St",
    "sg:city":"Colorado Springs",
    "sg:classifiers":[
        {
            "category":"Real Estate",
            "subcategory":"Real Estate Operator",
            "type":"Services"
        }
    ],
    "sg:phone":"+1 719 596 2156",
    "sg:postcode":"80909",
    "sg:province":"CO",
    "sg:tags":[
        "building",
        "apartment"
    ],
    "wof:name":"Birchwood Village",
    "wof:placetype":"venue"
},
  "geometry": {"coordinates":[-104.760232,38.848531],"type":"Point"}
}