{
  "type": "Feature",
  "properties": {
    "iso:country":"US",
    "sg:address":"10115 W Washburn Way",
    "sg:city":"Denver",
    "sg:classifiers":[
        {
            "category":"Professional",
            "subcategory":"Management & Consulting",
            "type":"Services"
        }
    ],
    "sg:phone":"+1 303 988 0976",
    "sg:postcode":"80227",
    "sg:province":"CO",
    "sg:tags":[
        "consultant",
        "business"
    ],
    "wof:name":"Pappas Consulting",
    "wof:placetype":"venue"
},
  "geometry": {"coordinates":[-105.11111200000001,39.6664],"type":"Point"}
}