{
  "type": "Feature",
  "properties": {
    "addr:full":"112 E 31st St Durango CO 81301",
    "addr:housenumber":"112",
    "addr:postcode":"co 81301",
    "addr:street":"E 31St St",
    "iso:country":"US",
    "sg:address":"112 E 31st St",
    "sg:city":"Durango",
    "sg:classifiers":[
        {
            "category":"Building & Trades",
            "subcategory":"Landscaping Services",
            "type":"Services"
        }
    ],
    "sg:phone":"+1 970 382 8649",
    "sg:postcode":"81301",
    "sg:province":"CO",
    "wof:name":"Columbine Landscapes",
    "wof:placetype":"venue"
},
  "geometry": {"coordinates":[-107.870239,37.298746],"type":"Point"}
}