{
  "type": "Feature",
  "properties": {
    "addr:full":"2730 S Wadsworth Blvd Denver CO 80227",
    "addr:housenumber":"2730",
    "addr:postcode":"80227",
    "addr:street":"S Wadsworth Blvd",
    "iso:country":"US",
    "sg:address":"2730 S Wadsworth Blvd",
    "sg:city":"Denver",
    "sg:classifiers":[
        {
            "category":"Real Estate",
            "subcategory":"Real Estate Services",
            "type":"Services"
        }
    ],
    "sg:phone":"+1 303 985 8099",
    "sg:postcode":"80227",
    "sg:province":"CO",
    "sg:tags":[
        "abstract",
        "title"
    ],
    "wof:name":"Frontier Title Llc",
    "wof:placetype":"venue"
},
  "geometry": {"coordinates":[-105.081378,39.666222],"type":"Point"}
}