{
  "type": "Feature",
  "properties": {
    "addr:full":"1101 Mountain Village Cir Steamboat Springs CO 80487",
    "addr:housenumber":"1101",
    "addr:postcode":"80487",
    "addr:street":"Mountain Village Cir",
    "iso:country":"US",
    "sg:address":"1101 Mountain Village Cir",
    "sg:city":"Steamboat Springs",
    "sg:classifiers":[
        {
            "category":"Real Estate",
            "subcategory":"Real Estate Agent",
            "type":"Services"
        }
    ],
    "sg:phone":"+1 970 870 1720",
    "sg:postcode":"80487",
    "sg:province":"CO",
    "wof:name":"Courm Real Estate",
    "wof:placetype":"venue"
},
  "geometry": {"coordinates":[-106.80713799999999,40.449286],"type":"Point"}
}