{
  "type": "Feature",
  "properties": {
    "iso:country":"US",
    "sg:address":"1331 E Colfax Ave",
    "sg:city":"Denver",
    "sg:classifiers":[
        {
            "category":"Education",
            "subcategory":"School",
            "type":"Public Place"
        }
    ],
    "sg:phone":"+1 303 837 0598",
    "sg:postcode":"80218",
    "sg:province":"CO",
    "sg:tags":[
        "university",
        "college"
    ],
    "wof:name":"Operation School Bell",
    "wof:placetype":"venue"
},
  "geometry": {"coordinates":[-104.971001,39.739899],"type":"Point"}
}