{
  "type": "Feature",
  "properties": {
    "addr:full":"12368 Whaley Rd Alamosa CO 81101",
    "addr:housenumber":"12368",
    "addr:postcode":"81101",
    "addr:street":"Whaley Rd",
    "iso:country":"US",
    "sg:address":"12368 Whaley Rd",
    "sg:city":"Alamosa",
    "sg:classifiers":[
        {
            "category":"Retail",
            "subcategory":"Repair Shop",
            "type":"Services"
        }
    ],
    "sg:phone":"+1 719 589 4443",
    "sg:postcode":"81101",
    "sg:province":"CO",
    "sg:tags":[
        "reupholstery",
        "upholsterer"
    ],
    "wof:name":"Monte Canvas & Upholstery Shop",
    "wof:placetype":"venue"
},
  "geometry": {"coordinates":[-105.813497,37.47074],"type":"Point"}
}