{
  "type": "Feature",
  "properties": {
    "iso:country":"US",
    "sg:address":"12000 Washington St",
    "sg:city":"Thornton",
    "sg:classifiers":[
        {
            "category":"Professional",
            "subcategory":"Lawyer & Legal Services",
            "type":"Services"
        }
    ],
    "sg:phone":"+1 303 457 2000",
    "sg:postcode":"80241",
    "sg:province":"CO",
    "sg:tags":[
        "attorney"
    ],
    "wof:name":"Solano Law Office",
    "wof:placetype":"venue"
},
  "geometry": {"coordinates":[-104.97782100000001,39.919353],"type":"Point"}
}