{
  "type": "Feature",
  "properties": {
    "iso:country":"US",
    "sg:address":"2715 S Prairie Ave",
    "sg:city":"Pueblo",
    "sg:classifiers":[
        {
            "category":"Insurance",
            "subcategory":"Insurance Agent",
            "type":"Services"
        }
    ],
    "sg:phone":"+1 719 566 3460",
    "sg:postcode":"81005",
    "sg:province":"CO",
    "wof:name":"Allstate Insurance",
    "wof:placetype":"venue"
},
  "geometry": {"coordinates":[-104.643772,38.224322],"type":"Point"}
}