{
  "type": "Feature",
  "properties": {
    "iso:country":"US",
    "sg:address":"414 W Pikes Peak Ave",
    "sg:city":"Colorado Springs",
    "sg:classifiers":[
        {
            "category":"Building & Trades",
            "subcategory":"Electrical",
            "type":"Services"
        }
    ],
    "sg:phone":"+1 719 473 1781",
    "sg:postcode":"80905",
    "sg:province":"CO",
    "sg:tags":[
        "electric",
        "contractor"
    ],
    "wof:name":"Colorado Springs ELEC Jatc",
    "wof:placetype":"venue"
},
  "geometry": {"coordinates":[-104.834109,38.834252],"type":"Point"}
}