{
  "type": "Feature",
  "properties": {
    "addr:full":"3652 W Seramonte Dr Littleton CO 80129",
    "addr:housenumber":"3652",
    "addr:postcode":"80129",
    "addr:street":"W Seramonte Dr",
    "iso:country":"US",
    "sg:address":"3652 W Seramonte Dr",
    "sg:city":"Littleton",
    "sg:classifiers":[
        {
            "category":"Shopping",
            "subcategory":"Catalog Store",
            "type":"Retail Goods"
        }
    ],
    "sg:phone":"+1 303 470 9584",
    "sg:postcode":"80129",
    "sg:province":"CO",
    "sg:tags":[
        "e"
    ],
    "wof:name":"Skate Mall",
    "wof:placetype":"venue"
},
  "geometry": {"coordinates":[-105.031074,39.534129],"type":"Point"}
}