{
  "type": "Feature",
  "properties": {
    "addr:full":"10333 E Colfax Ave Aurora CO 80010",
    "addr:housenumber":"10333",
    "addr:postcode":"80010",
    "addr:street":"E Colfax Ave",
    "iso:country":"US",
    "sg:address":"10333 E Colfax Ave",
    "sg:city":"Aurora",
    "sg:classifiers":[
        {
            "category":"Health Services",
            "subcategory":"Clinic",
            "type":"Services"
        }
    ],
    "sg:phone":"+1 720 858 9200",
    "sg:postcode":"80010",
    "sg:province":"CO",
    "sg:tags":[
        "home"
    ],
    "wof:name":"Artek Homecare",
    "wof:placetype":"venue"
},
  "geometry": {"coordinates":[-104.867368,39.740279],"type":"Point"}
}