{
  "type": "Feature",
  "properties": {
    "addr:full":"1850 28th St Boulder CO 80301",
    "addr:housenumber":"1850",
    "addr:postcode":"80301",
    "addr:street":"28Th St",
    "iso:country":"US",
    "sg:address":"1850 28th St",
    "sg:city":"Boulder",
    "sg:classifiers":[
        {
            "category":"Shopping",
            "subcategory":"Department Store",
            "type":"Retail Goods"
        }
    ],
    "sg:phone":"+1 303 442 8802",
    "sg:postcode":"80301",
    "sg:province":"CO",
    "wof:name":"Mervyns",
    "wof:placetype":"venue"
},
  "geometry": {"coordinates":[-105.258207,40.015122],"type":"Point"}
}