{
  "type": "Feature",
  "properties": {
    "iso:country":"US",
    "sg:address":"14300 E 35th Pl",
    "sg:city":"Aurora",
    "sg:classifiers":[
        {
            "category":"Airline",
            "type":"Transportation"
        }
    ],
    "sg:phone":"+1 303 371 4742",
    "sg:postcode":"80011",
    "sg:province":"CO",
    "sg:tags":[
        "scheduled",
        "arr",
        "freight",
        "air"
    ],
    "wof:name":"Aero Ground Inc",
    "wof:placetype":"venue"
},
  "geometry": {"coordinates":[-104.822126,39.769193],"type":"Point"}
}