{
  "type": "Feature",
  "properties": {
    "addr:full":"1285 S Telluride St Aurora CO 80017",
    "addr:housenumber":"1285",
    "addr:postcode":"80017",
    "addr:street":"S Telluride St",
    "iso:country":"US",
    "sg:address":"1285 S Telluride St",
    "sg:city":"Aurora",
    "sg:classifiers":[
        {
            "category":"Shopping",
            "subcategory":"Gifts & Souvenirs",
            "type":"Retail Goods"
        }
    ],
    "sg:phone":"+1 303 369 3921",
    "sg:postcode":"80017",
    "sg:province":"CO",
    "wof:name":"Trudie Adams",
    "wof:placetype":"venue"
},
  "geometry": {"coordinates":[-104.781108,39.693499],"type":"Point"}
}