{
  "type": "Feature",
  "properties": {
    "iso:country":"US",
    "sg:address":"67676 Osprey Ln",
    "sg:city":"Montrose",
    "sg:classifiers":[
        {
            "category":"Shopping",
            "subcategory":"Stationery & Office Supplies",
            "type":"Retail Goods"
        }
    ],
    "sg:phone":"+1 970 249 4557",
    "sg:postcode":"81401",
    "sg:province":"CO",
    "wof:name":"Adams Office Supply Inc",
    "wof:placetype":"venue"
},
  "geometry": {"coordinates":[-107.82351199999999,38.452193],"type":"Point"}
}