{
  "type": "Feature",
  "properties": {
    "iso:country":"US",
    "sg:address":"239 W 67th Ct",
    "sg:city":"Loveland",
    "sg:classifiers":[
        {
            "category":"Health Services",
            "subcategory":"Doctor",
            "type":"Services"
        }
    ],
    "sg:phone":"+1 970 461 1880",
    "sg:postcode":"80538",
    "sg:province":"CO",
    "sg:tags":[
        "clinic"
    ],
    "wof:name":"Greeley Medical Clinic",
    "wof:placetype":"venue"
},
  "geometry": {"coordinates":[-105.079808,40.461259],"type":"Point"}
}