{
  "type": "Feature",
  "properties": {
    "iso:country":"US",
    "sg:address":"8141 1st St",
    "sg:city":"Wellington",
    "sg:classifiers":[
        {
            "category":"Building & Trades",
            "subcategory":"Equipment Rental",
            "type":"Services"
        }
    ],
    "sg:phone":"+1 970 568 0078",
    "sg:postcode":"80549",
    "sg:province":"CO",
    "sg:tags":[
        "contractor"
    ],
    "wof:name":"Best Rental Inc",
    "wof:placetype":"venue"
},
  "geometry": {"coordinates":[-105.00767,40.70378],"type":"Point"}
}