{
  "type": "Feature",
  "properties": {
    "iso:country":"US",
    "sg:address":"8547 E Costilla Ave",
    "sg:city":"Englewood",
    "sg:classifiers":[
        {
            "category":"Professional",
            "type":"Services"
        }
    ],
    "sg:phone":"+1 303 773 6351",
    "sg:postcode":"80112",
    "sg:province":"CO",
    "wof:name":"Brian Mackinnon",
    "wof:placetype":"venue"
},
  "geometry": {"coordinates":[-104.89161300000001,39.592039],"type":"Point"}
}