{
  "type": "Feature",
  "properties": {
    "addr:full":"221 N Kuner Rd Brighton CO 80601",
    "addr:housenumber":"221",
    "addr:postcode":"80601",
    "addr:street":"N Kuner Rd",
    "iso:country":"US",
    "sg:address":"221 N Kuner Rd",
    "sg:city":"Brighton",
    "sg:classifiers":[
        {
            "category":"Professional",
            "type":"Services"
        }
    ],
    "sg:phone":"+1 303 655 0379",
    "sg:postcode":"80601",
    "sg:province":"CO",
    "sg:tags":[
        "establishment"
    ],
    "wof:name":"S-Square Tube Products",
    "wof:placetype":"venue"
},
  "geometry": {"coordinates":[-104.823261,39.989928],"type":"Point"}
}