{
  "type": "Feature",
  "properties": {
    "iso:country":"US",
    "sg:address":"1301 Speer Blvd",
    "sg:city":"Denver",
    "sg:classifiers":[
        {
            "category":"Real Estate",
            "subcategory":"Real Estate Agent",
            "type":"Services"
        }
    ],
    "sg:phone":"+1 303 480 1580",
    "sg:postcode":"80204",
    "sg:province":"CO",
    "wof:name":"Bob Leino Realty",
    "wof:placetype":"venue"
},
  "geometry": {"coordinates":[-104.997646,39.738457],"type":"Point"}
}