{
  "type": "Feature",
  "properties": {
    "iso:country":"US",
    "sg:address":"112 S Pikes Peak Ave",
    "sg:city":"Florence",
    "sg:classifiers":[
        {
            "category":"Shopping",
            "subcategory":"Computers & Home Electronics",
            "type":"Retail Goods"
        }
    ],
    "sg:phone":"+1 719 784 3222",
    "sg:postcode":"81226",
    "sg:province":"CO",
    "sg:tags":[
        "equipment",
        "satellite",
        "system"
    ],
    "wof:name":"Florence TV & VCR Repair",
    "wof:placetype":"venue"
},
  "geometry": {"coordinates":[-105.117884,38.389835],"type":"Point"}
}