{
  "type": "Feature",
  "properties": {
    "addr:full":"9085 E Mineral Cir Centennial CO 80112",
    "addr:housenumber":"9085",
    "addr:postcode":"80112",
    "addr:street":"E Mineral Cir",
    "iso:country":"US",
    "sg:address":"9085 E Mineral Cir",
    "sg:city":"Centennial",
    "sg:classifiers":[
        {
            "category":"Utilities",
            "subcategory":"Cable",
            "type":"Services"
        }
    ],
    "sg:phone":"+1 303 705 3500",
    "sg:postcode":"80112",
    "sg:province":"CO",
    "sg:tags":[
        "television"
    ],
    "wof:name":"Comcast Cable",
    "wof:placetype":"venue"
},
  "geometry": {"coordinates":[-104.88394599999999,39.576157],"type":"Point"}
}