{
  "type": "Feature",
  "properties": {
    "addr:full":"2101 Ken Pratt Blvd Longmont CO 80501",
    "addr:housenumber":"2101",
    "addr:postcode":"80501",
    "addr:street":"Ken Pratt Blvd",
    "iso:country":"US",
    "sg:address":"2101 Ken Pratt Blvd",
    "sg:city":"Longmont",
    "sg:classifiers":[
        {
            "category":"Professional",
            "subcategory":"Accounting & Tax Preparation",
            "type":"Services"
        }
    ],
    "sg:phone":"+1 303 678 7819",
    "sg:postcode":"80501",
    "sg:province":"CO",
    "sg:tags":[
        "return",
        "filing"
    ],
    "wof:name":"H & R Block Premium Tax Svc",
    "wof:placetype":"venue"
},
  "geometry": {"coordinates":[-105.130673,40.152417],"type":"Point"}
}