{
  "type": "Feature",
  "properties": {
    "addr:full":"6456 Pierson St Arvada CO 80004",
    "addr:housenumber":"6456",
    "addr:postcode":"80004",
    "addr:street":"Pierson St",
    "iso:country":"US",
    "sg:address":"6456 Pierson St",
    "sg:city":"Arvada",
    "sg:classifiers":[
        {
            "category":"Building & Trades",
            "subcategory":"Plumbing",
            "type":"Services"
        }
    ],
    "sg:phone":"+1 303 425 6838",
    "sg:postcode":"80004",
    "sg:province":"CO",
    "sg:tags":[
        "contractor"
    ],
    "wof:name":"Sprinkler Service Specialists",
    "wof:placetype":"venue"
},
  "geometry": {"coordinates":[-105.12187900000001,39.814862],"type":"Point"}
}