{
  "type": "Feature",
  "properties": {
    "addr:full":"5879 Palmer Park Blvd Colorado Springs CO 80915",
    "addr:housenumber":"5879",
    "addr:postcode":"80915",
    "addr:street":"Palmer Park Blvd",
    "iso:country":"US",
    "sg:address":"5879 Palmer Park Blvd",
    "sg:city":"Colorado Springs",
    "sg:classifiers":[
        {
            "category":"Personal",
            "type":"Services"
        }
    ],
    "sg:phone":"+1 719 638 8030",
    "sg:postcode":"80915",
    "sg:province":"CO",
    "sg:tags":[
        "therapist",
        "massage"
    ],
    "wof:name":"Fuji Oriental Massage Therapy",
    "wof:placetype":"venue"
},
  "geometry": {"coordinates":[-104.718802,38.857012],"type":"Point"}
}