{
  "type": "Feature",
  "properties": {
    "iso:country":"US",
    "sg:address":"16755 Eastonville Rd",
    "sg:city":"Elbert",
    "sg:classifiers":[
        {
            "category":"Building & Trades",
            "subcategory":"Construction",
            "type":"Services"
        }
    ],
    "sg:phone":"+1 719 494 0476",
    "sg:postcode":"80106",
    "sg:province":"CO",
    "sg:tags":[
        "excavation",
        "contractor"
    ],
    "wof:name":"Norvell Excavating",
    "wof:placetype":"venue"
},
  "geometry": {"coordinates":[-104.570905,39.074623],"type":"Point"}
}