{
  "type": "Feature",
  "properties": {
    "addr:full":"2963 North Ave Grand Junction CO 81504",
    "addr:housenumber":"2963",
    "addr:postcode":"81504",
    "addr:street":"North Ave",
    "iso:country":"US",
    "sg:address":"2963 North Ave",
    "sg:city":"Grand Junction",
    "sg:classifiers":[
        {
            "category":"Home & Garden",
            "subcategory":"Building Materials",
            "type":"Retail Goods"
        }
    ],
    "sg:phone":"+1 970 242 4982",
    "sg:postcode":"81504",
    "sg:province":"CO",
    "wof:name":"True Value",
    "wof:placetype":"venue"
},
  "geometry": {"coordinates":[-108.50454000000001,39.077321],"type":"Point"}
}