{
  "type": "Feature",
  "properties": {
    "addr:full":"19105 Greenbrier Ln Monument CO 80132",
    "addr:housenumber":"19105",
    "addr:postcode":"80132",
    "addr:street":"Greenbrier Ln",
    "iso:country":"US",
    "sg:address":"19105 Greenbrier Ln",
    "sg:city":"Monument",
    "sg:classifiers":[
        {
            "category":"Restaurant",
            "type":"Food & Drink"
        }
    ],
    "sg:phone":"+1 719 481 8464",
    "sg:postcode":"80132",
    "sg:province":"CO",
    "sg:tags":[
        "eating"
    ],
    "wof:name":"McDonalds",
    "wof:placetype":"venue"
},
  "geometry": {"coordinates":[-104.83599,39.10796],"type":"Point"}
}