{
  "type": "Feature",
  "properties": {
    "iso:country":"US",
    "sg:address":"425 Wilcox St",
    "sg:city":"Castle Rock",
    "sg:classifiers":[
        {
            "category":"Banks & Credit Unions",
            "subcategory":"Bank",
            "type":"Services"
        }
    ],
    "sg:phone":"+1 303 663 4526",
    "sg:postcode":"80104",
    "sg:province":"CO",
    "sg:tags":[
        "mortgage"
    ],
    "sg:website":"www.imperiallending.com",
    "wof:name":"Imperial Lending",
    "wof:placetype":"venue"
},
  "geometry": {"coordinates":[-104.860074,39.373579],"type":"Point"}
}