{
  "type": "Feature",
  "properties": {
    "iso:country":"US",
    "sg:address":"3117 San Luis Dr",
    "sg:city":"Colorado Springs",
    "sg:classifiers":[
        {
            "category":"Mining & Drilling",
            "type":"Manufacturing & Wholesale Goods"
        }
    ],
    "sg:phone":"+1 719 596 7506",
    "sg:postcode":"80909",
    "sg:province":"CO",
    "sg:tags":[
        "crude",
        "production",
        "gas"
    ],
    "wof:name":"Adobe Oil and Gas",
    "wof:placetype":"venue"
},
  "geometry": {"coordinates":[-104.770447,38.867218],"type":"Point"}
}