{
  "type": "Feature",
  "properties": {
    "addr:full":"802 Grand Ave Glenwood Springs CO 81601",
    "addr:housenumber":"802",
    "addr:postcode":"81601",
    "addr:street":"Grand Ave",
    "iso:country":"US",
    "sg:address":"802 Grand Ave",
    "sg:city":"Glenwood Springs",
    "sg:classifiers":[
        {
            "category":"Shopping",
            "subcategory":"Computers & Home Electronics",
            "type":"Retail Goods"
        }
    ],
    "sg:phone":"+1 970 928 2100",
    "sg:postcode":"81601",
    "sg:province":"CO",
    "sg:tags":[
        "software"
    ],
    "sg:website":"www.aspenres.com",
    "wof:name":"Aspen Research Group",
    "wof:placetype":"venue"
},
  "geometry": {"coordinates":[-107.32467,39.546688],"type":"Point"}
}