{
  "type": "Feature",
  "properties": {
    "addr:full":"1225 E Hampden Ave Englewood CO 80113",
    "addr:housenumber":"1225",
    "addr:postcode":"80113",
    "addr:street":"E Hampden Ave",
    "iso:country":"US",
    "sg:address":"1225 E Hampden Ave",
    "sg:city":"Englewood",
    "sg:classifiers":[
        {
            "category":"Restaurant",
            "type":"Food & Drink"
        }
    ],
    "sg:phone":"+1 303 806 9354",
    "sg:postcode":"80113",
    "sg:province":"CO",
    "sg:tags":[
        "cafe"
    ],
    "wof:name":"Bangkok Cafe",
    "wof:placetype":"venue"
},
  "geometry": {"coordinates":[-104.972565,39.653198],"type":"Point"}
}