{
  "type": "Feature",
  "properties": {
    "addr:full":"6530 S Academy Blvd Colorado Springs CO 80906",
    "addr:housenumber":"6530",
    "addr:postcode":"80906",
    "addr:street":"S Academy Blvd",
    "iso:country":"US",
    "sg:address":"6530 S Academy Blvd",
    "sg:city":"Colorado Springs",
    "sg:classifiers":[
        {
            "category":"Personal",
            "subcategory":"Beauty Salon",
            "type":"Services"
        }
    ],
    "sg:phone":"+1 719 226 6747",
    "sg:postcode":"80906",
    "sg:province":"CO",
    "sg:tags":[
        "manicuring"
    ],
    "wof:name":"New York New York Nail Salon",
    "wof:placetype":"venue"
},
  "geometry": {"coordinates":[-104.809241,38.765814],"type":"Point"}
}