{
  "type": "Feature",
  "properties": {
    "iso:country":"US",
    "sg:address":"7300 E Harvard Ave",
    "sg:city":"Denver",
    "sg:classifiers":[
        {
            "category":"Real Estate",
            "subcategory":"Real Estate Operator",
            "type":"Services"
        }
    ],
    "sg:phone":"+1 303 750 0660",
    "sg:postcode":"80231",
    "sg:province":"CO",
    "sg:tags":[
        "apartment"
    ],
    "wof:name":"Timberline Apartments",
    "wof:placetype":"venue"
},
  "geometry": {"coordinates":[-104.90116,39.671227],"type":"Point"}
}