{
  "type": "Feature",
  "properties": {
    "iso:country":"US",
    "sg:address":"189 Ten Mile Cir",
    "sg:city":"Frisco",
    "sg:classifiers":[
        {
            "category":"Shopping",
            "type":"Retail Goods"
        }
    ],
    "sg:phone":"+1 970 968 2565",
    "sg:postcode":"80443",
    "sg:province":"CO",
    "sg:tags":[
        "art",
        "gallery",
        "dealer"
    ],
    "wof:name":"Galleria Eclectica",
    "wof:placetype":"venue"
},
  "geometry": {"coordinates":[-106.15359599999999,39.500833],"type":"Point"}
}