{
  "type": "Feature",
  "properties": {
    "iso:country":"US",
    "sg:address":"8350 E Yale Avenue Ofc",
    "sg:city":"Denver",
    "sg:classifiers":[
        {
            "category":"Real Estate",
            "subcategory":"Real Estate Operator",
            "type":"Services"
        }
    ],
    "sg:phone":"+1 303 337 0001",
    "sg:postcode":"80231",
    "sg:province":"CO",
    "sg:tags":[
        "apartment"
    ],
    "wof:name":"Fox Crossing Apartments",
    "wof:placetype":"venue"
},
  "geometry": {"coordinates":[-104.891707,39.668653],"type":"Point"}
}