{
  "type": "Feature",
  "properties": {
    "iso:country":"US",
    "sg:address":"10881 W Asbury Ave",
    "sg:city":"Denver",
    "sg:classifiers":[
        {
            "category":"Professional",
            "subcategory":"Testing Lab",
            "type":"Services"
        },
        {
            "category":"Professional",
            "subcategory":"Engineering",
            "type":"Services"
        }
    ],
    "sg:phone":"+1 720 962 8688",
    "sg:postcode":"80227",
    "sg:province":"CO",
    "sg:tags":[
        "consultant",
        "forensic",
        "architectural"
    ],
    "wof:name":"WISS Janney Elstner Assoc Inc",
    "wof:placetype":"venue"
},
  "geometry": {"coordinates":[-105.12017400000001,39.680488],"type":"Point"}
}