{
  "type": "Feature",
  "properties": {
    "iso:country":"US",
    "sg:address":"2350 Ogden St",
    "sg:city":"Denver",
    "sg:classifiers":[
        {
            "category":"Manufacturing",
            "subcategory":"Printing",
            "type":"Manufacturing & Wholesale Goods"
        }
    ],
    "sg:phone":"+1 303 832 6658",
    "sg:postcode":"80205",
    "sg:province":"CO",
    "sg:tags":[
        "lithographic",
        "commercial"
    ],
    "wof:name":"Cire Printing & Promos",
    "wof:placetype":"venue"
},
  "geometry": {"coordinates":[-104.97448900000001,39.751348],"type":"Point"}
}