{
  "type": "Feature",
  "properties": {
    "iso:country":"US",
    "sg:address":"2320 E Main St",
    "sg:city":"Montrose",
    "sg:classifiers":[
        {
            "category":"Home & Garden",
            "subcategory":"Carpets & Floor Coverings",
            "type":"Retail Goods"
        }
    ],
    "sg:phone":"+1 970 240 0790",
    "sg:postcode":"81401",
    "sg:province":"CO",
    "sg:tags":[
        "dealer",
        "rug"
    ],
    "wof:name":"Mountain Design Ctr",
    "wof:placetype":"venue"
},
  "geometry": {"coordinates":[-107.85382799999999,38.488353],"type":"Point"}
}