{
  "type": "Feature",
  "properties": {
    "addr:full":"8180 Syracuse St Commerce City CO 80022",
    "addr:housenumber":"8180",
    "addr:postcode":"80022",
    "addr:street":"Syracuse St",
    "iso:country":"US",
    "sg:address":"8180 Syracuse St",
    "sg:city":"Commerce City",
    "sg:classifiers":[
        {
            "category":"Freight",
            "type":"Transportation"
        }
    ],
    "sg:phone":"+1 303 288 0912",
    "sg:postcode":"80022",
    "sg:province":"CO",
    "sg:tags":[
        "trucking"
    ],
    "wof:name":"John W Witt Trucking",
    "wof:placetype":"venue"
},
  "geometry": {"coordinates":[-104.89841800000001,39.844589],"type":"Point"}
}