{
  "type": "Feature",
  "properties": {
    "addr:full":"205 3rd St Paonia CO 81428",
    "addr:housenumber":"205",
    "addr:postcode":"81428",
    "addr:street":"3Rd St",
    "iso:country":"US",
    "sg:address":"205 3rd St",
    "sg:city":"Paonia",
    "sg:classifiers":[
        {
            "category":"Organizations",
            "subcategory":"Non-profit Organization",
            "type":"Services"
        }
    ],
    "sg:phone":"+1 970 527 4397",
    "sg:postcode":"81428",
    "sg:province":"CO",
    "wof:name":"Fire Of Truth Satsanga",
    "wof:placetype":"venue"
},
  "geometry": {"coordinates":[-107.59779,38.86848],"type":"Point"}
}