{
  "type": "Feature",
  "properties": {
    "addr:full":"2148 75th St Boulder CO 80301",
    "addr:housenumber":"2148",
    "addr:postcode":"80301",
    "addr:street":"75Th St",
    "iso:country":"US",
    "sg:address":"2148 75th St",
    "sg:city":"Boulder",
    "sg:phone":"+1 303 442 2332",
    "sg:postcode":"80301",
    "sg:province":"CO",
    "sg:tags":[
        "farm"
    ],
    "wof:name":"Alan Patrick",
    "wof:placetype":"venue"
},
  "geometry": {"coordinates":[-105.178324,40.021079],"type":"Point"}
}