{
  "type": "Feature",
  "properties": {
    "iso:country":"US",
    "sg:address":"2502 Co Rd 61",
    "sg:city":"Center",
    "sg:classifiers":[
        {
            "category":"Building & Trades",
            "subcategory":"Equipment Rental",
            "type":"Services"
        }
    ],
    "sg:phone":"+1 719 378 2271",
    "sg:postcode":"81125",
    "sg:province":"CO",
    "sg:tags":[
        "aircraft",
        "leasing",
        "charter"
    ],
    "sg:website":"www.ufowatchtower.com",
    "wof:name":"UFO Watchtower",
    "wof:placetype":"venue"
},
  "geometry": {"coordinates":[-105.89169099999999,37.778641],"type":"Point"}
}