{
  "type": "Feature",
  "properties": {
    "addr:full":"2603 Wakonda Dr Fort Collins CO 80521",
    "addr:housenumber":"2603",
    "addr:postcode":"80521",
    "addr:street":"Wakonda Dr",
    "iso:country":"US",
    "sg:address":"2603 Wakonda Dr",
    "sg:city":"Fort Collins",
    "sg:classifiers":[
        {
            "category":"Personal",
            "type":"Services"
        }
    ],
    "sg:phone":"+1 970 231 9859",
    "sg:postcode":"80521",
    "sg:province":"CO",
    "sg:tags":[
        "therapist",
        "massage"
    ],
    "wof:name":"Neuromuscular Therapeutic",
    "wof:placetype":"venue"
},
  "geometry": {"coordinates":[-105.125863,40.604693],"type":"Point"}
}