{
  "type": "Feature",
  "properties": {
    "addr:full":"183 Gore Creek Dr Vail CO 81657",
    "addr:housenumber":"183",
    "addr:postcode":"81657",
    "addr:street":"Gore Creek Dr",
    "iso:country":"US",
    "sg:address":"183 Gore Creek Dr",
    "sg:city":"Vail",
    "sg:classifiers":[
        {
            "category":"Shopping",
            "subcategory":"Clothing, Apparel, & Fashions",
            "type":"Retail Goods"
        }
    ],
    "sg:phone":"+1 970 479 0050",
    "sg:postcode":"81657",
    "sg:province":"CO",
    "wof:name":"Luca Bruno Inc",
    "wof:placetype":"venue"
},
  "geometry": {"coordinates":[-106.37506999999999,39.640726],"type":"Point"}
}