{
  "type": "Feature",
  "properties": {
    "iso:country":"US",
    "sg:address":"2255 S Broadway",
    "sg:city":"Denver",
    "sg:classifiers":[
        {
            "category":"Professional",
            "subcategory":"Employment Agencies",
            "type":"Services"
        }
    ],
    "sg:phone":"+1 303 321 0022",
    "sg:postcode":"80210",
    "sg:province":"CO",
    "sg:tags":[
        "medical",
        "temporary",
        "staffing"
    ],
    "wof:name":"A Plus Medical Staffing LLC",
    "wof:placetype":"venue"
},
  "geometry": {"coordinates":[-104.987649,39.67589],"type":"Point"}
}