{
  "type": "Feature",
  "properties": {
    "iso:country":"US",
    "sg:address":"1419 Main St",
    "sg:city":"Alamosa",
    "sg:classifiers":[
        {
            "category":"Restaurant",
            "type":"Food & Drink"
        }
    ],
    "sg:phone":"+1 719 589 3039",
    "sg:postcode":"81101",
    "sg:province":"CO",
    "sg:tags":[
        "pizza"
    ],
    "wof:name":"Pizza Den & Pasta",
    "wof:placetype":"venue"
},
  "geometry": {"coordinates":[-105.87746,37.468249],"type":"Point"}
}