{
  "type": "Feature",
  "properties": {
    "iso:country":"US",
    "sg:address":"8594 W Fairview Dr",
    "sg:city":"Littleton",
    "sg:classifiers":[
        {
            "category":"Building & Trades",
            "subcategory":"Construction",
            "type":"Services"
        }
    ],
    "sg:phone":"+1 303 932 1660",
    "sg:postcode":"80128",
    "sg:province":"CO",
    "sg:tags":[
        "house"
    ],
    "wof:name":"Big Mountain Builders LLC",
    "wof:placetype":"venue"
},
  "geometry": {"coordinates":[-105.095057,39.578181],"type":"Point"}
}