{
  "type": "Feature",
  "properties": {
    "iso:country":"US",
    "sg:address":"5177 Hwy 86",
    "sg:city":"Elizabeth",
    "sg:classifiers":[
        {
            "category":"Retail",
            "subcategory":"Repair Shop",
            "type":"Services"
        }
    ],
    "sg:phone":"+1 303 646 4142",
    "sg:postcode":"80107",
    "sg:province":"CO",
    "sg:tags":[
        "repairing",
        "lawn",
        "mower"
    ],
    "wof:name":"Cliff's One Stop",
    "wof:placetype":"venue"
},
  "geometry": {"coordinates":[-104.568625,39.361276],"type":"Point"}
}