{
  "type": "Feature",
  "properties": {
    "addr:full":"190 Shady Hollow Nederland CO 80466",
    "addr:housenumber":"190",
    "addr:postcode":"80466",
    "addr:street":"Shady",
    "iso:country":"US",
    "sg:address":"190 Shady Hollow",
    "sg:city":"Nederland",
    "sg:classifiers":[
        {
            "category":"Home & Garden",
            "subcategory":"Home Furnishings",
            "type":"Retail Goods"
        }
    ],
    "sg:phone":"+1 303 258 9649",
    "sg:postcode":"80466",
    "sg:province":"CO",
    "wof:name":"Pats Draperies & Decor",
    "wof:placetype":"venue"
},
  "geometry": {"coordinates":[-105.448138,39.991248],"type":"Point"}
}