{
  "type": "Feature",
  "properties": {
    "addr:full":"10610 W Cooper Pl Littleton CO 80127",
    "addr:housenumber":"10610",
    "addr:postcode":"80127",
    "addr:street":"W Cooper Pl",
    "iso:country":"US",
    "sg:address":"10610 W Cooper Pl",
    "sg:city":"Littleton",
    "sg:classifiers":[
        {
            "category":"Wholesale",
            "subcategory":"Furniture",
            "type":"Manufacturing & Wholesale Goods"
        }
    ],
    "sg:phone":"+1 303 971 0553",
    "sg:postcode":"80127",
    "sg:province":"CO",
    "sg:tags":[
        "comp",
        "electronics"
    ],
    "sg:website":"www.ossc-inc.com",
    "wof:name":"Office Space Saving Concepts",
    "wof:placetype":"venue"
},
  "geometry": {"coordinates":[-105.116545,39.595613],"type":"Point"}
}