{
  "type": "Feature",
  "properties": {
    "iso:country":"US",
    "sg:address":"333 W Drake Rd",
    "sg:city":"Fort Collins",
    "sg:classifiers":[
        {
            "category":"Health Services",
            "subcategory":"Doctor",
            "type":"Services"
        }
    ],
    "sg:phone":"+1 970 223 6100",
    "sg:postcode":"80526",
    "sg:province":"CO",
    "sg:tags":[
        "dentist"
    ],
    "wof:name":"Associates In Family Dentistry",
    "wof:placetype":"venue"
},
  "geometry": {"coordinates":[-105.080258,40.552524],"type":"Point"}
}