{
  "type": "Feature",
  "properties": {
    "iso:country":"US",
    "sg:address":"1575 S Birch St",
    "sg:city":"Denver",
    "sg:classifiers":[
        {
            "category":"Wholesale",
            "subcategory":"Plants",
            "type":"Manufacturing & Wholesale Goods"
        }
    ],
    "sg:phone":"+1 303 758 9479",
    "sg:postcode":"80222",
    "sg:province":"CO",
    "sg:tags":[
        "product",
        "nursery"
    ],
    "wof:name":"Green Screenery",
    "wof:placetype":"venue"
},
  "geometry": {"coordinates":[-104.936078,39.688952],"type":"Point"}
}