{
  "type": "Feature",
  "properties": {
    "iso:country":"US",
    "sg:address":"23954 E Archer Pl",
    "sg:city":"Aurora",
    "sg:classifiers":[
        {
            "category":"Autos & Motor Vehicles",
            "subcategory":"Recreational Vehicle Sales",
            "type":"Retail Goods"
        }
    ],
    "sg:phone":"+1 303 363 6887",
    "sg:postcode":"80018",
    "sg:province":"CO",
    "sg:tags":[
        "bicycle",
        "electric"
    ],
    "wof:name":"Bates Mtrhome Rntl Ntwrk Dnver",
    "wof:placetype":"venue"
},
  "geometry": {"coordinates":[-104.70742199999999,39.71594],"type":"Point"}
}