{
  "type": "Feature",
  "properties": {
    "addr:full":"10798 Foxwood Ct Parker CO 80138",
    "addr:housenumber":"10798",
    "addr:postcode":"80138",
    "addr:street":"Foxwood Ct",
    "iso:country":"US",
    "sg:address":"10798 Foxwood Ct",
    "sg:city":"Parker",
    "sg:classifiers":[
        {
            "category":"Retail",
            "subcategory":"Animal Services",
            "type":"Services"
        }
    ],
    "sg:phone":"+1 303 841 3504",
    "sg:postcode":"80138",
    "sg:province":"CO",
    "wof:name":"Best Dog Training",
    "wof:placetype":"venue"
},
  "geometry": {"coordinates":[-104.757655,39.521131],"type":"Point"}
}