{
  "type": "Feature",
  "properties": {
    "addr:full":"2650 Bahamas Way Grand Junction CO 81506",
    "addr:postcode":"2650;81506",
    "addr:street":"Bahamas Way",
    "iso:country":"US",
    "sg:address":"2650 Bahamas Way",
    "sg:city":"Grand Junction",
    "sg:classifiers":[
        {
            "category":"Building & Trades",
            "subcategory":"Cleaning & Sanitation",
            "type":"Services"
        }
    ],
    "sg:phone":"+1 970 256 1237",
    "sg:postcode":"81506",
    "sg:province":"CO",
    "sg:tags":[
        "janitor"
    ],
    "wof:name":"Mountain Summit Cleaning",
    "wof:placetype":"venue"
},
  "geometry": {"coordinates":[-108.56159700000001,39.123069],"type":"Point"}
}