{
  "type": "Feature",
  "properties": {
    "iso:country":"US",
    "sg:address":"2910 San Isabel Ave",
    "sg:city":"Pueblo",
    "sg:classifiers":[
        {
            "category":"Personal",
            "subcategory":"Beauty Salon",
            "type":"Services"
        }
    ],
    "sg:phone":"+1 719 542 9292",
    "sg:postcode":"81008",
    "sg:province":"CO",
    "wof:name":"Color Solution Hair Salon",
    "wof:placetype":"venue"
},
  "geometry": {"coordinates":[-104.638293,38.299609],"type":"Point"}
}