{
  "type": "Feature",
  "properties": {
    "iso:country":"US",
    "sg:address":"15955 Tee Rd",
    "sg:city":"Buena Vista",
    "sg:classifiers":[
        {
            "category":"Building & Trades",
            "subcategory":"Construction",
            "type":"Services"
        }
    ],
    "sg:phone":"+1 719 395 2024",
    "sg:postcode":"81211",
    "sg:province":"CO",
    "sg:tags":[
        "general",
        "contractor"
    ],
    "wof:name":"Hachmann's Custom Building",
    "wof:placetype":"venue"
},
  "geometry": {"coordinates":[-106.16292300000001,38.833731],"type":"Point"}
}