{
  "type": "Feature",
  "properties": {
    "iso:country":"US",
    "sg:address":"11056 W Co Rd 18E",
    "sg:city":"Loveland",
    "sg:classifiers":[
        {
            "category":"Government",
            "subcategory":"Office",
            "type":"Public Place"
        }
    ],
    "sg:phone":"+1 970 667 4410",
    "sg:postcode":"80537",
    "sg:province":"CO",
    "sg:tags":[
        "water",
        "waste",
        "management",
        "air"
    ],
    "wof:name":"Eastern Colorado Area Office",
    "wof:placetype":"venue"
},
  "geometry": {"coordinates":[-105.237067,40.370312],"type":"Point"}
}