{
  "type": "Feature",
  "properties": {
    "iso:country":"US",
    "sg:address":"5820 Flintridge Dr",
    "sg:city":"Colorado Springs",
    "sg:classifiers":[
        {
            "category":"Real Estate",
            "subcategory":"Real Estate Operator",
            "type":"Services"
        }
    ],
    "sg:phone":"+1 719 590 1247",
    "sg:postcode":"80918",
    "sg:province":"CO",
    "sg:tags":[
        "building",
        "apartment"
    ],
    "wof:name":"Sunridge Retirement Residence",
    "wof:placetype":"venue"
},
  "geometry": {"coordinates":[-104.764178,38.91606],"type":"Point"}
}