{
  "type": "Feature",
  "properties": {
    "iso:country":"US",
    "sg:address":"1402 Blake Ave",
    "sg:city":"Glenwood Springs",
    "sg:classifiers":[
        {
            "category":"Education",
            "subcategory":"College",
            "type":"Public Place"
        }
    ],
    "sg:phone":"+1 970 945 7486",
    "sg:postcode":"81601",
    "sg:province":"CO",
    "sg:tags":[
        "academic",
        "school"
    ],
    "sg:website":"www.coloradomtn.edu",
    "wof:name":"Colorado Mountain College",
    "wof:placetype":"venue"
},
  "geometry": {"coordinates":[-107.322794,39.539061],"type":"Point"}
}