{
  "type": "Feature",
  "properties": {
    "iso:country":"US",
    "sg:address":"2136 Oakland Ave",
    "sg:city":"Pueblo",
    "sg:classifiers":[
        {
            "category":"Farming",
            "subcategory":"Livestock Farm",
            "type":"Manufacturing & Wholesale Goods"
        }
    ],
    "sg:phone":"+1 719 560 0823",
    "sg:postcode":"81004",
    "sg:province":"CO",
    "sg:tags":[
        "equine"
    ],
    "wof:name":"Keator Farms",
    "wof:placetype":"venue"
},
  "geometry": {"coordinates":[-104.621853,38.229866],"type":"Point"}
}