{
  "type": "Feature",
  "properties": {
    "addr:full":"6489 S Havana St Englewood CO 80111",
    "addr:housenumber":"6489",
    "addr:postcode":"80111",
    "addr:street":"S Havana St",
    "iso:country":"US",
    "sg:address":"6489 S Havana St",
    "sg:city":"Englewood",
    "sg:classifiers":[
        {
            "category":"Freight",
            "type":"Transportation"
        }
    ],
    "sg:phone":"+1 720 482 9283",
    "sg:postcode":"80111",
    "sg:province":"CO",
    "sg:tags":[
        "operator",
        "local",
        "trucking"
    ],
    "wof:name":"Goldblat Trucking",
    "wof:placetype":"venue"
},
  "geometry": {"coordinates":[-104.866822,39.599216],"type":"Point"}
}