{
  "type": "Feature",
  "properties": {
    "iso:country":"US",
    "sg:address":"5511 Altura St",
    "sg:city":"Denver",
    "sg:classifiers":[
        {
            "category":"Retail",
            "subcategory":"Animal Services",
            "type":"Services"
        }
    ],
    "sg:phone":"+1 303 371 6243",
    "sg:postcode":"80239",
    "sg:province":"CO",
    "wof:name":"Dog Would Training",
    "wof:placetype":"venue"
},
  "geometry": {"coordinates":[-104.813069,39.79353],"type":"Point"}
}