{
  "type": "Feature",
  "properties": {
    "addr:full":"9983 Hwy 550 Durango CO 81303",
    "addr:housenumber":"9983",
    "addr:postcode":"co 81303",
    "addr:street":"Hwy 550",
    "iso:country":"US",
    "sg:address":"9983 Hwy 550",
    "sg:city":"Durango",
    "sg:classifiers":[
        {
            "category":"Wholesale",
            "subcategory":"Construction Materials",
            "type":"Manufacturing & Wholesale Goods"
        }
    ],
    "sg:phone":"+1 970 247 1596",
    "sg:postcode":"81303",
    "sg:province":"CO",
    "sg:tags":[
        "operator",
        "local",
        "trucking"
    ],
    "wof:name":"Sunnyside Gravel & Excavation",
    "wof:placetype":"venue"
},
  "geometry": {"coordinates":[-107.857868,37.139475],"type":"Point"}
}