{
  "type": "Feature",
  "properties": {
    "addr:full":"1060 Harrison Rd Colorado Springs CO 80906",
    "addr:housenumber":"1060",
    "addr:postcode":"80906",
    "addr:street":"Harrison Rd",
    "iso:country":"US",
    "sg:address":"1060 Harrison Rd",
    "sg:city":"Colorado Springs",
    "sg:classifiers":[
        {
            "category":"Education",
            "subcategory":"School",
            "type":"Public Place"
        }
    ],
    "sg:phone":"+1 719 579 2000",
    "sg:postcode":"80906",
    "sg:province":"CO",
    "sg:tags":[
        "district"
    ],
    "sg:website":"www.harrisond2fcu.org",
    "wof:name":"Harrison School District 2",
    "wof:placetype":"venue"
},
  "geometry": {"coordinates":[-104.810962,38.796881],"type":"Point"}
}