{
  "type": "Feature",
  "properties": {
    "addr:full":"310 N 42nd Ave Greeley CO 80634",
    "addr:housenumber":"310",
    "addr:postcode":"80634",
    "addr:street":"N 42Nd Ave",
    "iso:country":"US",
    "sg:address":"310 N 42nd Ave",
    "sg:city":"Greeley",
    "sg:classifiers":[
        {
            "category":"Banks & Credit Unions",
            "subcategory":"Financial Services",
            "type":"Services"
        }
    ],
    "sg:phone":"+1 970 352 7585",
    "sg:postcode":"80634",
    "sg:province":"CO",
    "sg:tags":[
        "investor"
    ],
    "wof:name":"Ark Investments LLC",
    "wof:placetype":"venue"
},
  "geometry": {"coordinates":[-104.74529,40.435641],"type":"Point"}
}