{
  "type": "Feature",
  "properties": {
    "addr:full":"2186 S Holly St Denver CO 80222",
    "addr:housenumber":"2186",
    "addr:postcode":"80222",
    "addr:street":"S Holly St",
    "iso:country":"US",
    "sg:address":"2186 S Holly St",
    "sg:city":"Denver",
    "sg:classifiers":[
        {
            "category":"Real Estate",
            "subcategory":"Real Estate Operator",
            "type":"Services"
        }
    ],
    "sg:phone":"+1 720 524 5605",
    "sg:postcode":"80222",
    "sg:province":"CO",
    "sg:tags":[
        "apartment"
    ],
    "wof:name":"Ranchlands West Co",
    "wof:placetype":"venue"
},
  "geometry": {"coordinates":[-104.922076,39.677364],"type":"Point"}
}