{
  "type": "Feature",
  "properties": {
    "addr:full":"1439 S Pearl St Denver CO 80210",
    "addr:housenumber":"1439",
    "addr:postcode":"80210",
    "addr:street":"S Pearl St",
    "iso:country":"US",
    "sg:address":"1439 S Pearl St",
    "sg:city":"Denver",
    "sg:classifiers":[
        {
            "category":"Shopping",
            "subcategory":"Used Merchandise",
            "type":"Retail Goods"
        }
    ],
    "sg:phone":"+1 303 282 5958",
    "sg:postcode":"80210",
    "sg:province":"CO",
    "sg:tags":[
        "antique"
    ],
    "wof:name":"A 1 Antique Buyer & Appraiser",
    "wof:placetype":"venue"
},
  "geometry": {"coordinates":[-104.98051599999999,39.69008],"type":"Point"}
}