{
  "type": "Feature",
  "properties": {
    "iso:country":"US",
    "sg:address":"311 Main St",
    "sg:city":"Breckenridge",
    "sg:classifiers":[
        {
            "category":"Real Estate",
            "subcategory":"Real Estate Agent",
            "type":"Services"
        }
    ],
    "sg:phone":"+1 970 453 0466",
    "sg:postcode":"80424",
    "sg:province":"CO",
    "wof:name":"Paffrath & Thomas Real Estate",
    "wof:placetype":"venue"
},
  "geometry": {"coordinates":[-106.04565599999999,39.478983],"type":"Point"}
}