{
  "type": "Feature",
  "properties": {
    "addr:full":"350 7th St Limon CO 80828",
    "addr:housenumber":"350",
    "addr:postcode":"80828",
    "addr:street":"7Th St",
    "iso:country":"US",
    "sg:address":"350 7th St",
    "sg:city":"Limon",
    "sg:classifiers":[
        {
            "category":"Retail",
            "subcategory":"Auto Repair",
            "type":"Services"
        }
    ],
    "sg:phone":"+1 719 775 9295",
    "sg:postcode":"80828",
    "sg:province":"CO",
    "sg:tags":[
        "wrecker"
    ],
    "wof:name":"H D Towing & Transport",
    "wof:placetype":"venue"
},
  "geometry": {"coordinates":[-103.68134499999999,39.267748],"type":"Point"}
}