{
  "type": "Feature",
  "properties": {
    "iso:country":"US",
    "sg:address":"8065 Forest Heights Cir",
    "sg:city":"Colorado Springs",
    "sg:classifiers":[
        {
            "category":"Professional",
            "type":"Services"
        }
    ],
    "sg:phone":"+1 719 649 4087",
    "sg:postcode":"80908",
    "sg:province":"CO",
    "wof:name":"Accents Etc",
    "wof:placetype":"venue"
},
  "geometry": {"coordinates":[-104.678623,39.018867],"type":"Point"}
}