{
  "type": "Feature",
  "properties": {
    "addr:full":"7865 Newman St Arvada CO 80005",
    "addr:housenumber":"7865",
    "addr:postcode":"80005",
    "addr:street":"Newman St",
    "iso:country":"US",
    "sg:address":"7865 Newman St",
    "sg:city":"Arvada",
    "sg:classifiers":[
        {
            "category":"Home & Garden",
            "subcategory":"Furniture",
            "type":"Retail Goods"
        }
    ],
    "sg:phone":"+1 303 421 5980",
    "sg:postcode":"80005",
    "sg:province":"CO",
    "wof:name":"Artistic Cabinets",
    "wof:placetype":"venue"
},
  "geometry": {"coordinates":[-105.118475,39.839687],"type":"Point"}
}