{
  "type": "Feature",
  "properties": {
    "addr:full":"9655 W 69th Ave Arvada CO 80004",
    "addr:housenumber":"9655",
    "addr:postcode":"80004",
    "addr:street":"W 69Th Ave",
    "iso:country":"US",
    "sg:address":"9655 W 69th Ave",
    "sg:city":"Arvada",
    "sg:classifiers":[
        {
            "category":"Shopping",
            "subcategory":"Computers & Home Electronics",
            "type":"Retail Goods"
        }
    ],
    "sg:phone":"+1 303 940 2468",
    "sg:postcode":"80004",
    "sg:province":"CO",
    "sg:tags":[
        "software"
    ],
    "wof:name":"Shade Tree Software",
    "wof:placetype":"venue"
},
  "geometry": {"coordinates":[-105.105216,39.821902],"type":"Point"}
}