{
  "type": "Feature",
  "properties": {
    "addr:full":"801 N Weber St Colorado Springs CO 80903",
    "addr:housenumber":"801",
    "addr:postcode":"80903",
    "addr:street":"N Weber St",
    "iso:country":"US",
    "sg:address":"801 N Weber St",
    "sg:city":"Colorado Springs",
    "sg:classifiers":[
        {
            "category":"Professional",
            "subcategory":"Lawyer & Legal Services",
            "type":"Services"
        }
    ],
    "sg:phone":"+1 719 634 7200",
    "sg:postcode":"80903",
    "sg:province":"CO",
    "sg:tags":[
        "attorney"
    ],
    "wof:name":"Zimmerman & Michel",
    "wof:placetype":"venue"
},
  "geometry": {"coordinates":[-104.819174,38.846371],"type":"Point"}
}