{
  "type": "Feature",
  "properties": {
    "iso:country":"US",
    "sg:address":"3503 1st St S",
    "sg:city":"Lamar",
    "sg:classifiers":[
        {
            "category":"Professional",
            "subcategory":"Lawyer & Legal Services",
            "type":"Services"
        }
    ],
    "sg:phone":"+1 719 336 7772",
    "sg:postcode":"81052",
    "sg:province":"CO",
    "sg:tags":[
        "attorney"
    ],
    "wof:name":"George Mc Lachlan",
    "wof:placetype":"venue"
},
  "geometry": {"coordinates":[-102.61333500000001,38.052543],"type":"Point"}
}