{
  "type": "Feature",
  "properties": {
    "iso:country":"US",
    "sg:address":"5330 Wadsworth Byp",
    "sg:city":"Arvada",
    "sg:classifiers":[
        {
            "category":"Autos & Motor Vehicles",
            "subcategory":"Auto Supplies",
            "type":"Retail Goods"
        }
    ],
    "sg:phone":"+1 303 423 1883",
    "sg:postcode":"80002",
    "sg:province":"CO",
    "sg:tags":[
        "tire"
    ],
    "sg:website":"www.discounttire.com/makeappt",
    "wof:name":"Discount Tire",
    "wof:placetype":"venue"
},
  "geometry": {"coordinates":[-105.07846499999999,39.793489],"type":"Point"}
}