{
  "type": "Feature",
  "properties": {
    "iso:country":"US",
    "sg:address":"2705 W Greens Dr",
    "sg:city":"Littleton",
    "sg:classifiers":[
        {
            "category":"Building & Trades",
            "subcategory":"Construction",
            "type":"Services"
        }
    ],
    "sg:phone":"+1 303 778 0965",
    "sg:postcode":"80123",
    "sg:province":"CO",
    "sg:tags":[
        "contractor"
    ],
    "wof:name":"Vogel Roofing Services Inc",
    "wof:placetype":"venue"
},
  "geometry": {"coordinates":[-105.019008,39.619824],"type":"Point"}
}