{
  "type": "Feature",
  "properties": {
    "addr:full":"3 Sequoyah Rd Colorado Springs CO 80906",
    "addr:housenumber":"3",
    "addr:postcode":"80906",
    "addr:street":"Sequoyah Rd",
    "iso:country":"US",
    "sg:address":"3 Sequoyah Rd",
    "sg:city":"Colorado Springs",
    "sg:classifiers":[
        {
            "category":"Insurance",
            "subcategory":"Insurance Agent",
            "type":"Services"
        }
    ],
    "sg:phone":"+1 719 471 4146",
    "sg:postcode":"80906",
    "sg:province":"CO",
    "sg:tags":[
        "consulting",
        "business"
    ],
    "wof:name":"Colorado Emplyee Bneft Conslts",
    "wof:placetype":"venue"
},
  "geometry": {"coordinates":[-104.835065,38.785822],"type":"Point"}
}