{
  "type": "Feature",
  "properties": {
    "iso:country":"US",
    "sg:address":"7000 S Windermere St",
    "sg:city":"Littleton",
    "sg:classifiers":[
        {
            "category":"Organizations",
            "subcategory":"Religious Organization",
            "type":"Services"
        }
    ],
    "sg:phone":"+1 303 797 1536",
    "sg:postcode":"80120",
    "sg:province":"CO",
    "sg:tags":[
        "church"
    ],
    "wof:name":"Prince Of Peace Church",
    "wof:placetype":"venue"
},
  "geometry": {"coordinates":[-105.007041,39.589392],"type":"Point"}
}