{
  "type": "Feature",
  "properties": {
    "addr:full":"1450 Hwy 50 Delta CO 81416",
    "addr:housenumber":"1450",
    "addr:postcode":"81416",
    "addr:street":"Hwy 50",
    "iso:country":"US",
    "sg:address":"1450 Hwy 50",
    "sg:city":"Delta",
    "sg:classifiers":[
        {
            "category":"Professional",
            "subcategory":"Business Services",
            "type":"Services"
        }
    ],
    "sg:phone":"+1 970 874 4500",
    "sg:postcode":"81416",
    "sg:province":"CO",
    "wof:name":"Custom Keys",
    "wof:placetype":"venue"
},
  "geometry": {"coordinates":[-108.09268,38.762741],"type":"Point"}
}