{
  "type": "Feature",
  "properties": {
    "iso:country":"US",
    "sg:address":"13920 W 74th Pl",
    "sg:city":"Arvada",
    "sg:classifiers":[
        {
            "category":"Professional",
            "subcategory":"Management & Consulting",
            "type":"Services"
        }
    ],
    "sg:phone":"+1 303 809 7466",
    "sg:postcode":"80005",
    "sg:province":"CO",
    "sg:tags":[
        "sound",
        "consultant",
        "system"
    ],
    "wof:name":"Nvs Sound",
    "wof:placetype":"venue"
},
  "geometry": {"coordinates":[-105.155171,39.831549],"type":"Point"}
}