{
  "type": "Feature",
  "properties": {
    "iso:country":"US",
    "sg:address":"2047 21st Ave",
    "sg:city":"Greeley",
    "sg:classifiers":[
        {
            "category":"Home & Garden",
            "subcategory":"Garden Supply",
            "type":"Retail Goods"
        }
    ],
    "sg:phone":"+1 970 353 3600",
    "sg:postcode":"80631",
    "sg:province":"CO",
    "sg:tags":[
        "sprinkler"
    ],
    "wof:name":"Bruner Sprinkler Co",
    "wof:placetype":"venue"
},
  "geometry": {"coordinates":[-104.712665,40.405011],"type":"Point"}
}