{
  "type": "Feature",
  "properties": {
    "addr:full":"795 York St Denver CO 80206",
    "addr:housenumber":"795",
    "addr:postcode":"80206",
    "addr:street":"York St",
    "iso:country":"US",
    "sg:address":"795 York St",
    "sg:city":"Denver",
    "sg:classifiers":[
        {
            "category":"Real Estate",
            "subcategory":"Real Estate Operator",
            "type":"Services"
        }
    ],
    "sg:phone":"+1 303 320 9707",
    "sg:postcode":"80206",
    "sg:province":"CO",
    "sg:tags":[
        "building",
        "nonresidential"
    ],
    "wof:name":"Lindberg Properties 04 LLC",
    "wof:placetype":"venue"
},
  "geometry": {"coordinates":[-104.960257,39.727391],"type":"Point"}
}