{
  "type": "Feature",
  "properties": {
    "addr:full":"9229 Lark Sparrow Trl Littleton CO 80126",
    "addr:housenumber":"9229",
    "addr:postcode":"80126",
    "addr:street":"Lark Sparrow Trl",
    "iso:country":"US",
    "sg:address":"9229 Lark Sparrow Trl",
    "sg:city":"Littleton",
    "sg:classifiers":[
        {
            "category":"Building & Trades",
            "subcategory":"Landscaping Services",
            "type":"Services"
        }
    ],
    "sg:phone":"+1 720 348 0726",
    "sg:postcode":"80126",
    "sg:province":"CO",
    "wof:name":"Bella Casa Custom Homes Inc",
    "wof:placetype":"venue"
},
  "geometry": {"coordinates":[-104.939662,39.549206],"type":"Point"}
}