{
  "type": "Feature",
  "properties": {
    "iso:country":"US",
    "sg:address":"449 San Juan St",
    "sg:city":"Pagosa Springs",
    "sg:classifiers":[
        {
            "category":"Government",
            "subcategory":"Police Station",
            "type":"Public Place"
        }
    ],
    "sg:phone":"+1 970 264 2131",
    "sg:postcode":"81147",
    "sg:province":"CO",
    "sg:tags":[
        "sheriff"
    ],
    "sg:website":"www.archuletacounty.org",
    "wof:name":"County Sheriff",
    "wof:placetype":"venue"
},
  "geometry": {"coordinates":[-107.01424400000001,37.26624],"type":"Point"}
}