{
  "type": "Feature",
  "properties": {
    "addr:full":"18808 Eagle Ridge Dr Golden CO 80401",
    "addr:housenumber":"18808",
    "addr:postcode":"80401",
    "addr:street":"Eagle Ridge Dr",
    "iso:country":"US",
    "sg:address":"18808 Eagle Ridge Dr",
    "sg:city":"Golden",
    "sg:classifiers":[
        {
            "category":"Restaurant",
            "type":"Food & Drink"
        }
    ],
    "sg:phone":"+1 303 202 0055",
    "sg:postcode":"80401",
    "sg:province":"CO",
    "sg:tags":[
        "cafeteria"
    ],
    "wof:name":"Euroserv Inc",
    "wof:placetype":"venue"
},
  "geometry": {"coordinates":[-105.21545500000001,39.731223],"type":"Point"}
}