{
  "type": "Feature",
  "properties": {
    "addr:full":"481 N 16th Ave Brighton CO 80601",
    "addr:housenumber":"481",
    "addr:postcode":"80601",
    "addr:street":"N 16Th Ave",
    "iso:country":"US",
    "sg:address":"481 N 16th Ave",
    "sg:city":"Brighton",
    "sg:classifiers":[
        {
            "category":"Building & Trades",
            "subcategory":"Construction",
            "type":"Services"
        }
    ],
    "sg:phone":"+1 303 659 5894",
    "sg:postcode":"80601",
    "sg:province":"CO",
    "sg:tags":[
        "contractor"
    ],
    "wof:name":"Little Tree Ldscp & Fencing",
    "wof:placetype":"venue"
},
  "geometry": {"coordinates":[-104.803174,39.995047],"type":"Point"}
}