{
  "type": "Feature",
  "properties": {
    "addr:full":"4990 E Peakview Ave Centennial CO 80121",
    "addr:housenumber":"4990",
    "addr:postcode":"80121",
    "addr:street":"E Peakview Ave",
    "iso:country":"US",
    "sg:address":"4990 E Peakview Ave",
    "sg:city":"Centennial",
    "sg:classifiers":[
        {
            "category":"Building & Trades",
            "subcategory":"Construction",
            "type":"Services"
        }
    ],
    "sg:phone":"+1 303 773 8861",
    "sg:postcode":"80121",
    "sg:province":"CO",
    "sg:tags":[
        "company"
    ],
    "wof:name":"Elite Construction Co",
    "wof:placetype":"venue"
},
  "geometry": {"coordinates":[-104.93128299999999,39.598528],"type":"Point"}
}