{
  "type": "Feature",
  "properties": {
    "addr:full":"1119 13th St Boulder CO 80302",
    "addr:housenumber":"1119",
    "addr:postcode":"80302",
    "addr:street":"13Th St",
    "iso:country":"US",
    "sg:address":"1119 13th St",
    "sg:city":"Boulder",
    "sg:classifiers":[
        {
            "category":"Restaurant",
            "type":"Food & Drink"
        }
    ],
    "sg:menulink":"http://www.allmenus.com/co/boulder/40703-qdoba/menu/",
    "sg:phone":"+1 303 449 3439",
    "sg:postcode":"80302",
    "sg:province":"CO",
    "sg:tags":[
        "mexican"
    ],
    "wof:name":"Qdoba",
    "wof:placetype":"venue"
},
  "geometry": {"coordinates":[-105.27640700000001,40.007664],"type":"Point"}
}