{
  "type": "Feature",
  "properties": {
    "addr:full":"9910 Palisade Ridge Dr Colorado Springs CO 80920",
    "addr:housenumber":"9910",
    "addr:postcode":"80920",
    "addr:street":"Palisade Ridge Dr",
    "iso:country":"US",
    "sg:address":"9910 Palisade Ridge Dr",
    "sg:city":"Colorado Springs",
    "sg:classifiers":[
        {
            "category":"Professional",
            "subcategory":"Management & Consulting",
            "type":"Services"
        }
    ],
    "sg:phone":"+1 719 264 0761",
    "sg:postcode":"80920",
    "sg:province":"CO",
    "sg:tags":[
        "consultant",
        "business"
    ],
    "wof:name":"Pro Point Solutions",
    "wof:placetype":"venue"
},
  "geometry": {"coordinates":[-104.765395,38.978425],"type":"Point"}
}