{
  "type": "Feature",
  "properties": {
    "addr:full":"1310 Eastmeadow Ct Colorado Springs CO 80906",
    "addr:housenumber":"1310",
    "addr:postcode":"80906",
    "addr:street":"Eastmeadow Ct",
    "iso:country":"US",
    "sg:address":"1310 Eastmeadow Ct",
    "sg:city":"Colorado Springs",
    "sg:classifiers":[
        {
            "category":"Airline",
            "type":"Transportation"
        }
    ],
    "sg:phone":"+1 719 226 1668",
    "sg:postcode":"80906",
    "sg:province":"CO",
    "sg:tags":[
        "scheduled",
        "air"
    ],
    "wof:name":"Sierra West Airlines",
    "wof:placetype":"venue"
},
  "geometry": {"coordinates":[-104.804429,38.768502],"type":"Point"}
}