{
  "type": "Feature",
  "properties": {
    "addr:full":"1114 W 7th Ave Denver CO 80204",
    "addr:housenumber":"1114",
    "addr:postcode":"80204",
    "addr:street":"W 7Th Ave",
    "iso:country":"US",
    "sg:address":"1114 W 7th Ave",
    "sg:city":"Denver",
    "sg:classifiers":[
        {
            "category":"Building & Trades",
            "subcategory":"Locksmith",
            "type":"Services"
        }
    ],
    "sg:phone":"+1 866 316 0298",
    "sg:postcode":"80204",
    "sg:province":"CO",
    "sg:tags":[
        "key"
    ],
    "wof:name":"Always Affective Available Emergency Locksmith",
    "wof:placetype":"venue"
},
  "geometry": {"coordinates":[-105.001696,39.727183],"type":"Point"}
}