{
  "type": "Feature",
  "properties": {
    "addr:full":"2301 Ross Dr Fort Collins CO 80526",
    "addr:housenumber":"2301",
    "addr:postcode":"80526",
    "addr:street":"Ross Dr",
    "iso:country":"US",
    "sg:address":"2301 Ross Dr",
    "sg:city":"Fort Collins",
    "sg:classifiers":[
        {
            "category":"Professional",
            "subcategory":"Computer Services",
            "type":"Services"
        }
    ],
    "sg:phone":"+1 970 224 4996",
    "sg:postcode":"80526",
    "sg:province":"CO",
    "sg:tags":[
        "software"
    ],
    "wof:name":"T G S Technology",
    "wof:placetype":"venue"
},
  "geometry": {"coordinates":[-105.13184,40.56077],"type":"Point"}
}