{
  "type": "Feature",
  "properties": {
    "addr:full":"1925 Mountain View Ave Longmont CO 80501",
    "addr:housenumber":"1925",
    "addr:postcode":"80501",
    "addr:street":"Mountain View Ave",
    "iso:country":"US",
    "sg:address":"1925 Mountain View Ave",
    "sg:city":"Longmont",
    "sg:classifiers":[
        {
            "category":"Health Services",
            "subcategory":"Doctor",
            "type":"Services"
        }
    ],
    "sg:phone":"+1 303 776 8718",
    "sg:postcode":"80501",
    "sg:province":"CO",
    "sg:tags":[
        "physician",
        "surgeon"
    ],
    "wof:name":"Longmont Medical Research Netw",
    "wof:placetype":"venue"
},
  "geometry": {"coordinates":[-105.125688,40.181248],"type":"Point"}
}