{
  "type": "Feature",
  "properties": {
    "iso:country":"US",
    "sg:address":"3175 Vance St",
    "sg:city":"Wheat Ridge",
    "sg:classifiers":[
        {
            "category":"Building & Trades",
            "subcategory":"Construction",
            "type":"Services"
        }
    ],
    "sg:phone":"+1 303 233 5334",
    "sg:postcode":"80033",
    "sg:province":"CO",
    "sg:tags":[
        "gutter",
        "contractor"
    ],
    "wof:name":"D G Gutters Inc",
    "wof:placetype":"venue"
},
  "geometry": {"coordinates":[-105.079571,39.760497],"type":"Point"}
}