{
  "type": "Feature",
  "properties": {
    "addr:full":"3409 Thistlebrook Cir Littleton CO 80126",
    "addr:postcode":"3409;80126",
    "addr:street":"Thistlebrook Cir",
    "iso:country":"US",
    "sg:address":"3409 Thistlebrook Cir",
    "sg:city":"Littleton",
    "sg:classifiers":[
        {
            "category":"Shopping",
            "subcategory":"Clothing, Apparel, & Fashions",
            "type":"Retail Goods"
        }
    ],
    "sg:phone":"+1 720 344 9416",
    "sg:postcode":"80126",
    "sg:province":"CO",
    "wof:name":"Trick or Treaters Ltd LLC",
    "wof:placetype":"venue"
},
  "geometry": {"coordinates":[-104.953141,39.528117],"type":"Point"}
}