{
  "type": "Feature",
  "properties": {
    "iso:country":"US",
    "sg:address":"3306 Windmill Ct",
    "sg:city":"Evans",
    "sg:classifiers":[
        {
            "category":"Freight",
            "type":"Transportation"
        }
    ],
    "sg:phone":"+1 970 330 2662",
    "sg:postcode":"80620",
    "sg:province":"CO",
    "sg:tags":[
        "operator",
        "trucking"
    ],
    "wof:name":"Dalenara Co",
    "wof:placetype":"venue"
},
  "geometry": {"coordinates":[-104.738913,40.383222],"type":"Point"}
}