{
  "type": "Feature",
  "properties": {
    "iso:country":"US",
    "sg:address":"2000 Vermont Dr",
    "sg:city":"Fort Collins",
    "sg:classifiers":[
        {
            "category":"Professional",
            "subcategory":"Engineering",
            "type":"Services"
        }
    ],
    "sg:phone":"+1 970 226 8557",
    "sg:postcode":"80525",
    "sg:province":"CO",
    "sg:tags":[
        "consulting",
        "engineer"
    ],
    "sg:website":"www.barlowprojects.com",
    "wof:name":"Barlow Group Inc",
    "wof:placetype":"venue"
},
  "geometry": {"coordinates":[-105.039255,40.543203],"type":"Point"}
}