{
  "type": "Feature",
  "properties": {
    "addr:full":"1028 S Gaylord St Denver CO 80209",
    "addr:housenumber":"1028",
    "addr:postcode":"80209",
    "addr:street":"S Gaylord St",
    "iso:country":"US",
    "sg:address":"1028 S Gaylord St",
    "sg:city":"Denver",
    "sg:classifiers":[
        {
            "category":"Sports & Exercise",
            "subcategory":"Gym",
            "type":"Entertainment"
        }
    ],
    "sg:phone":"+1 303 322 7132",
    "sg:postcode":"80209",
    "sg:province":"CO",
    "sg:tags":[
        "trainer"
    ],
    "sg:website":"www.fitnesstogetherdenver.com/",
    "wof:name":"Fitness Together",
    "wof:placetype":"venue"
},
  "geometry": {"coordinates":[-104.96141900000001,39.697838],"type":"Point"}
}