{
  "type": "Feature",
  "properties": {
    "addr:full":"2844 Kyle Cir Loveland CO 80537",
    "addr:housenumber":"2844",
    "addr:postcode":"80537",
    "addr:street":"Kyle Cir",
    "iso:country":"US",
    "sg:address":"2844 Kyle Cir",
    "sg:city":"Loveland",
    "sg:classifiers":[
        {
            "category":"Banks & Credit Unions",
            "subcategory":"Bank",
            "type":"Services"
        }
    ],
    "sg:phone":"+1 970 278 9000",
    "sg:postcode":"80537",
    "sg:province":"CO",
    "sg:tags":[
        "short",
        "institution",
        "business"
    ],
    "wof:name":"Cashbook Funding Inc",
    "wof:placetype":"venue"
},
  "geometry": {"coordinates":[-105.172331,40.362023],"type":"Point"}
}