{
  "type": "Feature",
  "properties": {
    "addr:full":"1430 S Wadsworth Boulevard Lakewood CO 80232",
    "addr:housenumber":"1430",
    "addr:postcode":"80232",
    "addr:street":"S Wadsworth Boulevard",
    "iso:country":"US",
    "sg:address":"1430 S Wadsworth Boulevard",
    "sg:city":"Lakewood",
    "sg:classifiers":[
        {
            "category":"Professional",
            "subcategory":"Lawyer & Legal Services",
            "type":"Services"
        }
    ],
    "sg:phone":"+1 303 986 8799",
    "sg:postcode":"80232",
    "sg:province":"CO",
    "sg:tags":[
        "notary"
    ],
    "wof:name":"Rosemary's Baby",
    "wof:placetype":"venue"
},
  "geometry": {"coordinates":[-105.081677,39.690841],"type":"Point"}
}