{
  "type": "Feature",
  "properties": {
    "iso:country":"US",
    "sg:address":"501 Thornton Pkwy",
    "sg:city":"Denver",
    "sg:classifiers":[
        {
            "category":"Health Services",
            "subcategory":"Nursing And Care Facility",
            "type":"Services"
        }
    ],
    "sg:phone":"+1 720 872 7960",
    "sg:postcode":"80229",
    "sg:province":"CO",
    "sg:tags":[
        "home",
        "convalescent"
    ],
    "wof:name":"Mariner Health Care Inc",
    "wof:placetype":"venue"
},
  "geometry": {"coordinates":[-104.98150099999999,39.870576],"type":"Point"}
}