{
  "type": "Feature",
  "properties": {
    "iso:country":"US",
    "sg:address":"143 Lone Hand Way",
    "sg:city":"Breckenridge",
    "sg:classifiers":[
        {
            "category":"Professional",
            "type":"Services"
        }
    ],
    "sg:phone":"+1 970 453 3972",
    "sg:postcode":"80424",
    "sg:province":"CO",
    "wof:name":"John D Eldredge",
    "wof:placetype":"venue"
},
  "geometry": {"coordinates":[-106.06456799999999,39.50081],"type":"Point"}
}