{
  "type": "Feature",
  "properties": {
    "iso:country":"US",
    "sg:address":"430 Kensington St",
    "sg:city":"Longmont",
    "sg:classifiers":[
        {
            "category":"Shopping",
            "subcategory":"Shoes",
            "type":"Retail Goods"
        }
    ],
    "sg:phone":"+1 303 651 6291",
    "sg:postcode":"80501",
    "sg:province":"CO",
    "wof:name":"Jamie Richey",
    "wof:placetype":"venue"
},
  "geometry": {"coordinates":[-105.090754,40.166933],"type":"Point"}
}