{
  "type": "Feature",
  "properties": {
    "addr:full":"2432 S Oswego St Aurora CO 80014",
    "addr:housenumber":"2432",
    "addr:postcode":"80014",
    "addr:street":"S Oswego St",
    "iso:country":"US",
    "sg:address":"2432 S Oswego St",
    "sg:city":"Aurora",
    "sg:classifiers":[
        {
            "category":"Personal",
            "subcategory":"Beauty Salon",
            "type":"Services"
        }
    ],
    "sg:phone":"+1 303 283 8838",
    "sg:postcode":"80014",
    "sg:province":"CO",
    "sg:tags":[
        "manicuring"
    ],
    "wof:name":"Magic Nails",
    "wof:placetype":"venue"
},
  "geometry": {"coordinates":[-104.849977,39.670476],"type":"Point"}
}