{
  "type": "Feature",
  "properties": {
    "addr:full":"1900 1900 Rd Delta CO 81416",
    "addr:postcode":"1900;81416",
    "addr:street":"Rd",
    "iso:country":"US",
    "sg:address":"1900 1900 Rd",
    "sg:city":"Delta",
    "sg:classifiers":[
        {
            "category":"Farming",
            "subcategory":"Farm",
            "type":"Manufacturing & Wholesale Goods"
        }
    ],
    "sg:phone":"+1 970 874 8144",
    "sg:postcode":"81416",
    "sg:province":"CO",
    "sg:tags":[
        "crop",
        "general"
    ],
    "wof:name":"Byron Benson",
    "wof:placetype":"venue"
},
  "geometry": {"coordinates":[-108.00879399999999,38.726462],"type":"Point"}
}