{
  "type": "Feature",
  "properties": {
    "iso:country":"US",
    "sg:address":"31285 State Hwy 24",
    "sg:city":"Buena Vista",
    "sg:classifiers":[
        {
            "category":"Building & Trades",
            "subcategory":"Construction",
            "type":"Services"
        }
    ],
    "sg:phone":"+1 719 395 6938",
    "sg:postcode":"81211",
    "sg:province":"CO",
    "sg:tags":[
        "home",
        "builder"
    ],
    "wof:name":"Ritchie Builders",
    "wof:placetype":"venue"
},
  "geometry": {"coordinates":[-106.156305,38.870517],"type":"Point"}
}