{
  "type": "Feature",
  "properties": {
    "addr:full":"7293 Monaco St Commerce City CO 80022",
    "addr:housenumber":"7293",
    "addr:postcode":"80022",
    "addr:street":"Monaco St",
    "iso:country":"US",
    "sg:address":"7293 Monaco St",
    "sg:city":"Commerce City",
    "sg:classifiers":[
        {
            "category":"Restaurant",
            "type":"Food & Drink"
        }
    ],
    "sg:phone":"+1 303 288 3500",
    "sg:postcode":"80022",
    "sg:province":"CO",
    "sg:tags":[
        "eating"
    ],
    "wof:name":"Ben Martinez Sr",
    "wof:placetype":"venue"
},
  "geometry": {"coordinates":[-104.912115,39.828385],"type":"Point"}
}