{
  "type": "Feature",
  "properties": {
    "addr:full":"5799 Green Oaks Dr Greenwood Vlg CO 80121",
    "addr:housenumber":"5799",
    "addr:postcode":"co 80121",
    "addr:street":"Green Oaks Dr",
    "iso:country":"US",
    "sg:address":"5799 Green Oaks Dr",
    "sg:city":"Greenwood Vlg",
    "sg:classifiers":[
        {
            "category":"Banks & Credit Unions",
            "subcategory":"Financial Services",
            "type":"Services"
        }
    ],
    "sg:phone":"+1 303 797 2599",
    "sg:postcode":"80121",
    "sg:province":"CO",
    "sg:tags":[
        "company",
        "holding"
    ],
    "wof:name":"JGR Ventures",
    "wof:placetype":"venue"
},
  "geometry": {"coordinates":[-104.974726,39.612626],"type":"Point"}
}