{
  "type": "Feature",
  "properties": {
    "addr:full":"726 E Columbia Ave Telluride CO 81435",
    "addr:housenumber":"726",
    "addr:postcode":"81435",
    "addr:street":"E Columbia Ave",
    "iso:country":"US",
    "sg:address":"726 E Columbia Ave",
    "sg:city":"Telluride",
    "sg:classifiers":[
        {
            "category":"Professional",
            "subcategory":"Accounting & Tax Preparation",
            "type":"Services"
        }
    ],
    "sg:phone":"+1 970 728 3666",
    "sg:postcode":"81435",
    "sg:province":"CO",
    "sg:tags":[
        "accountant"
    ],
    "wof:name":"Friedman & Assoc",
    "wof:placetype":"venue"
},
  "geometry": {"coordinates":[-107.80431299999999,37.936311],"type":"Point"}
}