{
  "type": "Feature",
  "properties": {
    "iso:country":"US",
    "sg:address":"1829 N Circle Dr",
    "sg:city":"Colorado Springs",
    "sg:classifiers":[
        {
            "category":"Personal",
            "subcategory":"Beauty Salon",
            "type":"Services"
        }
    ],
    "sg:phone":"+1 719 520 5049",
    "sg:postcode":"80909",
    "sg:province":"CO",
    "wof:name":"Connie Burwell Hair",
    "wof:placetype":"venue"
},
  "geometry": {"coordinates":[-104.775666,38.858367],"type":"Point"}
}