{
  "type": "Feature",
  "properties": {
    "iso:country":"US",
    "sg:address":"2315 Broadway St",
    "sg:city":"Boulder",
    "sg:classifiers":[
        {
            "category":"Social Services",
            "type":"Services"
        }
    ],
    "sg:phone":"+1 303 449 8895",
    "sg:postcode":"80304",
    "sg:province":"CO",
    "sg:tags":[
        "worker"
    ],
    "wof:name":"Lawrence Nelson",
    "wof:placetype":"venue"
},
  "geometry": {"coordinates":[-105.281329,40.021592],"type":"Point"}
}