{
  "type": "Feature",
  "properties": {
    "iso:country":"US",
    "sg:address":"6736 W Coal Mine Ave",
    "sg:city":"Littleton",
    "sg:classifiers":[
        {
            "category":"Health Services",
            "subcategory":"Doctor",
            "type":"Services"
        }
    ],
    "sg:phone":"+1 303 973 9000",
    "sg:postcode":"80123",
    "sg:province":"CO",
    "sg:tags":[
        "dentist"
    ],
    "wof:name":"Family Dentistry",
    "wof:placetype":"venue"
},
  "geometry": {"coordinates":[-105.06974200000001,39.595217],"type":"Point"}
}