{
  "type": "Feature",
  "properties": {
    "addr:full":"1001 Ulysses St Golden CO 80401",
    "addr:housenumber":"1001",
    "addr:postcode":"80401",
    "addr:street":"Ulysses St",
    "iso:country":"US",
    "sg:address":"1001 Ulysses St",
    "sg:city":"Golden",
    "sg:classifiers":[
        {
            "category":"Education",
            "subcategory":"School",
            "type":"Public Place"
        }
    ],
    "sg:phone":"+1 303 982 4280",
    "sg:postcode":"80401",
    "sg:province":"CO",
    "wof:name":"Bell Middle School",
    "wof:placetype":"venue"
},
  "geometry": {"coordinates":[-105.19383500000001,39.735202],"type":"Point"}
}