{
  "type": "Feature",
  "properties": {
    "addr:full":"331 S Union Ave Pueblo CO 81003",
    "addr:housenumber":"331",
    "addr:postcode":"81003",
    "addr:street":"S Union Ave",
    "iso:country":"US",
    "sg:address":"331 S Union Ave",
    "sg:city":"Pueblo",
    "sg:classifiers":[
        {
            "category":"Shopping",
            "subcategory":"Gifts & Souvenirs",
            "type":"Retail Goods"
        }
    ],
    "sg:phone":"+1 719 545 5245",
    "sg:postcode":"81003",
    "sg:province":"CO",
    "sg:tags":[
        "shop"
    ],
    "wof:name":"Granny's Attic",
    "wof:placetype":"venue"
},
  "geometry": {"coordinates":[-104.615747,38.262817],"type":"Point"}
}