{
  "type": "Feature",
  "properties": {
    "addr:full":"2527 W 26th Ave Denver CO 80211",
    "addr:housenumber":"2527",
    "addr:postcode":"80211",
    "addr:street":"W 26Th Ave",
    "iso:country":"US",
    "sg:address":"2527 W 26th Ave",
    "sg:city":"Denver",
    "sg:classifiers":[
        {
            "category":"Restaurant",
            "type":"Food & Drink"
        }
    ],
    "sg:menulink":"http://www.allmenus.com/co/denver/274967-la-loma-restaurant/menu/",
    "sg:phone":"+1 303 433 3800",
    "sg:postcode":"80211",
    "sg:province":"CO",
    "sg:tags":[
        "mexican"
    ],
    "wof:name":"La Loma Restaurant",
    "wof:placetype":"venue"
},
  "geometry": {"coordinates":[-105.018227,39.754941],"type":"Point"}
}