{
  "type": "Feature",
  "properties": {
    "addr:full":"11919 Washington St Northglenn CO 80233",
    "addr:housenumber":"11919",
    "addr:postcode":"80233",
    "addr:street":"Washington St",
    "iso:country":"US",
    "sg:address":"11919 Washington St",
    "sg:city":"Northglenn",
    "sg:classifiers":[
        {
            "category":"Retail",
            "subcategory":"Car Wash",
            "type":"Services"
        }
    ],
    "sg:phone":"+1 303 255 1765",
    "sg:postcode":"80233",
    "sg:province":"CO",
    "sg:tags":[
        "operated",
        "polishing",
        "washing"
    ],
    "wof:name":"Mc Clintock's Classic Car Wash",
    "wof:placetype":"venue"
},
  "geometry": {"coordinates":[-104.978008,39.913029],"type":"Point"}
}