{
  "type": "Feature",
  "properties": {
    "iso:country":"US",
    "sg:address":"5 Inverness Dr E",
    "sg:city":"Englewood",
    "sg:classifiers":[
        {
            "category":"Mining & Drilling",
            "type":"Manufacturing & Wholesale Goods"
        }
    ],
    "sg:phone":"+1 303 799 9828",
    "sg:postcode":"80112",
    "sg:province":"CO",
    "sg:tags":[
        "crude",
        "gas",
        "production",
        "well"
    ],
    "wof:name":"Rim Companies  The",
    "wof:placetype":"venue"
},
  "geometry": {"coordinates":[-104.86447800000001,39.566847],"type":"Point"}
}