{
  "type": "Feature",
  "properties": {
    "iso:country":"US",
    "sg:address":"405 Breeze St",
    "sg:city":"Craig",
    "sg:classifiers":[
        {
            "category":"Retail",
            "subcategory":"Auto Repair",
            "type":"Services"
        }
    ],
    "sg:phone":"+1 970 826 2626",
    "sg:postcode":"81625",
    "sg:province":"CO",
    "sg:tags":[
        "body",
        "automobile",
        "painting"
    ],
    "wof:name":"C C Auto & Body",
    "wof:placetype":"venue"
},
  "geometry": {"coordinates":[-107.54842499999999,40.514166],"type":"Point"}
}