{
  "type": "Feature",
  "properties": {
    "iso:country":"US",
    "sg:address":"1770 S Buckley Rd",
    "sg:city":"Aurora",
    "sg:classifiers":[
        {
            "category":"Manufacturing",
            "subcategory":"Textiles",
            "type":"Manufacturing & Wholesale Goods"
        }
    ],
    "sg:phone":"+1 303 337 9905",
    "sg:postcode":"80017",
    "sg:province":"CO",
    "sg:tags":[
        "finishing",
        "plant",
        "cotton"
    ],
    "wof:name":"Buckley At Mexico Coin Laundry",
    "wof:placetype":"venue"
},
  "geometry": {"coordinates":[-104.790924,39.683254],"type":"Point"}
}