{
  "type": "Feature",
  "properties": {
    "addr:full":"1305 Elm Ave Loveland CO 80537",
    "addr:housenumber":"1305",
    "addr:postcode":"80537",
    "addr:street":"Elm Ave",
    "iso:country":"US",
    "sg:address":"1305 Elm Ave",
    "sg:city":"Loveland",
    "sg:classifiers":[
        {
            "category":"Building & Trades",
            "subcategory":"Plumbing",
            "type":"Services"
        }
    ],
    "sg:phone":"+1 970 667 3756",
    "sg:postcode":"80537",
    "sg:province":"CO",
    "sg:tags":[
        "contractor"
    ],
    "wof:name":"Big John Plumbing & Heating",
    "wof:placetype":"venue"
},
  "geometry": {"coordinates":[-105.11774,40.407371],"type":"Point"}
}