{
  "type": "Feature",
  "properties": {
    "iso:country":"US",
    "sg:address":"41184 US Hwy 24",
    "sg:city":"Avon",
    "sg:classifiers":[
        {
            "category":"Building & Trades",
            "subcategory":"Construction",
            "type":"Services"
        }
    ],
    "sg:phone":"+1 970 748 1368",
    "sg:postcode":"81620",
    "sg:province":"CO",
    "sg:tags":[
        "masonry",
        "contractor"
    ],
    "wof:name":"Gore Range Masonry",
    "wof:placetype":"venue"
},
  "geometry": {"coordinates":[-106.46891599999999,39.620803],"type":"Point"}
}