{
  "type": "Feature",
  "properties": {
    "iso:country":"US",
    "sg:address":"2201 S Townsend Ave",
    "sg:city":"Montrose",
    "sg:classifiers":[
        {
            "category":"Shopping",
            "subcategory":"Stationery & Office Supplies",
            "type":"Retail Goods"
        }
    ],
    "sg:phone":"+1 970 240 3859",
    "sg:postcode":"81401",
    "sg:province":"CO",
    "sg:website":"www.officedepot.com",
    "wof:name":"Office Depot",
    "wof:placetype":"venue"
},
  "geometry": {"coordinates":[-107.866202,38.462309],"type":"Point"}
}