{
  "type": "Feature",
  "properties": {
    "addr:full":"930 Pearl St Denver CO 80203",
    "addr:housenumber":"930",
    "addr:postcode":"80203",
    "addr:street":"Pearl St",
    "iso:country":"US",
    "sg:address":"930 Pearl St",
    "sg:city":"Denver",
    "sg:classifiers":[
        {
            "category":"Professional",
            "subcategory":"Business Services",
            "type":"Services"
        }
    ],
    "sg:phone":"+1 303 570 3315",
    "sg:postcode":"80203",
    "sg:province":"CO",
    "sg:tags":[
        "broker"
    ],
    "wof:name":"Verto Group",
    "wof:placetype":"venue"
},
  "geometry": {"coordinates":[-104.979754,39.731521],"type":"Point"}
}