{
  "type": "Feature",
  "properties": {
    "iso:country":"US",
    "sg:address":"50 Mount View Ln",
    "sg:city":"Colorado Springs",
    "sg:classifiers":[
        {
            "category":"Retail",
            "subcategory":"Auto Repair",
            "type":"Services"
        },
        {
            "category":"Wholesale",
            "subcategory":"Auto Parts",
            "type":"Manufacturing & Wholesale Goods"
        }
    ],
    "sg:phone":"+1 719 598 9188",
    "sg:postcode":"80907",
    "sg:province":"CO",
    "sg:tags":[
        "automotive",
        "clutches"
    ],
    "wof:name":"Clutch Service Wholesale",
    "wof:placetype":"venue"
},
  "geometry": {"coordinates":[-104.82118,38.889671],"type":"Point"}
}