{
  "type": "Feature",
  "properties": {
    "iso:country":"US",
    "sg:address":"7523 Grandview Ave",
    "sg:city":"Arvada",
    "sg:classifiers":[
        {
            "category":"Ice Cream",
            "type":"Food & Drink"
        }
    ],
    "sg:phone":"+1 303 431 2639",
    "sg:postcode":"80002",
    "sg:province":"CO",
    "sg:tags":[
        "frozen",
        "yogurt"
    ],
    "wof:name":"Scrumptious",
    "wof:placetype":"venue"
},
  "geometry": {"coordinates":[-105.081129,39.799464],"type":"Point"}
}