{
  "type": "Feature",
  "properties": {
    "addr:full":"5613 McWhinney Blvd Loveland CO 80538",
    "addr:housenumber":"5613",
    "addr:postcode":"80538",
    "addr:street":"Mcwhinney Blvd",
    "iso:country":"US",
    "sg:address":"5613 McWhinney Blvd",
    "sg:city":"Loveland",
    "sg:classifiers":[
        {
            "category":"Shopping",
            "type":"Retail Goods"
        },
        {
            "category":"Shopping",
            "subcategory":"Clothing, Apparel, & Fashions",
            "type":"Retail Goods"
        }
    ],
    "sg:phone":"+1 970 669 7002",
    "sg:postcode":"80538",
    "sg:province":"CO",
    "sg:tags":[
        "hosiery",
        "knit",
        "retailer",
        "factory",
        "outlet",
        "lady",
        "sportswear"
    ],
    "wof:name":"Jockey Factory Store",
    "wof:placetype":"venue"
},
  "geometry": {"coordinates":[-104.997782,40.410855],"type":"Point"}
}