{
  "type": "Feature",
  "properties": {
    "iso:country":"US",
    "sg:address":"8558 Sun Country Dr",
    "sg:city":"Elizabeth",
    "sg:classifiers":[
        {
            "category":"Building & Trades",
            "subcategory":"Plumbing",
            "type":"Services"
        }
    ],
    "sg:phone":"+1 303 680 6676",
    "sg:postcode":"80107",
    "sg:province":"CO",
    "sg:tags":[
        "heating",
        "contractor"
    ],
    "wof:name":"J & J Heating & Cooling Inc",
    "wof:placetype":"venue"
},
  "geometry": {"coordinates":[-104.509857,39.516701],"type":"Point"}
}