{
  "type": "Feature",
  "properties": {
    "iso:country":"US",
    "sg:address":"3300 28th St",
    "sg:city":"Boulder",
    "sg:classifiers":[
        {
            "category":"Real Estate",
            "subcategory":"Real Estate Services",
            "type":"Services"
        }
    ],
    "sg:phone":"+1 303 413 2384",
    "sg:postcode":"80301",
    "sg:province":"CO",
    "sg:tags":[
        "company",
        "title"
    ],
    "wof:name":"Guardian Title Agency LLC",
    "wof:placetype":"venue"
},
  "geometry": {"coordinates":[-105.258366,40.035082],"type":"Point"}
}