{
  "type": "Feature",
  "properties": {
    "iso:country":"US",
    "sg:address":"969 S Pearl St",
    "sg:city":"Denver",
    "sg:classifiers":[
        {
            "category":"Real Estate",
            "subcategory":"Real Estate Operator",
            "type":"Services"
        }
    ],
    "sg:phone":"+1 720 570 3914",
    "sg:postcode":"80209",
    "sg:province":"CO",
    "sg:tags":[
        "condominium"
    ],
    "wof:name":"South Pearl Commons Condo",
    "wof:placetype":"venue"
},
  "geometry": {"coordinates":[-104.980485,39.699715],"type":"Point"}
}