{
  "type": "Feature",
  "properties": {
    "iso:country":"US",
    "sg:address":"4930 Ashbrook Cir",
    "sg:city":"Littleton",
    "sg:classifiers":[
        {
            "category":"Professional",
            "subcategory":"Employment Agencies",
            "type":"Services"
        }
    ],
    "sg:phone":"+1 720 344 1012",
    "sg:postcode":"80130",
    "sg:province":"CO",
    "sg:tags":[
        "consultant",
        "search",
        "executive"
    ],
    "sg:website":"www.providerman.com",
    "wof:name":"Provider Management",
    "wof:placetype":"venue"
},
  "geometry": {"coordinates":[-104.930509,39.53134],"type":"Point"}
}