{
  "type": "Feature",
  "properties": {
    "iso:country":"US",
    "sg:address":"870 Dodge St",
    "sg:city":"Delta",
    "sg:classifiers":[
        {
            "category":"Social Services",
            "subcategory":"Child Care",
            "type":"Services"
        }
    ],
    "sg:phone":"+1 970 874 0418",
    "sg:postcode":"81416",
    "sg:province":"CO",
    "sg:tags":[
        "kindergarten",
        "academic",
        "school"
    ],
    "wof:name":"Rocky Mountain SER-Head Strt",
    "wof:placetype":"venue"
},
  "geometry": {"coordinates":[-108.07340499999999,38.7355],"type":"Point"}
}