{
  "type": "Feature",
  "properties": {
    "iso:country":"US",
    "sg:address":"1822 Skyway Dr",
    "sg:city":"Longmont",
    "sg:classifiers":[
        {
            "category":"Professional",
            "subcategory":"Testing Lab",
            "type":"Services"
        }
    ],
    "sg:phone":"+1 303 684 6650",
    "sg:postcode":"80504",
    "sg:province":"CO",
    "sg:tags":[
        "laboratory"
    ],
    "wof:name":"EMI Test Lab",
    "wof:placetype":"venue"
},
  "geometry": {"coordinates":[-105.021286,40.158084],"type":"Point"}
}