{
  "type": "Feature",
  "properties": {
    "addr:full":"601 Bross St Longmont CO 80501",
    "addr:housenumber":"601",
    "addr:postcode":"80501",
    "addr:street":"Bross St",
    "iso:country":"US",
    "sg:address":"601 Bross St",
    "sg:city":"Longmont",
    "sg:classifiers":[
        {
            "category":"Education",
            "subcategory":"Special Training",
            "type":"Public Place"
        }
    ],
    "sg:phone":"+1 303 776 0395",
    "sg:postcode":"80501",
    "sg:province":"CO",
    "sg:tags":[
        "center"
    ],
    "wof:name":"Anderson Educational Ctr",
    "wof:placetype":"venue"
},
  "geometry": {"coordinates":[-105.108537,40.170686],"type":"Point"}
}