{
  "type": "Feature",
  "properties": {
    "addr:full":"1660 Sherman St Denver CO 80203",
    "addr:housenumber":"1660",
    "addr:postcode":"80203",
    "addr:street":"Sherman St",
    "iso:country":"US",
    "sg:address":"1660 Sherman St",
    "sg:city":"Denver",
    "sg:classifiers":[
        {
            "category":"Organizations",
            "subcategory":"Religious Organization",
            "type":"Services"
        }
    ],
    "sg:phone":"+1 303 839 5500",
    "sg:postcode":"80203",
    "sg:province":"CO",
    "sg:tags":[
        "church"
    ],
    "sg:website":"www.centraldenver.com",
    "wof:name":"Central Presbyterian Church",
    "wof:placetype":"venue"
},
  "geometry": {"coordinates":[-104.98482199999999,39.742585],"type":"Point"}
}