{
  "type": "Feature",
  "properties": {
    "iso:country":"US",
    "sg:address":"5901 Dexter St",
    "sg:city":"Commerce City",
    "sg:classifiers":[
        {
            "category":"Freight",
            "type":"Transportation"
        }
    ],
    "sg:phone":"+1 303 293 8664",
    "sg:postcode":"80022",
    "sg:province":"CO",
    "sg:tags":[
        "hauling",
        "trucking"
    ],
    "wof:name":"Kalco Express Inc",
    "wof:placetype":"venue"
},
  "geometry": {"coordinates":[-104.93201000000001,39.804751],"type":"Point"}
}