{
  "type": "Feature",
  "properties": {
    "addr:full":"9203 Huron St Denver CO 80260",
    "addr:housenumber":"9203",
    "addr:postcode":"80260",
    "addr:street":"Huron St",
    "iso:country":"US",
    "sg:address":"9203 Huron St",
    "sg:city":"Denver",
    "sg:classifiers":[
        {
            "category":"Health Services",
            "subcategory":"Doctor",
            "type":"Services"
        }
    ],
    "sg:phone":"+1 303 429 2273",
    "sg:postcode":"80260",
    "sg:province":"CO",
    "sg:tags":[
        "dentist"
    ],
    "wof:name":"Comfort Dental",
    "wof:placetype":"venue"
},
  "geometry": {"coordinates":[-104.996757,39.865632],"type":"Point"}
}