{
  "type": "Feature",
  "properties": {
    "addr:full":"1605 N Academy Blvd Colorado Springs CO 80909",
    "addr:housenumber":"1605",
    "addr:postcode":"80909",
    "addr:street":"N Academy Blvd",
    "iso:country":"US",
    "sg:address":"1605 N Academy Blvd",
    "sg:city":"Colorado Springs",
    "sg:classifiers":[
        {
            "category":"Recreation",
            "subcategory":"Amusement Park",
            "type":"Entertainment"
        }
    ],
    "sg:phone":"+1 719 570 1115",
    "sg:postcode":"80909",
    "sg:province":"CO",
    "sg:tags":[
        "park"
    ],
    "wof:name":"Laser Quest Inc",
    "wof:placetype":"venue"
},
  "geometry": {"coordinates":[-104.756377,38.85536],"type":"Point"}
}