{
  "type": "Feature",
  "properties": {
    "addr:full":"410 5th St Paonia CO 81428",
    "addr:housenumber":"410",
    "addr:postcode":"81428",
    "addr:street":"5Th St",
    "iso:country":"US",
    "sg:address":"410 5th St",
    "sg:city":"Paonia",
    "sg:classifiers":[
        {
            "category":"Retail",
            "subcategory":"Auto Repair",
            "type":"Services"
        }
    ],
    "sg:phone":"+1 970 527 5262",
    "sg:postcode":"81428",
    "sg:province":"CO",
    "sg:tags":[
        "repairing",
        "automobile"
    ],
    "wof:name":"A-Z Automotive",
    "wof:placetype":"venue"
},
  "geometry": {"coordinates":[-107.596648,38.871436],"type":"Point"}
}