{
  "type": "Feature",
  "properties": {
    "iso:country":"US",
    "sg:address":"5501 S Broadway",
    "sg:city":"Littleton",
    "sg:classifiers":[
        {
            "category":"Professional",
            "type":"Services"
        }
    ],
    "sg:phone":"+1 720 283 6350",
    "sg:postcode":"80121",
    "sg:province":"CO",
    "wof:name":"Genet Tassema",
    "wof:placetype":"venue"
},
  "geometry": {"coordinates":[-104.988039,39.61502],"type":"Point"}
}