{
  "type": "Feature",
  "properties": {
    "addr:full":"14500 W Colfax Ave Unit 548 Lakewood CO 80401",
    "addr:housenumber":"14500;548",
    "addr:postcode":"80401",
    "addr:street":"W Colfax Ave Unit",
    "iso:country":"US",
    "sg:address":"14500 W Colfax Ave Unit 548",
    "sg:city":"Lakewood",
    "sg:phone":"+1 303 277 1640",
    "sg:postcode":"80401",
    "sg:province":"CO",
    "sg:website":"http://www.orangejulius.com",
    "wof:name":"Dairy Queen",
    "wof:placetype":"venue"
},
  "geometry": {"coordinates":[-105.159637,39.73481],"type":"Point"}
}