{
  "type": "Feature",
  "properties": {
    "addr:full":"19818 E Girard Dr Aurora CO 80013",
    "addr:housenumber":"19818",
    "addr:postcode":"80013",
    "addr:street":"E Girard Dr",
    "iso:country":"US",
    "sg:address":"19818 E Girard Dr",
    "sg:city":"Aurora",
    "sg:classifiers":[
        {
            "category":"Building & Trades",
            "subcategory":"Construction",
            "type":"Services"
        }
    ],
    "sg:phone":"+1 720 870 9941",
    "sg:postcode":"80013",
    "sg:province":"CO",
    "sg:tags":[
        "carpentry",
        "contractor"
    ],
    "wof:name":"Precision Framing",
    "wof:placetype":"venue"
},
  "geometry": {"coordinates":[-104.75665499999999,39.654206],"type":"Point"}
}