{
  "type": "Feature",
  "properties": {
    "iso:country":"US",
    "sg:address":"1900 Wazee St",
    "sg:city":"Denver",
    "sg:classifiers":[
        {
            "category":"Professional",
            "subcategory":"Computer Services",
            "type":"Services"
        }
    ],
    "sg:phone":"+1 303 291 0246",
    "sg:postcode":"80202",
    "sg:province":"CO",
    "sg:tags":[
        "home",
        "consulting",
        "page",
        "dev",
        "internet"
    ],
    "sg:website":"www.creationchamber.com",
    "wof:name":"Creation Chamber Inc",
    "wof:placetype":"venue"
},
  "geometry": {"coordinates":[-104.995148,39.754992],"type":"Point"}
}