{
  "type": "Feature",
  "properties": {
    "iso:country":"US",
    "sg:address":"720 N Main St",
    "sg:city":"Pueblo",
    "sg:classifiers":[
        {
            "category":"Building & Trades",
            "subcategory":"Cleaning & Sanitation",
            "type":"Services"
        }
    ],
    "sg:phone":"+1 719 545 0475",
    "sg:postcode":"81003",
    "sg:province":"CO",
    "sg:tags":[
        "janitor"
    ],
    "wof:name":"FBG Corp",
    "wof:placetype":"venue"
},
  "geometry": {"coordinates":[-104.608575,38.274155],"type":"Point"}
}