{
  "type": "Feature",
  "properties": {
    "iso:country":"US",
    "sg:address":"526 Main St",
    "sg:city":"Wray",
    "sg:classifiers":[
        {
            "category":"Professional",
            "type":"Services"
        }
    ],
    "sg:phone":"+1 970 332 4883",
    "sg:postcode":"80758",
    "sg:province":"CO",
    "wof:name":"Conrad Shaw",
    "wof:placetype":"venue"
},
  "geometry": {"coordinates":[-102.222005,40.076698],"type":"Point"}
}