{
  "type": "Feature",
  "properties": {
    "iso:country":"US",
    "sg:address":"31 W Main St",
    "sg:city":"Alpine",
    "sg:classifiers":[
        {
            "category":"Professional",
            "type":"Services"
        }
    ],
    "sg:phone":"+1 201 784 0335",
    "sg:postcode":"81140",
    "sg:province":"CO",
    "sg:tags":[
        "establishment"
    ],
    "wof:name":"Joong Kim Log",
    "wof:placetype":"venue"
},
  "geometry": {"coordinates":[-105.964299,37.275719],"type":"Point"}
}