{
  "type": "Feature",
  "properties": {
    "iso:country":"US",
    "sg:address":"3855 Interpark Dr",
    "sg:city":"Colorado Springs",
    "sg:classifiers":[
        {
            "category":"Wholesale",
            "subcategory":"Construction Materials",
            "type":"Manufacturing & Wholesale Goods"
        }
    ],
    "sg:phone":"+1 719 632 4298",
    "sg:postcode":"80907",
    "sg:province":"CO",
    "sg:tags":[
        "equipment",
        "roofing",
        "supply"
    ],
    "sg:website":"www.alliedbuilding.com",
    "wof:name":"Allied Building Products Corp",
    "wof:placetype":"venue"
},
  "geometry": {"coordinates":[-104.83062700000001,38.887965],"type":"Point"}
}