{
  "type": "Feature",
  "properties": {
    "addr:full":"3220 W 24th Ave Denver CO 80211",
    "addr:housenumber":"3220",
    "addr:postcode":"80211",
    "addr:street":"W 24Th Ave",
    "iso:country":"US",
    "sg:address":"3220 W 24th Ave",
    "sg:city":"Denver",
    "sg:classifiers":[
        {
            "category":"Shopping",
            "subcategory":"Used Merchandise",
            "type":"Retail Goods"
        }
    ],
    "sg:phone":"+1 303 935 2266",
    "sg:postcode":"80211",
    "sg:province":"CO",
    "sg:tags":[
        "shop",
        "thrift"
    ],
    "wof:name":"Cache Closet",
    "wof:placetype":"venue"
},
  "geometry": {"coordinates":[-105.029645,39.75234],"type":"Point"}
}