{
  "type": "Feature",
  "properties": {
    "addr:full":"7426 S Quince Ct Englewood CO 80112",
    "addr:housenumber":"7426",
    "addr:postcode":"80112",
    "addr:street":"S Quince Ct",
    "iso:country":"US",
    "sg:address":"7426 S Quince Ct",
    "sg:city":"Englewood",
    "sg:classifiers":[
        {
            "category":"Real Estate",
            "subcategory":"Real Estate Operator",
            "type":"Services"
        }
    ],
    "sg:phone":"+1 303 796 7531",
    "sg:postcode":"80112",
    "sg:province":"CO",
    "sg:tags":[
        "building",
        "nonresidential"
    ],
    "wof:name":"Loke Properties",
    "wof:placetype":"venue"
},
  "geometry": {"coordinates":[-104.901805,39.581336],"type":"Point"}
}