{
  "type": "Feature",
  "properties": {
    "iso:country":"US",
    "sg:address":"2717 Glenwood Dr",
    "sg:city":"Boulder",
    "sg:classifiers":[
        {
            "category":"Building & Trades",
            "subcategory":"Construction",
            "type":"Services"
        }
    ],
    "sg:phone":"+1 720 565 0317",
    "sg:postcode":"80304",
    "sg:province":"CO",
    "sg:tags":[
        "house"
    ],
    "wof:name":"Top Shelf Construction",
    "wof:placetype":"venue"
},
  "geometry": {"coordinates":[-105.261234,40.032879],"type":"Point"}
}