{
  "type": "Feature",
  "properties": {
    "addr:full":"490 Utica Ave Boulder CO 80304",
    "addr:housenumber":"490",
    "addr:postcode":"80304",
    "addr:street":"Utica Ave",
    "iso:country":"US",
    "sg:address":"490 Utica Ave",
    "sg:city":"Boulder",
    "sg:classifiers":[
        {
            "category":"Wholesale",
            "subcategory":"Drugs",
            "type":"Manufacturing & Wholesale Goods"
        }
    ],
    "sg:phone":"+1 303 544 9220",
    "sg:postcode":"80304",
    "sg:province":"CO",
    "wof:name":"Enrich Distributors",
    "wof:placetype":"venue"
},
  "geometry": {"coordinates":[-105.291507,40.052697],"type":"Point"}
}