{
  "type": "Feature",
  "properties": {
    "addr:full":"426 S Arthur Ave Louisville CO 80027",
    "addr:housenumber":"426",
    "addr:postcode":"80027",
    "addr:street":"S Arthur Ave",
    "iso:country":"US",
    "sg:address":"426 S Arthur Ave",
    "sg:city":"Louisville",
    "sg:classifiers":[
        {
            "category":"Home & Garden",
            "subcategory":"Hardware",
            "type":"Retail Goods"
        },
        {
            "category":"Home & Garden",
            "subcategory":"Building Materials",
            "type":"Retail Goods"
        }
    ],
    "sg:phone":"+1 303 666 2200",
    "sg:postcode":"80027",
    "sg:province":"CO",
    "sg:tags":[
        "store"
    ],
    "wof:name":"Parker Store",
    "wof:placetype":"venue"
},
  "geometry": {"coordinates":[-105.123257,39.960684],"type":"Point"}
}