{
  "type": "Feature",
  "properties": {
    "iso:country":"US",
    "sg:address":"1219 W Mountain Ave",
    "sg:city":"Fort Collins",
    "sg:classifiers":[
        {
            "category":"Professional",
            "type":"Services"
        }
    ],
    "sg:phone":"+1 970 221 5923",
    "sg:postcode":"80521",
    "sg:province":"CO",
    "wof:name":"Joel Nevison",
    "wof:placetype":"venue"
},
  "geometry": {"coordinates":[-105.09795200000001,40.587026],"type":"Point"}
}