{
  "type": "Feature",
  "properties": {
    "iso:country":"US",
    "sg:address":"19 E Kiowa St",
    "sg:city":"Colorado Springs",
    "sg:classifiers":[
        {
            "category":"Bars & Pubs",
            "type":"Food & Drink"
        }
    ],
    "sg:phone":"+1 719 471 8622",
    "sg:postcode":"80903",
    "sg:province":"CO",
    "sg:tags":[
        "drinking"
    ],
    "wof:name":"Crl Enterprises Inc",
    "wof:placetype":"venue"
},
  "geometry": {"coordinates":[-104.824569,38.835267],"type":"Point"}
}