{
  "type": "Feature",
  "properties": {
    "iso:country":"US",
    "sg:address":"135 W 3rd St",
    "sg:city":"Wray",
    "sg:classifiers":[
        {
            "category":"Retail",
            "subcategory":"Repair Shop",
            "type":"Services"
        }
    ],
    "sg:phone":"+1 970 332 4411",
    "sg:postcode":"80758",
    "sg:province":"CO",
    "sg:tags":[
        "appliance"
    ],
    "wof:name":"Lukas Appliance & Refrig",
    "wof:placetype":"venue"
},
  "geometry": {"coordinates":[-102.222391,40.079001],"type":"Point"}
}