{
  "type": "Feature",
  "properties": {
    "addr:full":"445 E Cheyenne Mountain Blvd Colorado Springs CO 80906",
    "addr:housenumber":"445",
    "addr:postcode":"80906",
    "addr:street":"E Cheyenne Mountain Blvd",
    "iso:country":"US",
    "sg:address":"445 E Cheyenne Mountain Blvd",
    "sg:city":"Colorado Springs",
    "sg:classifiers":[
        {
            "category":"Building & Trades",
            "subcategory":"Construction",
            "type":"Services"
        }
    ],
    "sg:phone":"+1 719 633 2998",
    "sg:postcode":"80906",
    "sg:province":"CO",
    "sg:tags":[
        "contractor"
    ],
    "wof:name":"El Paso Cnty Rofg Contrs Assoc",
    "wof:placetype":"venue"
},
  "geometry": {"coordinates":[-104.820069,38.788456],"type":"Point"}
}