{
  "type": "Feature",
  "properties": {
    "iso:country":"US",
    "sg:address":"29551 Co Rd 357",
    "sg:city":"Buena Vista",
    "sg:classifiers":[
        {
            "category":"Professional",
            "subcategory":"Accounting & Tax Preparation",
            "type":"Services"
        }
    ],
    "sg:phone":"+1 719 395 4804",
    "sg:postcode":"81211",
    "sg:province":"CO",
    "sg:tags":[
        "accountant"
    ],
    "wof:name":"B & C Bookkeeping Inc",
    "wof:placetype":"venue"
},
  "geometry": {"coordinates":[-106.163769,38.850608],"type":"Point"}
}