{
  "type": "Feature",
  "properties": {
    "addr:full":"2630 S Broadway Denver CO 80210",
    "addr:housenumber":"2630",
    "addr:postcode":"80210",
    "addr:street":"S Broadway",
    "iso:country":"US",
    "sg:address":"2630 S Broadway",
    "sg:city":"Denver",
    "sg:classifiers":[
        {
            "category":"Retail",
            "subcategory":"Auto Repair",
            "type":"Services"
        }
    ],
    "sg:phone":"+1 303 761 8841",
    "sg:postcode":"80210",
    "sg:province":"CO",
    "sg:website":"www.cottmandenver.com",
    "wof:name":"Cottman Transmission Center",
    "wof:placetype":"venue"
},
  "geometry": {"coordinates":[-104.98771499999999,39.669072],"type":"Point"}
}