{
  "type": "Feature",
  "properties": {
    "iso:country":"US",
    "sg:address":"2630 S Broadway",
    "sg:city":"Denver",
    "sg:classifiers":[
        {
            "category":"Retail",
            "subcategory":"Auto Repair",
            "type":"Services"
        }
    ],
    "sg:phone":"+1 303 761 8841",
    "sg:postcode":"80210",
    "sg:province":"CO",
    "sg:website":"www.cottmandenver.com",
    "wof:name":"Cottman Transmission Center",
    "wof:placetype":"venue"
},
  "geometry": {"coordinates":[-104.987715,39.669072],"type":"Point"}
}