{
  "type": "Feature",
  "properties": {
    "addr:full":"30 W Dale St Colorado Springs CO 80903",
    "addr:housenumber":"30",
    "addr:postcode":"80903",
    "addr:street":"W Dale St",
    "iso:country":"US",
    "sg:address":"30 W Dale St",
    "sg:city":"Colorado Springs",
    "sg:classifiers":[
        {
            "category":"Arts & Performance",
            "subcategory":"Theater",
            "type":"Entertainment"
        }
    ],
    "sg:phone":"+1 719 634 5581",
    "sg:postcode":"80903",
    "sg:province":"CO",
    "sg:tags":[
        "school",
        "art",
        "center",
        "museum",
        "performing",
        "library"
    ],
    "wof:name":"Colorado Springs Fine Arts Ctr",
    "wof:placetype":"venue"
},
  "geometry": {"coordinates":[-104.826673,38.845118],"type":"Point"}
}