{
  "type": "Feature",
  "properties": {
    "iso:country":"US",
    "sg:address":"2343 Aspen Brook Dr",
    "sg:city":"Estes Park",
    "sg:classifiers":[
        {
            "category":"Travel",
            "subcategory":"Hotels & Motels",
            "type":"Entertainment"
        }
    ],
    "sg:phone":"+1 970 586 3748",
    "sg:postcode":"80517",
    "sg:province":"CO",
    "sg:tags":[
        "resort"
    ],
    "sg:website":"www.aspenbrook.com",
    "wof:name":"Aspen Brook",
    "wof:placetype":"venue"
},
  "geometry": {"coordinates":[-105.567041,40.349522],"type":"Point"}
}