{
  "type": "Feature",
  "properties": {
    "addr:full":"475 Circle Dr Evergreen CO 80439",
    "addr:housenumber":"475",
    "addr:postcode":"80439",
    "addr:street":"Circle Dr",
    "iso:country":"US",
    "sg:address":"475 Circle Dr",
    "sg:city":"Evergreen",
    "sg:classifiers":[
        {
            "category":"Building & Trades",
            "subcategory":"Construction",
            "type":"Services"
        }
    ],
    "sg:phone":"+1 303 670 2067",
    "sg:postcode":"80439",
    "sg:province":"CO",
    "sg:tags":[
        "carpentry",
        "contractor"
    ],
    "wof:name":"Sjo LLC",
    "wof:placetype":"venue"
},
  "geometry": {"coordinates":[-105.412496,39.693372],"type":"Point"}
}