{
  "type": "Feature",
  "properties": {
    "iso:country":"US",
    "sg:address":"845 Wadsworth Blvd",
    "sg:city":"Lakewood",
    "sg:classifiers":[
        {
            "category":"Home & Garden",
            "subcategory":"Garden Supply",
            "type":"Retail Goods"
        }
    ],
    "sg:phone":"+1 303 465 2226",
    "sg:postcode":"80214",
    "sg:province":"CO",
    "sg:tags":[
        "nursery",
        "gardening"
    ],
    "sg:website":"www.jensensflowerandgarden.com",
    "wof:name":"Jensen's Flower and Garden",
    "wof:placetype":"venue"
},
  "geometry": {"coordinates":[-105.081621,39.730218],"type":"Point"}
}