{
  "type": "Feature",
  "properties": {
    "iso:country":"US",
    "sg:address":"8925 S Ridgeline Blvd",
    "sg:city":"Littleton",
    "sg:classifiers":[
        {
            "category":"Professional",
            "subcategory":"Accounting & Tax Preparation",
            "type":"Services"
        }
    ],
    "sg:phone":"+1 303 791 6080",
    "sg:postcode":"80129",
    "sg:province":"CO",
    "sg:tags":[
        "accountant"
    ],
    "wof:name":"Brashier & Foss",
    "wof:placetype":"venue"
},
  "geometry": {"coordinates":[-104.996594,39.554365],"type":"Point"}
}