{
  "type": "Feature",
  "properties": {
    "iso:country":"US",
    "sg:address":"555 Santa Fe Dr",
    "sg:city":"Denver",
    "sg:classifiers":[
        {
            "category":"Building & Trades",
            "subcategory":"Landscaping Services",
            "type":"Services"
        }
    ],
    "sg:phone":"+1 303 825 0484",
    "sg:postcode":"80204",
    "sg:province":"CO",
    "sg:tags":[
        "lawn",
        "care",
        "maintenance",
        "grounds"
    ],
    "wof:name":"All-Pro Lawn Care Inc",
    "wof:placetype":"venue"
},
  "geometry": {"coordinates":[-104.998648,39.724837],"type":"Point"}
}