{
  "type": "Feature",
  "properties": {
    "iso:country":"US",
    "sg:address":"405 22nd St",
    "sg:city":"Greeley",
    "sg:classifiers":[
        {
            "category":"Building & Trades",
            "subcategory":"Construction",
            "type":"Services"
        }
    ],
    "sg:phone":"+1 970 482 5784",
    "sg:postcode":"80631",
    "sg:province":"CO",
    "sg:tags":[
        "contractor"
    ],
    "wof:name":"Independent Roofing Inc",
    "wof:placetype":"venue"
},
  "geometry": {"coordinates":[-104.68424899999999,40.402507],"type":"Point"}
}