{
  "type": "Feature",
  "properties": {
    "iso:country":"US",
    "sg:address":"1101 Sunrise Ln",
    "sg:city":"Estes Park",
    "sg:classifiers":[
        {
            "category":"Retail",
            "subcategory":"Repair Shop",
            "type":"Services"
        }
    ],
    "sg:phone":"+1 970 586 5650",
    "sg:postcode":"80517",
    "sg:province":"CO",
    "sg:tags":[
        "repairing",
        "piano",
        "refinishing"
    ],
    "wof:name":"Carl E Burgenger Piano Tuning",
    "wof:placetype":"venue"
},
  "geometry": {"coordinates":[-105.543077,40.368519],"type":"Point"}
}