{
  "type": "Feature",
  "properties": {
    "iso:country":"US",
    "sg:address":"2770 E Uintah St",
    "sg:city":"Colorado Springs",
    "sg:classifiers":[
        {
            "category":"Real Estate",
            "subcategory":"Real Estate Operator",
            "type":"Services"
        }
    ],
    "sg:phone":"+1 719 632 4700",
    "sg:postcode":"80909",
    "sg:province":"CO",
    "sg:tags":[
        "apartment"
    ],
    "wof:name":"Devonshire Square Apartments",
    "wof:placetype":"venue"
},
  "geometry": {"coordinates":[-104.775933,38.849046],"type":"Point"}
}