{
  "type": "Feature",
  "properties": {
    "addr:full":"950 Lashley St Longmont CO 80501",
    "addr:housenumber":"950",
    "addr:postcode":"80501",
    "addr:street":"Lashley St",
    "iso:country":"US",
    "sg:address":"950 Lashley St",
    "sg:city":"Longmont",
    "sg:classifiers":[
        {
            "category":"Social Services",
            "subcategory":"Child Care",
            "type":"Services"
        }
    ],
    "sg:phone":"+1 303 776 2003",
    "sg:postcode":"80501",
    "sg:province":"CO",
    "sg:tags":[
        "day"
    ],
    "wof:name":"YMCA Preschool",
    "wof:placetype":"venue"
},
  "geometry": {"coordinates":[-105.088205,40.176294],"type":"Point"}
}