{
  "type": "Feature",
  "properties": {
    "addr:full":"21200 Rd U Cortez CO 81321",
    "addr:postcode":"21200;81321",
    "addr:street":"Rd U",
    "iso:country":"US",
    "sg:address":"21200 Rd U",
    "sg:city":"Cortez",
    "sg:classifiers":[
        {
            "category":"Shopping",
            "type":"Retail Goods"
        }
    ],
    "sg:phone":"+1 970 882 4041",
    "sg:postcode":"81321",
    "sg:province":"CO",
    "sg:tags":[
        "trophy",
        "medal",
        "award"
    ],
    "wof:name":"All Star Ribbon Mfg",
    "wof:placetype":"venue"
},
  "geometry": {"coordinates":[-108.658721,37.471543],"type":"Point"}
}