{
  "type": "Feature",
  "properties": {
    "addr:full":"600 S Airport Rd Longmont CO 80503",
    "addr:housenumber":"600",
    "addr:postcode":"longmont;80503",
    "addr:street":"S Airport Rd",
    "iso:country":"US",
    "sg:address":"600 S Airport Rd",
    "sg:city":"Longmont",
    "sg:classifiers":[
        {
            "category":"Insurance",
            "subcategory":"Insurance Agent",
            "type":"Services"
        }
    ],
    "sg:phone":"+1 303 772 3072",
    "sg:postcode":"80503",
    "sg:province":"CO",
    "wof:name":"Allstate Insurance",
    "wof:placetype":"venue"
},
  "geometry": {"coordinates":[-105.154461,40.152126],"type":"Point"}
}