{
  "type": "Feature",
  "properties": {
    "iso:country":"US",
    "sg:address":"5 Maroon Dr",
    "sg:city":"Carbondale",
    "sg:classifiers":[
        {
            "category":"Shopping",
            "subcategory":"Crafts & Fabrics",
            "type":"Retail Goods"
        }
    ],
    "sg:phone":"+1 970 963 0894",
    "sg:postcode":"81623",
    "sg:province":"CO",
    "sg:tags":[
        "sewing"
    ],
    "wof:name":"Home Stitchery",
    "wof:placetype":"venue"
},
  "geometry": {"coordinates":[-107.208044,39.397196],"type":"Point"}
}