{
  "type": "Feature",
  "properties": {
    "iso:country":"US",
    "sg:address":"599 Pioneer Rd",
    "sg:city":"Grand Junction",
    "sg:classifiers":[
        {
            "category":"Professional",
            "type":"Services"
        }
    ],
    "sg:phone":"+1 970 245 0004",
    "sg:postcode":"81504",
    "sg:province":"CO",
    "wof:name":"Audie Williams",
    "wof:placetype":"venue"
},
  "geometry": {"coordinates":[-108.50375699999999,39.090768],"type":"Point"}
}