{
  "type": "Feature",
  "properties": {
    "iso:country":"US",
    "sg:address":"4315 E 115th Ave",
    "sg:city":"Denver",
    "sg:classifiers":[
        {
            "category":"Wholesale",
            "subcategory":"Vending Machines",
            "type":"Manufacturing & Wholesale Goods"
        }
    ],
    "sg:phone":"+1 303 451 5558",
    "sg:postcode":"80233",
    "sg:province":"CO",
    "sg:tags":[
        "operator"
    ],
    "wof:name":"Lefebvre Enterprises",
    "wof:placetype":"venue"
},
  "geometry": {"coordinates":[-104.93706299999999,39.904161],"type":"Point"}
}