{
  "type": "Feature",
  "properties": {
    "addr:full":"801 E 4th St Akron CO 80720",
    "addr:housenumber":"801",
    "addr:postcode":"80720",
    "addr:street":"E 4Th St",
    "iso:country":"US",
    "sg:address":"801 E 4th St",
    "sg:city":"Akron",
    "sg:classifiers":[
        {
            "category":"Building & Trades",
            "subcategory":"Construction",
            "type":"Services"
        }
    ],
    "sg:phone":"+1 970 345 2087",
    "sg:postcode":"80720",
    "sg:province":"CO",
    "sg:tags":[
        "general",
        "contractor"
    ],
    "wof:name":"Glosson Construction Company",
    "wof:placetype":"venue"
},
  "geometry": {"coordinates":[-103.20187300000001,40.162544],"type":"Point"}
}