{
  "type": "Feature",
  "properties": {
    "iso:country":"US",
    "sg:address":"109 Main St",
    "sg:city":"Breckenridge",
    "sg:classifiers":[
        {
            "category":"Shopping",
            "subcategory":"Clothing, Apparel, & Fashions",
            "type":"Retail Goods"
        }
    ],
    "sg:phone":"+1 970 547 4570",
    "sg:postcode":"80424",
    "sg:province":"CO",
    "sg:tags":[
        "t"
    ],
    "wof:name":"Artic Attitude",
    "wof:placetype":"venue"
},
  "geometry": {"coordinates":[-106.046201,39.481705],"type":"Point"}
}