{
  "type": "Feature",
  "properties": {
    "addr:full":"15280 E Iliff Ave Aurora CO 80014",
    "addr:housenumber":"15280",
    "addr:postcode":"80014",
    "addr:street":"E Iliff Ave",
    "iso:country":"US",
    "sg:address":"15280 E Iliff Ave",
    "sg:city":"Aurora",
    "sg:classifiers":[
        {
            "category":"Fast Food",
            "type":"Food & Drink"
        },
        {
            "category":"Restaurant",
            "type":"Food & Drink"
        }
    ],
    "sg:phone":"+1 720 747 9542",
    "sg:postcode":"80014",
    "sg:province":"CO",
    "sg:tags":[
        "grill",
        "style",
        "mexican",
        "family",
        "take",
        "bar"
    ],
    "sg:website":"http://www.chipolte.com",
    "wof:name":"Chipotle",
    "wof:placetype":"venue"
},
  "geometry": {"coordinates":[-104.810227,39.67474],"type":"Point"}
}