{
  "type": "Feature",
  "properties": {
    "iso:country":"US",
    "sg:address":"2171 S Trenton Way",
    "sg:city":"Denver",
    "sg:classifiers":[
        {
            "category":"Retail",
            "subcategory":"Auto Rental",
            "type":"Services"
        }
    ],
    "sg:phone":"+1 303 752 0234",
    "sg:postcode":"80231",
    "sg:province":"CO",
    "sg:tags":[
        "car"
    ],
    "wof:name":"Southwest Leasing",
    "wof:placetype":"venue"
},
  "geometry": {"coordinates":[-104.896517,39.677452],"type":"Point"}
}