{
  "type": "Feature",
  "properties": {
    "addr:full":"5847 Palmer Park Blvd Colorado Springs CO 80915",
    "addr:housenumber":"5847",
    "addr:postcode":"80915",
    "addr:street":"Palmer Park Blvd",
    "iso:country":"US",
    "sg:address":"5847 Palmer Park Blvd",
    "sg:city":"Colorado Springs",
    "sg:classifiers":[
        {
            "category":"Food & Beverages",
            "subcategory":"Liquor & Beverages",
            "type":"Retail Goods"
        }
    ],
    "sg:phone":"+1 719 596 4700",
    "sg:postcode":"80915",
    "sg:province":"CO",
    "sg:tags":[
        "store"
    ],
    "sg:website":"www.powersliquor.com",
    "wof:name":"Powers Liquor Mart LLC",
    "wof:placetype":"venue"
},
  "geometry": {"coordinates":[-104.71967100000001,38.857016],"type":"Point"}
}