{
  "type": "Feature",
  "properties": {
    "iso:country":"US",
    "sg:address":"8690 Wolff Ct",
    "sg:city":"Westminster",
    "sg:classifiers":[
        {
            "category":"Banks & Credit Unions",
            "subcategory":"Bank",
            "type":"Services"
        }
    ],
    "sg:phone":"+1 303 428 2200",
    "sg:postcode":"80031",
    "sg:province":"CO",
    "sg:tags":[
        "financing",
        "factoring"
    ],
    "wof:name":"First Eagle Funding Corp",
    "wof:placetype":"venue"
},
  "geometry": {"coordinates":[-105.049345,39.854499],"type":"Point"}
}