{
  "type": "Feature",
  "properties": {
    "addr:full":"21601 E Rowland Pl Aurora CO 80016",
    "addr:housenumber":"21601",
    "addr:postcode":"80016",
    "addr:street":"E Rowland Pl",
    "iso:country":"US",
    "sg:address":"21601 E Rowland Pl",
    "sg:city":"Aurora",
    "sg:classifiers":[
        {
            "category":"Insurance",
            "subcategory":"Insurance Agent",
            "type":"Services"
        }
    ],
    "sg:phone":"+1 303 699 5158",
    "sg:postcode":"80016",
    "sg:province":"CO",
    "wof:name":"Raymond Burns",
    "wof:placetype":"venue"
},
  "geometry": {"coordinates":[-104.73563300000001,39.587604],"type":"Point"}
}