{
  "type": "Feature",
  "properties": {
    "iso:country":"US",
    "sg:address":"3933 Highplains Dr",
    "sg:city":"Berthoud",
    "sg:classifiers":[
        {
            "category":"Building & Trades",
            "subcategory":"Construction",
            "type":"Services"
        }
    ],
    "sg:phone":"+1 303 651 2178",
    "sg:postcode":"80513",
    "sg:province":"CO",
    "sg:tags":[
        "excavation",
        "contractor"
    ],
    "wof:name":"Dzbzx Kavating Inc",
    "wof:placetype":"venue"
},
  "geometry": {"coordinates":[-105.149494,40.271975],"type":"Point"}
}