{
  "type": "Feature",
  "properties": {
    "iso:country":"US",
    "sg:address":"34500 Co Rd 13",
    "sg:city":"Lamar",
    "sg:phone":"+1 719 336 2169",
    "sg:postcode":"81052",
    "sg:province":"CO",
    "sg:tags":[
        "farm",
        "field",
        "corn",
        "crop"
    ],
    "wof:name":"Flint Lawrence",
    "wof:placetype":"venue"
},
  "geometry": {"coordinates":[-102.52117200000001,38.139848],"type":"Point"}
}