{
  "type": "Feature",
  "properties": {
    "iso:country":"US",
    "sg:address":"9777 Race St",
    "sg:city":"Denver",
    "sg:classifiers":[
        {
            "category":"Building & Trades",
            "subcategory":"Construction",
            "type":"Services"
        }
    ],
    "sg:phone":"+1 720 929 9434",
    "sg:postcode":"80229",
    "sg:province":"CO",
    "sg:tags":[
        "house"
    ],
    "wof:name":"Juan E Urbina Construction",
    "wof:placetype":"venue"
},
  "geometry": {"coordinates":[-104.963705,39.87507],"type":"Point"}
}