{
  "type": "Feature",
  "properties": {
    "addr:full":"701 N Union Blvd Colorado Springs CO 80909",
    "addr:housenumber":"701",
    "addr:postcode":"80909",
    "addr:street":"N Union Blvd",
    "iso:country":"US",
    "sg:address":"701 N Union Blvd",
    "sg:city":"Colorado Springs",
    "sg:classifiers":[
        {
            "category":"Autos & Motor Vehicles",
            "subcategory":"Fuel & Gas Station",
            "type":"Retail Goods"
        }
    ],
    "sg:phone":"+1 719 633 2854",
    "sg:postcode":"80909",
    "sg:province":"CO",
    "sg:tags":[
        "grocery",
        "station",
        "gasoline",
        "oil"
    ],
    "wof:name":"Conoco Station Union",
    "wof:placetype":"venue"
},
  "geometry": {"coordinates":[-104.794275,38.843624],"type":"Point"}
}