{
  "type": "Feature",
  "properties": {
    "iso:country":"US",
    "sg:address":"15542 Higgins Ave",
    "sg:city":"Fort Lupton",
    "sg:classifiers":[
        {
            "category":"Shopping",
            "subcategory":"Gifts & Souvenirs",
            "type":"Retail Goods"
        }
    ],
    "sg:phone":"+1 303 857 9261",
    "sg:postcode":"80621",
    "sg:province":"CO",
    "wof:name":"Fun E Farm Creations",
    "wof:placetype":"venue"
},
  "geometry": {"coordinates":[-104.76429,40.108514],"type":"Point"}
}