{
  "type": "Feature",
  "properties": {
    "iso:country":"US",
    "sg:address":"5125 Centennial Blvd",
    "sg:city":"Colorado Springs",
    "sg:classifiers":[
        {
            "category":"Wholesale",
            "subcategory":"Jewelry",
            "type":"Manufacturing & Wholesale Goods"
        }
    ],
    "sg:phone":"+1 719 536 0009",
    "sg:postcode":"80919",
    "sg:province":"CO",
    "sg:tags":[
        "diamond",
        "jeweler"
    ],
    "wof:name":"Richa Creations",
    "wof:placetype":"venue"
},
  "geometry": {"coordinates":[-104.86093,38.903714],"type":"Point"}
}