{
  "type": "Feature",
  "properties": {
    "iso:country":"US",
    "sg:address":"1595 Briargate Blvd",
    "sg:city":"Colorado Springs",
    "sg:classifiers":[
        {
            "category":"Autos & Motor Vehicles",
            "subcategory":"Auto Supplies",
            "type":"Retail Goods"
        }
    ],
    "sg:phone":"+1 719 548 1115",
    "sg:postcode":"80920",
    "sg:province":"CO",
    "sg:website":"www.advance.com",
    "wof:name":"Advance Auto Parts",
    "wof:placetype":"venue"
},
  "geometry": {"coordinates":[-104.79921299999999,38.945268],"type":"Point"}
}