{
  "type": "Feature",
  "properties": {
    "iso:country":"US",
    "sg:address":"11970 W Colfax Ave",
    "sg:city":"Lakewood",
    "sg:classifiers":[
        {
            "category":"Banks & Credit Unions",
            "subcategory":"Bank",
            "type":"Services"
        }
    ],
    "sg:phone":"+1 303 274 2010",
    "sg:postcode":"80215",
    "sg:province":"CO",
    "sg:tags":[
        "loan"
    ],
    "wof:name":"Cash Fast Inc",
    "wof:placetype":"venue"
},
  "geometry": {"coordinates":[-105.13229200000001,39.740065],"type":"Point"}
}