{
  "type": "Feature",
  "properties": {
    "iso:country":"US",
    "sg:address":"1602 Garfield Ave",
    "sg:city":"Louisville",
    "sg:classifiers":[
        {
            "category":"Manufacturing",
            "subcategory":"Wood Products",
            "type":"Manufacturing & Wholesale Goods"
        }
    ],
    "sg:phone":"+1 720 890 7600",
    "sg:postcode":"80027",
    "sg:province":"CO",
    "sg:tags":[
        "mfg"
    ],
    "wof:name":"Ark Woodworks Inc",
    "wof:placetype":"venue"
},
  "geometry": {"coordinates":[-105.13804,39.986889],"type":"Point"}
}