{
  "type": "Feature",
  "properties": {
    "iso:country":"US",
    "sg:address":"950 17th St",
    "sg:city":"Denver",
    "sg:classifiers":[
        {
            "category":"Banks & Credit Unions",
            "subcategory":"Atm",
            "type":"Services"
        }
    ],
    "sg:phone":"+1 303 825 8400",
    "sg:postcode":"80202",
    "sg:province":"CO",
    "sg:tags":[
        "bankruptcy"
    ],
    "wof:name":"Segev Aviv Atty",
    "wof:placetype":"venue"
},
  "geometry": {"coordinates":[-104.993251,39.747711],"type":"Point"}
}