{
  "type": "Feature",
  "properties": {
    "iso:country":"US",
    "sg:address":"11515 Wadsworth Blvd",
    "sg:city":"Broomfield",
    "sg:classifiers":[
        {
            "category":"Building & Trades",
            "subcategory":"Construction",
            "type":"Services"
        }
    ],
    "sg:phone":"+1 303 460 0256",
    "sg:postcode":"80020",
    "sg:province":"CO",
    "sg:tags":[
        "foundation"
    ],
    "wof:name":"J & C Foundations",
    "wof:placetype":"venue"
},
  "geometry": {"coordinates":[-105.08110499999999,39.90471],"type":"Point"}
}