{
  "type": "Feature",
  "properties": {
    "addr:full":"12 Scutti Dr Florence CO 81226",
    "addr:housenumber":"12",
    "addr:postcode":"81226",
    "addr:street":"Scutti Dr",
    "iso:country":"US",
    "sg:address":"12 Scutti Dr",
    "sg:city":"Florence",
    "sg:classifiers":[
        {
            "category":"Wholesale",
            "subcategory":"Motor Vehicles",
            "type":"Manufacturing & Wholesale Goods"
        }
    ],
    "sg:phone":"+1 719 784 2092",
    "sg:postcode":"81226",
    "sg:province":"CO",
    "wof:name":"Gearheads",
    "wof:placetype":"venue"
},
  "geometry": {"coordinates":[-105.14767000000001,38.38286],"type":"Point"}
}