{
  "type": "Feature",
  "properties": {
    "iso:country":"US",
    "sg:address":"3005 Parfet Dr",
    "sg:city":"Denver",
    "sg:classifiers":[
        {
            "category":"Professional",
            "type":"Services"
        }
    ],
    "sg:phone":"+1 303 445 1216",
    "sg:postcode":"80215",
    "sg:province":"CO",
    "wof:name":"Cooper Ribner Co",
    "wof:placetype":"venue"
},
  "geometry": {"coordinates":[-105.122815,39.760249],"type":"Point"}
}