{
  "type": "Feature",
  "properties": {
    "iso:country":"US",
    "sg:address":"3405 Harbor Way",
    "sg:city":"Fort Collins",
    "sg:classifiers":[
        {
            "category":"Manufacturing",
            "subcategory":"Building Materials",
            "type":"Manufacturing & Wholesale Goods"
        }
    ],
    "sg:phone":"+1 970 495 1735",
    "sg:postcode":"80524",
    "sg:province":"CO",
    "sg:tags":[
        "mfg",
        "wood",
        "kitchen",
        "cabinet"
    ],
    "wof:name":"Mike Wilkinson Woodworking",
    "wof:placetype":"venue"
},
  "geometry": {"coordinates":[-105.07646,40.637178],"type":"Point"}
}