{
  "type": "Feature",
  "properties": {
    "addr:full":"1840 Pima Dr Colorado Springs CO 80915",
    "addr:housenumber":"1840",
    "addr:postcode":"80915",
    "addr:street":"Pima Dr",
    "iso:country":"US",
    "sg:address":"1840 Pima Dr",
    "sg:city":"Colorado Springs",
    "sg:classifiers":[
        {
            "category":"Building & Trades",
            "subcategory":"Construction",
            "type":"Services"
        }
    ],
    "sg:phone":"+1 719 638 0922",
    "sg:postcode":"80915",
    "sg:province":"CO",
    "sg:tags":[
        "carpentry",
        "contractor"
    ],
    "wof:name":"Awe Carpentry Div",
    "wof:placetype":"venue"
},
  "geometry": {"coordinates":[-104.708181,38.859418],"type":"Point"}
}