{
  "type": "Feature",
  "properties": {
    "addr:full":"83 Brothers Ln Pueblo CO 81001",
    "addr:housenumber":"83",
    "addr:postcode":"81001",
    "addr:street":"Brothers Ln",
    "iso:country":"US",
    "sg:address":"83 Brothers Ln",
    "sg:city":"Pueblo",
    "sg:classifiers":[
        {
            "category":"Home & Garden",
            "subcategory":"Garden Supply",
            "type":"Retail Goods"
        }
    ],
    "sg:phone":"+1 719 546 3405",
    "sg:postcode":"81001",
    "sg:province":"CO",
    "wof:name":"Hys Corp",
    "wof:placetype":"venue"
},
  "geometry": {"coordinates":[-104.575534,38.290625],"type":"Point"}
}