{
  "type": "Feature",
  "properties": {
    "iso:country":"US",
    "sg:address":"2464 Hwy 6 and 50",
    "sg:city":"Grand Junction",
    "sg:classifiers":[
        {
            "category":"Wholesale",
            "subcategory":"Machinery & Supplies",
            "type":"Manufacturing & Wholesale Goods"
        }
    ],
    "sg:phone":"+1 970 242 3601",
    "sg:postcode":"81505",
    "sg:province":"CO",
    "sg:tags":[
        "beauty"
    ],
    "wof:name":"Sally Beauty Supply",
    "wof:placetype":"venue"
},
  "geometry": {"coordinates":[-108.596743,39.086496],"type":"Point"}
}