{
  "type": "Feature",
  "properties": {
    "iso:country":"US",
    "sg:address":"5660 Central Ave",
    "sg:city":"Boulder",
    "sg:classifiers":[
        {
            "category":"Wholesale",
            "subcategory":"Vending Machines",
            "type":"Manufacturing & Wholesale Goods"
        }
    ],
    "sg:phone":"+1 303 444 2559",
    "sg:postcode":"80301",
    "sg:province":"CO",
    "sg:tags":[
        "operator"
    ],
    "wof:name":"Sugarloaf Creations Inc",
    "wof:placetype":"venue"
},
  "geometry": {"coordinates":[-105.22132999999999,40.019734],"type":"Point"}
}