{
  "type": "Feature",
  "properties": {
    "iso:country":"US",
    "sg:address":"101 Main St",
    "sg:city":"Central City",
    "sg:classifiers":[
        {
            "category":"Recreation",
            "subcategory":"Arcade",
            "type":"Entertainment"
        }
    ],
    "sg:phone":"+1 303 582 1400",
    "sg:postcode":"80427",
    "sg:province":"CO",
    "sg:tags":[
        "casino"
    ],
    "wof:name":"Doc Holiday Inc",
    "wof:placetype":"venue"
},
  "geometry": {"coordinates":[-105.51257,39.800762],"type":"Point"}
}