{
  "type": "Feature",
  "properties": {
    "addr:full":"8255 White Antelope Dr Colorado Springs CO 80908",
    "addr:housenumber":"8255",
    "addr:postcode":"80908",
    "addr:street":"White Antelope Dr",
    "iso:country":"US",
    "sg:address":"8255 White Antelope Dr",
    "sg:city":"Colorado Springs",
    "sg:classifiers":[
        {
            "category":"Recreation",
            "type":"Entertainment"
        }
    ],
    "sg:phone":"+1 719 495 1008",
    "sg:postcode":"80908",
    "sg:province":"CO",
    "sg:tags":[
        "stable"
    ],
    "wof:name":"Sterling Family Ventures",
    "wof:placetype":"venue"
},
  "geometry": {"coordinates":[-104.673708,39.110974],"type":"Point"}
}