{
  "type": "Feature",
  "properties": {
    "addr:full":"3103 Morris Ave Pueblo CO 81008",
    "addr:housenumber":"3103",
    "addr:postcode":"81008",
    "addr:street":"Morris Ave",
    "iso:country":"US",
    "sg:address":"3103 Morris Ave",
    "sg:city":"Pueblo",
    "sg:classifiers":[
        {
            "category":"Professional",
            "subcategory":"Accounting & Tax Preparation",
            "type":"Services"
        }
    ],
    "sg:phone":"+1 719 542 3771",
    "sg:postcode":"81008",
    "sg:province":"CO",
    "sg:tags":[
        "return",
        "filing"
    ],
    "wof:name":"Business Associates Of Pueblo",
    "wof:placetype":"venue"
},
  "geometry": {"coordinates":[-104.63028799999999,38.301921],"type":"Point"}
}