{
  "type": "Feature",
  "properties": {
    "addr:full":"200 N 4th St Lamar CO 81052",
    "addr:housenumber":"200",
    "addr:postcode":"81052",
    "addr:street":"N 4Th St",
    "iso:country":"US",
    "sg:address":"200 N 4th St",
    "sg:city":"Lamar",
    "sg:classifiers":[
        {
            "category":"Retail",
            "subcategory":"Auto Repair",
            "type":"Services"
        }
    ],
    "sg:phone":"+1 719 336 3451",
    "sg:postcode":"81052",
    "sg:province":"CO",
    "sg:tags":[
        "truck"
    ],
    "wof:name":"Heath & Son & Turpin Trucking",
    "wof:placetype":"venue"
},
  "geometry": {"coordinates":[-102.618182,38.092396],"type":"Point"}
}