{
  "type": "Feature",
  "properties": {
    "iso:country":"US",
    "sg:address":"3740 Interpark Dr",
    "sg:city":"Colorado Springs",
    "sg:classifiers":[
        {
            "category":"Wholesale",
            "subcategory":"Durable Goods & Equipment",
            "type":"Manufacturing & Wholesale Goods"
        }
    ],
    "sg:phone":"+1 719 447 0331",
    "sg:postcode":"80907",
    "sg:province":"CO",
    "sg:tags":[
        "novelty",
        "robot",
        "mfg"
    ],
    "wof:name":"The Robot Factory Inc",
    "wof:placetype":"venue"
},
  "geometry": {"coordinates":[-104.8305,38.889144],"type":"Point"}
}