{
  "type": "Feature",
  "properties": {
    "iso:country":"US",
    "sg:address":"1050 S Nutmeg St",
    "sg:city":"Bennett",
    "sg:classifiers":[
        {
            "category":"Wholesale",
            "subcategory":"Machinery & Supplies",
            "type":"Manufacturing & Wholesale Goods"
        }
    ],
    "sg:phone":"+1 303 644 4943",
    "sg:postcode":"80102",
    "sg:province":"CO",
    "wof:name":"Daniel M McCormick",
    "wof:placetype":"venue"
},
  "geometry": {"coordinates":[-104.513626,39.696469],"type":"Point"}
}