{
  "type": "Feature",
  "properties": {
    "iso:country":"US",
    "sg:address":"3300 Arapahoe Ave",
    "sg:city":"Boulder",
    "sg:classifiers":[
        {
            "category":"Wholesale",
            "subcategory":"Toys & Hobbies",
            "type":"Manufacturing & Wholesale Goods"
        }
    ],
    "sg:phone":"+1 303 402 1573",
    "sg:postcode":"80303",
    "sg:province":"CO",
    "sg:tags":[
        "wholesaler"
    ],
    "wof:name":"Peterzon Enterprises Inc",
    "wof:placetype":"venue"
},
  "geometry": {"coordinates":[-105.246664,40.014516],"type":"Point"}
}