{
  "type": "Feature",
  "properties": {
    "iso:country":"US",
    "sg:address":"130 Ski Hill Rd",
    "sg:city":"Breckenridge",
    "sg:classifiers":[
        {
            "category":"Insurance",
            "subcategory":"Insurance Agent",
            "type":"Services"
        }
    ],
    "sg:phone":"+1 970 453 7190",
    "sg:postcode":"80424",
    "sg:province":"CO",
    "wof:name":"Gary Longballa Insurance",
    "wof:placetype":"venue"
},
  "geometry": {"coordinates":[-106.046955,39.482301],"type":"Point"}
}