{
  "type": "Feature",
  "properties": {
    "addr:full":"109 Patchwork Ct Fountain CO 80817",
    "addr:housenumber":"109",
    "addr:postcode":"80817",
    "addr:street":"Patchwork Ct",
    "iso:country":"US",
    "sg:address":"109 Patchwork Ct",
    "sg:city":"Fountain",
    "sg:classifiers":[
        {
            "category":"Professional",
            "subcategory":"Detective & Security Services",
            "type":"Services"
        }
    ],
    "sg:phone":"+1 719 382 3630",
    "sg:postcode":"80817",
    "sg:province":"CO",
    "sg:tags":[
        "guard",
        "patrol"
    ],
    "wof:name":"Lord Will Provide",
    "wof:placetype":"venue"
},
  "geometry": {"coordinates":[-104.668795,38.666728],"type":"Point"}
}