{
  "type": "Feature",
  "properties": {
    "addr:full":"2180 Donelan Ave Burlington CO 80807",
    "addr:housenumber":"2180",
    "addr:postcode":"80807",
    "addr:street":"Donelan Ave",
    "iso:country":"US",
    "sg:address":"2180 Donelan Ave",
    "sg:city":"Burlington",
    "sg:phone":"+1 719 346 7653",
    "sg:postcode":"80807",
    "sg:province":"CO",
    "sg:tags":[
        "farm"
    ],
    "wof:name":"Wilks Farms Ranches",
    "wof:placetype":"venue"
},
  "geometry": {"coordinates":[-102.277795,39.302384],"type":"Point"}
}