{
  "type": "Feature",
  "properties": {
    "addr:full":"1114 Bonforte Blvd Pueblo CO 81001",
    "addr:housenumber":"1114",
    "addr:postcode":"81001",
    "addr:street":"Bonforte Blvd",
    "iso:country":"US",
    "sg:address":"1114 Bonforte Blvd",
    "sg:city":"Pueblo",
    "sg:classifiers":[
        {
            "category":"Food & Beverages",
            "subcategory":"Liquor & Beverages",
            "type":"Retail Goods"
        }
    ],
    "sg:phone":"+1 719 545 2630",
    "sg:postcode":"81001",
    "sg:province":"CO",
    "wof:name":"Bonny Hy-Land Liquors",
    "wof:placetype":"venue"
},
  "geometry": {"coordinates":[-104.595215,38.289408],"type":"Point"}
}