{
  "type": "Feature",
  "properties": {
    "addr:full":"303 S Broadway #200 Denver CO 80209",
    "addr:housenumber":"303",
    "addr:postcode":"80209",
    "addr:street":"S Broadway # 200",
    "iso:country":"US",
    "sg:address":"303 S Broadway #200",
    "sg:city":"Denver",
    "sg:classifiers":[
        {
            "category":"Building & Trades",
            "subcategory":"Plumbing",
            "type":"Services"
        }
    ],
    "sg:phone":"+1 303 586 8146",
    "sg:postcode":"80209",
    "sg:province":"CO",
    "wof:name":"Plumbers Denver",
    "wof:placetype":"venue"
},
  "geometry": {"coordinates":[-104.98759099999999,39.710603],"type":"Point"}
}