{
  "type": "Feature",
  "properties": {
    "iso:country":"US",
    "sg:address":"303 S Broadway #200",
    "sg:city":"Denver",
    "sg:classifiers":[
        {
            "category":"Building & Trades",
            "subcategory":"Plumbing",
            "type":"Services"
        }
    ],
    "sg:phone":"+1 303 586 8146",
    "sg:postcode":"80209",
    "sg:province":"CO",
    "wof:name":"Plumbers Denver",
    "wof:placetype":"venue"
},
  "geometry": {"coordinates":[-104.987591,39.710603],"type":"Point"}
}