{
  "type": "Feature",
  "properties": {
    "addr:full":"13489 Osage St Denver CO 80234",
    "addr:housenumber":"13489",
    "addr:postcode":"80234",
    "addr:street":"Osage St",
    "iso:country":"US",
    "sg:address":"13489 Osage St",
    "sg:city":"Denver",
    "sg:classifiers":[
        {
            "category":"Building & Trades",
            "subcategory":"Plumbing",
            "type":"Services"
        }
    ],
    "sg:phone":"+1 720 290 0562",
    "sg:postcode":"80234",
    "sg:province":"CO",
    "sg:tags":[
        "contractor"
    ],
    "wof:name":"CB Plumbing Services Inc",
    "wof:placetype":"venue"
},
  "geometry": {"coordinates":[-105.005858,39.940926],"type":"Point"}
}