{
  "type": "Feature",
  "properties": {
    "iso:country":"US",
    "sg:address":"2525 15th Street",
    "sg:city":"Denver",
    "sg:classifiers":[
        {
            "category":"Banks & Credit Unions",
            "subcategory":"Financial Services",
            "type":"Services"
        }
    ],
    "sg:phone":"+1 303 524 9907",
    "sg:postcode":"80211",
    "sg:province":"CO",
    "sg:tags":[
        "broker",
        "mortgage"
    ],
    "wof:name":"Front Range Mortgage",
    "wof:placetype":"venue"
},
  "geometry": {"coordinates":[-105.022577,39.76322],"type":"Point"}
}