{
  "type": "Feature",
  "properties": {
    "addr:full":"8340 Bannock Rd Larkspur CO 80118",
    "addr:housenumber":"8340",
    "addr:postcode":"80118",
    "addr:street":"Bannock Rd",
    "iso:country":"US",
    "sg:address":"8340 Bannock Rd",
    "sg:city":"Larkspur",
    "sg:classifiers":[
        {
            "category":"Mining & Drilling",
            "type":"Manufacturing & Wholesale Goods"
        }
    ],
    "sg:phone":"+1 303 808 3901",
    "sg:postcode":"80118",
    "sg:province":"CO",
    "sg:tags":[
        "oil",
        "gas",
        "for",
        "surveying"
    ],
    "wof:name":"Maverick Exploration Services",
    "wof:placetype":"venue"
},
  "geometry": {"coordinates":[-104.959343,39.246062],"type":"Point"}
}