{
  "type": "Feature",
  "properties": {
    "iso:country":"US",
    "sg:address":"1 Beaver Creek Dr",
    "sg:city":"Avon",
    "sg:classifiers":[
        {
            "category":"Restaurant",
            "type":"Food & Drink"
        }
    ],
    "sg:phone":"+1 970 845 6245",
    "sg:postcode":"81620",
    "sg:province":"CO",
    "sg:tags":[
        "shop",
        "coffee"
    ],
    "wof:name":"Starbucks",
    "wof:placetype":"venue"
},
  "geometry": {"coordinates":[-106.526083,39.622536],"type":"Point"}
}