{
  "type": "Feature",
  "properties": {
    "addr:full":"2303 6th Ave Greeley CO 80631",
    "addr:housenumber":"2303",
    "addr:postcode":"80631",
    "addr:street":"6Th Ave",
    "iso:country":"US",
    "sg:address":"2303 6th Ave",
    "sg:city":"Greeley",
    "sg:classifiers":[
        {
            "category":"Real Estate",
            "subcategory":"Developer",
            "type":"Services"
        }
    ],
    "sg:phone":"+1 970 353 9600",
    "sg:postcode":"80631",
    "sg:province":"CO",
    "wof:name":"Helgeson Development Inc",
    "wof:placetype":"venue"
},
  "geometry": {"coordinates":[-104.687591,40.399847],"type":"Point"}
}