{
  "type": "Feature",
  "properties": {
    "iso:country":"US",
    "sg:address":"100 Rio Grande Blvd",
    "sg:city":"Denver",
    "sg:classifiers":[
        {
            "category":"Home & Garden",
            "subcategory":"Furniture",
            "type":"Retail Goods"
        }
    ],
    "sg:phone":"+1 303 892 6998",
    "sg:postcode":"80223",
    "sg:province":"CO",
    "wof:name":"Davis & Shawn Furniture Co",
    "wof:placetype":"venue"
},
  "geometry": {"coordinates":[-105.00310399999999,39.717865],"type":"Point"}
}