{
  "type": "Feature",
  "properties": {
    "addr:full":"1860 Glen Ayr Dr Lakewood CO 80215",
    "addr:housenumber":"1860",
    "addr:postcode":"80215",
    "addr:street":"Glen Ayr Dr",
    "iso:country":"US",
    "sg:address":"1860 Glen Ayr Dr",
    "sg:city":"Lakewood",
    "sg:classifiers":[
        {
            "category":"Health Services",
            "subcategory":"Clinic",
            "type":"Services"
        }
    ],
    "sg:phone":"+1 303 274 7979",
    "sg:postcode":"80215",
    "sg:province":"CO",
    "sg:tags":[
        "wellness",
        "program"
    ],
    "wof:name":"Inflnite Wellness",
    "wof:placetype":"venue"
},
  "geometry": {"coordinates":[-105.098828,39.745768],"type":"Point"}
}