{
  "type": "Feature",
  "properties": {
    "addr:full":"2809 E Harmony Rd Fort Collins CO 80528",
    "addr:housenumber":"2809",
    "addr:postcode":"80528",
    "addr:street":"E Harmony Rd",
    "iso:country":"US",
    "sg:address":"2809 E Harmony Rd",
    "sg:city":"Fort Collins",
    "sg:classifiers":[
        {
            "category":"Professional",
            "subcategory":"Advertising",
            "type":"Services"
        }
    ],
    "sg:phone":"+1 970 493 5100",
    "sg:postcode":"80528",
    "sg:province":"CO",
    "sg:website":"www.comcast.com",
    "wof:name":"Comcast Cable",
    "wof:placetype":"venue"
},
  "geometry": {"coordinates":[-105.02435699999999,40.523011],"type":"Point"}
}