{
  "type": "Feature",
  "properties": {
    "addr:full":"39 W 11th Ave Denver CO 80205",
    "addr:housenumber":"39",
    "addr:postcode":"80205",
    "addr:street":"W 11Th Ave",
    "iso:country":"US",
    "sg:address":"39 W 11th Ave",
    "sg:city":"Denver",
    "sg:classifiers":[
        {
            "category":"Professional",
            "subcategory":"Advertising",
            "type":"Services"
        }
    ],
    "sg:phone":"+1 303 831 6341",
    "sg:postcode":"80205",
    "sg:province":"CO",
    "sg:tags":[
        "marketing"
    ],
    "wof:name":"Premier Image Agency",
    "wof:placetype":"venue"
},
  "geometry": {"coordinates":[-104.988535,39.734032],"type":"Point"}
}