{
  "type": "Feature",
  "properties": {
    "iso:country":"US",
    "sg:address":"6862 S Lamar St",
    "sg:city":"Littleton",
    "sg:classifiers":[
        {
            "category":"Food & Beverages",
            "subcategory":"Specialty",
            "type":"Retail Goods"
        }
    ],
    "sg:phone":"+1 303 972 0272",
    "sg:postcode":"80128",
    "sg:province":"CO",
    "wof:name":"Shaklee Products",
    "wof:placetype":"venue"
},
  "geometry": {"coordinates":[-105.066429,39.59137],"type":"Point"}
}