{
  "type": "Feature",
  "properties": {
    "iso:country":"US",
    "sg:address":"3500 Blake St",
    "sg:city":"Denver",
    "sg:classifiers":[
        {
            "category":"Manufacturing",
            "subcategory":"Glass & Minerals",
            "type":"Manufacturing & Wholesale Goods"
        }
    ],
    "sg:phone":"+1 303 295 1010",
    "sg:postcode":"80205",
    "sg:province":"CO",
    "sg:tags":[
        "sink",
        "mfg"
    ],
    "wof:name":"Vitraform Inc",
    "wof:placetype":"venue"
},
  "geometry": {"coordinates":[-104.97503500000001,39.769217],"type":"Point"}
}