{
  "type": "Feature",
  "properties": {
    "iso:country":"US",
    "sg:address":"104 6th St",
    "sg:city":"Kremmling",
    "sg:classifiers":[
        {
            "category":"Restaurant",
            "type":"Food & Drink"
        }
    ],
    "sg:phone":"+1 970 724 1107",
    "sg:postcode":"80459",
    "sg:province":"CO",
    "wof:name":"Our Family Kitchen",
    "wof:placetype":"venue"
},
  "geometry": {"coordinates":[-106.388632,40.059643],"type":"Point"}
}