{
  "type": "Feature",
  "properties": {
    "iso:country":"US",
    "sg:address":"300 W Tomichi Ave",
    "sg:city":"Gunnison",
    "sg:classifiers":[
        {
            "category":"Real Estate",
            "subcategory":"Real Estate Agent",
            "type":"Services"
        }
    ],
    "sg:phone":"+1 970 641 4880",
    "sg:postcode":"81230",
    "sg:province":"CO",
    "wof:name":"Peak Property Management & Sls",
    "wof:placetype":"venue"
},
  "geometry": {"coordinates":[-106.930798,38.544397],"type":"Point"}
}