{
  "type": "Feature",
  "properties": {
    "addr:full":"5077 S Bear Mountain Dr Evergreen CO 80439",
    "addr:housenumber":"5077",
    "addr:postcode":"80439",
    "addr:street":"S Bear Mountain Dr",
    "iso:country":"US",
    "sg:address":"5077 S Bear Mountain Dr",
    "sg:city":"Evergreen",
    "sg:classifiers":[
        {
            "category":"Professional",
            "type":"Services"
        }
    ],
    "sg:phone":"+1 303 674 1210",
    "sg:postcode":"80439",
    "sg:province":"CO",
    "wof:name":"Donald L Banghart PC",
    "wof:placetype":"venue"
},
  "geometry": {"coordinates":[-105.285873,39.623573],"type":"Point"}
}