{
  "type": "Feature",
  "properties": {
    "iso:country":"US",
    "sg:address":"7003 E 47th Avenue Dr",
    "sg:city":"Denver",
    "sg:classifiers":[
        {
            "category":"Retail",
            "subcategory":"Veterinary Services",
            "type":"Services"
        }
    ],
    "sg:phone":"+1 303 320 6034",
    "sg:postcode":"80216",
    "sg:province":"CO",
    "sg:tags":[
        "veterinarian"
    ],
    "wof:name":"Vet Pet Solutions",
    "wof:placetype":"venue"
},
  "geometry": {"coordinates":[-104.90582499999999,39.782494],"type":"Point"}
}