{
  "type": "Feature",
  "properties": {
    "addr:full":"50 S Steele Street Denver CO 80209",
    "addr:housenumber":"50",
    "addr:postcode":"80209",
    "addr:street":"S Steele Street",
    "iso:country":"US",
    "sg:address":"50 S Steele Street",
    "sg:city":"Denver",
    "sg:classifiers":[
        {
            "category":"Professional",
            "subcategory":"Accounting & Tax Preparation",
            "type":"Services"
        }
    ],
    "sg:phone":"+1 303 394 9600",
    "sg:postcode":"80209",
    "sg:province":"CO",
    "sg:tags":[
        "accountant"
    ],
    "wof:name":"Wagner Wealth Management CPA",
    "wof:placetype":"venue"
},
  "geometry": {"coordinates":[-104.949752,39.715458],"type":"Point"}
}