{
  "type": "Feature",
  "properties": {
    "iso:country":"US",
    "sg:address":"8637 US Hwy 285",
    "sg:city":"Alamosa",
    "sg:classifiers":[
        {
            "category":"Freight",
            "type":"Transportation"
        }
    ],
    "sg:phone":"+1 719 589 6200",
    "sg:postcode":"81101",
    "sg:province":"CO",
    "sg:tags":[
        "operator",
        "arrangement",
        "trucking"
    ],
    "wof:name":"Trucking Co",
    "wof:placetype":"venue"
},
  "geometry": {"coordinates":[-105.880511,37.44953],"type":"Point"}
}