{
  "type": "Feature",
  "properties": {
    "iso:country":"US",
    "sg:address":"2510 Westen Rd",
    "sg:city":"Colorado Springs",
    "sg:classifiers":[
        {
            "category":"Manufacturing",
            "subcategory":"Tools & Machinery",
            "type":"Manufacturing & Wholesale Goods"
        }
    ],
    "sg:phone":"+1 719 393 0010",
    "sg:postcode":"80910",
    "sg:province":"CO",
    "sg:tags":[
        "cleaners",
        "household",
        "vacuum"
    ],
    "wof:name":"Silverking Int'l",
    "wof:placetype":"venue"
},
  "geometry": {"coordinates":[-104.777997,38.795384],"type":"Point"}
}