{
  "type": "Feature",
  "properties": {
    "addr:full":"145 N Mesa St Fruita CO 81521",
    "addr:housenumber":"145",
    "addr:postcode":"81521",
    "addr:street":"N Mesa St",
    "iso:country":"US",
    "sg:address":"145 N Mesa St",
    "sg:city":"Fruita",
    "sg:classifiers":[
        {
            "category":"Personal",
            "subcategory":"Beauty Salon",
            "type":"Services"
        }
    ],
    "sg:phone":"+1 970 858 3992",
    "sg:postcode":"81521",
    "sg:province":"CO",
    "wof:name":"Hair By Design",
    "wof:placetype":"venue"
},
  "geometry": {"coordinates":[-108.733722,39.15991],"type":"Point"}
}