{
  "type": "Feature",
  "properties": {
    "addr:full":"33 Rockaway Avenue Castle Rock CO 80104",
    "addr:housenumber":"33",
    "addr:postcode":"80104",
    "addr:street":"Rockaway Avenue",
    "iso:country":"US",
    "sg:address":"33 Rockaway Avenue",
    "sg:city":"Castle Rock",
    "sg:classifiers":[
        {
            "category":"Retail",
            "subcategory":"Pet Boarding",
            "type":"Services"
        }
    ],
    "sg:phone":"+1 303 660 5312",
    "sg:postcode":"80104",
    "sg:province":"CO",
    "sg:tags":[
        "boarding/pet",
        "sitting"
    ],
    "wof:name":"Family Pet Sitting",
    "wof:placetype":"venue"
},
  "geometry": {"coordinates":[-104.80147599999999,39.369663],"type":"Point"}
}