{
  "type": "Feature",
  "properties": {
    "iso:country":"US",
    "sg:address":"5640 W Alameda Ave",
    "sg:city":"Lakewood",
    "sg:classifiers":[
        {
            "category":"Recreation",
            "type":"Entertainment"
        }
    ],
    "sg:phone":"+1 303 922 3912",
    "sg:postcode":"80226",
    "sg:province":"CO",
    "sg:tags":[
        "martial",
        "arts",
        "instruction"
    ],
    "wof:name":"Ralph Krause's Sport Karate",
    "wof:placetype":"venue"
},
  "geometry": {"coordinates":[-105.05876000000001,39.7111],"type":"Point"}
}