{
  "type": "Feature",
  "properties": {
    "iso:country":"US",
    "sg:address":"4180 S Broadway",
    "sg:city":"Englewood",
    "sg:classifiers":[
        {
            "category":"Retail",
            "subcategory":"Car Wash",
            "type":"Services"
        }
    ],
    "sg:phone":"+1 303 762 1035",
    "sg:postcode":"80113",
    "sg:province":"CO",
    "sg:tags":[
        "operated",
        "polishing",
        "washing"
    ],
    "wof:name":"Jumbo Car Wash",
    "wof:placetype":"venue"
},
  "geometry": {"coordinates":[-104.9877,39.641844],"type":"Point"}
}