{
  "type": "Feature",
  "properties": {
    "iso:country":"US",
    "sg:address":"18054 Hanson Rd",
    "sg:city":"Cedaredge",
    "sg:classifiers":[
        {
            "category":"Building & Trades",
            "subcategory":"Construction",
            "type":"Services"
        }
    ],
    "sg:phone":"+1 970 856 6284",
    "sg:postcode":"81413",
    "sg:province":"CO",
    "sg:tags":[
        "house"
    ],
    "wof:name":"Hinchman Construction Inc",
    "wof:placetype":"venue"
},
  "geometry": {"coordinates":[-107.900092,38.918544],"type":"Point"}
}