{
  "type": "Feature",
  "properties": {
    "iso:country":"US",
    "sg:address":"5490 Parmalee Gulch Rd",
    "sg:city":"Indian Hills",
    "sg:classifiers":[
        {
            "category":"Wholesale",
            "subcategory":"Durable Goods & Equipment",
            "type":"Manufacturing & Wholesale Goods"
        }
    ],
    "sg:phone":"+1 303 697 8450",
    "sg:postcode":"80454",
    "sg:province":"CO",
    "sg:tags":[
        "exporter"
    ],
    "wof:name":"Gorm International",
    "wof:placetype":"venue"
},
  "geometry": {"coordinates":[-105.236839,39.617495],"type":"Point"}
}