{
  "type": "Feature",
  "properties": {
    "iso:country":"US",
    "sg:address":"6490 S Quebec St",
    "sg:city":"Centennial",
    "sg:classifiers":[
        {
            "category":"Restaurant",
            "type":"Food & Drink"
        }
    ],
    "sg:phone":"+1 303 779 9424",
    "sg:postcode":"80111",
    "sg:province":"CO",
    "sg:tags":[
        "house",
        "steak"
    ],
    "wof:name":"Wich Wich",
    "wof:placetype":"venue"
},
  "geometry": {"coordinates":[-104.904083,39.59988],"type":"Point"}
}