{
  "type": "Feature",
  "properties": {
    "addr:full":"522 E Bleeker St Aspen CO 81611",
    "addr:housenumber":"522",
    "addr:postcode":"81611",
    "addr:street":"E Bleeker St",
    "iso:country":"US",
    "sg:address":"522 E Bleeker St",
    "sg:city":"Aspen",
    "sg:classifiers":[
        {
            "category":"Building & Trades",
            "subcategory":"Construction",
            "type":"Services"
        }
    ],
    "sg:phone":"+1 970 925 3951",
    "sg:postcode":"81611",
    "sg:province":"CO",
    "sg:tags":[
        "painter"
    ],
    "wof:name":"Aspen Painting",
    "wof:placetype":"venue"
},
  "geometry": {"coordinates":[-106.817104,39.19134],"type":"Point"}
}