{
  "type": "Feature",
  "properties": {
    "addr:full":"5686 Logan Ct Denver CO 80216",
    "addr:housenumber":"5686",
    "addr:postcode":"80216",
    "addr:street":"Logan Ct",
    "iso:country":"US",
    "sg:address":"5686 Logan Ct",
    "sg:city":"Denver",
    "sg:classifiers":[
        {
            "category":"Shopping",
            "subcategory":"Gifts & Souvenirs",
            "type":"Retail Goods"
        }
    ],
    "sg:phone":"+1 303 298 8589",
    "sg:postcode":"80216",
    "sg:province":"CO",
    "sg:tags":[
        "shop"
    ],
    "wof:name":"Two Crazy Ladies & Gifts",
    "wof:placetype":"venue"
},
  "geometry": {"coordinates":[-104.98112,39.800332],"type":"Point"}
}