{
  "type": "Feature",
  "properties": {
    "iso:country":"US",
    "sg:address":"2837 W 55th Ave",
    "sg:city":"Denver",
    "sg:classifiers":[
        {
            "category":"Autos & Motor Vehicles",
            "subcategory":"Automobile Sales",
            "type":"Retail Goods"
        }
    ],
    "sg:phone":"+1 303 667 3573",
    "sg:postcode":"80221",
    "sg:province":"CO",
    "sg:tags":[
        "wrecker"
    ],
    "wof:name":"J A Towing",
    "wof:placetype":"venue"
},
  "geometry": {"coordinates":[-105.023578,39.796615],"type":"Point"}
}