{
  "type": "Feature",
  "properties": {
    "addr:full":"990 Dayton St Aurora CO 80010",
    "addr:housenumber":"990",
    "addr:postcode":"80010",
    "addr:street":"Dayton St",
    "iso:country":"US",
    "sg:address":"990 Dayton St",
    "sg:city":"Aurora",
    "sg:classifiers":[
        {
            "category":"Banks & Credit Unions",
            "subcategory":"Bank",
            "type":"Services"
        }
    ],
    "sg:phone":"+1 303 343 9570",
    "sg:postcode":"80010",
    "sg:province":"CO",
    "sg:tags":[
        "personal",
        "institution"
    ],
    "wof:name":"Fischer Financial Services",
    "wof:placetype":"venue"
},
  "geometry": {"coordinates":[-104.87522800000001,39.729385],"type":"Point"}
}