{
  "type": "Feature",
  "properties": {
    "addr:full":"4415 Industrial Pkwy Evans CO 80620",
    "addr:housenumber":"4415",
    "addr:postcode":"80620",
    "addr:street":"Industrial Pkwy",
    "iso:country":"US",
    "sg:address":"4415 Industrial Pkwy",
    "sg:city":"Evans",
    "sg:classifiers":[
        {
            "category":"Autos & Motor Vehicles",
            "subcategory":"Automobile Sales",
            "type":"Retail Goods"
        }
    ],
    "sg:phone":"+1 970 330 6675",
    "sg:postcode":"80620",
    "sg:province":"CO",
    "sg:tags":[
        "car",
        "dealer"
    ],
    "wof:name":"Blue Mountain Truck & Auto",
    "wof:placetype":"venue"
},
  "geometry": {"coordinates":[-104.70499599999999,40.365751],"type":"Point"}
}