{
  "type": "Feature",
  "properties": {
    "iso:country":"US",
    "sg:address":"268 S Santa Fe Dr",
    "sg:city":"Denver",
    "sg:classifiers":[
        {
            "category":"Building & Trades",
            "subcategory":"Landscaping Services",
            "type":"Services"
        }
    ],
    "sg:phone":"+1 303 750 1957",
    "sg:postcode":"80223",
    "sg:province":"CO",
    "sg:tags":[
        "landscape"
    ],
    "wof:name":"R & R Landscaping",
    "wof:placetype":"venue"
},
  "geometry": {"coordinates":[-104.997236,39.711625],"type":"Point"}
}