{
  "type": "Feature",
  "properties": {
    "addr:full":"939 E 4th Ave Durango CO 81301",
    "addr:housenumber":"939",
    "addr:postcode":"co 81301",
    "addr:street":"E 4Th Ave",
    "iso:country":"US",
    "sg:address":"939 E 4th Ave",
    "sg:city":"Durango",
    "sg:classifiers":[
        {
            "category":"Professional",
            "subcategory":"Business Services",
            "type":"Services"
        }
    ],
    "sg:phone":"+1 970 259 6736",
    "sg:postcode":"81301",
    "sg:province":"CO",
    "sg:tags":[
        "sporting",
        "amusement"
    ],
    "wof:name":"San Juan Anglers",
    "wof:placetype":"venue"
},
  "geometry": {"coordinates":[-107.876356,37.273188],"type":"Point"}
}