{
  "type": "Feature",
  "properties": {
    "iso:country":"US",
    "sg:address":"6930 S University Blvd",
    "sg:city":"Littleton",
    "sg:classifiers":[
        {
            "category":"Professional",
            "subcategory":"Accounting & Tax Preparation",
            "type":"Services"
        }
    ],
    "sg:phone":"+1 720 544 8500",
    "sg:postcode":"80122",
    "sg:province":"CO",
    "sg:tags":[
        "return",
        "filing"
    ],
    "wof:name":"H & R Block Denver Tax School",
    "wof:placetype":"venue"
},
  "geometry": {"coordinates":[-104.960179,39.590365],"type":"Point"}
}