{
  "type": "Feature",
  "properties": {
    "addr:full":"16016 E Rice Pl Aurora CO 80015",
    "addr:housenumber":"16016",
    "addr:postcode":"80015",
    "addr:street":"E Rice Pl",
    "iso:country":"US",
    "sg:address":"16016 E Rice Pl",
    "sg:city":"Aurora",
    "sg:classifiers":[
        {
            "category":"Retail",
            "subcategory":"Laundry & Dry Cleaning",
            "type":"Services"
        }
    ],
    "sg:phone":"+1 303 690 7006",
    "sg:postcode":"80015",
    "sg:province":"CO",
    "sg:tags":[
        "cleaners",
        "rug",
        "carpet"
    ],
    "wof:name":"Carpet Engineering",
    "wof:placetype":"venue"
},
  "geometry": {"coordinates":[-104.801457,39.635162],"type":"Point"}
}