{
  "type": "Feature",
  "properties": {
    "iso:country":"US",
    "sg:address":"2505 Co Rd 46",
    "sg:city":"Berthoud",
    "sg:classifiers":[
        {
            "category":"Building & Trades",
            "subcategory":"Construction",
            "type":"Services"
        }
    ],
    "sg:phone":"+1 970 532 2588",
    "sg:postcode":"80513",
    "sg:province":"CO",
    "sg:tags":[
        "boring",
        "drilling",
        "contractor"
    ],
    "wof:name":"Van Thuyne-Downs Inc",
    "wof:placetype":"venue"
},
  "geometry": {"coordinates":[-105.008702,40.320706],"type":"Point"}
}