{
  "type": "Feature",
  "properties": {
    "addr:full":"7298 W 96th Ave Broomfield CO 80021",
    "addr:housenumber":"7298",
    "addr:postcode":"80021",
    "addr:street":"W 96Th Ave",
    "iso:country":"US",
    "sg:address":"7298 W 96th Ave",
    "sg:city":"Broomfield",
    "sg:classifiers":[
        {
            "category":"Health Services",
            "subcategory":"Health Practitioner",
            "type":"Services"
        }
    ],
    "sg:phone":"+1 303 467 9890",
    "sg:postcode":"80021",
    "sg:province":"CO",
    "sg:tags":[
        "nutritionist"
    ],
    "wof:name":"Physicians Medical Nutrition",
    "wof:placetype":"venue"
},
  "geometry": {"coordinates":[-105.079032,39.870961],"type":"Point"}
}