{
  "type": "Feature",
  "properties": {
    "iso:country":"US",
    "sg:address":"6145 E 72nd Ave",
    "sg:city":"Commerce City",
    "sg:classifiers":[
        {
            "category":"Utilities",
            "subcategory":"Mobile Phone",
            "type":"Services"
        }
    ],
    "sg:phone":"+1 303 287 6952",
    "sg:postcode":"80022",
    "sg:province":"CO",
    "sg:tags":[
        "telephone",
        "cellular"
    ],
    "wof:name":"All Signals Wireless",
    "wof:placetype":"venue"
},
  "geometry": {"coordinates":[-104.916786,39.827314],"type":"Point"}
}