{
  "type": "Feature",
  "properties": {
    "addr:full":"309 State Hwy 56 Berthoud CO 80513",
    "addr:housenumber":"309",
    "addr:postcode":"80513",
    "addr:street":"State Hwy 56",
    "iso:country":"US",
    "sg:address":"309 State Hwy 56",
    "sg:city":"Berthoud",
    "sg:classifiers":[
        {
            "category":"Real Estate",
            "subcategory":"Surveying",
            "type":"Services"
        }
    ],
    "sg:phone":"+1 970 532 9824",
    "sg:postcode":"80513",
    "sg:province":"CO",
    "sg:tags":[
        "surveyor"
    ],
    "wof:name":"Hascall Surveys Inc",
    "wof:placetype":"venue"
},
  "geometry": {"coordinates":[-105.049604,40.30544],"type":"Point"}
}