{
  "type": "Feature",
  "properties": {
    "iso:country":"US",
    "sg:address":"300 S Jackson St",
    "sg:city":"Denver",
    "sg:classifiers":[
        {
            "category":"Banks & Credit Unions",
            "subcategory":"Bank",
            "type":"Services"
        }
    ],
    "sg:phone":"+1 303 398 7033",
    "sg:postcode":"80209",
    "sg:province":"CO",
    "sg:tags":[
        "loan",
        "real estate"
    ],
    "wof:name":"Hawk Financial Svc",
    "wof:placetype":"venue"
},
  "geometry": {"coordinates":[-104.94255800000001,39.709326],"type":"Point"}
}