{
  "type": "Feature",
  "properties": {
    "addr:full":"110 Cedar St Log Lane Village CO 80705",
    "addr:housenumber":"110",
    "addr:postcode":"80705",
    "addr:street":"Cedar St",
    "iso:country":"US",
    "sg:address":"110 Cedar St",
    "sg:city":"Log Lane Village",
    "sg:classifiers":[
        {
            "category":"Shopping",
            "subcategory":"Hobbies, Toys, & Games",
            "type":"Retail Goods"
        }
    ],
    "sg:phone":"+1 970 867 2876",
    "sg:postcode":"80705",
    "sg:province":"CO",
    "wof:name":"Visions of Yesteryear",
    "wof:placetype":"venue"
},
  "geometry": {"coordinates":[-103.83444299999999,40.271701],"type":"Point"}
}