{
  "type": "Feature",
  "properties": {
    "iso:country":"US",
    "sg:address":"10040 W Colfax Ave",
    "sg:city":"Lakewood",
    "sg:classifiers":[
        {
            "category":"Restaurant",
            "type":"Food & Drink"
        }
    ],
    "sg:phone":"+1 303 238 7393",
    "sg:postcode":"80215",
    "sg:province":"CO",
    "wof:name":"Dino's Italian Food",
    "wof:placetype":"venue"
},
  "geometry": {"coordinates":[-105.1118,39.740144],"type":"Point"}
}