{
  "type": "Feature",
  "properties": {
    "addr:full":"110 S Parkside Dr Colorado Springs CO 80910",
    "addr:housenumber":"110",
    "addr:postcode":"80910",
    "addr:street":"S Parkside Dr",
    "iso:country":"US",
    "sg:address":"110 S Parkside Dr",
    "sg:city":"Colorado Springs",
    "sg:classifiers":[
        {
            "category":"Professional",
            "type":"Services"
        }
    ],
    "sg:phone":"+1 719 328 9818",
    "sg:postcode":"80910",
    "sg:province":"CO",
    "sg:tags":[
        "establishment"
    ],
    "wof:name":"Pikes Peak Boces",
    "wof:placetype":"venue"
},
  "geometry": {"coordinates":[-104.78537900000001,38.830533],"type":"Point"}
}