{
  "type": "Feature",
  "properties": {
    "iso:country":"US",
    "sg:address":"1 S Federal Blvd",
    "sg:city":"Denver",
    "sg:classifiers":[
        {
            "category":"Restaurant",
            "type":"Food & Drink"
        }
    ],
    "sg:phone":"+1 303 202 9480",
    "sg:postcode":"80219",
    "sg:province":"CO",
    "sg:tags":[
        "cafeteria"
    ],
    "wof:name":"Dons Snack Bar",
    "wof:placetype":"venue"
},
  "geometry": {"coordinates":[-105.025094,39.715721],"type":"Point"}
}