{
  "type": "Feature",
  "properties": {
    "addr:full":"44365 State Hwy 72 Ward CO 80481",
    "addr:housenumber":"44365",
    "addr:postcode":"80481",
    "addr:street":"State Hwy 72",
    "iso:country":"US",
    "sg:address":"44365 State Hwy 72",
    "sg:city":"Ward",
    "sg:classifiers":[
        {
            "category":"Restaurant",
            "type":"Food & Drink"
        }
    ],
    "sg:phone":"+1 303 459 3308",
    "sg:postcode":"80481",
    "sg:province":"CO",
    "sg:tags":[
        "eating"
    ],
    "wof:name":"Millsite Inn",
    "wof:placetype":"venue"
},
  "geometry": {"coordinates":[-105.502298,40.078244],"type":"Point"}
}