{
  "type": "Feature",
  "properties": {
    "addr:full":"805 Desert Flower Blvd Pueblo CO 81001",
    "addr:housenumber":"805",
    "addr:postcode":"81001",
    "addr:street":"Desert Flower Blvd",
    "iso:country":"US",
    "sg:address":"805 Desert Flower Blvd",
    "sg:city":"Pueblo",
    "sg:classifiers":[
        {
            "category":"Shopping",
            "subcategory":"Gifts & Souvenirs",
            "type":"Retail Goods"
        }
    ],
    "sg:phone":"+1 719 583 0901",
    "sg:postcode":"81001",
    "sg:province":"CO",
    "wof:name":"Carol Sue Designs",
    "wof:placetype":"venue"
},
  "geometry": {"coordinates":[-104.59709599999999,38.308682],"type":"Point"}
}