{
  "type": "Feature",
  "properties": {
    "addr:full":"60 Dahlia St Hudson CO 80642",
    "addr:housenumber":"60",
    "addr:postcode":"80642",
    "addr:street":"Dahlia St",
    "iso:country":"US",
    "sg:address":"60 Dahlia St",
    "sg:city":"Hudson",
    "sg:classifiers":[
        {
            "category":"Building & Trades",
            "subcategory":"Construction",
            "type":"Services"
        }
    ],
    "sg:phone":"+1 303 536 0806",
    "sg:postcode":"80642",
    "sg:province":"CO",
    "sg:tags":[
        "concrete",
        "contractor"
    ],
    "wof:name":"Chavez Paving & Concrete",
    "wof:placetype":"venue"
},
  "geometry": {"coordinates":[-104.64516,40.066599],"type":"Point"}
}