{
  "type": "Feature",
  "properties": {
    "addr:full":"3675 S Santa Fe Dr Englewood CO 80110",
    "addr:housenumber":"3675",
    "addr:postcode":"80110",
    "addr:street":"S Santa Fe Dr",
    "iso:country":"US",
    "sg:address":"3675 S Santa Fe Dr",
    "sg:city":"Englewood",
    "sg:classifiers":[
        {
            "category":"Wholesale",
            "subcategory":"Machinery & Supplies",
            "type":"Manufacturing & Wholesale Goods"
        }
    ],
    "sg:phone":"+1 303 761 3943",
    "sg:postcode":"80110",
    "sg:province":"CO",
    "sg:tags":[
        "contractor"
    ],
    "wof:name":"HSS Rent X",
    "wof:placetype":"venue"
},
  "geometry": {"coordinates":[-105.002945,39.650599],"type":"Point"}
}