{
  "type": "Feature",
  "properties": {
    "iso:country":"US",
    "sg:address":"625 7th Ave",
    "sg:city":"Deer Trail",
    "sg:classifiers":[
        {
            "category":"Organizations",
            "subcategory":"Religious Organization",
            "type":"Services"
        }
    ],
    "sg:phone":"+1 303 769 4923",
    "sg:postcode":"80105",
    "sg:province":"CO",
    "sg:tags":[
        "church"
    ],
    "wof:name":"Grace Baptist Church",
    "wof:placetype":"venue"
},
  "geometry": {"coordinates":[-104.040617,39.617264],"type":"Point"}
}