{
  "type": "Feature",
  "properties": {
    "iso:country":"US",
    "sg:address":"23701 Preston Rd",
    "sg:city":"Pueblo",
    "sg:classifiers":[
        {
            "category":"Education",
            "subcategory":"School",
            "type":"Public Place"
        }
    ],
    "sg:phone":"+1 719 543 6444",
    "sg:postcode":"81006",
    "sg:province":"CO",
    "wof:name":"South Mesa Elementary School",
    "wof:placetype":"venue"
},
  "geometry": {"coordinates":[-104.55161200000001,38.23097],"type":"Point"}
}