{
  "type": "Feature",
  "properties": {
    "iso:country":"US",
    "sg:address":"4390 Morning Glory Rd",
    "sg:city":"Colorado Springs",
    "sg:classifiers":[
        {
            "category":"Travel",
            "subcategory":"Travel Agent",
            "type":"Entertainment"
        }
    ],
    "sg:phone":"+1 719 282 8205",
    "sg:postcode":"80920",
    "sg:province":"CO",
    "sg:tags":[
        "operator",
        "tour"
    ],
    "wof:name":"Rock Doctor Audio Tours",
    "wof:placetype":"venue"
},
  "geometry": {"coordinates":[-104.753612,38.966675],"type":"Point"}
}