{
  "type": "Feature",
  "properties": {
    "addr:full":"1004 Vine St Aspen CO 81611",
    "addr:housenumber":"1004",
    "addr:postcode":"81611",
    "addr:street":"Vine St",
    "iso:country":"US",
    "sg:address":"1004 Vine St",
    "sg:city":"Aspen",
    "sg:classifiers":[
        {
            "category":"Real Estate",
            "subcategory":"Real Estate Agent",
            "type":"Services"
        }
    ],
    "sg:phone":"+1 970 925 4437",
    "sg:postcode":"81611",
    "sg:province":"CO",
    "wof:name":"Western Resorts International",
    "wof:placetype":"venue"
},
  "geometry": {"coordinates":[-106.81532799999999,39.195473],"type":"Point"}
}