{
  "type": "Feature",
  "properties": {
    "addr:full":"2398 Ridgeway Ct Grand Junction CO 81503",
    "addr:housenumber":"2398",
    "addr:postcode":"81503",
    "addr:street":"Ridgeway Ct",
    "iso:country":"US",
    "sg:address":"2398 Ridgeway Ct",
    "sg:city":"Grand Junction",
    "sg:classifiers":[
        {
            "category":"Shopping",
            "subcategory":"Jewelry",
            "type":"Retail Goods"
        }
    ],
    "sg:phone":"+1 970 241 4325",
    "sg:postcode":"81503",
    "sg:province":"CO",
    "wof:name":"Colorado Gifts & Jewelry LLC",
    "wof:placetype":"venue"
},
  "geometry": {"coordinates":[-108.607952,39.058167],"type":"Point"}
}