{
  "type": "Feature",
  "properties": {
    "iso:country":"US",
    "sg:address":"643 Cam del Rio",
    "sg:city":"Durango",
    "sg:classifiers":[
        {
            "category":"Recreation",
            "type":"Entertainment"
        }
    ],
    "sg:phone":"+1 970 259 4191",
    "sg:postcode":"81303",
    "sg:province":"CO",
    "sg:tags":[
        "raft",
        "trip"
    ],
    "sg:website":"www.mtnh2o.com",
    "wof:name":"Mountain Waters Rafting Inc",
    "wof:placetype":"venue"
},
  "geometry": {"coordinates":[-107.884241,37.271342],"type":"Point"}
}