{
  "type": "Feature",
  "properties": {
    "iso:country":"US",
    "sg:address":"3400 W Nevada Pl",
    "sg:city":"Denver",
    "sg:classifiers":[
        {
            "category":"Education",
            "subcategory":"School",
            "type":"Public Place"
        }
    ],
    "sg:phone":"+1 303 934 0422",
    "sg:postcode":"80219",
    "sg:province":"CO",
    "sg:tags":[
        "high",
        "middle",
        "elementary"
    ],
    "wof:name":"Lutheran-Missouri Synod Schools",
    "wof:placetype":"venue"
},
  "geometry": {"coordinates":[-105.031998,39.7104],"type":"Point"}
}