{
  "type": "Feature",
  "properties": {
    "iso:country":"US",
    "sg:address":"665 Southpointe Ct",
    "sg:city":"Colorado Springs",
    "sg:classifiers":[
        {
            "category":"Professional",
            "subcategory":"Lawyer & Legal Services",
            "type":"Services"
        }
    ],
    "sg:phone":"+1 719 632 3450",
    "sg:postcode":"80906",
    "sg:province":"CO",
    "sg:tags":[
        "attorney"
    ],
    "sg:website":"www.rmdlaw.com",
    "wof:name":"Robert M Duitch",
    "wof:placetype":"venue"
},
  "geometry": {"coordinates":[-104.81618899999999,38.796236],"type":"Point"}
}