{
  "type": "Feature",
  "properties": {
    "iso:country":"US",
    "sg:address":"2842 E Pikes Peak Ave",
    "sg:city":"Colorado Springs",
    "sg:classifiers":[
        {
            "category":"Food & Beverages",
            "subcategory":"Liquor & Beverages",
            "type":"Retail Goods"
        }
    ],
    "sg:phone":"+1 719 473 8453",
    "sg:postcode":"80909",
    "sg:province":"CO",
    "sg:tags":[
        "alcoholic"
    ],
    "wof:name":"Paul's Liquors",
    "wof:placetype":"venue"
},
  "geometry": {"coordinates":[-104.774665,38.832781],"type":"Point"}
}