{
  "type": "Feature",
  "properties": {
    "addr:full":"260 S 1st St E Cheyenne Wells CO 80810",
    "addr:housenumber":"260",
    "addr:postcode":"80810",
    "addr:street":"S 1St St E",
    "iso:country":"US",
    "sg:address":"260 S 1st St E",
    "sg:city":"Cheyenne Wells",
    "sg:classifiers":[
        {
            "category":"Mining & Drilling",
            "type":"Manufacturing & Wholesale Goods"
        }
    ],
    "sg:phone":"+1 719 767 8707",
    "sg:postcode":"80810",
    "sg:province":"CO",
    "sg:tags":[
        "field",
        "oil"
    ],
    "wof:name":"Peak Wireline",
    "wof:placetype":"venue"
},
  "geometry": {"coordinates":[-102.346361,38.820875],"type":"Point"}
}