{
  "type": "Feature",
  "properties": {
    "iso:country":"US",
    "sg:address":"7563 Sourdough Dr",
    "sg:city":"Morrison",
    "sg:classifiers":[
        {
            "category":"Building & Trades",
            "subcategory":"Construction",
            "type":"Services"
        }
    ],
    "sg:phone":"+1 303 697 5845",
    "sg:postcode":"80465",
    "sg:province":"CO",
    "sg:tags":[
        "home",
        "general",
        "family",
        "contractor"
    ],
    "wof:name":"Jarvis Construction Company",
    "wof:placetype":"venue"
},
  "geometry": {"coordinates":[-105.234476,39.585677],"type":"Point"}
}