{
  "type": "Feature",
  "properties": {
    "iso:country":"US",
    "sg:address":"302 E Saint Elmo Ave",
    "sg:city":"Colorado Springs",
    "sg:classifiers":[
        {
            "category":"Real Estate",
            "subcategory":"Developer",
            "type":"Services"
        },
        {
            "category":"Real Estate",
            "subcategory":"Real Estate Operator",
            "type":"Services"
        }
    ],
    "sg:phone":"+1 719 447 0065",
    "sg:postcode":"80906",
    "sg:province":"CO",
    "sg:tags":[
        "mobile",
        "home",
        "site"
    ],
    "wof:name":"Aspen Mobile Home Estate",
    "wof:placetype":"venue"
},
  "geometry": {"coordinates":[-104.82005700000001,38.80872],"type":"Point"}
}