{
  "type": "Feature",
  "properties": {
    "addr:full":"224 N Lincoln Ave Loveland CO 80537",
    "addr:housenumber":"224",
    "addr:postcode":"80537",
    "addr:street":"N Lincoln Ave",
    "iso:country":"US",
    "sg:address":"224 N Lincoln Ave",
    "sg:city":"Loveland",
    "sg:classifiers":[
        {
            "category":"Retail",
            "subcategory":"Auto Repair",
            "type":"Services"
        }
    ],
    "sg:phone":"+1 970 663 2051",
    "sg:postcode":"80537",
    "sg:province":"CO",
    "sg:tags":[
        "body",
        "automobile",
        "used",
        "painting"
    ],
    "wof:name":"Dave's Auto Body",
    "wof:placetype":"venue"
},
  "geometry": {"coordinates":[-105.07314700000001,40.394148],"type":"Point"}
}