{
  "type": "Feature",
  "properties": {
    "iso:country":"US",
    "sg:address":"6595 S Dayton St",
    "sg:city":"Englewood",
    "sg:classifiers":[
        {
            "category":"Wholesale",
            "subcategory":"Machinery & Supplies",
            "type":"Manufacturing & Wholesale Goods"
        }
    ],
    "sg:phone":"+1 303 799 1377",
    "sg:postcode":"80111",
    "sg:province":"CO",
    "sg:tags":[
        "industrial"
    ],
    "wof:name":"Wilson Valve Specialities",
    "wof:placetype":"venue"
},
  "geometry": {"coordinates":[-104.876255,39.596763],"type":"Point"}
}