{
  "type": "Feature",
  "properties": {
    "addr:full":"2458 Lafayette Rd Colorado Springs CO 80907",
    "addr:housenumber":"2458",
    "addr:postcode":"80907",
    "iso:country":"US",
    "sg:address":"2458 Lafayette Rd",
    "sg:city":"Colorado Springs",
    "sg:classifiers":[
        {
            "category":"Building & Trades",
            "subcategory":"Construction",
            "type":"Services"
        }
    ],
    "sg:phone":"+1 719 632 4043",
    "sg:postcode":"80907",
    "sg:province":"CO",
    "sg:tags":[
        "house"
    ],
    "wof:name":"Ledford Custom Paint & Rmdlg",
    "wof:placetype":"venue"
},
  "geometry": {"coordinates":[-104.79947900000001,38.865892],"type":"Point"}
}