{
  "type": "Feature",
  "properties": {
    "iso:country":"US",
    "sg:address":"127 Justice Center Rd",
    "sg:city":"Canon City",
    "sg:classifiers":[
        {
            "category":"Sports & Exercise",
            "subcategory":"Gym",
            "type":"Entertainment"
        }
    ],
    "sg:phone":"+1 719 275 9789",
    "sg:postcode":"81212",
    "sg:province":"CO",
    "sg:tags":[
        "club",
        "health",
        "studio",
        "gymnasium"
    ],
    "wof:name":"Curves For Women",
    "wof:placetype":"venue"
},
  "geometry": {"coordinates":[-105.182874,38.441054],"type":"Point"}
}