{
  "type": "Feature",
  "properties": {
    "addr:full":"27 E Vermijo Ave Colorado Springs CO 80903",
    "addr:housenumber":"27",
    "addr:postcode":"80903",
    "addr:street":"E Vermijo Ave",
    "iso:country":"US",
    "sg:address":"27 E Vermijo Ave",
    "sg:city":"Colorado Springs",
    "sg:classifiers":[
        {
            "category":"Health Services",
            "subcategory":"Doctor",
            "type":"Services"
        }
    ],
    "sg:phone":"+1 719 597 9737",
    "sg:postcode":"80903",
    "sg:province":"CO",
    "wof:name":"Huffman Thomas D DDS",
    "wof:placetype":"venue"
},
  "geometry": {"coordinates":[-104.824153,38.829532],"type":"Point"}
}