{
  "type": "Feature",
  "properties": {
    "iso:country":"US",
    "sg:address":"225 S Pine St",
    "sg:city":"Telluride",
    "sg:classifiers":[
        {
            "category":"Food & Beverages",
            "subcategory":"Groceries & Convenience Stores",
            "type":"Retail Goods"
        }
    ],
    "sg:phone":"+1 970 728 0200",
    "sg:postcode":"81435",
    "sg:province":"CO",
    "sg:tags":[
        "market"
    ],
    "wof:name":"Wildflour Market",
    "wof:placetype":"venue"
},
  "geometry": {"coordinates":[-107.81124800000001,37.936145],"type":"Point"}
}