{
  "type": "Feature",
  "properties": {
    "iso:country":"US",
    "sg:address":"2940 E Las Vegas St",
    "sg:city":"Colorado Springs",
    "sg:classifiers":[
        {
            "category":"Wholesale",
            "subcategory":"Machinery & Supplies",
            "type":"Manufacturing & Wholesale Goods"
        }
    ],
    "sg:phone":"+1 719 392 1155",
    "sg:postcode":"80906",
    "sg:province":"CO",
    "sg:tags":[
        "equipment",
        "contractor"
    ],
    "wof:name":"Power Equipment Company",
    "wof:placetype":"venue"
},
  "geometry": {"coordinates":[-104.772271,38.778675],"type":"Point"}
}