{
  "type": "Feature",
  "properties": {
    "iso:country":"US",
    "sg:address":"2648 S Parker Road Suite Suite",
    "sg:city":"Denver",
    "sg:classifiers":[
        {
            "category":"Shopping",
            "subcategory":"Jewelry",
            "type":"Retail Goods"
        },
        {
            "category":"Shopping",
            "subcategory":"Pawn Shop",
            "type":"Retail Goods"
        }
    ],
    "sg:phone":"+1 303 337 7518",
    "sg:postcode":"80202",
    "sg:province":"CO",
    "wof:name":"Fast Cash Pawn & Payday Loan",
    "wof:placetype":"venue"
},
  "geometry": {"coordinates":[-104.99574699999999,39.749758],"type":"Point"}
}