{
  "type": "Feature",
  "properties": {
    "iso:country":"US",
    "sg:address":"2805 Wilderness Pl",
    "sg:city":"Boulder",
    "sg:classifiers":[
        {
            "category":"Professional",
            "subcategory":"Advertising",
            "type":"Services"
        }
    ],
    "sg:phone":"+1 303 447 8103",
    "sg:postcode":"80301",
    "sg:province":"CO",
    "wof:name":"Sportsrug Com",
    "wof:placetype":"venue"
},
  "geometry": {"coordinates":[-105.248885,40.025975],"type":"Point"}
}