{
  "type": "Feature",
  "properties": {
    "iso:country":"US",
    "sg:address":"441 S Wadsworth Blvd",
    "sg:city":"Denver",
    "sg:classifiers":[
        {
            "category":"Real Estate",
            "subcategory":"Real Estate Operator",
            "type":"Services"
        }
    ],
    "sg:phone":"+1 303 232 3707",
    "sg:postcode":"80226",
    "sg:province":"CO",
    "sg:tags":[
        "building",
        "nonresidential"
    ],
    "wof:name":"441 Office Building",
    "wof:placetype":"venue"
},
  "geometry": {"coordinates":[-105.081563,39.706953],"type":"Point"}
}