{
  "type": "Feature",
  "properties": {
    "addr:full":"1155 S Huron St Denver CO 80223",
    "addr:housenumber":"1155",
    "addr:postcode":"80223",
    "addr:street":"S Huron St",
    "iso:country":"US",
    "sg:address":"1155 S Huron St",
    "sg:city":"Denver",
    "sg:classifiers":[
        {
            "category":"Real Estate",
            "subcategory":"Real Estate Operator",
            "type":"Services"
        }
    ],
    "sg:phone":"+1 303 722 0370",
    "sg:postcode":"80223",
    "sg:province":"CO",
    "sg:tags":[
        "building",
        "special",
        "nonresidential"
    ],
    "wof:name":"U-Stor-All",
    "wof:placetype":"venue"
},
  "geometry": {"coordinates":[-104.996877,39.69587],"type":"Point"}
}