{
  "type": "Feature",
  "properties": {
    "iso:country":"US",
    "sg:address":"13730 Smith Rd",
    "sg:city":"Aurora",
    "sg:classifiers":[
        {
            "category":"Building & Trades",
            "subcategory":"Construction",
            "type":"Services"
        }
    ],
    "sg:phone":"+1 303 360 0488",
    "sg:postcode":"80011",
    "sg:province":"CO",
    "sg:tags":[
        "house",
        "remodeling",
        "general"
    ],
    "wof:name":"Colorado Sound Insulators Inc",
    "wof:placetype":"venue"
},
  "geometry": {"coordinates":[-104.832864,39.765548],"type":"Point"}
}