{
  "type": "Feature",
  "properties": {
    "iso:country":"US",
    "sg:address":"1398 US Hwy 287",
    "sg:city":"Broomfield",
    "sg:classifiers":[
        {
            "category":"Food & Beverages",
            "subcategory":"Liquor & Beverages",
            "type":"Retail Goods"
        }
    ],
    "sg:phone":"+1 303 466 6421",
    "sg:postcode":"80020",
    "sg:province":"CO",
    "sg:tags":[
        "packaged"
    ],
    "wof:name":"Go Go Liquors",
    "wof:placetype":"venue"
},
  "geometry": {"coordinates":[-105.090925,39.935745],"type":"Point"}
}