{
  "type": "Feature",
  "properties": {
    "iso:country":"US",
    "sg:address":"5275 Wadsworth Byp",
    "sg:city":"Arvada",
    "sg:classifiers":[
        {
            "category":"Shopping",
            "subcategory":"Stationery & Office Supplies",
            "type":"Retail Goods"
        }
    ],
    "sg:phone":"+1 303 940 8610",
    "sg:postcode":"80002",
    "sg:province":"CO",
    "sg:tags":[
        "equipment"
    ],
    "sg:website":"http://www.officemax.com",
    "wof:name":"OfficeMax-PrintingEquipment&Supplies",
    "wof:placetype":"venue"
},
  "geometry": {"coordinates":[-105.080946,39.792342],"type":"Point"}
}