{
  "type": "Feature",
  "properties": {
    "addr:full":"301 Bryant St Denver CO 80219",
    "addr:housenumber":"301",
    "addr:postcode":"80219",
    "addr:street":"Bryant St",
    "iso:country":"US",
    "sg:address":"301 Bryant St",
    "sg:city":"Denver",
    "sg:classifiers":[
        {
            "category":"Wholesale",
            "subcategory":"Durable Goods & Equipment",
            "type":"Manufacturing & Wholesale Goods"
        }
    ],
    "sg:phone":"+1 303 935 5566",
    "sg:postcode":"80219",
    "sg:province":"CO",
    "wof:name":"Streamline Distribution",
    "wof:placetype":"venue"
},
  "geometry": {"coordinates":[-105.018663,39.722037],"type":"Point"}
}