{
  "type": "Feature",
  "properties": {
    "addr:full":"530 W 16th St Salida CO 81201",
    "addr:housenumber":"530",
    "addr:postcode":"81201",
    "addr:street":"W 16Th St",
    "iso:country":"US",
    "sg:address":"530 W 16th St",
    "sg:city":"Salida",
    "sg:classifiers":[
        {
            "category":"Health Services",
            "subcategory":"Nursing And Care Facility",
            "type":"Services"
        }
    ],
    "sg:phone":"+1 719 539 2557",
    "sg:postcode":"81201",
    "sg:province":"CO",
    "sg:tags":[
        "skilled"
    ],
    "wof:name":"Life Care Center of Salida",
    "wof:placetype":"venue"
},
  "geometry": {"coordinates":[-106.009325,38.526922],"type":"Point"}
}