{
  "type": "Feature",
  "properties": {
    "iso:country":"US",
    "sg:address":"1074 Hawk Ct",
    "sg:city":"Louisville",
    "sg:classifiers":[
        {
            "category":"Shopping",
            "subcategory":"Hobbies, Toys, & Games",
            "type":"Retail Goods"
        }
    ],
    "sg:phone":"+1 303 604 6563",
    "sg:postcode":"80027",
    "sg:province":"CO",
    "wof:name":"Hickory Dickory Dock",
    "wof:placetype":"venue"
},
  "geometry": {"coordinates":[-105.151365,39.979788],"type":"Point"}
}