{
  "type": "Feature",
  "properties": {
    "iso:country":"US",
    "sg:address":"37 Co Rd 9",
    "sg:city":"Aspen",
    "sg:classifiers":[
        {
            "category":"Retail",
            "subcategory":"Laundry & Dry Cleaning",
            "type":"Services"
        }
    ],
    "sg:phone":"+1 970 925 9255",
    "sg:postcode":"81641",
    "sg:province":"CO",
    "sg:tags":[
        "cleaners",
        "rug",
        "carpet"
    ],
    "wof:name":"Service Master",
    "wof:placetype":"venue"
},
  "geometry": {"coordinates":[-107.96992400000001,40.138002],"type":"Point"}
}