{
  "type": "Feature",
  "properties": {
    "iso:country":"US",
    "sg:address":"113 W 4th St",
    "sg:city":"Pueblo",
    "sg:classifiers":[
        {
            "category":"Shopping",
            "subcategory":"Used Merchandise",
            "type":"Retail Goods"
        }
    ],
    "sg:phone":"+1 719 545 4661",
    "sg:postcode":"81004",
    "sg:province":"CO",
    "sg:tags":[
        "antique"
    ],
    "wof:name":"Oldies But Goodies Antique Shp",
    "wof:placetype":"venue"
},
  "geometry": {"coordinates":[-104.608408,38.270741],"type":"Point"}
}