{
  "type": "Feature",
  "properties": {
    "addr:full":"254 Co Rd 500 Bayfield CO 81122",
    "addr:housenumber":"254;500",
    "addr:postcode":"bayfield;81122",
    "addr:street":"Co Rd",
    "iso:country":"US",
    "sg:address":"254 Co Rd 500",
    "sg:city":"Bayfield",
    "sg:classifiers":[
        {
            "category":"Travel",
            "subcategory":"Campground",
            "type":"Entertainment"
        }
    ],
    "sg:phone":"+1 970 884 4115",
    "sg:postcode":"81122",
    "sg:province":"CO",
    "sg:tags":[
        "camp"
    ],
    "wof:name":"Wits End Ranch",
    "wof:placetype":"venue"
},
  "geometry": {"coordinates":[-107.556703,37.446052],"type":"Point"}
}