{
  "type": "Feature",
  "properties": {
    "iso:country":"US",
    "sg:address":"8464 W 74th Ave",
    "sg:city":"Arvada",
    "sg:classifiers":[
        {
            "category":"Restaurant",
            "type":"Food & Drink"
        }
    ],
    "sg:phone":"+1 303 463 5530",
    "sg:postcode":"80005",
    "sg:province":"CO",
    "sg:tags":[
        "communications",
        "eating",
        "telephone"
    ],
    "wof:name":"Turning Point Enterprises LLC",
    "wof:placetype":"venue"
},
  "geometry": {"coordinates":[-105.092243,39.830717],"type":"Point"}
}