{
  "type": "Feature",
  "properties": {
    "addr:full":"65 Hanson Ln Pueblo CO 81001",
    "addr:housenumber":"65",
    "addr:postcode":"81001",
    "addr:street":"Hanson Ln",
    "iso:country":"US",
    "sg:address":"65 Hanson Ln",
    "sg:city":"Pueblo",
    "sg:classifiers":[
        {
            "category":"Building & Trades",
            "subcategory":"Electrical",
            "type":"Services"
        }
    ],
    "sg:phone":"+1 719 545 4411",
    "sg:postcode":"81001",
    "sg:province":"CO",
    "sg:tags":[
        "electric",
        "contractor"
    ],
    "wof:name":"A Quality Electric Svc",
    "wof:placetype":"venue"
},
  "geometry": {"coordinates":[-104.57532500000001,38.291392],"type":"Point"}
}