{
  "type": "Feature",
  "properties": {
    "addr:full":"615 Juniper Ave Boulder CO 80304",
    "addr:housenumber":"615",
    "addr:postcode":"80304",
    "addr:street":"Juniper Ave",
    "iso:country":"US",
    "sg:address":"615 Juniper Ave",
    "sg:city":"Boulder",
    "sg:classifiers":[
        {
            "category":"Food & Beverages",
            "subcategory":"Groceries & Convenience Stores",
            "type":"Retail Goods"
        }
    ],
    "sg:phone":"+1 303 938 8223",
    "sg:postcode":"80304",
    "sg:province":"CO",
    "sg:tags":[
        "product"
    ],
    "wof:name":"Juniper Natural Foods",
    "wof:placetype":"venue"
},
  "geometry": {"coordinates":[-105.287678,40.037329],"type":"Point"}
}