{
  "type": "Feature",
  "properties": {
    "iso:country":"US",
    "sg:address":"7405 W US Hwy 50",
    "sg:city":"Salida",
    "sg:classifiers":[
        {
            "category":"Social Services",
            "type":"Services"
        }
    ],
    "sg:phone":"+1 719 539 2676",
    "sg:postcode":"81201",
    "sg:province":"CO",
    "sg:tags":[
        "counselor",
        "marriage",
        "family"
    ],
    "wof:name":"ARC Counseling Svc",
    "wof:placetype":"venue"
},
  "geometry": {"coordinates":[-106.017313,38.523827],"type":"Point"}
}