{
  "type": "Feature",
  "properties": {
    "addr:full":"6862 Galley Rd Colorado Springs CO 80915",
    "addr:housenumber":"6862",
    "addr:postcode":"80915",
    "addr:street":"Galley Rd",
    "iso:country":"US",
    "sg:address":"6862 Galley Rd",
    "sg:city":"Colorado Springs",
    "sg:classifiers":[
        {
            "category":"Organizations",
            "subcategory":"Religious Organization",
            "type":"Services"
        }
    ],
    "sg:phone":"+1 719 596 6523",
    "sg:postcode":"80915",
    "sg:province":"CO",
    "sg:tags":[
        "church"
    ],
    "wof:name":"New Heart Community Church",
    "wof:placetype":"venue"
},
  "geometry": {"coordinates":[-104.70267,38.845516],"type":"Point"}
}