{
  "type": "Feature",
  "properties": {
    "iso:country":"US",
    "sg:address":"1165 Delaware St",
    "sg:city":"Denver",
    "sg:classifiers":[
        {
            "category":"Organizations",
            "subcategory":"Professional Association",
            "type":"Services"
        }
    ],
    "sg:phone":"+1 303 573 1717",
    "sg:postcode":"80204",
    "sg:province":"CO",
    "sg:tags":[
        "employer"
    ],
    "sg:website":"http://www.afm655.org",
    "wof:name":"Our Musical Heritage Inc",
    "wof:placetype":"venue"
},
  "geometry": {"coordinates":[-104.992935,39.734764],"type":"Point"}
}