{
  "type": "Feature",
  "properties": {
    "iso:country":"US",
    "sg:address":"475 S 8th St",
    "sg:city":"Pagosa Springs",
    "sg:classifiers":[
        {
            "category":"Social Services",
            "subcategory":"Child Care",
            "type":"Services"
        }
    ],
    "sg:phone":"+1 970 264 2484",
    "sg:postcode":"81147",
    "sg:province":"CO",
    "sg:tags":[
        "kindergarten",
        "academic",
        "school"
    ],
    "sg:website":"www.tch.org",
    "wof:name":"Pagosa Springs Head Start",
    "wof:placetype":"venue"
},
  "geometry": {"coordinates":[-107.017259,37.260348],"type":"Point"}
}