{
  "type": "Feature",
  "properties": {
    "iso:country":"US",
    "sg:address":"48 S Broadway",
    "sg:city":"Denver",
    "sg:classifiers":[
        {
            "category":"Building & Trades",
            "subcategory":"Locksmith",
            "type":"Services"
        }
    ],
    "sg:phone":"+1 303 573 0923",
    "sg:postcode":"80209",
    "sg:province":"CO",
    "sg:tags":[
        "key"
    ],
    "wof:name":"Locksmith",
    "wof:placetype":"venue"
},
  "geometry": {"coordinates":[-104.987692,39.71575],"type":"Point"}
}