{
  "type": "Feature",
  "properties": {
    "addr:full":"7541 E Iliff Ave Denver CO 80231",
    "addr:housenumber":"7541",
    "addr:postcode":"80231",
    "addr:street":"E Iliff Ave",
    "iso:country":"US",
    "sg:address":"7541 E Iliff Ave",
    "sg:city":"Denver",
    "sg:classifiers":[
        {
            "category":"Banks & Credit Unions",
            "subcategory":"Bank",
            "type":"Services"
        }
    ],
    "sg:phone":"+1 303 832 4816",
    "sg:postcode":"80231",
    "sg:province":"CO",
    "wof:name":"Colorado State Employees Credit Union",
    "wof:placetype":"venue"
},
  "geometry": {"coordinates":[-104.899469,39.67495],"type":"Point"}
}