{
  "type": "Feature",
  "properties": {
    "addr:full":"129 S Madison Ave Loveland CO 80537",
    "addr:housenumber":"129",
    "addr:postcode":"80537",
    "addr:street":"S Madison Ave",
    "iso:country":"US",
    "sg:address":"129 S Madison Ave",
    "sg:city":"Loveland",
    "sg:classifiers":[
        {
            "category":"Retail",
            "subcategory":"Auto Rental",
            "type":"Services"
        }
    ],
    "sg:phone":"+1 970 667 3450",
    "sg:postcode":"80537",
    "sg:province":"CO",
    "sg:tags":[
        "renting",
        "automobile"
    ],
    "wof:name":"Hertz Rent A Car",
    "wof:placetype":"venue"
},
  "geometry": {"coordinates":[-105.058959,40.390017],"type":"Point"}
}