{
  "type": "Feature",
  "properties": {
    "addr:full":"2400 Cherry Creek Dr S Denver CO 80209",
    "addr:housenumber":"2400",
    "addr:postcode":"80209",
    "addr:street":"Cherry Creek Dr S",
    "iso:country":"US",
    "sg:address":"2400 Cherry Creek Dr S",
    "sg:city":"Denver",
    "sg:classifiers":[
        {
            "category":"Banks & Credit Unions",
            "subcategory":"Bank",
            "type":"Services"
        }
    ],
    "sg:phone":"+1 303 777 3332",
    "sg:postcode":"80209",
    "sg:province":"CO",
    "sg:tags":[
        "loan",
        "broker",
        "business"
    ],
    "wof:name":"National Acceptance Company",
    "wof:placetype":"venue"
},
  "geometry": {"coordinates":[-104.956898,39.715386],"type":"Point"}
}