{
  "type": "Feature",
  "properties": {
    "addr:full":"2880 Enchanted Cir W Colorado Springs CO 80917",
    "addr:housenumber":"2880",
    "addr:postcode":"80917",
    "addr:street":"Enchanted Cir W",
    "iso:country":"US",
    "sg:address":"2880 Enchanted Cir W",
    "sg:city":"Colorado Springs",
    "sg:classifiers":[
        {
            "category":"Real Estate",
            "subcategory":"Real Estate Agent",
            "type":"Services"
        }
    ],
    "sg:phone":"+1 719 597 1973",
    "sg:postcode":"80917",
    "sg:province":"CO",
    "sg:tags":[
        "appraiser"
    ],
    "wof:name":"Springs Appraisal Svc",
    "wof:placetype":"venue"
},
  "geometry": {"coordinates":[-104.739192,38.873126],"type":"Point"}
}