{
  "type": "Feature",
  "properties": {
    "iso:country":"US",
    "sg:address":"1809 L Rd",
    "sg:city":"Fruita",
    "sg:classifiers":[
        {
            "category":"Wholesale",
            "subcategory":"Groceries",
            "type":"Manufacturing & Wholesale Goods"
        }
    ],
    "sg:phone":"+1 970 858 9807",
    "sg:postcode":"81521",
    "sg:province":"CO",
    "sg:tags":[
        "general"
    ],
    "wof:name":"Schwans Consumer Brands N Amer",
    "wof:placetype":"venue"
},
  "geometry": {"coordinates":[-108.71972100000001,39.178813],"type":"Point"}
}