{
  "type": "Feature",
  "properties": {
    "iso:country":"US",
    "sg:address":"3335 N Academy Blvd",
    "sg:city":"Colorado Springs",
    "sg:classifiers":[
        {
            "category":"Shopping",
            "subcategory":"Florist",
            "type":"Retail Goods"
        }
    ],
    "sg:phone":"+1 719 574 2207",
    "sg:postcode":"80917",
    "sg:province":"CO",
    "wof:name":"Safeway",
    "wof:placetype":"venue"
},
  "geometry": {"coordinates":[-104.756991,38.881063],"type":"Point"}
}