{
  "type": "Feature",
  "properties": {
    "addr:full":"278 Rippy Ln New Castle CO 81647",
    "addr:housenumber":"278",
    "addr:postcode":"81647",
    "addr:street":"Rippy Ln",
    "iso:country":"US",
    "sg:address":"278 Rippy Ln",
    "sg:city":"New Castle",
    "sg:classifiers":[
        {
            "category":"Freight",
            "type":"Transportation"
        }
    ],
    "sg:phone":"+1 970 984 2216",
    "sg:postcode":"81647",
    "sg:province":"CO",
    "sg:tags":[
        "mover"
    ],
    "wof:name":"All Hours Moving",
    "wof:placetype":"venue"
},
  "geometry": {"coordinates":[-107.57096900000001,39.553169],"type":"Point"}
}