{
  "type": "Feature",
  "properties": {
    "addr:full":"5010 Boardwalk Dr Colorado Springs CO 80919",
    "addr:housenumber":"5010",
    "addr:postcode":"80919",
    "addr:street":"Boardwalk Dr",
    "iso:country":"US",
    "sg:address":"5010 Boardwalk Dr",
    "sg:city":"Colorado Springs",
    "sg:classifiers":[
        {
            "category":"Retail",
            "subcategory":"Veterinary Services",
            "type":"Services"
        }
    ],
    "sg:phone":"+1 719 533 0910",
    "sg:postcode":"80919",
    "sg:province":"CO",
    "wof:name":"Mountain Shadows Pet Hospital",
    "wof:placetype":"venue"
},
  "geometry": {"coordinates":[-104.864571,38.904176],"type":"Point"}
}