{
  "type": "Feature",
  "properties": {
    "addr:full":"191 E Agate Ave Granby CO 80446",
    "addr:housenumber":"191",
    "addr:postcode":"80446",
    "addr:street":"E Agate Ave",
    "iso:country":"US",
    "sg:address":"191 E Agate Ave",
    "sg:city":"Granby",
    "sg:classifiers":[
        {
            "category":"Real Estate",
            "subcategory":"Real Estate Agent",
            "type":"Services"
        }
    ],
    "sg:phone":"+1 970 887 9588",
    "sg:postcode":"80446",
    "sg:province":"CO",
    "wof:name":"Grand County Board Of Realtors",
    "wof:placetype":"venue"
},
  "geometry": {"coordinates":[-105.93923700000001,40.085486],"type":"Point"}
}