{
  "type": "Feature",
  "properties": {
    "addr:full":"1250 S Buckley Rd Aurora CO 80017",
    "addr:housenumber":"1250",
    "addr:postcode":"80017",
    "addr:street":"S Buckley Rd",
    "iso:country":"US",
    "sg:address":"1250 S Buckley Rd",
    "sg:city":"Aurora",
    "sg:classifiers":[
        {
            "category":"Personal",
            "subcategory":"Beauty Salon",
            "type":"Services"
        }
    ],
    "sg:phone":"+1 720 747 0253",
    "sg:postcode":"80017",
    "sg:province":"CO",
    "wof:name":"Supercuts",
    "wof:placetype":"venue"
},
  "geometry": {"coordinates":[-104.79098999999999,39.694206],"type":"Point"}
}