{
  "type": "Feature",
  "properties": {
    "addr:full":"12163 Sheridan Blvd Broomfield CO 80020",
    "addr:housenumber":"12163",
    "addr:postcode":"80020",
    "addr:street":"Sheridan Blvd",
    "iso:country":"US",
    "sg:address":"12163 Sheridan Blvd",
    "sg:city":"Broomfield",
    "sg:classifiers":[
        {
            "category":"Shopping",
            "subcategory":"Pharmacy",
            "type":"Retail Goods"
        }
    ],
    "sg:phone":"+1 303 410 8777",
    "sg:postcode":"80020",
    "sg:province":"CO",
    "wof:name":"Longs Drugs 460",
    "wof:placetype":"venue"
},
  "geometry": {"coordinates":[-105.05302500000001,39.914783],"type":"Point"}
}