{
  "type": "Feature",
  "properties": {
    "addr:full":"3000 S Williams St Denver CO 80210",
    "addr:housenumber":"3000",
    "addr:postcode":"80210",
    "addr:street":"S Williams St",
    "iso:country":"US",
    "sg:address":"3000 S Williams St",
    "sg:city":"Denver",
    "sg:classifiers":[
        {
            "category":"Home & Garden",
            "subcategory":"Garden Supply",
            "type":"Retail Goods"
        }
    ],
    "sg:phone":"+1 303 758 3886",
    "sg:postcode":"80210",
    "sg:province":"CO",
    "sg:tags":[
        "lawn",
        "mower"
    ],
    "wof:name":"Walker Mower",
    "wof:placetype":"venue"
},
  "geometry": {"coordinates":[-104.966999,39.660405],"type":"Point"}
}