{
  "type": "Feature",
  "properties": {
    "addr:full":"3050 67th Ave Greeley CO 80634",
    "addr:housenumber":"3050",
    "addr:postcode":"80634",
    "addr:street":"67Th Ave",
    "iso:country":"US",
    "sg:address":"3050 67th Ave",
    "sg:city":"Greeley",
    "sg:classifiers":[
        {
            "category":"Ice Cream",
            "type":"Food & Drink"
        }
    ],
    "sg:menulink":"http://www.allmenus.com/co/greeley/230303-marble-slab-creamery/menu/",
    "sg:phone":"+1 970 330 1900",
    "sg:postcode":"80634",
    "sg:province":"CO",
    "sg:tags":[
        "american"
    ],
    "wof:name":"Marble Slab Creamery",
    "wof:placetype":"venue"
},
  "geometry": {"coordinates":[-104.78709499999999,40.388574],"type":"Point"}
}