{
  "type": "Feature",
  "properties": {
    "iso:country":"US",
    "sg:address":"7861 Grizzly Way",
    "sg:city":"Evergreen",
    "sg:classifiers":[
        {
            "category":"Building & Trades",
            "subcategory":"Landscaping Services",
            "type":"Services"
        }
    ],
    "sg:phone":"+1 303 670 8252",
    "sg:postcode":"80439",
    "sg:province":"CO",
    "sg:tags":[
        "landscape",
        "contractor"
    ],
    "sg:website":"www.coloradonaturedesign.com",
    "wof:name":"Colorado Nature Design Inc",
    "wof:placetype":"venue"
},
  "geometry": {"coordinates":[-105.311871,39.571134],"type":"Point"}
}