{
  "type": "Feature",
  "properties": {
    "addr:full":"2222 S Albion St Denver CO 80222",
    "addr:housenumber":"2222",
    "addr:postcode":"80222",
    "addr:street":"S Albion St",
    "iso:country":"US",
    "sg:address":"2222 S Albion St",
    "sg:city":"Denver",
    "sg:classifiers":[
        {
            "category":"Manufacturing",
            "subcategory":"Printing",
            "type":"Manufacturing & Wholesale Goods"
        }
    ],
    "sg:phone":"+1 303 753 6109",
    "sg:postcode":"80222",
    "sg:province":"CO",
    "sg:tags":[
        "newspaper"
    ],
    "wof:name":"Restaurant News Of The Rockies",
    "wof:placetype":"venue"
},
  "geometry": {"coordinates":[-104.93951800000001,39.675226],"type":"Point"}
}