{
  "type": "Feature",
  "properties": {
    "iso:country":"US",
    "sg:address":"1007 S Gay Dr",
    "sg:city":"Longmont",
    "sg:classifiers":[
        {
            "category":"Professional",
            "type":"Services"
        }
    ],
    "sg:phone":"+1 303 776 7789",
    "sg:postcode":"80501",
    "sg:province":"CO",
    "wof:name":"Steel Huggers Inc",
    "wof:placetype":"venue"
},
  "geometry": {"coordinates":[-105.109652,40.146177],"type":"Point"}
}