{
  "type": "Feature",
  "properties": {
    "addr:full":"2040 Ken Pratt Blvd Longmont CO 80501",
    "addr:housenumber":"2040",
    "addr:postcode":"80501",
    "addr:street":"Ken Pratt Blvd",
    "iso:country":"US",
    "sg:address":"2040 Ken Pratt Blvd",
    "sg:city":"Longmont",
    "sg:phone":"+1 303 702 9995",
    "sg:postcode":"80501",
    "sg:province":"CO",
    "sg:website":"http://www.ihop.com",
    "wof:name":"Ihop",
    "wof:placetype":"venue"
},
  "geometry": {"coordinates":[-105.12715799999999,40.144022],"type":"Point"}
}