{
  "type": "Feature",
  "properties": {
    "addr:full":"370 Interlocken Blvd Broomfield CO 80021",
    "addr:housenumber":"370",
    "addr:postcode":"80021",
    "addr:street":"Interlocken Blvd",
    "iso:country":"US",
    "sg:address":"370 Interlocken Blvd",
    "sg:city":"Broomfield",
    "sg:classifiers":[
        {
            "category":"Utilities",
            "subcategory":"Telephone",
            "type":"Services"
        }
    ],
    "sg:phone":"+1 303 327 1408",
    "sg:postcode":"80021",
    "sg:province":"CO",
    "sg:tags":[
        "communications"
    ],
    "wof:name":"Eclata Inc",
    "wof:placetype":"venue"
},
  "geometry": {"coordinates":[-105.110991,39.921844],"type":"Point"}
}