{
  "type": "Feature",
  "properties": {
    "addr:full":"750 S 9th St Grand Junction CO 81501",
    "addr:housenumber":"750",
    "addr:postcode":"81501",
    "addr:street":"S 9Th St",
    "iso:country":"US",
    "sg:address":"750 S 9th St",
    "sg:city":"Grand Junction",
    "sg:classifiers":[
        {
            "category":"Professional",
            "type":"Services"
        }
    ],
    "sg:phone":"+1 970 243 4470",
    "sg:postcode":"81501",
    "sg:province":"CO",
    "sg:tags":[
        "establishment"
    ],
    "wof:name":"Right Stuff",
    "wof:placetype":"venue"
},
  "geometry": {"coordinates":[-108.557613,39.060269],"type":"Point"}
}