{
  "type": "Feature",
  "properties": {
    "iso:country":"US",
    "sg:address":"1234 E Main St",
    "sg:city":"Montrose",
    "sg:classifiers":[
        {
            "category":"Health Services",
            "subcategory":"Podiatrist",
            "type":"Services"
        }
    ],
    "sg:phone":"+1 970 249 6363",
    "sg:postcode":"81401",
    "sg:province":"CO",
    "wof:name":"Podiatrist Foot Specialists",
    "wof:placetype":"venue"
},
  "geometry": {"coordinates":[-107.867634,38.485587],"type":"Point"}
}