{
  "type": "Feature",
  "properties": {
    "iso:country":"US",
    "sg:address":"1634 Walnut St",
    "sg:city":"Boulder",
    "sg:classifiers":[
        {
            "category":"Social Services",
            "type":"Services"
        }
    ],
    "sg:phone":"+1 303 543 7777",
    "sg:postcode":"80302",
    "sg:province":"CO",
    "sg:tags":[
        "counselor",
        "marriage",
        "family"
    ],
    "wof:name":"Ann M Norris",
    "wof:placetype":"venue"
},
  "geometry": {"coordinates":[-105.273405,40.01806],"type":"Point"}
}