{
  "type": "Feature",
  "properties": {
    "iso:country":"US",
    "sg:address":"600 S Cherry St Ste 527",
    "sg:city":"Denver",
    "sg:classifiers":[
        {
            "category":"Education",
            "subcategory":"School",
            "type":"Public Place"
        }
    ],
    "sg:phone":"+1 303 388 6009",
    "sg:postcode":"80246",
    "sg:province":"CO",
    "sg:website":"www.razortechnical.com",
    "wof:name":"Razor Technical Staffing",
    "wof:placetype":"venue"
},
  "geometry": {"coordinates":[-104.933249,39.705783],"type":"Point"}
}