{
  "type": "Feature",
  "properties": {
    "addr:full":"11845 E 124th Ave Henderson CO 80640",
    "addr:housenumber":"11845",
    "addr:postcode":"80640",
    "addr:street":"E 124Th Ave",
    "iso:country":"US",
    "sg:address":"11845 E 124th Ave",
    "sg:city":"Henderson",
    "sg:classifiers":[
        {
            "category":"Manufacturing",
            "subcategory":"Signs",
            "type":"Manufacturing & Wholesale Goods"
        }
    ],
    "sg:phone":"+1 303 659 5848",
    "sg:postcode":"80640",
    "sg:province":"CO",
    "wof:name":"Stan's Sign Co",
    "wof:placetype":"venue"
},
  "geometry": {"coordinates":[-104.849644,39.921688],"type":"Point"}
}