{
  "type": "Feature",
  "properties": {
    "iso:country":"US",
    "sg:address":"441 Wadsworth Blvd",
    "sg:city":"Lakewood",
    "sg:classifiers":[
        {
            "category":"Real Estate",
            "subcategory":"Real Estate Operator",
            "type":"Services"
        }
    ],
    "sg:phone":"+1 303 232 3707",
    "sg:postcode":"80226",
    "sg:province":"CO",
    "sg:tags":[
        "building",
        "parks"
    ],
    "wof:name":"San Marco Investments",
    "wof:placetype":"venue"
},
  "geometry": {"coordinates":[-105.08158299999999,39.723191],"type":"Point"}
}