{
  "type": "Feature",
  "properties": {
    "iso:country":"US",
    "sg:address":"3150 Wesley Pl",
    "sg:city":"Colorado Springs",
    "sg:classifiers":[
        {
            "category":"Retail",
            "subcategory":"Laundry & Dry Cleaning",
            "type":"Services"
        }
    ],
    "sg:phone":"+1 719 599 5325",
    "sg:postcode":"80917",
    "sg:province":"CO",
    "sg:tags":[
        "cleaners"
    ],
    "wof:name":"Pressed 4 Time",
    "wof:placetype":"venue"
},
  "geometry": {"coordinates":[-104.767043,38.888713],"type":"Point"}
}