{
  "type": "Feature",
  "properties": {
    "iso:country":"US",
    "sg:address":"2755 Ore Mill Rd",
    "sg:city":"Colorado Springs",
    "sg:classifiers":[
        {
            "category":"Freight",
            "type":"Transportation"
        }
    ],
    "sg:phone":"+1 719 634 6332",
    "sg:postcode":"80904",
    "sg:province":"CO",
    "sg:tags":[
        "commercial",
        "storage",
        "general"
    ],
    "wof:name":"Old Mill Self Storage",
    "wof:placetype":"venue"
},
  "geometry": {"coordinates":[-104.870227,38.848237],"type":"Point"}
}