{
  "type": "Feature",
  "properties": {
    "addr:full":"59043 Ida Rd Olathe CO 81425",
    "addr:housenumber":"59043",
    "addr:postcode":"81425",
    "addr:street":"Ida Rd",
    "iso:country":"US",
    "sg:address":"59043 Ida Rd",
    "sg:city":"Olathe",
    "sg:classifiers":[
        {
            "category":"Manufacturing",
            "subcategory":"Wood Products",
            "type":"Manufacturing & Wholesale Goods"
        }
    ],
    "sg:phone":"+1 970 323 6516",
    "sg:postcode":"81425",
    "sg:province":"CO",
    "sg:tags":[
        "mfg",
        "preserving",
        "kitchen",
        "cabinet"
    ],
    "wof:name":"Architectural Interiors Inc",
    "wof:placetype":"venue"
},
  "geometry": {"coordinates":[-107.989386,38.547458],"type":"Point"}
}