{
  "type": "Feature",
  "properties": {
    "iso:country":"US",
    "sg:address":"910 Alta St",
    "sg:city":"Longmont",
    "sg:classifiers":[
        {
            "category":"Building & Trades",
            "subcategory":"Construction",
            "type":"Services"
        }
    ],
    "sg:phone":"+1 303 678 7507",
    "sg:postcode":"80501",
    "sg:province":"CO",
    "sg:tags":[
        "nonresidential"
    ],
    "wof:name":"Fine Line Trim",
    "wof:placetype":"venue"
},
  "geometry": {"coordinates":[-105.106093,40.175627],"type":"Point"}
}