{
  "type": "Feature",
  "properties": {
    "iso:country":"US",
    "sg:address":"9781 S Meridian Blvd",
    "sg:city":"Englewood",
    "sg:classifiers":[
        {
            "category":"Professional",
            "subcategory":"Computer Services",
            "type":"Services"
        }
    ],
    "sg:phone":"+1 303 302 1250",
    "sg:postcode":"80112",
    "sg:province":"CO",
    "sg:tags":[
        "agency",
        "employment",
        "programing",
        "custom"
    ],
    "wof:name":"Digitalreach Corporation",
    "wof:placetype":"venue"
},
  "geometry": {"coordinates":[-104.856606,39.548936],"type":"Point"}
}