{
  "type": "Feature",
  "properties": {
    "addr:full":"405 W Tomichi Ave Gunnison CO 81230",
    "addr:housenumber":"405",
    "addr:postcode":"81230",
    "addr:street":"W Tomichi Ave",
    "iso:country":"US",
    "sg:address":"405 W Tomichi Ave",
    "sg:city":"Gunnison",
    "sg:classifiers":[
        {
            "category":"Restaurant",
            "type":"Food & Drink"
        }
    ],
    "sg:phone":"+1 970 641 0667",
    "sg:postcode":"81230",
    "sg:province":"CO",
    "wof:name":"House Of China",
    "wof:placetype":"venue"
},
  "geometry": {"coordinates":[-106.93141,38.544324],"type":"Point"}
}