{
  "type": "Feature",
  "properties": {
    "addr:full":"340 Grand Ave Grand Junction CO 81501",
    "addr:housenumber":"340",
    "addr:postcode":"81501",
    "addr:street":"Grand Ave",
    "iso:country":"US",
    "sg:address":"340 Grand Ave",
    "sg:city":"Grand Junction",
    "sg:classifiers":[
        {
            "category":"Professional",
            "subcategory":"Lawyer & Legal Services",
            "type":"Services"
        }
    ],
    "sg:phone":"+1 970 243 3558",
    "sg:postcode":"81501",
    "sg:province":"CO",
    "sg:tags":[
        "attorney"
    ],
    "wof:name":"Vicki A Alsin Law Office",
    "wof:placetype":"venue"
},
  "geometry": {"coordinates":[-108.566771,39.070389],"type":"Point"}
}