{
  "type": "Feature",
  "properties": {
    "iso:country":"US",
    "sg:address":"3615 Fair Dawn Dr",
    "sg:city":"Colorado Springs",
    "sg:classifiers":[
        {
            "category":"Building & Trades",
            "subcategory":"Cleaning & Sanitation",
            "type":"Services"
        }
    ],
    "sg:phone":"+1 719 660 2375",
    "sg:postcode":"80920",
    "sg:province":"CO",
    "sg:tags":[
        "janitor"
    ],
    "wof:name":"Office Cleaning Solutions Inc",
    "wof:placetype":"venue"
},
  "geometry": {"coordinates":[-104.757577,38.943582],"type":"Point"}
}