{
  "type": "Feature",
  "properties": {
    "iso:country":"US",
    "sg:address":"6720 Indiana St",
    "sg:city":"Arvada",
    "sg:classifiers":[
        {
            "category":"Shopping",
            "subcategory":"Bicycles & Sporting Goods",
            "type":"Retail Goods"
        }
    ],
    "sg:phone":"+1 303 422 0627",
    "sg:postcode":"80007",
    "sg:province":"CO",
    "wof:name":"Hathaways",
    "wof:placetype":"venue"
},
  "geometry": {"coordinates":[-105.16515699999999,39.817312],"type":"Point"}
}