{
  "type": "Feature",
  "properties": {
    "addr:full":"7601 E Colfax Avenue Denver CO 80220",
    "addr:housenumber":"7601",
    "addr:postcode":"80220",
    "addr:street":"E Colfax Avenue",
    "iso:country":"US",
    "sg:address":"7601 E Colfax Avenue",
    "sg:city":"Denver",
    "sg:classifiers":[
        {
            "category":"Ice Cream",
            "type":"Food & Drink"
        }
    ],
    "sg:phone":"+1 303 388 5144",
    "sg:postcode":"80220",
    "sg:province":"CO",
    "sg:tags":[
        "frozen",
        "yogurt"
    ],
    "wof:name":"Dairy Queen",
    "wof:placetype":"venue"
},
  "geometry": {"coordinates":[-104.899531,39.740311],"type":"Point"}
}