{
  "type": "Feature",
  "properties": {
    "addr:full":"1817 Bear Creek Dr Steamboat Spgs CO 80487",
    "addr:housenumber":"1817",
    "addr:postcode":"80487",
    "addr:street":"Bear Creek Dr;Spgs",
    "iso:country":"US",
    "sg:address":"1817 Bear Creek Dr",
    "sg:city":"Steamboat Spgs",
    "sg:classifiers":[
        {
            "category":"Building & Trades",
            "subcategory":"Construction",
            "type":"Services"
        }
    ],
    "sg:phone":"+1 970 879 7344",
    "sg:postcode":"80487",
    "sg:province":"CO",
    "sg:tags":[
        "general",
        "contractor"
    ],
    "wof:name":"Colorado Professional Builders",
    "wof:placetype":"venue"
},
  "geometry": {"coordinates":[-106.804356,40.44492],"type":"Point"}
}