{
  "type": "Feature",
  "properties": {
    "iso:country":"US",
    "sg:address":"1842 Lincoln Ave",
    "sg:city":"Steamboat Spgs",
    "sg:classifiers":[
        {
            "category":"Home & Garden",
            "subcategory":"Garden Supply",
            "type":"Retail Goods"
        }
    ],
    "sg:phone":"+1 970 879 1422",
    "sg:postcode":"80487",
    "sg:province":"CO",
    "sg:tags":[
        "lawn",
        "mower"
    ],
    "wof:name":"Hilltop Rentals Sales & Svc",
    "wof:placetype":"venue"
},
  "geometry": {"coordinates":[-106.85416499999999,40.498496],"type":"Point"}
}