{
  "type": "Feature",
  "properties": {
    "addr:full":"13790 E Mississippi Ave Aurora CO 80012",
    "addr:housenumber":"13790",
    "addr:postcode":"80012",
    "addr:street":"E Mississippi Ave",
    "iso:country":"US",
    "sg:address":"13790 E Mississippi Ave",
    "sg:city":"Aurora",
    "sg:classifiers":[
        {
            "category":"Shopping",
            "subcategory":"Hobbies, Toys, & Games",
            "type":"Retail Goods"
        }
    ],
    "sg:phone":"+1 303 745 8697",
    "sg:postcode":"80012",
    "sg:province":"CO",
    "wof:name":"Toys R Us",
    "wof:placetype":"venue"
},
  "geometry": {"coordinates":[-104.827626,39.696544],"type":"Point"}
}