{
  "type": "Feature",
  "properties": {
    "addr:full":"804 Main St Canon City CO 81212",
    "addr:housenumber":"804",
    "addr:postcode":"81212",
    "addr:street":"Main St",
    "iso:country":"US",
    "sg:address":"804 Main St",
    "sg:city":"Canon City",
    "sg:classifiers":[
        {
            "category":"Real Estate",
            "subcategory":"Real Estate Services",
            "type":"Services"
        }
    ],
    "sg:phone":"+1 719 275 3304",
    "sg:postcode":"81212",
    "sg:province":"CO",
    "sg:tags":[
        "company",
        "title"
    ],
    "wof:name":"Security Title Guaranty Co",
    "wof:placetype":"venue"
},
  "geometry": {"coordinates":[-105.235542,38.442921],"type":"Point"}
}