{
  "type": "Feature",
  "properties": {
    "addr:full":"2620 Cody Dr Colorado Springs CO 80911",
    "addr:housenumber":"2620",
    "addr:postcode":"80911",
    "addr:street":"Cody Dr",
    "iso:country":"US",
    "sg:address":"2620 Cody Dr",
    "sg:city":"Colorado Springs",
    "sg:classifiers":[
        {
            "category":"Manufacturing",
            "subcategory":"Metals",
            "type":"Manufacturing & Wholesale Goods"
        }
    ],
    "sg:phone":"+1 719 391 0221",
    "sg:postcode":"80911",
    "sg:province":"CO",
    "sg:tags":[
        "equipment",
        "mfg",
        "vehicle"
    ],
    "wof:name":"UPC Inc",
    "wof:placetype":"venue"
},
  "geometry": {"coordinates":[-104.756947,38.769771],"type":"Point"}
}