{
  "type": "Feature",
  "properties": {
    "iso:country":"US",
    "sg:address":"441 Ln 1 N",
    "sg:city":"Alpine",
    "sg:classifiers":[
        {
            "category":"Travel",
            "subcategory":"Campground",
            "type":"Entertainment"
        }
    ],
    "sg:phone":"+1 201 768 1910",
    "sg:postcode":"81101",
    "sg:province":"CO",
    "sg:tags":[
        "camp"
    ],
    "wof:name":"Alpine Scout Camp",
    "wof:placetype":"venue"
},
  "geometry": {"coordinates":[-106.037729,37.58904],"type":"Point"}
}