{
  "type": "Feature",
  "properties": {
    "iso:country":"US",
    "sg:address":"3900 E Mexico Ave",
    "sg:city":"Denver",
    "sg:classifiers":[
        {
            "category":"Professional",
            "subcategory":"Lawyer & Legal Services",
            "type":"Services"
        }
    ],
    "sg:phone":"+1 303 691 3737",
    "sg:postcode":"80210",
    "sg:province":"CO",
    "wof:name":"Allan Mena",
    "wof:placetype":"venue"
},
  "geometry": {"coordinates":[-104.942001,39.685699],"type":"Point"}
}