{
  "type": "Feature",
  "properties": {
    "addr:full":"2925 E 26th Ave Denver CO 80205",
    "addr:housenumber":"2925",
    "addr:postcode":"80205",
    "addr:street":"E 26Th Ave",
    "iso:country":"US",
    "sg:address":"2925 E 26th Ave",
    "sg:city":"Denver",
    "sg:classifiers":[
        {
            "category":"Autos & Motor Vehicles",
            "subcategory":"Automobile Sales",
            "type":"Retail Goods"
        }
    ],
    "sg:phone":"+1 303 394 3600",
    "sg:postcode":"80205",
    "sg:province":"CO",
    "sg:tags":[
        "car",
        "dealer"
    ],
    "wof:name":"Cary's Cars",
    "wof:placetype":"venue"
},
  "geometry": {"coordinates":[-104.952714,39.754524],"type":"Point"}
}