{
  "type": "Feature",
  "properties": {
    "addr:full":"2484 S University Blvd Denver CO 80210",
    "addr:housenumber":"2484",
    "addr:postcode":"80210",
    "addr:street":"S University Blvd",
    "iso:country":"US",
    "sg:address":"2484 S University Blvd",
    "sg:city":"Denver",
    "sg:classifiers":[
        {
            "category":"Personal",
            "subcategory":"Beauty Salon",
            "type":"Services"
        }
    ],
    "sg:phone":"+1 303 733 6111",
    "sg:postcode":"80210",
    "sg:province":"CO",
    "wof:name":"Haute Tops",
    "wof:placetype":"venue"
},
  "geometry": {"coordinates":[-104.959311,39.672768],"type":"Point"}
}