{
  "type": "Feature",
  "properties": {
    "addr:full":"5845 Peerless Farms Rd Peyton CO 80831",
    "addr:housenumber":"5845",
    "addr:postcode":"80831",
    "addr:street":"Peerless Farms Rd",
    "iso:country":"US",
    "sg:address":"5845 Peerless Farms Rd",
    "sg:city":"Peyton",
    "sg:classifiers":[
        {
            "category":"Building & Trades",
            "subcategory":"Construction",
            "type":"Services"
        }
    ],
    "sg:phone":"+1 719 683 8245",
    "sg:postcode":"80831",
    "sg:province":"CO",
    "sg:tags":[
        "contractor"
    ],
    "wof:name":"Roof Craft Services Inc",
    "wof:placetype":"venue"
},
  "geometry": {"coordinates":[-104.507204,38.918267],"type":"Point"}
}