{
  "type": "Feature",
  "properties": {
    "addr:full":"14356 E Tennessee Ave Aurora CO 80012",
    "addr:housenumber":"14356",
    "addr:postcode":"80012",
    "addr:street":"E Tennessee Ave",
    "iso:country":"US",
    "sg:address":"14356 E Tennessee Ave",
    "sg:city":"Aurora",
    "sg:classifiers":[
        {
            "category":"Home & Garden",
            "subcategory":"Building Materials",
            "type":"Retail Goods"
        }
    ],
    "sg:phone":"+1 303 368 7378",
    "sg:postcode":"80012",
    "sg:province":"CO",
    "wof:name":"Soper Enterprises Inc",
    "wof:placetype":"venue"
},
  "geometry": {"coordinates":[-104.822721,39.699124],"type":"Point"}
}