{
  "type": "Feature",
  "properties": {
    "addr:full":"711 W 2nd St Walsenburg CO 81089",
    "addr:housenumber":"711",
    "addr:postcode":"81089",
    "addr:street":"W 2Nd St",
    "iso:country":"US",
    "sg:address":"711 W 2nd St",
    "sg:city":"Walsenburg",
    "sg:classifiers":[
        {
            "category":"Organizations",
            "subcategory":"Religious Organization",
            "type":"Services"
        }
    ],
    "sg:phone":"+1 719 738 1873",
    "sg:postcode":"81089",
    "sg:province":"CO",
    "sg:tags":[
        "church"
    ],
    "wof:name":"Emanuel Apostolic Temple",
    "wof:placetype":"venue"
},
  "geometry": {"coordinates":[-104.79227,37.624213],"type":"Point"}
}