{
  "type": "Feature",
  "properties": {
    "iso:country":"US",
    "sg:address":"1550 Larimer St",
    "sg:city":"Denver",
    "sg:classifiers":[
        {
            "category":"Building & Trades",
            "subcategory":"Construction",
            "type":"Services"
        }
    ],
    "sg:phone":"+1 303 586 1091",
    "sg:postcode":"80202",
    "sg:province":"CO",
    "sg:tags":[
        "painter"
    ],
    "sg:website":"www.painterindenver.info",
    "wof:name":"AAA Affordable Painting Contractors & Snow",
    "wof:placetype":"venue"
},
  "geometry": {"coordinates":[-104.997657,39.748994],"type":"Point"}
}