{
  "type": "Feature",
  "properties": {
    "iso:country":"US",
    "sg:address":"7543 N Academy Blvd",
    "sg:city":"Colorado Springs",
    "sg:classifiers":[
        {
            "category":"Personal",
            "subcategory":"Beauty Salon",
            "type":"Services"
        }
    ],
    "sg:phone":"+1 719 528 8288",
    "sg:postcode":"80920",
    "sg:province":"CO",
    "sg:tags":[
        "shop",
        "barber"
    ],
    "wof:name":"Salon Oasis",
    "wof:placetype":"venue"
},
  "geometry": {"coordinates":[-104.79908399999999,38.940169],"type":"Point"}
}