{
  "type": "Feature",
  "properties": {
    "addr:full":"200 Park Ave Kremmling CO 80459",
    "addr:housenumber":"200",
    "addr:postcode":"80459",
    "addr:street":"Park Ave",
    "iso:country":"US",
    "sg:address":"200 Park Ave",
    "sg:city":"Kremmling",
    "sg:classifiers":[
        {
            "category":"Food & Beverages",
            "subcategory":"Liquor & Beverages",
            "type":"Retail Goods"
        }
    ],
    "sg:phone":"+1 970 724 3564",
    "sg:postcode":"80459",
    "sg:province":"CO",
    "wof:name":"Kremmling Package Liquors",
    "wof:placetype":"venue"
},
  "geometry": {"coordinates":[-106.393541,40.058948],"type":"Point"}
}