{
  "type": "Feature",
  "properties": {
    "iso:country":"US",
    "sg:address":"1901 Constitution Rd",
    "sg:city":"Pueblo",
    "sg:classifiers":[
        {
            "category":"Professional",
            "subcategory":"Accounting & Tax Preparation",
            "type":"Services"
        }
    ],
    "sg:phone":"+1 719 546 0831",
    "sg:postcode":"81001",
    "sg:province":"CO",
    "sg:tags":[
        "return",
        "filing"
    ],
    "wof:name":"Belmont Tax Svc",
    "wof:placetype":"venue"
},
  "geometry": {"coordinates":[-104.57153599999999,38.288205],"type":"Point"}
}