{
  "type": "Feature",
  "properties": {
    "addr:full":"10071 Lewis Ct Broomfield CO 80021",
    "addr:housenumber":"10071",
    "addr:postcode":"80021",
    "addr:street":"Lewis Ct",
    "iso:country":"US",
    "sg:address":"10071 Lewis Ct",
    "sg:city":"Broomfield",
    "sg:classifiers":[
        {
            "category":"Retail",
            "subcategory":"Repair Shop",
            "type":"Services"
        }
    ],
    "sg:phone":"+1 303 474 0873",
    "sg:postcode":"80021",
    "sg:province":"CO",
    "sg:tags":[
        "spa",
        "hot",
        "tub"
    ],
    "wof:name":"Elite Spa & Pool Svc",
    "wof:placetype":"venue"
},
  "geometry": {"coordinates":[-105.113946,39.879196],"type":"Point"}
}