{
  "type": "Feature",
  "properties": {
    "iso:country":"US",
    "sg:address":"4211 E 100th Ave",
    "sg:city":"Denver",
    "sg:classifiers":[
        {
            "category":"Building & Trades",
            "subcategory":"Construction",
            "type":"Services"
        }
    ],
    "sg:phone":"+1 720 872 2311",
    "sg:postcode":"80229",
    "sg:province":"CO",
    "sg:tags":[
        "contractor"
    ],
    "wof:name":"German Vega Construction",
    "wof:placetype":"venue"
},
  "geometry": {"coordinates":[-104.940161,39.877379],"type":"Point"}
}