{
  "type": "Feature",
  "properties": {
    "iso:country":"US",
    "sg:address":"400 Corporate Cir",
    "sg:city":"Golden",
    "sg:classifiers":[
        {
            "category":"Communications",
            "subcategory":"Film & Video Production",
            "type":"Services"
        }
    ],
    "sg:phone":"+1 303 940 0083",
    "sg:postcode":"80401",
    "sg:province":"CO",
    "sg:tags":[
        "duplication",
        "tape"
    ],
    "wof:name":"MCE Digital Media Inc",
    "wof:placetype":"venue"
},
  "geometry": {"coordinates":[-105.192988,39.720872],"type":"Point"}
}