{
  "type": "Feature",
  "properties": {
    "addr:full":"620 Teller St Salida CO 81201",
    "addr:housenumber":"620",
    "addr:postcode":"81201",
    "addr:street":"Teller St",
    "iso:country":"US",
    "sg:address":"620 Teller St",
    "sg:city":"Salida",
    "sg:classifiers":[
        {
            "category":"Manufacturing",
            "subcategory":"Building Materials",
            "type":"Manufacturing & Wholesale Goods"
        }
    ],
    "sg:phone":"+1 719 530 0200",
    "sg:postcode":"81201",
    "sg:province":"CO",
    "sg:tags":[
        "wooden",
        "truss",
        "roof",
        "mfg"
    ],
    "wof:name":"D & W Building Specialties",
    "wof:placetype":"venue"
},
  "geometry": {"coordinates":[-105.992454,38.525739],"type":"Point"}
}