{
  "type": "Feature",
  "properties": {
    "addr:full":"119 N 6th St Grand Junction CO 81501",
    "addr:housenumber":"119",
    "addr:postcode":"81501",
    "addr:street":"N 6Th St",
    "iso:country":"US",
    "sg:address":"119 N 6th St",
    "sg:city":"Grand Junction",
    "sg:classifiers":[
        {
            "category":"Personal",
            "subcategory":"Beauty Salon",
            "type":"Services"
        }
    ],
    "sg:phone":"+1 970 244 8454",
    "sg:postcode":"81501",
    "sg:province":"CO",
    "wof:name":"Your Hair",
    "wof:placetype":"venue"
},
  "geometry": {"coordinates":[-108.56281300000001,39.068131],"type":"Point"}
}