{
  "type": "Feature",
  "properties": {
    "iso:country":"US",
    "sg:address":"2935 Baseline Rd",
    "sg:city":"Boulder",
    "sg:classifiers":[
        {
            "category":"Communications",
            "subcategory":"Television Station",
            "type":"Services"
        }
    ],
    "sg:phone":"+1 303 442 4244",
    "sg:postcode":"80303",
    "sg:province":"CO",
    "sg:tags":[
        "broadcasting",
        "co"
    ],
    "wof:name":"News 4 Boulder Valley Bureau",
    "wof:placetype":"venue"
},
  "geometry": {"coordinates":[-105.255551,40.000215],"type":"Point"}
}