{
  "type": "Feature",
  "properties": {
    "iso:country":"US",
    "sg:address":"6900 E 47th Avenue Dr",
    "sg:city":"Denver",
    "sg:classifiers":[
        {
            "category":"Manufacturing",
            "subcategory":"Printing",
            "type":"Manufacturing & Wholesale Goods"
        }
    ],
    "sg:phone":"+1 303 355 2966",
    "sg:postcode":"80216",
    "sg:province":"CO",
    "sg:tags":[
        "screen"
    ],
    "wof:name":"Image West",
    "wof:placetype":"venue"
},
  "geometry": {"coordinates":[-104.911384,39.783344],"type":"Point"}
}