{
  "type": "Feature",
  "properties": {
    "addr:full":"3220 W 134th Ave Broomfield CO 80020",
    "addr:housenumber":"3220",
    "addr:postcode":"80020",
    "addr:street":"W 134Th Ave",
    "iso:country":"US",
    "sg:address":"3220 W 134th Ave",
    "sg:city":"Broomfield",
    "sg:classifiers":[
        {
            "category":"Building & Trades",
            "subcategory":"Construction",
            "type":"Services"
        }
    ],
    "sg:phone":"+1 303 469 4142",
    "sg:postcode":"80020",
    "sg:province":"CO",
    "sg:tags":[
        "tile",
        "ceramic",
        "marble",
        "contractor"
    ],
    "wof:name":"Ceramic Tile Instllation Maint",
    "wof:placetype":"venue"
},
  "geometry": {"coordinates":[-105.02695799999999,39.939958],"type":"Point"}
}