{
  "type": "Feature",
  "properties": {
    "addr:full":"2830 Table Mesa Dr Boulder CO 80305",
    "addr:housenumber":"2830",
    "addr:postcode":"80305",
    "addr:street":"Table Mesa Dr",
    "iso:country":"US",
    "sg:address":"2830 Table Mesa Dr",
    "sg:city":"Boulder",
    "sg:classifiers":[
        {
            "category":"Professional",
            "subcategory":"Art Services",
            "type":"Services"
        }
    ],
    "sg:phone":"+1 303 499 2004",
    "sg:postcode":"80305",
    "sg:province":"CO",
    "sg:tags":[
        "graphic",
        "designer"
    ],
    "sg:website":"www.rwtdesign.com",
    "wof:name":"Robert W Taylor Design Inc",
    "wof:placetype":"venue"
},
  "geometry": {"coordinates":[-105.25790600000001,39.980372],"type":"Point"}
}