{
  "type": "Feature",
  "properties": {
    "addr:full":"3605 W Colfax Avenue Denver CO 80204",
    "addr:housenumber":"3605",
    "addr:postcode":"80204",
    "addr:street":"W Colfax Avenue",
    "iso:country":"US",
    "sg:address":"3605 W Colfax Avenue",
    "sg:city":"Denver",
    "sg:classifiers":[
        {
            "category":"Health Services",
            "subcategory":"Doctor",
            "type":"Services"
        }
    ],
    "sg:phone":"+1 303 592 7716",
    "sg:postcode":"80204",
    "sg:province":"CO",
    "sg:tags":[
        "dermatologist"
    ],
    "wof:name":"Metro Denver Services",
    "wof:placetype":"venue"
},
  "geometry": {"coordinates":[-105.034971,39.740204],"type":"Point"}
}