{
  "type": "Feature",
  "properties": {
    "iso:country":"US",
    "sg:address":"6016 Wadsworth Blvd",
    "sg:city":"Arvada",
    "sg:classifiers":[
        {
            "category":"Real Estate",
            "subcategory":"Real Estate Operator",
            "type":"Services"
        }
    ],
    "sg:phone":"+1 303 422 7211",
    "sg:postcode":"80003",
    "sg:province":"CO",
    "sg:tags":[
        "building",
        "apartment"
    ],
    "wof:name":"Elmwood Apts",
    "wof:placetype":"venue"
},
  "geometry": {"coordinates":[-105.077308,39.805401],"type":"Point"}
}