{
  "type": "Feature",
  "properties": {
    "addr:full":"8774 Yates Dr Westminster CO 80031",
    "addr:housenumber":"8774",
    "addr:postcode":"80031",
    "addr:street":"Yates Dr",
    "iso:country":"US",
    "sg:address":"8774 Yates Dr",
    "sg:city":"Westminster",
    "sg:classifiers":[
        {
            "category":"Professional",
            "subcategory":"Employment Agencies",
            "type":"Services"
        }
    ],
    "sg:phone":"+1 720 542 0500",
    "sg:postcode":"80031",
    "sg:province":"CO",
    "sg:tags":[
        "consultant",
        "search",
        "executive"
    ],
    "wof:name":"SCW Consulting Inc",
    "wof:placetype":"venue"
},
  "geometry": {"coordinates":[-105.050161,39.855],"type":"Point"}
}