{
  "type": "Feature",
  "properties": {
    "iso:country":"US",
    "sg:address":"2206 Downhill Dr",
    "sg:city":"Steamboat Spgs",
    "sg:classifiers":[
        {
            "category":"Building & Trades",
            "subcategory":"Construction",
            "type":"Services"
        }
    ],
    "sg:phone":"+1 970 879 7861",
    "sg:postcode":"80487",
    "sg:province":"CO",
    "sg:tags":[
        "boring",
        "drilling",
        "contractor"
    ],
    "sg:website":"www.mjmillerinc.com",
    "wof:name":"M J Miller Inc",
    "wof:placetype":"venue"
},
  "geometry": {"coordinates":[-106.863563,40.503488],"type":"Point"}
}