{
  "type": "Feature",
  "properties": {
    "iso:country":"US",
    "sg:address":"1105 26th Ave",
    "sg:city":"Greeley",
    "sg:classifiers":[
        {
            "category":"Restaurant",
            "type":"Food & Drink"
        }
    ],
    "sg:phone":"+1 970 356 3222",
    "sg:postcode":"80634",
    "sg:province":"CO",
    "sg:tags":[
        "eating"
    ],
    "wof:name":"Kites Cafevietnamese Cuisine",
    "wof:placetype":"venue"
},
  "geometry": {"coordinates":[-104.722356,40.422885],"type":"Point"}
}