{
  "type": "Feature",
  "properties": {
    "addr:full":"231 53rd Ave Ct Greeley CO 80634",
    "addr:housenumber":"231",
    "addr:postcode":"80634",
    "addr:street":"53Rd Ave Ct",
    "iso:country":"US",
    "sg:address":"231 53rd Ave Ct",
    "sg:city":"Greeley",
    "sg:classifiers":[
        {
            "category":"Building & Trades",
            "subcategory":"Construction",
            "type":"Services"
        }
    ],
    "sg:phone":"+1 970 351 0256",
    "sg:postcode":"80634",
    "sg:province":"CO",
    "sg:tags":[
        "stucco",
        "contractor"
    ],
    "wof:name":"Diamond Stucco Inc",
    "wof:placetype":"venue"
},
  "geometry": {"coordinates":[-104.767847,40.432264],"type":"Point"}
}