{
  "type": "Feature",
  "properties": {
    "iso:country":"US",
    "sg:address":"1501 Main St",
    "sg:city":"Springfield",
    "sg:classifiers":[
        {
            "category":"Building & Trades",
            "subcategory":"Electrical",
            "type":"Services"
        }
    ],
    "sg:phone":"+1 719 523 4848",
    "sg:postcode":"81073",
    "sg:province":"CO",
    "sg:tags":[
        "electric",
        "contractor"
    ],
    "wof:name":"Holcomb Appliance & Electric",
    "wof:placetype":"venue"
},
  "geometry": {"coordinates":[-102.616518,37.398509],"type":"Point"}
}