{
  "type": "Feature",
  "properties": {
    "iso:country":"US",
    "sg:address":"1587 S Colorado Boulevard",
    "sg:city":"Denver",
    "sg:classifiers":[
        {
            "category":"Personal",
            "subcategory":"Nail Salon",
            "type":"Services"
        }
    ],
    "sg:phone":"+1 303 758 2464",
    "sg:postcode":"80222",
    "sg:province":"CO",
    "wof:name":"Nails Blvd",
    "wof:placetype":"venue"
},
  "geometry": {"coordinates":[-104.94058699999999,39.687822],"type":"Point"}
}