{
  "type": "Feature",
  "properties": {
    "iso:country":"US",
    "sg:address":"3235 E Platte Ave",
    "sg:city":"Colorado Springs",
    "sg:classifiers":[
        {
            "category":"Shopping",
            "subcategory":"Hobbies, Toys, & Games",
            "type":"Retail Goods"
        }
    ],
    "sg:phone":"+1 719 632 2390",
    "sg:postcode":"80909",
    "sg:province":"CO",
    "sg:tags":[
        "supply"
    ],
    "wof:name":"EB Games",
    "wof:placetype":"venue"
},
  "geometry": {"coordinates":[-104.76924200000001,38.839565],"type":"Point"}
}