{
  "type": "Feature",
  "properties": {
    "iso:country":"US",
    "sg:address":"561 Zerex St",
    "sg:city":"Fraser",
    "sg:classifiers":[
        {
            "category":"Building & Trades",
            "subcategory":"Electrical",
            "type":"Services"
        }
    ],
    "sg:phone":"+1 970 726 9526",
    "sg:postcode":"80442",
    "sg:province":"CO",
    "sg:tags":[
        "home",
        "system",
        "automation"
    ],
    "wof:name":"Mountain Man Entertainment",
    "wof:placetype":"venue"
},
  "geometry": {"coordinates":[-105.81753,39.949643],"type":"Point"}
}