{
  "type": "Feature",
  "properties": {
    "iso:country":"US",
    "sg:address":"725 E Main St",
    "sg:city":"Aspen",
    "sg:classifiers":[
        {
            "category":"Professional",
            "type":"Services"
        }
    ],
    "sg:phone":"+1 970 925 1342",
    "sg:postcode":"81611",
    "sg:province":"CO",
    "wof:name":"Virginia P Waitley",
    "wof:placetype":"venue"
},
  "geometry": {"coordinates":[-106.815389,39.189799],"type":"Point"}
}