{
  "type": "Feature",
  "properties": {
    "iso:country":"US",
    "sg:address":"6042 Alkire Ct",
    "sg:city":"Arvada",
    "sg:classifiers":[
        {
            "category":"Professional",
            "type":"Services"
        }
    ],
    "sg:phone":"+1 303 424 7569",
    "sg:postcode":"80004",
    "sg:province":"CO",
    "wof:name":"Pretty Interesting Music",
    "wof:placetype":"venue"
},
  "geometry": {"coordinates":[-105.146784,39.80644],"type":"Point"}
}