{
  "type": "Feature",
  "properties": {
    "iso:country":"US",
    "sg:address":"701 Sandy Knoll Cir",
    "sg:city":"Kersey",
    "sg:classifiers":[
        {
            "category":"Real Estate",
            "subcategory":"Real Estate Operator",
            "type":"Services"
        }
    ],
    "sg:phone":"+1 970 356 1697",
    "sg:postcode":"80644",
    "sg:province":"CO",
    "sg:tags":[
        "apartment"
    ],
    "wof:name":"Kersey Apartments",
    "wof:placetype":"venue"
},
  "geometry": {"coordinates":[-104.565225,40.383919],"type":"Point"}
}