{
  "type": "Feature",
  "properties": {
    "iso:country":"US",
    "sg:address":"902 Wadsworth Blvd",
    "sg:city":"Lakewood",
    "sg:classifiers":[
        {
            "category":"Shopping",
            "subcategory":"Clothing, Apparel, & Fashions",
            "type":"Retail Goods"
        }
    ],
    "sg:phone":"+1 303 239 9770",
    "sg:postcode":"80214",
    "sg:province":"CO",
    "sg:tags":[
        "alteration"
    ],
    "wof:name":"Pat's Alterations",
    "wof:placetype":"venue"
},
  "geometry": {"coordinates":[-105.081367,39.732964],"type":"Point"}
}