{
  "type": "Feature",
  "properties": {
    "iso:country":"US",
    "sg:address":"237 22nd St",
    "sg:city":"Greeley",
    "sg:classifiers":[
        {
            "category":"Professional",
            "subcategory":"Computer Services",
            "type":"Services"
        }
    ],
    "sg:phone":"+1 970 352 6800",
    "sg:postcode":"80631",
    "sg:province":"CO",
    "sg:tags":[
        "prepackaged",
        "s",
        "fulfillment",
        "software"
    ],
    "wof:name":"Startek Usa Inc",
    "wof:placetype":"venue"
},
  "geometry": {"coordinates":[-104.681826,40.402492],"type":"Point"}
}