{
  "type": "Feature",
  "properties": {
    "addr:full":"336 Main St Grand Junction CO 81501",
    "addr:housenumber":"336",
    "addr:postcode":"81501",
    "addr:street":"Main St",
    "iso:country":"US",
    "sg:address":"336 Main St",
    "sg:city":"Grand Junction",
    "sg:classifiers":[
        {
            "category":"Real Estate",
            "subcategory":"Real Estate Agent",
            "type":"Services"
        }
    ],
    "sg:phone":"+1 970 244 9074",
    "sg:postcode":"81501",
    "sg:province":"CO",
    "sg:tags":[
        "investment"
    ],
    "wof:name":"Bill Wagner & Assoc-Metro",
    "wof:placetype":"venue"
},
  "geometry": {"coordinates":[-108.56673000000001,39.067453],"type":"Point"}
}