{
  "type": "Feature",
  "properties": {
    "iso:country":"US",
    "sg:address":"514 E Colfax Avenue",
    "sg:city":"Denver",
    "sg:classifiers":[
        {
            "category":"Restaurant",
            "type":"Food & Drink"
        }
    ],
    "sg:phone":"+1 303 832 7854",
    "sg:postcode":"80203",
    "sg:province":"CO",
    "sg:tags":[
        "traditional",
        "american"
    ],
    "wof:name":"Pete's Steak House",
    "wof:placetype":"venue"
},
  "geometry": {"coordinates":[-104.980416,39.739939],"type":"Point"}
}