{
  "type": "Feature",
  "properties": {
    "iso:country":"US",
    "sg:address":"1843 S Townsend Ave",
    "sg:city":"Montrose",
    "sg:classifiers":[
        {
            "category":"Social Services",
            "type":"Services"
        }
    ],
    "sg:phone":"+1 970 252 7445",
    "sg:postcode":"81401",
    "sg:province":"CO",
    "sg:tags":[
        "support",
        "collection",
        "child"
    ],
    "wof:name":"Tandem Families",
    "wof:placetype":"venue"
},
  "geometry": {"coordinates":[-107.86622800000001,38.466746],"type":"Point"}
}