{
  "type": "Feature",
  "properties": {
    "iso:country":"US",
    "sg:address":"1460 S Colorado Boulevard",
    "sg:city":"Denver",
    "sg:classifiers":[
        {
            "category":"Arts & Performance",
            "subcategory":"Art Gallery",
            "type":"Entertainment"
        }
    ],
    "sg:phone":"+1 303 757 4647",
    "sg:postcode":"80222",
    "sg:province":"CO",
    "wof:name":"Square Deal Framing",
    "wof:placetype":"venue"
},
  "geometry": {"coordinates":[-104.940658,39.690078],"type":"Point"}
}