{
  "type": "Feature",
  "properties": {
    "iso:country":"US",
    "sg:address":"5433 W 88th Ave",
    "sg:city":"Westminster",
    "sg:classifiers":[
        {
            "category":"Shopping",
            "subcategory":"Jewelry",
            "type":"Retail Goods"
        }
    ],
    "sg:phone":"+1 303 429 8575",
    "sg:postcode":"80031",
    "sg:province":"CO",
    "sg:tags":[
        "jeweler"
    ],
    "wof:name":"Jewelfire Diamonds",
    "wof:placetype":"venue"
},
  "geometry": {"coordinates":[-105.061716,39.856563],"type":"Point"}
}