{
  "type": "Feature",
  "properties": {
    "addr:full":"43918 Bowie Rd Paonia CO 81428",
    "addr:housenumber":"43918",
    "addr:postcode":"81428",
    "addr:street":"Bowie Rd",
    "iso:country":"US",
    "sg:address":"43918 Bowie Rd",
    "sg:city":"Paonia",
    "sg:classifiers":[
        {
            "category":"Mining & Drilling",
            "type":"Manufacturing & Wholesale Goods"
        }
    ],
    "sg:phone":"+1 970 527 4135",
    "sg:postcode":"81428",
    "sg:province":"CO",
    "sg:tags":[
        "company"
    ],
    "wof:name":"Bowie Resource LTD",
    "wof:placetype":"venue"
},
  "geometry": {"coordinates":[-107.528248,38.924925],"type":"Point"}
}