{
  "type": "Feature",
  "properties": {
    "iso:country":"US",
    "sg:address":"6465 Greenwood Plaza Blvd",
    "sg:city":"Englewood",
    "sg:classifiers":[
        {
            "category":"Real Estate",
            "subcategory":"Real Estate Agent",
            "type":"Services"
        }
    ],
    "sg:phone":"+1 720 482 3164",
    "sg:postcode":"80111",
    "sg:province":"CO",
    "sg:tags":[
        "management"
    ],
    "wof:name":"Crescent Real Estate",
    "wof:placetype":"venue"
},
  "geometry": {"coordinates":[-104.89478800000001,39.599049],"type":"Point"}
}