{
  "type": "Feature",
  "properties": {
    "iso:country":"US",
    "sg:address":"2970 S Fox Street",
    "sg:city":"Englewood",
    "sg:classifiers":[
        {
            "category":"Building & Trades",
            "subcategory":"Construction",
            "type":"Services"
        }
    ],
    "sg:phone":"+1 303 788 1500",
    "sg:postcode":"80110",
    "sg:province":"CO",
    "sg:tags":[
        "contractor"
    ],
    "wof:name":"Danielson W O",
    "wof:placetype":"venue"
},
  "geometry": {"coordinates":[-104.994791,39.662834],"type":"Point"}
}