{
  "type": "Feature",
  "properties": {
    "iso:country":"US",
    "sg:address":"1232 Yates St",
    "sg:city":"Denver",
    "sg:classifiers":[
        {
            "category":"Home & Garden",
            "subcategory":"Carpets & Floor Coverings",
            "type":"Retail Goods"
        }
    ],
    "sg:phone":"+1 303 893 1771",
    "sg:postcode":"80204",
    "sg:province":"CO",
    "wof:name":"J M Carpet Service",
    "wof:placetype":"venue"
},
  "geometry": {"coordinates":[-105.05088600000001,39.735581],"type":"Point"}
}