{
  "type": "Feature",
  "properties": {
    "iso:country":"US",
    "sg:address":"2366 Glenhaven Dr",
    "sg:city":"Highlands Ranch",
    "sg:classifiers":[
        {
            "category":"Professional",
            "subcategory":"Art Services",
            "type":"Services"
        }
    ],
    "sg:phone":"+1 303 346 1173",
    "sg:postcode":"80126",
    "sg:province":"CO",
    "sg:tags":[
        "graphic",
        "designer"
    ],
    "wof:name":"Graphic Advantage LTD",
    "wof:placetype":"venue"
},
  "geometry": {"coordinates":[-104.965231,39.558694],"type":"Point"}
}