{
  "type": "Feature",
  "properties": {
    "iso:country":"US",
    "sg:address":"3102 E Rd",
    "sg:city":"Grand Junction",
    "sg:classifiers":[
        {
            "category":"Communications",
            "subcategory":"Radio Station",
            "type":"Services"
        }
    ],
    "sg:phone":"+1 970 434 8391",
    "sg:postcode":"81504",
    "sg:province":"CO",
    "sg:tags":[
        "broadcast"
    ],
    "wof:name":"Kcicfm Stereo",
    "wof:placetype":"venue"
},
  "geometry": {"coordinates":[-108.474138,39.077246],"type":"Point"}
}