{
  "type": "Feature",
  "properties": {
    "addr:full":"346 Brittany Dr Florissant CO 80814",
    "addr:housenumber":"346",
    "addr:postcode":"80814",
    "addr:street":"Brittany Dr",
    "iso:country":"US",
    "sg:address":"346 Brittany Dr",
    "sg:city":"Florissant",
    "sg:classifiers":[
        {
            "category":"Shopping",
            "subcategory":"Hobbies, Toys, & Games",
            "type":"Retail Goods"
        }
    ],
    "sg:phone":"+1 719 748 5110",
    "sg:postcode":"80814",
    "sg:province":"CO",
    "sg:tags":[
        "craft"
    ],
    "wof:name":"Prairie Craft Co",
    "wof:placetype":"venue"
},
  "geometry": {"coordinates":[-105.26015099999999,38.94385],"type":"Point"}
}