{
  "type": "Feature",
  "properties": {
    "addr:full":"420 W 4th St Pueblo CO 81003",
    "addr:housenumber":"420",
    "addr:postcode":"81003",
    "addr:street":"W 4Th St",
    "iso:country":"US",
    "sg:address":"420 W 4th St",
    "sg:city":"Pueblo",
    "sg:classifiers":[
        {
            "category":"Shopping",
            "subcategory":"Music",
            "type":"Retail Goods"
        }
    ],
    "sg:phone":"+1 719 543 9501",
    "sg:postcode":"81003",
    "sg:province":"CO",
    "sg:tags":[
        "compact",
        "record",
        "disc",
        "tape"
    ],
    "wof:name":"Independent Records and Video",
    "wof:placetype":"venue"
},
  "geometry": {"coordinates":[-104.612847,38.270531],"type":"Point"}
}