{
  "type": "Feature",
  "properties": {
    "addr:full":"3200 Zenobia St Denver CO 80212",
    "addr:housenumber":"3200",
    "addr:postcode":"80212",
    "addr:street":"Zenobia St",
    "iso:country":"US",
    "sg:address":"3200 Zenobia St",
    "sg:city":"Denver",
    "sg:classifiers":[
        {
            "category":"Organizations",
            "subcategory":"Religious Organization",
            "type":"Services"
        }
    ],
    "sg:phone":"+1 303 477 6881",
    "sg:postcode":"80212",
    "sg:province":"CO",
    "sg:tags":[
        "church"
    ],
    "wof:name":"Faith United Methodist Church",
    "wof:placetype":"venue"
},
  "geometry": {"coordinates":[-105.05260699999999,39.76299],"type":"Point"}
}