{
  "type": "Feature",
  "properties": {
    "iso:country":"US",
    "sg:address":"130 W 11th Ave",
    "sg:city":"Denver",
    "sg:classifiers":[
        {
            "category":"Building & Trades",
            "subcategory":"Construction",
            "type":"Services"
        }
    ],
    "sg:phone":"+1 303 628 5490",
    "sg:postcode":"80204",
    "sg:province":"CO",
    "sg:tags":[
        "interior",
        "design"
    ],
    "wof:name":"Facilities Collaborative LLC",
    "wof:placetype":"venue"
},
  "geometry": {"coordinates":[-104.989853,39.733782],"type":"Point"}
}