{
  "type": "Feature",
  "properties": {
    "addr:full":"7400 E Arapahoe Rd Centennial CO 80112",
    "addr:housenumber":"7400",
    "addr:postcode":"80112",
    "addr:street":"E Arapahoe Rd",
    "iso:country":"US",
    "sg:address":"7400 E Arapahoe Rd",
    "sg:city":"Centennial",
    "sg:classifiers":[
        {
            "category":"Banks & Credit Unions",
            "subcategory":"Bank",
            "type":"Services"
        }
    ],
    "sg:phone":"+1 303 770 7400",
    "sg:postcode":"80112",
    "sg:province":"CO",
    "sg:tags":[
        "mortgage",
        "loan",
        "broker",
        "real estate"
    ],
    "wof:name":"Centennial State Mortgage Co",
    "wof:placetype":"venue"
},
  "geometry": {"coordinates":[-104.898883,39.594954],"type":"Point"}
}