{
  "type": "Feature",
  "properties": {
    "iso:country":"US",
    "sg:address":"1142 Pearl St",
    "sg:city":"Boulder",
    "sg:classifiers":[
        {
            "category":"Shopping",
            "subcategory":"Clothing, Apparel, & Fashions",
            "type":"Retail Goods"
        }
    ],
    "sg:phone":"+1 303 442 8250",
    "sg:postcode":"80302",
    "sg:province":"CO",
    "wof:name":"Banana Republic",
    "wof:placetype":"venue"
},
  "geometry": {"coordinates":[-105.284614,40.016817],"type":"Point"}
}