{
  "type": "Feature",
  "properties": {
    "iso:country":"US",
    "sg:address":"832 Roadrunner Ct",
    "sg:city":"Loveland",
    "sg:classifiers":[
        {
            "category":"Banks & Credit Unions",
            "subcategory":"Financial Services",
            "type":"Services"
        }
    ],
    "sg:phone":"+1 970 635 1898",
    "sg:postcode":"80537",
    "sg:province":"CO",
    "sg:tags":[
        "company",
        "holding"
    ],
    "wof:name":"Annapaul Property Holding LLC",
    "wof:placetype":"venue"
},
  "geometry": {"coordinates":[-105.013195,40.384165],"type":"Point"}
}