{
  "type": "Feature",
  "properties": {
    "iso:country":"US",
    "sg:address":"2500 Pearl St",
    "sg:city":"Boulder",
    "sg:classifiers":[
        {
            "category":"Shopping",
            "subcategory":"Photographic Equipment",
            "type":"Retail Goods"
        }
    ],
    "sg:phone":"+1 303 443 1715",
    "sg:postcode":"80302",
    "sg:province":"CO",
    "sg:tags":[
        "digital",
        "commercial",
        "sales",
        "supply"
    ],
    "sg:website":"www.mikescamera.com",
    "wof:name":"Mike's Camera",
    "wof:placetype":"venue"
},
  "geometry": {"coordinates":[-105.260893,40.021799],"type":"Point"}
}