{
  "type": "Feature",
  "properties": {
    "iso:country":"US",
    "sg:address":"18800 E Clarke Rd",
    "sg:city":"Parker",
    "sg:classifiers":[
        {
            "category":"Wholesale",
            "subcategory":"Machinery & Supplies",
            "type":"Manufacturing & Wholesale Goods"
        }
    ],
    "sg:phone":"+1 303 805 7731",
    "sg:postcode":"80134",
    "sg:province":"CO",
    "sg:tags":[
        "fastening",
        "equipment",
        "industrial"
    ],
    "sg:website":"www.empirestaple.com",
    "wof:name":"Empire Staple Co",
    "wof:placetype":"venue"
},
  "geometry": {"coordinates":[-104.769544,39.523368],"type":"Point"}
}