{
  "type": "Feature",
  "properties": {
    "iso:country":"US",
    "sg:address":"705 Steamboat Blvd",
    "sg:city":"Steamboat Spgs",
    "sg:classifiers":[
        {
            "category":"Shopping",
            "subcategory":"Bicycles & Sporting Goods",
            "type":"Retail Goods"
        }
    ],
    "sg:phone":"+1 970 871 6739",
    "sg:postcode":"80487",
    "sg:province":"CO",
    "wof:name":"Gart Sports",
    "wof:placetype":"venue"
},
  "geometry": {"coordinates":[-106.798659,40.474826],"type":"Point"}
}