{
  "type": "Feature",
  "properties": {
    "addr:full":"3111 28th St Boulder CO 80301",
    "addr:housenumber":"3111",
    "addr:postcode":"80301",
    "addr:street":"28Th St",
    "iso:country":"US",
    "sg:address":"3111 28th St",
    "sg:city":"Boulder",
    "sg:classifiers":[
        {
            "category":"Home & Garden",
            "subcategory":"Furniture",
            "type":"Retail Goods"
        }
    ],
    "sg:phone":"+1 303 449 0214",
    "sg:postcode":"80301",
    "sg:province":"CO",
    "wof:name":"Danish Furniture Of Colorado",
    "wof:placetype":"venue"
},
  "geometry": {"coordinates":[-105.25849700000001,40.030755],"type":"Point"}
}