{
  "type": "Feature",
  "properties": {
    "addr:full":"91 E Dartmouth Ave Englewood CO 80113",
    "addr:housenumber":"91",
    "addr:postcode":"80113",
    "addr:street":"E Dartmouth Ave",
    "iso:country":"US",
    "sg:address":"91 E Dartmouth Ave",
    "sg:city":"Englewood",
    "sg:classifiers":[
        {
            "category":"Real Estate",
            "subcategory":"Developer",
            "type":"Services"
        }
    ],
    "sg:phone":"+1 303 773 1551",
    "sg:postcode":"80113",
    "sg:province":"CO",
    "wof:name":"Mc Dermott Properties LLC",
    "wof:placetype":"venue"
},
  "geometry": {"coordinates":[-104.98724799999999,39.660548],"type":"Point"}
}