{
  "type": "Feature",
  "properties": {
    "iso:country":"US",
    "sg:address":"1113 Spruce St",
    "sg:city":"Boulder",
    "sg:classifiers":[
        {
            "category":"Banks & Credit Unions",
            "subcategory":"Investment Brokerage",
            "type":"Services"
        }
    ],
    "sg:phone":"+1 303 381 2520",
    "sg:postcode":"80302",
    "sg:province":"CO",
    "sg:tags":[
        "security"
    ],
    "wof:name":"Rankin Investment Corp",
    "wof:placetype":"venue"
},
  "geometry": {"coordinates":[-105.280474,40.018935],"type":"Point"}
}