{
  "type": "Feature",
  "properties": {
    "addr:full":"6533 N Academy Blvd Colorado Springs CO 80918",
    "addr:housenumber":"6533",
    "addr:postcode":"80918",
    "addr:street":"N Academy Blvd",
    "iso:country":"US",
    "sg:address":"6533 N Academy Blvd",
    "sg:city":"Colorado Springs",
    "sg:classifiers":[
        {
            "category":"Shopping",
            "subcategory":"Computers & Home Electronics",
            "type":"Retail Goods"
        }
    ],
    "sg:phone":"+1 719 266 6578",
    "sg:postcode":"80918",
    "sg:province":"CO",
    "sg:tags":[
        "equipment",
        "dealer"
    ],
    "wof:name":"Computers 4 Less",
    "wof:placetype":"venue"
},
  "geometry": {"coordinates":[-104.793736,38.926635],"type":"Point"}
}