{
  "type": "Feature",
  "properties": {
    "iso:country":"US",
    "sg:address":"14231 E 4th Ave",
    "sg:city":"Aurora",
    "sg:classifiers":[
        {
            "category":"Professional",
            "type":"Services"
        },
        {
            "category":"Health Services",
            "subcategory":"Clinic",
            "type":"Services"
        }
    ],
    "sg:phone":"+1 303 367 1220",
    "sg:postcode":"80011",
    "sg:province":"CO",
    "sg:tags":[
        "home"
    ],
    "wof:name":"Little Loving Home Svc",
    "wof:placetype":"venue"
},
  "geometry": {"coordinates":[-104.81974200000001,39.722078],"type":"Point"}
}