{
  "type": "Feature",
  "properties": {
    "addr:full":"523 Florence Rd Grand Junction CO 81504",
    "addr:housenumber":"523",
    "addr:postcode":"81504",
    "addr:street":"Florence Rd",
    "iso:country":"US",
    "sg:address":"523 Florence Rd",
    "sg:city":"Grand Junction",
    "sg:classifiers":[
        {
            "category":"Building & Trades",
            "subcategory":"Construction",
            "type":"Services"
        }
    ],
    "sg:phone":"+1 970 242 8035",
    "sg:postcode":"81504",
    "sg:province":"CO",
    "sg:tags":[
        "residential",
        "nonresidential"
    ],
    "wof:name":"McGleeson Inc",
    "wof:placetype":"venue"
},
  "geometry": {"coordinates":[-108.498368,39.080222],"type":"Point"}
}