{
  "type": "Feature",
  "properties": {
    "iso:country":"US",
    "sg:address":"4121 S Clermont St",
    "sg:city":"Englewood",
    "sg:classifiers":[
        {
            "category":"Professional",
            "subcategory":"Research",
            "type":"Services"
        }
    ],
    "sg:phone":"+1 303 758 1400",
    "sg:postcode":"80113",
    "sg:province":"CO",
    "sg:tags":[
        "organization",
        "noncommercial"
    ],
    "wof:name":"Pellish Foundation For Arts",
    "wof:placetype":"venue"
},
  "geometry": {"coordinates":[-104.935416,39.644715],"type":"Point"}
}