{
  "type": "Feature",
  "properties": {
    "addr:full":"13299 E County Line Rd Longmont CO 80501",
    "addr:housenumber":"13299",
    "addr:postcode":"80501",
    "addr:street":"E County Line Rd",
    "iso:country":"US",
    "sg:address":"13299 E County Line Rd",
    "sg:city":"Longmont",
    "sg:classifiers":[
        {
            "category":"Wholesale",
            "subcategory":"Sporting Goods",
            "type":"Manufacturing & Wholesale Goods"
        },
        {
            "category":"Manufacturing",
            "subcategory":"Toys & Sporting Goods",
            "type":"Manufacturing & Wholesale Goods"
        }
    ],
    "sg:phone":"+1 303 684 8817",
    "sg:postcode":"80501",
    "sg:province":"CO",
    "sg:tags":[
        "athletic"
    ],
    "wof:name":"Ted Allen Horseshoes Inc",
    "wof:placetype":"venue"
},
  "geometry": {"coordinates":[-105.05523700000001,40.21594],"type":"Point"}
}