{
  "type": "Feature",
  "properties": {
    "iso:country":"US",
    "sg:address":"146 W Main St",
    "sg:city":"Montrose",
    "sg:classifiers":[
        {
            "category":"Utilities",
            "subcategory":"Cable",
            "type":"Services"
        }
    ],
    "sg:phone":"+1 970 249 4506",
    "sg:postcode":"81401",
    "sg:province":"CO",
    "sg:tags":[
        "television"
    ],
    "wof:name":"Spring Creek Cable",
    "wof:placetype":"venue"
},
  "geometry": {"coordinates":[-107.881683,38.47618],"type":"Point"}
}