{
  "type": "Feature",
  "properties": {
    "addr:full":"2875 7th St Boulder CO 80304",
    "addr:housenumber":"2875",
    "addr:postcode":"80304",
    "addr:street":"7Th St",
    "iso:country":"US",
    "sg:address":"2875 7th St",
    "sg:city":"Boulder",
    "sg:classifiers":[
        {
            "category":"Professional",
            "type":"Services"
        }
    ],
    "sg:phone":"+1 303 440 0630",
    "sg:postcode":"80304",
    "sg:province":"CO",
    "wof:name":"Schulte Jaeckle LLC",
    "wof:placetype":"venue"
},
  "geometry": {"coordinates":[-105.28802399999999,40.026343],"type":"Point"}
}