{
  "type": "Feature",
  "properties": {
    "addr:full":"2911 Richard Dr Durango CO 81301",
    "addr:housenumber":"2911",
    "addr:postcode":"co 81301",
    "addr:street":"Richard Dr",
    "iso:country":"US",
    "sg:address":"2911 Richard Dr",
    "sg:city":"Durango",
    "sg:classifiers":[
        {
            "category":"Building & Trades",
            "subcategory":"Plumbing",
            "type":"Services"
        }
    ],
    "sg:phone":"+1 970 259 6695",
    "sg:postcode":"81301",
    "sg:province":"CO",
    "sg:tags":[
        "contractor"
    ],
    "wof:name":"Butler Plumbing",
    "wof:placetype":"venue"
},
  "geometry": {"coordinates":[-107.85224599999999,37.29523],"type":"Point"}
}