{
  "type": "Feature",
  "properties": {
    "iso:country":"US",
    "sg:address":"1100 10th St",
    "sg:city":"Greeley",
    "sg:classifiers":[
        {
            "category":"Government",
            "subcategory":"Office",
            "type":"Public Place"
        }
    ],
    "sg:phone":"+1 970 350 9833",
    "sg:postcode":"80631",
    "sg:province":"CO",
    "sg:tags":[
        "village"
    ],
    "wof:name":"Greeley Code Enforcement",
    "wof:placetype":"venue"
},
  "geometry": {"coordinates":[-104.69804499999999,40.422588],"type":"Point"}
}