{
  "type": "Feature",
  "properties": {
    "addr:full":"2050 Sather Dr Colorado Springs CO 80915",
    "addr:housenumber":"2050",
    "addr:postcode":"80915",
    "addr:street":"Sather Dr",
    "iso:country":"US",
    "sg:address":"2050 Sather Dr",
    "sg:city":"Colorado Springs",
    "sg:classifiers":[
        {
            "category":"Freight",
            "type":"Transportation"
        }
    ],
    "sg:phone":"+1 719 266 8767",
    "sg:postcode":"80915",
    "sg:province":"CO",
    "sg:tags":[
        "storage"
    ],
    "wof:name":"Dalby Drive Storage",
    "wof:placetype":"venue"
},
  "geometry": {"coordinates":[-104.728021,38.861698],"type":"Point"}
}