{
  "type": "Feature",
  "properties": {
    "iso:country":"US",
    "sg:address":"4800 Wheaton Dr",
    "sg:city":"Fort Collins",
    "sg:classifiers":[
        {
            "category":"Organizations",
            "subcategory":"Religious Organization",
            "type":"Services"
        }
    ],
    "sg:phone":"+1 970 581 1917",
    "sg:postcode":"80525",
    "sg:province":"CO",
    "sg:tags":[
        "church"
    ],
    "wof:name":"Mountain View Vineyard",
    "wof:placetype":"venue"
},
  "geometry": {"coordinates":[-105.053309,40.521696],"type":"Point"}
}