{
  "type": "Feature",
  "properties": {
    "addr:full":"4487 Co Rd 4 Meeker CO 81641",
    "addr:housenumber":"4487",
    "addr:postcode":"81641",
    "addr:street":"Co Rd 4",
    "iso:country":"US",
    "sg:address":"4487 Co Rd 4",
    "sg:city":"Meeker",
    "sg:classifiers":[
        {
            "category":"Building & Trades",
            "subcategory":"Construction",
            "type":"Services"
        }
    ],
    "sg:phone":"+1 970 878 4463",
    "sg:postcode":"81641",
    "sg:province":"CO",
    "sg:tags":[
        "excavating",
        "contractor"
    ],
    "wof:name":"Mobley Construction",
    "wof:placetype":"venue"
},
  "geometry": {"coordinates":[-107.85393000000001,40.00524],"type":"Point"}
}