{
  "type": "Feature",
  "properties": {
    "addr:full":"1075 S Havana St Denver CO 80012",
    "addr:housenumber":"1075",
    "addr:postcode":"80012",
    "addr:street":"S Havana St",
    "iso:country":"US",
    "sg:address":"1075 S Havana St",
    "sg:city":"Denver",
    "sg:classifiers":[
        {
            "category":"Insurance",
            "subcategory":"Insurance Agent",
            "type":"Services"
        }
    ],
    "sg:phone":"+1 303 367 8029",
    "sg:postcode":"80012",
    "sg:province":"CO",
    "wof:name":"STATE National",
    "wof:placetype":"venue"
},
  "geometry": {"coordinates":[-104.865888,39.697946],"type":"Point"}
}