{
  "type": "Feature",
  "properties": {
    "addr:full":"1266 S Havana St Aurora CO 80012",
    "addr:housenumber":"1266",
    "addr:postcode":"80012",
    "addr:street":"S Havana St",
    "iso:country":"US",
    "sg:address":"1266 S Havana St",
    "sg:city":"Aurora",
    "sg:classifiers":[
        {
            "category":"Shopping",
            "subcategory":"Used Merchandise",
            "type":"Retail Goods"
        }
    ],
    "sg:phone":"+1 303 750 6709",
    "sg:postcode":"80012",
    "sg:province":"CO",
    "sg:tags":[
        "antique"
    ],
    "wof:name":"Unique Shop",
    "wof:placetype":"venue"
},
  "geometry": {"coordinates":[-104.865887,39.694494],"type":"Point"}
}