{
  "type": "Feature",
  "properties": {
    "iso:country":"US",
    "sg:address":"3 S Tejon St",
    "sg:city":"Colorado Springs",
    "sg:classifiers":[
        {
            "category":"Professional",
            "subcategory":"Lawyer & Legal Services",
            "type":"Services"
        }
    ],
    "sg:phone":"+1 719 471 4780",
    "sg:postcode":"80903",
    "sg:province":"CO",
    "sg:tags":[
        "attorney"
    ],
    "wof:name":"William H Kirkman Jr",
    "wof:placetype":"venue"
},
  "geometry": {"coordinates":[-104.823502,38.832472],"type":"Point"}
}