{
  "type": "Feature",
  "properties": {
    "addr:full":"165 Dumont Ln Dumont CO 80436",
    "addr:housenumber":"165",
    "addr:postcode":"80436",
    "addr:street":"Dumont Ln",
    "iso:country":"US",
    "sg:address":"165 Dumont Ln",
    "sg:city":"Dumont",
    "sg:classifiers":[
        {
            "category":"Manufacturing",
            "subcategory":"Leather Goods",
            "type":"Manufacturing & Wholesale Goods"
        }
    ],
    "sg:phone":"+1 303 567 2936",
    "sg:postcode":"80436",
    "sg:province":"CO",
    "wof:name":"Mountain Mama Leather Products",
    "wof:placetype":"venue"
},
  "geometry": {"coordinates":[-105.603998,39.766157],"type":"Point"}
}