{
  "type": "Feature",
  "properties": {
    "addr:full":"2486 S Lansing Way Aurora CO 80014",
    "addr:housenumber":"2486",
    "addr:postcode":"80014",
    "addr:street":"S Lansing Way",
    "iso:country":"US",
    "sg:address":"2486 S Lansing Way",
    "sg:city":"Aurora",
    "sg:classifiers":[
        {
            "category":"Building & Trades",
            "subcategory":"Construction",
            "type":"Services"
        }
    ],
    "sg:phone":"+1 303 750 3460",
    "sg:postcode":"80014",
    "sg:province":"CO",
    "sg:tags":[
        "house"
    ],
    "wof:name":"Biltnew Construction (llc)",
    "wof:placetype":"venue"
},
  "geometry": {"coordinates":[-104.856889,39.670436],"type":"Point"}
}