{
  "type": "Feature",
  "properties": {
    "iso:country":"US",
    "sg:address":"14128 W Warren Dr",
    "sg:city":"Lakewood",
    "sg:classifiers":[
        {
            "category":"Shopping",
            "subcategory":"Gifts & Souvenirs",
            "type":"Retail Goods"
        }
    ],
    "sg:phone":"+1 303 984 0021",
    "sg:postcode":"80228",
    "sg:province":"CO",
    "sg:tags":[
        "basket",
        "parcel"
    ],
    "wof:name":"Original Basket Boutique",
    "wof:placetype":"venue"
},
  "geometry": {"coordinates":[-105.15893,39.677278],"type":"Point"}
}