{
  "type": "Feature",
  "properties": {
    "iso:country":"US",
    "sg:address":"1805 33rd St",
    "sg:city":"Boulder",
    "sg:classifiers":[
        {
            "category":"Government",
            "subcategory":"Office",
            "type":"Public Place"
        }
    ],
    "sg:phone":"+1 303 441 3390",
    "sg:postcode":"80301",
    "sg:province":"CO",
    "sg:tags":[
        "county",
        "executive",
        "safety",
        "order"
    ],
    "wof:name":"Boulder Emergency Management",
    "wof:placetype":"venue"
},
  "geometry": {"coordinates":[-105.249678,40.019871],"type":"Point"}
}