{
  "type": "Feature",
  "properties": {
    "addr:full":"2583 Hwy 6 and 50 Grand Junction CO 81501",
    "addr:housenumber":"2583",
    "addr:postcode":"81501",
    "addr:street":"Hwy 6 And 50",
    "iso:country":"US",
    "sg:address":"2583 Hwy 6 and 50",
    "sg:city":"Grand Junction",
    "sg:classifiers":[
        {
            "category":"Autos & Motor Vehicles",
            "subcategory":"Motorcycle Sales",
            "type":"Retail Goods"
        }
    ],
    "sg:phone":"+1 970 243 7148",
    "sg:postcode":"81501",
    "sg:province":"CO",
    "sg:tags":[
        "all"
    ],
    "wof:name":"Sport Center Grand Jct Inc",
    "wof:placetype":"venue"
},
  "geometry": {"coordinates":[-108.571195,39.07071],"type":"Point"}
}