{
  "type": "Feature",
  "properties": {
    "iso:country":"US",
    "sg:address":"980 S Geneva St",
    "sg:city":"Denver",
    "sg:classifiers":[
        {
            "category":"Shopping",
            "subcategory":"Clothing, Apparel, & Fashions",
            "type":"Retail Goods"
        }
    ],
    "sg:phone":"+1 303 367 9266",
    "sg:postcode":"80247",
    "sg:province":"CO",
    "wof:name":"Browns Fashions",
    "wof:placetype":"venue"
},
  "geometry": {"coordinates":[-104.86835499999999,39.69979],"type":"Point"}
}