{
  "type": "Feature",
  "properties": {
    "addr:full":"245 W Co Rd 68 Fort Collins CO 80524",
    "addr:housenumber":"245;68",
    "addr:postcode":"80524",
    "addr:street":"W Co Rd",
    "iso:country":"US",
    "sg:address":"245 W Co Rd 68",
    "sg:city":"Fort Collins",
    "sg:classifiers":[
        {
            "category":"Professional",
            "type":"Services"
        }
    ],
    "sg:phone":"+1 970 568 0955",
    "sg:postcode":"80524",
    "sg:province":"CO",
    "wof:name":"Rightawaycouriercom Inc",
    "wof:placetype":"venue"
},
  "geometry": {"coordinates":[-105.083822,40.740215],"type":"Point"}
}