{
  "type": "Feature",
  "properties": {
    "addr:full":"1482 W Tufts Ave Englewood CO 80110",
    "addr:housenumber":"1482",
    "addr:postcode":"80110",
    "addr:street":"W Tufts Ave",
    "iso:country":"US",
    "sg:address":"1482 W Tufts Ave",
    "sg:city":"Englewood",
    "sg:classifiers":[
        {
            "category":"Manufacturing",
            "subcategory":"Metals",
            "type":"Manufacturing & Wholesale Goods"
        }
    ],
    "sg:phone":"+1 303 781 8947",
    "sg:postcode":"80110",
    "sg:province":"CO",
    "sg:tags":[
        "work",
        "sheet",
        "metalwork",
        "mfg"
    ],
    "sg:website":"http://www.protosheetmetal.com",
    "wof:name":"Proto Sheet Metal Products, Inc",
    "wof:placetype":"venue"
},
  "geometry": {"coordinates":[-105.005094,39.633234],"type":"Point"}
}