{
  "type": "Feature",
  "properties": {
    "addr:full":"15316 Wagon Wheel Dr Brighton CO 80603",
    "addr:housenumber":"15316",
    "addr:postcode":"80603",
    "addr:street":"Wagon Wheel Dr",
    "iso:country":"US",
    "sg:address":"15316 Wagon Wheel Dr",
    "sg:city":"Brighton",
    "sg:classifiers":[
        {
            "category":"Building & Trades",
            "subcategory":"Construction",
            "type":"Services"
        }
    ],
    "sg:phone":"+1 303 451 1806",
    "sg:postcode":"80603",
    "sg:province":"CO",
    "sg:tags":[
        "contractor"
    ],
    "wof:name":"Allways Your Design",
    "wof:placetype":"venue"
},
  "geometry": {"coordinates":[-104.770212,40.00457],"type":"Point"}
}