{
  "type": "Feature",
  "properties": {
    "addr:full":"4413 Andes St Denver CO 80249",
    "addr:housenumber":"4413",
    "addr:postcode":"80249",
    "addr:street":"Andes St",
    "iso:country":"US",
    "sg:address":"4413 Andes St",
    "sg:city":"Denver",
    "sg:classifiers":[
        {
            "category":"Personal",
            "type":"Services"
        },
        {
            "category":"Organizations",
            "subcategory":"Professional Association",
            "type":"Services"
        }
    ],
    "sg:phone":"+1 303 373 1202",
    "sg:postcode":"80249",
    "sg:province":"CO",
    "sg:tags":[
        "singles-organizations",
        "dating"
    ],
    "wof:name":"Soul Mate",
    "wof:placetype":"venue"
},
  "geometry": {"coordinates":[-104.771474,39.777327],"type":"Point"}
}