{
  "type": "Feature",
  "properties": {
    "addr:full":"2830 D Rd Grand Junction CO 81501",
    "addr:housenumber":"2830",
    "addr:postcode":"81501",
    "addr:street":"D Rd",
    "iso:country":"US",
    "sg:address":"2830 D Rd",
    "sg:city":"Grand Junction",
    "sg:classifiers":[
        {
            "category":"Real Estate",
            "subcategory":"Developer",
            "type":"Services"
        }
    ],
    "sg:phone":"+1 970 263 8986",
    "sg:postcode":"81501",
    "sg:province":"CO",
    "sg:tags":[
        "cemetery"
    ],
    "wof:name":"Veteran's Memorial Cemetery",
    "wof:placetype":"venue"
},
  "geometry": {"coordinates":[-108.52802699999999,39.062844],"type":"Point"}
}