{
  "type": "Feature",
  "properties": {
    "iso:country":"US",
    "sg:address":"7720 S Broadway",
    "sg:city":"Littleton",
    "sg:classifiers":[
        {
            "category":"Professional",
            "type":"Services"
        }
    ],
    "sg:phone":"+1 303 707 1001",
    "sg:postcode":"80122",
    "sg:province":"CO",
    "sg:tags":[
        "establishment"
    ],
    "wof:name":"Conceptions Reproductive Assoc",
    "wof:placetype":"venue"
},
  "geometry": {"coordinates":[-104.988317,39.578095],"type":"Point"}
}