{
  "type": "Feature",
  "properties": {
    "iso:country":"US",
    "sg:address":"9203 W 103rd Ave",
    "sg:city":"Broomfield",
    "sg:classifiers":[
        {
            "category":"Manufacturing",
            "subcategory":"Paper Products",
            "type":"Manufacturing & Wholesale Goods"
        }
    ],
    "sg:phone":"+1 303 467 2551",
    "sg:postcode":"80021",
    "sg:province":"CO",
    "sg:tags":[
        "converted",
        "mfg"
    ],
    "wof:name":"Classic Wallcovering",
    "wof:placetype":"venue"
},
  "geometry": {"coordinates":[-105.101389,39.882272],"type":"Point"}
}