{
  "type": "Feature",
  "properties": {
    "addr:full":"10669 Melody Dr Northglenn CO 80234",
    "addr:housenumber":"10669",
    "addr:postcode":"80234",
    "addr:street":"Melody Dr",
    "iso:country":"US",
    "sg:address":"10669 Melody Dr",
    "sg:city":"Northglenn",
    "sg:classifiers":[
        {
            "category":"Shopping",
            "subcategory":"Optical Goods",
            "type":"Retail Goods"
        }
    ],
    "sg:phone":"+1 303 452 9312",
    "sg:postcode":"80234",
    "sg:province":"CO",
    "wof:name":"Pearle Vision",
    "wof:placetype":"venue"
},
  "geometry": {"coordinates":[-104.993335,39.890415],"type":"Point"}
}