{
  "type": "Feature",
  "properties": {
    "addr:full":"8214 W Ken Caryl Pl Littleton CO 80128",
    "addr:housenumber":"8214",
    "addr:postcode":"80128",
    "addr:street":"W Ken Caryl Pl",
    "iso:country":"US",
    "sg:address":"8214 W Ken Caryl Pl",
    "sg:city":"Littleton",
    "sg:classifiers":[
        {
            "category":"Real Estate",
            "subcategory":"Real Estate Operator",
            "type":"Services"
        }
    ],
    "sg:phone":"+1 303 972 2967",
    "sg:postcode":"80128",
    "sg:province":"CO",
    "sg:tags":[
        "apartment"
    ],
    "wof:name":"Columbine Meadows",
    "wof:placetype":"venue"
},
  "geometry": {"coordinates":[-105.09087700000001,39.57991],"type":"Point"}
}