{
  "type": "Feature",
  "properties": {
    "iso:country":"US",
    "sg:address":"6521 Federal Blvd",
    "sg:city":"Denver",
    "sg:classifiers":[
        {
            "category":"Retail",
            "subcategory":"Auto Repair",
            "type":"Services"
        }
    ],
    "sg:phone":"+1 303 428 5503",
    "sg:postcode":"80221",
    "sg:province":"CO",
    "wof:name":"Gomez Auto Repair",
    "wof:placetype":"venue"
},
  "geometry": {"coordinates":[-105.02541600000001,39.815002],"type":"Point"}
}