{
  "type": "Feature",
  "properties": {
    "addr:full":"4865 Sterling Dr Boulder CO 80301",
    "addr:housenumber":"4865",
    "addr:postcode":"80301",
    "addr:street":"Sterling Dr",
    "iso:country":"US",
    "sg:address":"4865 Sterling Dr",
    "sg:city":"Boulder",
    "sg:classifiers":[
        {
            "category":"Professional",
            "subcategory":"Computer Services",
            "type":"Services"
        }
    ],
    "sg:phone":"+1 303 443 9808",
    "sg:postcode":"80301",
    "sg:province":"CO",
    "sg:tags":[
        "internet"
    ],
    "wof:name":"Fast Data Technology",
    "wof:placetype":"venue"
},
  "geometry": {"coordinates":[-105.241156,40.027388],"type":"Point"}
}