{
  "type": "Feature",
  "properties": {
    "addr:full":"2442 F Rd Grand Junction CO 81505",
    "addr:housenumber":"2442",
    "addr:postcode":"81505",
    "addr:street":"F Rd",
    "iso:country":"US",
    "sg:address":"2442 F Rd",
    "sg:city":"Grand Junction",
    "sg:classifiers":[
        {
            "category":"Retail",
            "subcategory":"Car Wash",
            "type":"Services"
        }
    ],
    "sg:phone":"+1 970 243 8030",
    "sg:postcode":"81505",
    "sg:province":"CO",
    "sg:tags":[
        "operated",
        "polishing",
        "washing"
    ],
    "wof:name":"Mall Car Wash",
    "wof:placetype":"venue"
},
  "geometry": {"coordinates":[-108.59983699999999,39.093986],"type":"Point"}
}