{
  "type": "Feature",
  "properties": {
    "addr:full":"931 Blake Ave Glenwood Springs CO 81601",
    "addr:housenumber":"931",
    "addr:postcode":"81601",
    "addr:street":"Blake Ave",
    "iso:country":"US",
    "sg:address":"931 Blake Ave",
    "sg:city":"Glenwood Springs",
    "sg:classifiers":[
        {
            "category":"Travel",
            "subcategory":"Travel Agent",
            "type":"Entertainment"
        }
    ],
    "sg:phone":"+1 970 945 4028",
    "sg:postcode":"81601",
    "sg:province":"CO",
    "sg:tags":[
        "tours",
        "skiing"
    ],
    "sg:website":"www.colorado-ski-vacations.com",
    "wof:name":"Rocky Mountain Vacations Ski",
    "wof:placetype":"venue"
},
  "geometry": {"coordinates":[-107.322782,39.544955],"type":"Point"}
}