{
  "type": "Feature",
  "properties": {
    "iso:country":"US",
    "sg:address":"2860 Kalmia Ave",
    "sg:city":"Boulder",
    "sg:classifiers":[
        {
            "category":"Shopping",
            "subcategory":"Used Merchandise",
            "type":"Retail Goods"
        }
    ],
    "sg:phone":"+1 303 447 0238",
    "sg:postcode":"80301",
    "sg:province":"CO",
    "wof:name":"Esale Consignment Llc",
    "wof:placetype":"venue"
},
  "geometry": {"coordinates":[-105.257149,40.040093],"type":"Point"}
}