{
  "type": "Feature",
  "properties": {
    "addr:full":"7474 E Arkansas Ave Denver CO 80231",
    "addr:housenumber":"7474",
    "addr:postcode":"80231",
    "addr:street":"E Arkansas Ave",
    "iso:country":"US",
    "sg:address":"7474 E Arkansas Ave",
    "sg:city":"Denver",
    "sg:classifiers":[
        {
            "category":"Personal",
            "subcategory":"Beauty Salon",
            "type":"Services"
        }
    ],
    "sg:phone":"+1 720 323 5641",
    "sg:postcode":"80231",
    "sg:province":"CO",
    "sg:tags":[
        "makeup",
        "artist"
    ],
    "wof:name":"Cherry Creek Makeup",
    "wof:placetype":"venue"
},
  "geometry": {"coordinates":[-104.903115,39.690052],"type":"Point"}
}