{
  "type": "Feature",
  "properties": {
    "iso:country":"US",
    "sg:address":"6446 Co Rd 328",
    "sg:city":"Westcliffe",
    "sg:classifiers":[
        {
            "category":"Building & Trades",
            "subcategory":"Construction",
            "type":"Services"
        }
    ],
    "sg:phone":"+1 719 783 0423",
    "sg:postcode":"81252",
    "sg:province":"CO",
    "sg:tags":[
        "house"
    ],
    "wof:name":"Timothy James Thrun",
    "wof:placetype":"venue"
},
  "geometry": {"coordinates":[-105.33995,38.095649],"type":"Point"}
}