{
  "type": "Feature",
  "properties": {
    "iso:country":"US",
    "sg:address":"9110 E Nichols Ave",
    "sg:city":"Centennial",
    "sg:classifiers":[
        {
            "category":"Mining & Drilling",
            "type":"Manufacturing & Wholesale Goods"
        }
    ],
    "sg:phone":"+1 303 790 0940",
    "sg:postcode":"80112",
    "sg:province":"CO",
    "sg:tags":[
        "development",
        "gas",
        "oil",
        "exploration"
    ],
    "wof:name":"Intoil Inc",
    "wof:placetype":"venue"
},
  "geometry": {"coordinates":[-104.883439,39.571912],"type":"Point"}
}