{
  "type": "Feature",
  "properties": {
    "addr:full":"1660 Wynkoop Street Denver CO 80202",
    "addr:housenumber":"1660",
    "addr:postcode":"80202",
    "addr:street":"Wynkoop Street",
    "iso:country":"US",
    "sg:address":"1660 Wynkoop Street",
    "sg:city":"Denver",
    "sg:classifiers":[
        {
            "category":"Professional",
            "subcategory":"Lawyer & Legal Services",
            "type":"Services"
        }
    ],
    "sg:phone":"+1 303 296 1400",
    "sg:postcode":"80202",
    "sg:province":"CO",
    "sg:tags":[
        "divorce",
        "law",
        "family"
    ],
    "wof:name":"Straface Mark W Atty",
    "wof:placetype":"venue"
},
  "geometry": {"coordinates":[-105.000304,39.752406],"type":"Point"}
}