{
  "type": "Feature",
  "properties": {
    "addr:full":"1420 Blake St Denver CO 80202",
    "addr:housenumber":"1420",
    "addr:postcode":"80202",
    "addr:street":"Blake St",
    "iso:country":"US",
    "sg:address":"1420 Blake St",
    "sg:city":"Denver",
    "sg:classifiers":[
        {
            "category":"Manufacturing",
            "subcategory":"Printing",
            "type":"Manufacturing & Wholesale Goods"
        }
    ],
    "sg:phone":"+1 303 623 2800",
    "sg:postcode":"80202",
    "sg:province":"CO",
    "sg:tags":[
        "offset",
        "typesetting"
    ],
    "sg:website":"www.teleprinting.com",
    "wof:name":"National Teleprinting Inc",
    "wof:placetype":"venue"
},
  "geometry": {"coordinates":[-105.000426,39.749433],"type":"Point"}
}