{
  "type": "Feature",
  "properties": {
    "addr:full":"143 E Meadow Dr Vail CO 81657",
    "addr:housenumber":"143",
    "addr:postcode":"81657",
    "addr:street":"E Meadow Dr",
    "iso:country":"US",
    "sg:address":"143 E Meadow Dr",
    "sg:city":"Vail",
    "sg:classifiers":[
        {
            "category":"Banks & Credit Unions",
            "subcategory":"Bank",
            "type":"Services"
        }
    ],
    "sg:phone":"+1 970 476 0602",
    "sg:postcode":"81657",
    "sg:province":"CO",
    "sg:tags":[
        "loan",
        "real estate"
    ],
    "wof:name":"Blue Sky Mortgage",
    "wof:placetype":"venue"
},
  "geometry": {"coordinates":[-106.375803,39.641982],"type":"Point"}
}