{
  "type": "Feature",
  "properties": {
    "addr:full":"319 Main St Ordway CO 81063",
    "addr:housenumber":"319",
    "addr:postcode":"81063",
    "addr:street":"Main St",
    "iso:country":"US",
    "sg:address":"319 Main St",
    "sg:city":"Ordway",
    "sg:classifiers":[
        {
            "category":"Health Services",
            "subcategory":"Doctor",
            "type":"Services"
        }
    ],
    "sg:phone":"+1 719 267 3503",
    "sg:postcode":"81063",
    "sg:province":"CO",
    "sg:tags":[
        "physician",
        "surgeon"
    ],
    "wof:name":"Centennial Family Health Ctr",
    "wof:placetype":"venue"
},
  "geometry": {"coordinates":[-103.756529,38.218746],"type":"Point"}
}