{
  "type": "Feature",
  "properties": {
    "iso:country":"US",
    "sg:address":"3705 E Saint Vrain St",
    "sg:city":"Colorado Springs",
    "sg:classifiers":[
        {
            "category":"Shopping",
            "subcategory":"Gifts & Souvenirs",
            "type":"Retail Goods"
        }
    ],
    "sg:phone":"+1 719 597 7801",
    "sg:postcode":"80909",
    "sg:province":"CO",
    "sg:tags":[
        "party",
        "supply"
    ],
    "wof:name":"Big-Air-Jumpers",
    "wof:placetype":"venue"
},
  "geometry": {"coordinates":[-104.759218,38.839247],"type":"Point"}
}