{
  "type": "Feature",
  "properties": {
    "iso:country":"US",
    "sg:address":"7 Fireweed Ct",
    "sg:city":"Pueblo",
    "sg:classifiers":[
        {
            "category":"Banks & Credit Unions",
            "subcategory":"Investment Brokerage",
            "type":"Services"
        }
    ],
    "sg:phone":"+1 719 545 0355",
    "sg:postcode":"81001",
    "sg:province":"CO",
    "sg:tags":[
        "exchange"
    ],
    "wof:name":"Cunningham Mercantile Exchange",
    "wof:placetype":"venue"
},
  "geometry": {"coordinates":[-104.59310499999999,38.31234],"type":"Point"}
}