{
  "type": "Feature",
  "properties": {
    "addr:full":"7 Fireweed Ct Pueblo CO 81001",
    "addr:housenumber":"7",
    "addr:postcode":"81001",
    "addr:street":"Fireweed Ct",
    "iso:country":"US",
    "sg:address":"7 Fireweed Ct",
    "sg:city":"Pueblo",
    "sg:classifiers":[
        {
            "category":"Banks & Credit Unions",
            "subcategory":"Investment Brokerage",
            "type":"Services"
        }
    ],
    "sg:phone":"+1 719 545 0355",
    "sg:postcode":"81001",
    "sg:province":"CO",
    "sg:tags":[
        "exchange"
    ],
    "wof:name":"Cunningham Mercantile Exchange",
    "wof:placetype":"venue"
},
  "geometry": {"coordinates":[-104.59310499999999,38.31234],"type":"Point"}
}