{
  "type": "Feature",
  "properties": {
    "iso:country":"US",
    "sg:address":"5064 Billings St",
    "sg:city":"Denver",
    "sg:classifiers":[
        {
            "category":"Freight",
            "type":"Transportation"
        }
    ],
    "sg:phone":"+1 303 371 7056",
    "sg:postcode":"80239",
    "sg:province":"CO",
    "sg:tags":[
        "operator",
        "local",
        "trucking"
    ],
    "wof:name":"A & T Trucking",
    "wof:placetype":"venue"
},
  "geometry": {"coordinates":[-104.83074499999999,39.787856],"type":"Point"}
}