{
  "type": "Feature",
  "properties": {
    "iso:country":"US",
    "sg:address":"1344 S Wright St",
    "sg:city":"Denver",
    "sg:classifiers":[
        {
            "category":"Real Estate",
            "subcategory":"Real Estate Agent",
            "type":"Services"
        }
    ],
    "sg:phone":"+1 303 986 1212",
    "sg:postcode":"80228",
    "sg:province":"CO",
    "wof:name":"Puerto Vallarta Prpts Intl",
    "wof:placetype":"venue"
},
  "geometry": {"coordinates":[-105.140568,39.693082],"type":"Point"}
}