{
  "type": "Feature",
  "properties": {
    "addr:full":"7056 Robb St Arvada CO 80004",
    "addr:housenumber":"7056",
    "addr:postcode":"80004",
    "addr:street":"Robb St",
    "iso:country":"US",
    "sg:address":"7056 Robb St",
    "sg:city":"Arvada",
    "sg:classifiers":[
        {
            "category":"Professional",
            "type":"Services"
        }
    ],
    "sg:phone":"+1 303 425 5785",
    "sg:postcode":"80004",
    "sg:province":"CO",
    "wof:name":"Ralph A Tawney",
    "wof:placetype":"venue"
},
  "geometry": {"coordinates":[-105.125157,39.825871],"type":"Point"}
}