{
  "type": "Feature",
  "properties": {
    "iso:country":"US",
    "sg:address":"8080 Park Meadows Dr",
    "sg:city":"Lone Tree",
    "sg:classifiers":[
        {
            "category":"Health Services",
            "subcategory":"Health Practitioner",
            "type":"Services"
        }
    ],
    "sg:phone":"+1 303 796 0083",
    "sg:postcode":"80124",
    "sg:province":"CO",
    "sg:tags":[
        "therapist",
        "physical"
    ],
    "wof:name":"Theracare Pediatric Therapies",
    "wof:placetype":"venue"
},
  "geometry": {"coordinates":[-104.903873,39.560518],"type":"Point"}
}