{
  "type": "Feature",
  "properties": {
    "iso:country":"US",
    "sg:address":"1375 W Alameda Ave",
    "sg:city":"Denver",
    "sg:classifiers":[
        {
            "category":"Autos & Motor Vehicles",
            "subcategory":"Boat Sales",
            "type":"Retail Goods"
        }
    ],
    "sg:phone":"+1 720 570 2177",
    "sg:postcode":"80223",
    "sg:province":"CO",
    "sg:tags":[
        "top",
        "upholstery",
        "cover"
    ],
    "wof:name":"Raul's Boat Specialist",
    "wof:placetype":"venue"
},
  "geometry": {"coordinates":[-105.00477600000001,39.711264],"type":"Point"}
}