{
  "type": "Feature",
  "properties": {
    "addr:full":"4604 S Routt St Littleton CO 80127",
    "addr:housenumber":"4604",
    "addr:postcode":"80127",
    "addr:street":"S Routt St",
    "iso:country":"US",
    "sg:address":"4604 S Routt St",
    "sg:city":"Littleton",
    "sg:classifiers":[
        {
            "category":"Professional",
            "type":"Services"
        }
    ],
    "sg:phone":"+1 303 904 2281",
    "sg:postcode":"80127",
    "sg:province":"CO",
    "sg:tags":[
        "establishment"
    ],
    "wof:name":"Diverseye Design",
    "wof:placetype":"venue"
},
  "geometry": {"coordinates":[-105.126836,39.632582],"type":"Point"}
}