{
  "type": "Feature",
  "properties": {
    "iso:country":"US",
    "sg:address":"618 Main St",
    "sg:city":"Fort Morgan",
    "sg:classifiers":[
        {
            "category":"Organizations",
            "subcategory":"Religious Organization",
            "type":"Services"
        }
    ],
    "sg:phone":"+1 970 867 7383",
    "sg:postcode":"80701",
    "sg:province":"CO",
    "sg:tags":[
        "church"
    ],
    "wof:name":"First Baptist Church",
    "wof:placetype":"venue"
},
  "geometry": {"coordinates":[-103.801422,40.255203],"type":"Point"}
}