{
  "type": "Feature",
  "properties": {
    "iso:country":"US",
    "sg:address":"980 Cowen Dr",
    "sg:city":"Carbondale",
    "sg:classifiers":[
        {
            "category":"Food & Beverages",
            "subcategory":"Groceries & Convenience Stores",
            "type":"Retail Goods"
        }
    ],
    "sg:phone":"+1 970 963 2660",
    "sg:postcode":"81623",
    "sg:province":"CO",
    "wof:name":"Cowen Center Convenience Store",
    "wof:placetype":"venue"
},
  "geometry": {"coordinates":[-107.219086,39.41326],"type":"Point"}
}