{
  "type": "Feature",
  "properties": {
    "addr:full":"18641 E Brown Pl Aurora CO 80013",
    "addr:housenumber":"18641",
    "addr:postcode":"80013",
    "addr:street":"E Brown Pl",
    "iso:country":"US",
    "sg:address":"18641 E Brown Pl",
    "sg:city":"Aurora",
    "sg:classifiers":[
        {
            "category":"Building & Trades",
            "subcategory":"Construction",
            "type":"Services"
        }
    ],
    "sg:phone":"+1 303 375 1443",
    "sg:postcode":"80013",
    "sg:province":"CO",
    "sg:tags":[
        "company"
    ],
    "wof:name":"Hollyjay Construction Inc",
    "wof:placetype":"venue"
},
  "geometry": {"coordinates":[-104.77139,39.664555],"type":"Point"}
}