{
  "type": "Feature",
  "properties": {
    "addr:full":"6905 S Broadway Littleton CO 80122",
    "addr:housenumber":"6905",
    "addr:postcode":"80122",
    "addr:street":"S Broadway",
    "iso:country":"US",
    "sg:address":"6905 S Broadway",
    "sg:city":"Littleton",
    "sg:classifiers":[
        {
            "category":"Home & Garden",
            "subcategory":"Hardware",
            "type":"Retail Goods"
        }
    ],
    "sg:phone":"+1 303 795 9469",
    "sg:postcode":"80122",
    "sg:province":"CO",
    "wof:name":"Ace Hardware",
    "wof:placetype":"venue"
},
  "geometry": {"coordinates":[-104.988361,39.591257],"type":"Point"}
}