{
  "type": "Feature",
  "properties": {
    "addr:full":"2600 Magnolia St Denver CO 80207",
    "addr:housenumber":"2600",
    "addr:postcode":"80207",
    "addr:street":"Magnolia St",
    "iso:country":"US",
    "sg:address":"2600 Magnolia St",
    "sg:city":"Denver",
    "sg:classifiers":[
        {
            "category":"Social Services",
            "subcategory":"Child Care",
            "type":"Services"
        }
    ],
    "sg:phone":"+1 303 322 2822",
    "sg:postcode":"80207",
    "sg:province":"CO",
    "sg:tags":[
        "day"
    ],
    "sg:website":"www.coloradoschoolguides.com",
    "wof:name":"Hicks Margerie",
    "wof:placetype":"venue"
},
  "geometry": {"coordinates":[-104.91148200000001,39.754712],"type":"Point"}
}