{
  "type": "Feature",
  "properties": {
    "iso:country":"US",
    "sg:address":"338 Washington St",
    "sg:city":"Eagle",
    "sg:classifiers":[
        {
            "category":"Building & Trades",
            "subcategory":"Plumbing",
            "type":"Services"
        }
    ],
    "sg:phone":"+1 970 328 9315",
    "sg:postcode":"81631",
    "sg:province":"CO",
    "sg:tags":[
        "heating",
        "contractor"
    ],
    "wof:name":"Wiemer's Heating & Sheetmetal",
    "wof:placetype":"venue"
},
  "geometry": {"coordinates":[-106.830224,39.653787],"type":"Point"}
}