{
  "type": "Feature",
  "properties": {
    "iso:country":"US",
    "sg:address":"6080 W 92nd Ave",
    "sg:city":"Westminster",
    "sg:classifiers":[
        {
            "category":"Restaurant",
            "type":"Food & Drink"
        }
    ],
    "sg:phone":"+1 303 429 9173",
    "sg:postcode":"80031",
    "sg:province":"CO",
    "sg:tags":[
        "drinking",
        "eating"
    ],
    "wof:name":"Pink ES Fun Food and Spirits",
    "wof:placetype":"venue"
},
  "geometry": {"coordinates":[-105.063562,39.863562],"type":"Point"}
}