{
  "type": "Feature",
  "properties": {
    "iso:country":"US",
    "sg:address":"28656 Cragmont Dr",
    "sg:city":"Evergreen",
    "sg:classifiers":[
        {
            "category":"Home & Garden",
            "subcategory":"Garden Supply",
            "type":"Retail Goods"
        }
    ],
    "sg:phone":"+1 303 670 8049",
    "sg:postcode":"80439",
    "sg:province":"CO",
    "sg:tags":[
        "sprinkler"
    ],
    "wof:name":"Irrigation Engineering",
    "wof:placetype":"venue"
},
  "geometry": {"coordinates":[-105.32865200000001,39.597196],"type":"Point"}
}