{
  "type": "Feature",
  "properties": {
    "addr:full":"3803 Half Turn Rd Colorado Springs CO 80917",
    "addr:housenumber":"3803",
    "addr:postcode":"80917",
    "addr:street":"Half Turn Rd",
    "iso:country":"US",
    "sg:address":"3803 Half Turn Rd",
    "sg:city":"Colorado Springs",
    "sg:classifiers":[
        {
            "category":"Real Estate",
            "subcategory":"Real Estate Operator",
            "type":"Services"
        }
    ],
    "sg:phone":"+1 719 596 3190",
    "sg:postcode":"80917",
    "sg:province":"CO",
    "sg:tags":[
        "apartment"
    ],
    "wof:name":"Tanglewood Apartments",
    "wof:placetype":"venue"
},
  "geometry": {"coordinates":[-104.755116,38.88605],"type":"Point"}
}