{
  "type": "Feature",
  "properties": {
    "iso:country":"US",
    "sg:address":"2592 S Richfield St",
    "sg:city":"Aurora",
    "sg:classifiers":[
        {
            "category":"Building & Trades",
            "subcategory":"Construction",
            "type":"Services"
        }
    ],
    "sg:phone":"+1 303 671 7677",
    "sg:postcode":"80013",
    "sg:province":"CO",
    "sg:tags":[
        "floor",
        "laying",
        "contractor"
    ],
    "wof:name":"C&R Custom Hardwood Floors",
    "wof:placetype":"venue"
},
  "geometry": {"coordinates":[-104.784986,39.670104],"type":"Point"}
}