{
  "type": "Feature",
  "properties": {
    "addr:full":"5754 W 11th St Greeley CO 80634",
    "addr:housenumber":"5754",
    "addr:postcode":"80634",
    "addr:street":"W 11Th St",
    "iso:country":"US",
    "sg:address":"5754 W 11th St",
    "sg:city":"Greeley",
    "sg:classifiers":[
        {
            "category":"Professional",
            "subcategory":"Business Services",
            "type":"Services"
        }
    ],
    "sg:phone":"+1 970 346 7889",
    "sg:postcode":"80634",
    "sg:province":"CO",
    "sg:tags":[
        "license"
    ],
    "wof:name":"Promissor Test Ctr",
    "wof:placetype":"venue"
},
  "geometry": {"coordinates":[-104.77293,40.420284],"type":"Point"}
}