{
  "type": "Feature",
  "properties": {
    "addr:full":"1422 N Hancock Ave Colorado Springs CO 80903",
    "addr:housenumber":"1422",
    "addr:postcode":"80903",
    "addr:street":"N Hancock Ave",
    "iso:country":"US",
    "sg:address":"1422 N Hancock Ave",
    "sg:city":"Colorado Springs",
    "sg:classifiers":[
        {
            "category":"Personal",
            "type":"Services"
        }
    ],
    "sg:phone":"+1 719 634 0664",
    "sg:postcode":"80903",
    "sg:province":"CO",
    "sg:tags":[
        "therapist",
        "massage"
    ],
    "wof:name":"Karen Gale",
    "wof:placetype":"venue"
},
  "geometry": {"coordinates":[-104.802621,38.853296],"type":"Point"}
}