{
  "type": "Feature",
  "properties": {
    "iso:country":"US",
    "sg:address":"2507 8th Ave",
    "sg:city":"Greeley",
    "sg:classifiers":[
        {
            "category":"Retail",
            "subcategory":"Repair Shop",
            "type":"Services"
        }
    ],
    "sg:phone":"+1 970 356 5060",
    "sg:postcode":"80631",
    "sg:province":"CO",
    "sg:tags":[
        "upholsterer"
    ],
    "wof:name":"Melba's Custom Upholstery",
    "wof:placetype":"venue"
},
  "geometry": {"coordinates":[-104.69104799999999,40.397175],"type":"Point"}
}