{
  "type": "Feature",
  "properties": {
    "iso:country":"US",
    "sg:address":"21975 S Hwy 550",
    "sg:city":"Montrose",
    "sg:classifiers":[
        {
            "category":"Retail",
            "subcategory":"Auto Repair",
            "type":"Services"
        }
    ],
    "sg:phone":"+1 970 252 1638",
    "sg:postcode":"81401",
    "sg:province":"CO",
    "sg:tags":[
        "repairing",
        "automobile"
    ],
    "wof:name":"Tri-County Automotive",
    "wof:placetype":"venue"
},
  "geometry": {"coordinates":[-107.815335,38.373958],"type":"Point"}
}