{
  "type": "Feature",
  "properties": {
    "iso:country":"US",
    "sg:address":"410 Gold Rush Dr",
    "sg:city":"Fruita",
    "sg:classifiers":[
        {
            "category":"Organizations",
            "subcategory":"Religious Organization",
            "type":"Services"
        }
    ],
    "sg:phone":"+1 970 858 8306",
    "sg:postcode":"81521",
    "sg:province":"CO",
    "sg:tags":[
        "church"
    ],
    "wof:name":"Crown Financial Ministries",
    "wof:placetype":"venue"
},
  "geometry": {"coordinates":[-108.742356,39.166848],"type":"Point"}
}