{
  "type": "Feature",
  "properties": {
    "iso:country":"US",
    "sg:address":"522 8th St",
    "sg:city":"Greeley",
    "sg:classifiers":[
        {
            "category":"Building & Trades",
            "subcategory":"Electrical",
            "type":"Services"
        }
    ],
    "sg:phone":"+1 970 352 4650",
    "sg:postcode":"80631",
    "sg:province":"CO",
    "sg:tags":[
        "electric",
        "contractor"
    ],
    "wof:name":"Loos Electric Inc",
    "wof:placetype":"venue"
},
  "geometry": {"coordinates":[-104.686915,40.424774],"type":"Point"}
}