{
  "type": "Feature",
  "properties": {
    "iso:country":"US",
    "sg:address":"8593 W Florida Ave",
    "sg:city":"Denver",
    "sg:classifiers":[
        {
            "category":"Professional",
            "type":"Services"
        }
    ],
    "sg:phone":"+1 303 985 0872",
    "sg:postcode":"80232",
    "sg:province":"CO",
    "wof:name":"Maestas Family Partnershp",
    "wof:placetype":"venue"
},
  "geometry": {"coordinates":[-105.09316800000001,39.689504],"type":"Point"}
}