{
  "type": "Feature",
  "properties": {
    "addr:full":"1103 Valley View Rd Glenwood Springs CO 81601",
    "addr:housenumber":"1103",
    "addr:postcode":"81601",
    "addr:street":"Valley View Rd",
    "iso:country":"US",
    "sg:address":"1103 Valley View Rd",
    "sg:city":"Glenwood Springs",
    "sg:classifiers":[
        {
            "category":"Banks & Credit Unions",
            "subcategory":"Financial Services",
            "type":"Services"
        }
    ],
    "sg:phone":"+1 970 945 2457",
    "sg:postcode":"81601",
    "sg:province":"CO",
    "sg:tags":[
        "company",
        "holding"
    ],
    "wof:name":"Ticune Holdings LLC",
    "wof:placetype":"venue"
},
  "geometry": {"coordinates":[-107.316891,39.513719],"type":"Point"}
}