{
  "type": "Feature",
  "properties": {
    "addr:full":"4525 S Kipling St Littleton CO 80127",
    "addr:housenumber":"4525",
    "addr:postcode":"80127",
    "addr:street":"S Kipling St",
    "iso:country":"US",
    "sg:address":"4525 S Kipling St",
    "sg:city":"Littleton",
    "sg:classifiers":[
        {
            "category":"Government",
            "subcategory":"Fire Station",
            "type":"Public Place"
        }
    ],
    "sg:phone":"+1 303 973 0325",
    "sg:postcode":"80127",
    "sg:province":"CO",
    "sg:tags":[
        "protection"
    ],
    "wof:name":"Fire Department Maint Fcilty",
    "wof:placetype":"venue"
},
  "geometry": {"coordinates":[-105.109818,39.632684],"type":"Point"}
}