{
  "type": "Feature",
  "properties": {
    "iso:country":"US",
    "sg:address":"211 5th St",
    "sg:city":"Windsor",
    "sg:classifiers":[
        {
            "category":"Personal",
            "subcategory":"Barber",
            "type":"Services"
        }
    ],
    "sg:phone":"+1 970 674 9105",
    "sg:postcode":"80550",
    "sg:province":"CO",
    "wof:name":"5th Street Barber Shop",
    "wof:placetype":"venue"
},
  "geometry": {"coordinates":[-104.904055,40.478687],"type":"Point"}
}