{
  "type": "Feature",
  "properties": {
    "iso:country":"US",
    "sg:address":"8371 E Amherst Cir",
    "sg:city":"Denver",
    "sg:classifiers":[
        {
            "category":"Professional",
            "subcategory":"Management & Consulting",
            "type":"Services"
        }
    ],
    "sg:phone":"+1 303 695 6764",
    "sg:postcode":"80231",
    "sg:province":"CO",
    "sg:tags":[
        "marketing",
        "consultant"
    ],
    "wof:name":"N A Turner Marketing Svc",
    "wof:placetype":"venue"
},
  "geometry": {"coordinates":[-104.89179,39.666289],"type":"Point"}
}