{
  "type": "Feature",
  "properties": {
    "iso:country":"US",
    "sg:address":"2205 State Ave",
    "sg:city":"Alamosa",
    "sg:classifiers":[
        {
            "category":"Government",
            "subcategory":"Office",
            "type":"Public Place"
        }
    ],
    "sg:phone":"+1 719 589 6432",
    "sg:postcode":"81101",
    "sg:province":"CO",
    "sg:tags":[
        "wildlife",
        "conservation",
        "mineral",
        "land"
    ],
    "wof:name":"Alamosa Field Office",
    "wof:placetype":"venue"
},
  "geometry": {"coordinates":[-105.865533,37.449528],"type":"Point"}
}