{
  "type": "Feature",
  "properties": {
    "iso:country":"US",
    "sg:address":"825 Main St",
    "sg:city":"Ouray",
    "sg:classifiers":[
        {
            "category":"Shopping",
            "subcategory":"Used Merchandise",
            "type":"Retail Goods"
        }
    ],
    "sg:phone":"+1 970 729 2453",
    "sg:postcode":"81427",
    "sg:province":"CO",
    "sg:tags":[
        "antique"
    ],
    "wof:name":"Carolyn Moorehead Est Jewelers",
    "wof:placetype":"venue"
},
  "geometry": {"coordinates":[-107.671402,38.025747],"type":"Point"}
}