{
  "type": "Feature",
  "properties": {
    "iso:country":"US",
    "sg:address":"13071 W Alameda Pkwy",
    "sg:city":"Denver",
    "sg:classifiers":[
        {
            "category":"Personal",
            "subcategory":"Beauty Salon",
            "type":"Services"
        }
    ],
    "sg:phone":"+1 303 716 9560",
    "sg:postcode":"80228",
    "sg:province":"CO",
    "sg:tags":[
        "shop"
    ],
    "wof:name":"Great Clips",
    "wof:placetype":"venue"
},
  "geometry": {"coordinates":[-105.14543,39.697314],"type":"Point"}
}