{
  "type": "Feature",
  "properties": {
    "addr:full":"5070 Oakland St Denver CO 80239",
    "addr:housenumber":"5070",
    "addr:postcode":"80239",
    "addr:street":"Oakland St",
    "iso:country":"US",
    "sg:address":"5070 Oakland St",
    "sg:city":"Denver",
    "sg:classifiers":[
        {
            "category":"Manufacturing",
            "subcategory":"Tools & Machinery",
            "type":"Manufacturing & Wholesale Goods"
        }
    ],
    "sg:phone":"+1 303 371 8097",
    "sg:postcode":"80239",
    "sg:province":"CO",
    "sg:tags":[
        "equipment",
        "construction"
    ],
    "sg:website":"www.ctiattachments.com",
    "wof:name":"Construction Technology Inc",
    "wof:placetype":"venue"
},
  "geometry": {"coordinates":[-104.850587,39.786957],"type":"Point"}
}