{
  "type": "Feature",
  "properties": {
    "addr:full":"302 Main St Westcliffe CO 81252",
    "addr:housenumber":"302",
    "addr:postcode":"81252",
    "addr:street":"Main St",
    "iso:country":"US",
    "sg:address":"302 Main St",
    "sg:city":"Westcliffe",
    "sg:classifiers":[
        {
            "category":"Real Estate",
            "subcategory":"Real Estate Agent",
            "type":"Services"
        }
    ],
    "sg:phone":"+1 719 783 4888",
    "sg:postcode":"81252",
    "sg:province":"CO",
    "wof:name":"Mattie Burtt Realty Inc",
    "wof:placetype":"venue"
},
  "geometry": {"coordinates":[-105.467349,38.135921],"type":"Point"}
}