{
  "type": "Feature",
  "properties": {
    "addr:full":"629 Co Rd 303 Parachute CO 81635",
    "addr:housenumber":"629",
    "addr:postcode":"81635",
    "addr:street":"Co Rd 303",
    "iso:country":"US",
    "sg:address":"629 Co Rd 303",
    "sg:city":"Parachute",
    "sg:classifiers":[
        {
            "category":"Building & Trades",
            "subcategory":"Landscaping Services",
            "type":"Services"
        }
    ],
    "sg:phone":"+1 970 285 7494",
    "sg:postcode":"81635",
    "sg:province":"CO",
    "sg:tags":[
        "landscape"
    ],
    "wof:name":"Precision Tile Works",
    "wof:placetype":"venue"
},
  "geometry": {"coordinates":[-108.017906,39.430617],"type":"Point"}
}