{
  "type": "Feature",
  "properties": {
    "addr:full":"308 Breeze St Craig CO 81625",
    "addr:housenumber":"308",
    "addr:postcode":"81625",
    "addr:street":"Breeze St",
    "iso:country":"US",
    "sg:address":"308 Breeze St",
    "sg:city":"Craig",
    "sg:classifiers":[
        {
            "category":"Building & Trades",
            "subcategory":"Construction",
            "type":"Services"
        }
    ],
    "sg:phone":"+1 970 824 2686",
    "sg:postcode":"81625",
    "sg:province":"CO",
    "sg:tags":[
        "contractor"
    ],
    "wof:name":"Breeze Street Ironworks",
    "wof:placetype":"venue"
},
  "geometry": {"coordinates":[-107.54854400000001,40.512279],"type":"Point"}
}