{
  "type": "Feature",
  "properties": {
    "addr:full":"740 Railroad St Coal Creek CO 81244",
    "addr:housenumber":"740",
    "addr:postcode":"81244",
    "addr:street":"Railroad St",
    "iso:country":"US",
    "sg:address":"740 Railroad St",
    "sg:city":"Coal Creek",
    "sg:classifiers":[
        {
            "category":"Mining & Drilling",
            "type":"Manufacturing & Wholesale Goods"
        }
    ],
    "sg:phone":"+1 719 784 2170",
    "sg:postcode":"81244",
    "sg:province":"CO",
    "sg:tags":[
        "coal",
        "shipping"
    ],
    "wof:name":"Coal Creek Volunter Fire Dept",
    "wof:placetype":"venue"
},
  "geometry": {"coordinates":[-105.148285,38.356718],"type":"Point"}
}