{
  "type": "Feature",
  "properties": {
    "iso:country":"US",
    "sg:address":"3800 Buchtel Blvd",
    "sg:city":"Denver",
    "sg:classifiers":[
        {
            "category":"Government",
            "subcategory":"Post Office",
            "type":"Public Place"
        }
    ],
    "sg:phone":"+1 303 504 4721",
    "sg:postcode":"80210",
    "sg:province":"CO",
    "wof:name":"University Park Station",
    "wof:placetype":"venue"
},
  "geometry": {"coordinates":[-104.942508,39.680237],"type":"Point"}
}