{
  "type": "Feature",
  "properties": {
    "iso:country":"US",
    "sg:address":"1502 Alexander Cir",
    "sg:city":"Pueblo",
    "sg:phone":"+1 719 545 3154",
    "sg:postcode":"81001",
    "sg:province":"CO",
    "sg:tags":[
        "equipment",
        "commercial"
    ],
    "wof:name":"National Equipment Corp",
    "wof:placetype":"venue"
},
  "geometry": {"coordinates":[-104.584037,38.292207],"type":"Point"}
}