{
  "type": "Feature",
  "properties": {
    "iso:country":"US",
    "sg:address":"26620 Co Rd 2l",
    "sg:city":"Hugo",
    "sg:classifiers":[
        {
            "category":"Building & Trades",
            "subcategory":"Construction",
            "type":"Services"
        }
    ],
    "sg:phone":"+1 719 743 2178",
    "sg:postcode":"80821",
    "sg:province":"CO",
    "sg:tags":[
        "excavating",
        "contractor"
    ],
    "wof:name":"Cochran Construction Co",
    "wof:placetype":"venue"
},
  "geometry": {"coordinates":[-103.57922499999999,38.995881],"type":"Point"}
}