{
  "type": "Feature",
  "properties": {
    "iso:country":"US",
    "sg:address":"5038 Federal Boulevard",
    "sg:city":"Denver",
    "sg:classifiers":[
        {
            "category":"Shopping",
            "subcategory":"Books",
            "type":"Retail Goods"
        }
    ],
    "sg:phone":"+1 303 433 3981",
    "sg:postcode":"80221",
    "sg:province":"CO",
    "sg:tags":[
        "bookstore"
    ],
    "wof:name":"Te Tel",
    "wof:placetype":"venue"
},
  "geometry": {"coordinates":[-105.024985,39.787962],"type":"Point"}
}