{
  "type": "Feature",
  "properties": {
    "addr:full":"10115 Granite Hill Dr Parker CO 80134",
    "addr:housenumber":"10115",
    "addr:postcode":"80134",
    "addr:street":"Granite Hill Dr",
    "iso:country":"US",
    "sg:address":"10115 Granite Hill Dr",
    "sg:city":"Parker",
    "sg:classifiers":[
        {
            "category":"Professional",
            "subcategory":"Management & Consulting",
            "type":"Services"
        }
    ],
    "sg:phone":"+1 303 840 4641",
    "sg:postcode":"80134",
    "sg:province":"CO",
    "wof:name":"Advancepcs",
    "wof:placetype":"venue"
},
  "geometry": {"coordinates":[-104.809714,39.534213],"type":"Point"}
}