{
  "type": "Feature",
  "properties": {
    "iso:country":"US",
    "sg:address":"1616 17th St",
    "sg:city":"Denver",
    "sg:classifiers":[
        {
            "category":"Retail",
            "subcategory":"Car Wash",
            "type":"Services"
        }
    ],
    "sg:phone":"+1 303 316 3924",
    "sg:postcode":"80202",
    "sg:province":"CO",
    "wof:name":"Mercury Car Wash",
    "wof:placetype":"venue"
},
  "geometry": {"coordinates":[-104.99913,39.752201],"type":"Point"}
}