{
  "type": "Feature",
  "properties": {
    "iso:country":"US",
    "sg:address":"8073 Co Rd 12 S",
    "sg:city":"Alamosa",
    "sg:classifiers":[
        {
            "category":"Farming",
            "subcategory":"Farm & Veterinary Services",
            "type":"Manufacturing & Wholesale Goods"
        }
    ],
    "sg:phone":"+1 719 589 3035",
    "sg:postcode":"81101",
    "sg:province":"CO",
    "sg:tags":[
        "raise",
        "cattle"
    ],
    "wof:name":"Double S Cattle Co Inc",
    "wof:placetype":"venue"
},
  "geometry": {"coordinates":[-105.9061,37.400328],"type":"Point"}
}