{
  "type": "Feature",
  "properties": {
    "iso:country":"US",
    "sg:address":"420 6th Ave",
    "sg:city":"Ouray",
    "sg:classifiers":[
        {
            "category":"Museum",
            "type":"Entertainment"
        }
    ],
    "sg:phone":"+1 970 325 4576",
    "sg:postcode":"81427",
    "sg:province":"CO",
    "wof:name":"Ouray County Museum",
    "wof:placetype":"venue"
},
  "geometry": {"coordinates":[-107.669872,38.022845],"type":"Point"}
}