{
  "type": "Feature",
  "properties": {
    "addr:full":"17421 Rimrock Dr Golden CO 80401",
    "addr:housenumber":"17421",
    "addr:postcode":"80401",
    "addr:street":"Rimrock Dr",
    "iso:country":"US",
    "sg:address":"17421 Rimrock Dr",
    "sg:city":"Golden",
    "sg:classifiers":[
        {
            "category":"Professional",
            "type":"Services"
        }
    ],
    "sg:phone":"+1 720 200 0825",
    "sg:postcode":"80401",
    "sg:province":"CO",
    "wof:name":"Change and Go Inc",
    "wof:placetype":"venue"
},
  "geometry": {"coordinates":[-105.197306,39.7451],"type":"Point"}
}