{
  "type": "Feature",
  "properties": {
    "iso:country":"US",
    "sg:address":"4120 Co Rd 54G",
    "sg:city":"Laporte",
    "sg:classifiers":[
        {
            "category":"Restaurant",
            "type":"Food & Drink"
        },
        {
            "category":"Autos & Motor Vehicles",
            "subcategory":"Fuel & Gas Station",
            "type":"Retail Goods"
        }
    ],
    "sg:phone":"+1 970 482 5511",
    "sg:postcode":"80535",
    "sg:province":"CO",
    "sg:tags":[
        "gasoline",
        "grocery",
        "station",
        "eating"
    ],
    "wof:name":"Vern's Place",
    "wof:placetype":"venue"
},
  "geometry": {"coordinates":[-105.154189,40.632778],"type":"Point"}
}