{
  "type": "Feature",
  "properties": {
    "iso:country":"US",
    "sg:address":"617 W Main St",
    "sg:city":"Aspen",
    "sg:classifiers":[
        {
            "category":"Building & Trades",
            "subcategory":"Construction",
            "type":"Services"
        }
    ],
    "sg:phone":"+1 970 925 8521",
    "sg:postcode":"81611",
    "sg:province":"CO",
    "sg:tags":[
        "general",
        "contractor"
    ],
    "wof:name":"Iglehart Construction",
    "wof:placetype":"venue"
},
  "geometry": {"coordinates":[-106.829782,39.192767],"type":"Point"}
}