{
  "type": "Feature",
  "properties": {
    "iso:country":"US",
    "sg:address":"2809 E Harmony Rd",
    "sg:city":"Fort Collins",
    "sg:classifiers":[
        {
            "category":"Health Services",
            "subcategory":"Hospital",
            "type":"Services"
        }
    ],
    "sg:phone":"+1 970 297 6700",
    "sg:postcode":"80528",
    "sg:province":"CO",
    "wof:name":"Poudre Valley Hospital",
    "wof:placetype":"venue"
},
  "geometry": {"coordinates":[-105.02435699999999,40.523011],"type":"Point"}
}