{
  "type": "Feature",
  "properties": {
    "addr:full":"800 W Ohio Ave Gunnison CO 81230",
    "addr:housenumber":"800",
    "addr:postcode":"81230",
    "addr:street":"W Ohio Ave",
    "iso:country":"US",
    "sg:address":"800 W Ohio Ave",
    "sg:city":"Gunnison",
    "sg:classifiers":[
        {
            "category":"Education",
            "subcategory":"School",
            "type":"Public Place"
        }
    ],
    "sg:phone":"+1 970 641 7700",
    "sg:postcode":"81230",
    "sg:province":"CO",
    "sg:tags":[
        "high"
    ],
    "wof:name":"Gunnison High School",
    "wof:placetype":"venue"
},
  "geometry": {"coordinates":[-106.93610099999999,38.547734],"type":"Point"}
}