{
  "type": "Feature",
  "properties": {
    "addr:full":"5621 S Delaware St Littleton CO 80120",
    "addr:housenumber":"5621",
    "addr:postcode":"80120",
    "addr:street":"S Delaware St",
    "iso:country":"US",
    "sg:address":"5621 S Delaware St",
    "sg:city":"Littleton",
    "sg:classifiers":[
        {
            "category":"Organizations",
            "subcategory":"Religious Organization",
            "type":"Services"
        }
    ],
    "sg:phone":"+1 303 798 9647",
    "sg:postcode":"80120",
    "sg:province":"CO",
    "sg:tags":[
        "church"
    ],
    "sg:website":"www.littletoncogholiness.org",
    "wof:name":"Church Of God Holiness",
    "wof:placetype":"venue"
},
  "geometry": {"coordinates":[-104.993302,39.614895],"type":"Point"}
}