{
  "type": "Feature",
  "properties": {
    "iso:country":"US",
    "sg:address":"2176 K Path",
    "sg:city":"Cotopaxi",
    "sg:classifiers":[
        {
            "category":"Professional",
            "type":"Services"
        }
    ],
    "sg:phone":"+1 719 942 4007",
    "sg:postcode":"81223",
    "sg:province":"CO",
    "wof:name":"Honor Sterling LLC",
    "wof:placetype":"venue"
},
  "geometry": {"coordinates":[-105.498605,38.313778],"type":"Point"}
}