{
  "type": "Feature",
  "properties": {
    "iso:country":"US",
    "sg:address":"3726 Brighton Boulevard",
    "sg:city":"Denver",
    "sg:classifiers":[
        {
            "category":"Autos & Motor Vehicles",
            "subcategory":"Motorcycle Sales",
            "type":"Retail Goods"
        }
    ],
    "sg:phone":"+1 303 293 2453",
    "sg:postcode":"80216",
    "sg:province":"CO",
    "wof:name":"Biker's Dream of Denver",
    "wof:placetype":"venue"
},
  "geometry": {"coordinates":[-104.976264,39.772374],"type":"Point"}
}