{
  "type": "Feature",
  "properties": {
    "addr:full":"14500 W Colfax Ave Lakewood CO 80401",
    "addr:housenumber":"14500",
    "addr:postcode":"80401",
    "addr:street":"W Colfax Ave",
    "iso:country":"US",
    "sg:address":"14500 W Colfax Ave",
    "sg:city":"Lakewood",
    "sg:classifiers":[
        {
            "category":"Shopping",
            "subcategory":"Hobbies, Toys, & Games",
            "type":"Retail Goods"
        }
    ],
    "sg:phone":"+1 303 384 3534",
    "sg:postcode":"80401",
    "sg:province":"CO",
    "sg:tags":[
        "supply"
    ],
    "wof:name":"Games Workshop",
    "wof:placetype":"venue"
},
  "geometry": {"coordinates":[-105.165448,39.732095],"type":"Point"}
}