{
  "type": "Feature",
  "properties": {
    "addr:full":"320 N Circle Dr Colorado Springs CO 80909",
    "addr:housenumber":"320",
    "addr:postcode":"80909",
    "addr:street":"N Circle Dr",
    "iso:country":"US",
    "sg:address":"320 N Circle Dr",
    "sg:city":"Colorado Springs",
    "sg:classifiers":[
        {
            "category":"Restaurant",
            "type":"Food & Drink"
        }
    ],
    "sg:phone":"+1 719 634 9945",
    "sg:postcode":"80909",
    "sg:province":"CO",
    "wof:name":"Bean Bandit",
    "wof:placetype":"venue"
},
  "geometry": {"coordinates":[-104.775965,38.835798],"type":"Point"}
}