{
  "type": "Feature",
  "properties": {
    "addr:full":"1012 S 9th St Canon City CO 81212",
    "addr:housenumber":"1012",
    "addr:postcode":"81212",
    "addr:street":"S 9Th St",
    "iso:country":"US",
    "sg:address":"1012 S 9th St",
    "sg:city":"Canon City",
    "sg:classifiers":[
        {
            "category":"Insurance",
            "subcategory":"Insurance Agent",
            "type":"Services"
        }
    ],
    "sg:phone":"+1 719 275 4296",
    "sg:postcode":"81212",
    "sg:province":"CO",
    "wof:name":"Detata Life & Health",
    "wof:placetype":"venue"
},
  "geometry": {"coordinates":[-105.231855,38.433928],"type":"Point"}
}