{
  "type": "Feature",
  "properties": {
    "iso:country":"US",
    "sg:address":"12001 Crabapple Dr",
    "sg:city":"Franktown",
    "sg:classifiers":[
        {
            "category":"Retail",
            "subcategory":"Repair Shop",
            "type":"Services"
        }
    ],
    "sg:phone":"+1 303 805 8674",
    "sg:postcode":"80116",
    "sg:province":"CO",
    "sg:tags":[
        "blacksmith"
    ],
    "wof:name":"Jack Lawler Farrier Svc",
    "wof:placetype":"venue"
},
  "geometry": {"coordinates":[-104.66394099999999,39.396957],"type":"Point"}
}