{
  "type": "Feature",
  "properties": {
    "iso:country":"US",
    "sg:address":"469 E 8th Ave",
    "sg:city":"Durango",
    "sg:classifiers":[
        {
            "category":"Health Services",
            "subcategory":"Health Practitioner",
            "type":"Services"
        }
    ],
    "sg:phone":"+1 970 375 0393",
    "sg:postcode":"81301",
    "sg:province":"CO",
    "sg:tags":[
        "acupuncture"
    ],
    "wof:name":"Alpine Acupuncture Clinic",
    "wof:placetype":"venue"
},
  "geometry": {"coordinates":[-107.872716,37.266861],"type":"Point"}
}