{
  "type": "Feature",
  "properties": {
    "addr:full":"1388 Main St Springfield CO 81073",
    "addr:housenumber":"1388",
    "addr:postcode":"81073",
    "addr:street":"Main St",
    "iso:country":"US",
    "sg:address":"1388 Main St",
    "sg:city":"Springfield",
    "sg:classifiers":[
        {
            "category":"Health Services",
            "subcategory":"Clinic",
            "type":"Services"
        }
    ],
    "sg:phone":"+1 719 523 6747",
    "sg:postcode":"81073",
    "sg:province":"CO",
    "wof:name":"Orebaugh Insurance",
    "wof:placetype":"venue"
},
  "geometry": {"coordinates":[-102.616452,37.398983],"type":"Point"}
}