{
  "type": "Feature",
  "properties": {
    "iso:country":"US",
    "sg:address":"2085 S Josephine St",
    "sg:city":"Denver",
    "sg:classifiers":[
        {
            "category":"Real Estate",
            "subcategory":"Real Estate Operator",
            "type":"Services"
        }
    ],
    "sg:phone":"+1 303 761 1132",
    "sg:postcode":"80210",
    "sg:province":"CO",
    "sg:tags":[
        "building",
        "nonresidential"
    ],
    "wof:name":"Hana Properties LLC",
    "wof:placetype":"venue"
},
  "geometry": {"coordinates":[-104.958006,39.679992],"type":"Point"}
}