{
  "type": "Feature",
  "properties": {
    "addr:full":"16265 S Golden Rd Golden CO 80401",
    "addr:housenumber":"16265",
    "addr:postcode":"80401",
    "addr:street":"S Golden Rd",
    "iso:country":"US",
    "sg:address":"16265 S Golden Rd",
    "sg:city":"Golden",
    "sg:classifiers":[
        {
            "category":"Food & Beverages",
            "subcategory":"Liquor & Beverages",
            "type":"Retail Goods"
        }
    ],
    "sg:phone":"+1 303 279 3968",
    "sg:postcode":"80401",
    "sg:province":"CO",
    "wof:name":"Ace Liquor Store",
    "wof:placetype":"venue"
},
  "geometry": {"coordinates":[-105.183735,39.735247],"type":"Point"}
}