{
  "type": "Feature",
  "properties": {
    "iso:country":"US",
    "sg:address":"580 S Broadway",
    "sg:city":"Denver",
    "sg:classifiers":[
        {
            "category":"Professional",
            "subcategory":"Computer Services",
            "type":"Services"
        }
    ],
    "sg:phone":"+1 303 698 2923",
    "sg:postcode":"80209",
    "sg:province":"CO",
    "sg:tags":[
        "repair"
    ],
    "sg:website":"www.cpuweb.net",
    "wof:name":"CPU Svc",
    "wof:placetype":"venue"
},
  "geometry": {"coordinates":[-104.98753499999999,39.707206],"type":"Point"}
}