{
  "type": "Feature",
  "properties": {
    "iso:country":"US",
    "sg:address":"26 W Dry Creek Cir",
    "sg:city":"Littleton",
    "sg:classifiers":[
        {
            "category":"Building & Trades",
            "subcategory":"Plumbing",
            "type":"Services"
        }
    ],
    "sg:phone":"+1 303 730 2188",
    "sg:postcode":"80120",
    "sg:province":"CO",
    "sg:tags":[
        "product",
        "management",
        "energy",
        "system"
    ],
    "wof:name":"Oneok Energy Marketing Co",
    "wof:placetype":"venue"
},
  "geometry": {"coordinates":[-104.991429,39.581897],"type":"Point"}
}