{
  "type": "Feature",
  "properties": {
    "iso:country":"US",
    "sg:address":"406 W 1st St",
    "sg:city":"La Junta",
    "sg:classifiers":[
        {
            "category":"Autos & Motor Vehicles",
            "subcategory":"Fuel & Gas Station",
            "type":"Retail Goods"
        }
    ],
    "sg:phone":"+1 719 384 2784",
    "sg:postcode":"81050",
    "sg:province":"CO",
    "sg:tags":[
        "oil"
    ],
    "wof:name":"Conoco Of LA Junta",
    "wof:placetype":"venue"
},
  "geometry": {"coordinates":[-103.548485,37.987826],"type":"Point"}
}