{
  "type": "Feature",
  "properties": {
    "iso:country":"US",
    "sg:address":"13750 E Quincy Ave",
    "sg:city":"Aurora",
    "sg:classifiers":[
        {
            "category":"Building & Trades",
            "subcategory":"Construction",
            "type":"Services"
        },
        {
            "category":"Personal",
            "subcategory":"Day Spa",
            "type":"Services"
        }
    ],
    "sg:phone":"+1 303 680 2000",
    "sg:postcode":"80015",
    "sg:province":"CO",
    "sg:tags":[
        "hot",
        "tub",
        "pool",
        "swimming"
    ],
    "wof:name":"Splash N Rack",
    "wof:placetype":"venue"
},
  "geometry": {"coordinates":[-104.828092,39.63851],"type":"Point"}
}