{
  "type": "Feature",
  "properties": {
    "addr:full":"638 Elkton Dr Colorado Springs CO 80907",
    "addr:housenumber":"638",
    "addr:postcode":"80907",
    "addr:street":"Elkton Dr",
    "iso:country":"US",
    "sg:address":"638 Elkton Dr",
    "sg:city":"Colorado Springs",
    "sg:classifiers":[
        {
            "category":"Manufacturing",
            "subcategory":"Metals",
            "type":"Manufacturing & Wholesale Goods"
        },
        {
            "category":"Professional",
            "subcategory":"Business Services",
            "type":"Services"
        }
    ],
    "sg:phone":"+1 719 531 6677",
    "sg:postcode":"80907",
    "sg:province":"CO",
    "sg:tags":[
        "equipment",
        "product",
        "etched",
        "glass"
    ],
    "wof:name":"Colorado Laser Marking Corp",
    "wof:placetype":"venue"
},
  "geometry": {"coordinates":[-104.837305,38.900774],"type":"Point"}
}