{
  "type": "Feature",
  "properties": {
    "iso:country":"US",
    "sg:address":"15047 Deer Run Rd",
    "sg:city":"Delta",
    "sg:classifiers":[
        {
            "category":"Shopping",
            "subcategory":"Crafts & Fabrics",
            "type":"Retail Goods"
        }
    ],
    "sg:phone":"+1 970 874 3799",
    "sg:postcode":"81416",
    "sg:province":"CO",
    "sg:tags":[
        "sewing"
    ],
    "wof:name":"Just Sew It",
    "wof:placetype":"venue"
},
  "geometry": {"coordinates":[-108.082795,38.734232],"type":"Point"}
}