{
  "type": "Feature",
  "properties": {
    "addr:full":"13789 E Marina Dr Aurora CO 80014",
    "addr:housenumber":"13789",
    "addr:postcode":"80014",
    "addr:street":"E Marina Dr",
    "iso:country":"US",
    "sg:address":"13789 E Marina Dr",
    "sg:city":"Aurora",
    "sg:classifiers":[
        {
            "category":"Banks & Credit Unions",
            "subcategory":"Financial Services",
            "type":"Services"
        }
    ],
    "sg:phone":"+1 303 752 1466",
    "sg:postcode":"80014",
    "sg:province":"CO",
    "sg:tags":[
        "trust",
        "management"
    ],
    "wof:name":"Daughenbaugh Family Ltd P",
    "wof:placetype":"venue"
},
  "geometry": {"coordinates":[-104.829938,39.659982],"type":"Point"}
}