{
  "type": "Feature",
  "properties": {
    "iso:country":"US",
    "sg:address":"1700 W Belleview Ave",
    "sg:city":"Littleton",
    "sg:classifiers":[
        {
            "category":"Building & Trades",
            "subcategory":"Construction",
            "type":"Services"
        }
    ],
    "sg:phone":"+1 303 795 5201",
    "sg:postcode":"80120",
    "sg:province":"CO",
    "sg:tags":[
        "carpentry",
        "contractor"
    ],
    "wof:name":"Whiteheart Cabinetry",
    "wof:placetype":"venue"
},
  "geometry": {"coordinates":[-105.010122,39.624125],"type":"Point"}
}