{
  "type": "Feature",
  "properties": {
    "iso:country":"US",
    "sg:address":"152 Industrial Dr",
    "sg:city":"Rock Springs",
    "sg:classifiers":[
        {
            "category":"Building & Trades",
            "subcategory":"Equipment Rental",
            "type":"Services"
        }
    ],
    "sg:phone":"+1 307 362 4421",
    "sg:postcode":"82901",
    "sg:province":"CO",
    "wof:name":"Halliburton Energy Services",
    "wof:placetype":"venue"
},
  "geometry": {"coordinates":[-109.23445700000001,41.617832],"type":"Point"}
}