{
  "type": "Feature",
  "properties": {
    "addr:full":"703 Main St Blanca CO 81123",
    "addr:housenumber":"703",
    "addr:postcode":"81123",
    "addr:street":"Main St",
    "iso:country":"US",
    "sg:address":"703 Main St",
    "sg:city":"Blanca",
    "sg:classifiers":[
        {
            "category":"Food & Beverages",
            "subcategory":"Groceries & Convenience Stores",
            "type":"Retail Goods"
        }
    ],
    "sg:phone":"+1 719 379 3532",
    "sg:postcode":"81123",
    "sg:province":"CO",
    "sg:tags":[
        "grocer"
    ],
    "wof:name":"Smith's Store",
    "wof:placetype":"venue"
},
  "geometry": {"coordinates":[-105.51641499999999,37.435603],"type":"Point"}
}