{
  "type": "Feature",
  "properties": {
    "iso:country":"US",
    "sg:address":"11 W Dry Creek Ct",
    "sg:city":"Littleton",
    "sg:classifiers":[
        {
            "category":"Recreation",
            "type":"Entertainment"
        }
    ],
    "sg:phone":"+1 303 797 9622",
    "sg:postcode":"80120",
    "sg:province":"CO",
    "sg:tags":[
        "club",
        "membership"
    ],
    "wof:name":"Highline YMCA",
    "wof:placetype":"venue"
},
  "geometry": {"coordinates":[-104.98973599999999,39.580492],"type":"Point"}
}