{
  "type": "Feature",
  "properties": {
    "addr:full":"509 Trinchera St San Luis CO 81152",
    "addr:housenumber":"509",
    "addr:postcode":"81152",
    "addr:street":"Trinchera St",
    "iso:country":"US",
    "sg:address":"509 Trinchera St",
    "sg:city":"San Luis",
    "sg:classifiers":[
        {
            "category":"Building & Trades",
            "subcategory":"Landscaping Services",
            "type":"Services"
        }
    ],
    "sg:phone":"+1 719 672 3672",
    "sg:postcode":"81152",
    "sg:province":"CO",
    "sg:tags":[
        "tree"
    ],
    "wof:name":"Trees On Wheels",
    "wof:placetype":"venue"
},
  "geometry": {"coordinates":[-105.42263800000001,37.200349],"type":"Point"}
}