{
  "type": "Feature",
  "properties": {
    "addr:full":"37804 Back River Rd Paonia CO 81428",
    "addr:housenumber":"37804",
    "addr:postcode":"81428",
    "addr:street":"Back River Rd",
    "iso:country":"US",
    "sg:address":"37804 Back River Rd",
    "sg:city":"Paonia",
    "sg:classifiers":[
        {
            "category":"Professional",
            "subcategory":"Business Services",
            "type":"Services"
        }
    ],
    "sg:phone":"+1 970 527 3060",
    "sg:postcode":"81428",
    "sg:province":"CO",
    "sg:tags":[
        "water",
        "hauling"
    ],
    "wof:name":"North Fork Water Svc",
    "wof:placetype":"venue"
},
  "geometry": {"coordinates":[-107.652062,38.831151],"type":"Point"}
}