{
  "type": "Feature",
  "properties": {
    "addr:full":"193 Sunny Acres Rd Glenwood Springs CO 81601",
    "addr:housenumber":"193",
    "addr:postcode":"81601",
    "addr:street":"Sunny Acres Rd",
    "iso:country":"US",
    "sg:address":"193 Sunny Acres Rd",
    "sg:city":"Glenwood Springs",
    "sg:classifiers":[
        {
            "category":"Restaurant",
            "type":"Food & Drink"
        }
    ],
    "sg:phone":"+1 970 945 9536",
    "sg:postcode":"81601",
    "sg:province":"CO",
    "sg:tags":[
        "eating"
    ],
    "wof:name":"Hilltop Cafe",
    "wof:placetype":"venue"
},
  "geometry": {"coordinates":[-107.346318,39.564051],"type":"Point"}
}