{
  "type": "Feature",
  "properties": {
    "iso:country":"US",
    "sg:address":"1825 State Ave",
    "sg:city":"Alamosa",
    "sg:classifiers":[
        {
            "category":"Freight",
            "type":"Transportation"
        }
    ],
    "sg:phone":"+1 800 742 5877",
    "sg:postcode":"81101",
    "sg:province":"CO",
    "sg:tags":[
        "delivery",
        "parcel"
    ],
    "wof:name":"UPS",
    "wof:placetype":"venue"
},
  "geometry": {"coordinates":[-105.865557,37.453084],"type":"Point"}
}