{
  "type": "Feature",
  "properties": {
    "iso:country":"US",
    "sg:address":"659 Weston Rd",
    "sg:city":"Larkspur",
    "sg:classifiers":[
        {
            "category":"Manufacturing",
            "subcategory":"Glass & Minerals",
            "type":"Manufacturing & Wholesale Goods"
        }
    ],
    "sg:phone":"+1 303 681 2934",
    "sg:postcode":"80118",
    "sg:province":"CO",
    "sg:tags":[
        "tile",
        "ceramic",
        "mfg"
    ],
    "wof:name":"Larkspur Art Tile",
    "wof:placetype":"venue"
},
  "geometry": {"coordinates":[-104.896931,39.254955],"type":"Point"}
}