{
  "type": "Feature",
  "properties": {
    "addr:full":"2500 Arapahoe Ave Boulder CO 80302",
    "addr:housenumber":"2500",
    "addr:postcode":"80302",
    "addr:street":"Arapahoe Ave",
    "iso:country":"US",
    "sg:address":"2500 Arapahoe Ave",
    "sg:city":"Boulder",
    "sg:classifiers":[
        {
            "category":"Banks & Credit Unions",
            "subcategory":"Bank",
            "type":"Services"
        }
    ],
    "sg:phone":"+1 303 245 6620",
    "sg:postcode":"80302",
    "sg:province":"CO",
    "wof:name":"Bank One",
    "wof:placetype":"venue"
},
  "geometry": {"coordinates":[-105.259396,40.014479],"type":"Point"}
}