{
  "type": "Feature",
  "properties": {
    "addr:full":"3830 Barr Ct Boulder CO 80305",
    "addr:housenumber":"3830",
    "addr:postcode":"80305",
    "addr:street":"Barr Ct",
    "iso:country":"US",
    "sg:address":"3830 Barr Ct",
    "sg:city":"Boulder",
    "sg:classifiers":[
        {
            "category":"Shopping",
            "subcategory":"Catalog Store",
            "type":"Retail Goods"
        }
    ],
    "sg:phone":"+1 303 499 6870",
    "sg:postcode":"80305",
    "sg:province":"CO",
    "sg:tags":[
        "mail",
        "house"
    ],
    "wof:name":"Allan Keesling",
    "wof:placetype":"venue"
},
  "geometry": {"coordinates":[-105.249831,39.980921],"type":"Point"}
}