{
  "type": "Feature",
  "properties": {
    "iso:country":"US",
    "sg:address":"2660 Federal Blvd",
    "sg:city":"Denver",
    "sg:classifiers":[
        {
            "category":"Banks & Credit Unions",
            "subcategory":"Bank",
            "type":"Services"
        }
    ],
    "sg:phone":"+1 303 561 1000",
    "sg:postcode":"80211",
    "sg:province":"CO",
    "wof:name":"Firstbank S-Fed",
    "wof:placetype":"venue"
},
  "geometry": {"coordinates":[-105.024975,39.755578],"type":"Point"}
}