{
  "type": "Feature",
  "properties": {
    "addr:full":"17450 E 10th Ave Aurora CO 80011",
    "addr:housenumber":"17450",
    "addr:postcode":"80011",
    "addr:street":"E 10Th Ave",
    "iso:country":"US",
    "sg:address":"17450 E 10th Ave",
    "sg:city":"Aurora",
    "sg:classifiers":[
        {
            "category":"Building & Trades",
            "subcategory":"Construction",
            "type":"Services"
        }
    ],
    "sg:phone":"+1 303 364 7255",
    "sg:postcode":"80011",
    "sg:province":"CO",
    "sg:tags":[
        "concrete",
        "contractor"
    ],
    "wof:name":"Mc Clure Concrete",
    "wof:placetype":"venue"
},
  "geometry": {"coordinates":[-104.790227,39.732821],"type":"Point"}
}