{
  "type": "Feature",
  "properties": {
    "addr:full":"5105 Solar Ridge Dr Colorado Springs CO 80917",
    "addr:housenumber":"5105",
    "addr:postcode":"80917",
    "addr:street":"Solar Ridge Dr",
    "iso:country":"US",
    "sg:address":"5105 Solar Ridge Dr",
    "sg:city":"Colorado Springs",
    "sg:classifiers":[
        {
            "category":"Building & Trades",
            "subcategory":"Construction",
            "type":"Services"
        }
    ],
    "sg:phone":"+1 719 550 9389",
    "sg:postcode":"80917",
    "sg:province":"CO",
    "sg:tags":[
        "shed",
        "storage"
    ],
    "wof:name":"Adsi Storage",
    "wof:placetype":"venue"
},
  "geometry": {"coordinates":[-104.730769,38.89605],"type":"Point"}
}