{
  "type": "Feature",
  "properties": {
    "addr:full":"1529 W 31st St Loveland CO 80538",
    "addr:housenumber":"1529",
    "addr:postcode":"80538",
    "addr:street":"W 31St St",
    "iso:country":"US",
    "sg:address":"1529 W 31st St",
    "sg:city":"Loveland",
    "sg:classifiers":[
        {
            "category":"Home & Garden",
            "subcategory":"Furniture",
            "type":"Retail Goods"
        }
    ],
    "sg:phone":"+1 970 663 2552",
    "sg:postcode":"80538",
    "sg:province":"CO",
    "sg:tags":[
        "cabinet"
    ],
    "wof:name":"Kitchen Tune-Up",
    "wof:placetype":"venue"
},
  "geometry": {"coordinates":[-105.10034899999999,40.422997],"type":"Point"}
}