{
  "type": "Feature",
  "properties": {
    "iso:country":"US",
    "sg:address":"10970 S Parker Rd Unit A5",
    "sg:city":"Parker",
    "sg:phone":"+1 303 805 2551",
    "sg:postcode":"80134",
    "sg:province":"CO",
    "wof:name":"Cotton Kloset",
    "wof:placetype":"venue"
},
  "geometry": {"coordinates":[-104.764619,39.516476],"type":"Point"}
}