{
  "type": "Feature",
  "properties": {
    "addr:full":"3675 Jeannine Dr Colorado Springs CO 80917",
    "addr:postcode":"3675;80917",
    "addr:street":"Jeannine Dr",
    "iso:country":"US",
    "sg:address":"3675 Jeannine Dr",
    "sg:city":"Colorado Springs",
    "sg:classifiers":[
        {
            "category":"Home & Garden",
            "subcategory":"Household Appliances",
            "type":"Retail Goods"
        }
    ],
    "sg:phone":"+1 719 597 8659",
    "sg:postcode":"80917",
    "sg:province":"CO",
    "sg:tags":[
        "cleaners",
        "vacuum"
    ],
    "wof:name":"Rainbow Vacuum Inc",
    "wof:placetype":"venue"
},
  "geometry": {"coordinates":[-104.75832699999999,38.885601],"type":"Point"}
}