{
  "type": "Feature",
  "properties": {
    "addr:full":"1475 36th St Denver CO 80205",
    "addr:housenumber":"1475",
    "addr:postcode":"80205",
    "addr:street":"36Th St",
    "iso:country":"US",
    "sg:address":"1475 36th St",
    "sg:city":"Denver",
    "sg:classifiers":[
        {
            "category":"Manufacturing",
            "subcategory":"Metals",
            "type":"Manufacturing & Wholesale Goods"
        }
    ],
    "sg:phone":"+1 303 297 2195",
    "sg:postcode":"80205",
    "sg:province":"CO",
    "sg:tags":[
        "steel",
        "fabricator"
    ],
    "wof:name":"Rail Shop Inc",
    "wof:placetype":"venue"
},
  "geometry": {"coordinates":[-104.974503,39.768841],"type":"Point"}
}