{
  "type": "Feature",
  "properties": {
    "iso:country":"US",
    "sg:address":"3084 Ff 70 Dr",
    "sg:city":"Somerset",
    "sg:classifiers":[
        {
            "category":"Farming",
            "subcategory":"Livestock Farm",
            "type":"Manufacturing & Wholesale Goods"
        }
    ],
    "sg:phone":"+1 970 929 5385",
    "sg:postcode":"81434",
    "sg:province":"CO",
    "sg:tags":[
        "beef",
        "feedlot",
        "cattle"
    ],
    "wof:name":"Flying M Ranch",
    "wof:placetype":"venue"
},
  "geometry": {"coordinates":[-107.55762300000001,39.125679],"type":"Point"}
}