{
  "type": "Feature",
  "properties": {
    "addr:full":"8601 Turnpike Dr Westminster CO 80031",
    "addr:housenumber":"8601",
    "addr:postcode":"80031",
    "addr:street":"Turnpike Dr",
    "iso:country":"US",
    "sg:address":"8601 Turnpike Dr",
    "sg:city":"Westminster",
    "sg:classifiers":[
        {
            "category":"Manufacturing",
            "subcategory":"Printing",
            "type":"Manufacturing & Wholesale Goods"
        }
    ],
    "sg:phone":"+1 303 650 1795",
    "sg:postcode":"80031",
    "sg:province":"CO",
    "sg:tags":[
        "periodical"
    ],
    "wof:name":"Mile High Sports Magazine",
    "wof:placetype":"venue"
},
  "geometry": {"coordinates":[-105.05122,39.85191],"type":"Point"}
}