{
  "type": "Feature",
  "properties": {
    "iso:country":"US",
    "sg:address":"2220 S Peoria St",
    "sg:city":"Aurora",
    "sg:classifiers":[
        {
            "category":"Food & Beverages",
            "subcategory":"Groceries & Convenience Stores",
            "type":"Retail Goods"
        }
    ],
    "sg:phone":"+1 303 671 5940",
    "sg:postcode":"80014",
    "sg:province":"CO",
    "sg:tags":[
        "drinking"
    ],
    "wof:name":"7-Eleven",
    "wof:placetype":"venue"
},
  "geometry": {"coordinates":[-104.847341,39.674966],"type":"Point"}
}