{
  "type": "Feature",
  "properties": {
    "addr:full":"1168 Wintergate Cir Castle Rock CO 80104",
    "addr:housenumber":"1168",
    "addr:postcode":"80104",
    "addr:street":"Wintergate Cir",
    "iso:country":"US",
    "sg:address":"1168 Wintergate Cir",
    "sg:city":"Castle Rock",
    "sg:classifiers":[
        {
            "category":"Building & Trades",
            "subcategory":"Construction",
            "type":"Services"
        }
    ],
    "sg:phone":"+1 303 660 3675",
    "sg:postcode":"80104",
    "sg:province":"CO",
    "sg:tags":[
        "home",
        "builder"
    ],
    "wof:name":"Platinum Homes LLC",
    "wof:placetype":"venue"
},
  "geometry": {"coordinates":[-104.86315399999999,39.309489],"type":"Point"}
}