{
  "type": "Feature",
  "properties": {
    "iso:country":"US",
    "sg:address":"165 S Union Blvd",
    "sg:city":"Lakewood",
    "sg:classifiers":[
        {
            "category":"Professional",
            "subcategory":"Lawyer & Legal Services",
            "type":"Services"
        }
    ],
    "sg:phone":"+1 303 980 1805",
    "sg:postcode":"80228",
    "sg:province":"CO",
    "sg:tags":[
        "attorney"
    ],
    "wof:name":"Jack E Ebel Law Office",
    "wof:placetype":"venue"
},
  "geometry": {"coordinates":[-105.13333299999999,39.714661],"type":"Point"}
}