{
  "type": "Feature",
  "properties": {
    "addr:full":"9676 E Alameda Ave Denver CO 80247",
    "addr:housenumber":"9676",
    "addr:postcode":"80247",
    "addr:street":"E Alameda Ave",
    "iso:country":"US",
    "sg:address":"9676 E Alameda Ave",
    "sg:city":"Denver",
    "sg:classifiers":[
        {
            "category":"Personal",
            "subcategory":"Beauty Salon",
            "type":"Services"
        }
    ],
    "sg:phone":"+1 303 366 3574",
    "sg:postcode":"80247",
    "sg:province":"CO",
    "sg:tags":[
        "shop"
    ],
    "wof:name":"Windsor World Beauty Salon",
    "wof:placetype":"venue"
},
  "geometry": {"coordinates":[-104.877696,39.708281],"type":"Point"}
}