{
  "type": "Feature",
  "properties": {
    "addr:full":"2831 Ponderosa Rd Franktown CO 80116",
    "addr:housenumber":"2831",
    "addr:postcode":"80116",
    "addr:street":"Ponderosa Rd",
    "iso:country":"US",
    "sg:address":"2831 Ponderosa Rd",
    "sg:city":"Franktown",
    "sg:classifiers":[
        {
            "category":"Retail",
            "subcategory":"Animal Services",
            "type":"Services"
        },
        {
            "category":"Farming",
            "subcategory":"Farm & Veterinary Services",
            "type":"Manufacturing & Wholesale Goods"
        }
    ],
    "sg:phone":"+1 303 840 8261",
    "sg:postcode":"80116",
    "sg:province":"CO",
    "sg:tags":[
        "breeder",
        "livestock"
    ],
    "sg:website":"www.bayoucreek.com",
    "wof:name":"Bayou Creek Creations LLC",
    "wof:placetype":"venue"
},
  "geometry": {"coordinates":[-104.66856,39.403872],"type":"Point"}
}