{
  "type": "Feature",
  "properties": {
    "iso:country":"US",
    "sg:address":"4359 Wildflower Ct",
    "sg:city":"Evergreen",
    "sg:classifiers":[
        {
            "category":"Banks & Credit Unions",
            "subcategory":"Financial Services",
            "type":"Services"
        }
    ],
    "sg:phone":"+1 303 674 6396",
    "sg:postcode":"80439",
    "sg:province":"CO",
    "sg:tags":[
        "trust",
        "management"
    ],
    "wof:name":"Troutdale LLC",
    "wof:placetype":"venue"
},
  "geometry": {"coordinates":[-105.348578,39.640118],"type":"Point"}
}