{
  "type": "Feature",
  "properties": {
    "addr:full":"1145 S. Broadway Denver CO 80210",
    "addr:housenumber":"1145",
    "addr:postcode":"80210",
    "addr:street":"S. Broadway",
    "iso:country":"US",
    "sg:address":"1145 S. Broadway",
    "sg:city":"Denver",
    "sg:classifiers":[
        {
            "category":"Real Estate",
            "subcategory":"Real Estate Operator",
            "type":"Services"
        }
    ],
    "sg:phone":"+1 303 825 3010",
    "sg:postcode":"80210",
    "sg:province":"CO",
    "sg:tags":[
        "apartment"
    ],
    "sg:website":"www.alexanbroadwaystation.com/",
    "wof:name":"Alexan Broadway Station",
    "wof:placetype":"venue"
},
  "geometry": {"coordinates":[-104.98745099999999,39.695876],"type":"Point"}
}