{
  "type": "Feature",
  "properties": {
    "addr:full":"3731 S Rosemary Way Denver CO 80237",
    "addr:housenumber":"3731",
    "addr:postcode":"80237",
    "addr:street":"S Rosemary Way",
    "iso:country":"US",
    "sg:address":"3731 S Rosemary Way",
    "sg:city":"Denver",
    "sg:classifiers":[
        {
            "category":"Restaurant",
            "type":"Food & Drink"
        }
    ],
    "sg:phone":"+1 720 488 3016",
    "sg:postcode":"80237",
    "sg:province":"CO",
    "sg:tags":[
        "eating"
    ],
    "wof:name":"Fireplace & Grill",
    "wof:placetype":"venue"
},
  "geometry": {"coordinates":[-104.89943599999999,39.648453],"type":"Point"}
}