{
  "type": "Feature",
  "properties": {
    "iso:country":"US",
    "sg:address":"200 W 1st St",
    "sg:city":"Pueblo",
    "sg:classifiers":[
        {
            "category":"Personal",
            "type":"Services"
        }
    ],
    "sg:phone":"+1 719 542 6620",
    "sg:postcode":"81003",
    "sg:province":"CO",
    "sg:tags":[
        "credit",
        "debt",
        "counseling"
    ],
    "wof:name":"Consumer Credit Counseling Svc",
    "wof:placetype":"venue"
},
  "geometry": {"coordinates":[-104.60897199999999,38.267876],"type":"Point"}
}