{
  "type": "Feature",
  "properties": {
    "addr:full":"8465 W Colfax Ave Lakewood CO 80215",
    "addr:housenumber":"8465",
    "addr:postcode":"80215",
    "addr:street":"W Colfax Ave",
    "iso:country":"US",
    "sg:address":"8465 W Colfax Ave",
    "sg:city":"Lakewood",
    "sg:classifiers":[
        {
            "category":"Shopping",
            "type":"Retail Goods"
        }
    ],
    "sg:phone":"+1 303 231 0886",
    "sg:postcode":"80215",
    "sg:province":"CO",
    "sg:tags":[
        "candle"
    ],
    "wof:name":"Candle Cupboard",
    "wof:placetype":"venue"
},
  "geometry": {"coordinates":[-105.09218300000001,39.740332],"type":"Point"}
}