{
  "type": "Feature",
  "properties": {
    "addr:full":"1717 Lincoln Ave Steamboat Spgs CO 80487",
    "addr:housenumber":"1717",
    "addr:postcode":"80487",
    "addr:street":"Lincoln Ave;Spgs",
    "iso:country":"US",
    "sg:address":"1717 Lincoln Ave",
    "sg:city":"Steamboat Spgs",
    "sg:classifiers":[
        {
            "category":"Building & Trades",
            "subcategory":"Equipment Rental",
            "type":"Services"
        }
    ],
    "sg:phone":"+1 970 879 2468",
    "sg:postcode":"80487",
    "sg:province":"CO",
    "sg:tags":[
        "yard"
    ],
    "wof:name":"Steamboat Rentals",
    "wof:placetype":"venue"
},
  "geometry": {"coordinates":[-106.84888599999999,40.49395],"type":"Point"}
}