{
  "type": "Feature",
  "properties": {
    "addr:full":"3350 30th St Boulder CO 80301",
    "addr:housenumber":"3350",
    "addr:postcode":"80301",
    "addr:street":"30Th St",
    "iso:country":"US",
    "sg:address":"3350 30th St",
    "sg:city":"Boulder",
    "sg:classifiers":[
        {
            "category":"Health Services",
            "subcategory":"Nursing And Care Facility",
            "type":"Services"
        }
    ],
    "sg:phone":"+1 303 444 0200",
    "sg:postcode":"80301",
    "sg:province":"CO",
    "sg:tags":[
        "home",
        "retirement",
        "community"
    ],
    "wof:name":"Alterra Villas",
    "wof:placetype":"venue"
},
  "geometry": {"coordinates":[-105.253691,40.035002],"type":"Point"}
}