{
  "type": "Feature",
  "properties": {
    "addr:full":"1640 E Evans Ave Denver CO 80210",
    "addr:housenumber":"1640",
    "addr:postcode":"80210",
    "addr:street":"E Evans Ave",
    "iso:country":"US",
    "sg:address":"1640 E Evans Ave",
    "sg:city":"Denver",
    "sg:classifiers":[
        {
            "category":"Health Services",
            "subcategory":"Clinic",
            "type":"Services"
        }
    ],
    "sg:phone":"+1 303 975 6485",
    "sg:postcode":"80210",
    "sg:province":"CO",
    "sg:tags":[
        "cannabis"
    ],
    "sg:website":"www.citi-med.com",
    "wof:name":"Citi-Med",
    "wof:placetype":"venue"
},
  "geometry": {"coordinates":[-104.96783600000001,39.678484],"type":"Point"}
}