{
  "type": "Feature",
  "properties": {
    "iso:country":"US",
    "sg:address":"211 Main St",
    "sg:city":"Breckenridge",
    "sg:classifiers":[
        {
            "category":"Retail",
            "subcategory":"Repair Shop",
            "type":"Services"
        }
    ],
    "sg:phone":"+1 970 453 7039",
    "sg:postcode":"80424",
    "sg:province":"CO",
    "sg:tags":[
        "equipment",
        "skiing"
    ],
    "wof:name":"Breckenridge Ski Shop",
    "wof:placetype":"venue"
},
  "geometry": {"coordinates":[-106.04621,39.487134],"type":"Point"}
}