{
  "type": "Feature",
  "properties": {
    "iso:country":"US",
    "sg:address":"210 Largo Ave",
    "sg:city":"Palmer Lake",
    "sg:classifiers":[
        {
            "category":"Home & Garden",
            "subcategory":"Building Materials",
            "type":"Retail Goods"
        }
    ],
    "sg:phone":"+1 719 488 5599",
    "sg:postcode":"80133",
    "sg:province":"CO",
    "sg:tags":[
        "glass",
        "window",
        "plate"
    ],
    "wof:name":"Superior Auto Glass",
    "wof:placetype":"venue"
},
  "geometry": {"coordinates":[-104.919476,39.115872],"type":"Point"}
}