{
  "type": "Feature",
  "properties": {
    "iso:country":"US",
    "sg:address":"951 Claremont Pl",
    "sg:city":"Loveland",
    "sg:classifiers":[
        {
            "category":"Building & Trades",
            "subcategory":"Construction",
            "type":"Services"
        }
    ],
    "sg:phone":"+1 970 635 2523",
    "sg:postcode":"80538",
    "sg:province":"CO",
    "sg:tags":[
        "house"
    ],
    "wof:name":"Weberbilt Construction Service",
    "wof:placetype":"venue"
},
  "geometry": {"coordinates":[-105.089686,40.436004],"type":"Point"}
}