{
  "type": "Feature",
  "properties": {
    "addr:full":"2121 Mesa Dr Boulder CO 80304",
    "addr:housenumber":"2121",
    "addr:postcode":"80304",
    "addr:street":"Mesa Dr",
    "iso:country":"US",
    "sg:address":"2121 Mesa Dr",
    "sg:city":"Boulder",
    "sg:classifiers":[
        {
            "category":"Health Services",
            "subcategory":"Nursing And Care Facility",
            "type":"Services"
        }
    ],
    "sg:phone":"+1 303 442 4037",
    "sg:postcode":"80304",
    "sg:province":"CO",
    "sg:tags":[
        "home",
        "convalescent"
    ],
    "wof:name":"Terrace Heights Care Ctr",
    "wof:placetype":"venue"
},
  "geometry": {"coordinates":[-105.269164,40.025049],"type":"Point"}
}