{
  "type": "Feature",
  "properties": {
    "iso:country":"US",
    "sg:address":"4945 Montebello Dr",
    "sg:city":"Colorado Springs",
    "sg:classifiers":[
        {
            "category":"Wholesale",
            "subcategory":"Non-durable Goods",
            "type":"Manufacturing & Wholesale Goods"
        }
    ],
    "sg:phone":"+1 719 266 5700",
    "sg:postcode":"80918",
    "sg:province":"CO",
    "sg:tags":[
        "business"
    ],
    "wof:name":"EZ Advertising",
    "wof:placetype":"venue"
},
  "geometry": {"coordinates":[-104.75446599999999,38.90198],"type":"Point"}
}