{
  "type": "Feature",
  "properties": {
    "addr:full":"5245 E 69th Ave Commerce City CO 80022",
    "addr:housenumber":"5245",
    "addr:postcode":"80022",
    "addr:street":"E 69Th Ave",
    "iso:country":"US",
    "sg:address":"5245 E 69th Ave",
    "sg:city":"Commerce City",
    "sg:classifiers":[
        {
            "category":"Utilities",
            "subcategory":"Refuse",
            "type":"Services"
        }
    ],
    "sg:phone":"+1 303 329 6301",
    "sg:postcode":"80022",
    "sg:province":"CO",
    "sg:tags":[
        "disposal",
        "waste"
    ],
    "wof:name":"Consolidated Construction Svc",
    "wof:placetype":"venue"
},
  "geometry": {"coordinates":[-104.926149,39.82196],"type":"Point"}
}