{
  "type": "Feature",
  "properties": {
    "addr:full":"20 Crestline Dr Colorado Springs CO 80907",
    "addr:housenumber":"20",
    "addr:postcode":"80907",
    "addr:street":"Crestline Dr",
    "iso:country":"US",
    "sg:address":"20 Crestline Dr",
    "sg:city":"Colorado Springs",
    "sg:classifiers":[
        {
            "category":"Organizations",
            "subcategory":"Religious Organization",
            "type":"Services"
        }
    ],
    "sg:phone":"+1 719 550 9710",
    "sg:postcode":"80907",
    "sg:province":"CO",
    "sg:tags":[
        "church"
    ],
    "wof:name":"Jehovah's Witness",
    "wof:placetype":"venue"
},
  "geometry": {"coordinates":[-104.823531,38.899226],"type":"Point"}
}