{
  "type": "Feature",
  "properties": {
    "iso:country":"US",
    "sg:address":"1261 E 3rd Ave",
    "sg:city":"Durango",
    "sg:classifiers":[
        {
            "category":"Retail",
            "subcategory":"Funeral Services",
            "type":"Services"
        }
    ],
    "sg:phone":"+1 970 247 2312",
    "sg:postcode":"81301",
    "sg:province":"CO",
    "sg:tags":[
        "director"
    ],
    "wof:name":"Hood Mortuary",
    "wof:placetype":"venue"
},
  "geometry": {"coordinates":[-107.87678,37.276467],"type":"Point"}
}