{
  "type": "Feature",
  "properties": {
    "addr:full":"101 W Plum St Trinidad CO 81082",
    "addr:housenumber":"101",
    "addr:postcode":"81082",
    "addr:street":"W Plum St",
    "iso:country":"US",
    "sg:address":"101 W Plum St",
    "sg:city":"Trinidad",
    "sg:classifiers":[
        {
            "category":"Shopping",
            "subcategory":"Computers & Home Electronics",
            "type":"Retail Goods"
        }
    ],
    "sg:phone":"+1 719 846 0999",
    "sg:postcode":"81082",
    "sg:province":"CO",
    "sg:tags":[
        "equipment",
        "satellite",
        "system"
    ],
    "wof:name":"Digital Entertainment Store",
    "wof:placetype":"venue"
},
  "geometry": {"coordinates":[-104.506536,37.170395],"type":"Point"}
}