{
  "type": "Feature",
  "properties": {
    "iso:country":"US",
    "sg:address":"1415 Grand Ave",
    "sg:city":"Norwood",
    "sg:classifiers":[
        {
            "category":"Travel",
            "subcategory":"Hotels & Motels",
            "type":"Entertainment"
        }
    ],
    "sg:phone":"+1 970 327 4982",
    "sg:postcode":"81423",
    "sg:province":"CO",
    "wof:name":"NORWOOD Inn",
    "wof:placetype":"venue"
},
  "geometry": {"coordinates":[-108.291973,38.130741],"type":"Point"}
}