{
  "type": "Feature",
  "properties": {
    "addr:full":"130 Co Rd 332 Rifle CO 81650",
    "addr:housenumber":"130",
    "addr:postcode":"81650",
    "addr:street":"Co Rd 332",
    "iso:country":"US",
    "sg:address":"130 Co Rd 332",
    "sg:city":"Rifle",
    "sg:classifiers":[
        {
            "category":"Retail",
            "subcategory":"Repair Shop",
            "type":"Services"
        }
    ],
    "sg:phone":"+1 970 625 2203",
    "sg:postcode":"81650",
    "sg:province":"CO",
    "sg:tags":[
        "welding"
    ],
    "wof:name":"Renner Iron Works",
    "wof:placetype":"venue"
},
  "geometry": {"coordinates":[-107.777657,39.518473],"type":"Point"}
}