{
  "type": "Feature",
  "properties": {
    "iso:country":"US",
    "sg:address":"31623 Ponderosa Way",
    "sg:city":"Evergreen",
    "sg:classifiers":[
        {
            "category":"Shopping",
            "type":"Retail Goods"
        },
        {
            "category":"Manufacturing",
            "subcategory":"Lumber",
            "type":"Manufacturing & Wholesale Goods"
        }
    ],
    "sg:phone":"+1 303 679 7990",
    "sg:postcode":"80439",
    "sg:province":"CO",
    "sg:tags":[
        "hardwood",
        "mill",
        "wood",
        "carving"
    ],
    "wof:name":"Jay Hawk Woodcarving",
    "wof:placetype":"venue"
},
  "geometry": {"coordinates":[-105.364666,39.584746],"type":"Point"}
}