{
  "type": "Feature",
  "properties": {
    "iso:country":"US",
    "sg:address":"3068 E 3rd Ave",
    "sg:city":"Durango",
    "sg:classifiers":[
        {
            "category":"Banks & Credit Unions",
            "subcategory":"Financial Services",
            "type":"Services"
        }
    ],
    "sg:phone":"+1 970 375 6286",
    "sg:postcode":"81301",
    "sg:province":"CO",
    "sg:tags":[
        "investor"
    ],
    "wof:name":"Summit Investment Properties L",
    "wof:placetype":"venue"
},
  "geometry": {"coordinates":[-107.869128,37.297286],"type":"Point"}
}