{
  "type": "Feature",
  "properties": {
    "addr:full":"1700 Park St Castle Rock CO 80109",
    "addr:housenumber":"1700",
    "addr:postcode":"80109",
    "addr:street":"Park St",
    "iso:country":"US",
    "sg:address":"1700 Park St",
    "sg:city":"Castle Rock",
    "sg:classifiers":[
        {
            "category":"Building & Trades",
            "subcategory":"Equipment Rental",
            "type":"Services"
        },
        {
            "category":"Building & Trades",
            "subcategory":"Construction",
            "type":"Services"
        }
    ],
    "sg:phone":"+1 303 688 5254",
    "sg:postcode":"80109",
    "sg:province":"CO",
    "sg:tags":[
        "heavy",
        "excavating",
        "contractor",
        "lease"
    ],
    "wof:name":"H & H Machinery LLC",
    "wof:placetype":"venue"
},
  "geometry": {"coordinates":[-104.86855799999999,39.385831],"type":"Point"}
}