{
  "type": "Feature",
  "properties": {
    "addr:full":"429 Hwy 92 Crawford CO 81415",
    "addr:housenumber":"429",
    "addr:postcode":"81415",
    "addr:street":"Hwy 92",
    "iso:country":"US",
    "sg:address":"429 Hwy 92",
    "sg:city":"Crawford",
    "sg:classifiers":[
        {
            "category":"Education",
            "subcategory":"Library",
            "type":"Public Place"
        }
    ],
    "sg:phone":"+1 970 921 3500",
    "sg:postcode":"81415",
    "sg:province":"CO",
    "wof:name":"Crawford Community Library",
    "wof:placetype":"venue"
},
  "geometry": {"coordinates":[-107.611993,38.703739],"type":"Point"}
}