{
  "type": "Feature",
  "properties": {
    "iso:country":"US",
    "sg:address":"2530 Brenton Dr",
    "sg:city":"Colorado Springs",
    "sg:classifiers":[
        {
            "category":"Utilities",
            "subcategory":"Telephone",
            "type":"Services"
        }
    ],
    "sg:phone":"+1 719 598 0892",
    "sg:postcode":"80918",
    "sg:province":"CO",
    "sg:tags":[
        "communications"
    ],
    "wof:name":"Hatfield Enterprises",
    "wof:placetype":"venue"
},
  "geometry": {"coordinates":[-104.781268,38.916186],"type":"Point"}
}