{
  "type": "Feature",
  "properties": {
    "addr:full":"109 E Fontanero St Colorado Springs CO 80907",
    "addr:housenumber":"109",
    "addr:postcode":"80907",
    "addr:street":"E Fontanero St",
    "iso:country":"US",
    "sg:address":"109 E Fontanero St",
    "sg:city":"Colorado Springs",
    "sg:classifiers":[
        {
            "category":"Real Estate",
            "subcategory":"Real Estate Agent",
            "type":"Services"
        }
    ],
    "sg:phone":"+1 719 634 3785",
    "sg:postcode":"80907",
    "sg:province":"CO",
    "sg:tags":[
        "condo",
        "manager",
        "broker"
    ],
    "wof:name":"Haley Realty Inc",
    "wof:placetype":"venue"
},
  "geometry": {"coordinates":[-104.821355,38.860423],"type":"Point"}
}