{
  "type": "Feature",
  "properties": {
    "iso:country":"US",
    "sg:address":"282 2nd St",
    "sg:city":"Fort Lupton",
    "sg:classifiers":[
        {
            "category":"Professional",
            "subcategory":"Engineering",
            "type":"Services"
        }
    ],
    "sg:phone":"+1 303 857 1664",
    "sg:postcode":"80621",
    "sg:province":"CO",
    "sg:tags":[
        "engineer"
    ],
    "wof:name":"SDG Engineering",
    "wof:placetype":"venue"
},
  "geometry": {"coordinates":[-104.81784500000001,40.081238],"type":"Point"}
}