{
  "type": "Feature",
  "properties": {
    "addr:full":"228 S Pine Dr Bailey CO 80421",
    "addr:housenumber":"228",
    "addr:postcode":"80421",
    "addr:street":"S Pine Dr",
    "iso:country":"US",
    "sg:address":"228 S Pine Dr",
    "sg:city":"Bailey",
    "sg:classifiers":[
        {
            "category":"Organizations",
            "subcategory":"Non-profit Organization",
            "type":"Services"
        }
    ],
    "sg:phone":"+1 303 838 5647",
    "sg:postcode":"80421",
    "sg:province":"CO",
    "wof:name":"Deer Creek Christian Camp",
    "wof:placetype":"venue"
},
  "geometry": {"coordinates":[-105.47614900000001,39.44691],"type":"Point"}
}