{
  "type": "Feature",
  "properties": {
    "iso:country":"US",
    "sg:address":"4455 Mark Dabling Blvd",
    "sg:city":"Colorado Springs",
    "sg:classifiers":[
        {
            "category":"Restaurant",
            "type":"Food & Drink"
        }
    ],
    "sg:phone":"+1 719 635 5769",
    "sg:postcode":"80907",
    "sg:province":"CO",
    "sg:tags":[
        "eating"
    ],
    "wof:name":"Ritas Restaurants",
    "wof:placetype":"venue"
},
  "geometry": {"coordinates":[-104.82556099999999,38.892579],"type":"Point"}
}