{
  "type": "Feature",
  "properties": {
    "addr:full":"656 Galapago St Denver CO 80204",
    "addr:housenumber":"656",
    "addr:postcode":"80204",
    "addr:street":"Galapago St",
    "iso:country":"US",
    "sg:address":"656 Galapago St",
    "sg:city":"Denver",
    "sg:classifiers":[
        {
            "category":"Professional",
            "subcategory":"Management & Consulting",
            "type":"Services"
        }
    ],
    "sg:phone":"+1 303 623 5178",
    "sg:postcode":"80204",
    "sg:province":"CO",
    "sg:tags":[
        "communications",
        "consultant"
    ],
    "wof:name":"Transition Communications",
    "wof:placetype":"venue"
},
  "geometry": {"coordinates":[-104.996309,39.726386],"type":"Point"}
}