{
  "type": "Feature",
  "properties": {
    "iso:country":"US",
    "sg:address":"719 Wedge Dr",
    "sg:city":"Grand Junction",
    "sg:classifiers":[
        {
            "category":"Building & Trades",
            "subcategory":"Equipment Rental",
            "type":"Services"
        }
    ],
    "sg:phone":"+1 970 245 5187",
    "sg:postcode":"81506",
    "sg:province":"CO",
    "sg:tags":[
        "leasing"
    ],
    "wof:name":"Park Western Leasing Inc",
    "wof:placetype":"venue"
},
  "geometry": {"coordinates":[-108.551661,39.109286],"type":"Point"}
}