{
  "type": "Feature",
  "properties": {
    "iso:country":"US",
    "sg:address":"5620 W 2nd Ave",
    "sg:city":"Lakewood",
    "sg:classifiers":[
        {
            "category":"Building & Trades",
            "subcategory":"Construction",
            "type":"Services"
        }
    ],
    "sg:phone":"+1 303 947 2544",
    "sg:postcode":"80226",
    "sg:province":"CO",
    "sg:tags":[
        "handyman"
    ],
    "wof:name":"Du-N-A Handiman & Referral Svc",
    "wof:placetype":"venue"
},
  "geometry": {"coordinates":[-105.05958200000001,39.719826],"type":"Point"}
}