{
  "type": "Feature",
  "properties": {
    "addr:full":"1638 Park St Castle Rock CO 80109",
    "addr:housenumber":"1638",
    "addr:postcode":"80109",
    "addr:street":"Park St",
    "iso:country":"US",
    "sg:address":"1638 Park St",
    "sg:city":"Castle Rock",
    "sg:classifiers":[
        {
            "category":"Organizations",
            "subcategory":"Religious Organization",
            "type":"Services"
        }
    ],
    "sg:phone":"+1 303 688 4224",
    "sg:postcode":"80109",
    "sg:province":"CO",
    "wof:name":"Legacy Christian Academy",
    "wof:placetype":"venue"
},
  "geometry": {"coordinates":[-104.868173,39.385426],"type":"Point"}
}