{
  "type": "Feature",
  "properties": {
    "addr:full":"933 S Main St Longmont CO 80501",
    "addr:housenumber":"933",
    "addr:postcode":"80501",
    "addr:street":"S Main St",
    "iso:country":"US",
    "sg:address":"933 S Main St",
    "sg:city":"Longmont",
    "sg:classifiers":[
        {
            "category":"Restaurant",
            "type":"Food & Drink"
        }
    ],
    "sg:phone":"+1 303 772 7560",
    "sg:postcode":"80501",
    "sg:province":"CO",
    "sg:tags":[
        "eating"
    ],
    "wof:name":"Taco Johns",
    "wof:placetype":"venue"
},
  "geometry": {"coordinates":[-105.102583,40.149919],"type":"Point"}
}