{
  "type": "Feature",
  "properties": {
    "iso:country":"US",
    "sg:address":"6390 Gardenia St",
    "sg:city":"Arvada",
    "sg:classifiers":[
        {
            "category":"Banks & Credit Unions",
            "subcategory":"Investment Brokerage",
            "type":"Services"
        }
    ],
    "sg:phone":"+1 303 420 0577",
    "sg:postcode":"80004",
    "sg:province":"CO",
    "sg:tags":[
        "security"
    ],
    "wof:name":"Edward Jones 17307",
    "wof:placetype":"venue"
},
  "geometry": {"coordinates":[-105.160336,39.812104],"type":"Point"}
}