{
  "type": "Feature",
  "properties": {
    "addr:full":"799 S University Blvd Denver CO 80209",
    "addr:housenumber":"799",
    "addr:postcode":"80209",
    "addr:street":"S University Blvd",
    "iso:country":"US",
    "sg:address":"799 S University Blvd",
    "sg:city":"Denver",
    "sg:classifiers":[
        {
            "category":"Ice Cream",
            "type":"Food & Drink"
        }
    ],
    "sg:phone":"+1 303 777 0808",
    "sg:postcode":"80209",
    "sg:province":"CO",
    "sg:tags":[
        "frozen",
        "yogurt"
    ],
    "sg:website":"www.bonniebraeicecream.com/",
    "wof:name":"Bonnie Brae Ice Cream",
    "wof:placetype":"venue"
},
  "geometry": {"coordinates":[-104.959,39.702202],"type":"Point"}
}