{
  "type": "Feature",
  "properties": {
    "iso:country":"US",
    "sg:address":"7114 W Jefferson Ave",
    "sg:city":"Lakewood",
    "sg:classifiers":[
        {
            "category":"Health Services",
            "subcategory":"Health Practitioner",
            "type":"Services"
        }
    ],
    "sg:phone":"+1 303 716 3577",
    "sg:postcode":"80235",
    "sg:province":"CO",
    "sg:tags":[
        "psychotherapist"
    ],
    "wof:name":"Marguerite Harper",
    "wof:placetype":"venue"
},
  "geometry": {"coordinates":[-105.079031,39.649846],"type":"Point"}
}