{
  "type": "Feature",
  "properties": {
    "iso:country":"US",
    "sg:address":"1125 16th St Mall",
    "sg:city":"Denver",
    "sg:classifiers":[
        {
            "category":"Sports & Exercise",
            "subcategory":"Ice Rink",
            "type":"Entertainment"
        }
    ],
    "sg:postcode":"80265",
    "sg:province":"CO",
    "sg:tags":[
        "skating"
    ],
    "sg:website":"www.downtowndenver.com",
    "wof:name":"Southwest Rink",
    "wof:placetype":"venue"
},
  "geometry": {"coordinates":[-104.99589400000001,39.748059],"type":"Point"}
}