{
  "type": "Feature",
  "properties": {
    "iso:country":"US",
    "sg:address":"9832 Amber Rock Dr",
    "sg:city":"Parker",
    "sg:classifiers":[
        {
            "category":"Building & Trades",
            "subcategory":"Construction",
            "type":"Services"
        }
    ],
    "sg:phone":"+1 303 840 1154",
    "sg:postcode":"80134",
    "sg:province":"CO",
    "sg:tags":[
        "solid",
        "surfacing"
    ],
    "wof:name":"Cooks Countertops",
    "wof:placetype":"venue"
},
  "geometry": {"coordinates":[-104.801721,39.539309],"type":"Point"}
}