{
  "type": "Feature",
  "properties": {
    "iso:country":"US",
    "sg:address":"13462 Shiloh Dr",
    "sg:city":"Conifer",
    "sg:classifiers":[
        {
            "category":"Freight",
            "type":"Transportation"
        }
    ],
    "sg:phone":"+1 303 816 2223",
    "sg:postcode":"80433",
    "sg:province":"CO",
    "sg:tags":[
        "operator",
        "local",
        "trucking"
    ],
    "wof:name":"Champagne Movers",
    "wof:placetype":"venue"
},
  "geometry": {"coordinates":[-105.287333,39.469788],"type":"Point"}
}