{
  "type": "Feature",
  "properties": {
    "iso:country":"US",
    "sg:address":"710 Kipling St",
    "sg:city":"Lakewood",
    "sg:classifiers":[
        {
            "category":"Insurance",
            "subcategory":"Insurance Agent",
            "type":"Services"
        },
        {
            "category":"Insurance",
            "subcategory":"Hazard Insurance",
            "type":"Services"
        },
        {
            "category":"Insurance",
            "subcategory":"Title Insurance",
            "type":"Services"
        },
        {
            "category":"Insurance",
            "subcategory":"Life Insurance",
            "type":"Services"
        }
    ],
    "sg:phone":"+1 303 238 4489",
    "sg:postcode":"80215",
    "sg:province":"CO",
    "sg:tags":[
        "business",
        "auto",
        "commercial",
        "homeowner",
        "motorcycle",
        "renter"
    ],
    "wof:name":"Allstate Insurance Company - Chad Thielen",
    "wof:placetype":"venue"
},
  "geometry": {"coordinates":[-105.109698,39.728293],"type":"Point"}
}