{
  "type": "Feature",
  "properties": {
    "addr:full":"7710 Iowa Gulch Rd Morrison CO 80465",
    "addr:housenumber":"7710",
    "addr:postcode":"80465",
    "addr:street":"Iowa Gulch Rd",
    "iso:country":"US",
    "sg:address":"7710 Iowa Gulch Rd",
    "sg:city":"Morrison",
    "sg:classifiers":[
        {
            "category":"Building & Trades",
            "subcategory":"Construction",
            "type":"Services"
        }
    ],
    "sg:phone":"+1 303 697 3212",
    "sg:postcode":"80465",
    "sg:province":"CO",
    "sg:tags":[
        "house"
    ],
    "wof:name":"Simpson Construction Inc",
    "wof:placetype":"venue"
},
  "geometry": {"coordinates":[-105.23594300000001,39.572502],"type":"Point"}
}