{
  "type": "Feature",
  "properties": {
    "iso:country":"US",
    "sg:address":"880 Happy Canyon Road",
    "sg:city":"Castle Rock",
    "sg:classifiers":[
        {
            "category":"Health Services",
            "subcategory":"Health Practitioner",
            "type":"Services"
        }
    ],
    "sg:phone":"+1 720 733 3655",
    "sg:postcode":"80108",
    "sg:province":"CO",
    "sg:tags":[
        "therapy",
        "physical"
    ],
    "wof:name":"Advanced Physical & Sports Therapy",
    "wof:placetype":"venue"
},
  "geometry": {"coordinates":[-104.902351,39.427723],"type":"Point"}
}