{
  "type": "Feature",
  "properties": {
    "addr:full":"1030 13th St Boulder CO 80302",
    "addr:housenumber":"1030",
    "addr:postcode":"80302",
    "addr:street":"13Th St",
    "iso:country":"US",
    "sg:address":"1030 13th St",
    "sg:city":"Boulder",
    "sg:classifiers":[
        {
            "category":"Professional",
            "subcategory":"Management & Consulting",
            "type":"Services"
        }
    ],
    "sg:phone":"+1 303 449 4204",
    "sg:postcode":"80302",
    "sg:province":"CO",
    "sg:tags":[
        "consultant",
        "educational"
    ],
    "wof:name":"Learning For Living",
    "wof:placetype":"venue"
},
  "geometry": {"coordinates":[-105.276123,40.006737],"type":"Point"}
}