{
  "type": "Feature",
  "properties": {
    "addr:full":"979 Valley Rd Carbondale CO 81623",
    "addr:housenumber":"979",
    "addr:postcode":"81623",
    "addr:street":"Valley Rd",
    "iso:country":"US",
    "sg:address":"979 Valley Rd",
    "sg:city":"Carbondale",
    "sg:classifiers":[
        {
            "category":"Building & Trades",
            "subcategory":"Construction",
            "type":"Services"
        }
    ],
    "sg:phone":"+1 970 963 3915",
    "sg:postcode":"81623",
    "sg:province":"CO",
    "sg:tags":[
        "hanging",
        "contractor"
    ],
    "wof:name":"Volckhausen Painting Inc",
    "wof:placetype":"venue"
},
  "geometry": {"coordinates":[-107.105469,39.395009],"type":"Point"}
}