{
  "type": "Feature",
  "properties": {
    "iso:country":"US",
    "sg:address":"1425 N 5th St",
    "sg:city":"Grand Junction",
    "sg:classifiers":[
        {
            "category":"Social Services",
            "type":"Services"
        }
    ],
    "sg:phone":"+1 970 245 9791",
    "sg:postcode":"81501",
    "sg:province":"CO",
    "sg:tags":[
        "agency",
        "adoption"
    ],
    "wof:name":"Adoption Options",
    "wof:placetype":"venue"
},
  "geometry": {"coordinates":[-108.564548,39.080581],"type":"Point"}
}