{
  "type": "Feature",
  "properties": {
    "iso:country":"US",
    "sg:address":"565 E 70th Ave Unit 7W",
    "sg:city":"Denver",
    "sg:classifiers":[
        {
            "category":"Manufacturing",
            "subcategory":"Motor Vehicles & Parts",
            "type":"Manufacturing & Wholesale Goods"
        }
    ],
    "sg:phone":"+1 303 287 0635",
    "sg:postcode":"80229",
    "sg:province":"CO",
    "sg:tags":[
        "radiators-wholesale",
        "manufacturer"
    ],
    "wof:name":"Radiator",
    "wof:placetype":"venue"
},
  "geometry": {"coordinates":[-104.980411,39.823761],"type":"Point"}
}