{
  "type": "Feature",
  "properties": {
    "iso:country":"US",
    "sg:address":"20674 Seminole Rd",
    "sg:city":"Indian Hills",
    "sg:classifiers":[
        {
            "category":"Manufacturing",
            "subcategory":"Toys & Sporting Goods",
            "type":"Manufacturing & Wholesale Goods"
        }
    ],
    "sg:phone":"+1 303 697 7460",
    "sg:postcode":"80454",
    "sg:province":"CO",
    "sg:tags":[
        "mfg"
    ],
    "wof:name":"Having A Blast LLC",
    "wof:placetype":"venue"
},
  "geometry": {"coordinates":[-105.237866,39.619468],"type":"Point"}
}