{
  "type": "Feature",
  "properties": {
    "iso:country":"US",
    "sg:address":"1200 Galapago St",
    "sg:city":"Denver",
    "sg:classifiers":[
        {
            "category":"Restaurant",
            "type":"Food & Drink"
        }
    ],
    "sg:phone":"+1 303 571 1640",
    "sg:postcode":"80204",
    "sg:province":"CO",
    "sg:tags":[
        "eating"
    ],
    "wof:name":"Quinche Factory",
    "wof:placetype":"venue"
},
  "geometry": {"coordinates":[-104.996368,39.734104],"type":"Point"}
}