{
  "type": "Feature",
  "properties": {
    "addr:full":"1831 L Rd Fruita CO 81521",
    "addr:housenumber":"1831",
    "addr:postcode":"81521",
    "addr:street":"L Rd",
    "iso:country":"US",
    "sg:address":"1831 L Rd",
    "sg:city":"Fruita",
    "sg:classifiers":[
        {
            "category":"Professional",
            "type":"Services"
        }
    ],
    "sg:phone":"+1 970 858 3176",
    "sg:postcode":"81521",
    "sg:province":"CO",
    "wof:name":"Ancient Free & Accepted M",
    "wof:placetype":"venue"
},
  "geometry": {"coordinates":[-108.714764,39.178803],"type":"Point"}
}