{
  "type": "Feature",
  "properties": {
    "addr:full":"207 Elm St Leadville CO 80461",
    "addr:housenumber":"207",
    "addr:postcode":"80461",
    "addr:street":"Elm St",
    "iso:country":"US",
    "sg:address":"207 Elm St",
    "sg:city":"Leadville",
    "sg:classifiers":[
        {
            "category":"Travel",
            "subcategory":"Hotels & Motels",
            "type":"Entertainment"
        }
    ],
    "sg:phone":"+1 719 486 1223",
    "sg:postcode":"80461",
    "sg:province":"CO",
    "wof:name":"Alps Motel",
    "wof:placetype":"venue"
},
  "geometry": {"coordinates":[-106.292348,39.243218],"type":"Point"}
}