{
  "type": "Feature",
  "properties": {
    "addr:full":"1335 Elati St Ste A Denver CO 80204",
    "addr:housenumber":"1335",
    "addr:postcode":"80204",
    "addr:street":"Elati St Ste A",
    "iso:country":"US",
    "sg:address":"1335 Elati St Ste A",
    "sg:city":"Denver",
    "sg:classifiers":[
        {
            "category":"Building & Trades",
            "subcategory":"Construction",
            "type":"Services"
        }
    ],
    "sg:phone":"+1 303 623 3336",
    "sg:postcode":"80204",
    "sg:province":"CO",
    "sg:tags":[
        "interior",
        "design"
    ],
    "wof:name":"Lili Marlene Custom Lampshades",
    "wof:placetype":"venue"
},
  "geometry": {"coordinates":[-104.994435,39.737559],"type":"Point"}
}