{
  "type": "Feature",
  "properties": {
    "addr:full":"3006 Starlight Cir Colorado Springs CO 80916",
    "addr:housenumber":"3006",
    "addr:postcode":"80916",
    "addr:street":"Starlight Cir",
    "iso:country":"US",
    "sg:address":"3006 Starlight Cir",
    "sg:city":"Colorado Springs",
    "sg:classifiers":[
        {
            "category":"Shopping",
            "subcategory":"Gifts & Souvenirs",
            "type":"Retail Goods"
        }
    ],
    "sg:phone":"+1 719 473 7583",
    "sg:postcode":"80916",
    "sg:province":"CO",
    "wof:name":"Aracelis Gift Baskets & Flora",
    "wof:placetype":"venue"
},
  "geometry": {"coordinates":[-104.75151200000001,38.788114],"type":"Point"}
}