{
  "type": "Feature",
  "properties": {
    "addr:full":"8720 Franklin St Denver CO 80229",
    "addr:housenumber":"8720",
    "addr:postcode":"80229",
    "addr:street":"Franklin St",
    "iso:country":"US",
    "sg:address":"8720 Franklin St",
    "sg:city":"Denver",
    "sg:classifiers":[
        {
            "category":"Building & Trades",
            "subcategory":"Plumbing",
            "type":"Services"
        }
    ],
    "sg:phone":"+1 303 287 8860",
    "sg:postcode":"80229",
    "sg:province":"CO",
    "sg:tags":[
        "contractor"
    ],
    "wof:name":"Glenn Rayna",
    "wof:placetype":"venue"
},
  "geometry": {"coordinates":[-104.96836500000001,39.856151],"type":"Point"}
}