{
  "type": "Feature",
  "properties": {
    "addr:full":"1801 Hollywood Dr Pueblo CO 81005",
    "addr:housenumber":"1801",
    "addr:postcode":"81005",
    "addr:street":"Hollywood Dr",
    "iso:country":"US",
    "sg:address":"1801 Hollywood Dr",
    "sg:city":"Pueblo",
    "sg:classifiers":[
        {
            "category":"Education",
            "subcategory":"School",
            "type":"Public Place"
        }
    ],
    "sg:phone":"+1 719 549 7255",
    "sg:postcode":"81005",
    "sg:province":"CO",
    "wof:name":"South High",
    "wof:placetype":"venue"
},
  "geometry": {"coordinates":[-104.65466000000001,38.234981],"type":"Point"}
}