{
  "type": "Feature",
  "properties": {
    "iso:country":"US",
    "sg:address":"215 Riverside Dr",
    "sg:city":"Basalt",
    "sg:classifiers":[
        {
            "category":"Real Estate",
            "subcategory":"Real Estate Agent",
            "type":"Services"
        }
    ],
    "sg:phone":"+1 970 927 3003",
    "sg:postcode":"81621",
    "sg:province":"CO",
    "sg:tags":[
        "property",
        "management"
    ],
    "wof:name":"Hood Management LLC",
    "wof:placetype":"venue"
},
  "geometry": {"coordinates":[-107.02580399999999,39.370514],"type":"Point"}
}