{
  "type": "Feature",
  "properties": {
    "addr:full":"5700 Lincoln Dr Denver CO 80216",
    "addr:housenumber":"5700",
    "addr:postcode":"80216",
    "addr:street":"Lincoln Dr",
    "iso:country":"US",
    "sg:address":"5700 Lincoln Dr",
    "sg:city":"Denver",
    "sg:classifiers":[
        {
            "category":"Autos & Motor Vehicles",
            "subcategory":"Motorcycle Sales",
            "type":"Retail Goods"
        },
        {
            "category":"Retail",
            "subcategory":"Auto Repair",
            "type":"Services"
        }
    ],
    "sg:phone":"+1 303 657 3550",
    "sg:postcode":"80216",
    "sg:province":"CO",
    "sg:website":"www.topgun-motorsports.com/Home....",
    "wof:name":"Top Gun Motorsports",
    "wof:placetype":"venue"
},
  "geometry": {"coordinates":[-104.984787,39.799577],"type":"Point"}
}