{
  "type": "Feature",
  "properties": {
    "iso:country":"US",
    "sg:address":"541 Long St",
    "sg:city":"Pueblo",
    "sg:classifiers":[
        {
            "category":"Building & Trades",
            "subcategory":"Landscaping Services",
            "type":"Services"
        }
    ],
    "sg:phone":"+1 719 566 0458",
    "sg:postcode":"81005",
    "sg:province":"CO",
    "sg:tags":[
        "tree"
    ],
    "wof:name":"Rocky Mountain Tree Service",
    "wof:placetype":"venue"
},
  "geometry": {"coordinates":[-104.67683100000001,38.258296],"type":"Point"}
}