{
  "type": "Feature",
  "properties": {
    "iso:country":"US",
    "sg:address":"713 Sir Galahad Dr",
    "sg:city":"Lafayette",
    "sg:classifiers":[
        {
            "category":"Wholesale",
            "subcategory":"Machinery & Supplies",
            "type":"Manufacturing & Wholesale Goods"
        }
    ],
    "sg:phone":"+1 303 604 9733",
    "sg:postcode":"80026",
    "sg:province":"CO",
    "sg:tags":[
        "equipment",
        "industrial"
    ],
    "wof:name":"Darlington Design",
    "wof:placetype":"venue"
},
  "geometry": {"coordinates":[-105.083195,39.990119],"type":"Point"}
}