{
  "type": "Feature",
  "properties": {
    "iso:country":"US",
    "sg:address":"3200 Cherry Creek Dr N",
    "sg:city":"Denver",
    "sg:classifiers":[
        {
            "category":"Professional",
            "subcategory":"Business Services",
            "type":"Services"
        }
    ],
    "sg:phone":"+1 303 777 7833",
    "sg:postcode":"80209",
    "sg:province":"CO",
    "sg:tags":[
        "arbitration"
    ],
    "wof:name":"Elizabeth Henson",
    "wof:placetype":"venue"
},
  "geometry": {"coordinates":[-104.94649800000001,39.71152],"type":"Point"}
}