{
  "type": "Feature",
  "properties": {
    "iso:country":"US",
    "sg:address":"930 Leta Dr",
    "sg:city":"Colorado Springs",
    "sg:classifiers":[
        {
            "category":"Education",
            "subcategory":"School",
            "type":"Public Place"
        }
    ],
    "sg:phone":"+1 719 391 3050",
    "sg:postcode":"80911",
    "sg:province":"CO",
    "wof:name":"Widefield School District 3",
    "wof:placetype":"venue"
},
  "geometry": {"coordinates":[-104.740139,38.766218],"type":"Point"}
}