{
  "type": "Feature",
  "properties": {
    "iso:country":"US",
    "sg:address":"17551 US Hwy 34",
    "sg:city":"Fort Morgan",
    "sg:phone":"+1 970 867 6714",
    "sg:postcode":"80701",
    "sg:province":"CO",
    "sg:tags":[
        "farm",
        "beet"
    ],
    "wof:name":"Western Agricultural Shop",
    "wof:placetype":"venue"
},
  "geometry": {"coordinates":[-103.819613,40.254058],"type":"Point"}
}