{
  "type": "Feature",
  "properties": {
    "iso:country":"US",
    "sg:address":"8405 S Park Meadows Center Dr",
    "sg:city":"Lone Tree",
    "sg:classifiers":[
        {
            "category":"Home & Garden",
            "subcategory":"Furniture",
            "type":"Retail Goods"
        },
        {
            "category":"Home & Garden",
            "subcategory":"Home Furnishings",
            "type":"Retail Goods"
        }
    ],
    "sg:phone":"+1 303 799 4781",
    "sg:postcode":"80124",
    "sg:province":"CO",
    "sg:website":"www.potterybarn.com",
    "wof:name":"Pottery Barn",
    "wof:placetype":"venue"
},
  "geometry": {"coordinates":[-104.875241,39.559106],"type":"Point"}
}