{
  "type": "Feature",
  "properties": {
    "iso:country":"US",
    "sg:address":"7395 S Peoria St",
    "sg:city":"Englewood",
    "sg:classifiers":[
        {
            "category":"Airport",
            "type":"Transportation"
        }
    ],
    "sg:phone":"+1 303 858 9077",
    "sg:postcode":"80112",
    "sg:province":"CO",
    "sg:tags":[
        "aircraft",
        "maintenance"
    ],
    "wof:name":"Global Flight Support",
    "wof:placetype":"venue"
},
  "geometry": {"coordinates":[-104.84552600000001,39.581152],"type":"Point"}
}