{
  "type": "Feature",
  "properties": {
    "iso:country":"US",
    "sg:address":"3235 B Rd",
    "sg:city":"Grand Junction",
    "sg:classifiers":[
        {
            "category":"Farming",
            "subcategory":"Farm & Veterinary Services",
            "type":"Manufacturing & Wholesale Goods"
        }
    ],
    "sg:phone":"+1 970 434 9081",
    "sg:postcode":"81503",
    "sg:province":"CO",
    "sg:tags":[
        "crop"
    ],
    "wof:name":"Sun Mesa Orchard LLC",
    "wof:placetype":"venue"
},
  "geometry": {"coordinates":[-108.458307,39.033938],"type":"Point"}
}