{
  "type": "Feature",
  "properties": {
    "iso:country":"US",
    "sg:address":"4900 Boardwalk Dr",
    "sg:city":"Fort Collins",
    "sg:classifiers":[
        {
            "category":"Real Estate",
            "subcategory":"Real Estate Operator",
            "type":"Services"
        }
    ],
    "sg:phone":"+1 970 223 4940",
    "sg:postcode":"80525",
    "sg:province":"CO",
    "sg:tags":[
        "apartment",
        "complex"
    ],
    "wof:name":"Mira Mont Apartment Homes",
    "wof:placetype":"venue"
},
  "geometry": {"coordinates":[-105.064026,40.518116],"type":"Point"}
}