{
  "type": "Feature",
  "properties": {
    "iso:country":"US",
    "sg:address":"22518 Co Rd 74",
    "sg:city":"Eaton",
    "sg:classifiers":[
        {
            "category":"Manufacturing",
            "subcategory":"Metals",
            "type":"Manufacturing & Wholesale Goods"
        }
    ],
    "sg:phone":"+1 970 396 6877",
    "sg:postcode":"80615",
    "sg:province":"CO",
    "sg:tags":[
        "copper",
        "foundry"
    ],
    "wof:name":"Gary Pitcher",
    "wof:placetype":"venue"
},
  "geometry": {"coordinates":[-104.62812599999999,40.522721],"type":"Point"}
}