{
  "type": "Feature",
  "properties": {
    "iso:country":"US",
    "sg:address":"12391 Co Rd 29",
    "sg:city":"Sterling",
    "sg:classifiers":[
        {
            "category":"Building & Trades",
            "subcategory":"Construction",
            "type":"Services"
        }
    ],
    "sg:phone":"+1 970 522 7993",
    "sg:postcode":"80751",
    "sg:province":"CO",
    "sg:tags":[
        "contractor"
    ],
    "wof:name":"Cornerstone Cnstr & Excvtg LLC",
    "wof:placetype":"venue"
},
  "geometry": {"coordinates":[-103.318004,40.61037],"type":"Point"}
}