{
  "type": "Feature",
  "properties": {
    "iso:country":"US",
    "sg:address":"23731 Tesuque Rd",
    "sg:city":"Indian Hills",
    "sg:classifiers":[
        {
            "category":"Shopping",
            "subcategory":"Used Merchandise",
            "type":"Retail Goods"
        }
    ],
    "sg:phone":"+1 720 530 0913",
    "sg:postcode":"80454",
    "sg:province":"CO",
    "sg:tags":[
        "antique"
    ],
    "wof:name":"Second Hand Kates",
    "wof:placetype":"venue"
},
  "geometry": {"coordinates":[-105.271435,39.634249],"type":"Point"}
}