{
  "type": "Feature",
  "properties": {
    "addr:full":"2503 Holiday Ln Colorado Springs CO 80909",
    "addr:housenumber":"2503",
    "addr:postcode":"80909",
    "addr:street":"Holiday Ln",
    "iso:country":"US",
    "sg:address":"2503 Holiday Ln",
    "sg:city":"Colorado Springs",
    "sg:classifiers":[
        {
            "category":"Organizations",
            "subcategory":"Membership Organization",
            "type":"Services"
        }
    ],
    "sg:phone":"+1 719 634 5439",
    "sg:postcode":"80909",
    "sg:province":"CO",
    "wof:name":"KPC Kids",
    "wof:placetype":"venue"
},
  "geometry": {"coordinates":[-104.784013,38.868154],"type":"Point"}
}