{
  "type": "Feature",
  "properties": {
    "addr:full":"5739 W Milan Pl Denver CO 80235",
    "addr:housenumber":"5739",
    "addr:postcode":"80235",
    "addr:street":"W Milan Pl",
    "iso:country":"US",
    "sg:address":"5739 W Milan Pl",
    "sg:city":"Denver",
    "sg:classifiers":[
        {
            "category":"Real Estate",
            "subcategory":"Real Estate Agent",
            "type":"Services"
        }
    ],
    "sg:phone":"+1 303 985 2059",
    "sg:postcode":"80235",
    "sg:province":"CO",
    "wof:name":"Future Enterprises Inc",
    "wof:placetype":"venue"
},
  "geometry": {"coordinates":[-105.056973,39.646323],"type":"Point"}
}