{
  "type": "Feature",
  "properties": {
    "iso:country":"US",
    "sg:address":"4567 E 9th Ave",
    "sg:city":"Denver",
    "sg:classifiers":[
        {
            "category":"Health Services",
            "subcategory":"Doctor",
            "type":"Services"
        }
    ],
    "sg:phone":"+1 303 322 7921",
    "sg:postcode":"80220",
    "sg:province":"CO",
    "wof:name":"Pediatrix",
    "wof:placetype":"venue"
},
  "geometry": {"coordinates":[-104.934362,39.731211],"type":"Point"}
}