{
  "type": "Feature",
  "properties": {
    "addr:full":"400 S 9th St Rocky Ford CO 81067",
    "addr:housenumber":"400",
    "addr:postcode":"81067",
    "addr:street":"S 9Th St",
    "iso:country":"US",
    "sg:address":"400 S 9th St",
    "sg:city":"Rocky Ford",
    "sg:classifiers":[
        {
            "category":"Organizations",
            "subcategory":"Religious Organization",
            "type":"Services"
        }
    ],
    "sg:phone":"+1 719 254 3519",
    "sg:postcode":"81067",
    "sg:province":"CO",
    "sg:tags":[
        "church"
    ],
    "wof:name":"First Christian Church",
    "wof:placetype":"venue"
},
  "geometry": {"coordinates":[-103.72203,38.051719],"type":"Point"}
}