{
  "type": "Feature",
  "properties": {
    "addr:full":"2177 Co Rd 154 Glenwood Springs CO 81601",
    "addr:housenumber":"2177;154",
    "addr:postcode":"81601",
    "addr:street":"Co Rd",
    "iso:country":"US",
    "sg:address":"2177 Co Rd 154",
    "sg:city":"Glenwood Springs",
    "sg:classifiers":[
        {
            "category":"Building & Trades",
            "subcategory":"Construction",
            "type":"Services"
        }
    ],
    "sg:phone":"+1 970 945 7775",
    "sg:postcode":"81601",
    "sg:province":"CO",
    "sg:tags":[
        "floor",
        "laying",
        "contractor"
    ],
    "wof:name":"Roach Tom Flooring",
    "wof:placetype":"venue"
},
  "geometry": {"coordinates":[-107.308452,39.511502],"type":"Point"}
}