{
  "type": "Feature",
  "properties": {
    "iso:country":"US",
    "sg:address":"15 E Iowa Ave",
    "sg:city":"Denver",
    "sg:classifiers":[
        {
            "category":"Organizations",
            "subcategory":"Community Association",
            "type":"Services"
        }
    ],
    "sg:phone":"+1 303 715 3712",
    "sg:postcode":"80210",
    "sg:province":"CO",
    "sg:tags":[
        "fraternal"
    ],
    "wof:name":"George Washington Lodge",
    "wof:placetype":"venue"
},
  "geometry": {"coordinates":[-104.98642599999999,39.687638],"type":"Point"}
}