{
  "type": "Feature",
  "properties": {
    "iso:country":"US",
    "sg:address":"15200 E Colfax Ave",
    "sg:city":"Aurora",
    "sg:classifiers":[
        {
            "category":"Professional",
            "type":"Services"
        }
    ],
    "sg:phone":"+1 303 340 1591",
    "sg:postcode":"80011",
    "sg:province":"CO",
    "wof:name":"Fitz Federal",
    "wof:placetype":"venue"
},
  "geometry": {"coordinates":[-104.81127600000001,39.740068],"type":"Point"}
}