{
  "type": "Feature",
  "properties": {
    "addr:full":"13363 Gaylord St Denver CO 80241",
    "addr:housenumber":"13363",
    "addr:postcode":"80241",
    "addr:street":"Gaylord St",
    "iso:country":"US",
    "sg:address":"13363 Gaylord St",
    "sg:city":"Denver",
    "sg:classifiers":[
        {
            "category":"Shopping",
            "subcategory":"Hobbies, Toys, & Games",
            "type":"Retail Goods"
        }
    ],
    "sg:phone":"+1 303 920 8563",
    "sg:postcode":"80241",
    "sg:province":"CO",
    "wof:name":"Red Barn Primitives",
    "wof:placetype":"venue"
},
  "geometry": {"coordinates":[-104.962154,39.9369],"type":"Point"}
}