{
  "type": "Feature",
  "properties": {
    "iso:country":"US",
    "sg:address":"Asbury St",
    "sg:city":"Denver",
    "sg:classifiers":[
        {
            "category":"Restaurant",
            "type":"Food & Drink"
        }
    ],
    "sg:postcode":"80210",
    "sg:province":"CO",
    "wof:name":"DU Hot Dog Vendor",
    "wof:placetype":"venue"
},
  "geometry": {"coordinates":[-104.966388,39.68028],"type":"Point"}
}