{
  "type": "Feature",
  "properties": {
    "addr:full":"11450 Community Center Dr Denver CO 80233",
    "addr:housenumber":"11450",
    "addr:postcode":"80233",
    "addr:street":"Community Center Dr",
    "iso:country":"US",
    "sg:address":"11450 Community Center Dr",
    "sg:city":"Denver",
    "sg:classifiers":[
        {
            "category":"Real Estate",
            "subcategory":"Real Estate Operator",
            "type":"Services"
        }
    ],
    "sg:phone":"+1 303 280 3600",
    "sg:postcode":"80233",
    "sg:province":"CO",
    "sg:tags":[
        "building",
        "apartment"
    ],
    "wof:name":"Reserve At North Glenn",
    "wof:placetype":"venue"
},
  "geometry": {"coordinates":[-104.987275,39.906161],"type":"Point"}
}