{
  "type": "Feature",
  "properties": {
    "iso:country":"US",
    "sg:address":"591 S Taft St",
    "sg:city":"Denver",
    "sg:classifiers":[
        {
            "category":"Building & Trades",
            "subcategory":"Plumbing",
            "type":"Services"
        }
    ],
    "sg:phone":"+1 303 988 0143",
    "sg:postcode":"80228",
    "sg:province":"CO",
    "sg:tags":[
        "conditioning",
        "contractor",
        "system",
        "air"
    ],
    "wof:name":"Dave's Heating & Cooling Inc",
    "wof:placetype":"venue"
},
  "geometry": {"coordinates":[-105.130501,39.707191],"type":"Point"}
}