{
  "type": "Feature",
  "properties": {
    "iso:country":"US",
    "sg:address":"1868 Meadow Vale Rd",
    "sg:city":"Longmont",
    "sg:classifiers":[
        {
            "category":"Social Services",
            "subcategory":"Child Care",
            "type":"Services"
        }
    ],
    "sg:phone":"+1 303 772 5789",
    "sg:postcode":"80504",
    "sg:province":"CO",
    "sg:tags":[
        "center"
    ],
    "wof:name":"SFE Inc",
    "wof:placetype":"venue"
},
  "geometry": {"coordinates":[-105.014634,40.167225],"type":"Point"}
}