{
  "type": "Feature",
  "properties": {
    "iso:country":"US",
    "sg:address":"1400 Nelson Rd",
    "sg:city":"Longmont",
    "sg:classifiers":[
        {
            "category":"Retail",
            "subcategory":"Auto Rental",
            "type":"Services"
        }
    ],
    "sg:phone":"+1 303 678 0116",
    "sg:postcode":"80501",
    "sg:province":"CO",
    "sg:tags":[
        "renting",
        "truck",
        "leasing"
    ],
    "wof:name":"Penske Truck Rental",
    "wof:placetype":"venue"
},
  "geometry": {"coordinates":[-105.117099,40.152163],"type":"Point"}
}