{
  "type": "Feature",
  "properties": {
    "addr:full":"725 Old Stone Dr Littleton CO 80126",
    "addr:housenumber":"725",
    "addr:postcode":"80126",
    "addr:street":"Old Stone Dr",
    "iso:country":"US",
    "sg:address":"725 Old Stone Dr",
    "sg:city":"Littleton",
    "sg:classifiers":[
        {
            "category":"Real Estate",
            "subcategory":"Real Estate Agent",
            "type":"Services"
        }
    ],
    "sg:phone":"+1 303 791 3231",
    "sg:postcode":"80126",
    "sg:province":"CO",
    "wof:name":"Joe R Mottershaw Realtors",
    "wof:placetype":"venue"
},
  "geometry": {"coordinates":[-104.977996,39.556602],"type":"Point"}
}