{
  "type": "Feature",
  "properties": {
    "addr:full":"PO BOX 17921 Boulder CO 80308-0921",
    "addr:housenumber":"po box 17921",
    "addr:postcode":"80308-0921",
    "iso:country":"US",
    "sg:address":"PO BOX 17921",
    "sg:city":"Boulder",
    "sg:classifiers":[
        {
            "category":"Professional",
            "subcategory":"Computer Services",
            "type":"Services"
        }
    ],
    "sg:phone":"+1 303 459 2792",
    "sg:postcode":"80308-0921",
    "sg:province":"CO",
    "sg:tags":[
        "deals-bargains-revenue-sharing"
    ],
    "sg:website":"http://www.dealstop.com/",
    "wof:name":"DealStop",
    "wof:placetype":"venue"
},
  "geometry": {"coordinates":[-105.38679999999999,40.027672],"type":"Point"}
}