{
  "type": "Feature",
  "properties": {
    "iso:country":"US",
    "sg:address":"1466 W Hwy 105",
    "sg:city":"Monument",
    "sg:classifiers":[
        {
            "category":"Utilities",
            "subcategory":"Telephone",
            "type":"Services"
        }
    ],
    "sg:phone":"+1 719 487 8424",
    "sg:postcode":"80132",
    "sg:province":"CO",
    "sg:tags":[
        "communications"
    ],
    "wof:name":"Communications Sunwest",
    "wof:placetype":"venue"
},
  "geometry": {"coordinates":[-104.860867,39.092741],"type":"Point"}
}