{
  "type": "Feature",
  "properties": {
    "addr:full":"6525 W 4th St Greeley CO 80634",
    "addr:housenumber":"6525",
    "addr:postcode":"80634",
    "addr:street":"W 4Th St",
    "iso:country":"US",
    "sg:address":"6525 W 4th St",
    "sg:city":"Greeley",
    "sg:classifiers":[
        {
            "category":"Building & Trades",
            "subcategory":"Plumbing",
            "type":"Services"
        }
    ],
    "sg:phone":"+1 970 352 3432",
    "sg:postcode":"80634",
    "sg:province":"CO",
    "sg:tags":[
        "contractor"
    ],
    "wof:name":"Western Comfort Systems Inc",
    "wof:placetype":"venue"
},
  "geometry": {"coordinates":[-104.793104,40.429321],"type":"Point"}
}