{
  "type": "Feature",
  "properties": {
    "iso:country":"US",
    "sg:address":"4271 S Bannock St",
    "sg:city":"Englewood",
    "sg:classifiers":[
        {
            "category":"Professional",
            "subcategory":"Management & Consulting",
            "type":"Services"
        }
    ],
    "sg:phone":"+1 303 781 0240",
    "sg:postcode":"80110",
    "sg:province":"CO",
    "sg:tags":[
        "home",
        "demonstration"
    ],
    "wof:name":"Tuperware",
    "wof:placetype":"venue"
},
  "geometry": {"coordinates":[-104.990253,39.63985],"type":"Point"}
}