{
  "type": "Feature",
  "properties": {
    "addr:full":"17150 E 14th Dr Aurora CO 80011",
    "addr:housenumber":"17150",
    "addr:postcode":"80011",
    "addr:street":"E 14Th Dr",
    "iso:country":"US",
    "sg:address":"17150 E 14th Dr",
    "sg:city":"Aurora",
    "sg:classifiers":[
        {
            "category":"Mining & Drilling",
            "type":"Manufacturing & Wholesale Goods"
        }
    ],
    "sg:phone":"+1 303 363 8841",
    "sg:postcode":"80011",
    "sg:province":"CO",
    "sg:tags":[
        "jacking",
        "mud",
        "contractor"
    ],
    "wof:name":"Aurora Mud Jack",
    "wof:placetype":"venue"
},
  "geometry": {"coordinates":[-104.787057,39.739032],"type":"Point"}
}