{
  "type": "Feature",
  "properties": {
    "iso:country":"US",
    "sg:address":"11510 W Colfax Ave",
    "sg:city":"Lakewood",
    "sg:classifiers":[
        {
            "category":"Retail",
            "subcategory":"Auto Rental",
            "type":"Services"
        }
    ],
    "sg:phone":"+1 303 237 4473",
    "sg:postcode":"80215",
    "sg:province":"CO",
    "sg:tags":[
        "renting",
        "automobile"
    ],
    "sg:website":"www.hertz.com",
    "wof:name":"Hertz Rent A Car",
    "wof:placetype":"venue"
},
  "geometry": {"coordinates":[-105.12816100000001,39.740085],"type":"Point"}
}