{
  "type": "Feature",
  "properties": {
    "iso:country":"US",
    "sg:address":"17514 E Progress Dr",
    "sg:city":"Aurora",
    "sg:classifiers":[
        {
            "category":"Professional",
            "type":"Services"
        }
    ],
    "sg:phone":"+1 303 693 2984",
    "sg:postcode":"80015",
    "sg:province":"CO",
    "wof:name":"W J Fox",
    "wof:placetype":"venue"
},
  "geometry": {"coordinates":[-104.78488400000001,39.621248],"type":"Point"}
}