{
  "type": "Feature",
  "properties": {
    "iso:country":"US",
    "sg:address":"6025 S Quebec St",
    "sg:city":"Englewood",
    "sg:classifiers":[
        {
            "category":"Social Services",
            "subcategory":"Job Training",
            "type":"Services"
        }
    ],
    "sg:phone":"+1 720 493 0355",
    "sg:postcode":"80111",
    "sg:province":"CO",
    "sg:tags":[
        "rehabilitation"
    ],
    "wof:name":"Mark E Litvin Phd LLC",
    "wof:placetype":"venue"
},
  "geometry": {"coordinates":[-104.904191,39.606291],"type":"Point"}
}