{
  "type": "Feature",
  "properties": {
    "addr:full":"2073 Park Ave Pagosa Springs CO 81147",
    "addr:housenumber":"2073",
    "addr:postcode":"81147",
    "addr:street":"Park Ave",
    "iso:country":"US",
    "sg:address":"2073 Park Ave",
    "sg:city":"Pagosa Springs",
    "sg:classifiers":[
        {
            "category":"Food & Beverages",
            "subcategory":"Specialty",
            "type":"Retail Goods"
        }
    ],
    "sg:phone":"+1 970 731 5484",
    "sg:postcode":"81147",
    "sg:province":"CO",
    "wof:name":"Uncle Zacks",
    "wof:placetype":"venue"
},
  "geometry": {"coordinates":[-107.075166,37.270877],"type":"Point"}
}