{
  "type": "Feature",
  "properties": {
    "addr:full":"3644 E Co Rd 16 Loveland CO 80537",
    "addr:housenumber":"3644;16",
    "addr:postcode":"80537",
    "addr:street":"E Co Rd",
    "iso:country":"US",
    "sg:address":"3644 E Co Rd 16",
    "sg:city":"Loveland",
    "sg:classifiers":[
        {
            "category":"Professional",
            "subcategory":"Lawyer & Legal Services",
            "type":"Services"
        }
    ],
    "sg:phone":"+1 970 663 7834",
    "sg:postcode":"80537",
    "sg:province":"CO",
    "sg:tags":[
        "attorney"
    ],
    "wof:name":"Warberg & Assoc",
    "wof:placetype":"venue"
},
  "geometry": {"coordinates":[-105.025148,40.363788],"type":"Point"}
}