{
  "type": "Feature",
  "properties": {
    "addr:full":"4298 Abstract St Castle Rock CO 80109",
    "addr:housenumber":"4298",
    "addr:postcode":"80109",
    "addr:street":"Abstract St",
    "iso:country":"US",
    "sg:address":"4298 Abstract St",
    "sg:city":"Castle Rock",
    "sg:classifiers":[
        {
            "category":"Building & Trades",
            "subcategory":"Construction",
            "type":"Services"
        }
    ],
    "sg:phone":"+1 303 406 4340",
    "sg:postcode":"80109",
    "sg:province":"CO",
    "sg:tags":[
        "contractor"
    ],
    "sg:website":"www.meritagehomes.com",
    "wof:name":"Meritage Homes",
    "wof:placetype":"venue"
},
  "geometry": {"coordinates":[-104.90823899999999,39.388436],"type":"Point"}
}