{
  "type": "Feature",
  "properties": {
    "addr:full":"2348 Mc Kinley Ave Louisville CO 80027",
    "addr:housenumber":"2348",
    "addr:postcode":"80027",
    "addr:street":"Mc Kinley Ave",
    "iso:country":"US",
    "sg:address":"2348 Mc Kinley Ave",
    "sg:city":"Louisville",
    "sg:classifiers":[
        {
            "category":"Building & Trades",
            "subcategory":"Construction",
            "type":"Services"
        }
    ],
    "sg:phone":"+1 303 673 9740",
    "sg:postcode":"80027",
    "sg:province":"CO",
    "sg:tags":[
        "hanging",
        "contractor"
    ],
    "wof:name":"Pinnacle Pntg & Wallpainting",
    "wof:placetype":"venue"
},
  "geometry": {"coordinates":[-105.14136999999999,39.992685],"type":"Point"}
}