{
  "type": "Feature",
  "properties": {
    "addr:full":"480 S Marion Pkwy Denver CO 80209",
    "addr:housenumber":"480",
    "addr:postcode":"80209",
    "addr:street":"S Marion Pkwy",
    "iso:country":"US",
    "sg:address":"480 S Marion Pkwy",
    "sg:city":"Denver",
    "sg:classifiers":[
        {
            "category":"Real Estate",
            "subcategory":"Developer",
            "type":"Services"
        }
    ],
    "sg:phone":"+1 303 733 7612",
    "sg:postcode":"80209",
    "sg:province":"CO",
    "wof:name":"Trg Lincoln LLC",
    "wof:placetype":"venue"
},
  "geometry": {"coordinates":[-104.97218599999999,39.707488],"type":"Point"}
}