{
  "type": "Feature",
  "properties": {
    "iso:country":"US",
    "sg:address":"1 Olympic Plz",
    "sg:city":"Colorado Springs",
    "sg:classifiers":[
        {
            "category":"Organizations",
            "subcategory":"Membership Organization",
            "type":"Services"
        }
    ],
    "sg:phone":"+1 719 866 4581",
    "sg:postcode":"80909",
    "sg:province":"CO",
    "sg:tags":[
        "promotion",
        "sport",
        "amateur"
    ],
    "wof:name":"Norba",
    "wof:placetype":"venue"
},
  "geometry": {"coordinates":[-104.79941700000001,38.839092],"type":"Point"}
}