{
  "type": "Feature",
  "properties": {
    "addr:full":"505 Thunderbird Ct E Boulder CO 80303",
    "addr:housenumber":"505",
    "addr:postcode":"80303",
    "addr:street":"Thunderbird Ct E",
    "iso:country":"US",
    "sg:address":"505 Thunderbird Ct E",
    "sg:city":"Boulder",
    "sg:classifiers":[
        {
            "category":"Sports & Exercise",
            "subcategory":"Gym",
            "type":"Entertainment"
        }
    ],
    "sg:phone":"+1 303 499 6590",
    "sg:postcode":"80303",
    "sg:province":"CO",
    "sg:tags":[
        "membership",
        "fitness",
        "physical",
        "c",
        "facility"
    ],
    "wof:name":"Flatiron Athletic Club",
    "wof:placetype":"venue"
},
  "geometry": {"coordinates":[-105.23201899999999,39.996095],"type":"Point"}
}