{
  "type": "Feature",
  "properties": {
    "iso:country":"US",
    "sg:address":"8181 Monarch Blvd",
    "sg:city":"Castle Rock",
    "sg:classifiers":[
        {
            "category":"Professional",
            "subcategory":"Management & Consulting",
            "type":"Services"
        }
    ],
    "sg:phone":"+1 303 660 9593",
    "sg:postcode":"80108",
    "sg:province":"CO",
    "sg:tags":[
        "business"
    ],
    "wof:name":"Select Solutions Inc",
    "wof:placetype":"venue"
},
  "geometry": {"coordinates":[-104.900542,39.478579],"type":"Point"}
}