{
  "type": "Feature",
  "properties": {
    "addr:full":"9535 E Colfax Ave Aurora CO 80010",
    "addr:housenumber":"9535",
    "addr:postcode":"80010",
    "addr:street":"E Colfax Ave",
    "iso:country":"US",
    "sg:address":"9535 E Colfax Ave",
    "sg:city":"Aurora",
    "sg:classifiers":[
        {
            "category":"Shopping",
            "subcategory":"Books",
            "type":"Retail Goods"
        }
    ],
    "sg:phone":"+1 303 367 2035",
    "sg:postcode":"80010",
    "sg:province":"CO",
    "sg:tags":[
        "dealer"
    ],
    "wof:name":"New Wine Bookstore",
    "wof:placetype":"venue"
},
  "geometry": {"coordinates":[-104.87729899999999,39.740135],"type":"Point"}
}