{
  "type": "Feature",
  "properties": {
    "addr:full":"4864 N Wildflowers Way Castle Rock CO 80109",
    "addr:housenumber":"4864",
    "addr:postcode":"80109",
    "addr:street":"N Wildflowers Way",
    "iso:country":"US",
    "sg:address":"4864 N Wildflowers Way",
    "sg:city":"Castle Rock",
    "sg:classifiers":[
        {
            "category":"Building & Trades",
            "subcategory":"Electrical",
            "type":"Services"
        }
    ],
    "sg:phone":"+1 303 688 2048",
    "sg:postcode":"80109",
    "sg:province":"CO",
    "sg:tags":[
        "electrical",
        "contractor"
    ],
    "wof:name":"Picker  Eugene C & Picker",
    "wof:placetype":"venue"
},
  "geometry": {"coordinates":[-104.899547,39.410145],"type":"Point"}
}