{
  "type": "Feature",
  "properties": {
    "iso:country":"US",
    "sg:address":"3622 E Highlands Ranch Pkwy",
    "sg:city":"Highlands Ranch",
    "sg:classifiers":[
        {
            "category":"Shopping",
            "subcategory":"Optical Goods",
            "type":"Retail Goods"
        }
    ],
    "sg:phone":"+1 303 683 4466",
    "sg:postcode":"80126",
    "sg:province":"CO",
    "sg:tags":[
        "contact",
        "lense"
    ],
    "wof:name":"Eye To Eye Care",
    "wof:placetype":"venue"
},
  "geometry": {"coordinates":[-104.95260500000001,39.541195],"type":"Point"}
}