{
  "type": "Feature",
  "properties": {
    "addr:full":"1220 Lee St Denver CO 80215",
    "addr:housenumber":"1220",
    "addr:postcode":"80215",
    "addr:street":"Lee St",
    "iso:country":"US",
    "sg:address":"1220 Lee St",
    "sg:city":"Denver",
    "sg:classifiers":[
        {
            "category":"Building & Trades",
            "subcategory":"Construction",
            "type":"Services"
        }
    ],
    "sg:phone":"+1 303 235 6882",
    "sg:postcode":"80215",
    "sg:province":"CO",
    "sg:tags":[
        "hanging",
        "contractor"
    ],
    "wof:name":"Bills Painting Svc",
    "wof:placetype":"venue"
},
  "geometry": {"coordinates":[-105.11187,39.735783],"type":"Point"}
}