{
  "type": "Feature",
  "properties": {
    "addr:full":"6263 N Co Rd 29 Loveland CO 80538",
    "addr:housenumber":"6263;29",
    "addr:postcode":"80538",
    "addr:street":"N Co Rd",
    "iso:country":"US",
    "sg:address":"6263 N Co Rd 29",
    "sg:city":"Loveland",
    "sg:classifiers":[
        {
            "category":"Health Services",
            "subcategory":"Nursing And Care Facility",
            "type":"Services"
        }
    ],
    "sg:phone":"+1 970 667 6911",
    "sg:postcode":"80538",
    "sg:province":"CO",
    "sg:tags":[
        "home",
        "convalescent"
    ],
    "wof:name":"Eden Valley Retirement Ctr",
    "wof:placetype":"venue"
},
  "geometry": {"coordinates":[-105.20903,40.457647],"type":"Point"}
}