{
  "type": "Feature",
  "properties": {
    "iso:country":"US",
    "sg:address":"500 E 84th Ave",
    "sg:city":"Denver",
    "sg:classifiers":[
        {
            "category":"Communications",
            "type":"Services"
        }
    ],
    "sg:phone":"+1 303 227 9640",
    "sg:postcode":"80229",
    "sg:province":"CO",
    "sg:website":"www.webex.com",
    "wof:name":"Webex Communications",
    "wof:placetype":"venue"
},
  "geometry": {"coordinates":[-104.981127,39.848867],"type":"Point"}
}