{
  "type": "Feature",
  "properties": {
    "addr:full":"18601 E Hampden Ave Aurora CO 80013",
    "addr:housenumber":"18601",
    "addr:postcode":"80013",
    "addr:street":"E Hampden Ave",
    "iso:country":"US",
    "sg:address":"18601 E Hampden Ave",
    "sg:city":"Aurora",
    "sg:classifiers":[
        {
            "category":"Restaurant",
            "type":"Food & Drink"
        }
    ],
    "sg:menulink":"http://www.allmenus.com/co/south-aurora/109276-village-inn/menu/",
    "sg:phone":"+1 303 627 1392",
    "sg:postcode":"80013",
    "sg:province":"CO",
    "sg:tags":[
        "new",
        "american"
    ],
    "wof:name":"Village Inn",
    "wof:placetype":"venue"
},
  "geometry": {"coordinates":[-104.77069400000001,39.653427],"type":"Point"}
}