{
  "type": "Feature",
  "properties": {
    "addr:full":"9881 W 58th Ave Arvada CO 80002",
    "addr:housenumber":"9881",
    "addr:postcode":"80002",
    "addr:street":"W 58Th Ave",
    "iso:country":"US",
    "sg:address":"9881 W 58th Ave",
    "sg:city":"Arvada",
    "sg:classifiers":[
        {
            "category":"Restaurant",
            "type":"Food & Drink"
        }
    ],
    "sg:phone":"+1 303 424 8581",
    "sg:postcode":"80002",
    "sg:province":"CO",
    "wof:name":"Little Caesars",
    "wof:placetype":"venue"
},
  "geometry": {"coordinates":[-105.10643899999999,39.80202],"type":"Point"}
}