{
  "type": "Feature",
  "properties": {
    "iso:country":"US",
    "sg:address":"1458 Periwinkle Dr",
    "sg:city":"Boulder",
    "sg:classifiers":[
        {
            "category":"Professional",
            "type":"Services"
        }
    ],
    "sg:phone":"+1 303 546 9682",
    "sg:postcode":"80304",
    "sg:province":"CO",
    "wof:name":"Medairco Inc",
    "wof:placetype":"venue"
},
  "geometry": {"coordinates":[-105.28056100000001,40.046472],"type":"Point"}
}