{
  "type": "Feature",
  "properties": {
    "iso:country":"US",
    "sg:address":"7990 W Alameda Avenue",
    "sg:city":"Lakewood",
    "sg:classifiers":[
        {
            "category":"Banks & Credit Unions",
            "subcategory":"Bank",
            "type":"Services"
        }
    ],
    "sg:phone":"+1 303 914 2220",
    "sg:postcode":"80226",
    "sg:province":"CO",
    "wof:name":"Foothills Credit Union",
    "wof:placetype":"venue"
},
  "geometry": {"coordinates":[-105.085691,39.711047],"type":"Point"}
}