{
  "type": "Feature",
  "properties": {
    "iso:country":"US",
    "sg:address":"440 Main St",
    "sg:city":"Lyons",
    "sg:classifiers":[
        {
            "category":"Shopping",
            "subcategory":"Pharmacy",
            "type":"Retail Goods"
        }
    ],
    "sg:phone":"+1 303 823 9134",
    "sg:postcode":"80540",
    "sg:province":"CO",
    "wof:name":"St Vrain Pharmacy",
    "wof:placetype":"venue"
},
  "geometry": {"coordinates":[-105.27099699999999,40.22475],"type":"Point"}
}