{
  "type": "Feature",
  "properties": {
    "addr:full":"10636 W Tufts Pl Littleton CO 80127",
    "addr:housenumber":"10636",
    "addr:postcode":"80127",
    "addr:street":"W Tufts Pl",
    "iso:country":"US",
    "sg:address":"10636 W Tufts Pl",
    "sg:city":"Littleton",
    "sg:classifiers":[
        {
            "category":"Building & Trades",
            "subcategory":"Construction",
            "type":"Services"
        }
    ],
    "sg:phone":"+1 303 972 8755",
    "sg:postcode":"80127",
    "sg:province":"CO",
    "sg:tags":[
        "contractor"
    ],
    "wof:name":"L & L Interiors Inc",
    "wof:placetype":"venue"
},
  "geometry": {"coordinates":[-105.11787200000001,39.633456],"type":"Point"}
}