{
  "type": "Feature",
  "properties": {
    "iso:country":"US",
    "sg:address":"301 N Howes St",
    "sg:city":"Fort Collins",
    "sg:classifiers":[
        {
            "category":"Professional",
            "subcategory":"Engineering",
            "type":"Services"
        }
    ],
    "sg:phone":"+1 970 484 0359",
    "sg:postcode":"80521",
    "sg:province":"CO",
    "sg:tags":[
        "engineer"
    ],
    "sg:website":"www.terracon.com",
    "wof:name":"Terracon Consultants Inc",
    "wof:placetype":"venue"
},
  "geometry": {"coordinates":[-105.08066100000001,40.592171],"type":"Point"}
}