{
  "type": "Feature",
  "properties": {
    "addr:full":"1133 Delaware St Denver CO 80204",
    "addr:housenumber":"1133",
    "addr:postcode":"80204",
    "addr:street":"Delaware St",
    "iso:country":"US",
    "sg:address":"1133 Delaware St",
    "sg:city":"Denver",
    "sg:classifiers":[
        {
            "category":"Building & Trades",
            "subcategory":"Locksmith",
            "type":"Services"
        }
    ],
    "sg:phone":"+1 303 876 0317",
    "sg:postcode":"80204",
    "sg:province":"CO",
    "sg:tags":[
        "key"
    ],
    "wof:name":"A 24 7 Able Locksmith",
    "wof:placetype":"venue"
},
  "geometry": {"coordinates":[-104.993088,39.734344],"type":"Point"}
}