{
  "type": "Feature",
  "properties": {
    "addr:full":"5520 Federal Blvd Denver CO 80221",
    "addr:housenumber":"5520",
    "addr:postcode":"80221",
    "addr:street":"Federal Blvd",
    "iso:country":"US",
    "sg:address":"5520 Federal Blvd",
    "sg:city":"Denver",
    "sg:classifiers":[
        {
            "category":"Professional",
            "type":"Services"
        }
    ],
    "sg:phone":"+1 303 433 6456",
    "sg:postcode":"80221",
    "sg:province":"CO",
    "wof:name":"Carlson Brower Exteriors",
    "wof:placetype":"venue"
},
  "geometry": {"coordinates":[-105.02517899999999,39.797681],"type":"Point"}
}