{
  "type": "Feature",
  "properties": {
    "addr:full":"1520 E Willamette Ave Colorado Springs CO 80909",
    "addr:housenumber":"1520",
    "addr:postcode":"80909",
    "addr:street":"E Willamette Ave",
    "iso:country":"US",
    "sg:address":"1520 E Willamette Ave",
    "sg:city":"Colorado Springs",
    "sg:classifiers":[
        {
            "category":"Government",
            "subcategory":"Office",
            "type":"Public Place"
        }
    ],
    "sg:phone":"+1 719 227 0511",
    "sg:postcode":"80909",
    "sg:province":"CO",
    "sg:tags":[
        "federal"
    ],
    "wof:name":"US General Svc Adm",
    "wof:placetype":"venue"
},
  "geometry": {"coordinates":[-104.79831,38.841664],"type":"Point"}
}