{
  "type": "Feature",
  "properties": {
    "iso:country":"US",
    "sg:address":"2960 Dory Hill Rd",
    "sg:city":"Golden",
    "sg:classifiers":[
        {
            "category":"Government",
            "subcategory":"Police Station",
            "type":"Public Place"
        }
    ],
    "sg:phone":"+1 303 582 1060",
    "sg:postcode":"80403",
    "sg:province":"CO",
    "sg:tags":[
        "dept",
        "sheriff"
    ],
    "wof:name":"Sheriff Dept",
    "wof:placetype":"venue"
},
  "geometry": {"coordinates":[-105.48307800000001,39.841362],"type":"Point"}
}