{
  "type": "Feature",
  "properties": {
    "iso:country":"US",
    "sg:address":"2764 Compass Dr",
    "sg:city":"Grand Junction",
    "sg:classifiers":[
        {
            "category":"Social Services",
            "type":"Services"
        }
    ],
    "sg:phone":"+1 970 241 3346",
    "sg:postcode":"81506",
    "sg:province":"CO",
    "sg:tags":[
        "youth",
        "organization",
        "center"
    ],
    "wof:name":"Colorado State University",
    "wof:placetype":"venue"
},
  "geometry": {"coordinates":[-108.54051800000001,39.116436],"type":"Point"}
}