{
  "type": "Feature",
  "properties": {
    "addr:full":"132 Walnut Ave Grand Junction CO 81501",
    "addr:housenumber":"132",
    "addr:postcode":"81501",
    "addr:street":"Walnut Ave",
    "iso:country":"US",
    "sg:address":"132 Walnut Ave",
    "sg:city":"Grand Junction",
    "sg:classifiers":[
        {
            "category":"Health Services",
            "subcategory":"Doctor",
            "type":"Services"
        }
    ],
    "sg:phone":"+1 970 242 0288",
    "sg:postcode":"81501",
    "sg:province":"CO",
    "sg:tags":[
        "dentist"
    ],
    "wof:name":"Corbett & Moses",
    "wof:placetype":"venue"
},
  "geometry": {"coordinates":[-108.567482,39.086143],"type":"Point"}
}