{
  "type": "Feature",
  "properties": {
    "iso:country":"US",
    "sg:address":"19114 Co Rd 42",
    "sg:city":"Haxtun",
    "sg:classifiers":[
        {
            "category":"Farming",
            "subcategory":"Farm",
            "type":"Manufacturing & Wholesale Goods"
        }
    ],
    "sg:phone":"+1 970 774 6351",
    "sg:postcode":"80731",
    "sg:province":"CO",
    "sg:tags":[
        "crop",
        "general"
    ],
    "wof:name":"Zion Farms",
    "wof:placetype":"venue"
},
  "geometry": {"coordinates":[-102.471842,40.734554],"type":"Point"}
}