{
  "type": "Feature",
  "properties": {
    "addr:full":"79 Sugarloaf Dr Pagosa Springs CO 81147",
    "addr:housenumber":"79",
    "addr:postcode":"81147",
    "addr:street":"Sugarloaf Dr",
    "iso:country":"US",
    "sg:address":"79 Sugarloaf Dr",
    "sg:city":"Pagosa Springs",
    "sg:classifiers":[
        {
            "category":"Building & Trades",
            "subcategory":"Construction",
            "type":"Services"
        }
    ],
    "sg:phone":"+1 970 731 9911",
    "sg:postcode":"81147",
    "sg:province":"CO",
    "sg:tags":[
        "home",
        "builder"
    ],
    "wof:name":"Brule Brothers Contracting",
    "wof:placetype":"venue"
},
  "geometry": {"coordinates":[-107.129001,37.312992],"type":"Point"}
}