{
  "type": "Feature",
  "properties": {
    "iso:country":"US",
    "sg:address":"6900 E Belleview Ave",
    "sg:city":"Englewood",
    "sg:classifiers":[
        {
            "category":"Professional",
            "subcategory":"Accounting & Tax Preparation",
            "type":"Services"
        }
    ],
    "sg:phone":"+1 303 779 5034",
    "sg:postcode":"80111",
    "sg:province":"CO",
    "wof:name":"Haskins & Associates PC",
    "wof:placetype":"venue"
},
  "geometry": {"coordinates":[-104.907618,39.624211],"type":"Point"}
}