{
  "type": "Feature",
  "properties": {
    "addr:full":"8233 State Hwy 15 S Monte Vista CO 81144",
    "addr:housenumber":"8233",
    "addr:postcode":"81144",
    "addr:street":"State Hwy 15 S",
    "iso:country":"US",
    "sg:address":"8233 State Hwy 15 S",
    "sg:city":"Monte Vista",
    "sg:classifiers":[
        {
            "category":"Freight",
            "type":"Transportation"
        }
    ],
    "sg:phone":"+1 719 852 3015",
    "sg:postcode":"81144",
    "sg:province":"CO",
    "sg:tags":[
        "operator",
        "local",
        "trucking"
    ],
    "wof:name":"Sawyer Firms & Trucking",
    "wof:placetype":"venue"
},
  "geometry": {"coordinates":[-106.148415,37.455346],"type":"Point"}
}