{
  "type": "Feature",
  "properties": {
    "addr:full":"1852 Jasper St Aurora CO 80011",
    "addr:housenumber":"1852",
    "addr:postcode":"80011",
    "addr:street":"Jasper St",
    "iso:country":"US",
    "sg:address":"1852 Jasper St",
    "sg:city":"Aurora",
    "sg:classifiers":[
        {
            "category":"Professional",
            "type":"Services"
        }
    ],
    "sg:phone":"+1 720 859 6722",
    "sg:postcode":"80011",
    "sg:province":"CO",
    "wof:name":"Bobbi Grear",
    "wof:placetype":"venue"
},
  "geometry": {"coordinates":[-104.806059,39.745705],"type":"Point"}
}