{
  "type": "Feature",
  "properties": {
    "iso:country":"US",
    "sg:address":"7935 Forest Heights Cir",
    "sg:city":"Colorado Springs",
    "sg:classifiers":[
        {
            "category":"Shopping",
            "subcategory":"Beauty & Cosmetics",
            "type":"Retail Goods"
        }
    ],
    "sg:phone":"+1 719 495 4901",
    "sg:postcode":"80908",
    "sg:province":"CO",
    "sg:tags":[
        "merchandise"
    ],
    "wof:name":"Indepndenta Agt Mary Kay Cosmt",
    "wof:placetype":"venue"
},
  "geometry": {"coordinates":[-104.679852,39.018873],"type":"Point"}
}