{
  "type": "Feature",
  "properties": {
    "addr:full":"1115 E Rainbow Blvd Salida CO 81201",
    "addr:housenumber":"1115",
    "addr:postcode":"81201",
    "addr:street":"E Rainbow Blvd",
    "iso:country":"US",
    "sg:address":"1115 E Rainbow Blvd",
    "sg:city":"Salida",
    "sg:classifiers":[
        {
            "category":"Insurance",
            "subcategory":"Hazard Insurance",
            "type":"Services"
        }
    ],
    "sg:phone":"+1 719 539 9000",
    "sg:postcode":"81201",
    "sg:province":"CO",
    "sg:tags":[
        "bond"
    ],
    "wof:name":"AAA/Asap Bonding",
    "wof:placetype":"venue"
},
  "geometry": {"coordinates":[-105.989375,38.524132],"type":"Point"}
}