{
  "type": "Feature",
  "properties": {
    "iso:country":"US",
    "sg:address":"105 S Cherokee St",
    "sg:city":"Denver",
    "sg:classifiers":[
        {
            "category":"Wholesale",
            "subcategory":"Non-durable Goods",
            "type":"Manufacturing & Wholesale Goods"
        }
    ],
    "sg:phone":"+1 303 733 7660",
    "sg:postcode":"80223",
    "sg:province":"CO",
    "sg:tags":[
        "oil",
        "for",
        "spill"
    ],
    "sg:website":"www.seasweep.com",
    "wof:name":"Sea Sweep Inc",
    "wof:placetype":"venue"
},
  "geometry": {"coordinates":[-104.992439,39.714],"type":"Point"}
}