{
  "type": "Feature",
  "properties": {
    "addr:full":"8600 Ralston Rd Arvada CO 80002",
    "addr:housenumber":"8600",
    "addr:postcode":"80002",
    "addr:street":"Ralston Rd",
    "iso:country":"US",
    "sg:address":"8600 Ralston Rd",
    "sg:city":"Arvada",
    "sg:classifiers":[
        {
            "category":"Personal",
            "subcategory":"Massage",
            "type":"Services"
        },
        {
            "category":"Personal",
            "subcategory":"Beauty Salon",
            "type":"Services"
        }
    ],
    "sg:phone":"+1 303 424 1042",
    "sg:postcode":"80002",
    "sg:province":"CO",
    "wof:name":"Oasis Day Spa Ltd",
    "wof:placetype":"venue"
},
  "geometry": {"coordinates":[-105.09343699999999,39.80204],"type":"Point"}
}