{
  "type": "Feature",
  "properties": {
    "iso:country":"US",
    "sg:address":"996 S Gilpin St",
    "sg:city":"Denver",
    "sg:classifiers":[
        {
            "category":"Banks & Credit Unions",
            "subcategory":"Financial Services",
            "type":"Services"
        }
    ],
    "sg:phone":"+1 303 744 6711",
    "sg:postcode":"80209",
    "sg:province":"CO",
    "sg:tags":[
        "investor"
    ],
    "wof:name":"SGB Capital Corporation",
    "wof:placetype":"venue"
},
  "geometry": {"coordinates":[-104.967491,39.700183],"type":"Point"}
}