{
  "type": "Feature",
  "properties": {
    "addr:full":"965 Venhorst Rd Colorado Springs CO 80920",
    "addr:housenumber":"965",
    "addr:postcode":"80920",
    "addr:street":"Venhorst Rd",
    "iso:country":"US",
    "sg:address":"965 Venhorst Rd",
    "sg:city":"Colorado Springs",
    "sg:classifiers":[
        {
            "category":"Banks & Credit Unions",
            "subcategory":"Financial Services",
            "type":"Services"
        }
    ],
    "sg:phone":"+1 719 598 2112",
    "sg:postcode":"80920",
    "sg:province":"CO",
    "sg:tags":[
        "trust",
        "nonprofit",
        "management"
    ],
    "wof:name":"Slack Family Partnership",
    "wof:placetype":"venue"
},
  "geometry": {"coordinates":[-104.807351,38.935608],"type":"Point"}
}