{
  "type": "Feature",
  "properties": {
    "iso:country":"US",
    "sg:address":"10836 E Crestline Pl",
    "sg:city":"Englewood",
    "sg:classifiers":[
        {
            "category":"Professional",
            "subcategory":"Management & Consulting",
            "type":"Services"
        }
    ],
    "sg:phone":"+1 303 741 4821",
    "sg:postcode":"80111",
    "sg:province":"CO",
    "sg:tags":[
        "consultant",
        "security",
        "system"
    ],
    "sg:website":"www.philipbwayne.com",
    "wof:name":"Philip B Wayne Consultants Inc",
    "wof:placetype":"venue"
},
  "geometry": {"coordinates":[-104.86311000000001,39.617909],"type":"Point"}
}