{
  "type": "Feature",
  "properties": {
    "addr:full":"122 N Main St Eckley CO 80727",
    "addr:housenumber":"122",
    "addr:postcode":"80727",
    "addr:street":"N Main St",
    "iso:country":"US",
    "sg:address":"122 N Main St",
    "sg:city":"Eckley",
    "sg:classifiers":[
        {
            "category":"Government",
            "subcategory":"Fire Station",
            "type":"Public Place"
        }
    ],
    "sg:phone":"+1 970 359 2300",
    "sg:postcode":"80727",
    "sg:province":"CO",
    "sg:tags":[
        "department"
    ],
    "wof:name":"Eckley Fire Dept",
    "wof:placetype":"venue"
},
  "geometry": {"coordinates":[-102.489473,40.113164],"type":"Point"}
}