{
  "type": "Feature",
  "properties": {
    "addr:full":"571 N Academy Blvd Colorado Springs CO 80909",
    "addr:housenumber":"571",
    "addr:postcode":"80909",
    "addr:street":"N Academy Blvd",
    "iso:country":"US",
    "sg:address":"571 N Academy Blvd",
    "sg:city":"Colorado Springs",
    "sg:classifiers":[
        {
            "category":"Retail",
            "subcategory":"Veterinary Services",
            "type":"Services"
        }
    ],
    "sg:phone":"+1 719 638 9631",
    "sg:postcode":"80909",
    "sg:province":"CO",
    "sg:tags":[
        "veterinarian"
    ],
    "wof:name":"Banfield The Pet Hospital",
    "wof:placetype":"venue"
},
  "geometry": {"coordinates":[-104.75744299999999,38.841803],"type":"Point"}
}