{
  "type": "Feature",
  "properties": {
    "iso:country":"US",
    "sg:address":"12000 Washington St",
    "sg:city":"Denver",
    "sg:classifiers":[
        {
            "category":"Insurance",
            "subcategory":"Hazard Insurance",
            "type":"Services"
        }
    ],
    "sg:phone":"+1 303 457 4311",
    "sg:postcode":"80241",
    "sg:province":"CO",
    "sg:tags":[
        "carrier"
    ],
    "wof:name":"Aspen Insurance Agency Inc",
    "wof:placetype":"venue"
},
  "geometry": {"coordinates":[-104.97782100000001,39.919353],"type":"Point"}
}