{
  "type": "Feature",
  "properties": {
    "iso:country":"US",
    "sg:address":"10201 Co Rd 69.3",
    "sg:city":"Trinidad",
    "sg:classifiers":[
        {
            "category":"Government",
            "subcategory":"Police Station",
            "type":"Public Place"
        }
    ],
    "sg:phone":"+1 719 846 2227",
    "sg:postcode":"81082",
    "sg:province":"CO",
    "sg:tags":[
        "state",
        "patrol"
    ],
    "wof:name":"Colorado State Patrol 810",
    "wof:placetype":"venue"
},
  "geometry": {"coordinates":[-104.519723,37.135964],"type":"Point"}
}