{
  "type": "Feature",
  "properties": {
    "iso:country":"US",
    "sg:address":"801 W 62nd Ave",
    "sg:city":"Denver",
    "sg:classifiers":[
        {
            "category":"Manufacturing",
            "subcategory":"Glass & Minerals",
            "type":"Manufacturing & Wholesale Goods"
        }
    ],
    "sg:phone":"+1 303 254 8846",
    "sg:postcode":"80221",
    "sg:province":"CO",
    "sg:tags":[
        "concrete"
    ],
    "wof:name":"Venture Retaining Wall Systems",
    "wof:placetype":"venue"
},
  "geometry": {"coordinates":[-105.00201199999999,39.809127],"type":"Point"}
}