{
  "type": "Feature",
  "properties": {
    "iso:country":"US",
    "sg:address":"6086 W Floyd Ave",
    "sg:city":"Denver",
    "sg:classifiers":[
        {
            "category":"Retail",
            "subcategory":"Repair Shop",
            "type":"Services"
        }
    ],
    "sg:phone":"+1 303 989 7466",
    "sg:postcode":"80227",
    "sg:province":"CO",
    "wof:name":"Exceptional House Cleaning",
    "wof:placetype":"venue"
},
  "geometry": {"coordinates":[-105.064193,39.655552],"type":"Point"}
}