{
  "type": "Feature",
  "properties": {
    "iso:country":"US",
    "sg:address":"615 W Platte Ave",
    "sg:city":"Fort Morgan",
    "sg:classifiers":[
        {
            "category":"Retail",
            "subcategory":"Self-service Laundry",
            "type":"Services"
        }
    ],
    "sg:phone":"+1 970 867 9920",
    "sg:postcode":"80701",
    "sg:province":"CO",
    "wof:name":"Lady-Saver Laundromat",
    "wof:placetype":"venue"
},
  "geometry": {"coordinates":[-103.80995,40.254089],"type":"Point"}
}