{
  "type": "Feature",
  "properties": {
    "addr:full":"905 N Main St Gunnison CO 81230",
    "addr:housenumber":"905",
    "addr:postcode":"81230",
    "addr:street":"N Main St",
    "iso:country":"US",
    "sg:address":"905 N Main St",
    "sg:city":"Gunnison",
    "sg:classifiers":[
        {
            "category":"Food & Beverages",
            "subcategory":"Groceries & Convenience Stores",
            "type":"Retail Goods"
        }
    ],
    "sg:phone":"+1 970 641 4729",
    "sg:postcode":"81230",
    "sg:province":"CO",
    "sg:tags":[
        "grocer"
    ],
    "wof:name":"Van's Food Store",
    "wof:placetype":"venue"
},
  "geometry": {"coordinates":[-106.92698,38.553409],"type":"Point"}
}