{
  "type": "Feature",
  "properties": {
    "iso:country":"US",
    "sg:address":"2967 Foothills Ranch Dr",
    "sg:city":"Boulder",
    "sg:classifiers":[
        {
            "category":"Banks & Credit Unions",
            "subcategory":"Financial Services",
            "type":"Services"
        }
    ],
    "sg:phone":"+1 303 448 0117",
    "sg:postcode":"80302",
    "sg:province":"CO",
    "sg:tags":[
        "management",
        "open",
        "investment"
    ],
    "wof:name":"Goldfarb Management",
    "wof:placetype":"venue"
},
  "geometry": {"coordinates":[-105.283931,40.151235],"type":"Point"}
}