{
  "type": "Feature",
  "properties": {
    "iso:country":"US",
    "sg:address":"522 Lincoln Ave",
    "sg:city":"Steamboat Spgs",
    "sg:classifiers":[
        {
            "category":"Government",
            "subcategory":"Office",
            "type":"Public Place"
        }
    ],
    "sg:phone":"+1 970 879 7265",
    "sg:postcode":"80477",
    "sg:province":"CO",
    "sg:tags":[
        "state",
        "program",
        "health"
    ],
    "wof:name":"Alcohol & Drug Evaluator",
    "wof:placetype":"venue"
},
  "geometry": {"coordinates":[-106.832204,40.484766],"type":"Point"}
}