{
  "type": "Feature",
  "properties": {
    "iso:country":"US",
    "sg:address":"2801 Remington St",
    "sg:city":"Fort Collins",
    "sg:classifiers":[
        {
            "category":"Health Services",
            "subcategory":"Chiropractor",
            "type":"Services"
        }
    ],
    "sg:phone":"+1 970 229 9993",
    "sg:postcode":"80525",
    "sg:province":"CO",
    "wof:name":"Chiropractic Works",
    "wof:placetype":"venue"
},
  "geometry": {"coordinates":[-105.075817,40.548097],"type":"Point"}
}