{
  "type": "Feature",
  "properties": {
    "addr:full":"582 Eagle Ave Akron CO 80720",
    "addr:housenumber":"582",
    "addr:postcode":"80720",
    "addr:street":"Eagle Ave",
    "iso:country":"US",
    "sg:address":"582 Eagle Ave",
    "sg:city":"Akron",
    "sg:classifiers":[
        {
            "category":"Building & Trades",
            "subcategory":"Construction",
            "type":"Services"
        }
    ],
    "sg:phone":"+1 970 345 6400",
    "sg:postcode":"80720",
    "sg:province":"CO",
    "sg:tags":[
        "excavation",
        "contractor"
    ],
    "wof:name":"Slusser Brothers Construction",
    "wof:placetype":"venue"
},
  "geometry": {"coordinates":[-103.219697,40.163544],"type":"Point"}
}