{
  "type": "Feature",
  "properties": {
    "addr:full":"616 Kimbark St Longmont CO 80501",
    "addr:housenumber":"616",
    "addr:postcode":"80501",
    "addr:street":"Kimbark St",
    "iso:country":"US",
    "sg:address":"616 Kimbark St",
    "sg:city":"Longmont",
    "sg:classifiers":[
        {
            "category":"Building & Trades",
            "subcategory":"Landscaping Services",
            "type":"Services"
        }
    ],
    "sg:phone":"+1 303 682 0854",
    "sg:postcode":"80501",
    "sg:province":"CO",
    "sg:tags":[
        "designer",
        "landscape"
    ],
    "wof:name":"Play Environments LLC",
    "wof:placetype":"venue"
},
  "geometry": {"coordinates":[-105.10109300000001,40.17041],"type":"Point"}
}