{
  "type": "Feature",
  "properties": {
    "addr:full":"1109 Country Acres Dr Johnstown CO 80534",
    "addr:housenumber":"1109",
    "addr:postcode":"80534",
    "addr:street":"Country Acres Dr",
    "iso:country":"US",
    "sg:address":"1109 Country Acres Dr",
    "sg:city":"Johnstown",
    "sg:classifiers":[
        {
            "category":"Wholesale",
            "subcategory":"Drugs",
            "type":"Manufacturing & Wholesale Goods"
        }
    ],
    "sg:phone":"+1 970 587 8605",
    "sg:postcode":"80534",
    "sg:province":"CO",
    "sg:tags":[
        "pharmaceutical"
    ],
    "wof:name":"Eli Lilly and Company",
    "wof:placetype":"venue"
},
  "geometry": {"coordinates":[-104.91819099999999,40.332003],"type":"Point"}
}