{
  "type": "Feature",
  "properties": {
    "iso:country":"US",
    "sg:address":"5754 S Lowell Way",
    "sg:city":"Littleton",
    "sg:classifiers":[
        {
            "category":"Real Estate",
            "subcategory":"Real Estate Operator",
            "type":"Services"
        }
    ],
    "sg:phone":"+1 303 794 2241",
    "sg:postcode":"80123",
    "sg:province":"CO",
    "sg:tags":[
        "building",
        "apartment"
    ],
    "wof:name":"Canyon Crest Apartments",
    "wof:placetype":"venue"
},
  "geometry": {"coordinates":[-105.03554699999999,39.611973],"type":"Point"}
}