{
  "type": "Feature",
  "properties": {
    "addr:full":"2375 E 1st Ave Denver CO 80206",
    "addr:housenumber":"2375",
    "addr:postcode":"80206",
    "addr:street":"E 1St Ave",
    "iso:country":"US",
    "sg:address":"2375 E 1st Ave",
    "sg:city":"Denver",
    "sg:classifiers":[
        {
            "category":"Professional",
            "subcategory":"Accounting & Tax Preparation",
            "type":"Services"
        }
    ],
    "sg:phone":"+1 303 399 6593",
    "sg:postcode":"80206",
    "sg:province":"CO",
    "sg:tags":[
        "return",
        "filing"
    ],
    "wof:name":"H & R Block Tax Svc",
    "wof:placetype":"venue"
},
  "geometry": {"coordinates":[-104.955158,39.718283],"type":"Point"}
}