{
  "type": "Feature",
  "properties": {
    "addr:full":"237 N Main St Gunnison CO 81230",
    "addr:housenumber":"237",
    "addr:postcode":"81230",
    "addr:street":"N Main St",
    "iso:country":"US",
    "sg:address":"237 N Main St",
    "sg:city":"Gunnison",
    "sg:classifiers":[
        {
            "category":"Retail",
            "subcategory":"Laundry & Dry Cleaning",
            "type":"Services"
        }
    ],
    "sg:phone":"+1 970 641 0152",
    "sg:postcode":"81230",
    "sg:province":"CO",
    "sg:tags":[
        "cleaners"
    ],
    "wof:name":"French Electric Cleaner",
    "wof:placetype":"venue"
},
  "geometry": {"coordinates":[-106.926996,38.546107],"type":"Point"}
}