{
  "type": "Feature",
  "properties": {
    "addr:full":"3518 S Broadway Englewood CO 80113",
    "addr:housenumber":"3518",
    "addr:postcode":"80113",
    "addr:street":"S Broadway",
    "iso:country":"US",
    "sg:address":"3518 S Broadway",
    "sg:city":"Englewood",
    "sg:classifiers":[
        {
            "category":"Food & Beverages",
            "subcategory":"Groceries & Convenience Stores",
            "type":"Retail Goods"
        }
    ],
    "sg:phone":"+1 303 761 2971",
    "sg:postcode":"80113",
    "sg:province":"CO",
    "wof:name":"Westing Trading Co",
    "wof:placetype":"venue"
},
  "geometry": {"coordinates":[-104.98757999999999,39.653111],"type":"Point"}
}