{
  "type": "Feature",
  "properties": {
    "iso:country":"US",
    "sg:address":"132 W Elkhorn Ave",
    "sg:city":"Estes Park",
    "sg:classifiers":[
        {
            "category":"Shopping",
            "type":"Retail Goods"
        }
    ],
    "sg:phone":"+1 970 586 8567",
    "sg:postcode":"80517",
    "sg:province":"CO",
    "sg:tags":[
        "art",
        "gallery",
        "dealer"
    ],
    "wof:name":"DMS Gallery LTD",
    "wof:placetype":"venue"
},
  "geometry": {"coordinates":[-105.52441,40.376061],"type":"Point"}
}