{
  "type": "Feature",
  "properties": {
    "addr:full":"17584 E Belleview Pl Aurora CO 80015",
    "addr:housenumber":"17584",
    "addr:postcode":"80015",
    "addr:street":"E Belleview Pl",
    "iso:country":"US",
    "sg:address":"17584 E Belleview Pl",
    "sg:city":"Aurora",
    "sg:classifiers":[
        {
            "category":"Travel",
            "subcategory":"Travel Agent",
            "type":"Entertainment"
        }
    ],
    "sg:phone":"+1 303 699 5286",
    "sg:postcode":"80015",
    "sg:province":"CO",
    "sg:tags":[
        "agency"
    ],
    "wof:name":"R&R Travel",
    "wof:placetype":"venue"
},
  "geometry": {"coordinates":[-104.784147,39.623754],"type":"Point"}
}