{
  "type": "Feature",
  "properties": {
    "addr:full":"9330 Osceola St Westminster CO 80031",
    "addr:housenumber":"9330",
    "addr:postcode":"80031",
    "addr:street":"Osceola St",
    "iso:country":"US",
    "sg:address":"9330 Osceola St",
    "sg:city":"Westminster",
    "sg:classifiers":[
        {
            "category":"Real Estate",
            "subcategory":"Real Estate Agent",
            "type":"Services"
        }
    ],
    "sg:phone":"+1 303 426 1755",
    "sg:postcode":"80031",
    "sg:province":"CO",
    "sg:tags":[
        "management"
    ],
    "wof:name":"Dencol Real Estate Services",
    "wof:placetype":"venue"
},
  "geometry": {"coordinates":[-105.03743900000001,39.864744],"type":"Point"}
}