{
  "type": "Feature",
  "properties": {
    "addr:full":"2727 Nelson Rd Longmont CO 80503",
    "addr:housenumber":"2727",
    "addr:postcode":"80503",
    "addr:street":"Nelson Rd",
    "iso:country":"US",
    "sg:address":"2727 Nelson Rd",
    "sg:city":"Longmont",
    "sg:classifiers":[
        {
            "category":"Government",
            "subcategory":"Office",
            "type":"Public Place"
        }
    ],
    "sg:phone":"+1 720 652 0509",
    "sg:postcode":"80503",
    "sg:province":"CO",
    "sg:tags":[
        "management"
    ],
    "wof:name":"Mun Sing Loh",
    "wof:placetype":"venue"
},
  "geometry": {"coordinates":[-105.133509,40.152418],"type":"Point"}
}