{
  "type": "Feature",
  "properties": {
    "addr:full":"555 Ln 9 N Monte Vista CO 81144",
    "addr:housenumber":"9",
    "addr:postcode":"81144",
    "addr:street":"555 Ln;N Monte",
    "iso:country":"US",
    "sg:address":"555 Ln 9 N",
    "sg:city":"Monte Vista",
    "sg:classifiers":[
        {
            "category":"Home & Garden",
            "subcategory":"Garden Supply",
            "type":"Retail Goods"
        }
    ],
    "sg:phone":"+1 719 754 2582",
    "sg:postcode":"81144",
    "sg:province":"CO",
    "sg:tags":[
        "sprinkler"
    ],
    "wof:name":"Oasis Lawn & Garden Irrigation",
    "wof:placetype":"venue"
},
  "geometry": {"coordinates":[-106.029825,37.704994],"type":"Point"}
}