{
  "type": "Feature",
  "properties": {
    "addr:full":"3008 Folsom St Boulder CO 80304",
    "addr:housenumber":"3008",
    "addr:postcode":"80304",
    "addr:street":"Folsom St",
    "iso:country":"US",
    "sg:address":"3008 Folsom St",
    "sg:city":"Boulder",
    "sg:classifiers":[
        {
            "category":"Real Estate",
            "subcategory":"Architect",
            "type":"Services"
        }
    ],
    "sg:phone":"+1 303 444 6902",
    "sg:postcode":"80304",
    "sg:province":"CO",
    "sg:website":"www.arch-inc.com",
    "wof:name":"Architecture Inc",
    "wof:placetype":"venue"
},
  "geometry": {"coordinates":[-105.263105,40.03098],"type":"Point"}
}