{
  "type": "Feature",
  "properties": {
    "iso:country":"US",
    "sg:address":"425 S Cherry Street Suite 420",
    "sg:city":"Denver",
    "sg:classifiers":[
        {
            "category":"Insurance",
            "subcategory":"Insurance Agent",
            "type":"Services"
        },
        {
            "category":"Insurance",
            "subcategory":"Hazard Insurance",
            "type":"Services"
        },
        {
            "category":"Insurance",
            "subcategory":"Title Insurance",
            "type":"Services"
        },
        {
            "category":"Insurance",
            "subcategory":"Health Insurance",
            "type":"Services"
        }
    ],
    "sg:phone":"+1 303 322 0800",
    "sg:postcode":"80246",
    "sg:province":"CO",
    "sg:tags":[
        "group",
        "business",
        "commercial",
        "worker",
        "homeowner",
        "compensation",
        "consultant",
        "disability",
        "analyst"
    ],
    "sg:website":"www.madisoninsurance.net",
    "wof:name":"Madison Insurance Group",
    "wof:placetype":"venue"
},
  "geometry": {"coordinates":[-104.934187,39.70896],"type":"Point"}
}