{
  "type": "Feature",
  "properties": {
    "addr:full":"324 Coryell Ridge Rd Glenwood Springs CO 81601",
    "addr:housenumber":"324",
    "addr:postcode":"81601",
    "addr:street":"Coryell Ridge Rd",
    "iso:country":"US",
    "sg:address":"324 Coryell Ridge Rd",
    "sg:city":"Glenwood Springs",
    "sg:classifiers":[
        {
            "category":"Building & Trades",
            "subcategory":"Plumbing",
            "type":"Services"
        }
    ],
    "sg:phone":"+1 970 945 5519",
    "sg:postcode":"81601",
    "sg:province":"CO",
    "sg:tags":[
        "plumbing",
        "contractor"
    ],
    "wof:name":"Roto-Rooter Plumbing & Drain",
    "wof:placetype":"venue"
},
  "geometry": {"coordinates":[-107.27182999999999,39.470286],"type":"Point"}
}