{
  "type": "Feature",
  "properties": {
    "addr:full":"5225 E Colfax Ave Denver CO 80220",
    "addr:housenumber":"5225",
    "addr:postcode":"80220",
    "addr:street":"E Colfax Ave",
    "iso:country":"US",
    "sg:address":"5225 E Colfax Ave",
    "sg:city":"Denver",
    "sg:classifiers":[
        {
            "category":"Restaurant",
            "type":"Food & Drink"
        }
    ],
    "sg:menulink":"http://www.allmenus.com/co/denver/207891-taco-bell/menu/",
    "sg:phone":"+1 303 322 2934",
    "sg:postcode":"80220",
    "sg:province":"CO",
    "sg:tags":[
        "mexican"
    ],
    "wof:name":"Taco Bell",
    "wof:placetype":"venue"
},
  "geometry": {"coordinates":[-104.92653900000001,39.740385],"type":"Point"}
}