{
  "type": "Feature",
  "properties": {
    "iso:country":"US",
    "sg:address":"336 Adams St",
    "sg:city":"Naturita",
    "sg:classifiers":[
        {
            "category":"Education",
            "subcategory":"School",
            "type":"Public Place"
        }
    ],
    "sg:phone":"+1 970 865 2597",
    "sg:postcode":"81422",
    "sg:province":"CO",
    "sg:tags":[
        "academic",
        "special"
    ],
    "wof:name":"W E Learning Ctr",
    "wof:placetype":"venue"
},
  "geometry": {"coordinates":[-108.573502,38.218682],"type":"Point"}
}