{
  "type": "Feature",
  "properties": {
    "addr:full":"95 Cody Trl Ward CO 80455",
    "addr:housenumber":"95",
    "addr:postcode":"80455",
    "addr:street":"Cody Trl",
    "iso:country":"US",
    "sg:address":"95 Cody Trl",
    "sg:city":"Ward",
    "sg:classifiers":[
        {
            "category":"Real Estate",
            "subcategory":"Real Estate Agent",
            "type":"Services"
        }
    ],
    "sg:phone":"+1 303 459 0200",
    "sg:postcode":"80455",
    "sg:province":"CO",
    "wof:name":"Diesing Real Estate",
    "wof:placetype":"venue"
},
  "geometry": {"coordinates":[-105.43575199999999,40.121057],"type":"Point"}
}