{
  "type": "Feature",
  "properties": {
    "iso:country":"US",
    "sg:address":"20395 E Top-T Ranch Pl",
    "sg:city":"Parker",
    "sg:classifiers":[
        {
            "category":"Professional",
            "type":"Services"
        }
    ],
    "sg:phone":"+1 303 484 8882",
    "sg:postcode":"80134",
    "sg:province":"CO",
    "wof:name":"Spring Darek",
    "wof:placetype":"venue"
},
  "geometry": {"coordinates":[-104.752821,39.488483],"type":"Point"}
}