{
  "type": "Feature",
  "properties": {
    "addr:full":"12900 E Colfax Ave Aurora CO 80011",
    "addr:housenumber":"12900",
    "addr:postcode":"80011",
    "addr:street":"E Colfax Ave",
    "iso:country":"US",
    "sg:address":"12900 E Colfax Ave",
    "sg:city":"Aurora",
    "sg:classifiers":[
        {
            "category":"Real Estate",
            "subcategory":"Developer",
            "type":"Services"
        }
    ],
    "sg:phone":"+1 303 364 1720",
    "sg:postcode":"80011",
    "sg:province":"CO",
    "sg:tags":[
        "mobile",
        "home"
    ],
    "wof:name":"Capri Mobile Home Park",
    "wof:placetype":"venue"
},
  "geometry": {"coordinates":[-104.840401,39.740308],"type":"Point"}
}