{
  "type": "Feature",
  "properties": {
    "addr:full":"5480 Reed St Arvada CO 80002",
    "addr:housenumber":"5480",
    "addr:postcode":"80002",
    "addr:street":"Reed St",
    "iso:country":"US",
    "sg:address":"5480 Reed St",
    "sg:city":"Arvada",
    "sg:classifiers":[
        {
            "category":"Freight",
            "type":"Transportation"
        }
    ],
    "sg:phone":"+1 303 467 7768",
    "sg:postcode":"80002",
    "sg:province":"CO",
    "sg:tags":[
        "agent"
    ],
    "wof:name":"Timberline Transportation Inc",
    "wof:placetype":"venue"
},
  "geometry": {"coordinates":[-105.074071,39.794543],"type":"Point"}
}