{
  "type": "Feature",
  "properties": {
    "addr:full":"1941 Samuel Dr Denver CO 80221",
    "addr:housenumber":"1941",
    "addr:postcode":"80221",
    "addr:street":"Samuel Dr",
    "iso:country":"US",
    "sg:address":"1941 Samuel Dr",
    "sg:city":"Denver",
    "sg:classifiers":[
        {
            "category":"Building & Trades",
            "subcategory":"Plumbing",
            "type":"Services"
        }
    ],
    "sg:phone":"+1 303 429 6129",
    "sg:postcode":"80221",
    "sg:province":"CO",
    "sg:tags":[
        "plumbing",
        "contractor"
    ],
    "wof:name":"L & M Svc",
    "wof:placetype":"venue"
},
  "geometry": {"coordinates":[-105.012169,39.831622],"type":"Point"}
}