{
  "type": "Feature",
  "properties": {
    "addr:full":"706 Heather Dr Loveland CO 80537",
    "addr:housenumber":"706",
    "addr:postcode":"80537",
    "addr:street":"Heather Dr",
    "iso:country":"US",
    "sg:address":"706 Heather Dr",
    "sg:city":"Loveland",
    "sg:classifiers":[
        {
            "category":"Professional",
            "subcategory":"Lawyer & Legal Services",
            "type":"Services"
        }
    ],
    "sg:phone":"+1 303 919 7916",
    "sg:postcode":"80537",
    "sg:province":"CO",
    "sg:tags":[
        "attorney"
    ],
    "wof:name":"Wendt Law Offices",
    "wof:placetype":"venue"
},
  "geometry": {"coordinates":[-105.10403700000001,40.384819],"type":"Point"}
}