{
  "type": "Feature",
  "properties": {
    "addr:full":"26291 Main St Conifer CO 80433",
    "addr:housenumber":"26291",
    "addr:postcode":"80433",
    "addr:street":"Main St",
    "iso:country":"US",
    "sg:address":"26291 Main St",
    "sg:city":"Conifer",
    "sg:classifiers":[
        {
            "category":"Banks & Credit Unions",
            "subcategory":"Bank",
            "type":"Services"
        }
    ],
    "sg:phone":"+1 303 674 0649",
    "sg:postcode":"80433",
    "sg:province":"CO",
    "wof:name":"Bank Of The West",
    "wof:placetype":"venue"
},
  "geometry": {"coordinates":[-105.299485,39.538554],"type":"Point"}
}