{
  "type": "Feature",
  "properties": {
    "addr:full":"1775 Merlin Ln Windsor CO 80550",
    "addr:housenumber":"1775",
    "addr:postcode":"80550",
    "addr:street":"Merlin Ln",
    "iso:country":"US",
    "sg:address":"1775 Merlin Ln",
    "sg:city":"Windsor",
    "sg:classifiers":[
        {
            "category":"Building & Trades",
            "subcategory":"Construction",
            "type":"Services"
        }
    ],
    "sg:phone":"+1 970 686 9105",
    "sg:postcode":"80550",
    "sg:province":"CO",
    "sg:tags":[
        "hanging",
        "contractor"
    ],
    "wof:name":"Parrott Painting Inc",
    "wof:placetype":"venue"
},
  "geometry": {"coordinates":[-104.919308,40.452081],"type":"Point"}
}