{
  "type": "Feature",
  "properties": {
    "iso:country":"US",
    "sg:address":"5200 Hahns Peak Dr",
    "sg:city":"Loveland",
    "sg:classifiers":[
        {
            "category":"Professional",
            "subcategory":"Computer Services",
            "type":"Services"
        }
    ],
    "sg:phone":"+1 970 663 5700",
    "sg:postcode":"80538",
    "sg:province":"CO",
    "sg:tags":[
        "information",
        "datum"
    ],
    "wof:name":"Kroll Government Services",
    "wof:placetype":"venue"
},
  "geometry": {"coordinates":[-105.007897,40.412649],"type":"Point"}
}