{
  "type": "Feature",
  "properties": {
    "addr:full":"19704 Co Rd 87 Orchard CO 80649",
    "addr:housenumber":"19704;87 orchard",
    "addr:postcode":"80649",
    "addr:street":"Co Rd",
    "iso:country":"US",
    "sg:address":"19704 Co Rd 87",
    "sg:city":"Orchard",
    "sg:classifiers":[
        {
            "category":"Retail",
            "subcategory":"Animal Services",
            "type":"Services"
        }
    ],
    "sg:phone":"+1 970 645 2225",
    "sg:postcode":"80649",
    "sg:province":"CO",
    "wof:name":"Kingsbury Ranch",
    "wof:placetype":"venue"
},
  "geometry": {"coordinates":[-104.24456499999999,40.288812],"type":"Point"}
}