{
  "type": "Feature",
  "properties": {
    "iso:country":"US",
    "sg:address":"2926 Zuni St",
    "sg:city":"Denver",
    "sg:classifiers":[
        {
            "category":"Professional",
            "subcategory":"Management & Consulting",
            "type":"Services"
        }
    ],
    "sg:phone":"+1 303 477 3756",
    "sg:postcode":"80211",
    "sg:province":"CO",
    "sg:tags":[
        "fuel"
    ],
    "wof:name":"Continental Divide Management",
    "wof:placetype":"venue"
},
  "geometry": {"coordinates":[-105.01576,39.758637],"type":"Point"}
}