{
  "type": "Feature",
  "properties": {
    "iso:country":"US",
    "sg:address":"243 N College Ave",
    "sg:city":"Fort Collins",
    "sg:classifiers":[
        {
            "category":"Retail",
            "subcategory":"Car Wash",
            "type":"Services"
        }
    ],
    "sg:phone":"+1 970 482 4895",
    "sg:postcode":"80524",
    "sg:province":"CO",
    "sg:tags":[
        "carwash",
        "detailing",
        "center"
    ],
    "wof:name":"Autawash of Colorado LLC",
    "wof:placetype":"venue"
},
  "geometry": {"coordinates":[-105.07708,40.590096],"type":"Point"}
}