{
  "type": "Feature",
  "properties": {
    "addr:full":"7120 Campus Dr Colorado Springs CO 80920",
    "addr:housenumber":"7120",
    "addr:postcode":"80920",
    "addr:street":"Campus Dr",
    "iso:country":"US",
    "sg:address":"7120 Campus Dr",
    "sg:city":"Colorado Springs",
    "sg:classifiers":[
        {
            "category":"Restaurant",
            "type":"Food & Drink"
        }
    ],
    "sg:phone":"+1 719 264 0401",
    "sg:postcode":"80920",
    "sg:province":"CO",
    "sg:tags":[
        "italian"
    ],
    "wof:name":"Carrabbas Italian Grill Inc",
    "wof:placetype":"venue"
},
  "geometry": {"coordinates":[-104.81038700000001,38.934441],"type":"Point"}
}