{
  "type": "Feature",
  "properties": {
    "iso:country":"US",
    "sg:address":"101 Remington St",
    "sg:city":"Fort Collins",
    "sg:classifiers":[
        {
            "category":"Real Estate",
            "subcategory":"Real Estate Agent",
            "type":"Services"
        }
    ],
    "sg:phone":"+1 970 484 1345",
    "sg:postcode":"80524",
    "sg:province":"CO",
    "wof:name":"Vantage Properties",
    "wof:placetype":"venue"
},
  "geometry": {"coordinates":[-105.075532,40.586439],"type":"Point"}
}