{
  "type": "Feature",
  "properties": {
    "addr:full":"1494 Clover Creek Dr Longmont CO 80503",
    "addr:housenumber":"1494",
    "addr:postcode":"80503",
    "addr:street":"Clover Creek Dr",
    "iso:country":"US",
    "sg:address":"1494 Clover Creek Dr",
    "sg:city":"Longmont",
    "sg:classifiers":[
        {
            "category":"Manufacturing",
            "subcategory":"Tools & Machinery",
            "type":"Manufacturing & Wholesale Goods"
        }
    ],
    "sg:phone":"+1 303 684 6579",
    "sg:postcode":"80503",
    "sg:province":"CO",
    "sg:tags":[
        "computer"
    ],
    "wof:name":"IBM",
    "wof:placetype":"venue"
},
  "geometry": {"coordinates":[-105.146334,40.139073],"type":"Point"}
}