{
  "type": "Feature",
  "properties": {
    "iso:country":"US",
    "sg:address":"617 W Main St",
    "sg:city":"Aspen",
    "sg:classifiers":[
        {
            "category":"Professional",
            "subcategory":"Business Services",
            "type":"Services"
        },
        {
            "category":"Building & Trades",
            "subcategory":"Construction",
            "type":"Services"
        }
    ],
    "sg:phone":"+1 970 925 4342",
    "sg:postcode":"81611",
    "sg:province":"CO",
    "sg:tags":[
        "specializing",
        "consultant",
        "contractor",
        "design",
        "interior",
        "new",
        "decorator"
    ],
    "wof:name":"I D Interiors",
    "wof:placetype":"venue"
},
  "geometry": {"coordinates":[-106.82978199999999,39.192767],"type":"Point"}
}