{
  "type": "Feature",
  "properties": {
    "addr:full":"5975 Pike Dr Larkspur CO 80118",
    "addr:housenumber":"5975",
    "addr:postcode":"80118",
    "addr:street":"Pike Dr",
    "iso:country":"US",
    "sg:address":"5975 Pike Dr",
    "sg:city":"Larkspur",
    "sg:classifiers":[
        {
            "category":"Professional",
            "type":"Services"
        }
    ],
    "sg:phone":"+1 303 681 3359",
    "sg:postcode":"80118",
    "sg:province":"CO",
    "wof:name":"Pete Karabatsos",
    "wof:placetype":"venue"
},
  "geometry": {"coordinates":[-104.997891,39.260873],"type":"Point"}
}