{
  "type": "Feature",
  "properties": {
    "addr:full":"1435 Adams Ave Loveland CO 80538",
    "addr:housenumber":"1435",
    "addr:postcode":"80538",
    "addr:street":"Adams Ave",
    "iso:country":"US",
    "sg:address":"1435 Adams Ave",
    "sg:city":"Loveland",
    "sg:classifiers":[
        {
            "category":"Building & Trades",
            "subcategory":"Construction",
            "type":"Services"
        }
    ],
    "sg:phone":"+1 970 669 7665",
    "sg:postcode":"80538",
    "sg:province":"CO",
    "sg:tags":[
        "hanging",
        "contractor"
    ],
    "wof:name":"Wohlman Painting",
    "wof:placetype":"venue"
},
  "geometry": {"coordinates":[-105.06921800000001,40.408746],"type":"Point"}
}