{
  "type": "Feature",
  "properties": {
    "iso:country":"US",
    "sg:address":"201 3rd St",
    "sg:city":"Mead",
    "sg:classifiers":[
        {
            "category":"Wholesale",
            "subcategory":"Farm Supplies",
            "type":"Manufacturing & Wholesale Goods"
        }
    ],
    "sg:phone":"+1 970 535 4450",
    "sg:postcode":"80542",
    "sg:province":"CO",
    "sg:tags":[
        "fertilizer"
    ],
    "wof:name":"American Pride Coop",
    "wof:placetype":"venue"
},
  "geometry": {"coordinates":[-104.99866,40.235338],"type":"Point"}
}